{
  "type": "Feature",
  "properties": {
    "gn:admin1_code":"1",
    "gn:asciiname":"Victor",
    "gn:country_code":"CA",
    "gn:dem":849,
    "gn:feature_class":"P",
    "gn:feature_code":"PPLL",
    "gn:name":"Victor",
    "gn:population":0,
    "gn:timezone":"America/Edmonton",
    "iso:country":"CA",
    "name:bre_x_preferred":[
        "Victor"
    ],
    "name:ceb_x_preferred":[
        "Victor"
    ],
    "name:dan_x_preferred":[
        "Victor"
    ],
    "name:deu_x_preferred":[
        "Victor"
    ],
    "name:fas_x_preferred":[
        "\u0648\u06cc\u06a9\u062a\u0648\u0631"
    ],
    "name:fra_x_preferred":[
        "Victor"
    ],
    "name:heb_x_preferred":[
        "\u05d5\u05d9\u05e7\u05d8\u05d5\u05e8"
    ],
    "name:hun_x_preferred":[
        "Victor"
    ],
    "name:ita_x_preferred":[
        "Victor"
    ],
    "name:jpn_x_preferred":[
        "\u30f4\u30a3\u30af\u30bf\u30fc"
    ],
    "name:nld_x_preferred":[
        "Victor"
    ],
    "name:pol_x_preferred":[
        "Victor"
    ],
    "name:por_x_preferred":[
        "Victor"
    ],
    "name:rus_x_preferred":[
        "Victor"
    ],
    "name:swe_x_preferred":[
        "Victor"
    ],
    "wof:name":"Victor",
    "wof:placetype":"locality"
},
  "geometry": {"coordinates":[-112.33514,51.80013],"type":"Point"}
}