{
  "type": "Feature",
  "properties": {
    "gn:admin1_code":"1",
    "gn:asciiname":"Victor",
    "gn:country_code":"CA",
    "gn:dem":849,
    "gn:feature_class":"P",
    "gn:feature_code":"PPLL",
    "gn:name":"Victor",
    "gn:population":0,
    "gn:timezone":"America/Edmonton",
    "iso:country":"CA",
    "wof:name":"Victor",
    "wof:placetype":"locality"
},
  "geometry": {"coordinates":[-112.33514,51.80013],"type":"Point"}
}