{
  "type": "Feature",
  "properties": {
    "iso:country":"CA",
    "name:eng_x_preferred":[
        "Airport Heights"
    ],
    "qs:gn_adm0_cc":"CA",
    "qs:gn_local":6324733,
    "qs:gn_nam_loc":"St. John's, Newfoundland and Labrador, Newfoundland and Labrador, CA",
    "qs:gn_namadm1":"05",
    "qs:local_max":5403,
    "qs:local_sum":16210,
    "qs:localhoods":11,
    "qs:name":"Airport Heights",
    "qs:name_adm0":"Canada",
    "qs:name_adm1":"Newfoundland and Labrador",
    "qs:name_adm2":"Newfoundland and Labrador",
    "qs:name_local":"St. John's",
    "qs:photo_max":9,
    "qs:photo_sum":28,
    "qs:placetype":"Suburb",
    "qs:quad_count":10,
    "qs:woe_adm0":23424775,
    "qs:woe_adm1":2344919,
    "qs:woe_adm2":29375216,
    "qs:woe_lau":0,
    "qs:woe_local":3996,
    "qs:woe_ver":"7.10.0",
    "wof:lang":[
        "eng"
    ],
    "wof:name":"Airport Heights",
    "wof:placetype":"neighbourhood"
},
  "geometry": {"coordinates":[-52.75105,47.603519],"type":"Point"}
}