{
  "type": "Feature",
  "properties": {
    "gn:admin1_code":"8.0",
    "gn:asciiname":"Bethesda",
    "gn:country_code":"CA",
    "gn:dem":282,
    "gn:feature_class":"P",
    "gn:feature_code":"PPL",
    "gn:name":"Bethesda",
    "gn:population":0,
    "gn:timezone":"America/Toronto",
    "iso:country":"CA",
    "wof:name":"Bethesda",
    "wof:placetype":"locality"
},
  "geometry": {"coordinates":[-79.67304,44.23239],"type":"Point"}
}