{
  "type": "Feature",
  "properties": {
    "gn:admin1_code":"8.0",
    "gn:asciiname":"Bethesda",
    "gn:country_code":"CA",
    "gn:dem":282,
    "gn:feature_class":"P",
    "gn:feature_code":"PPL",
    "gn:name":"Bethesda",
    "gn:population":0,
    "gn:timezone":"America/Toronto",
    "iso:country":"CA",
    "name:ast_x_preferred":[
        "Bethesda"
    ],
    "name:bre_x_preferred":[
        "Bethesda"
    ],
    "name:cat_x_preferred":[
        "Bethesda"
    ],
    "name:ceb_x_preferred":[
        "Bethesda"
    ],
    "name:ces_x_preferred":[
        "Bethesda"
    ],
    "name:cor_x_preferred":[
        "Bethesda"
    ],
    "name:cym_x_preferred":[
        "Bethesda"
    ],
    "name:dan_x_preferred":[
        "Bethesda"
    ],
    "name:deu_x_preferred":[
        "Bethesda"
    ],
    "name:eus_x_preferred":[
        "Bethesda"
    ],
    "name:fin_x_preferred":[
        "Bethesda"
    ],
    "name:fra_x_preferred":[
        "Bethesda"
    ],
    "name:ind_x_preferred":[
        "Bethesda"
    ],
    "name:ita_x_preferred":[
        "Bethesda"
    ],
    "name:jpn_x_preferred":[
        "\u30d9\u30bb\u30b9\u30c0"
    ],
    "name:kor_x_preferred":[
        "\ubca0\ub370\uc2a4\ub2e4"
    ],
    "name:nld_x_preferred":[
        "Bethesda"
    ],
    "name:pol_x_preferred":[
        "Bethesda"
    ],
    "name:por_x_preferred":[
        "Betesda"
    ],
    "name:rus_x_preferred":[
        "\u0411\u0435\u0442\u0435\u0441\u0434\u0430"
    ],
    "name:slk_x_preferred":[
        "Bethesda"
    ],
    "name:spa_x_preferred":[
        "Bethesda"
    ],
    "name:srp_x_preferred":[
        "\u0411\u0435\u0442\u0435\u0441\u0434\u0430"
    ],
    "name:swe_x_preferred":[
        "Bethesda"
    ],
    "name:ukr_x_preferred":[
        "\u0411\u0435\u0442\u0435\u0441\u0434\u0430"
    ],
    "name:vol_x_preferred":[
        "Bethesda"
    ],
    "name:zho_x_preferred":[
        "\u8d1d\u585e\u65af\u8fbe"
    ],
    "wof:name":"Bethesda",
    "wof:placetype":"locality"
},
  "geometry": {"coordinates":[-79.67304,44.23239],"type":"Point"}
}