{
  "type": "Feature",
  "properties": {
    "gn:admin1_code":"7.0",
    "gn:asciiname":"Big Brook",
    "gn:country_code":"CA",
    "gn:dem":60,
    "gn:feature_class":"P",
    "gn:feature_code":"PPL",
    "gn:name":"Big Brook",
    "gn:population":0,
    "gn:timezone":"America/Halifax",
    "iso:country":"CA",
    "wof:name":"Big Brook",
    "wof:placetype":"locality"
},
  "geometry": {"coordinates":[-61.22967,45.78896],"type":"Point"}
}