{
  "type": "Feature",
  "properties": {
    "iso:country":"CA",
    "name:bul_x_preferred":[
        "\u0413\u0440\u0438\u0439\u043d\u0443\u0434"
    ],
    "name:cat_x_preferred":[
        "Greenwood"
    ],
    "name:ceb_x_preferred":[
        "Greenwood"
    ],
    "name:ces_x_preferred":[
        "Greenwood"
    ],
    "name:deu_x_preferred":[
        "Greenwood"
    ],
    "name:eng_x_preferred":[
        "Greenwood"
    ],
    "name:fin_x_preferred":[
        "Greenwood"
    ],
    "name:fra_x_preferred":[
        "Greenwood"
    ],
    "name:heb_x_preferred":[
        "\u05d2\u05e8\u05d9\u05e0\u05d5\u05d5\u05d3"
    ],
    "name:hun_x_preferred":[
        "Greenwood"
    ],
    "name:ita_x_preferred":[
        "Greenwood"
    ],
    "name:jpn_x_preferred":[
        "\u30b0\u30ea\u30fc\u30f3\u30a6\u30c3\u30c9"
    ],
    "name:kor_x_preferred":[
        "\uadf8\ub9b0\uc6b0\ub4dc"
    ],
    "name:nld_x_preferred":[
        "Greenwood"
    ],
    "name:pol_x_preferred":[
        "Greenwood"
    ],
    "name:por_x_preferred":[
        "Greenwood"
    ],
    "name:rus_x_preferred":[
        "\u0413\u0440\u0438\u043d\u0432\u0443\u0434"
    ],
    "name:spa_x_preferred":[
        "Greenwood"
    ],
    "name:srp_x_preferred":[
        "\u0413\u0440\u0438\u043d\u0432\u0443\u0434"
    ],
    "name:swe_x_preferred":[
        "Greenwood"
    ],
    "name:ukr_x_preferred":[
        "\u0490\u0440\u0456\u043d\u0432\u0443\u0434"
    ],
    "name:vol_x_preferred":[
        "Greenwood"
    ],
    "qs:gn_adm0_cc":"CA",
    "qs:gn_local":6076211,
    "qs:gn_nam_loc":"moncton",
    "qs:gn_namadm1":"04",
    "qs:local_max":1229,
    "qs:local_sum":6372,
    "qs:localhoods":28,
    "qs:name":"Greenwood",
    "qs:name_adm0":"Canada",
    "qs:name_adm1":"New Brunswick",
    "qs:name_adm2":"Westmorland",
    "qs:name_local":"Moncton",
    "qs:photo_max":25,
    "qs:photo_sum":27,
    "qs:placetype":"Suburb",
    "qs:quad_count":2,
    "qs:woe_adm0":23424775,
    "qs:woe_adm1":2344918,
    "qs:woe_adm2":29375181,
    "qs:woe_lau":0,
    "qs:woe_local":3796,
    "qs:woe_ver":"7.10.0",
    "wof:lang":[
        "eng"
    ],
    "wof:name":"Greenwood",
    "wof:placetype":"neighbourhood"
},
  "geometry": {"coordinates":[-64.78194999999999,46.110302],"type":"Point"}
}