{
  "type": "Feature",
  "properties": {
    "gn:admin1_code":"3",
    "gn:asciiname":"Lily Bay",
    "gn:country_code":"CA",
    "gn:dem":257,
    "gn:feature_class":"P",
    "gn:feature_code":"PPLL",
    "gn:name":"Lily Bay",
    "gn:population":0,
    "gn:timezone":"America/Winnipeg",
    "iso:country":"CA",
    "wof:name":"Lily Bay",
    "wof:placetype":"locality"
},
  "geometry": {"coordinates":[-98.22762,50.76942],"type":"Point"}
}