{
  "type": "Feature",
  "properties": {
    "gn:admin1_code":"3.0",
    "gn:asciiname":"Bluff Creek",
    "gn:country_code":"CA",
    "gn:dem":256,
    "gn:feature_class":"P",
    "gn:feature_code":"PPLL",
    "gn:name":"Bluff Creek",
    "gn:population":0,
    "gn:timezone":"America/Winnipeg",
    "iso:country":"CA",
    "name:ceb_x_preferred":[
        "Bluff Creek"
    ],
    "name:deu_x_preferred":[
        "Bluff Creek"
    ],
    "name:swe_x_preferred":[
        "Bluff Creek"
    ],
    "wof:name":"Bluff Creek",
    "wof:placetype":"locality"
},
  "geometry": {"coordinates":[-98.83466,50.81672],"type":"Point"}
}