{
  "type": "Feature",
  "properties": {
    "gn:admin1_code":"1.0",
    "gn:asciiname":"Dimsdale",
    "gn:country_code":"CA",
    "gn:dem":676,
    "gn:feature_class":"P",
    "gn:feature_code":"PPLL",
    "gn:name":"Dimsdale",
    "gn:population":0,
    "gn:timezone":"America/Edmonton",
    "iso:country":"CA",
    "name:fra_x_preferred":[
        "Dimsdale"
    ],
    "wof:name":"Dimsdale",
    "wof:placetype":"locality"
},
  "geometry": {"coordinates":[-118.98602,55.13327],"type":"Point"}
}