{
  "type": "Feature",
  "properties": {
    "gn:admin1_code":"3",
    "gn:asciiname":"Odhill",
    "gn:country_code":"CA",
    "gn:dem":221,
    "gn:feature_class":"P",
    "gn:feature_code":"PPLL",
    "gn:name":"Odhill",
    "gn:population":0,
    "gn:timezone":"America/Winnipeg",
    "iso:country":"CA",
    "wof:name":"Odhill",
    "wof:placetype":"locality"
},
  "geometry": {"coordinates":[-98.22555,55.10764],"type":"Point"}
}