{
  "type": "Feature",
  "properties": {
    "iso:country":"CA",
    "name:cat_x_preferred":[
        "Seven Persons"
    ],
    "name:eng_x_preferred":[
        "Seven Persons"
    ],
    "name:fra_x_preferred":[
        "Seven Persons"
    ],
    "name:spa_x_preferred":[
        "Seven Persons"
    ],
    "qs:name":"Seven Persons",
    "qs:name_adm0":"Canada",
    "qs:name_adm1":"Alberta",
    "qs:photos":27,
    "qs:photos_1k":5,
    "qs:photos_9k":1,
    "qs:photos_9r":2,
    "qs:photos_all":27,
    "qs:photos_sr":2,
    "qs:placetype":"Town",
    "qs:pop_sr":"0",
    "wd:wordcount":275,
    "wof:name":"Seven Persons",
    "wof:placetype":"locality"
},
  "geometry": {"coordinates":[-110.912902,49.876201],"type":"Point"}
}