{
  "type": "Feature",
  "properties": {
    "gn:admin1_code":"12",
    "gn:asciiname":"Gold Run",
    "gn:country_code":"CA",
    "gn:dem":615,
    "gn:feature_class":"P",
    "gn:feature_code":"PPLL",
    "gn:name":"Gold Run",
    "gn:population":0,
    "gn:timezone":"America/Whitehorse",
    "iso:country":"CA",
    "name:ceb_x_preferred":[
        "Gold Run"
    ],
    "wof:name":"Gold Run",
    "wof:placetype":"locality"
},
  "geometry": {"coordinates":[-138.59601999999998,63.69945],"type":"Point"}
}