{
  "type": "Feature",
  "properties": {
    "gn:admin1_code":"4",
    "gn:asciiname":"Sunpoke",
    "gn:country_code":"CA",
    "gn:dem":26,
    "gn:feature_class":"P",
    "gn:feature_code":"PPL",
    "gn:name":"Sunpoke",
    "gn:population":0,
    "gn:timezone":"America/Moncton",
    "iso:country":"CA",
    "wof:name":"Sunpoke",
    "wof:placetype":"locality"
},
  "geometry": {"coordinates":[-66.59016,45.7874],"type":"Point"}
}