{
  "type": "Feature",
  "properties": {
    "gn:admin1_code":"1.0",
    "gn:asciiname":"Camp Creek",
    "gn:country_code":"CA",
    "gn:dem":686,
    "gn:feature_class":"P",
    "gn:feature_code":"PPLL",
    "gn:name":"Camp Creek",
    "gn:population":0,
    "gn:timezone":"America/Edmonton",
    "iso:country":"CA",
    "wof:name":"Camp Creek",
    "wof:placetype":"locality"
},
  "geometry": {"coordinates":[-114.58544999999999,54.25014],"type":"Point"}
}