{
  "type": "Feature",
  "properties": {
    "gn:admin1_code":"10",
    "gn:admin2_code":"03",
    "gn:admin3_code":"34058.0",
    "gn:asciiname":"Saint-Charles-des-Grondines",
    "gn:country_code":"CA",
    "gn:dem":16,
    "gn:feature_class":"P",
    "gn:feature_code":"PPL",
    "gn:name":"Saint-Charles-des-Grondines",
    "gn:population":0,
    "gn:timezone":"America/Toronto",
    "iso:country":"CA",
    "wof:name":"Saint-Charles-des-Grondines",
    "wof:placetype":"locality"
},
  "geometry": {"coordinates":[-72.0416,46.59225],"type":"Point"}
}