{
  "type": "Feature",
  "properties": {
    "gn:admin1_code":"8.0",
    "gn:asciiname":"Burriss",
    "gn:country_code":"CA",
    "gn:dem":353,
    "gn:feature_class":"P",
    "gn:feature_code":"PPL",
    "gn:name":"Burriss",
    "gn:population":0,
    "gn:timezone":"America/Winnipeg",
    "iso:country":"CA",
    "wof:name":"Burriss",
    "wof:placetype":"locality"
},
  "geometry": {"coordinates":[-93.65031,48.69988],"type":"Point"}
}