{
  "type": "Feature",
  "properties": {
    "gn:admin1_code":"2",
    "gn:asciiname":"Upper Cutbank",
    "gn:country_code":"CA",
    "gn:dem":762,
    "gn:feature_class":"P",
    "gn:feature_code":"PPLL",
    "gn:name":"Upper Cutbank",
    "gn:population":0,
    "gn:timezone":"America/Dawson_Creek",
    "iso:country":"CA",
    "wof:name":"Upper Cutbank",
    "wof:placetype":"locality"
},
  "geometry": {"coordinates":[-120.43616000000002,55.51659],"type":"Point"}
}