{
  "type": "Feature",
  "properties": {
    "gn:admin1_code":"1.0",
    "gn:asciiname":"Western Monarch",
    "gn:country_code":"CA",
    "gn:dem":678,
    "gn:feature_class":"P",
    "gn:feature_code":"PPL",
    "gn:name":"Western Monarch",
    "gn:population":0,
    "gn:timezone":"America/Edmonton",
    "iso:country":"CA",
    "wof:name":"Western Monarch",
    "wof:placetype":"locality"
},
  "geometry": {"coordinates":[-112.47972,51.32861],"type":"Point"}
}