{
  "type": "Feature",
  "properties": {
    "gn:admin1_code":"10",
    "gn:admin2_code":"16",
    "gn:admin3_code":"46045.0",
    "gn:asciiname":"Riceburg",
    "gn:country_code":"CA",
    "gn:dem":71,
    "gn:feature_class":"P",
    "gn:feature_code":"PPL",
    "gn:name":"Riceburg",
    "gn:population":0,
    "gn:timezone":"America/Toronto",
    "iso:country":"CA",
    "wof:name":"Riceburg",
    "wof:placetype":"locality"
},
  "geometry": {"coordinates":[-72.9329,45.13587],"type":"Point"}
}