{
  "type": "Feature",
  "properties": {
    "gn:country":"CA",
    "gn:fcode":"PPL",
    "gn:population":500,
    "iso:country":"CA",
    "name:bre_x_preferred":[
        "Kemptville"
    ],
    "name:bul_x_preferred":[
        "\u041a\u0435\u043c\u043f\u0442\u0432\u0438\u043b\u0435"
    ],
    "name:ceb_x_preferred":[
        "Kemptville"
    ],
    "name:cos_x_preferred":[
        "Kemptville"
    ],
    "name:dan_x_preferred":[
        "Kemptville"
    ],
    "name:deu_x_preferred":[
        "Kemptville"
    ],
    "name:eng_x_preferred":[
        "Kemptville"
    ],
    "name:fas_x_preferred":[
        "\u06a9\u0645\u067e\u062a\u0648\u06cc\u0644"
    ],
    "name:fra_x_preferred":[
        "Kemptville"
    ],
    "name:ind_x_preferred":[
        "Kemptville"
    ],
    "name:ita_x_preferred":[
        "Kemptville"
    ],
    "name:nds_x_preferred":[
        "Kemptville"
    ],
    "name:nld_x_preferred":[
        "Kemptville"
    ],
    "name:por_x_preferred":[
        "Kemptville"
    ],
    "name:ron_x_preferred":[
        "Kemptville"
    ],
    "name:rus_x_preferred":[
        "\u041a\u0435\u043c\u043f\u0442\u0432\u0438\u043b\u043b"
    ],
    "name:spa_x_preferred":[
        "Kemptville"
    ],
    "name:swe_x_preferred":[
        "Kemptville"
    ],
    "name:tah_x_preferred":[
        "Kemptville"
    ],
    "qs_pg:aaroncc":"CA",
    "qs_pg:gn_country":"CA",
    "qs_pg:gn_fcode":"PPL",
    "qs_pg:gn_pop":500,
    "qs_pg:name":"Kemptville",
    "qs_pg:name_adm0":"Canada",
    "qs_pg:name_adm1":"Ontario",
    "qs_pg:photos":292,
    "qs_pg:photos_1k":59,
    "qs_pg:photos_9k":1,
    "qs_pg:photos_9r":4,
    "qs_pg:photos_all":292,
    "qs_pg:photos_sr":5,
    "qs_pg:pop_sr":2,
    "qs_pg:qs_pg_placetype":"locality",
    "qs_pg:qs_pg_placetype_gp":"Town",
    "qs_pg:woe_adm0":23424775,
    "woe:adm0_id":23424775,
    "woe:name_adm0":"Canada",
    "woe:name_adm1":"Ontario",
    "woe:placetype":"Town",
    "wof:name":"Kemptville",
    "wof:placetype":"locality",
    "wof:population":500
},
  "geometry": {"coordinates":[-75.64104,45.0168],"type":"Point"}
}