{
  "type": "Feature",
  "properties": {
    "iso:country":"CA",
    "name:eng_x_preferred":[
        "Newell County No 4"
    ],
    "qs:name":"Newell County No 4",
    "qs:name_adm0":"Canada",
    "qs:name_adm1":"Alberta",
    "qs:photos":88,
    "qs:photos_1k":18,
    "qs:photos_9k":1,
    "qs:photos_9r":3,
    "qs:photos_all":88,
    "qs:photos_sr":3,
    "qs:placetype":"Town",
    "qs:pop_sr":"0",
    "wd:wordcount":481,
    "wof:name":"Newell County No 4",
    "wof:placetype":"locality"
},
  "geometry": {"coordinates":[-111.862449,50.540244],"type":"Point"}
}