{
  "type": "Feature",
  "properties": {
    "gn:admin1_code":"1",
    "gn:asciiname":"Peacock",
    "gn:country_code":"CA",
    "gn:dem":946,
    "gn:feature_class":"P",
    "gn:feature_code":"PPLL",
    "gn:name":"Peacock",
    "gn:population":0,
    "gn:timezone":"America/Edmonton",
    "iso:country":"CA",
    "wof:name":"Peacock",
    "wof:placetype":"locality"
},
  "geometry": {"coordinates":[-113.08517000000001,50.08333],"type":"Point"}
}