{
  "type": "Feature",
  "properties": {
    "iso:country":"CA",
    "name:eng_x_preferred":[
        "Knights Cove"
    ],
    "name:nld_x_preferred":[
        "Knight's Cove"
    ],
    "qs:name":"Knights Cove",
    "qs:name_adm0":"Canada",
    "qs:name_adm1":"Newfoundland and Labrador",
    "qs:photos":22,
    "qs:photos_1k":4,
    "qs:photos_9k":1,
    "qs:photos_9r":1,
    "qs:photos_all":22,
    "qs:photos_sr":1,
    "qs:placetype":"Town",
    "qs:pop_sr":"0",
    "wof:name":"Knights Cove",
    "wof:placetype":"locality"
},
  "geometry": {"coordinates":[-53.295707,48.532975],"type":"Point"}
}