{
  "type": "Feature",
  "properties": {
    "gn:admin1_code":"10.0",
    "gn:admin2_code":"5.0",
    "gn:admin3_code":"40017.0",
    "gn:asciiname":"Domaine-Morin",
    "gn:country_code":"CA",
    "gn:dem":266,
    "gn:feature_class":"P",
    "gn:feature_code":"PPL",
    "gn:name":"Domaine-Morin",
    "gn:population":0,
    "gn:timezone":"America/Toronto",
    "iso:country":"CA",
    "wof:name":"Domaine-Morin",
    "wof:placetype":"locality"
},
  "geometry": {"coordinates":[-71.85509999999999,45.76559],"type":"Point"}
}