{
  "type": "Feature",
  "properties": {
    "gn:admin1_code":"10",
    "gn:admin2_code":"07",
    "gn:admin3_code":"81017.0",
    "gn:asciiname":"Riviera",
    "gn:country_code":"CA",
    "gn:dem":56,
    "gn:feature_class":"P",
    "gn:feature_code":"PPL",
    "gn:name":"Riviera",
    "gn:population":0,
    "gn:timezone":"America/Toronto",
    "iso:country":"CA",
    "name:ara_x_preferred":[
        "\u0631\u064a\u0641\u064a\u064a\u0631\u0627"
    ],
    "name:ben_x_preferred":[
        "\u09b0\u09bf\u09ad\u09bf\u09df\u09c7\u09b0\u09be"
    ],
    "name:bre_x_preferred":[
        "Riviera"
    ],
    "name:bul_x_preferred":[
        "\u0420\u0438\u0432\u0438\u0435\u0440\u0430"
    ],
    "name:deu_x_preferred":[
        "Riviera"
    ],
    "name:ell_x_preferred":[
        "\u03a1\u03b9\u03b2\u03b9\u03ad\u03c1\u03b1"
    ],
    "name:epo_x_preferred":[
        "Riviero"
    ],
    "name:fin_x_preferred":[
        "Riviera"
    ],
    "name:fra_x_preferred":[
        "Riviera"
    ],
    "name:hin_x_preferred":[
        "\u0930\u093f\u0935\u0947\u0930\u093e"
    ],
    "name:hun_x_preferred":[
        "Rivi\u00e9ra"
    ],
    "name:hye_x_preferred":[
        "\u054c\u056b\u057e\u056b\u0565\u0580\u0561"
    ],
    "name:ita_x_preferred":[
        "Riviera"
    ],
    "name:kir_x_preferred":[
        "\u0420\u0438\u0432\u044c\u0435\u0440\u0430"
    ],
    "name:lav_x_preferred":[
        "Rivj\u0113ra"
    ],
    "name:nld_x_preferred":[
        "Rivi\u00e8ra"
    ],
    "name:nor_x_preferred":[
        "Rivieraen"
    ],
    "name:pol_x_preferred":[
        "Riwiera"
    ],
    "name:ron_x_preferred":[
        "Riviera"
    ],
    "name:rus_x_preferred":[
        "\u0420\u0438\u0432\u044c\u0435\u0440\u0430"
    ],
    "name:spa_x_preferred":[
        "Riviera"
    ],
    "name:swe_x_preferred":[
        "Rivieran"
    ],
    "name:urd_x_preferred":[
        "\u0631\u0627\u0626\u06cc\u0648\u06cc\u0631\u0627"
    ],
    "wof:name":"Riviera",
    "wof:placetype":"locality"
},
  "geometry": {"coordinates":[-75.72134,45.47588],"type":"Point"}
}