{
  "type": "Feature",
  "properties": {
    "gn:admin1_code":"10",
    "gn:admin2_code":"07",
    "gn:admin3_code":"81017.0",
    "gn:asciiname":"Riviera",
    "gn:country_code":"CA",
    "gn:dem":56,
    "gn:feature_class":"P",
    "gn:feature_code":"PPL",
    "gn:name":"Riviera",
    "gn:population":0,
    "gn:timezone":"America/Toronto",
    "iso:country":"CA",
    "wof:name":"Riviera",
    "wof:placetype":"locality"
},
  "geometry": {"coordinates":[-75.72134,45.47588],"type":"Point"}
}