{
  "type": "Feature",
  "properties": {
    "gn:admin1_code":"12.0",
    "gn:asciiname":"Wernecke",
    "gn:country_code":"CA",
    "gn:dem":1109,
    "gn:feature_class":"P",
    "gn:feature_code":"PPLL",
    "gn:name":"Wernecke",
    "gn:population":0,
    "gn:timezone":"America/Whitehorse",
    "iso:country":"CA",
    "wof:name":"Wernecke",
    "wof:placetype":"locality"
},
  "geometry": {"coordinates":[-135.27077,63.95249],"type":"Point"}
}