{
  "type": "Feature",
  "properties": {
    "gn:admin1_code":"7.0",
    "gn:asciiname":"West Springhill",
    "gn:country_code":"CA",
    "gn:dem":179,
    "gn:feature_class":"P",
    "gn:feature_code":"PPL",
    "gn:name":"West Springhill",
    "gn:population":0,
    "gn:timezone":"America/Halifax",
    "iso:country":"CA",
    "wof:name":"West Springhill",
    "wof:placetype":"locality"
},
  "geometry": {"coordinates":[-65.44991999999999,44.58421],"type":"Point"}
}