{
  "type": "Feature",
  "properties": {
    "gn:country":"CA",
    "gn:fcode":"PPL",
    "gn:population":0,
    "iso:country":"CA",
    "name:ceb_x_preferred":[
        "Tiverton"
    ],
    "name:deu_x_preferred":[
        "Tiverton"
    ],
    "name:fra_x_preferred":[
        "Tiverton"
    ],
    "name:nld_x_preferred":[
        "Tiverton"
    ],
    "name:pol_x_preferred":[
        "Tiverton"
    ],
    "name:slk_x_preferred":[
        "Tiverton"
    ],
    "name:spa_x_preferred":[
        "Tiverton"
    ],
    "name:swe_x_preferred":[
        "Tiverton"
    ],
    "name:ukr_x_preferred":[
        "\u0422\u0456\u0432\u0435\u0440\u0442\u043e\u043d"
    ],
    "name:vol_x_preferred":[
        "Tiverton"
    ],
    "qs_pg:aaroncc":"CA",
    "qs_pg:gn_country":"CA",
    "qs_pg:gn_fcode":"PPL",
    "qs_pg:gn_pop":0,
    "qs_pg:name":"Tiverton",
    "qs_pg:name_adm0":"Canada",
    "qs_pg:name_adm1":"Ontario",
    "qs_pg:photos":54,
    "qs_pg:photos_1k":11,
    "qs_pg:photos_9k":1,
    "qs_pg:photos_9r":2,
    "qs_pg:photos_all":54,
    "qs_pg:photos_sr":2,
    "qs_pg:pop_sr":0,
    "qs_pg:qs_pg_placetype":"locality",
    "qs_pg:qs_pg_placetype_gp":"Town",
    "qs_pg:woe_adm0":23424775,
    "woe:adm0_id":23424775,
    "woe:name_adm0":"Canada",
    "woe:name_adm1":"Ontario",
    "woe:placetype":"Town",
    "wof:name":"Tiverton",
    "wof:placetype":"locality"
},
  "geometry": {"coordinates":[-80.91643000000001,43.5668],"type":"Point"}
}