{
  "type": "Feature",
  "properties": {
    "gn:admin1_code":"11.0",
    "gn:asciiname":"Alticane",
    "gn:country_code":"CA",
    "gn:dem":701,
    "gn:feature_class":"P",
    "gn:feature_code":"PPL",
    "gn:name":"Alticane",
    "gn:population":0,
    "gn:timezone":"America/Regina",
    "iso:country":"CA",
    "wof:name":"Alticane",
    "wof:placetype":"locality"
},
  "geometry": {"coordinates":[-107.48394999999999,52.90006],"type":"Point"}
}