{
  "type": "Feature",
  "properties": {
    "gn:admin1_code":"8",
    "gn:asciiname":"Ruel",
    "gn:country_code":"CA",
    "gn:dem":416,
    "gn:feature_class":"P",
    "gn:feature_code":"PPL",
    "gn:name":"Ruel",
    "gn:population":0,
    "gn:timezone":"America/Toronto",
    "iso:country":"CA",
    "wof:name":"Ruel",
    "wof:placetype":"locality"
},
  "geometry": {"coordinates":[-81.46646,47.26679],"type":"Point"}
}