{
  "type": "Feature",
  "properties": {
    "gn:admin1_code":"1",
    "gn:asciiname":"Northbank",
    "gn:country_code":"CA",
    "gn:dem":631,
    "gn:feature_class":"P",
    "gn:feature_code":"PPLL",
    "gn:name":"Northbank",
    "gn:population":0,
    "gn:timezone":"America/Edmonton",
    "iso:country":"CA",
    "wof:name":"Northbank",
    "wof:placetype":"locality"
},
  "geometry": {"coordinates":[-112.55193,54.03347],"type":"Point"}
}