{
  "type": "Feature",
  "properties": {
    "gn:admin1_code":"10",
    "gn:admin2_code":"14.0",
    "gn:admin3_code":"61050.0",
    "gn:asciiname":"Pied-de-la-Montagne",
    "gn:country_code":"CA",
    "gn:dem":113,
    "gn:feature_class":"P",
    "gn:feature_code":"PPL",
    "gn:name":"Pied-de-la-Montagne",
    "gn:population":0,
    "gn:timezone":"America/Toronto",
    "iso:country":"CA",
    "wof:name":"Pied-de-la-Montagne",
    "wof:placetype":"locality"
},
  "geometry": {"coordinates":[-73.56735999999999,46.12809],"type":"Point"}
}