{
  "type": "Feature",
  "properties": {
    "gn:country":"CA",
    "gn:fcode":"PPL",
    "gn:population":0,
    "iso:country":"CA",
    "name:bul_x_preferred":[
        "\u041f\u0440\u0438\u0442\u0447\u0430\u0440\u0434"
    ],
    "name:ceb_x_preferred":[
        "Pritchard"
    ],
    "name:eng_x_preferred":[
        "Pritchard"
    ],
    "name:nld_x_preferred":[
        "Pritchard"
    ],
    "name:swe_x_preferred":[
        "Pritchard"
    ],
    "qs_pg:aaroncc":"CA",
    "qs_pg:gn_country":"CA",
    "qs_pg:gn_fcode":"PPL",
    "qs_pg:gn_pop":0,
    "qs_pg:name":"Pritchard",
    "qs_pg:name_adm0":"Canada",
    "qs_pg:name_adm1":"British Columbia",
    "qs_pg:photos":317,
    "qs_pg:photos_1k":64,
    "qs_pg:photos_9k":1,
    "qs_pg:photos_9r":5,
    "qs_pg:photos_all":317,
    "qs_pg:photos_sr":5,
    "qs_pg:pop_sr":0,
    "qs_pg:qs_pg_placetype":"locality",
    "qs_pg:qs_pg_placetype_gp":"Town",
    "qs_pg:woe_adm0":23424775,
    "woe:adm0_id":23424775,
    "woe:name_adm0":"Canada",
    "woe:name_adm1":"British Columbia",
    "woe:placetype":"Town",
    "wof:name":"Pritchard",
    "wof:placetype":"locality"
},
  "geometry": {"coordinates":[-119.81910999999999,50.6831],"type":"Point"}
}