{
  "type": "Feature",
  "properties": {
    "gn:admin1_code":"8",
    "gn:asciiname":"Harcourt",
    "gn:country_code":"CA",
    "gn:dem":424,
    "gn:feature_class":"P",
    "gn:feature_code":"PPL",
    "gn:name":"Harcourt",
    "gn:population":0,
    "gn:timezone":"America/Toronto",
    "iso:country":"CA",
    "name:cat_x_preferred":[
        "Harcourt"
    ],
    "name:ceb_x_preferred":[
        "Harcourt"
    ],
    "name:deu_x_preferred":[
        "Harcourt"
    ],
    "name:fra_x_preferred":[
        "Harcourt"
    ],
    "name:nds_x_preferred":[
        "Harcourt"
    ],
    "name:nld_x_preferred":[
        "Harcourt"
    ],
    "name:por_x_preferred":[
        "Harcourt"
    ],
    "name:rus_x_preferred":[
        "\u0414\u2019\u0410\u0440\u043a\u0443\u0440"
    ],
    "name:swe_x_preferred":[
        "Harcourt"
    ],
    "name:vie_x_preferred":[
        "Harcourt"
    ],
    "wof:name":"Harcourt",
    "wof:placetype":"locality"
},
  "geometry": {"coordinates":[-78.15555999999999,45.085],"type":"Point"}
}