{
  "type": "Feature",
  "properties": {
    "gn:admin1_code":"1.0",
    "gn:asciiname":"Berwyn",
    "gn:country_code":"CA",
    "gn:dem":656,
    "gn:feature_class":"P",
    "gn:feature_code":"PPL",
    "gn:name":"Berwyn",
    "gn:population":0,
    "gn:timezone":"America/Edmonton",
    "iso:country":"CA",
    "wof:name":"Berwyn",
    "wof:placetype":"locality"
},
  "geometry": {"coordinates":[-117.73600999999999,56.15008],"type":"Point"}
}