{
  "type": "Feature",
  "properties": {
    "gn:admin1_code":"1.0",
    "gn:asciiname":"Berwyn",
    "gn:country_code":"CA",
    "gn:dem":656,
    "gn:feature_class":"P",
    "gn:feature_code":"PPL",
    "gn:name":"Berwyn",
    "gn:population":0,
    "gn:timezone":"America/Edmonton",
    "iso:country":"CA",
    "name:ara_x_preferred":[
        "\u0628\u064a\u0631\u0648\u0627\u064a\u0646"
    ],
    "name:fas_x_preferred":[
        "\u0628\u0631\u0648\u06cc\u0646"
    ],
    "name:fra_x_preferred":[
        "Berwyn"
    ],
    "name:ita_x_preferred":[
        "Berwyn"
    ],
    "wof:name":"Berwyn",
    "wof:placetype":"locality"
},
  "geometry": {"coordinates":[-117.73600999999999,56.15008],"type":"Point"}
}