{
  "type": "Feature",
  "properties": {
    "gn:admin1_code":"7",
    "gn:asciiname":"Riverside",
    "gn:country_code":"CA",
    "gn:dem":19,
    "gn:feature_class":"P",
    "gn:feature_code":"PPL",
    "gn:name":"Riverside",
    "gn:population":0,
    "gn:timezone":"America/Halifax",
    "iso:country":"CA",
    "wof:name":"Riverside",
    "wof:placetype":"locality"
},
  "geometry": {"coordinates":[-63.3933,45.20307],"type":"Point"}
}