{
  "type": "Feature",
  "properties": {
    "gn:admin1_code":"11.0",
    "gn:asciiname":"Bekevar",
    "gn:country_code":"CA",
    "gn:dem":712,
    "gn:feature_class":"P",
    "gn:feature_code":"PPLL",
    "gn:name":"Bekevar",
    "gn:population":0,
    "gn:timezone":"America/Regina",
    "iso:country":"CA",
    "wof:name":"Bekevar",
    "wof:placetype":"locality"
},
  "geometry": {"coordinates":[-102.6177,50.03334],"type":"Point"}
}