{
  "type": "Feature",
  "properties": {
    "gn:admin1_code":"8",
    "gn:asciiname":"Ostryhon Corners",
    "gn:country_code":"CA",
    "gn:dem":188,
    "gn:feature_class":"P",
    "gn:feature_code":"PPL",
    "gn:name":"Ostryhon Corners",
    "gn:population":0,
    "gn:timezone":"America/Toronto",
    "iso:country":"CA",
    "wof:name":"Ostryhon Corners",
    "wof:placetype":"locality"
},
  "geometry": {"coordinates":[-79.35472,42.89083],"type":"Point"}
}