{
  "type": "Feature",
  "properties": {
    "gn:admin1_code":"8",
    "gn:asciiname":"Gill",
    "gn:country_code":"CA",
    "gn:dem":218,
    "gn:feature_class":"P",
    "gn:feature_code":"PPL",
    "gn:name":"Gill",
    "gn:population":0,
    "gn:timezone":"America/Toronto",
    "iso:country":"CA",
    "wof:name":"Gill",
    "wof:placetype":"locality"
},
  "geometry": {"coordinates":[-79.98568,42.93861],"type":"Point"}
}