{
  "type": "Feature",
  "properties": {
    "iso:country":"CA",
    "name:cat_x_preferred":[
        "Hopedale"
    ],
    "name:ceb_x_preferred":[
        "Hopedale"
    ],
    "name:deu_x_preferred":[
        "Hopedale"
    ],
    "name:fra_x_preferred":[
        "Hopedale"
    ],
    "name:ita_x_preferred":[
        "Hopedale"
    ],
    "name:nld_x_preferred":[
        "Hopedale"
    ],
    "name:pol_x_preferred":[
        "Hopedale"
    ],
    "name:srp_x_preferred":[
        "\u0425\u043e\u0443\u0434\u0435\u0458\u043b"
    ],
    "name:swe_x_preferred":[
        "Hopedale"
    ],
    "name:vol_x_preferred":[
        "Hopedale"
    ],
    "ne:ADM0CAP":0.0,
    "ne:ADM0NAME":"Canada",
    "ne:ADM0_A3":"CAN",
    "ne:ADM1NAME":"Newfoundland and Labrador",
    "ne:ADMIN1_COD":0,
    "ne:CAPALT":0,
    "ne:CHANGED":0,
    "ne:CHECKME":0,
    "ne:COMPARE":0,
    "ne:DIFFASCII":0,
    "ne:ELEVATION":0.0,
    "ne:FEATURECLA":"Populated place",
    "ne:GEONAMEID":-1,
    "ne:GEONAMESNO":"No GeoNames match due to small population, not in GeoNames, or poor NEV placement.",
    "ne:GN_POP":0,
    "ne:GTOPO30":0.0,
    "ne:ISO_A2":"CA",
    "ne:LABELRANK":2,
    "ne:LATITUDE":55.44996,
    "ne:LONGITUDE":-60.216671,
    "ne:LS_MATCH":1,
    "ne:LS_NAME":"Hopedale",
    "ne:MAX_AREAKM":1.0,
    "ne:MAX_AREAMI":1.0,
    "ne:MAX_BBXMAX":-60.208332,
    "ne:MAX_BBXMIN":-60.233334,
    "ne:MAX_BBYMAX":55.466669,
    "ne:MAX_BBYMIN":55.450003,
    "ne:MAX_NATSCA":10.0,
    "ne:MAX_PERKM":8.0,
    "ne:MAX_PERMI":5.0,
    "ne:MAX_POP10":442,
    "ne:MAX_POP20":0,
    "ne:MAX_POP300":0,
    "ne:MAX_POP310":0,
    "ne:MAX_POP50":0,
    "ne:MEAN_BBXC":-60.220832,
    "ne:MEAN_BBYC":55.459725,
    "ne:MEGACITY":0,
    "ne:MIN_AREAKM":1.0,
    "ne:MIN_AREAMI":1.0,
    "ne:MIN_BBXMAX":-60.208332,
    "ne:MIN_BBXMIN":-60.233334,
    "ne:MIN_BBYMAX":55.466669,
    "ne:MIN_BBYMIN":55.450003,
    "ne:MIN_PERKM":8.0,
    "ne:MIN_PERMI":5.0,
    "ne:NAME":"Hopedale",
    "ne:NAMEASCII":"Hopedale",
    "ne:NAMEDIFF":0,
    "ne:NATSCALE":10,
    "ne:POP1950":0,
    "ne:POP1955":0,
    "ne:POP1960":0,
    "ne:POP1965":0,
    "ne:POP1970":0,
    "ne:POP1975":0,
    "ne:POP1980":0,
    "ne:POP1985":0,
    "ne:POP1990":0,
    "ne:POP1995":0,
    "ne:POP2000":0,
    "ne:POP2005":0,
    "ne:POP2010":0,
    "ne:POP2015":0,
    "ne:POP2020":0,
    "ne:POP2025":0,
    "ne:POP2050":0,
    "ne:POP_MAX":442,
    "ne:POP_MIN":442,
    "ne:POP_OTHER":0,
    "ne:RANK_MAX":2,
    "ne:RANK_MIN":2,
    "ne:SCALERANK":8,
    "ne:SOV0NAME":"Canada",
    "ne:SOV_A3":"CAN",
    "ne:UN_FID":0,
    "ne:UN_LAT":0.0,
    "ne:UN_LONG":0.0,
    "ne:WORLDCITY":0,
    "ne:min_zoom":7.0,
    "wof:name":"Hopedale",
    "wof:placetype":"locality"
},
  "geometry": {"coordinates":[-60.21667098147327,55.44996034659232],"type":"Point"}
}