{
  "type": "Feature",
  "properties": {
    "gn:admin1_code":"7",
    "gn:asciiname":"French River",
    "gn:country_code":"CA",
    "gn:dem":26,
    "gn:feature_class":"P",
    "gn:feature_code":"PPL",
    "gn:name":"French River",
    "gn:population":0,
    "gn:timezone":"America/Halifax",
    "iso:country":"CA",
    "name:ceb_x_preferred":[
        "French River"
    ],
    "name:deu_x_preferred":[
        "French River"
    ],
    "name:swe_x_preferred":[
        "French River"
    ],
    "wof:name":"French River",
    "wof:placetype":"locality"
},
  "geometry": {"coordinates":[-63.33348,45.71526],"type":"Point"}
}