{
  "type": "Feature",
  "properties": {
    "gn:admin1_code":"11",
    "gn:asciiname":"Steen",
    "gn:country_code":"CA",
    "gn:dem":498,
    "gn:feature_class":"P",
    "gn:feature_code":"PPL",
    "gn:name":"Steen",
    "gn:population":0,
    "gn:timezone":"America/Regina",
    "iso:country":"CA",
    "wof:name":"Steen",
    "wof:placetype":"locality"
},
  "geometry": {"coordinates":[-103.53382000000001,52.68333000000001],"type":"Point"}
}