{
  "type": "Feature",
  "properties": {
    "gn:admin1_code":"11",
    "gn:asciiname":"Steen",
    "gn:country_code":"CA",
    "gn:dem":498,
    "gn:feature_class":"P",
    "gn:feature_code":"PPL",
    "gn:name":"Steen",
    "gn:population":0,
    "gn:timezone":"America/Regina",
    "iso:country":"CA",
    "name:ceb_x_preferred":[
        "Steen"
    ],
    "name:dan_x_preferred":[
        "Steen"
    ],
    "name:deu_x_preferred":[
        "Steen"
    ],
    "name:fra_x_preferred":[
        "Steen"
    ],
    "name:ita_x_preferred":[
        "Steen"
    ],
    "name:nds_x_preferred":[
        "Steen"
    ],
    "name:nld_x_preferred":[
        "Steen"
    ],
    "name:pol_x_preferred":[
        "Steen"
    ],
    "name:rus_x_preferred":[
        "\u0421\u0442\u0435\u0435\u043d"
    ],
    "name:swe_x_preferred":[
        "Steen"
    ],
    "name:ukr_x_preferred":[
        "\u0421\u0442\u0435\u0435\u043d"
    ],
    "wof:name":"Steen",
    "wof:placetype":"locality"
},
  "geometry": {"coordinates":[-103.53382000000001,52.68333000000001],"type":"Point"}
}