{
  "type": "Feature",
  "properties": {
    "gn:admin1_code":"7",
    "gn:asciiname":"Oxford Junction",
    "gn:country_code":"CA",
    "gn:dem":26,
    "gn:feature_class":"P",
    "gn:feature_code":"PPL",
    "gn:name":"Oxford Junction",
    "gn:population":0,
    "gn:timezone":"America/Halifax",
    "iso:country":"CA",
    "wof:name":"Oxford Junction",
    "wof:placetype":"locality"
},
  "geometry": {"coordinates":[-63.88057,45.69392],"type":"Point"}
}