{
  "type": "Feature",
  "properties": {
    "gn:admin1_code":"4",
    "gn:asciiname":"Saint-Maurice",
    "gn:country_code":"CA",
    "gn:dem":38,
    "gn:feature_class":"P",
    "gn:feature_code":"PPL",
    "gn:name":"Saint-Maurice",
    "gn:population":0,
    "gn:timezone":"America/Moncton",
    "iso:country":"CA",
    "name:als_x_preferred":[
        "Saint-Maurice"
    ],
    "name:bul_x_preferred":[
        "\u0421\u0435\u043d \u041c\u043e\u0440\u0438\u0441"
    ],
    "name:cat_x_preferred":[
        "Saint-Maurice"
    ],
    "name:ceb_x_preferred":[
        "Saint-Maurice"
    ],
    "name:ces_x_preferred":[
        "Saint-Maurice"
    ],
    "name:deu_x_preferred":[
        "Saint-Maurice"
    ],
    "name:epo_x_preferred":[
        "Saint-Maurice"
    ],
    "name:fra_x_preferred":[
        "Saint-Maurice"
    ],
    "name:ita_x_preferred":[
        "Saint-Maurice"
    ],
    "name:jpn_x_preferred":[
        "\u30b5\u30f3\u30fb\u30e2\u30fc\u30ea\u30b9"
    ],
    "name:kor_x_preferred":[
        "\uc0dd\ubaa8\ub9ac\uc2a4"
    ],
    "name:nds_x_preferred":[
        "Saint-Maurice"
    ],
    "name:nld_x_preferred":[
        "Saint-Maurice"
    ],
    "name:oci_x_preferred":[
        "Saint-Maurice"
    ],
    "name:pms_x_preferred":[
        "Saint-Maurice"
    ],
    "name:pol_x_preferred":[
        "Saint-Maurice"
    ],
    "name:por_x_preferred":[
        "Saint-Maurice"
    ],
    "name:rus_x_preferred":[
        "\u0421\u0435\u043d-\u041c\u043e\u0440\u0438\u0441"
    ],
    "name:slk_x_preferred":[
        "Saint-Maurice"
    ],
    "name:spa_x_preferred":[
        "Saint-Maurice"
    ],
    "name:swe_x_preferred":[
        "Saint-Maurice"
    ],
    "name:ukr_x_preferred":[
        "\u0421\u0435\u043d-\u041c\u043e\u0440\u0438\u0441"
    ],
    "wof:name":"Saint-Maurice",
    "wof:placetype":"locality"
},
  "geometry": {"coordinates":[-64.80314,46.49287],"type":"Point"}
}