{
  "type": "Feature",
  "properties": {
    "gn:admin1_code":"11",
    "gn:asciiname":"Murraydale",
    "gn:country_code":"CA",
    "gn:dem":1217,
    "gn:feature_class":"P",
    "gn:feature_code":"PPLL",
    "gn:name":"Murraydale",
    "gn:population":0,
    "gn:timezone":"America/Regina",
    "iso:country":"CA",
    "wof:name":"Murraydale",
    "wof:placetype":"locality"
},
  "geometry": {"coordinates":[-109.28478,49.70006],"type":"Point"}
}