{
  "type": "Feature",
  "properties": {
    "gn:admin1_code":"3",
    "gn:asciiname":"Petlura",
    "gn:country_code":"CA",
    "gn:dem":574,
    "gn:feature_class":"P",
    "gn:feature_code":"PPLL",
    "gn:name":"Petlura",
    "gn:population":0,
    "gn:timezone":"America/Winnipeg",
    "iso:country":"CA",
    "wof:name":"Petlura",
    "wof:placetype":"locality"
},
  "geometry": {"coordinates":[-101.02338,51.06669],"type":"Point"}
}