{
  "type": "Feature",
  "properties": {
    "gn:admin1_code":"8",
    "gn:asciiname":"Fort Erie North",
    "gn:country_code":"CA",
    "gn:dem":187,
    "gn:feature_class":"P",
    "gn:feature_code":"PPL",
    "gn:name":"Fort Erie North",
    "gn:population":0,
    "gn:timezone":"America/Toronto",
    "iso:country":"CA",
    "wof:name":"Fort Erie North",
    "wof:placetype":"locality"
},
  "geometry": {"coordinates":[-78.92265999999999,42.93227],"type":"Point"}
}