{
  "type": "Feature",
  "properties": {
    "gn:admin1_code":"2",
    "gn:asciiname":"Okanagan Falls",
    "gn:country_code":"CA",
    "gn:dem":357,
    "gn:feature_class":"P",
    "gn:feature_code":"PPL",
    "gn:name":"Okanagan Falls",
    "gn:population":0,
    "gn:timezone":"America/Vancouver",
    "iso:country":"CA",
    "wof:name":"Okanagan Falls",
    "wof:placetype":"locality"
},
  "geometry": {"coordinates":[-119.56667,49.35],"type":"Point"}
}