{
  "type": "Feature",
  "properties": {
    "gn:admin1_code":"7",
    "gn:asciiname":"St. Marys River",
    "gn:country_code":"CA",
    "gn:dem":8,
    "gn:feature_class":"P",
    "gn:feature_code":"PPL",
    "gn:name":"St. Marys River",
    "gn:population":0,
    "gn:timezone":"America/Halifax",
    "iso:country":"CA",
    "wof:name":"St. Marys River",
    "wof:placetype":"locality"
},
  "geometry": {"coordinates":[-61.9312,45.08045],"type":"Point"}
}