{
  "type": "Feature",
  "properties": {
    "gn:admin1_code":"7",
    "gn:asciiname":"St. Marys River",
    "gn:country_code":"CA",
    "gn:dem":8,
    "gn:feature_class":"P",
    "gn:feature_code":"PPL",
    "gn:name":"St. Marys River",
    "gn:population":0,
    "gn:timezone":"America/Halifax",
    "iso:country":"CA",
    "name:ara_x_preferred":[
        "\u0646\u0647\u0631 \u0633\u0627\u0646 \u0645\u0627\u0631\u064a"
    ],
    "name:fas_x_preferred":[
        "\u0631\u0648\u062f\u062e\u0627\u0646\u0647 \u0633\u0646\u062a \u0645\u0627\u0631\u06cc\u0633"
    ],
    "name:hin_x_preferred":[
        "\u0938\u0947\u0902\u091f \u092e\u0948\u0930\u0940\u095b \u0928\u0926\u0940"
    ],
    "name:hun_x_preferred":[
        "St. Marys River"
    ],
    "name:ind_x_preferred":[
        "Sungai St. Marys"
    ],
    "name:kor_x_preferred":[
        "\uc138\uc778\ud2b8 \uba54\ub9ac\uc2a4 \ub9ac\ubc84"
    ],
    "name:tur_x_preferred":[
        "St. Marys Nehri"
    ],
    "name:urd_x_preferred":[
        "\u0633\u06cc\u0646\u0679 \u0645\u0627\u0631\u06cc\u0632 \u0631\u06cc\u0648\u0631"
    ],
    "wof:name":"St. Marys River",
    "wof:placetype":"locality"
},
  "geometry": {"coordinates":[-61.9312,45.08045],"type":"Point"}
}