{
  "type": "Feature",
  "properties": {
    "gn:admin1_code":"8",
    "gn:asciiname":"Tobacco Lake",
    "gn:country_code":"CA",
    "gn:dem":230,
    "gn:feature_class":"P",
    "gn:feature_code":"PPL",
    "gn:name":"Tobacco Lake",
    "gn:population":0,
    "gn:timezone":"America/Toronto",
    "iso:country":"CA",
    "wof:name":"Tobacco Lake",
    "wof:placetype":"locality"
},
  "geometry": {"coordinates":[-82.4349,45.85436],"type":"Point"}
}