{
  "type": "Feature",
  "properties": {
    "iso:country":"CA",
    "name:eng_x_preferred":[
        "Cootes Paradise B"
    ],
    "name:unk_x_variant":[
        "Cootes Paradise B"
    ],
    "qs:gn_adm0_cc":"CA",
    "qs:gn_local":6948482,
    "qs:gn_nam_loc":"dundas",
    "qs:gn_namadm1":"08",
    "qs:local_max":2086,
    "qs:local_sum":5844,
    "qs:localhoods":8,
    "qs:name":"Cootes Paradise B",
    "qs:name_adm0":"Canada",
    "qs:name_adm1":"Ontario",
    "qs:name_adm2":"Hamilton",
    "qs:name_local":"Dundas",
    "qs:photo_max":126,
    "qs:photo_sum":714,
    "qs:placetype":"Suburb",
    "qs:quad_count":44,
    "qs:woe_adm0":23424775,
    "qs:woe_adm1":2344922,
    "qs:woe_adm2":29375120,
    "qs:woe_funk":"Parented by a neighborhood",
    "qs:woe_lau":0,
    "qs:woe_local":55999149,
    "qs:woe_ver":"7.10.0",
    "wof:lang":[
        "eng"
    ],
    "wof:name":"Cootes Paradise B",
    "wof:placetype":"neighbourhood"
},
  "geometry": {"coordinates":[-79.90331500000001,43.279948],"type":"Point"}
}