{
  "type": "Feature",
  "properties": {
    "gn:admin1_code":"4.0",
    "gn:asciiname":"Carpenter",
    "gn:country_code":"CA",
    "gn:dem":14,
    "gn:feature_class":"P",
    "gn:feature_code":"PPL",
    "gn:name":"Carpenter",
    "gn:population":0,
    "gn:timezone":"America/Moncton",
    "iso:country":"CA",
    "name:ang_x_preferred":[
        "Timborwyrhta"
    ],
    "name:arc_x_preferred":[
        "\u0722\u0713\u072a\u0718\u072c\u0710"
    ],
    "name:ben_x_preferred":[
        "\u099b\u09c1\u09a4\u09cb\u09b0"
    ],
    "name:bod_x_preferred":[
        "\u0f64\u0f72\u0f44\u0f0b\u0f56\u0f5f\u0f7c\u0f0b\u0f56\u0f0d"
    ],
    "name:bre_x_preferred":[
        "Kalvez"
    ],
    "name:bul_x_preferred":[
        "\u041c\u0430\u0440\u0430\u043d\u0433\u043e\u0437"
    ],
    "name:cat_x_preferred":[
        "Fuster"
    ],
    "name:csb_x_preferred":[
        "Cesla"
    ],
    "name:dan_x_preferred":[
        "T\u00f8mrer"
    ],
    "name:deu_x_preferred":[
        "Zimmerer"
    ],
    "name:eml_x_preferred":[
        "Marang\u00f2un"
    ],
    "name:epo_x_preferred":[
        "\u0108arpentisto"
    ],
    "name:est_x_preferred":[
        "Puusepp"
    ],
    "name:eus_x_preferred":[
        "Zurgintza"
    ],
    "name:fas_x_preferred":[
        "\u0646\u062c\u0627\u0631"
    ],
    "name:fin_x_preferred":[
        "Puusepp\u00e4"
    ],
    "name:fra_x_preferred":[
        "Charpentier"
    ],
    "name:fry_x_preferred":[
        "Timmerman"
    ],
    "name:gla_x_preferred":[
        "Saor"
    ],
    "name:gle_x_preferred":[
        "Si\u00fain\u00e9ir"
    ],
    "name:hin_x_preferred":[
        "\u092c\u0922\u093c\u0908"
    ],
    "name:hun_x_preferred":[
        "\u00c1cs"
    ],
    "name:hye_x_preferred":[
        "\u0531\u057f\u0561\u0572\u0571\u0561\u0563\u0578\u0580\u056e"
    ],
    "name:ind_x_preferred":[
        "Tukang kayu"
    ],
    "name:ita_x_preferred":[
        "Carpentiere"
    ],
    "name:kir_x_preferred":[
        "\u0416\u044b\u0433\u0430\u0447 \u0443\u0441\u0442\u0430\u0447\u044b\u043b\u044b\u043a"
    ],
    "name:lit_x_preferred":[
        "Dailid\u0117"
    ],
    "name:lmo_x_preferred":[
        "Legnamee"
    ],
    "name:ltz_x_preferred":[
        "Zammermann"
    ],
    "name:mal_x_preferred":[
        "\u0d06\u0d36\u0d3e\u0d30\u0d3f"
    ],
    "name:mar_x_preferred":[
        "\u0938\u0941\u0924\u093e\u0930\u0915\u093e\u092e"
    ],
    "name:nld_x_preferred":[
        "Timmerman"
    ],
    "name:nno_x_preferred":[
        "T\u00f8mrar"
    ],
    "name:nor_x_preferred":[
        "T\u00f8mrer"
    ],
    "name:oci_x_preferred":[
        "Fusti\u00e8r"
    ],
    "name:pol_x_preferred":[
        "Cie\u015bla"
    ],
    "name:que_x_preferred":[
        "Llaqllaq"
    ],
    "name:ron_x_preferred":[
        "Dulgher"
    ],
    "name:rus_x_preferred":[
        "\u041f\u043b\u043e\u0442\u043d\u0438\u043a"
    ],
    "name:scn_x_preferred":[
        "Lignaloru"
    ],
    "name:swe_x_preferred":[
        "Timmerman"
    ],
    "name:tam_x_preferred":[
        "\u0ba4\u0b9a\u0bcd\u0b9a\u0bb0\u0bcd"
    ],
    "name:tel_x_preferred":[
        "\u0c35\u0c21\u0c4d\u0c30\u0c02\u0c17\u0c3f"
    ],
    "name:tgl_x_preferred":[
        "Karpintero"
    ],
    "name:ukr_x_preferred":[
        "\u0422\u0435\u0441\u043b\u044f\u0440"
    ],
    "name:urd_x_preferred":[
        "\u0646\u062c\u0627\u0631\u062a"
    ],
    "name:vie_x_preferred":[
        "Th\u1ee3 m\u1ed9c"
    ],
    "wof:name":"Carpenter",
    "wof:placetype":"locality"
},
  "geometry": {"coordinates":[-66.06259,45.67141],"type":"Point"}
}