{
  "type": "Feature",
  "properties": {
    "gn:admin1_code":"11",
    "gn:asciiname":"Gapview",
    "gn:country_code":"CA",
    "gn:dem":635,
    "gn:feature_class":"P",
    "gn:feature_code":"PPLL",
    "gn:name":"Gapview",
    "gn:population":0,
    "gn:timezone":"America/Regina",
    "iso:country":"CA",
    "wof:name":"Gapview",
    "wof:placetype":"locality"
},
  "geometry": {"coordinates":[-102.83429,49.80004],"type":"Point"}
}