{
  "type": "Feature",
  "properties": {
    "gn:admin1_code":"1",
    "gn:asciiname":"Grovedale",
    "gn:country_code":"CA",
    "gn:dem":682,
    "gn:feature_class":"P",
    "gn:feature_code":"PPLL",
    "gn:name":"Grovedale",
    "gn:population":0,
    "gn:timezone":"America/Edmonton",
    "iso:country":"CA",
    "name:fra_x_preferred":[
        "Grovedale"
    ],
    "wof:name":"Grovedale",
    "wof:placetype":"locality"
},
  "geometry": {"coordinates":[-118.86941000000002,55.04997],"type":"Point"}
}