{
  "type": "Feature",
  "properties": {
    "iso:country":"CA",
    "name:eng_x_preferred":[
        "River Oaks"
    ],
    "qs:gn_adm0_cc":"CA",
    "qs:gn_local":5911592,
    "qs:gn_nam_loc":"burlington",
    "qs:gn_namadm1":"08",
    "qs:local_max":750,
    "qs:local_sum":2488,
    "qs:localhoods":11,
    "qs:name":"River Oaks",
    "qs:name_adm0":"Canada",
    "qs:name_adm1":"Ontario",
    "qs:name_adm2":"Halton",
    "qs:name_local":"Burlington",
    "qs:photo_max":140,
    "qs:photo_sum":287,
    "qs:placetype":"Suburb",
    "qs:quad_count":20,
    "qs:woe_adm0":23424775,
    "qs:woe_adm1":2344922,
    "qs:woe_adm2":29375078,
    "qs:woe_funk":"Parented by a neighborhood",
    "qs:woe_lau":0,
    "qs:woe_local":4124,
    "qs:woe_ver":"7.10.0",
    "wof:lang":[
        "eng"
    ],
    "wof:name":"River Oaks",
    "wof:placetype":"neighbourhood"
},
  "geometry": {"coordinates":[-79.744719,43.461341],"type":"Point"}
}