{
  "type": "Feature",
  "properties": {
    "gn:admin1_code":"8.0",
    "gn:asciiname":"Clear Lake",
    "gn:country_code":"CA",
    "gn:dem":299,
    "gn:feature_class":"P",
    "gn:feature_code":"PPL",
    "gn:name":"Clear Lake",
    "gn:population":0,
    "gn:timezone":"America/Toronto",
    "iso:country":"CA",
    "wof:name":"Clear Lake",
    "wof:placetype":"locality"
},
  "geometry": {"coordinates":[-79.01572,45.00809],"type":"Point"}
}