{
  "type": "Feature",
  "properties": {
    "gn:admin1_code":"8",
    "gn:asciiname":"Vyner",
    "gn:country_code":"CA",
    "gn:dem":184,
    "gn:feature_class":"P",
    "gn:feature_code":"PPL",
    "gn:name":"Vyner",
    "gn:population":0,
    "gn:timezone":"America/Toronto",
    "iso:country":"CA",
    "name:fra_x_preferred":[
        "Vyner"
    ],
    "wof:name":"Vyner",
    "wof:placetype":"locality"
},
  "geometry": {"coordinates":[-82.25417,43.0075],"type":"Point"}
}