{
  "type": "Feature",
  "properties": {
    "gn:admin1_code":"3.0",
    "gn:asciiname":"Clear Springs",
    "gn:country_code":"CA",
    "gn:dem":256,
    "gn:feature_class":"P",
    "gn:feature_code":"PPLL",
    "gn:name":"Clear Springs",
    "gn:population":0,
    "gn:timezone":"America/Winnipeg",
    "iso:country":"CA",
    "name:ceb_x_preferred":[
        "Clear Springs"
    ],
    "name:deu_x_preferred":[
        "Clear Springs"
    ],
    "wof:name":"Clear Springs",
    "wof:placetype":"locality"
},
  "geometry": {"coordinates":[-96.6842,49.56029],"type":"Point"}
}