{
  "type": "Feature",
  "properties": {
    "gn:admin1_code":"8",
    "gn:asciiname":"Halls Lake",
    "gn:country_code":"CA",
    "gn:dem":334,
    "gn:feature_class":"P",
    "gn:feature_code":"PPL",
    "gn:name":"Halls Lake",
    "gn:population":0,
    "gn:timezone":"America/Toronto",
    "iso:country":"CA",
    "wof:name":"Halls Lake",
    "wof:placetype":"locality"
},
  "geometry": {"coordinates":[-78.75516,45.1215],"type":"Point"}
}