{
  "type": "Feature",
  "properties": {
    "gn:admin1_code":"7",
    "gn:asciiname":"Two Rivers",
    "gn:country_code":"CA",
    "gn:dem":32,
    "gn:feature_class":"P",
    "gn:feature_code":"PPLL",
    "gn:name":"Two Rivers",
    "gn:population":0,
    "gn:timezone":"America/Halifax",
    "iso:country":"CA",
    "name:ceb_x_preferred":[
        "Two Rivers"
    ],
    "name:deu_x_preferred":[
        "Two Rivers"
    ],
    "name:ita_x_preferred":[
        "Two Rivers"
    ],
    "name:nld_x_preferred":[
        "Two Rivers"
    ],
    "name:pol_x_preferred":[
        "Two Rivers"
    ],
    "name:por_x_preferred":[
        "Two Rivers"
    ],
    "name:srp_x_preferred":[
        "\u0422\u0443 \u0420\u0438\u0432\u0435\u0440\u0441"
    ],
    "name:swe_x_preferred":[
        "Two Rivers"
    ],
    "name:urd_x_preferred":[
        "\u0679\u0648 \u0631\u06cc\u0648\u0631\u0632"
    ],
    "name:vol_x_preferred":[
        "Two Rivers"
    ],
    "wof:name":"Two Rivers",
    "wof:placetype":"locality"
},
  "geometry": {"coordinates":[-64.48352,45.66025],"type":"Point"}
}