{
  "type": "Feature",
  "properties": {
    "gn:admin1_code":"7",
    "gn:asciiname":"Two Rivers",
    "gn:country_code":"CA",
    "gn:dem":32,
    "gn:feature_class":"P",
    "gn:feature_code":"PPLL",
    "gn:name":"Two Rivers",
    "gn:population":0,
    "gn:timezone":"America/Halifax",
    "iso:country":"CA",
    "wof:name":"Two Rivers",
    "wof:placetype":"locality"
},
  "geometry": {"coordinates":[-64.48352,45.66025],"type":"Point"}
}