{
  "type": "Feature",
  "properties": {
    "gn:admin1_code":"1",
    "gn:asciiname":"Wabasca-Desmarais",
    "gn:country_code":"CA",
    "gn:dem":542,
    "gn:feature_class":"P",
    "gn:feature_code":"PPL",
    "gn:name":"Wabasca-Desmarais",
    "gn:population":0,
    "gn:timezone":"America/Edmonton",
    "iso:country":"CA",
    "wof:name":"Wabasca-Desmarais",
    "wof:placetype":"locality"
},
  "geometry": {"coordinates":[-113.84999999999999,55.96666999999999],"type":"Point"}
}