{
  "type": "Feature",
  "properties": {
    "gn:admin1_code":"8.0",
    "gn:asciiname":"Dunnet's Corner",
    "gn:country_code":"CA",
    "gn:dem":231,
    "gn:feature_class":"P",
    "gn:feature_code":"PPLL",
    "gn:name":"Dunnet's Corner",
    "gn:population":0,
    "gn:timezone":"America/Toronto",
    "iso:country":"CA",
    "wof:name":"Dunnet's Corner",
    "wof:placetype":"locality"
},
  "geometry": {"coordinates":[-80.34969,46.38339000000001],"type":"Point"}
}