{
  "type": "Feature",
  "properties": {
    "gn:admin1_code":"11",
    "gn:asciiname":"Unwin",
    "gn:country_code":"CA",
    "gn:dem":546,
    "gn:feature_class":"P",
    "gn:feature_code":"PPLL",
    "gn:name":"Unwin",
    "gn:population":0,
    "gn:timezone":"America/Edmonton",
    "iso:country":"CA",
    "name:deu_x_preferred":[
        "Unwin"
    ],
    "name:fra_x_preferred":[
        "Unwin"
    ],
    "name:ita_x_preferred":[
        "Unwin"
    ],
    "name:nds_x_preferred":[
        "Unwin"
    ],
    "name:por_x_preferred":[
        "Unwin"
    ],
    "name:rus_x_preferred":[
        "\u0410\u043d\u0432\u0438\u043d"
    ],
    "wof:name":"Unwin",
    "wof:placetype":"locality"
},
  "geometry": {"coordinates":[-109.86824,52.93346],"type":"Point"}
}