{
  "type": "Feature",
  "properties": {
    "gn:admin1_code":"8",
    "gn:asciiname":"Manotick Station",
    "gn:country_code":"CA",
    "gn:dem":102,
    "gn:feature_class":"P",
    "gn:feature_code":"PPL",
    "gn:name":"Manotick Station",
    "gn:population":0,
    "gn:timezone":"America/Toronto",
    "iso:country":"CA",
    "wof:name":"Manotick Station",
    "wof:placetype":"locality"
},
  "geometry": {"coordinates":[-75.62266,45.25434],"type":"Point"}
}