{
  "type": "Feature",
  "properties": {
    "iso:country":"CA",
    "name:dut_x_preferred":[
        "Kleinburg"
    ],
    "name:eng_x_preferred":[
        "Kleinburg"
    ],
    "name:jpn_x_preferred":[
        "\u30af\u30ec\u30a4\u30f3\u30d0\u30fc\u30b0"
    ],
    "name:urd_x_preferred":[
        "\u0646\u06cc\u0634\u0648\u06cc\u0644\u060c \u0627\u0648\u0646\u0679\u0627\u0631\u06cc\u0648"
    ],
    "qs_pg:aaroncc":"CA",
    "qs_pg:name":"Kleinburg",
    "qs_pg:name_adm0":"Canada",
    "qs_pg:name_adm1":"Ontario",
    "qs_pg:photos":1397,
    "qs_pg:photos_1k":283,
    "qs_pg:photos_9k":6,
    "qs_pg:photos_9r":7,
    "qs_pg:photos_all":1397,
    "qs_pg:photos_sr":12,
    "qs_pg:pop_sr":0,
    "qs_pg:qs_pg_placetype":"locality",
    "qs_pg:qs_pg_placetype_gp":"Town",
    "qs_pg:woe_adm0":23424775,
    "woe:adm0_id":23424775,
    "woe:name_adm0":"Canada",
    "woe:name_adm1":"Ontario",
    "woe:placetype":"Town",
    "wof:name":"Kleinburg",
    "wof:placetype":"locality"
},
  "geometry": {"coordinates":[-79.613242,43.840549],"type":"Point"}
}