{
  "type": "Feature",
  "properties": {
    "gn:admin1_code":"2",
    "gn:asciiname":"Renata",
    "gn:country_code":"CA",
    "gn:dem":446,
    "gn:feature_class":"P",
    "gn:feature_code":"PPLL",
    "gn:name":"Renata",
    "gn:population":0,
    "gn:timezone":"America/Vancouver",
    "iso:country":"CA",
    "wof:name":"Renata",
    "wof:placetype":"locality"
},
  "geometry": {"coordinates":[-118.10227999999999,49.43313],"type":"Point"}
}