{
  "type": "Feature",
  "properties": {
    "iso:country":"CA",
    "name:eng_x_preferred":[
        "Falun"
    ],
    "name:fra_x_preferred":[
        "Falun"
    ],
    "qs:name":"Falun",
    "qs:name_adm0":"Canada",
    "qs:name_adm1":"Alberta",
    "qs:photos":6,
    "qs:photos_1k":1,
    "qs:photos_9k":1,
    "qs:photos_9r":1,
    "qs:photos_all":6,
    "qs:photos_sr":1,
    "qs:placetype":"Town",
    "qs:pop_sr":"0",
    "wd:elevation":110.0,
    "wd:wordcount":2133,
    "wof:name":"Falun",
    "wof:placetype":"locality"
},
  "geometry": {"coordinates":[-113.834667,52.961719],"type":"Point"}
}