{
  "type": "Feature",
  "properties": {
    "gn:admin1_code":"7",
    "gn:asciiname":"Jimtown",
    "gn:country_code":"CA",
    "gn:dem":1,
    "gn:feature_class":"P",
    "gn:feature_code":"PPLL",
    "gn:name":"Jimtown",
    "gn:population":0,
    "gn:timezone":"America/Halifax",
    "iso:country":"CA",
    "name:deu_x_preferred":[
        "Jimtown"
    ],
    "name:fra_x_preferred":[
        "Jimtown"
    ],
    "name:vol_x_preferred":[
        "Jimtown"
    ],
    "wof:name":"Jimtown",
    "wof:placetype":"locality"
},
  "geometry": {"coordinates":[-61.89858,45.70014000000001],"type":"Point"}
}