{
  "type": "Feature",
  "properties": {
    "iso:country":"CA",
    "name:fra_x_preferred":[
        "Fort Severn"
    ],
    "ne:ADM0CAP":0.0,
    "ne:ADM0NAME":"Canada",
    "ne:ADM0_A3":"CAN",
    "ne:ADM1NAME":"Ontario",
    "ne:ADMIN1_COD":0,
    "ne:CAPALT":0,
    "ne:CHANGED":0,
    "ne:CHECKME":0,
    "ne:COMPARE":0,
    "ne:DIFFASCII":0,
    "ne:ELEVATION":0.0,
    "ne:FEATURECLA":"Populated place",
    "ne:GEONAMEID":-1,
    "ne:GEONAMESNO":"Top 50 ranks with no GeoNames match due to small population, not in GeoNames, or poor NEV placement.",
    "ne:GN_POP":0,
    "ne:GTOPO30":0.0,
    "ne:ISO_A2":"CA",
    "ne:LABELRANK":2,
    "ne:LATITUDE":55.983339,
    "ne:LONGITUDE":-87.649984,
    "ne:LS_MATCH":1,
    "ne:LS_NAME":"Fort Severn",
    "ne:MAX_AREAKM":0.0,
    "ne:MAX_AREAMI":0.0,
    "ne:MAX_BBXMAX":-87.633333,
    "ne:MAX_BBXMIN":-87.641667,
    "ne:MAX_BBYMAX":55.991667,
    "ne:MAX_BBYMIN":55.983333,
    "ne:MAX_NATSCA":100.0,
    "ne:MAX_PERKM":3.0,
    "ne:MAX_PERMI":2.0,
    "ne:MAX_POP10":125,
    "ne:MAX_POP20":125,
    "ne:MAX_POP300":125,
    "ne:MAX_POP310":0,
    "ne:MAX_POP50":125,
    "ne:MEAN_BBXC":-87.6375,
    "ne:MEAN_BBYC":55.9875,
    "ne:MEGACITY":0,
    "ne:MIN_AREAKM":0.0,
    "ne:MIN_AREAMI":0.0,
    "ne:MIN_BBXMAX":-87.633333,
    "ne:MIN_BBXMIN":-87.641667,
    "ne:MIN_BBYMAX":55.991667,
    "ne:MIN_BBYMIN":55.983333,
    "ne:MIN_PERKM":3.0,
    "ne:MIN_PERMI":2.0,
    "ne:NAME":"Fort Severn",
    "ne:NAMEASCII":"Fort Severn",
    "ne:NAMEDIFF":0,
    "ne:NATSCALE":110,
    "ne:POP1950":0,
    "ne:POP1955":0,
    "ne:POP1960":0,
    "ne:POP1965":0,
    "ne:POP1970":0,
    "ne:POP1975":0,
    "ne:POP1980":0,
    "ne:POP1985":0,
    "ne:POP1990":0,
    "ne:POP1995":0,
    "ne:POP2000":0,
    "ne:POP2005":0,
    "ne:POP2010":0,
    "ne:POP2015":0,
    "ne:POP2020":0,
    "ne:POP2025":0,
    "ne:POP2050":0,
    "ne:POP_MAX":125,
    "ne:POP_MIN":125,
    "ne:POP_OTHER":0,
    "ne:RANK_MAX":1,
    "ne:RANK_MIN":1,
    "ne:SCALERANK":3,
    "ne:SOV0NAME":"Canada",
    "ne:SOV_A3":"CAN",
    "ne:UN_FID":0,
    "ne:UN_LAT":0.0,
    "ne:UN_LONG":0.0,
    "ne:WORLDCITY":0,
    "ne:min_zoom":5.0,
    "wof:name":"Fort Severn",
    "wof:placetype":"locality"
},
  "geometry": {"coordinates":[-87.6499835629632,55.98333864249298],"type":"Point"}
}