{
  "type": "Feature",
  "properties": {
    "gn:admin1_code":"8",
    "gn:asciiname":"Middlemarch",
    "gn:country_code":"CA",
    "gn:dem":226,
    "gn:feature_class":"P",
    "gn:feature_code":"PPL",
    "gn:name":"Middlemarch",
    "gn:population":0,
    "gn:timezone":"America/Toronto",
    "iso:country":"CA",
    "wof:name":"Middlemarch",
    "wof:placetype":"locality"
},
  "geometry": {"coordinates":[-81.26517,42.75715],"type":"Point"}
}