{
  "type": "Feature",
  "properties": {
    "gn:admin1_code":"8",
    "gn:asciiname":"Middlemarch",
    "gn:country_code":"CA",
    "gn:dem":226,
    "gn:feature_class":"P",
    "gn:feature_code":"PPL",
    "gn:name":"Middlemarch",
    "gn:population":0,
    "gn:timezone":"America/Toronto",
    "iso:country":"CA",
    "name:ara_x_preferred":[
        "\u0645\u062f\u0644 \u0645\u0627\u0631\u0634"
    ],
    "name:cym_x_preferred":[
        "Middlemarch"
    ],
    "name:deu_x_preferred":[
        "Middlemarch"
    ],
    "name:fas_x_preferred":[
        "\u0645\u06cc\u062f\u0644\u200c\u0645\u0627\u0631\u0686"
    ],
    "name:fra_x_preferred":[
        "Middlemarch"
    ],
    "name:heb_x_preferred":[
        "\u05de\u05d9\u05d3\u05dc\u05de\u05d0\u05e8\u05e5'"
    ],
    "name:ita_x_preferred":[
        "Middlemarch"
    ],
    "name:kir_x_preferred":[
        "\u041c\u0438\u0434\u043b\u043c\u0430\u0440\u0447"
    ],
    "name:nld_x_preferred":[
        "Middlemarch"
    ],
    "name:pan_x_preferred":[
        "\u0a2e\u0a3f\u0a21\u0a32\u0a2e\u0a3e\u0a30\u0a1a"
    ],
    "name:pol_x_preferred":[
        "Miasteczko Middlemarch"
    ],
    "name:por_x_preferred":[
        "Middlemarch"
    ],
    "name:spa_x_preferred":[
        "Middlemarch"
    ],
    "name:swe_x_preferred":[
        "Middlemarch"
    ],
    "name:tur_x_preferred":[
        "Middlemarch"
    ],
    "name:zho_x_preferred":[
        "\u7c73\u5fb7\u5c14\u9a6c\u5951"
    ],
    "wof:name":"Middlemarch",
    "wof:placetype":"locality"
},
  "geometry": {"coordinates":[-81.26517,42.75715],"type":"Point"}
}