{
  "type": "Feature",
  "properties": {
    "gn:admin1_code":"8",
    "gn:asciiname":"Opasquia",
    "gn:country_code":"CA",
    "gn:dem":271,
    "gn:feature_class":"P",
    "gn:feature_code":"PPL",
    "gn:name":"Opasquia",
    "gn:population":0,
    "gn:timezone":"America/Winnipeg",
    "iso:country":"CA",
    "wof:name":"Opasquia",
    "wof:placetype":"locality"
},
  "geometry": {"coordinates":[-93.58369,53.26685],"type":"Point"}
}