{
  "type": "Feature",
  "properties": {
    "gn:admin1_code":"4.0",
    "gn:asciiname":"Perth",
    "gn:country_code":"CA",
    "gn:dem":234,
    "gn:feature_class":"P",
    "gn:feature_code":"PPL",
    "gn:name":"Perth",
    "gn:population":0,
    "gn:timezone":"America/Moncton",
    "iso:country":"CA",
    "wof:name":"Perth",
    "wof:placetype":"locality"
},
  "geometry": {"coordinates":[-67.61604,46.68595],"type":"Point"}
}