{
  "type": "Feature",
  "properties": {
    "gn:admin1_code":"7.0",
    "gn:asciiname":"College Grant",
    "gn:country_code":"CA",
    "gn:dem":154,
    "gn:feature_class":"P",
    "gn:feature_code":"PPL",
    "gn:name":"College Grant",
    "gn:population":0,
    "gn:timezone":"America/Halifax",
    "iso:country":"CA",
    "wof:name":"College Grant",
    "wof:placetype":"locality"
},
  "geometry": {"coordinates":[-62.07617,45.40144],"type":"Point"}
}