{
  "type": "Feature",
  "properties": {
    "gn:admin1_code":"1.0",
    "gn:asciiname":"Akenside",
    "gn:country_code":"CA",
    "gn:dem":649,
    "gn:feature_class":"P",
    "gn:feature_code":"PPLL",
    "gn:name":"Akenside",
    "gn:population":0,
    "gn:timezone":"America/Edmonton",
    "iso:country":"CA",
    "wof:name":"Akenside",
    "wof:placetype":"locality"
},
  "geometry": {"coordinates":[-113.252,53.60014],"type":"Point"}
}