{
  "type": "Feature",
  "properties": {
    "gn:admin1_code":"7.0",
    "gn:asciiname":"East Baccaro",
    "gn:country_code":"CA",
    "gn:dem":13,
    "gn:feature_class":"P",
    "gn:feature_code":"PPL",
    "gn:name":"East Baccaro",
    "gn:population":0,
    "gn:timezone":"America/Halifax",
    "iso:country":"CA",
    "wof:name":"East Baccaro",
    "wof:placetype":"locality"
},
  "geometry": {"coordinates":[-65.46845,43.46245],"type":"Point"}
}