{
  "type": "Feature",
  "properties": {
    "gn:admin1_code":"3",
    "gn:asciiname":"Leifur",
    "gn:country_code":"CA",
    "gn:dem":259,
    "gn:feature_class":"P",
    "gn:feature_code":"PPLL",
    "gn:name":"Leifur",
    "gn:population":0,
    "gn:timezone":"America/Winnipeg",
    "iso:country":"CA",
    "wof:name":"Leifur",
    "wof:placetype":"locality"
},
  "geometry": {"coordinates":[-98.76515999999999,50.74312000000001],"type":"Point"}
}