{
  "type": "Feature",
  "properties": {
    "gn:admin1_code":"7",
    "gn:asciiname":"Rogers Hill",
    "gn:country_code":"CA",
    "gn:dem":65,
    "gn:feature_class":"P",
    "gn:feature_code":"PPL",
    "gn:name":"Rogers Hill",
    "gn:population":0,
    "gn:timezone":"America/Halifax",
    "iso:country":"CA",
    "wof:name":"Rogers Hill",
    "wof:placetype":"locality"
},
  "geometry": {"coordinates":[-62.82966,45.63724000000001],"type":"Point"}
}