{
  "type": "Feature",
  "properties": {
    "gn:admin1_code":"7",
    "gn:asciiname":"Murphy Lake",
    "gn:country_code":"CA",
    "gn:dem":216,
    "gn:feature_class":"P",
    "gn:feature_code":"PPL",
    "gn:name":"Murphy Lake",
    "gn:population":0,
    "gn:timezone":"America/Halifax",
    "iso:country":"CA",
    "name:ceb_x_preferred":[
        "Murphy Lake"
    ],
    "name:swe_x_preferred":[
        "Murphy Lake"
    ],
    "wof:name":"Murphy Lake",
    "wof:placetype":"locality"
},
  "geometry": {"coordinates":[-64.53381999999999,44.90289],"type":"Point"}
}