{
  "type": "Feature",
  "properties": {
    "iso:country":"CA",
    "name:bul_x_preferred":[
        "\u0414\u044a\u043d\u0432\u0435\u0433\u0430\u043d"
    ],
    "name:ceb_x_preferred":[
        "Dunvegan"
    ],
    "name:eus_x_preferred":[
        "Dunvegan"
    ],
    "name:fas_x_preferred":[
        "\u062f\u0627\u0646\u0648\u06af\u0627\u0646"
    ],
    "name:fin_x_preferred":[
        "D\u00f9n Bheagain"
    ],
    "name:fra_x_preferred":[
        "Dunvegan"
    ],
    "name:gla_x_preferred":[
        "D\u00f9n Bheagain"
    ],
    "name:gle_x_preferred":[
        "D\u00fan Bheagain"
    ],
    "name:ita_x_preferred":[
        "Dunvegan"
    ],
    "name:nld_x_preferred":[
        "Dunvegan"
    ],
    "name:swe_x_preferred":[
        "Dunvegan"
    ],
    "qs_pg:aaroncc":"CA",
    "qs_pg:name":"Dunvegan",
    "qs_pg:name_adm0":"Canada",
    "qs_pg:name_adm1":"Ontario",
    "qs_pg:photos":71,
    "qs_pg:photos_1k":14,
    "qs_pg:photos_9k":1,
    "qs_pg:photos_9r":2,
    "qs_pg:photos_all":71,
    "qs_pg:photos_sr":2,
    "qs_pg:pop_sr":0,
    "qs_pg:qs_pg_placetype":"locality",
    "qs_pg:qs_pg_placetype_gp":"Town",
    "qs_pg:woe_adm0":23424775,
    "woe:adm0_id":23424775,
    "woe:name_adm0":"Canada",
    "woe:name_adm1":"Ontario",
    "woe:placetype":"Town",
    "wof:name":"Dunvegan",
    "wof:placetype":"locality"
},
  "geometry": {"coordinates":[-74.79028700000001,45.393387],"type":"Point"}
}