{
  "type": "Feature",
  "properties": {
    "gn:admin1_code":"10",
    "gn:admin2_code":"9.0",
    "gn:admin3_code":"98010.0",
    "gn:asciiname":"Stick Point",
    "gn:country_code":"CA",
    "gn:dem":-9999,
    "gn:feature_class":"P",
    "gn:feature_code":"PPL",
    "gn:name":"Stick Point",
    "gn:population":0,
    "gn:timezone":"America/Blanc-Sablon",
    "iso:country":"CA",
    "wof:name":"Stick Point",
    "wof:placetype":"locality"
},
  "geometry": {"coordinates":[-57.66019,51.42228],"type":"Point"}
}