{
  "type": "Feature",
  "properties": {
    "gn:admin1_code":"8",
    "gn:asciiname":"Gillies",
    "gn:country_code":"CA",
    "gn:dem":297,
    "gn:feature_class":"P",
    "gn:feature_code":"PPL",
    "gn:name":"Gillies",
    "gn:population":0,
    "gn:timezone":"America/Toronto",
    "iso:country":"CA",
    "wof:name":"Gillies",
    "wof:placetype":"locality"
},
  "geometry": {"coordinates":[-79.74806,47.37861],"type":"Point"}
}