{
  "type": "Feature",
  "properties": {
    "gn:admin1_code":"1.0",
    "gn:asciiname":"Christina Crossing",
    "gn:country_code":"CA",
    "gn:dem":430,
    "gn:feature_class":"P",
    "gn:feature_code":"PPLL",
    "gn:name":"Christina Crossing",
    "gn:population":0,
    "gn:timezone":"America/Edmonton",
    "iso:country":"CA",
    "wof:name":"Christina Crossing",
    "wof:placetype":"locality"
},
  "geometry": {"coordinates":[-110.45734,56.25852],"type":"Point"}
}