{
  "type": "Feature",
  "properties": {
    "gn:admin1_code":"10.0",
    "gn:admin2_code":"15.0",
    "gn:admin3_code":"79030.0",
    "gn:asciiname":"Domaine-Nominingue",
    "gn:country_code":"CA",
    "gn:dem":249,
    "gn:feature_class":"P",
    "gn:feature_code":"PPL",
    "gn:name":"Domaine-Nominingue",
    "gn:population":0,
    "gn:timezone":"America/Toronto",
    "iso:country":"CA",
    "wof:name":"Domaine-Nominingue",
    "wof:placetype":"locality"
},
  "geometry": {"coordinates":[-75.01528,46.40056],"type":"Point"}
}