{
  "type": "Feature",
  "properties": {
    "gn:admin1_code":"8",
    "gn:asciiname":"Menie",
    "gn:country_code":"CA",
    "gn:dem":147,
    "gn:feature_class":"P",
    "gn:feature_code":"PPL",
    "gn:name":"Menie",
    "gn:population":0,
    "gn:timezone":"America/Toronto",
    "iso:country":"CA",
    "wof:name":"Menie",
    "wof:placetype":"locality"
},
  "geometry": {"coordinates":[-77.69806,44.31194],"type":"Point"}
}