{
  "type": "Feature",
  "properties": {
    "gn:country":"CA",
    "gn:fcode":"PPL",
    "gn:population":0,
    "iso:country":"CA",
    "name:eng_x_preferred":[
        "Port Hastings"
    ],
    "name:fra_x_preferred":[
        "Port Hastings"
    ],
    "name:gla_x_preferred":[
        "C\u00f2bh a' Phl\u00e0stair"
    ],
    "name:gle_x_preferred":[
        "C\u00f3bh a' Phl\u00e1stair"
    ],
    "name:nld_x_preferred":[
        "Port Hastings"
    ],
    "name:spa_x_preferred":[
        "Port Hastings"
    ],
    "qs:name":"Port Hastings",
    "qs:name_adm0":"Canada",
    "qs:name_adm1":"Nova Scotia",
    "qs:photos":76,
    "qs:photos_1k":15,
    "qs:photos_9k":1,
    "qs:photos_9r":3,
    "qs:photos_all":76,
    "qs:photos_sr":3,
    "qs:placetype":"Town",
    "qs:pop_sr":"0",
    "wd:wordcount":320,
    "wof:name":"Port Hastings",
    "wof:placetype":"locality",
    "wof:population":0
},
  "geometry": {"coordinates":[-61.39854,45.65014],"type":"Point"}
}