{
  "type": "Feature",
  "properties": {
    "gn:admin1_code":"2",
    "gn:admin2_code":"5924.0",
    "gn:asciiname":"Hecate",
    "gn:country_code":"CA",
    "gn:dem":5,
    "gn:feature_class":"P",
    "gn:feature_code":"PPL",
    "gn:name":"Hecate",
    "gn:population":0,
    "gn:timezone":"America/Vancouver",
    "iso:country":"CA",
    "name:ara_x_preferred":[
        "\u0647\u064a\u0643\u0627\u062a"
    ],
    "name:ast_x_preferred":[
        "H\u00e9cate"
    ],
    "name:bar_x_preferred":[
        "Hekate"
    ],
    "name:bel_x_preferred":[
        "\u0413\u0435\u043a\u0430\u0442\u0430"
    ],
    "name:bre_x_preferred":[
        "Hekate"
    ],
    "name:bul_x_preferred":[
        "\u0425\u0435\u043a\u0430\u0442\u0430"
    ],
    "name:cat_x_preferred":[
        "H\u00e8cate"
    ],
    "name:ces_x_preferred":[
        "Hekat\u00e9"
    ],
    "name:dan_x_preferred":[
        "Hekate"
    ],
    "name:deu_x_preferred":[
        "Hekate"
    ],
    "name:ell_x_preferred":[
        "\u0395\u03ba\u03ac\u03c4\u03b7"
    ],
    "name:epo_x_preferred":[
        "Hekato"
    ],
    "name:est_x_preferred":[
        "Hekate"
    ],
    "name:fas_x_preferred":[
        "\u0647\u06a9\u0627\u062a\u0647"
    ],
    "name:fin_x_preferred":[
        "Hekate"
    ],
    "name:fra_x_preferred":[
        "H\u00e9cate"
    ],
    "name:glg_x_preferred":[
        "H\u00e9cate"
    ],
    "name:heb_x_preferred":[
        "\u05d4\u05e7\u05d8\u05d4"
    ],
    "name:hrv_x_preferred":[
        "Hekata"
    ],
    "name:hun_x_preferred":[
        "Hekat\u00e9"
    ],
    "name:hye_x_preferred":[
        "\u0540\u0565\u056f\u0561\u057f\u0561"
    ],
    "name:ind_x_preferred":[
        "Hekate"
    ],
    "name:ita_x_preferred":[
        "Ecate"
    ],
    "name:jpn_x_preferred":[
        "\u30d8\u30ab\u30c6\u30fc"
    ],
    "name:kat_x_preferred":[
        "\u10f0\u10d4\u10d9\u10d0\u10e2\u10d4"
    ],
    "name:kaz_x_preferred":[
        "\u0413\u0435\u043a\u0430\u0442\u0430"
    ],
    "name:kor_x_preferred":[
        "\ud5e4\uce74\ud14c"
    ],
    "name:lat_x_preferred":[
        "Hecate"
    ],
    "name:lit_x_preferred":[
        "Hekat\u0117"
    ],
    "name:ltz_x_preferred":[
        "Hekate"
    ],
    "name:mkd_x_preferred":[
        "\u0425\u0435\u043a\u0430\u0442\u0430"
    ],
    "name:nld_x_preferred":[
        "Hekate"
    ],
    "name:nor_x_preferred":[
        "Hekate"
    ],
    "name:pol_x_preferred":[
        "Hekate"
    ],
    "name:por_x_preferred":[
        "H\u00e9cate"
    ],
    "name:ron_x_preferred":[
        "Hecate"
    ],
    "name:rus_x_preferred":[
        "\u0413\u0435\u043a\u0430\u0442\u0430"
    ],
    "name:sco_x_preferred":[
        "Hecate"
    ],
    "name:slk_x_preferred":[
        "Hekat\u00e9"
    ],
    "name:slv_x_preferred":[
        "Hekata"
    ],
    "name:spa_x_preferred":[
        "H\u00e9cate"
    ],
    "name:sqi_x_preferred":[
        "Hekata"
    ],
    "name:srp_x_preferred":[
        "\u0425\u0435\u043a\u0430\u0442\u0430"
    ],
    "name:swe_x_preferred":[
        "Hekate"
    ],
    "name:tgl_x_preferred":[
        "Hecate"
    ],
    "name:tur_x_preferred":[
        "Hekate"
    ],
    "name:ukr_x_preferred":[
        "\u0413\u0435\u043a\u0430\u0442\u0430"
    ],
    "name:vie_x_preferred":[
        "Hecate"
    ],
    "name:war_x_preferred":[
        "Hecate"
    ],
    "name:zho_x_preferred":[
        "\u8d6b\u5361\u5fd2"
    ],
    "wof:name":"Hecate",
    "wof:placetype":"locality"
},
  "geometry": {"coordinates":[-126.74659,49.85134],"type":"Point"}
}