{
  "type": "Feature",
  "properties": {
    "gn:admin1_code":"2",
    "gn:admin2_code":"5924.0",
    "gn:asciiname":"Hecate",
    "gn:country_code":"CA",
    "gn:dem":5,
    "gn:feature_class":"P",
    "gn:feature_code":"PPL",
    "gn:name":"Hecate",
    "gn:population":0,
    "gn:timezone":"America/Vancouver",
    "iso:country":"CA",
    "wof:name":"Hecate",
    "wof:placetype":"locality"
},
  "geometry": {"coordinates":[-126.74659,49.85134],"type":"Point"}
}