{
  "type": "Feature",
  "properties": {
    "gn:admin1_code":"8",
    "gn:asciiname":"Kenson Park",
    "gn:country_code":"CA",
    "gn:dem":79,
    "gn:feature_class":"P",
    "gn:feature_code":"PPL",
    "gn:name":"Kenson Park",
    "gn:population":0,
    "gn:timezone":"America/Toronto",
    "iso:country":"CA",
    "wof:name":"Kenson Park",
    "wof:placetype":"locality"
},
  "geometry": {"coordinates":[-75.7675,45.35583],"type":"Point"}
}