{
  "type": "Feature",
  "properties": {
    "gn:admin1_code":"10",
    "gn:admin2_code":"7.0",
    "gn:admin3_code":"84005.0",
    "gn:asciiname":"Pine Lodge",
    "gn:country_code":"CA",
    "gn:dem":84,
    "gn:feature_class":"P",
    "gn:feature_code":"PPL",
    "gn:name":"Pine Lodge",
    "gn:population":0,
    "gn:timezone":"America/Toronto",
    "iso:country":"CA",
    "wof:name":"Pine Lodge",
    "wof:placetype":"locality"
},
  "geometry": {"coordinates":[-76.45639,45.52083],"type":"Point"}
}