{
  "type": "Feature",
  "properties": {
    "gn:gn_country":"CA",
    "gn:gn_fcode":"PPL",
    "gn:gn_pop":0,
    "iso:country":"CA",
    "name:dut_x_preferred":[
        "Shalalth"
    ],
    "name:eng_x_preferred":[
        "Shalalth"
    ],
    "qs_pg:aaroncc":"CA",
    "qs_pg:gn_country":"CA",
    "qs_pg:gn_fcode":"PPL",
    "qs_pg:gn_pop":0,
    "qs_pg:name":"Shalalth",
    "qs_pg:name_adm0":"Canada",
    "qs_pg:name_adm1":"British Columbia",
    "qs_pg:photos":1,
    "qs_pg:photos_1k":1,
    "qs_pg:photos_9k":1,
    "qs_pg:photos_9r":1,
    "qs_pg:photos_all":1,
    "qs_pg:photos_sr":1,
    "qs_pg:pop_sr":0,
    "qs_pg:qs_pg_placetype":"locality",
    "qs_pg:qs_pg_placetype_gp":"Town",
    "qs_pg:woe_adm0":23424775,
    "woe:adm0_id":23424775,
    "woe:name_adm0":"Canada",
    "woe:name_adm1":"British Columbia",
    "woe:placetype":"Town",
    "wof:name":"Shalalth",
    "wof:placetype":"locality"
},
  "geometry": {"coordinates":[-122.21937,50.73307],"type":"Point"}
}