{
  "type": "Feature",
  "properties": {
    "gn:admin1_code":"7.0",
    "gn:asciiname":"Buckleys Corner",
    "gn:country_code":"CA",
    "gn:dem":59,
    "gn:feature_class":"P",
    "gn:feature_code":"PPL",
    "gn:name":"Buckleys Corner",
    "gn:population":0,
    "gn:timezone":"America/Halifax",
    "iso:country":"CA",
    "wof:name":"Buckleys Corner",
    "wof:placetype":"locality"
},
  "geometry": {"coordinates":[-64.69709,45.10252],"type":"Point"}
}