{
  "type": "Feature",
  "properties": {
    "iso:country":"CA",
    "name:eng_x_preferred":[
        "Chester Basin"
    ],
    "name:gla_x_preferred":[
        "Chester Basin"
    ],
    "name:nld_x_preferred":[
        "Chester Basin"
    ],
    "qs:name":"Chester Basin",
    "qs:name_adm0":"Canada",
    "qs:name_adm1":"Nova Scotia",
    "qs:photos":77,
    "qs:photos_1k":16,
    "qs:photos_9k":1,
    "qs:photos_9r":3,
    "qs:photos_all":77,
    "qs:photos_sr":3,
    "qs:placetype":"Town",
    "qs:pop_sr":"0",
    "wd:wordcount":114,
    "wof:name":"Chester Basin",
    "wof:placetype":"locality"
},
  "geometry": {"coordinates":[-64.30767899999999,44.567357],"type":"Point"}
}