{
  "type": "Feature",
  "properties": {
    "iso:country":"CA",
    "name:ceb_x_preferred":[
        "Sainte-Marguerite-Marie"
    ],
    "name:eng_x_preferred":[
        "Sainte-Marguerite"
    ],
    "name:eus_x_preferred":[
        "Sainte-Marguerite-Marie"
    ],
    "name:fas_x_preferred":[
        "\u0633\u0646\u062a-\u0645\u0627\u0631\u06af\u0631\u06cc\u062a-\u0645\u0627\u0631\u06cc\u060c \u06a9\u0628\u06a9"
    ],
    "name:fas_x_variant":[
        "\u0633\u0646\u062a-\u0645\u0627\u0631\u06af\u0631\u06cc\u062a-\u0645\u0627\u0631\u06cc"
    ],
    "name:fra_x_preferred":[
        "Sainte-Marguerite-Marie"
    ],
    "name:fra_x_variant":[
        "Sainte-Marguerite"
    ],
    "name:swe_x_preferred":[
        "Sainte-Marguerite-Marie"
    ],
    "name:urd_x_preferred":[
        "\u0633\u06cc\u0646-\u0645\u0631\u06af\u06cc\u0631\u0679\u06d2-\u0645\u0631\u06d2"
    ],
    "qs:gn_adm0_cc":"CA",
    "qs:gn_local":6169141,
    "qs:gn_nam_loc":"trois-rivieres",
    "qs:gn_namadm1":"10",
    "qs:local_max":4119,
    "qs:local_sum":9025,
    "qs:localhoods":14,
    "qs:name":"Sainte-Marguerite",
    "qs:name_adm0":"Canada",
    "qs:name_adm1":"Qu\u00e9bec",
    "qs:name_adm2":"Trois-Rivi\u00e8res",
    "qs:name_local":"Trois-Rivi\u00e8res",
    "qs:photo_max":88,
    "qs:photo_sum":250,
    "qs:placetype":"Suburb",
    "qs:quad_count":20,
    "qs:woe_adm0":23424775,
    "qs:woe_adm1":2344924,
    "qs:woe_adm2":29375104,
    "qs:woe_funk":"Parented by a neighborhood",
    "qs:woe_lau":0,
    "qs:woe_local":3474,
    "qs:woe_ver":"7.10.0",
    "wof:lang":[
        "fre"
    ],
    "wof:name":"Sainte-Marguerite",
    "wof:placetype":"neighbourhood"
},
  "geometry": {"coordinates":[-72.585122,46.339503],"type":"Point"}
}