{
  "type": "Feature",
  "properties": {
    "iso:country":"CA",
    "name:eng_x_preferred":[
        "Rumsey"
    ],
    "name:fre_x_preferred":[
        "Rumsey"
    ],
    "qs:name":"Rumsey",
    "qs:name_adm0":"Canada",
    "qs:name_adm1":"Alberta",
    "qs:photos":7,
    "qs:photos_1k":1,
    "qs:photos_9k":1,
    "qs:photos_9r":1,
    "qs:photos_all":7,
    "qs:photos_sr":1,
    "qs:placetype":"Town",
    "qs:pop_sr":"0",
    "wd:wordcount":10,
    "wof:name":"Rumsey",
    "wof:placetype":"locality"
},
  "geometry": {"coordinates":[-112.843773,51.842293],"type":"Point"}
}