{
  "type": "Feature",
  "properties": {
    "gn:admin1_code":"4",
    "gn:asciiname":"Southfield",
    "gn:country_code":"CA",
    "gn:dem":115,
    "gn:feature_class":"P",
    "gn:feature_code":"PPL",
    "gn:name":"Southfield",
    "gn:population":0,
    "gn:timezone":"America/Moncton",
    "iso:country":"CA",
    "name:ceb_x_preferred":[
        "Southfield"
    ],
    "name:pol_x_preferred":[
        "Southfield"
    ],
    "name:swe_x_preferred":[
        "Southfield"
    ],
    "wof:name":"Southfield",
    "wof:placetype":"locality"
},
  "geometry": {"coordinates":[-65.62114,45.59573],"type":"Point"}
}