{
  "type": "Feature",
  "properties": {
    "gn:admin1_code":"10.0",
    "gn:admin2_code":"11.0",
    "gn:asciiname":"Cap-au-Renard",
    "gn:country_code":"CA",
    "gn:dem":39,
    "gn:feature_class":"P",
    "gn:feature_code":"PPL",
    "gn:name":"Cap-au-Renard",
    "gn:population":0,
    "gn:timezone":"America/Toronto",
    "iso:country":"CA",
    "wof:name":"Cap-au-Renard",
    "wof:placetype":"locality"
},
  "geometry": {"coordinates":[-66.24023000000001,49.19504000000001],"type":"Point"}
}