{
  "type": "Feature",
  "properties": {
    "gn:admin1_code":"9.0",
    "gn:asciiname":"Confederation Bridge",
    "gn:country_code":"CA",
    "gn:dem":-9999,
    "gn:feature_class":"P",
    "gn:feature_code":"PPL",
    "gn:name":"Confederation Bridge",
    "gn:population":0,
    "gn:timezone":"America/Moncton",
    "iso:country":"CA",
    "name:dan_x_preferred":[
        "Confederation Bridge"
    ],
    "name:deu_x_preferred":[
        "Confederation Bridge"
    ],
    "name:fin_x_preferred":[
        "Confederation Bridge"
    ],
    "name:heb_x_preferred":[
        "\u05d2\u05e9\u05e8 \u05d4\u05e7\u05d5\u05e0\u05e4\u05d3\u05e8\u05e6\u05d9\u05d4"
    ],
    "name:hrv_x_preferred":[
        "Most Konfederacije"
    ],
    "name:ita_x_preferred":[
        "Confederation Bridge"
    ],
    "name:jpn_x_preferred":[
        "\u30b3\u30f3\u30d5\u30a7\u30c7\u30ec\u30fc\u30b7\u30e7\u30f3\u6a4b"
    ],
    "name:kor_x_preferred":[
        "\ucee8\ud398\ub354\ub808\uc774\uc158 \ub2e4\ub9ac"
    ],
    "name:mkd_x_preferred":[
        "\u041c\u043e\u0441\u0442 \u043d\u0430 \u041a\u043e\u043d\u0444\u0435\u0434\u0435\u0440\u0430\u0446\u0438\u0458\u0430\u0442\u0430"
    ],
    "name:nld_x_preferred":[
        "Confederation Bridge"
    ],
    "name:nor_x_preferred":[
        "Confederation Bridge"
    ],
    "name:pol_x_preferred":[
        "Most Konfederacji"
    ],
    "name:por_x_preferred":[
        "Ponte Confederation"
    ],
    "name:rus_x_preferred":[
        "\u041c\u043e\u0441\u0442 \u041a\u043e\u043d\u0444\u0435\u0434\u0435\u0440\u0430\u0446\u0438\u0438"
    ],
    "name:swe_x_preferred":[
        "Confederation Bridge"
    ],
    "name:ukr_x_preferred":[
        "\u041c\u0456\u0441\u0442 \u041a\u043e\u043d\u0444\u0435\u0434\u0435\u0440\u0430\u0446\u0456\u0457"
    ],
    "name:zho_x_preferred":[
        "\u806f\u90a6\u5927\u6a4b"
    ],
    "wof:name":"Confederation Bridge",
    "wof:placetype":"locality"
},
  "geometry": {"coordinates":[-63.7725,46.1944],"type":"Point"}
}