{
  "type": "Feature",
  "properties": {
    "gn:admin1_code":"9.0",
    "gn:asciiname":"Confederation Bridge",
    "gn:country_code":"CA",
    "gn:dem":-9999,
    "gn:feature_class":"P",
    "gn:feature_code":"PPL",
    "gn:name":"Confederation Bridge",
    "gn:population":0,
    "gn:timezone":"America/Moncton",
    "iso:country":"CA",
    "wof:name":"Confederation Bridge",
    "wof:placetype":"locality"
},
  "geometry": {"coordinates":[-63.7725,46.1944],"type":"Point"}
}