{
  "type": "Feature",
  "properties": {
    "gn:admin1_code":"11.0",
    "gn:asciiname":"Belbutte",
    "gn:country_code":"CA",
    "gn:dem":663,
    "gn:feature_class":"P",
    "gn:feature_code":"PPL",
    "gn:name":"Belbutte",
    "gn:population":0,
    "gn:timezone":"America/Regina",
    "iso:country":"CA",
    "wof:name":"Belbutte",
    "wof:placetype":"locality"
},
  "geometry": {"coordinates":[-107.81798000000001,53.36684],"type":"Point"}
}