{
  "type": "Feature",
  "properties": {
    "gn:admin1_code":"9.0",
    "gn:asciiname":"Abney",
    "gn:country_code":"CA",
    "gn:dem":36,
    "gn:feature_class":"P",
    "gn:feature_code":"PPLL",
    "gn:name":"Abney",
    "gn:population":0,
    "gn:timezone":"America/Halifax",
    "iso:country":"CA",
    "wof:name":"Abney",
    "wof:placetype":"locality"
},
  "geometry": {"coordinates":[-62.56534,45.98342],"type":"Point"}
}