{
  "type": "Feature",
  "properties": {
    "gn:admin1_code":"8",
    "gn:asciiname":"Glanmire",
    "gn:country_code":"CA",
    "gn:dem":302,
    "gn:feature_class":"P",
    "gn:feature_code":"PPL",
    "gn:name":"Glanmire",
    "gn:population":0,
    "gn:timezone":"America/Toronto",
    "iso:country":"CA",
    "wof:name":"Glanmire",
    "wof:placetype":"locality"
},
  "geometry": {"coordinates":[-77.68389000000001,44.75389000000001],"type":"Point"}
}