{
  "type": "Feature",
  "properties": {
    "gn:admin1_code":"8",
    "gn:asciiname":"Glanmire",
    "gn:country_code":"CA",
    "gn:dem":302,
    "gn:feature_class":"P",
    "gn:feature_code":"PPL",
    "gn:name":"Glanmire",
    "gn:population":0,
    "gn:timezone":"America/Toronto",
    "iso:country":"CA",
    "name:cat_x_preferred":[
        "Glanmire"
    ],
    "name:eus_x_preferred":[
        "Glanmire"
    ],
    "name:gle_x_preferred":[
        "Gleann Maghair"
    ],
    "name:rus_x_preferred":[
        "\u0413\u043b\u0430\u043d\u043c\u0430\u0439\u0440"
    ],
    "name:swe_x_preferred":[
        "Glanmire"
    ],
    "wof:name":"Glanmire",
    "wof:placetype":"locality"
},
  "geometry": {"coordinates":[-77.68389000000001,44.75389000000001],"type":"Point"}
}