{
  "type": "Feature",
  "properties": {
    "gn:admin1_code":"2.0",
    "gn:asciiname":"Blewett",
    "gn:country_code":"CA",
    "gn:dem":745,
    "gn:feature_class":"P",
    "gn:feature_code":"PPL",
    "gn:name":"Blewett",
    "gn:population":0,
    "gn:timezone":"America/Vancouver",
    "iso:country":"CA",
    "wof:name":"Blewett",
    "wof:placetype":"locality"
},
  "geometry": {"coordinates":[-117.40833000000001,49.475],"type":"Point"}
}