{
  "type": "Feature",
  "properties": {
    "gn:admin1_code":"3",
    "gn:asciiname":"Olha",
    "gn:country_code":"CA",
    "gn:dem":628,
    "gn:feature_class":"P",
    "gn:feature_code":"PPLL",
    "gn:name":"Olha",
    "gn:population":0,
    "gn:timezone":"America/Winnipeg",
    "iso:country":"CA",
    "wof:name":"Olha",
    "wof:placetype":"locality"
},
  "geometry": {"coordinates":[-100.55616000000001,50.6689],"type":"Point"}
}