{
  "type": "Feature",
  "properties": {
    "gn:admin1_code":"5.0",
    "gn:asciiname":"Butts",
    "gn:country_code":"CA",
    "gn:dem":34,
    "gn:feature_class":"P",
    "gn:feature_code":"PPLL",
    "gn:name":"Butts",
    "gn:population":0,
    "gn:timezone":"America/St_Johns",
    "iso:country":"CA",
    "name:deu_x_preferred":[
        "Butts"
    ],
    "name:nld_x_preferred":[
        "Butts"
    ],
    "name:pol_x_preferred":[
        "Butts"
    ],
    "name:rus_x_preferred":[
        "\u0411\u0430\u0442\u0442\u0441"
    ],
    "wof:name":"Butts",
    "wof:placetype":"locality"
},
  "geometry": {"coordinates":[-54.28142,48.8166],"type":"Point"}
}