{
  "type": "Feature",
  "properties": {
    "gn:country":"CA",
    "gn:fcode":"ADMD",
    "gn:pop":0,
    "iso:country":"CA",
    "name:eng_x_preferred":[
        "South Stormont"
    ],
    "qs:name":"South Stormont",
    "qs:photos_9r":0,
    "qs:photos_sr":0,
    "qs:pop_sr":"0",
    "wd:wordcount":432,
    "wof:name":"South Stormont",
    "wof:placetype":"localadmin",
    "wof:population":0
},
  "geometry": {"coordinates":[-74.96599999999999,45.0834],"type":"Point"}
}