{
  "type": "Feature",
  "properties": {
    "gn:country":"CA",
    "gn:fcode":"ADMD",
    "gn:pop":0,
    "iso:country":"CA",
    "name:ara_x_preferred":[
        "\u0633\u0627\u0648\u062b \u0633\u062a\u0648\u0631\u0645\u0648\u0646\u062a"
    ],
    "name:eng_x_preferred":[
        "South Stormont"
    ],
    "name:fra_x_preferred":[
        "South Stormont"
    ],
    "name:nld_x_preferred":[
        "South Stormont"
    ],
    "name:pol_x_preferred":[
        "South Stormont"
    ],
    "name:por_x_preferred":[
        "South Stormont"
    ],
    "name:spa_x_preferred":[
        "South Stormont"
    ],
    "name:ukr_x_preferred":[
        "\u0421\u0430\u0443\u0442 \u0421\u0442\u043e\u0440\u043c\u043e\u043d\u0442"
    ],
    "qs:name":"South Stormont",
    "qs:photos_9r":0,
    "qs:photos_sr":0,
    "qs:pop_sr":"0",
    "wd:wordcount":432,
    "wof:name":"South Stormont",
    "wof:placetype":"localadmin",
    "wof:population":0
},
  "geometry": {"coordinates":[-74.96599999999999,45.0834],"type":"Point"}
}