{
  "type": "Feature",
  "properties": {
    "iso:country":"CA",
    "name:eng_x_preferred":[
        "Briarwood"
    ],
    "wd:wordcount":89,
    "wof:lang":[
        "eng"
    ],
    "wof:name":"Briarwood",
    "wof:placetype":"neighbourhood"
},
  "geometry": {"coordinates":[-106.564026,52.113441],"type":"Point"}
}