{
  "type": "Feature",
  "properties": {
    "gn:admin1_code":"1",
    "gn:asciiname":"Tulliby Lake",
    "gn:country_code":"CA",
    "gn:dem":582,
    "gn:feature_class":"P",
    "gn:feature_code":"PPL",
    "gn:name":"Tulliby Lake",
    "gn:population":0,
    "gn:timezone":"America/Edmonton",
    "iso:country":"CA",
    "wof:name":"Tulliby Lake",
    "wof:placetype":"locality"
},
  "geometry": {"coordinates":[-110.18528000000001,53.71639],"type":"Point"}
}