{
  "type": "Feature",
  "properties": {
    "gn:admin1_code":"1",
    "gn:asciiname":"Millicent",
    "gn:country_code":"CA",
    "gn:dem":728,
    "gn:feature_class":"P",
    "gn:feature_code":"PPLL",
    "gn:name":"Millicent",
    "gn:population":0,
    "gn:timezone":"America/Edmonton",
    "iso:country":"CA",
    "wof:name":"Millicent",
    "wof:placetype":"locality"
},
  "geometry": {"coordinates":[-111.76848,50.70012],"type":"Point"}
}