{
  "type": "Feature",
  "properties": {
    "gn:admin1_code":"8",
    "gn:asciiname":"Haddo",
    "gn:country_code":"CA",
    "gn:dem":78,
    "gn:feature_class":"P",
    "gn:feature_code":"PPL",
    "gn:name":"Haddo",
    "gn:population":0,
    "gn:timezone":"America/Toronto",
    "iso:country":"CA",
    "wof:name":"Haddo",
    "wof:placetype":"locality"
},
  "geometry": {"coordinates":[-75.37444000000001,44.86778],"type":"Point"}
}