{
  "type": "Feature",
  "properties": {
    "gn:admin1_code":"1",
    "gn:asciiname":"Parkland Beach",
    "gn:country_code":"CA",
    "gn:dem":932,
    "gn:feature_class":"P",
    "gn:feature_code":"PPL",
    "gn:name":"Parkland Beach",
    "gn:population":0,
    "gn:timezone":"America/Edmonton",
    "iso:country":"CA",
    "wof:name":"Parkland Beach",
    "wof:placetype":"locality"
},
  "geometry": {"coordinates":[-114.06872,52.60011],"type":"Point"}
}