{
  "type": "Feature",
  "properties": {
    "gn:admin1_code":"2.0",
    "gn:admin2_code":"5927",
    "gn:asciiname":"Westview",
    "gn:country_code":"CA",
    "gn:dem":28,
    "gn:feature_class":"P",
    "gn:feature_code":"PPL",
    "gn:name":"Westview",
    "gn:population":0,
    "gn:timezone":"America/Vancouver",
    "iso:country":"CA",
    "name:ara_x_preferred":[
        "\u0628\u0648\u064a\u0644 \u0631\u064a\u0641\u0631"
    ],
    "name:ceb_x_preferred":[
        "Powell River"
    ],
    "name:deu_x_preferred":[
        "Powell River"
    ],
    "name:eng_x_preferred":[
        "Westview"
    ],
    "name:fas_x_preferred":[
        "\u067e\u0627\u0648\u0644 \u0631\u06cc\u0648\u0631"
    ],
    "name:fra_x_preferred":[
        "Westview"
    ],
    "name:fra_x_variant":[
        "Powell River"
    ],
    "name:ita_x_preferred":[
        "Powell River"
    ],
    "name:por_x_preferred":[
        "Powell River"
    ],
    "name:srp_x_preferred":[
        "\u041f\u0430\u0443\u0435\u043b \u0420\u0438\u0432\u0435\u0440"
    ],
    "name:swe_x_preferred":[
        "Powell River"
    ],
    "wof:name":"Westview",
    "wof:placetype":"locality"
},
  "geometry": {"coordinates":[-124.52677,49.83582],"type":"Point"}
}