{
  "type": "Feature",
  "properties": {
    "gn:admin1_code":"2.0",
    "gn:admin2_code":"5927",
    "gn:asciiname":"Westview",
    "gn:country_code":"CA",
    "gn:dem":28,
    "gn:feature_class":"P",
    "gn:feature_code":"PPL",
    "gn:name":"Westview",
    "gn:population":0,
    "gn:timezone":"America/Vancouver",
    "iso:country":"CA",
    "name:eng_x_preferred":[
        "Westview"
    ],
    "name:fra_x_preferred":[
        "Westview"
    ],
    "wof:name":"Westview",
    "wof:placetype":"locality"
},
  "geometry": {"coordinates":[-124.52677,49.83582],"type":"Point"}
}