{
  "type": "Feature",
  "properties": {
    "gn:admin1_code":"8",
    "gn:asciiname":"Great Desert",
    "gn:country_code":"CA",
    "gn:dem":308,
    "gn:feature_class":"P",
    "gn:feature_code":"PPL",
    "gn:name":"Great Desert",
    "gn:population":0,
    "gn:timezone":"America/Toronto",
    "iso:country":"CA",
    "wof:name":"Great Desert",
    "wof:placetype":"locality"
},
  "geometry": {"coordinates":[-79.02528000000002,46.21417],"type":"Point"}
}