{
  "type": "Feature",
  "properties": {
    "gn:admin1_code":"3.0",
    "gn:asciiname":"Bayend",
    "gn:country_code":"CA",
    "gn:dem":250,
    "gn:feature_class":"P",
    "gn:feature_code":"PPLL",
    "gn:name":"Bayend",
    "gn:population":0,
    "gn:timezone":"America/Winnipeg",
    "iso:country":"CA",
    "wof:name":"Bayend",
    "wof:placetype":"locality"
},
  "geometry": {"coordinates":[-99.02636,51.24812],"type":"Point"}
}