{
  "type": "Feature",
  "properties": {
    "gn:country":"CA",
    "gn:fcode":"PPL",
    "gn:population":24388,
    "iso:country":"CA",
    "name:ara_x_preferred":[
        "\u0633\u0627\u0646 \u0628\u0631\u0648\u0646\u0648 \u062f\u064a \u0645\u0648\u0646\u062a\u0631\u0627\u0641\u0644\u064a"
    ],
    "name:atj_x_preferred":[
        "Saint-Bruno-de-Montarville"
    ],
    "name:ceb_x_preferred":[
        "Saint-Bruno-de-Montarville"
    ],
    "name:deu_x_preferred":[
        "Saint-Bruno-de-Montarville"
    ],
    "name:ell_x_preferred":[
        "\u03a3\u03b1\u03b9\u03bd-\u039c\u03c0\u03c1\u03bf\u03c5\u03bd\u03cc-\u03bd\u03c4\u03b5-\u039c\u03bf\u03bd\u03c4\u03b1\u03c1\u03b2\u03af\u03bb"
    ],
    "name:eng_x_preferred":[
        "Saint-Bruno-de-Montarville"
    ],
    "name:eus_x_preferred":[
        "Saint-Bruno-de-Montarville"
    ],
    "name:fas_x_preferred":[
        "\u0633\u0646-\u0628\u0631\u0648\u0646\u0648-\u062f\u0648-\u0645\u0648\u0646\u062a\u0627\u0631\u0648\u06cc\u0644"
    ],
    "name:fra_x_preferred":[
        "Saint-Bruno-de-Montarville"
    ],
    "name:hak_x_preferred":[
        "Saint-Bruno-de-Montarville"
    ],
    "name:ita_x_preferred":[
        "Saint-Bruno-de-Montarville"
    ],
    "name:jpn_x_preferred":[
        "\u30b5\u30f3\u30fb\u30d6\u30eb\u30ce\u30fb\u30c7\u30a5\u30fb\u30e2\u30f3\u30bf\u30eb\u30f4\u30a3\u30eb"
    ],
    "name:nld_x_preferred":[
        "Saint-Bruno-de-Montarville"
    ],
    "name:pol_x_preferred":[
        "Saint-Bruno-de-Montarville"
    ],
    "name:por_x_preferred":[
        "Saint-Bruno-de-Montarville"
    ],
    "name:spa_x_preferred":[
        "Saint-Bruno-de-Montarville"
    ],
    "name:srp_x_preferred":[
        "\u0421\u0435\u043d \u0411\u0440\u0438\u043d\u043e \u0434\u0435 \u041c\u043e\u043d\u0442\u0430\u0440\u0432\u0438\u043b"
    ],
    "name:swe_x_preferred":[
        "Saint-Bruno-de-Montarville"
    ],
    "name:tur_x_preferred":[
        "Saint-Bruno-de-Montarville"
    ],
    "name:urd_x_preferred":[
        "\u0633\u06cc\u0646\u0679-\u0628\u0631\u0648\u0646\u0648-\u062f\u06d2-\u0645\u0648\u0646\u062a\u0631\u0648\u0644\u06d2"
    ],
    "qs_pg:aaroncc":"CA",
    "qs_pg:gn_country":"CA",
    "qs_pg:gn_fcode":"PPL",
    "qs_pg:gn_pop":24388,
    "qs_pg:name":"St.-Bruno-de-Montarville",
    "qs_pg:name_adm0":"Canada",
    "qs_pg:name_adm1":"Qu\u00e9bec",
    "qs_pg:photos":708,
    "qs_pg:photos_1k":143,
    "qs_pg:photos_9k":3,
    "qs_pg:photos_9r":5,
    "qs_pg:photos_all":708,
    "qs_pg:photos_sr":8,
    "qs_pg:pop_sr":7,
    "qs_pg:qs_pg_placetype":"locality",
    "qs_pg:qs_pg_placetype_gp":"Town",
    "qs_pg:woe_adm0":23424775,
    "woe:adm0_id":23424775,
    "woe:name_adm0":"Canada",
    "woe:name_adm1":"Qu\u00e9bec",
    "woe:placetype":"Town",
    "wof:name":"St.-Bruno-de-Montarville",
    "wof:placetype":"locality",
    "wof:population":24388
},
  "geometry": {"coordinates":[-73.34916,45.53341],"type":"Point"}
}