{
  "type": "Feature",
  "properties": {
    "gn:admin1_code":"8",
    "gn:asciiname":"Millgrove",
    "gn:country_code":"CA",
    "gn:dem":255,
    "gn:feature_class":"P",
    "gn:feature_code":"PPL",
    "gn:name":"Millgrove",
    "gn:population":0,
    "gn:timezone":"America/Toronto",
    "iso:country":"CA",
    "wof:name":"Millgrove",
    "wof:placetype":"locality"
},
  "geometry": {"coordinates":[-79.96083,43.3375],"type":"Point"}
}