{
  "type": "Feature",
  "properties": {
    "gn:admin1_code":"2",
    "gn:admin2_code":"5941.0",
    "gn:asciiname":"Pine Valley",
    "gn:country_code":"CA",
    "gn:dem":836,
    "gn:feature_class":"P",
    "gn:feature_code":"PPL",
    "gn:name":"Pine Valley",
    "gn:population":0,
    "gn:timezone":"America/Vancouver",
    "iso:country":"CA",
    "name:ceb_x_preferred":[
        "Pine Valley"
    ],
    "name:deu_x_preferred":[
        "Pine Valley"
    ],
    "name:ita_x_preferred":[
        "Pine Valley"
    ],
    "name:nld_x_preferred":[
        "Pine Valley"
    ],
    "name:pol_x_preferred":[
        "Pine Valley"
    ],
    "name:por_x_preferred":[
        "Pine Valley"
    ],
    "name:srp_x_preferred":[
        "\u041f\u0430\u0458\u043d \u0412\u0430\u043b\u0438"
    ],
    "name:swe_x_preferred":[
        "Pine Valley"
    ],
    "name:vol_x_preferred":[
        "Pine Valley"
    ],
    "wof:name":"Pine Valley",
    "wof:placetype":"locality"
},
  "geometry": {"coordinates":[-122.08866,52.1773],"type":"Point"}
}