{
  "type": "Feature",
  "properties": {
    "iso:country":"CA",
    "name:eng_x_preferred":[
        "St. Andrews"
    ],
    "name:gla_x_preferred":[
        "Cill R\u00ecmhinn"
    ],
    "name:nld_x_preferred":[
        "St. Andrews"
    ],
    "qs:name":"St. Andrews",
    "qs:name_adm0":"Canada",
    "qs:name_adm1":"Nova Scotia",
    "qs:photos":11,
    "qs:photos_1k":2,
    "qs:photos_9k":1,
    "qs:photos_9r":1,
    "qs:photos_all":11,
    "qs:photos_sr":1,
    "qs:placetype":"Town",
    "qs:pop_sr":"0",
    "wof:name":"St. Andrews",
    "wof:placetype":"locality"
},
  "geometry": {"coordinates":[-61.891136,45.556777],"type":"Point"}
}