{
  "type": "Feature",
  "properties": {
    "gn:admin1_code":"11",
    "gn:asciiname":"Kinloch",
    "gn:country_code":"CA",
    "gn:dem":611,
    "gn:feature_class":"P",
    "gn:feature_code":"PPLL",
    "gn:name":"Kinloch",
    "gn:population":0,
    "gn:timezone":"America/Regina",
    "iso:country":"CA",
    "name:deu_x_preferred":[
        "Kinloch"
    ],
    "name:pol_x_preferred":[
        "Kinloch"
    ],
    "name:rus_x_preferred":[
        "\u041a\u0438\u043d\u043b\u043e\u0445"
    ],
    "wof:name":"Kinloch",
    "wof:placetype":"locality"
},
  "geometry": {"coordinates":[-103.43425999999999,52.39999],"type":"Point"}
}