{
  "type": "Feature",
  "properties": {
    "gn:admin1_code":"8",
    "gn:asciiname":"Topping",
    "gn:country_code":"CA",
    "gn:dem":373,
    "gn:feature_class":"P",
    "gn:feature_code":"PPL",
    "gn:name":"Topping",
    "gn:population":0,
    "gn:timezone":"America/Toronto",
    "iso:country":"CA",
    "wof:name":"Topping",
    "wof:placetype":"locality"
},
  "geometry": {"coordinates":[-80.87860999999999,43.50139],"type":"Point"}
}