{
  "type": "Feature",
  "properties": {
    "gn:admin1_code":"8",
    "gn:asciiname":"Topping",
    "gn:country_code":"CA",
    "gn:dem":373,
    "gn:feature_class":"P",
    "gn:feature_code":"PPL",
    "gn:name":"Topping",
    "gn:population":0,
    "gn:timezone":"America/Toronto",
    "iso:country":"CA",
    "name:deu_x_preferred":[
        "Topping"
    ],
    "name:rus_x_preferred":[
        "\u0422\u043e\u043f\u043f\u0438\u043d\u0433"
    ],
    "name:tur_x_preferred":[
        "Topping"
    ],
    "wof:name":"Topping",
    "wof:placetype":"locality"
},
  "geometry": {"coordinates":[-80.87860999999999,43.50139],"type":"Point"}
}