{
  "type": "Feature",
  "properties": {
    "gn:admin1_code":"8.0",
    "gn:asciiname":"Carlow",
    "gn:country_code":"CA",
    "gn:dem":282,
    "gn:feature_class":"P",
    "gn:feature_code":"PPL",
    "gn:name":"Carlow",
    "gn:population":0,
    "gn:timezone":"America/Toronto",
    "iso:country":"CA",
    "name:bre_x_preferred":[
        "Ceatharlach"
    ],
    "name:bul_x_preferred":[
        "\u041a\u0430\u0440\u043b\u043e\u0443"
    ],
    "name:cat_x_preferred":[
        "Carlow"
    ],
    "name:ceb_x_preferred":[
        "Carlow"
    ],
    "name:ces_x_preferred":[
        "Carlow"
    ],
    "name:cym_x_preferred":[
        "Carlow"
    ],
    "name:dan_x_preferred":[
        "Carlow"
    ],
    "name:deu_x_preferred":[
        "Carlow"
    ],
    "name:est_x_preferred":[
        "Carlow"
    ],
    "name:eus_x_preferred":[
        "Carlow"
    ],
    "name:fas_x_preferred":[
        "\u06a9\u0627\u0631\u0644\u0648"
    ],
    "name:fra_x_preferred":[
        "Carlow"
    ],
    "name:gla_x_preferred":[
        "Ceatharlach"
    ],
    "name:gle_x_preferred":[
        "Ceatharlach"
    ],
    "name:glg_x_preferred":[
        "Carlow"
    ],
    "name:ind_x_preferred":[
        "Carlow"
    ],
    "name:ita_x_preferred":[
        "Carlow"
    ],
    "name:jpn_x_preferred":[
        "\u30ab\u30fc\u30ed\u30a6"
    ],
    "name:kat_x_preferred":[
        "\u10d9\u10d0\u10e0\u10da\u10dd\u10e3"
    ],
    "name:kor_x_preferred":[
        "\uce7c\ub85c"
    ],
    "name:lit_x_preferred":[
        "Karlou"
    ],
    "name:nld_x_preferred":[
        "Carlow"
    ],
    "name:nno_x_preferred":[
        "Carlow"
    ],
    "name:nor_x_preferred":[
        "Carlow"
    ],
    "name:pol_x_preferred":[
        "Carlow"
    ],
    "name:por_x_preferred":[
        "Carlow"
    ],
    "name:rus_x_preferred":[
        "\u041a\u0430\u0440\u043b\u043e\u0443"
    ],
    "name:slk_x_preferred":[
        "Carlow"
    ],
    "name:spa_x_preferred":[
        "Carlow"
    ],
    "name:srp_x_preferred":[
        "\u041a\u0430\u0440\u043b\u043e\u0443"
    ],
    "name:swa_x_preferred":[
        "Carlow"
    ],
    "name:swe_x_preferred":[
        "Carlow"
    ],
    "name:ukr_x_preferred":[
        "\u041a\u0430\u0440\u043b\u043e\u0443"
    ],
    "name:urd_x_preferred":[
        "\u06a9\u0627\u0631\u0644\u0648"
    ],
    "wof:name":"Carlow",
    "wof:placetype":"locality"
},
  "geometry": {"coordinates":[-81.62953,43.77654],"type":"Point"}
}