{
  "type": "Feature",
  "properties": {
    "iso:country":"CA",
    "name:eng_x_preferred":[
        "Jefferson Forest"
    ],
    "qs:gn_adm0_cc":"CA",
    "qs:gn_local":6122091,
    "qs:gn_nam_loc":"penetanguishene",
    "qs:gn_namadm1":"08",
    "qs:local_max":90,
    "qs:local_sum":90,
    "qs:localhoods":1,
    "qs:name":"Jefferson Forest",
    "qs:name_adm0":"Canada",
    "qs:name_adm1":"Ontario",
    "qs:name_adm2":"York",
    "qs:name_local":"Richmond Hill North",
    "qs:photo_max":13,
    "qs:photo_sum":90,
    "qs:placetype":"Suburb",
    "qs:quad_count":22,
    "qs:woe_adm0":23424775,
    "qs:woe_adm1":2344922,
    "qs:woe_adm2":29375112,
    "qs:woe_funk":"Grouping neighborhood",
    "qs:woe_lau":0,
    "qs:woe_local":55999656,
    "qs:woe_ver":"7.10.0",
    "wof:lang":[
        "eng"
    ],
    "wof:name":"Jefferson Forest",
    "wof:placetype":"neighbourhood"
},
  "geometry": {"coordinates":[-79.451559,43.923018],"type":"Point"}
}