{
  "type": "Feature",
  "properties": {
    "gn:admin1_code":"10",
    "gn:admin2_code":"15.0",
    "gn:asciiname":"Poissant",
    "gn:country_code":"CA",
    "gn:dem":261,
    "gn:feature_class":"P",
    "gn:feature_code":"PPL",
    "gn:name":"Poissant",
    "gn:population":0,
    "gn:timezone":"America/Toronto",
    "iso:country":"CA",
    "wof:name":"Poissant",
    "wof:placetype":"locality"
},
  "geometry": {"coordinates":[-75.27,46.76667],"type":"Point"}
}