{
  "type": "Feature",
  "properties": {
    "gn:admin1_code":"2.0",
    "gn:asciiname":"Christian Valley",
    "gn:country_code":"CA",
    "gn:dem":1197,
    "gn:feature_class":"P",
    "gn:feature_code":"PPLL",
    "gn:name":"Christian Valley",
    "gn:population":0,
    "gn:timezone":"America/Vancouver",
    "iso:country":"CA",
    "wof:name":"Christian Valley",
    "wof:placetype":"locality"
},
  "geometry": {"coordinates":[-118.81903,49.54978],"type":"Point"}
}