{
  "type": "Feature",
  "properties": {
    "gn:admin1_code":"4.0",
    "gn:asciiname":"Woodlands",
    "gn:country_code":"CA",
    "gn:dem":233,
    "gn:feature_class":"P",
    "gn:feature_code":"PPL",
    "gn:name":"Woodlands",
    "gn:population":0,
    "gn:timezone":"America/Moncton",
    "iso:country":"CA",
    "name:bar_x_preferred":[
        "Woodlands"
    ],
    "name:ceb_x_preferred":[
        "Woodlands"
    ],
    "name:deu_x_preferred":[
        "Woodlands"
    ],
    "name:ita_x_preferred":[
        "Woodlands"
    ],
    "name:nld_x_preferred":[
        "Woodlands"
    ],
    "name:pol_x_preferred":[
        "Woodlands"
    ],
    "name:rus_x_preferred":[
        "\u0412\u0443\u0434\u043b\u0435\u043d\u0434\u0441"
    ],
    "name:srp_x_preferred":[
        "\u0412\u0443\u0434\u043b\u0430\u043d\u0434\u0441"
    ],
    "name:swe_x_preferred":[
        "Woodlands"
    ],
    "wof:name":"Woodlands",
    "wof:placetype":"locality"
},
  "geometry": {"coordinates":[-66.76609999999999,46.17881],"type":"Point"}
}