{
  "type": "Feature",
  "properties": {
    "gn:admin1_code":"3.0",
    "gn:asciiname":"Bernic Lake",
    "gn:country_code":"CA",
    "gn:dem":320,
    "gn:feature_class":"P",
    "gn:feature_code":"PPLL",
    "gn:name":"Bernic Lake",
    "gn:population":0,
    "gn:timezone":"America/Winnipeg",
    "iso:country":"CA",
    "wof:name":"Bernic Lake",
    "wof:placetype":"locality"
},
  "geometry": {"coordinates":[-95.45302,50.42922],"type":"Point"}
}