{
  "type": "Feature",
  "properties": {
    "gn:admin1_code":"3.0",
    "gn:asciiname":"Bernic Lake",
    "gn:country_code":"CA",
    "gn:dem":320,
    "gn:feature_class":"P",
    "gn:feature_code":"PPLL",
    "gn:name":"Bernic Lake",
    "gn:population":0,
    "gn:timezone":"America/Winnipeg",
    "iso:country":"CA",
    "name:ceb_x_preferred":[
        "Bernic Lake"
    ],
    "name:fra_x_preferred":[
        "Bernic Lake"
    ],
    "name:jpn_x_preferred":[
        "\u30d0\u30fc\u30cb\u30c3\u30af\u6e56"
    ],
    "name:rus_x_preferred":[
        "\u0411\u0435\u0440\u043d\u0438\u043a-\u041b\u0435\u0439\u043a"
    ],
    "name:swe_x_preferred":[
        "Bernic Lake"
    ],
    "name:ukr_x_preferred":[
        "\u0411\u0435\u0440\u043d\u0456\u043a-\u041b\u0435\u0439\u043a"
    ],
    "wof:name":"Bernic Lake",
    "wof:placetype":"locality"
},
  "geometry": {"coordinates":[-95.45302,50.42922],"type":"Point"}
}