{
  "type": "Feature",
  "properties": {
    "gn:admin1_code":"8",
    "gn:asciiname":"Highland Point",
    "gn:country_code":"CA",
    "gn:dem":195,
    "gn:feature_class":"P",
    "gn:feature_code":"PPL",
    "gn:name":"Highland Point",
    "gn:population":0,
    "gn:timezone":"America/Toronto",
    "iso:country":"CA",
    "wof:name":"Highland Point",
    "wof:placetype":"locality"
},
  "geometry": {"coordinates":[-79.94301999999998,44.79265],"type":"Point"}
}