{
  "type": "Feature",
  "properties": {
    "gn:admin1_code":"10",
    "gn:admin2_code":"15.0",
    "gn:admin3_code":"76035.0",
    "gn:asciiname":"Louisa",
    "gn:country_code":"CA",
    "gn:dem":261,
    "gn:feature_class":"P",
    "gn:feature_code":"PPL",
    "gn:name":"Louisa",
    "gn:population":0,
    "gn:timezone":"America/Toronto",
    "iso:country":"CA",
    "name:ara_x_preferred":[
        "\u0644\u0648\u064a\u0632\u0629"
    ],
    "name:ceb_x_preferred":[
        "Louisa"
    ],
    "name:deu_x_preferred":[
        "Louisa"
    ],
    "name:fra_x_preferred":[
        "Louisa"
    ],
    "name:ita_x_preferred":[
        "Louisa"
    ],
    "name:nld_x_preferred":[
        "Louisa"
    ],
    "name:pol_x_preferred":[
        "Louisa"
    ],
    "name:por_x_preferred":[
        "Louisa"
    ],
    "name:srp_x_preferred":[
        "\u041b\u0443\u0438\u0437\u0430"
    ],
    "name:swe_x_preferred":[
        "Luiza"
    ],
    "name:ukr_x_preferred":[
        "\u041b\u0443\u0457\u0437\u0430"
    ],
    "name:vol_x_preferred":[
        "Louisa"
    ],
    "wof:name":"Louisa",
    "wof:placetype":"locality"
},
  "geometry": {"coordinates":[-74.36462,45.76338],"type":"Point"}
}