{
  "type": "Feature",
  "properties": {
    "gn:admin1_code":"10",
    "gn:admin2_code":"15.0",
    "gn:admin3_code":"76035.0",
    "gn:asciiname":"Louisa",
    "gn:country_code":"CA",
    "gn:dem":261,
    "gn:feature_class":"P",
    "gn:feature_code":"PPL",
    "gn:name":"Louisa",
    "gn:population":0,
    "gn:timezone":"America/Toronto",
    "iso:country":"CA",
    "wof:name":"Louisa",
    "wof:placetype":"locality"
},
  "geometry": {"coordinates":[-74.36462,45.76338],"type":"Point"}
}