{
  "type": "Feature",
  "properties": {
    "gn:admin1_code":"7.0",
    "gn:asciiname":"Charleston",
    "gn:country_code":"CA",
    "gn:dem":15,
    "gn:feature_class":"P",
    "gn:feature_code":"PPL",
    "gn:name":"Charleston",
    "gn:population":0,
    "gn:timezone":"America/Halifax",
    "iso:country":"CA",
    "wof:name":"Charleston",
    "wof:placetype":"locality"
},
  "geometry": {"coordinates":[-64.65963000000001,44.17349],"type":"Point"}
}