{
  "type": "Feature",
  "properties": {
    "gn:admin1_code":"7",
    "gn:asciiname":"Smithville",
    "gn:country_code":"CA",
    "gn:dem":176,
    "gn:feature_class":"P",
    "gn:feature_code":"PPLL",
    "gn:name":"Smithville",
    "gn:population":0,
    "gn:timezone":"America/Halifax",
    "iso:country":"CA",
    "name:cat_x_preferred":[
        "Smithville"
    ],
    "name:ceb_x_preferred":[
        "Smithville"
    ],
    "name:deu_x_preferred":[
        "Smithville"
    ],
    "name:fra_x_preferred":[
        "Smithville"
    ],
    "name:ita_x_preferred":[
        "Smithville"
    ],
    "name:nld_x_preferred":[
        "Smithville"
    ],
    "name:pol_x_preferred":[
        "Smithville"
    ],
    "name:por_x_preferred":[
        "Smithville"
    ],
    "name:spa_x_preferred":[
        "Smithville"
    ],
    "name:srp_x_preferred":[
        "\u0421\u043c\u0438\u0442\u0432\u0438\u043b"
    ],
    "name:swe_x_preferred":[
        "Smithville"
    ],
    "name:vol_x_preferred":[
        "Smithville"
    ],
    "wof:name":"Smithville",
    "wof:placetype":"locality"
},
  "geometry": {"coordinates":[-61.33183,46.10014],"type":"Point"}
}