{
  "type": "Feature",
  "properties": {
    "gn:admin1_code":"3",
    "gn:asciiname":"Kirkella",
    "gn:country_code":"CA",
    "gn:dem":518,
    "gn:feature_class":"P",
    "gn:feature_code":"PPL",
    "gn:name":"Kirkella",
    "gn:population":0,
    "gn:timezone":"America/Winnipeg",
    "iso:country":"CA",
    "wof:name":"Kirkella",
    "wof:placetype":"locality"
},
  "geometry": {"coordinates":[-101.36624999999999,50.0239],"type":"Point"}
}