{
  "type": "Feature",
  "properties": {
    "gn:admin1_code":"8.0",
    "gn:asciiname":"Armitage",
    "gn:country_code":"CA",
    "gn:dem":270,
    "gn:feature_class":"P",
    "gn:feature_code":"PPL",
    "gn:name":"Armitage",
    "gn:population":0,
    "gn:timezone":"America/Toronto",
    "iso:country":"CA",
    "name:ceb_x_preferred":[
        "Armitage"
    ],
    "name:pol_x_preferred":[
        "Armitage"
    ],
    "name:spa_x_preferred":[
        "Armitage"
    ],
    "name:swe_x_preferred":[
        "Armitage"
    ],
    "wof:name":"Armitage",
    "wof:placetype":"locality"
},
  "geometry": {"coordinates":[-79.47610999999998,44.03361],"type":"Point"}
}