{
  "type": "Feature",
  "properties": {
    "gn:admin1_code":"8.0",
    "gn:asciiname":"Buck Lake",
    "gn:country_code":"CA",
    "gn:dem":148,
    "gn:feature_class":"P",
    "gn:feature_code":"PPL",
    "gn:name":"Buck Lake",
    "gn:population":0,
    "gn:timezone":"America/Toronto",
    "iso:country":"CA",
    "name:ceb_x_preferred":[
        "Buck Lake"
    ],
    "name:deu_x_preferred":[
        "Buck Lake"
    ],
    "name:swe_x_preferred":[
        "Buck Lake"
    ],
    "wof:name":"Buck Lake",
    "wof:placetype":"locality"
},
  "geometry": {"coordinates":[-76.45471999999999,44.52528],"type":"Point"}
}