{
  "type": "Feature",
  "properties": {
    "gn:admin1_code":"9",
    "gn:asciiname":"St. Chrysostome",
    "gn:country_code":"CA",
    "gn:dem":15,
    "gn:feature_class":"P",
    "gn:feature_code":"PPLL",
    "gn:name":"St. Chrysostome",
    "gn:population":0,
    "gn:timezone":"America/Halifax",
    "iso:country":"CA",
    "wof:name":"St. Chrysostome",
    "wof:placetype":"locality"
},
  "geometry": {"coordinates":[-64.09874000000001,46.51684],"type":"Point"}
}