{
  "type": "Feature",
  "properties": {
    "gn:admin1_code":"8.0",
    "gn:asciiname":"Ardendale",
    "gn:country_code":"CA",
    "gn:dem":203,
    "gn:feature_class":"P",
    "gn:feature_code":"PPL",
    "gn:name":"Ardendale",
    "gn:population":0,
    "gn:timezone":"America/Toronto",
    "iso:country":"CA",
    "wof:name":"Ardendale",
    "wof:placetype":"locality"
},
  "geometry": {"coordinates":[-76.94444,44.72167],"type":"Point"}
}