{
  "type": "Feature",
  "properties": {
    "iso:country":"CA",
    "name:eng_x_preferred":[
        "Domaine des Cheminots"
    ],
    "name:fra_x_preferred":[
        "Domaine des Cheminots"
    ],
    "name:unk_x_variant":[
        "Domaine des Cheminots"
    ],
    "qs:gn_adm0_cc":"CA",
    "qs:gn_local":5937612,
    "qs:gn_nam_loc":"delson",
    "qs:gn_namadm1":"10",
    "qs:local_max":1288,
    "qs:local_sum":1332,
    "qs:localhoods":2,
    "qs:name":"Domaine des Cheminots",
    "qs:name_adm0":"Canada",
    "qs:name_adm1":"Qu\u00e9bec",
    "qs:name_adm2":"Roussillon",
    "qs:name_local":"Delson",
    "qs:photo_max":482,
    "qs:photo_sum":1288,
    "qs:placetype":"Suburb",
    "qs:quad_count":19,
    "qs:woe_adm0":23424775,
    "qs:woe_adm1":2344924,
    "qs:woe_adm2":29375054,
    "qs:woe_lau":0,
    "qs:woe_local":386,
    "qs:woe_ver":"7.10.0",
    "wof:lang":[
        "fre"
    ],
    "wof:name":"Domaine des Cheminots",
    "wof:placetype":"neighbourhood"
},
  "geometry": {"coordinates":[-73.564618,45.374899],"type":"Point"}
}