{
  "type": "Feature",
  "properties": {
    "gn:admin1_code":"9.0",
    "gn:asciiname":"Dundas",
    "gn:country_code":"CA",
    "gn:dem":26,
    "gn:feature_class":"P",
    "gn:feature_code":"PPLL",
    "gn:name":"Dundas",
    "gn:population":0,
    "gn:timezone":"America/Halifax",
    "iso:country":"CA",
    "name:ceb_x_preferred":[
        "Dundas"
    ],
    "name:deu_x_preferred":[
        "Dundas"
    ],
    "name:fra_x_preferred":[
        "Dundas"
    ],
    "name:jpn_x_preferred":[
        "\u30c0\u30f3\u30c0\u30b9"
    ],
    "name:kor_x_preferred":[
        "\ub358\ub2e4\uc2a4"
    ],
    "name:nld_x_preferred":[
        "Dundas"
    ],
    "name:por_x_preferred":[
        "Dundas"
    ],
    "name:rus_x_preferred":[
        "\u0414\u0430\u043d\u0434\u0430\u0441"
    ],
    "name:swe_x_preferred":[
        "Dundas"
    ],
    "name:tur_x_preferred":[
        "Dundas"
    ],
    "wof:name":"Dundas",
    "wof:placetype":"locality"
},
  "geometry": {"coordinates":[-62.51534,46.3168],"type":"Point"}
}