{
  "type": "Feature",
  "properties": {
    "gn:admin1_code":"3",
    "gn:asciiname":"Sans Souci",
    "gn:country_code":"CA",
    "gn:dem":224,
    "gn:feature_class":"P",
    "gn:feature_code":"PPLL",
    "gn:name":"Sans Souci",
    "gn:population":0,
    "gn:timezone":"America/Winnipeg",
    "iso:country":"CA",
    "name:cat_x_preferred":[
        "Sans Souci"
    ],
    "name:ces_x_preferred":[
        "Sanssouci"
    ],
    "name:deu_x_preferred":[
        "Sanssouci"
    ],
    "name:fra_x_preferred":[
        "Sans souci"
    ],
    "name:ita_x_preferred":[
        "Sans Souci"
    ],
    "name:nld_x_preferred":[
        "Sans Souci"
    ],
    "name:pol_x_preferred":[
        "Sans Souci"
    ],
    "name:rus_x_preferred":[
        "\u0421\u0430\u043d-\u0421\u0443\u0441\u0438"
    ],
    "name:spa_x_preferred":[
        "Sans Souci"
    ],
    "name:ukr_x_preferred":[
        "\u0421\u0430\u043d-\u0421\u0443\u0441\u0456"
    ],
    "wof:name":"Sans Souci",
    "wof:placetype":"locality"
},
  "geometry": {"coordinates":[-96.94874,50.42722],"type":"Point"}
}