{
  "type": "Feature",
  "properties": {
    "gn:admin1_code":"8.0",
    "gn:asciiname":"Cloverdale",
    "gn:country_code":"CA",
    "gn:dem":72,
    "gn:feature_class":"P",
    "gn:feature_code":"PPL",
    "gn:name":"Cloverdale",
    "gn:population":0,
    "gn:timezone":"America/Toronto",
    "iso:country":"CA",
    "wof:name":"Cloverdale",
    "wof:placetype":"locality"
},
  "geometry": {"coordinates":[-75.40056,45.11778],"type":"Point"}
}