{
  "type": "Feature",
  "properties": {
    "gn:admin1_code":"10.0",
    "gn:admin2_code":"15.0",
    "gn:admin3_code":"78060.0",
    "gn:asciiname":"Crystal Falls",
    "gn:country_code":"CA",
    "gn:dem":208,
    "gn:feature_class":"P",
    "gn:feature_code":"PPL",
    "gn:name":"Crystal Falls",
    "gn:population":0,
    "gn:timezone":"America/Toronto",
    "iso:country":"CA",
    "wof:name":"Crystal Falls",
    "wof:placetype":"locality"
},
  "geometry": {"coordinates":[-74.6074,46.04421],"type":"Point"}
}