{
  "type": "Feature",
  "properties": {
    "gn:admin1_code":"4.0",
    "gn:asciiname":"Cosman Settlement",
    "gn:country_code":"CA",
    "gn:dem":143,
    "gn:feature_class":"P",
    "gn:feature_code":"PPL",
    "gn:name":"Cosman Settlement",
    "gn:population":0,
    "gn:timezone":"America/Moncton",
    "iso:country":"CA",
    "wof:name":"Cosman Settlement",
    "wof:placetype":"locality"
},
  "geometry": {"coordinates":[-65.45839000000001,45.90323],"type":"Point"}
}