{
  "type": "Feature",
  "properties": {
    "gn:admin1_code":"8",
    "gn:asciiname":"English River",
    "gn:country_code":"CA",
    "gn:dem":467,
    "gn:feature_class":"P",
    "gn:feature_code":"PPL",
    "gn:name":"English River",
    "gn:population":0,
    "gn:timezone":"America/Toronto",
    "iso:country":"CA",
    "name:fas_x_preferred":[
        "\u0631\u0648\u062f\u062e\u0627\u0646\u0647 \u0627\u0646\u06af\u0644\u06cc\u0633"
    ],
    "name:heb_x_preferred":[
        "\u05d0\u05e0\u05d2\u05dc\u05d9\u05e9 \u05e8\u05d9\u05d1\u05e8"
    ],
    "name:hun_x_preferred":[
        "English-foly\u00f3"
    ],
    "wof:name":"English River",
    "wof:placetype":"locality"
},
  "geometry": {"coordinates":[-90.96566,49.22676],"type":"Point"}
}