{
  "type": "Feature",
  "properties": {
    "gn:admin1_code":"9",
    "gn:asciiname":"Milburn",
    "gn:country_code":"CA",
    "gn:dem":32,
    "gn:feature_class":"P",
    "gn:feature_code":"PPLL",
    "gn:name":"Milburn",
    "gn:population":0,
    "gn:timezone":"America/Halifax",
    "iso:country":"CA",
    "name:ceb_x_preferred":[
        "Milburn"
    ],
    "name:deu_x_preferred":[
        "Milburn"
    ],
    "name:fra_x_preferred":[
        "Milburn"
    ],
    "name:ita_x_preferred":[
        "Milburn"
    ],
    "name:nld_x_preferred":[
        "Milburn"
    ],
    "name:pol_x_preferred":[
        "Milburn"
    ],
    "name:por_x_preferred":[
        "Milburn"
    ],
    "name:rus_x_preferred":[
        "\u041c\u0438\u043b\u0431\u0435\u0440\u043d"
    ],
    "name:ukr_x_preferred":[
        "\u041c\u0456\u043b\u0431\u0435\u0440\u043d"
    ],
    "wof:name":"Milburn",
    "wof:placetype":"locality"
},
  "geometry": {"coordinates":[-62.63195,46.36681],"type":"Point"}
}