{
  "type": "Feature",
  "properties": {
    "gn:admin1_code":"10",
    "gn:admin2_code":"15.0",
    "gn:admin3_code":"76043.0",
    "gn:asciiname":"Pine Hill",
    "gn:country_code":"CA",
    "gn:dem":236,
    "gn:feature_class":"P",
    "gn:feature_code":"PPL",
    "gn:name":"Pine Hill",
    "gn:population":0,
    "gn:timezone":"America/Toronto",
    "iso:country":"CA",
    "name:ceb_x_preferred":[
        "Pine Hill"
    ],
    "name:deu_x_preferred":[
        "Pine Hill"
    ],
    "name:ita_x_preferred":[
        "Pine Hill"
    ],
    "name:nds_x_preferred":[
        "Pine Hill"
    ],
    "name:nld_x_preferred":[
        "Pine Hill"
    ],
    "name:pol_x_preferred":[
        "Pine Hill"
    ],
    "name:por_x_preferred":[
        "Pine Hill"
    ],
    "name:srp_x_preferred":[
        "\u041f\u0430\u0458\u043d \u0425\u0438\u043b"
    ],
    "name:swe_x_preferred":[
        "Pine Hill"
    ],
    "name:vol_x_preferred":[
        "Pine Hill"
    ],
    "wof:name":"Pine Hill",
    "wof:placetype":"locality"
},
  "geometry": {"coordinates":[-74.48461999999998,45.73338],"type":"Point"}
}