{
  "type": "Feature",
  "properties": {
    "gn:admin1_code":"8.0",
    "gn:asciiname":"Dealtown",
    "gn:country_code":"CA",
    "gn:dem":199,
    "gn:feature_class":"P",
    "gn:feature_code":"PPL",
    "gn:name":"Dealtown",
    "gn:population":0,
    "gn:timezone":"America/Toronto",
    "iso:country":"CA",
    "wof:name":"Dealtown",
    "wof:placetype":"locality"
},
  "geometry": {"coordinates":[-82.09820000000001,42.24813],"type":"Point"}
}