{
  "type": "Feature",
  "properties": {
    "gn:admin1_code":"8",
    "gn:asciiname":"Glen Eden",
    "gn:country_code":"CA",
    "gn:dem":180,
    "gn:feature_class":"P",
    "gn:feature_code":"PPL",
    "gn:name":"Glen Eden",
    "gn:population":0,
    "gn:timezone":"America/Toronto",
    "iso:country":"CA",
    "name:deu_x_preferred":[
        "Glen Eden"
    ],
    "wof:name":"Glen Eden",
    "wof:placetype":"locality"
},
  "geometry": {"coordinates":[-83.11444,42.05889000000001],"type":"Point"}
}