{
  "type": "Feature",
  "properties": {
    "gn:admin1_code":"11",
    "gn:asciiname":"Springfeld",
    "gn:country_code":"CA",
    "gn:dem":880,
    "gn:feature_class":"P",
    "gn:feature_code":"PPLL",
    "gn:name":"Springfeld",
    "gn:population":0,
    "gn:timezone":"America/Regina",
    "iso:country":"CA",
    "wof:name":"Springfeld",
    "wof:placetype":"locality"
},
  "geometry": {"coordinates":[-107.73463999999998,50.15007],"type":"Point"}
}