{
  "type": "Feature",
  "properties": {
    "gn:admin1_code":"11.0",
    "gn:asciiname":"Clair",
    "gn:country_code":"CA",
    "gn:dem":526,
    "gn:feature_class":"P",
    "gn:feature_code":"PPL",
    "gn:name":"Clair",
    "gn:population":0,
    "gn:timezone":"America/Regina",
    "iso:country":"CA",
    "wof:name":"Clair",
    "wof:placetype":"locality"
},
  "geometry": {"coordinates":[-104.08434,52.01671],"type":"Point"}
}