{
  "type": "Feature",
  "properties": {
    "gn:admin1_code":"3",
    "gn:asciiname":"Osborne",
    "gn:country_code":"CA",
    "gn:dem":235,
    "gn:feature_class":"P",
    "gn:feature_code":"PPL",
    "gn:name":"Osborne",
    "gn:population":0,
    "gn:timezone":"America/Winnipeg",
    "iso:country":"CA",
    "wof:name":"Osborne",
    "wof:placetype":"locality"
},
  "geometry": {"coordinates":[-97.36957,49.5419],"type":"Point"}
}