{
  "type": "Feature",
  "properties": {
    "gn:admin1_code":"10",
    "gn:admin2_code":"8.0",
    "gn:admin3_code":"88035.0",
    "gn:asciiname":"Fisher",
    "gn:country_code":"CA",
    "gn:dem":344,
    "gn:feature_class":"P",
    "gn:feature_code":"PPL",
    "gn:name":"Fisher",
    "gn:population":0,
    "gn:timezone":"America/Toronto",
    "iso:country":"CA",
    "name:bul_x_preferred":[
        "\u0424\u0438\u0448\u0435\u0440"
    ],
    "name:cat_x_preferred":[
        "Fisher"
    ],
    "name:ceb_x_preferred":[
        "Fisher"
    ],
    "name:ces_x_preferred":[
        "Fisher"
    ],
    "name:deu_x_preferred":[
        "Fisher"
    ],
    "name:fas_x_preferred":[
        "\u0641\u06cc\u0634\u0631"
    ],
    "name:fin_x_preferred":[
        "Fisher"
    ],
    "name:fra_x_preferred":[
        "Fisher"
    ],
    "name:ita_x_preferred":[
        "Fisher"
    ],
    "name:nld_x_preferred":[
        "Fisher"
    ],
    "name:nor_x_preferred":[
        "Fisher"
    ],
    "name:pol_x_preferred":[
        "Fisher"
    ],
    "name:por_x_preferred":[
        "Fisher"
    ],
    "name:rus_x_preferred":[
        "\u0424\u0438\u0448\u0435\u0440"
    ],
    "name:slk_x_preferred":[
        "Fisher"
    ],
    "name:spa_x_preferred":[
        "Fisher"
    ],
    "name:srp_x_preferred":[
        "\u0424\u0438\u0448\u0435\u0440"
    ],
    "name:swe_x_preferred":[
        "Fisher"
    ],
    "name:tat_x_preferred":[
        "\u0424\u0438\u0448\u0435\u0440"
    ],
    "name:vol_x_preferred":[
        "Fisher"
    ],
    "wof:name":"Fisher",
    "wof:placetype":"locality"
},
  "geometry": {"coordinates":[-77.79951,48.48349],"type":"Point"}
}