{
  "type": "Feature",
  "properties": {
    "gn:admin1_code":"10",
    "gn:admin2_code":"8.0",
    "gn:admin3_code":"88035.0",
    "gn:asciiname":"Fisher",
    "gn:country_code":"CA",
    "gn:dem":344,
    "gn:feature_class":"P",
    "gn:feature_code":"PPL",
    "gn:name":"Fisher",
    "gn:population":0,
    "gn:timezone":"America/Toronto",
    "iso:country":"CA",
    "wof:name":"Fisher",
    "wof:placetype":"locality"
},
  "geometry": {"coordinates":[-77.79951,48.48349],"type":"Point"}
}