{
  "type": "Feature",
  "properties": {
    "gn:admin1_code":"1.0",
    "gn:asciiname":"Acheson",
    "gn:country_code":"CA",
    "gn:dem":710,
    "gn:feature_class":"P",
    "gn:feature_code":"PPLL",
    "gn:name":"Acheson",
    "gn:population":0,
    "gn:timezone":"America/Edmonton",
    "iso:country":"CA",
    "name:fas_x_preferred":[
        "\u0627\u06a9\u0633\u0648\u0646"
    ],
    "wof:name":"Acheson",
    "wof:placetype":"locality"
},
  "geometry": {"coordinates":[-113.76873999999999,53.55014],"type":"Point"}
}