{
  "type": "Feature",
  "properties": {
    "iso:country":"CA",
    "name:eng_x_preferred":[
        "Zone Industrielle Beauharnois-Melochville"
    ],
    "name:fra_x_preferred":[
        "Zone Industrielle Beauharnois-Melochville"
    ],
    "qs:gn_local":0,
    "qs:local_max":56,
    "qs:local_sum":56,
    "qs:localhoods":1,
    "qs:name":"Zone Industrielle Beauharnois-Melochville",
    "qs:name_adm0":"Canada",
    "qs:name_adm1":"Qu\u00e9bec",
    "qs:name_adm2":"Beauharnois-Salaberry",
    "qs:name_local":"Parc r\u00e9gional du canal de Beauharnois",
    "qs:photo_max":29,
    "qs:photo_sum":56,
    "qs:placetype":"Suburb",
    "qs:quad_count":5,
    "qs:woe_adm0":23424775,
    "qs:woe_adm1":2344924,
    "qs:woe_adm2":29375171,
    "qs:woe_funk":"Parented by a neighborhood",
    "qs:woe_lau":0,
    "qs:woe_local":55999746,
    "qs:woe_ver":"7.10.0",
    "wof:lang":[
        "fre"
    ],
    "wof:name":"Zone Industrielle Beauharnois-Melochville",
    "wof:placetype":"neighbourhood"
},
  "geometry": {"coordinates":[-73.900884,45.314944],"type":"Point"}
}