{
  "type": "Feature",
  "properties": {
    "gn:admin1_code":"5.0",
    "gn:asciiname":"Doctors Harbour",
    "gn:country_code":"CA",
    "gn:dem":7,
    "gn:feature_class":"P",
    "gn:feature_code":"PPLL",
    "gn:name":"Doctors Harbour",
    "gn:population":0,
    "gn:timezone":"America/St_Johns",
    "iso:country":"CA",
    "wof:name":"Doctors Harbour",
    "wof:placetype":"locality"
},
  "geometry": {"coordinates":[-57.76517,47.63329],"type":"Point"}
}