{
  "type": "Feature",
  "properties": {
    "gn:country":"CA",
    "gn:fcode":"PPL",
    "gn:pop":0,
    "iso:country":"CA",
    "name:dut_x_preferred":[
        "North Rustico"
    ],
    "name:eng_x_preferred":[
        "South Rustico"
    ],
    "name:fre_x_preferred":[
        "North Rustico"
    ],
    "name:swe_x_preferred":[
        "North Rustico"
    ],
    "qs:name":"South Rustico",
    "qs:name_adm0":"Canada",
    "qs:name_adm1":"Prince Edward Island",
    "qs:photos_9r":0,
    "qs:photos_sr":0,
    "qs:placetype":"Town",
    "qs:pop_sr":"0",
    "wof:name":"South Rustico",
    "wof:placetype":"locality",
    "wof:population":0
},
  "geometry": {"coordinates":[-63.3154,46.45012],"type":"Point"}
}