{
  "type": "Feature",
  "properties": {
    "gn:country":"CA",
    "gn:fcode":"PPL",
    "gn:pop":0,
    "iso:country":"CA",
    "name:ceb_x_preferred":[
        "North Rustico"
    ],
    "name:eng_x_preferred":[
        "South Rustico"
    ],
    "name:eng_x_variant":[
        "North Rustico"
    ],
    "name:fas_x_preferred":[
        "\u0646\u0648\u0631\u062a \u0631\u0627\u0633\u062a\u06cc\u06a9\u0648"
    ],
    "name:fra_x_preferred":[
        "North Rustico"
    ],
    "name:lit_x_preferred":[
        "Nord Rastikas"
    ],
    "name:nld_x_preferred":[
        "North Rustico"
    ],
    "name:por_x_preferred":[
        "North Rustico"
    ],
    "name:rus_x_preferred":[
        "\u041d\u043e\u0440\u0442-\u0420\u0430\u0441\u0442\u0438\u043a\u043e"
    ],
    "name:swe_x_preferred":[
        "North Rustico"
    ],
    "qs:name":"South Rustico",
    "qs:name_adm0":"Canada",
    "qs:name_adm1":"Prince Edward Island",
    "qs:photos_9r":0,
    "qs:photos_sr":0,
    "qs:placetype":"Town",
    "qs:pop_sr":"0",
    "wof:name":"South Rustico",
    "wof:placetype":"locality",
    "wof:population":0
},
  "geometry": {"coordinates":[-63.3154,46.45012],"type":"Point"}
}