{
  "type": "Feature",
  "properties": {
    "iso:country":"CA",
    "name:eng_x_preferred":[
        "Whites Lake"
    ],
    "qs:name":"Whites Lake",
    "qs:name_adm0":"Canada",
    "qs:name_adm1":"Nova Scotia",
    "qs:photos":13,
    "qs:photos_1k":3,
    "qs:photos_9k":1,
    "qs:photos_9r":1,
    "qs:photos_all":13,
    "qs:photos_sr":1,
    "qs:placetype":"Town",
    "qs:pop_sr":"0",
    "wd:wordcount":202,
    "wof:name":"Whites Lake",
    "wof:placetype":"locality"
},
  "geometry": {"coordinates":[-63.759412,44.528913],"type":"Point"}
}