{
  "type": "Feature",
  "properties": {
    "gn:admin1_code":"2",
    "gn:admin2_code":"5943.0",
    "gn:asciiname":"Minstrel Island",
    "gn:country_code":"CA",
    "gn:dem":26,
    "gn:feature_class":"P",
    "gn:feature_code":"PPL",
    "gn:name":"Minstrel Island",
    "gn:population":0,
    "gn:timezone":"America/Vancouver",
    "iso:country":"CA",
    "wof:name":"Minstrel Island",
    "wof:placetype":"locality"
},
  "geometry": {"coordinates":[-126.30677,50.61345],"type":"Point"}
}