{
  "type": "Feature",
  "properties": {
    "gn:admin1_code":"11.0",
    "gn:asciiname":"Cymric",
    "gn:country_code":"CA",
    "gn:dem":526,
    "gn:feature_class":"P",
    "gn:feature_code":"PPLL",
    "gn:name":"Cymric",
    "gn:population":0,
    "gn:timezone":"America/Regina",
    "iso:country":"CA",
    "name:fas_x_preferred":[
        "\u0633\u06cc\u0645\u0631\u06a9"
    ],
    "wof:name":"Cymric",
    "wof:placetype":"locality"
},
  "geometry": {"coordinates":[-104.98445,51.23338],"type":"Point"}
}