{
  "type": "Feature",
  "properties": {
    "gn:admin1_code":"2",
    "gn:asciiname":"Kootenay Bay",
    "gn:country_code":"CA",
    "gn:dem":588,
    "gn:feature_class":"P",
    "gn:feature_code":"PPL",
    "gn:name":"Kootenay Bay",
    "gn:population":0,
    "gn:timezone":"America/Dawson_Creek",
    "iso:country":"CA",
    "wof:name":"Kootenay Bay",
    "wof:placetype":"locality"
},
  "geometry": {"coordinates":[-116.86888,49.68322],"type":"Point"}
}