{
  "type": "Feature",
  "properties": {
    "gn:admin1_code":"2",
    "gn:asciiname":"Kootenay Bay",
    "gn:country_code":"CA",
    "gn:dem":588,
    "gn:feature_class":"P",
    "gn:feature_code":"PPL",
    "gn:name":"Kootenay Bay",
    "gn:population":0,
    "gn:timezone":"America/Dawson_Creek",
    "iso:country":"CA",
    "name:ara_x_preferred":[
        "\u062e\u0644\u064a\u062c \u0643\u0648\u062a\u064a\u0646\u0627\u064a"
    ],
    "wof:name":"Kootenay Bay",
    "wof:placetype":"locality"
},
  "geometry": {"coordinates":[-116.86888,49.68322],"type":"Point"}
}