{
  "type": "Feature",
  "properties": {
    "gn:admin1_code":"2",
    "gn:admin2_code":"5931.0",
    "gn:asciiname":"Hospital Hill",
    "gn:country_code":"CA",
    "gn:dem":24,
    "gn:feature_class":"P",
    "gn:feature_code":"PPL",
    "gn:name":"Hospital Hill",
    "gn:population":0,
    "gn:timezone":"America/Vancouver",
    "iso:country":"CA",
    "wof:name":"Hospital Hill",
    "wof:placetype":"locality"
},
  "geometry": {"coordinates":[-123.13605,49.69734],"type":"Point"}
}