{
  "type": "Feature",
  "properties": {
    "gn:admin1_code":"5",
    "gn:asciiname":"Little Bay Islands",
    "gn:country_code":"CA",
    "gn:dem":38,
    "gn:feature_class":"P",
    "gn:feature_code":"PPL",
    "gn:name":"Little Bay Islands",
    "gn:population":0,
    "gn:timezone":"America/St_Johns",
    "iso:country":"CA",
    "wof:name":"Little Bay Islands",
    "wof:placetype":"locality"
},
  "geometry": {"coordinates":[-55.78147,49.64995],"type":"Point"}
}