{
  "type": "Feature",
  "properties": {
    "gn:admin1_code":"7",
    "gn:asciiname":"New Canaan",
    "gn:country_code":"CA",
    "gn:dem":112,
    "gn:feature_class":"P",
    "gn:feature_code":"PPLL",
    "gn:name":"New Canaan",
    "gn:population":0,
    "gn:timezone":"America/Halifax",
    "iso:country":"CA",
    "wof:name":"New Canaan",
    "wof:placetype":"locality"
},
  "geometry": {"coordinates":[-64.26545,45.51685],"type":"Point"}
}