{
  "type": "Feature",
  "properties": {
    "gn:admin1_code":"8",
    "gn:asciiname":"Middleport",
    "gn:country_code":"CA",
    "gn:dem":198,
    "gn:feature_class":"P",
    "gn:feature_code":"PPL",
    "gn:name":"Middleport",
    "gn:population":0,
    "gn:timezone":"America/Toronto",
    "iso:country":"CA",
    "name:cat_x_preferred":[
        "Middleport"
    ],
    "name:ceb_x_preferred":[
        "Middleport"
    ],
    "name:deu_x_preferred":[
        "Middleport"
    ],
    "name:fra_x_preferred":[
        "Middleport"
    ],
    "name:ita_x_preferred":[
        "Middleport"
    ],
    "name:nld_x_preferred":[
        "Middleport"
    ],
    "name:pol_x_preferred":[
        "Middleport"
    ],
    "name:sco_x_preferred":[
        "Middleport"
    ],
    "name:spa_x_preferred":[
        "Middleport"
    ],
    "name:srp_x_preferred":[
        "\u041c\u0438\u0434\u043b\u043f\u043e\u0440\u0442"
    ],
    "name:vol_x_preferred":[
        "Middleport"
    ],
    "wof:name":"Middleport",
    "wof:placetype":"locality"
},
  "geometry": {"coordinates":[-80.07375999999999,43.10078],"type":"Point"}
}