{
  "type": "Feature",
  "properties": {
    "gn:admin1_code":"3.0",
    "gn:asciiname":"Bedford",
    "gn:country_code":"CA",
    "gn:dem":335,
    "gn:feature_class":"P",
    "gn:feature_code":"PPL",
    "gn:name":"Bedford",
    "gn:population":0,
    "gn:timezone":"America/Winnipeg",
    "iso:country":"CA",
    "wof:name":"Bedford",
    "wof:placetype":"locality"
},
  "geometry": {"coordinates":[-96.32228000000001,49.37248],"type":"Point"}
}