{
  "type": "Feature",
  "properties": {
    "gn:admin1_code":"10",
    "gn:admin2_code":"9.0",
    "gn:asciiname":"Vieux-Poste",
    "gn:country_code":"CA",
    "gn:dem":3,
    "gn:feature_class":"P",
    "gn:feature_code":"PPL",
    "gn:name":"Vieux-Poste",
    "gn:population":0,
    "gn:timezone":"America/Blanc-Sablon",
    "iso:country":"CA",
    "wof:name":"Vieux-Poste",
    "wof:placetype":"locality"
},
  "geometry": {"coordinates":[-58.95412,50.83089],"type":"Point"}
}