{
  "type": "Feature",
  "properties": {
    "gn:admin1_code":"3",
    "gn:asciiname":"Ste. Rose du Lac",
    "gn:country_code":"CA",
    "gn:dem":267,
    "gn:feature_class":"P",
    "gn:feature_code":"PPL",
    "gn:name":"Ste. Rose du Lac",
    "gn:population":0,
    "gn:timezone":"America/Winnipeg",
    "iso:country":"CA",
    "wof:name":"Ste. Rose du Lac",
    "wof:placetype":"locality"
},
  "geometry": {"coordinates":[-99.5241,51.05941],"type":"Point"}
}