{
  "type": "Feature",
  "properties": {
    "iso:country":"CA",
    "name:ara_x_preferred":[
        "\u0645\u064a \u0641\u064a\u0631"
    ],
    "name:bel_x_preferred":[
        "\u041c\u0435\u0439\u0444\u044d\u0440"
    ],
    "name:bul_x_preferred":[
        "\u041c\u0435\u0439\u0444\u0435\u044a\u0440"
    ],
    "name:cat_x_preferred":[
        "Mayfair"
    ],
    "name:ces_x_preferred":[
        "Mayfair"
    ],
    "name:cym_x_preferred":[
        "Mayfair"
    ],
    "name:dan_x_preferred":[
        "Mayfair"
    ],
    "name:deu_x_preferred":[
        "Mayfair"
    ],
    "name:ell_x_preferred":[
        "\u039c\u03ad\u03b9\u03c6\u03b5\u03c1"
    ],
    "name:eng_x_preferred":[
        "Mayfair"
    ],
    "name:epo_x_preferred":[
        "Mayfair"
    ],
    "name:fas_x_preferred":[
        "\u0645\u06cc\u200c\u0641\u0631"
    ],
    "name:fra_x_preferred":[
        "Mayfair"
    ],
    "name:gle_x_preferred":[
        "Mayfair"
    ],
    "name:heb_x_preferred":[
        "\u05de\u05d9\u05d9\u05e4\u05d9\u05d9\u05e8"
    ],
    "name:hin_x_preferred":[
        "\u092e\u0947\u092b\u093c\u0947\u092f\u0930"
    ],
    "name:ind_x_preferred":[
        "Mayfair"
    ],
    "name:isl_x_preferred":[
        "Mayfair"
    ],
    "name:ita_x_preferred":[
        "Mayfair"
    ],
    "name:jpn_x_preferred":[
        "\u30e1\u30a4\u30d5\u30a7\u30a2"
    ],
    "name:kab_x_preferred":[
        "Mayfair"
    ],
    "name:kor_x_preferred":[
        "\uba54\uc774\ud398\uc5b4"
    ],
    "name:lat_x_preferred":[
        "Mayfair"
    ],
    "name:msa_x_preferred":[
        "Mayfair"
    ],
    "name:nld_x_preferred":[
        "Mayfair"
    ],
    "name:nno_x_preferred":[
        "Mayfair"
    ],
    "name:nor_x_preferred":[
        "Mayfair"
    ],
    "name:pol_x_preferred":[
        "Mayfair"
    ],
    "name:por_x_preferred":[
        "Mayfair"
    ],
    "name:rus_x_preferred":[
        "\u041c\u0435\u0439\u0444\u044d\u0440"
    ],
    "name:spa_x_preferred":[
        "Mayfair"
    ],
    "name:swe_x_preferred":[
        "Mayfair"
    ],
    "name:ukr_x_preferred":[
        "\u041c\u0435\u0439\u0444\u0435\u0440"
    ],
    "name:unk_x_variant":[
        "Mayfair"
    ],
    "name:urd_x_preferred":[
        "\u0645\u06d2 \u0641\u06cc\u0626\u0631"
    ],
    "name:zho_x_preferred":[
        "\u6885\u8d39\u5c14"
    ],
    "qs:gn_adm0_cc":"CA",
    "qs:gn_local":5907990,
    "qs:gn_nam_loc":"brantford",
    "qs:gn_namadm1":"08",
    "qs:local_max":1489,
    "qs:local_sum":3298,
    "qs:localhoods":11,
    "qs:name":"Mayfair",
    "qs:name_adm0":"Canada",
    "qs:name_adm1":"Ontario",
    "qs:name_adm2":"Brant",
    "qs:name_local":"Brantford",
    "qs:photo_max":17,
    "qs:photo_sum":45,
    "qs:placetype":"Suburb",
    "qs:quad_count":14,
    "qs:woe_adm0":23424775,
    "qs:woe_adm1":2344922,
    "qs:woe_adm2":29375169,
    "qs:woe_lau":0,
    "qs:woe_local":4059,
    "qs:woe_ver":"7.10.0",
    "wof:lang":[
        "eng"
    ],
    "wof:name":"Mayfair",
    "wof:placetype":"neighbourhood"
},
  "geometry": {"coordinates":[-80.282414,43.171611],"type":"Point"}
}