{
  "type": "Feature",
  "properties": {
    "gn:gn_country":"CA",
    "gn:gn_fcode":"PPL",
    "gn:gn_pop":0,
    "iso:country":"CA",
    "name:eng_x_preferred":[
        "Lafl\u00e8che"
    ],
    "name:fra_x_preferred":[
        "quartier Lafl\u00e8che"
    ],
    "name:nld_x_preferred":[
        "Lafl\u00e8che"
    ],
    "qs_pg:aaroncc":"CA",
    "qs_pg:gn_country":"CA",
    "qs_pg:gn_fcode":"PPL",
    "qs_pg:gn_pop":0,
    "qs_pg:name":"Lafl\u00e8che",
    "qs_pg:name_adm0":"Canada",
    "qs_pg:name_adm1":"Qu\u00e9bec",
    "qs_pg:photos":8,
    "qs_pg:photos_1k":2,
    "qs_pg:photos_9k":1,
    "qs_pg:photos_9r":1,
    "qs_pg:photos_all":8,
    "qs_pg:photos_sr":1,
    "qs_pg:pop_sr":0,
    "qs_pg:qs_pg_placetype":"locality",
    "qs_pg:qs_pg_placetype_gp":"Town",
    "qs_pg:woe_adm0":23424775,
    "woe:adm0_id":23424775,
    "woe:name_adm0":"Canada",
    "woe:name_adm1":"Qu\u00e9bec",
    "woe:placetype":"Town",
    "wof:name":"Lafl\u00e8che",
    "wof:placetype":"locality"
},
  "geometry": {"coordinates":[-73.46587,45.50008],"type":"Point"}
}