{
  "type": "Feature",
  "properties": {
    "gn:admin1_code":"11.0",
    "gn:asciiname":"Bellegarde",
    "gn:country_code":"CA",
    "gn:dem":543,
    "gn:feature_class":"P",
    "gn:feature_code":"PPLL",
    "gn:name":"Bellegarde",
    "gn:population":0,
    "gn:timezone":"America/Regina",
    "iso:country":"CA",
    "name:fra_x_preferred":[
        "Bellegarde"
    ],
    "wof:name":"Bellegarde",
    "wof:placetype":"locality"
},
  "geometry": {"coordinates":[-101.55092999999999,49.53332],"type":"Point"}
}