{
  "type": "Feature",
  "properties": {
    "gn:admin1_code":"8.0",
    "gn:asciiname":"Booth Landing",
    "gn:country_code":"CA",
    "gn:dem":269,
    "gn:feature_class":"P",
    "gn:feature_code":"PPL",
    "gn:name":"Booth Landing",
    "gn:population":0,
    "gn:timezone":"America/Toronto",
    "iso:country":"CA",
    "wof:name":"Booth Landing",
    "wof:placetype":"locality"
},
  "geometry": {"coordinates":[-79.20478,46.14378],"type":"Point"}
}