{
  "type": "Feature",
  "properties": {
    "gn:admin1_code":"8.0",
    "gn:asciiname":"Blandford Station",
    "gn:country_code":"CA",
    "gn:dem":296,
    "gn:feature_class":"P",
    "gn:feature_code":"PPLL",
    "gn:name":"Blandford Station",
    "gn:population":0,
    "gn:timezone":"America/Toronto",
    "iso:country":"CA",
    "wof:name":"Blandford Station",
    "wof:placetype":"locality"
},
  "geometry": {"coordinates":[-80.63779,43.21789],"type":"Point"}
}