{
  "type": "Feature",
  "properties": {
    "iso:country":"CA",
    "name:eng_x_preferred":[
        "Micmac"
    ],
    "qs:name":"Micmac",
    "qs:name_adm0":"Canada",
    "qs:name_adm1":"Nova Scotia",
    "qs:photos":125,
    "qs:photos_1k":25,
    "qs:photos_9k":1,
    "qs:photos_9r":3,
    "qs:photos_all":125,
    "qs:photos_sr":3,
    "qs:placetype":"Town",
    "qs:pop_sr":"0",
    "wd:wordcount":144,
    "wof:name":"Micmac",
    "wof:placetype":"locality"
},
  "geometry": {"coordinates":[-63.474712,45.107696],"type":"Point"}
}