{
  "type": "Feature",
  "properties": {
    "gn:admin1_code":"4.0",
    "gn:asciiname":"Bagdad",
    "gn:country_code":"CA",
    "gn:dem":57,
    "gn:feature_class":"P",
    "gn:feature_code":"PPL",
    "gn:name":"Bagdad",
    "gn:population":0,
    "gn:timezone":"America/Moncton",
    "iso:country":"CA",
    "name:cat_x_preferred":[
        "Bagdad"
    ],
    "name:ceb_x_preferred":[
        "Bagdad"
    ],
    "name:deu_x_preferred":[
        "Bagdad"
    ],
    "name:fra_x_preferred":[
        "Bagdad"
    ],
    "name:hun_x_preferred":[
        "Bagdad"
    ],
    "name:nep_x_preferred":[
        "\u092c\u0917\u0926\u093e\u0926"
    ],
    "name:nld_x_preferred":[
        "Bagdad"
    ],
    "name:pol_x_preferred":[
        "Bagdad"
    ],
    "name:ron_x_preferred":[
        "Bagdad"
    ],
    "name:slv_x_preferred":[
        "Bagdad"
    ],
    "name:spa_x_preferred":[
        "Bagdad"
    ],
    "name:srp_x_preferred":[
        "\u0411\u0430\u0433\u0434\u0430\u0434"
    ],
    "name:swe_x_preferred":[
        "Bagdad"
    ],
    "name:vol_x_preferred":[
        "Bagdad"
    ],
    "wof:name":"Bagdad",
    "wof:placetype":"locality"
},
  "geometry": {"coordinates":[-65.86006999999999,45.9233],"type":"Point"}
}