{
  "type": "Feature",
  "properties": {
    "gn:admin1_code":"8.0",
    "gn:asciiname":"Crescent Beach",
    "gn:country_code":"CA",
    "gn:dem":184,
    "gn:feature_class":"P",
    "gn:feature_code":"PPL",
    "gn:name":"Crescent Beach",
    "gn:population":0,
    "gn:timezone":"America/Toronto",
    "iso:country":"CA",
    "name:ceb_x_preferred":[
        "Crescent Beach"
    ],
    "name:deu_x_preferred":[
        "Crescent Beach"
    ],
    "name:swe_x_preferred":[
        "Crescent Beach"
    ],
    "wof:name":"Crescent Beach",
    "wof:placetype":"locality"
},
  "geometry": {"coordinates":[-78.96876,42.88397],"type":"Point"}
}