{
  "type": "Feature",
  "properties": {
    "gn:admin1_code":"8",
    "gn:asciiname":"Lawrence Station",
    "gn:country_code":"CA",
    "gn:dem":227,
    "gn:feature_class":"P",
    "gn:feature_code":"PPL",
    "gn:name":"Lawrence Station",
    "gn:population":0,
    "gn:timezone":"America/Toronto",
    "iso:country":"CA",
    "wof:name":"Lawrence Station",
    "wof:placetype":"locality"
},
  "geometry": {"coordinates":[-81.41484,42.75646],"type":"Point"}
}