{
  "type": "Feature",
  "properties": {
    "gn:admin1_code":"10",
    "gn:admin2_code":"8.0",
    "gn:asciiname":"Latulipe",
    "gn:country_code":"CA",
    "gn:dem":271,
    "gn:feature_class":"P",
    "gn:feature_code":"PPL",
    "gn:name":"Latulipe",
    "gn:population":0,
    "gn:timezone":"America/Toronto",
    "iso:country":"CA",
    "wof:name":"Latulipe",
    "wof:placetype":"locality"
},
  "geometry": {"coordinates":[-79.03315000000001,47.42702],"type":"Point"}
}