{
  "type": "Feature",
  "properties": {
    "gn:admin1_code":"3.0",
    "gn:asciiname":"Birdtail",
    "gn:country_code":"CA",
    "gn:dem":516,
    "gn:feature_class":"P",
    "gn:feature_code":"PPLL",
    "gn:name":"Birdtail",
    "gn:population":0,
    "gn:timezone":"America/Winnipeg",
    "iso:country":"CA",
    "wof:name":"Birdtail",
    "wof:placetype":"locality"
},
  "geometry": {"coordinates":[-100.88728,50.7269],"type":"Point"}
}