{
  "type": "Feature",
  "properties": {
    "iso:country":"CA",
    "name:eng_x_preferred":[
        "Northeast"
    ],
    "name:unk_x_variant":[
        "Northeast"
    ],
    "qs:gn_adm0_cc":"CA",
    "qs:gn_local":6075357,
    "qs:gn_nam_loc":"mississauga",
    "qs:gn_namadm1":"08",
    "qs:local_max":5508,
    "qs:local_sum":26805,
    "qs:localhoods":22,
    "qs:name":"Northeast",
    "qs:name_adm0":"Canada",
    "qs:name_adm1":"Ontario",
    "qs:name_adm2":"Peel",
    "qs:name_local":"Mississauga",
    "qs:photo_max":191,
    "qs:photo_sum":1299,
    "qs:placetype":"Suburb",
    "qs:quad_count":99,
    "qs:woe_adm0":23424775,
    "qs:woe_adm1":2344922,
    "qs:woe_adm2":29375178,
    "qs:woe_funk":"Grouping neighborhood",
    "qs:woe_lau":0,
    "qs:woe_local":22664159,
    "qs:woe_ver":"7.10.0",
    "wof:lang":[
        "eng"
    ],
    "wof:name":"Northeast",
    "wof:placetype":"neighbourhood"
},
  "geometry": {"coordinates":[-79.65703600000001,43.67602],"type":"Point"}
}