{
  "type": "Feature",
  "properties": {
    "gn:admin1_code":"8.0",
    "gn:asciiname":"Cornell",
    "gn:country_code":"CA",
    "gn:dem":252,
    "gn:feature_class":"P",
    "gn:feature_code":"PPL",
    "gn:name":"Cornell",
    "gn:population":0,
    "gn:timezone":"America/Toronto",
    "iso:country":"CA",
    "wof:name":"Cornell",
    "wof:placetype":"locality"
},
  "geometry": {"coordinates":[-80.62651,42.90426],"type":"Point"}
}