{
  "type": "Feature",
  "properties": {
    "gn:admin1_code":"3",
    "gn:asciiname":"Pansy",
    "gn:country_code":"CA",
    "gn:dem":287,
    "gn:feature_class":"P",
    "gn:feature_code":"PPLL",
    "gn:name":"Pansy",
    "gn:population":0,
    "gn:timezone":"America/Winnipeg",
    "iso:country":"CA",
    "name:ara_x_preferred":[
        "\u0628\u0627\u0646\u0633\u064a"
    ],
    "name:bel_x_preferred":[
        "\u0424\u0456\u044f\u043b\u043a\u0430 \u0412\u0456\u0442\u0440\u0430\u043a\u0430"
    ],
    "name:ben_x_preferred":[
        "\u09aa\u09c7\u09a8\u099c\u09bf"
    ],
    "name:ceb_x_preferred":[
        "Viola wittrockiana"
    ],
    "name:ces_x_preferred":[
        "Violka zahradn\u00ed"
    ],
    "name:csb_x_preferred":[
        "Maceszka"
    ],
    "name:cym_x_preferred":[
        "Caru'n ofer"
    ],
    "name:deu_x_preferred":[
        "Garten-Stiefm\u00fctterchen"
    ],
    "name:ell_x_preferred":[
        "\u03a0\u03b1\u03bd\u03c3\u03ad\u03c2"
    ],
    "name:est_x_preferred":[
        "V\u00f5\u00f5rasema"
    ],
    "name:fas_x_preferred":[
        "\u0628\u0646\u0641\u0634\u0647 \u062f\u0648\u0631\u06af\u0647"
    ],
    "name:fin_x_preferred":[
        "Tarhaorvokki"
    ],
    "name:fra_x_preferred":[
        "Viola \u00d7wittrockiana"
    ],
    "name:gle_x_preferred":[
        "Goirm\u00edn"
    ],
    "name:glg_x_preferred":[
        "Pensamento"
    ],
    "name:heb_x_preferred":[
        "\u05d0\u05de\u05e0\u05d5\u05df \u05d5\u05ea\u05de\u05e8"
    ],
    "name:hun_x_preferred":[
        "Kerti \u00e1rv\u00e1cska"
    ],
    "name:ido_x_preferred":[
        "Panseo"
    ],
    "name:ita_x_preferred":[
        "Viola wittrockiana"
    ],
    "name:jpn_x_preferred":[
        "\u30d1\u30f3\u30b8\u30fc"
    ],
    "name:kat_x_preferred":[
        "Viola tricolor"
    ],
    "name:lit_x_preferred":[
        "Dar\u017eelin\u0117 na\u0161lait\u0117"
    ],
    "name:ltz_x_preferred":[
        "Pens\u00e9e"
    ],
    "name:mal_x_preferred":[
        "\u0d2a\u0d3e\u0d7b\u0d38\u0d3f"
    ],
    "name:nds_x_preferred":[
        "Grootmudderbloom"
    ],
    "name:pan_x_preferred":[
        "\u0a2a\u0a48\u0a02\u0a1c\u0a3c\u0a40"
    ],
    "name:pnb_x_preferred":[
        "\u067e\u06cc\u0646\u0632\u06cc"
    ],
    "name:pol_x_preferred":[
        "Fio\u0142ek ogrodowy"
    ],
    "name:rus_x_preferred":[
        "\u0424\u0438\u0430\u043b\u043a\u0430 \u0412\u0438\u0442\u0442\u0440\u043e\u043a\u0430"
    ],
    "name:slk_x_preferred":[
        "Fialka z\u00e1hradn\u00e1"
    ],
    "name:slv_x_preferred":[
        "Ma\u010deha"
    ],
    "name:swe_x_preferred":[
        "Pens\u00e9er"
    ],
    "name:szl_x_preferred":[
        "\u015ayrotki"
    ],
    "name:vie_x_preferred":[
        "P\u0103ng-x\u00ea"
    ],
    "name:war_x_preferred":[
        "Viola wittrockiana"
    ],
    "name:zho_x_preferred":[
        "\u5927\u82b1\u4e09\u8272\u5807"
    ],
    "wof:name":"Pansy",
    "wof:placetype":"locality"
},
  "geometry": {"coordinates":[-96.71451,49.32608],"type":"Point"}
}