{
  "type": "Feature",
  "properties": {
    "gn:admin1_code":"3",
    "gn:asciiname":"Pansy",
    "gn:country_code":"CA",
    "gn:dem":287,
    "gn:feature_class":"P",
    "gn:feature_code":"PPLL",
    "gn:name":"Pansy",
    "gn:population":0,
    "gn:timezone":"America/Winnipeg",
    "iso:country":"CA",
    "wof:name":"Pansy",
    "wof:placetype":"locality"
},
  "geometry": {"coordinates":[-96.71451,49.32608],"type":"Point"}
}