{
  "type": "Feature",
  "properties": {
    "gn:admin1_code":"1",
    "gn:asciiname":"Nier",
    "gn:country_code":"CA",
    "gn:dem":1151,
    "gn:feature_class":"P",
    "gn:feature_code":"PPLL",
    "gn:name":"Nier",
    "gn:population":0,
    "gn:timezone":"America/Edmonton",
    "iso:country":"CA",
    "wof:name":"Nier",
    "wof:placetype":"locality"
},
  "geometry": {"coordinates":[-114.16868999999998,51.4168],"type":"Point"}
}