{
  "type": "Feature",
  "properties": {
    "gn:admin1_code":"4",
    "gn:asciiname":"Harvey",
    "gn:country_code":"CA",
    "gn:dem":16,
    "gn:feature_class":"P",
    "gn:feature_code":"PPL",
    "gn:name":"Harvey",
    "gn:population":0,
    "gn:timezone":"America/Moncton",
    "iso:country":"CA",
    "name:ara_x_preferred":[
        "\u0647\u0627\u0631\u0641\u064a \u0633\u062a\u064a\u0634\u0646"
    ],
    "name:ceb_x_preferred":[
        "Harvey Station"
    ],
    "name:deu_x_preferred":[
        "Harvey Station"
    ],
    "name:fas_x_preferred":[
        "\u0647\u0627\u0631\u0648\u06cc"
    ],
    "name:fra_x_preferred":[
        "Harvey"
    ],
    "name:ita_x_preferred":[
        "Harvey"
    ],
    "name:swe_x_preferred":[
        "Harvey Station"
    ],
    "wof:name":"Harvey",
    "wof:placetype":"locality"
},
  "geometry": {"coordinates":[-64.71028000000001,45.72458],"type":"Point"}
}