{
  "type": "Feature",
  "properties": {
    "gn:admin1_code":"2.0",
    "gn:admin2_code":"5921",
    "gn:asciiname":"Nanoose Bay",
    "gn:country_code":"CA",
    "gn:dem":44,
    "gn:feature_class":"P",
    "gn:feature_code":"PPL",
    "gn:name":"Nanoose Bay",
    "gn:population":0,
    "gn:timezone":"America/Vancouver",
    "iso:country":"CA",
    "name:ceb_x_preferred":[
        "Nanoose Bay"
    ],
    "name:fra_x_preferred":[
        "Nanoose Bay"
    ],
    "name:swe_x_preferred":[
        "Nanoose Bay"
    ],
    "wof:name":"Nanoose Bay",
    "wof:placetype":"locality"
},
  "geometry": {"coordinates":[-124.19332,49.27237],"type":"Point"}
}