{
  "type": "Feature",
  "properties": {
    "gn:admin1_code":"8",
    "gn:asciiname":"Pine Point",
    "gn:country_code":"CA",
    "gn:dem":147,
    "gn:feature_class":"P",
    "gn:feature_code":"PPL",
    "gn:name":"Pine Point",
    "gn:population":0,
    "gn:timezone":"America/Toronto",
    "iso:country":"CA",
    "name:ceb_x_preferred":[
        "Pine Point"
    ],
    "name:pol_x_preferred":[
        "Pine Point"
    ],
    "name:swe_x_preferred":[
        "Pine Point"
    ],
    "wof:name":"Pine Point",
    "wof:placetype":"locality"
},
  "geometry": {"coordinates":[-79.54805999999998,43.71444],"type":"Point"}
}