{
  "type": "Feature",
  "properties": {
    "gn:admin1_code":"4",
    "gn:asciiname":"Queenstown",
    "gn:country_code":"CA",
    "gn:dem":71,
    "gn:feature_class":"P",
    "gn:feature_code":"PPL",
    "gn:name":"Queenstown",
    "gn:population":0,
    "gn:timezone":"America/Moncton",
    "iso:country":"CA",
    "name:arg_x_preferred":[
        "Queenstown"
    ],
    "name:ast_x_preferred":[
        "Queenstown"
    ],
    "name:ceb_x_preferred":[
        "Queenstown"
    ],
    "name:ces_x_preferred":[
        "Queenstown"
    ],
    "name:dan_x_preferred":[
        "Queenstown"
    ],
    "name:deu_x_preferred":[
        "Queenstown"
    ],
    "name:est_x_preferred":[
        "Queenstown"
    ],
    "name:fin_x_preferred":[
        "Queenstown"
    ],
    "name:fra_x_preferred":[
        "Queenstown"
    ],
    "name:heb_x_preferred":[
        "\u05e7\u05d5\u05d5\u05d9\u05e0\u05e1\u05d8\u05d0\u05d5\u05df"
    ],
    "name:ind_x_preferred":[
        "Queenstown"
    ],
    "name:ita_x_preferred":[
        "Queenstown"
    ],
    "name:jpn_x_preferred":[
        "\u30af\u30a4\u30fc\u30f3\u30ba\u30bf\u30a6\u30f3"
    ],
    "name:kor_x_preferred":[
        "\ud038\uc2a4\ud0c0\uc6b4"
    ],
    "name:mkd_x_preferred":[
        "\u041a\u0432\u0438\u043d\u0441\u0442\u0430\u0443\u043d"
    ],
    "name:mlg_x_preferred":[
        "Queenstown"
    ],
    "name:nld_x_preferred":[
        "Queenstown"
    ],
    "name:nno_x_preferred":[
        "Queenstown"
    ],
    "name:nor_x_preferred":[
        "Queenstown"
    ],
    "name:pol_x_preferred":[
        "Queenstown"
    ],
    "name:rus_x_preferred":[
        "\u041a\u0443\u0438\u043d\u0441\u0442\u0430\u0443\u043d"
    ],
    "name:spa_x_preferred":[
        "Queenstown"
    ],
    "name:swe_x_preferred":[
        "Queenstown"
    ],
    "name:zho_x_preferred":[
        "\u7687\u540e\u9547"
    ],
    "wof:name":"Queenstown",
    "wof:placetype":"locality"
},
  "geometry": {"coordinates":[-66.11556,45.68344],"type":"Point"}
}