{
  "type": "Feature",
  "properties": {
    "gn:admin1_code":"10.0",
    "gn:admin2_code":"7.0",
    "gn:admin3_code":"81017.0",
    "gn:asciiname":"Domaine-Glenwood",
    "gn:country_code":"CA",
    "gn:dem":78,
    "gn:feature_class":"P",
    "gn:feature_code":"PPL",
    "gn:name":"Domaine-Glenwood",
    "gn:population":0,
    "gn:timezone":"America/Toronto",
    "iso:country":"CA",
    "wof:name":"Domaine-Glenwood",
    "wof:placetype":"locality"
},
  "geometry": {"coordinates":[-75.82607,45.38977],"type":"Point"}
}