{
  "type": "Feature",
  "properties": {
    "gn:admin1_code":"1",
    "gn:asciiname":"Evarts",
    "gn:country_code":"CA",
    "gn:dem":917,
    "gn:feature_class":"P",
    "gn:feature_code":"PPLL",
    "gn:name":"Evarts",
    "gn:population":0,
    "gn:timezone":"America/Edmonton",
    "iso:country":"CA",
    "wof:name":"Evarts",
    "wof:placetype":"locality"
},
  "geometry": {"coordinates":[-114.26871,52.26681],"type":"Point"}
}