{
  "type": "Feature",
  "properties": {
    "iso:country":"CA",
    "name:eng_x_preferred":[
        "Taylor Woods"
    ],
    "qs:gn_adm0_cc":"CA",
    "qs:gn_local":5913415,
    "qs:gn_nam_loc":"caledon",
    "qs:gn_namadm1":"08",
    "qs:local_max":389,
    "qs:local_sum":2625,
    "qs:localhoods":17,
    "qs:name":"Taylor Woods",
    "qs:name_adm0":"Canada",
    "qs:name_adm1":"Ontario",
    "qs:name_adm2":"Peel",
    "qs:name_local":"Caledon",
    "qs:photo_max":23,
    "qs:photo_sum":91,
    "qs:placetype":"Suburb",
    "qs:quad_count":18,
    "qs:woe_adm0":23424775,
    "qs:woe_adm1":2344922,
    "qs:woe_adm2":29375178,
    "qs:woe_funk":"Parented by a neighborhood",
    "qs:woe_lau":0,
    "qs:woe_local":23396905,
    "qs:woe_ver":"7.10.0",
    "wof:lang":[
        "eng"
    ],
    "wof:name":"Taylor Woods",
    "wof:placetype":"neighbourhood"
},
  "geometry": {"coordinates":[-79.74290499999999,43.884385],"type":"Point"}
}