{
  "type": "Feature",
  "properties": {
    "gn:admin1_code":"10",
    "gn:admin2_code":"13",
    "gn:admin3_code":"65005.0",
    "gn:asciiname":"Saint-Elzear",
    "gn:country_code":"CA",
    "gn:dem":47,
    "gn:feature_class":"P",
    "gn:feature_code":"PPL",
    "gn:name":"Saint-Elz\u00e9ar",
    "gn:population":0,
    "gn:timezone":"America/Toronto",
    "iso:country":"CA",
    "wof:name":"Saint-Elzear",
    "wof:placetype":"locality"
},
  "geometry": {"coordinates":[-73.72698000000003,45.60338],"type":"Point"}
}