{
  "type": "Feature",
  "properties": {
    "gn:admin1_code":"8",
    "gn:asciiname":"Grenville Park",
    "gn:country_code":"CA",
    "gn:dem":83,
    "gn:feature_class":"P",
    "gn:feature_code":"PPL",
    "gn:name":"Grenville Park",
    "gn:population":0,
    "gn:timezone":"America/Toronto",
    "iso:country":"CA",
    "wof:name":"Grenville Park",
    "wof:placetype":"locality"
},
  "geometry": {"coordinates":[-76.53407,44.24153],"type":"Point"}
}