{
  "type": "Feature",
  "properties": {
    "gn:admin1_code":"11",
    "gn:asciiname":"Katepwa Beach",
    "gn:country_code":"CA",
    "gn:dem":475,
    "gn:feature_class":"P",
    "gn:feature_code":"PPL",
    "gn:name":"Katepwa Beach",
    "gn:population":0,
    "gn:timezone":"America/Regina",
    "iso:country":"CA",
    "wof:name":"Katepwa Beach",
    "wof:placetype":"locality"
},
  "geometry": {"coordinates":[-103.63433000000001,50.70007],"type":"Point"}
}