{
  "type": "Feature",
  "properties": {
    "gn:admin1_code":"8.0",
    "gn:asciiname":"Centreville",
    "gn:country_code":"CA",
    "gn:dem":202,
    "gn:feature_class":"P",
    "gn:feature_code":"PPL",
    "gn:name":"Centreville",
    "gn:population":0,
    "gn:timezone":"America/Toronto",
    "iso:country":"CA",
    "wof:name":"Centreville",
    "wof:placetype":"locality"
},
  "geometry": {"coordinates":[-80.61778000000002,44.62278],"type":"Point"}
}