{
  "type": "Feature",
  "properties": {
    "gn:admin1_code":"11",
    "gn:asciiname":"Totzke",
    "gn:country_code":"CA",
    "gn:dem":572,
    "gn:feature_class":"P",
    "gn:feature_code":"PPL",
    "gn:name":"Totzke",
    "gn:population":0,
    "gn:timezone":"America/Regina",
    "iso:country":"CA",
    "wof:name":"Totzke",
    "wof:placetype":"locality"
},
  "geometry": {"coordinates":[-105.66783999999998,52.28337],"type":"Point"}
}