{
  "type": "Feature",
  "properties": {
    "gn:admin1_code":"10",
    "gn:admin2_code":"2.0",
    "gn:asciiname":"Poisson-Blanc",
    "gn:country_code":"CA",
    "gn:dem":328,
    "gn:feature_class":"P",
    "gn:feature_code":"PPL",
    "gn:name":"Poisson-Blanc",
    "gn:population":0,
    "gn:timezone":"America/Toronto",
    "iso:country":"CA",
    "wof:name":"Poisson-Blanc",
    "wof:placetype":"locality"
},
  "geometry": {"coordinates":[-73.29583000000002,48.99694],"type":"Point"}
}