{
  "type": "Feature",
  "properties": {
    "gn:admin1_code":"1.0",
    "gn:asciiname":"Assineau",
    "gn:country_code":"CA",
    "gn:dem":592,
    "gn:feature_class":"P",
    "gn:feature_code":"PPLL",
    "gn:name":"Assineau",
    "gn:population":0,
    "gn:timezone":"America/Edmonton",
    "iso:country":"CA",
    "wof:name":"Assineau",
    "wof:placetype":"locality"
},
  "geometry": {"coordinates":[-115.18562,55.36683000000001],"type":"Point"}
}