{
  "type": "Feature",
  "properties": {
    "gn:admin1_code":"8.0",
    "gn:asciiname":"Long Branch",
    "gn:country_code":"CA",
    "gn:dem":86,
    "gn:feature_class":"P",
    "gn:feature_code":"PPL",
    "gn:name":"Long Branch",
    "gn:population":0,
    "gn:timezone":"America/Toronto",
    "iso:country":"CA",
    "wof:name":"Long Branch",
    "wof:placetype":"locality"
},
  "geometry": {"coordinates":[-79.53251999999998,43.5914],"type":"Point"}
}