{
  "type": "Feature",
  "properties": {
    "iso:country":"CA",
    "name:eng_x_preferred":[
        "Lawson Heights"
    ],
    "name:nld_x_preferred":[
        "Lawson Heights"
    ],
    "wd:wordcount":17,
    "wof:lang":[
        "eng"
    ],
    "wof:name":"Lawson Heights",
    "wof:placetype":"neighbourhood"
},
  "geometry": {"coordinates":[-106.611869,52.169728],"type":"Point"}
}