{
  "type": "Feature",
  "properties": {
    "gn:admin1_code":"7",
    "gn:asciiname":"Hillsburn",
    "gn:country_code":"CA",
    "gn:dem":42,
    "gn:feature_class":"P",
    "gn:feature_code":"PPL",
    "gn:name":"Hillsburn",
    "gn:population":0,
    "gn:timezone":"America/Halifax",
    "iso:country":"CA",
    "name:gla_x_preferred":[
        "Hillsburn"
    ],
    "wof:name":"Hillsburn",
    "wof:placetype":"locality"
},
  "geometry": {"coordinates":[-65.5677,44.79745],"type":"Point"}
}