{
  "type": "Feature",
  "properties": {
    "gn:admin1_code":"8.0",
    "gn:asciiname":"Atherton",
    "gn:country_code":"CA",
    "gn:dem":238,
    "gn:feature_class":"P",
    "gn:feature_code":"PPL",
    "gn:name":"Atherton",
    "gn:population":0,
    "gn:timezone":"America/Toronto",
    "iso:country":"CA",
    "name:ceb_x_preferred":[
        "Atherton"
    ],
    "name:ces_x_preferred":[
        "Atherton"
    ],
    "name:deu_x_preferred":[
        "Atherton"
    ],
    "name:fra_x_preferred":[
        "Atherton"
    ],
    "name:ita_x_preferred":[
        "Atherton"
    ],
    "name:jpn_x_preferred":[
        "\u30a2\u30b5\u30fc\u30c8\u30f3"
    ],
    "name:nld_x_preferred":[
        "Atherton"
    ],
    "name:pol_x_preferred":[
        "Atherton"
    ],
    "name:rus_x_preferred":[
        "\u0410\u0442\u0435\u0440\u0442\u043e\u043d"
    ],
    "name:swe_x_preferred":[
        "Atherton"
    ],
    "name:ukr_x_preferred":[
        "\u0410\u0442\u0435\u0440\u0442\u043e\u043d"
    ],
    "name:vol_x_preferred":[
        "Atherton"
    ],
    "wof:name":"Atherton",
    "wof:placetype":"locality"
},
  "geometry": {"coordinates":[-80.44906,42.82246],"type":"Point"}
}