{
  "type": "Feature",
  "properties": {
    "gn:admin1_code":"8.0",
    "gn:asciiname":"Atherton",
    "gn:country_code":"CA",
    "gn:dem":238,
    "gn:feature_class":"P",
    "gn:feature_code":"PPL",
    "gn:name":"Atherton",
    "gn:population":0,
    "gn:timezone":"America/Toronto",
    "iso:country":"CA",
    "name:ben_x_preferred":[
        "\u0986\u09a5\u09be\u09b0\u09cd\u099f\u09a8"
    ],
    "name:ceb_x_preferred":[
        "Atherton"
    ],
    "name:ces_x_preferred":[
        "Atherton"
    ],
    "name:deu_x_preferred":[
        "Atherton"
    ],
    "name:fra_x_preferred":[
        "Atherton"
    ],
    "name:hin_x_preferred":[
        "\u090f\u0925\u0930\u091f\u0928"
    ],
    "name:hun_x_preferred":[
        "Atherton"
    ],
    "name:ind_x_preferred":[
        "Atherton"
    ],
    "name:ita_x_preferred":[
        "Atherton"
    ],
    "name:jpn_x_preferred":[
        "\u30a2\u30b5\u30fc\u30c8\u30f3"
    ],
    "name:kor_x_preferred":[
        "\uc560\uc11c\ud2bc"
    ],
    "name:nld_x_preferred":[
        "Atherton"
    ],
    "name:pol_x_preferred":[
        "Atherton"
    ],
    "name:rus_x_preferred":[
        "\u0410\u0442\u0435\u0440\u0442\u043e\u043d"
    ],
    "name:spa_x_preferred":[
        "Atherton"
    ],
    "name:swe_x_preferred":[
        "Atherton"
    ],
    "name:tur_x_preferred":[
        "Atherton"
    ],
    "name:ukr_x_preferred":[
        "\u0410\u0442\u0435\u0440\u0442\u043e\u043d"
    ],
    "name:urd_x_preferred":[
        "\u0627\u06cc\u062a\u06be\u0631\u0679\u0646"
    ],
    "name:vie_x_preferred":[
        "Atherton"
    ],
    "name:vol_x_preferred":[
        "Atherton"
    ],
    "name:zho_cn_x_preferred":[
        "\u963f\u745f\u987f"
    ],
    "name:zho_tw_x_preferred":[
        "\u963f\u745f\u9813"
    ],
    "wof:name":"Atherton",
    "wof:placetype":"locality"
},
  "geometry": {"coordinates":[-80.44906,42.82246],"type":"Point"}
}