{
  "type": "Feature",
  "properties": {
    "gn:admin1_code":"7",
    "gn:asciiname":"New Harbour East",
    "gn:country_code":"CA",
    "gn:dem":6,
    "gn:feature_class":"P",
    "gn:feature_code":"PPL",
    "gn:name":"New Harbour East",
    "gn:population":0,
    "gn:timezone":"America/Halifax",
    "iso:country":"CA",
    "wof:name":"New Harbour East",
    "wof:placetype":"locality"
},
  "geometry": {"coordinates":[-61.47718,45.19437],"type":"Point"}
}