{
  "type": "Feature",
  "properties": {
    "gn:admin1_code":"7.0",
    "gn:asciiname":"East Quoddy",
    "gn:country_code":"CA",
    "gn:dem":14,
    "gn:feature_class":"P",
    "gn:feature_code":"PPLL",
    "gn:name":"East Quoddy",
    "gn:population":0,
    "gn:timezone":"America/Halifax",
    "iso:country":"CA",
    "wof:name":"East Quoddy",
    "wof:placetype":"locality"
},
  "geometry": {"coordinates":[-62.3319,44.91685],"type":"Point"}
}