{
  "type": "Feature",
  "properties": {
    "gn:admin1_code":"8.0",
    "gn:asciiname":"Charleville",
    "gn:country_code":"CA",
    "gn:dem":93,
    "gn:feature_class":"P",
    "gn:feature_code":"PPL",
    "gn:name":"Charleville",
    "gn:population":0,
    "gn:timezone":"America/Toronto",
    "iso:country":"CA",
    "wof:name":"Charleville",
    "wof:placetype":"locality"
},
  "geometry": {"coordinates":[-75.6129,44.75149],"type":"Point"}
}