{
  "type": "Feature",
  "properties": {
    "gn:admin1_code":"8.0",
    "gn:asciiname":"Charleville",
    "gn:country_code":"CA",
    "gn:dem":93,
    "gn:feature_class":"P",
    "gn:feature_code":"PPL",
    "gn:name":"Charleville",
    "gn:population":0,
    "gn:timezone":"America/Toronto",
    "iso:country":"CA",
    "name:bre_x_preferred":[
        "Charleville"
    ],
    "name:ceb_x_preferred":[
        "Charleville"
    ],
    "name:deu_x_preferred":[
        "Charleville"
    ],
    "name:fra_x_preferred":[
        "Charleville"
    ],
    "name:heb_x_preferred":[
        "\u05e6'\u05e8\u05dc\u05d5\u05d5\u05d9\u05dc"
    ],
    "name:hun_x_preferred":[
        "Charleville"
    ],
    "name:ita_x_preferred":[
        "Charleville"
    ],
    "name:nld_x_preferred":[
        "Charleville"
    ],
    "name:oci_x_preferred":[
        "Charleville"
    ],
    "name:pol_x_preferred":[
        "Charleville"
    ],
    "name:rus_x_preferred":[
        "\u0428\u0430\u0440\u043b\u0435\u0432\u0438\u043b\u044c"
    ],
    "name:spa_x_preferred":[
        "Charleville"
    ],
    "name:sqi_x_preferred":[
        "Charleville"
    ],
    "name:swe_x_preferred":[
        "Charleville"
    ],
    "wof:name":"Charleville",
    "wof:placetype":"locality"
},
  "geometry": {"coordinates":[-75.6129,44.75149],"type":"Point"}
}