{
  "type": "Feature",
  "properties": {
    "gn:admin1_code":"9",
    "gn:asciiname":"Stanley Bridge, Hope River, Bayview, Cavendish and North Rustico",
    "gn:country_code":"CA",
    "gn:dem":40,
    "gn:feature_class":"P",
    "gn:feature_code":"PPL",
    "gn:name":"Stanley Bridge, Hope River, Bayview, Cavendish and North Rustico",
    "gn:population":0,
    "gn:timezone":"America/Halifax",
    "iso:country":"CA",
    "wof:name":"Stanley Bridge, Hope River, Bayview, Cavendish and North Rustico",
    "wof:placetype":"locality"
},
  "geometry": {"coordinates":[-63.3909,46.48072],"type":"Point"}
}