{
  "type": "Feature",
  "properties": {
    "iso:country":"CA",
    "name:eng_x_preferred":[
        "Copper Cliff"
    ],
    "qs:gn_adm0_cc":"CA",
    "qs:gn_fcode":"PPL",
    "qs:gn_local":5964700,
    "qs:gn_namadm1":"08",
    "qs:gn_name":"Copper Cliff",
    "qs:local_max":3398,
    "qs:local_sum":5038,
    "qs:localhoods":10,
    "qs:name":"Copper Cliff",
    "qs:name_adm0":"Canada",
    "qs:name_adm1":"Ontario",
    "qs:name_adm2":"Greater Sudbury",
    "qs:name_local":"Sudbury",
    "qs:photo_max":26,
    "qs:photo_sum":115,
    "qs:placetype":"Suburb",
    "qs:quad_count":21,
    "qs:woe_adm0":23424775,
    "qs:woe_adm1":2344922,
    "qs:woe_adm2":29375071,
    "qs:woe_lau":0,
    "qs:woe_local":3198,
    "qs:woe_ver":"7.10.0",
    "wof:lang":[
        "eng"
    ],
    "wof:name":"Copper Cliff",
    "wof:placetype":"neighbourhood"
},
  "geometry": {"coordinates":[-81.064221,46.474269],"type":"Point"}
}