{
  "type": "Feature",
  "properties": {
    "gn:admin1_code":"8",
    "gn:asciiname":"Malden Centre",
    "gn:country_code":"CA",
    "gn:dem":180,
    "gn:feature_class":"P",
    "gn:feature_code":"PPL",
    "gn:name":"Malden Centre",
    "gn:population":0,
    "gn:timezone":"America/Toronto",
    "iso:country":"CA",
    "wof:name":"Malden Centre",
    "wof:placetype":"locality"
},
  "geometry": {"coordinates":[-83.03654,42.05955],"type":"Point"}
}