{
  "type": "Feature",
  "properties": {
    "gn:gn_country":"CA",
    "iso:country":"CA",
    "qs_pg:aaroncc":"CA",
    "qs_pg:gn_country":"CA",
    "qs_pg:name":"Leondardville",
    "qs_pg:name_adm0":"Canada",
    "qs_pg:name_adm1":"New Brunswick",
    "qs_pg:photos":38,
    "qs_pg:photos_1k":8,
    "qs_pg:photos_9k":1,
    "qs_pg:photos_9r":2,
    "qs_pg:photos_all":38,
    "qs_pg:photos_sr":2,
    "qs_pg:pop_sr":0,
    "qs_pg:qs_pg_placetype":"locality",
    "qs_pg:qs_pg_placetype_gp":"Town",
    "qs_pg:woe_adm0":23424775,
    "woe:adm0_id":23424775,
    "woe:name_adm0":"Canada",
    "woe:name_adm1":"New Brunswick",
    "woe:placetype":"Town",
    "wof:name":"Leondardville",
    "wof:placetype":"locality"
},
  "geometry": {"coordinates":[-66.94725,44.9747715],"type":"Point"}
}