{
  "type": "Feature",
  "properties": {
    "gn:admin1_code":"8",
    "gn:asciiname":"Rosetta",
    "gn:country_code":"CA",
    "gn:dem":178,
    "gn:feature_class":"P",
    "gn:feature_code":"PPL",
    "gn:name":"Rosetta",
    "gn:population":0,
    "gn:timezone":"America/Toronto",
    "iso:country":"CA",
    "name:afr_x_preferred":[
        "Rosetta"
    ],
    "name:ara_x_preferred":[
        "\u0631\u0634\u064a\u062f"
    ],
    "name:arz_x_preferred":[
        "\u0631\u0634\u064a\u062f"
    ],
    "name:bul_x_preferred":[
        "\u0420\u043e\u0437\u0435\u0442\u0430"
    ],
    "name:cat_x_preferred":[
        "Rosetta"
    ],
    "name:ceb_x_preferred":[
        "Rosetta"
    ],
    "name:deu_x_preferred":[
        "Rosette"
    ],
    "name:ell_x_preferred":[
        "\u03a1\u03bf\u03b6\u03ad\u03c4\u03b1"
    ],
    "name:epo_x_preferred":[
        "Ra\u015dido"
    ],
    "name:est_x_preferred":[
        "Rash\u012bd"
    ],
    "name:eus_x_preferred":[
        "Rosetta"
    ],
    "name:fas_x_preferred":[
        "\u0631\u0634\u06cc\u062f"
    ],
    "name:fra_x_preferred":[
        "Rosette"
    ],
    "name:heb_x_preferred":[
        "\u05e8\u05e9\u05d9\u05d3"
    ],
    "name:hrv_x_preferred":[
        "Rozeta"
    ],
    "name:hun_x_preferred":[
        "Rosetta"
    ],
    "name:ind_x_preferred":[
        "Rashid"
    ],
    "name:isl_x_preferred":[
        "Rosetta"
    ],
    "name:ita_x_preferred":[
        "Rosetta"
    ],
    "name:jav_x_preferred":[
        "Rosetta"
    ],
    "name:jpn_x_preferred":[
        "\u30ed\u30bc\u30c3\u30bf"
    ],
    "name:kat_x_preferred":[
        "\u10e0\u10d0\u10e8\u10d8\u10d3\u10d8"
    ],
    "name:kor_x_preferred":[
        "\ub85c\uc81c\ud0c0"
    ],
    "name:lat_x_preferred":[
        "Rosetta"
    ],
    "name:nld_x_preferred":[
        "Rosetta"
    ],
    "name:nor_x_preferred":[
        "Rosetta"
    ],
    "name:pol_x_preferred":[
        "Rosetta"
    ],
    "name:por_x_preferred":[
        "Roseta"
    ],
    "name:rus_x_preferred":[
        "\u0420\u0430\u0448\u0438\u0434"
    ],
    "name:slk_x_preferred":[
        "Ar-Ra\u0161\u00edd"
    ],
    "name:slv_x_preferred":[
        "Rosetta"
    ],
    "name:spa_x_preferred":[
        "Rosetta"
    ],
    "name:srp_x_preferred":[
        "\u0420\u043e\u0437\u0435\u0442\u0430"
    ],
    "name:swe_x_preferred":[
        "Rosetta"
    ],
    "name:tur_x_preferred":[
        "Re\u015fid"
    ],
    "name:ukr_x_preferred":[
        "\u0420\u0430\u0448\u0438\u0434"
    ],
    "name:wuu_x_preferred":[
        "\u7f57\u585e\u5854"
    ],
    "name:zho_x_preferred":[
        "\u7f85\u585e\u5854"
    ],
    "wof:name":"Rosetta",
    "wof:placetype":"locality"
},
  "geometry": {"coordinates":[-76.33389,45.12083],"type":"Point"}
}