{
  "type": "Feature",
  "properties": {
    "gn:admin1_code":"4.0",
    "gn:asciiname":"Camerons Mill",
    "gn:country_code":"CA",
    "gn:dem":49,
    "gn:feature_class":"P",
    "gn:feature_code":"PPL",
    "gn:name":"Camerons Mill",
    "gn:population":0,
    "gn:timezone":"America/Moncton",
    "iso:country":"CA",
    "wof:name":"Camerons Mill",
    "wof:placetype":"locality"
},
  "geometry": {"coordinates":[-65.10986,46.67914],"type":"Point"}
}