{
  "type": "Feature",
  "properties": {
    "gn:admin1_code":"11",
    "gn:asciiname":"Flat Valley",
    "gn:country_code":"CA",
    "gn:dem":498,
    "gn:feature_class":"P",
    "gn:feature_code":"PPLL",
    "gn:name":"Flat Valley",
    "gn:population":0,
    "gn:timezone":"America/Regina",
    "iso:country":"CA",
    "wof:name":"Flat Valley",
    "wof:placetype":"locality"
},
  "geometry": {"coordinates":[-109.23484999999999,54.30019],"type":"Point"}
}