{
  "type": "Feature",
  "properties": {
    "iso:country":"CA",
    "name:eng_x_preferred":[
        "Haultain"
    ],
    "name:nld_x_preferred":[
        "Haultain"
    ],
    "wd:wordcount":34,
    "wof:lang":[
        "eng"
    ],
    "wof:name":"Haultain",
    "wof:placetype":"neighbourhood"
},
  "geometry": {"coordinates":[-106.64766400000001,52.110589],"type":"Point"}
}