{
  "type": "Feature",
  "properties": {
    "gn:country":"CA",
    "gn:fcode":"ADMD",
    "gn:population":0,
    "iso:country":"CA",
    "name:deu_x_preferred":[
        "Leduc County"
    ],
    "name:eng_x_preferred":[
        "Leduc County"
    ],
    "name:mal_x_preferred":[
        "\u0d35\u0d30\u0d4d\u200d\u0d17\u0d4d\u0d17\u0d02: \u0d32\u0d46\u0d21\u0d41\u0d15\u0d4d\u0d15\u0d4d \u0d15\u0d57\u0d23\u0d4d\u0d1f\u0d3f"
    ],
    "name:ron_x_preferred":[
        "Comitatul Leduc"
    ],
    "name:ukr_x_preferred":[
        "\u041b\u0435\u0434\u044e\u043a"
    ],
    "qs:name":"Leduc County",
    "qs:photos_9r":0,
    "qs:photos_sr":0,
    "qs:pop_sr":"0",
    "wd:wordcount":529,
    "wof:name":"Leduc County",
    "wof:placetype":"localadmin",
    "wof:population":0
},
  "geometry": {"coordinates":[-113.80643000000001,53.23573],"type":"Point"}
}