{
  "type": "Feature",
  "properties": {
    "gn:country":"CA",
    "gn:fcode":"ADMD",
    "gn:pop":0,
    "iso:country":"CA",
    "name:eng_x_preferred":[
        "Leduc County"
    ],
    "name:ron_x_preferred":[
        "Comitatul Leduc"
    ],
    "qs:name":"Leduc County",
    "qs:photos_9r":0,
    "qs:photos_sr":0,
    "qs:pop_sr":"0",
    "wd:wordcount":529,
    "wof:name":"Leduc County",
    "wof:placetype":"localadmin",
    "wof:population":0
},
  "geometry": {"coordinates":[-113.80643000000001,53.23573],"type":"Point"}
}