{
  "type": "Feature",
  "properties": {
    "gn:admin1_code":"8.0",
    "gn:asciiname":"Bellwood",
    "gn:country_code":"CA",
    "gn:dem":400,
    "gn:feature_class":"P",
    "gn:feature_code":"PPL",
    "gn:name":"Bellwood",
    "gn:population":0,
    "gn:timezone":"America/Toronto",
    "iso:country":"CA",
    "wof:name":"Bellwood",
    "wof:placetype":"locality"
},
  "geometry": {"coordinates":[-78.24889,45.5025],"type":"Point"}
}