{
  "type": "Feature",
  "properties": {
    "gn:admin1_code":"8.0",
    "gn:asciiname":"Bellwood",
    "gn:country_code":"CA",
    "gn:dem":400,
    "gn:feature_class":"P",
    "gn:feature_code":"PPL",
    "gn:name":"Bellwood",
    "gn:population":0,
    "gn:timezone":"America/Toronto",
    "iso:country":"CA",
    "name:ceb_x_preferred":[
        "Bellwood"
    ],
    "name:deu_x_preferred":[
        "Bellwood"
    ],
    "name:ita_x_preferred":[
        "Bellwood"
    ],
    "name:mlg_x_preferred":[
        "Bellwood"
    ],
    "name:nld_x_preferred":[
        "Bellwood"
    ],
    "name:pol_x_preferred":[
        "Bellwood"
    ],
    "name:por_x_preferred":[
        "Bellwood"
    ],
    "name:srp_x_preferred":[
        "\u0411\u0435\u043b\u0432\u0443\u0434"
    ],
    "name:ukr_x_preferred":[
        "\u0411\u0435\u043b\u043b\u0432\u0443\u0434"
    ],
    "name:urd_x_preferred":[
        "\u0628\u06cc\u0644\u0648\u0648\u0688"
    ],
    "name:vol_x_preferred":[
        "Bellwood"
    ],
    "wof:name":"Bellwood",
    "wof:placetype":"locality"
},
  "geometry": {"coordinates":[-78.24889,45.5025],"type":"Point"}
}