{
  "type": "Feature",
  "properties": {
    "gn:admin1_code":"1.0",
    "gn:asciiname":"Bantry",
    "gn:country_code":"CA",
    "gn:dem":762,
    "gn:feature_class":"P",
    "gn:feature_code":"PPLL",
    "gn:name":"Bantry",
    "gn:population":0,
    "gn:timezone":"America/Edmonton",
    "iso:country":"CA",
    "name:bre_x_preferred":[
        "Beanntra\u00ed"
    ],
    "name:bul_x_preferred":[
        "\u0411\u0430\u043d\u0442\u0440\u0438"
    ],
    "name:cat_x_preferred":[
        "Bantry"
    ],
    "name:ceb_x_preferred":[
        "Bantry"
    ],
    "name:dan_x_preferred":[
        "Bantry"
    ],
    "name:deu_x_preferred":[
        "Bantry"
    ],
    "name:eus_x_preferred":[
        "Bantry"
    ],
    "name:fas_x_preferred":[
        "\u0628\u0627\u0646\u062a\u0631\u06cc"
    ],
    "name:fra_x_preferred":[
        "Bantry"
    ],
    "name:gle_x_preferred":[
        "Beanntra\u00ed"
    ],
    "name:ind_x_preferred":[
        "Bantry"
    ],
    "name:ita_x_preferred":[
        "Bantry"
    ],
    "name:kat_x_preferred":[
        "\u10d1\u10d0\u10dc\u10e2\u10e0\u10d8"
    ],
    "name:kor_x_preferred":[
        "\ubc34\ud2b8\ub9ac"
    ],
    "name:nld_x_preferred":[
        "Bantry"
    ],
    "name:nor_x_preferred":[
        "Bantry"
    ],
    "name:pol_x_preferred":[
        "Bantry"
    ],
    "name:rus_x_preferred":[
        "\u0411\u0430\u043d\u0442\u0440\u0438"
    ],
    "name:spa_x_preferred":[
        "Bantry"
    ],
    "name:swe_x_preferred":[
        "Bantry"
    ],
    "name:zho_x_preferred":[
        "\u73ed\u7279\u91cc"
    ],
    "wof:name":"Bantry",
    "wof:placetype":"locality"
},
  "geometry": {"coordinates":[-111.75178,50.48341],"type":"Point"}
}