{
  "type": "Feature",
  "properties": {
    "gn:admin1_code":"8",
    "gn:asciiname":"Korah",
    "gn:country_code":"CA",
    "gn:dem":215,
    "gn:feature_class":"P",
    "gn:feature_code":"PPL",
    "gn:name":"Korah",
    "gn:population":0,
    "gn:timezone":"America/Toronto",
    "iso:country":"CA",
    "name:ara_x_preferred":[
        "\u0642\u0627\u0631\u0648\u0646"
    ],
    "name:cat_x_preferred":[
        "Cor\u00e8"
    ],
    "name:ces_x_preferred":[
        "K\u00f3rach"
    ],
    "name:dan_x_preferred":[
        "Kora"
    ],
    "name:deu_x_preferred":[
        "Korach"
    ],
    "name:fas_x_preferred":[
        "\u0642\u0627\u0631\u0648\u0646"
    ],
    "name:fin_x_preferred":[
        "Korah"
    ],
    "name:fra_x_preferred":[
        "Cor\u00e9"
    ],
    "name:heb_x_preferred":[
        "\u05e7\u05d5\u05e8\u05d7"
    ],
    "name:ina_x_preferred":[
        "Korakh"
    ],
    "name:ind_x_preferred":[
        "Korah"
    ],
    "name:ita_x_preferred":[
        "Core"
    ],
    "name:kaz_x_preferred":[
        "\u049a\u0430\u0440\u0443\u043d"
    ],
    "name:nld_x_preferred":[
        "Korach"
    ],
    "name:nor_x_preferred":[
        "Korah"
    ],
    "name:pol_x_preferred":[
        "Korach"
    ],
    "name:por_x_preferred":[
        "Cor\u00e9"
    ],
    "name:pus_x_preferred":[
        "\u0642\u0627\u0631\u0648\u0646"
    ],
    "name:ron_x_preferred":[
        "Korah"
    ],
    "name:rus_x_preferred":[
        "\u041a\u043e\u0440\u0435\u0439"
    ],
    "name:tur_x_preferred":[
        "K\u00e2r\u00fbn"
    ],
    "name:urd_x_preferred":[
        "\u0642\u0627\u0631\u0648\u0646"
    ],
    "wof:name":"Korah",
    "wof:placetype":"locality"
},
  "geometry": {"coordinates":[-84.40472,46.55139000000001],"type":"Point"}
}