{
  "type": "Feature",
  "properties": {
    "gn:admin1_code":"11",
    "gn:asciiname":"Vanstone",
    "gn:country_code":"CA",
    "gn:dem":513,
    "gn:feature_class":"P",
    "gn:feature_code":"PPLL",
    "gn:name":"Vanstone",
    "gn:population":0,
    "gn:timezone":"America/Regina",
    "iso:country":"CA",
    "wof:name":"Vanstone",
    "wof:placetype":"locality"
},
  "geometry": {"coordinates":[-102.60096,51.2167],"type":"Point"}
}