{
  "type": "Feature",
  "properties": {
    "gn:admin1_code":"1.0",
    "gn:asciiname":"Alcomdale",
    "gn:country_code":"CA",
    "gn:dem":718,
    "gn:feature_class":"P",
    "gn:feature_code":"PPLL",
    "gn:name":"Alcomdale",
    "gn:population":0,
    "gn:timezone":"America/Edmonton",
    "iso:country":"CA",
    "wof:name":"Alcomdale",
    "wof:placetype":"locality"
},
  "geometry": {"coordinates":[-113.83535000000001,53.90015],"type":"Point"}
}