{
  "type": "Feature",
  "properties": {
    "gn:admin1_code":"1",
    "gn:asciiname":"Hoadley",
    "gn:country_code":"CA",
    "gn:dem":959,
    "gn:feature_class":"P",
    "gn:feature_code":"PPL",
    "gn:name":"Hoadley",
    "gn:population":0,
    "gn:timezone":"America/Edmonton",
    "iso:country":"CA",
    "wof:name":"Hoadley",
    "wof:placetype":"locality"
},
  "geometry": {"coordinates":[-114.36875000000001,52.85011],"type":"Point"}
}