{
  "type": "Feature",
  "properties": {
    "gn:admin1_code":"3.0",
    "gn:asciiname":"Drifting River",
    "gn:country_code":"CA",
    "gn:dem":433,
    "gn:feature_class":"P",
    "gn:feature_code":"PPLL",
    "gn:name":"Drifting River",
    "gn:population":0,
    "gn:timezone":"America/Winnipeg",
    "iso:country":"CA",
    "wof:name":"Drifting River",
    "wof:placetype":"locality"
},
  "geometry": {"coordinates":[-100.55616999999999,51.3336],"type":"Point"}
}