{
  "type": "Feature",
  "properties": {
    "gn:admin1_code":"7",
    "gn:asciiname":"Lake Road Corner",
    "gn:country_code":"CA",
    "gn:dem":56,
    "gn:feature_class":"P",
    "gn:feature_code":"PPLL",
    "gn:name":"Lake Road Corner",
    "gn:population":0,
    "gn:timezone":"America/Halifax",
    "iso:country":"CA",
    "wof:name":"Lake Road Corner",
    "wof:placetype":"locality"
},
  "geometry": {"coordinates":[-64.33205,45.46685],"type":"Point"}
}