{
  "type": "Feature",
  "properties": {
    "gn:admin1_code":"7",
    "gn:asciiname":"McKay Section",
    "gn:country_code":"CA",
    "gn:dem":48,
    "gn:feature_class":"P",
    "gn:feature_code":"PPL",
    "gn:name":"McKay Section",
    "gn:population":0,
    "gn:timezone":"America/Halifax",
    "iso:country":"CA",
    "wof:name":"McKay Section",
    "wof:placetype":"locality"
},
  "geometry": {"coordinates":[-63.95908000000001,45.00917000000001],"type":"Point"}
}