{
  "type": "Feature",
  "properties": {
    "gn:admin1_code":"8.0",
    "gn:asciiname":"Avonton",
    "gn:country_code":"CA",
    "gn:dem":341,
    "gn:feature_class":"P",
    "gn:feature_code":"PPL",
    "gn:name":"Avonton",
    "gn:population":0,
    "gn:timezone":"America/Toronto",
    "iso:country":"CA",
    "wof:name":"Avonton",
    "wof:placetype":"locality"
},
  "geometry": {"coordinates":[-81.0868,43.35377],"type":"Point"}
}