{
  "type": "Feature",
  "properties": {
    "gn:admin1_code":"9.0",
    "gn:asciiname":"Duvar",
    "gn:country_code":"CA",
    "gn:dem":36,
    "gn:feature_class":"P",
    "gn:feature_code":"PPLL",
    "gn:name":"Duvar",
    "gn:population":0,
    "gn:timezone":"America/Halifax",
    "iso:country":"CA",
    "name:fra_x_preferred":[
        "Duvar"
    ],
    "wof:name":"Duvar",
    "wof:placetype":"locality"
},
  "geometry": {"coordinates":[-64.23204,46.75015],"type":"Point"}
}