{
  "type": "Feature",
  "properties": {
    "gn:admin1_code":"7",
    "gn:asciiname":"St. Joseph",
    "gn:country_code":"CA",
    "gn:dem":67,
    "gn:feature_class":"P",
    "gn:feature_code":"PPL",
    "gn:name":"St. Joseph",
    "gn:population":0,
    "gn:timezone":"America/Halifax",
    "iso:country":"CA",
    "name:ben_x_preferred":[
        "\u09b8\u09c7\u09a8\u09cd\u099f \u099c\u09cb\u09b8\u09c7\u09ab"
    ],
    "name:hin_x_preferred":[
        "\u0938\u0947\u0902\u091f \u091c\u094b\u0938\u0947\u092b\u093c"
    ],
    "name:ind_x_preferred":[
        "St. Joseph"
    ],
    "wof:name":"St. Joseph",
    "wof:placetype":"locality"
},
  "geometry": {"coordinates":[-66.01175000000001,44.26401],"type":"Point"}
}