{
  "type": "Feature",
  "properties": {
    "gn:admin1_code":"10",
    "gn:admin2_code":"7.0",
    "gn:admin3_code":"82025.0",
    "gn:asciiname":"Gleneagle",
    "gn:country_code":"CA",
    "gn:dem":145,
    "gn:feature_class":"P",
    "gn:feature_code":"PPL",
    "gn:name":"Gleneagle",
    "gn:population":0,
    "gn:timezone":"America/Toronto",
    "iso:country":"CA",
    "wof:name":"Gleneagle",
    "wof:placetype":"locality"
},
  "geometry": {"coordinates":[-75.80801,45.53505],"type":"Point"}
}