{
  "type": "Feature",
  "properties": {
    "gn:admin1_code":"8",
    "gn:asciiname":"Hearts Desire",
    "gn:country_code":"CA",
    "gn:dem":90,
    "gn:feature_class":"P",
    "gn:feature_code":"PPL",
    "gn:name":"Hearts Desire",
    "gn:population":0,
    "gn:timezone":"America/Toronto",
    "iso:country":"CA",
    "wof:name":"Hearts Desire",
    "wof:placetype":"locality"
},
  "geometry": {"coordinates":[-75.71666999999999,45.26667],"type":"Point"}
}