{
  "type": "Feature",
  "properties": {
    "gn:admin1_code":"1.0",
    "gn:asciiname":"Brazeau",
    "gn:country_code":"CA",
    "gn:dem":1401,
    "gn:feature_class":"P",
    "gn:feature_code":"PPL",
    "gn:name":"Brazeau",
    "gn:population":0,
    "gn:timezone":"America/Edmonton",
    "iso:country":"CA",
    "wof:name":"Brazeau",
    "wof:placetype":"locality"
},
  "geometry": {"coordinates":[-116.08551,52.46678000000001],"type":"Point"}
}