{
  "type": "Feature",
  "properties": {
    "gn:admin1_code":"3",
    "gn:asciiname":"Fishing River",
    "gn:country_code":"CA",
    "gn:dem":279,
    "gn:feature_class":"P",
    "gn:feature_code":"PPLL",
    "gn:name":"Fishing River",
    "gn:population":0,
    "gn:timezone":"America/Winnipeg",
    "iso:country":"CA",
    "wof:name":"Fishing River",
    "wof:placetype":"locality"
},
  "geometry": {"coordinates":[-100.08775,51.44831],"type":"Point"}
}