{
  "type": "Feature",
  "properties": {
    "gn:admin1_code":"1",
    "gn:asciiname":"Royal Park",
    "gn:country_code":"CA",
    "gn:dem":660,
    "gn:feature_class":"P",
    "gn:feature_code":"PPLL",
    "gn:name":"Royal Park",
    "gn:population":0,
    "gn:timezone":"America/Edmonton",
    "iso:country":"CA",
    "wof:name":"Royal Park",
    "wof:placetype":"locality"
},
  "geometry": {"coordinates":[-112.20184,53.53345],"type":"Point"}
}