{
  "type": "Feature",
  "properties": {
    "gn:admin1_code":"5.0",
    "gn:asciiname":"White House",
    "gn:country_code":"CA",
    "gn:dem":-9999,
    "gn:feature_class":"P",
    "gn:feature_code":"PPLL",
    "gn:name":"White House",
    "gn:population":0,
    "gn:timezone":"America/St_Johns",
    "iso:country":"CA",
    "wof:name":"White House",
    "wof:placetype":"locality"
},
  "geometry": {"coordinates":[-56.9481,51.4834],"type":"Point"}
}