{
  "type": "Feature",
  "properties": {
    "gn:admin1_code":"8",
    "gn:asciiname":"Kinkora",
    "gn:country_code":"CA",
    "gn:dem":365,
    "gn:feature_class":"P",
    "gn:feature_code":"PPL",
    "gn:name":"Kinkora",
    "gn:population":0,
    "gn:timezone":"America/Toronto",
    "iso:country":"CA",
    "name:deu_x_preferred":[
        "Kinkora"
    ],
    "wof:name":"Kinkora",
    "wof:placetype":"locality"
},
  "geometry": {"coordinates":[-81.07417,43.4775],"type":"Point"}
}