{
  "type": "Feature",
  "properties": {
    "gn:admin1_code":"4",
    "gn:asciiname":"Red Bank",
    "gn:country_code":"CA",
    "gn:dem":3,
    "gn:feature_class":"P",
    "gn:feature_code":"PPL",
    "gn:name":"Red Bank",
    "gn:population":0,
    "gn:timezone":"America/Moncton",
    "iso:country":"CA",
    "wof:name":"Red Bank",
    "wof:placetype":"locality"
},
  "geometry": {"coordinates":[-65.82125000000001,46.93903],"type":"Point"}
}