{
  "type": "Feature",
  "properties": {
    "iso:country":"CA",
    "name:ceb_x_preferred":[
        "Pinantan Lake"
    ],
    "name:eng_x_preferred":[
        "Pinantan"
    ],
    "name:eng_x_variant":[
        "Pinantan Lake"
    ],
    "name:swe_x_preferred":[
        "Pinantan Lake"
    ],
    "name:unk_x_variant":[
        "Pinantan"
    ],
    "qs:gn_adm0_cc":"CA",
    "qs:gn_local":5989045,
    "qs:gn_nam_loc":"kamloops",
    "qs:gn_namadm1":"02",
    "qs:local_max":1274,
    "qs:local_sum":4464,
    "qs:localhoods":14,
    "qs:name":"Pinantan",
    "qs:name_adm0":"Canada",
    "qs:name_adm1":"British Columbia",
    "qs:name_adm2":"Thompson-Nicola",
    "qs:name_local":"Kamloops",
    "qs:photo_max":193,
    "qs:photo_sum":324,
    "qs:placetype":"Suburb",
    "qs:quad_count":6,
    "qs:woe_adm0":23424775,
    "qs:woe_adm1":2344916,
    "qs:woe_adm2":29375074,
    "qs:woe_lau":0,
    "qs:woe_local":9633,
    "qs:woe_ver":"7.10.0",
    "wd:wordcount":109,
    "wof:lang":[
        "eng"
    ],
    "wof:name":"Pinantan",
    "wof:placetype":"neighbourhood"
},
  "geometry": {"coordinates":[-120.028115,50.726656],"type":"Point"}
}