{
  "type": "Feature",
  "properties": {
    "gn:admin1_code":"7",
    "gn:asciiname":"Highland Hill",
    "gn:country_code":"CA",
    "gn:dem":55,
    "gn:feature_class":"P",
    "gn:feature_code":"PPLL",
    "gn:name":"Highland Hill",
    "gn:population":0,
    "gn:timezone":"America/Halifax",
    "iso:country":"CA",
    "wof:name":"Highland Hill",
    "wof:placetype":"locality"
},
  "geometry": {"coordinates":[-60.86519000000001,45.96684000000001],"type":"Point"}
}