{
  "type": "Feature",
  "properties": {
    "gn:admin1_code":"8",
    "gn:asciiname":"Farewell",
    "gn:country_code":"CA",
    "gn:dem":419,
    "gn:feature_class":"P",
    "gn:feature_code":"PPL",
    "gn:name":"Farewell",
    "gn:population":0,
    "gn:timezone":"America/Toronto",
    "iso:country":"CA",
    "name:deu_x_preferred":[
        "Farewell"
    ],
    "name:ita_x_preferred":[
        "Farewell"
    ],
    "name:por_x_preferred":[
        "Farewell"
    ],
    "name:tur_x_preferred":[
        "Elveda"
    ],
    "wof:name":"Farewell",
    "wof:placetype":"locality"
},
  "geometry": {"coordinates":[-80.7225,43.91333],"type":"Point"}
}