{
  "type": "Feature",
  "properties": {
    "gn:admin1_code":"10",
    "gn:admin2_code":"16.0",
    "gn:asciiname":"Texas",
    "gn:country_code":"CA",
    "gn:dem":27,
    "gn:feature_class":"P",
    "gn:feature_code":"PPL",
    "gn:name":"Texas",
    "gn:population":0,
    "gn:timezone":"America/Toronto",
    "iso:country":"CA",
    "wof:name":"Texas",
    "wof:placetype":"locality"
},
  "geometry": {"coordinates":[-73.63265,45.39921],"type":"Point"}
}