{
  "type": "Feature",
  "properties": {
    "gn:admin1_code":"10",
    "gn:admin2_code":"9.0",
    "gn:asciiname":"Lac-Sainte-Anne",
    "gn:country_code":"CA",
    "gn:dem":272,
    "gn:feature_class":"P",
    "gn:feature_code":"PPL",
    "gn:name":"Lac-Sainte-Anne",
    "gn:population":0,
    "gn:timezone":"America/Toronto",
    "iso:country":"CA",
    "wof:name":"Lac-Sainte-Anne",
    "wof:placetype":"locality"
},
  "geometry": {"coordinates":[-67.95166999999999,50.09028],"type":"Point"}
}