{
  "type": "Feature",
  "properties": {
    "gn:admin1_code":"2",
    "gn:asciiname":"Retallack",
    "gn:country_code":"CA",
    "gn:dem":1409,
    "gn:feature_class":"P",
    "gn:feature_code":"PPLL",
    "gn:name":"Retallack",
    "gn:population":0,
    "gn:timezone":"America/Vancouver",
    "iso:country":"CA",
    "wof:name":"Retallack",
    "wof:placetype":"locality"
},
  "geometry": {"coordinates":[-117.13549999999999,50.04987],"type":"Point"}
}