{
  "type": "Feature",
  "properties": {
    "gn:admin1_code":"11.0",
    "gn:asciiname":"Battrum",
    "gn:country_code":"CA",
    "gn:dem":688,
    "gn:feature_class":"P",
    "gn:feature_code":"PPL",
    "gn:name":"Battrum",
    "gn:population":0,
    "gn:timezone":"America/Regina",
    "iso:country":"CA",
    "wof:name":"Battrum",
    "wof:placetype":"locality"
},
  "geometry": {"coordinates":[-108.33403,50.55004],"type":"Point"}
}