{
  "type": "Feature",
  "properties": {
    "gn:admin1_code":"11.0",
    "gn:asciiname":"Druid",
    "gn:country_code":"CA",
    "gn:dem":643,
    "gn:feature_class":"P",
    "gn:feature_code":"PPL",
    "gn:name":"Druid",
    "gn:population":0,
    "gn:timezone":"America/Regina",
    "iso:country":"CA",
    "wof:name":"Druid",
    "wof:placetype":"locality"
},
  "geometry": {"coordinates":[-108.80073,51.80006],"type":"Point"}
}