{
  "type": "Feature",
  "properties": {
    "gn:admin1_code":"1",
    "gn:asciiname":"Halkirk",
    "gn:country_code":"CA",
    "gn:dem":832,
    "gn:feature_class":"P",
    "gn:feature_code":"PPL",
    "gn:name":"Halkirk",
    "gn:population":0,
    "gn:timezone":"America/Edmonton",
    "iso:country":"CA",
    "wof:name":"Halkirk",
    "wof:placetype":"locality"
},
  "geometry": {"coordinates":[-112.15182,52.28344],"type":"Point"}
}