{
  "type": "Feature",
  "properties": {
    "gn:admin1_code":"8.0",
    "gn:asciiname":"Devonshire",
    "gn:country_code":"CA",
    "gn:dem":292,
    "gn:feature_class":"P",
    "gn:feature_code":"PPL",
    "gn:name":"Devonshire",
    "gn:population":0,
    "gn:timezone":"America/Toronto",
    "iso:country":"CA",
    "wof:name":"Devonshire",
    "wof:placetype":"locality"
},
  "geometry": {"coordinates":[-80.83308000000002,48.81688],"type":"Point"}
}