{
  "type": "Feature",
  "properties": {
    "gn:admin1_code":"8.0",
    "gn:asciiname":"Devonshire",
    "gn:country_code":"CA",
    "gn:dem":292,
    "gn:feature_class":"P",
    "gn:feature_code":"PPL",
    "gn:name":"Devonshire",
    "gn:population":0,
    "gn:timezone":"America/Toronto",
    "iso:country":"CA",
    "name:ara_x_preferred":[
        "\u062f\u064a\u0641\u0648\u0646\u0634\u064a\u0631"
    ],
    "name:ben_x_preferred":[
        "\u09a1\u09c7\u09ad\u09a8\u09b6\u09be\u09df\u09be\u09b0"
    ],
    "name:deu_x_preferred":[
        "Devonshire"
    ],
    "name:ell_x_preferred":[
        "\u039d\u03c4\u03ad\u03b2\u03bf\u03bd\u03c3\u03b9\u03c1"
    ],
    "name:eng_x_preferred":[
        "Devonshire"
    ],
    "name:fas_x_preferred":[
        "\u062f\u0648\u0648\u0646 \u0634\u0627\u06cc\u0631"
    ],
    "name:fra_x_preferred":[
        "Devon"
    ],
    "name:heb_x_preferred":[
        "\u05d3\u05d1\u05d5\u05e0\u05e9\u05d9\u05d9\u05e8"
    ],
    "name:hin_x_preferred":[
        "\u0921\u0947\u0935\u094b\u0928\u0936\u093e\u092f\u0930"
    ],
    "name:hun_x_preferred":[
        "Devonshire"
    ],
    "name:ind_x_preferred":[
        "Devonshire"
    ],
    "name:ita_x_preferred":[
        "Devonshire"
    ],
    "name:jpn_x_preferred":[
        "\u30c7\u30f4\u30a9\u30f3\u5dde"
    ],
    "name:kor_x_preferred":[
        "\ub370\ubcf8\uc154"
    ],
    "name:nld_x_preferred":[
        "Devon"
    ],
    "name:pol_x_preferred":[
        "Devonshire"
    ],
    "name:por_x_preferred":[
        "Devonshire"
    ],
    "name:rus_x_preferred":[
        "\u0414\u0435\u0432\u043e\u043d\u0448\u0438\u0440"
    ],
    "name:spa_x_preferred":[
        "Devon"
    ],
    "name:swe_x_preferred":[
        "Devonshire"
    ],
    "name:tur_x_preferred":[
        "Devonshire"
    ],
    "name:ukr_x_preferred":[
        "\u0414\u0435\u0432\u043e\u043d\u0448\u0438\u0440"
    ],
    "name:urd_x_preferred":[
        "\u0688\u06cc\u0648\u0646\u0634\u0627\u0626\u0631"
    ],
    "name:vie_x_preferred":[
        "Devonshire"
    ],
    "name:zho_cn_x_preferred":[
        "\u5fb7\u6587\u90e1"
    ],
    "name:zho_tw_x_preferred":[
        "\u5fb7\u6587\u90e1"
    ],
    "wof:name":"Devonshire",
    "wof:placetype":"locality"
},
  "geometry": {"coordinates":[-80.83308,48.81688],"type":"Point"}
}