{
  "type": "Feature",
  "properties": {
    "gn:elevation":175,
    "iso:country":"CA",
    "name:cat_x_preferred":[
        "La Salle"
    ],
    "name:ceb_x_preferred":[
        "La Salle"
    ],
    "name:deu_x_preferred":[
        "La Salle"
    ],
    "name:eng_x_preferred":[
        "La Salle"
    ],
    "name:fra_x_preferred":[
        "La Salle"
    ],
    "name:jpn_x_preferred":[
        "\u30e9\u30b5\u30fc\u30eb"
    ],
    "name:lmo_x_preferred":[
        "La Salle"
    ],
    "name:nds_x_preferred":[
        "La Salle"
    ],
    "name:nld_x_preferred":[
        "La Salle"
    ],
    "name:pms_x_preferred":[
        "La Salle"
    ],
    "name:pol_x_preferred":[
        "La Salle"
    ],
    "name:por_x_preferred":[
        "La Salle"
    ],
    "name:rus_x_preferred":[
        "\u041b\u0430 \u0421\u0430\u043b\u043b\u044c"
    ],
    "name:slk_x_preferred":[
        "La Salle"
    ],
    "name:spa_x_preferred":[
        "La Salle"
    ],
    "name:srp_x_preferred":[
        "\u041b\u0430 \u0421\u0430\u043b"
    ],
    "name:swe_x_preferred":[
        "La Salle"
    ],
    "name:ukr_x_preferred":[
        "\u041b\u0430-\u0421\u0430\u043b\u043b"
    ],
    "name:und_x_variant":[
        "Lasalle"
    ],
    "name:vol_x_preferred":[
        "La Salle"
    ],
    "qs:gn_adm0_cc":"CA",
    "qs:gn_fcode":"PPL",
    "qs:gn_local":5911592,
    "qs:gn_nam_loc":"north ridge",
    "qs:gn_namadm1":"NY",
    "qs:gn_name":"La Salle",
    "qs:local_max":999,
    "qs:local_sum":999,
    "qs:localhoods":1,
    "qs:name":"La Salle",
    "qs:name_adm0":"Canada",
    "qs:name_adm1":"Ontario",
    "qs:name_adm2":"Halton",
    "qs:name_local":"East Burlington",
    "qs:photo_max":347,
    "qs:photo_sum":999,
    "qs:placetype":"Suburb",
    "qs:quad_count":29,
    "qs:woe_adm0":23424775,
    "qs:woe_adm1":2344922,
    "qs:woe_adm2":29375078,
    "qs:woe_funk":"Grouping neighborhood",
    "qs:woe_lau":0,
    "qs:woe_local":55999471,
    "qs:woe_ver":"7.10.0",
    "wof:lang":[
        "eng"
    ],
    "wof:name":"La Salle",
    "wof:placetype":"neighbourhood"
},
  "geometry": {"coordinates":[-79.84352699999999,43.30431],"type":"Point"}
}