{
  "type": "Feature",
  "properties": {
    "gn:admin1_code":"11",
    "gn:asciiname":"Melaval",
    "gn:country_code":"CA",
    "gn:dem":744,
    "gn:feature_class":"P",
    "gn:feature_code":"PPL",
    "gn:name":"Melaval",
    "gn:population":0,
    "gn:timezone":"America/Regina",
    "iso:country":"CA",
    "wof:name":"Melaval",
    "wof:placetype":"locality"
},
  "geometry": {"coordinates":[-106.45059999999999,49.68336],"type":"Point"}
}