{
  "type": "Feature",
  "properties": {
    "gn:admin1_code":"10",
    "gn:admin2_code":"8.0",
    "gn:admin3_code":"89050.0",
    "gn:asciiname":"Uniacke",
    "gn:country_code":"CA",
    "gn:dem":323,
    "gn:feature_class":"P",
    "gn:feature_code":"PPL",
    "gn:name":"Uniacke",
    "gn:population":0,
    "gn:timezone":"America/Toronto",
    "iso:country":"CA",
    "wof:name":"Uniacke",
    "wof:placetype":"locality"
},
  "geometry": {"coordinates":[-77.51618000000001,48.41689],"type":"Point"}
}