{
  "type": "Feature",
  "properties": {
    "gn:admin1_code":"2.0",
    "gn:asciiname":"Canford",
    "gn:country_code":"CA",
    "gn:dem":785,
    "gn:feature_class":"P",
    "gn:feature_code":"PPLL",
    "gn:name":"Canford",
    "gn:population":0,
    "gn:timezone":"America/Vancouver",
    "iso:country":"CA",
    "wof:name":"Canford",
    "wof:placetype":"locality"
},
  "geometry": {"coordinates":[-121.00252,50.14975],"type":"Point"}
}