{
  "type": "Feature",
  "properties": {
    "gn:admin1_code":"8",
    "gn:asciiname":"Nestleton Station",
    "gn:country_code":"CA",
    "gn:dem":301,
    "gn:feature_class":"P",
    "gn:feature_code":"PPL",
    "gn:name":"Nestleton Station",
    "gn:population":0,
    "gn:timezone":"America/Toronto",
    "iso:country":"CA",
    "wof:name":"Nestleton Station",
    "wof:placetype":"locality"
},
  "geometry": {"coordinates":[-78.79326,44.14083],"type":"Point"}
}