{
  "type": "Feature",
  "properties": {
    "gn:admin1_code":"11",
    "gn:asciiname":"Glenelm Park",
    "gn:country_code":"CA",
    "gn:dem":579,
    "gn:feature_class":"P",
    "gn:feature_code":"PPL",
    "gn:name":"Glenelm Park",
    "gn:population":0,
    "gn:timezone":"America/Regina",
    "iso:country":"CA",
    "wof:name":"Glenelm Park",
    "wof:placetype":"locality"
},
  "geometry": {"coordinates":[-104.56777,50.45087],"type":"Point"}
}