{
  "type": "Feature",
  "properties": {
    "gn:gn_country":"CA",
    "gn:gn_fcode":"PPL",
    "gn:gn_pop":0,
    "iso:country":"CA",
    "name:baq_x_preferred":[
        "Sainte-Anne-de-Sorel"
    ],
    "name:dut_x_preferred":[
        "Sainte-Anne-de-Sorel"
    ],
    "name:eng_x_preferred":[
        "Sainte-Anne-de-Sorel"
    ],
    "name:fre_x_preferred":[
        "Sainte-Anne-de-Sorel"
    ],
    "name:ger_x_preferred":[
        "Sainte-Anne-de-Sorel"
    ],
    "name:per_x_preferred":[
        "\u0633\u0646\u062a-\u0622\u0646-\u062f\u0648-\u0633\u0648\u0631\u0644\u060c \u06a9\u0628\u06a9"
    ],
    "name:spa_x_preferred":[
        "Sainte-Anne-de-Sorel"
    ],
    "name:swe_x_preferred":[
        "Sainte-Anne-de-Sorel"
    ],
    "name:urd_x_preferred":[
        "\u0633\u06cc\u0646-\u0627\u06cc\u0646-\u062f\u06d2-\u0633\u0648\u0631\u0644\u060c \u06a9\u06cc\u0648\u0628\u06a9"
    ],
    "qs_pg:aaroncc":"CA",
    "qs_pg:gn_country":"CA",
    "qs_pg:gn_fcode":"PPL",
    "qs_pg:gn_pop":0,
    "qs_pg:name":"Ste.-Anne-de-Sorel",
    "qs_pg:name_adm0":"Canada",
    "qs_pg:name_adm1":"Qu\u00e9bec",
    "qs_pg:photos":43,
    "qs_pg:photos_1k":9,
    "qs_pg:photos_9k":1,
    "qs_pg:photos_9r":2,
    "qs_pg:photos_all":43,
    "qs_pg:photos_sr":2,
    "qs_pg:pop_sr":0,
    "qs_pg:qs_pg_placetype":"locality",
    "qs_pg:qs_pg_placetype_gp":"Town",
    "qs_pg:woe_adm0":23424775,
    "woe:adm0_id":23424775,
    "woe:name_adm0":"Canada",
    "woe:name_adm1":"Qu\u00e9bec",
    "woe:placetype":"Town",
    "wof:name":"Ste.-Anne-de-Sorel",
    "wof:placetype":"locality"
},
  "geometry": {"coordinates":[-73.07736,46.04714],"type":"Point"}
}