{
  "type": "Feature",
  "properties": {
    "gn:admin1_code":"11",
    "gn:asciiname":"Trossachs",
    "gn:country_code":"CA",
    "gn:dem":605,
    "gn:feature_class":"P",
    "gn:feature_code":"PPLL",
    "gn:name":"Trossachs",
    "gn:population":0,
    "gn:timezone":"America/Regina",
    "iso:country":"CA",
    "wof:name":"Trossachs",
    "wof:placetype":"locality"
},
  "geometry": {"coordinates":[-104.21778999999999,49.63336],"type":"Point"}
}