{
  "type": "Feature",
  "properties": {
    "gn:admin1_code":"1",
    "gn:asciiname":"Tiger Lily",
    "gn:country_code":"CA",
    "gn:dem":673,
    "gn:feature_class":"P",
    "gn:feature_code":"PPLL",
    "gn:name":"Tiger Lily",
    "gn:population":0,
    "gn:timezone":"America/Edmonton",
    "iso:country":"CA",
    "wof:name":"Tiger Lily",
    "wof:placetype":"locality"
},
  "geometry": {"coordinates":[-114.76886,54.18344],"type":"Point"}
}