{
  "type": "Feature",
  "properties": {
    "gn:admin1_code":"3.0",
    "gn:asciiname":"Curtis",
    "gn:country_code":"CA",
    "gn:dem":258,
    "gn:feature_class":"P",
    "gn:feature_code":"PPLL",
    "gn:name":"Curtis",
    "gn:population":0,
    "gn:timezone":"America/Winnipeg",
    "iso:country":"CA",
    "wof:name":"Curtis",
    "wof:placetype":"locality"
},
  "geometry": {"coordinates":[-98.14632,49.94142],"type":"Point"}
}