{
  "type": "Feature",
  "properties": {
    "gn:admin1_code":"9.0",
    "gn:asciiname":"Bungay",
    "gn:country_code":"CA",
    "gn:dem":65,
    "gn:feature_class":"P",
    "gn:feature_code":"PPLL",
    "gn:name":"Bungay",
    "gn:population":0,
    "gn:timezone":"America/Halifax",
    "iso:country":"CA",
    "name:azb_x_preferred":[
        "\u0628\u0627\u0646\u0642\u06cc"
    ],
    "name:ceb_x_preferred":[
        "Bungay"
    ],
    "name:cym_x_preferred":[
        "Bungay"
    ],
    "name:deu_x_preferred":[
        "Bungay"
    ],
    "name:epo_x_preferred":[
        "Bungay"
    ],
    "name:fas_x_preferred":[
        "\u0628\u0627\u0646\u06af\u06cc"
    ],
    "name:fra_x_preferred":[
        "Bungay"
    ],
    "name:gle_x_preferred":[
        "Bungay"
    ],
    "name:ita_x_preferred":[
        "Bungay"
    ],
    "name:nld_x_preferred":[
        "Bungay"
    ],
    "name:nno_x_preferred":[
        "Bungay"
    ],
    "name:pol_x_preferred":[
        "Bungay"
    ],
    "name:ron_x_preferred":[
        "Bungay"
    ],
    "name:rus_x_preferred":[
        "\u0411\u0430\u043d\u0433\u0438"
    ],
    "name:spa_x_preferred":[
        "Bungay"
    ],
    "name:swe_x_preferred":[
        "Bungay"
    ],
    "name:vol_x_preferred":[
        "Bungay"
    ],
    "wof:name":"Bungay",
    "wof:placetype":"locality"
},
  "geometry": {"coordinates":[-63.3154,46.36682],"type":"Point"}
}