{
  "type": "Feature",
  "properties": {
    "gn:admin1_code":"8.0",
    "gn:asciiname":"Advance",
    "gn:country_code":"CA",
    "gn:dem":233,
    "gn:feature_class":"P",
    "gn:feature_code":"PPL",
    "gn:name":"Advance",
    "gn:population":0,
    "gn:timezone":"America/Toronto",
    "iso:country":"CA",
    "name:ceb_x_preferred":[
        "Advance"
    ],
    "name:deu_x_preferred":[
        "Advance"
    ],
    "name:fra_x_preferred":[
        "Advance"
    ],
    "name:ita_x_preferred":[
        "Advance"
    ],
    "name:jpn_x_preferred":[
        "\u30a2\u30c9\u30f4\u30a1\u30f3\u30b9"
    ],
    "name:kor_x_preferred":[
        "\uc5b4\ub4dc\ubc34\uc2a4"
    ],
    "name:nld_x_preferred":[
        "Advance"
    ],
    "name:pol_x_preferred":[
        "Advance"
    ],
    "name:por_x_preferred":[
        "Advance"
    ],
    "name:slk_x_preferred":[
        "Advance"
    ],
    "name:srp_x_preferred":[
        "\u0410\u0434\u0432\u0430\u043d\u0441"
    ],
    "name:ukr_x_preferred":[
        "\u0410\u0434\u0432\u0430\u043d\u0441"
    ],
    "name:urd_x_preferred":[
        "\u0627\u06cc\u0688\u0648\u0627\u0646\u0633"
    ],
    "name:vol_x_preferred":[
        "Advance"
    ],
    "wof:name":"Advance",
    "wof:placetype":"locality"
},
  "geometry": {"coordinates":[-82.42901999999999,45.86849],"type":"Point"}
}