{
  "type": "Feature",
  "properties": {
    "gn:admin1_code":"14",
    "gn:asciiname":"Wager Bay",
    "gn:country_code":"CA",
    "gn:dem":95,
    "gn:feature_class":"P",
    "gn:feature_code":"PPLL",
    "gn:name":"Wager Bay",
    "gn:population":0,
    "gn:timezone":"America/Rankin_Inlet",
    "iso:country":"CA",
    "name:ara_x_preferred":[
        "\u062e\u0644\u064a\u062c \u0648\u064a\u062c\u0631"
    ],
    "name:ben_x_preferred":[
        "\u0993\u09df\u09c7\u099c\u09be\u09b0 \u09ac\u09c7"
    ],
    "name:ceb_x_preferred":[
        "Wager Bay"
    ],
    "name:deu_x_preferred":[
        "Wager Bay"
    ],
    "name:ell_x_preferred":[
        "\u039a\u03cc\u03bb\u03c0\u03bf\u03c2 \u039f\u03c5\u03ac\u03b3\u03ba\u03b5\u03c1"
    ],
    "name:fas_x_preferred":[
        "\u062e\u0644\u06cc\u062c \u0648\u06cc\u06af\u0631"
    ],
    "name:fra_x_preferred":[
        "Baie Wager"
    ],
    "name:heb_x_preferred":[
        "\u05de\u05e4\u05e8\u05e5 \u05d5\u05d5\u05d0\u05d2\u05e8"
    ],
    "name:hin_x_preferred":[
        "\u0935\u0947\u091c\u0930 \u092c\u0947 "
    ],
    "name:hun_x_preferred":[
        "Wager-\u00f6b\u00f6l"
    ],
    "name:ind_x_preferred":[
        "Teluk Wager"
    ],
    "name:ita_x_preferred":[
        "Wager Bay"
    ],
    "name:kor_x_preferred":[
        "\uc6e8\uc774\uc800 \ubca0\uc774"
    ],
    "name:pol_x_preferred":[
        "Wager Bay"
    ],
    "name:por_x_preferred":[
        "Ba\u00eda de Wager"
    ],
    "name:rus_x_preferred":[
        "\u0431\u0443\u0445\u0442\u0430 \u0423\u044d\u0439\u0434\u0436\u0435\u0440"
    ],
    "name:spa_x_preferred":[
        "Bah\u00eda Wager"
    ],
    "name:swe_x_preferred":[
        "Wager Bay"
    ],
    "name:tur_x_preferred":[
        "Wager Koyu"
    ],
    "name:ukr_x_preferred":[
        "\u0412\u0430\u0433\u0435\u0440-\u0411\u0435\u0439"
    ],
    "name:urd_x_preferred":[
        "\u0648\u06cc\u062c\u0631 \u0628\u06d2"
    ],
    "name:vie_x_preferred":[
        "V\u1ecbnh Wager"
    ],
    "name:zho_cn_x_preferred":[
        "\u74e6\u683c\u6e7e"
    ],
    "name:zho_tw_x_preferred":[
        "\u7dad\u6770\u7063"
    ],
    "wof:name":"Wager Bay",
    "wof:placetype":"locality"
},
  "geometry": {"coordinates":[-90.81659000000001,65.9342],"type":"Point"}
}