{
  "type": "Feature",
  "properties": {
    "gn:admin1_code":"14",
    "gn:asciiname":"Wager Bay",
    "gn:country_code":"CA",
    "gn:dem":95,
    "gn:feature_class":"P",
    "gn:feature_code":"PPLL",
    "gn:name":"Wager Bay",
    "gn:population":0,
    "gn:timezone":"America/Rankin_Inlet",
    "iso:country":"CA",
    "wof:name":"Wager Bay",
    "wof:placetype":"locality"
},
  "geometry": {"coordinates":[-90.81659000000001,65.9342],"type":"Point"}
}