{
  "type": "Feature",
  "properties": {
    "gn:admin1_code":"3",
    "gn:asciiname":"Molson",
    "gn:country_code":"CA",
    "gn:dem":267,
    "gn:feature_class":"P",
    "gn:feature_code":"PPL",
    "gn:name":"Molson",
    "gn:population":0,
    "gn:timezone":"America/Winnipeg",
    "iso:country":"CA",
    "wof:name":"Molson",
    "wof:placetype":"locality"
},
  "geometry": {"coordinates":[-96.30837,50.02439],"type":"Point"}
}