{
  "type": "Feature",
  "properties": {
    "gn:admin1_code":"8.0",
    "gn:asciiname":"Wilcox Lake",
    "gn:country_code":"CA",
    "gn:dem":476,
    "gn:feature_class":"P",
    "gn:feature_code":"PPLL",
    "gn:name":"Wilcox Lake",
    "gn:population":0,
    "gn:timezone":"America/Toronto",
    "iso:country":"CA",
    "wof:name":"Wilcox Lake",
    "wof:placetype":"locality"
},
  "geometry": {"coordinates":[-80.5497,44.2168],"type":"Point"}
}