{
  "type": "Feature",
  "properties": {
    "gn:admin1_code":"2",
    "gn:asciiname":"Longworth",
    "gn:country_code":"CA",
    "gn:dem":660,
    "gn:feature_class":"P",
    "gn:feature_code":"PPLL",
    "gn:name":"Longworth",
    "gn:population":0,
    "gn:timezone":"America/Vancouver",
    "iso:country":"CA",
    "wof:name":"Longworth",
    "wof:placetype":"locality"
},
  "geometry": {"coordinates":[-121.46956000000002,53.91664],"type":"Point"}
}