{
  "type": "Feature",
  "properties": {
    "gn:admin1_code":"8",
    "gn:asciiname":"Sunny Slope",
    "gn:country_code":"CA",
    "gn:dem":276,
    "gn:feature_class":"P",
    "gn:feature_code":"PPL",
    "gn:name":"Sunny Slope",
    "gn:population":0,
    "gn:timezone":"America/Toronto",
    "iso:country":"CA",
    "wof:name":"Sunny Slope",
    "wof:placetype":"locality"
},
  "geometry": {"coordinates":[-79.88611,45.61694],"type":"Point"}
}