{
  "type": "Feature",
  "properties": {
    "gn:admin1_code":"4",
    "gn:asciiname":"Roach",
    "gn:country_code":"CA",
    "gn:dem":149,
    "gn:feature_class":"P",
    "gn:feature_code":"PPLL",
    "gn:name":"Roach",
    "gn:population":0,
    "gn:timezone":"America/Moncton",
    "iso:country":"CA",
    "name:ces_x_preferred":[
        "Roach"
    ],
    "name:deu_x_preferred":[
        "Roach"
    ],
    "name:fra_x_preferred":[
        "Roach"
    ],
    "name:ita_x_preferred":[
        "Roach"
    ],
    "name:jpn_x_preferred":[
        "\u30ed\u30fc\u30c1"
    ],
    "name:nld_x_preferred":[
        "Roach"
    ],
    "name:rus_x_preferred":[
        "\u0420\u043e\u0443\u0447"
    ],
    "name:ukr_x_preferred":[
        "\u0420\u043e\u0443\u0447"
    ],
    "wof:name":"Roach",
    "wof:placetype":"locality"
},
  "geometry": {"coordinates":[-66.93218,45.66682],"type":"Point"}
}