{
  "type": "Feature",
  "properties": {
    "gn:admin1_code":"7",
    "gn:asciiname":"Meadow Springs",
    "gn:country_code":"CA",
    "gn:dem":173,
    "gn:feature_class":"P",
    "gn:feature_code":"PPL",
    "gn:name":"Meadow Springs",
    "gn:population":0,
    "gn:timezone":"America/Halifax",
    "iso:country":"CA",
    "wof:name":"Meadow Springs",
    "wof:placetype":"locality"
},
  "geometry": {"coordinates":[-62.37751,45.50523],"type":"Point"}
}