{
  "type": "Feature",
  "properties": {
    "gn:admin1_code":"8",
    "gn:asciiname":"Orient Bay",
    "gn:country_code":"CA",
    "gn:dem":258,
    "gn:feature_class":"P",
    "gn:feature_code":"PPL",
    "gn:name":"Orient Bay",
    "gn:population":0,
    "gn:timezone":"America/Toronto",
    "iso:country":"CA",
    "wof:name":"Orient Bay",
    "wof:placetype":"locality"
},
  "geometry": {"coordinates":[-88.13332,49.36681],"type":"Point"}
}