{
  "type": "Feature",
  "properties": {
    "gn:admin1_code":"9",
    "gn:asciiname":"St. Ann",
    "gn:country_code":"CA",
    "gn:dem":69,
    "gn:feature_class":"P",
    "gn:feature_code":"PPLL",
    "gn:name":"St. Ann",
    "gn:population":0,
    "gn:timezone":"America/Halifax",
    "iso:country":"CA",
    "wof:name":"St. Ann",
    "wof:placetype":"locality"
},
  "geometry": {"coordinates":[-63.3987,46.43342],"type":"Point"}
}