{
  "type": "Feature",
  "properties": {
    "gn:admin1_code":"8",
    "gn:asciiname":"Enniskerry",
    "gn:country_code":"CA",
    "gn:dem":90,
    "gn:feature_class":"P",
    "gn:feature_code":"PPLL",
    "gn:name":"Enniskerry",
    "gn:population":0,
    "gn:timezone":"America/Toronto",
    "iso:country":"CA",
    "name:ceb_x_preferred":[
        "Enniskerry"
    ],
    "name:deu_x_preferred":[
        "Enniskerry"
    ],
    "name:eus_x_preferred":[
        "Enniskerry"
    ],
    "name:fra_x_preferred":[
        "Enniskerry"
    ],
    "name:ita_x_preferred":[
        "Enniskerry"
    ],
    "name:jpn_x_preferred":[
        "\u30a8\u30cb\u30b9\u30b1\u30ea\u30fc"
    ],
    "name:nld_x_preferred":[
        "Enniskerry"
    ],
    "name:nor_x_preferred":[
        "Enniskerry"
    ],
    "name:pol_x_preferred":[
        "Enniskerry"
    ],
    "name:por_x_preferred":[
        "Enniskerry"
    ],
    "name:rus_x_preferred":[
        "\u042d\u043d\u043d\u0438\u0441\u043a\u0435\u0440\u0440\u0438"
    ],
    "name:spa_x_preferred":[
        "Enniskerry"
    ],
    "name:swe_x_preferred":[
        "Enniskerry"
    ],
    "name:urd_x_preferred":[
        "\u0627\u0646\u06cc\u0633\u06a9\u06cc\u0631\u06cc"
    ],
    "wof:name":"Enniskerry",
    "wof:placetype":"locality"
},
  "geometry": {"coordinates":[-75.56824,45.2023],"type":"Point"}
}