{
  "type": "Feature",
  "properties": {
    "gn:country":"CA",
    "gn:fcode":"PPL",
    "gn:pop":0,
    "iso:country":"CA",
    "name:ceb_x_preferred":[
        "Port Rexton"
    ],
    "name:eng_x_preferred":[
        "Port Rexton"
    ],
    "name:fra_x_preferred":[
        "Port Rexton"
    ],
    "name:nld_x_preferred":[
        "Port Rexton"
    ],
    "name:swe_x_preferred":[
        "Port Rexton"
    ],
    "qs:name":"Port Rexton",
    "qs:name_adm0":"Canada",
    "qs:name_adm1":"Newfoundland and Labrador",
    "qs:photos":201,
    "qs:photos_1k":41,
    "qs:photos_9k":1,
    "qs:photos_9r":4,
    "qs:photos_all":201,
    "qs:photos_sr":4,
    "qs:placetype":"Town",
    "qs:pop_sr":"0",
    "wd:wordcount":126,
    "wof:name":"Port Rexton",
    "wof:placetype":"locality",
    "wof:population":0
},
  "geometry": {"coordinates":[-53.33137,48.39019],"type":"Point"}
}