{
  "type": "Feature",
  "properties": {
    "gn:admin1_code":"8",
    "gn:asciiname":"Theresa",
    "gn:country_code":"CA",
    "gn:dem":329,
    "gn:feature_class":"P",
    "gn:feature_code":"PPL",
    "gn:name":"Theresa",
    "gn:population":0,
    "gn:timezone":"America/Toronto",
    "iso:country":"CA",
    "wof:name":"Theresa",
    "wof:placetype":"locality"
},
  "geometry": {"coordinates":[-86.52006,49.69872],"type":"Point"}
}