{
  "type": "Feature",
  "properties": {
    "gn:admin1_code":"8.0",
    "gn:asciiname":"Adamsville",
    "gn:country_code":"CA",
    "gn:dem":224,
    "gn:feature_class":"P",
    "gn:feature_code":"PPL",
    "gn:name":"Adamsville",
    "gn:population":0,
    "gn:timezone":"America/Toronto",
    "iso:country":"CA",
    "wof:name":"Adamsville",
    "wof:placetype":"locality"
},
  "geometry": {"coordinates":[-81.16360999999998,44.85986],"type":"Point"}
}