{
  "type": "Feature",
  "properties": {
    "gn:admin1_code":"8.0",
    "gn:asciiname":"Adamsville",
    "gn:country_code":"CA",
    "gn:dem":224,
    "gn:feature_class":"P",
    "gn:feature_code":"PPL",
    "gn:name":"Adamsville",
    "gn:population":0,
    "gn:timezone":"America/Toronto",
    "iso:country":"CA",
    "name:azb_x_preferred":[
        "\u0622\u062f\u0627\u0645\u0632\u0648\u06cc\u0644"
    ],
    "name:cat_x_preferred":[
        "Adamsville"
    ],
    "name:ceb_x_preferred":[
        "Adamsville"
    ],
    "name:ces_x_preferred":[
        "Adamsville"
    ],
    "name:deu_x_preferred":[
        "Adamsville"
    ],
    "name:fra_x_preferred":[
        "Adamsville"
    ],
    "name:ido_x_preferred":[
        "Adamsville"
    ],
    "name:ita_x_preferred":[
        "Adamsville"
    ],
    "name:nld_x_preferred":[
        "Adamsville"
    ],
    "name:pol_x_preferred":[
        "Adamsville"
    ],
    "name:por_x_preferred":[
        "Adamsville"
    ],
    "name:slv_x_preferred":[
        "Adamsville"
    ],
    "name:spa_x_preferred":[
        "Adamsville"
    ],
    "name:srp_x_preferred":[
        "\u0410\u0434\u0430\u043c\u0441\u0432\u0438\u043b"
    ],
    "name:vol_x_preferred":[
        "Adamsville"
    ],
    "wof:name":"Adamsville",
    "wof:placetype":"locality"
},
  "geometry": {"coordinates":[-81.16360999999998,44.85986],"type":"Point"}
}