{
  "type": "Feature",
  "properties": {
    "iso:country":"CA",
    "name:eng_x_preferred":[
        "Centre-Ville"
    ],
    "name:fra_x_preferred":[
        "Centre-Ville"
    ],
    "qs:gn_adm0_cc":"CA",
    "qs:gn_local":6173508,
    "qs:gn_nam_loc":"varennes",
    "qs:gn_namadm1":"10",
    "qs:local_max":87,
    "qs:local_sum":87,
    "qs:localhoods":1,
    "qs:name":"Centre-Ville",
    "qs:name_adm0":"Canada",
    "qs:name_adm1":"Qu\u00e9bec",
    "qs:name_adm2":"Lajemmerais",
    "qs:name_local":"Varennes",
    "qs:photo_max":22,
    "qs:photo_sum":87,
    "qs:placetype":"Suburb",
    "qs:quad_count":13,
    "qs:woe_adm0":23424775,
    "qs:woe_adm1":2344924,
    "qs:woe_adm2":29375052,
    "qs:woe_lau":0,
    "qs:woe_local":1858,
    "qs:woe_ver":"7.10.0",
    "wof:lang":[
        "fre"
    ],
    "wof:name":"Centre-Ville",
    "wof:placetype":"neighbourhood"
},
  "geometry": {"coordinates":[-73.437744,45.682049],"type":"Point"}
}