{
  "type": "Feature",
  "properties": {
    "gn:admin1_code":"8.0",
    "gn:asciiname":"Port Lands",
    "gn:country_code":"CA",
    "gn:dem":75,
    "gn:feature_class":"P",
    "gn:feature_code":"PPL",
    "gn:name":"Port Lands",
    "gn:population":0,
    "gn:timezone":"America/Toronto",
    "iso:country":"CA",
    "name:fra_x_preferred":[
        "Port Lands"
    ],
    "name:urd_x_preferred":[
        "\u067e\u0648\u0631\u0679 \u0644\u06cc\u0646\u0688\u0632"
    ],
    "wof:name":"Port Lands",
    "wof:placetype":"locality"
},
  "geometry": {"coordinates":[-79.34223,43.64732],"type":"Point"}
}