{
  "type": "Feature",
  "properties": {
    "gn:admin1_code":"8.0",
    "gn:asciiname":"Port Lands",
    "gn:country_code":"CA",
    "gn:dem":75,
    "gn:feature_class":"P",
    "gn:feature_code":"PPL",
    "gn:name":"Port Lands",
    "gn:population":0,
    "gn:timezone":"America/Toronto",
    "iso:country":"CA",
    "wof:name":"Port Lands",
    "wof:placetype":"locality"
},
  "geometry": {"coordinates":[-79.34223,43.64732],"type":"Point"}
}