{
  "type": "Feature",
  "properties": {
    "gn:admin1_code":"10.0",
    "gn:admin2_code":"08",
    "gn:admin3_code":"86042.0",
    "gn:asciiname":"Arntfield",
    "gn:country_code":"CA",
    "gn:dem":282,
    "gn:feature_class":"P",
    "gn:feature_code":"PPL",
    "gn:name":"Arntfield",
    "gn:population":0,
    "gn:timezone":"America/Toronto",
    "iso:country":"CA",
    "wof:name":"Arntfield",
    "wof:placetype":"locality"
},
  "geometry": {"coordinates":[-79.25524,48.19737],"type":"Point"}
}