{
  "type": "Feature",
  "properties": {
    "iso:country":"CA",
    "name:eng_x_preferred":[
        "Centreville Chicopee"
    ],
    "qs:gn_adm0_cc":"CA",
    "qs:gn_local":5992996,
    "qs:gn_nam_loc":"kitchener",
    "qs:gn_namadm1":"08",
    "qs:local_max":6042,
    "qs:local_sum":26102,
    "qs:localhoods":44,
    "qs:name":"Centreville Chicopee",
    "qs:name_adm0":"Canada",
    "qs:name_adm1":"Ontario",
    "qs:name_adm2":"Waterloo",
    "qs:name_local":"Kitchener",
    "qs:photo_max":181,
    "qs:photo_sum":458,
    "qs:placetype":"Suburb",
    "qs:quad_count":35,
    "qs:woe_adm0":23424775,
    "qs:woe_adm1":2344922,
    "qs:woe_adm2":29375060,
    "qs:woe_lau":0,
    "qs:woe_local":4051,
    "qs:woe_ver":"7.10.0",
    "wof:lang":[
        "eng"
    ],
    "wof:name":"Centreville Chicopee",
    "wof:placetype":"neighbourhood"
},
  "geometry": {"coordinates":[-80.414095,43.429663],"type":"Point"}
}