{
  "type": "Feature",
  "properties": {
    "gn:admin1_code":"12.0",
    "gn:asciiname":"Coffee Creek",
    "gn:country_code":"CA",
    "gn:dem":429,
    "gn:feature_class":"P",
    "gn:feature_code":"PPLL",
    "gn:name":"Coffee Creek",
    "gn:population":0,
    "gn:timezone":"America/Whitehorse",
    "iso:country":"CA",
    "name:ceb_x_preferred":[
        "Coffee Creek"
    ],
    "name:swe_x_preferred":[
        "Coffee Creek"
    ],
    "wof:name":"Coffee Creek",
    "wof:placetype":"locality"
},
  "geometry": {"coordinates":[-139.08743999999999,62.91611999999999],"type":"Point"}
}