{
  "type": "Feature",
  "properties": {
    "gn:admin1_code":"2",
    "gn:admin2_code":"5924.0",
    "gn:asciiname":"Nuchatlitz",
    "gn:country_code":"CA",
    "gn:dem":8,
    "gn:feature_class":"P",
    "gn:feature_code":"PPL",
    "gn:name":"Nuchatlitz",
    "gn:population":0,
    "gn:timezone":"America/Vancouver",
    "iso:country":"CA",
    "wof:name":"Nuchatlitz",
    "wof:placetype":"locality"
},
  "geometry": {"coordinates":[-126.96434000000001,49.80625],"type":"Point"}
}