{
  "type": "Feature",
  "properties": {
    "gn:admin1_code":"4.0",
    "gn:asciiname":"Chockpish",
    "gn:country_code":"CA",
    "gn:dem":9,
    "gn:feature_class":"P",
    "gn:feature_code":"PPL",
    "gn:name":"Chockpish",
    "gn:population":0,
    "gn:timezone":"America/Moncton",
    "iso:country":"CA",
    "wof:name":"Chockpish",
    "wof:placetype":"locality"
},
  "geometry": {"coordinates":[-64.73514,46.57171],"type":"Point"}
}