{
  "type": "Feature",
  "properties": {
    "gn:admin1_code":"4.0",
    "gn:asciiname":"Days Landing",
    "gn:country_code":"CA",
    "gn:dem":0,
    "gn:feature_class":"P",
    "gn:feature_code":"PPLL",
    "gn:name":"Days Landing",
    "gn:population":0,
    "gn:timezone":"America/Moncton",
    "iso:country":"CA",
    "wof:name":"Days Landing",
    "wof:placetype":"locality"
},
  "geometry": {"coordinates":[-66.21554999999999,45.36685],"type":"Point"}
}