{
  "type": "Feature",
  "properties": {
    "gn:admin1_code":"4",
    "gn:asciiname":"Johnson's Mills",
    "gn:country_code":"CA",
    "gn:dem":27,
    "gn:feature_class":"P",
    "gn:feature_code":"PPL",
    "gn:name":"Johnson's Mills",
    "gn:population":0,
    "gn:timezone":"America/Moncton",
    "iso:country":"CA",
    "wof:name":"Johnson's Mills",
    "wof:placetype":"locality"
},
  "geometry": {"coordinates":[-64.51201999999999,45.77173],"type":"Point"}
}