{
  "type": "Feature",
  "properties": {
    "gn:admin1_code":"8",
    "gn:asciiname":"Wallace",
    "gn:country_code":"CA",
    "gn:dem":459,
    "gn:feature_class":"P",
    "gn:feature_code":"PPL",
    "gn:name":"Wallace",
    "gn:population":0,
    "gn:timezone":"America/Toronto",
    "iso:country":"CA",
    "name:ara_x_preferred":[
        "\u0648\u0627\u0644\u0627\u0633"
    ],
    "name:bel_x_preferred":[
        "\u0423\u043e\u043b\u0435\u0441"
    ],
    "name:cat_x_preferred":[
        "Wallace"
    ],
    "name:ceb_x_preferred":[
        "Wallace"
    ],
    "name:ces_x_preferred":[
        "Wallace"
    ],
    "name:deu_x_preferred":[
        "Wallace"
    ],
    "name:epo_x_preferred":[
        "Wallace"
    ],
    "name:fas_x_preferred":[
        "\u0648\u0627\u0644\u0627\u0633"
    ],
    "name:fin_x_preferred":[
        "Wallace"
    ],
    "name:fra_x_preferred":[
        "Wallace"
    ],
    "name:ind_x_preferred":[
        "Wallace"
    ],
    "name:ita_x_preferred":[
        "Wallace"
    ],
    "name:jpn_x_preferred":[
        "\u30a6\u30a9\u30ec\u30b9"
    ],
    "name:kor_x_preferred":[
        "\uc6d4\ub9ac\uc2a4"
    ],
    "name:lav_x_preferred":[
        "Volless"
    ],
    "name:lit_x_preferred":[
        "Wallace"
    ],
    "name:nld_x_preferred":[
        "Wallace"
    ],
    "name:nor_x_preferred":[
        "Wallace"
    ],
    "name:pol_x_preferred":[
        "Wallace"
    ],
    "name:por_x_preferred":[
        "Wallace"
    ],
    "name:rus_x_preferred":[
        "\u0423\u043e\u043b\u043b\u0435\u0441"
    ],
    "name:spa_x_preferred":[
        "Wallace"
    ],
    "name:srp_x_preferred":[
        "\u0412\u043e\u043b\u0430\u0441"
    ],
    "name:swe_x_preferred":[
        "Wallace"
    ],
    "name:tur_x_preferred":[
        "Wallace"
    ],
    "name:ukr_x_preferred":[
        "\u0412\u043e\u043b\u043b\u0435\u0441"
    ],
    "name:vol_x_preferred":[
        "Wallace"
    ],
    "name:zho_x_preferred":[
        "\u534e\u83b1\u58eb"
    ],
    "wof:name":"Wallace",
    "wof:placetype":"locality"
},
  "geometry": {"coordinates":[-78.08778000000002,45.39944000000001],"type":"Point"}
}