{
  "type": "Feature",
  "properties": {
    "gn:admin1_code":"8",
    "gn:asciiname":"Wallace",
    "gn:country_code":"CA",
    "gn:dem":459,
    "gn:feature_class":"P",
    "gn:feature_code":"PPL",
    "gn:name":"Wallace",
    "gn:population":0,
    "gn:timezone":"America/Toronto",
    "iso:country":"CA",
    "wof:name":"Wallace",
    "wof:placetype":"locality"
},
  "geometry": {"coordinates":[-78.08778000000002,45.39944000000001],"type":"Point"}
}