{
  "type": "Feature",
  "properties": {
    "gn:admin1_code":"8.0",
    "gn:admin2_code":"3520",
    "gn:asciiname":"Metropolitan Area Apt",
    "gn:country_code":"CA",
    "gn:dem":170,
    "gn:feature_class":"P",
    "gn:feature_code":"PPL",
    "gn:name":"Metropolitan Area Apt",
    "gn:population":0,
    "gn:timezone":"America/Toronto",
    "iso:country":"CA",
    "wof:name":"Metropolitan Area Apt",
    "wof:placetype":"locality"
},
  "geometry": {"coordinates":[-79.40193000000002,43.71964000000001],"type":"Point"}
}