{
  "type": "Feature",
  "properties": {
    "gn:admin1_code":"9",
    "gn:asciiname":"Tracadie",
    "gn:country_code":"CA",
    "gn:dem":22,
    "gn:feature_class":"P",
    "gn:feature_code":"PPLL",
    "gn:name":"Tracadie",
    "gn:population":0,
    "gn:timezone":"America/Halifax",
    "iso:country":"CA",
    "wof:name":"Tracadie",
    "wof:placetype":"locality"
},
  "geometry": {"coordinates":[-62.96536999999999,46.35011],"type":"Point"}
}