{
  "type": "Feature",
  "properties": {
    "gn:admin1_code":"1",
    "gn:asciiname":"Harlow",
    "gn:country_code":"CA",
    "gn:dem":664,
    "gn:feature_class":"P",
    "gn:feature_code":"PPL",
    "gn:name":"Harlow",
    "gn:population":0,
    "gn:timezone":"America/Edmonton",
    "iso:country":"CA",
    "name:afr_x_preferred":[
        "Harlow"
    ],
    "name:ara_x_preferred":[
        "\u0647\u0627\u0631\u0644\u0648"
    ],
    "name:azb_x_preferred":[
        "\u0647\u0627\u0631\u0644\u0648"
    ],
    "name:bel_x_preferred":[
        "\u0425\u0430\u0440\u043b\u0430\u0443"
    ],
    "name:bre_x_preferred":[
        "Harlow"
    ],
    "name:bul_x_preferred":[
        "\u0425\u0430\u0440\u043b\u043e\u0443"
    ],
    "name:cat_x_preferred":[
        "Harlow"
    ],
    "name:ceb_x_preferred":[
        "Harlow"
    ],
    "name:ces_x_preferred":[
        "Harlow"
    ],
    "name:cym_x_preferred":[
        "Harlow"
    ],
    "name:dan_x_preferred":[
        "Harlow"
    ],
    "name:deu_x_preferred":[
        "Harlow"
    ],
    "name:epo_x_preferred":[
        "Harlow"
    ],
    "name:fas_x_preferred":[
        "\u0647\u0627\u0631\u0644\u0648"
    ],
    "name:fra_x_preferred":[
        "Harlow"
    ],
    "name:gle_x_preferred":[
        "Harlow"
    ],
    "name:ind_x_preferred":[
        "Harlow"
    ],
    "name:ita_x_preferred":[
        "Harlow"
    ],
    "name:jpn_x_preferred":[
        "\u30cf\u30fc\u30ed\u30a6"
    ],
    "name:nld_x_preferred":[
        "Harlow"
    ],
    "name:nno_x_preferred":[
        "Harlow"
    ],
    "name:nor_x_preferred":[
        "Harlow"
    ],
    "name:pol_x_preferred":[
        "Harlow"
    ],
    "name:por_x_preferred":[
        "Harlow"
    ],
    "name:ron_x_preferred":[
        "Harlow"
    ],
    "name:rus_x_preferred":[
        "\u0425\u0430\u0440\u043b\u043e\u0443"
    ],
    "name:spa_x_preferred":[
        "Harlow"
    ],
    "name:swe_x_preferred":[
        "Harlow"
    ],
    "name:tat_x_preferred":[
        "\u04ba\u0430\u0440\u043b\u043e\u0443"
    ],
    "name:tur_x_preferred":[
        "Harlow"
    ],
    "name:urd_x_preferred":[
        "\u06c1\u0627\u0631\u0644\u0648"
    ],
    "name:vol_x_preferred":[
        "Harlow"
    ],
    "wof:name":"Harlow",
    "wof:placetype":"locality"
},
  "geometry": {"coordinates":[-110.71111000000001,50.04167],"type":"Point"}
}