{
  "type": "Feature",
  "properties": {
    "gn:admin1_code":"1",
    "gn:asciiname":"Stirlingville",
    "gn:country_code":"CA",
    "gn:dem":924,
    "gn:feature_class":"P",
    "gn:feature_code":"PPLL",
    "gn:name":"Stirlingville",
    "gn:population":0,
    "gn:timezone":"America/Edmonton",
    "iso:country":"CA",
    "wof:name":"Stirlingville",
    "wof:placetype":"locality"
},
  "geometry": {"coordinates":[-113.70196,51.56681],"type":"Point"}
}