{
  "type": "Feature",
  "properties": {
    "gn:admin1_code":"12",
    "gn:asciiname":"Forestview",
    "gn:country_code":"CA",
    "gn:dem":709,
    "gn:feature_class":"P",
    "gn:feature_code":"PPL",
    "gn:name":"Forestview",
    "gn:population":0,
    "gn:timezone":"America/Whitehorse",
    "iso:country":"CA",
    "wof:name":"Forestview",
    "wof:placetype":"locality"
},
  "geometry": {"coordinates":[-135.19999999999999,60.81111],"type":"Point"}
}