{
  "type": "Feature",
  "properties": {
    "gn:admin1_code":"1",
    "gn:asciiname":"Peace Grove",
    "gn:country_code":"CA",
    "gn:dem":666,
    "gn:feature_class":"P",
    "gn:feature_code":"PPLL",
    "gn:name":"Peace Grove",
    "gn:population":0,
    "gn:timezone":"America/Edmonton",
    "iso:country":"CA",
    "wof:name":"Peace Grove",
    "wof:placetype":"locality"
},
  "geometry": {"coordinates":[-118.7195,56.30004],"type":"Point"}
}