{
  "type": "Feature",
  "properties": {
    "iso:country":"CA",
    "name:eng_x_preferred":[
        "South Fredericton"
    ],
    "qs:gn_local":0,
    "qs:local_max":468,
    "qs:local_sum":468,
    "qs:localhoods":1,
    "qs:name":"South Fredericton",
    "qs:name_adm0":"Canada",
    "qs:name_adm1":"New Brunswick",
    "qs:name_adm2":"York",
    "qs:name_local":"Hill Area",
    "qs:photo_max":69,
    "qs:photo_sum":468,
    "qs:placetype":"Suburb",
    "qs:quad_count":41,
    "qs:woe_adm0":23424775,
    "qs:woe_adm1":2344918,
    "qs:woe_adm2":29375042,
    "qs:woe_funk":"Grouping neighborhood",
    "qs:woe_lau":0,
    "qs:woe_local":55998495,
    "qs:woe_ver":"7.10.0",
    "wof:lang":[
        "eng"
    ],
    "wof:name":"South Fredericton",
    "wof:placetype":"neighbourhood"
},
  "geometry": {"coordinates":[-66.666258,45.948403],"type":"Point"}
}