{
  "type": "Feature",
  "properties": {
    "gn:country":"CA",
    "gn:fcode":"PPL",
    "gn:pop":0,
    "iso:country":"CA",
    "name:eng_x_preferred":[
        "Change Islands"
    ],
    "qs:name":"Change Islands",
    "qs:name_adm0":"Canada",
    "qs:name_adm1":"Newfoundland and Labrador",
    "qs:photos":132,
    "qs:photos_1k":27,
    "qs:photos_9k":1,
    "qs:photos_9r":3,
    "qs:photos_all":132,
    "qs:photos_sr":3,
    "qs:placetype":"Town",
    "qs:pop_sr":"3",
    "wd:wordcount":277,
    "wof:name":"Change Islands",
    "wof:placetype":"locality",
    "wof:population":0
},
  "geometry": {"coordinates":[-54.41483,49.66662],"type":"Point"}
}