{
  "type": "Feature",
  "properties": {
    "gn:country":"CA",
    "gn:fcode":"PPL",
    "gn:population":0,
    "iso:country":"CA",
    "name:bre_x_preferred":[
        "Change Islands"
    ],
    "name:cos_x_preferred":[
        "Change Islands"
    ],
    "name:dan_x_preferred":[
        "Change Islands"
    ],
    "name:deu_x_preferred":[
        "Change Islands"
    ],
    "name:eng_x_preferred":[
        "Change Islands"
    ],
    "name:fas_x_preferred":[
        "\u0686\u06cc\u0646\u062c \u0622\u06cc\u0644\u0646\u062f\u0632"
    ],
    "name:fra_x_preferred":[
        "Change Islands"
    ],
    "name:ind_x_preferred":[
        "Change Islands"
    ],
    "name:ita_x_preferred":[
        "Change Islands"
    ],
    "name:nds_x_preferred":[
        "Change Islands"
    ],
    "name:nld_x_preferred":[
        "Change Islands"
    ],
    "name:por_x_preferred":[
        "Change Islands"
    ],
    "name:ron_x_preferred":[
        "Change Islands"
    ],
    "name:spa_x_preferred":[
        "Change Islands"
    ],
    "name:swe_x_preferred":[
        "Change Islands"
    ],
    "name:tah_x_preferred":[
        "Change Islands"
    ],
    "qs:name":"Change Islands",
    "qs:name_adm0":"Canada",
    "qs:name_adm1":"Newfoundland and Labrador",
    "qs:photos":132,
    "qs:photos_1k":27,
    "qs:photos_9k":1,
    "qs:photos_9r":3,
    "qs:photos_all":132,
    "qs:photos_sr":3,
    "qs:placetype":"Town",
    "qs:pop_sr":"3",
    "wd:wordcount":277,
    "wof:name":"Change Islands",
    "wof:placetype":"locality",
    "wof:population":0
},
  "geometry": {"coordinates":[-54.41483,49.66662],"type":"Point"}
}