{
  "type": "Feature",
  "properties": {
    "gn:admin1_code":"8",
    "gn:asciiname":"Rondeau Park",
    "gn:country_code":"CA",
    "gn:dem":180,
    "gn:feature_class":"P",
    "gn:feature_code":"PPL",
    "gn:name":"Rondeau Park",
    "gn:population":0,
    "gn:timezone":"America/Toronto",
    "iso:country":"CA",
    "wof:name":"Rondeau Park",
    "wof:placetype":"locality"
},
  "geometry": {"coordinates":[-81.84361,42.32778],"type":"Point"}
}