{
  "type": "Feature",
  "properties": {
    "gn:admin1_code":"12.0",
    "gn:asciiname":"Mooshide",
    "gn:country_code":"CA",
    "gn:dem":372,
    "gn:feature_class":"P",
    "gn:feature_code":"PPL",
    "gn:name":"Mooshide",
    "gn:population":0,
    "gn:timezone":"America/Whitehorse",
    "iso:country":"CA",
    "wof:name":"Mooshide",
    "wof:placetype":"locality"
},
  "geometry": {"coordinates":[-139.44002,64.09649],"type":"Point"}
}