{
  "type": "Feature",
  "properties": {
    "gn:admin1_code":"2.0",
    "gn:asciiname":"Big Creek",
    "gn:country_code":"CA",
    "gn:dem":1125,
    "gn:feature_class":"P",
    "gn:feature_code":"PPLL",
    "gn:name":"Big Creek",
    "gn:population":0,
    "gn:timezone":"America/Vancouver",
    "iso:country":"CA",
    "name:urd_x_preferred":[
        "\u0628\u06af \u06a9\u0631\u06cc\u06a9"
    ],
    "wof:name":"Big Creek",
    "wof:placetype":"locality"
},
  "geometry": {"coordinates":[-123.03619,51.71652],"type":"Point"}
}