{
  "type": "Feature",
  "properties": {
    "gn:admin1_code":"2",
    "gn:asciiname":"Trout Lake",
    "gn:country_code":"CA",
    "gn:dem":723,
    "gn:feature_class":"P",
    "gn:feature_code":"PPL",
    "gn:name":"Trout Lake",
    "gn:population":0,
    "gn:timezone":"America/Vancouver",
    "iso:country":"CA",
    "name:ara_x_preferred":[
        "\u0628\u062d\u064a\u0631\u0629 \u062a\u0631\u0627\u0648\u062a"
    ],
    "name:ben_x_preferred":[
        "\u099f\u09cd\u09b0\u09be\u0989\u099f \u09b2\u09c7\u0995"
    ],
    "name:ell_x_preferred":[
        "\u039b\u03af\u03bc\u03bd\u03b7 \u03a4\u03c1\u03ac\u03bf\u03c5\u03c4"
    ],
    "name:fas_x_preferred":[
        "\u062f\u0631\u06cc\u0627\u0686\u0647 \u062a\u0631\u0648\u062a"
    ],
    "name:fra_x_preferred":[
        "Lac Trout"
    ],
    "name:heb_x_preferred":[
        "\u05d0\u05d2\u05dd \u05e4\u05d5\u05e8\u05dc"
    ],
    "name:hin_x_preferred":[
        "\u091f\u094d\u0930\u093e\u0909\u091f \u091d\u0940\u0932"
    ],
    "name:hun_x_preferred":[
        "Trout-t\u00f3"
    ],
    "name:ind_x_preferred":[
        "Danau Trout"
    ],
    "name:ita_x_preferred":[
        "Trout Lake"
    ],
    "name:jpn_x_preferred":[
        "\u30c8\u30e9\u30a6\u30c8\u6e56"
    ],
    "name:kor_x_preferred":[
        "\ud2b8\ub77c\uc6b0\ud2b8 \ub808\uc774\ud06c"
    ],
    "name:nld_x_preferred":[
        "Trout Lake"
    ],
    "name:pol_x_preferred":[
        "Trout Lake"
    ],
    "name:por_x_preferred":[
        "Lago Trout"
    ],
    "name:rus_x_preferred":[
        "\u043e\u0437\u0435\u0440\u043e \u0422\u0440\u0430\u0443\u0442"
    ],
    "name:spa_x_preferred":[
        "Lago Trout"
    ],
    "name:swe_x_preferred":[
        "Trout Lake"
    ],
    "name:tur_x_preferred":[
        "Trout G\u00f6l\u00fc"
    ],
    "name:ukr_x_preferred":[
        "\u0422\u0440\u043e\u0443\u0442"
    ],
    "name:urd_x_preferred":[
        "\u0679\u0631\u0627\u0624\u0679 \u062c\u06be\u06cc\u0644"
    ],
    "name:vie_x_preferred":[
        "H\u1ed3 Trout"
    ],
    "wof:name":"Trout Lake",
    "wof:placetype":"locality"
},
  "geometry": {"coordinates":[-117.53888999999999,50.64722],"type":"Point"}
}