{
  "type": "Feature",
  "properties": {
    "gn:admin1_code":"11.0",
    "gn:asciiname":"Crichton",
    "gn:country_code":"CA",
    "gn:dem":797,
    "gn:feature_class":"P",
    "gn:feature_code":"PPLL",
    "gn:name":"Crichton",
    "gn:population":0,
    "gn:timezone":"America/Regina",
    "iso:country":"CA",
    "name:deu_x_preferred":[
        "Crichton"
    ],
    "name:fra_x_preferred":[
        "Crichton"
    ],
    "name:ita_x_preferred":[
        "Crichton"
    ],
    "name:por_x_preferred":[
        "Crichton"
    ],
    "name:rus_x_preferred":[
        "\u041a\u0440\u0430\u0439\u0442\u043e\u043d"
    ],
    "wof:name":"Crichton",
    "wof:placetype":"locality"
},
  "geometry": {"coordinates":[-107.88464999999999,49.73336],"type":"Point"}
}