{
  "type": "Feature",
  "properties": {
    "gn:admin1_code":"11.0",
    "gn:asciiname":"Blumenort",
    "gn:country_code":"CA",
    "gn:dem":902,
    "gn:feature_class":"P",
    "gn:feature_code":"PPLL",
    "gn:name":"Blumenort",
    "gn:population":0,
    "gn:timezone":"America/Regina",
    "iso:country":"CA",
    "wof:name":"Blumenort",
    "wof:placetype":"locality"
},
  "geometry": {"coordinates":[-107.75133999999998,50.00006],"type":"Point"}
}