{
  "type": "Feature",
  "properties": {
    "iso:country":"CA",
    "name:ceb_x_preferred":[
        "Gondola Point"
    ],
    "name:eng_x_preferred":[
        "Gondola Point"
    ],
    "name:nld_x_preferred":[
        "Gondola Point"
    ],
    "name:swe_x_preferred":[
        "Gondola Point"
    ],
    "qs_pg:aaroncc":"CA",
    "qs_pg:name":"Gondola Point",
    "qs_pg:name_adm0":"Canada",
    "qs_pg:name_adm1":"New Brunswick",
    "qs_pg:photos":122,
    "qs_pg:photos_1k":25,
    "qs_pg:photos_9k":1,
    "qs_pg:photos_9r":3,
    "qs_pg:photos_all":122,
    "qs_pg:photos_sr":3,
    "qs_pg:pop_sr":0,
    "qs_pg:qs_pg_placetype":"locality",
    "qs_pg:qs_pg_placetype_gp":"Town",
    "qs_pg:woe_adm0":23424775,
    "woe:adm0_id":23424775,
    "woe:name_adm0":"Canada",
    "woe:name_adm1":"New Brunswick",
    "woe:placetype":"Town",
    "wof:name":"Gondola Point",
    "wof:placetype":"locality"
},
  "geometry": {"coordinates":[-65.979766,45.454621],"type":"Point"}
}