{
  "type": "Feature",
  "properties": {
    "gn:admin1_code":"7",
    "gn:asciiname":"Tarbotvale",
    "gn:country_code":"CA",
    "gn:dem":31,
    "gn:feature_class":"P",
    "gn:feature_code":"PPL",
    "gn:name":"Tarbotvale",
    "gn:population":0,
    "gn:timezone":"America/Halifax",
    "iso:country":"CA",
    "wof:name":"Tarbotvale",
    "wof:placetype":"locality"
},
  "geometry": {"coordinates":[-60.56685,46.35049],"type":"Point"}
}