{
  "type": "Feature",
  "properties": {
    "gn:admin1_code":"8",
    "gn:asciiname":"Uffington",
    "gn:country_code":"CA",
    "gn:dem":313,
    "gn:feature_class":"P",
    "gn:feature_code":"PPL",
    "gn:name":"Uffington",
    "gn:population":0,
    "gn:timezone":"America/Toronto",
    "iso:country":"CA",
    "name:ceb_x_preferred":[
        "Uffington"
    ],
    "name:cym_x_preferred":[
        "Uffington"
    ],
    "name:deu_x_preferred":[
        "Uffington"
    ],
    "name:fra_x_preferred":[
        "Uffington"
    ],
    "name:ita_x_preferred":[
        "Uffington"
    ],
    "name:kor_x_preferred":[
        "\uc5b4\ud551\ud134"
    ],
    "name:nld_x_preferred":[
        "Uffington"
    ],
    "name:pol_x_preferred":[
        "Uffington"
    ],
    "name:swe_x_preferred":[
        "Uffington"
    ],
    "wof:name":"Uffington",
    "wof:placetype":"locality"
},
  "geometry": {"coordinates":[-79.18056,44.98361],"type":"Point"}
}