{
  "type": "Feature",
  "properties": {
    "gn:country":"CA",
    "gn:fcode":"PPL",
    "gn:pop":6915,
    "gn:population":6915,
    "iso:country":"CA",
    "name:ara_x_preferred":[
        "\u063a\u0631\u064a\u0646\u0648\u0648\u062f"
    ],
    "name:dut_x_preferred":[
        "Greenwood"
    ],
    "name:eng_x_preferred":[
        "Greenwood"
    ],
    "name:fre_x_preferred":[
        "Greenwood"
    ],
    "name:gla_x_preferred":[
        "Greenwood"
    ],
    "name:swe_x_preferred":[
        "Greenwood"
    ],
    "qs:name":"Greenwood",
    "qs:name_adm0":"Canada",
    "qs:name_adm1":"Nova Scotia",
    "qs:photos":376,
    "qs:photos_1k":76,
    "qs:photos_9k":2,
    "qs:photos_9r":5,
    "qs:photos_all":376,
    "qs:photos_sr":6,
    "qs:placetype":"Town",
    "qs:pop_sr":"5",
    "wd:wordcount":476,
    "wof:name":"Greenwood",
    "wof:placetype":"locality",
    "wof:population":6915
},
  "geometry": {"coordinates":[-64.89879000000001,44.98345],"type":"Point"}
}