{
  "type": "Feature",
  "properties": {
    "gn:admin1_code":"5",
    "gn:asciiname":"Swansea",
    "gn:country_code":"CA",
    "gn:dem":129,
    "gn:feature_class":"P",
    "gn:feature_code":"PPLL",
    "gn:name":"Swansea",
    "gn:population":0,
    "gn:timezone":"America/St_Johns",
    "iso:country":"CA",
    "wof:name":"Swansea",
    "wof:placetype":"locality"
},
  "geometry": {"coordinates":[-53.26478,47.74989],"type":"Point"}
}