{
  "type": "Feature",
  "properties": {
    "gn:admin1_code":"1",
    "gn:asciiname":"St. Francis",
    "gn:country_code":"CA",
    "gn:dem":801,
    "gn:feature_class":"P",
    "gn:feature_code":"PPLL",
    "gn:name":"St. Francis",
    "gn:population":0,
    "gn:timezone":"America/Edmonton",
    "iso:country":"CA",
    "wof:name":"St. Francis",
    "wof:placetype":"locality"
},
  "geometry": {"coordinates":[-114.33538,53.28343],"type":"Point"}
}