{
  "type": "Feature",
  "properties": {
    "gn:admin1_code":"11",
    "gn:asciiname":"Red Cross",
    "gn:country_code":"CA",
    "gn:dem":629,
    "gn:feature_class":"P",
    "gn:feature_code":"PPLL",
    "gn:name":"Red Cross",
    "gn:population":0,
    "gn:timezone":"America/Regina",
    "iso:country":"CA",
    "wof:name":"Red Cross",
    "wof:placetype":"locality"
},
  "geometry": {"coordinates":[-109.45151,53.71689],"type":"Point"}
}