{
  "type": "Feature",
  "properties": {
    "gn:admin1_code":"7",
    "gn:asciiname":"Newton Mills",
    "gn:country_code":"CA",
    "gn:dem":56,
    "gn:feature_class":"P",
    "gn:feature_code":"PPL",
    "gn:name":"Newton Mills",
    "gn:population":0,
    "gn:timezone":"America/Halifax",
    "iso:country":"CA",
    "wof:name":"Newton Mills",
    "wof:placetype":"locality"
},
  "geometry": {"coordinates":[-62.91651,45.22653],"type":"Point"}
}