{
  "type": "Feature",
  "properties": {
    "gn:admin1_code":"1.0",
    "gn:asciiname":"Cline River",
    "gn:country_code":"CA",
    "gn:dem":1363,
    "gn:feature_class":"P",
    "gn:feature_code":"PPL",
    "gn:name":"Cline River",
    "gn:population":0,
    "gn:timezone":"America/Edmonton",
    "iso:country":"CA",
    "name:ceb_x_preferred":[
        "Cline River"
    ],
    "name:pol_x_preferred":[
        "Cline"
    ],
    "name:swe_x_preferred":[
        "Cline River"
    ],
    "wof:name":"Cline River",
    "wof:placetype":"locality"
},
  "geometry": {"coordinates":[-116.47906999999999,52.18931],"type":"Point"}
}