{
  "type": "Feature",
  "properties": {
    "gn:admin1_code":"3",
    "gn:asciiname":"Pine Ridge",
    "gn:country_code":"CA",
    "gn:dem":260,
    "gn:feature_class":"P",
    "gn:feature_code":"PPLL",
    "gn:name":"Pine Ridge",
    "gn:population":0,
    "gn:timezone":"America/Winnipeg",
    "iso:country":"CA",
    "wof:name":"Pine Ridge",
    "wof:placetype":"locality"
},
  "geometry": {"coordinates":[-96.84142,50.0044],"type":"Point"}
}