{
  "type": "Feature",
  "properties": {
    "gn:admin1_code":"5",
    "gn:asciiname":"Tickle Harbour Station",
    "gn:country_code":"CA",
    "gn:dem":124,
    "gn:feature_class":"P",
    "gn:feature_code":"PPLL",
    "gn:name":"Tickle Harbour Station",
    "gn:population":0,
    "gn:timezone":"America/St_Johns",
    "iso:country":"CA",
    "wof:name":"Tickle Harbour Station",
    "wof:placetype":"locality"
},
  "geometry": {"coordinates":[-53.82872,47.57489],"type":"Point"}
}