{
  "type": "Feature",
  "properties": {
    "gn:admin1_code":"8",
    "gn:asciiname":"Richwood",
    "gn:country_code":"CA",
    "gn:dem":289,
    "gn:feature_class":"P",
    "gn:feature_code":"PPL",
    "gn:name":"Richwood",
    "gn:population":0,
    "gn:timezone":"America/Toronto",
    "iso:country":"CA",
    "name:ara_x_preferred":[
        "\u0631\u064a\u062a\u0634\u0648\u0648\u062f"
    ],
    "name:cat_x_preferred":[
        "Richwood"
    ],
    "name:ceb_x_preferred":[
        "Richwood"
    ],
    "name:deu_x_preferred":[
        "Richwood"
    ],
    "name:fra_x_preferred":[
        "Richwood"
    ],
    "name:ita_x_preferred":[
        "Richwood"
    ],
    "name:nld_x_preferred":[
        "Richwood"
    ],
    "name:pol_x_preferred":[
        "Richwood"
    ],
    "name:rus_x_preferred":[
        "\u0420\u0438\u0447\u0432\u0443\u0434"
    ],
    "name:spa_x_preferred":[
        "Richwood"
    ],
    "name:srp_x_preferred":[
        "\u0420\u0438\u0447\u0432\u0443\u0434"
    ],
    "name:swe_x_preferred":[
        "Richwood"
    ],
    "name:vol_x_preferred":[
        "Richwood"
    ],
    "wof:name":"Richwood",
    "wof:placetype":"locality"
},
  "geometry": {"coordinates":[-80.50314,43.22012],"type":"Point"}
}