{
  "type": "Feature",
  "properties": {
    "gn:admin1_code":"10",
    "gn:admin2_code":"5.0",
    "gn:admin3_code":"45085.0",
    "gn:asciiname":"Millington",
    "gn:country_code":"CA",
    "gn:dem":242,
    "gn:feature_class":"P",
    "gn:feature_code":"PPL",
    "gn:name":"Millington",
    "gn:population":0,
    "gn:timezone":"America/Toronto",
    "iso:country":"CA",
    "name:cat_x_preferred":[
        "Millington"
    ],
    "name:ceb_x_preferred":[
        "Millington"
    ],
    "name:deu_x_preferred":[
        "Millington"
    ],
    "name:fra_x_preferred":[
        "Millington"
    ],
    "name:ita_x_preferred":[
        "Millington"
    ],
    "name:nld_x_preferred":[
        "Millington"
    ],
    "name:pol_x_preferred":[
        "Millington"
    ],
    "name:por_x_preferred":[
        "Millington"
    ],
    "name:srp_x_preferred":[
        "\u041c\u0438\u043b\u0438\u043d\u0433\u0442\u043e\u043d"
    ],
    "name:swe_x_preferred":[
        "Millington"
    ],
    "name:ukr_x_preferred":[
        "\u041c\u0456\u043b\u043b\u0456\u043d\u0433\u0442\u043e\u043d"
    ],
    "name:vol_x_preferred":[
        "Millington"
    ],
    "wof:name":"Millington",
    "wof:placetype":"locality"
},
  "geometry": {"coordinates":[-72.29011,45.20532],"type":"Point"}
}