{
  "type": "Feature",
  "properties": {
    "gn:admin1_code":"11",
    "gn:asciiname":"Springwater",
    "gn:country_code":"CA",
    "gn:dem":683,
    "gn:feature_class":"P",
    "gn:feature_code":"PPL",
    "gn:name":"Springwater",
    "gn:population":0,
    "gn:timezone":"America/Regina",
    "iso:country":"CA",
    "name:deu_x_preferred":[
        "Springwater"
    ],
    "name:fra_x_preferred":[
        "Springwater"
    ],
    "name:ita_x_preferred":[
        "Springwater"
    ],
    "name:pol_x_preferred":[
        "Springwater"
    ],
    "name:spa_x_preferred":[
        "Springwater"
    ],
    "wof:name":"Springwater",
    "wof:placetype":"locality"
},
  "geometry": {"coordinates":[-108.38471,51.96681],"type":"Point"}
}