{
  "type": "Feature",
  "properties": {
    "gn:admin1_code":"7.0",
    "gn:asciiname":"Western Head",
    "gn:country_code":"CA",
    "gn:dem":19,
    "gn:feature_class":"P",
    "gn:feature_code":"PPL",
    "gn:name":"Western Head",
    "gn:population":0,
    "gn:timezone":"America/Halifax",
    "iso:country":"CA",
    "wof:name":"Western Head",
    "wof:placetype":"locality"
},
  "geometry": {"coordinates":[-65.12988,43.67904],"type":"Point"}
}