{
  "type": "Feature",
  "properties": {
    "gn:admin1_code":"8.0",
    "gn:asciiname":"Willow Grove",
    "gn:country_code":"CA",
    "gn:dem":349,
    "gn:feature_class":"P",
    "gn:feature_code":"PPL",
    "gn:name":"Willow Grove",
    "gn:population":0,
    "gn:timezone":"America/Toronto",
    "iso:country":"CA",
    "wof:name":"Willow Grove",
    "wof:placetype":"locality"
},
  "geometry": {"coordinates":[-81.15778,43.51611],"type":"Point"}
}