{
  "type": "Feature",
  "properties": {
    "iso:country":"CA",
    "name:eng_x_preferred":[
        "Riverport"
    ],
    "name:fra_x_preferred":[
        "Riverport"
    ],
    "name:jpn_x_preferred":[
        "\u30ea\u30d0\u30fc\u30dd\u30fc\u30c8"
    ],
    "name:nld_x_preferred":[
        "Riverport"
    ],
    "qs:name":"Riverport",
    "qs:name_adm0":"Canada",
    "qs:name_adm1":"Nova Scotia",
    "qs:photos":26,
    "qs:photos_1k":5,
    "qs:photos_9k":1,
    "qs:photos_9r":2,
    "qs:photos_all":26,
    "qs:photos_sr":2,
    "qs:placetype":"Town",
    "qs:pop_sr":"0",
    "wd:wordcount":16,
    "wof:name":"Riverport",
    "wof:placetype":"locality"
},
  "geometry": {"coordinates":[-64.33576499999999,44.286287],"type":"Point"}
}