{
  "type": "Feature",
  "properties": {
    "iso:country":"CA",
    "name:ceb_x_preferred":[
        "Ilderton"
    ],
    "name:swe_x_preferred":[
        "Ilderton"
    ],
    "qs_pg:aaroncc":"CA",
    "qs_pg:name":"Ilderton",
    "qs_pg:name_adm0":"Canada",
    "qs_pg:name_adm1":"Ontario",
    "qs_pg:photos":260,
    "qs_pg:photos_1k":53,
    "qs_pg:photos_9k":1,
    "qs_pg:photos_9r":4,
    "qs_pg:photos_all":260,
    "qs_pg:photos_sr":5,
    "qs_pg:pop_sr":0,
    "qs_pg:qs_pg_placetype":"locality",
    "qs_pg:qs_pg_placetype_gp":"Town",
    "qs_pg:woe_adm0":23424775,
    "woe:adm0_id":23424775,
    "woe:name_adm0":"Canada",
    "woe:name_adm1":"Ontario",
    "woe:placetype":"Town",
    "wof:name":"Ilderton",
    "wof:placetype":"locality"
},
  "geometry": {"coordinates":[-81.38847800000001,43.079107],"type":"Point"}
}