{
  "type": "Feature",
  "properties": {
    "gn:admin1_code":"7",
    "gn:asciiname":"Indian Harbour Lake",
    "gn:country_code":"CA",
    "gn:dem":4,
    "gn:feature_class":"P",
    "gn:feature_code":"PPL",
    "gn:name":"Indian Harbour Lake",
    "gn:population":0,
    "gn:timezone":"America/Halifax",
    "iso:country":"CA",
    "wof:name":"Indian Harbour Lake",
    "wof:placetype":"locality"
},
  "geometry": {"coordinates":[-61.88003000000001,45.13431],"type":"Point"}
}