{
  "type": "Feature",
  "properties": {
    "gn:admin1_code":"8",
    "gn:asciiname":"Newbridge",
    "gn:country_code":"CA",
    "gn:dem":369,
    "gn:feature_class":"P",
    "gn:feature_code":"PPL",
    "gn:name":"Newbridge",
    "gn:population":0,
    "gn:timezone":"America/Toronto",
    "iso:country":"CA",
    "name:bul_x_preferred":[
        "\u041d\u044e\u0431\u0440\u0438\u0434\u0436"
    ],
    "name:ceb_x_preferred":[
        "Newbridge"
    ],
    "name:ces_x_preferred":[
        "Newbridge"
    ],
    "name:cym_x_preferred":[
        "Newbridge"
    ],
    "name:deu_x_preferred":[
        "Newbridge"
    ],
    "name:fra_x_preferred":[
        "Newbridge"
    ],
    "name:kor_x_preferred":[
        "\ub274\ube0c\ub9ac\uc9c0"
    ],
    "name:nld_x_preferred":[
        "Newbridge"
    ],
    "name:pol_x_preferred":[
        "Newbridge"
    ],
    "name:slk_x_preferred":[
        "Newbridge"
    ],
    "name:swe_x_preferred":[
        "Newbridge"
    ],
    "wof:name":"Newbridge",
    "wof:placetype":"locality"
},
  "geometry": {"coordinates":[-80.97410000000001,43.85072],"type":"Point"}
}