{
  "type": "Feature",
  "properties": {
    "gn:admin1_code":"4.0",
    "gn:asciiname":"Cherryvale",
    "gn:country_code":"CA",
    "gn:dem":21,
    "gn:feature_class":"P",
    "gn:feature_code":"PPL",
    "gn:name":"Cherryvale",
    "gn:population":0,
    "gn:timezone":"America/Moncton",
    "iso:country":"CA",
    "name:ceb_x_preferred":[
        "Cherryvale"
    ],
    "name:deu_x_preferred":[
        "Cherryvale"
    ],
    "name:fra_x_preferred":[
        "Cherryvale"
    ],
    "name:ita_x_preferred":[
        "Cherryvale"
    ],
    "name:nld_x_preferred":[
        "Cherryvale"
    ],
    "name:pol_x_preferred":[
        "Cherryvale"
    ],
    "name:spa_x_preferred":[
        "Cherryvale"
    ],
    "name:srp_x_preferred":[
        "\u0427\u0435\u0440\u0438\u0432\u0435\u0458\u043b"
    ],
    "name:vol_x_preferred":[
        "Cherryvale"
    ],
    "wof:name":"Cherryvale",
    "wof:placetype":"locality"
},
  "geometry": {"coordinates":[-65.48017,46.05838],"type":"Point"}
}