{
  "type": "Feature",
  "properties": {
    "gn:admin1_code":"10",
    "gn:admin2_code":"8.0",
    "gn:admin3_code":"89040.0",
    "gn:asciiname":"Forsythe",
    "gn:country_code":"CA",
    "gn:dem":391,
    "gn:feature_class":"P",
    "gn:feature_code":"PPL",
    "gn:name":"Forsythe",
    "gn:population":0,
    "gn:timezone":"America/Toronto",
    "iso:country":"CA",
    "name:deu_x_preferred":[
        "Forsythe"
    ],
    "name:fas_x_preferred":[
        "\u0641\u0648\u0631\u0633\u0627\u06cc\u062a"
    ],
    "name:fra_x_preferred":[
        "Forsythe"
    ],
    "name:rus_x_preferred":[
        "\u0424\u043e\u0440\u0441\u0430\u0439\u0442"
    ],
    "name:ukr_x_preferred":[
        "\u0424\u043e\u0440\u0441\u0430\u0439\u0442"
    ],
    "wof:name":"Forsythe",
    "wof:placetype":"locality"
},
  "geometry": {"coordinates":[-76.42778,48.23722],"type":"Point"}
}