{
  "type": "Feature",
  "properties": {
    "gn:country":"CA",
    "gn:fcode":"ADMD",
    "gn:population":608124,
    "iso:country":"CA",
    "name:bel_x_preferred":[
        "\u0414\u0430\u0440\u044d\u043c"
    ],
    "name:bre_x_preferred":[
        "Durham"
    ],
    "name:bul_x_preferred":[
        "\u0414\u044a\u0440\u0430\u043c"
    ],
    "name:cat_x_preferred":[
        "Durham"
    ],
    "name:ceb_x_preferred":[
        "Durham"
    ],
    "name:ces_x_preferred":[
        "Durham"
    ],
    "name:dan_x_preferred":[
        "Durham"
    ],
    "name:deu_x_preferred":[
        "Durham"
    ],
    "name:eng_x_preferred":[
        "Durham"
    ],
    "name:epo_x_preferred":[
        "Durham"
    ],
    "name:fas_x_preferred":[
        "\u062f\u0648\u0631\u0647\u0627\u0645"
    ],
    "name:fra_x_preferred":[
        "Durham"
    ],
    "name:glg_x_preferred":[
        "Durham"
    ],
    "name:heb_x_preferred":[
        "\u05d3\u05e8\u05d4\u05d0\u05dd"
    ],
    "name:hun_x_preferred":[
        "Durham"
    ],
    "name:ita_x_preferred":[
        "Durham"
    ],
    "name:jpn_x_preferred":[
        "\u30c0\u30fc\u30e9\u30e0"
    ],
    "name:kor_x_preferred":[
        "\ub354\ub7fc"
    ],
    "name:lit_x_preferred":[
        "Daramas"
    ],
    "name:nld_x_preferred":[
        "Durham"
    ],
    "name:nor_x_preferred":[
        "Durham"
    ],
    "name:pol_x_preferred":[
        "Durham"
    ],
    "name:por_x_preferred":[
        "Durham"
    ],
    "name:ron_x_preferred":[
        "Durham"
    ],
    "name:rus_x_preferred":[
        "\u0414\u0430\u0440\u0435\u043c"
    ],
    "name:sco_x_preferred":[
        "Durham"
    ],
    "name:slk_x_preferred":[
        "Durham"
    ],
    "name:spa_x_preferred":[
        "Durham"
    ],
    "name:srp_x_preferred":[
        "\u0414\u0430\u0440\u0430\u043c"
    ],
    "name:swe_x_preferred":[
        "Durham"
    ],
    "name:tha_x_preferred":[
        "\u0e40\u0e14\u0e2d\u0e41\u0e23\u0e21"
    ],
    "name:ukr_x_preferred":[
        "\u0414\u0430\u0440\u0435\u043c"
    ],
    "name:vol_x_preferred":[
        "Durham"
    ],
    "name:zho_x_preferred":[
        "\u8fbe\u52d2\u59c6"
    ],
    "qs:name":"Durham",
    "qs:photos_9r":0,
    "qs:photos_sr":0,
    "qs:pop_sr":"11",
    "wd:wordcount":350,
    "wof:name":"Durham",
    "wof:placetype":"localadmin",
    "wof:population":608124
},
  "geometry": {"coordinates":[-78.99957000000001,44.20012],"type":"Point"}
}