{
  "type": "Feature",
  "properties": {
    "gn:country":"CA",
    "gn:fcode":"ADMD",
    "gn:pop":608124,
    "gn:population":608124,
    "iso:country":"CA",
    "name:eng_x_preferred":[
        "Durham"
    ],
    "qs:name":"Durham",
    "qs:photos_9r":0,
    "qs:photos_sr":0,
    "qs:pop_sr":"11",
    "wd:wordcount":350,
    "wof:name":"Durham",
    "wof:placetype":"localadmin",
    "wof:population":608124
},
  "geometry": {"coordinates":[-78.99957000000001,44.20012],"type":"Point"}
}