{
  "type": "Feature",
  "properties": {
    "gn:admin1_code":"2",
    "gn:asciiname":"Port Neville",
    "gn:country_code":"CA",
    "gn:dem":7,
    "gn:feature_class":"P",
    "gn:feature_code":"PPLL",
    "gn:name":"Port Neville",
    "gn:population":0,
    "gn:timezone":"America/Vancouver",
    "iso:country":"CA",
    "name:ceb_x_preferred":[
        "Port Neville"
    ],
    "name:swe_x_preferred":[
        "Port Neville"
    ],
    "wof:name":"Port Neville",
    "wof:placetype":"locality"
},
  "geometry": {"coordinates":[-126.08691,50.49328],"type":"Point"}
}