{
  "type": "Feature",
  "properties": {
    "gn:admin1_code":"5.0",
    "gn:asciiname":"Clarke's Beach",
    "gn:country_code":"CA",
    "gn:dem":1,
    "gn:feature_class":"P",
    "gn:feature_code":"PPL",
    "gn:name":"Clarke's Beach",
    "gn:population":0,
    "gn:timezone":"America/St_Johns",
    "iso:country":"CA",
    "name:fas_x_preferred":[
        "\u06a9\u0644\u0627\u0631\u06a9\u0633 \u0628\u06cc\u0686"
    ],
    "name:fra_x_preferred":[
        "Clarke's Beach"
    ],
    "name:nld_x_preferred":[
        "Clarke's Beach"
    ],
    "wof:name":"Clarke's Beach",
    "wof:placetype":"locality"
},
  "geometry": {"coordinates":[-53.28138000000001,47.54989000000001],"type":"Point"}
}