{
  "type": "Feature",
  "properties": {
    "gn:admin1_code":"7",
    "gn:asciiname":"Pomquet Forks",
    "gn:country_code":"CA",
    "gn:dem":31,
    "gn:feature_class":"P",
    "gn:feature_code":"PPL",
    "gn:name":"Pomquet Forks",
    "gn:population":0,
    "gn:timezone":"America/Halifax",
    "iso:country":"CA",
    "wof:name":"Pomquet Forks",
    "wof:placetype":"locality"
},
  "geometry": {"coordinates":[-61.81511999999999,45.59001],"type":"Point"}
}