{
  "type": "Feature",
  "properties": {
    "gn:admin1_code":"8.0",
    "gn:asciiname":"Cavan",
    "gn:country_code":"CA",
    "gn:dem":206,
    "gn:feature_class":"P",
    "gn:feature_code":"PPL",
    "gn:name":"Cavan",
    "gn:population":0,
    "gn:timezone":"America/Toronto",
    "iso:country":"CA",
    "name:bre_x_preferred":[
        "An Cabh\u00e1n"
    ],
    "name:bul_x_preferred":[
        "\u041a\u0430\u0432\u0430\u043d"
    ],
    "name:cat_x_preferred":[
        "Cavan"
    ],
    "name:ceb_x_preferred":[
        "Cavan"
    ],
    "name:cym_x_preferred":[
        "Cavan"
    ],
    "name:dan_x_preferred":[
        "Cavan"
    ],
    "name:deu_x_preferred":[
        "Cavan"
    ],
    "name:eus_x_preferred":[
        "Cavan"
    ],
    "name:fas_x_preferred":[
        "\u06a9\u0627\u0648\u0627\u0646"
    ],
    "name:fin_x_preferred":[
        "Cavan"
    ],
    "name:fra_x_preferred":[
        "Cavan"
    ],
    "name:gla_x_preferred":[
        "An Cabh\u00e1n"
    ],
    "name:gle_x_preferred":[
        "An Cabh\u00e1n"
    ],
    "name:glg_x_preferred":[
        "Cavan"
    ],
    "name:glv_x_preferred":[
        "Yn Cavan"
    ],
    "name:ind_x_preferred":[
        "Cavan"
    ],
    "name:ita_x_preferred":[
        "Cavan"
    ],
    "name:jpn_x_preferred":[
        "\u30ad\u30e3\u30d0\u30f3"
    ],
    "name:kat_x_preferred":[
        "\u10d9\u10d0\u10d5\u10d0\u10dc\u10d8"
    ],
    "name:lit_x_preferred":[
        "Kavanas"
    ],
    "name:nld_x_preferred":[
        "Cavan"
    ],
    "name:nno_x_preferred":[
        "Cavan"
    ],
    "name:nor_x_preferred":[
        "Cavan"
    ],
    "name:pol_x_preferred":[
        "Cavan"
    ],
    "name:por_x_preferred":[
        "Cavan"
    ],
    "name:rus_x_preferred":[
        "\u041a\u0430\u0432\u0430\u043d"
    ],
    "name:sco_x_preferred":[
        "Cavan"
    ],
    "name:slk_x_preferred":[
        "Cavan"
    ],
    "name:spa_x_preferred":[
        "Cavan"
    ],
    "name:srp_x_preferred":[
        "\u041a\u0430\u0432\u0430\u043d"
    ],
    "name:swa_x_preferred":[
        "Cavan"
    ],
    "name:swe_x_preferred":[
        "Cavan"
    ],
    "name:ukr_x_preferred":[
        "\u041a\u0430\u0432\u0430\u043d"
    ],
    "name:urd_x_preferred":[
        "\u06a9\u06cc\u0648\u0627\u0646"
    ],
    "wof:name":"Cavan",
    "wof:placetype":"locality"
},
  "geometry": {"coordinates":[-78.46873000000002,44.19987],"type":"Point"}
}