{
  "type": "Feature",
  "properties": {
    "gn:admin1_code":"8.0",
    "gn:asciiname":"Cavan",
    "gn:country_code":"CA",
    "gn:dem":206,
    "gn:feature_class":"P",
    "gn:feature_code":"PPL",
    "gn:name":"Cavan",
    "gn:population":0,
    "gn:timezone":"America/Toronto",
    "iso:country":"CA",
    "wof:name":"Cavan",
    "wof:placetype":"locality"
},
  "geometry": {"coordinates":[-78.46873000000002,44.19987],"type":"Point"}
}