{
  "type": "Feature",
  "properties": {
    "gn:admin1_code":"8",
    "gn:asciiname":"Kennicott",
    "gn:country_code":"CA",
    "gn:dem":358,
    "gn:feature_class":"P",
    "gn:feature_code":"PPL",
    "gn:name":"Kennicott",
    "gn:population":0,
    "gn:timezone":"America/Toronto",
    "iso:country":"CA",
    "name:deu_x_preferred":[
        "Kennicott"
    ],
    "name:fra_x_preferred":[
        "Kennicott"
    ],
    "name:nds_x_preferred":[
        "Kennicott"
    ],
    "name:por_x_preferred":[
        "Kennecott"
    ],
    "name:rus_x_preferred":[
        "\u041a\u0435\u043d\u043d\u0438\u043a\u043e\u0442\u0442"
    ],
    "wof:name":"Kennicott",
    "wof:placetype":"locality"
},
  "geometry": {"coordinates":[-81.12361,43.55583],"type":"Point"}
}