{
  "type": "Feature",
  "properties": {
    "gn:admin1_code":"8.0",
    "gn:asciiname":"Bigwin",
    "gn:country_code":"CA",
    "gn:dem":321,
    "gn:feature_class":"P",
    "gn:feature_code":"PPL",
    "gn:name":"Bigwin",
    "gn:population":0,
    "gn:timezone":"America/Toronto",
    "iso:country":"CA",
    "wof:name":"Bigwin",
    "wof:placetype":"locality"
},
  "geometry": {"coordinates":[-79.02333,45.24278],"type":"Point"}
}