{
  "type": "Feature",
  "properties": {
    "gn:admin1_code":"4.0",
    "gn:asciiname":"Beersville",
    "gn:country_code":"CA",
    "gn:dem":63,
    "gn:feature_class":"P",
    "gn:feature_code":"PPL",
    "gn:name":"Beersville",
    "gn:population":0,
    "gn:timezone":"America/Moncton",
    "iso:country":"CA",
    "wof:name":"Beersville",
    "wof:placetype":"locality"
},
  "geometry": {"coordinates":[-65.07579,46.44701],"type":"Point"}
}