{
  "type": "Feature",
  "properties": {
    "gn:admin1_code":"4",
    "gn:asciiname":"Richmond",
    "gn:country_code":"CA",
    "gn:dem":165,
    "gn:feature_class":"P",
    "gn:feature_code":"PPL",
    "gn:name":"Richmond",
    "gn:population":0,
    "gn:timezone":"America/Moncton",
    "iso:country":"CA",
    "wof:name":"Richmond",
    "wof:placetype":"locality"
},
  "geometry": {"coordinates":[-67.6593,46.0749],"type":"Point"}
}