{
  "type": "Feature",
  "properties": {
    "gn:admin1_code":"4",
    "gn:asciiname":"Richmond",
    "gn:country_code":"CA",
    "gn:dem":165,
    "gn:feature_class":"P",
    "gn:feature_code":"PPL",
    "gn:name":"Richmond",
    "gn:population":0,
    "gn:timezone":"America/Moncton",
    "iso:country":"CA",
    "name:afr_x_preferred":[
        "Richmond"
    ],
    "name:ara_x_preferred":[
        "\u0631\u064a\u062a\u0634\u0645\u0648\u0646\u062f"
    ],
    "name:bar_x_preferred":[
        "Richmond"
    ],
    "name:bre_x_preferred":[
        "Richmond"
    ],
    "name:bul_x_preferred":[
        "\u0420\u0438\u0447\u043c\u044a\u043d\u0434"
    ],
    "name:cat_x_preferred":[
        "Richmond"
    ],
    "name:ceb_x_preferred":[
        "Richmond"
    ],
    "name:ces_x_preferred":[
        "Richmond"
    ],
    "name:che_x_preferred":[
        "\u0420\u0438\u0447\u043c\u043e\u043d\u0434"
    ],
    "name:cym_x_preferred":[
        "Richmond"
    ],
    "name:dan_x_preferred":[
        "Richmond"
    ],
    "name:deu_x_preferred":[
        "Richmond"
    ],
    "name:ell_x_preferred":[
        "\u03a1\u03af\u03c4\u03c3\u03bc\u03bf\u03bd\u03c4"
    ],
    "name:epo_x_preferred":[
        "Richmond"
    ],
    "name:est_x_preferred":[
        "Richmond"
    ],
    "name:fas_x_preferred":[
        "\u0631\u06cc\u0686\u0645\u0648\u0646\u062f"
    ],
    "name:fin_x_preferred":[
        "Richmond"
    ],
    "name:fra_x_preferred":[
        "Richmond"
    ],
    "name:heb_x_preferred":[
        "\u05e8\u05d9\u05e6'\u05de\u05d5\u05e0\u05d3"
    ],
    "name:hrv_x_preferred":[
        "Richmond"
    ],
    "name:hun_x_preferred":[
        "Richmond"
    ],
    "name:ido_x_preferred":[
        "Richmond"
    ],
    "name:ind_x_preferred":[
        "Richmond"
    ],
    "name:ita_x_preferred":[
        "Richmond"
    ],
    "name:jpn_x_preferred":[
        "\u30ea\u30c3\u30c1\u30e2\u30f3\u30c9"
    ],
    "name:kor_x_preferred":[
        "\ub9ac\uce58\uba3c\ub4dc"
    ],
    "name:lit_x_preferred":[
        "Ri\u010dmondas"
    ],
    "name:mlg_x_preferred":[
        "Richmond"
    ],
    "name:nld_x_preferred":[
        "Richmond"
    ],
    "name:nor_x_preferred":[
        "Richmond"
    ],
    "name:pol_x_preferred":[
        "Richmond"
    ],
    "name:por_x_preferred":[
        "Richmond"
    ],
    "name:ron_x_preferred":[
        "Richmond"
    ],
    "name:rus_x_preferred":[
        "\u0420\u0438\u0447\u043c\u043e\u043d\u0434"
    ],
    "name:sco_x_preferred":[
        "Richmond"
    ],
    "name:slk_x_preferred":[
        "Richmond"
    ],
    "name:spa_x_preferred":[
        "Richmond"
    ],
    "name:srp_x_preferred":[
        "\u0420\u0438\u0447\u043c\u043e\u043d\u0434"
    ],
    "name:swa_x_preferred":[
        "Richmond"
    ],
    "name:swe_x_preferred":[
        "Richmond"
    ],
    "name:tur_x_preferred":[
        "Richmond"
    ],
    "name:ukr_x_preferred":[
        "\u0420\u0438\u0447\u043c\u043e\u043d\u0434"
    ],
    "name:urd_x_preferred":[
        "\u0631\u0686\u0645\u0646\u0688"
    ],
    "name:vol_x_preferred":[
        "Richmond"
    ],
    "name:yid_x_preferred":[
        "\u05e8\u05d9\u05d8\u05e9\u05de\u05d0\u05e0\u05d3"
    ],
    "name:zho_x_preferred":[
        "\u91cc\u58eb\u6ee1"
    ],
    "wof:name":"Richmond",
    "wof:placetype":"locality"
},
  "geometry": {"coordinates":[-67.6593,46.0749],"type":"Point"}
}