{
  "type": "Feature",
  "properties": {
    "gn:admin1_code":"2.0",
    "gn:admin2_code":"5915",
    "gn:asciiname":"Brunswick Beach",
    "gn:country_code":"CA",
    "gn:dem":17,
    "gn:feature_class":"P",
    "gn:feature_code":"PPLL",
    "gn:name":"Brunswick Beach",
    "gn:population":0,
    "gn:timezone":"America/Vancouver",
    "iso:country":"CA",
    "wof:name":"Brunswick Beach",
    "wof:placetype":"locality"
},
  "geometry": {"coordinates":[-123.24341,49.47214],"type":"Point"}
}