{
  "type": "Feature",
  "properties": {
    "gn:admin1_code":"10",
    "gn:admin2_code":"17.0",
    "gn:admin3_code":"38010.0",
    "gn:asciiname":"Gentilly",
    "gn:country_code":"CA",
    "gn:dem":17,
    "gn:feature_class":"P",
    "gn:feature_code":"PPL",
    "gn:name":"Gentilly",
    "gn:population":0,
    "gn:timezone":"America/Toronto",
    "iso:country":"CA",
    "name:fra_x_preferred":[
        "Gentilly"
    ],
    "wof:name":"Gentilly",
    "wof:placetype":"locality"
},
  "geometry": {"coordinates":[-72.2741,46.40005],"type":"Point"}
}