{
  "type": "Feature",
  "properties": {
    "gn:admin1_code":"8",
    "gn:asciiname":"The Ninth",
    "gn:country_code":"CA",
    "gn:dem":82,
    "gn:feature_class":"P",
    "gn:feature_code":"PPL",
    "gn:name":"The Ninth",
    "gn:population":0,
    "gn:timezone":"America/Toronto",
    "iso:country":"CA",
    "wof:name":"The Ninth",
    "wof:placetype":"locality"
},
  "geometry": {"coordinates":[-75.26444000000002,45.15278],"type":"Point"}
}