{
  "type": "Feature",
  "properties": {
    "gn:admin1_code":"8",
    "gn:asciiname":"Pottersburg",
    "gn:country_code":"CA",
    "gn:dem":264,
    "gn:feature_class":"P",
    "gn:feature_code":"PPL",
    "gn:name":"Pottersburg",
    "gn:population":0,
    "gn:timezone":"America/Toronto",
    "iso:country":"CA",
    "wof:name":"Pottersburg",
    "wof:placetype":"locality"
},
  "geometry": {"coordinates":[-81.18056,42.99806],"type":"Point"}
}