{
  "type": "Feature",
  "properties": {
    "gn:admin1_code":"1",
    "gn:asciiname":"Tolman",
    "gn:country_code":"CA",
    "gn:dem":710,
    "gn:feature_class":"P",
    "gn:feature_code":"PPLL",
    "gn:name":"Tolman",
    "gn:population":0,
    "gn:timezone":"America/Edmonton",
    "iso:country":"CA",
    "wof:name":"Tolman",
    "wof:placetype":"locality"
},
  "geometry": {"coordinates":[-113.01860000000001,51.83342],"type":"Point"}
}