{
  "type": "Feature",
  "properties": {
    "gn:admin1_code":"3",
    "gn:asciiname":"Otter Falls",
    "gn:country_code":"CA",
    "gn:dem":281,
    "gn:feature_class":"P",
    "gn:feature_code":"PPLL",
    "gn:name":"Otter Falls",
    "gn:population":0,
    "gn:timezone":"America/Winnipeg",
    "iso:country":"CA",
    "wof:name":"Otter Falls",
    "wof:placetype":"locality"
},
  "geometry": {"coordinates":[-95.81113999999999,50.1467],"type":"Point"}
}