{
  "type": "Feature",
  "properties": {
    "gn:admin1_code":"7.0",
    "gn:asciiname":"Devils Island",
    "gn:country_code":"CA",
    "gn:dem":5,
    "gn:feature_class":"P",
    "gn:feature_code":"PPLL",
    "gn:name":"Devils Island",
    "gn:population":0,
    "gn:timezone":"America/Halifax",
    "iso:country":"CA",
    "wof:name":"Devils Island",
    "wof:placetype":"locality"
},
  "geometry": {"coordinates":[-63.45928000000001,44.58089],"type":"Point"}
}