{
  "type": "Feature",
  "properties": {
    "gn:admin1_code":"1",
    "gn:asciiname":"Stowe",
    "gn:country_code":"CA",
    "gn:dem":986,
    "gn:feature_class":"P",
    "gn:feature_code":"PPLL",
    "gn:name":"Stowe",
    "gn:population":0,
    "gn:timezone":"America/Edmonton",
    "iso:country":"CA",
    "name:cat_x_preferred":[
        "Stowe"
    ],
    "name:ceb_x_preferred":[
        "Stowe"
    ],
    "name:ces_x_preferred":[
        "Stowe"
    ],
    "name:deu_x_preferred":[
        "Stowe"
    ],
    "name:fas_x_preferred":[
        "\u0627\u0633\u062a\u0648"
    ],
    "name:fra_x_preferred":[
        "Stowe"
    ],
    "name:ita_x_preferred":[
        "Stowe"
    ],
    "name:jpn_x_preferred":[
        "\u30b9\u30c8\u30a6"
    ],
    "name:nld_x_preferred":[
        "Stowe"
    ],
    "name:pol_x_preferred":[
        "Stowe"
    ],
    "name:por_x_preferred":[
        "Stowe"
    ],
    "name:rus_x_preferred":[
        "\u0421\u0442\u043e\u0443"
    ],
    "name:srp_x_preferred":[
        "\u0421\u0442\u043e\u0443"
    ],
    "name:swe_x_preferred":[
        "Stowe"
    ],
    "name:vol_x_preferred":[
        "Stowe"
    ],
    "wof:name":"Stowe",
    "wof:placetype":"locality"
},
  "geometry": {"coordinates":[-113.50189,49.6833],"type":"Point"}
}