{
  "type": "Feature",
  "properties": {
    "gn:admin1_code":"8.0",
    "gn:asciiname":"Westview",
    "gn:country_code":"CA",
    "gn:dem":187,
    "gn:feature_class":"P",
    "gn:feature_code":"PPL",
    "gn:name":"Westview",
    "gn:population":0,
    "gn:timezone":"America/Toronto",
    "iso:country":"CA",
    "name:deu_x_preferred":[
        "Westview"
    ],
    "wof:name":"Westview",
    "wof:placetype":"locality"
},
  "geometry": {"coordinates":[-77.90805999999998,44.34389],"type":"Point"}
}