{
  "type": "Feature",
  "properties": {
    "gn:admin1_code":"8",
    "gn:asciiname":"Midhurst Station",
    "gn:country_code":"CA",
    "gn:dem":234,
    "gn:feature_class":"P",
    "gn:feature_code":"PPL",
    "gn:name":"Midhurst Station",
    "gn:population":0,
    "gn:timezone":"America/Toronto",
    "iso:country":"CA",
    "wof:name":"Midhurst Station",
    "wof:placetype":"locality"
},
  "geometry": {"coordinates":[-79.75434,44.44411],"type":"Point"}
}