{
  "type": "Feature",
  "properties": {
    "gn:admin1_code":"9.0",
    "gn:asciiname":"Albion Cross",
    "gn:country_code":"CA",
    "gn:dem":14,
    "gn:feature_class":"P",
    "gn:feature_code":"PPLL",
    "gn:name":"Albion Cross",
    "gn:population":0,
    "gn:timezone":"America/Halifax",
    "iso:country":"CA",
    "wof:name":"Albion Cross",
    "wof:placetype":"locality"
},
  "geometry": {"coordinates":[-62.48194,46.3334],"type":"Point"}
}