{
  "type": "Feature",
  "properties": {
    "gn:country":"CA",
    "gn:fcode":"PPL",
    "gn:population":2362,
    "iso:country":"CA",
    "name:eng_x_preferred":[
        "Wabana"
    ],
    "qs:name":"Wabana",
    "qs:name_adm0":"Canada",
    "qs:name_adm1":"Newfoundland and Labrador",
    "qs:photos":170,
    "qs:photos_1k":34,
    "qs:photos_9k":1,
    "qs:photos_9r":4,
    "qs:photos_all":170,
    "qs:photos_sr":4,
    "qs:placetype":"Town",
    "qs:pop_sr":"4",
    "wd:wordcount":20,
    "wof:name":"Wabana",
    "wof:placetype":"locality",
    "wof:population":2362
},
  "geometry": {"coordinates":[-52.94806,47.63319],"type":"Point"}
}