{
  "type": "Feature",
  "properties": {
    "gn:admin1_code":"8.0",
    "gn:asciiname":"Allan Mills",
    "gn:country_code":"CA",
    "gn:dem":176,
    "gn:feature_class":"P",
    "gn:feature_code":"PPL",
    "gn:name":"Allan Mills",
    "gn:population":0,
    "gn:timezone":"America/Toronto",
    "iso:country":"CA",
    "wof:name":"Allan Mills",
    "wof:placetype":"locality"
},
  "geometry": {"coordinates":[-77.72221999999999,44.40833],"type":"Point"}
}