{
  "type": "Feature",
  "properties": {
    "iso:country":"CA",
    "name:deu_x_preferred":[
        "Beaverdell"
    ],
    "name:eng_x_preferred":[
        "Beaverdell"
    ],
    "name:fas_x_preferred":[
        "\u0628\u06cc\u0648\u0631\u062f\u0644"
    ],
    "name:nld_x_preferred":[
        "Beaverdell"
    ],
    "qs_pg:aaroncc":"CA",
    "qs_pg:name":"Beaverdell",
    "qs_pg:name_adm0":"Canada",
    "qs_pg:name_adm1":"British Columbia",
    "qs_pg:photos":81,
    "qs_pg:photos_1k":16,
    "qs_pg:photos_9k":1,
    "qs_pg:photos_9r":3,
    "qs_pg:photos_all":81,
    "qs_pg:photos_sr":3,
    "qs_pg:pop_sr":0,
    "qs_pg:qs_pg_placetype":"locality",
    "qs_pg:qs_pg_placetype_gp":"Town",
    "qs_pg:woe_adm0":23424775,
    "woe:adm0_id":23424775,
    "woe:name_adm0":"Canada",
    "woe:name_adm1":"British Columbia",
    "woe:placetype":"Town",
    "wof:name":"Beaverdell",
    "wof:placetype":"locality"
},
  "geometry": {"coordinates":[-119.10338400000001,49.410498],"type":"Point"}
}