{
  "type": "Feature",
  "properties": {
    "gn:admin1_code":"7",
    "gn:asciiname":"Upper Economy",
    "gn:country_code":"CA",
    "gn:dem":27,
    "gn:feature_class":"P",
    "gn:feature_code":"PPL",
    "gn:name":"Upper Economy",
    "gn:population":0,
    "gn:timezone":"America/Halifax",
    "iso:country":"CA",
    "wof:name":"Upper Economy",
    "wof:placetype":"locality"
},
  "geometry": {"coordinates":[-63.83664,45.38908],"type":"Point"}
}