{
  "type": "Feature",
  "properties": {
    "gn:admin1_code":"9",
    "gn:asciiname":"Lakeville",
    "gn:country_code":"CA",
    "gn:dem":19,
    "gn:feature_class":"P",
    "gn:feature_code":"PPLL",
    "gn:name":"Lakeville",
    "gn:population":0,
    "gn:timezone":"America/Halifax",
    "iso:country":"CA",
    "name:ben_x_preferred":[
        "\u09b2\u09c7\u0995\u09ad\u09bf\u09b2\u09c7"
    ],
    "name:cat_x_preferred":[
        "Lakeville"
    ],
    "name:ceb_x_preferred":[
        "Lakeville"
    ],
    "name:deu_x_preferred":[
        "Lakeville"
    ],
    "name:ell_x_preferred":[
        "\u039b\u03ad\u03b9\u03ba\u03b2\u03b9\u03bb"
    ],
    "name:fra_x_preferred":[
        "Lakeville"
    ],
    "name:hin_x_preferred":[
        "\u0932\u0947\u0915\u0935\u093f\u0932"
    ],
    "name:hun_x_preferred":[
        "Lakeville"
    ],
    "name:ind_x_preferred":[
        "Lakeville"
    ],
    "name:ita_x_preferred":[
        "Lakeville"
    ],
    "name:kor_x_preferred":[
        "\ub808\uc774\ud06c\ube4c"
    ],
    "name:nld_x_preferred":[
        "Lakeville"
    ],
    "name:pol_x_preferred":[
        "Lakeville"
    ],
    "name:por_x_preferred":[
        "Lakeville"
    ],
    "name:rus_x_preferred":[
        "\u041b\u0435\u0439\u043a\u0432\u0438\u043b\u043b"
    ],
    "name:srp_x_preferred":[
        "\u041b\u0435\u0458\u043a\u0432\u0438\u043b"
    ],
    "name:vol_x_preferred":[
        "Lakeville"
    ],
    "wof:name":"Lakeville",
    "wof:placetype":"locality"
},
  "geometry": {"coordinates":[-62.09861,46.4668],"type":"Point"}
}