{
  "type": "Feature",
  "properties": {
    "gn:admin1_code":"1.0",
    "gn:asciiname":"Cadotte Lake",
    "gn:country_code":"CA",
    "gn:dem":573,
    "gn:feature_class":"P",
    "gn:feature_code":"PPL",
    "gn:name":"Cadotte Lake",
    "gn:population":0,
    "gn:timezone":"America/Edmonton",
    "iso:country":"CA",
    "name:ceb_x_preferred":[
        "Cadotte Lake"
    ],
    "name:fra_x_preferred":[
        "Cadotte Lake"
    ],
    "wof:name":"Cadotte Lake",
    "wof:placetype":"locality"
},
  "geometry": {"coordinates":[-116.38083,56.46722],"type":"Point"}
}