{
  "type": "Feature",
  "properties": {
    "gn:admin1_code":"4",
    "gn:asciiname":"Purdys Corner",
    "gn:country_code":"CA",
    "gn:dem":48,
    "gn:feature_class":"P",
    "gn:feature_code":"PPLL",
    "gn:name":"Purdys Corner",
    "gn:population":0,
    "gn:timezone":"America/Moncton",
    "iso:country":"CA",
    "wof:name":"Purdys Corner",
    "wof:placetype":"locality"
},
  "geometry": {"coordinates":[-66.11555,45.25015],"type":"Point"}
}