{
  "type": "Feature",
  "properties": {
    "gn:admin1_code":"8",
    "gn:asciiname":"Havergal",
    "gn:country_code":"CA",
    "gn:dem":344,
    "gn:feature_class":"P",
    "gn:feature_code":"PPL",
    "gn:name":"Havergal",
    "gn:population":0,
    "gn:timezone":"America/Toronto",
    "iso:country":"CA",
    "wof:name":"Havergal",
    "wof:placetype":"locality"
},
  "geometry": {"coordinates":[-77.62333000000002,45.23528],"type":"Point"}
}