{
  "type": "Feature",
  "properties": {
    "gn:admin1_code":"7",
    "gn:asciiname":"Old Cobequid Road",
    "gn:country_code":"CA",
    "gn:dem":52,
    "gn:feature_class":"P",
    "gn:feature_code":"PPL",
    "gn:name":"Old Cobequid Road",
    "gn:population":0,
    "gn:timezone":"America/Halifax",
    "iso:country":"CA",
    "wof:name":"Old Cobequid Road",
    "wof:placetype":"locality"
},
  "geometry": {"coordinates":[-63.64624,44.76708],"type":"Point"}
}