{
  "type": "Feature",
  "properties": {
    "gn:admin1_code":"8",
    "gn:asciiname":"Hayes Corners",
    "gn:country_code":"CA",
    "gn:dem":124,
    "gn:feature_class":"P",
    "gn:feature_code":"PPL",
    "gn:name":"Hayes Corners",
    "gn:population":0,
    "gn:timezone":"America/Toronto",
    "iso:country":"CA",
    "wof:name":"Hayes Corners",
    "wof:placetype":"locality"
},
  "geometry": {"coordinates":[-75.92192,44.59265],"type":"Point"}
}