{
  "type": "Feature",
  "properties": {
    "gn:admin1_code":"11",
    "gn:asciiname":"Edmore",
    "gn:country_code":"CA",
    "gn:dem":589,
    "gn:feature_class":"P",
    "gn:feature_code":"PPLL",
    "gn:name":"Edmore",
    "gn:population":0,
    "gn:timezone":"America/Regina",
    "iso:country":"CA",
    "name:ceb_x_preferred":[
        "Edmore"
    ],
    "name:deu_x_preferred":[
        "Edmore"
    ],
    "name:fra_x_preferred":[
        "Edmore"
    ],
    "name:ita_x_preferred":[
        "Edmore"
    ],
    "name:nld_x_preferred":[
        "Edmore"
    ],
    "name:pol_x_preferred":[
        "Edmore"
    ],
    "name:srp_x_preferred":[
        "\u0415\u0434\u043c\u043e\u0440"
    ],
    "name:vol_x_preferred":[
        "Edmore"
    ],
    "wof:name":"Edmore",
    "wof:placetype":"locality"
},
  "geometry": {"coordinates":[-103.58432000000001,51.56672],"type":"Point"}
}