{
  "type": "Feature",
  "properties": {
    "gn:admin1_code":"11.0",
    "gn:asciiname":"Carlyle Lake Resort",
    "gn:country_code":"CA",
    "gn:dem":757,
    "gn:feature_class":"P",
    "gn:feature_code":"PPL",
    "gn:name":"Carlyle Lake Resort",
    "gn:population":0,
    "gn:timezone":"America/Regina",
    "iso:country":"CA",
    "wof:name":"Carlyle Lake Resort",
    "wof:placetype":"locality"
},
  "geometry": {"coordinates":[-102.26715,49.75002],"type":"Point"}
}