{
  "type": "Feature",
  "properties": {
    "gn:admin1_code":"7",
    "gn:asciiname":"South Side Basin of River Denys",
    "gn:country_code":"CA",
    "gn:dem":16,
    "gn:feature_class":"P",
    "gn:feature_code":"PPL",
    "gn:name":"South Side Basin of River Denys",
    "gn:population":0,
    "gn:timezone":"America/Halifax",
    "iso:country":"CA",
    "wof:name":"South Side Basin of River Denys",
    "wof:placetype":"locality"
},
  "geometry": {"coordinates":[-61.03045,45.87974000000001],"type":"Point"}
}