{
  "type": "Feature",
  "properties": {
    "iso:country":"CA",
    "name:cat_x_preferred":[
        "Neil's Harbour"
    ],
    "name:eng_x_preferred":[
        "Neils Harbour"
    ],
    "name:eng_x_variant":[
        "Neil's Harbour"
    ],
    "name:gla_x_preferred":[
        "Acarsaid N\u00ecll"
    ],
    "name:nld_x_preferred":[
        "Neil's Harbour"
    ],
    "qs:name":"Neils Harbour",
    "qs:name_adm0":"Canada",
    "qs:name_adm1":"Nova Scotia",
    "qs:photos":670,
    "qs:photos_1k":136,
    "qs:photos_9k":3,
    "qs:photos_9r":5,
    "qs:photos_all":670,
    "qs:photos_sr":8,
    "qs:placetype":"Town",
    "qs:pop_sr":"0",
    "wd:wordcount":200,
    "wof:name":"Neils Harbour",
    "wof:placetype":"locality"
},
  "geometry": {"coordinates":[-60.327987,46.780758],"type":"Point"}
}