{
  "type": "Feature",
  "properties": {
    "gn:admin1_code":"3.0",
    "gn:asciiname":"Cadurcis",
    "gn:country_code":"CA",
    "gn:dem":585,
    "gn:feature_class":"P",
    "gn:feature_code":"PPLL",
    "gn:name":"Cadurcis",
    "gn:population":0,
    "gn:timezone":"America/Winnipeg",
    "iso:country":"CA",
    "wof:name":"Cadurcis",
    "wof:placetype":"locality"
},
  "geometry": {"coordinates":[-100.02366000000001,50.24082],"type":"Point"}
}