{
  "type": "Feature",
  "properties": {
    "gn:admin1_code":"14.0",
    "gn:asciiname":"Amadjuak",
    "gn:country_code":"CA",
    "gn:dem":6,
    "gn:feature_class":"P",
    "gn:feature_code":"PPLL",
    "gn:name":"Amadjuak",
    "gn:population":0,
    "gn:timezone":"America/Iqaluit",
    "iso:country":"CA",
    "name:fas_x_preferred":[
        "\u0627\u0645\u0627\u062f\u062c\u0648\u0626\u0627\u06a9"
    ],
    "name:fra_x_preferred":[
        "Amadjuak"
    ],
    "wof:name":"Amadjuak",
    "wof:placetype":"locality"
},
  "geometry": {"coordinates":[-72.64827,64.01733],"type":"Point"}
}