{
  "type": "Feature",
  "properties": {
    "gn:admin1_code":"4",
    "gn:asciiname":"The Range",
    "gn:country_code":"CA",
    "gn:dem":14,
    "gn:feature_class":"P",
    "gn:feature_code":"PPL",
    "gn:name":"The Range",
    "gn:population":0,
    "gn:timezone":"America/Moncton",
    "iso:country":"CA",
    "name:bar_x_preferred":[
        "The Range"
    ],
    "wof:name":"The Range",
    "wof:placetype":"locality"
},
  "geometry": {"coordinates":[-65.90094999999999,46.06634],"type":"Point"}
}