{
  "type": "Feature",
  "properties": {
    "gn:admin1_code":"7",
    "gn:asciiname":"Elgin",
    "gn:country_code":"CA",
    "gn:dem":84,
    "gn:feature_class":"P",
    "gn:feature_code":"PPL",
    "gn:name":"Elgin",
    "gn:population":0,
    "gn:timezone":"America/Halifax",
    "iso:country":"CA",
    "wof:name":"Elgin",
    "wof:placetype":"locality"
},
  "geometry": {"coordinates":[-62.67014,45.42313],"type":"Point"}
}