{
  "type": "Feature",
  "properties": {
    "gn:admin1_code":"8",
    "gn:asciiname":"Morrish",
    "gn:country_code":"CA",
    "gn:dem":128,
    "gn:feature_class":"P",
    "gn:feature_code":"PPL",
    "gn:name":"Morrish",
    "gn:population":0,
    "gn:timezone":"America/Toronto",
    "iso:country":"CA",
    "wof:name":"Morrish",
    "wof:placetype":"locality"
},
  "geometry": {"coordinates":[-78.39394,43.96239],"type":"Point"}
}