{
  "type": "Feature",
  "properties": {
    "gn:admin1_code":"1.0",
    "gn:asciiname":"Brule Mines",
    "gn:country_code":"CA",
    "gn:dem":1283,
    "gn:feature_class":"P",
    "gn:feature_code":"PPLL",
    "gn:name":"Br\u00fbl\u00e9 Mines",
    "gn:population":0,
    "gn:timezone":"America/Edmonton",
    "iso:country":"CA",
    "wof:name":"Brule Mines",
    "wof:placetype":"locality"
},
  "geometry": {"coordinates":[-117.88569,53.30007],"type":"Point"}
}