{
  "type": "Feature",
  "properties": {
    "gn:admin1_code":"8",
    "gn:asciiname":"Ouellette",
    "gn:country_code":"CA",
    "gn:dem":218,
    "gn:feature_class":"P",
    "gn:feature_code":"PPL",
    "gn:name":"Ouellette",
    "gn:population":0,
    "gn:timezone":"America/Toronto",
    "iso:country":"CA",
    "name:deu_x_preferred":[
        "Ouellette"
    ],
    "name:fra_x_preferred":[
        "Ouellette"
    ],
    "name:rus_x_preferred":[
        "\u0423\u044d\u043b\u043b\u0435\u0442\u0442"
    ],
    "wof:name":"Ouellette",
    "wof:placetype":"locality"
},
  "geometry": {"coordinates":[-80.52389000000002,46.10389],"type":"Point"}
}