{
  "type": "Feature",
  "properties": {
    "gn:country":"CA",
    "gn:fcode":"PPL",
    "gn:population":0,
    "iso:country":"CA",
    "name:bre_x_preferred":[
        "Aquaforte"
    ],
    "name:cos_x_preferred":[
        "Aquaforte"
    ],
    "name:dan_x_preferred":[
        "Aquaforte"
    ],
    "name:deu_x_preferred":[
        "Aquaforte"
    ],
    "name:eng_x_preferred":[
        "Aquaforte"
    ],
    "name:fra_x_preferred":[
        "Aquaforte"
    ],
    "name:ind_x_preferred":[
        "Aquaforte"
    ],
    "name:ita_x_preferred":[
        "Aquaforte"
    ],
    "name:nds_x_preferred":[
        "Aquaforte"
    ],
    "name:nld_x_preferred":[
        "Aquaforte"
    ],
    "name:por_x_preferred":[
        "Aquaforte"
    ],
    "name:ron_x_preferred":[
        "Aquaforte"
    ],
    "name:spa_x_preferred":[
        "Aquaforte"
    ],
    "name:swe_x_preferred":[
        "Aquaforte"
    ],
    "name:tah_x_preferred":[
        "Aquaforte"
    ],
    "name:ukr_x_preferred":[
        "\u0410\u043a\u0432\u0430\u0444\u043e\u0440\u0442"
    ],
    "name:zho_x_preferred":[
        "\u963f\u5938\u798f\u7279"
    ],
    "qs:name":"Aquaforte",
    "qs:name_adm0":"Canada",
    "qs:name_adm1":"Newfoundland and Labrador",
    "qs:photos":5,
    "qs:photos_1k":1,
    "qs:photos_9k":1,
    "qs:photos_9r":1,
    "qs:photos_all":5,
    "qs:photos_sr":1,
    "qs:placetype":"Town",
    "qs:pop_sr":"0",
    "wd:wordcount":284,
    "wof:name":"Aquaforte",
    "wof:placetype":"locality",
    "wof:population":0
},
  "geometry": {"coordinates":[-52.96477,46.99989],"type":"Point"}
}