{
  "type": "Feature",
  "properties": {
    "gn:admin1_code":"2.0",
    "gn:asciiname":"Cedarvale",
    "gn:country_code":"CA",
    "gn:dem":211,
    "gn:feature_class":"P",
    "gn:feature_code":"PPL",
    "gn:name":"Cedarvale",
    "gn:population":0,
    "gn:timezone":"America/Vancouver",
    "iso:country":"CA",
    "wof:name":"Cedarvale",
    "wof:placetype":"locality"
},
  "geometry": {"coordinates":[-128.33275,55.01909000000001],"type":"Point"}
}