{
  "type": "Feature",
  "properties": {
    "gn:admin1_code":"8",
    "gn:asciiname":"Sunset Beach",
    "gn:country_code":"CA",
    "gn:dem":179,
    "gn:feature_class":"P",
    "gn:feature_code":"PPL",
    "gn:name":"Sunset Beach",
    "gn:population":0,
    "gn:timezone":"America/Toronto",
    "iso:country":"CA",
    "name:ceb_x_preferred":[
        "Sunset Beach"
    ],
    "name:deu_x_preferred":[
        "Sunset Beach"
    ],
    "name:fra_x_preferred":[
        "Sunset Beach"
    ],
    "name:ita_x_preferred":[
        "Sunset Beach"
    ],
    "name:por_x_preferred":[
        "Sunset Beach"
    ],
    "name:srp_x_preferred":[
        "\u0421\u0430\u043d\u0441\u0435\u0442 \u0411\u0438\u0447"
    ],
    "name:swe_x_preferred":[
        "Sunset Beach"
    ],
    "name:vol_x_preferred":[
        "Sunset Beach"
    ],
    "wof:name":"Sunset Beach",
    "wof:placetype":"locality"
},
  "geometry": {"coordinates":[-83.1125,42.05139000000001],"type":"Point"}
}