{
  "type": "Feature",
  "properties": {
    "gn:admin1_code":"8",
    "gn:asciiname":"Islay",
    "gn:country_code":"CA",
    "gn:dem":279,
    "gn:feature_class":"P",
    "gn:feature_code":"PPL",
    "gn:name":"Islay",
    "gn:population":0,
    "gn:timezone":"America/Toronto",
    "iso:country":"CA",
    "wof:name":"Islay",
    "wof:placetype":"locality"
},
  "geometry": {"coordinates":[-78.85512,44.46267],"type":"Point"}
}