{
  "type": "Feature",
  "properties": {
    "gn:admin1_code":"8",
    "gn:asciiname":"Islay",
    "gn:country_code":"CA",
    "gn:dem":279,
    "gn:feature_class":"P",
    "gn:feature_code":"PPL",
    "gn:name":"Islay",
    "gn:population":0,
    "gn:timezone":"America/Toronto",
    "iso:country":"CA",
    "name:afr_x_preferred":[
        "Islay"
    ],
    "name:bre_x_preferred":[
        "\u00ccle"
    ],
    "name:cat_x_preferred":[
        "Islay"
    ],
    "name:ceb_x_preferred":[
        "Islay"
    ],
    "name:ces_x_preferred":[
        "Islay"
    ],
    "name:cym_x_preferred":[
        "\u00ccle"
    ],
    "name:dan_x_preferred":[
        "Islay"
    ],
    "name:deu_x_preferred":[
        "Islay"
    ],
    "name:ell_x_preferred":[
        "\u0386\u03b9\u03bb\u03b1"
    ],
    "name:epo_x_preferred":[
        "Islay"
    ],
    "name:est_x_preferred":[
        "Islay"
    ],
    "name:eus_x_preferred":[
        "Islay"
    ],
    "name:fin_x_preferred":[
        "Islay"
    ],
    "name:fra_x_preferred":[
        "Islay"
    ],
    "name:gla_x_preferred":[
        "\u00ccle"
    ],
    "name:gle_x_preferred":[
        "\u00ccle"
    ],
    "name:glg_x_preferred":[
        "Islay"
    ],
    "name:heb_x_preferred":[
        "\u05d0\u05d9\u05d9\u05dc\u05d4"
    ],
    "name:hun_x_preferred":[
        "Islay"
    ],
    "name:ita_x_preferred":[
        "Islay"
    ],
    "name:jpn_x_preferred":[
        "\u30a2\u30a4\u30e9\u5cf6"
    ],
    "name:lat_x_preferred":[
        "Ila insula"
    ],
    "name:lit_x_preferred":[
        "Aila"
    ],
    "name:nds_x_preferred":[
        "Islay"
    ],
    "name:nld_x_preferred":[
        "Islay"
    ],
    "name:nno_x_preferred":[
        "Islay"
    ],
    "name:nor_x_preferred":[
        "Islay"
    ],
    "name:olo_x_preferred":[
        "\u00ccle"
    ],
    "name:pnb_x_preferred":[
        "\u0627\u0632\u0644\u06d2"
    ],
    "name:pol_x_preferred":[
        "Islay"
    ],
    "name:por_x_preferred":[
        "Islay"
    ],
    "name:rus_x_preferred":[
        "\u0410\u0439\u043b\u0435\u0439"
    ],
    "name:sco_x_preferred":[
        "Islay"
    ],
    "name:slk_x_preferred":[
        "Islay"
    ],
    "name:spa_x_preferred":[
        "Islay"
    ],
    "name:srp_x_preferred":[
        "\u0410\u0458\u043b\u0435\u0458"
    ],
    "name:swe_x_preferred":[
        "Islay"
    ],
    "name:tha_x_preferred":[
        "\u0e44\u0e2d\u0e40\u0e25\u0e22\u0e4c"
    ],
    "name:ukr_x_preferred":[
        "\u0410\u0439\u043b\u0435\u0439"
    ],
    "name:wuu_x_preferred":[
        "\u827e\u62c9\u5c9b"
    ],
    "name:zho_x_preferred":[
        "\u827e\u62c9\u5cf6"
    ],
    "wof:name":"Islay",
    "wof:placetype":"locality"
},
  "geometry": {"coordinates":[-78.85512,44.46267],"type":"Point"}
}