{
  "type": "Feature",
  "properties": {
    "gn:admin1_code":"8",
    "gn:asciiname":"Northfield Station",
    "gn:country_code":"CA",
    "gn:dem":99,
    "gn:feature_class":"P",
    "gn:feature_code":"PPL",
    "gn:name":"Northfield Station",
    "gn:population":0,
    "gn:timezone":"America/Toronto",
    "iso:country":"CA",
    "wof:name":"Northfield Station",
    "wof:placetype":"locality"
},
  "geometry": {"coordinates":[-74.95222,45.10556],"type":"Point"}
}