{
  "type": "Feature",
  "properties": {
    "gn:admin1_code":"8",
    "gn:asciiname":"Rat Rapids",
    "gn:country_code":"CA",
    "gn:dem":371,
    "gn:feature_class":"P",
    "gn:feature_code":"PPL",
    "gn:name":"Rat Rapids",
    "gn:population":0,
    "gn:timezone":"America/Toronto",
    "iso:country":"CA",
    "wof:name":"Rat Rapids",
    "wof:placetype":"locality"
},
  "geometry": {"coordinates":[-90.23345,51.18341],"type":"Point"}
}