{
  "type": "Feature",
  "properties": {
    "gn:admin1_code":"10",
    "gn:admin2_code":"16.0",
    "gn:admin3_code":"70012.0",
    "gn:asciiname":"Laberge",
    "gn:country_code":"CA",
    "gn:dem":36,
    "gn:feature_class":"P",
    "gn:feature_code":"PPL",
    "gn:name":"Laberge",
    "gn:population":0,
    "gn:timezone":"America/Toronto",
    "iso:country":"CA",
    "name:deu_x_preferred":[
        "Laberge"
    ],
    "name:fra_x_preferred":[
        "Laberge"
    ],
    "name:rus_x_preferred":[
        "\u041b\u0430\u0431\u0435\u0440\u0436"
    ],
    "wof:name":"Laberge",
    "wof:placetype":"locality"
},
  "geometry": {"coordinates":[-73.80654,45.28532],"type":"Point"}
}