{
  "type": "Feature",
  "properties": {
    "gn:country":"CA",
    "gn:fcode":"PPL",
    "gn:population":0,
    "iso:country":"CA",
    "name:ara_x_preferred":[
        "\u0628\u064a\u0644\u064a \u0647\u064a\u0644"
    ],
    "name:eng_x_preferred":[
        "Bible Hill"
    ],
    "name:fas_x_preferred":[
        "\u0628\u0627\u06cc\u0628\u0644 \u0647\u06cc\u0644"
    ],
    "name:gla_x_preferred":[
        "Cnoc a' Bhiobaill"
    ],
    "name:ita_x_preferred":[
        "Bible Hill"
    ],
    "name:jpn_x_preferred":[
        "\u30d0\u30a4\u30d6\u30eb\u30d2\u30eb"
    ],
    "name:nld_x_preferred":[
        "Bible Hill"
    ],
    "qs:name":"Bible Hill",
    "qs:name_adm0":"Canada",
    "qs:name_adm1":"Nova Scotia",
    "qs:photos":101,
    "qs:photos_1k":20,
    "qs:photos_9k":1,
    "qs:photos_9r":3,
    "qs:photos_all":101,
    "qs:photos_sr":3,
    "qs:placetype":"Town",
    "qs:pop_sr":"5",
    "wd:wordcount":35,
    "wof:name":"Bible Hill",
    "wof:placetype":"locality",
    "wof:population":0
},
  "geometry": {"coordinates":[-63.28198,45.36685],"type":"Point"}
}