{
  "type": "Feature",
  "properties": {
    "gn:admin1_code":"1",
    "gn:asciiname":"Imperial Mills",
    "gn:country_code":"CA",
    "gn:dem":585,
    "gn:feature_class":"P",
    "gn:feature_code":"PPL",
    "gn:name":"Imperial Mills",
    "gn:population":0,
    "gn:timezone":"America/Edmonton",
    "iso:country":"CA",
    "wof:name":"Imperial Mills",
    "wof:placetype":"locality"
},
  "geometry": {"coordinates":[-111.73518,55.00021],"type":"Point"}
}