{
  "type": "Feature",
  "properties": {
    "iso:country":"CA",
    "name:eng_x_preferred":[
        "Wirral"
    ],
    "name:fra_x_preferred":[
        "Wirral-Enniskillen"
    ],
    "name:nld_x_preferred":[
        "Wirral"
    ],
    "name:swe_x_preferred":[
        "Wirral"
    ],
    "qs_pg:aaroncc":"CA",
    "qs_pg:name":"Wirral",
    "qs_pg:name_adm0":"Canada",
    "qs_pg:name_adm1":"New Brunswick",
    "qs_pg:photos":18,
    "qs_pg:photos_1k":4,
    "qs_pg:photos_9k":1,
    "qs_pg:photos_9r":1,
    "qs_pg:photos_all":18,
    "qs_pg:photos_sr":1,
    "qs_pg:pop_sr":0,
    "qs_pg:qs_pg_placetype":"locality",
    "qs_pg:qs_pg_placetype_gp":"Town",
    "qs_pg:woe_adm0":23424775,
    "woe:adm0_id":23424775,
    "woe:name_adm0":"Canada",
    "woe:name_adm1":"New Brunswick",
    "woe:placetype":"Town",
    "wof:name":"Wirral",
    "wof:placetype":"locality"
},
  "geometry": {"coordinates":[-66.527795,45.539661],"type":"Point"}
}