{
  "type": "Feature",
  "properties": {
    "gn:admin1_code":"7",
    "gn:asciiname":"Joggin Bridge",
    "gn:country_code":"CA",
    "gn:dem":32,
    "gn:feature_class":"P",
    "gn:feature_code":"PPL",
    "gn:name":"Joggin Bridge",
    "gn:population":0,
    "gn:timezone":"America/Halifax",
    "iso:country":"CA",
    "wof:name":"Joggin Bridge",
    "wof:placetype":"locality"
},
  "geometry": {"coordinates":[-65.73773,44.59715],"type":"Point"}
}