{
  "type": "Feature",
  "properties": {
    "gn:admin1_code":"1",
    "gn:asciiname":"Kersey",
    "gn:country_code":"CA",
    "gn:dem":1007,
    "gn:feature_class":"P",
    "gn:feature_code":"PPLL",
    "gn:name":"Kersey",
    "gn:population":0,
    "gn:timezone":"America/Edmonton",
    "iso:country":"CA",
    "name:ceb_x_preferred":[
        "Kersey"
    ],
    "name:deu_x_preferred":[
        "Kersey"
    ],
    "name:fra_x_preferred":[
        "Kersey"
    ],
    "name:nld_x_preferred":[
        "Kersey"
    ],
    "name:pol_x_preferred":[
        "Kersey"
    ],
    "name:por_x_preferred":[
        "Kersey"
    ],
    "name:srp_x_preferred":[
        "\u041a\u0435\u043d\u0441\u0438"
    ],
    "name:swe_x_preferred":[
        "Kersey"
    ],
    "name:ukr_x_preferred":[
        "\u041a\u0435\u0440\u0441\u0456"
    ],
    "wof:name":"Kersey",
    "wof:placetype":"locality"
},
  "geometry": {"coordinates":[-113.81867,51.40011],"type":"Point"}
}