{
  "type": "Feature",
  "properties": {
    "gn:admin1_code":"1",
    "gn:asciiname":"Kersey",
    "gn:country_code":"CA",
    "gn:dem":1007,
    "gn:feature_class":"P",
    "gn:feature_code":"PPLL",
    "gn:name":"Kersey",
    "gn:population":0,
    "gn:timezone":"America/Edmonton",
    "iso:country":"CA",
    "wof:name":"Kersey",
    "wof:placetype":"locality"
},
  "geometry": {"coordinates":[-113.81867,51.40011],"type":"Point"}
}