{
  "type": "Feature",
  "properties": {
    "gn:admin1_code":"8",
    "gn:asciiname":"Rock's Mills",
    "gn:country_code":"CA",
    "gn:dem":233,
    "gn:feature_class":"P",
    "gn:feature_code":"PPL",
    "gn:name":"Rock's Mills",
    "gn:population":0,
    "gn:timezone":"America/Toronto",
    "iso:country":"CA",
    "wof:name":"Rock's Mills",
    "wof:placetype":"locality"
},
  "geometry": {"coordinates":[-80.66083,42.88944],"type":"Point"}
}