{
  "type": "Feature",
  "properties": {
    "gn:admin1_code":"8.0",
    "gn:asciiname":"Woodbine Gardens",
    "gn:country_code":"CA",
    "gn:dem":129,
    "gn:feature_class":"P",
    "gn:feature_code":"PPL",
    "gn:name":"Woodbine Gardens",
    "gn:population":0,
    "gn:timezone":"America/Toronto",
    "iso:country":"CA",
    "wof:name":"Woodbine Gardens",
    "wof:placetype":"locality"
},
  "geometry": {"coordinates":[-79.30139,43.70917],"type":"Point"}
}