{
  "type": "Feature",
  "properties": {
    "gn:admin1_code":"10.0",
    "gn:admin2_code":"3.0",
    "gn:admin3_code":"34090.0",
    "gn:asciiname":"Domaine-Denis",
    "gn:country_code":"CA",
    "gn:dem":147,
    "gn:feature_class":"P",
    "gn:feature_code":"PPL",
    "gn:name":"Domaine-Denis",
    "gn:population":0,
    "gn:timezone":"America/Toronto",
    "iso:country":"CA",
    "wof:name":"Domaine-Denis",
    "wof:placetype":"locality"
},
  "geometry": {"coordinates":[-72.26899,46.81669],"type":"Point"}
}