{
  "type": "Feature",
  "properties": {
    "gn:admin1_code":"7",
    "gn:asciiname":"Port Saxon",
    "gn:country_code":"CA",
    "gn:dem":17,
    "gn:feature_class":"P",
    "gn:feature_code":"PPL",
    "gn:name":"Port Saxon",
    "gn:population":0,
    "gn:timezone":"America/Halifax",
    "iso:country":"CA",
    "wof:name":"Port Saxon",
    "wof:placetype":"locality"
},
  "geometry": {"coordinates":[-65.43595000000001,43.59387],"type":"Point"}
}