{
  "type": "Feature",
  "properties": {
    "gn:admin1_code":"5",
    "gn:asciiname":"Hannah Cove",
    "gn:country_code":"CA",
    "gn:dem":110,
    "gn:feature_class":"P",
    "gn:feature_code":"PPLL",
    "gn:name":"Hannah Cove",
    "gn:population":0,
    "gn:timezone":"America/St_Johns",
    "iso:country":"CA",
    "wof:name":"Hannah Cove",
    "wof:placetype":"locality"
},
  "geometry": {"coordinates":[-56.83155,49.6167],"type":"Point"}
}