{
  "type": "Feature",
  "properties": {
    "gn:country":"CA",
    "gn:fcode":"PPL",
    "gn:population":0,
    "iso:country":"CA",
    "name:ara_x_preferred":[
        "\u062a\u0631\u064a\u0628\u0627\u0633\u064a"
    ],
    "name:ceb_x_preferred":[
        "Trepassey"
    ],
    "name:eng_x_preferred":[
        "Trepassey"
    ],
    "name:fra_x_preferred":[
        "Trepassey"
    ],
    "name:ind_x_preferred":[
        "Trepassey"
    ],
    "name:jpn_x_preferred":[
        "\u30c8\u30ec\u30d1\u30c3\u30b7\u30fc"
    ],
    "name:nld_x_preferred":[
        "Trepassey"
    ],
    "name:por_x_preferred":[
        "Trepassey"
    ],
    "name:swe_x_preferred":[
        "Trepassey"
    ],
    "ne:ADM0CAP":0.0,
    "ne:ADM0NAME":"Canada",
    "ne:ADM0_A3":"CAN",
    "ne:ADM1NAME":"Newfoundland and Labrador",
    "ne:ADMIN1_COD":0,
    "ne:CAPALT":0,
    "ne:CHANGED":0,
    "ne:CHECKME":0,
    "ne:COMPARE":0,
    "ne:DIFFASCII":0,
    "ne:ELEVATION":0.0,
    "ne:FEATURECLA":"Populated place",
    "ne:GEONAMEID":-1,
    "ne:GEONAMESNO":"No GeoNames match due to small population, not in GeoNames, or poor NEV placement.",
    "ne:GN_POP":0,
    "ne:GTOPO30":0.0,
    "ne:ISO_A2":"CA",
    "ne:LABELRANK":0,
    "ne:LATITUDE":46.736978,
    "ne:LONGITUDE":-53.363291,
    "ne:LS_MATCH":1,
    "ne:LS_NAME":"Trepassey",
    "ne:MAX_AREAKM":1.0,
    "ne:MAX_AREAMI":0.0,
    "ne:MAX_BBXMAX":-53.358333,
    "ne:MAX_BBXMIN":-53.366667,
    "ne:MAX_BBYMAX":46.741667,
    "ne:MAX_BBYMIN":46.725,
    "ne:MAX_NATSCA":20.0,
    "ne:MAX_PERKM":4.0,
    "ne:MAX_PERMI":3.0,
    "ne:MAX_POP10":398,
    "ne:MAX_POP20":398,
    "ne:MAX_POP300":0,
    "ne:MAX_POP310":0,
    "ne:MAX_POP50":0,
    "ne:MEAN_BBXC":-53.3625,
    "ne:MEAN_BBYC":46.733333,
    "ne:MEGACITY":0,
    "ne:MIN_AREAKM":1.0,
    "ne:MIN_AREAMI":0.0,
    "ne:MIN_BBXMAX":-53.358333,
    "ne:MIN_BBXMIN":-53.366667,
    "ne:MIN_BBYMAX":46.741667,
    "ne:MIN_BBYMIN":46.725,
    "ne:MIN_PERKM":4.0,
    "ne:MIN_PERMI":3.0,
    "ne:NAME":"Trepassey",
    "ne:NAMEASCII":"Trepassey",
    "ne:NAMEDIFF":0,
    "ne:NATSCALE":20,
    "ne:POP1950":0,
    "ne:POP1955":0,
    "ne:POP1960":0,
    "ne:POP1965":0,
    "ne:POP1970":0,
    "ne:POP1975":0,
    "ne:POP1980":0,
    "ne:POP1985":0,
    "ne:POP1990":0,
    "ne:POP1995":0,
    "ne:POP2000":0,
    "ne:POP2005":0,
    "ne:POP2010":0,
    "ne:POP2015":0,
    "ne:POP2020":0,
    "ne:POP2025":0,
    "ne:POP2050":0,
    "ne:POP_MAX":398,
    "ne:POP_MIN":398,
    "ne:POP_OTHER":246,
    "ne:RANK_MAX":2,
    "ne:RANK_MIN":2,
    "ne:SCALERANK":7,
    "ne:SOV0NAME":"Canada",
    "ne:SOV_A3":"CAN",
    "ne:UN_FID":0,
    "ne:UN_LAT":0.0,
    "ne:UN_LONG":0.0,
    "ne:WORLDCITY":0,
    "ne:min_zoom":6.7,
    "wof:name":"Trepassey",
    "wof:placetype":"locality",
    "wof:population":0
},
  "geometry": {"coordinates":[-53.36329085449262,46.73697796537272],"type":"Point"}
}