{
  "type": "Feature",
  "properties": {
    "gn:admin1_code":"3.0",
    "gn:asciiname":"Alpine",
    "gn:country_code":"CA",
    "gn:dem":595,
    "gn:feature_class":"P",
    "gn:feature_code":"PPLL",
    "gn:name":"Alpine",
    "gn:population":0,
    "gn:timezone":"America/Winnipeg",
    "iso:country":"CA",
    "name:ceb_x_preferred":[
        "Alpine"
    ],
    "name:ces_x_preferred":[
        "Alpine"
    ],
    "name:dan_x_preferred":[
        "Alpine"
    ],
    "name:deu_x_preferred":[
        "Alpine"
    ],
    "name:fas_x_preferred":[
        "\u0622\u0644\u067e\u0627\u06cc\u0646"
    ],
    "name:fin_x_preferred":[
        "Alpine"
    ],
    "name:fra_x_preferred":[
        "Alpine"
    ],
    "name:hun_x_preferred":[
        "Alpine"
    ],
    "name:ita_x_preferred":[
        "Alpine"
    ],
    "name:jpn_x_preferred":[
        "\u30a2\u30eb\u30d1\u30a4\u30f3"
    ],
    "name:kor_x_preferred":[
        "\uc54c\ud30c\uc778"
    ],
    "name:nld_x_preferred":[
        "Alpine"
    ],
    "name:nor_x_preferred":[
        "Alpine"
    ],
    "name:pol_x_preferred":[
        "Alpine"
    ],
    "name:por_x_preferred":[
        "Alpine"
    ],
    "name:ron_x_preferred":[
        "Alpine"
    ],
    "name:rus_x_preferred":[
        "\u0410\u043b\u043f\u0430\u0439\u043d"
    ],
    "name:slk_x_preferred":[
        "Alpine"
    ],
    "name:spa_x_preferred":[
        "Alpine"
    ],
    "name:srp_x_preferred":[
        "\u0410\u043b\u043f\u0430\u0458\u043d"
    ],
    "name:swe_x_preferred":[
        "Alpine"
    ],
    "name:tam_x_preferred":[
        "\u0b85\u0bb2\u0bcd\u0baa\u0bc8\u0ba9\u0bcd"
    ],
    "name:tur_x_preferred":[
        "Alpine"
    ],
    "name:ukr_x_preferred":[
        "\u0415\u043b\u043f\u0430\u0439\u043d"
    ],
    "name:vol_x_preferred":[
        "Alpine"
    ],
    "name:zho_x_preferred":[
        "Alpine"
    ],
    "wof:name":"Alpine",
    "wof:placetype":"locality"
},
  "geometry": {"coordinates":[-101.49982,51.75029],"type":"Point"}
}