{
  "type": "Feature",
  "properties": {
    "gn:admin1_code":"3.0",
    "gn:asciiname":"Alpine",
    "gn:country_code":"CA",
    "gn:dem":595,
    "gn:feature_class":"P",
    "gn:feature_code":"PPLL",
    "gn:name":"Alpine",
    "gn:population":0,
    "gn:timezone":"America/Winnipeg",
    "iso:country":"CA",
    "wof:name":"Alpine",
    "wof:placetype":"locality"
},
  "geometry": {"coordinates":[-101.49982,51.75029],"type":"Point"}
}