{
  "type": "Feature",
  "properties": {
    "gn:admin1_code":"10",
    "gn:admin2_code":"15.0",
    "gn:admin3_code":"77012.0",
    "gn:asciiname":"Sommet-Vert",
    "gn:country_code":"CA",
    "gn:dem":330,
    "gn:feature_class":"P",
    "gn:feature_code":"PPL",
    "gn:name":"Sommet-Vert",
    "gn:population":0,
    "gn:timezone":"America/Toronto",
    "iso:country":"CA",
    "wof:name":"Sommet-Vert",
    "wof:placetype":"locality"
},
  "geometry": {"coordinates":[-74.07694000000002,46.02806],"type":"Point"}
}