{
  "type": "Feature",
  "properties": {
    "gn:admin1_code":"7",
    "gn:asciiname":"Springfield",
    "gn:country_code":"CA",
    "gn:dem":176,
    "gn:feature_class":"P",
    "gn:feature_code":"PPL",
    "gn:name":"Springfield",
    "gn:population":0,
    "gn:timezone":"America/Halifax",
    "iso:country":"CA",
    "name:ben_x_preferred":[
        "\u09b8\u09cd\u09aa\u09cd\u09b0\u09bf\u0982\u09ab\u09bf\u09b2\u09cd\u09a1"
    ],
    "name:gla_x_preferred":[
        "Springfield"
    ],
    "name:hin_x_preferred":[
        "\u0938\u094d\u092a\u094d\u0930\u093f\u0902\u0917\u092b\u093c\u0940\u0932\u094d\u0921"
    ],
    "name:ind_x_preferred":[
        "Springfield"
    ],
    "wof:name":"Springfield",
    "wof:placetype":"locality"
},
  "geometry": {"coordinates":[-64.86548999999999,44.63345],"type":"Point"}
}