{
  "type": "Feature",
  "properties": {
    "gn:admin1_code":"7",
    "gn:asciiname":"Springfield",
    "gn:country_code":"CA",
    "gn:dem":176,
    "gn:feature_class":"P",
    "gn:feature_code":"PPL",
    "gn:name":"Springfield",
    "gn:population":0,
    "gn:timezone":"America/Halifax",
    "iso:country":"CA",
    "name:gla_x_preferred":[
        "Springfield"
    ],
    "wof:name":"Springfield",
    "wof:placetype":"locality"
},
  "geometry": {"coordinates":[-64.86549000000001,44.63345],"type":"Point"}
}