{
  "type": "Feature",
  "properties": {
    "gn:country":"CA",
    "gn:fcode":"PPL",
    "gn:pop":0,
    "iso:country":"CA",
    "name:ceb_x_preferred":[
        "West St. Modeste"
    ],
    "name:deu_x_preferred":[
        "West St. Modeste"
    ],
    "name:eng_x_preferred":[
        "West St. Modeste"
    ],
    "name:fra_x_preferred":[
        "West St. Modeste"
    ],
    "name:nld_x_preferred":[
        "West St. Modeste"
    ],
    "name:swe_x_preferred":[
        "West St. Modeste"
    ],
    "qs:name":"West St. Modeste",
    "qs:name_adm0":"Canada",
    "qs:name_adm1":"Newfoundland and Labrador",
    "qs:photos":39,
    "qs:photos_1k":8,
    "qs:photos_9k":1,
    "qs:photos_9r":2,
    "qs:photos_all":39,
    "qs:photos_sr":2,
    "qs:placetype":"Town",
    "qs:pop_sr":"0",
    "wd:wordcount":68,
    "wof:name":"West St. Modeste",
    "wof:placetype":"locality",
    "wof:population":0
},
  "geometry": {"coordinates":[-56.69808,51.6001],"type":"Point"}
}