{
  "type": "Feature",
  "properties": {
    "gn:admin1_code":"2.0",
    "gn:asciiname":"Copper Mountain",
    "gn:country_code":"CA",
    "gn:dem":935,
    "gn:feature_class":"P",
    "gn:feature_code":"PPL",
    "gn:name":"Copper Mountain",
    "gn:population":0,
    "gn:timezone":"America/Vancouver",
    "iso:country":"CA",
    "name:rus_x_preferred":[
        "\u041a\u043e\u043f\u043f\u0435\u0440-\u041c\u0430\u0443\u043d\u0442\u0438\u043d"
    ],
    "wof:name":"Copper Mountain",
    "wof:placetype":"locality"
},
  "geometry": {"coordinates":[-120.54137,49.32472],"type":"Point"}
}