{
  "type": "Feature",
  "properties": {
    "gn:admin1_code":"7.0",
    "gn:asciiname":"Broad Cove Banks",
    "gn:country_code":"CA",
    "gn:dem":74,
    "gn:feature_class":"P",
    "gn:feature_code":"PPL",
    "gn:name":"Broad Cove Banks",
    "gn:population":0,
    "gn:timezone":"America/Halifax",
    "iso:country":"CA",
    "wof:name":"Broad Cove Banks",
    "wof:placetype":"locality"
},
  "geometry": {"coordinates":[-61.32173,46.22092],"type":"Point"}
}