{
  "type": "Feature",
  "properties": {
    "gn:admin1_code":"1",
    "gn:asciiname":"Simon Lakes",
    "gn:country_code":"CA",
    "gn:dem":624,
    "gn:feature_class":"P",
    "gn:feature_code":"PPLL",
    "gn:name":"Simon Lakes",
    "gn:population":0,
    "gn:timezone":"America/Edmonton",
    "iso:country":"CA",
    "wof:name":"Simon Lakes",
    "wof:placetype":"locality"
},
  "geometry": {"coordinates":[-116.63591,56.48348000000001],"type":"Point"}
}