{
  "type": "Feature",
  "properties": {
    "gn:admin1_code":"4",
    "gn:asciiname":"Germany",
    "gn:country_code":"CA",
    "gn:dem":135,
    "gn:feature_class":"P",
    "gn:feature_code":"PPLL",
    "gn:name":"Germany",
    "gn:population":0,
    "gn:timezone":"America/Moncton",
    "iso:country":"CA",
    "wof:name":"Germany",
    "wof:placetype":"locality"
},
  "geometry": {"coordinates":[-66.63217,45.56683],"type":"Point"}
}