{
  "type": "Feature",
  "properties": {
    "gn:admin1_code":"10",
    "gn:admin2_code":"15.0",
    "gn:admin3_code":"74005.0",
    "gn:asciiname":"La Chapelle",
    "gn:country_code":"CA",
    "gn:dem":69,
    "gn:feature_class":"P",
    "gn:feature_code":"PPL",
    "gn:name":"La Chapelle",
    "gn:population":0,
    "gn:timezone":"America/Toronto",
    "iso:country":"CA",
    "wof:name":"La Chapelle",
    "wof:placetype":"locality"
},
  "geometry": {"coordinates":[-74.00349,45.74782],"type":"Point"}
}