{
  "type": "Feature",
  "properties": {
    "gn:admin1_code":"8",
    "gn:asciiname":"Mullifarry",
    "gn:country_code":"CA",
    "gn:dem":249,
    "gn:feature_class":"P",
    "gn:feature_code":"PPL",
    "gn:name":"Mullifarry",
    "gn:population":0,
    "gn:timezone":"America/Toronto",
    "iso:country":"CA",
    "wof:name":"Mullifarry",
    "wof:placetype":"locality"
},
  "geometry": {"coordinates":[-81.6657,42.98086],"type":"Point"}
}