{
  "type": "Feature",
  "properties": {
    "gn:admin1_code":"8.0",
    "gn:asciiname":"Broadbent",
    "gn:country_code":"CA",
    "gn:dem":248,
    "gn:feature_class":"P",
    "gn:feature_code":"PPL",
    "gn:name":"Broadbent",
    "gn:population":0,
    "gn:timezone":"America/Toronto",
    "iso:country":"CA",
    "name:fra_x_preferred":[
        "Broadbent"
    ],
    "name:jpn_x_preferred":[
        "\u30d6\u30ed\u30fc\u30c9\u30d9\u30f3\u30c8"
    ],
    "name:rus_x_preferred":[
        "\u0411\u0440\u043e\u0434\u0431\u0435\u043d\u0442"
    ],
    "name:swe_x_preferred":[
        "Broadbent"
    ],
    "wof:name":"Broadbent",
    "wof:placetype":"locality"
},
  "geometry": {"coordinates":[-79.83556,45.44694000000001],"type":"Point"}
}