{
  "type": "Feature",
  "properties": {
    "iso:country":"CA",
    "qs_pg:aaroncc":"CA",
    "qs_pg:name":"Perkinsfield",
    "qs_pg:name_adm0":"Canada",
    "qs_pg:name_adm1":"Ontario",
    "qs_pg:photos":267,
    "qs_pg:photos_1k":54,
    "qs_pg:photos_9k":1,
    "qs_pg:photos_9r":4,
    "qs_pg:photos_all":267,
    "qs_pg:photos_sr":5,
    "qs_pg:pop_sr":0,
    "qs_pg:qs_pg_placetype":"locality",
    "qs_pg:qs_pg_placetype_gp":"Town",
    "qs_pg:woe_adm0":23424775,
    "woe:adm0_id":23424775,
    "woe:name_adm0":"Canada",
    "woe:name_adm1":"Ontario",
    "woe:placetype":"Town",
    "wof:name":"Perkinsfield",
    "wof:placetype":"locality"
},
  "geometry": {"coordinates":[-79.931225,44.690187],"type":"Point"}
}