{
  "type": "Feature",
  "properties": {
    "gn:admin1_code":"10",
    "gn:admin2_code":"7.0",
    "gn:admin3_code":"84090.0",
    "gn:asciiname":"Nichabau",
    "gn:country_code":"CA",
    "gn:dem":146,
    "gn:feature_class":"P",
    "gn:feature_code":"PPL",
    "gn:name":"Nichabau",
    "gn:population":0,
    "gn:timezone":"America/Toronto",
    "iso:country":"CA",
    "wof:name":"Nichabau",
    "wof:placetype":"locality"
},
  "geometry": {"coordinates":[-77.13472,45.96972],"type":"Point"}
}