{
  "type": "Feature",
  "properties": {
    "gn:admin1_code":"10",
    "gn:admin2_code":"5.0",
    "gn:admin3_code":"42100.0",
    "gn:asciiname":"Lac-Boissonneault",
    "gn:country_code":"CA",
    "gn:dem":217,
    "gn:feature_class":"P",
    "gn:feature_code":"PPL",
    "gn:name":"Lac-Boissonneault",
    "gn:population":0,
    "gn:timezone":"America/Toronto",
    "iso:country":"CA",
    "wof:name":"Lac-Boissonneault",
    "wof:placetype":"locality"
},
  "geometry": {"coordinates":[-71.90954000000001,45.60059],"type":"Point"}
}