{
  "type": "Feature",
  "properties": {
    "gn:admin1_code":"11",
    "gn:asciiname":"Elbourne",
    "gn:country_code":"CA",
    "gn:dem":560,
    "gn:feature_class":"P",
    "gn:feature_code":"PPLL",
    "gn:name":"Elbourne",
    "gn:population":0,
    "gn:timezone":"America/Regina",
    "iso:country":"CA",
    "wof:name":"Elbourne",
    "wof:placetype":"locality"
},
  "geometry": {"coordinates":[-104.63442000000001,51.13338],"type":"Point"}
}