{
  "type": "Feature",
  "properties": {
    "gn:country":"CA",
    "gn:fcode":"PPL",
    "gn:pop":0,
    "iso:country":"CA",
    "name:eng_x_preferred":[
        "Langdon"
    ],
    "name:fra_x_preferred":[
        "Langdon"
    ],
    "name:urd_x_preferred":[
        "\u0644\u06cc\u0646\u06af\u0688\u0646\u060c \u0627\u0644\u0628\u0631\u0679\u0627"
    ],
    "qs:name":"Langdon",
    "qs:name_adm0":"Canada",
    "qs:name_adm1":"Alberta",
    "qs:photos":177,
    "qs:photos_1k":36,
    "qs:photos_9k":1,
    "qs:photos_9r":4,
    "qs:photos_all":177,
    "qs:photos_sr":4,
    "qs:placetype":"Town",
    "qs:pop_sr":"0",
    "wd:wordcount":140,
    "wof:name":"Langdon",
    "wof:placetype":"locality",
    "wof:population":0
},
  "geometry": {"coordinates":[-113.6776,50.97399],"type":"Point"}
}