{
  "type": "Feature",
  "properties": {
    "gn:country":"CA",
    "gn:fcode":"PPL",
    "gn:population":0,
    "iso:country":"CA",
    "name:aze_x_preferred":[
        "Kardinal"
    ],
    "name:deu_x_preferred":[
        "Cardinal"
    ],
    "name:fas_x_preferred":[
        "\u06a9\u0627\u0631\u062f\u06cc\u0646\u0627\u0644"
    ],
    "name:fra_x_preferred":[
        "Cardinal"
    ],
    "name:glg_x_preferred":[
        "Cardinal"
    ],
    "name:hun_x_preferred":[
        "Cardinal"
    ],
    "name:ita_x_preferred":[
        "Cardinal"
    ],
    "name:jpn_x_preferred":[
        "\u30ab\u30fc\u30c7\u30a3\u30ca\u30eb"
    ],
    "name:kor_x_preferred":[
        "\uce74\ub514\ub110"
    ],
    "name:pol_x_preferred":[
        "Kardyna\u0142"
    ],
    "name:por_x_preferred":[
        "Cardinal"
    ],
    "name:ron_x_preferred":[
        "Cardinal"
    ],
    "name:spa_x_preferred":[
        "Cardinal"
    ],
    "qs_pg:aaroncc":"CA",
    "qs_pg:gn_country":"CA",
    "qs_pg:gn_fcode":"PPL",
    "qs_pg:gn_pop":0,
    "qs_pg:name":"Cardinal",
    "qs_pg:name_adm0":"Canada",
    "qs_pg:name_adm1":"Ontario",
    "qs_pg:photos":90,
    "qs_pg:photos_1k":18,
    "qs_pg:photos_9k":1,
    "qs_pg:photos_9r":3,
    "qs_pg:photos_all":90,
    "qs_pg:photos_sr":3,
    "qs_pg:pop_sr":0,
    "qs_pg:qs_pg_placetype":"locality",
    "qs_pg:qs_pg_placetype_gp":"Town",
    "qs_pg:woe_adm0":23424775,
    "woe:adm0_id":23424775,
    "woe:name_adm0":"Canada",
    "woe:name_adm1":"Ontario",
    "woe:placetype":"Town",
    "wof:name":"Cardinal",
    "wof:placetype":"locality"
},
  "geometry": {"coordinates":[-75.38263000000001,44.78341],"type":"Point"}
}