{
  "type": "Feature",
  "properties": {
    "gn:admin1_code":"7",
    "gn:asciiname":"Ogden",
    "gn:country_code":"CA",
    "gn:dem":39,
    "gn:feature_class":"P",
    "gn:feature_code":"PPL",
    "gn:name":"Ogden",
    "gn:population":0,
    "gn:timezone":"America/Halifax",
    "iso:country":"CA",
    "wof:name":"Ogden",
    "wof:placetype":"locality"
},
  "geometry": {"coordinates":[-61.63158000000001,45.34602],"type":"Point"}
}