{
  "type": "Feature",
  "properties": {
    "gn:admin1_code":"7",
    "gn:asciiname":"New Britain",
    "gn:country_code":"CA",
    "gn:dem":197,
    "gn:feature_class":"P",
    "gn:feature_code":"PPLL",
    "gn:name":"New Britain",
    "gn:population":0,
    "gn:timezone":"America/Halifax",
    "iso:country":"CA",
    "wof:name":"New Britain",
    "wof:placetype":"locality"
},
  "geometry": {"coordinates":[-64.03205,45.45016],"type":"Point"}
}