{
  "type": "Feature",
  "properties": {
    "gn:admin1_code":"1.0",
    "gn:asciiname":"Big Slough",
    "gn:country_code":"CA",
    "gn:dem":227,
    "gn:feature_class":"P",
    "gn:feature_code":"PPLL",
    "gn:name":"Big Slough",
    "gn:population":0,
    "gn:timezone":"America/Edmonton",
    "iso:country":"CA",
    "wof:name":"Big Slough",
    "wof:placetype":"locality"
},
  "geometry": {"coordinates":[-113.15217,58.81693000000001],"type":"Point"}
}