{
  "type": "Feature",
  "properties": {
    "gn:admin1_code":"8",
    "gn:asciiname":"Hall Landing",
    "gn:country_code":"CA",
    "gn:dem":192,
    "gn:feature_class":"P",
    "gn:feature_code":"PPL",
    "gn:name":"Hall Landing",
    "gn:population":0,
    "gn:timezone":"America/Toronto",
    "iso:country":"CA",
    "wof:name":"Hall Landing",
    "wof:placetype":"locality"
},
  "geometry": {"coordinates":[-78.26833000000001,44.14833],"type":"Point"}
}