{
  "type": "Feature",
  "properties": {
    "iso:country":"CA",
    "name:eng_x_preferred":[
        "Farmington"
    ],
    "name:hun_x_preferred":[
        "Farmington"
    ],
    "name:nld_x_preferred":[
        "Farmington"
    ],
    "name:urd_x_preferred":[
        "\u0641\u0627\u0631\u0645\u0646\u06af\u0679\u0646\u060c \u0628\u0631\u0679\u0634 \u06a9\u0648\u0644\u0645\u0628\u06cc\u0627"
    ],
    "name:urd_x_variant":[
        "\u0641\u0627\u0631\u0645\u0646\u06af\u0679\u0646"
    ],
    "qs_pg:aaroncc":"CA",
    "qs_pg:name":"Farmington",
    "qs_pg:name_adm0":"Canada",
    "qs_pg:name_adm1":"British Columbia",
    "qs_pg:photos":8,
    "qs_pg:photos_1k":2,
    "qs_pg:photos_9k":1,
    "qs_pg:photos_9r":1,
    "qs_pg:photos_all":8,
    "qs_pg:photos_sr":1,
    "qs_pg:pop_sr":0,
    "qs_pg:qs_pg_placetype":"locality",
    "qs_pg:qs_pg_placetype_gp":"Town",
    "qs_pg:woe_adm0":23424775,
    "woe:adm0_id":23424775,
    "woe:name_adm0":"Canada",
    "woe:name_adm1":"British Columbia",
    "woe:placetype":"Town",
    "wof:name":"Farmington",
    "wof:placetype":"locality"
},
  "geometry": {"coordinates":[-120.524654,55.927278],"type":"Point"}
}