{
  "type": "Feature",
  "properties": {
    "gn:admin1_code":"8",
    "gn:asciiname":"Fralick's Beach",
    "gn:country_code":"CA",
    "gn:dem":259,
    "gn:feature_class":"P",
    "gn:feature_code":"PPL",
    "gn:name":"Fralick's Beach",
    "gn:population":0,
    "gn:timezone":"America/Toronto",
    "iso:country":"CA",
    "wof:name":"Fralick's Beach",
    "wof:placetype":"locality"
},
  "geometry": {"coordinates":[-78.89139,44.20306],"type":"Point"}
}