{
  "type": "Feature",
  "properties": {
    "gn:admin1_code":"7",
    "gn:asciiname":"Habitant",
    "gn:country_code":"CA",
    "gn:dem":24,
    "gn:feature_class":"P",
    "gn:feature_code":"PPL",
    "gn:name":"Habitant",
    "gn:population":0,
    "gn:timezone":"America/Halifax",
    "iso:country":"CA",
    "wof:name":"Habitant",
    "wof:placetype":"locality"
},
  "geometry": {"coordinates":[-64.39891,45.15452],"type":"Point"}
}