{
  "type": "Feature",
  "properties": {
    "gn:admin1_code":"8",
    "gn:asciiname":"Lauriston",
    "gn:country_code":"CA",
    "gn:dem":405,
    "gn:feature_class":"P",
    "gn:feature_code":"PPL",
    "gn:name":"Lauriston",
    "gn:population":0,
    "gn:timezone":"America/Toronto",
    "iso:country":"CA",
    "wof:name":"Lauriston",
    "wof:placetype":"locality"
},
  "geometry": {"coordinates":[-80.72194,44.30472],"type":"Point"}
}