{
  "type": "Feature",
  "properties": {
    "gn:admin1_code":"9",
    "gn:asciiname":"Greenfield",
    "gn:country_code":"CA",
    "gn:dem":57,
    "gn:feature_class":"P",
    "gn:feature_code":"PPLL",
    "gn:name":"Greenfield",
    "gn:population":0,
    "gn:timezone":"America/Halifax",
    "iso:country":"CA",
    "wof:name":"Greenfield",
    "wof:placetype":"locality"
},
  "geometry": {"coordinates":[-62.73196,46.18341],"type":"Point"}
}