{
  "type": "Feature",
  "properties": {
    "gn:admin1_code":"10.0",
    "gn:admin2_code":"07",
    "gn:admin3_code":"80115.0",
    "gn:asciiname":"Brookdale",
    "gn:country_code":"CA",
    "gn:dem":207,
    "gn:feature_class":"P",
    "gn:feature_code":"PPL",
    "gn:name":"Brookdale",
    "gn:population":0,
    "gn:timezone":"America/Toronto",
    "iso:country":"CA",
    "name:ceb_x_preferred":[
        "Brookdale"
    ],
    "name:deu_x_preferred":[
        "Brookdale"
    ],
    "name:fra_x_preferred":[
        "Brookdale"
    ],
    "name:ita_x_preferred":[
        "Brookdale"
    ],
    "name:nld_x_preferred":[
        "Brookdale"
    ],
    "name:pol_x_preferred":[
        "Brookdale"
    ],
    "name:spa_x_preferred":[
        "Brookdale"
    ],
    "name:srp_x_preferred":[
        "\u0411\u0440\u0443\u043a\u0434\u0435\u0458\u043b"
    ],
    "name:swe_x_preferred":[
        "Brookdale"
    ],
    "name:vol_x_preferred":[
        "Brookdale"
    ],
    "wof:name":"Brookdale",
    "wof:placetype":"locality"
},
  "geometry": {"coordinates":[-74.80824,45.93005],"type":"Point"}
}