{
  "type": "Feature",
  "properties": {
    "gn:admin1_code":"8",
    "gn:asciiname":"Hay",
    "gn:country_code":"CA",
    "gn:dem":270,
    "gn:feature_class":"P",
    "gn:feature_code":"PPL",
    "gn:name":"Hay",
    "gn:population":0,
    "gn:timezone":"America/Toronto",
    "iso:country":"CA",
    "wof:name":"Hay",
    "wof:placetype":"locality"
},
  "geometry": {"coordinates":[-81.48362,43.36132],"type":"Point"}
}