{
  "type": "Feature",
  "properties": {
    "gn:admin1_code":"3.0",
    "gn:asciiname":"Clarkleigh",
    "gn:country_code":"CA",
    "gn:dem":251,
    "gn:feature_class":"P",
    "gn:feature_code":"PPLL",
    "gn:name":"Clarkleigh",
    "gn:population":0,
    "gn:timezone":"America/Winnipeg",
    "iso:country":"CA",
    "wof:name":"Clarkleigh",
    "wof:placetype":"locality"
},
  "geometry": {"coordinates":[-98.01511000000001,50.59442],"type":"Point"}
}