{
  "type": "Feature",
  "properties": {
    "gn:admin1_code":"8",
    "gn:asciiname":"Jumbo Gardens",
    "gn:country_code":"CA",
    "gn:dem":255,
    "gn:feature_class":"P",
    "gn:feature_code":"PPL",
    "gn:name":"Jumbo Gardens",
    "gn:population":0,
    "gn:timezone":"America/Thunder_Bay",
    "iso:country":"CA",
    "wof:name":"Jumbo Gardens",
    "wof:placetype":"locality"
},
  "geometry": {"coordinates":[-89.26403000000001,48.45184],"type":"Point"}
}