{
  "type": "Feature",
  "properties": {
    "iso:country":"CA",
    "name:eng_x_preferred":[
        "Wismer Commons"
    ],
    "name:nld_x_preferred":[
        "Wismer Commons"
    ],
    "qs:gn_adm0_cc":"US",
    "qs:gn_local":5130569,
    "qs:gn_nam_loc":"long beach",
    "qs:gn_namadm1":"NY",
    "qs:local_max":262,
    "qs:local_sum":580,
    "qs:localhoods":3,
    "qs:name":"Wismer Commons",
    "qs:name_adm0":"Canada",
    "qs:name_adm1":"Ontario",
    "qs:name_adm2":"York",
    "qs:name_local":"Markham Village",
    "qs:photo_max":50,
    "qs:photo_sum":124,
    "qs:placetype":"Suburb",
    "qs:quad_count":26,
    "qs:woe_adm0":23424775,
    "qs:woe_adm1":2344922,
    "qs:woe_adm2":29375112,
    "qs:woe_funk":"Grouping neighborhood",
    "qs:woe_lau":0,
    "qs:woe_local":55999583,
    "qs:woe_ver":"7.10.0",
    "wd:wordcount":230,
    "wof:lang":[
        "eng"
    ],
    "wof:name":"Wismer Commons",
    "wof:placetype":"neighbourhood"
},
  "geometry": {"coordinates":[-79.294094,43.893209],"type":"Point"}
}