{
  "type": "Feature",
  "properties": {
    "gn:admin1_code":"8",
    "gn:asciiname":"Fairground",
    "gn:country_code":"CA",
    "gn:dem":208,
    "gn:feature_class":"P",
    "gn:feature_code":"PPL",
    "gn:name":"Fairground",
    "gn:population":0,
    "gn:timezone":"America/Toronto",
    "iso:country":"CA",
    "wof:name":"Fairground",
    "wof:placetype":"locality"
},
  "geometry": {"coordinates":[-80.65971999999999,42.64917],"type":"Point"}
}