{
  "type": "Feature",
  "properties": {
    "gn:admin1_code":"10",
    "gn:admin2_code":"15.0",
    "gn:admin3_code":"77055.0",
    "gn:asciiname":"Lac-Laurel",
    "gn:country_code":"CA",
    "gn:dem":282,
    "gn:feature_class":"P",
    "gn:feature_code":"PPL",
    "gn:name":"Lac-Laurel",
    "gn:population":0,
    "gn:timezone":"America/Toronto",
    "iso:country":"CA",
    "wof:name":"Lac-Laurel",
    "wof:placetype":"locality"
},
  "geometry": {"coordinates":[-74.47379000000002,45.87421],"type":"Point"}
}