{
  "type": "Feature",
  "properties": {
    "gn:admin1_code":"11",
    "gn:asciiname":"Elmhurst",
    "gn:country_code":"CA",
    "gn:dem":689,
    "gn:feature_class":"P",
    "gn:feature_code":"PPLL",
    "gn:name":"Elmhurst",
    "gn:population":0,
    "gn:timezone":"America/Regina",
    "iso:country":"CA",
    "wof:name":"Elmhurst",
    "wof:placetype":"locality"
},
  "geometry": {"coordinates":[-108.73471000000001,53.65018000000001],"type":"Point"}
}