{
  "type": "Feature",
  "properties": {
    "gn:admin1_code":"11",
    "gn:asciiname":"Elmhurst",
    "gn:country_code":"CA",
    "gn:dem":689,
    "gn:feature_class":"P",
    "gn:feature_code":"PPLL",
    "gn:name":"Elmhurst",
    "gn:population":0,
    "gn:timezone":"America/Regina",
    "iso:country":"CA",
    "name:deu_x_preferred":[
        "Elmhurst"
    ],
    "name:fra_x_preferred":[
        "Elmhurst"
    ],
    "name:ita_x_preferred":[
        "Elmhurst"
    ],
    "name:nld_x_preferred":[
        "Elmhurst"
    ],
    "name:pol_x_preferred":[
        "Elmhurst"
    ],
    "name:por_x_preferred":[
        "Elmhurst"
    ],
    "name:slk_x_preferred":[
        "Elmhurst"
    ],
    "name:ukr_x_preferred":[
        "\u0415\u043b\u043c\u0433\u0435\u0440\u0441\u0442"
    ],
    "name:vol_x_preferred":[
        "Elmhurst"
    ],
    "wof:name":"Elmhurst",
    "wof:placetype":"locality"
},
  "geometry": {"coordinates":[-108.73471000000001,53.65018000000001],"type":"Point"}
}