{
  "type": "Feature",
  "properties": {
    "gn:admin1_code":"1.0",
    "gn:asciiname":"Donnelly",
    "gn:country_code":"CA",
    "gn:dem":590,
    "gn:feature_class":"P",
    "gn:feature_code":"PPL",
    "gn:name":"Donnelly",
    "gn:population":0,
    "gn:timezone":"America/Edmonton",
    "iso:country":"CA",
    "name:eng_x_preferred":[
        "Donnelly"
    ],
    "wof:name":"Donnelly",
    "wof:placetype":"locality"
},
  "geometry": {"coordinates":[-117.10545999999999,55.72786],"type":"Point"}
}