{
  "type": "Feature",
  "properties": {
    "gn:admin1_code":"14",
    "gn:asciiname":"Kivitoo",
    "gn:country_code":"CA",
    "gn:dem":142,
    "gn:feature_class":"P",
    "gn:feature_code":"PPLL",
    "gn:name":"Kivitoo",
    "gn:population":0,
    "gn:timezone":"America/Pangnirtung",
    "iso:country":"CA",
    "name:ces_x_preferred":[
        "Kivitoo"
    ],
    "name:fra_x_preferred":[
        "Kivitoo"
    ],
    "wof:name":"Kivitoo",
    "wof:placetype":"locality"
},
  "geometry": {"coordinates":[-64.86341999999999,67.93414],"type":"Point"}
}