{
  "type": "Feature",
  "properties": {
    "gn:admin1_code":"8.0",
    "gn:asciiname":"Crozier",
    "gn:country_code":"CA",
    "gn:dem":348,
    "gn:feature_class":"P",
    "gn:feature_code":"PPL",
    "gn:name":"Crozier",
    "gn:population":0,
    "gn:timezone":"America/Winnipeg",
    "iso:country":"CA",
    "wof:name":"Crozier",
    "wof:placetype":"locality"
},
  "geometry": {"coordinates":[-93.51701,48.61658],"type":"Point"}
}