{
  "type": "Feature",
  "properties": {
    "gn:admin1_code":"3.0",
    "gn:asciiname":"Chillon",
    "gn:country_code":"CA",
    "gn:dem":535,
    "gn:feature_class":"P",
    "gn:feature_code":"PPLL",
    "gn:name":"Chillon",
    "gn:population":0,
    "gn:timezone":"America/Winnipeg",
    "iso:country":"CA",
    "wof:name":"Chillon",
    "wof:placetype":"locality"
},
  "geometry": {"coordinates":[-101.2217,50.5764],"type":"Point"}
}