{
  "type": "Feature",
  "properties": {
    "gn:admin1_code":"10",
    "gn:admin2_code":"7.0",
    "gn:admin3_code":"81017.0",
    "gn:asciiname":"Parc-Glenwood",
    "gn:country_code":"CA",
    "gn:dem":74,
    "gn:feature_class":"P",
    "gn:feature_code":"PPL",
    "gn:name":"Parc-Glenwood",
    "gn:population":0,
    "gn:timezone":"America/Toronto",
    "iso:country":"CA",
    "wof:name":"Parc-Glenwood",
    "wof:placetype":"locality"
},
  "geometry": {"coordinates":[-75.83759000000001,45.39287],"type":"Point"}
}