{
  "type": "Feature",
  "properties": {
    "iso:country":"CA",
    "name:eng_x_preferred":[
        "East Haney"
    ],
    "name:unk_x_variant":[
        "East Haney"
    ],
    "qs:gn_local":0,
    "qs:local_max":291,
    "qs:local_sum":334,
    "qs:localhoods":2,
    "qs:name":"East Haney",
    "qs:name_adm0":"Canada",
    "qs:name_adm1":"British Columbia",
    "qs:name_adm2":"Greater Vancouver",
    "qs:name_local":"Central Maple Ridge",
    "qs:photo_max":105,
    "qs:photo_sum":291,
    "qs:placetype":"Suburb",
    "qs:quad_count":16,
    "qs:woe_adm0":23424775,
    "qs:woe_adm1":2344916,
    "qs:woe_adm2":29375222,
    "qs:woe_funk":"Grouping neighborhood",
    "qs:woe_lau":0,
    "qs:woe_local":55998844,
    "qs:woe_ver":"7.10.0",
    "wof:lang":[
        "eng"
    ],
    "wof:name":"East Haney",
    "wof:placetype":"neighbourhood"
},
  "geometry": {"coordinates":[-122.544741,49.216296],"type":"Point"}
}