{
  "type": "Feature",
  "properties": {
    "gn:admin1_code":"10.0",
    "gn:admin2_code":"14.0",
    "gn:admin3_code":"63055.0",
    "gn:asciiname":"Domaine-Beauport",
    "gn:country_code":"CA",
    "gn:dem":177,
    "gn:feature_class":"P",
    "gn:feature_code":"PPL",
    "gn:name":"Domaine-Beauport",
    "gn:population":0,
    "gn:timezone":"America/Toronto",
    "iso:country":"CA",
    "wof:name":"Domaine-Beauport",
    "wof:placetype":"locality"
},
  "geometry": {"coordinates":[-73.84459,45.95726],"type":"Point"}
}