{
  "type": "Feature",
  "properties": {
    "gn:admin1_code":"7",
    "gn:asciiname":"Jordan Falls",
    "gn:country_code":"CA",
    "gn:dem":10,
    "gn:feature_class":"P",
    "gn:feature_code":"PPL",
    "gn:name":"Jordan Falls",
    "gn:population":0,
    "gn:timezone":"America/Halifax",
    "iso:country":"CA",
    "wof:name":"Jordan Falls",
    "wof:placetype":"locality"
},
  "geometry": {"coordinates":[-65.23211999999999,43.81553],"type":"Point"}
}