{
  "type": "Feature",
  "properties": {
    "gn:admin1_code":"8",
    "gn:asciiname":"Hickory Beach",
    "gn:country_code":"CA",
    "gn:dem":254,
    "gn:feature_class":"P",
    "gn:feature_code":"PPL",
    "gn:name":"Hickory Beach",
    "gn:population":0,
    "gn:timezone":"America/Toronto",
    "iso:country":"CA",
    "wof:name":"Hickory Beach",
    "wof:placetype":"locality"
},
  "geometry": {"coordinates":[-78.67683000000002,44.48262],"type":"Point"}
}