{
  "type": "Feature",
  "properties": {
    "gn:admin1_code":"13",
    "gn:asciiname":"Trout Lake",
    "gn:country_code":"CA",
    "gn:dem":483,
    "gn:feature_class":"P",
    "gn:feature_code":"PPL",
    "gn:name":"Trout Lake",
    "gn:population":0,
    "gn:timezone":"America/Yellowknife",
    "iso:country":"CA",
    "wof:name":"Trout Lake",
    "wof:placetype":"locality"
},
  "geometry": {"coordinates":[-121.25306,60.43344],"type":"Point"}
}