{
  "type": "Feature",
  "properties": {
    "gn:admin1_code":"7.0",
    "gn:asciiname":"Denver",
    "gn:country_code":"CA",
    "gn:dem":46,
    "gn:feature_class":"P",
    "gn:feature_code":"PPL",
    "gn:name":"Denver",
    "gn:population":0,
    "gn:timezone":"America/Halifax",
    "iso:country":"CA",
    "wof:name":"Denver",
    "wof:placetype":"locality"
},
  "geometry": {"coordinates":[-62.10992,45.337],"type":"Point"}
}