{
  "type": "Feature",
  "properties": {
    "gn:admin1_code":"2",
    "gn:admin2_code":"5921.0",
    "gn:asciiname":"Extension",
    "gn:country_code":"CA",
    "gn:dem":116,
    "gn:feature_class":"P",
    "gn:feature_code":"PPL",
    "gn:name":"Extension",
    "gn:population":0,
    "gn:timezone":"America/Vancouver",
    "iso:country":"CA",
    "wof:name":"Extension",
    "wof:placetype":"locality"
},
  "geometry": {"coordinates":[-123.95271,49.09964],"type":"Point"}
}