{
  "type": "Feature",
  "properties": {
    "gn:admin1_code":"2",
    "gn:asciiname":"Eddontenajon",
    "gn:country_code":"CA",
    "gn:dem":852,
    "gn:feature_class":"P",
    "gn:feature_code":"PPL",
    "gn:name":"Eddontenajon",
    "gn:population":0,
    "gn:timezone":"America/Vancouver",
    "iso:country":"CA",
    "wof:name":"Eddontenajon",
    "wof:placetype":"locality"
},
  "geometry": {"coordinates":[-129.96222,57.81556],"type":"Point"}
}