{
  "type": "Feature",
  "properties": {
    "gn:admin1_code":"8",
    "gn:asciiname":"Edys Mills",
    "gn:country_code":"CA",
    "gn:dem":200,
    "gn:feature_class":"P",
    "gn:feature_code":"PPL",
    "gn:name":"Edys Mills",
    "gn:population":0,
    "gn:timezone":"America/Toronto",
    "iso:country":"CA",
    "wof:name":"Edys Mills",
    "wof:placetype":"locality"
},
  "geometry": {"coordinates":[-82.12303,42.73876],"type":"Point"}
}