{
  "type": "Feature",
  "properties": {
    "gn:admin1_code":"2",
    "gn:admin2_code":"5943.0",
    "gn:asciiname":"Hopetown",
    "gn:country_code":"CA",
    "gn:dem":20,
    "gn:feature_class":"P",
    "gn:feature_code":"PPL",
    "gn:name":"Hopetown",
    "gn:population":0,
    "gn:timezone":"America/Vancouver",
    "iso:country":"CA",
    "wof:name":"Hopetown",
    "wof:placetype":"locality"
},
  "geometry": {"coordinates":[-126.82227,50.92384000000001],"type":"Point"}
}