{
  "type": "Feature",
  "properties": {
    "gn:admin1_code":"7",
    "gn:asciiname":"Mount Pleasant",
    "gn:country_code":"CA",
    "gn:dem":67,
    "gn:feature_class":"P",
    "gn:feature_code":"PPL",
    "gn:name":"Mount Pleasant",
    "gn:population":0,
    "gn:timezone":"America/Halifax",
    "iso:country":"CA",
    "wof:name":"Mount Pleasant",
    "wof:placetype":"locality"
},
  "geometry": {"coordinates":[-64.43000000000001,44.2739],"type":"Point"}
}