{
  "type": "Feature",
  "properties": {
    "gn:admin1_code":"8",
    "gn:asciiname":"Field",
    "gn:country_code":"CA",
    "gn:dem":228,
    "gn:feature_class":"P",
    "gn:feature_code":"PPL",
    "gn:name":"Field",
    "gn:population":0,
    "gn:timezone":"America/Toronto",
    "iso:country":"CA",
    "wof:name":"Field",
    "wof:placetype":"locality"
},
  "geometry": {"coordinates":[-80.01638,46.51679],"type":"Point"}
}