{
  "type": "Feature",
  "properties": {
    "gn:admin1_code":"8",
    "gn:asciiname":"Field",
    "gn:country_code":"CA",
    "gn:dem":228,
    "gn:feature_class":"P",
    "gn:feature_code":"PPL",
    "gn:name":"Field",
    "gn:population":0,
    "gn:timezone":"America/Toronto",
    "iso:country":"CA",
    "name:bre_x_preferred":[
        "Field"
    ],
    "name:ceb_x_preferred":[
        "Field"
    ],
    "name:deu_x_preferred":[
        "Field"
    ],
    "name:fra_x_preferred":[
        "Field"
    ],
    "name:heb_x_preferred":[
        "\u05e9\u05d3\u05d4"
    ],
    "name:hye_x_preferred":[
        "\u0534\u0561\u0577\u057f"
    ],
    "name:ido_x_preferred":[
        "Feldo"
    ],
    "name:ita_x_preferred":[
        "Field"
    ],
    "name:jpn_x_preferred":[
        "\u30d5\u30a3\u30fc\u30eb\u30c9"
    ],
    "name:pol_x_preferred":[
        "Field"
    ],
    "name:rus_x_preferred":[
        "\u0424\u0438\u043b\u0434"
    ],
    "name:slv_x_preferred":[
        "Field"
    ],
    "name:spa_x_preferred":[
        "Campo"
    ],
    "name:swe_x_preferred":[
        "Field"
    ],
    "wof:name":"Field",
    "wof:placetype":"locality"
},
  "geometry": {"coordinates":[-80.01638,46.51679],"type":"Point"}
}