{
  "type": "Feature",
  "properties": {
    "gn:admin1_code":"11",
    "gn:asciiname":"Watertown",
    "gn:country_code":"CA",
    "gn:dem":494,
    "gn:feature_class":"P",
    "gn:feature_code":"PPLL",
    "gn:name":"Watertown",
    "gn:population":0,
    "gn:timezone":"America/Regina",
    "iso:country":"CA",
    "name:cat_x_preferred":[
        "Watertown"
    ],
    "name:ceb_x_preferred":[
        "Watertown"
    ],
    "name:deu_x_preferred":[
        "Watertown"
    ],
    "name:fas_x_preferred":[
        "\u0648\u0627\u062a\u0631\u062a\u0627\u0648\u0646"
    ],
    "name:fra_x_preferred":[
        "Watertown"
    ],
    "name:ita_x_preferred":[
        "Watertown"
    ],
    "name:jpn_x_preferred":[
        "\u30a6\u30a9\u30fc\u30bf\u30fc\u30bf\u30a6\u30f3"
    ],
    "name:kor_x_preferred":[
        "\uc6cc\ud130\ud0c0\uc6b4"
    ],
    "name:nld_x_preferred":[
        "Watertown"
    ],
    "name:nor_x_preferred":[
        "Watertown"
    ],
    "name:pol_x_preferred":[
        "Watertown"
    ],
    "name:por_x_preferred":[
        "Watertown"
    ],
    "name:rus_x_preferred":[
        "\u0423\u043e\u0442\u0435\u0440\u0442\u0430\u0443\u043d"
    ],
    "name:slk_x_preferred":[
        "Watertown"
    ],
    "name:spa_x_preferred":[
        "Watertown"
    ],
    "name:srp_x_preferred":[
        "\u0412\u043e\u0442\u0435\u0440\u0442\u0430\u0443\u043d"
    ],
    "name:swe_x_preferred":[
        "Watertown"
    ],
    "name:urd_x_preferred":[
        "\u0648\u0627\u0679\u0631\u0679\u0627\u0624\u0646"
    ],
    "name:vol_x_preferred":[
        "Watertown"
    ],
    "name:zho_x_preferred":[
        "\u6c83\u7279\u6566"
    ],
    "wof:name":"Watertown",
    "wof:placetype":"locality"
},
  "geometry": {"coordinates":[-105.26786,51.38337],"type":"Point"}
}