{
  "type": "Feature",
  "properties": {
    "iso:country":"CA",
    "qs_pg:aaroncc":"CA",
    "qs_pg:name":"Ste.-Foy",
    "qs_pg:name_adm0":"Canada",
    "qs_pg:name_adm1":"Qu\u00e9bec",
    "qs_pg:photos":1836,
    "qs_pg:photos_1k":372,
    "qs_pg:photos_9k":8,
    "qs_pg:photos_9r":9,
    "qs_pg:photos_all":1836,
    "qs_pg:photos_sr":14,
    "qs_pg:pop_sr":0,
    "qs_pg:qs_pg_placetype":"locality",
    "qs_pg:qs_pg_placetype_gp":"Town",
    "qs_pg:woe_adm0":23424775,
    "woe:adm0_id":23424775,
    "woe:name_adm0":"Canada",
    "woe:name_adm1":"Qu\u00e9bec",
    "woe:placetype":"Town",
    "wof:name":"Ste.-Foy",
    "wof:placetype":"locality"
},
  "geometry": {"coordinates":[-71.291763,46.781254],"type":"Point"}
}