{
  "type": "Feature",
  "properties": {
    "gn:admin1_code":"8",
    "gn:asciiname":"Northdale",
    "gn:country_code":"CA",
    "gn:dem":252,
    "gn:feature_class":"P",
    "gn:feature_code":"PPL",
    "gn:name":"Northdale",
    "gn:population":0,
    "gn:timezone":"America/Toronto",
    "iso:country":"CA",
    "wof:name":"Northdale",
    "wof:placetype":"locality"
},
  "geometry": {"coordinates":[-81.25,43.03333],"type":"Point"}
}