{
  "type": "Feature",
  "properties": {
    "gn:admin1_code":"8",
    "gn:asciiname":"Ryland",
    "gn:country_code":"CA",
    "gn:dem":256,
    "gn:feature_class":"P",
    "gn:feature_code":"PPL",
    "gn:name":"Ryland",
    "gn:population":0,
    "gn:timezone":"America/Toronto",
    "iso:country":"CA",
    "name:deu_x_preferred":[
        "Ryland"
    ],
    "name:ita_x_preferred":[
        "Ryland"
    ],
    "wof:name":"Ryland",
    "wof:placetype":"locality"
},
  "geometry": {"coordinates":[-83.78860999999998,49.71348],"type":"Point"}
}