{
  "type": "Feature",
  "properties": {
    "gn:admin1_code":"7",
    "gn:asciiname":"Enon",
    "gn:country_code":"CA",
    "gn:dem":128,
    "gn:feature_class":"P",
    "gn:feature_code":"PPLL",
    "gn:name":"Enon",
    "gn:population":0,
    "gn:timezone":"America/Glace_Bay",
    "iso:country":"CA",
    "wof:name":"Enon",
    "wof:placetype":"locality"
},
  "geometry": {"coordinates":[-60.53177,45.80014],"type":"Point"}
}