{
  "type": "Feature",
  "properties": {
    "gn:admin1_code":"5",
    "gn:asciiname":"Tibbos Hill",
    "gn:country_code":"CA",
    "gn:dem":53,
    "gn:feature_class":"P",
    "gn:feature_code":"PPLL",
    "gn:name":"Tibbos Hill",
    "gn:population":0,
    "gn:timezone":"America/St_Johns",
    "iso:country":"CA",
    "wof:name":"Tibbos Hill",
    "wof:placetype":"locality"
},
  "geometry": {"coordinates":[-55.59832,47.49994],"type":"Point"}
}