{
  "type": "Feature",
  "properties": {
    "gn:admin1_code":"8",
    "gn:asciiname":"Richan",
    "gn:country_code":"CA",
    "gn:dem":398,
    "gn:feature_class":"P",
    "gn:feature_code":"PPL",
    "gn:name":"Richan",
    "gn:population":0,
    "gn:timezone":"America/Winnipeg",
    "iso:country":"CA",
    "wof:name":"Richan",
    "wof:placetype":"locality"
},
  "geometry": {"coordinates":[-92.82908999999999,49.99467],"type":"Point"}
}