{
  "type": "Feature",
  "properties": {
    "gn:admin1_code":"7.0",
    "gn:asciiname":"Brazil Lake",
    "gn:country_code":"CA",
    "gn:dem":76,
    "gn:feature_class":"P",
    "gn:feature_code":"PPL",
    "gn:name":"Brazil Lake",
    "gn:population":0,
    "gn:timezone":"America/Halifax",
    "iso:country":"CA",
    "wof:name":"Brazil Lake",
    "wof:placetype":"locality"
},
  "geometry": {"coordinates":[-66.00191,43.9912],"type":"Point"}
}