{
  "type": "Feature",
  "properties": {
    "gn:admin1_code":"8",
    "gn:asciiname":"Nickeldale",
    "gn:country_code":"CA",
    "gn:dem":256,
    "gn:feature_class":"P",
    "gn:feature_code":"PPL",
    "gn:name":"Nickeldale",
    "gn:population":0,
    "gn:timezone":"America/Toronto",
    "iso:country":"CA",
    "wof:name":"Nickeldale",
    "wof:placetype":"locality"
},
  "geometry": {"coordinates":[-80.97333,46.51972],"type":"Point"}
}