{
  "type": "Feature",
  "properties": {
    "gn:admin1_code":"8",
    "gn:asciiname":"Progreston",
    "gn:country_code":"CA",
    "gn:dem":260,
    "gn:feature_class":"P",
    "gn:feature_code":"PPL",
    "gn:name":"Progreston",
    "gn:population":0,
    "gn:timezone":"America/Toronto",
    "iso:country":"CA",
    "wof:name":"Progreston",
    "wof:placetype":"locality"
},
  "geometry": {"coordinates":[-79.95917,43.39778],"type":"Point"}
}