{
  "type": "Feature",
  "properties": {
    "gn:admin1_code":"8.0",
    "gn:asciiname":"Bell Rapids",
    "gn:country_code":"CA",
    "gn:dem":438,
    "gn:feature_class":"P",
    "gn:feature_code":"PPL",
    "gn:name":"Bell Rapids",
    "gn:population":0,
    "gn:timezone":"America/Toronto",
    "iso:country":"CA",
    "wof:name":"Bell Rapids",
    "wof:placetype":"locality"
},
  "geometry": {"coordinates":[-77.79539,45.38777],"type":"Point"}
}