{
  "type": "Feature",
  "properties": {
    "gn:admin1_code":"8.0",
    "gn:asciiname":"Cedar Shores",
    "gn:country_code":"CA",
    "gn:dem":257,
    "gn:feature_class":"P",
    "gn:feature_code":"PPL",
    "gn:name":"Cedar Shores",
    "gn:population":0,
    "gn:timezone":"America/Toronto",
    "iso:country":"CA",
    "wof:name":"Cedar Shores",
    "wof:placetype":"locality"
},
  "geometry": {"coordinates":[-78.91764000000001,44.13618],"type":"Point"}
}