{
  "type": "Feature",
  "properties": {
    "gn:admin1_code":"8",
    "gn:asciiname":"Rothwell Heights",
    "gn:country_code":"CA",
    "gn:dem":92,
    "gn:feature_class":"P",
    "gn:feature_code":"PPL",
    "gn:name":"Rothwell Heights",
    "gn:population":0,
    "gn:timezone":"America/Toronto",
    "iso:country":"CA",
    "wof:name":"Rothwell Heights",
    "wof:placetype":"locality"
},
  "geometry": {"coordinates":[-75.61349,45.45382],"type":"Point"}
}