{
  "type": "Feature",
  "properties": {
    "gn:admin1_code":"2",
    "gn:asciiname":"Tsay Keh Dene",
    "gn:country_code":"CA",
    "gn:dem":688,
    "gn:feature_class":"P",
    "gn:feature_code":"PPLL",
    "gn:name":"Tsay Keh Dene",
    "gn:population":0,
    "gn:timezone":"America/Vancouver",
    "iso:country":"CA",
    "wof:name":"Tsay Keh Dene",
    "wof:placetype":"locality"
},
  "geometry": {"coordinates":[-124.97002000000001,56.88305],"type":"Point"}
}