{
  "type": "Feature",
  "properties": {
    "gn:admin1_code":"3",
    "gn:asciiname":"Middlebro",
    "gn:country_code":"CA",
    "gn:dem":333,
    "gn:feature_class":"P",
    "gn:feature_code":"PPL",
    "gn:name":"Middlebro",
    "gn:population":0,
    "gn:timezone":"America/Winnipeg",
    "iso:country":"CA",
    "wof:name":"Middlebro",
    "wof:placetype":"locality"
},
  "geometry": {"coordinates":[-95.4419,49.01968],"type":"Point"}
}