{
  "type": "Feature",
  "properties": {
    "gn:admin1_code":"4",
    "gn:asciiname":"Greenock",
    "gn:country_code":"CA",
    "gn:dem":154,
    "gn:feature_class":"P",
    "gn:feature_code":"PPL",
    "gn:name":"Greenock",
    "gn:population":0,
    "gn:timezone":"America/Moncton",
    "iso:country":"CA",
    "name:ara_x_preferred":[
        "\u063a\u0631\u064a\u0646\u0648\u0643"
    ],
    "name:ast_x_preferred":[
        "Greenock"
    ],
    "name:azb_x_preferred":[
        "\u0642\u0631\u06cc\u0646\u0648\u06a9"
    ],
    "name:aze_x_preferred":[
        "Qrinok"
    ],
    "name:bre_x_preferred":[
        "Grianaig"
    ],
    "name:bul_x_preferred":[
        "\u0413\u0440\u0438\u0439\u043d\u043e\u043a"
    ],
    "name:cat_x_preferred":[
        "Greenock"
    ],
    "name:ceb_x_preferred":[
        "Greenock"
    ],
    "name:ces_x_preferred":[
        "Greenock"
    ],
    "name:che_x_preferred":[
        "\u0413\u0440\u0438\u043d\u043e\u043a"
    ],
    "name:cym_x_preferred":[
        "Greenock"
    ],
    "name:dan_x_preferred":[
        "Greenock"
    ],
    "name:deu_x_preferred":[
        "Greenock"
    ],
    "name:epo_x_preferred":[
        "Greenock"
    ],
    "name:est_x_preferred":[
        "Greenock"
    ],
    "name:eus_x_preferred":[
        "Greenock"
    ],
    "name:fas_x_preferred":[
        "\u06af\u0631\u06cc\u0646\u0648\u06a9"
    ],
    "name:fin_x_preferred":[
        "Greenock"
    ],
    "name:fra_x_preferred":[
        "Greenock"
    ],
    "name:fry_x_preferred":[
        "Greenock"
    ],
    "name:gla_x_preferred":[
        "Grianaig"
    ],
    "name:gle_x_preferred":[
        "Grianaig"
    ],
    "name:glv_x_preferred":[
        "Grianaig"
    ],
    "name:ita_x_preferred":[
        "Greenock"
    ],
    "name:jpn_x_preferred":[
        "\u30b0\u30ea\u30fc\u30ce\u30c3\u30af"
    ],
    "name:kat_x_preferred":[
        "\u10d2\u10e0\u10d8\u10dc\u10dd\u10d9\u10d8"
    ],
    "name:kor_x_preferred":[
        "\uadf8\ub9ac\ub179"
    ],
    "name:lit_x_preferred":[
        "Grinokas"
    ],
    "name:nld_x_preferred":[
        "Greenock"
    ],
    "name:nno_x_preferred":[
        "Greenock"
    ],
    "name:nor_x_preferred":[
        "Greenock"
    ],
    "name:pnb_x_preferred":[
        "\u06af\u0631\u06cc\u0646\u0648\u06a9"
    ],
    "name:pol_x_preferred":[
        "Greenock"
    ],
    "name:por_x_preferred":[
        "Greenock"
    ],
    "name:rus_x_preferred":[
        "\u0413\u0440\u0438\u043d\u043e\u043a"
    ],
    "name:sco_x_preferred":[
        "Greenock"
    ],
    "name:slk_x_preferred":[
        "Greenock"
    ],
    "name:spa_x_preferred":[
        "Greenock"
    ],
    "name:swe_x_preferred":[
        "Greenock"
    ],
    "name:szl_x_preferred":[
        "Greenock"
    ],
    "name:ukr_x_preferred":[
        "\u0413\u0440\u0456\u043d\u043e\u043a"
    ],
    "name:zho_x_preferred":[
        "\u683c\u91cc\u8bfa\u514b"
    ],
    "wof:name":"Greenock",
    "wof:placetype":"locality"
},
  "geometry": {"coordinates":[-67.12139999999999,45.32879000000001],"type":"Point"}
}