{
  "type": "Feature",
  "properties": {
    "gn:admin1_code":"4",
    "gn:asciiname":"Greenock",
    "gn:country_code":"CA",
    "gn:dem":154,
    "gn:feature_class":"P",
    "gn:feature_code":"PPL",
    "gn:name":"Greenock",
    "gn:population":0,
    "gn:timezone":"America/Moncton",
    "iso:country":"CA",
    "wof:name":"Greenock",
    "wof:placetype":"locality"
},
  "geometry": {"coordinates":[-67.12139999999999,45.32879000000001],"type":"Point"}
}