{
  "type": "Feature",
  "properties": {
    "gn:admin1_code":"7",
    "gn:asciiname":"Lower Glencoe",
    "gn:country_code":"CA",
    "gn:dem":95,
    "gn:feature_class":"P",
    "gn:feature_code":"PPL",
    "gn:name":"Lower Glencoe",
    "gn:population":0,
    "gn:timezone":"America/Halifax",
    "iso:country":"CA",
    "wof:name":"Lower Glencoe",
    "wof:placetype":"locality"
},
  "geometry": {"coordinates":[-61.72281,45.40427],"type":"Point"}
}