{
  "type": "Feature",
  "properties": {
    "gn:admin1_code":"1.0",
    "gn:asciiname":"Codesa",
    "gn:country_code":"CA",
    "gn:dem":570,
    "gn:feature_class":"P",
    "gn:feature_code":"PPLL",
    "gn:name":"Codesa",
    "gn:population":0,
    "gn:timezone":"America/Edmonton",
    "iso:country":"CA",
    "wof:name":"Codesa",
    "wof:placetype":"locality"
},
  "geometry": {"coordinates":[-118.06941,55.76675],"type":"Point"}
}