{
  "type": "Feature",
  "properties": {
    "gn:admin1_code":"8",
    "gn:asciiname":"Robin Landing",
    "gn:country_code":"CA",
    "gn:dem":198,
    "gn:feature_class":"P",
    "gn:feature_code":"PPL",
    "gn:name":"Robin Landing",
    "gn:population":0,
    "gn:timezone":"America/Toronto",
    "iso:country":"CA",
    "wof:name":"Robin Landing",
    "wof:placetype":"locality"
},
  "geometry": {"coordinates":[-78.08639000000002,44.21889],"type":"Point"}
}