{
  "type": "Feature",
  "properties": {
    "gn:admin1_code":"11",
    "gn:asciiname":"Lac Vert",
    "gn:country_code":"CA",
    "gn:dem":535,
    "gn:feature_class":"P",
    "gn:feature_code":"PPLL",
    "gn:name":"Lac Vert",
    "gn:population":0,
    "gn:timezone":"America/Regina",
    "iso:country":"CA",
    "name:ceb_x_preferred":[
        "Lac Vert"
    ],
    "name:fra_x_preferred":[
        "Lac Vert"
    ],
    "name:nld_x_preferred":[
        "Lac Vert"
    ],
    "name:swe_x_preferred":[
        "Lac Vert"
    ],
    "wof:name":"Lac Vert",
    "wof:placetype":"locality"
},
  "geometry": {"coordinates":[-104.48430999999999,52.50001999999999],"type":"Point"}
}