{
  "type": "Feature",
  "properties": {
    "gn:admin1_code":"2",
    "gn:asciiname":"Twidwell Bend",
    "gn:country_code":"CA",
    "gn:dem":554,
    "gn:feature_class":"P",
    "gn:feature_code":"PPLL",
    "gn:name":"Twidwell Bend",
    "gn:population":0,
    "gn:timezone":"America/Dawson_Creek",
    "iso:country":"CA",
    "wof:name":"Twidwell Bend",
    "wof:placetype":"locality"
},
  "geometry": {"coordinates":[-121.56966,55.61658000000001],"type":"Point"}
}