{
  "type": "Feature",
  "properties": {
    "gn:admin1_code":"3.0",
    "gn:asciiname":"Brown",
    "gn:country_code":"CA",
    "gn:dem":453,
    "gn:feature_class":"P",
    "gn:feature_code":"PPLL",
    "gn:name":"Brown",
    "gn:population":0,
    "gn:timezone":"America/Winnipeg",
    "iso:country":"CA",
    "wof:name":"Brown",
    "wof:placetype":"locality"
},
  "geometry": {"coordinates":[-98.17907,49.0444],"type":"Point"}
}