{
  "type": "Feature",
  "properties": {
    "iso:country":"CA",
    "name:ara_x_preferred":[
        "\u0641\u0648\u0631\u062a \u062a\u0634\u064a\u0628\u0648\u0627\u064a\u0627\u0646"
    ],
    "name:cat_x_preferred":[
        "Fort Chipewyan"
    ],
    "name:deu_x_preferred":[
        "Fort Chipewyan"
    ],
    "name:eng_x_preferred":[
        "Fort Chipewyan"
    ],
    "name:fin_x_preferred":[
        "Fort Chipewyan"
    ],
    "name:fra_x_preferred":[
        "Fort Chipewyan"
    ],
    "name:jpn_x_preferred":[
        "\u30c1\u30d4\u30e5\u30fc\u30e4\u30f3\u7826"
    ],
    "name:por_x_preferred":[
        "Fort Chipewyan"
    ],
    "name:swe_x_preferred":[
        "Fort Chipewyan"
    ],
    "name:zho_x_preferred":[
        "\u5947\u4f69\u7dad\u5b89\u5821"
    ],
    "ne:ADM0CAP":0.0,
    "ne:ADM0NAME":"Canada",
    "ne:ADM0_A3":"CAN",
    "ne:ADM1NAME":"Alberta",
    "ne:ADMIN1_COD":0,
    "ne:CAPALT":0,
    "ne:CHANGED":0,
    "ne:CHECKME":0,
    "ne:COMPARE":0,
    "ne:DIFFASCII":0,
    "ne:ELEVATION":0.0,
    "ne:FEATURECLA":"Populated place",
    "ne:GEONAMEID":-1,
    "ne:GEONAMESNO":"No GeoNames match due to small population, not in GeoNames, or poor NEV placement.",
    "ne:GN_POP":0,
    "ne:GTOPO30":0.0,
    "ne:ISO_A2":"CA",
    "ne:LABELRANK":2,
    "ne:LATITUDE":58.717099,
    "ne:LONGITUDE":-111.149996,
    "ne:LS_MATCH":1,
    "ne:LS_NAME":"Fort Chipewyan",
    "ne:MAX_AREAKM":4.0,
    "ne:MAX_AREAMI":2.0,
    "ne:MAX_BBXMAX":-111.133333,
    "ne:MAX_BBXMIN":-111.191667,
    "ne:MAX_BBYMAX":58.733333,
    "ne:MAX_BBYMIN":58.708333,
    "ne:MAX_NATSCA":20.0,
    "ne:MAX_PERKM":16.0,
    "ne:MAX_PERMI":10.0,
    "ne:MAX_POP10":3222,
    "ne:MAX_POP20":3222,
    "ne:MAX_POP300":0,
    "ne:MAX_POP310":0,
    "ne:MAX_POP50":0,
    "ne:MEAN_BBXC":-111.1575,
    "ne:MEAN_BBYC":58.716667,
    "ne:MEGACITY":0,
    "ne:MIN_AREAKM":4.0,
    "ne:MIN_AREAMI":2.0,
    "ne:MIN_BBXMAX":-111.133333,
    "ne:MIN_BBXMIN":-111.191667,
    "ne:MIN_BBYMAX":58.733333,
    "ne:MIN_BBYMIN":58.708333,
    "ne:MIN_PERKM":16.0,
    "ne:MIN_PERMI":10.0,
    "ne:NAME":"Fort Chipewyan",
    "ne:NAMEASCII":"Fort Chipewyan",
    "ne:NAMEDIFF":0,
    "ne:NATSCALE":20,
    "ne:POP1950":0,
    "ne:POP1955":0,
    "ne:POP1960":0,
    "ne:POP1965":0,
    "ne:POP1970":0,
    "ne:POP1975":0,
    "ne:POP1980":0,
    "ne:POP1985":0,
    "ne:POP1990":0,
    "ne:POP1995":0,
    "ne:POP2000":0,
    "ne:POP2005":0,
    "ne:POP2010":0,
    "ne:POP2015":0,
    "ne:POP2020":0,
    "ne:POP2025":0,
    "ne:POP2050":0,
    "ne:POP_MAX":3222,
    "ne:POP_MIN":3222,
    "ne:POP_OTHER":2981,
    "ne:RANK_MAX":4,
    "ne:RANK_MIN":4,
    "ne:SCALERANK":7,
    "ne:SOV0NAME":"Canada",
    "ne:SOV_A3":"CAN",
    "ne:UN_FID":0,
    "ne:UN_LAT":0.0,
    "ne:UN_LONG":0.0,
    "ne:WORLDCITY":0,
    "qs:name":"Fort Chipewyan",
    "qs:name_adm0":"Canada",
    "qs:name_adm1":"Alberta",
    "qs:photos":122,
    "qs:photos_1k":25,
    "qs:photos_9k":1,
    "qs:photos_9r":3,
    "qs:photos_all":122,
    "qs:photos_sr":3,
    "qs:placetype":"Town",
    "qs:pop_sr":"0",
    "wd:wordcount":1056,
    "wof:name":"Fort Chipewyan",
    "wof:placetype":"locality"
},
  "geometry": {"coordinates":[-111.158123,58.712348],"type":"Point"}
}