{
  "type": "Feature",
  "properties": {
    "gn:admin1_code":"8",
    "gn:asciiname":"Watercombe",
    "gn:country_code":"CA",
    "gn:dem":73,
    "gn:feature_class":"P",
    "gn:feature_code":"PPL",
    "gn:name":"Watercombe",
    "gn:population":0,
    "gn:timezone":"America/Toronto",
    "iso:country":"CA",
    "wof:name":"Watercombe",
    "wof:placetype":"locality"
},
  "geometry": {"coordinates":[-77.06407,44.12433],"type":"Point"}
}