{
  "type": "Feature",
  "properties": {
    "gn:admin1_code":"1",
    "gn:asciiname":"Inverlake",
    "gn:country_code":"CA",
    "gn:dem":1002,
    "gn:feature_class":"P",
    "gn:feature_code":"PPLL",
    "gn:name":"Inverlake",
    "gn:population":0,
    "gn:timezone":"America/Edmonton",
    "iso:country":"CA",
    "wof:name":"Inverlake",
    "wof:placetype":"locality"
},
  "geometry": {"coordinates":[-113.63525,51.05011],"type":"Point"}
}