{
  "type": "Feature",
  "properties": {
    "gn:admin1_code":"11",
    "gn:asciiname":"Halvorgate",
    "gn:country_code":"CA",
    "gn:dem":623,
    "gn:feature_class":"P",
    "gn:feature_code":"PPL",
    "gn:name":"Halvorgate",
    "gn:population":0,
    "gn:timezone":"America/Regina",
    "iso:country":"CA",
    "wof:name":"Halvorgate",
    "wof:placetype":"locality"
},
  "geometry": {"coordinates":[-106.70125,50.63336],"type":"Point"}
}