{
  "type": "Feature",
  "properties": {
    "gn:admin1_code":"7",
    "gn:asciiname":"Melford",
    "gn:country_code":"CA",
    "gn:dem":28,
    "gn:feature_class":"P",
    "gn:feature_code":"PPL",
    "gn:name":"Melford",
    "gn:population":0,
    "gn:timezone":"America/Halifax",
    "iso:country":"CA",
    "wof:name":"Melford",
    "wof:placetype":"locality"
},
  "geometry": {"coordinates":[-61.26113,45.87073],"type":"Point"}
}