{
  "type": "Feature",
  "properties": {
    "gn:admin1_code":"2.0",
    "gn:asciiname":"Cheam View",
    "gn:country_code":"CA",
    "gn:dem":29,
    "gn:feature_class":"P",
    "gn:feature_code":"PPLL",
    "gn:name":"Cheam View",
    "gn:population":0,
    "gn:timezone":"America/Vancouver",
    "iso:country":"CA",
    "wof:name":"Cheam View",
    "wof:placetype":"locality"
},
  "geometry": {"coordinates":[-121.68585,49.24969],"type":"Point"}
}