{
  "type": "Feature",
  "properties": {
    "gn:admin1_code":"8",
    "gn:asciiname":"Mafeking",
    "gn:country_code":"CA",
    "gn:dem":265,
    "gn:feature_class":"P",
    "gn:feature_code":"PPL",
    "gn:name":"Mafeking",
    "gn:population":0,
    "gn:timezone":"America/Toronto",
    "iso:country":"CA",
    "wof:name":"Mafeking",
    "wof:placetype":"locality"
},
  "geometry": {"coordinates":[-81.60600000000002,43.91406],"type":"Point"}
}