{
  "type": "Feature",
  "properties": {
    "gn:admin1_code":"9",
    "gn:asciiname":"South Lake",
    "gn:country_code":"CA",
    "gn:dem":3,
    "gn:feature_class":"P",
    "gn:feature_code":"PPLL",
    "gn:name":"South Lake",
    "gn:population":0,
    "gn:timezone":"America/Halifax",
    "iso:country":"CA",
    "wof:name":"South Lake",
    "wof:placetype":"locality"
},
  "geometry": {"coordinates":[-62.04861,46.4168],"type":"Point"}
}