{
  "type": "Feature",
  "properties": {
    "gn:admin1_code":"11",
    "gn:asciiname":"South Star",
    "gn:country_code":"CA",
    "gn:dem":513,
    "gn:feature_class":"P",
    "gn:feature_code":"PPLL",
    "gn:name":"South Star",
    "gn:population":0,
    "gn:timezone":"America/Regina",
    "iso:country":"CA",
    "name:ast_x_preferred":[
        "Estrella del Sur"
    ],
    "name:jpn_x_preferred":[
        "\u5357\u6975\u661f"
    ],
    "name:kor_x_preferred":[
        "\ub0a8\uadf9\uc131"
    ],
    "name:nor_x_preferred":[
        "Den himmelske s\u00f8rpol"
    ],
    "name:spa_x_preferred":[
        "Estrella del Sur"
    ],
    "wof:name":"South Star",
    "wof:placetype":"locality"
},
  "geometry": {"coordinates":[-104.25098,52.71672],"type":"Point"}
}