{
  "type": "Feature",
  "properties": {
    "gn:admin1_code":"8",
    "gn:asciiname":"Fair Valley",
    "gn:country_code":"CA",
    "gn:dem":277,
    "gn:feature_class":"P",
    "gn:feature_code":"PPL",
    "gn:name":"Fair Valley",
    "gn:population":0,
    "gn:timezone":"America/Toronto",
    "iso:country":"CA",
    "wof:name":"Fair Valley",
    "wof:placetype":"locality"
},
  "geometry": {"coordinates":[-79.59484999999999,44.64862],"type":"Point"}
}