{
  "type": "Feature",
  "properties": {
    "gn:admin1_code":"10",
    "gn:admin2_code":"08",
    "gn:admin3_code":"85100.0",
    "gn:asciiname":"Roulier",
    "gn:country_code":"CA",
    "gn:dem":294,
    "gn:feature_class":"P",
    "gn:feature_code":"PPL",
    "gn:name":"Roulier",
    "gn:population":0,
    "gn:timezone":"America/Toronto",
    "iso:country":"CA",
    "wof:name":"Roulier",
    "wof:placetype":"locality"
},
  "geometry": {"coordinates":[-79.40944,47.77611],"type":"Point"}
}