{
  "type": "Feature",
  "properties": {
    "gn:admin1_code":"2",
    "gn:asciiname":"Glenannan",
    "gn:country_code":"CA",
    "gn:dem":832,
    "gn:feature_class":"P",
    "gn:feature_code":"PPLL",
    "gn:name":"Glenannan",
    "gn:population":0,
    "gn:timezone":"America/Vancouver",
    "iso:country":"CA",
    "wof:name":"Glenannan",
    "wof:placetype":"locality"
},
  "geometry": {"coordinates":[-125.00320000000001,54.01653],"type":"Point"}
}