{
  "type": "Feature",
  "properties": {
    "gn:admin1_code":"8.0",
    "gn:asciiname":"Cedar Nook",
    "gn:country_code":"CA",
    "gn:dem":191,
    "gn:feature_class":"P",
    "gn:feature_code":"PPL",
    "gn:name":"Cedar Nook",
    "gn:population":0,
    "gn:timezone":"America/Toronto",
    "iso:country":"CA",
    "wof:name":"Cedar Nook",
    "wof:placetype":"locality"
},
  "geometry": {"coordinates":[-79.75528,44.91139],"type":"Point"}
}