{
  "type": "Feature",
  "properties": {
    "gn:admin1_code":"10",
    "gn:admin2_code":"10.0",
    "gn:asciiname":"Mistissini",
    "gn:country_code":"CA",
    "gn:dem":439,
    "gn:feature_class":"P",
    "gn:feature_code":"PPL",
    "gn:name":"Mistissini",
    "gn:population":0,
    "gn:timezone":"America/Toronto",
    "iso:country":"CA",
    "wof:name":"Mistissini",
    "wof:placetype":"locality"
},
  "geometry": {"coordinates":[-74.01586,50.31684],"type":"Point"}
}