{
  "type": "Feature",
  "properties": {
    "gn:admin1_code":"1",
    "gn:asciiname":"Moose Portage",
    "gn:country_code":"CA",
    "gn:dem":588,
    "gn:feature_class":"P",
    "gn:feature_code":"PPLL",
    "gn:name":"Moose Portage",
    "gn:population":0,
    "gn:timezone":"America/Edmonton",
    "iso:country":"CA",
    "wof:name":"Moose Portage",
    "wof:placetype":"locality"
},
  "geometry": {"coordinates":[-113.86886,55.21686999999999],"type":"Point"}
}