{
  "type": "Feature",
  "properties": {
    "gn:admin1_code":"4",
    "gn:asciiname":"Pleasant Ridge",
    "gn:country_code":"CA",
    "gn:dem":176,
    "gn:feature_class":"P",
    "gn:feature_code":"PPL",
    "gn:name":"Pleasant Ridge",
    "gn:population":0,
    "gn:timezone":"America/Moncton",
    "iso:country":"CA",
    "name:ceb_x_preferred":[
        "Pleasant Ridge"
    ],
    "name:deu_x_preferred":[
        "Pleasant Ridge"
    ],
    "name:fra_x_preferred":[
        "Pleasant Ridge"
    ],
    "name:ita_x_preferred":[
        "Pleasant Ridge"
    ],
    "name:pol_x_preferred":[
        "Pleasant Ridge"
    ],
    "name:swe_x_preferred":[
        "Pleasant Ridge"
    ],
    "name:vol_x_preferred":[
        "Pleasant Ridge"
    ],
    "wof:name":"Pleasant Ridge",
    "wof:placetype":"locality"
},
  "geometry": {"coordinates":[-66.96666999999999,45.38333],"type":"Point"}
}