{
  "type": "Feature",
  "properties": {
    "gn:admin1_code":"4",
    "gn:asciiname":"Pleasant Ridge",
    "gn:country_code":"CA",
    "gn:dem":176,
    "gn:feature_class":"P",
    "gn:feature_code":"PPL",
    "gn:name":"Pleasant Ridge",
    "gn:population":0,
    "gn:timezone":"America/Moncton",
    "iso:country":"CA",
    "wof:name":"Pleasant Ridge",
    "wof:placetype":"locality"
},
  "geometry": {"coordinates":[-66.96666999999999,45.38333],"type":"Point"}
}