{
  "type": "Feature",
  "properties": {
    "gn:admin1_code":"10.0",
    "gn:admin2_code":"16.0",
    "gn:admin3_code":"69010.0",
    "gn:asciiname":"Dorea",
    "gn:country_code":"CA",
    "gn:dem":238,
    "gn:feature_class":"P",
    "gn:feature_code":"PPL",
    "gn:name":"Dorea",
    "gn:population":0,
    "gn:timezone":"America/Toronto",
    "iso:country":"CA",
    "wof:name":"Dorea",
    "wof:placetype":"locality"
},
  "geometry": {"coordinates":[-73.92820999999998,45.00588],"type":"Point"}
}