{
  "type": "Feature",
  "properties": {
    "iso:country":"CA",
    "name:cat_x_preferred":[
        "Durand"
    ],
    "name:deu_x_preferred":[
        "Durand"
    ],
    "name:eng_x_preferred":[
        "Durand"
    ],
    "name:fra_x_preferred":[
        "Durand"
    ],
    "name:hbs_x_preferred":[
        "Djurand"
    ],
    "name:ita_x_preferred":[
        "Durand"
    ],
    "name:nld_x_preferred":[
        "Durand"
    ],
    "name:pol_x_preferred":[
        "Durand"
    ],
    "name:rus_x_preferred":[
        "\u0414\u044e\u0440\u0430\u043d"
    ],
    "name:spa_x_preferred":[
        "Durand"
    ],
    "name:srp_x_preferred":[
        "\u0414\u0458\u0443\u0440\u0430\u043d\u0434"
    ],
    "name:swe_x_preferred":[
        "Durand"
    ],
    "name:ukr_x_preferred":[
        "\u0414\u044e\u0440\u0430\u043d"
    ],
    "name:unk_x_variant":[
        "Durand"
    ],
    "name:vol_x_preferred":[
        "Durand"
    ],
    "qs:gn_adm0_cc":"CA",
    "qs:gn_local":5969782,
    "qs:gn_nam_loc":"hamilton",
    "qs:gn_namadm1":"08",
    "qs:local_max":3547,
    "qs:local_sum":20353,
    "qs:localhoods":46,
    "qs:name":"Durand",
    "qs:name_adm0":"Canada",
    "qs:name_adm1":"Ontario",
    "qs:name_adm2":"Hamilton",
    "qs:name_local":"Hamilton",
    "qs:photo_max":130,
    "qs:photo_sum":784,
    "qs:placetype":"Suburb",
    "qs:quad_count":31,
    "qs:woe_adm0":23424775,
    "qs:woe_adm1":2344922,
    "qs:woe_adm2":29375120,
    "qs:woe_lau":0,
    "qs:woe_local":4125,
    "qs:woe_ver":"7.10.0",
    "wd:wordcount":138,
    "wof:lang":[
        "eng"
    ],
    "wof:name":"Durand",
    "wof:placetype":"neighbourhood"
},
  "geometry": {"coordinates":[-79.875123,43.251465],"type":"Point"}
}