{
  "type": "Feature",
  "properties": {
    "gn:admin1_code":"10.0",
    "gn:admin2_code":"15.0",
    "gn:asciiname":"De Lesseps",
    "gn:country_code":"CA",
    "gn:dem":238,
    "gn:feature_class":"P",
    "gn:feature_code":"PPL",
    "gn:name":"De Lesseps",
    "gn:population":0,
    "gn:timezone":"America/Toronto",
    "iso:country":"CA",
    "wof:name":"De Lesseps",
    "wof:placetype":"locality"
},
  "geometry": {"coordinates":[-74.56489999999999,46.1281],"type":"Point"}
}