{
  "type": "Feature",
  "properties": {
    "gn:admin1_code":"10",
    "gn:admin2_code":"15.0",
    "gn:admin3_code":"78055.0",
    "gn:asciiname":"Weir",
    "gn:country_code":"CA",
    "gn:dem":196,
    "gn:feature_class":"P",
    "gn:feature_code":"PPL",
    "gn:name":"Weir",
    "gn:population":0,
    "gn:timezone":"America/Toronto",
    "iso:country":"CA",
    "wof:name":"Weir",
    "wof:placetype":"locality"
},
  "geometry": {"coordinates":[-74.54907,45.94505],"type":"Point"}
}