{
  "type": "Feature",
  "properties": {
    "gn:admin1_code":"10",
    "gn:admin2_code":"15.0",
    "gn:admin3_code":"78055.0",
    "gn:asciiname":"Weir",
    "gn:country_code":"CA",
    "gn:dem":196,
    "gn:feature_class":"P",
    "gn:feature_code":"PPL",
    "gn:name":"Weir",
    "gn:population":0,
    "gn:timezone":"America/Toronto",
    "iso:country":"CA",
    "name:ara_x_preferred":[
        "\u0648\u064a\u0631"
    ],
    "name:ben_x_preferred":[
        "\u0989\u09df\u09bf\u09b0"
    ],
    "name:ell_x_preferred":[
        "\u0393\u03bf\u03c5\u03ad\u03b9\u03c1"
    ],
    "name:fas_x_preferred":[
        "\u0648\u06cc\u0631"
    ],
    "name:fra_x_preferred":[
        "Weir"
    ],
    "name:heb_x_preferred":[
        "\u05d5\u05b6\u05d5\u05d9\u05e8"
    ],
    "name:hin_x_preferred":[
        "\u0935\u0940\u092f\u0930 "
    ],
    "name:hun_x_preferred":[
        "Weir"
    ],
    "name:ind_x_preferred":[
        "Weir"
    ],
    "name:ita_x_preferred":[
        "Weir"
    ],
    "name:jpn_x_preferred":[
        "\u30a6\u30a3\u30a2\u30fc\u5ddd"
    ],
    "name:kor_x_preferred":[
        "\uc704\uc5b4"
    ],
    "name:nld_x_preferred":[
        "Weir"
    ],
    "name:pol_x_preferred":[
        "Weir"
    ],
    "name:por_x_preferred":[
        "Weir"
    ],
    "name:spa_x_preferred":[
        "Weir"
    ],
    "name:tur_x_preferred":[
        "Weir"
    ],
    "name:ukr_x_preferred":[
        "\u0412\u0435\u0439\u0440"
    ],
    "name:urd_x_preferred":[
        "\u0648\u06cc\u0626\u0631"
    ],
    "name:vie_x_preferred":[
        "S\u00f4ng Weir"
    ],
    "name:zho_cn_x_preferred":[
        "\u97e6\u5c14\u6cb3"
    ],
    "name:zho_tw_x_preferred":[
        "\u97cb\u723e\u6cb3"
    ],
    "wof:name":"Weir",
    "wof:placetype":"locality"
},
  "geometry": {"coordinates":[-74.54907,45.94505],"type":"Point"}
}