{
  "type": "Feature",
  "properties": {
    "gn:admin1_code":"4",
    "gn:asciiname":"Lower Burton",
    "gn:country_code":"CA",
    "gn:dem":30,
    "gn:feature_class":"P",
    "gn:feature_code":"PPL",
    "gn:name":"Lower Burton",
    "gn:population":0,
    "gn:timezone":"America/Moncton",
    "iso:country":"CA",
    "wof:name":"Lower Burton",
    "wof:placetype":"locality"
},
  "geometry": {"coordinates":[-66.37806999999999,45.87421],"type":"Point"}
}