{
  "type": "Feature",
  "properties": {
    "gn:admin1_code":"5.0",
    "gn:asciiname":"Wild Cove",
    "gn:country_code":"CA",
    "gn:dem":35,
    "gn:feature_class":"P",
    "gn:feature_code":"PPLL",
    "gn:name":"Wild Cove",
    "gn:population":0,
    "gn:timezone":"America/St_Johns",
    "iso:country":"CA",
    "wof:name":"Wild Cove",
    "wof:placetype":"locality"
},
  "geometry": {"coordinates":[-56.16481,50.68339],"type":"Point"}
}