{
  "type": "Feature",
  "properties": {
    "gn:admin1_code":"2.0",
    "gn:asciiname":"Wistaria",
    "gn:country_code":"CA",
    "gn:dem":927,
    "gn:feature_class":"P",
    "gn:feature_code":"PPLL",
    "gn:name":"Wistaria",
    "gn:population":0,
    "gn:timezone":"America/Vancouver",
    "iso:country":"CA",
    "wof:name":"Wistaria",
    "wof:placetype":"locality"
},
  "geometry": {"coordinates":[-126.27,53.84976999999999],"type":"Point"}
}