{
  "type": "Feature",
  "properties": {
    "gn:admin1_code":"8.0",
    "gn:asciiname":"Clarksdale",
    "gn:country_code":"CA",
    "gn:dem":116,
    "gn:feature_class":"P",
    "gn:feature_code":"PPL",
    "gn:name":"Clarksdale",
    "gn:population":0,
    "gn:timezone":"America/Toronto",
    "iso:country":"CA",
    "wof:name":"Clarksdale",
    "wof:placetype":"locality"
},
  "geometry": {"coordinates":[-79.81378000000002,43.35319000000001],"type":"Point"}
}