{
  "type": "Feature",
  "properties": {
    "gn:admin1_code":"10",
    "gn:admin2_code":"5.0",
    "gn:admin3_code":"45043.0",
    "gn:asciiname":"Massawippi",
    "gn:country_code":"CA",
    "gn:dem":228,
    "gn:feature_class":"P",
    "gn:feature_code":"PPL",
    "gn:name":"Massawippi",
    "gn:population":0,
    "gn:timezone":"America/Toronto",
    "iso:country":"CA",
    "wof:name":"Massawippi",
    "wof:placetype":"locality"
},
  "geometry": {"coordinates":[-71.9901,45.18143],"type":"Point"}
}