{
  "type": "Feature",
  "properties": {
    "gn:country":"CA",
    "iso:country":"CA",
    "name:ceb_x_preferred":[
        "Rock Island"
    ],
    "name:ces_x_preferred":[
        "Rock Island"
    ],
    "name:deu_x_preferred":[
        "Rock Island"
    ],
    "name:fra_x_preferred":[
        "Rock Island"
    ],
    "name:ita_x_preferred":[
        "Rock Island"
    ],
    "name:nld_x_preferred":[
        "Rock Island"
    ],
    "name:pol_x_preferred":[
        "Rock Island"
    ],
    "name:por_x_preferred":[
        "Rock Island"
    ],
    "name:rus_x_preferred":[
        "\u0420\u043e\u043a-\u0410\u0439\u043b\u0435\u043d\u0434"
    ],
    "name:spa_x_preferred":[
        "Rock Island"
    ],
    "name:srp_x_preferred":[
        "\u0420\u043e\u043a \u0410\u0458\u043b\u0430\u043d\u0434"
    ],
    "name:swe_x_preferred":[
        "Rock Island"
    ],
    "name:vol_x_preferred":[
        "Rock Island"
    ],
    "qs_pg:aaroncc":"CA",
    "qs_pg:gn_country":"CA",
    "qs_pg:name":"Rock Island",
    "qs_pg:name_adm0":"Canada",
    "qs_pg:name_adm1":"Qu\u00e9bec",
    "qs_pg:photos":159,
    "qs_pg:photos_1k":32,
    "qs_pg:photos_9k":1,
    "qs_pg:photos_9r":4,
    "qs_pg:photos_all":159,
    "qs_pg:photos_sr":4,
    "qs_pg:pop_sr":0,
    "qs_pg:qs_pg_placetype":"locality",
    "qs_pg:qs_pg_placetype_gp":"Town",
    "qs_pg:woe_adm0":23424775,
    "woe:adm0_id":23424775,
    "woe:name_adm0":"Canada",
    "woe:name_adm1":"Qu\u00e9bec",
    "woe:placetype":"Town",
    "wof:name":"Rock Island",
    "wof:placetype":"locality"
},
  "geometry": {"coordinates":[-72.098089,45.005911],"type":"Point"}
}