{
  "type": "Feature",
  "properties": {
    "gn:country":"CA",
    "iso:country":"CA",
    "name:ben_x_preferred":[
        "\u09b0\u0995 \u0986\u0987\u09b2\u09cd\u09af\u09be\u09a8\u09cd\u09a1"
    ],
    "name:ceb_x_preferred":[
        "Rock Island"
    ],
    "name:ces_x_preferred":[
        "Rock Island"
    ],
    "name:deu_x_preferred":[
        "Rock Island"
    ],
    "name:ell_x_preferred":[
        "\u03a1\u03bf\u03ba \u0386\u03b9\u03bb\u03b1\u03bd\u03c4"
    ],
    "name:fra_x_preferred":[
        "Rock Island"
    ],
    "name:hin_x_preferred":[
        "\u0930\u0949\u0915 \u0906\u0907\u0932\u0948\u0902\u0921"
    ],
    "name:ita_x_preferred":[
        "Rock Island"
    ],
    "name:kor_x_preferred":[
        "\ub85d \uc544\uc77c\ub79c\ub4dc"
    ],
    "name:nld_x_preferred":[
        "Rock Island"
    ],
    "name:pol_x_preferred":[
        "Rock Island"
    ],
    "name:por_x_preferred":[
        "Rock Island"
    ],
    "name:rus_x_preferred":[
        "\u0420\u043e\u043a-\u0410\u0439\u043b\u0435\u043d\u0434"
    ],
    "name:spa_x_preferred":[
        "Rock Island"
    ],
    "name:srp_x_preferred":[
        "\u0420\u043e\u043a \u0410\u0458\u043b\u0430\u043d\u0434"
    ],
    "name:swe_x_preferred":[
        "Rock Island"
    ],
    "name:vol_x_preferred":[
        "Rock Island"
    ],
    "qs_pg:aaroncc":"CA",
    "qs_pg:gn_country":"CA",
    "qs_pg:name":"Rock Island",
    "qs_pg:name_adm0":"Canada",
    "qs_pg:name_adm1":"Qu\u00e9bec",
    "qs_pg:photos":159,
    "qs_pg:photos_1k":32,
    "qs_pg:photos_9k":1,
    "qs_pg:photos_9r":4,
    "qs_pg:photos_all":159,
    "qs_pg:photos_sr":4,
    "qs_pg:pop_sr":0,
    "qs_pg:qs_pg_placetype":"locality",
    "qs_pg:qs_pg_placetype_gp":"Town",
    "qs_pg:woe_adm0":23424775,
    "woe:adm0_id":23424775,
    "woe:name_adm0":"Canada",
    "woe:name_adm1":"Qu\u00e9bec",
    "woe:placetype":"Town",
    "wof:name":"Rock Island",
    "wof:placetype":"locality"
},
  "geometry": {"coordinates":[-72.098089,45.005911],"type":"Point"}
}