{
  "type": "Feature",
  "properties": {
    "gn:admin1_code":"8.0",
    "gn:asciiname":"Clanbrassil",
    "gn:country_code":"CA",
    "gn:dem":217,
    "gn:feature_class":"P",
    "gn:feature_code":"PPL",
    "gn:name":"Clanbrassil",
    "gn:population":0,
    "gn:timezone":"America/Toronto",
    "iso:country":"CA",
    "wof:name":"Clanbrassil",
    "wof:placetype":"locality"
},
  "geometry": {"coordinates":[-79.95056,42.96694],"type":"Point"}
}