{
  "type": "Feature",
  "properties": {
    "gn:admin1_code":"10",
    "gn:admin2_code":"5.0",
    "gn:admin3_code":"41037.0",
    "gn:asciiname":"Parker Hill",
    "gn:country_code":"CA",
    "gn:dem":359,
    "gn:feature_class":"P",
    "gn:feature_code":"PPL",
    "gn:name":"Parker Hill",
    "gn:population":0,
    "gn:timezone":"America/Toronto",
    "iso:country":"CA",
    "name:ceb_x_preferred":[
        "Parker Hill"
    ],
    "name:deu_x_preferred":[
        "Parker Hill"
    ],
    "name:nno_x_preferred":[
        "Parker Hill"
    ],
    "name:swe_x_preferred":[
        "Parker Hill"
    ],
    "name:zho_x_preferred":[
        "\u5e15\u514b\u5c71"
    ],
    "wof:name":"Parker Hill",
    "wof:placetype":"locality"
},
  "geometry": {"coordinates":[-71.5262,45.3206],"type":"Point"}
}