{
  "type": "Feature",
  "properties": {
    "gn:admin1_code":"8",
    "gn:asciiname":"Thompsonville",
    "gn:country_code":"CA",
    "gn:dem":222,
    "gn:feature_class":"P",
    "gn:feature_code":"PPL",
    "gn:name":"Thompsonville",
    "gn:population":0,
    "gn:timezone":"America/Toronto",
    "iso:country":"CA",
    "name:ceb_x_preferred":[
        "Thompsonville"
    ],
    "name:deu_x_preferred":[
        "Thompsonville"
    ],
    "name:fra_x_preferred":[
        "Thompsonville"
    ],
    "name:ita_x_preferred":[
        "Thompsonville"
    ],
    "name:nld_x_preferred":[
        "Thompsonville"
    ],
    "name:pol_x_preferred":[
        "Thompsonville"
    ],
    "name:por_x_preferred":[
        "Thompsonville"
    ],
    "name:spa_x_preferred":[
        "Thompsonville"
    ],
    "name:srp_x_preferred":[
        "\u0422\u043e\u043c\u043f\u0441\u043e\u043d\u0432\u0438\u043b"
    ],
    "name:vol_x_preferred":[
        "Thompsonville"
    ],
    "wof:name":"Thompsonville",
    "wof:placetype":"locality"
},
  "geometry": {"coordinates":[-79.83778000000002,44.13333],"type":"Point"}
}