{
  "type": "Feature",
  "properties": {
    "gn:admin1_code":"7",
    "gn:asciiname":"Five Mile Plains",
    "gn:country_code":"CA",
    "gn:dem":32,
    "gn:feature_class":"P",
    "gn:feature_code":"PPL",
    "gn:name":"Five Mile Plains",
    "gn:population":0,
    "gn:timezone":"America/Halifax",
    "iso:country":"CA",
    "wof:name":"Five Mile Plains",
    "wof:placetype":"locality"
},
  "geometry": {"coordinates":[-64.08648000000001,44.96375],"type":"Point"}
}