{
  "type": "Feature",
  "properties": {
    "gn:admin1_code":"11.0",
    "gn:asciiname":"Blumenhof",
    "gn:country_code":"CA",
    "gn:dem":893,
    "gn:feature_class":"P",
    "gn:feature_code":"PPL",
    "gn:name":"Blumenhof",
    "gn:population":0,
    "gn:timezone":"America/Regina",
    "iso:country":"CA",
    "wof:name":"Blumenhof",
    "wof:placetype":"locality"
},
  "geometry": {"coordinates":[-107.70067,50.0167],"type":"Point"}
}