{
  "type": "Feature",
  "properties": {
    "iso:country":"CA",
    "name:fas_x_preferred":[
        "\u0646\u06cc\u06a9\u0644 \u0633\u0646\u062a\u0631"
    ],
    "name:fra_x_preferred":[
        "Nickel Centre"
    ],
    "name:urd_x_preferred":[
        "\u0646\u06a9\u0644 \u0633\u06cc\u0646\u0679\u0631"
    ],
    "qs_pg:aaroncc":"CA",
    "qs_pg:name":"Nickel Centre",
    "qs_pg:name_adm0":"Canada",
    "qs_pg:name_adm1":"Ontario",
    "qs_pg:photos":19,
    "qs_pg:photos_1k":4,
    "qs_pg:photos_9k":1,
    "qs_pg:photos_9r":2,
    "qs_pg:photos_all":40,
    "qs_pg:photos_sr":1,
    "qs_pg:pop_sr":0,
    "qs_pg:qs_pg_placetype":"locality",
    "qs_pg:qs_pg_placetype_gp":"Town",
    "qs_pg:woe_adm0":23424775,
    "woe:adm0_id":23424775,
    "woe:name_adm0":"Canada",
    "woe:name_adm1":"Ontario",
    "woe:placetype":"Town",
    "wof:name":"Nickel Centre",
    "wof:placetype":"locality"
},
  "geometry": {"coordinates":[-80.909757,46.475108],"type":"Point"}
}