{
  "type": "Feature",
  "properties": {
    "gn:admin1_code":"1.0",
    "gn:asciiname":"Devenish",
    "gn:country_code":"CA",
    "gn:dem":659,
    "gn:feature_class":"P",
    "gn:feature_code":"PPLL",
    "gn:name":"Devenish",
    "gn:population":0,
    "gn:timezone":"America/Edmonton",
    "iso:country":"CA",
    "name:deu_x_preferred":[
        "Devenish"
    ],
    "wof:name":"Devenish",
    "wof:placetype":"locality"
},
  "geometry": {"coordinates":[-111.20182,55.53351],"type":"Point"}
}