{
  "type": "Feature",
  "properties": {
    "gn:admin1_code":"8.0",
    "gn:asciiname":"Christian Valley",
    "gn:country_code":"CA",
    "gn:dem":201,
    "gn:feature_class":"P",
    "gn:feature_code":"PPL",
    "gn:name":"Christian Valley",
    "gn:population":0,
    "gn:timezone":"America/Toronto",
    "iso:country":"CA",
    "wof:name":"Christian Valley",
    "wof:placetype":"locality"
},
  "geometry": {"coordinates":[-79.48305999999999,46.07083],"type":"Point"}
}