{
  "type": "Feature",
  "properties": {
    "gn:admin1_code":"8",
    "gn:asciiname":"Lucasville",
    "gn:country_code":"CA",
    "gn:dem":193,
    "gn:feature_class":"P",
    "gn:feature_code":"PPL",
    "gn:name":"Lucasville",
    "gn:population":0,
    "gn:timezone":"America/Toronto",
    "iso:country":"CA",
    "name:deu_x_preferred":[
        "Lucasville"
    ],
    "wof:name":"Lucasville",
    "wof:placetype":"locality"
},
  "geometry": {"coordinates":[-82.34528,42.935],"type":"Point"}
}