{
  "type": "Feature",
  "properties": {
    "gn:admin1_code":"5",
    "gn:asciiname":"Port au Port West-Aguathuna-Felix Cove",
    "gn:country_code":"CA",
    "gn:dem":28,
    "gn:feature_class":"P",
    "gn:feature_code":"PPL",
    "gn:name":"Port au Port West-Aguathuna-Felix Cove",
    "gn:population":0,
    "gn:timezone":"America/St_Johns",
    "iso:country":"CA",
    "name:nld_x_preferred":[
        "Port au Port West-Aguathuna-Felix Cove"
    ],
    "wof:name":"Port au Port West-Aguathuna-Felix Cove",
    "wof:placetype":"locality"
},
  "geometry": {"coordinates":[-58.75184,48.55539],"type":"Point"}
}