{
  "type": "Feature",
  "properties": {
    "gn:admin1_code":"8.0",
    "gn:asciiname":"Willisville",
    "gn:country_code":"CA",
    "gn:dem":216,
    "gn:feature_class":"P",
    "gn:feature_code":"PPL",
    "gn:name":"Willisville",
    "gn:population":0,
    "gn:timezone":"America/Toronto",
    "iso:country":"CA",
    "name:ceb_x_preferred":[
        "Willisville"
    ],
    "name:deu_x_preferred":[
        "Willisville"
    ],
    "name:ita_x_preferred":[
        "Willisville"
    ],
    "name:nld_x_preferred":[
        "Willisville"
    ],
    "name:rus_x_preferred":[
        "\u0423\u0438\u043b\u043b\u0438\u0441\u0432\u0438\u043b\u043b"
    ],
    "name:srp_x_preferred":[
        "\u0412\u0438\u043b\u0438\u0441\u0432\u0438\u043b"
    ],
    "name:ukr_x_preferred":[
        "\u0412\u0456\u043b\u043b\u0456\u0441\u0432\u0456\u043b\u043b"
    ],
    "name:vol_x_preferred":[
        "Willisville"
    ],
    "wof:name":"Willisville",
    "wof:placetype":"locality"
},
  "geometry": {"coordinates":[-81.72139,46.13056],"type":"Point"}
}