{
  "type": "Feature",
  "properties": {
    "gn:admin1_code":"7",
    "gn:asciiname":"Seabrook",
    "gn:country_code":"CA",
    "gn:dem":23,
    "gn:feature_class":"P",
    "gn:feature_code":"PPL",
    "gn:name":"Seabrook",
    "gn:population":0,
    "gn:timezone":"America/Halifax",
    "iso:country":"CA",
    "wof:name":"Seabrook",
    "wof:placetype":"locality"
},
  "geometry": {"coordinates":[-65.81081999999999,44.61026],"type":"Point"}
}