{
  "type": "Feature",
  "properties": {
    "gn:admin1_code":"7",
    "gn:asciiname":"Seabrook",
    "gn:country_code":"CA",
    "gn:dem":23,
    "gn:feature_class":"P",
    "gn:feature_code":"PPL",
    "gn:name":"Seabrook",
    "gn:population":0,
    "gn:timezone":"America/Halifax",
    "iso:country":"CA",
    "name:cat_x_preferred":[
        "Seabrook"
    ],
    "name:ceb_x_preferred":[
        "Seabrook"
    ],
    "name:deu_x_preferred":[
        "Seabrook"
    ],
    "name:fra_x_preferred":[
        "Seabrook"
    ],
    "name:ita_x_preferred":[
        "Seabrook"
    ],
    "name:nld_x_preferred":[
        "Seabrook"
    ],
    "name:pol_x_preferred":[
        "Seabrook"
    ],
    "name:rus_x_preferred":[
        "\u0421\u0438\u0431\u0440\u0443\u043a"
    ],
    "name:srp_x_preferred":[
        "\u0421\u0438\u0431\u0440\u0443\u043a"
    ],
    "name:swe_x_preferred":[
        "Seabrook"
    ],
    "name:vol_x_preferred":[
        "Seabrook"
    ],
    "wof:name":"Seabrook",
    "wof:placetype":"locality"
},
  "geometry": {"coordinates":[-65.81081999999999,44.61026],"type":"Point"}
}