{
  "type": "Feature",
  "properties": {
    "gn:admin1_code":"8",
    "gn:asciiname":"Melrose",
    "gn:country_code":"CA",
    "gn:dem":265,
    "gn:feature_class":"P",
    "gn:feature_code":"PPL",
    "gn:name":"Melrose",
    "gn:population":0,
    "gn:timezone":"America/Toronto",
    "iso:country":"CA",
    "wof:name":"Melrose",
    "wof:placetype":"locality"
},
  "geometry": {"coordinates":[-81.39792,42.99906],"type":"Point"}
}