{
  "type": "Feature",
  "properties": {
    "gn:admin1_code":"3",
    "gn:asciiname":"South Knife Lake",
    "gn:country_code":"CA",
    "gn:dem":224,
    "gn:feature_class":"P",
    "gn:feature_code":"PPLL",
    "gn:name":"South Knife Lake",
    "gn:population":0,
    "gn:timezone":"America/Winnipeg",
    "iso:country":"CA",
    "wof:name":"South Knife Lake",
    "wof:placetype":"locality"
},
  "geometry": {"coordinates":[-96.35204,58.22094],"type":"Point"}
}