{
  "type": "Feature",
  "properties": {
    "gn:admin1_code":"2",
    "gn:asciiname":"Pinchi Lake",
    "gn:country_code":"CA",
    "gn:dem":790,
    "gn:feature_class":"P",
    "gn:feature_code":"PPLL",
    "gn:name":"Pinchi Lake",
    "gn:population":0,
    "gn:timezone":"America/Vancouver",
    "iso:country":"CA",
    "wof:name":"Pinchi Lake",
    "wof:placetype":"locality"
},
  "geometry": {"coordinates":[-124.41992999999999,54.63316999999999],"type":"Point"}
}