{
  "type": "Feature",
  "properties": {
    "gn:admin1_code":"13",
    "gn:asciiname":"Kittigazuit",
    "gn:country_code":"CA",
    "gn:dem":1,
    "gn:feature_class":"P",
    "gn:feature_code":"PPLL",
    "gn:name":"Kittigazuit",
    "gn:population":0,
    "gn:timezone":"America/Yellowknife",
    "iso:country":"CA",
    "wof:name":"Kittigazuit",
    "wof:placetype":"locality"
},
  "geometry": {"coordinates":[-133.69999000000001,69.34028000000001],"type":"Point"}
}