{
  "type": "Feature",
  "properties": {
    "gn:admin1_code":"5",
    "gn:asciiname":"Gunridge",
    "gn:country_code":"CA",
    "gn:dem":43,
    "gn:feature_class":"P",
    "gn:feature_code":"PPLL",
    "gn:name":"Gunridge",
    "gn:population":0,
    "gn:timezone":"America/St_Johns",
    "iso:country":"CA",
    "wof:name":"Gunridge",
    "wof:placetype":"locality"
},
  "geometry": {"coordinates":[-52.78883,47.31083],"type":"Point"}
}