{
  "type": "Feature",
  "properties": {
    "iso:country":"CA",
    "name:eng_x_preferred":[
        "Scotsville"
    ],
    "name:nld_x_preferred":[
        "Scotsville"
    ],
    "qs:name":"Scotsville",
    "qs:name_adm0":"Canada",
    "qs:name_adm1":"Nova Scotia",
    "qs:photos":12,
    "qs:photos_1k":2,
    "qs:photos_9k":1,
    "qs:photos_9r":1,
    "qs:photos_all":12,
    "qs:photos_sr":1,
    "qs:placetype":"Town",
    "qs:pop_sr":"0",
    "wd:wordcount":58,
    "wof:name":"Scotsville",
    "wof:placetype":"locality"
},
  "geometry": {"coordinates":[-61.1537225,46.1622065],"type":"Point"}
}