{
  "type": "Feature",
  "properties": {
    "gn:admin1_code":"3",
    "gn:asciiname":"Millwater",
    "gn:country_code":"CA",
    "gn:dem":296,
    "gn:feature_class":"P",
    "gn:feature_code":"PPLL",
    "gn:name":"Millwater",
    "gn:population":0,
    "gn:timezone":"America/Winnipeg",
    "iso:country":"CA",
    "wof:name":"Millwater",
    "wof:placetype":"locality"
},
  "geometry": {"coordinates":[-101.61518,54.59263000000001],"type":"Point"}
}