{
  "type": "Feature",
  "properties": {
    "gn:admin1_code":"4",
    "gn:asciiname":"Hicksville",
    "gn:country_code":"CA",
    "gn:dem":63,
    "gn:feature_class":"P",
    "gn:feature_code":"PPL",
    "gn:name":"Hicksville",
    "gn:population":0,
    "gn:timezone":"America/Moncton",
    "iso:country":"CA",
    "name:ceb_x_preferred":[
        "Hicksville"
    ],
    "name:dan_x_preferred":[
        "Hicksville"
    ],
    "name:deu_x_preferred":[
        "Hicksville"
    ],
    "name:fra_x_preferred":[
        "Hicksville"
    ],
    "name:ita_x_preferred":[
        "Hicksville"
    ],
    "name:nld_x_preferred":[
        "Hicksville"
    ],
    "name:pol_x_preferred":[
        "Hicksville"
    ],
    "name:por_x_preferred":[
        "Hicksville"
    ],
    "name:srp_x_preferred":[
        "\u0425\u0438\u043a\u0441\u0432\u0438\u043b"
    ],
    "name:ukr_x_preferred":[
        "\u0413\u0456\u043a\u0441\u0432\u0456\u043b\u043b"
    ],
    "name:vol_x_preferred":[
        "Hicksville"
    ],
    "wof:name":"Hicksville",
    "wof:placetype":"locality"
},
  "geometry": {"coordinates":[-65.30519,46.02224],"type":"Point"}
}