{
  "type": "Feature",
  "properties": {
    "gn:admin1_code":"1",
    "gn:asciiname":"Marten River",
    "gn:country_code":"CA",
    "gn:dem":572,
    "gn:feature_class":"P",
    "gn:feature_code":"PPLL",
    "gn:name":"Marten River",
    "gn:population":0,
    "gn:timezone":"America/Edmonton",
    "iso:country":"CA",
    "wof:name":"Marten River",
    "wof:placetype":"locality"
},
  "geometry": {"coordinates":[-116.16927,56.5002],"type":"Point"}
}