{
  "type": "Feature",
  "properties": {
    "iso:country":"CA",
    "name:eng_x_preferred":[
        "Summerhill"
    ],
    "name:unk_x_variant":[
        "Summerhill"
    ],
    "qs:gn_local":0,
    "qs:local_max":477,
    "qs:local_sum":525,
    "qs:localhoods":2,
    "qs:name":"Summerhill",
    "qs:name_adm0":"Canada",
    "qs:name_adm1":"Ontario",
    "qs:name_adm2":"York",
    "qs:name_local":"South Newmarket",
    "qs:photo_max":270,
    "qs:photo_sum":477,
    "qs:placetype":"Suburb",
    "qs:quad_count":21,
    "qs:woe_adm0":23424775,
    "qs:woe_adm1":2344922,
    "qs:woe_adm2":29375112,
    "qs:woe_funk":"Grouping neighborhood",
    "qs:woe_lau":0,
    "qs:woe_local":55999554,
    "qs:woe_ver":"7.10.0",
    "wof:lang":[
        "eng"
    ],
    "wof:name":"Summerhill",
    "wof:placetype":"neighbourhood"
},
  "geometry": {"coordinates":[-79.486226,44.035393],"type":"Point"}
}