{
  "type": "Feature",
  "properties": {
    "iso:country":"CA",
    "name:eng_x_preferred":[
        "Secteur Saint Jean"
    ],
    "name:fra_x_preferred":[
        "Secteur Saint Jean"
    ],
    "qs:gn_adm0_cc":"CA",
    "qs:gn_local":6138495,
    "qs:gn_nam_loc":"west branch",
    "qs:gn_namadm1":"10",
    "qs:local_max":217,
    "qs:local_sum":217,
    "qs:localhoods":1,
    "qs:name":"Secteur Saint Jean",
    "qs:name_adm0":"Canada",
    "qs:name_adm1":"Qu\u00e9bec",
    "qs:name_adm2":"Le Haut-Richelieu",
    "qs:name_local":"St-Jean-sur-Richelieu",
    "qs:photo_max":196,
    "qs:photo_sum":217,
    "qs:placetype":"Suburb",
    "qs:quad_count":9,
    "qs:woe_adm0":23424775,
    "qs:woe_adm1":2344924,
    "qs:woe_adm2":29375141,
    "qs:woe_funk":"Parented by a neighborhood",
    "qs:woe_lau":0,
    "qs:woe_local":3554,
    "qs:woe_ver":"7.10.0",
    "wof:lang":[
        "fre"
    ],
    "wof:name":"Secteur Saint Jean",
    "wof:placetype":"neighbourhood"
},
  "geometry": {"coordinates":[-73.26084899999999,45.310352],"type":"Point"}
}