{
  "type": "Feature",
  "properties": {
    "gn:country":"CA",
    "gn:fcode":"ADMD",
    "gn:pop":0,
    "iso:country":"CA",
    "name:eng_x_preferred":[
        "Bonfield"
    ],
    "qs:name":"Bonfield",
    "qs:photos_9r":0,
    "qs:photos_sr":0,
    "qs:pop_sr":"0",
    "wd:wordcount":8,
    "wof:name":"Bonfield",
    "wof:placetype":"localadmin",
    "wof:population":0
},
  "geometry": {"coordinates":[-79.0829,46.21681],"type":"Point"}
}