{
  "type": "Feature",
  "properties": {
    "iso:country":"CA",
    "name:deu_x_preferred":[
        "Louisbourg"
    ],
    "name:deu_x_variant":[
        "Festung Louisbourg"
    ],
    "name:eng_x_preferred":[
        "Fortress Louisburg"
    ],
    "name:eng_x_variant":[
        "Fortress of Louisbourg"
    ],
    "name:fra_x_preferred":[
        "Forteresse de Louisbourg"
    ],
    "name:gla_x_preferred":[
        "D\u00f9n nam Frangach"
    ],
    "name:heb_x_preferred":[
        "\u05de\u05e6\u05d5\u05d3\u05ea \u05dc\u05d5\u05d0\u05d9\u05d1\u05d5\u05e8"
    ],
    "name:ido_x_preferred":[
        "Louisbourg"
    ],
    "name:ita_x_preferred":[
        "Fortezza di Louisbourg"
    ],
    "name:jpn_x_preferred":[
        "\u30eb\u30a4\u30d6\u30fc\u30eb\u8981\u585e"
    ],
    "name:kat_x_preferred":[
        "\u10da\u10e3\u10d8\u10e1\u10d1\u10e3\u10e0\u10d2\u10d8\u10e1 \u10ea\u10d8\u10ee\u10d4\u10e1\u10d8\u10db\u10d0\u10d2\u10e0\u10d4"
    ],
    "name:kor_x_preferred":[
        "\ub8e8\uc774\uc2a4\ubc84\uadf8 \uc694\uc0c8"
    ],
    "name:lat_x_preferred":[
        "Castellum Ludoviciburgense"
    ],
    "name:nld_x_preferred":[
        "Louisbourg"
    ],
    "name:nno_x_preferred":[
        "Festninga Louisbourg"
    ],
    "name:nob_x_preferred":[
        "Festningen Louisbourg"
    ],
    "name:nor_x_preferred":[
        "Festningen Louisbourg"
    ],
    "name:pol_x_preferred":[
        "Twierdza Louisbourg"
    ],
    "name:por_x_preferred":[
        "Forte Louisbourg"
    ],
    "name:rus_x_preferred":[
        "\u041b\u0443\u0438\u0441\u0431\u0443\u0440\u0433"
    ],
    "name:spa_x_preferred":[
        "Fortaleza de Luisburgo"
    ],
    "name:swe_x_preferred":[
        "Louisbourg"
    ],
    "name:ukr_x_preferred":[
        "\u041b\u0443\u0457\u0441\u0431\u0443\u0440"
    ],
    "name:zho_x_preferred":[
        "\u8def\u6613\u65af\u5821\u8981\u585e"
    ],
    "qs:gn_adm0_cc":"CA",
    "qs:gn_local":6354908,
    "qs:gn_nam_loc":"sydney",
    "qs:gn_namadm1":"07",
    "qs:local_max":789,
    "qs:local_sum":2869,
    "qs:localhoods":18,
    "qs:name":"Fortress Louisburg",
    "qs:name_adm0":"Canada",
    "qs:name_adm1":"Nova Scotia",
    "qs:name_adm2":"Cape Breton",
    "qs:name_local":"Sydney",
    "qs:photo_max":275,
    "qs:photo_sum":789,
    "qs:placetype":"Suburb",
    "qs:quad_count":23,
    "qs:woe_adm0":23424775,
    "qs:woe_adm1":2344921,
    "qs:woe_adm2":29375130,
    "qs:woe_lau":0,
    "qs:woe_local":3755,
    "qs:woe_ver":"7.10.0",
    "wd:wordcount":3247,
    "wof:lang":[
        "eng"
    ],
    "wof:name":"Fortress Louisburg",
    "wof:placetype":"neighbourhood"
},
  "geometry": {"coordinates":[-59.992612,45.893641],"type":"Point"}
}