{
  "type": "Feature",
  "properties": {
    "gn:admin1_code":"7",
    "gn:asciiname":"Rocky Mountain",
    "gn:country_code":"CA",
    "gn:dem":117,
    "gn:feature_class":"P",
    "gn:feature_code":"PPL",
    "gn:name":"Rocky Mountain",
    "gn:population":0,
    "gn:timezone":"America/Halifax",
    "iso:country":"CA",
    "wof:name":"Rocky Mountain",
    "wof:placetype":"locality"
},
  "geometry": {"coordinates":[-62.24635,45.39424],"type":"Point"}
}