{
  "type": "Feature",
  "properties": {
    "gn:admin1_code":"8.0",
    "gn:asciiname":"Britannia Road",
    "gn:country_code":"CA",
    "gn:dem":337,
    "gn:feature_class":"P",
    "gn:feature_code":"PPL",
    "gn:name":"Britannia Road",
    "gn:population":0,
    "gn:timezone":"America/Toronto",
    "iso:country":"CA",
    "wof:name":"Britannia Road",
    "wof:placetype":"locality"
},
  "geometry": {"coordinates":[-79.17775999999998,45.27125],"type":"Point"}
}