{
  "type": "Feature",
  "properties": {
    "gn:admin1_code":"2",
    "gn:asciiname":"Palling",
    "gn:country_code":"CA",
    "gn:dem":735,
    "gn:feature_class":"P",
    "gn:feature_code":"PPL",
    "gn:name":"Palling",
    "gn:population":0,
    "gn:timezone":"America/Vancouver",
    "iso:country":"CA",
    "wof:name":"Palling",
    "wof:placetype":"locality"
},
  "geometry": {"coordinates":[-125.88333,54.35],"type":"Point"}
}