{
  "type": "Feature",
  "properties": {
    "gn:admin1_code":"2",
    "gn:asciiname":"Palling",
    "gn:country_code":"CA",
    "gn:dem":735,
    "gn:feature_class":"P",
    "gn:feature_code":"PPL",
    "gn:name":"Palling",
    "gn:population":0,
    "gn:timezone":"America/Vancouver",
    "iso:country":"CA",
    "name:arg_x_preferred":[
        "Palling"
    ],
    "name:bar_x_preferred":[
        "Palling"
    ],
    "name:ceb_x_preferred":[
        "Palling"
    ],
    "name:deu_x_preferred":[
        "Palling"
    ],
    "name:epo_x_preferred":[
        "Palling"
    ],
    "name:eus_x_preferred":[
        "Palling"
    ],
    "name:fas_x_preferred":[
        "\u067e\u0627\u0644\u06cc\u0646\u06af"
    ],
    "name:fra_x_preferred":[
        "Palling"
    ],
    "name:hun_x_preferred":[
        "Palling"
    ],
    "name:hye_x_preferred":[
        "\u0553\u0561\u056c\u056b\u0576\u0563"
    ],
    "name:ita_x_preferred":[
        "Palling"
    ],
    "name:kaz_x_preferred":[
        "\u041f\u0430\u043b\u043b\u0438\u043d\u0433"
    ],
    "name:kir_x_preferred":[
        "\u041f\u0430\u043b\u043b\u0438\u043d\u0433"
    ],
    "name:lmo_x_preferred":[
        "Palling"
    ],
    "name:msa_x_preferred":[
        "Palling"
    ],
    "name:nld_x_preferred":[
        "Palling"
    ],
    "name:pol_x_preferred":[
        "Palling"
    ],
    "name:ron_x_preferred":[
        "Palling"
    ],
    "name:rus_x_preferred":[
        "\u041f\u0430\u043b\u043b\u0438\u043d\u0433"
    ],
    "name:spa_x_preferred":[
        "Palling"
    ],
    "name:srp_x_preferred":[
        "\u041f\u0430\u043b\u0438\u043d\u0433"
    ],
    "name:ukr_x_preferred":[
        "\u041f\u0430\u043b\u043b\u0456\u043d\u0433"
    ],
    "name:uzb_x_preferred":[
        "Palling"
    ],
    "name:vie_x_preferred":[
        "Palling"
    ],
    "name:vol_x_preferred":[
        "Palling"
    ],
    "name:war_x_preferred":[
        "Palling"
    ],
    "wof:name":"Palling",
    "wof:placetype":"locality"
},
  "geometry": {"coordinates":[-125.88333,54.35],"type":"Point"}
}