{
  "type": "Feature",
  "properties": {
    "gn:admin1_code":"8.0",
    "gn:asciiname":"Campbells Beach",
    "gn:country_code":"CA",
    "gn:dem":232,
    "gn:feature_class":"P",
    "gn:feature_code":"PPL",
    "gn:name":"Campbells Beach",
    "gn:population":0,
    "gn:timezone":"America/Toronto",
    "iso:country":"CA",
    "wof:name":"Campbells Beach",
    "wof:placetype":"locality"
},
  "geometry": {"coordinates":[-79.11721999999997,44.615],"type":"Point"}
}