{
  "type": "Feature",
  "properties": {
    "gn:admin1_code":"11",
    "gn:asciiname":"Rockford",
    "gn:country_code":"CA",
    "gn:dem":579,
    "gn:feature_class":"P",
    "gn:feature_code":"PPLL",
    "gn:name":"Rockford",
    "gn:population":0,
    "gn:timezone":"America/Regina",
    "iso:country":"CA",
    "wof:name":"Rockford",
    "wof:placetype":"locality"
},
  "geometry": {"coordinates":[-102.93425999999999,52.16668],"type":"Point"}
}