{
  "type": "Feature",
  "properties": {
    "gn:admin1_code":"11",
    "gn:asciiname":"Rockford",
    "gn:country_code":"CA",
    "gn:dem":579,
    "gn:feature_class":"P",
    "gn:feature_code":"PPLL",
    "gn:name":"Rockford",
    "gn:population":0,
    "gn:timezone":"America/Regina",
    "iso:country":"CA",
    "name:ara_x_preferred":[
        "\u0631\u0648\u0643\u0641\u0648\u0631\u062f"
    ],
    "name:bre_x_preferred":[
        "Rockford"
    ],
    "name:cat_x_preferred":[
        "Rockford"
    ],
    "name:ceb_x_preferred":[
        "Rockford"
    ],
    "name:deu_x_preferred":[
        "Rockford"
    ],
    "name:epo_x_preferred":[
        "Rockford"
    ],
    "name:fin_x_preferred":[
        "Rockford"
    ],
    "name:fra_x_preferred":[
        "Rockford"
    ],
    "name:ita_x_preferred":[
        "Rockford"
    ],
    "name:jpn_x_preferred":[
        "\u30ed\u30c3\u30af\u30d5\u30a9\u30fc\u30c9"
    ],
    "name:kor_x_preferred":[
        "\ub85d\ud37c\ub4dc"
    ],
    "name:nds_x_preferred":[
        "Rockford"
    ],
    "name:nld_x_preferred":[
        "Rockford"
    ],
    "name:pol_x_preferred":[
        "Rockford"
    ],
    "name:por_x_preferred":[
        "Rockford"
    ],
    "name:rus_x_preferred":[
        "\u0420\u043e\u043a\u0444\u043e\u0440\u0434"
    ],
    "name:spa_x_preferred":[
        "Rockford"
    ],
    "name:srp_x_preferred":[
        "\u0420\u043e\u043a\u0444\u043e\u0440\u0434"
    ],
    "name:swe_x_preferred":[
        "Rockford"
    ],
    "name:vol_x_preferred":[
        "Rockford"
    ],
    "wof:name":"Rockford",
    "wof:placetype":"locality"
},
  "geometry": {"coordinates":[-102.93425999999999,52.16668],"type":"Point"}
}