{
  "type": "Feature",
  "properties": {
    "gn:admin1_code":"2",
    "gn:asciiname":"Nazko",
    "gn:country_code":"CA",
    "gn:dem":837,
    "gn:feature_class":"P",
    "gn:feature_code":"PPL",
    "gn:name":"Nazko",
    "gn:population":0,
    "gn:timezone":"America/Vancouver",
    "iso:country":"CA",
    "wof:name":"Nazko",
    "wof:placetype":"locality"
},
  "geometry": {"coordinates":[-123.61971,52.99983],"type":"Point"}
}