{
  "type": "Feature",
  "properties": {
    "gn:admin1_code":"7",
    "gn:asciiname":"Noel Shore",
    "gn:country_code":"CA",
    "gn:dem":21,
    "gn:feature_class":"P",
    "gn:feature_code":"PPL",
    "gn:name":"Noel Shore",
    "gn:population":0,
    "gn:timezone":"America/Halifax",
    "iso:country":"CA",
    "wof:name":"Noel Shore",
    "wof:placetype":"locality"
},
  "geometry": {"coordinates":[-63.63339000000001,45.31314],"type":"Point"}
}