{
  "type": "Feature",
  "properties": {
    "gn:admin1_code":"8",
    "gn:asciiname":"Varency",
    "gn:country_code":"CA",
    "gn:dem":205,
    "gn:feature_class":"P",
    "gn:feature_code":"PPL",
    "gn:name":"Varency",
    "gn:population":0,
    "gn:timezone":"America/Toronto",
    "iso:country":"CA",
    "wof:name":"Varency",
    "wof:placetype":"locality"
},
  "geometry": {"coordinates":[-80.12461,42.84902],"type":"Point"}
}