{
  "type": "Feature",
  "properties": {
    "gn:admin1_code":"10",
    "gn:admin2_code":"15.0",
    "gn:admin3_code":"77060.0",
    "gn:asciiname":"Newaygo",
    "gn:country_code":"CA",
    "gn:dem":411,
    "gn:feature_class":"P",
    "gn:feature_code":"PPL",
    "gn:name":"Newaygo",
    "gn:population":0,
    "gn:timezone":"America/Toronto",
    "iso:country":"CA",
    "wof:name":"Newaygo",
    "wof:placetype":"locality"
},
  "geometry": {"coordinates":[-74.34878,45.88115],"type":"Point"}
}