{
  "type": "Feature",
  "properties": {
    "gn:admin1_code":"9.0",
    "gn:asciiname":"Commercial Cross",
    "gn:country_code":"CA",
    "gn:dem":52,
    "gn:feature_class":"P",
    "gn:feature_code":"PPLL",
    "gn:name":"Commercial Cross",
    "gn:population":0,
    "gn:timezone":"America/Halifax",
    "iso:country":"CA",
    "wof:name":"Commercial Cross",
    "wof:placetype":"locality"
},
  "geometry": {"coordinates":[-62.63196,46.13341],"type":"Point"}
}