{
  "type": "Feature",
  "properties": {
    "gn:admin1_code":"2",
    "gn:asciiname":"Toby Creek",
    "gn:country_code":"CA",
    "gn:dem":1458,
    "gn:feature_class":"P",
    "gn:feature_code":"PPLL",
    "gn:name":"Toby Creek",
    "gn:population":0,
    "gn:timezone":"America/Edmonton",
    "iso:country":"CA",
    "wof:name":"Toby Creek",
    "wof:placetype":"locality"
},
  "geometry": {"coordinates":[-116.41878,50.33325],"type":"Point"}
}