{
  "type": "Feature",
  "properties": {
    "gn:admin1_code":"1.0",
    "gn:asciiname":"Beaver Lake",
    "gn:country_code":"CA",
    "gn:dem":579,
    "gn:feature_class":"P",
    "gn:feature_code":"PPL",
    "gn:name":"Beaver Lake",
    "gn:population":0,
    "gn:timezone":"America/Edmonton",
    "iso:country":"CA",
    "name:fra_x_preferred":[
        "Beaver Lake"
    ],
    "wof:name":"Beaver Lake",
    "wof:placetype":"locality"
},
  "geometry": {"coordinates":[-111.9186,54.7669],"type":"Point"}
}