{
  "type": "Feature",
  "properties": {
    "gn:admin1_code":"11",
    "gn:asciiname":"Square Hill",
    "gn:country_code":"CA",
    "gn:dem":656,
    "gn:feature_class":"P",
    "gn:feature_code":"PPLL",
    "gn:name":"Square Hill",
    "gn:population":0,
    "gn:timezone":"America/Regina",
    "iso:country":"CA",
    "wof:name":"Square Hill",
    "wof:placetype":"locality"
},
  "geometry": {"coordinates":[-107.90128,53.01683000000001],"type":"Point"}
}