{
  "type": "Feature",
  "properties": {
    "gn:admin1_code":"10",
    "gn:admin2_code":"7.0",
    "gn:admin3_code":"82025.0",
    "gn:asciiname":"Farm Point",
    "gn:country_code":"CA",
    "gn:dem":113,
    "gn:feature_class":"P",
    "gn:feature_code":"PPL",
    "gn:name":"Farm Point",
    "gn:population":0,
    "gn:timezone":"America/Toronto",
    "iso:country":"CA",
    "wof:name":"Farm Point",
    "wof:placetype":"locality"
},
  "geometry": {"coordinates":[-75.89468000000002,45.60227],"type":"Point"}
}