{
  "type": "Feature",
  "properties": {
    "gn:admin1_code":"11",
    "gn:asciiname":"Lyons",
    "gn:country_code":"CA",
    "gn:dem":568,
    "gn:feature_class":"P",
    "gn:feature_code":"PPL",
    "gn:name":"Lyons",
    "gn:population":0,
    "gn:timezone":"America/Regina",
    "iso:country":"CA",
    "wof:name":"Lyons",
    "wof:placetype":"locality"
},
  "geometry": {"coordinates":[-107.02146999999999,51.26115],"type":"Point"}
}