{
  "type": "Feature",
  "properties": {
    "gn:admin1_code":"3",
    "gn:asciiname":"Gregorys Mill",
    "gn:country_code":"CA",
    "gn:dem":382,
    "gn:feature_class":"P",
    "gn:feature_code":"PPLL",
    "gn:name":"Gregorys Mill",
    "gn:population":0,
    "gn:timezone":"America/Winnipeg",
    "iso:country":"CA",
    "wof:name":"Gregorys Mill",
    "wof:placetype":"locality"
},
  "geometry": {"coordinates":[-99.82944999999999,49.52422],"type":"Point"}
}