{
  "type": "Feature",
  "properties": {
    "gn:admin1_code":"10",
    "gn:asciiname":"Riviere-aux-Graines",
    "gn:country_code":"CA",
    "gn:dem":9,
    "gn:feature_class":"P",
    "gn:feature_code":"PPL",
    "gn:name":"Rivi\u00e8re-aux-Graines",
    "gn:population":0,
    "gn:timezone":"America/Toronto",
    "iso:country":"CA",
    "wof:name":"Riviere-aux-Graines",
    "wof:placetype":"locality"
},
  "geometry": {"coordinates":[-65.18205,50.28341],"type":"Point"}
}