{
  "type": "Feature",
  "properties": {
    "gn:admin1_code":"11",
    "gn:asciiname":"Robinhood",
    "gn:country_code":"CA",
    "gn:dem":715,
    "gn:feature_class":"P",
    "gn:feature_code":"PPL",
    "gn:name":"Robinhood",
    "gn:population":0,
    "gn:timezone":"America/Regina",
    "iso:country":"CA",
    "name:ita_x_preferred":[
        "Robinhood"
    ],
    "wof:name":"Robinhood",
    "wof:placetype":"locality"
},
  "geometry": {"coordinates":[-108.20067,53.28341],"type":"Point"}
}