{
  "type": "Feature",
  "properties": {
    "gn:admin1_code":"8",
    "gn:asciiname":"Toimela",
    "gn:country_code":"CA",
    "gn:dem":471,
    "gn:feature_class":"P",
    "gn:feature_code":"PPL",
    "gn:name":"Toimela",
    "gn:population":0,
    "gn:timezone":"America/Toronto",
    "iso:country":"CA",
    "wof:name":"Toimela",
    "wof:placetype":"locality"
},
  "geometry": {"coordinates":[-89.39265999999998,48.55013],"type":"Point"}
}