{
  "type": "Feature",
  "properties": {
    "gn:admin1_code":"8",
    "gn:asciiname":"Motts Mills",
    "gn:country_code":"CA",
    "gn:dem":127,
    "gn:feature_class":"P",
    "gn:feature_code":"PPL",
    "gn:name":"Motts Mills",
    "gn:population":0,
    "gn:timezone":"America/Toronto",
    "iso:country":"CA",
    "wof:name":"Motts Mills",
    "wof:placetype":"locality"
},
  "geometry": {"coordinates":[-76.03055999999999,44.78778],"type":"Point"}
}