{
  "type": "Feature",
  "properties": {
    "iso:country":"CA",
    "name:eng_x_preferred":[
        "Uncas"
    ],
    "qs:name":"Uncas",
    "qs:name_adm0":"Canada",
    "qs:name_adm1":"Alberta",
    "qs:photos":75,
    "qs:photos_1k":15,
    "qs:photos_9k":1,
    "qs:photos_9r":2,
    "qs:photos_all":75,
    "qs:photos_sr":2,
    "qs:placetype":"Town",
    "qs:pop_sr":"0",
    "wd:wordcount":1238,
    "wof:name":"Uncas",
    "wof:placetype":"locality"
},
  "geometry": {"coordinates":[-113.021,53.504843],"type":"Point"}
}