{
  "type": "Feature",
  "properties": {
    "iso:country":"CA",
    "name:ast_x_preferred":[
        "Uncas"
    ],
    "name:bul_x_preferred":[
        "\u0423\u043d\u043a\u0430\u0441"
    ],
    "name:cat_x_preferred":[
        "Uncas"
    ],
    "name:ces_x_preferred":[
        "Uncas"
    ],
    "name:deu_x_preferred":[
        "Uncas"
    ],
    "name:eng_x_preferred":[
        "Uncas"
    ],
    "name:fin_x_preferred":[
        "Uncas"
    ],
    "name:fra_x_preferred":[
        "Uncas"
    ],
    "name:gle_x_preferred":[
        "Uncas"
    ],
    "name:ita_x_preferred":[
        "Uncas"
    ],
    "name:jpn_x_preferred":[
        "\u30a6\u30f3\u30ab\u30b9"
    ],
    "name:nld_x_preferred":[
        "Uncas"
    ],
    "name:rus_x_preferred":[
        "\u0423\u043d\u043a\u0430\u0441"
    ],
    "name:spa_x_preferred":[
        "Uncas"
    ],
    "name:swe_x_preferred":[
        "Uncas"
    ],
    "name:tur_x_preferred":[
        "Uncas"
    ],
    "qs:name":"Uncas",
    "qs:name_adm0":"Canada",
    "qs:name_adm1":"Alberta",
    "qs:photos":75,
    "qs:photos_1k":15,
    "qs:photos_9k":1,
    "qs:photos_9r":2,
    "qs:photos_all":75,
    "qs:photos_sr":2,
    "qs:placetype":"Town",
    "qs:pop_sr":"0",
    "wd:wordcount":1238,
    "wof:name":"Uncas",
    "wof:placetype":"locality"
},
  "geometry": {"coordinates":[-113.021,53.504843],"type":"Point"}
}