{
  "type": "Feature",
  "properties": {
    "gn:admin1_code":"11",
    "gn:asciiname":"Horseshoe Bay",
    "gn:country_code":"CA",
    "gn:dem":658,
    "gn:feature_class":"P",
    "gn:feature_code":"PPLL",
    "gn:name":"Horseshoe Bay",
    "gn:population":0,
    "gn:timezone":"America/Regina",
    "iso:country":"CA",
    "wof:name":"Horseshoe Bay",
    "wof:placetype":"locality"
},
  "geometry": {"coordinates":[-108.6347,53.61688],"type":"Point"}
}