{
  "type": "Feature",
  "properties": {
    "gn:admin1_code":"4.0",
    "gn:asciiname":"Castaway",
    "gn:country_code":"CA",
    "gn:dem":34,
    "gn:feature_class":"P",
    "gn:feature_code":"PPL",
    "gn:name":"Castaway",
    "gn:population":0,
    "gn:timezone":"America/Moncton",
    "iso:country":"CA",
    "name:fra_x_preferred":[
        "Naufrag\u00e9"
    ],
    "name:isl_x_preferred":[
        "Skipbrotsma\u00f0ur"
    ],
    "name:ita_x_preferred":[
        "Naufrago"
    ],
    "name:por_x_preferred":[
        "N\u00e1ufrago"
    ],
    "wof:name":"Castaway",
    "wof:placetype":"locality"
},
  "geometry": {"coordinates":[-65.72714000000001,46.29239000000001],"type":"Point"}
}