{
  "type": "Feature",
  "properties": {
    "gn:admin1_code":"8",
    "gn:asciiname":"Sea Breeze",
    "gn:country_code":"CA",
    "gn:dem":323,
    "gn:feature_class":"P",
    "gn:feature_code":"PPL",
    "gn:name":"Sea Breeze",
    "gn:population":0,
    "gn:timezone":"America/Toronto",
    "iso:country":"CA",
    "name:deu_x_preferred":[
        "Sea Breeze"
    ],
    "name:nld_x_preferred":[
        "Sea Breeze"
    ],
    "name:pol_x_preferred":[
        "Sea Breeze"
    ],
    "wof:name":"Sea Breeze",
    "wof:placetype":"locality"
},
  "geometry": {"coordinates":[-78.97139,45.28583],"type":"Point"}
}