{
  "type": "Feature",
  "properties": {
    "gn:admin1_code":"8",
    "gn:asciiname":"Oakgrove",
    "gn:country_code":"CA",
    "gn:dem":144,
    "gn:feature_class":"P",
    "gn:feature_code":"PPL",
    "gn:name":"Oakgrove",
    "gn:population":0,
    "gn:timezone":"America/Toronto",
    "iso:country":"CA",
    "name:pol_x_preferred":[
        "Oakgrove"
    ],
    "wof:name":"Oakgrove",
    "wof:placetype":"locality"
},
  "geometry": {"coordinates":[-76.81548000000002,45.46261],"type":"Point"}
}