{
  "type": "Feature",
  "properties": {
    "gn:admin1_code":"2",
    "gn:asciiname":"Stanley",
    "gn:country_code":"CA",
    "gn:dem":1277,
    "gn:feature_class":"P",
    "gn:feature_code":"PPLL",
    "gn:name":"Stanley",
    "gn:population":0,
    "gn:timezone":"America/Vancouver",
    "iso:country":"CA",
    "wof:name":"Stanley",
    "wof:placetype":"locality"
},
  "geometry": {"coordinates":[-121.7195,53.0332],"type":"Point"}
}