{
  "type": "Feature",
  "properties": {
    "gn:admin1_code":"8.0",
    "gn:asciiname":"Coldwell",
    "gn:country_code":"CA",
    "gn:dem":217,
    "gn:feature_class":"P",
    "gn:feature_code":"PPL",
    "gn:name":"Coldwell",
    "gn:population":0,
    "gn:timezone":"America/Toronto",
    "iso:country":"CA",
    "name:deu_x_preferred":[
        "Coldwell"
    ],
    "name:nds_x_preferred":[
        "Coldwell"
    ],
    "wof:name":"Coldwell",
    "wof:placetype":"locality"
},
  "geometry": {"coordinates":[-86.52871999999998,48.76242],"type":"Point"}
}