{
  "type": "Feature",
  "properties": {
    "gn:admin1_code":"8",
    "gn:asciiname":"Kirk",
    "gn:country_code":"CA",
    "gn:dem":203,
    "gn:feature_class":"P",
    "gn:feature_code":"PPL",
    "gn:name":"Kirk",
    "gn:population":0,
    "gn:timezone":"America/Toronto",
    "iso:country":"CA",
    "wof:name":"Kirk",
    "wof:placetype":"locality"
},
  "geometry": {"coordinates":[-80.21666999999999,46.42778],"type":"Point"}
}