{
  "type": "Feature",
  "properties": {
    "gn:admin1_code":"8.0",
    "gn:asciiname":"Annable Settlement",
    "gn:country_code":"CA",
    "gn:dem":75,
    "gn:feature_class":"P",
    "gn:feature_code":"PPL",
    "gn:name":"Annable Settlement",
    "gn:population":0,
    "gn:timezone":"America/Toronto",
    "iso:country":"CA",
    "wof:name":"Annable Settlement",
    "wof:placetype":"locality"
},
  "geometry": {"coordinates":[-75.35684000000001,45.10627],"type":"Point"}
}