{
  "type": "Feature",
  "properties": {
    "gn:admin1_code":"4.0",
    "gn:admin2_code":"1309",
    "gn:asciiname":"Wayerton",
    "gn:country_code":"CA",
    "gn:dem":28,
    "gn:feature_class":"P",
    "gn:feature_code":"PPL",
    "gn:name":"Wayerton",
    "gn:population":0,
    "gn:timezone":"America/Moncton",
    "iso:country":"CA",
    "wof:name":"Wayerton",
    "wof:placetype":"locality"
},
  "geometry": {"coordinates":[-65.83463,47.13515],"type":"Point"}
}