{
  "type": "Feature",
  "properties": {
    "gn:admin1_code":"3.0",
    "gn:asciiname":"Channing",
    "gn:country_code":"CA",
    "gn:dem":303,
    "gn:feature_class":"P",
    "gn:feature_code":"PPL",
    "gn:name":"Channing",
    "gn:population":0,
    "gn:timezone":"America/Winnipeg",
    "iso:country":"CA",
    "name:deu_x_preferred":[
        "Channing"
    ],
    "name:fra_x_preferred":[
        "Channing"
    ],
    "name:ita_x_preferred":[
        "Channing"
    ],
    "name:nds_x_preferred":[
        "Channing"
    ],
    "name:pol_x_preferred":[
        "Channing"
    ],
    "name:por_x_preferred":[
        "Channing"
    ],
    "name:rus_x_preferred":[
        "\u0427\u0430\u043d\u043d\u0438\u043d\u0433"
    ],
    "name:swe_x_preferred":[
        "Channing"
    ],
    "wof:name":"Channing",
    "wof:placetype":"locality"
},
  "geometry": {"coordinates":[-101.83327,54.75374],"type":"Point"}
}