{
  "type": "Feature",
  "properties": {
    "gn:admin1_code":"4",
    "gn:asciiname":"Lower Derby",
    "gn:country_code":"CA",
    "gn:dem":21,
    "gn:feature_class":"P",
    "gn:feature_code":"PPL",
    "gn:name":"Lower Derby",
    "gn:population":0,
    "gn:timezone":"America/Moncton",
    "iso:country":"CA",
    "wof:name":"Lower Derby",
    "wof:placetype":"locality"
},
  "geometry": {"coordinates":[-65.61941,46.93146],"type":"Point"}
}