{
  "type": "Feature",
  "properties": {
    "gn:admin1_code":"2",
    "gn:admin2_code":"5923.0",
    "gn:asciiname":"Ecoole",
    "gn:country_code":"CA",
    "gn:dem":42,
    "gn:feature_class":"P",
    "gn:feature_code":"PPLL",
    "gn:name":"Ecoole",
    "gn:population":0,
    "gn:timezone":"America/Vancouver",
    "iso:country":"CA",
    "wof:name":"Ecoole",
    "wof:placetype":"locality"
},
  "geometry": {"coordinates":[-125.05662,48.96881],"type":"Point"}
}