{
  "type": "Feature",
  "properties": {
    "gn:admin1_code":"11.0",
    "gn:asciiname":"Cantuar",
    "gn:country_code":"CA",
    "gn:dem":730,
    "gn:feature_class":"P",
    "gn:feature_code":"PPL",
    "gn:name":"Cantuar",
    "gn:population":0,
    "gn:timezone":"America/Regina",
    "iso:country":"CA",
    "wof:name":"Cantuar",
    "wof:placetype":"locality"
},
  "geometry": {"coordinates":[-108.00068,50.38337],"type":"Point"}
}