{
  "type": "Feature",
  "properties": {
    "gn:admin1_code":"2.0",
    "gn:asciiname":"Braeloch",
    "gn:country_code":"CA",
    "gn:dem":581,
    "gn:feature_class":"P",
    "gn:feature_code":"PPLL",
    "gn:name":"Braeloch",
    "gn:population":0,
    "gn:timezone":"America/Vancouver",
    "iso:country":"CA",
    "wof:name":"Braeloch",
    "wof:placetype":"locality"
},
  "geometry": {"coordinates":[-119.51907,49.78307],"type":"Point"}
}