{
  "type": "Feature",
  "properties": {
    "gn:admin1_code":"5",
    "gn:asciiname":"Renews-Cappahayden",
    "gn:country_code":"CA",
    "gn:dem":23,
    "gn:feature_class":"P",
    "gn:feature_code":"PPL",
    "gn:name":"Renews-Cappahayden",
    "gn:population":0,
    "gn:timezone":"America/St_Johns",
    "iso:country":"CA",
    "name:ceb_x_preferred":[
        "Renews-Cappahayden"
    ],
    "name:swe_x_preferred":[
        "Renews-Cappahayden"
    ],
    "wof:name":"Renews-Cappahayden",
    "wof:placetype":"locality"
},
  "geometry": {"coordinates":[-52.93899999999999,46.93104],"type":"Point"}
}