{
  "type": "Feature",
  "properties": {
    "gn:admin1_code":"8",
    "gn:asciiname":"Lorne Park",
    "gn:country_code":"CA",
    "gn:dem":97,
    "gn:feature_class":"P",
    "gn:feature_code":"PPL",
    "gn:name":"Lorne Park",
    "gn:population":0,
    "gn:timezone":"America/Toronto",
    "iso:country":"CA",
    "wof:name":"Lorne Park",
    "wof:placetype":"locality"
},
  "geometry": {"coordinates":[-79.61861,43.53528],"type":"Point"}
}