{
  "type": "Feature",
  "properties": {
    "gn:admin1_code":"3",
    "gn:asciiname":"Sperling",
    "gn:country_code":"CA",
    "gn:dem":242,
    "gn:feature_class":"P",
    "gn:feature_code":"PPL",
    "gn:name":"Sperling",
    "gn:population":0,
    "gn:timezone":"America/Winnipeg",
    "iso:country":"CA",
    "wof:name":"Sperling",
    "wof:placetype":"locality"
},
  "geometry": {"coordinates":[-97.7054,49.50811],"type":"Point"}
}