{
  "type": "Feature",
  "properties": {
    "gn:admin1_code":"7",
    "gn:asciiname":"Head of Loch Lomond",
    "gn:country_code":"CA",
    "gn:dem":50,
    "gn:feature_class":"P",
    "gn:feature_code":"PPL",
    "gn:name":"Head of Loch Lomond",
    "gn:population":0,
    "gn:timezone":"America/Halifax",
    "iso:country":"CA",
    "wof:name":"Head of Loch Lomond",
    "wof:placetype":"locality"
},
  "geometry": {"coordinates":[-60.59866,45.7271],"type":"Point"}
}