{
  "type": "Feature",
  "properties": {
    "gn:admin1_code":"1.0",
    "gn:asciiname":"Burnside Heights",
    "gn:country_code":"CA",
    "gn:dem":722,
    "gn:feature_class":"P",
    "gn:feature_code":"PPL",
    "gn:name":"Burnside Heights",
    "gn:population":0,
    "gn:timezone":"America/Edmonton",
    "iso:country":"CA",
    "wof:name":"Burnside Heights",
    "wof:placetype":"locality"
},
  "geometry": {"coordinates":[-110.75139,50.05556],"type":"Point"}
}