{
  "type": "Feature",
  "properties": {
    "gn:country":"CA",
    "gn:fcode":"PPL",
    "gn:population":0,
    "iso:country":"CA",
    "name:ceb_x_preferred":[
        "Woody Point"
    ],
    "name:eng_x_preferred":[
        "Woody Point"
    ],
    "name:mlg_x_preferred":[
        "Woody Point"
    ],
    "name:swe_x_preferred":[
        "Woody Point"
    ],
    "qs:name":"Woody Point",
    "qs:name_adm0":"Canada",
    "qs:name_adm1":"Newfoundland and Labrador",
    "qs:photos":240,
    "qs:photos_1k":49,
    "qs:photos_9k":1,
    "qs:photos_9r":4,
    "qs:photos_all":240,
    "qs:photos_sr":4,
    "qs:placetype":"Town",
    "qs:pop_sr":"0",
    "wof:name":"Woody Point",
    "wof:placetype":"locality",
    "wof:population":0
},
  "geometry": {"coordinates":[-57.93162,49.50001],"type":"Point"}
}