{
  "type": "Feature",
  "properties": {
    "gn:admin1_code":"10.0",
    "gn:admin2_code":"15.0",
    "gn:admin3_code":"75017.0",
    "gn:asciiname":"Domaine-Hatin",
    "gn:country_code":"CA",
    "gn:dem":135,
    "gn:feature_class":"P",
    "gn:feature_code":"PPL",
    "gn:name":"Domaine-Hatin",
    "gn:population":0,
    "gn:timezone":"America/Toronto",
    "iso:country":"CA",
    "wof:name":"Domaine-Hatin",
    "wof:placetype":"locality"
},
  "geometry": {"coordinates":[-74.04765999999999,45.77254],"type":"Point"}
}