{
  "type": "Feature",
  "properties": {
    "gn:admin1_code":"2.0",
    "gn:asciiname":"Doig River",
    "gn:country_code":"CA",
    "gn:dem":651,
    "gn:feature_class":"P",
    "gn:feature_code":"PPL",
    "gn:name":"Doig River",
    "gn:population":0,
    "gn:timezone":"America/Dawson_Creek",
    "iso:country":"CA",
    "wof:name":"Doig River",
    "wof:placetype":"locality"
},
  "geometry": {"coordinates":[-120.49167,56.57222],"type":"Point"}
}