{
  "type": "Feature",
  "properties": {
    "gn:admin1_code":"7.0",
    "gn:asciiname":"Cherry Hill",
    "gn:country_code":"CA",
    "gn:dem":9,
    "gn:feature_class":"P",
    "gn:feature_code":"PPL",
    "gn:name":"Cherry Hill",
    "gn:population":0,
    "gn:timezone":"America/Halifax",
    "iso:country":"CA",
    "name:gla_x_preferred":[
        "Cherry Hill"
    ],
    "wof:name":"Cherry Hill",
    "wof:placetype":"locality"
},
  "geometry": {"coordinates":[-64.49011999999999,44.15235],"type":"Point"}
}