{
  "type": "Feature",
  "properties": {
    "gn:admin1_code":"9",
    "gn:asciiname":"North Carleton",
    "gn:country_code":"CA",
    "gn:dem":19,
    "gn:feature_class":"P",
    "gn:feature_code":"PPLL",
    "gn:name":"North Carleton",
    "gn:population":0,
    "gn:timezone":"America/Halifax",
    "iso:country":"CA",
    "wof:name":"North Carleton",
    "wof:placetype":"locality"
},
  "geometry": {"coordinates":[-63.69872,46.28343],"type":"Point"}
}