{
  "type": "Feature",
  "properties": {
    "gn:admin1_code":"11",
    "gn:asciiname":"Gladmer",
    "gn:country_code":"CA",
    "gn:dem":501,
    "gn:feature_class":"P",
    "gn:feature_code":"PPL",
    "gn:name":"Gladmer",
    "gn:population":0,
    "gn:timezone":"America/Regina",
    "iso:country":"CA",
    "wof:name":"Gladmer",
    "wof:placetype":"locality"
},
  "geometry": {"coordinates":[-106.65895,52.10699],"type":"Point"}
}