{
  "type": "Feature",
  "properties": {
    "gn:admin1_code":"14",
    "gn:asciiname":"Tavani",
    "gn:country_code":"CA",
    "gn:dem":1,
    "gn:feature_class":"P",
    "gn:feature_code":"PPLL",
    "gn:name":"Tavani",
    "gn:population":0,
    "gn:timezone":"America/Rankin_Inlet",
    "iso:country":"CA",
    "wof:name":"Tavani",
    "wof:placetype":"locality"
},
  "geometry": {"coordinates":[-93.10008000000001,62.06728],"type":"Point"}
}