{
  "type": "Feature",
  "properties": {
    "gn:admin1_code":"11.0",
    "gn:asciiname":"Cannington Lake",
    "gn:country_code":"CA",
    "gn:dem":734,
    "gn:feature_class":"P",
    "gn:feature_code":"PPLL",
    "gn:name":"Cannington Lake",
    "gn:population":0,
    "gn:timezone":"America/Regina",
    "iso:country":"CA",
    "name:ceb_x_preferred":[
        "Cannington Lake"
    ],
    "name:swe_x_preferred":[
        "Cannington Lake"
    ],
    "wof:name":"Cannington Lake",
    "wof:placetype":"locality"
},
  "geometry": {"coordinates":[-102.16767,49.78334],"type":"Point"}
}