{
  "type": "Feature",
  "properties": {
    "gn:admin1_code":"11.0",
    "gn:asciiname":"Brabant",
    "gn:country_code":"CA",
    "gn:dem":380,
    "gn:feature_class":"P",
    "gn:feature_code":"PPLL",
    "gn:name":"Brabant",
    "gn:population":0,
    "gn:timezone":"America/Regina",
    "iso:country":"CA",
    "wof:name":"Brabant",
    "wof:placetype":"locality"
},
  "geometry": {"coordinates":[-103.75082999999999,56.11686],"type":"Point"}
}