{
  "type": "Feature",
  "properties": {
    "gn:admin1_code":"11.0",
    "gn:asciiname":"Brabant",
    "gn:country_code":"CA",
    "gn:dem":380,
    "gn:feature_class":"P",
    "gn:feature_code":"PPLL",
    "gn:name":"Brabant",
    "gn:population":0,
    "gn:timezone":"America/Regina",
    "iso:country":"CA",
    "name:arg_x_preferred":[
        "Brabant"
    ],
    "name:bel_x_preferred":[
        "\u0411\u0440\u0430\u0431\u0430\u043d\u0442"
    ],
    "name:bre_x_preferred":[
        "Brabant"
    ],
    "name:cat_x_preferred":[
        "Brabant"
    ],
    "name:ceb_x_preferred":[
        "Brabant"
    ],
    "name:ces_x_preferred":[
        "Brabant"
    ],
    "name:cym_x_preferred":[
        "Brabant"
    ],
    "name:deu_x_preferred":[
        "Brabant"
    ],
    "name:ell_x_preferred":[
        "\u0392\u03c1\u03b1\u03b2\u03ac\u03bd\u03c4\u03b7"
    ],
    "name:eus_x_preferred":[
        "Brabante"
    ],
    "name:fin_x_preferred":[
        "Brabant"
    ],
    "name:fra_x_preferred":[
        "Brabant"
    ],
    "name:glg_x_preferred":[
        "Brabante"
    ],
    "name:hrv_x_preferred":[
        "Brabant"
    ],
    "name:hun_x_preferred":[
        "Brabant"
    ],
    "name:hye_x_preferred":[
        "\u0532\u0580\u0561\u0562\u0561\u0576\u057f"
    ],
    "name:ita_x_preferred":[
        "Brabante"
    ],
    "name:jpn_x_preferred":[
        "\u30d6\u30e9\u30d0\u30f3\u30c8"
    ],
    "name:kor_x_preferred":[
        "\ube0c\ub77c\ubc18\ud2b8"
    ],
    "name:lim_x_preferred":[
        "Braobantj"
    ],
    "name:lit_x_preferred":[
        "Brabantas"
    ],
    "name:ltz_x_preferred":[
        "Brabant"
    ],
    "name:nld_x_preferred":[
        "Brabant"
    ],
    "name:nor_x_preferred":[
        "Brabant"
    ],
    "name:pol_x_preferred":[
        "Brabancja"
    ],
    "name:ron_x_preferred":[
        "Brabant"
    ],
    "name:rus_x_preferred":[
        "\u0411\u0440\u0430\u0431\u0430\u043d\u0442"
    ],
    "name:spa_x_preferred":[
        "Brabante"
    ],
    "name:srp_x_preferred":[
        "\u0411\u0440\u0430\u0431\u0430\u043d\u0442"
    ],
    "name:swe_x_preferred":[
        "Brabant"
    ],
    "name:ukr_x_preferred":[
        "\u0411\u0440\u0430\u0431\u0430\u043d\u0442"
    ],
    "name:uzb_x_preferred":[
        "Brabant"
    ],
    "name:zho_x_preferred":[
        "\u5e03\u62c9\u73ed\u7279"
    ],
    "wof:name":"Brabant",
    "wof:placetype":"locality"
},
  "geometry": {"coordinates":[-103.75082999999999,56.11686],"type":"Point"}
}