{
  "type": "Feature",
  "properties": {
    "gn:country":"CA",
    "gn:fcode":"PPL",
    "gn:population":0,
    "iso:country":"CA",
    "name:eng_x_preferred":[
        "Newmans Cove"
    ],
    "name:eng_x_variant":[
        "Newman's Cove"
    ],
    "name:fra_x_preferred":[
        "Newmans Cove"
    ],
    "qs:name":"Newmans Cove",
    "qs:name_adm0":"Canada",
    "qs:name_adm1":"Newfoundland and Labrador",
    "qs:photos":25,
    "qs:photos_1k":5,
    "qs:photos_9k":1,
    "qs:photos_9r":1,
    "qs:photos_all":25,
    "qs:photos_sr":1,
    "qs:placetype":"Town",
    "qs:pop_sr":"0",
    "wd:wordcount":30,
    "wof:name":"Newmans Cove",
    "wof:placetype":"locality",
    "wof:population":0
},
  "geometry": {"coordinates":[-53.19805,48.58319],"type":"Point"}
}