{
  "type": "Feature",
  "properties": {
    "gn:admin1_code":"7",
    "gn:asciiname":"French Road",
    "gn:country_code":"CA",
    "gn:dem":71,
    "gn:feature_class":"P",
    "gn:feature_code":"PPL",
    "gn:name":"French Road",
    "gn:population":0,
    "gn:timezone":"America/Glace_Bay",
    "iso:country":"CA",
    "name:gla_x_preferred":[
        "Rathad nam Frangach"
    ],
    "wof:name":"French Road",
    "wof:placetype":"locality"
},
  "geometry": {"coordinates":[-60.22612,45.90245],"type":"Point"}
}