{
  "type": "Feature",
  "properties": {
    "gn:admin1_code":"8",
    "gn:asciiname":"Killbear Park",
    "gn:country_code":"CA",
    "gn:dem":178,
    "gn:feature_class":"P",
    "gn:feature_code":"PPL",
    "gn:name":"Killbear Park",
    "gn:population":0,
    "gn:timezone":"America/Toronto",
    "iso:country":"CA",
    "wof:name":"Killbear Park",
    "wof:placetype":"locality"
},
  "geometry": {"coordinates":[-80.24221999999997,45.35583],"type":"Point"}
}