{
  "type": "Feature",
  "properties": {
    "gn:admin1_code":"8",
    "gn:asciiname":"Emery",
    "gn:country_code":"CA",
    "gn:dem":148,
    "gn:feature_class":"P",
    "gn:feature_code":"PPL",
    "gn:name":"Emery",
    "gn:population":0,
    "gn:timezone":"America/Toronto",
    "iso:country":"CA",
    "name:ceb_x_preferred":[
        "Emery"
    ],
    "name:deu_x_preferred":[
        "Emery"
    ],
    "name:fra_x_preferred":[
        "Emery"
    ],
    "name:ita_x_preferred":[
        "Emery"
    ],
    "name:nld_x_preferred":[
        "Emery"
    ],
    "name:pol_x_preferred":[
        "Emery"
    ],
    "name:rus_x_preferred":[
        "Emery"
    ],
    "name:srp_x_preferred":[
        "\u0415\u043c\u0435\u0440\u0438"
    ],
    "name:ukr_x_preferred":[
        "\u0415\u043c\u0435\u0440\u0456"
    ],
    "name:vol_x_preferred":[
        "Emery"
    ],
    "wof:name":"Emery",
    "wof:placetype":"locality"
},
  "geometry": {"coordinates":[-79.54416999999999,43.7525],"type":"Point"}
}