{
  "type": "Feature",
  "properties": {
    "gn:admin1_code":"7.0",
    "gn:asciiname":"Beckwith",
    "gn:country_code":"CA",
    "gn:dem":43,
    "gn:feature_class":"P",
    "gn:feature_code":"PPL",
    "gn:name":"Beckwith",
    "gn:population":0,
    "gn:timezone":"America/Halifax",
    "iso:country":"CA",
    "name:deu_x_preferred":[
        "Beckwith"
    ],
    "name:fra_x_preferred":[
        "Beckwith"
    ],
    "name:rus_x_preferred":[
        "\u0411\u0435\u043a\u0432\u0438\u0442"
    ],
    "wof:name":"Beckwith",
    "wof:placetype":"locality"
},
  "geometry": {"coordinates":[-63.8128,45.83394000000001],"type":"Point"}
}