{
  "type": "Feature",
  "properties": {
    "gn:admin1_code":"1",
    "gn:asciiname":"Lahaieville",
    "gn:country_code":"CA",
    "gn:dem":609,
    "gn:feature_class":"P",
    "gn:feature_code":"PPLL",
    "gn:name":"Lahaieville",
    "gn:population":0,
    "gn:timezone":"America/Edmonton",
    "iso:country":"CA",
    "wof:name":"Lahaieville",
    "wof:placetype":"locality"
},
  "geometry": {"coordinates":[-113.5521,54.80017],"type":"Point"}
}