{
  "type": "Feature",
  "properties": {
    "gn:admin1_code":"10.0",
    "gn:admin2_code":"16.0",
    "gn:admin3_code":"71133.0",
    "gn:asciiname":"Dragon",
    "gn:country_code":"CA",
    "gn:dem":27,
    "gn:feature_class":"P",
    "gn:feature_code":"PPL",
    "gn:name":"Dragon",
    "gn:population":0,
    "gn:timezone":"America/Toronto",
    "iso:country":"CA",
    "wof:name":"Dragon",
    "wof:placetype":"locality"
},
  "geometry": {"coordinates":[-74.25684,45.47977],"type":"Point"}
}