{
  "type": "Feature",
  "properties": {
    "gn:admin1_code":"10",
    "gn:admin2_code":"5.0",
    "gn:admin3_code":"44050.0",
    "gn:asciiname":"Fairfax",
    "gn:country_code":"CA",
    "gn:dem":336,
    "gn:feature_class":"P",
    "gn:feature_code":"PPL",
    "gn:name":"Fairfax",
    "gn:population":0,
    "gn:timezone":"America/Toronto",
    "iso:country":"CA",
    "wof:name":"Fairfax",
    "wof:placetype":"locality"
},
  "geometry": {"coordinates":[-72.02231999999999,45.08893],"type":"Point"}
}