{
  "type": "Feature",
  "properties": {
    "gn:admin1_code":"4",
    "gn:admin2_code":"1306.0",
    "gn:asciiname":"Weldon",
    "gn:country_code":"CA",
    "gn:dem":8,
    "gn:feature_class":"P",
    "gn:feature_code":"PPL",
    "gn:name":"Weldon",
    "gn:population":0,
    "gn:timezone":"America/Moncton",
    "iso:country":"CA",
    "wof:name":"Weldon",
    "wof:placetype":"locality"
},
  "geometry": {"coordinates":[-64.67350999999999,45.947],"type":"Point"}
}