{
  "type": "Feature",
  "properties": {
    "iso:country":"CA",
    "name:eng_x_preferred":[
        "Terrace Hill"
    ],
    "qs:gn_adm0_cc":"CA",
    "qs:gn_local":5907990,
    "qs:gn_nam_loc":"brantford",
    "qs:gn_namadm1":"08",
    "qs:local_max":1489,
    "qs:local_sum":3298,
    "qs:localhoods":11,
    "qs:name":"Terrace Hill",
    "qs:name_adm0":"Canada",
    "qs:name_adm1":"Ontario",
    "qs:name_adm2":"Brant",
    "qs:name_local":"Brantford",
    "qs:photo_max":86,
    "qs:photo_sum":294,
    "qs:placetype":"Suburb",
    "qs:quad_count":19,
    "qs:woe_adm0":23424775,
    "qs:woe_adm1":2344922,
    "qs:woe_adm2":29375169,
    "qs:woe_lau":0,
    "qs:woe_local":4059,
    "qs:woe_ver":"7.10.0",
    "wd:wordcount":1231,
    "wof:lang":[
        "eng"
    ],
    "wof:name":"Terrace Hill",
    "wof:placetype":"neighbourhood"
},
  "geometry": {"coordinates":[-80.26612799999999,43.158447],"type":"Point"}
}