{
  "type": "Feature",
  "properties": {
    "gn:admin1_code":"2",
    "gn:asciiname":"Maple Bay",
    "gn:country_code":"CA",
    "gn:dem":70,
    "gn:feature_class":"P",
    "gn:feature_code":"PPL",
    "gn:name":"Maple Bay",
    "gn:population":0,
    "gn:timezone":"America/Vancouver",
    "iso:country":"CA",
    "name:ceb_x_preferred":[
        "Maple Bay"
    ],
    "name:eng_x_preferred":[
        "Maple Bay"
    ],
    "name:ita_x_preferred":[
        "Maple Bay"
    ],
    "name:swe_x_preferred":[
        "Maple Bay"
    ],
    "wof:name":"Maple Bay",
    "wof:placetype":"locality"
},
  "geometry": {"coordinates":[-123.61936,48.81633],"type":"Point"}
}