{
  "type": "Feature",
  "properties": {
    "gn:gn_country":"CA",
    "gn:gn_fcode":"PPL",
    "gn:gn_pop":0,
    "iso:country":"CA",
    "name:bre_x_preferred":[
        "Saint-Bernard-de-Michaudville"
    ],
    "name:ceb_x_preferred":[
        "Saint-Bernard-de-Michaudville"
    ],
    "name:cos_x_preferred":[
        "Saint-Bernard-de-Michaudville"
    ],
    "name:dan_x_preferred":[
        "Saint-Bernard-de-Michaudville"
    ],
    "name:deu_x_preferred":[
        "Saint-Bernard-de-Michaudville"
    ],
    "name:eng_x_preferred":[
        "Saint-Bernard-de-Michaudville"
    ],
    "name:eus_x_preferred":[
        "Saint-Bernard-de-Michaudville"
    ],
    "name:fas_x_preferred":[
        "\u0633\u0646-\u0628\u0631\u0646\u0627\u0631-\u062f\u0648-\u0645\u06cc\u0634\u0648\u062f\u0648\u06cc\u0644\u060c \u06a9\u0628\u06a9"
    ],
    "name:fas_x_variant":[
        "\u0633\u0646-\u0628\u0631\u0646\u0627\u0631-\u062f\u0648-\u0645\u06cc\u0634\u0648\u062f\u0648\u06cc\u0644"
    ],
    "name:fra_x_preferred":[
        "Saint-Bernard-de-Michaudville"
    ],
    "name:ind_x_preferred":[
        "Saint-Bernard-de-Michaudville"
    ],
    "name:ita_x_preferred":[
        "Saint-Bernard-de-Michaudville"
    ],
    "name:nds_x_preferred":[
        "Saint-Bernard-de-Michaudville"
    ],
    "name:nld_x_preferred":[
        "Saint-Bernard-de-Michaudville"
    ],
    "name:por_x_preferred":[
        "Saint-Bernard-de-Michaudville"
    ],
    "name:ron_x_preferred":[
        "Saint-Bernard-de-Michaudville"
    ],
    "name:spa_x_preferred":[
        "Saint-Bernard-de-Michaudville"
    ],
    "name:swe_x_preferred":[
        "Saint-Bernard-de-Michaudville"
    ],
    "name:tah_x_preferred":[
        "Saint-Bernard-de-Michaudville"
    ],
    "name:urd_x_preferred":[
        "\u0633\u06cc\u0646\u0679-\u0628\u0631\u0646\u0627\u0631\u0688-\u062f\u06d2-\u0645\u0686\u0648\u062f\u0648\u0644\u06d2\u060c \u06a9\u06cc\u0648\u0628\u06a9"
    ],
    "name:urd_x_variant":[
        "\u0633\u06cc\u0646\u0679-\u0628\u0631\u0646\u0627\u0631\u0688-\u062f\u06d2-\u0645\u0686\u0648\u062f\u0648\u0644\u06d2"
    ],
    "qs_pg:aaroncc":"CA",
    "qs_pg:gn_country":"CA",
    "qs_pg:gn_fcode":"PPL",
    "qs_pg:gn_pop":0,
    "qs_pg:name":"St.-Bernard-de-Michaudville",
    "qs_pg:name_adm0":"Canada",
    "qs_pg:name_adm1":"Qu\u00e9bec",
    "qs_pg:photos":7,
    "qs_pg:photos_1k":1,
    "qs_pg:photos_9k":1,
    "qs_pg:photos_9r":1,
    "qs_pg:photos_all":7,
    "qs_pg:photos_sr":1,
    "qs_pg:pop_sr":0,
    "qs_pg:qs_pg_placetype":"locality",
    "qs_pg:qs_pg_placetype_gp":"Town",
    "qs_pg:woe_adm0":23424775,
    "woe:adm0_id":23424775,
    "woe:name_adm0":"Canada",
    "woe:name_adm1":"Qu\u00e9bec",
    "woe:placetype":"Town",
    "wof:name":"St.-Bernard-de-Michaudville",
    "wof:placetype":"locality"
},
  "geometry": {"coordinates":[-73.06583999999999,45.83337],"type":"Point"}
}