{
  "type": "Feature",
  "properties": {
    "gn:country":"CA",
    "iso:country":"CA",
    "name:dut_x_preferred":[
        "Port Medway"
    ],
    "name:eng_x_preferred":[
        "Port Medway"
    ],
    "name:fre_x_preferred":[
        "Port Medway"
    ],
    "name:gla_x_preferred":[
        "Port Medway"
    ],
    "qs:name":"Port Medway",
    "qs:name_adm0":"Canada",
    "qs:name_adm1":"Nova Scotia",
    "qs:photos":280,
    "qs:photos_1k":57,
    "qs:photos_9k":1,
    "qs:photos_9r":4,
    "qs:photos_all":280,
    "qs:photos_sr":5,
    "qs:placetype":"Town",
    "qs:pop_sr":"0",
    "wd:wordcount":48,
    "wof:name":"Port Medway",
    "wof:placetype":"locality"
},
  "geometry": {"coordinates":[-64.54138349999999,44.131679],"type":"Point"}
}