{
  "type": "Feature",
  "properties": {
    "gn:admin1_code":"10",
    "gn:admin2_code":"15.0",
    "gn:admin3_code":"77012.0",
    "gn:asciiname":"Lac-Charlebois",
    "gn:country_code":"CA",
    "gn:dem":380,
    "gn:feature_class":"P",
    "gn:feature_code":"PPL",
    "gn:name":"Lac-Charlebois",
    "gn:population":0,
    "gn:timezone":"America/Toronto",
    "iso:country":"CA",
    "wof:name":"Lac-Charlebois",
    "wof:placetype":"locality"
},
  "geometry": {"coordinates":[-74.04404,46.08171],"type":"Point"}
}