{
  "type": "Feature",
  "properties": {
    "gn:admin1_code":"3",
    "gn:asciiname":"Glenlochar",
    "gn:country_code":"CA",
    "gn:dem":446,
    "gn:feature_class":"P",
    "gn:feature_code":"PPLL",
    "gn:name":"Glenlochar",
    "gn:population":0,
    "gn:timezone":"America/Winnipeg",
    "iso:country":"CA",
    "name:bre_x_preferred":[
        "Glenlochar"
    ],
    "name:deu_x_preferred":[
        "Glenlochar"
    ],
    "name:eus_x_preferred":[
        "Glenlochar"
    ],
    "name:gla_x_preferred":[
        "Gleann Lochair"
    ],
    "name:gle_x_preferred":[
        "Gleann Lochair"
    ],
    "wof:name":"Glenlochar",
    "wof:placetype":"locality"
},
  "geometry": {"coordinates":[-100.97032,50.10891],"type":"Point"}
}