{
  "type": "Feature",
  "properties": {
    "gn:admin1_code":"3",
    "gn:asciiname":"Pikwitonei",
    "gn:country_code":"CA",
    "gn:dem":189,
    "gn:feature_class":"P",
    "gn:feature_code":"PPL",
    "gn:name":"Pikwitonei",
    "gn:population":0,
    "gn:timezone":"America/Winnipeg",
    "iso:country":"CA",
    "wof:name":"Pikwitonei",
    "wof:placetype":"locality"
},
  "geometry": {"coordinates":[-97.15604,55.588],"type":"Point"}
}