{
  "type": "Feature",
  "properties": {
    "iso:country":"CA",
    "name:eng_x_preferred":[
        "Lakeview"
    ],
    "qs:name":"Lakeview",
    "qs:name_adm0":"Canada",
    "qs:name_adm1":"Nova Scotia",
    "qs:photos":235,
    "qs:photos_1k":48,
    "qs:photos_9k":1,
    "qs:photos_9r":4,
    "qs:photos_all":235,
    "qs:photos_sr":4,
    "qs:placetype":"Town",
    "qs:pop_sr":"0",
    "wd:wordcount":266,
    "wof:name":"Lakeview",
    "wof:placetype":"locality"
},
  "geometry": {"coordinates":[-63.63705,44.767211],"type":"Point"}
}