{
  "type": "Feature",
  "properties": {
    "gn:admin1_code":"7",
    "gn:asciiname":"Salt Springs",
    "gn:country_code":"CA",
    "gn:dem":70,
    "gn:feature_class":"P",
    "gn:feature_code":"PPL",
    "gn:name":"Salt Springs",
    "gn:population":0,
    "gn:timezone":"America/Halifax",
    "iso:country":"CA",
    "wof:name":"Salt Springs",
    "wof:placetype":"locality"
},
  "geometry": {"coordinates":[-64.01715,45.66955],"type":"Point"}
}