{
  "type": "Feature",
  "properties": {
    "gn:admin1_code":"8.0",
    "gn:asciiname":"Apple Hill",
    "gn:country_code":"CA",
    "gn:dem":86,
    "gn:feature_class":"P",
    "gn:feature_code":"PPLL",
    "gn:name":"Apple Hill",
    "gn:population":0,
    "gn:timezone":"America/Toronto",
    "iso:country":"CA",
    "wof:name":"Apple Hill",
    "wof:placetype":"locality"
},
  "geometry": {"coordinates":[-74.76598,45.21679],"type":"Point"}
}