{
  "type": "Feature",
  "properties": {
    "gn:admin1_code":"11",
    "gn:asciiname":"Moose Range",
    "gn:country_code":"CA",
    "gn:dem":753,
    "gn:feature_class":"P",
    "gn:feature_code":"PPLL",
    "gn:name":"Moose Range",
    "gn:population":0,
    "gn:timezone":"America/Regina",
    "iso:country":"CA",
    "wof:name":"Moose Range",
    "wof:placetype":"locality"
},
  "geometry": {"coordinates":[-107.71795,53.20013],"type":"Point"}
}