{
  "type": "Feature",
  "properties": {
    "gn:admin1_code":"8.0",
    "gn:asciiname":"Yearley",
    "gn:country_code":"CA",
    "gn:dem":327,
    "gn:feature_class":"P",
    "gn:feature_code":"PPL",
    "gn:name":"Yearley",
    "gn:population":0,
    "gn:timezone":"America/Toronto",
    "iso:country":"CA",
    "wof:name":"Yearley",
    "wof:placetype":"locality"
},
  "geometry": {"coordinates":[-79.446,45.37621],"type":"Point"}
}