{
  "type": "Feature",
  "properties": {
    "gn:admin1_code":"11.0",
    "gn:asciiname":"Cutbank",
    "gn:country_code":"CA",
    "gn:dem":567,
    "gn:feature_class":"P",
    "gn:feature_code":"PPL",
    "gn:name":"Cutbank",
    "gn:population":0,
    "gn:timezone":"America/Regina",
    "iso:country":"CA",
    "wof:name":"Cutbank",
    "wof:placetype":"locality"
},
  "geometry": {"coordinates":[-106.85063,51.30004],"type":"Point"}
}