{
  "type": "Feature",
  "properties": {
    "gn:admin1_code":"7",
    "gn:asciiname":"Stewiacke East",
    "gn:country_code":"CA",
    "gn:dem":23,
    "gn:feature_class":"P",
    "gn:feature_code":"PPL",
    "gn:name":"Stewiacke East",
    "gn:population":0,
    "gn:timezone":"America/Halifax",
    "iso:country":"CA",
    "wof:name":"Stewiacke East",
    "wof:placetype":"locality"
},
  "geometry": {"coordinates":[-63.29787,45.14442],"type":"Point"}
}