{
  "type": "Feature",
  "properties": {
    "gn:admin1_code":"11.0",
    "gn:asciiname":"Dummer",
    "gn:country_code":"CA",
    "gn:dem":637,
    "gn:feature_class":"P",
    "gn:feature_code":"PPL",
    "gn:name":"Dummer",
    "gn:population":0,
    "gn:timezone":"America/Regina",
    "iso:country":"CA",
    "wof:name":"Dummer",
    "wof:placetype":"locality"
},
  "geometry": {"coordinates":[-104.83750000000001,49.84365],"type":"Point"}
}