{
  "type": "Feature",
  "properties": {
    "iso:country":"CA",
    "name:dut_x_preferred":[
        "Fort Assiniboine"
    ],
    "name:eng_x_preferred":[
        "Fort Assiniboine"
    ],
    "name:epo_x_preferred":[
        "Fuorto Assiniboine"
    ],
    "name:fre_x_preferred":[
        "Fort Assiniboine"
    ],
    "name:por_x_preferred":[
        "Fort Assiniboine"
    ],
    "qs:name":"Fort Assiniboine",
    "qs:name_adm0":"Canada",
    "qs:name_adm1":"Alberta",
    "qs:photos":19,
    "qs:photos_1k":4,
    "qs:photos_9k":1,
    "qs:photos_9r":1,
    "qs:photos_all":19,
    "qs:photos_sr":1,
    "qs:placetype":"Town",
    "qs:pop_sr":"0",
    "wd:wordcount":739,
    "wof:name":"Fort Assiniboine",
    "wof:placetype":"locality"
},
  "geometry": {"coordinates":[-114.773139,54.333594],"type":"Point"}
}