{
  "type": "Feature",
  "properties": {
    "iso:country":"CA",
    "name:eng_x_preferred":[
        "Parc Laurier"
    ],
    "name:fra_x_preferred":[
        "Parc Laurier"
    ],
    "qs:gn_adm0_cc":"CA",
    "qs:gn_local":5914826,
    "qs:gn_nam_loc":"candiac",
    "qs:gn_namadm1":"10",
    "qs:local_max":17,
    "qs:local_sum":17,
    "qs:localhoods":1,
    "qs:name":"Parc Laurier",
    "qs:name_adm0":"Canada",
    "qs:name_adm1":"Qu\u00e9bec",
    "qs:name_adm2":"Roussillon",
    "qs:name_local":"Candiac",
    "qs:photo_max":6,
    "qs:photo_sum":17,
    "qs:placetype":"Suburb",
    "qs:quad_count":6,
    "qs:woe_adm0":23424775,
    "qs:woe_adm1":2344924,
    "qs:woe_adm2":29375054,
    "qs:woe_lau":0,
    "qs:woe_local":207,
    "qs:woe_ver":"7.10.0",
    "wof:lang":[
        "fre"
    ],
    "wof:name":"Parc Laurier",
    "wof:placetype":"neighbourhood"
},
  "geometry": {"coordinates":[-73.50402800000001,45.380231],"type":"Point"}
}