{
  "type": "Feature",
  "properties": {
    "gn:admin1_code":"8.0",
    "gn:asciiname":"Baelstadt",
    "gn:country_code":"CA",
    "gn:dem":153,
    "gn:feature_class":"P",
    "gn:feature_code":"PPLL",
    "gn:name":"Baelstadt",
    "gn:population":0,
    "gn:timezone":"America/Toronto",
    "iso:country":"CA",
    "wof:name":"Baelstadt",
    "wof:placetype":"locality"
},
  "geometry": {"coordinates":[-77.34947,45.91682],"type":"Point"}
}