{
  "type": "Feature",
  "properties": {
    "gn:admin1_code":"10",
    "gn:admin2_code":"15",
    "gn:admin3_code":"75005.0",
    "gn:asciiname":"Saint-Colomban",
    "gn:country_code":"CA",
    "gn:dem":149,
    "gn:feature_class":"P",
    "gn:feature_code":"PPLA3",
    "gn:name":"Saint-Colomban",
    "gn:population":0,
    "gn:timezone":"America/Toronto",
    "iso:country":"CA",
    "name:ara_x_preferred":[
        "\u0633\u0627\u0646 \u0643\u0648\u0644\u0648\u0645\u0628\u0627\u0646"
    ],
    "name:atj_x_preferred":[
        "Saint-Colomban"
    ],
    "name:ceb_x_preferred":[
        "Saint-Colomban"
    ],
    "name:eus_x_preferred":[
        "Saint-Colomban"
    ],
    "name:fas_x_preferred":[
        "\u0633\u0646-\u06a9\u0648\u0644\u0648\u0645\u0628\u0627\u0646"
    ],
    "name:fra_x_preferred":[
        "Saint-Colomban"
    ],
    "name:ita_x_preferred":[
        "Saint-Colomban"
    ],
    "name:por_x_preferred":[
        "Saint-Colomban"
    ],
    "name:spa_x_preferred":[
        "Saint-Colomban"
    ],
    "name:srp_x_preferred":[
        "\u0421\u0435\u043d \u041a\u043e\u043b\u043e\u043c\u0431\u0430\u043d"
    ],
    "name:swe_x_preferred":[
        "Saint-Colomban"
    ],
    "name:tur_x_preferred":[
        "Saint-Colomban"
    ],
    "name:urd_x_preferred":[
        "\u0633\u06cc\u0646\u0679-\u06a9\u0648\u0644\u0648\u0645\u0628\u0627\u0646"
    ],
    "wof:name":"Saint-Colomban",
    "wof:placetype":"locality"
},
  "geometry": {"coordinates":[-74.13251,45.73338],"type":"Point"}
}