{
  "type": "Feature",
  "properties": {
    "gn:admin1_code":"10",
    "gn:admin2_code":"15",
    "gn:admin3_code":"75005.0",
    "gn:asciiname":"Saint-Colomban",
    "gn:country_code":"CA",
    "gn:dem":149,
    "gn:feature_class":"P",
    "gn:feature_code":"PPLA3",
    "gn:name":"Saint-Colomban",
    "gn:population":0,
    "gn:timezone":"America/Toronto",
    "iso:country":"CA",
    "wof:name":"Saint-Colomban",
    "wof:placetype":"locality"
},
  "geometry": {"coordinates":[-74.13251,45.73338],"type":"Point"}
}