{
  "type": "Feature",
  "properties": {
    "gn:admin1_code":"8",
    "gn:asciiname":"Vasey",
    "gn:country_code":"CA",
    "gn:dem":299,
    "gn:feature_class":"P",
    "gn:feature_code":"PPL",
    "gn:name":"Vasey",
    "gn:population":0,
    "gn:timezone":"America/Toronto",
    "iso:country":"CA",
    "wof:name":"Vasey",
    "wof:placetype":"locality"
},
  "geometry": {"coordinates":[-79.75721999999998,44.67],"type":"Point"}
}