{
  "type": "Feature",
  "properties": {
    "gn:admin1_code":"8.0",
    "gn:asciiname":"Callum",
    "gn:country_code":"CA",
    "gn:dem":253,
    "gn:feature_class":"P",
    "gn:feature_code":"PPL",
    "gn:name":"Callum",
    "gn:population":0,
    "gn:timezone":"America/Toronto",
    "iso:country":"CA",
    "wof:name":"Callum",
    "wof:placetype":"locality"
},
  "geometry": {"coordinates":[-80.62755,46.51545],"type":"Point"}
}