{
  "type": "Feature",
  "properties": {
    "gn:admin1_code":"8",
    "gn:asciiname":"Stanley",
    "gn:country_code":"CA",
    "gn:dem":231,
    "gn:feature_class":"P",
    "gn:feature_code":"PPL",
    "gn:name":"Stanley",
    "gn:population":0,
    "gn:timezone":"America/Toronto",
    "iso:country":"CA",
    "wof:name":"Stanley",
    "wof:placetype":"locality"
},
  "geometry": {"coordinates":[-89.56999999999999,48.36889],"type":"Point"}
}