{
  "type": "Feature",
  "properties": {
    "gn:admin1_code":"8",
    "gn:asciiname":"Stanley",
    "gn:country_code":"CA",
    "gn:dem":231,
    "gn:feature_class":"P",
    "gn:feature_code":"PPL",
    "gn:name":"Stanley",
    "gn:population":0,
    "gn:timezone":"America/Toronto",
    "iso:country":"CA",
    "name:bel_x_preferred":[
        "\u0421\u0442\u044d\u043d\u043b\u0456"
    ],
    "name:bul_x_preferred":[
        "\u0421\u0442\u0435\u043d\u043b\u0438"
    ],
    "name:ceb_x_preferred":[
        "Stanley"
    ],
    "name:ces_x_preferred":[
        "Stanley"
    ],
    "name:cym_x_preferred":[
        "Stanley"
    ],
    "name:deu_x_preferred":[
        "Stanley"
    ],
    "name:est_x_preferred":[
        "Stanley"
    ],
    "name:eus_x_preferred":[
        "Stanley"
    ],
    "name:fas_x_preferred":[
        "\u0627\u0633\u062a\u0646\u0644\u06cc"
    ],
    "name:fin_x_preferred":[
        "Stanley"
    ],
    "name:fra_x_preferred":[
        "Stanley"
    ],
    "name:heb_x_preferred":[
        "\u05e1\u05d8\u05e0\u05dc\u05d9"
    ],
    "name:hrv_x_preferred":[
        "Stanley"
    ],
    "name:hun_x_preferred":[
        "Stanley"
    ],
    "name:isl_x_preferred":[
        "Stanley"
    ],
    "name:ita_x_preferred":[
        "Stanley"
    ],
    "name:jpn_x_preferred":[
        "\u30b9\u30bf\u30f3\u30ea\u30fc"
    ],
    "name:kat_x_preferred":[
        "\u10e1\u10e2\u10d4\u10dc\u10da\u10d8"
    ],
    "name:kor_x_preferred":[
        "\uc2a4\ud0e0\ub9ac"
    ],
    "name:lav_x_preferred":[
        "Stenlijs"
    ],
    "name:lin_x_preferred":[
        "Stanley"
    ],
    "name:nld_x_preferred":[
        "Stanley"
    ],
    "name:pol_x_preferred":[
        "Stanley"
    ],
    "name:por_x_preferred":[
        "Stanley"
    ],
    "name:ron_x_preferred":[
        "Stanley"
    ],
    "name:rus_x_preferred":[
        "\u0421\u0442\u044d\u043d\u043b\u0438"
    ],
    "name:slk_x_preferred":[
        "Stanley"
    ],
    "name:slv_x_preferred":[
        "Stanley"
    ],
    "name:spa_x_preferred":[
        "Stanley"
    ],
    "name:srp_x_preferred":[
        "\u0421\u0442\u0435\u043d\u043b\u0438"
    ],
    "name:swe_x_preferred":[
        "Stanley"
    ],
    "name:tam_x_preferred":[
        "\u0bb8\u0bcd\u0b9f\u0bbe\u0ba9\u0bcd\u0bb2\u0bbf"
    ],
    "name:ukr_x_preferred":[
        "\u0421\u0442\u0435\u043d\u043b\u0456"
    ],
    "name:vol_x_preferred":[
        "Stanley"
    ],
    "name:war_x_preferred":[
        "Stanley"
    ],
    "name:zho_x_preferred":[
        "\u53f2\u4e39\u5229"
    ],
    "wof:name":"Stanley",
    "wof:placetype":"locality"
},
  "geometry": {"coordinates":[-89.56999999999999,48.36889],"type":"Point"}
}