{
  "type": "Feature",
  "properties": {
    "gn:admin1_code":"1",
    "gn:asciiname":"Michichi",
    "gn:country_code":"CA",
    "gn:dem":837,
    "gn:feature_class":"P",
    "gn:feature_code":"PPL",
    "gn:name":"Michichi",
    "gn:population":0,
    "gn:timezone":"America/Edmonton",
    "iso:country":"CA",
    "name:fra_x_preferred":[
        "Michichi"
    ],
    "wof:name":"Michichi",
    "wof:placetype":"locality"
},
  "geometry": {"coordinates":[-112.53515,51.58343],"type":"Point"}
}