{
  "type": "Feature",
  "properties": {
    "gn:admin1_code":"8",
    "gn:asciiname":"Ottawa West",
    "gn:country_code":"CA",
    "gn:dem":50,
    "gn:feature_class":"P",
    "gn:feature_code":"PPL",
    "gn:name":"Ottawa West",
    "gn:population":0,
    "gn:timezone":"America/Toronto",
    "iso:country":"CA",
    "name:fra_x_preferred":[
        "Ottawa-Ouest"
    ],
    "wof:name":"Ottawa West",
    "wof:placetype":"locality"
},
  "geometry": {"coordinates":[-75.75,45.41667],"type":"Point"}
}