{
  "type": "Feature",
  "properties": {
    "gn:admin1_code":"3",
    "gn:asciiname":"Overstoneville",
    "gn:country_code":"CA",
    "gn:dem":280,
    "gn:feature_class":"P",
    "gn:feature_code":"PPLL",
    "gn:name":"Overstoneville",
    "gn:population":0,
    "gn:timezone":"America/Winnipeg",
    "iso:country":"CA",
    "wof:name":"Overstoneville",
    "wof:placetype":"locality"
},
  "geometry": {"coordinates":[-96.88234,49.07497],"type":"Point"}
}