{
  "type": "Feature",
  "properties": {
    "gn:admin1_code":"7",
    "gn:asciiname":"Ship Harbour",
    "gn:country_code":"CA",
    "gn:dem":15,
    "gn:feature_class":"P",
    "gn:feature_code":"PPL",
    "gn:name":"Ship Harbour",
    "gn:population":0,
    "gn:timezone":"America/Halifax",
    "iso:country":"CA",
    "wof:name":"Ship Harbour",
    "wof:placetype":"locality"
},
  "geometry": {"coordinates":[-62.88257,44.80784],"type":"Point"}
}