{
  "type": "Feature",
  "properties": {
    "gn:admin1_code":"7",
    "gn:asciiname":"Thornhill",
    "gn:country_code":"CA",
    "gn:dem":60,
    "gn:feature_class":"P",
    "gn:feature_code":"PPL",
    "gn:name":"Thornhill",
    "gn:population":0,
    "gn:timezone":"America/Halifax",
    "iso:country":"CA",
    "name:ceb_x_preferred":[
        "Thornhill"
    ],
    "name:cym_x_preferred":[
        "Thornhill"
    ],
    "name:deu_x_preferred":[
        "Thornhill"
    ],
    "name:fra_x_preferred":[
        "Thornhill"
    ],
    "name:ita_x_preferred":[
        "Thornhill"
    ],
    "name:nld_x_preferred":[
        "Thornhill"
    ],
    "name:pol_x_preferred":[
        "Thornhill"
    ],
    "name:por_x_preferred":[
        "Thornhill"
    ],
    "name:rus_x_preferred":[
        "\u0422\u043e\u0440\u043d\u0445\u0438\u043b\u043b"
    ],
    "name:swe_x_preferred":[
        "Thornhill"
    ],
    "name:ukr_x_preferred":[
        "\u0422\u043e\u0440\u043d\u0445\u0456\u043b\u043b"
    ],
    "wof:name":"Thornhill",
    "wof:placetype":"locality"
},
  "geometry": {"coordinates":[-63.61147,44.60347],"type":"Point"}
}