{
  "type": "Feature",
  "properties": {
    "gn:admin1_code":"10.0",
    "gn:asciiname":"Weymont",
    "gn:country_code":"CA",
    "gn:dem":364,
    "gn:feature_class":"P",
    "gn:feature_code":"PPL",
    "gn:name":"Weymont",
    "gn:population":0,
    "gn:timezone":"America/Toronto",
    "iso:country":"CA",
    "wof:name":"Weymont",
    "wof:placetype":"locality"
},
  "geometry": {"coordinates":[-73.74913000000002,47.90011],"type":"Point"}
}