{
  "type": "Feature",
  "properties": {
    "gn:admin1_code":"8.0",
    "gn:asciiname":"Carthage",
    "gn:country_code":"CA",
    "gn:dem":395,
    "gn:feature_class":"P",
    "gn:feature_code":"PPL",
    "gn:name":"Carthage",
    "gn:population":0,
    "gn:timezone":"America/Toronto",
    "iso:country":"CA",
    "wof:name":"Carthage",
    "wof:placetype":"locality"
},
  "geometry": {"coordinates":[-80.84999999999999,43.66139],"type":"Point"}
}