{
  "type": "Feature",
  "properties": {
    "gn:country":"CA",
    "iso:country":"CA",
    "name:ceb_x_preferred":[
        "East Point"
    ],
    "name:eng_x_preferred":[
        "East Point"
    ],
    "name:fra_x_preferred":[
        "East Point"
    ],
    "name:jpn_x_preferred":[
        "\u30a4\u30fc\u30b9\u30c8\u30dd\u30a4\u30f3\u30c8"
    ],
    "name:nld_x_preferred":[
        "East Point"
    ],
    "qs:name":"East Point",
    "qs:name_adm0":"Canada",
    "qs:name_adm1":"Prince Edward Island",
    "qs:photos":274,
    "qs:photos_1k":56,
    "qs:photos_9k":1,
    "qs:photos_9r":4,
    "qs:photos_all":274,
    "qs:photos_sr":5,
    "qs:placetype":"Town",
    "qs:pop_sr":"0",
    "wd:wordcount":114,
    "wof:name":"East Point",
    "wof:placetype":"locality"
},
  "geometry": {"coordinates":[-61.971902,46.453292],"type":"Point"}
}