{
  "type": "Feature",
  "properties": {
    "gn:country":"CA",
    "gn:fcode":"PPL",
    "gn:population":0,
    "iso:country":"CA",
    "name:eng_x_preferred":[
        "Wentworth Centre"
    ],
    "name:nld_x_preferred":[
        "Wentworth Centre"
    ],
    "qs:name":"Wentworth Centre",
    "qs:name_adm0":"Canada",
    "qs:name_adm1":"Nova Scotia",
    "qs:photos":16,
    "qs:photos_1k":3,
    "qs:photos_9k":1,
    "qs:photos_9r":1,
    "qs:photos_all":16,
    "qs:photos_sr":1,
    "qs:placetype":"Town",
    "qs:pop_sr":"0",
    "wd:wordcount":45,
    "wof:name":"Wentworth Centre",
    "wof:placetype":"locality",
    "wof:population":0
},
  "geometry": {"coordinates":[-63.5487,45.66685],"type":"Point"}
}