{
  "type": "Feature",
  "properties": {
    "gn:admin1_code":"8",
    "gn:admin2_code":"3560.0",
    "gn:asciiname":"Minaki",
    "gn:country_code":"CA",
    "gn:dem":321,
    "gn:feature_class":"P",
    "gn:feature_code":"PPL",
    "gn:name":"Minaki",
    "gn:population":0,
    "gn:timezone":"America/Winnipeg",
    "iso:country":"CA",
    "name:eng_x_preferred":[
        "Minaki"
    ],
    "wof:name":"Minaki",
    "wof:placetype":"locality"
},
  "geometry": {"coordinates":[-94.67064999999999,49.98194],"type":"Point"}
}