{
  "type": "Feature",
  "properties": {
    "gn:admin1_code":"10",
    "gn:admin2_code":"16",
    "gn:admin3_code":"48015.0",
    "gn:asciiname":"Quartier-Auger",
    "gn:country_code":"CA",
    "gn:dem":117,
    "gn:feature_class":"P",
    "gn:feature_code":"PPL",
    "gn:name":"Quartier-Auger",
    "gn:population":0,
    "gn:timezone":"America/Toronto",
    "iso:country":"CA",
    "wof:name":"Quartier-Auger",
    "wof:placetype":"locality"
},
  "geometry": {"coordinates":[-72.52011,45.56198],"type":"Point"}
}