{
  "type": "Feature",
  "properties": {
    "gn:admin1_code":"2.0",
    "gn:asciiname":"Buckinghorse River",
    "gn:country_code":"CA",
    "gn:dem":1009,
    "gn:feature_class":"P",
    "gn:feature_code":"PPL",
    "gn:name":"Buckinghorse River",
    "gn:population":0,
    "gn:timezone":"America/Vancouver",
    "iso:country":"CA",
    "name:ceb_x_preferred":[
        "Buckinghorse River"
    ],
    "name:swe_x_preferred":[
        "Buckinghorse River"
    ],
    "wof:name":"Buckinghorse River",
    "wof:placetype":"locality"
},
  "geometry": {"coordinates":[-122.84999999999999,57.38333000000001],"type":"Point"}
}