{
  "type": "Feature",
  "properties": {
    "gn:admin1_code":"11.0",
    "gn:asciiname":"Wroxton",
    "gn:country_code":"CA",
    "gn:dem":531,
    "gn:feature_class":"P",
    "gn:feature_code":"PPLL",
    "gn:name":"Wroxton",
    "gn:population":0,
    "gn:timezone":"America/Regina",
    "iso:country":"CA",
    "wof:name":"Wroxton",
    "wof:placetype":"locality"
},
  "geometry": {"coordinates":[-101.88423,51.23329],"type":"Point"}
}