{
  "type": "Feature",
  "properties": {
    "gn:admin1_code":"10",
    "gn:admin2_code":"5.0",
    "gn:admin3_code":"43027.0",
    "gn:asciiname":"Moulton Hill",
    "gn:country_code":"CA",
    "gn:dem":195,
    "gn:feature_class":"P",
    "gn:feature_code":"PPL",
    "gn:name":"Moulton Hill",
    "gn:population":0,
    "gn:timezone":"America/Toronto",
    "iso:country":"CA",
    "wof:name":"Moulton Hill",
    "wof:placetype":"locality"
},
  "geometry": {"coordinates":[-71.84732,45.38226],"type":"Point"}
}