{
  "type": "Feature",
  "properties": {
    "gn:admin1_code":"7",
    "gn:asciiname":"Mossman Corner",
    "gn:country_code":"CA",
    "gn:dem":49,
    "gn:feature_class":"P",
    "gn:feature_code":"PPLL",
    "gn:name":"Mossman Corner",
    "gn:population":0,
    "gn:timezone":"America/Halifax",
    "iso:country":"CA",
    "wof:name":"Mossman Corner",
    "wof:placetype":"locality"
},
  "geometry": {"coordinates":[-64.58207,44.43345],"type":"Point"}
}