{
  "type": "Feature",
  "properties": {
    "gn:country":"CA",
    "gn:fcode":"PPL",
    "gn:pop":3732,
    "gn:population":3732,
    "iso:country":"CA",
    "name:ceb_x_preferred":[
        "Pictou"
    ],
    "name:ces_x_preferred":[
        "Pictou"
    ],
    "name:deu_x_preferred":[
        "Pictou"
    ],
    "name:eng_x_preferred":[
        "Pictou"
    ],
    "name:fas_x_preferred":[
        "\u067e\u06cc\u06a9\u062a\u0648"
    ],
    "name:fra_x_preferred":[
        "Pictou"
    ],
    "name:gla_x_preferred":[
        "Piogto"
    ],
    "name:gla_x_variant":[
        "Pictou"
    ],
    "name:ita_x_preferred":[
        "Pictou"
    ],
    "name:jpn_x_preferred":[
        "\u30d4\u30af\u30c8\u30fc"
    ],
    "name:nld_x_preferred":[
        "Pictou"
    ],
    "name:por_x_preferred":[
        "Pictou"
    ],
    "name:rus_x_preferred":[
        "\u041f\u0438\u043a\u0442\u0443"
    ],
    "name:slv_x_preferred":[
        "Pictou"
    ],
    "name:swe_x_preferred":[
        "Pictou"
    ],
    "qs:name":"Pictou",
    "qs:name_adm0":"Canada",
    "qs:name_adm1":"Nova Scotia",
    "qs:photos":957,
    "qs:photos_1k":194,
    "qs:photos_9k":4,
    "qs:photos_9r":6,
    "qs:photos_all":957,
    "qs:photos_sr":10,
    "qs:placetype":"Town",
    "qs:pop_sr":"4",
    "wd:wordcount":1546,
    "wof:name":"Pictou",
    "wof:placetype":"locality",
    "wof:population":3732
},
  "geometry": {"coordinates":[-62.71534,45.68344],"type":"Point"}
}