{
  "type": "Feature",
  "properties": {
    "gn:admin1_code":"11.0",
    "gn:asciiname":"Chemong",
    "gn:country_code":"CA",
    "gn:dem":346,
    "gn:feature_class":"P",
    "gn:feature_code":"PPLL",
    "gn:name":"Chemong",
    "gn:population":0,
    "gn:timezone":"America/Regina",
    "iso:country":"CA",
    "wof:name":"Chemong",
    "wof:placetype":"locality"
},
  "geometry": {"coordinates":[-102.10093999999999,53.20006],"type":"Point"}
}