{
  "type": "Feature",
  "properties": {
    "gn:admin1_code":"7",
    "gn:asciiname":"Middle Cape",
    "gn:country_code":"CA",
    "gn:dem":16,
    "gn:feature_class":"P",
    "gn:feature_code":"PPL",
    "gn:name":"Middle Cape",
    "gn:population":0,
    "gn:timezone":"America/Glace_Bay",
    "iso:country":"CA",
    "name:gla_x_preferred":[
        "An Rubha Meadhanach"
    ],
    "name:nld_x_preferred":[
        "Middle Cape"
    ],
    "wof:name":"Middle Cape",
    "wof:placetype":"locality"
},
  "geometry": {"coordinates":[-60.61495,45.86718],"type":"Point"}
}