{
  "type": "Feature",
  "properties": {
    "gn:admin1_code":"1.0",
    "gn:asciiname":"Botha",
    "gn:country_code":"CA",
    "gn:dem":809,
    "gn:feature_class":"P",
    "gn:feature_code":"PPL",
    "gn:name":"Botha",
    "gn:population":0,
    "gn:timezone":"America/Edmonton",
    "iso:country":"CA",
    "wof:name":"Botha",
    "wof:placetype":"locality"
},
  "geometry": {"coordinates":[-112.53519,52.30013],"type":"Point"}
}