{
  "type": "Feature",
  "properties": {
    "gn:admin1_code":"1.0",
    "gn:asciiname":"Botha",
    "gn:country_code":"CA",
    "gn:dem":809,
    "gn:feature_class":"P",
    "gn:feature_code":"PPL",
    "gn:name":"Botha",
    "gn:population":0,
    "gn:timezone":"America/Edmonton",
    "iso:country":"CA",
    "name:ara_x_preferred":[
        "\u0628\u0648\u062a\u0627"
    ],
    "name:ceb_x_preferred":[
        "Botha"
    ],
    "name:fra_x_preferred":[
        "Botha"
    ],
    "name:nld_x_preferred":[
        "Botha"
    ],
    "name:swe_x_preferred":[
        "Botha"
    ],
    "wof:name":"Botha",
    "wof:placetype":"locality"
},
  "geometry": {"coordinates":[-112.53519,52.30013],"type":"Point"}
}