{
  "type": "Feature",
  "properties": {
    "gn:admin1_code":"9.0",
    "gn:asciiname":"Darnley",
    "gn:country_code":"CA",
    "gn:dem":25,
    "gn:feature_class":"P",
    "gn:feature_code":"PPLL",
    "gn:name":"Darnley",
    "gn:population":0,
    "gn:timezone":"America/Halifax",
    "iso:country":"CA",
    "name:eus_x_preferred":[
        "Darnley"
    ],
    "wof:name":"Darnley",
    "wof:placetype":"locality"
},
  "geometry": {"coordinates":[-63.63201,46.53343],"type":"Point"}
}