{
  "type": "Feature",
  "properties": {
    "gn:admin1_code":"3",
    "gn:asciiname":"Kitchiokonim Place",
    "gn:country_code":"CA",
    "gn:dem":251,
    "gn:feature_class":"P",
    "gn:feature_code":"PPLL",
    "gn:name":"Kitchiokonim Place",
    "gn:population":0,
    "gn:timezone":"America/Winnipeg",
    "iso:country":"CA",
    "wof:name":"Kitchiokonim Place",
    "wof:placetype":"locality"
},
  "geometry": {"coordinates":[-94.33434,53.91269000000001],"type":"Point"}
}