{
  "type": "Feature",
  "properties": {
    "gn:admin1_code":"1",
    "gn:asciiname":"Val Quentin",
    "gn:country_code":"CA",
    "gn:dem":726,
    "gn:feature_class":"P",
    "gn:feature_code":"PPL",
    "gn:name":"Val Quentin",
    "gn:population":0,
    "gn:timezone":"America/Edmonton",
    "iso:country":"CA",
    "wof:name":"Val Quentin",
    "wof:placetype":"locality"
},
  "geometry": {"coordinates":[-114.38538,53.66684],"type":"Point"}
}