{
  "type": "Feature",
  "properties": {
    "gn:admin1_code":"2.0",
    "gn:asciiname":"Willow Valley",
    "gn:country_code":"CA",
    "gn:dem":701,
    "gn:feature_class":"P",
    "gn:feature_code":"PPLL",
    "gn:name":"Willow Valley",
    "gn:population":0,
    "gn:timezone":"America/Dawson_Creek",
    "iso:country":"CA",
    "name:ceb_x_preferred":[
        "Willow Valley"
    ],
    "name:pol_x_preferred":[
        "Willow Valley"
    ],
    "name:swe_x_preferred":[
        "Willow Valley"
    ],
    "name:ukr_x_preferred":[
        "\u0412\u0456\u043b\u043b\u043e\u0432-\u0412\u0435\u0439\u043b\u043b\u0456"
    ],
    "wof:name":"Willow Valley",
    "wof:placetype":"locality"
},
  "geometry": {"coordinates":[-120.86962,55.84989],"type":"Point"}
}