{
  "type": "Feature",
  "properties": {
    "gn:admin1_code":"11",
    "gn:asciiname":"Hatton",
    "gn:country_code":"CA",
    "gn:dem":734,
    "gn:feature_class":"P",
    "gn:feature_code":"PPL",
    "gn:name":"Hatton",
    "gn:population":0,
    "gn:timezone":"America/Regina",
    "iso:country":"CA",
    "wof:name":"Hatton",
    "wof:placetype":"locality"
},
  "geometry": {"coordinates":[-109.83486000000001,50.0501],"type":"Point"}
}