{
  "type": "Feature",
  "properties": {
    "gn:admin1_code":"11",
    "gn:asciiname":"Hatton",
    "gn:country_code":"CA",
    "gn:dem":734,
    "gn:feature_class":"P",
    "gn:feature_code":"PPL",
    "gn:name":"Hatton",
    "gn:population":0,
    "gn:timezone":"America/Regina",
    "iso:country":"CA",
    "name:ceb_x_preferred":[
        "Hatton"
    ],
    "name:deu_x_preferred":[
        "Hatton"
    ],
    "name:fas_x_preferred":[
        "\u0647\u0627\u062a\u0648\u0646"
    ],
    "name:fra_x_preferred":[
        "Hatton"
    ],
    "name:hin_x_preferred":[
        "\u0939\u0948\u091f\u0928"
    ],
    "name:ita_x_preferred":[
        "Hatton"
    ],
    "name:nld_x_preferred":[
        "Hatton"
    ],
    "name:pol_x_preferred":[
        "Hatton"
    ],
    "name:por_x_preferred":[
        "Hatton"
    ],
    "name:rus_x_preferred":[
        "\u0425\u044d\u0442\u0442\u043e\u043d"
    ],
    "name:spa_x_preferred":[
        "Hatton"
    ],
    "name:srp_x_preferred":[
        "\u0425\u0430\u0442\u043e\u043d"
    ],
    "name:swe_x_preferred":[
        "Hatton"
    ],
    "name:vol_x_preferred":[
        "Hatton"
    ],
    "wof:name":"Hatton",
    "wof:placetype":"locality"
},
  "geometry": {"coordinates":[-109.83486000000001,50.0501],"type":"Point"}
}