{
  "type": "Feature",
  "properties": {
    "gn:admin1_code":"7",
    "gn:asciiname":"Valley",
    "gn:country_code":"CA",
    "gn:dem":43,
    "gn:feature_class":"P",
    "gn:feature_code":"PPL",
    "gn:name":"Valley",
    "gn:population":0,
    "gn:timezone":"America/Halifax",
    "iso:country":"CA",
    "name:urd_x_preferred":[
        "\u0648\u06cc\u0644\u06cc"
    ],
    "wof:name":"Valley",
    "wof:placetype":"locality"
},
  "geometry": {"coordinates":[-63.19705,45.38754],"type":"Point"}
}