{
  "type": "Feature",
  "properties": {
    "gn:admin1_code":"7",
    "gn:asciiname":"Glencoe Station",
    "gn:country_code":"CA",
    "gn:dem":79,
    "gn:feature_class":"P",
    "gn:feature_code":"PPL",
    "gn:name":"Glencoe Station",
    "gn:population":0,
    "gn:timezone":"America/Halifax",
    "iso:country":"CA",
    "wof:name":"Glencoe Station",
    "wof:placetype":"locality"
},
  "geometry": {"coordinates":[-61.44526,45.9911],"type":"Point"}
}