{
  "type": "Feature",
  "properties": {
    "gn:admin1_code":"10",
    "gn:admin2_code":"11.0",
    "gn:admin3_code":"1023.0",
    "gn:asciiname":"Pointe-Basse",
    "gn:country_code":"CA",
    "gn:dem":5,
    "gn:feature_class":"P",
    "gn:feature_code":"PPL",
    "gn:name":"Pointe-Basse",
    "gn:population":0,
    "gn:timezone":"America/Halifax",
    "iso:country":"CA",
    "wof:name":"Pointe-Basse",
    "wof:placetype":"locality"
},
  "geometry": {"coordinates":[-61.79095,47.39312],"type":"Point"}
}