{
  "type": "Feature",
  "properties": {
    "gn:admin1_code":"7",
    "gn:asciiname":"Ironville",
    "gn:country_code":"CA",
    "gn:dem":13,
    "gn:feature_class":"P",
    "gn:feature_code":"PPL",
    "gn:name":"Ironville",
    "gn:population":0,
    "gn:timezone":"America/Glace_Bay",
    "iso:country":"CA",
    "wof:name":"Ironville",
    "wof:placetype":"locality"
},
  "geometry": {"coordinates":[-60.46218,46.13317],"type":"Point"}
}