{
  "type": "Feature",
  "properties": {
    "gn:country":"CA",
    "iso:country":"CA",
    "name:eng_x_preferred":[
        "Cape Negro"
    ],
    "name:fra_x_preferred":[
        "Cap-Noir"
    ],
    "name:nld_x_preferred":[
        "Cape Negro"
    ],
    "name:zho_x_preferred":[
        "\u5185\u683c\u7f57\u89d2"
    ],
    "qs:name":"Cape Negro",
    "qs:name_adm0":"Canada",
    "qs:name_adm1":"Nova Scotia",
    "qs:photos":34,
    "qs:photos_1k":7,
    "qs:photos_9k":1,
    "qs:photos_9r":2,
    "qs:photos_all":34,
    "qs:photos_sr":2,
    "qs:placetype":"Town",
    "qs:pop_sr":"0",
    "wd:wordcount":513,
    "wof:name":"Cape Negro",
    "wof:placetype":"locality"
},
  "geometry": {"coordinates":[-65.42735999999999,43.530504],"type":"Point"}
}