{
  "type": "Feature",
  "properties": {
    "iso:country":"CA",
    "name:eng_x_preferred":[
        "Maskinonge"
    ],
    "qs:gn_local":0,
    "qs:local_max":47,
    "qs:local_sum":65,
    "qs:localhoods":2,
    "qs:name":"Maskinonge",
    "qs:name_adm0":"Canada",
    "qs:name_adm1":"Ontario",
    "qs:name_adm2":"York",
    "qs:name_local":"Glenwoods",
    "qs:photo_max":9,
    "qs:photo_sum":18,
    "qs:placetype":"Suburb",
    "qs:quad_count":7,
    "qs:woe_adm0":23424775,
    "qs:woe_adm1":2344922,
    "qs:woe_adm2":29375112,
    "qs:woe_funk":"Grouping neighborhood",
    "qs:woe_lau":0,
    "qs:woe_local":55999238,
    "qs:woe_ver":"7.10.0",
    "wof:lang":[
        "eng"
    ],
    "wof:name":"Maskinonge",
    "wof:placetype":"neighbourhood"
},
  "geometry": {"coordinates":[-79.45343,44.227708],"type":"Point"}
}