{
  "type": "Feature",
  "properties": {
    "gn:admin1_code":"10.0",
    "gn:admin2_code":"4.0",
    "gn:admin3_code":"51075.0",
    "gn:asciiname":"Domaine-des-Bouleaux-Blancs",
    "gn:country_code":"CA",
    "gn:dem":171,
    "gn:feature_class":"P",
    "gn:feature_code":"PPL",
    "gn:name":"Domaine-des-Bouleaux-Blancs",
    "gn:population":0,
    "gn:timezone":"America/Toronto",
    "iso:country":"CA",
    "wof:name":"Domaine-des-Bouleaux-Blancs",
    "wof:placetype":"locality"
},
  "geometry": {"coordinates":[-72.92456999999997,46.47808],"type":"Point"}
}