{
  "type": "Feature",
  "properties": {
    "iso:country":"CA",
    "name:ara_x_preferred":[
        "\u0628\u064a\u062a\u064a\u062a \u0631\u0648\u062a\u0634\u0631"
    ],
    "name:ceb_x_preferred":[
        "Petit-Rocher"
    ],
    "name:eng_x_preferred":[
        "Petit-Rocher"
    ],
    "name:fas_x_preferred":[
        "\u067e\u062a\u06cc\u062a \u0631\u0648\u0634\u0631"
    ],
    "name:fra_x_preferred":[
        "Petit-Rocher"
    ],
    "name:nld_x_preferred":[
        "Petit-Rocher"
    ],
    "name:swe_x_preferred":[
        "Petit-Rocher"
    ],
    "qs_pg:aaroncc":"CA",
    "qs_pg:name":"Petit Rocher",
    "qs_pg:name_adm0":"Canada",
    "qs_pg:name_adm1":"New Brunswick",
    "qs_pg:photos":138,
    "qs_pg:photos_1k":28,
    "qs_pg:photos_9k":1,
    "qs_pg:photos_9r":3,
    "qs_pg:photos_all":138,
    "qs_pg:photos_sr":3,
    "qs_pg:pop_sr":0,
    "qs_pg:qs_pg_placetype":"locality",
    "qs_pg:qs_pg_placetype_gp":"Town",
    "qs_pg:woe_adm0":23424775,
    "woe:adm0_id":23424775,
    "woe:name_adm0":"Canada",
    "woe:name_adm1":"New Brunswick",
    "woe:placetype":"Town",
    "wof:name":"Petit Rocher",
    "wof:placetype":"locality"
},
  "geometry": {"coordinates":[-65.714721,47.78276],"type":"Point"}
}