{
  "type": "Feature",
  "properties": {
    "gn:country":"CA",
    "gn:fcode":"PPL",
    "gn:pop":0,
    "iso:country":"CA",
    "name:bre_x_preferred":[
        "Twillingate"
    ],
    "name:ceb_x_preferred":[
        "Twillingate"
    ],
    "name:cos_x_preferred":[
        "Twillingate"
    ],
    "name:dan_x_preferred":[
        "Twillingate"
    ],
    "name:deu_x_preferred":[
        "Twillingate"
    ],
    "name:eng_x_preferred":[
        "Twillingate"
    ],
    "name:fra_x_preferred":[
        "Twillingate"
    ],
    "name:gle_x_preferred":[
        "Twillingate"
    ],
    "name:ind_x_preferred":[
        "Twillingate"
    ],
    "name:ita_x_preferred":[
        "Twillingate"
    ],
    "name:nds_x_preferred":[
        "Twillingate"
    ],
    "name:nld_x_preferred":[
        "Twillingate"
    ],
    "name:por_x_preferred":[
        "Twillingate"
    ],
    "name:ron_x_preferred":[
        "Twillingate"
    ],
    "name:spa_x_preferred":[
        "Twillingate"
    ],
    "name:swe_x_preferred":[
        "Twillingate"
    ],
    "name:tah_x_preferred":[
        "Twillingate"
    ],
    "qs:name":"Twillingate",
    "qs:name_adm0":"Canada",
    "qs:name_adm1":"Newfoundland and Labrador",
    "qs:photos":542,
    "qs:photos_1k":110,
    "qs:photos_9k":2,
    "qs:photos_9r":5,
    "qs:photos_all":542,
    "qs:photos_sr":7,
    "qs:placetype":"Town",
    "qs:pop_sr":"0",
    "wd:wordcount":2862,
    "wof:name":"Twillingate",
    "wof:placetype":"locality",
    "wof:population":0
},
  "geometry": {"coordinates":[-54.76486,49.64992],"type":"Point"}
}