{
  "type": "Feature",
  "properties": {
    "gn:admin1_code":"8.0",
    "gn:asciiname":"Cooks Mills",
    "gn:country_code":"CA",
    "gn:dem":344,
    "gn:feature_class":"P",
    "gn:feature_code":"PPL",
    "gn:name":"Cooks Mills",
    "gn:population":0,
    "gn:timezone":"America/Toronto",
    "iso:country":"CA",
    "name:deu_x_preferred":[
        "Cooks Mills"
    ],
    "wof:name":"Cooks Mills",
    "wof:placetype":"locality"
},
  "geometry": {"coordinates":[-79.46710999999998,46.40453],"type":"Point"}
}