{
  "type": "Feature",
  "properties": {
    "gn:admin1_code":"1.0",
    "gn:asciiname":"Chateh",
    "gn:country_code":"CA",
    "gn:dem":344,
    "gn:feature_class":"P",
    "gn:feature_code":"PPL",
    "gn:name":"Chateh",
    "gn:population":0,
    "gn:timezone":"America/Edmonton",
    "iso:country":"CA",
    "wof:name":"Chateh",
    "wof:placetype":"locality"
},
  "geometry": {"coordinates":[-118.67637999999999,58.6714],"type":"Point"}
}