{
  "type": "Feature",
  "properties": {
    "gn:admin1_code":"7",
    "gn:asciiname":"Marvins Island",
    "gn:country_code":"CA",
    "gn:dem":18,
    "gn:feature_class":"P",
    "gn:feature_code":"PPL",
    "gn:name":"Marvins Island",
    "gn:population":0,
    "gn:timezone":"America/Halifax",
    "iso:country":"CA",
    "wof:name":"Marvins Island",
    "wof:placetype":"locality"
},
  "geometry": {"coordinates":[-64.29991,44.5549],"type":"Point"}
}