{
  "type": "Feature",
  "properties": {
    "gn:admin1_code":"10",
    "gn:admin2_code":"7.0",
    "gn:admin3_code":"82035.0",
    "gn:asciiname":"Joynt",
    "gn:country_code":"CA",
    "gn:dem":188,
    "gn:feature_class":"P",
    "gn:feature_code":"PPL",
    "gn:name":"Joynt",
    "gn:population":0,
    "gn:timezone":"America/Toronto",
    "iso:country":"CA",
    "wof:name":"Joynt",
    "wof:placetype":"locality"
},
  "geometry": {"coordinates":[-76.01472,45.75694],"type":"Point"}
}