{
  "type": "Feature",
  "properties": {
    "gn:admin1_code":"4.0",
    "gn:asciiname":"Aboushagan Road",
    "gn:country_code":"CA",
    "gn:dem":11,
    "gn:feature_class":"P",
    "gn:feature_code":"PPLL",
    "gn:name":"Aboushagan Road",
    "gn:population":0,
    "gn:timezone":"America/Moncton",
    "iso:country":"CA",
    "wof:name":"Aboushagan Road",
    "wof:placetype":"locality"
},
  "geometry": {"coordinates":[-64.34875,45.98345],"type":"Point"}
}