{
  "type": "Feature",
  "properties": {
    "gn:admin1_code":"8",
    "gn:asciiname":"Newholm",
    "gn:country_code":"CA",
    "gn:dem":390,
    "gn:feature_class":"P",
    "gn:feature_code":"PPL",
    "gn:name":"Newholm",
    "gn:population":0,
    "gn:timezone":"America/Toronto",
    "iso:country":"CA",
    "wof:name":"Newholm",
    "wof:placetype":"locality"
},
  "geometry": {"coordinates":[-79.15722,45.23472],"type":"Point"}
}