{
  "type": "Feature",
  "properties": {
    "gn:admin1_code":"4",
    "gn:asciiname":"The Grant",
    "gn:country_code":"CA",
    "gn:dem":51,
    "gn:feature_class":"P",
    "gn:feature_code":"PPL",
    "gn:name":"The Grant",
    "gn:population":0,
    "gn:timezone":"America/Moncton",
    "iso:country":"CA",
    "wof:name":"The Grant",
    "wof:placetype":"locality"
},
  "geometry": {"coordinates":[-65.8887,45.67088],"type":"Point"}
}