{
  "type": "Feature",
  "properties": {
    "gn:admin1_code":"11",
    "gn:asciiname":"Riverside Estates",
    "gn:country_code":"CA",
    "gn:dem":500,
    "gn:feature_class":"P",
    "gn:feature_code":"PPL",
    "gn:name":"Riverside Estates",
    "gn:population":0,
    "gn:timezone":"America/Regina",
    "iso:country":"CA",
    "wof:name":"Riverside Estates",
    "wof:placetype":"locality"
},
  "geometry": {"coordinates":[-106.70560999999999,52.04905],"type":"Point"}
}