{
  "type": "Feature",
  "properties": {
    "gn:admin1_code":"11",
    "gn:asciiname":"Longhope",
    "gn:country_code":"CA",
    "gn:dem":673,
    "gn:feature_class":"P",
    "gn:feature_code":"PPLL",
    "gn:name":"Longhope",
    "gn:population":0,
    "gn:timezone":"America/Regina",
    "iso:country":"CA",
    "name:ceb_x_preferred":[
        "Longhope"
    ],
    "name:cym_x_preferred":[
        "Longhope"
    ],
    "name:fas_x_preferred":[
        "\u0644\u0627\u0646\u06af\u0647\u0648\u067e"
    ],
    "name:ita_x_preferred":[
        "Longhope"
    ],
    "name:pol_x_preferred":[
        "Longhope"
    ],
    "name:por_x_preferred":[
        "Longhope"
    ],
    "name:spa_x_preferred":[
        "Longhope"
    ],
    "name:swe_x_preferred":[
        "Longhope"
    ],
    "wof:name":"Longhope",
    "wof:placetype":"locality"
},
  "geometry": {"coordinates":[-108.56807999999999,53.33347],"type":"Point"}
}