{
  "type": "Feature",
  "properties": {
    "gn:admin1_code":"8.0",
    "gn:asciiname":"Attercliffe Station",
    "gn:country_code":"CA",
    "gn:dem":181,
    "gn:feature_class":"P",
    "gn:feature_code":"PPL",
    "gn:name":"Attercliffe Station",
    "gn:population":0,
    "gn:timezone":"America/Toronto",
    "iso:country":"CA",
    "wof:name":"Attercliffe Station",
    "wof:placetype":"locality"
},
  "geometry": {"coordinates":[-79.59238000000001,42.96874],"type":"Point"}
}