{
  "type": "Feature",
  "properties": {
    "gn:admin1_code":"8",
    "gn:asciiname":"Peel Village",
    "gn:country_code":"CA",
    "gn:dem":216,
    "gn:feature_class":"P",
    "gn:feature_code":"PPL",
    "gn:name":"Peel Village",
    "gn:population":0,
    "gn:timezone":"America/Toronto",
    "iso:country":"CA",
    "wof:name":"Peel Village",
    "wof:placetype":"locality"
},
  "geometry": {"coordinates":[-79.73349,43.67492],"type":"Point"}
}