{
  "type": "Feature",
  "properties": {
    "gn:admin1_code":"4",
    "gn:asciiname":"Vautour",
    "gn:country_code":"CA",
    "gn:dem":62,
    "gn:feature_class":"P",
    "gn:feature_code":"PPL",
    "gn:name":"Vautour",
    "gn:population":0,
    "gn:timezone":"America/Moncton",
    "iso:country":"CA",
    "name:fra_x_preferred":[
        "Vautour"
    ],
    "wof:name":"Vautour",
    "wof:placetype":"locality"
},
  "geometry": {"coordinates":[-65.23333000000001,46.75],"type":"Point"}
}