{
  "type": "Feature",
  "properties": {
    "iso:country":"CA",
    "name:eng_x_preferred":[
        "Pukatawagan"
    ],
    "name:fin_x_preferred":[
        "Pukatawagan"
    ],
    "name:nld_x_preferred":[
        "Pukatawagan"
    ],
    "ne:ADM0CAP":0.0,
    "ne:ADM0NAME":"Canada",
    "ne:ADM0_A3":"CAN",
    "ne:ADM1NAME":"Manitoba",
    "ne:ADMIN1_COD":0,
    "ne:CAPALT":0,
    "ne:CHANGED":0,
    "ne:CHECKME":0,
    "ne:COMPARE":0,
    "ne:DIFFASCII":0,
    "ne:ELEVATION":0.0,
    "ne:FEATURECLA":"Populated place",
    "ne:GEONAMEID":-1,
    "ne:GEONAMESNO":"No GeoNames match due to small population, not in GeoNames, or poor NEV placement.",
    "ne:GN_POP":0,
    "ne:GTOPO30":0.0,
    "ne:ISO_A2":"CA",
    "ne:LABELRANK":2,
    "ne:LATITUDE":55.733276,
    "ne:LONGITUDE":-101.316617,
    "ne:LS_MATCH":1,
    "ne:LS_NAME":"Pukatawagan",
    "ne:MAX_AREAKM":1.0,
    "ne:MAX_AREAMI":0.0,
    "ne:MAX_BBXMAX":-101.308333,
    "ne:MAX_BBXMIN":-101.325,
    "ne:MAX_BBYMAX":55.75,
    "ne:MAX_BBYMIN":55.741667,
    "ne:MAX_NATSCA":10.0,
    "ne:MAX_PERKM":5.0,
    "ne:MAX_PERMI":3.0,
    "ne:MAX_POP10":431,
    "ne:MAX_POP20":0,
    "ne:MAX_POP300":0,
    "ne:MAX_POP310":0,
    "ne:MAX_POP50":0,
    "ne:MEAN_BBXC":-101.316667,
    "ne:MEAN_BBYC":55.745833,
    "ne:MEGACITY":0,
    "ne:MIN_AREAKM":1.0,
    "ne:MIN_AREAMI":0.0,
    "ne:MIN_BBXMAX":-101.308333,
    "ne:MIN_BBXMIN":-101.325,
    "ne:MIN_BBYMAX":55.75,
    "ne:MIN_BBYMIN":55.741667,
    "ne:MIN_PERKM":5.0,
    "ne:MIN_PERMI":3.0,
    "ne:NAME":"Pukatawagan",
    "ne:NAMEASCII":"Pukatawagan",
    "ne:NAMEDIFF":0,
    "ne:NATSCALE":10,
    "ne:POP1950":0,
    "ne:POP1955":0,
    "ne:POP1960":0,
    "ne:POP1965":0,
    "ne:POP1970":0,
    "ne:POP1975":0,
    "ne:POP1980":0,
    "ne:POP1985":0,
    "ne:POP1990":0,
    "ne:POP1995":0,
    "ne:POP2000":0,
    "ne:POP2005":0,
    "ne:POP2010":0,
    "ne:POP2015":0,
    "ne:POP2020":0,
    "ne:POP2025":0,
    "ne:POP2050":0,
    "ne:POP_MAX":431,
    "ne:POP_MIN":431,
    "ne:POP_OTHER":0,
    "ne:RANK_MAX":2,
    "ne:RANK_MIN":2,
    "ne:SCALERANK":8,
    "ne:SOV0NAME":"Canada",
    "ne:SOV_A3":"CAN",
    "ne:UN_FID":0,
    "ne:UN_LAT":0.0,
    "ne:UN_LONG":0.0,
    "ne:WORLDCITY":0,
    "ne:min_zoom":7.0,
    "wof:name":"Pukatawagan",
    "wof:placetype":"locality"
},
  "geometry": {"coordinates":[-101.31661706724964,55.73327638663267],"type":"Point"}
}