{
  "type": "Feature",
  "properties": {
    "gn:admin1_code":"10.0",
    "gn:admin2_code":"16.0",
    "gn:admin3_code":"69037.0",
    "gn:asciiname":"Domaine-Chantigny",
    "gn:country_code":"CA",
    "gn:dem":41,
    "gn:feature_class":"P",
    "gn:feature_code":"PPL",
    "gn:name":"Domaine-Chantigny",
    "gn:population":0,
    "gn:timezone":"America/Toronto",
    "iso:country":"CA",
    "wof:name":"Domaine-Chantigny",
    "wof:placetype":"locality"
},
  "geometry": {"coordinates":[-73.99794,45.1181],"type":"Point"}
}