{
  "type": "Feature",
  "properties": {
    "gn:admin1_code":"8",
    "gn:asciiname":"Mosher",
    "gn:country_code":"CA",
    "gn:dem":350,
    "gn:feature_class":"P",
    "gn:feature_code":"PPL",
    "gn:name":"Mosher",
    "gn:population":0,
    "gn:timezone":"America/Toronto",
    "iso:country":"CA",
    "name:deu_x_preferred":[
        "Mosher"
    ],
    "name:fra_x_preferred":[
        "Mosher"
    ],
    "name:hin_x_preferred":[
        "\u092e\u094b\u0936\u0947\u0930"
    ],
    "name:nds_x_preferred":[
        "Mosher"
    ],
    "wof:name":"Mosher",
    "wof:placetype":"locality"
},
  "geometry": {"coordinates":[-84.19750000000001,48.70528],"type":"Point"}
}