{
  "type": "Feature",
  "properties": {
    "gn:admin1_code":"4.0",
    "gn:asciiname":"Dufferin",
    "gn:country_code":"CA",
    "gn:dem":53,
    "gn:feature_class":"P",
    "gn:feature_code":"PPL",
    "gn:name":"Dufferin",
    "gn:population":0,
    "gn:timezone":"America/Moncton",
    "iso:country":"CA",
    "name:fra_x_preferred":[
        "Dufferin"
    ],
    "wof:name":"Dufferin",
    "wof:placetype":"locality"
},
  "geometry": {"coordinates":[-65.83635,46.14298],"type":"Point"}
}