{
  "type": "Feature",
  "properties": {
    "gn:admin1_code":"8",
    "gn:asciiname":"Reading",
    "gn:country_code":"CA",
    "gn:dem":491,
    "gn:feature_class":"P",
    "gn:feature_code":"PPL",
    "gn:name":"Reading",
    "gn:population":0,
    "gn:timezone":"America/Toronto",
    "iso:country":"CA",
    "wof:name":"Reading",
    "wof:placetype":"locality"
},
  "geometry": {"coordinates":[-80.21131,43.83711],"type":"Point"}
}