{
  "type": "Feature",
  "properties": {
    "gn:admin1_code":"8.0",
    "gn:asciiname":"Dereham Centre",
    "gn:country_code":"CA",
    "gn:dem":278,
    "gn:feature_class":"P",
    "gn:feature_code":"PPL",
    "gn:name":"Dereham Centre",
    "gn:population":0,
    "gn:timezone":"America/Toronto",
    "iso:country":"CA",
    "wof:name":"Dereham Centre",
    "wof:placetype":"locality"
},
  "geometry": {"coordinates":[-80.81156,42.92586],"type":"Point"}
}