{
  "type": "Feature",
  "properties": {
    "iso:country":"CA",
    "name:eng_x_preferred":[
        "Locust Hill"
    ],
    "name:nld_x_preferred":[
        "Locust Hill"
    ],
    "qs_pg:aaroncc":"CA",
    "qs_pg:name":"Locust Hill",
    "qs_pg:name_adm0":"Canada",
    "qs_pg:name_adm1":"Ontario",
    "qs_pg:photos":590,
    "qs_pg:photos_1k":120,
    "qs_pg:photos_9k":3,
    "qs_pg:photos_9r":5,
    "qs_pg:photos_all":590,
    "qs_pg:photos_sr":8,
    "qs_pg:pop_sr":0,
    "qs_pg:qs_pg_placetype":"locality",
    "qs_pg:qs_pg_placetype_gp":"Town",
    "qs_pg:woe_adm0":23424775,
    "woe:adm0_id":23424775,
    "woe:name_adm0":"Canada",
    "woe:name_adm1":"Ontario",
    "woe:placetype":"Town",
    "wof:name":"Locust Hill",
    "wof:placetype":"locality"
},
  "geometry": {"coordinates":[-79.23647699999999,43.898533],"type":"Point"}
}