{
  "type": "Feature",
  "properties": {
    "gn:admin1_code":"8",
    "gn:asciiname":"Frood Mine",
    "gn:country_code":"CA",
    "gn:dem":302,
    "gn:feature_class":"P",
    "gn:feature_code":"PPL",
    "gn:name":"Frood Mine",
    "gn:population":0,
    "gn:timezone":"America/Toronto",
    "iso:country":"CA",
    "wof:name":"Frood Mine",
    "wof:placetype":"locality"
},
  "geometry": {"coordinates":[-81.00381999999998,46.5251],"type":"Point"}
}