{
  "type": "Feature",
  "properties": {
    "gn:admin1_code":"4",
    "gn:asciiname":"Tay Falls",
    "gn:country_code":"CA",
    "gn:dem":138,
    "gn:feature_class":"P",
    "gn:feature_code":"PPL",
    "gn:name":"Tay Falls",
    "gn:population":0,
    "gn:timezone":"America/Moncton",
    "iso:country":"CA",
    "wof:name":"Tay Falls",
    "wof:placetype":"locality"
},
  "geometry": {"coordinates":[-66.77249999999999,46.2274],"type":"Point"}
}