{
  "type": "Feature",
  "properties": {
    "gn:admin1_code":"13",
    "gn:asciiname":"Rocher River",
    "gn:country_code":"CA",
    "gn:dem":206,
    "gn:feature_class":"P",
    "gn:feature_code":"PPLL",
    "gn:name":"Rocher River",
    "gn:population":0,
    "gn:timezone":"America/Yellowknife",
    "iso:country":"CA",
    "wof:name":"Rocher River",
    "wof:placetype":"locality"
},
  "geometry": {"coordinates":[-112.74233999999998,61.38213],"type":"Point"}
}