{
  "type": "Feature",
  "properties": {
    "gn:admin1_code":"10",
    "gn:admin2_code":"9.0",
    "gn:admin3_code":"98012.0",
    "gn:asciiname":"Shekatika",
    "gn:country_code":"CA",
    "gn:dem":7,
    "gn:feature_class":"P",
    "gn:feature_code":"PPL",
    "gn:name":"Shekatika",
    "gn:population":0,
    "gn:timezone":"America/Blanc-Sablon",
    "iso:country":"CA",
    "wof:name":"Shekatika",
    "wof:placetype":"locality"
},
  "geometry": {"coordinates":[-58.33187,51.28061],"type":"Point"}
}