{
  "type": "Feature",
  "properties": {
    "gn:admin1_code":"4",
    "gn:asciiname":"Hillside",
    "gn:country_code":"CA",
    "gn:dem":140,
    "gn:feature_class":"P",
    "gn:feature_code":"PPL",
    "gn:name":"Hillside",
    "gn:population":0,
    "gn:timezone":"America/Moncton",
    "iso:country":"CA",
    "name:bar_x_preferred":[
        "Hillside"
    ],
    "name:ceb_x_preferred":[
        "Hillside"
    ],
    "name:cym_x_preferred":[
        "Hillside"
    ],
    "name:deu_x_preferred":[
        "Hillside"
    ],
    "name:ita_x_preferred":[
        "Hillside"
    ],
    "name:mlg_x_preferred":[
        "Hillside"
    ],
    "name:nld_x_preferred":[
        "Hillside"
    ],
    "name:pol_x_preferred":[
        "Hillside"
    ],
    "name:por_x_preferred":[
        "Hillside"
    ],
    "name:srp_x_preferred":[
        "\u0425\u0438\u043b\u0441\u0430\u0458\u0434"
    ],
    "name:swe_x_preferred":[
        "Hillside"
    ],
    "name:ukr_x_preferred":[
        "\u0413\u0456\u043b\u043b\u0441\u0430\u0439\u0434"
    ],
    "name:vol_x_preferred":[
        "Hillside"
    ],
    "wof:name":"Hillside",
    "wof:placetype":"locality"
},
  "geometry": {"coordinates":[-65.02316999999999,45.7758],"type":"Point"}
}