{
  "type": "Feature",
  "properties": {
    "gn:admin1_code":"1.0",
    "gn:asciiname":"Atmore",
    "gn:country_code":"CA",
    "gn:dem":584,
    "gn:feature_class":"P",
    "gn:feature_code":"PPL",
    "gn:name":"Atmore",
    "gn:population":0,
    "gn:timezone":"America/Edmonton",
    "iso:country":"CA",
    "name:fra_x_preferred":[
        "Atmore"
    ],
    "wof:name":"Atmore",
    "wof:placetype":"locality"
},
  "geometry": {"coordinates":[-112.55197,54.81689],"type":"Point"}
}