{
  "type": "Feature",
  "properties": {
    "gn:country":"CA",
    "gn:fcode":"PPL",
    "gn:population":0,
    "iso:country":"CA",
    "name:ceb_x_preferred":[
        "Cowichan Bay"
    ],
    "name:eng_x_preferred":[
        "Cowichan Bay"
    ],
    "name:fra_x_preferred":[
        "Cowichan Bay"
    ],
    "name:jpn_x_preferred":[
        "\u30ab\u30a6\u30c1\u30f3\u6e7e"
    ],
    "name:nld_x_preferred":[
        "Cowichan Bay"
    ],
    "name:swe_x_preferred":[
        "Cowichan Bay"
    ],
    "qs_pg:aaroncc":"CA",
    "qs_pg:gn_country":"CA",
    "qs_pg:gn_fcode":"PPL",
    "qs_pg:gn_pop":0,
    "qs_pg:name":"Cowichan Bay",
    "qs_pg:name_adm0":"Canada",
    "qs_pg:name_adm1":"British Columbia",
    "qs_pg:photos":273,
    "qs_pg:photos_1k":55,
    "qs_pg:photos_9k":1,
    "qs_pg:photos_9r":4,
    "qs_pg:photos_all":273,
    "qs_pg:photos_sr":5,
    "qs_pg:pop_sr":0,
    "qs_pg:qs_pg_placetype":"locality",
    "qs_pg:qs_pg_placetype_gp":"Town",
    "qs_pg:woe_adm0":23424775,
    "woe:adm0_id":23424775,
    "woe:name_adm0":"Canada",
    "woe:name_adm1":"British Columbia",
    "woe:placetype":"Town",
    "wof:name":"Cowichan Bay",
    "wof:placetype":"locality"
},
  "geometry": {"coordinates":[-123.61739,48.73366],"type":"Point"}
}