{
  "type": "Feature",
  "properties": {
    "gn:admin1_code":"8",
    "gn:asciiname":"Martin Farm",
    "gn:country_code":"CA",
    "gn:dem":351,
    "gn:feature_class":"P",
    "gn:feature_code":"PPL",
    "gn:name":"Martin Farm",
    "gn:population":0,
    "gn:timezone":"America/Toronto",
    "iso:country":"CA",
    "wof:name":"Martin Farm",
    "wof:placetype":"locality"
},
  "geometry": {"coordinates":[-79.59083000000003,44.545],"type":"Point"}
}