{
  "type": "Feature",
  "properties": {
    "gn:admin1_code":"1.0",
    "gn:asciiname":"Craigend",
    "gn:country_code":"CA",
    "gn:dem":548,
    "gn:feature_class":"P",
    "gn:feature_code":"PPL",
    "gn:name":"Craigend",
    "gn:population":0,
    "gn:timezone":"America/Edmonton",
    "iso:country":"CA",
    "wof:name":"Craigend",
    "wof:placetype":"locality"
},
  "geometry": {"coordinates":[-111.93519999999999,54.58349000000001],"type":"Point"}
}