{
  "type": "Feature",
  "properties": {
    "gn:admin1_code":"3",
    "gn:asciiname":"Landseer",
    "gn:country_code":"CA",
    "gn:dem":379,
    "gn:feature_class":"P",
    "gn:feature_code":"PPLL",
    "gn:name":"Landseer",
    "gn:population":0,
    "gn:timezone":"America/Winnipeg",
    "iso:country":"CA",
    "wof:name":"Landseer",
    "wof:placetype":"locality"
},
  "geometry": {"coordinates":[-98.97328,49.57532],"type":"Point"}
}