{
  "type": "Feature",
  "properties": {
    "gn:admin1_code":"7.0",
    "gn:admin2_code":"1210",
    "gn:asciiname":"Brookside",
    "gn:country_code":"CA",
    "gn:dem":28,
    "gn:feature_class":"P",
    "gn:feature_code":"PPL",
    "gn:name":"Brookside",
    "gn:population":0,
    "gn:timezone":"America/Halifax",
    "iso:country":"CA",
    "wof:name":"Brookside",
    "wof:placetype":"locality"
},
  "geometry": {"coordinates":[-63.26207,45.39152],"type":"Point"}
}