{
  "type": "Feature",
  "properties": {
    "gn:admin1_code":"7.0",
    "gn:admin2_code":"1210",
    "gn:asciiname":"Brookside",
    "gn:country_code":"CA",
    "gn:dem":28,
    "gn:feature_class":"P",
    "gn:feature_code":"PPL",
    "gn:name":"Brookside",
    "gn:population":0,
    "gn:timezone":"America/Halifax",
    "iso:country":"CA",
    "name:ara_x_preferred":[
        "\u0628\u0631\u0648\u0643\u0633\u0627\u064a\u062f"
    ],
    "name:deu_x_preferred":[
        "Brookside"
    ],
    "name:fra_x_preferred":[
        "Brookside"
    ],
    "name:ita_x_preferred":[
        "Brookside"
    ],
    "name:nld_x_preferred":[
        "Brookside"
    ],
    "name:pol_x_preferred":[
        "Brookside"
    ],
    "name:rus_x_preferred":[
        "\u0411\u0440\u0443\u043a\u0441\u0430\u0439\u0434"
    ],
    "name:zho_x_preferred":[
        "\u5e03\u9b6f\u514b\u8cfd\u5fb7"
    ],
    "wof:name":"Brookside",
    "wof:placetype":"locality"
},
  "geometry": {"coordinates":[-63.26207,45.39152],"type":"Point"}
}