{
  "type": "Feature",
  "properties": {
    "gn:admin1_code":"10",
    "gn:admin2_code":"15",
    "gn:admin3_code":"77060.0",
    "gn:asciiname":"Saint-Michel-de-Wentworth",
    "gn:country_code":"CA",
    "gn:dem":250,
    "gn:feature_class":"P",
    "gn:feature_code":"PPL",
    "gn:name":"Saint-Michel-de-Wentworth",
    "gn:population":0,
    "gn:timezone":"America/Toronto",
    "iso:country":"CA",
    "wof:name":"Saint-Michel-de-Wentworth",
    "wof:placetype":"locality"
},
  "geometry": {"coordinates":[-74.48351,45.7731],"type":"Point"}
}