{
  "type": "Feature",
  "properties": {
    "gn:admin1_code":"8.0",
    "gn:asciiname":"Cambridge Forest Estates",
    "gn:country_code":"CA",
    "gn:dem":71,
    "gn:feature_class":"P",
    "gn:feature_code":"PPL",
    "gn:name":"Cambridge Forest Estates",
    "gn:population":0,
    "gn:timezone":"America/Toronto",
    "iso:country":"CA",
    "wof:name":"Cambridge Forest Estates",
    "wof:placetype":"locality"
},
  "geometry": {"coordinates":[-75.25239000000001,45.35782],"type":"Point"}
}