{
  "type": "Feature",
  "properties": {
    "gn:admin1_code":"8.0",
    "gn:asciiname":"Cold Springs",
    "gn:country_code":"CA",
    "gn:dem":290,
    "gn:feature_class":"P",
    "gn:feature_code":"PPL",
    "gn:name":"Cold Springs",
    "gn:population":0,
    "gn:timezone":"America/Toronto",
    "iso:country":"CA",
    "name:ceb_x_preferred":[
        "Cold Springs"
    ],
    "name:deu_x_preferred":[
        "Cold Springs"
    ],
    "name:ita_x_preferred":[
        "Cold Springs"
    ],
    "name:nld_x_preferred":[
        "Cold Springs"
    ],
    "name:pol_x_preferred":[
        "Cold Springs"
    ],
    "name:spa_x_preferred":[
        "Cold Springs"
    ],
    "name:srp_x_preferred":[
        "\u041a\u043e\u043b\u0434 \u0421\u043f\u0440\u0438\u043d\u0433"
    ],
    "wof:name":"Cold Springs",
    "wof:placetype":"locality"
},
  "geometry": {"coordinates":[-78.20917,44.06528],"type":"Point"}
}