{
  "type": "Feature",
  "properties": {
    "gn:admin1_code":"4",
    "gn:asciiname":"Sainte-Marie-de-Kent",
    "gn:country_code":"CA",
    "gn:dem":25,
    "gn:feature_class":"P",
    "gn:feature_code":"PPL",
    "gn:name":"Sainte-Marie-de-Kent",
    "gn:population":0,
    "gn:timezone":"America/Moncton",
    "iso:country":"CA",
    "name:ceb_x_preferred":[
        "Sainte-Marie-de-Kent"
    ],
    "name:swe_x_preferred":[
        "Sainte-Marie-de-Kent"
    ],
    "wof:name":"Sainte-Marie-de-Kent",
    "wof:placetype":"locality"
},
  "geometry": {"coordinates":[-64.82689000000001,46.41639],"type":"Point"}
}