{
  "type": "Feature",
  "properties": {
    "gn:gn_country":"CA",
    "gn:gn_fcode":"PPL",
    "gn:gn_pop":0,
    "iso:country":"CA",
    "name:deu_x_preferred":[
        "Saint-Louis-de-Blandford"
    ],
    "name:eng_x_preferred":[
        "Saint-Louis-de-Blandford"
    ],
    "name:eus_x_preferred":[
        "Saint-Louis-de-Blandford"
    ],
    "name:fas_x_preferred":[
        "\u0633\u0646-\u0644\u0648\u06cc\u06cc- \u062f\u0648-\u0628\u0644\u0627\u0646\u062f\u0641\u0648\u0631\u062f\u060c \u06a9\u0628\u06a9"
    ],
    "name:fra_x_preferred":[
        "Saint-Louis-de-Blandford"
    ],
    "name:nld_x_preferred":[
        "Saint-Louis-de-Blandford"
    ],
    "name:swe_x_preferred":[
        "Saint-Louis-de-Blandford"
    ],
    "name:urd_x_preferred":[
        "\u0633\u06cc\u0646\u0679-\u0644\u0648\u0626\u06cc\u0633-\u062f\u06d2-\u0628\u0644\u0627\u0646\u062f\u0641\u0648\u0631\u0688\u060c \u06a9\u06cc\u0648\u0628\u06a9"
    ],
    "qs_pg:aaroncc":"CA",
    "qs_pg:gn_country":"CA",
    "qs_pg:gn_fcode":"PPL",
    "qs_pg:gn_pop":0,
    "qs_pg:name":"St.-Louis-de-Blandford",
    "qs_pg:name_adm0":"Canada",
    "qs_pg:name_adm1":"Qu\u00e9bec",
    "qs_pg:photos":29,
    "qs_pg:photos_1k":6,
    "qs_pg:photos_9k":1,
    "qs_pg:photos_9r":2,
    "qs_pg:photos_all":29,
    "qs_pg:photos_sr":2,
    "qs_pg:pop_sr":0,
    "qs_pg:qs_pg_placetype":"locality",
    "qs_pg:qs_pg_placetype_gp":"Town",
    "qs_pg:woe_adm0":23424775,
    "woe:adm0_id":23424775,
    "woe:name_adm0":"Canada",
    "woe:name_adm1":"Qu\u00e9bec",
    "woe:placetype":"Town",
    "wof:name":"St.-Louis-de-Blandford",
    "wof:placetype":"locality"
},
  "geometry": {"coordinates":[-71.99909,46.25006],"type":"Point"}
}