{
  "type": "Feature",
  "properties": {
    "gn:admin1_code":"8",
    "gn:asciiname":"McKay's Waterfront",
    "gn:country_code":"CA",
    "gn:dem":55,
    "gn:feature_class":"P",
    "gn:feature_code":"PPL",
    "gn:name":"McKay's Waterfront",
    "gn:population":0,
    "gn:timezone":"America/Toronto",
    "iso:country":"CA",
    "wof:name":"McKay's Waterfront",
    "wof:placetype":"locality"
},
  "geometry": {"coordinates":[-76.19265,45.51543],"type":"Point"}
}