{
  "type": "Feature",
  "properties": {
    "gn:admin1_code":"1",
    "gn:asciiname":"Purple Springs",
    "gn:country_code":"CA",
    "gn:dem":801,
    "gn:feature_class":"P",
    "gn:feature_code":"PPLL",
    "gn:name":"Purple Springs",
    "gn:population":0,
    "gn:timezone":"America/Edmonton",
    "iso:country":"CA",
    "wof:name":"Purple Springs",
    "wof:placetype":"locality"
},
  "geometry": {"coordinates":[-111.90177,49.81675],"type":"Point"}
}