{
  "type": "Feature",
  "properties": {
    "gn:admin1_code":"8",
    "gn:asciiname":"Ottawa East",
    "gn:country_code":"CA",
    "gn:dem":65,
    "gn:feature_class":"P",
    "gn:feature_code":"PPL",
    "gn:name":"Ottawa East",
    "gn:population":0,
    "gn:timezone":"America/Toronto",
    "iso:country":"CA",
    "wof:name":"Ottawa East",
    "wof:placetype":"locality"
},
  "geometry": {"coordinates":[-75.67712,45.41258],"type":"Point"}
}