{
  "type": "Feature",
  "properties": {
    "gn:admin1_code":"8.0",
    "gn:admin2_code":"3548",
    "gn:asciiname":"Lavigne",
    "gn:country_code":"CA",
    "gn:dem":196,
    "gn:feature_class":"P",
    "gn:feature_code":"PPL",
    "gn:name":"Lavigne",
    "gn:population":0,
    "gn:timezone":"America/Toronto",
    "iso:country":"CA",
    "wof:name":"Lavigne",
    "wof:placetype":"locality"
},
  "geometry": {"coordinates":[-80.1699,46.32589],"type":"Point"}
}