{
  "type": "Feature",
  "properties": {
    "gn:admin1_code":"11",
    "gn:asciiname":"Sokal",
    "gn:country_code":"CA",
    "gn:dem":474,
    "gn:feature_class":"P",
    "gn:feature_code":"PPLL",
    "gn:name":"Sokal",
    "gn:population":0,
    "gn:timezone":"America/Regina",
    "iso:country":"CA",
    "wof:name":"Sokal",
    "wof:placetype":"locality"
},
  "geometry": {"coordinates":[-105.90111,52.70007],"type":"Point"}
}