{
  "type": "Feature",
  "properties": {
    "gn:admin1_code":"11",
    "gn:asciiname":"Sokal",
    "gn:country_code":"CA",
    "gn:dem":474,
    "gn:feature_class":"P",
    "gn:feature_code":"PPLL",
    "gn:name":"Sokal",
    "gn:population":0,
    "gn:timezone":"America/Regina",
    "iso:country":"CA",
    "name:ara_x_preferred":[
        "\u0633\u0648\u0643\u0627\u0644"
    ],
    "name:azb_x_preferred":[
        "\u0633\u0648\u06a9\u0627\u0644"
    ],
    "name:bel_x_preferred":[
        "\u0421\u0430\u043a\u0430\u043b\u044c"
    ],
    "name:ceb_x_preferred":[
        "Sokal'"
    ],
    "name:ces_x_preferred":[
        "Sokal"
    ],
    "name:crh_x_preferred":[
        "Sokal"
    ],
    "name:deu_x_preferred":[
        "Sokal"
    ],
    "name:fas_x_preferred":[
        "\u0633\u0648\u06a9\u0627\u0644"
    ],
    "name:fin_x_preferred":[
        "Sokal"
    ],
    "name:fra_x_preferred":[
        "Sokal"
    ],
    "name:heb_x_preferred":[
        "\u05e1\u05d5\u05e7\u05d0\u05dc"
    ],
    "name:hsb_x_preferred":[
        "Sokal"
    ],
    "name:hye_x_preferred":[
        "\u054d\u0578\u056f\u0561\u056c"
    ],
    "name:ita_x_preferred":[
        "Sokal'"
    ],
    "name:kat_x_preferred":[
        "\u10e1\u10dd\u10d9\u10d0\u10da\u10d8"
    ],
    "name:lav_x_preferred":[
        "Soka\u013ca"
    ],
    "name:nno_x_preferred":[
        "Sokal"
    ],
    "name:pol_x_preferred":[
        "Sokal"
    ],
    "name:ron_x_preferred":[
        "Sokal"
    ],
    "name:rus_x_preferred":[
        "\u0421\u043e\u043a\u0430\u043b\u044c"
    ],
    "name:srp_x_preferred":[
        "\u0421\u043e\u043a\u0430\u0459"
    ],
    "name:swe_x_preferred":[
        "Sokal"
    ],
    "name:szl_x_preferred":[
        "Sokal"
    ],
    "name:ukr_x_preferred":[
        "\u0421\u043e\u043a\u0430\u043b\u044c"
    ],
    "name:vie_x_preferred":[
        "Sokal"
    ],
    "name:zho_x_preferred":[
        "\u7d22\u5361\u723e"
    ],
    "wof:name":"Sokal",
    "wof:placetype":"locality"
},
  "geometry": {"coordinates":[-105.90111,52.70007],"type":"Point"}
}