{
  "type": "Feature",
  "properties": {
    "gn:admin1_code":"9",
    "gn:asciiname":"Mermaid",
    "gn:country_code":"CA",
    "gn:dem":12,
    "gn:feature_class":"P",
    "gn:feature_code":"PPLL",
    "gn:name":"Mermaid",
    "gn:population":0,
    "gn:timezone":"America/Halifax",
    "iso:country":"CA",
    "wof:name":"Mermaid",
    "wof:placetype":"locality"
},
  "geometry": {"coordinates":[-63.03198,46.26682],"type":"Point"}
}