{
  "type": "Feature",
  "properties": {
    "gn:admin1_code":"8.0",
    "gn:asciiname":"Blairhampton",
    "gn:country_code":"CA",
    "gn:dem":359,
    "gn:feature_class":"P",
    "gn:feature_code":"PPL",
    "gn:name":"Blairhampton",
    "gn:population":0,
    "gn:timezone":"America/Toronto",
    "iso:country":"CA",
    "wof:name":"Blairhampton",
    "wof:placetype":"locality"
},
  "geometry": {"coordinates":[-78.65571,45.02944],"type":"Point"}
}