{
  "type": "Feature",
  "properties": {
    "gn:admin1_code":"11",
    "gn:asciiname":"Orcadia",
    "gn:country_code":"CA",
    "gn:dem":509,
    "gn:feature_class":"P",
    "gn:feature_code":"PPL",
    "gn:name":"Orcadia",
    "gn:population":0,
    "gn:timezone":"America/Regina",
    "iso:country":"CA",
    "wof:name":"Orcadia",
    "wof:placetype":"locality"
},
  "geometry": {"coordinates":[-102.61715,51.26667],"type":"Point"}
}