{
  "type": "Feature",
  "properties": {
    "gn:admin1_code":"11",
    "gn:asciiname":"St. Cyr Lake",
    "gn:country_code":"CA",
    "gn:dem":474,
    "gn:feature_class":"P",
    "gn:feature_code":"PPLL",
    "gn:name":"St. Cyr Lake",
    "gn:population":0,
    "gn:timezone":"America/Regina",
    "iso:country":"CA",
    "wof:name":"St. Cyr Lake",
    "wof:placetype":"locality"
},
  "geometry": {"coordinates":[-108.06807999999999,54.21686999999999],"type":"Point"}
}