{
  "type": "Feature",
  "properties": {
    "iso:country":"CA",
    "name:eng_x_preferred":[
        "Centre Ville"
    ],
    "name:fra_x_preferred":[
        "Centre Ville"
    ],
    "name:unk_x_variant":[
        "Centre Ville"
    ],
    "qs:gn_adm0_cc":"CA",
    "qs:gn_local":6077340,
    "qs:gn_nam_loc":"valcour",
    "qs:gn_namadm1":"10",
    "qs:local_max":200,
    "qs:local_sum":290,
    "qs:localhoods":3,
    "qs:name":"Centre Ville",
    "qs:name_adm0":"Canada",
    "qs:name_adm1":"Qu\u00e9bec",
    "qs:name_adm2":"La Vall\u00e9e-du-Richelieu",
    "qs:name_local":"Mont-St.-Hilaire",
    "qs:photo_max":25,
    "qs:photo_sum":200,
    "qs:placetype":"Suburb",
    "qs:quad_count":30,
    "qs:woe_adm0":23424775,
    "qs:woe_adm1":2344924,
    "qs:woe_adm2":29375217,
    "qs:woe_lau":0,
    "qs:woe_local":1021,
    "qs:woe_ver":"7.10.0",
    "wof:lang":[
        "fre"
    ],
    "wof:name":"Centre Ville",
    "wof:placetype":"neighbourhood"
},
  "geometry": {"coordinates":[-73.18951800000001,45.565006],"type":"Point"}
}