{
  "type": "Feature",
  "properties": {
    "gn:country":"CA",
    "gn:fcode":"PPL",
    "gn:pop":2940,
    "gn:population":2940,
    "iso:country":"CA",
    "name:eng_x_preferred":[
        "Botwood"
    ],
    "qs:name":"Botwood",
    "qs:name_adm0":"Canada",
    "qs:name_adm1":"Newfoundland and Labrador",
    "qs:photos":125,
    "qs:photos_1k":25,
    "qs:photos_9k":1,
    "qs:photos_9r":3,
    "qs:photos_all":125,
    "qs:photos_sr":3,
    "qs:placetype":"Town",
    "qs:pop_sr":"4",
    "wd:elevation":41.0,
    "wd:wordcount":467,
    "wof:name":"Botwood",
    "wof:placetype":"locality",
    "wof:population":2940
},
  "geometry": {"coordinates":[-55.34819,49.14994],"type":"Point"}
}