{
  "type": "Feature",
  "properties": {
    "gn:admin1_code":"10.0",
    "gn:admin2_code":"5.0",
    "gn:admin3_code":"30040.0",
    "gn:asciiname":"Domaine-Donald-Morrison",
    "gn:country_code":"CA",
    "gn:dem":520,
    "gn:feature_class":"P",
    "gn:feature_code":"PPL",
    "gn:name":"Domaine-Donald-Morrison",
    "gn:population":0,
    "gn:timezone":"America/Toronto",
    "iso:country":"CA",
    "wof:name":"Domaine-Donald-Morrison",
    "wof:placetype":"locality"
},
  "geometry": {"coordinates":[-71.13758,45.60143],"type":"Point"}
}