{
  "type": "Feature",
  "properties": {
    "gn:admin1_code":"8",
    "gn:asciiname":"Errettsville",
    "gn:country_code":"CA",
    "gn:dem":205,
    "gn:feature_class":"P",
    "gn:feature_code":"PPL",
    "gn:name":"Errettsville",
    "gn:population":0,
    "gn:timezone":"America/Toronto",
    "iso:country":"CA",
    "wof:name":"Errettsville",
    "wof:placetype":"locality"
},
  "geometry": {"coordinates":[-79.86740999999998,47.83127],"type":"Point"}
}