{
  "type": "Feature",
  "properties": {
    "gn:admin1_code":"8.0",
    "gn:asciiname":"Downie",
    "gn:country_code":"CA",
    "gn:dem":360,
    "gn:feature_class":"P",
    "gn:feature_code":"PPL",
    "gn:name":"Downie",
    "gn:population":0,
    "gn:timezone":"America/Toronto",
    "iso:country":"CA",
    "wof:name":"Downie",
    "wof:placetype":"locality"
},
  "geometry": {"coordinates":[-81.04973000000003,43.33339],"type":"Point"}
}