{
  "type": "Feature",
  "properties": {
    "gn:admin1_code":"8.0",
    "gn:asciiname":"Canning",
    "gn:country_code":"CA",
    "gn:dem":254,
    "gn:feature_class":"P",
    "gn:feature_code":"PPL",
    "gn:name":"Canning",
    "gn:population":0,
    "gn:timezone":"America/Toronto",
    "iso:country":"CA",
    "name:ara_x_preferred":[
        "\u062a\u0639\u0644\u064a\u0628"
    ],
    "name:aze_x_preferred":[
        "Konserv"
    ],
    "name:bel_x_preferred":[
        "\u041a\u0430\u043d\u0441\u0435\u0440\u0432\u044b"
    ],
    "name:ces_x_preferred":[
        "Konzerva"
    ],
    "name:epo_x_preferred":[
        "Sterilvakuigo"
    ],
    "name:eus_x_preferred":[
        "Ontziratze"
    ],
    "name:fas_x_preferred":[
        "\u06a9\u0646\u0633\u0631\u0648\u0633\u0627\u0632\u06cc"
    ],
    "name:fin_x_preferred":[
        "S\u00e4ilyke"
    ],
    "name:fra_x_preferred":[
        "Conserve"
    ],
    "name:gle_x_preferred":[
        "Cann\u00fa"
    ],
    "name:heb_x_preferred":[
        "\u05e9\u05d9\u05de\u05d5\u05e8\u05d9\u05dd"
    ],
    "name:hrv_x_preferred":[
        "Konzerva"
    ],
    "name:hye_x_preferred":[
        "\u054a\u0561\u0570\u0561\u056e\u0578\u0575\u0561\u0581\u0578\u0582\u0574"
    ],
    "name:ind_x_preferred":[
        "Pengalengan"
    ],
    "name:isl_x_preferred":[
        "Ni\u00f0ursu\u00f0a"
    ],
    "name:kaz_x_preferred":[
        "\u041a\u043e\u043d\u0441\u0435\u0440\u0432\u0456\u043b\u0435\u0440"
    ],
    "name:kir_x_preferred":[
        "\u041a\u043e\u043d\u0441\u0435\u0440\u0432\u0430\u043b\u0430\u0440"
    ],
    "name:kor_x_preferred":[
        "\ud1b5\uc870\ub9bc"
    ],
    "name:msa_x_preferred":[
        "Pengetinan"
    ],
    "name:mya_x_preferred":[
        "\u1005\u100a\u103a\u101e\u103d\u1010\u103a\u1001\u103c\u1004\u103a\u1038"
    ],
    "name:nor_x_preferred":[
        "Hermetisering"
    ],
    "name:pol_x_preferred":[
        "Konserwa"
    ],
    "name:rus_x_preferred":[
        "\u041a\u043e\u043d\u0441\u0435\u0440\u0432\u044b"
    ],
    "name:spa_x_preferred":[
        "Envasado"
    ],
    "name:swe_x_preferred":[
        "Hermetisering"
    ],
    "name:tgl_x_preferred":[
        "Paglalata"
    ],
    "name:tur_x_preferred":[
        "Konserve"
    ],
    "name:ukr_x_preferred":[
        "\u041a\u043e\u043d\u0441\u0435\u0440\u0432\u0438"
    ],
    "name:vie_x_preferred":[
        "\u0110\u00f3ng h\u1ed9p"
    ],
    "name:war_x_preferred":[
        "Paglalata"
    ],
    "name:zho_x_preferred":[
        "\u7f50\u88dd\u98df\u54c1"
    ],
    "wof:name":"Canning",
    "wof:placetype":"locality"
},
  "geometry": {"coordinates":[-80.46805999999999,43.19583],"type":"Point"}
}