{
  "type": "Feature",
  "properties": {
    "gn:admin1_code":"8.0",
    "gn:asciiname":"Canning",
    "gn:country_code":"CA",
    "gn:dem":254,
    "gn:feature_class":"P",
    "gn:feature_code":"PPL",
    "gn:name":"Canning",
    "gn:population":0,
    "gn:timezone":"America/Toronto",
    "iso:country":"CA",
    "wof:name":"Canning",
    "wof:placetype":"locality"
},
  "geometry": {"coordinates":[-80.46805999999999,43.19583],"type":"Point"}
}