{
  "type": "Feature",
  "properties": {
    "gn:admin1_code":"3",
    "gn:asciiname":"Highland Glen",
    "gn:country_code":"CA",
    "gn:dem":237,
    "gn:feature_class":"P",
    "gn:feature_code":"PPLL",
    "gn:name":"Highland Glen",
    "gn:population":0,
    "gn:timezone":"America/Winnipeg",
    "iso:country":"CA",
    "wof:name":"Highland Glen",
    "wof:placetype":"locality"
},
  "geometry": {"coordinates":[-96.78501,50.0778],"type":"Point"}
}