{
  "type": "Feature",
  "properties": {
    "gn:admin1_code":"10",
    "gn:admin2_code":"07",
    "gn:admin3_code":"84082.0",
    "gn:asciiname":"Ryan's Corner",
    "gn:country_code":"CA",
    "gn:dem":114,
    "gn:feature_class":"P",
    "gn:feature_code":"PPL",
    "gn:name":"Ryan's Corner",
    "gn:population":0,
    "gn:timezone":"America/Toronto",
    "iso:country":"CA",
    "wof:name":"Ryan's Corner",
    "wof:placetype":"locality"
},
  "geometry": {"coordinates":[-76.94389,45.8275],"type":"Point"}
}