{
  "type": "Feature",
  "properties": {
    "gn:admin1_code":"7",
    "gn:asciiname":"Valley Cross Roads",
    "gn:country_code":"CA",
    "gn:dem":63,
    "gn:feature_class":"P",
    "gn:feature_code":"PPL",
    "gn:name":"Valley Cross Roads",
    "gn:population":0,
    "gn:timezone":"America/Halifax",
    "iso:country":"CA",
    "wof:name":"Valley Cross Roads",
    "wof:placetype":"locality"
},
  "geometry": {"coordinates":[-63.20409,45.39266],"type":"Point"}
}