{
  "type": "Feature",
  "properties": {
    "gn:admin1_code":"3.0",
    "gn:asciiname":"Blumengart",
    "gn:country_code":"CA",
    "gn:dem":257,
    "gn:feature_class":"P",
    "gn:feature_code":"PPLL",
    "gn:name":"Blumengart",
    "gn:population":0,
    "gn:timezone":"America/Winnipeg",
    "iso:country":"CA",
    "wof:name":"Blumengart",
    "wof:placetype":"locality"
},
  "geometry": {"coordinates":[-97.79653,49.13279],"type":"Point"}
}