{
  "type": "Feature",
  "properties": {
    "gn:admin1_code":"8",
    "gn:asciiname":"Oranmore",
    "gn:country_code":"CA",
    "gn:dem":298,
    "gn:feature_class":"P",
    "gn:feature_code":"PPL",
    "gn:name":"Oranmore",
    "gn:population":0,
    "gn:timezone":"America/Toronto",
    "iso:country":"CA",
    "wof:name":"Oranmore",
    "wof:placetype":"locality"
},
  "geometry": {"coordinates":[-79.70416999999998,45.58167],"type":"Point"}
}