{
  "type": "Feature",
  "properties": {
    "gn:admin1_code":"8",
    "gn:asciiname":"Oranmore",
    "gn:country_code":"CA",
    "gn:dem":298,
    "gn:feature_class":"P",
    "gn:feature_code":"PPL",
    "gn:name":"Oranmore",
    "gn:population":0,
    "gn:timezone":"America/Toronto",
    "iso:country":"CA",
    "name:bul_x_preferred":[
        "\u041e\u0440\u0430\u043d\u043c\u043e\u0440"
    ],
    "name:ceb_x_preferred":[
        "Oranmore"
    ],
    "name:dan_x_preferred":[
        "Oranmore"
    ],
    "name:deu_x_preferred":[
        "Oranmore"
    ],
    "name:epo_x_preferred":[
        "Oranmore"
    ],
    "name:eus_x_preferred":[
        "Oranmore"
    ],
    "name:fra_x_preferred":[
        "Oranmore"
    ],
    "name:gle_x_preferred":[
        "\u00d3r\u00e1n M\u00f3r"
    ],
    "name:glg_x_preferred":[
        "Oranmore"
    ],
    "name:ita_x_preferred":[
        "Oranmore"
    ],
    "name:kat_x_preferred":[
        "\u10dd\u10e0\u10d0\u10dc\u10db\u10dd\u10e0\u10d8"
    ],
    "name:nld_x_preferred":[
        "Oranmore"
    ],
    "name:nor_x_preferred":[
        "Oranmore"
    ],
    "name:pol_x_preferred":[
        "Oranmore"
    ],
    "name:rus_x_preferred":[
        "\u041e\u0440\u0430\u043d\u043c\u043e\u0440"
    ],
    "name:spa_x_preferred":[
        "Oranmore"
    ],
    "name:swe_x_preferred":[
        "Oranmore"
    ],
    "wof:name":"Oranmore",
    "wof:placetype":"locality"
},
  "geometry": {"coordinates":[-79.70416999999998,45.58167],"type":"Point"}
}