{
  "type": "Feature",
  "properties": {
    "gn:admin1_code":"8",
    "gn:asciiname":"Manitou Falls",
    "gn:country_code":"CA",
    "gn:dem":332,
    "gn:feature_class":"P",
    "gn:feature_code":"PPL",
    "gn:name":"Manitou Falls",
    "gn:population":0,
    "gn:timezone":"America/Winnipeg",
    "iso:country":"CA",
    "wof:name":"Manitou Falls",
    "wof:placetype":"locality"
},
  "geometry": {"coordinates":[-93.46611,50.58222],"type":"Point"}
}