{
  "type": "Feature",
  "properties": {
    "gn:admin1_code":"4",
    "gn:asciiname":"Garnett Settlement",
    "gn:country_code":"CA",
    "gn:dem":81,
    "gn:feature_class":"P",
    "gn:feature_code":"PPL",
    "gn:name":"Garnett Settlement",
    "gn:population":0,
    "gn:timezone":"America/Moncton",
    "iso:country":"CA",
    "wof:name":"Garnett Settlement",
    "wof:placetype":"locality"
},
  "geometry": {"coordinates":[-65.84923000000001,45.30725],"type":"Point"}
}