{
  "type": "Feature",
  "properties": {
    "gn:admin1_code":"5",
    "gn:asciiname":"Seldom-Little Seldom",
    "gn:country_code":"CA",
    "gn:dem":10,
    "gn:feature_class":"P",
    "gn:feature_code":"PPL",
    "gn:name":"Seldom-Little Seldom",
    "gn:population":0,
    "gn:timezone":"America/St_Johns",
    "iso:country":"CA",
    "name:fra_x_preferred":[
        "Seldom-Little Seldom"
    ],
    "wof:name":"Seldom-Little Seldom",
    "wof:placetype":"locality"
},
  "geometry": {"coordinates":[-54.19812,49.59992],"type":"Point"}
}