{
  "type": "Feature",
  "properties": {
    "gn:admin1_code":"8",
    "gn:asciiname":"Minet's Point",
    "gn:country_code":"CA",
    "gn:dem":222,
    "gn:feature_class":"P",
    "gn:feature_code":"PPL",
    "gn:name":"Minet's Point",
    "gn:population":0,
    "gn:timezone":"America/Toronto",
    "iso:country":"CA",
    "wof:name":"Minet's Point",
    "wof:placetype":"locality"
},
  "geometry": {"coordinates":[-79.66573000000002,44.37469],"type":"Point"}
}