{
  "type": "Feature",
  "properties": {
    "gn:admin1_code":"1",
    "gn:asciiname":"Moon Lake",
    "gn:country_code":"CA",
    "gn:dem":810,
    "gn:feature_class":"P",
    "gn:feature_code":"PPLL",
    "gn:name":"Moon Lake",
    "gn:population":0,
    "gn:timezone":"America/Edmonton",
    "iso:country":"CA",
    "name:ceb_x_preferred":[
        "Moon Lake"
    ],
    "name:swe_x_preferred":[
        "Moon Lake"
    ],
    "wof:name":"Moon Lake",
    "wof:placetype":"locality"
},
  "geometry": {"coordinates":[-114.95213,53.45013],"type":"Point"}
}