{
  "type": "Feature",
  "properties": {
    "gn:admin1_code":"11",
    "gn:asciiname":"Reliance",
    "gn:country_code":"CA",
    "gn:dem":948,
    "gn:feature_class":"P",
    "gn:feature_code":"PPLL",
    "gn:name":"Reliance",
    "gn:population":0,
    "gn:timezone":"America/Regina",
    "iso:country":"CA",
    "name:cat_x_preferred":[
        "Reliance"
    ],
    "name:ceb_x_preferred":[
        "Reliance"
    ],
    "name:deu_x_preferred":[
        "Reliance"
    ],
    "name:fra_x_preferred":[
        "Reliance"
    ],
    "name:ita_x_preferred":[
        "Reliance"
    ],
    "name:nep_x_preferred":[
        "\u0930\u093f\u0932\u093e\u092f\u0902\u0938"
    ],
    "name:nld_x_preferred":[
        "Reliance"
    ],
    "name:pol_x_preferred":[
        "Reliance"
    ],
    "name:srp_x_preferred":[
        "\u0420\u0438\u043b\u0430\u0458\u0430\u043d\u0441"
    ],
    "name:swe_x_preferred":[
        "Reliance"
    ],
    "name:vol_x_preferred":[
        "Reliance"
    ],
    "wof:name":"Reliance",
    "wof:placetype":"locality"
},
  "geometry": {"coordinates":[-107.31796,49.35005],"type":"Point"}
}