{
  "type": "Feature",
  "properties": {
    "gn:admin1_code":"3",
    "gn:asciiname":"Kingsley",
    "gn:country_code":"CA",
    "gn:dem":480,
    "gn:feature_class":"P",
    "gn:feature_code":"PPLL",
    "gn:name":"Kingsley",
    "gn:population":0,
    "gn:timezone":"America/Winnipeg",
    "iso:country":"CA",
    "wof:name":"Kingsley",
    "wof:placetype":"locality"
},
  "geometry": {"coordinates":[-98.70329,49.33811],"type":"Point"}
}