{
  "type": "Feature",
  "properties": {
    "gn:admin1_code":"3",
    "gn:asciiname":"Kingsley",
    "gn:country_code":"CA",
    "gn:dem":480,
    "gn:feature_class":"P",
    "gn:feature_code":"PPLL",
    "gn:name":"Kingsley",
    "gn:population":0,
    "gn:timezone":"America/Winnipeg",
    "iso:country":"CA",
    "name:ara_x_preferred":[
        "\u0643\u064a\u0646\u063a\u0633\u0644\u064a"
    ],
    "name:ceb_x_preferred":[
        "Kingsley"
    ],
    "name:ces_x_preferred":[
        "Kingsley"
    ],
    "name:deu_x_preferred":[
        "Kingsley"
    ],
    "name:epo_x_preferred":[
        "Kingsley"
    ],
    "name:fas_x_preferred":[
        "\u06a9\u06cc\u0646\u06af\u0632\u0644\u06cc"
    ],
    "name:fin_x_preferred":[
        "Kingsley"
    ],
    "name:fra_x_preferred":[
        "Kingsley"
    ],
    "name:heb_x_preferred":[
        "\u05e7\u05d9\u05e0\u05d2\u05e1\u05dc\u05d9"
    ],
    "name:ita_x_preferred":[
        "Kingsley"
    ],
    "name:jpn_x_preferred":[
        "\u30ad\u30f3\u30b0\u30ba\u30ea\u30fc"
    ],
    "name:kor_x_preferred":[
        "\ud0b9\uc990\ub9ac"
    ],
    "name:nld_x_preferred":[
        "Kingsley"
    ],
    "name:pol_x_preferred":[
        "Kingsley"
    ],
    "name:por_x_preferred":[
        "Kingsley"
    ],
    "name:ron_x_preferred":[
        "Kingsley"
    ],
    "name:slk_x_preferred":[
        "Kingsley"
    ],
    "name:spa_x_preferred":[
        "Kingsley"
    ],
    "name:srp_x_preferred":[
        "\u041a\u0438\u043d\u0433\u0441\u043b\u0438"
    ],
    "name:swe_x_preferred":[
        "Kingsley"
    ],
    "name:ukr_x_preferred":[
        "\u041a\u0456\u043d\u0433\u0441\u043b\u0456"
    ],
    "name:vol_x_preferred":[
        "Kingsley"
    ],
    "wof:name":"Kingsley",
    "wof:placetype":"locality"
},
  "geometry": {"coordinates":[-98.70329,49.33811],"type":"Point"}
}