{
  "type": "Feature",
  "properties": {
    "gn:admin1_code":"10.0",
    "gn:admin2_code":"05",
    "gn:admin3_code":"44037.0",
    "gn:asciiname":"Barford",
    "gn:country_code":"CA",
    "gn:dem":291,
    "gn:feature_class":"P",
    "gn:feature_code":"PPL",
    "gn:name":"Barford",
    "gn:population":0,
    "gn:timezone":"America/Toronto",
    "iso:country":"CA",
    "wof:name":"Barford",
    "wof:placetype":"locality"
},
  "geometry": {"coordinates":[-71.79509,45.11616],"type":"Point"}
}