{
  "type": "Feature",
  "properties": {
    "gn:admin1_code":"9",
    "gn:asciiname":"Green Bay",
    "gn:country_code":"CA",
    "gn:dem":55,
    "gn:feature_class":"P",
    "gn:feature_code":"PPLL",
    "gn:name":"Green Bay",
    "gn:population":0,
    "gn:timezone":"America/Halifax",
    "iso:country":"CA",
    "wof:name":"Green Bay",
    "wof:placetype":"locality"
},
  "geometry": {"coordinates":[-63.3654,46.25012],"type":"Point"}
}