{
  "type": "Feature",
  "properties": {
    "gn:admin1_code":"7.0",
    "gn:asciiname":"Burntcoat",
    "gn:country_code":"CA",
    "gn:dem":30,
    "gn:feature_class":"P",
    "gn:feature_code":"PPL",
    "gn:name":"Burntcoat",
    "gn:population":0,
    "gn:timezone":"America/Halifax",
    "iso:country":"CA",
    "wof:name":"Burntcoat",
    "wof:placetype":"locality"
},
  "geometry": {"coordinates":[-63.78973000000001,45.31204],"type":"Point"}
}