{
  "type": "Feature",
  "properties": {
    "gn:admin1_code":"8",
    "gn:asciiname":"Renton",
    "gn:country_code":"CA",
    "gn:dem":221,
    "gn:feature_class":"P",
    "gn:feature_code":"PPL",
    "gn:name":"Renton",
    "gn:population":0,
    "gn:timezone":"America/Toronto",
    "iso:country":"CA",
    "name:ceb_x_preferred":[
        "Renton"
    ],
    "name:deu_x_preferred":[
        "Renton"
    ],
    "name:fra_x_preferred":[
        "Renton"
    ],
    "name:ita_x_preferred":[
        "Renton"
    ],
    "name:pol_x_preferred":[
        "Renton"
    ],
    "name:por_x_preferred":[
        "Renton"
    ],
    "name:rus_x_preferred":[
        "\u0420\u0435\u043d\u0442\u043e\u043d"
    ],
    "name:swe_x_preferred":[
        "Renton"
    ],
    "wof:name":"Renton",
    "wof:placetype":"locality"
},
  "geometry": {"coordinates":[-80.22169,42.86039],"type":"Point"}
}