{
  "type": "Feature",
  "properties": {
    "gn:admin1_code":"2.0",
    "gn:asciiname":"Brandon",
    "gn:country_code":"CA",
    "gn:dem":737,
    "gn:feature_class":"P",
    "gn:feature_code":"PPL",
    "gn:name":"Brandon",
    "gn:population":0,
    "gn:timezone":"America/Vancouver",
    "iso:country":"CA",
    "name:bre_x_preferred":[
        "Brandon"
    ],
    "name:cat_x_preferred":[
        "Brandon"
    ],
    "name:ceb_x_preferred":[
        "Brandon"
    ],
    "name:ces_x_preferred":[
        "Brandon"
    ],
    "name:deu_x_preferred":[
        "Brandon"
    ],
    "name:eus_x_preferred":[
        "Brandon"
    ],
    "name:fin_x_preferred":[
        "Brandon"
    ],
    "name:fra_x_preferred":[
        "Brandon"
    ],
    "name:hun_x_preferred":[
        "Brandon"
    ],
    "name:ind_x_preferred":[
        "Brandon"
    ],
    "name:ita_x_preferred":[
        "Brandon"
    ],
    "name:jpn_x_preferred":[
        "\u30d6\u30e9\u30f3\u30c9\u30f3"
    ],
    "name:kor_x_preferred":[
        "\ube0c\ub79c\ub358"
    ],
    "name:nld_x_preferred":[
        "Brandon"
    ],
    "name:nor_x_preferred":[
        "Brandon"
    ],
    "name:oci_x_preferred":[
        "Brandon"
    ],
    "name:pol_x_preferred":[
        "Brandon"
    ],
    "name:por_x_preferred":[
        "Brandon"
    ],
    "name:rus_x_preferred":[
        "\u0411\u0440\u0430\u043d\u0434\u043e\u043d"
    ],
    "name:slk_x_preferred":[
        "Brandon"
    ],
    "name:spa_x_preferred":[
        "Brandon"
    ],
    "name:srp_x_preferred":[
        "\u0411\u0440\u0430\u043d\u0434\u043e\u043d"
    ],
    "name:swe_x_preferred":[
        "Brandon"
    ],
    "name:tur_x_preferred":[
        "Brandon"
    ],
    "name:ukr_x_preferred":[
        "\u0411\u0440\u0430\u043d\u0434\u043e\u043d"
    ],
    "name:urd_x_preferred":[
        "\u0628\u0631\u06cc\u0646\u0688\u0646"
    ],
    "name:vol_x_preferred":[
        "Brandon"
    ],
    "wof:name":"Brandon",
    "wof:placetype":"locality"
},
  "geometry": {"coordinates":[-117.45,49.75],"type":"Point"}
}