{
  "type": "Feature",
  "properties": {
    "iso:country":"CA",
    "name:eng_x_preferred":[
        "Mono Mills"
    ],
    "qs:gn_adm0_cc":"CA",
    "qs:gn_fcode":"PPL",
    "qs:gn_local":5913415,
    "qs:gn_nam_loc":"caledon",
    "qs:gn_namadm1":"08",
    "qs:gn_name":"Mono Mills",
    "qs:local_max":389,
    "qs:local_sum":2625,
    "qs:localhoods":17,
    "qs:name":"Mono Mills",
    "qs:name_adm0":"Canada",
    "qs:name_adm1":"Ontario",
    "qs:name_adm2":"Dufferin",
    "qs:name_local":"Caledon",
    "qs:photo_max":64,
    "qs:photo_sum":119,
    "qs:placetype":"Suburb",
    "qs:quad_count":19,
    "qs:woe_adm0":23424775,
    "qs:woe_adm1":2344922,
    "qs:woe_adm2":29375114,
    "qs:woe_lau":0,
    "qs:woe_local":23396905,
    "qs:woe_ver":"7.10.0",
    "wd:wordcount":14,
    "wof:lang":[
        "eng"
    ],
    "wof:name":"Mono Mills",
    "wof:placetype":"neighbourhood"
},
  "geometry": {"coordinates":[-79.970579,43.952091],"type":"Point"}
}