{
  "type": "Feature",
  "properties": {
    "gn:admin1_code":"2.0",
    "gn:asciiname":"Anniedale",
    "gn:country_code":"CA",
    "gn:dem":22,
    "gn:feature_class":"P",
    "gn:feature_code":"PPL",
    "gn:name":"Anniedale",
    "gn:population":0,
    "gn:timezone":"America/Vancouver",
    "iso:country":"CA",
    "wof:name":"Anniedale",
    "wof:placetype":"locality"
},
  "geometry": {"coordinates":[-122.71666999999999,49.16667],"type":"Point"}
}