{
  "type": "Feature",
  "properties": {
    "gn:admin1_code":"11.0",
    "gn:asciiname":"Artland",
    "gn:country_code":"CA",
    "gn:dem":614,
    "gn:feature_class":"P",
    "gn:feature_code":"PPL",
    "gn:name":"Artland",
    "gn:population":0,
    "gn:timezone":"America/Edmonton",
    "iso:country":"CA",
    "wof:name":"Artland",
    "wof:placetype":"locality"
},
  "geometry": {"coordinates":[-109.8841,52.70008000000001],"type":"Point"}
}