{
  "type": "Feature",
  "properties": {
    "gn:admin1_code":"11.0",
    "gn:asciiname":"Artland",
    "gn:country_code":"CA",
    "gn:dem":614,
    "gn:feature_class":"P",
    "gn:feature_code":"PPL",
    "gn:name":"Artland",
    "gn:population":0,
    "gn:timezone":"America/Edmonton",
    "iso:country":"CA",
    "name:dan_x_preferred":[
        "Samtgemeinde Artland"
    ],
    "name:deu_x_preferred":[
        "Samtgemeinde Artland"
    ],
    "name:epo_x_preferred":[
        "Samtgemeinde Artland"
    ],
    "name:est_x_preferred":[
        "Samtgemeinde Artland"
    ],
    "name:fas_x_preferred":[
        "\u0622\u0631\u062a\u0644\u0627\u0646\u062f"
    ],
    "name:fra_x_preferred":[
        "Samtgemeinde Artland"
    ],
    "name:ita_x_preferred":[
        "Samtgemeinde Artland"
    ],
    "name:jpn_x_preferred":[
        "\u30b6\u30e0\u30c8\u30b2\u30de\u30a4\u30f3\u30c7\u30fb\u30a2\u30eb\u30c8\u30e9\u30f3\u30c8"
    ],
    "name:msa_x_preferred":[
        "Artland"
    ],
    "name:nds_x_preferred":[
        "Samtgemeen Artland"
    ],
    "name:nld_x_preferred":[
        "Samtgemeinde Artland"
    ],
    "wof:name":"Artland",
    "wof:placetype":"locality"
},
  "geometry": {"coordinates":[-109.8841,52.70008000000001],"type":"Point"}
}