{
  "type": "Feature",
  "properties": {
    "gn:admin1_code":"7.0",
    "gn:asciiname":"Brooklyn Corner",
    "gn:country_code":"CA",
    "gn:dem":25,
    "gn:feature_class":"P",
    "gn:feature_code":"PPL",
    "gn:name":"Brooklyn Corner",
    "gn:population":0,
    "gn:timezone":"America/Halifax",
    "iso:country":"CA",
    "wof:name":"Brooklyn Corner",
    "wof:placetype":"locality"
},
  "geometry": {"coordinates":[-64.57791999999999,45.08849],"type":"Point"}
}