{
  "type": "Feature",
  "properties": {
    "iso:country":"CA",
    "name:deu_x_preferred":[
        "Lafontaine"
    ],
    "name:fra_x_preferred":[
        "Lafontaine"
    ],
    "name:nds_x_preferred":[
        "Lafontaine"
    ],
    "name:rus_x_preferred":[
        "\u041b\u0430\u0444\u043e\u043d\u0442\u0435\u043d"
    ],
    "name:swe_x_preferred":[
        "Lafontaine"
    ],
    "name:tur_x_preferred":[
        "Lafontaine"
    ],
    "qs_pg:aaroncc":"CA",
    "qs_pg:name":"Lafontaine",
    "qs_pg:name_adm0":"Canada",
    "qs_pg:name_adm1":"Qu\u00e9bec",
    "qs_pg:photos":32,
    "qs_pg:photos_1k":6,
    "qs_pg:photos_9k":1,
    "qs_pg:photos_9r":2,
    "qs_pg:photos_all":32,
    "qs_pg:photos_sr":2,
    "qs_pg:pop_sr":0,
    "qs_pg:qs_pg_placetype":"locality",
    "qs_pg:qs_pg_placetype_gp":"Town",
    "qs_pg:woe_adm0":23424775,
    "woe:adm0_id":23424775,
    "woe:name_adm0":"Canada",
    "woe:name_adm1":"Qu\u00e9bec",
    "woe:placetype":"Town",
    "wof:name":"Lafontaine",
    "wof:placetype":"locality"
},
  "geometry": {"coordinates":[-74.0098845,45.803913],"type":"Point"}
}