{
  "type": "Feature",
  "properties": {
    "gn:admin1_code":"1",
    "gn:asciiname":"Kenzie",
    "gn:country_code":"CA",
    "gn:dem":631,
    "gn:feature_class":"P",
    "gn:feature_code":"PPLL",
    "gn:name":"Kenzie",
    "gn:population":0,
    "gn:timezone":"America/Edmonton",
    "iso:country":"CA",
    "wof:name":"Kenzie",
    "wof:placetype":"locality"
},
  "geometry": {"coordinates":[-116.75254,55.51678],"type":"Point"}
}