{
  "type": "Feature",
  "properties": {
    "gn:admin1_code":"1",
    "gn:asciiname":"Spring Coulee",
    "gn:country_code":"CA",
    "gn:dem":1088,
    "gn:feature_class":"P",
    "gn:feature_code":"PPL",
    "gn:name":"Spring Coulee",
    "gn:population":0,
    "gn:timezone":"America/Edmonton",
    "iso:country":"CA",
    "name:fra_x_preferred":[
        "Spring Coulee"
    ],
    "wof:name":"Spring Coulee",
    "wof:placetype":"locality"
},
  "geometry": {"coordinates":[-113.05167,49.33444],"type":"Point"}
}