{
  "type": "Feature",
  "properties": {
    "gn:admin1_code":"2",
    "gn:asciiname":"Muskwa",
    "gn:country_code":"CA",
    "gn:dem":302,
    "gn:feature_class":"P",
    "gn:feature_code":"PPLL",
    "gn:name":"Muskwa",
    "gn:population":0,
    "gn:timezone":"America/Fort_Nelson",
    "iso:country":"CA",
    "wof:name":"Muskwa",
    "wof:placetype":"locality"
},
  "geometry": {"coordinates":[-122.69468999999999,58.76083000000001],"type":"Point"}
}