{
  "type": "Feature",
  "properties": {
    "gn:admin1_code":"8",
    "gn:asciiname":"Wade's Landing",
    "gn:country_code":"CA",
    "gn:dem":196,
    "gn:feature_class":"P",
    "gn:feature_code":"PPL",
    "gn:name":"Wade's Landing",
    "gn:population":0,
    "gn:timezone":"America/Toronto",
    "iso:country":"CA",
    "wof:name":"Wade's Landing",
    "wof:placetype":"locality"
},
  "geometry": {"coordinates":[-79.52835,46.11823],"type":"Point"}
}