{
  "type": "Feature",
  "properties": {
    "gn:admin1_code":"7",
    "gn:asciiname":"Kempt",
    "gn:country_code":"CA",
    "gn:dem":125,
    "gn:feature_class":"P",
    "gn:feature_code":"PPL",
    "gn:name":"Kempt",
    "gn:population":0,
    "gn:timezone":"America/Halifax",
    "iso:country":"CA",
    "wof:name":"Kempt",
    "wof:placetype":"locality"
},
  "geometry": {"coordinates":[-65.12047,44.42882],"type":"Point"}
}