{
  "type": "Feature",
  "properties": {
    "gn:admin1_code":"8",
    "gn:asciiname":"Elder",
    "gn:country_code":"CA",
    "gn:dem":402,
    "gn:feature_class":"P",
    "gn:feature_code":"PPL",
    "gn:name":"Elder",
    "gn:population":0,
    "gn:timezone":"America/Toronto",
    "iso:country":"CA",
    "name:ceb_x_preferred":[
        "Elder"
    ],
    "name:deu_x_preferred":[
        "Elder"
    ],
    "name:eus_x_preferred":[
        "Elder"
    ],
    "name:fra_x_preferred":[
        "Elder"
    ],
    "name:ita_x_preferred":[
        "Elder"
    ],
    "name:jpn_x_preferred":[
        "\u30a8\u30eb\u30c0\u30fc"
    ],
    "name:por_x_preferred":[
        "\u00c9lder"
    ],
    "name:rus_x_preferred":[
        "\u042d\u043b\u0434\u0435\u0440"
    ],
    "name:swe_x_preferred":[
        "Elder"
    ],
    "name:vie_x_preferred":[
        "Tr\u01b0\u1edfng l\u00e3o"
    ],
    "wof:name":"Elder",
    "wof:placetype":"locality"
},
  "geometry": {"coordinates":[-80.05110999999999,44.07155],"type":"Point"}
}