{
  "type": "Feature",
  "properties": {
    "gn:admin1_code":"10",
    "gn:admin2_code":"16",
    "gn:admin3_code":"47035.0",
    "gn:asciiname":"Saxby Corner",
    "gn:country_code":"CA",
    "gn:dem":157,
    "gn:feature_class":"P",
    "gn:feature_code":"PPL",
    "gn:name":"Saxby Corner",
    "gn:population":0,
    "gn:timezone":"America/Toronto",
    "iso:country":"CA",
    "wof:name":"Saxby Corner",
    "wof:placetype":"locality"
},
  "geometry": {"coordinates":[-72.63373,45.38171],"type":"Point"}
}