{
  "type": "Feature",
  "properties": {
    "gn:admin1_code":"4",
    "gn:asciiname":"South Saint-Norbert",
    "gn:country_code":"CA",
    "gn:dem":55,
    "gn:feature_class":"P",
    "gn:feature_code":"PPL",
    "gn:name":"South Saint-Norbert",
    "gn:population":0,
    "gn:timezone":"America/Moncton",
    "iso:country":"CA",
    "wof:name":"South Saint-Norbert",
    "wof:placetype":"locality"
},
  "geometry": {"coordinates":[-64.95029,46.4507],"type":"Point"}
}