{
  "type": "Feature",
  "properties": {
    "gn:admin1_code":"11.0",
    "gn:asciiname":"Congress",
    "gn:country_code":"CA",
    "gn:dem":720,
    "gn:feature_class":"P",
    "gn:feature_code":"PPLL",
    "gn:name":"Congress",
    "gn:population":0,
    "gn:timezone":"America/Regina",
    "iso:country":"CA",
    "wof:name":"Congress",
    "wof:placetype":"locality"
},
  "geometry": {"coordinates":[-106.01786,49.76676],"type":"Point"}
}