{
  "type": "Feature",
  "properties": {
    "iso:country":"CA",
    "name:eng_x_preferred":[
        "Walkerville"
    ],
    "name:eng_x_variant":[
        "Sainte-Doroth\u00e9e"
    ],
    "name:fra_x_preferred":[
        "Walkerville"
    ],
    "name:nld_x_preferred":[
        "Walkerville"
    ],
    "name:zho_x_preferred":[
        "\u6c83\u514b\u7ef4\u5c14"
    ],
    "wd:wordcount":700,
    "wof:lang":[
        "eng"
    ],
    "wof:name":"Walkerville",
    "wof:placetype":"neighbourhood"
},
  "geometry": {"coordinates":[-83.015807,42.314574],"type":"Point"}
}