{
  "type": "Feature",
  "properties": {
    "gn:country":"CA",
    "gn:fcode":"PPL",
    "gn:population":0,
    "iso:country":"CA",
    "name:bar_x_preferred":[
        "Sunnyside"
    ],
    "name:ceb_x_preferred":[
        "Sunnyside"
    ],
    "name:deu_x_preferred":[
        "Sunnyside"
    ],
    "name:eng_x_preferred":[
        "Sunnyside"
    ],
    "name:fra_x_preferred":[
        "Sunnyside"
    ],
    "name:ita_x_preferred":[
        "Sunnyside"
    ],
    "name:kor_x_preferred":[
        "\uc11c\ub2c8\uc0ac\uc774\ub4dc"
    ],
    "name:nld_x_preferred":[
        "Sunnyside"
    ],
    "name:pol_x_preferred":[
        "Sunnyside"
    ],
    "name:por_x_preferred":[
        "Sunnyside"
    ],
    "name:rus_x_preferred":[
        "\u0421\u0430\u043d\u043d\u0438\u0441\u0430\u0439\u0434"
    ],
    "name:spa_x_preferred":[
        "Sunnyside"
    ],
    "name:srp_x_preferred":[
        "\u0421\u0430\u043d\u0438\u0441\u0430\u0458\u0434"
    ],
    "name:swe_x_preferred":[
        "Sunnyside"
    ],
    "name:vol_x_preferred":[
        "Sunnyside"
    ],
    "qs:name":"Sunnyside",
    "qs:name_adm0":"Canada",
    "qs:name_adm1":"Newfoundland and Labrador",
    "qs:photos":17,
    "qs:photos_1k":3,
    "qs:photos_9k":1,
    "qs:photos_9r":1,
    "qs:photos_all":17,
    "qs:photos_sr":1,
    "qs:placetype":"Town",
    "qs:pop_sr":"4",
    "wd:wordcount":607,
    "wof:name":"Sunnyside",
    "wof:placetype":"locality",
    "wof:population":0
},
  "geometry": {"coordinates":[-53.91483,47.8555],"type":"Point"}
}