{
  "type": "Feature",
  "properties": {
    "gn:country":"CA",
    "gn:fcode":"PPL",
    "gn:pop":0,
    "iso:country":"CA",
    "name:eng_x_preferred":[
        "Sunnyside"
    ],
    "qs:name":"Sunnyside",
    "qs:name_adm0":"Canada",
    "qs:name_adm1":"Newfoundland and Labrador",
    "qs:photos":17,
    "qs:photos_1k":3,
    "qs:photos_9k":1,
    "qs:photos_9r":1,
    "qs:photos_all":17,
    "qs:photos_sr":1,
    "qs:placetype":"Town",
    "qs:pop_sr":"4",
    "wd:wordcount":607,
    "wof:name":"Sunnyside",
    "wof:placetype":"locality",
    "wof:population":0
},
  "geometry": {"coordinates":[-53.91483,47.8555],"type":"Point"}
}