{
  "type": "Feature",
  "properties": {
    "iso:country":"CA",
    "name:eng_x_preferred":[
        "Ridgetown"
    ],
    "name:nld_x_preferred":[
        "Ridgetown"
    ],
    "name:unk_x_variant":[
        "Ridgetown"
    ],
    "name:zho_x_preferred":[
        "\u91cc\u5947\u6566"
    ],
    "qs:gn_adm0_cc":"CA",
    "qs:gn_fcode":"PPL",
    "qs:gn_local":5920450,
    "qs:gn_nam_loc":"chatham-kent",
    "qs:gn_namadm1":"08",
    "qs:gn_name":"Ridgetown",
    "qs:local_max":1574,
    "qs:local_sum":4054,
    "qs:localhoods":11,
    "qs:name":"Ridgetown",
    "qs:name_adm0":"Canada",
    "qs:name_adm1":"Ontario",
    "qs:name_adm2":"Chatham-Kent",
    "qs:name_local":"Chatham-Kent",
    "qs:photo_max":17,
    "qs:photo_sum":62,
    "qs:placetype":"Suburb",
    "qs:quad_count":18,
    "qs:woe_adm0":23424775,
    "qs:woe_adm1":2344922,
    "qs:woe_adm2":29375096,
    "qs:woe_funk":"Parented by a neighborhood",
    "qs:woe_lau":0,
    "qs:woe_local":29374182,
    "qs:woe_ver":"7.10.0",
    "wd:wordcount":886,
    "wof:lang":[
        "eng"
    ],
    "wof:name":"Ridgetown",
    "wof:placetype":"neighbourhood"
},
  "geometry": {"coordinates":[-81.887393,42.437451],"type":"Point"}
}