{
  "type": "Feature",
  "properties": {
    "gn:admin1_code":"8",
    "gn:asciiname":"Sixty-Nine Corners",
    "gn:country_code":"CA",
    "gn:dem":218,
    "gn:feature_class":"P",
    "gn:feature_code":"PPLL",
    "gn:name":"Sixty-Nine Corners",
    "gn:population":0,
    "gn:timezone":"America/Toronto",
    "iso:country":"CA",
    "wof:name":"Sixty-Nine Corners",
    "wof:placetype":"locality"
},
  "geometry": {"coordinates":[-80.13905,43.03571],"type":"Point"}
}