{
  "type": "Feature",
  "properties": {
    "gn:gn_country":"CA",
    "gn:gn_fcode":"PPL",
    "gn:gn_pop":0,
    "iso:country":"CA",
    "name:deu_x_preferred":[
        "Ham-Sud"
    ],
    "name:eng_x_preferred":[
        "Ham-Sud"
    ],
    "name:eus_x_preferred":[
        "Ham-Sud"
    ],
    "name:fas_x_preferred":[
        "\u0622\u0645-\u0633\u0648\u062f\u060c \u06a9\u0628\u06a9"
    ],
    "name:fra_x_preferred":[
        "Ham-Sud"
    ],
    "name:nld_x_preferred":[
        "Ham-Sud"
    ],
    "name:por_x_preferred":[
        "Ham-Sud"
    ],
    "name:spa_x_preferred":[
        "Ham-Sud"
    ],
    "name:swe_x_preferred":[
        "Ham-Sud"
    ],
    "qs_pg:aaroncc":"CA",
    "qs_pg:gn_country":"CA",
    "qs_pg:gn_fcode":"PPL",
    "qs_pg:gn_pop":0,
    "qs_pg:name":"St.-Joseph-de-Ham-Sud",
    "qs_pg:name_adm0":"Canada",
    "qs_pg:name_adm1":"Qu\u00e9bec",
    "qs_pg:photos":168,
    "qs_pg:photos_1k":34,
    "qs_pg:photos_9k":1,
    "qs_pg:photos_9r":4,
    "qs_pg:photos_all":168,
    "qs_pg:photos_sr":4,
    "qs_pg:pop_sr":0,
    "qs_pg:qs_pg_placetype":"locality",
    "qs_pg:qs_pg_placetype_gp":"Town",
    "qs_pg:woe_adm0":23424775,
    "woe:adm0_id":23424775,
    "woe:name_adm0":"Canada",
    "woe:name_adm1":"Qu\u00e9bec",
    "woe:placetype":"Town",
    "wof:name":"St.-Joseph-de-Ham-Sud",
    "wof:placetype":"locality"
},
  "geometry": {"coordinates":[-71.59908,45.76677],"type":"Point"}
}