{
  "type": "Feature",
  "properties": {
    "gn:country":"CA",
    "gn:fcode":"PPL",
    "gn:pop":0,
    "iso:country":"CA",
    "name:ceb_x_preferred":[
        "Logy Bay-Middle Cove-Outer Cove"
    ],
    "name:eng_x_preferred":[
        "Logy Bay-Middle Cove-Outer Cove"
    ],
    "name:eng_x_variant":[
        "Logy Bay\u2013Middle Cove\u2013Outer Cove"
    ],
    "name:fra_x_preferred":[
        "Logy Bay-Middle Cove-Outer Cove"
    ],
    "name:nld_x_preferred":[
        "Logy Bay-Middle Cove-Outer Cove"
    ],
    "name:swe_x_preferred":[
        "Logy Bay-Middle Cove-Outer Cove"
    ],
    "qs:name":"Logy Bay-Middle Cove-Outer Cove",
    "qs:name_adm0":"Canada",
    "qs:name_adm1":"Newfoundland and Labrador",
    "qs:photos":303,
    "qs:photos_1k":61,
    "qs:photos_9k":1,
    "qs:photos_9r":5,
    "qs:photos_all":303,
    "qs:photos_sr":5,
    "qs:placetype":"Town",
    "qs:pop_sr":"0",
    "wd:wordcount":337,
    "wof:name":"Logy Bay-Middle Cove-Outer Cove",
    "wof:placetype":"locality",
    "wof:population":0
},
  "geometry": {"coordinates":[-52.68134,47.63319],"type":"Point"}
}