{
  "type": "Feature",
  "properties": {
    "gn:admin1_code":"7",
    "gn:asciiname":"Upper Clements",
    "gn:country_code":"CA",
    "gn:dem":22,
    "gn:feature_class":"P",
    "gn:feature_code":"PPL",
    "gn:name":"Upper Clements",
    "gn:population":0,
    "gn:timezone":"America/Halifax",
    "iso:country":"CA",
    "wof:name":"Upper Clements",
    "wof:placetype":"locality"
},
  "geometry": {"coordinates":[-65.5754,44.69919],"type":"Point"}
}