{
  "type": "Feature",
  "properties": {
    "gn:country":"CA",
    "gn:fcode":"PPL",
    "gn:pop":0,
    "iso:country":"CA",
    "name:ara_x_preferred":[
        "\u0633\u062a\u0648\u0631\u0645"
    ],
    "name:bul_x_preferred":[
        "\u0421\u0442\u0440\u043e\u043c\u0435"
    ],
    "name:eng_x_preferred":[
        "Strome"
    ],
    "name:fra_x_preferred":[
        "Strome"
    ],
    "name:nld_x_preferred":[
        "Strome"
    ],
    "name:por_x_preferred":[
        "Strome"
    ],
    "name:spa_x_preferred":[
        "Strome"
    ],
    "name:swe_x_preferred":[
        "Strome"
    ],
    "qs:name":"Strome",
    "qs:name_adm0":"Canada",
    "qs:name_adm1":"Alberta",
    "qs:photos":10,
    "qs:photos_1k":2,
    "qs:photos_9k":1,
    "qs:photos_9r":1,
    "qs:photos_all":10,
    "qs:photos_sr":1,
    "qs:placetype":"Town",
    "qs:pop_sr":"3",
    "wd:wordcount":115,
    "wof:name":"Strome",
    "wof:placetype":"locality",
    "wof:population":0
},
  "geometry": {"coordinates":[-112.0685,52.80014],"type":"Point"}
}