{
  "type": "Feature",
  "properties": {
    "gn:admin1_code":"10.0",
    "gn:admin2_code":"7.0",
    "gn:admin3_code":"84035.0",
    "gn:asciiname":"Duffyville",
    "gn:country_code":"CA",
    "gn:dem":145,
    "gn:feature_class":"P",
    "gn:feature_code":"PPL",
    "gn:name":"Duffyville",
    "gn:population":0,
    "gn:timezone":"America/Toronto",
    "iso:country":"CA",
    "wof:name":"Duffyville",
    "wof:placetype":"locality"
},
  "geometry": {"coordinates":[-76.6725,45.69444],"type":"Point"}
}