{
  "type": "Feature",
  "properties": {
    "iso:country":"CA",
    "name:ara_x_preferred":[
        "\u0627\u0644\u0628\u062d\u064a\u0631\u0629 \u0627\u0644\u062d\u0645\u0631\u0627\u0621"
    ],
    "name:ceb_x_preferred":[
        "Madsen"
    ],
    "name:deu_x_preferred":[
        "Red Lake"
    ],
    "name:eng_x_preferred":[
        "Red Lake"
    ],
    "name:fas_x_preferred":[
        "\u0631\u062f \u0644\u06cc\u06a9"
    ],
    "name:fin_x_preferred":[
        "Red Lake"
    ],
    "name:fra_x_preferred":[
        "Red Lake"
    ],
    "name:jpn_x_preferred":[
        "\u30ec\u30c3\u30c9\u30ec\u30a4\u30af"
    ],
    "name:nld_x_preferred":[
        "Red Lake"
    ],
    "name:pol_x_preferred":[
        "Red Lake"
    ],
    "name:por_x_preferred":[
        "Red Lake"
    ],
    "name:srp_x_preferred":[
        "\u0420\u0435\u0434 \u041b\u0435\u0458\u043a"
    ],
    "name:swe_x_preferred":[
        "Madsen"
    ],
    "name:ukr_x_preferred":[
        "\u0420\u0435\u0434-\u041b\u0435\u0439\u043a"
    ],
    "ne:ADM0CAP":0.0,
    "ne:ADM0NAME":"Canada",
    "ne:ADM0_A3":"CAN",
    "ne:ADM1NAME":"Ontario",
    "ne:ADMIN1_COD":0,
    "ne:CAPALT":0,
    "ne:CHANGED":0,
    "ne:CHECKME":0,
    "ne:COMPARE":0,
    "ne:DIFFASCII":0,
    "ne:ELEVATION":0.0,
    "ne:FEATURECLA":"Populated place",
    "ne:GEONAMEID":-1,
    "ne:GEONAMESNO":"No GeoNames match due to small population, not in GeoNames, or poor NEV placement.",
    "ne:GN_POP":0,
    "ne:GTOPO30":0.0,
    "ne:ISO_A2":"CA",
    "ne:LABELRANK":2,
    "ne:LATITUDE":51.033692,
    "ne:LONGITUDE":-93.833301,
    "ne:LS_MATCH":1,
    "ne:LS_NAME":"Red Lake",
    "ne:MAX_AREAKM":4.0,
    "ne:MAX_AREAMI":2.0,
    "ne:MAX_BBXMAX":-93.808333,
    "ne:MAX_BBXMIN":-93.841667,
    "ne:MAX_BBYMAX":51.025,
    "ne:MAX_BBYMIN":51.008333,
    "ne:MAX_NATSCA":20.0,
    "ne:MAX_PERKM":10.0,
    "ne:MAX_PERMI":6.0,
    "ne:MAX_POP10":1765,
    "ne:MAX_POP20":1765,
    "ne:MAX_POP300":0,
    "ne:MAX_POP310":0,
    "ne:MAX_POP50":0,
    "ne:MEAN_BBXC":-93.825,
    "ne:MEAN_BBYC":51.016667,
    "ne:MEGACITY":0,
    "ne:MIN_AREAKM":4.0,
    "ne:MIN_AREAMI":2.0,
    "ne:MIN_BBXMAX":-93.808333,
    "ne:MIN_BBXMIN":-93.841667,
    "ne:MIN_BBYMAX":51.025,
    "ne:MIN_BBYMIN":51.008333,
    "ne:MIN_PERKM":10.0,
    "ne:MIN_PERMI":6.0,
    "ne:NAME":"Red Lake",
    "ne:NAMEASCII":"Red Lake",
    "ne:NAMEDIFF":0,
    "ne:NATSCALE":20,
    "ne:POP1950":0,
    "ne:POP1955":0,
    "ne:POP1960":0,
    "ne:POP1965":0,
    "ne:POP1970":0,
    "ne:POP1975":0,
    "ne:POP1980":0,
    "ne:POP1985":0,
    "ne:POP1990":0,
    "ne:POP1995":0,
    "ne:POP2000":0,
    "ne:POP2005":0,
    "ne:POP2010":0,
    "ne:POP2015":0,
    "ne:POP2020":0,
    "ne:POP2025":0,
    "ne:POP2050":0,
    "ne:POP_MAX":1765,
    "ne:POP_MIN":1765,
    "ne:POP_OTHER":0,
    "ne:RANK_MAX":3,
    "ne:RANK_MIN":3,
    "ne:SCALERANK":7,
    "ne:SOV0NAME":"Canada",
    "ne:SOV_A3":"CAN",
    "ne:UN_FID":0,
    "ne:UN_LAT":0.0,
    "ne:UN_LONG":0.0,
    "ne:WORLDCITY":0,
    "ne:min_zoom":6.7,
    "wof:name":"Red Lake",
    "wof:placetype":"locality"
},
  "geometry": {"coordinates":[-93.83330123063115,51.03369244292901],"type":"Point"}
}