{
  "type": "Feature",
  "properties": {
    "gn:admin1_code":"11",
    "gn:asciiname":"Henribourg",
    "gn:country_code":"CA",
    "gn:dem":485,
    "gn:feature_class":"P",
    "gn:feature_code":"PPL",
    "gn:name":"Henribourg",
    "gn:population":0,
    "gn:timezone":"America/Regina",
    "iso:country":"CA",
    "wof:name":"Henribourg",
    "wof:placetype":"locality"
},
  "geometry": {"coordinates":[-105.61769,53.40009000000001],"type":"Point"}
}