{
  "type": "Feature",
  "properties": {
    "gn:admin1_code":"10",
    "gn:admin2_code":"4.0",
    "gn:asciiname":"Lac-Masketsi",
    "gn:country_code":"CA",
    "gn:dem":236,
    "gn:feature_class":"P",
    "gn:feature_code":"PPL",
    "gn:name":"Lac-Masketsi",
    "gn:population":0,
    "gn:timezone":"America/Toronto",
    "iso:country":"CA",
    "name:ara_x_preferred":[
        "\u0644\u0627\u0643 \u0645\u0627\u0633\u0643\u064a\u062a\u0633\u064a"
    ],
    "name:fra_x_preferred":[
        "Lac-Masketsi"
    ],
    "wof:name":"Lac-Masketsi",
    "wof:placetype":"locality"
},
  "geometry": {"coordinates":[-72.54864999999999,47.01625],"type":"Point"}
}