{
  "type": "Feature",
  "properties": {
    "gn:admin1_code":"4.0",
    "gn:asciiname":"West River",
    "gn:country_code":"CA",
    "gn:dem":37,
    "gn:feature_class":"P",
    "gn:feature_code":"PPL",
    "gn:name":"West River",
    "gn:population":0,
    "gn:timezone":"America/Moncton",
    "iso:country":"CA",
    "name:bre_x_preferred":[
        "West River"
    ],
    "name:ceb_x_preferred":[
        "West River"
    ],
    "name:deu_x_preferred":[
        "West River"
    ],
    "name:fra_x_preferred":[
        "West River"
    ],
    "name:rus_x_preferred":[
        "\u0423\u044d\u0441\u0442-\u0420\u0438\u0432\u0435\u0440"
    ],
    "name:swe_x_preferred":[
        "West River"
    ],
    "wof:name":"West River",
    "wof:placetype":"locality"
},
  "geometry": {"coordinates":[-64.84451999999999,45.64592],"type":"Point"}
}