{
  "type": "Feature",
  "properties": {
    "gn:admin1_code":"7.0",
    "gn:asciiname":"Big Tracadie",
    "gn:country_code":"CA",
    "gn:dem":20,
    "gn:feature_class":"P",
    "gn:feature_code":"PPL",
    "gn:name":"Big Tracadie",
    "gn:population":0,
    "gn:timezone":"America/Halifax",
    "iso:country":"CA",
    "wof:name":"Big Tracadie",
    "wof:placetype":"locality"
},
  "geometry": {"coordinates":[-61.63517,45.6193],"type":"Point"}
}