{
  "type": "Feature",
  "properties": {
    "gn:admin1_code":"10",
    "gn:admin2_code":"15.0",
    "gn:admin3_code":"72032.0",
    "gn:asciiname":"Pointe-aux-Anglais",
    "gn:country_code":"CA",
    "gn:dem":28,
    "gn:feature_class":"P",
    "gn:feature_code":"PPL",
    "gn:name":"Pointe-aux-Anglais",
    "gn:population":0,
    "gn:timezone":"America/Toronto",
    "iso:country":"CA",
    "name:fra_x_preferred":[
        "Pointe-aux-Anglais"
    ],
    "wof:name":"Pointe-aux-Anglais",
    "wof:placetype":"locality"
},
  "geometry": {"coordinates":[-74.16906,45.49893],"type":"Point"}
}