{
  "type": "Feature",
  "properties": {
    "gn:admin1_code":"7",
    "gn:asciiname":"Steep Creek",
    "gn:country_code":"CA",
    "gn:dem":2,
    "gn:feature_class":"P",
    "gn:feature_code":"PPL",
    "gn:name":"Steep Creek",
    "gn:population":0,
    "gn:timezone":"America/Halifax",
    "iso:country":"CA",
    "wof:name":"Steep Creek",
    "wof:placetype":"locality"
},
  "geometry": {"coordinates":[-61.34354,45.55481],"type":"Point"}
}