{
  "type": "Feature",
  "properties": {
    "gn:admin1_code":"8.0",
    "gn:asciiname":"Shuniah Township",
    "gn:country_code":"CA",
    "gn:dem":482,
    "gn:feature_class":"P",
    "gn:feature_code":"PPL",
    "gn:name":"Shuniah Township",
    "gn:population":0,
    "gn:timezone":"America/Toronto",
    "iso:country":"CA",
    "wof:name":"Shuniah Township",
    "wof:placetype":"locality"
},
  "geometry": {"coordinates":[-89.1147,48.5242],"type":"Point"}
}