{
  "type": "Feature",
  "properties": {
    "gn:admin1_code":"8",
    "gn:asciiname":"Sauble Beach South",
    "gn:country_code":"CA",
    "gn:dem":181,
    "gn:feature_class":"P",
    "gn:feature_code":"PPL",
    "gn:name":"Sauble Beach South",
    "gn:population":0,
    "gn:timezone":"America/Toronto",
    "iso:country":"CA",
    "wof:name":"Sauble Beach South",
    "wof:placetype":"locality"
},
  "geometry": {"coordinates":[-81.27939000000001,44.599],"type":"Point"}
}