{
  "type": "Feature",
  "properties": {
    "gn:admin1_code":"2",
    "gn:asciiname":"McLeod",
    "gn:country_code":"CA",
    "gn:dem":245,
    "gn:feature_class":"P",
    "gn:feature_code":"PPL",
    "gn:name":"McLeod",
    "gn:population":0,
    "gn:timezone":"America/Vancouver",
    "iso:country":"CA",
    "wof:name":"McLeod",
    "wof:placetype":"locality"
},
  "geometry": {"coordinates":[-127.68877000000001,55.25398000000001],"type":"Point"}
}