{
  "type": "Feature",
  "properties": {
    "gn:admin1_code":"10",
    "gn:admin2_code":"15.0",
    "gn:admin3_code":"75045.0",
    "gn:asciiname":"Lac-des-Sources",
    "gn:country_code":"CA",
    "gn:dem":335,
    "gn:feature_class":"P",
    "gn:feature_code":"PPL",
    "gn:name":"Lac-des-Sources",
    "gn:population":0,
    "gn:timezone":"America/Toronto",
    "iso:country":"CA",
    "wof:name":"Lac-des-Sources",
    "wof:placetype":"locality"
},
  "geometry": {"coordinates":[-74.04432,45.9506],"type":"Point"}
}