{
  "type": "Feature",
  "properties": {
    "gn:admin1_code":"8.0",
    "gn:asciiname":"Dover Centre",
    "gn:country_code":"CA",
    "gn:dem":179,
    "gn:feature_class":"P",
    "gn:feature_code":"PPL",
    "gn:name":"Dover Centre",
    "gn:population":0,
    "gn:timezone":"America/Toronto",
    "iso:country":"CA",
    "wof:name":"Dover Centre",
    "wof:placetype":"locality"
},
  "geometry": {"coordinates":[-82.31788,42.48994],"type":"Point"}
}