{
  "type": "Feature",
  "properties": {
    "gn:admin1_code":"8",
    "gn:asciiname":"Snake Falls",
    "gn:country_code":"CA",
    "gn:dem":352,
    "gn:feature_class":"P",
    "gn:feature_code":"PPL",
    "gn:name":"Snake Falls",
    "gn:population":0,
    "gn:timezone":"America/Winnipeg",
    "iso:country":"CA",
    "wof:name":"Snake Falls",
    "wof:placetype":"locality"
},
  "geometry": {"coordinates":[-93.46295000000001,50.83224000000001],"type":"Point"}
}