{
  "type": "Feature",
  "properties": {
    "gn:admin1_code":"8",
    "gn:asciiname":"Speyside",
    "gn:country_code":"CA",
    "gn:dem":339,
    "gn:feature_class":"P",
    "gn:feature_code":"PPL",
    "gn:name":"Speyside",
    "gn:population":0,
    "gn:timezone":"America/Toronto",
    "iso:country":"CA",
    "name:fra_x_preferred":[
        "Speyside"
    ],
    "name:spa_x_preferred":[
        "Speyside"
    ],
    "wof:name":"Speyside",
    "wof:placetype":"locality"
},
  "geometry": {"coordinates":[-79.97624,43.57808],"type":"Point"}
}