{
  "type": "Feature",
  "properties": {
    "gn:admin1_code":"8",
    "gn:asciiname":"Sheridan Park",
    "gn:country_code":"CA",
    "gn:dem":143,
    "gn:feature_class":"P",
    "gn:feature_code":"PPL",
    "gn:name":"Sheridan Park",
    "gn:population":0,
    "gn:timezone":"America/Toronto",
    "iso:country":"CA",
    "wof:name":"Sheridan Park",
    "wof:placetype":"locality"
},
  "geometry": {"coordinates":[-79.66632,43.51681],"type":"Point"}
}