{
  "type": "Feature",
  "properties": {
    "gn:admin1_code":"3",
    "gn:asciiname":"Scotch Bay",
    "gn:country_code":"CA",
    "gn:dem":248,
    "gn:feature_class":"P",
    "gn:feature_code":"PPLL",
    "gn:name":"Scotch Bay",
    "gn:population":0,
    "gn:timezone":"America/Winnipeg",
    "iso:country":"CA",
    "wof:name":"Scotch Bay",
    "wof:placetype":"locality"
},
  "geometry": {"coordinates":[-98.37993,50.82722],"type":"Point"}
}