{
  "type": "Feature",
  "properties": {
    "gn:admin1_code":"8.0",
    "gn:asciiname":"Clover Valley",
    "gn:country_code":"CA",
    "gn:dem":212,
    "gn:feature_class":"P",
    "gn:feature_code":"PPLL",
    "gn:name":"Clover Valley",
    "gn:population":0,
    "gn:timezone":"America/Toronto",
    "iso:country":"CA",
    "wof:name":"Clover Valley",
    "wof:placetype":"locality"
},
  "geometry": {"coordinates":[-81.81480000000001,45.71287],"type":"Point"}
}