{
  "type": "Feature",
  "properties": {
    "gn:country":"CA",
    "gn:fcode":"PPL",
    "gn:pop":0,
    "iso:country":"CA",
    "name:eng_x_preferred":[
        "Glenburnie"
    ],
    "qs:name":"Glenburnie",
    "qs:name_adm0":"Canada",
    "qs:name_adm1":"Newfoundland and Labrador",
    "qs:photos_9r":0,
    "qs:photos_sr":0,
    "qs:placetype":"Town",
    "qs:pop_sr":"0",
    "wd:wordcount":48,
    "wof:name":"Glenburnie",
    "wof:placetype":"locality",
    "wof:population":0
},
  "geometry": {"coordinates":[-57.89832,49.43331],"type":"Point"}
}