{
  "type": "Feature",
  "properties": {
    "gn:admin1_code":"7",
    "gn:asciiname":"Walkerville",
    "gn:country_code":"CA",
    "gn:dem":26,
    "gn:feature_class":"P",
    "gn:feature_code":"PPL",
    "gn:name":"Walkerville",
    "gn:population":0,
    "gn:timezone":"America/Halifax",
    "iso:country":"CA",
    "wof:name":"Walkerville",
    "wof:placetype":"locality"
},
  "geometry": {"coordinates":[-61.19592,45.60627],"type":"Point"}
}