{
  "type": "Feature",
  "properties": {
    "gn:admin1_code":"7.0",
    "gn:asciiname":"Cavanagh Mills",
    "gn:country_code":"CA",
    "gn:dem":194,
    "gn:feature_class":"P",
    "gn:feature_code":"PPLL",
    "gn:name":"Cavanagh Mills",
    "gn:population":0,
    "gn:timezone":"America/Halifax",
    "iso:country":"CA",
    "wof:name":"Cavanagh Mills",
    "wof:placetype":"locality"
},
  "geometry": {"coordinates":[-63.26538000000001,45.60015],"type":"Point"}
}