{
  "type": "Feature",
  "properties": {
    "gn:admin1_code":"8",
    "gn:asciiname":"Ostrom",
    "gn:country_code":"CA",
    "gn:dem":398,
    "gn:feature_class":"P",
    "gn:feature_code":"PPL",
    "gn:name":"Ostrom",
    "gn:population":0,
    "gn:timezone":"America/Toronto",
    "iso:country":"CA",
    "name:kor_x_preferred":[
        "\uc624\uc2a4\ud2b8\ub86c"
    ],
    "wof:name":"Ostrom",
    "wof:placetype":"locality"
},
  "geometry": {"coordinates":[-81.61704,47.46851],"type":"Point"}
}