{
  "type": "Feature",
  "properties": {
    "gn:admin1_code":"11.0",
    "gn:asciiname":"Bankend",
    "gn:country_code":"CA",
    "gn:dem":622,
    "gn:feature_class":"P",
    "gn:feature_code":"PPLL",
    "gn:name":"Bankend",
    "gn:population":0,
    "gn:timezone":"America/Regina",
    "iso:country":"CA",
    "name:nld_x_preferred":[
        "Bankend"
    ],
    "name:spa_x_preferred":[
        "Bankend"
    ],
    "wof:name":"Bankend",
    "wof:placetype":"locality"
},
  "geometry": {"coordinates":[-103.85105,51.51675],"type":"Point"}
}