{
  "type": "Feature",
  "properties": {
    "gn:admin1_code":"8.0",
    "gn:asciiname":"Brock Road",
    "gn:country_code":"CA",
    "gn:dem":129,
    "gn:feature_class":"P",
    "gn:feature_code":"PPL",
    "gn:name":"Brock Road",
    "gn:population":0,
    "gn:timezone":"America/Toronto",
    "iso:country":"CA",
    "wof:name":"Brock Road",
    "wof:placetype":"locality"
},
  "geometry": {"coordinates":[-79.08778000000002,43.88167],"type":"Point"}
}