{
  "type": "Feature",
  "properties": {
    "gn:admin1_code":"5",
    "gn:asciiname":"Quarry",
    "gn:country_code":"CA",
    "gn:dem":373,
    "gn:feature_class":"P",
    "gn:feature_code":"PPLL",
    "gn:name":"Quarry",
    "gn:population":0,
    "gn:timezone":"America/St_Johns",
    "iso:country":"CA",
    "wof:name":"Quarry",
    "wof:placetype":"locality"
},
  "geometry": {"coordinates":[-56.58155,49.04997],"type":"Point"}
}