{
  "type": "Feature",
  "properties": {
    "gn:admin1_code":"8",
    "gn:asciiname":"North Seguin",
    "gn:country_code":"CA",
    "gn:dem":299,
    "gn:feature_class":"P",
    "gn:feature_code":"PPL",
    "gn:name":"North Seguin",
    "gn:population":0,
    "gn:timezone":"America/Toronto",
    "iso:country":"CA",
    "wof:name":"North Seguin",
    "wof:placetype":"locality"
},
  "geometry": {"coordinates":[-79.67667,45.49722],"type":"Point"}
}