{
  "type": "Feature",
  "properties": {
    "gn:admin1_code":"8",
    "gn:asciiname":"Pengelly Landing",
    "gn:country_code":"CA",
    "gn:dem":186,
    "gn:feature_class":"P",
    "gn:feature_code":"PPL",
    "gn:name":"Pengelly Landing",
    "gn:population":0,
    "gn:timezone":"America/Toronto",
    "iso:country":"CA",
    "wof:name":"Pengelly Landing",
    "wof:placetype":"locality"
},
  "geometry": {"coordinates":[-78.30596,44.13037],"type":"Point"}
}