{
  "type": "Feature",
  "properties": {
    "gn:country":"CA",
    "gn:fcode":"ADMD",
    "gn:pop":0,
    "iso:country":"CA",
    "name:eng_x_preferred":[
        "Russell"
    ],
    "qs:name":"Russell",
    "qs:photos_9r":0,
    "qs:photos_sr":0,
    "qs:pop_sr":"0",
    "wd:wordcount":314,
    "wof:name":"Russell",
    "wof:placetype":"localadmin",
    "wof:population":0
},
  "geometry": {"coordinates":[-75.31601999999999,45.3001],"type":"Point"}
}