{
  "type": "Feature",
  "properties": {
    "gn:country":"CA",
    "gn:fcode":"ADMD",
    "gn:population":0,
    "iso:country":"CA",
    "name:bel_x_preferred":[
        "\u0420\u0430\u0441\u0435\u043b"
    ],
    "name:bul_x_preferred":[
        "\u0420\u044a\u0441\u0435\u043b"
    ],
    "name:cat_x_preferred":[
        "Russell"
    ],
    "name:ceb_x_preferred":[
        "Russell"
    ],
    "name:ces_x_preferred":[
        "Russell"
    ],
    "name:dan_x_preferred":[
        "Russell"
    ],
    "name:deu_x_preferred":[
        "Russell"
    ],
    "name:eng_x_preferred":[
        "Russell"
    ],
    "name:eus_x_preferred":[
        "Russell"
    ],
    "name:fas_x_preferred":[
        "\u0631\u0627\u0633\u0644"
    ],
    "name:fin_x_preferred":[
        "Russell"
    ],
    "name:fra_x_preferred":[
        "Russell"
    ],
    "name:heb_x_preferred":[
        "\u05e8\u05d0\u05e1\u05dc"
    ],
    "name:hun_x_preferred":[
        "Russell"
    ],
    "name:ita_x_preferred":[
        "Russell"
    ],
    "name:jpn_x_preferred":[
        "\u30e9\u30c3\u30bb\u30eb"
    ],
    "name:lav_x_preferred":[
        "Rasels"
    ],
    "name:nld_x_preferred":[
        "Russell"
    ],
    "name:nor_x_preferred":[
        "Russell"
    ],
    "name:pol_x_preferred":[
        "Russell"
    ],
    "name:por_x_preferred":[
        "Russell"
    ],
    "name:rus_x_preferred":[
        "\u0420\u0430\u0441\u0441\u0435\u043b\u043b"
    ],
    "name:slv_x_preferred":[
        "Russell"
    ],
    "name:spa_x_preferred":[
        "Russell"
    ],
    "name:srp_x_preferred":[
        "\u0420\u0430\u0441\u0435\u043b"
    ],
    "name:swe_x_preferred":[
        "Russell"
    ],
    "name:ukr_x_preferred":[
        "\u0420\u0430\u0441\u0441\u0435\u043b\u043b"
    ],
    "name:vie_x_preferred":[
        "Russell"
    ],
    "name:vol_x_preferred":[
        "Russell"
    ],
    "qs:name":"Russell",
    "qs:photos_9r":0,
    "qs:photos_sr":0,
    "qs:pop_sr":"0",
    "wd:wordcount":314,
    "wof:name":"Russell",
    "wof:placetype":"localadmin",
    "wof:population":0
},
  "geometry": {"coordinates":[-75.31601999999999,45.3001],"type":"Point"}
}