{
  "type": "Feature",
  "properties": {
    "gn:admin1_code":"10",
    "gn:admin2_code":"14.0",
    "gn:admin3_code":"63055.0",
    "gn:asciiname":"Lac-Beaudry",
    "gn:country_code":"CA",
    "gn:dem":312,
    "gn:feature_class":"P",
    "gn:feature_code":"PPL",
    "gn:name":"Lac-Beaudry",
    "gn:population":0,
    "gn:timezone":"America/Toronto",
    "iso:country":"CA",
    "wof:name":"Lac-Beaudry",
    "wof:placetype":"locality"
},
  "geometry": {"coordinates":[-73.93654000000002,45.98087],"type":"Point"}
}