{
  "type": "Feature",
  "properties": {
    "gn:admin1_code":"11",
    "gn:asciiname":"Forest Bank",
    "gn:country_code":"CA",
    "gn:dem":616,
    "gn:feature_class":"P",
    "gn:feature_code":"PPLL",
    "gn:name":"Forest Bank",
    "gn:population":0,
    "gn:timezone":"America/Edmonton",
    "iso:country":"CA",
    "wof:name":"Forest Bank",
    "wof:placetype":"locality"
},
  "geometry": {"coordinates":[-109.4348,53.21686999999999],"type":"Point"}
}