{
  "type": "Feature",
  "properties": {
    "gn:admin1_code":"7",
    "gn:asciiname":"Smithsville",
    "gn:country_code":"CA",
    "gn:dem":6,
    "gn:feature_class":"P",
    "gn:feature_code":"PPL",
    "gn:name":"Smithsville",
    "gn:population":0,
    "gn:timezone":"America/Halifax",
    "iso:country":"CA",
    "wof:name":"Smithsville",
    "wof:placetype":"locality"
},
  "geometry": {"coordinates":[-65.46981,43.48656],"type":"Point"}
}