{
  "type": "Feature",
  "properties": {
    "gn:admin1_code":"2.0",
    "gn:asciiname":"Cinema",
    "gn:country_code":"CA",
    "gn:dem":770,
    "gn:feature_class":"P",
    "gn:feature_code":"PPLL",
    "gn:name":"Cinema",
    "gn:population":0,
    "gn:timezone":"America/Vancouver",
    "iso:country":"CA",
    "wof:name":"Cinema",
    "wof:placetype":"locality"
},
  "geometry": {"coordinates":[-122.45292000000001,53.2332],"type":"Point"}
}