{
  "type": "Feature",
  "properties": {
    "gn:admin1_code":"2.0",
    "gn:asciiname":"Cinema",
    "gn:country_code":"CA",
    "gn:dem":770,
    "gn:feature_class":"P",
    "gn:feature_code":"PPLL",
    "gn:name":"Cinema",
    "gn:population":0,
    "gn:timezone":"America/Vancouver",
    "iso:country":"CA",
    "name:ces_x_preferred":[
        "Cinema"
    ],
    "name:deu_x_preferred":[
        "Cinema"
    ],
    "name:fas_x_preferred":[
        "\u0633\u06cc\u0646\u0645\u0627"
    ],
    "name:fin_x_preferred":[
        "Cinema"
    ],
    "name:fra_x_preferred":[
        "Cin\u00e9ma"
    ],
    "name:hin_x_preferred":[
        "\u091a\u0932\u091a\u093f\u0924\u094d\u0930\u092a\u091f"
    ],
    "name:hun_x_preferred":[
        "Cinema"
    ],
    "name:ind_x_preferred":[
        "Sinema"
    ],
    "name:ita_x_preferred":[
        "Cinema"
    ],
    "name:jpn_x_preferred":[
        "\u30b7\u30cd\u30de"
    ],
    "name:kor_x_preferred":[
        "\uc2dc\ub124\ub9c8"
    ],
    "name:nld_x_preferred":[
        "Cinema"
    ],
    "name:nor_x_preferred":[
        "Cinema"
    ],
    "name:pol_x_preferred":[
        "Cinema"
    ],
    "name:por_x_preferred":[
        "Cinema"
    ],
    "name:slk_x_preferred":[
        "Cinema"
    ],
    "name:swe_x_preferred":[
        "Cinema"
    ],
    "wof:name":"Cinema",
    "wof:placetype":"locality"
},
  "geometry": {"coordinates":[-122.45292000000001,53.2332],"type":"Point"}
}