{
  "type": "Feature",
  "properties": {
    "gn:admin1_code":"7",
    "gn:asciiname":"McNabs Cove",
    "gn:country_code":"CA",
    "gn:dem":7,
    "gn:feature_class":"P",
    "gn:feature_code":"PPLL",
    "gn:name":"McNabs Cove",
    "gn:population":0,
    "gn:timezone":"America/Halifax",
    "iso:country":"CA",
    "wof:name":"McNabs Cove",
    "wof:placetype":"locality"
},
  "geometry": {"coordinates":[-60.71989,45.73094],"type":"Point"}
}