{
  "type": "Feature",
  "properties": {
    "iso:country":"CA",
    "qs_pg:aaroncc":"CA",
    "qs_pg:name":"St.-Jean-Port-Joli",
    "qs_pg:name_adm0":"Canada",
    "qs_pg:name_adm1":"Qu\u00e9bec",
    "qs_pg:photos":859,
    "qs_pg:photos_1k":174,
    "qs_pg:photos_9k":4,
    "qs_pg:photos_9r":6,
    "qs_pg:photos_all":859,
    "qs_pg:photos_sr":10,
    "qs_pg:pop_sr":0,
    "qs_pg:qs_pg_placetype":"locality",
    "qs_pg:qs_pg_placetype_gp":"Town",
    "qs_pg:woe_adm0":23424775,
    "woe:adm0_id":23424775,
    "woe:name_adm0":"Canada",
    "woe:name_adm1":"Qu\u00e9bec",
    "woe:placetype":"Town",
    "wof:name":"St.-Jean-Port-Joli",
    "wof:placetype":"locality"
},
  "geometry": {"coordinates":[-70.26627999999999,47.217702],"type":"Point"}
}