{
  "type": "Feature",
  "properties": {
    "gn:admin1_code":"4",
    "gn:asciiname":"Lockstead",
    "gn:country_code":"CA",
    "gn:dem":78,
    "gn:feature_class":"P",
    "gn:feature_code":"PPL",
    "gn:name":"Lockstead",
    "gn:population":0,
    "gn:timezone":"America/Moncton",
    "iso:country":"CA",
    "wof:name":"Lockstead",
    "wof:placetype":"locality"
},
  "geometry": {"coordinates":[-65.86377,46.77718],"type":"Point"}
}