{
  "type": "Feature",
  "properties": {
    "gn:admin1_code":"8",
    "gn:asciiname":"Muirkirk",
    "gn:country_code":"CA",
    "gn:dem":217,
    "gn:feature_class":"P",
    "gn:feature_code":"PPL",
    "gn:name":"Muirkirk",
    "gn:population":0,
    "gn:timezone":"America/Toronto",
    "iso:country":"CA",
    "name:ceb_x_preferred":[
        "Muirkirk"
    ],
    "name:cym_x_preferred":[
        "Muirkirk"
    ],
    "name:eus_x_preferred":[
        "Muirkirk"
    ],
    "name:fas_x_preferred":[
        "\u0645\u0648\u06cc\u0631\u06a9\u06cc\u0631\u06a9"
    ],
    "name:fra_x_preferred":[
        "Muirkirk"
    ],
    "name:ita_x_preferred":[
        "Muirkirk"
    ],
    "name:sco_x_preferred":[
        "Muirkirk"
    ],
    "name:spa_x_preferred":[
        "Muirkirk"
    ],
    "name:swe_x_preferred":[
        "Muirkirk"
    ],
    "wof:name":"Muirkirk",
    "wof:placetype":"locality"
},
  "geometry": {"coordinates":[-81.77427,42.51599],"type":"Point"}
}