{
  "type": "Feature",
  "properties": {
    "iso:country":"CA",
    "name:ceb_x_preferred":[
        "Lac La Biche Airport"
    ],
    "name:eng_x_preferred":[
        "Lac La Biche Airport"
    ],
    "name:fas_x_preferred":[
        "\u0641\u0631\u0648\u062f\u06af\u0627\u0647 \u0644\u06a9 \u0644\u0627 \u0628\u06cc\u0686"
    ],
    "name:ind_x_preferred":[
        "Bandar Udara Lac La Biche"
    ],
    "name:msa_x_preferred":[
        "Lapangan Terbang Lac La Biche"
    ],
    "name:pms_x_preferred":[
        "Lac La Biche Airport"
    ],
    "name:ron_x_preferred":[
        "Aeroportul Lac La Biche"
    ],
    "name:swe_x_preferred":[
        "Lac La Biche Airport"
    ],
    "name:tgk_x_preferred":[
        "\u0424\u0443\u0440\u0443\u0434\u0433\u043e\u04b3\u0438 \u043b\u043a \u043b\u043e \u0431\u0438\u0447"
    ],
    "oa:elevation_ft":"1884",
    "oa:type":"small_airport",
    "wd:wordcount":62,
    "woe:hierarchy":{
        "country_id":23424775,
        "county_id":29375228,
        "planet_id":1,
        "state_id":2344915
    },
    "wof:name":"Lac la Biche Airport",
    "wof:placetype":"campus"
},
  "geometry": {"coordinates":[-112.032,54.7703],"type":"Point"}
}