{
  "type": "Feature",
  "properties": {
    "gn:admin1_code":"7",
    "gn:asciiname":"Ingonish Ferry",
    "gn:country_code":"CA",
    "gn:dem":36,
    "gn:feature_class":"P",
    "gn:feature_code":"PPL",
    "gn:name":"Ingonish Ferry",
    "gn:population":0,
    "gn:timezone":"America/Halifax",
    "iso:country":"CA",
    "wof:name":"Ingonish Ferry",
    "wof:placetype":"locality"
},
  "geometry": {"coordinates":[-60.39245,46.62779000000001],"type":"Point"}
}