{
  "type": "Feature",
  "properties": {
    "gn:country":"CA",
    "gn:fcode":"PPL",
    "gn:population":0,
    "iso:country":"CA",
    "name:ang_x_preferred":[
        "Dildo"
    ],
    "name:dan_x_preferred":[
        "Dildo"
    ],
    "name:deu_x_preferred":[
        "Dildo"
    ],
    "name:eng_x_preferred":[
        "Dildo"
    ],
    "name:eng_x_variant":[
        "dildo"
    ],
    "name:epo_x_preferred":[
        "dildo"
    ],
    "name:est_x_preferred":[
        "Dildo"
    ],
    "name:eus_x_preferred":[
        "Dildo"
    ],
    "name:fry_x_preferred":[
        "Dildo"
    ],
    "name:gsw_x_preferred":[
        "Dildo"
    ],
    "name:hrv_x_preferred":[
        "Dildo"
    ],
    "name:hun_x_preferred":[
        "Dild\u00f3"
    ],
    "name:ind_x_preferred":[
        "Dildo"
    ],
    "name:isl_x_preferred":[
        "Dild\u00f3"
    ],
    "name:ita_x_preferred":[
        "Dildo"
    ],
    "name:kur_x_preferred":[
        "D\u00eeldo"
    ],
    "name:lmo_x_preferred":[
        "Dildo"
    ],
    "name:ltz_x_preferred":[
        "Dildo"
    ],
    "name:nds_x_preferred":[
        "Dildo"
    ],
    "name:nld_x_preferred":[
        "Dildo"
    ],
    "name:nob_x_preferred":[
        "Dildo"
    ],
    "name:por_x_preferred":[
        "Dildo"
    ],
    "name:ron_x_preferred":[
        "Dildo"
    ],
    "name:sco_x_preferred":[
        "Dildo"
    ],
    "name:slk_x_preferred":[
        "Dildo"
    ],
    "name:sqi_x_preferred":[
        "Dildo"
    ],
    "name:swe_x_preferred":[
        "Dildo"
    ],
    "name:tgl_x_preferred":[
        "Dildo"
    ],
    "name:zea_x_preferred":[
        "Dildo"
    ],
    "qs:name":"Dildo",
    "qs:name_adm0":"Canada",
    "qs:name_adm1":"Newfoundland and Labrador",
    "qs:photos":224,
    "qs:photos_1k":45,
    "qs:photos_9k":1,
    "qs:photos_9r":4,
    "qs:photos_all":224,
    "qs:photos_sr":4,
    "qs:placetype":"Town",
    "qs:pop_sr":"0",
    "wd:wordcount":3543,
    "wof:name":"Dildo",
    "wof:placetype":"locality",
    "wof:population":0
},
  "geometry": {"coordinates":[-53.5481,47.56659],"type":"Point"}
}