{
  "type": "Feature",
  "properties": {
    "gn:admin1_code":"8",
    "gn:asciiname":"Squire",
    "gn:country_code":"CA",
    "gn:dem":263,
    "gn:feature_class":"P",
    "gn:feature_code":"PPL",
    "gn:name":"Squire",
    "gn:population":0,
    "gn:timezone":"America/Toronto",
    "iso:country":"CA",
    "name:cat_x_preferred":[
        "Escuder"
    ],
    "name:ces_x_preferred":[
        "Pano\u0161"
    ],
    "name:dan_x_preferred":[
        "V\u00e6bner"
    ],
    "name:deu_x_preferred":[
        "Schildknappe"
    ],
    "name:epo_x_preferred":[
        "Varleto"
    ],
    "name:fin_x_preferred":[
        "Asemies"
    ],
    "name:fra_x_preferred":[
        "\u00c9cuyer"
    ],
    "name:heb_x_preferred":[
        "\u05e0\u05d5\u05e9\u05d0 \u05db\u05dc\u05d9\u05dd"
    ],
    "name:hun_x_preferred":[
        "Apr\u00f3d"
    ],
    "name:ita_x_preferred":[
        "Scudiero"
    ],
    "name:lit_x_preferred":[
        "Ginklane\u0161ys"
    ],
    "name:nld_x_preferred":[
        "Schildknaap"
    ],
    "name:pol_x_preferred":[
        "Giermek"
    ],
    "name:por_x_preferred":[
        "Escudeiro"
    ],
    "name:rus_x_preferred":[
        "\u041e\u0440\u0443\u0436\u0435\u043d\u043e\u0441\u0435\u0446"
    ],
    "name:spa_x_preferred":[
        "Escudero"
    ],
    "name:swe_x_preferred":[
        "V\u00e4pnare"
    ],
    "name:tur_x_preferred":[
        "Squire"
    ],
    "name:ukr_x_preferred":[
        "\u0417\u0431\u0440\u043e\u0454\u043d\u043e\u0441\u0435\u0446\u044c"
    ],
    "wof:name":"Squire",
    "wof:placetype":"locality"
},
  "geometry": {"coordinates":[-80.98389,44.51611],"type":"Point"}
}