{
  "type": "Feature",
  "properties": {
    "gn:admin1_code":"11",
    "gn:asciiname":"Furdale",
    "gn:country_code":"CA",
    "gn:dem":502,
    "gn:feature_class":"P",
    "gn:feature_code":"PPLL",
    "gn:name":"Furdale",
    "gn:population":0,
    "gn:timezone":"America/Regina",
    "iso:country":"CA",
    "wof:name":"Furdale",
    "wof:placetype":"locality"
},
  "geometry": {"coordinates":[-106.68453,52.08339],"type":"Point"}
}