{
  "type": "Feature",
  "properties": {
    "gn:admin1_code":"1",
    "gn:asciiname":"Labuma",
    "gn:country_code":"CA",
    "gn:dem":873,
    "gn:feature_class":"P",
    "gn:feature_code":"PPLL",
    "gn:name":"Labuma",
    "gn:population":0,
    "gn:timezone":"America/Edmonton",
    "iso:country":"CA",
    "wof:name":"Labuma",
    "wof:placetype":"locality"
},
  "geometry": {"coordinates":[-113.80200000000001,52.33342],"type":"Point"}
}