{
  "type": "Feature",
  "properties": {
    "gn:admin1_code":"8",
    "gn:asciiname":"McKay's Corners",
    "gn:country_code":"CA",
    "gn:dem":189,
    "gn:feature_class":"P",
    "gn:feature_code":"PPL",
    "gn:name":"McKay's Corners",
    "gn:population":0,
    "gn:timezone":"America/Toronto",
    "iso:country":"CA",
    "wof:name":"McKay's Corners",
    "wof:placetype":"locality"
},
  "geometry": {"coordinates":[-81.99236999999999,42.45146],"type":"Point"}
}