{
  "type": "Feature",
  "properties": {
    "gn:admin1_code":"5",
    "gn:asciiname":"Gooseberry Cove",
    "gn:country_code":"CA",
    "gn:dem":47,
    "gn:feature_class":"P",
    "gn:feature_code":"PPLL",
    "gn:name":"Gooseberry Cove",
    "gn:population":0,
    "gn:timezone":"America/St_Johns",
    "iso:country":"CA",
    "wof:name":"Gooseberry Cove",
    "wof:placetype":"locality"
},
  "geometry": {"coordinates":[-54.09815,47.06661],"type":"Point"}
}