{
  "type": "Feature",
  "properties": {
    "gn:admin1_code":"8",
    "gn:asciiname":"North Woodslee",
    "gn:country_code":"CA",
    "gn:dem":187,
    "gn:feature_class":"P",
    "gn:feature_code":"PPL",
    "gn:name":"North Woodslee",
    "gn:population":0,
    "gn:timezone":"America/Toronto",
    "iso:country":"CA",
    "wof:name":"North Woodslee",
    "wof:placetype":"locality"
},
  "geometry": {"coordinates":[-82.71556,42.21444],"type":"Point"}
}