{
  "type": "Feature",
  "properties": {
    "gn:admin1_code":"8",
    "gn:asciiname":"Tramore",
    "gn:country_code":"CA",
    "gn:dem":174,
    "gn:feature_class":"P",
    "gn:feature_code":"PPL",
    "gn:name":"Tramore",
    "gn:population":0,
    "gn:timezone":"America/Toronto",
    "iso:country":"CA",
    "wof:name":"Tramore",
    "wof:placetype":"locality"
},
  "geometry": {"coordinates":[-77.46044999999999,45.62107],"type":"Point"}
}