{
  "type": "Feature",
  "properties": {
    "gn:admin1_code":"11.0",
    "gn:asciiname":"Brooksby",
    "gn:country_code":"CA",
    "gn:dem":431,
    "gn:feature_class":"P",
    "gn:feature_code":"PPL",
    "gn:name":"Brooksby",
    "gn:population":0,
    "gn:timezone":"America/Regina",
    "iso:country":"CA",
    "wof:name":"Brooksby",
    "wof:placetype":"locality"
},
  "geometry": {"coordinates":[-104.31765,53.00003],"type":"Point"}
}