{
  "type": "Feature",
  "properties": {
    "gn:gn_country":"CA",
    "gn:gn_fcode":"PPL",
    "gn:gn_pop":0,
    "iso:country":"CA",
    "name:baq_x_preferred":[
        "Saint-Casimir"
    ],
    "name:dut_x_preferred":[
        "Saint-Casimir"
    ],
    "name:eng_x_preferred":[
        "Saint-Casimir"
    ],
    "name:fre_x_preferred":[
        "Saint-Casimir"
    ],
    "name:ger_x_preferred":[
        "Saint-Casimir"
    ],
    "name:per_x_preferred":[
        "\u0633\u0646-\u06a9\u0627\u0632\u06cc\u0645\u06cc\u0631\u060c \u06a9\u0628\u06a9"
    ],
    "name:swe_x_preferred":[
        "Saint-Casimir"
    ],
    "name:urd_x_preferred":[
        "\u0633\u06cc\u0646\u0679-\u06a9\u0633\u0645\u06cc\u0631\u060c \u06a9\u06cc\u0648\u0628\u06a9"
    ],
    "qs_pg:aaroncc":"CA",
    "qs_pg:gn_country":"CA",
    "qs_pg:gn_fcode":"PPL",
    "qs_pg:gn_pop":0,
    "qs_pg:name":"St.-Casimir",
    "qs_pg:name_adm0":"Canada",
    "qs_pg:name_adm1":"Qu\u00e9bec",
    "qs_pg:photos":260,
    "qs_pg:photos_1k":53,
    "qs_pg:photos_9k":1,
    "qs_pg:photos_9r":4,
    "qs_pg:photos_all":260,
    "qs_pg:photos_sr":5,
    "qs_pg:pop_sr":0,
    "qs_pg:qs_pg_placetype":"locality",
    "qs_pg:qs_pg_placetype_gp":"Town",
    "qs_pg:woe_adm0":23424775,
    "woe:adm0_id":23424775,
    "woe:name_adm0":"Canada",
    "woe:name_adm1":"Qu\u00e9bec",
    "woe:placetype":"Town",
    "wof:name":"St.-Casimir",
    "wof:placetype":"locality"
},
  "geometry": {"coordinates":[-72.1324,46.65005],"type":"Point"}
}