{
  "type": "Feature",
  "properties": {
    "gn:country":"CA",
    "gn:fcode":"PPL",
    "gn:population":0,
    "iso:country":"CA",
    "name:deu_x_preferred":[
        "Arvida"
    ],
    "name:eng_x_preferred":[
        "Arvida"
    ],
    "name:fra_x_preferred":[
        "Arvida"
    ],
    "name:hye_x_preferred":[
        "\u0531\u0580\u057e\u056b\u0564\u0561"
    ],
    "name:ita_x_preferred":[
        "Arvida"
    ],
    "name:lit_x_preferred":[
        "Arvida"
    ],
    "name:spa_x_preferred":[
        "Arvida"
    ],
    "name:zho_x_preferred":[
        "\u4e9e\u7dad\u9054"
    ],
    "qs_pg:aaroncc":"CA",
    "qs_pg:gn_country":"CA",
    "qs_pg:gn_fcode":"PPL",
    "qs_pg:gn_pop":0,
    "qs_pg:name":"Arvida",
    "qs_pg:name_adm0":"Canada",
    "qs_pg:name_adm1":"Qu\u00e9bec",
    "qs_pg:photos":200,
    "qs_pg:photos_1k":41,
    "qs_pg:photos_9k":1,
    "qs_pg:photos_9r":4,
    "qs_pg:photos_all":200,
    "qs_pg:photos_sr":4,
    "qs_pg:pop_sr":0,
    "qs_pg:qs_pg_placetype":"locality",
    "qs_pg:qs_pg_placetype_gp":"Town",
    "qs_pg:woe_adm0":23424775,
    "woe:adm0_id":23424775,
    "woe:name_adm0":"Canada",
    "woe:name_adm1":"Qu\u00e9bec",
    "woe:placetype":"Town",
    "wof:name":"Arvida",
    "wof:placetype":"locality"
},
  "geometry": {"coordinates":[-71.17870000000001,48.42986],"type":"Point"}
}