{
  "type": "Feature",
  "properties": {
    "gn:admin1_code":"7",
    "gn:asciiname":"Ecum Secum West",
    "gn:country_code":"CA",
    "gn:dem":20,
    "gn:feature_class":"P",
    "gn:feature_code":"PPL",
    "gn:name":"Ecum Secum West",
    "gn:population":0,
    "gn:timezone":"America/Halifax",
    "iso:country":"CA",
    "wof:name":"Ecum Secum West",
    "wof:placetype":"locality"
},
  "geometry": {"coordinates":[-62.16601,44.96378],"type":"Point"}
}