{
  "type": "Feature",
  "properties": {
    "gn:admin1_code":"11",
    "gn:asciiname":"South Lakeview",
    "gn:country_code":"CA",
    "gn:dem":577,
    "gn:feature_class":"P",
    "gn:feature_code":"PPL",
    "gn:name":"South Lakeview",
    "gn:population":0,
    "gn:timezone":"America/Regina",
    "iso:country":"CA",
    "wof:name":"South Lakeview",
    "wof:placetype":"locality"
},
  "geometry": {"coordinates":[-104.62277,50.42393],"type":"Point"}
}