{
  "type": "Feature",
  "properties": {
    "gn:admin1_code":"8",
    "gn:asciiname":"Elsinore",
    "gn:country_code":"CA",
    "gn:dem":237,
    "gn:feature_class":"P",
    "gn:feature_code":"PPL",
    "gn:name":"Elsinore",
    "gn:population":0,
    "gn:timezone":"America/Toronto",
    "iso:country":"CA",
    "wof:name":"Elsinore",
    "wof:placetype":"locality"
},
  "geometry": {"coordinates":[-81.24306,44.52361],"type":"Point"}
}