{
  "type": "Feature",
  "properties": {
    "gn:admin1_code":"8",
    "gn:asciiname":"Foxey",
    "gn:country_code":"CA",
    "gn:dem":192,
    "gn:feature_class":"P",
    "gn:feature_code":"PPL",
    "gn:name":"Foxey",
    "gn:population":0,
    "gn:timezone":"America/Toronto",
    "iso:country":"CA",
    "wof:name":"Foxey",
    "wof:placetype":"locality"
},
  "geometry": {"coordinates":[-82.51222,45.87933],"type":"Point"}
}