{
  "type": "Feature",
  "properties": {
    "gn:admin1_code":"7",
    "gn:asciiname":"Pleasant River",
    "gn:country_code":"CA",
    "gn:dem":93,
    "gn:feature_class":"P",
    "gn:feature_code":"PPL",
    "gn:name":"Pleasant River",
    "gn:population":0,
    "gn:timezone":"America/Halifax",
    "iso:country":"CA",
    "wof:name":"Pleasant River",
    "wof:placetype":"locality"
},
  "geometry": {"coordinates":[-64.88194,44.43891],"type":"Point"}
}