{
  "type": "Feature",
  "properties": {
    "gn:admin1_code":"4.0",
    "gn:asciiname":"Anagance",
    "gn:country_code":"CA",
    "gn:dem":51,
    "gn:feature_class":"P",
    "gn:feature_code":"PPL",
    "gn:name":"Anagance",
    "gn:population":0,
    "gn:timezone":"America/Moncton",
    "iso:country":"CA",
    "name:ile_x_preferred":[
        "Anagance"
    ],
    "wof:name":"Anagance",
    "wof:placetype":"locality"
},
  "geometry": {"coordinates":[-65.25258000000001,45.86988],"type":"Point"}
}