{
  "type": "Feature",
  "properties": {
    "gn:admin1_code":"8.0",
    "gn:asciiname":"Banda",
    "gn:country_code":"CA",
    "gn:dem":266,
    "gn:feature_class":"P",
    "gn:feature_code":"PPL",
    "gn:name":"Banda",
    "gn:population":0,
    "gn:timezone":"America/Toronto",
    "iso:country":"CA",
    "wof:name":"Banda",
    "wof:placetype":"locality"
},
  "geometry": {"coordinates":[-80.06667,44.28722],"type":"Point"}
}