{
  "type": "Feature",
  "properties": {
    "gn:admin1_code":"4",
    "gn:asciiname":"Pennfield Corner",
    "gn:country_code":"CA",
    "gn:dem":75,
    "gn:feature_class":"P",
    "gn:feature_code":"PPL",
    "gn:name":"Pennfield Corner",
    "gn:population":0,
    "gn:timezone":"America/Moncton",
    "iso:country":"CA",
    "wof:name":"Pennfield Corner",
    "wof:placetype":"locality"
},
  "geometry": {"coordinates":[-66.7411,45.11163],"type":"Point"}
}