{
  "type": "Feature",
  "properties": {
    "gn:admin1_code":"4",
    "gn:asciiname":"Saint-Marcel",
    "gn:country_code":"CA",
    "gn:dem":23,
    "gn:feature_class":"P",
    "gn:feature_code":"PPL",
    "gn:name":"Saint-Marcel",
    "gn:population":0,
    "gn:timezone":"America/Moncton",
    "iso:country":"CA",
    "name:bar_x_preferred":[
        "Saint-Marcel"
    ],
    "name:ceb_x_preferred":[
        "Saint-Marcel"
    ],
    "name:deu_x_preferred":[
        "Saint-Marcel"
    ],
    "name:epo_x_preferred":[
        "Saint-Marcel"
    ],
    "name:eus_x_preferred":[
        "Saint-Marcel"
    ],
    "name:fra_x_preferred":[
        "Saint-Marcel"
    ],
    "name:hun_x_preferred":[
        "Saint-Marcel"
    ],
    "name:hye_x_preferred":[
        "\u054d\u0565\u0576 \u0544\u0561\u0580\u057d\u0565\u056c"
    ],
    "name:ita_x_preferred":[
        "Saint-Marcel"
    ],
    "name:nds_x_preferred":[
        "Saint-Marcel"
    ],
    "name:nld_x_preferred":[
        "Saint-Marcel"
    ],
    "name:oci_x_preferred":[
        "Sent Marc\u00e8l"
    ],
    "name:pms_x_preferred":[
        "Saint-Marcel"
    ],
    "name:pol_x_preferred":[
        "Saint-Marcel"
    ],
    "name:por_x_preferred":[
        "Saint-Marcel"
    ],
    "name:rus_x_preferred":[
        "\u0421\u0435\u043d-\u041c\u0430\u0440\u0441\u0435\u043b\u044c"
    ],
    "name:slk_x_preferred":[
        "Saint-Marcel"
    ],
    "name:spa_x_preferred":[
        "Saint-Marcel"
    ],
    "name:srp_x_preferred":[
        "\u0421\u0435\u043d-\u041c\u0430\u0440\u0441\u0435\u043b"
    ],
    "name:swe_x_preferred":[
        "Saint-Marcel"
    ],
    "name:ukr_x_preferred":[
        "\u0421\u0435\u043d-\u041c\u0430\u0440\u0441\u0435\u043b\u044c"
    ],
    "wof:name":"Saint-Marcel",
    "wof:placetype":"locality"
},
  "geometry": {"coordinates":[-64.58019,46.31907],"type":"Point"}
}