{
  "type": "Feature",
  "properties": {
    "gn:admin1_code":"8",
    "gn:asciiname":"Mount View",
    "gn:country_code":"CA",
    "gn:dem":498,
    "gn:feature_class":"P",
    "gn:feature_code":"PPL",
    "gn:name":"Mount View",
    "gn:population":0,
    "gn:timezone":"America/Toronto",
    "iso:country":"CA",
    "name:ceb_x_preferred":[
        "Mount View"
    ],
    "name:swe_x_preferred":[
        "Mount View"
    ],
    "wof:name":"Mount View",
    "wof:placetype":"locality"
},
  "geometry": {"coordinates":[-80.43143000000001,43.89987],"type":"Point"}
}