{
  "type": "Feature",
  "properties": {
    "gn:admin1_code":"3",
    "gn:asciiname":"Pine Bluff",
    "gn:country_code":"CA",
    "gn:dem":256,
    "gn:feature_class":"P",
    "gn:feature_code":"PPLL",
    "gn:name":"Pine Bluff",
    "gn:population":0,
    "gn:timezone":"America/Winnipeg",
    "iso:country":"CA",
    "wof:name":"Pine Bluff",
    "wof:placetype":"locality"
},
  "geometry": {"coordinates":[-100.66143,53.50946999999999],"type":"Point"}
}