{
  "type": "Feature",
  "properties": {
    "gn:admin1_code":"3",
    "gn:asciiname":"Pine Bluff",
    "gn:country_code":"CA",
    "gn:dem":256,
    "gn:feature_class":"P",
    "gn:feature_code":"PPLL",
    "gn:name":"Pine Bluff",
    "gn:population":0,
    "gn:timezone":"America/Winnipeg",
    "iso:country":"CA",
    "name:ben_x_preferred":[
        "\u09aa\u09be\u0987\u09a8 \u09ac\u09cd\u09b2\u09be\u09ab"
    ],
    "name:ell_x_preferred":[
        "\u03a0\u03ac\u03b9\u03bd \u039c\u03c0\u03bb\u03b1\u03c6"
    ],
    "name:hin_x_preferred":[
        "\u092a\u093e\u0907\u0928 \u092c\u094d\u0932\u092b\u093c"
    ],
    "name:ind_x_preferred":[
        "Pine Bluff"
    ],
    "wof:name":"Pine Bluff",
    "wof:placetype":"locality"
},
  "geometry": {"coordinates":[-100.66143,53.50947],"type":"Point"}
}