{
  "type": "Feature",
  "properties": {
    "gn:admin1_code":"8.0",
    "gn:asciiname":"Dufferin Bridge",
    "gn:country_code":"CA",
    "gn:dem":306,
    "gn:feature_class":"P",
    "gn:feature_code":"PPL",
    "gn:name":"Dufferin Bridge",
    "gn:population":0,
    "gn:timezone":"America/Toronto",
    "iso:country":"CA",
    "wof:name":"Dufferin Bridge",
    "wof:placetype":"locality"
},
  "geometry": {"coordinates":[-79.68194,45.47306],"type":"Point"}
}