{
  "type": "Feature",
  "properties": {
    "gn:admin1_code":"7",
    "gn:asciiname":"North Middleboro",
    "gn:country_code":"CA",
    "gn:dem":12,
    "gn:feature_class":"P",
    "gn:feature_code":"PPL",
    "gn:name":"North Middleboro",
    "gn:population":0,
    "gn:timezone":"America/Halifax",
    "iso:country":"CA",
    "wof:name":"North Middleboro",
    "wof:placetype":"locality"
},
  "geometry": {"coordinates":[-63.57787,45.77894000000001],"type":"Point"}
}