{
  "type": "Feature",
  "properties": {
    "gn:admin1_code":"8",
    "gn:asciiname":"Penhall",
    "gn:country_code":"CA",
    "gn:dem":250,
    "gn:feature_class":"P",
    "gn:feature_code":"PPL",
    "gn:name":"Penhall",
    "gn:population":0,
    "gn:timezone":"America/Toronto",
    "iso:country":"CA",
    "wof:name":"Penhall",
    "wof:placetype":"locality"
},
  "geometry": {"coordinates":[-83.94,49.74278],"type":"Point"}
}