{
  "type": "Feature",
  "properties": {
    "gn:admin1_code":"8.0",
    "gn:asciiname":"Camelot Beach",
    "gn:country_code":"CA",
    "gn:dem":180,
    "gn:feature_class":"P",
    "gn:feature_code":"PPL",
    "gn:name":"Camelot Beach",
    "gn:population":0,
    "gn:timezone":"America/Toronto",
    "iso:country":"CA",
    "wof:name":"Camelot Beach",
    "wof:placetype":"locality"
},
  "geometry": {"coordinates":[-79.30249999999999,42.87972],"type":"Point"}
}