{
  "type": "Feature",
  "properties": {
    "gn:country":"CA",
    "gn:fcode":"PPL",
    "gn:population":0,
    "iso:country":"CA",
    "name:bar_x_preferred":[
        "Glencoe"
    ],
    "name:bre_x_preferred":[
        "Glencoe"
    ],
    "name:cat_x_preferred":[
        "Glencoe"
    ],
    "name:ceb_x_preferred":[
        "Glencoe"
    ],
    "name:deu_x_preferred":[
        "Glencoe"
    ],
    "name:fra_x_preferred":[
        "Glencoe"
    ],
    "name:ita_x_preferred":[
        "Glencoe"
    ],
    "name:jpn_x_preferred":[
        "\u30b0\u30ec\u30f3\u30b3\u30fc"
    ],
    "name:kor_x_preferred":[
        "\uae00\ub80c\ucf54"
    ],
    "name:nld_x_preferred":[
        "Glencoe"
    ],
    "name:pol_x_preferred":[
        "Glencoe"
    ],
    "name:por_x_preferred":[
        "Glencoe"
    ],
    "name:rus_x_preferred":[
        "\u0413\u043b\u0435\u043d\u043a\u043e"
    ],
    "name:spa_x_preferred":[
        "Glencoe"
    ],
    "name:srp_x_preferred":[
        "\u0413\u043b\u0435\u043d\u043a\u043e"
    ],
    "name:swe_x_preferred":[
        "Glencoe"
    ],
    "name:ukr_x_preferred":[
        "\u0413\u043b\u0435\u043d\u043a\u043e"
    ],
    "name:vol_x_preferred":[
        "Glencoe"
    ],
    "qs_pg:aaroncc":"CA",
    "qs_pg:gn_country":"CA",
    "qs_pg:gn_fcode":"PPL",
    "qs_pg:gn_pop":0,
    "qs_pg:name":"Glencoe",
    "qs_pg:name_adm0":"Canada",
    "qs_pg:name_adm1":"Ontario",
    "qs_pg:photos":42,
    "qs_pg:photos_1k":9,
    "qs_pg:photos_9k":1,
    "qs_pg:photos_9r":2,
    "qs_pg:photos_all":42,
    "qs_pg:photos_sr":2,
    "qs_pg:pop_sr":0,
    "qs_pg:qs_pg_placetype":"locality",
    "qs_pg:qs_pg_placetype_gp":"Town",
    "qs_pg:woe_adm0":23424775,
    "woe:adm0_id":23424775,
    "woe:name_adm0":"Canada",
    "woe:name_adm1":"Ontario",
    "woe:placetype":"Town",
    "wof:name":"Glencoe",
    "wof:placetype":"locality"
},
  "geometry": {"coordinates":[-81.71648,42.75009],"type":"Point"}
}