{
  "type": "Feature",
  "properties": {
    "gn:admin1_code":"1",
    "gn:asciiname":"Northcliffe",
    "gn:country_code":"CA",
    "gn:dem":1191,
    "gn:feature_class":"P",
    "gn:feature_code":"PPLL",
    "gn:name":"Northcliffe",
    "gn:population":0,
    "gn:timezone":"America/Edmonton",
    "iso:country":"CA",
    "name:deu_x_preferred":[
        "Northcliffe"
    ],
    "name:nld_x_preferred":[
        "Northcliffe"
    ],
    "wof:name":"Northcliffe",
    "wof:placetype":"locality"
},
  "geometry": {"coordinates":[-113.45189999999999,49.21667],"type":"Point"}
}