{
  "type": "Feature",
  "properties": {
    "gn:admin1_code":"10",
    "gn:admin2_code":"02",
    "gn:admin3_code":"93042.0",
    "gn:asciiname":"Saint-Coeur-de-Marie",
    "gn:country_code":"CA",
    "gn:dem":119,
    "gn:feature_class":"P",
    "gn:feature_code":"PPL",
    "gn:name":"Saint-Coeur-de-Marie",
    "gn:population":0,
    "gn:timezone":"America/Toronto",
    "iso:country":"CA",
    "name:fra_x_preferred":[
        "Saint-C\u0153ur-de-Marie"
    ],
    "wof:name":"Saint-Coeur-de-Marie",
    "wof:placetype":"locality"
},
  "geometry": {"coordinates":[-71.6991,48.63339000000001],"type":"Point"}
}