{
  "type": "Feature",
  "properties": {
    "gn:admin1_code":"8",
    "gn:asciiname":"Harrisburg",
    "gn:country_code":"CA",
    "gn:dem":231,
    "gn:feature_class":"P",
    "gn:feature_code":"PPL",
    "gn:name":"Harrisburg",
    "gn:population":0,
    "gn:timezone":"America/Toronto",
    "iso:country":"CA",
    "wof:name":"Harrisburg",
    "wof:placetype":"locality"
},
  "geometry": {"coordinates":[-80.2129,43.23254],"type":"Point"}
}