{
  "type": "Feature",
  "properties": {
    "gn:admin1_code":"5",
    "gn:asciiname":"Great Codroy",
    "gn:country_code":"CA",
    "gn:dem":18,
    "gn:feature_class":"P",
    "gn:feature_code":"PPL",
    "gn:name":"Great Codroy",
    "gn:population":0,
    "gn:timezone":"America/St_Johns",
    "iso:country":"CA",
    "wof:name":"Great Codroy",
    "wof:placetype":"locality"
},
  "geometry": {"coordinates":[-59.26643000000001,47.83943],"type":"Point"}
}