{
  "type": "Feature",
  "properties": {
    "gn:admin1_code":"5.0",
    "gn:asciiname":"Back Shore",
    "gn:country_code":"CA",
    "gn:dem":0,
    "gn:feature_class":"P",
    "gn:feature_code":"PPLL",
    "gn:name":"Back Shore",
    "gn:population":0,
    "gn:timezone":"America/St_Johns",
    "iso:country":"CA",
    "wof:name":"Back Shore",
    "wof:placetype":"locality"
},
  "geometry": {"coordinates":[-53.59815,46.62209],"type":"Point"}
}