{
  "type": "Feature",
  "properties": {
    "gn:admin1_code":"7",
    "gn:asciiname":"Rear Forks",
    "gn:country_code":"CA",
    "gn:dem":98,
    "gn:feature_class":"P",
    "gn:feature_code":"PPLL",
    "gn:name":"Rear Forks",
    "gn:population":0,
    "gn:timezone":"America/Halifax",
    "iso:country":"CA",
    "wof:name":"Rear Forks",
    "wof:placetype":"locality"
},
  "geometry": {"coordinates":[-60.74849,46.20014000000001],"type":"Point"}
}