{
  "type": "Feature",
  "properties": {
    "gn:admin1_code":"8",
    "gn:asciiname":"Salem",
    "gn:country_code":"CA",
    "gn:dem":104,
    "gn:feature_class":"P",
    "gn:feature_code":"PPL",
    "gn:name":"Salem",
    "gn:population":0,
    "gn:timezone":"America/Toronto",
    "iso:country":"CA",
    "wof:name":"Salem",
    "wof:placetype":"locality"
},
  "geometry": {"coordinates":[-77.83878,44.0174],"type":"Point"}
}