{
  "type": "Feature",
  "properties": {
    "gn:admin1_code":"9.0",
    "gn:asciiname":"Belfast",
    "gn:country_code":"CA",
    "gn:dem":14,
    "gn:feature_class":"P",
    "gn:feature_code":"PPLL",
    "gn:name":"Belfast",
    "gn:population":1839,
    "gn:timezone":"America/Halifax",
    "iso:country":"CA",
    "name:ceb_x_preferred":[
        "Belfast"
    ],
    "name:fra_x_preferred":[
        "Belfast"
    ],
    "name:swe_x_preferred":[
        "Belfast"
    ],
    "wof:name":"Belfast",
    "wof:placetype":"locality",
    "wof:population":1839
},
  "geometry": {"coordinates":[-62.88197,46.08341],"type":"Point"}
}