{
  "type": "Feature",
  "properties": {
    "gn:admin1_code":"9.0",
    "gn:asciiname":"Belfast",
    "gn:country_code":"CA",
    "gn:dem":14,
    "gn:feature_class":"P",
    "gn:feature_code":"PPLL",
    "gn:name":"Belfast",
    "gn:population":1839,
    "gn:timezone":"America/Halifax",
    "iso:country":"CA",
    "name:ara_x_preferred":[
        "\u0628\u0644\u0641\u0627\u0633\u062a"
    ],
    "name:ben_x_preferred":[
        "\u09ac\u09c7\u09b2\u09ab\u09be\u09b8\u09cd\u099f"
    ],
    "name:ceb_x_preferred":[
        "Belfast"
    ],
    "name:deu_x_preferred":[
        "Belfast"
    ],
    "name:ell_x_preferred":[
        "\u039c\u03c0\u03ad\u03bb\u03c6\u03b1\u03c3\u03c4"
    ],
    "name:fas_x_preferred":[
        "\u0628\u0644\u0641\u0627\u0633\u062a"
    ],
    "name:fra_x_preferred":[
        "Belfast"
    ],
    "name:heb_x_preferred":[
        "\u05d1\u05dc\u05e4\u05e1\u05d8"
    ],
    "name:hin_x_preferred":[
        "\u092c\u0947\u0932\u092b\u093e\u0938\u094d\u091f"
    ],
    "name:hun_x_preferred":[
        "Belfast"
    ],
    "name:ind_x_preferred":[
        "Belfast"
    ],
    "name:ita_x_preferred":[
        "Belfast"
    ],
    "name:nld_x_preferred":[
        "Belfast"
    ],
    "name:pol_x_preferred":[
        "Belfast"
    ],
    "name:por_x_preferred":[
        "Belfast"
    ],
    "name:spa_x_preferred":[
        "Belfast"
    ],
    "name:swe_x_preferred":[
        "Belfast"
    ],
    "name:tur_x_preferred":[
        "Belfast"
    ],
    "name:urd_x_preferred":[
        "\u0628\u06cc\u0644 \u0641\u0627\u0633\u0679"
    ],
    "name:vie_x_preferred":[
        "Belfast"
    ],
    "wof:name":"Belfast",
    "wof:placetype":"locality",
    "wof:population":1839
},
  "geometry": {"coordinates":[-62.88197,46.08341],"type":"Point"}
}