{
  "type": "Feature",
  "properties": {
    "gn:admin1_code":"11.0",
    "gn:asciiname":"Assiniboia East",
    "gn:country_code":"CA",
    "gn:dem":578,
    "gn:feature_class":"P",
    "gn:feature_code":"PPL",
    "gn:name":"Assiniboia East",
    "gn:population":0,
    "gn:timezone":"America/Regina",
    "iso:country":"CA",
    "wof:name":"Assiniboia East",
    "wof:placetype":"locality"
},
  "geometry": {"coordinates":[-104.57832999999999,50.43476],"type":"Point"}
}