{
  "type": "Feature",
  "properties": {
    "gn:admin1_code":"7",
    "gn:asciiname":"North Preston",
    "gn:country_code":"CA",
    "gn:dem":90,
    "gn:feature_class":"P",
    "gn:feature_code":"PPL",
    "gn:name":"North Preston",
    "gn:population":0,
    "gn:timezone":"America/Halifax",
    "iso:country":"CA",
    "name:deu_x_preferred":[
        "North Preston"
    ],
    "wof:name":"North Preston",
    "wof:placetype":"locality"
},
  "geometry": {"coordinates":[-63.46453,44.74618],"type":"Point"}
}