{
  "type": "Feature",
  "properties": {
    "iso:country":"CA",
    "name:eng_x_preferred":[
        "North Flats"
    ],
    "name:unk_x_variant":[
        "North Flats"
    ],
    "qs:gn_adm0_cc":"CA",
    "qs:gn_local":6071618,
    "qs:gn_nam_loc":"Medicine Hat, Alberta, Alberta, CA",
    "qs:gn_namadm1":"01",
    "qs:local_max":559,
    "qs:local_sum":2195,
    "qs:localhoods":15,
    "qs:name":"North Flats",
    "qs:name_adm0":"Canada",
    "qs:name_adm1":"Alberta",
    "qs:name_adm2":"Alberta",
    "qs:name_local":"Medicine Hat",
    "qs:photo_max":3,
    "qs:photo_sum":5,
    "qs:placetype":"Suburb",
    "qs:quad_count":3,
    "qs:woe_adm0":23424775,
    "qs:woe_adm1":2344915,
    "qs:woe_adm2":29375228,
    "qs:woe_lau":0,
    "qs:woe_local":8623,
    "qs:woe_ver":"7.10.0",
    "wof:lang":[
        "eng"
    ],
    "wof:name":"North Flats",
    "wof:placetype":"neighbourhood"
},
  "geometry": {"coordinates":[-110.620789,50.032093],"type":"Point"}
}