{
  "type": "Feature",
  "properties": {
    "gn:admin1_code":"1",
    "gn:asciiname":"Tristram",
    "gn:country_code":"CA",
    "gn:dem":832,
    "gn:feature_class":"P",
    "gn:feature_code":"PPLL",
    "gn:name":"Tristram",
    "gn:population":0,
    "gn:timezone":"America/Edmonton",
    "iso:country":"CA",
    "name:bre_x_preferred":[
        "Tristram"
    ],
    "name:deu_x_preferred":[
        "Tristram"
    ],
    "name:fra_x_preferred":[
        "Tristram"
    ],
    "name:swe_x_preferred":[
        "Tristram"
    ],
    "wof:name":"Tristram",
    "wof:placetype":"locality"
},
  "geometry": {"coordinates":[-113.25197,52.60012],"type":"Point"}
}