{
  "type": "Feature",
  "properties": {
    "gn:admin1_code":"7",
    "gn:asciiname":"Upper Kemptown",
    "gn:country_code":"CA",
    "gn:dem":216,
    "gn:feature_class":"P",
    "gn:feature_code":"PPL",
    "gn:name":"Upper Kemptown",
    "gn:population":0,
    "gn:timezone":"America/Halifax",
    "iso:country":"CA",
    "wof:name":"Upper Kemptown",
    "wof:placetype":"locality"
},
  "geometry": {"coordinates":[-63.11237,45.53564],"type":"Point"}
}