{
  "type": "Feature",
  "properties": {
    "iso:country":"CA",
    "name:cat_x_preferred":[
        "Vell Sud"
    ],
    "name:ell_x_preferred":[
        "\u03a0\u03b1\u03bb\u03b1\u03b9\u03cc\u03c2 \u039d\u03cc\u03c4\u03bf\u03c2"
    ],
    "name:eng_x_preferred":[
        "Old South"
    ],
    "name:est_x_preferred":[
        "Vana-L\u00f5una"
    ],
    "name:eus_x_preferred":[
        "Old South"
    ],
    "name:fra_x_preferred":[
        "Old South"
    ],
    "name:jpn_x_preferred":[
        "\u30aa\u30fc\u30eb\u30c9\u30b5\u30a6\u30b9"
    ],
    "name:nld_x_preferred":[
        "Old South"
    ],
    "name:rus_x_preferred":[
        "\u0421\u0442\u0430\u0440\u044b\u0439 \u042e\u0433"
    ],
    "name:spa_x_preferred":[
        "Viejo Sur"
    ],
    "name:zho_x_preferred":[
        "\u8001\u5357\u90e8"
    ],
    "qs:gn_adm0_cc":"CA",
    "qs:gn_local":6141190,
    "qs:gn_nam_loc":"sarnia",
    "qs:gn_namadm1":"08",
    "qs:local_max":1209,
    "qs:local_sum":4368,
    "qs:localhoods":10,
    "qs:name":"Old South",
    "qs:name_adm0":"Canada",
    "qs:name_adm1":"Ontario",
    "qs:name_adm2":"Lambton",
    "qs:name_local":"Sarnia",
    "qs:photo_max":27,
    "qs:photo_sum":45,
    "qs:placetype":"Suburb",
    "qs:quad_count":6,
    "qs:woe_adm0":23424775,
    "qs:woe_adm1":2344922,
    "qs:woe_adm2":29375144,
    "qs:woe_funk":"Grouping neighborhood",
    "qs:woe_lau":0,
    "qs:woe_local":1646,
    "qs:woe_ver":"7.10.0",
    "wd:wordcount":427,
    "wof:lang":[
        "eng"
    ],
    "wof:name":"Old South",
    "wof:placetype":"neighbourhood"
},
  "geometry": {"coordinates":[-82.399597,42.963704],"type":"Point"}
}