{
  "type": "Feature",
  "properties": {
    "iso:country":"CA",
    "name:eng_x_preferred":[
        "Old South"
    ],
    "name:unk_x_variant":[
        "Old South"
    ],
    "qs:gn_adm0_cc":"CA",
    "qs:gn_local":6141190,
    "qs:gn_nam_loc":"sarnia",
    "qs:gn_namadm1":"08",
    "qs:local_max":1209,
    "qs:local_sum":4368,
    "qs:localhoods":10,
    "qs:name":"Old South",
    "qs:name_adm0":"Canada",
    "qs:name_adm1":"Ontario",
    "qs:name_adm2":"Lambton",
    "qs:name_local":"Sarnia",
    "qs:photo_max":27,
    "qs:photo_sum":45,
    "qs:placetype":"Suburb",
    "qs:quad_count":6,
    "qs:woe_adm0":23424775,
    "qs:woe_adm1":2344922,
    "qs:woe_adm2":29375144,
    "qs:woe_funk":"Grouping neighborhood",
    "qs:woe_lau":0,
    "qs:woe_local":1646,
    "qs:woe_ver":"7.10.0",
    "wd:wordcount":427,
    "wof:lang":[
        "eng"
    ],
    "wof:name":"Old South",
    "wof:placetype":"neighbourhood"
},
  "geometry": {"coordinates":[-82.399597,42.963704],"type":"Point"}
}