{
  "type": "Feature",
  "properties": {
    "gn:admin1_code":"2.0",
    "gn:asciiname":"Chapman Camp",
    "gn:country_code":"CA",
    "gn:dem":1063,
    "gn:feature_class":"P",
    "gn:feature_code":"PPL",
    "gn:name":"Chapman Camp",
    "gn:population":0,
    "gn:timezone":"America/Edmonton",
    "iso:country":"CA",
    "wof:name":"Chapman Camp",
    "wof:placetype":"locality"
},
  "geometry": {"coordinates":[-115.96666999999999,49.66667],"type":"Point"}
}