{
  "type": "Feature",
  "properties": {
    "gn:admin1_code":"10.0",
    "gn:admin2_code":"13.0",
    "gn:admin3_code":"65005.0",
    "gn:asciiname":"Champ-Fleuri",
    "gn:country_code":"CA",
    "gn:dem":39,
    "gn:feature_class":"P",
    "gn:feature_code":"PPL",
    "gn:name":"Champ-Fleuri",
    "gn:population":0,
    "gn:timezone":"America/Toronto",
    "iso:country":"CA",
    "wof:name":"Champ-Fleuri",
    "wof:placetype":"locality"
},
  "geometry": {"coordinates":[-73.78209,45.58921],"type":"Point"}
}