{
  "type": "Feature",
  "properties": {
    "gn:admin1_code":"8",
    "gn:asciiname":"Scotch Corners",
    "gn:country_code":"CA",
    "gn:dem":146,
    "gn:feature_class":"P",
    "gn:feature_code":"PPL",
    "gn:name":"Scotch Corners",
    "gn:population":0,
    "gn:timezone":"America/Toronto",
    "iso:country":"CA",
    "wof:name":"Scotch Corners",
    "wof:placetype":"locality"
},
  "geometry": {"coordinates":[-76.19716,45.07872],"type":"Point"}
}