{
  "type": "Feature",
  "properties": {
    "gn:admin1_code":"7",
    "gn:asciiname":"Rock Elm",
    "gn:country_code":"CA",
    "gn:dem":7,
    "gn:feature_class":"P",
    "gn:feature_code":"PPLL",
    "gn:name":"Rock Elm",
    "gn:population":0,
    "gn:timezone":"America/Glace_Bay",
    "iso:country":"CA",
    "wof:name":"Rock Elm",
    "wof:placetype":"locality"
},
  "geometry": {"coordinates":[-60.33176,45.91684],"type":"Point"}
}