{
  "type": "Feature",
  "properties": {
    "gn:country":"CA",
    "gn:fcode":"ADMD",
    "gn:pop":0,
    "iso:country":"CA",
    "name:eng_x_preferred":[
        "Renfrew"
    ],
    "qs:name":"Renfrew",
    "qs:photos_9r":0,
    "qs:photos_sr":0,
    "qs:pop_sr":"0",
    "wd:wordcount":1499,
    "wof:name":"Renfrew",
    "wof:placetype":"localadmin",
    "wof:population":0
},
  "geometry": {"coordinates":[-77.08275,45.50011],"type":"Point"}
}