{
  "type": "Feature",
  "properties": {
    "gn:country":"CA",
    "gn:fcode":"ADMD",
    "gn:population":0,
    "iso:country":"CA",
    "name:ara_x_preferred":[
        "\u0631\u064a\u0646\u0641\u0631\u0648"
    ],
    "name:azb_x_preferred":[
        "\u0631\u0646\u0641\u0631\u0648"
    ],
    "name:bel_x_preferred":[
        "\u0420\u044d\u043d\u0444\u0440\u0443"
    ],
    "name:bul_x_preferred":[
        "\u0420\u0435\u043d\u0444\u0440\u0443"
    ],
    "name:ceb_x_preferred":[
        "Renfrew"
    ],
    "name:deu_x_preferred":[
        "Renfrew"
    ],
    "name:eng_x_preferred":[
        "Renfrew"
    ],
    "name:eus_x_preferred":[
        "Renfrew"
    ],
    "name:fas_x_preferred":[
        "\u0631\u0646\u0641\u0631\u0648"
    ],
    "name:fin_x_preferred":[
        "Renfrew"
    ],
    "name:fra_x_preferred":[
        "Renfrew"
    ],
    "name:gla_x_preferred":[
        "Rinn Fri\u00f9"
    ],
    "name:gle_x_preferred":[
        "Rinn Fri\u00fa"
    ],
    "name:ita_x_preferred":[
        "Renfrew"
    ],
    "name:kor_x_preferred":[
        "\ub80c\ud504\ub8e8"
    ],
    "name:nld_x_preferred":[
        "Renfrew"
    ],
    "name:pol_x_preferred":[
        "Renfrew"
    ],
    "name:rus_x_preferred":[
        "\u0420\u0435\u043d\u0444\u0440\u0443"
    ],
    "name:sco_x_preferred":[
        "Renfrew"
    ],
    "name:spa_x_preferred":[
        "Renfrew"
    ],
    "name:swe_x_preferred":[
        "Renfrew"
    ],
    "name:szl_x_preferred":[
        "Renfrew"
    ],
    "name:tur_x_preferred":[
        "Renfrew"
    ],
    "name:ukr_x_preferred":[
        "\u0420\u0435\u043d\u0444\u0440\u044e"
    ],
    "name:zho_x_preferred":[
        "\u502b\u5f17\u9b6f"
    ],
    "qs:name":"Renfrew",
    "qs:photos_9r":0,
    "qs:photos_sr":0,
    "qs:pop_sr":"0",
    "wd:wordcount":1499,
    "wof:name":"Renfrew",
    "wof:placetype":"localadmin",
    "wof:population":0
},
  "geometry": {"coordinates":[-77.08275,45.50011],"type":"Point"}
}