{
  "type": "Feature",
  "properties": {
    "gn:admin1_code":"8",
    "gn:asciiname":"Quarindale",
    "gn:country_code":"CA",
    "gn:dem":391,
    "gn:feature_class":"P",
    "gn:feature_code":"PPLL",
    "gn:name":"Quarindale",
    "gn:population":0,
    "gn:timezone":"America/Toronto",
    "iso:country":"CA",
    "wof:name":"Quarindale",
    "wof:placetype":"locality"
},
  "geometry": {"coordinates":[-80.74970999999999,43.68649],"type":"Point"}
}