{
  "type": "Feature",
  "properties": {
    "gn:admin1_code":"8",
    "gn:asciiname":"Hardrock",
    "gn:country_code":"CA",
    "gn:dem":327,
    "gn:feature_class":"P",
    "gn:feature_code":"PPLL",
    "gn:name":"Hardrock",
    "gn:population":0,
    "gn:timezone":"America/Toronto",
    "iso:country":"CA",
    "wof:name":"Hardrock",
    "wof:placetype":"locality"
},
  "geometry": {"coordinates":[-86.88325999999998,49.71683],"type":"Point"}
}