{
  "type": "Feature",
  "properties": {
    "gn:admin1_code":"10.0",
    "gn:admin2_code":"14.0",
    "gn:admin3_code":"63060.0",
    "gn:asciiname":"Domaine-du-Lac-des-Fourches",
    "gn:country_code":"CA",
    "gn:dem":90,
    "gn:feature_class":"P",
    "gn:feature_code":"PPL",
    "gn:name":"Domaine-du-Lac-des-Fourches",
    "gn:population":0,
    "gn:timezone":"America/Toronto",
    "iso:country":"CA",
    "wof:name":"Domaine-du-Lac-des-Fourches",
    "wof:placetype":"locality"
},
  "geometry": {"coordinates":[-73.73487,45.93754000000001],"type":"Point"}
}