{
  "type": "Feature",
  "properties": {
    "gn:admin1_code":"8.0",
    "gn:asciiname":"Belmeade",
    "gn:country_code":"CA",
    "gn:dem":82,
    "gn:feature_class":"P",
    "gn:feature_code":"PPL",
    "gn:name":"Belmeade",
    "gn:population":0,
    "gn:timezone":"America/Toronto",
    "iso:country":"CA",
    "wof:name":"Belmeade",
    "wof:placetype":"locality"
},
  "geometry": {"coordinates":[-75.49319,45.12795],"type":"Point"}
}