{
  "type": "Feature",
  "properties": {
    "iso:country":"CA",
    "name:ceb_x_preferred":[
        "Sydenham"
    ],
    "name:deu_x_preferred":[
        "Sydenham"
    ],
    "name:eng_x_preferred":[
        "Sydenham"
    ],
    "name:fra_x_preferred":[
        "Sydenham"
    ],
    "name:nld_x_preferred":[
        "Sydenham"
    ],
    "name:pol_x_preferred":[
        "Sydenham"
    ],
    "name:ron_x_preferred":[
        "Sydenham"
    ],
    "name:swe_x_preferred":[
        "Sydenham"
    ],
    "qs:gn_adm0_cc":"CA",
    "qs:gn_local":5992500,
    "qs:gn_nam_loc":"kingston",
    "qs:gn_namadm1":"08",
    "qs:local_max":7347,
    "qs:local_sum":21295,
    "qs:localhoods":36,
    "qs:name":"Sydenham",
    "qs:name_adm0":"Canada",
    "qs:name_adm1":"Ontario",
    "qs:name_adm2":"Frontenac",
    "qs:name_local":"Kingston",
    "qs:photo_max":1941,
    "qs:photo_sum":7347,
    "qs:placetype":"Suburb",
    "qs:quad_count":56,
    "qs:woe_adm0":23424775,
    "qs:woe_adm1":2344922,
    "qs:woe_adm2":29375131,
    "qs:woe_lau":0,
    "qs:woe_local":4145,
    "qs:woe_ver":"7.10.0",
    "wof:lang":[
        "eng"
    ],
    "wof:name":"Sydenham",
    "wof:placetype":"neighbourhood"
},
  "geometry": {"coordinates":[-76.48063500000001,44.229724],"type":"Point"}
}