{
  "type": "Feature",
  "properties": {
    "gn:admin1_code":"3",
    "gn:asciiname":"Gilwell Estates",
    "gn:country_code":"CA",
    "gn:dem":222,
    "gn:feature_class":"P",
    "gn:feature_code":"PPLL",
    "gn:name":"Gilwell Estates",
    "gn:population":0,
    "gn:timezone":"America/Winnipeg",
    "iso:country":"CA",
    "wof:name":"Gilwell Estates",
    "wof:placetype":"locality"
},
  "geometry": {"coordinates":[-96.99396,50.67192],"type":"Point"}
}