{
  "type": "Feature",
  "properties": {
    "gn:admin1_code":"1.0",
    "gn:asciiname":"Crooked Creek",
    "gn:country_code":"CA",
    "gn:dem":662,
    "gn:feature_class":"P",
    "gn:feature_code":"PPL",
    "gn:name":"Crooked Creek",
    "gn:population":0,
    "gn:timezone":"America/Edmonton",
    "iso:country":"CA",
    "wof:name":"Crooked Creek",
    "wof:placetype":"locality"
},
  "geometry": {"coordinates":[-117.88972,55.17083],"type":"Point"}
}