{
  "type": "Feature",
  "properties": {
    "gn:admin1_code":"7.0",
    "gn:asciiname":"Avondale",
    "gn:country_code":"CA",
    "gn:dem":21,
    "gn:feature_class":"P",
    "gn:feature_code":"PPL",
    "gn:name":"Avondale",
    "gn:population":0,
    "gn:timezone":"America/Halifax",
    "iso:country":"CA",
    "name:bar_x_preferred":[
        "Avondale"
    ],
    "name:ceb_x_preferred":[
        "Avondale"
    ],
    "name:deu_x_preferred":[
        "Avondale"
    ],
    "name:fra_x_preferred":[
        "Avondale"
    ],
    "name:ita_x_preferred":[
        "Avondale"
    ],
    "name:nld_x_preferred":[
        "Avondale"
    ],
    "name:pol_x_preferred":[
        "Avondale"
    ],
    "name:por_x_preferred":[
        "Avondale"
    ],
    "name:ron_x_preferred":[
        "Avondale"
    ],
    "name:rus_x_preferred":[
        "\u042d\u0439\u0432\u043e\u043d\u0434\u0435\u0439\u043b"
    ],
    "name:spa_x_preferred":[
        "Avondale"
    ],
    "name:srp_x_preferred":[
        "\u0410\u0432\u043e\u043d\u0434\u0435\u0458\u043b"
    ],
    "name:swe_x_preferred":[
        "Avondale"
    ],
    "name:ukr_x_preferred":[
        "\u0415\u0439\u0432\u043e\u043d\u0435\u0439\u043b"
    ],
    "name:urd_x_preferred":[
        "\u0627\u06cc\u0648\u0646\u0688\u06cc\u0644"
    ],
    "name:vol_x_preferred":[
        "Avondale"
    ],
    "wof:name":"Avondale",
    "wof:placetype":"locality"
},
  "geometry": {"coordinates":[-62.29983000000001,45.63651],"type":"Point"}
}