{
  "type": "Feature",
  "properties": {
    "gn:admin1_code":"10.0",
    "gn:admin2_code":"12",
    "gn:admin3_code":"31035.0",
    "gn:asciiname":"Belmina",
    "gn:country_code":"CA",
    "gn:dem":256,
    "gn:feature_class":"P",
    "gn:feature_code":"PPL",
    "gn:name":"Belmina",
    "gn:population":0,
    "gn:timezone":"America/Toronto",
    "iso:country":"CA",
    "wof:name":"Belmina",
    "wof:placetype":"locality"
},
  "geometry": {"coordinates":[-71.47481999999999,45.98642],"type":"Point"}
}