{
  "type": "Feature",
  "properties": {
    "gn:admin1_code":"2",
    "gn:asciiname":"Ogden",
    "gn:country_code":"CA",
    "gn:dem":974,
    "gn:feature_class":"P",
    "gn:feature_code":"PPLL",
    "gn:name":"Ogden",
    "gn:population":0,
    "gn:timezone":"America/Vancouver",
    "iso:country":"CA",
    "wof:name":"Ogden",
    "wof:placetype":"locality"
},
  "geometry": {"coordinates":[-122.825,50.78166],"type":"Point"}
}