{
  "type": "Feature",
  "properties": {
    "gn:admin1_code":"2",
    "gn:asciiname":"Ogden",
    "gn:country_code":"CA",
    "gn:dem":974,
    "gn:feature_class":"P",
    "gn:feature_code":"PPLL",
    "gn:name":"Ogden",
    "gn:population":0,
    "gn:timezone":"America/Vancouver",
    "iso:country":"CA",
    "name:cat_x_preferred":[
        "Ogden"
    ],
    "name:ceb_x_preferred":[
        "Ogden"
    ],
    "name:ces_x_preferred":[
        "Ogden"
    ],
    "name:deu_x_preferred":[
        "Ogden"
    ],
    "name:fin_x_preferred":[
        "Ogden"
    ],
    "name:fra_x_preferred":[
        "Ogden"
    ],
    "name:heb_x_preferred":[
        "\u05d0\u05d5\u05d2\u05d3\u05df"
    ],
    "name:ita_x_preferred":[
        "Ogden"
    ],
    "name:jpn_x_preferred":[
        "\u30aa\u30b0\u30c7\u30f3"
    ],
    "name:kor_x_preferred":[
        "\uc624\uadf8\ub358"
    ],
    "name:nld_x_preferred":[
        "Ogden"
    ],
    "name:nor_x_preferred":[
        "Ogden"
    ],
    "name:pol_x_preferred":[
        "Ogden"
    ],
    "name:por_x_preferred":[
        "Ogden"
    ],
    "name:rus_x_preferred":[
        "\u041e\u0433\u0434\u0435\u043d"
    ],
    "name:spa_x_preferred":[
        "Ogden"
    ],
    "name:srp_x_preferred":[
        "\u041e\u0433\u0434\u0435\u043d"
    ],
    "name:swe_x_preferred":[
        "Ogden"
    ],
    "name:zho_x_preferred":[
        "\u5965\u683c\u767b"
    ],
    "wof:name":"Ogden",
    "wof:placetype":"locality"
},
  "geometry": {"coordinates":[-122.825,50.78166],"type":"Point"}
}