{
  "type": "Feature",
  "properties": {
    "gn:admin1_code":"8",
    "gn:asciiname":"New Park",
    "gn:country_code":"CA",
    "gn:dem":346,
    "gn:feature_class":"P",
    "gn:feature_code":"PPL",
    "gn:name":"New Park",
    "gn:population":0,
    "gn:timezone":"America/Toronto",
    "iso:country":"CA",
    "wof:name":"New Park",
    "wof:placetype":"locality"
},
  "geometry": {"coordinates":[-78.66889,44.06472],"type":"Point"}
}