{
  "type": "Feature",
  "properties": {
    "gn:admin1_code":"2.0",
    "gn:asciiname":"Callison Ranch",
    "gn:country_code":"CA",
    "gn:dem":982,
    "gn:feature_class":"P",
    "gn:feature_code":"PPLL",
    "gn:name":"Callison Ranch",
    "gn:population":0,
    "gn:timezone":"America/Vancouver",
    "iso:country":"CA",
    "wof:name":"Callison Ranch",
    "wof:placetype":"locality"
},
  "geometry": {"coordinates":[-131.68695,58.63283000000001],"type":"Point"}
}