{
  "type": "Feature",
  "properties": {
    "gn:admin1_code":"10",
    "gn:admin2_code":"15.0",
    "gn:admin3_code":"76052.0",
    "gn:asciiname":"Kilmar",
    "gn:country_code":"CA",
    "gn:dem":247,
    "gn:feature_class":"P",
    "gn:feature_code":"PPL",
    "gn:name":"Kilmar",
    "gn:population":0,
    "gn:timezone":"America/Toronto",
    "iso:country":"CA",
    "wof:name":"Kilmar",
    "wof:placetype":"locality"
},
  "geometry": {"coordinates":[-74.61518000000002,45.76977],"type":"Point"}
}