{
  "type": "Feature",
  "properties": {
    "gn:admin1_code":"11",
    "gn:asciiname":"Matador",
    "gn:country_code":"CA",
    "gn:dem":666,
    "gn:feature_class":"P",
    "gn:feature_code":"PPL",
    "gn:name":"Matador",
    "gn:population":0,
    "gn:timezone":"America/Regina",
    "iso:country":"CA",
    "wof:name":"Matador",
    "wof:placetype":"locality"
},
  "geometry": {"coordinates":[-107.95137,50.80008],"type":"Point"}
}