{
  "type": "Feature",
  "properties": {
    "gn:admin1_code":"8.0",
    "gn:asciiname":"Deloro",
    "gn:country_code":"CA",
    "gn:dem":209,
    "gn:feature_class":"P",
    "gn:feature_code":"PPL",
    "gn:name":"Deloro",
    "gn:population":0,
    "gn:timezone":"America/Toronto",
    "iso:country":"CA",
    "wof:name":"Deloro",
    "wof:placetype":"locality"
},
  "geometry": {"coordinates":[-77.61619,44.51682],"type":"Point"}
}