{
  "type": "Feature",
  "properties": {
    "gn:admin1_code":"3.0",
    "gn:asciiname":"Wisla",
    "gn:country_code":"CA",
    "gn:dem":615,
    "gn:feature_class":"P",
    "gn:feature_code":"PPLL",
    "gn:name":"Wisla",
    "gn:population":0,
    "gn:timezone":"America/Winnipeg",
    "iso:country":"CA",
    "wof:name":"Wisla",
    "wof:placetype":"locality"
},
  "geometry": {"coordinates":[-100.39335,50.59581],"type":"Point"}
}