{
  "type": "Feature",
  "properties": {
    "gn:admin1_code":"11",
    "gn:asciiname":"Lampard",
    "gn:country_code":"CA",
    "gn:dem":525,
    "gn:feature_class":"P",
    "gn:feature_code":"PPLL",
    "gn:name":"Lampard",
    "gn:population":0,
    "gn:timezone":"America/Regina",
    "iso:country":"CA",
    "wof:name":"Lampard",
    "wof:placetype":"locality"
},
  "geometry": {"coordinates":[-104.55108,51.93334],"type":"Point"}
}