{
  "type": "Feature",
  "properties": {
    "gn:admin1_code":"8",
    "gn:asciiname":"Lake Charles",
    "gn:country_code":"CA",
    "gn:dem":249,
    "gn:feature_class":"P",
    "gn:feature_code":"PPL",
    "gn:name":"Lake Charles",
    "gn:population":0,
    "gn:timezone":"America/Toronto",
    "iso:country":"CA",
    "name:ceb_x_preferred":[
        "Lake Charles"
    ],
    "name:swe_x_preferred":[
        "Lake Charles"
    ],
    "wof:name":"Lake Charles",
    "wof:placetype":"locality"
},
  "geometry": {"coordinates":[-81.01179999999999,44.75963],"type":"Point"}
}