{
  "type": "Feature",
  "properties": {
    "gn:admin1_code":"11",
    "gn:asciiname":"Saint-Front",
    "gn:country_code":"CA",
    "gn:dem":559,
    "gn:feature_class":"P",
    "gn:feature_code":"PPLL",
    "gn:name":"Saint-Front",
    "gn:population":0,
    "gn:timezone":"America/Regina",
    "iso:country":"CA",
    "name:cat_x_preferred":[
        "Sent Front"
    ],
    "name:ceb_x_preferred":[
        "Saint-Front"
    ],
    "name:deu_x_preferred":[
        "Saint-Front"
    ],
    "name:fra_x_preferred":[
        "Saint-Front"
    ],
    "name:ita_x_preferred":[
        "Saint-Front"
    ],
    "name:nds_x_preferred":[
        "Saint-Front"
    ],
    "name:nld_x_preferred":[
        "Saint-Front"
    ],
    "name:pol_x_preferred":[
        "Saint-Front"
    ],
    "name:por_x_preferred":[
        "Saint-Front"
    ],
    "name:rus_x_preferred":[
        "\u0421\u0435\u043d-\u0424\u0440\u043e\u043d"
    ],
    "name:slk_x_preferred":[
        "Saint-Front"
    ],
    "name:spa_x_preferred":[
        "Saint-Front"
    ],
    "name:swe_x_preferred":[
        "Saint-Front"
    ],
    "name:ukr_x_preferred":[
        "\u0421\u0435\u043d-\u0424\u0440\u043e\u043d"
    ],
    "wof:name":"Saint-Front",
    "wof:placetype":"locality"
},
  "geometry": {"coordinates":[-104.16771,52.36671],"type":"Point"}
}