{
  "type": "Feature",
  "properties": {
    "gn:admin1_code":"8",
    "gn:asciiname":"Hockley",
    "gn:country_code":"CA",
    "gn:dem":274,
    "gn:feature_class":"P",
    "gn:feature_code":"PPL",
    "gn:name":"Hockley",
    "gn:population":0,
    "gn:timezone":"America/Toronto",
    "iso:country":"CA",
    "name:ceb_x_preferred":[
        "Hockley"
    ],
    "name:gle_x_preferred":[
        "Hockley"
    ],
    "name:ita_x_preferred":[
        "Hockley"
    ],
    "name:nld_x_preferred":[
        "Hockley"
    ],
    "name:pol_x_preferred":[
        "Hockley"
    ],
    "name:swe_x_preferred":[
        "Hockley"
    ],
    "wof:name":"Hockley",
    "wof:placetype":"locality"
},
  "geometry": {"coordinates":[-79.96843,44.02181],"type":"Point"}
}