{
  "type": "Feature",
  "properties": {
    "gn:admin1_code":"8.0",
    "gn:asciiname":"Anoma Lea",
    "gn:country_code":"CA",
    "gn:dem":124,
    "gn:feature_class":"P",
    "gn:feature_code":"PPL",
    "gn:name":"Anoma Lea",
    "gn:population":0,
    "gn:timezone":"America/Toronto",
    "iso:country":"CA",
    "wof:name":"Anoma Lea",
    "wof:placetype":"locality"
},
  "geometry": {"coordinates":[-75.92194000000001,44.63806],"type":"Point"}
}