{
  "type": "Feature",
  "properties": {
    "gn:country":"CA",
    "gn:fcode":"ADMD",
    "gn:population":0,
    "iso:country":"CA",
    "name:cat_x_preferred":[
        "Ste. Anne"
    ],
    "name:ceb_x_preferred":[
        "Ste. Anne"
    ],
    "name:eng_x_preferred":[
        "Ste. Anne"
    ],
    "name:fas_x_preferred":[
        "\u0633\u0646\u062a \u0627\u0646"
    ],
    "name:fra_x_preferred":[
        "Sainte-Anne"
    ],
    "name:nld_x_preferred":[
        "Ste. Anne"
    ],
    "name:nob_x_preferred":[
        "Sainte-Anne"
    ],
    "name:oci_x_preferred":[
        "Ste. Anne"
    ],
    "name:pol_x_preferred":[
        "Ste. Anne"
    ],
    "name:rus_x_preferred":[
        "\u0421\u0435\u043d\u0442-\u0410\u043d\u043d"
    ],
    "name:srp_x_preferred":[
        "\u0421\u0435\u043d\u0442 \u0410\u043d"
    ],
    "qs:name":"Ste. Anne",
    "qs:photos_9r":0,
    "qs:photos_sr":0,
    "qs:pop_sr":"0",
    "wd:wordcount":1407,
    "wof:name":"Ste. Anne",
    "wof:placetype":"localadmin",
    "wof:population":0
},
  "geometry": {"coordinates":[-96.50059,49.58329],"type":"Point"}
}