{
  "type": "Feature",
  "properties": {
    "gn:country":"CA",
    "gn:fcode":"ADMD",
    "gn:pop":0,
    "iso:country":"CA",
    "name:eng_x_preferred":[
        "Ste. Anne"
    ],
    "qs:name":"Ste. Anne",
    "qs:photos_9r":0,
    "qs:photos_sr":0,
    "qs:pop_sr":"0",
    "wd:wordcount":1407,
    "wof:name":"Ste. Anne",
    "wof:placetype":"localadmin",
    "wof:population":0
},
  "geometry": {"coordinates":[-96.50059,49.58329],"type":"Point"}
}