{
  "type": "Feature",
  "properties": {
    "gn:admin1_code":"1.0",
    "gn:asciiname":"Baintree",
    "gn:country_code":"CA",
    "gn:dem":875,
    "gn:feature_class":"P",
    "gn:feature_code":"PPLL",
    "gn:name":"Baintree",
    "gn:population":0,
    "gn:timezone":"America/Edmonton",
    "iso:country":"CA",
    "wof:name":"Baintree",
    "wof:placetype":"locality"
},
  "geometry": {"coordinates":[-113.25192,51.16682],"type":"Point"}
}