{
  "type": "Feature",
  "properties": {
    "gn:admin1_code":"3",
    "gn:asciiname":"Renwer",
    "gn:country_code":"CA",
    "gn:dem":343,
    "gn:feature_class":"P",
    "gn:feature_code":"PPL",
    "gn:name":"Renwer",
    "gn:population":0,
    "gn:timezone":"America/Winnipeg",
    "iso:country":"CA",
    "wof:name":"Renwer",
    "wof:placetype":"locality"
},
  "geometry": {"coordinates":[-100.81398,52.09751],"type":"Point"}
}