{
  "type": "Feature",
  "properties": {
    "gn:gn_country":"CA",
    "gn:gn_fcode":"PPL",
    "gn:gn_pop":0,
    "iso:country":"CA",
    "name:eng_x_preferred":[
        "Delhi"
    ],
    "name:jpn_x_preferred":[
        "\u30c7\u30eb\u30cf\u30a4"
    ],
    "name:nld_x_preferred":[
        "Delhi"
    ],
    "name:slv_x_preferred":[
        "Delhi"
    ],
    "name:swe_x_preferred":[
        "Delhi"
    ],
    "name:vls_x_preferred":[
        "Delhi"
    ],
    "qs_pg:aaroncc":"CA",
    "qs_pg:gn_country":"CA",
    "qs_pg:gn_fcode":"PPL",
    "qs_pg:gn_pop":0,
    "qs_pg:name":"Delhi",
    "qs_pg:name_adm0":"Canada",
    "qs_pg:name_adm1":"Ontario",
    "qs_pg:photos":144,
    "qs_pg:photos_1k":29,
    "qs_pg:photos_9k":1,
    "qs_pg:photos_9r":3,
    "qs_pg:photos_all":144,
    "qs_pg:photos_sr":3,
    "qs_pg:pop_sr":0,
    "qs_pg:qs_pg_placetype":"locality",
    "qs_pg:qs_pg_placetype_gp":"Town",
    "qs_pg:woe_adm0":23424775,
    "woe:adm0_id":23424775,
    "woe:name_adm0":"Canada",
    "woe:name_adm1":"Ontario",
    "woe:placetype":"Town",
    "wof:name":"Delhi",
    "wof:placetype":"locality"
},
  "geometry": {"coordinates":[-80.49968,42.8501],"type":"Point"}
}