{
  "type": "Feature",
  "properties": {
    "gn:country":"CA",
    "gn:fcode":"PPL",
    "gn:population":0,
    "iso:country":"CA",
    "name:arz_x_preferred":[
        "\u0647\u064a\u062f\u0644\u0649"
    ],
    "name:eng_x_preferred":[
        "Hedley"
    ],
    "name:fra_x_preferred":[
        "Hedley"
    ],
    "name:nld_x_preferred":[
        "Hedley"
    ],
    "name:rus_x_preferred":[
        "\u0425\u0435\u0434\u043b\u0438"
    ],
    "qs_pg:aaroncc":"CA",
    "qs_pg:gn_country":"CA",
    "qs_pg:gn_fcode":"PPL",
    "qs_pg:gn_pop":0,
    "qs_pg:name":"Hedley",
    "qs_pg:name_adm0":"Canada",
    "qs_pg:name_adm1":"British Columbia",
    "qs_pg:photos":364,
    "qs_pg:photos_1k":74,
    "qs_pg:photos_9k":2,
    "qs_pg:photos_9r":5,
    "qs_pg:photos_all":364,
    "qs_pg:photos_sr":6,
    "qs_pg:pop_sr":0,
    "qs_pg:qs_pg_placetype":"locality",
    "qs_pg:qs_pg_placetype_gp":"Town",
    "qs_pg:woe_adm0":23424775,
    "woe:adm0_id":23424775,
    "woe:name_adm0":"Canada",
    "woe:name_adm1":"British Columbia",
    "woe:placetype":"Town",
    "wof:name":"Hedley",
    "wof:placetype":"locality"
},
  "geometry": {"coordinates":[-120.06914,49.34975],"type":"Point"}
}