{
  "type": "Feature",
  "properties": {
    "gn:admin1_code":"7",
    "gn:asciiname":"Ramseys",
    "gn:country_code":"CA",
    "gn:dem":165,
    "gn:feature_class":"P",
    "gn:feature_code":"PPLL",
    "gn:name":"Ramseys",
    "gn:population":0,
    "gn:timezone":"America/Halifax",
    "iso:country":"CA",
    "wof:name":"Ramseys",
    "wof:placetype":"locality"
},
  "geometry": {"coordinates":[-63.24867,45.08345],"type":"Point"}
}