{
  "type": "Feature",
  "properties": {
    "gn:admin1_code":"1.0",
    "gn:asciiname":"Zawale",
    "gn:country_code":"CA",
    "gn:dem":656,
    "gn:feature_class":"P",
    "gn:feature_code":"PPLL",
    "gn:name":"Zawale",
    "gn:population":0,
    "gn:timezone":"America/Edmonton",
    "iso:country":"CA",
    "wof:name":"Zawale",
    "wof:placetype":"locality"
},
  "geometry": {"coordinates":[-112.3852,53.80016],"type":"Point"}
}