{
  "type": "Feature",
  "properties": {
    "gn:admin1_code":"3",
    "gn:asciiname":"Silverwood",
    "gn:country_code":"CA",
    "gn:dem":593,
    "gn:feature_class":"P",
    "gn:feature_code":"PPLL",
    "gn:name":"Silverwood",
    "gn:population":0,
    "gn:timezone":"America/Winnipeg",
    "iso:country":"CA",
    "wof:name":"Silverwood",
    "wof:placetype":"locality"
},
  "geometry": {"coordinates":[-101.43011,51.42028],"type":"Point"}
}