{
  "type": "Feature",
  "properties": {
    "gn:admin1_code":"8",
    "gn:asciiname":"Gateway",
    "gn:country_code":"CA",
    "gn:dem":235,
    "gn:feature_class":"P",
    "gn:feature_code":"PPL",
    "gn:name":"Gateway",
    "gn:population":0,
    "gn:timezone":"America/Toronto",
    "iso:country":"CA",
    "name:ceb_x_preferred":[
        "Gateway"
    ],
    "name:deu_x_preferred":[
        "Gateway"
    ],
    "name:fas_x_preferred":[
        "\u062f\u0631\u0648\u0627\u0632\u0647"
    ],
    "name:fra_x_preferred":[
        "Gateway"
    ],
    "name:heb_x_preferred":[
        "\u05e9\u05e2\u05e8"
    ],
    "name:ita_x_preferred":[
        "Gateway"
    ],
    "name:jpn_x_preferred":[
        "\u30b2\u30fc\u30c8\u30a6\u30a7\u30a4"
    ],
    "name:kor_x_preferred":[
        "\uac8c\uc774\ud2b8\uc6e8\uc774"
    ],
    "name:lat_x_preferred":[
        "Gateway"
    ],
    "name:nld_x_preferred":[
        "Gateway"
    ],
    "name:pol_x_preferred":[
        "Gateway"
    ],
    "name:por_x_preferred":[
        "Gateway"
    ],
    "name:rus_x_preferred":[
        "\u0428\u043b\u044e\u0437"
    ],
    "name:spa_x_preferred":[
        "Gateway"
    ],
    "name:srp_x_preferred":[
        "\u0413\u0435\u0458\u0442\u0432\u0435\u0458"
    ],
    "name:swe_x_preferred":[
        "Gateway"
    ],
    "name:tha_x_preferred":[
        "\u0e40\u0e01\u0e15\u0e40\u0e27\u0e22\u0e4c"
    ],
    "name:ukr_x_preferred":[
        "\u0428\u043b\u044e\u0437"
    ],
    "name:vie_x_preferred":[
        "Gateway"
    ],
    "name:vol_x_preferred":[
        "Gateway"
    ],
    "name:zho_x_preferred":[
        "Gateway"
    ],
    "wof:name":"Gateway",
    "wof:placetype":"locality"
},
  "geometry": {"coordinates":[-79.4671,46.33171],"type":"Point"}
}