{
  "type": "Feature",
  "properties": {
    "gn:admin1_code":"8",
    "gn:asciiname":"Gateway",
    "gn:country_code":"CA",
    "gn:dem":235,
    "gn:feature_class":"P",
    "gn:feature_code":"PPL",
    "gn:name":"Gateway",
    "gn:population":0,
    "gn:timezone":"America/Toronto",
    "iso:country":"CA",
    "wof:name":"Gateway",
    "wof:placetype":"locality"
},
  "geometry": {"coordinates":[-79.4671,46.33171],"type":"Point"}
}