{
  "type": "Feature",
  "properties": {
    "gn:admin1_code":"8",
    "gn:asciiname":"Monck Road",
    "gn:country_code":"CA",
    "gn:dem":391,
    "gn:feature_class":"P",
    "gn:feature_code":"PPL",
    "gn:name":"Monck Road",
    "gn:population":0,
    "gn:timezone":"America/Toronto",
    "iso:country":"CA",
    "wof:name":"Monck Road",
    "wof:placetype":"locality"
},
  "geometry": {"coordinates":[-77.99278000000002,45.015],"type":"Point"}
}