{
  "type": "Feature",
  "properties": {
    "gn:admin1_code":"2",
    "gn:asciiname":"Paulson",
    "gn:country_code":"CA",
    "gn:dem":1207,
    "gn:feature_class":"P",
    "gn:feature_code":"PPLL",
    "gn:name":"Paulson",
    "gn:population":0,
    "gn:timezone":"America/Vancouver",
    "iso:country":"CA",
    "wof:name":"Paulson",
    "wof:placetype":"locality"
},
  "geometry": {"coordinates":[-118.11896000000002,49.19982],"type":"Point"}
}