{
  "type": "Feature",
  "properties": {
    "gn:admin1_code":"3.0",
    "gn:asciiname":"Douglas Station",
    "gn:country_code":"CA",
    "gn:dem":373,
    "gn:feature_class":"P",
    "gn:feature_code":"PPL",
    "gn:name":"Douglas Station",
    "gn:population":0,
    "gn:timezone":"America/Winnipeg",
    "iso:country":"CA",
    "wof:name":"Douglas Station",
    "wof:placetype":"locality"
},
  "geometry": {"coordinates":[-99.71084,49.89223],"type":"Point"}
}