{
  "type": "Feature",
  "properties": {
    "gn:admin1_code":"10.0",
    "gn:admin2_code":"17.0",
    "gn:admin3_code":"49058.0",
    "gn:asciiname":"Domaine-Caya",
    "gn:country_code":"CA",
    "gn:dem":97,
    "gn:feature_class":"P",
    "gn:feature_code":"PPL",
    "gn:name":"Domaine-Caya",
    "gn:population":0,
    "gn:timezone":"America/Toronto",
    "iso:country":"CA",
    "wof:name":"Domaine-Caya",
    "wof:placetype":"locality"
},
  "geometry": {"coordinates":[-72.46621999999998,45.82309],"type":"Point"}
}