{
  "type": "Feature",
  "properties": {
    "gn:admin1_code":"7",
    "gn:asciiname":"St. Francis Harbour",
    "gn:country_code":"CA",
    "gn:dem":17,
    "gn:feature_class":"P",
    "gn:feature_code":"PPL",
    "gn:name":"St. Francis Harbour",
    "gn:population":0,
    "gn:timezone":"America/Halifax",
    "iso:country":"CA",
    "wof:name":"St. Francis Harbour",
    "wof:placetype":"locality"
},
  "geometry": {"coordinates":[-61.31943,45.44503],"type":"Point"}
}