{
  "type": "Feature",
  "properties": {
    "gn:admin1_code":"7",
    "gn:asciiname":"Glen Bard",
    "gn:country_code":"CA",
    "gn:dem":127,
    "gn:feature_class":"P",
    "gn:feature_code":"PPL",
    "gn:name":"Glen Bard",
    "gn:population":0,
    "gn:timezone":"America/Halifax",
    "iso:country":"CA",
    "wof:name":"Glen Bard",
    "wof:placetype":"locality"
},
  "geometry": {"coordinates":[-62.16235,45.58004],"type":"Point"}
}