{
  "type": "Feature",
  "properties": {
    "gn:admin1_code":"3.0",
    "gn:asciiname":"Blackdale",
    "gn:country_code":"CA",
    "gn:dem":234,
    "gn:feature_class":"P",
    "gn:feature_code":"PPLL",
    "gn:name":"Blackdale",
    "gn:population":0,
    "gn:timezone":"America/Winnipeg",
    "iso:country":"CA",
    "wof:name":"Blackdale",
    "wof:placetype":"locality"
},
  "geometry": {"coordinates":[-97.13504,50.0642],"type":"Point"}
}