{
  "type": "Feature",
  "properties": {
    "gn:country":"CA",
    "iso:country":"CA",
    "name:ceb_x_preferred":[
        "Lambertville"
    ],
    "name:deu_x_preferred":[
        "Lambertville"
    ],
    "name:nld_x_preferred":[
        "Lambertville"
    ],
    "name:pol_x_preferred":[
        "Lambertville"
    ],
    "name:srp_x_preferred":[
        "\u041b\u0430\u043c\u0431\u0435\u0440\u0442\u0432\u0438\u043b"
    ],
    "qs_pg:aaroncc":"CA",
    "qs_pg:gn_country":"CA",
    "qs_pg:name":"Lambertville",
    "qs_pg:name_adm0":"Canada",
    "qs_pg:name_adm1":"New Brunswick",
    "qs_pg:photos":10,
    "qs_pg:photos_1k":2,
    "qs_pg:photos_9k":1,
    "qs_pg:photos_9r":1,
    "qs_pg:photos_all":10,
    "qs_pg:photos_sr":1,
    "qs_pg:pop_sr":0,
    "qs_pg:qs_pg_placetype":"locality",
    "qs_pg:qs_pg_placetype_gp":"Town",
    "qs_pg:woe_adm0":23424775,
    "woe:adm0_id":23424775,
    "woe:name_adm0":"Canada",
    "woe:name_adm1":"New Brunswick",
    "woe:placetype":"Town",
    "wof:name":"Lambertville",
    "wof:placetype":"locality"
},
  "geometry": {"coordinates":[-66.9409735,45.010296],"type":"Point"}
}