{
  "type": "Feature",
  "properties": {
    "gn:admin1_code":"10",
    "gn:admin2_code":"5.0",
    "gn:admin3_code":"42005.0",
    "gn:asciiname":"Lac-Stoke",
    "gn:country_code":"CA",
    "gn:dem":218,
    "gn:feature_class":"P",
    "gn:feature_code":"PPL",
    "gn:name":"Lac-Stoke",
    "gn:population":0,
    "gn:timezone":"America/Toronto",
    "iso:country":"CA",
    "wof:name":"Lac-Stoke",
    "wof:placetype":"locality"
},
  "geometry": {"coordinates":[-71.81454000000002,45.51921],"type":"Point"}
}