{
  "type": "Feature",
  "properties": {
    "gn:admin1_code":"7.0",
    "gn:asciiname":"Durells Island",
    "gn:country_code":"CA",
    "gn:dem":1,
    "gn:feature_class":"P",
    "gn:feature_code":"PPL",
    "gn:name":"Durells Island",
    "gn:population":0,
    "gn:timezone":"America/Halifax",
    "iso:country":"CA",
    "wof:name":"Durells Island",
    "wof:placetype":"locality"
},
  "geometry": {"coordinates":[-61.01548,45.34063],"type":"Point"}
}