{
  "type": "Feature",
  "properties": {
    "gn:admin1_code":"8.0",
    "gn:asciiname":"Seaton Village",
    "gn:country_code":"CA",
    "gn:dem":116,
    "gn:feature_class":"P",
    "gn:feature_code":"PPL",
    "gn:name":"Seaton Village",
    "gn:population":0,
    "gn:timezone":"America/Toronto",
    "iso:country":"CA",
    "wof:name":"Seaton Village",
    "wof:placetype":"locality"
},
  "geometry": {"coordinates":[-79.41669,43.66865],"type":"Point"}
}