{
  "type": "Feature",
  "properties": {
    "gn:country":"CA",
    "gn:fcode":"ADMD",
    "gn:population":0,
    "iso:country":"CA",
    "name:eng_x_preferred":[
        "Improvement District No. 9"
    ],
    "qs:name":"Improvement District No. 9",
    "qs:photos_9r":0,
    "qs:photos_sr":0,
    "qs:pop_sr":"0",
    "wd:wordcount":439,
    "wof:name":"Improvement District No. 9",
    "wof:placetype":"localadmin",
    "wof:population":0
},
  "geometry": {"coordinates":[-116.07159,51.5681],"type":"Point"}
}