{
  "type": "Feature",
  "properties": {
    "gn:admin1_code":"7",
    "gn:asciiname":"Long Point",
    "gn:country_code":"CA",
    "gn:dem":22,
    "gn:feature_class":"P",
    "gn:feature_code":"PPL",
    "gn:name":"Long Point",
    "gn:population":0,
    "gn:timezone":"America/Halifax",
    "iso:country":"CA",
    "name:ceb_x_preferred":[
        "Long Point"
    ],
    "name:deu_x_preferred":[
        "Long Point"
    ],
    "name:fin_x_preferred":[
        "Long Point"
    ],
    "name:pol_x_preferred":[
        "Long Point"
    ],
    "name:swe_x_preferred":[
        "Long Point"
    ],
    "wof:name":"Long Point",
    "wof:placetype":"locality"
},
  "geometry": {"coordinates":[-61.48052,45.81109],"type":"Point"}
}