{
  "type": "Feature",
  "properties": {
    "gn:admin1_code":"10.0",
    "gn:admin2_code":"4.0",
    "gn:admin3_code":"90012.0",
    "gn:asciiname":"Cann",
    "gn:country_code":"CA",
    "gn:dem":373,
    "gn:feature_class":"P",
    "gn:feature_code":"PPL",
    "gn:name":"Cann",
    "gn:population":0,
    "gn:timezone":"America/Toronto",
    "iso:country":"CA",
    "wof:name":"Cann",
    "wof:placetype":"locality"
},
  "geometry": {"coordinates":[-73.88243,47.90011],"type":"Point"}
}