{
  "type": "Feature",
  "properties": {
    "gn:admin1_code":"4",
    "gn:asciiname":"Kinnear Settlement",
    "gn:country_code":"CA",
    "gn:dem":153,
    "gn:feature_class":"P",
    "gn:feature_code":"PPL",
    "gn:name":"Kinnear Settlement",
    "gn:population":0,
    "gn:timezone":"America/Moncton",
    "iso:country":"CA",
    "wof:name":"Kinnear Settlement",
    "wof:placetype":"locality"
},
  "geometry": {"coordinates":[-65.27744,45.97699],"type":"Point"}
}