{
  "type": "Feature",
  "properties": {
    "iso:country":"CA",
    "name:eng_x_preferred":[
        "Finedale"
    ],
    "qs:gn_adm0_cc":"CA",
    "qs:gn_local":6076211,
    "qs:gn_nam_loc":"moncton",
    "qs:gn_namadm1":"04",
    "qs:local_max":1229,
    "qs:local_sum":6372,
    "qs:localhoods":28,
    "qs:name":"Finedale",
    "qs:name_adm0":"Canada",
    "qs:name_adm1":"New Brunswick",
    "qs:name_adm2":"Westmorland",
    "qs:name_local":"Moncton",
    "qs:photo_max":70,
    "qs:photo_sum":137,
    "qs:placetype":"Suburb",
    "qs:quad_count":10,
    "qs:woe_adm0":23424775,
    "qs:woe_adm1":2344918,
    "qs:woe_adm2":29375181,
    "qs:woe_lau":0,
    "qs:woe_local":3796,
    "qs:woe_ver":"7.10.0",
    "wof:lang":[
        "eng"
    ],
    "wof:name":"Finedale",
    "wof:placetype":"neighbourhood"
},
  "geometry": {"coordinates":[-64.77041,46.14343],"type":"Point"}
}