{
  "type": "Feature",
  "properties": {
    "gn:admin1_code":"8.0",
    "gn:asciiname":"Wilstead",
    "gn:country_code":"CA",
    "gn:dem":91,
    "gn:feature_class":"P",
    "gn:feature_code":"PPL",
    "gn:name":"Wilstead",
    "gn:population":0,
    "gn:timezone":"America/Toronto",
    "iso:country":"CA",
    "name:ara_x_preferred":[
        "\u0648\u064a\u0644\u0633\u062a\u064a\u062f"
    ],
    "name:ceb_x_preferred":[
        "Wilstead"
    ],
    "name:cym_x_preferred":[
        "Wilstead"
    ],
    "name:fas_x_preferred":[
        "\u0648\u06cc\u0644\u0632\u062a\u062f"
    ],
    "name:ita_x_preferred":[
        "Wilstead"
    ],
    "name:nld_x_preferred":[
        "Wilstead"
    ],
    "name:pol_x_preferred":[
        "Wilstead"
    ],
    "name:spa_x_preferred":[
        "Wilstead"
    ],
    "name:swe_x_preferred":[
        "Wilstead"
    ],
    "name:vol_x_preferred":[
        "Wilstead"
    ],
    "wof:name":"Wilstead",
    "wof:placetype":"locality"
},
  "geometry": {"coordinates":[-76.09541999999998,44.36283],"type":"Point"}
}