{
  "type": "Feature",
  "properties": {
    "gn:admin1_code":"1",
    "gn:asciiname":"Neapolis",
    "gn:country_code":"CA",
    "gn:dem":973,
    "gn:feature_class":"P",
    "gn:feature_code":"PPLL",
    "gn:name":"Neapolis",
    "gn:population":0,
    "gn:timezone":"America/Edmonton",
    "iso:country":"CA",
    "wof:name":"Neapolis",
    "wof:placetype":"locality"
},
  "geometry": {"coordinates":[-113.86866999999999,51.65011],"type":"Point"}
}