{
  "type": "Feature",
  "properties": {
    "iso:country":"CA",
    "name:azb_x_preferred":[
        "\u0631\u06cc\u0646\u0642\u0648\u0648\u062f"
    ],
    "name:cym_x_preferred":[
        "Ringwood"
    ],
    "name:fas_x_preferred":[
        "\u0631\u06cc\u0646\u06af\u0648\u0648\u062f"
    ],
    "name:fra_x_preferred":[
        "Ringwood"
    ],
    "name:gle_x_preferred":[
        "Ringwood"
    ],
    "name:ita_x_preferred":[
        "Ringwood"
    ],
    "name:lat_x_preferred":[
        "Ringwood"
    ],
    "name:nld_x_preferred":[
        "Ringwood"
    ],
    "name:nno_x_preferred":[
        "Ringwood"
    ],
    "name:pol_x_preferred":[
        "Ringwood"
    ],
    "name:ron_x_preferred":[
        "Ringwood"
    ],
    "name:spa_x_preferred":[
        "Ringwood"
    ],
    "name:swe_x_preferred":[
        "Ringwood"
    ],
    "name:vol_x_preferred":[
        "Ringwood"
    ],
    "name:zho_x_preferred":[
        "\u9748\u4f0d\u5fb7"
    ],
    "qs_pg:aaroncc":"CA",
    "qs_pg:name":"Ringwood",
    "qs_pg:name_adm0":"Canada",
    "qs_pg:name_adm1":"Ontario",
    "qs_pg:photos":2,
    "qs_pg:photos_1k":1,
    "qs_pg:photos_9k":1,
    "qs_pg:photos_9r":1,
    "qs_pg:photos_all":2,
    "qs_pg:photos_sr":1,
    "qs_pg:pop_sr":0,
    "qs_pg:qs_pg_placetype":"neighbourhood",
    "qs_pg:qs_pg_placetype_gp":"Suburb",
    "qs_pg:woe_adm0":23424775,
    "woe:adm0_id":23424775,
    "woe:name_adm0":"Canada",
    "woe:name_adm1":"Ontario",
    "woe:placetype":"Suburb",
    "wof:name":"Ringwood",
    "wof:placetype":"neighbourhood"
},
  "geometry": {"coordinates":[-79.27589999999999,43.96228],"type":"Point"}
}