{
  "type": "Feature",
  "properties": {
    "iso:country":"CA",
    "name:eng_x_preferred":[
        "The Kingsway"
    ],
    "torsdfa:AREA_NAME":"Kingsway South (15)",
    "torsdfa:AREA_S_CD":"015",
    "wd:wordcount":1600,
    "wof:lang":[
        "eng"
    ],
    "wof:name":"The Kingsway",
    "wof:placetype":"neighbourhood"
},
  "geometry": {"coordinates":[-79.510577,43.654064],"type":"Point"}
}