{
  "type": "Feature",
  "properties": {
    "gn:admin1_code":"4",
    "gn:asciiname":"Lisson Settlement",
    "gn:country_code":"CA",
    "gn:dem":313,
    "gn:feature_class":"P",
    "gn:feature_code":"PPL",
    "gn:name":"Lisson Settlement",
    "gn:population":0,
    "gn:timezone":"America/Moncton",
    "iso:country":"CA",
    "wof:name":"Lisson Settlement",
    "wof:placetype":"locality"
},
  "geometry": {"coordinates":[-65.4115,45.61243],"type":"Point"}
}