{
  "type": "Feature",
  "properties": {
    "iso:country":"CA",
    "name:eng_x_preferred":[
        "Southeast Old Aurora"
    ],
    "qs:gn_local":0,
    "qs:local_max":66,
    "qs:local_sum":66,
    "qs:localhoods":1,
    "qs:name":"Southeast Old Aurora",
    "qs:name_adm0":"Canada",
    "qs:name_adm1":"Ontario",
    "qs:name_adm2":"York",
    "qs:name_local":"Northeast  Aurora",
    "qs:photo_max":34,
    "qs:photo_sum":66,
    "qs:placetype":"Suburb",
    "qs:quad_count":6,
    "qs:woe_adm0":23424775,
    "qs:woe_adm1":2344922,
    "qs:woe_adm2":29375112,
    "qs:woe_funk":"Grouping neighborhood",
    "qs:woe_lau":0,
    "qs:woe_local":55999589,
    "qs:woe_ver":"7.10.0",
    "wof:lang":[
        "eng"
    ],
    "wof:name":"Southeast Old Aurora",
    "wof:placetype":"neighbourhood"
},
  "geometry": {"coordinates":[-79.465543,43.997935],"type":"Point"}
}