{
  "type": "Feature",
  "properties": {
    "gn:admin1_code":"10",
    "gn:admin2_code":"16.0",
    "gn:admin3_code":"46058.0",
    "gn:asciiname":"Glen Sutton",
    "gn:country_code":"CA",
    "gn:dem":162,
    "gn:feature_class":"P",
    "gn:feature_code":"PPL",
    "gn:name":"Glen Sutton",
    "gn:population":0,
    "gn:timezone":"America/Toronto",
    "iso:country":"CA",
    "wof:name":"Glen Sutton",
    "wof:placetype":"locality"
},
  "geometry": {"coordinates":[-72.54649999999999,45.04088],"type":"Point"}
}