{
  "type": "Feature",
  "properties": {
    "gn:admin1_code":"10",
    "gn:admin2_code":"5.0",
    "gn:admin3_code":"30045.0",
    "gn:asciiname":"Laval-Nord",
    "gn:country_code":"CA",
    "gn:dem":463,
    "gn:feature_class":"P",
    "gn:feature_code":"PPL",
    "gn:name":"Laval-Nord",
    "gn:population":0,
    "gn:timezone":"America/Toronto",
    "iso:country":"CA",
    "wof:name":"Laval-Nord",
    "wof:placetype":"locality"
},
  "geometry": {"coordinates":[-70.91951999999998,45.59754],"type":"Point"}
}