{
  "type": "Feature",
  "properties": {
    "iso:country":"CA",
    "name:eng_x_preferred":[
        "Brassar"
    ],
    "qs:gn_adm0_cc":"US",
    "qs:gn_fcode":"PPL",
    "qs:gn_local":4986873,
    "qs:gn_nam_loc":"brassar",
    "qs:gn_namadm1":"MI",
    "qs:gn_name":"Brassar",
    "qs:local_max":1,
    "qs:local_sum":1,
    "qs:localhoods":1,
    "qs:name":"Brassar",
    "qs:name_adm0":"United States",
    "qs:name_adm1":"Michigan",
    "qs:name_adm2":"Chippewa",
    "qs:name_local":"Brassar",
    "qs:photo_max":1,
    "qs:photo_sum":1,
    "qs:placetype":"Town",
    "qs:quad_count":1,
    "qs:woe_adm0":23424977,
    "qs:woe_adm1":2347581,
    "qs:woe_adm2":12588730,
    "qs:woe_lau":0,
    "qs:woe_local":2368283,
    "qs:woe_ver":"7.10.0",
    "wof:lang":[
        "eng"
    ],
    "wof:name":"Brassar",
    "wof:placetype":"neighbourhood"
},
  "geometry": {"coordinates":[-84.26239,46.519184],"type":"Point"}
}