{
  "type": "Feature",
  "properties": {
    "gn:country":"CA",
    "gn:fcode":"PPL",
    "gn:population":0,
    "iso:country":"CA",
    "name:deu_x_preferred":[
        "Atlin"
    ],
    "name:eng_x_preferred":[
        "Atlin"
    ],
    "name:fra_x_preferred":[
        "Atlin"
    ],
    "name:jpn_x_preferred":[
        "\u30a2\u30c8\u30ea\u30f3"
    ],
    "name:nld_x_preferred":[
        "Atlin"
    ],
    "qs_pg:aaroncc":"CA",
    "qs_pg:gn_country":"CA",
    "qs_pg:gn_fcode":"PPL",
    "qs_pg:gn_pop":0,
    "qs_pg:name":"Atlin",
    "qs_pg:name_adm0":"Canada",
    "qs_pg:name_adm1":"British Columbia",
    "qs_pg:photos":99,
    "qs_pg:photos_1k":20,
    "qs_pg:photos_9k":1,
    "qs_pg:photos_9r":3,
    "qs_pg:photos_all":99,
    "qs_pg:photos_sr":3,
    "qs_pg:pop_sr":9,
    "qs_pg:qs_pg_placetype":"locality",
    "qs_pg:qs_pg_placetype_gp":"Town",
    "qs_pg:woe_adm0":23424775,
    "woe:adm0_id":23424775,
    "woe:name_adm0":"Canada",
    "woe:name_adm1":"British Columbia",
    "woe:placetype":"Town",
    "wof:name":"Atlin",
    "wof:placetype":"locality"
},
  "geometry": {"coordinates":[-133.68944999999999,59.57807],"type":"Point"}
}