{
  "type": "Feature",
  "properties": {
    "gn:admin1_code":"7.0",
    "gn:asciiname":"Blanche",
    "gn:country_code":"CA",
    "gn:dem":16,
    "gn:feature_class":"P",
    "gn:feature_code":"PPL",
    "gn:name":"Blanche",
    "gn:population":0,
    "gn:timezone":"America/Halifax",
    "iso:country":"CA",
    "wof:name":"Blanche",
    "wof:placetype":"locality"
},
  "geometry": {"coordinates":[-65.40585,43.50459],"type":"Point"}
}