{
  "type": "Feature",
  "properties": {
    "gn:admin1_code":"2.0",
    "gn:asciiname":"Coquitlam",
    "gn:country_code":"CA",
    "gn:dem":33,
    "gn:feature_class":"P",
    "gn:feature_code":"PPL",
    "gn:name":"Coquitlam",
    "gn:population":114565,
    "gn:timezone":"America/Vancouver",
    "iso:country":"CA",
    "name:ara_x_preferred":[
        "\u0643\u0648\u0643\u0648\u064a\u062a\u0644\u0627\u0645"
    ],
    "name:azb_x_preferred":[
        "\u06a9\u0648\u06a9\u06cc\u062a\u0644\u0627\u0645"
    ],
    "name:deu_x_preferred":[
        "Coquitlam"
    ],
    "name:eng_x_preferred":[
        "Coquitlam"
    ],
    "name:epo_x_preferred":[
        "Coquitlam"
    ],
    "name:fas_x_preferred":[
        "\u06a9\u0648\u06a9\u06cc\u062a\u0644\u0627\u0645"
    ],
    "name:fin_x_preferred":[
        "Coquitlam"
    ],
    "name:fra_x_preferred":[
        "Coquitlam"
    ],
    "name:ita_x_preferred":[
        "Coquitlam"
    ],
    "name:jpn_x_preferred":[
        "\u30b3\u30ad\u30c3\u30c8\u30e9\u30e0"
    ],
    "name:jpn_x_variant":[
        "\u30b3\u30af\u30a4\u30c3\u30c8\u30e9\u30e0",
        "\u30b3\u30ad\u30c3\u30c8\u30e9\u30e0\u5e02"
    ],
    "name:kor_x_preferred":[
        "\ucf54\ud034\ud2c0\ub7fc"
    ],
    "name:lit_x_preferred":[
        "Kokitlamas"
    ],
    "name:nld_x_preferred":[
        "Coquitlam"
    ],
    "name:nor_x_preferred":[
        "Coquitlam"
    ],
    "name:pnb_x_preferred":[
        "\u06a9\u0648\u06a9\u0648\u0679\u0644\u0627\u0645"
    ],
    "name:pol_x_preferred":[
        "Coquitlam"
    ],
    "name:por_x_preferred":[
        "Coquitlam"
    ],
    "name:ron_x_preferred":[
        "Coquitlam"
    ],
    "name:rus_x_preferred":[
        "\u041a\u043e\u043a\u0443\u0438\u0442\u043b\u0430\u043c"
    ],
    "name:spa_x_preferred":[
        "Coquitlam"
    ],
    "name:srd_x_preferred":[
        "Coquitlam"
    ],
    "name:srp_x_preferred":[
        "\u041a\u043e\u043a\u0432\u0438\u0442\u043b\u0430\u043c"
    ],
    "name:swa_x_preferred":[
        "Coquitlam"
    ],
    "name:swe_x_preferred":[
        "Coquitlam"
    ],
    "name:tat_x_preferred":[
        "\u041a\u043e\u043a\u0432\u0438\u0442\u043b\u0430\u043c"
    ],
    "name:tgl_x_preferred":[
        "Coquitlam"
    ],
    "name:tur_x_preferred":[
        "Coquitlam"
    ],
    "name:ukr_x_preferred":[
        "\u041a\u043e\u043a\u0432\u0456\u0442\u043b\u0430\u043c"
    ],
    "name:urd_x_preferred":[
        "\u06a9\u0648\u06a9\u0648\u0626\u0679\u0644\u0645"
    ],
    "name:vol_x_preferred":[
        "Coquitlam"
    ],
    "name:war_x_preferred":[
        "Coquitlam"
    ],
    "name:zho_x_preferred":[
        "\u9ad8\u8cb4\u6797"
    ],
    "wof:name":"Coquitlam",
    "wof:placetype":"locality",
    "wof:population":114565
},
  "geometry": {"coordinates":[-122.75261999999999,49.28297],"type":"Point"}
}