{
  "type": "Feature",
  "properties": {
    "gn:admin1_code":"2.0",
    "gn:asciiname":"Coquitlam",
    "gn:country_code":"CA",
    "gn:dem":33,
    "gn:feature_class":"P",
    "gn:feature_code":"PPL",
    "gn:name":"Coquitlam",
    "gn:population":114565,
    "gn:timezone":"America/Vancouver",
    "iso:country":"CA",
    "name:deu_x_preferred":[
        "Coquitlam"
    ],
    "name:eng_x_preferred":[
        "Coquitlam"
    ],
    "name:epo_x_preferred":[
        "Coquitlam"
    ],
    "name:fin_x_preferred":[
        "Coquitlam"
    ],
    "name:fra_x_preferred":[
        "Coquitlam"
    ],
    "name:jpn_x_preferred":[
        "\u30b3\u30ad\u30c3\u30c8\u30e9\u30e0"
    ],
    "name:jpn_x_variant":[
        "\u30b3\u30af\u30a4\u30c3\u30c8\u30e9\u30e0",
        "\u30b3\u30ad\u30c3\u30c8\u30e9\u30e0\u5e02"
    ],
    "name:pol_x_preferred":[
        "Coquitlam"
    ],
    "name:por_x_preferred":[
        "Coquitlam"
    ],
    "name:spa_x_preferred":[
        "Coquitlam"
    ],
    "wof:name":"Coquitlam",
    "wof:placetype":"locality",
    "wof:population":114565
},
  "geometry": {"coordinates":[-122.75261999999999,49.28297],"type":"Point"}
}