{
  "type": "Feature",
  "properties": {
    "gn:admin1_code":"8",
    "gn:asciiname":"Etonia",
    "gn:country_code":"CA",
    "gn:dem":272,
    "gn:feature_class":"P",
    "gn:feature_code":"PPL",
    "gn:name":"Etonia",
    "gn:population":0,
    "gn:timezone":"America/Toronto",
    "iso:country":"CA",
    "wof:name":"Etonia",
    "wof:placetype":"locality"
},
  "geometry": {"coordinates":[-80.47444,43.17333],"type":"Point"}
}