{
  "type": "Feature",
  "properties": {
    "gn:admin1_code":"10.0",
    "gn:admin2_code":"2.0",
    "gn:admin3_code":"94245.0",
    "gn:asciiname":"Chute-aux-Galets",
    "gn:country_code":"CA",
    "gn:dem":179,
    "gn:feature_class":"P",
    "gn:feature_code":"PPL",
    "gn:name":"Chute-aux-Galets",
    "gn:population":0,
    "gn:timezone":"America/Toronto",
    "iso:country":"CA",
    "wof:name":"Chute-aux-Galets",
    "wof:placetype":"locality"
},
  "geometry": {"coordinates":[-71.19944,48.65111],"type":"Point"}
}