{
  "type": "Feature",
  "properties": {
    "gn:admin1_code":"1",
    "gn:asciiname":"Gurneyville",
    "gn:country_code":"CA",
    "gn:dem":555,
    "gn:feature_class":"P",
    "gn:feature_code":"PPLL",
    "gn:name":"Gurneyville",
    "gn:population":0,
    "gn:timezone":"America/Edmonton",
    "iso:country":"CA",
    "wof:name":"Gurneyville",
    "wof:placetype":"locality"
},
  "geometry": {"coordinates":[-110.75175,54.13345],"type":"Point"}
}