{
  "type": "Feature",
  "properties": {
    "gn:admin1_code":"8.0",
    "gn:asciiname":"Beardmore",
    "gn:country_code":"CA",
    "gn:dem":300,
    "gn:feature_class":"P",
    "gn:feature_code":"PPL",
    "gn:name":"Beardmore",
    "gn:population":0,
    "gn:timezone":"America/Toronto",
    "iso:country":"CA",
    "name:deu_x_preferred":[
        "Beardmore"
    ],
    "name:fra_x_preferred":[
        "Beardmore"
    ],
    "wof:name":"Beardmore",
    "wof:placetype":"locality"
},
  "geometry": {"coordinates":[-87.95603,49.60926],"type":"Point"}
}