{
  "type": "Feature",
  "properties": {
    "iso:country":"CA",
    "name:bre_x_preferred":[
        "Carmel"
    ],
    "name:cat_x_preferred":[
        "Carmel"
    ],
    "name:ceb_x_preferred":[
        "Carmel"
    ],
    "name:cym_x_preferred":[
        "Carmel"
    ],
    "name:deu_x_preferred":[
        "Carmel"
    ],
    "name:eng_x_preferred":[
        "Carmel"
    ],
    "name:fas_x_preferred":[
        "\u06a9\u0627\u0631\u0645\u0644"
    ],
    "name:fra_x_preferred":[
        "Carmel"
    ],
    "name:heb_x_preferred":[
        "\u05db\u05e8\u05de\u05dc"
    ],
    "name:ita_x_preferred":[
        "Carmel"
    ],
    "name:jpn_x_preferred":[
        "\u30ab\u30eb\u30e1\u30eb"
    ],
    "name:kor_x_preferred":[
        "\uce74\uba40"
    ],
    "name:nld_x_preferred":[
        "Carmel"
    ],
    "name:pol_x_preferred":[
        "Carmel"
    ],
    "name:por_x_preferred":[
        "Carmel"
    ],
    "name:rus_x_preferred":[
        "\u041a\u0430\u0440\u043c\u0435\u043b\u044c"
    ],
    "name:spa_x_preferred":[
        "Carmel"
    ],
    "name:swe_x_preferred":[
        "Carmel"
    ],
    "name:ukr_x_preferred":[
        "\u041a\u0430\u0440\u043c\u0435\u043b"
    ],
    "name:urd_x_preferred":[
        "\u06a9\u0627\u0631\u0645\u06cc\u0644"
    ],
    "name:vol_x_preferred":[
        "Carmel"
    ],
    "qs:gn_fcode":"PPL",
    "qs:gn_local":0,
    "qs:gn_namadm1":"10",
    "qs:gn_name":"Carmel",
    "qs:local_max":645,
    "qs:local_sum":645,
    "qs:localhoods":1,
    "qs:name":"Carmel",
    "qs:name_adm0":"Canada",
    "qs:name_adm1":"Qu\u00e9bec",
    "qs:name_adm2":"Trois-Rivi\u00e8res",
    "qs:name_local":"Trois-Rivi\u00e8res Ouest",
    "qs:photo_max":77,
    "qs:photo_sum":645,
    "qs:placetype":"Suburb",
    "qs:quad_count":43,
    "qs:woe_adm0":23424775,
    "qs:woe_adm1":2344924,
    "qs:woe_adm2":29375104,
    "qs:woe_funk":"Grouping neighborhood",
    "qs:woe_lau":0,
    "qs:woe_local":23394701,
    "qs:woe_ver":"7.10.0",
    "wd:wordcount":569,
    "wof:lang":[
        "fre"
    ],
    "wof:name":"Carmel",
    "wof:placetype":"neighbourhood"
},
  "geometry": {"coordinates":[-72.56800800000001,46.349198],"type":"Point"}
}