{
  "type": "Feature",
  "properties": {
    "iso:country":"CA",
    "name:eng_x_preferred":[
        "Uplands"
    ],
    "wof:lang":[
        "eng"
    ],
    "wof:name":"Uplands",
    "wof:placetype":"neighbourhood"
},
  "geometry": {"coordinates":[-104.604989,50.499411],"type":"Point"}
}