{
  "type": "Feature",
  "properties": {
    "gn:admin1_code":"11.0",
    "gn:asciiname":"Buckland",
    "gn:country_code":"CA",
    "gn:dem":435,
    "gn:feature_class":"P",
    "gn:feature_code":"PPLL",
    "gn:name":"Buckland",
    "gn:population":0,
    "gn:timezone":"America/Regina",
    "iso:country":"CA",
    "wof:name":"Buckland",
    "wof:placetype":"locality"
},
  "geometry": {"coordinates":[-105.93433,53.18339],"type":"Point"}
}