{
  "type": "Feature",
  "properties": {
    "gn:admin1_code":"11.0",
    "gn:asciiname":"Buckland",
    "gn:country_code":"CA",
    "gn:dem":435,
    "gn:feature_class":"P",
    "gn:feature_code":"PPLL",
    "gn:name":"Buckland",
    "gn:population":0,
    "gn:timezone":"America/Regina",
    "iso:country":"CA",
    "name:azb_x_preferred":[
        "\u0628\u0627\u06a9\u0644\u0646\u062f"
    ],
    "name:cat_x_preferred":[
        "Buckland"
    ],
    "name:ceb_x_preferred":[
        "Buckland"
    ],
    "name:dan_x_preferred":[
        "Buckland"
    ],
    "name:deu_x_preferred":[
        "Buckland"
    ],
    "name:fas_x_preferred":[
        "\u0628\u0627\u06a9\u0644\u0646\u062f"
    ],
    "name:fra_x_preferred":[
        "Buckland"
    ],
    "name:ita_x_preferred":[
        "Buckland"
    ],
    "name:kat_x_preferred":[
        "\u10d1\u10d0\u10d9\u10da\u10d4\u10dc\u10d3\u10d8"
    ],
    "name:nds_x_preferred":[
        "Buckland"
    ],
    "name:nld_x_preferred":[
        "Buckland"
    ],
    "name:pol_x_preferred":[
        "Buckland"
    ],
    "name:por_x_preferred":[
        "Buckland"
    ],
    "name:rus_x_preferred":[
        "\u0411\u0430\u043a\u043b\u0435\u043d\u0434"
    ],
    "name:spa_x_preferred":[
        "Buckland"
    ],
    "name:srp_x_preferred":[
        "\u0411\u0430\u043a\u043b\u0430\u043d\u0434"
    ],
    "name:swe_x_preferred":[
        "Buckland"
    ],
    "name:ukr_x_preferred":[
        "\u0411\u0430\u043a\u043b\u0435\u043d\u0434"
    ],
    "name:vol_x_preferred":[
        "Buckland"
    ],
    "wof:name":"Buckland",
    "wof:placetype":"locality"
},
  "geometry": {"coordinates":[-105.93433,53.18339],"type":"Point"}
}