{
  "type": "Feature",
  "properties": {
    "gn:admin1_code":"8.0",
    "gn:asciiname":"West Essa",
    "gn:country_code":"CA",
    "gn:dem":270,
    "gn:feature_class":"P",
    "gn:feature_code":"PPL",
    "gn:name":"West Essa",
    "gn:population":0,
    "gn:timezone":"America/Toronto",
    "iso:country":"CA",
    "wof:name":"West Essa",
    "wof:placetype":"locality"
},
  "geometry": {"coordinates":[-79.86960999999999,44.18218],"type":"Point"}
}