{
  "type": "Feature",
  "properties": {
    "gn:admin1_code":"10",
    "gn:admin2_code":"15.0",
    "gn:admin3_code":"79005.0",
    "gn:asciiname":"Lac-Serpent",
    "gn:country_code":"CA",
    "gn:dem":228,
    "gn:feature_class":"P",
    "gn:feature_code":"PPL",
    "gn:name":"Lac-Serpent",
    "gn:population":0,
    "gn:timezone":"America/Toronto",
    "iso:country":"CA",
    "wof:name":"Lac-Serpent",
    "wof:placetype":"locality"
},
  "geometry": {"coordinates":[-75.47778000000002,46.1575],"type":"Point"}
}