{
  "type": "Feature",
  "properties": {
    "gn:admin1_code":"5",
    "gn:asciiname":"Victoria Cove",
    "gn:country_code":"CA",
    "gn:dem":17,
    "gn:feature_class":"P",
    "gn:feature_code":"PPL",
    "gn:name":"Victoria Cove",
    "gn:population":0,
    "gn:timezone":"America/St_Johns",
    "iso:country":"CA",
    "name:fra_x_preferred":[
        "Victoria Cove"
    ],
    "wof:name":"Victoria Cove",
    "wof:placetype":"locality"
},
  "geometry": {"coordinates":[-54.49811,49.34992],"type":"Point"}
}