{
  "type": "Feature",
  "properties": {
    "gn:admin1_code":"7.0",
    "gn:asciiname":"Westfield",
    "gn:country_code":"CA",
    "gn:dem":105,
    "gn:feature_class":"P",
    "gn:feature_code":"PPL",
    "gn:name":"Westfield",
    "gn:population":0,
    "gn:timezone":"America/Halifax",
    "iso:country":"CA",
    "wof:name":"Westfield",
    "wof:placetype":"locality"
},
  "geometry": {"coordinates":[-65.0215,44.41448],"type":"Point"}
}