{
  "type": "Feature",
  "properties": {
    "gn:admin1_code":"11",
    "gn:asciiname":"Usherville",
    "gn:country_code":"CA",
    "gn:dem":529,
    "gn:feature_class":"P",
    "gn:feature_code":"PPLL",
    "gn:name":"Usherville",
    "gn:population":0,
    "gn:timezone":"America/Regina",
    "iso:country":"CA",
    "wof:name":"Usherville",
    "wof:placetype":"locality"
},
  "geometry": {"coordinates":[-102.65094999999999,52.23328],"type":"Point"}
}