{
  "type": "Feature",
  "properties": {
    "gn:admin1_code":"7",
    "gn:admin2_code":"1207",
    "gn:asciiname":"Scots Bay, Kings Subdivision B",
    "gn:country_code":"CA",
    "gn:dem":23,
    "gn:feature_class":"P",
    "gn:feature_code":"PPL",
    "gn:name":"Scots Bay, Kings Subdivision B",
    "gn:population":0,
    "gn:timezone":"America/Halifax",
    "iso:country":"CA",
    "wof:name":"Scots Bay, Kings Subdivision B",
    "wof:placetype":"locality"
},
  "geometry": {"coordinates":[-64.39984,45.30867],"type":"Point"}
}