{
  "type": "Feature",
  "properties": {
    "gn:admin1_code":"2",
    "gn:asciiname":"Granite",
    "gn:country_code":"CA",
    "gn:dem":793,
    "gn:feature_class":"P",
    "gn:feature_code":"PPL",
    "gn:name":"Granite",
    "gn:population":0,
    "gn:timezone":"America/Vancouver",
    "iso:country":"CA",
    "wof:name":"Granite",
    "wof:placetype":"locality"
},
  "geometry": {"coordinates":[-117.36667,49.48333],"type":"Point"}
}