{
  "type": "Feature",
  "properties": {
    "gn:admin1_code":"10.0",
    "gn:admin2_code":"11.0",
    "gn:asciiname":"Del-Val",
    "gn:country_code":"CA",
    "gn:dem":37,
    "gn:feature_class":"P",
    "gn:feature_code":"PPL",
    "gn:name":"Del-Val",
    "gn:population":0,
    "gn:timezone":"America/Toronto",
    "iso:country":"CA",
    "wof:name":"Del-Val",
    "wof:placetype":"locality"
},
  "geometry": {"coordinates":[-66.74219000000001,49.0831],"type":"Point"}
}