{
  "type": "Feature",
  "properties": {
    "gn:admin1_code":"8.0",
    "gn:asciiname":"Cheney",
    "gn:country_code":"CA",
    "gn:dem":63,
    "gn:feature_class":"P",
    "gn:feature_code":"PPL",
    "gn:name":"Cheney",
    "gn:population":0,
    "gn:timezone":"America/Toronto",
    "iso:country":"CA",
    "wof:name":"Cheney",
    "wof:placetype":"locality"
},
  "geometry": {"coordinates":[-75.24318000000002,45.4134],"type":"Point"}
}