{
  "type": "Feature",
  "properties": {
    "gn:admin1_code":"8.0",
    "gn:asciiname":"Cheney",
    "gn:country_code":"CA",
    "gn:dem":63,
    "gn:feature_class":"P",
    "gn:feature_code":"PPL",
    "gn:name":"Cheney",
    "gn:population":0,
    "gn:timezone":"America/Toronto",
    "iso:country":"CA",
    "name:ceb_x_preferred":[
        "Cheney"
    ],
    "name:dan_x_preferred":[
        "Cheney"
    ],
    "name:deu_x_preferred":[
        "Cheney"
    ],
    "name:epo_x_preferred":[
        "Cheney"
    ],
    "name:fra_x_preferred":[
        "Cheney"
    ],
    "name:heb_x_preferred":[
        "\u05e6'\u05d9\u05d9\u05e0\u05d9"
    ],
    "name:ita_x_preferred":[
        "Cheney"
    ],
    "name:nds_x_preferred":[
        "Cheney"
    ],
    "name:nld_x_preferred":[
        "Cheney"
    ],
    "name:pol_x_preferred":[
        "Cheney"
    ],
    "name:por_x_preferred":[
        "Cheney"
    ],
    "name:rus_x_preferred":[
        "\u0427\u0435\u0439\u043d\u0438"
    ],
    "name:spa_x_preferred":[
        "Cheney"
    ],
    "name:srp_x_preferred":[
        "\u0427\u0438\u043d\u0438"
    ],
    "name:swe_x_preferred":[
        "Cheney"
    ],
    "name:ukr_x_preferred":[
        "\u0427\u0435\u0439\u043d\u0456"
    ],
    "name:vol_x_preferred":[
        "Cheney"
    ],
    "wof:name":"Cheney",
    "wof:placetype":"locality"
},
  "geometry": {"coordinates":[-75.24318000000002,45.4134],"type":"Point"}
}