{
  "type": "Feature",
  "properties": {
    "gn:admin1_code":"11",
    "gn:asciiname":"Tangleflags",
    "gn:country_code":"CA",
    "gn:dem":560,
    "gn:feature_class":"P",
    "gn:feature_code":"PPLL",
    "gn:name":"Tangleflags",
    "gn:population":0,
    "gn:timezone":"America/Edmonton",
    "iso:country":"CA",
    "wof:name":"Tangleflags",
    "wof:placetype":"locality"
},
  "geometry": {"coordinates":[-109.63482999999999,53.48348000000001],"type":"Point"}
}