{
  "type": "Feature",
  "properties": {
    "gn:admin1_code":"8",
    "gn:asciiname":"Seouls Corners",
    "gn:country_code":"CA",
    "gn:dem":213,
    "gn:feature_class":"P",
    "gn:feature_code":"PPL",
    "gn:name":"Seouls Corners",
    "gn:population":0,
    "gn:timezone":"America/Toronto",
    "iso:country":"CA",
    "wof:name":"Seouls Corners",
    "wof:placetype":"locality"
},
  "geometry": {"coordinates":[-76.80085,44.78098],"type":"Point"}
}