{
  "type": "Feature",
  "properties": {
    "gn:admin1_code":"8.0",
    "gn:asciiname":"West Corners",
    "gn:country_code":"CA",
    "gn:dem":168,
    "gn:feature_class":"P",
    "gn:feature_code":"PPL",
    "gn:name":"West Corners",
    "gn:population":0,
    "gn:timezone":"America/Toronto",
    "iso:country":"CA",
    "wof:name":"West Corners",
    "wof:placetype":"locality"
},
  "geometry": {"coordinates":[-77.82971999999999,44.30306],"type":"Point"}
}