{
  "type": "Feature",
  "properties": {
    "gn:admin1_code":"3",
    "gn:asciiname":"Thicket Portage",
    "gn:country_code":"CA",
    "gn:dem":209,
    "gn:feature_class":"P",
    "gn:feature_code":"PPL",
    "gn:name":"Thicket Portage",
    "gn:population":0,
    "gn:timezone":"America/Winnipeg",
    "iso:country":"CA",
    "name:eng_x_preferred":[
        "Thicket Portage"
    ],
    "wof:name":"Thicket Portage",
    "wof:placetype":"locality"
},
  "geometry": {"coordinates":[-97.68738999999999,55.31826],"type":"Point"}
}