{
  "type": "Feature",
  "properties": {
    "gn:admin1_code":"11.0",
    "gn:asciiname":"Willows",
    "gn:country_code":"CA",
    "gn:dem":709,
    "gn:feature_class":"P",
    "gn:feature_code":"PPL",
    "gn:name":"Willows",
    "gn:population":0,
    "gn:timezone":"America/Regina",
    "iso:country":"CA",
    "wof:name":"Willows",
    "wof:placetype":"locality"
},
  "geometry": {"coordinates":[-105.85057,49.60003],"type":"Point"}
}