{
  "type": "Feature",
  "properties": {
    "gn:admin1_code":"8",
    "gn:asciiname":"Muskoka Falls",
    "gn:country_code":"CA",
    "gn:dem":269,
    "gn:feature_class":"P",
    "gn:feature_code":"PPL",
    "gn:name":"Muskoka Falls",
    "gn:population":0,
    "gn:timezone":"America/Toronto",
    "iso:country":"CA",
    "wof:name":"Muskoka Falls",
    "wof:placetype":"locality"
},
  "geometry": {"coordinates":[-79.29961999999998,45.00011],"type":"Point"}
}