{
  "type": "Feature",
  "properties": {
    "iso:country":"CA",
    "name:ceb_x_preferred":[
        "Westmont"
    ],
    "name:deu_x_preferred":[
        "Westmont"
    ],
    "name:eng_x_preferred":[
        "Westmont"
    ],
    "name:fra_x_preferred":[
        "Westmont"
    ],
    "name:ita_x_preferred":[
        "Westmont"
    ],
    "name:nld_x_preferred":[
        "Westmont"
    ],
    "name:pol_x_preferred":[
        "Westmont"
    ],
    "name:por_x_preferred":[
        "Westmont"
    ],
    "name:srp_x_preferred":[
        "\u0412\u0435\u0441\u0442\u043c\u043e\u043d\u0442"
    ],
    "name:vol_x_preferred":[
        "Westmont"
    ],
    "qs:gn_adm0_cc":"CA",
    "qs:gn_local":5992996,
    "qs:gn_nam_loc":"kitchener",
    "qs:gn_namadm1":"08",
    "qs:local_max":6042,
    "qs:local_sum":26102,
    "qs:localhoods":44,
    "qs:name":"Westmont",
    "qs:name_adm0":"Canada",
    "qs:name_adm1":"Ontario",
    "qs:name_adm2":"Waterloo",
    "qs:name_local":"Kitchener",
    "qs:photo_max":556,
    "qs:photo_sum":3831,
    "qs:placetype":"Suburb",
    "qs:quad_count":62,
    "qs:woe_adm0":23424775,
    "qs:woe_adm1":2344922,
    "qs:woe_adm2":29375060,
    "qs:woe_lau":0,
    "qs:woe_local":4051,
    "qs:woe_ver":"7.10.0",
    "wd:wordcount":37,
    "wof:lang":[
        "eng"
    ],
    "wof:name":"Westmont",
    "wof:placetype":"neighbourhood"
},
  "geometry": {"coordinates":[-80.526647,43.465034],"type":"Point"}
}