{
  "type": "Feature",
  "properties": {
    "gn:country":"CA",
    "gn:fcode":"ADMD",
    "gn:pop":0,
    "iso:country":"CA",
    "name:eng_x_preferred":[
        "Harrison"
    ],
    "qs:name":"Harrison",
    "qs:photos_9r":0,
    "qs:photos_sr":0,
    "qs:pop_sr":"0",
    "wd:wordcount":287,
    "wof:name":"Harrison",
    "wof:placetype":"localadmin",
    "wof:population":0
},
  "geometry": {"coordinates":[-100.08584,50.46611],"type":"Point"}
}