{
  "type": "Feature",
  "properties": {
    "gn:country":"CA",
    "iso:country":"CA",
    "name:eng_x_preferred":[
        "Tancook Island"
    ],
    "qs:name":"Tancook Island",
    "qs:name_adm0":"Canada",
    "qs:name_adm1":"Nova Scotia",
    "qs:photos":78,
    "qs:photos_1k":16,
    "qs:photos_9k":1,
    "qs:photos_9r":3,
    "qs:photos_all":78,
    "qs:photos_sr":3,
    "qs:placetype":"Town",
    "qs:pop_sr":"0",
    "wd:wordcount":24,
    "wof:name":"Tancook Island",
    "wof:placetype":"locality"
},
  "geometry": {"coordinates":[-64.166167,44.452982],"type":"Point"}
}