{
  "type": "Feature",
  "properties": {
    "gn:admin1_code":"7.0",
    "gn:asciiname":"Cape George Point",
    "gn:country_code":"CA",
    "gn:dem":113,
    "gn:feature_class":"P",
    "gn:feature_code":"PPL",
    "gn:name":"Cape George Point",
    "gn:population":0,
    "gn:timezone":"America/Halifax",
    "iso:country":"CA",
    "wof:name":"Cape George Point",
    "wof:placetype":"locality"
},
  "geometry": {"coordinates":[-61.90497,45.86928],"type":"Point"}
}