{
  "type": "Feature",
  "properties": {
    "gn:admin1_code":"1",
    "gn:asciiname":"Rivercourse",
    "gn:country_code":"CA",
    "gn:dem":649,
    "gn:feature_class":"P",
    "gn:feature_code":"PPLL",
    "gn:name":"Rivercourse",
    "gn:population":0,
    "gn:timezone":"America/Edmonton",
    "iso:country":"CA",
    "wof:name":"Rivercourse",
    "wof:placetype":"locality"
},
  "geometry": {"coordinates":[-110.05155999999999,53.01686],"type":"Point"}
}