{
  "type": "Feature",
  "properties": {
    "iso:country":"CA",
    "name:cat_x_preferred":[
        "Northbrook"
    ],
    "name:ceb_x_preferred":[
        "Northbrook"
    ],
    "name:deu_x_preferred":[
        "Northbrook"
    ],
    "name:ita_x_preferred":[
        "Northbrook"
    ],
    "name:kor_x_preferred":[
        "\ub178\uc2a4\ube0c\ub8e9"
    ],
    "name:nld_x_preferred":[
        "Northbrook"
    ],
    "name:pol_x_preferred":[
        "Northbrook"
    ],
    "name:por_x_preferred":[
        "Northbrook"
    ],
    "name:rus_x_preferred":[
        "\u041d\u043e\u0440\u0442\u0431\u0440\u0443\u043a"
    ],
    "name:spa_x_preferred":[
        "Northbrook"
    ],
    "name:srp_x_preferred":[
        "\u041d\u043e\u0440\u0442\u0431\u0440\u043e\u043e\u043a"
    ],
    "name:vol_x_preferred":[
        "Northbrook"
    ],
    "qs_pg:aaroncc":"CA",
    "qs_pg:name":"Northbrook",
    "qs_pg:name_adm0":"Canada",
    "qs_pg:name_adm1":"Ontario",
    "qs_pg:photos":3,
    "qs_pg:photos_1k":1,
    "qs_pg:photos_9k":1,
    "qs_pg:photos_9r":1,
    "qs_pg:photos_all":3,
    "qs_pg:photos_sr":1,
    "qs_pg:pop_sr":0,
    "qs_pg:qs_pg_placetype":"locality",
    "qs_pg:qs_pg_placetype_gp":"Town",
    "qs_pg:woe_adm0":23424775,
    "woe:adm0_id":23424775,
    "woe:name_adm0":"Canada",
    "woe:name_adm1":"Ontario",
    "woe:placetype":"Town",
    "wof:name":"Northbrook",
    "wof:placetype":"locality"
},
  "geometry": {"coordinates":[-77.167711,44.747068],"type":"Point"}
}