{
  "type": "Feature",
  "properties": {
    "gn:admin1_code":"8.0",
    "gn:asciiname":"Woodside",
    "gn:country_code":"CA",
    "gn:dem":311,
    "gn:feature_class":"P",
    "gn:feature_code":"PPL",
    "gn:name":"Woodside",
    "gn:population":0,
    "gn:timezone":"America/Toronto",
    "iso:country":"CA",
    "wof:name":"Woodside",
    "wof:placetype":"locality"
},
  "geometry": {"coordinates":[-80.03034,43.99084000000001],"type":"Point"}
}