{
  "type": "Feature",
  "properties": {
    "gn:admin1_code":"8.0",
    "gn:asciiname":"Woodside",
    "gn:country_code":"CA",
    "gn:dem":311,
    "gn:feature_class":"P",
    "gn:feature_code":"PPL",
    "gn:name":"Woodside",
    "gn:population":0,
    "gn:timezone":"America/Toronto",
    "iso:country":"CA",
    "name:cat_x_preferred":[
        "Woodside"
    ],
    "name:ceb_x_preferred":[
        "Woodside"
    ],
    "name:deu_x_preferred":[
        "Woodside"
    ],
    "name:fin_x_preferred":[
        "Woodside"
    ],
    "name:fra_x_preferred":[
        "Woodside"
    ],
    "name:fry_x_preferred":[
        "Woodside"
    ],
    "name:hin_x_preferred":[
        "\u0935\u0941\u0921\u0938\u093e\u0907\u0921 \u092a\u093e\u0930\u094d\u0915"
    ],
    "name:ita_x_preferred":[
        "Woodside"
    ],
    "name:kor_x_preferred":[
        "\uc6b0\ub4dc\uc0ac\uc774\ub4dc"
    ],
    "name:nld_x_preferred":[
        "Woodside"
    ],
    "name:pol_x_preferred":[
        "Woodside"
    ],
    "name:por_x_preferred":[
        "Woodside"
    ],
    "name:rus_x_preferred":[
        "\u0412\u0443\u0434\u0441\u0430\u0439\u0434"
    ],
    "name:srp_x_preferred":[
        "\u0412\u0443\u0434\u0441\u0430\u0458\u0434"
    ],
    "name:swe_x_preferred":[
        "Woodside"
    ],
    "name:vol_x_preferred":[
        "Woodside"
    ],
    "wof:name":"Woodside",
    "wof:placetype":"locality"
},
  "geometry": {"coordinates":[-80.03034,43.99084000000001],"type":"Point"}
}