{
  "type": "Feature",
  "properties": {
    "iso:country":"CA",
    "name:deu_x_preferred":[
        "Blakeley"
    ],
    "name:eng_x_preferred":[
        "Blakeley"
    ],
    "name:fra_x_preferred":[
        "Blakeley"
    ],
    "qs:gn_adm0_cc":"CA",
    "qs:gn_local":5969782,
    "qs:gn_nam_loc":"hamilton",
    "qs:gn_namadm1":"08",
    "qs:local_max":3547,
    "qs:local_sum":20353,
    "qs:localhoods":46,
    "qs:name":"Blakeley",
    "qs:name_adm0":"Canada",
    "qs:name_adm1":"Ontario",
    "qs:name_adm2":"Hamilton",
    "qs:name_local":"Hamilton",
    "qs:photo_max":43,
    "qs:photo_sum":125,
    "qs:placetype":"Suburb",
    "qs:quad_count":10,
    "qs:woe_adm0":23424775,
    "qs:woe_adm1":2344922,
    "qs:woe_adm2":29375120,
    "qs:woe_lau":0,
    "qs:woe_local":4125,
    "qs:woe_ver":"7.10.0",
    "wd:wordcount":92,
    "wof:lang":[
        "eng"
    ],
    "wof:name":"Blakeley",
    "wof:placetype":"neighbourhood"
},
  "geometry": {"coordinates":[-79.833174,43.241696],"type":"Point"}
}