{
  "type": "Feature",
  "properties": {
    "gn:admin1_code":"7",
    "gn:asciiname":"Riverside Corner",
    "gn:country_code":"CA",
    "gn:dem":53,
    "gn:feature_class":"P",
    "gn:feature_code":"PPL",
    "gn:name":"Riverside Corner",
    "gn:population":0,
    "gn:timezone":"America/Halifax",
    "iso:country":"CA",
    "wof:name":"Riverside Corner",
    "wof:placetype":"locality"
},
  "geometry": {"coordinates":[-63.78767,45.13272],"type":"Point"}
}