{
  "type": "Feature",
  "properties": {
    "gn:admin1_code":"3",
    "gn:asciiname":"Otto",
    "gn:country_code":"CA",
    "gn:dem":264,
    "gn:feature_class":"P",
    "gn:feature_code":"PPLL",
    "gn:name":"Otto",
    "gn:population":0,
    "gn:timezone":"America/Winnipeg",
    "iso:country":"CA",
    "name:bre_x_preferred":[
        "Otto"
    ],
    "name:dan_x_preferred":[
        "Otto"
    ],
    "name:deu_x_preferred":[
        "Otto"
    ],
    "name:epo_x_preferred":[
        "Otto"
    ],
    "name:est_x_preferred":[
        "Otto"
    ],
    "name:fin_x_preferred":[
        "Otto"
    ],
    "name:jpn_x_preferred":[
        "\u30aa\u30c3\u30c8\u30fc"
    ],
    "name:lat_x_preferred":[
        "Otto"
    ],
    "name:nno_x_preferred":[
        "Otto"
    ],
    "name:nor_x_preferred":[
        "Otto"
    ],
    "name:pol_x_preferred":[
        "Otto"
    ],
    "name:swe_x_preferred":[
        "Otto"
    ],
    "name:ukr_x_preferred":[
        "\u041e\u0442\u0442\u043e\u043d"
    ],
    "wof:name":"Otto",
    "wof:placetype":"locality"
},
  "geometry": {"coordinates":[-97.8165,50.65812],"type":"Point"}
}