{
  "type": "Feature",
  "properties": {
    "gn:admin1_code":"3",
    "gn:asciiname":"Otto",
    "gn:country_code":"CA",
    "gn:dem":264,
    "gn:feature_class":"P",
    "gn:feature_code":"PPLL",
    "gn:name":"Otto",
    "gn:population":0,
    "gn:timezone":"America/Winnipeg",
    "iso:country":"CA",
    "wof:name":"Otto",
    "wof:placetype":"locality"
},
  "geometry": {"coordinates":[-97.8165,50.65812],"type":"Point"}
}