{
  "type": "Feature",
  "properties": {
    "iso:country":"CA",
    "name:eng_x_preferred":[
        "Mills Haven"
    ],
    "wof:lang":[
        "eng"
    ],
    "wof:name":"Mills Haven",
    "wof:placetype":"neighbourhood"
},
  "geometry": {"coordinates":[-113.302809,53.537954],"type":"Point"}
}