{
  "type": "Feature",
  "properties": {
    "gn:admin1_code":"4",
    "gn:asciiname":"Waweig",
    "gn:country_code":"CA",
    "gn:dem":86,
    "gn:feature_class":"P",
    "gn:feature_code":"PPL",
    "gn:name":"Waweig",
    "gn:population":0,
    "gn:timezone":"America/Moncton",
    "iso:country":"CA",
    "wof:name":"Waweig",
    "wof:placetype":"locality"
},
  "geometry": {"coordinates":[-67.11667,45.25],"type":"Point"}
}