{
  "type": "Feature",
  "properties": {
    "gn:admin1_code":"8.0",
    "gn:asciiname":"Zorra Station",
    "gn:country_code":"CA",
    "gn:dem":304,
    "gn:feature_class":"P",
    "gn:feature_code":"PPLL",
    "gn:name":"Zorra Station",
    "gn:population":0,
    "gn:timezone":"America/Toronto",
    "iso:country":"CA",
    "wof:name":"Zorra Station",
    "wof:placetype":"locality"
},
  "geometry": {"coordinates":[-80.88441999999998,43.09899],"type":"Point"}
}