{
  "type": "Feature",
  "properties": {
    "gn:admin1_code":"8",
    "gn:asciiname":"Lakeside Beach",
    "gn:country_code":"CA",
    "gn:dem":267,
    "gn:feature_class":"P",
    "gn:feature_code":"PPL",
    "gn:name":"Lakeside Beach",
    "gn:population":0,
    "gn:timezone":"America/Toronto",
    "iso:country":"CA",
    "wof:name":"Lakeside Beach",
    "wof:placetype":"locality"
},
  "geometry": {"coordinates":[-78.91306,44.15722],"type":"Point"}
}