{
  "type": "Feature",
  "properties": {
    "gn:admin1_code":"8",
    "gn:asciiname":"Vigo",
    "gn:country_code":"CA",
    "gn:dem":207,
    "gn:feature_class":"P",
    "gn:feature_code":"PPL",
    "gn:name":"Vigo",
    "gn:population":0,
    "gn:timezone":"America/Toronto",
    "iso:country":"CA",
    "wof:name":"Vigo",
    "wof:placetype":"locality"
},
  "geometry": {"coordinates":[-79.90916999999997,44.47556],"type":"Point"}
}