{
  "type": "Feature",
  "properties": {
    "gn:country":"CA",
    "iso:country":"CA",
    "name:ceb_x_preferred":[
        "Milltown"
    ],
    "name:deu_x_preferred":[
        "Milltown"
    ],
    "name:eng_x_preferred":[
        "Milltown"
    ],
    "name:fra_x_preferred":[
        "Milltown"
    ],
    "name:ita_x_preferred":[
        "Milltown"
    ],
    "name:nld_x_preferred":[
        "Milltown"
    ],
    "name:pol_x_preferred":[
        "Milltown"
    ],
    "name:por_x_preferred":[
        "Milltown"
    ],
    "name:rus_x_preferred":[
        "\u041c\u0438\u043b\u0442\u0430\u0443\u043d"
    ],
    "name:srp_x_preferred":[
        "\u041c\u0438\u043b\u0442\u0430\u0443\u043d"
    ],
    "name:swe_x_preferred":[
        "Milltown"
    ],
    "name:ukr_x_preferred":[
        "\u041c\u0456\u043b\u043b\u0442\u0430\u0443\u043d"
    ],
    "name:vol_x_preferred":[
        "Milltown"
    ],
    "qs:name":"Milltown",
    "qs:name_adm0":"Canada",
    "qs:name_adm1":"Newfoundland and Labrador",
    "qs:photos":73,
    "qs:photos_1k":15,
    "qs:photos_9k":1,
    "qs:photos_9r":2,
    "qs:photos_all":73,
    "qs:photos_sr":2,
    "qs:placetype":"Town",
    "qs:pop_sr":"0",
    "wd:wordcount":294,
    "wof:name":"Milltown",
    "wof:placetype":"locality"
},
  "geometry": {"coordinates":[-55.747997,47.925221],"type":"Point"}
}