{
  "type": "Feature",
  "properties": {
    "iso:country":"CA",
    "name:eng_x_preferred":[
        "Malagash"
    ],
    "name:fra_x_preferred":[
        "Malagash"
    ],
    "name:gla_x_preferred":[
        "Malagais"
    ],
    "name:nld_x_preferred":[
        "Malagash"
    ],
    "qs:name":"Malagash",
    "qs:name_adm0":"Canada",
    "qs:name_adm1":"Nova Scotia",
    "qs:photos":52,
    "qs:photos_1k":11,
    "qs:photos_9k":1,
    "qs:photos_9r":2,
    "qs:photos_all":52,
    "qs:photos_sr":2,
    "qs:placetype":"Town",
    "qs:pop_sr":"0",
    "wd:wordcount":259,
    "wof:name":"Malagash",
    "wof:placetype":"locality"
},
  "geometry": {"coordinates":[-63.37326,45.794339],"type":"Point"}
}