{
  "type": "Feature",
  "properties": {
    "gn:admin1_code":"7",
    "gn:asciiname":"Gillis Point East",
    "gn:country_code":"CA",
    "gn:dem":18,
    "gn:feature_class":"P",
    "gn:feature_code":"PPL",
    "gn:name":"Gillis Point East",
    "gn:population":0,
    "gn:timezone":"America/Halifax",
    "iso:country":"CA",
    "wof:name":"Gillis Point East",
    "wof:placetype":"locality"
},
  "geometry": {"coordinates":[-60.78893000000001,46.01802],"type":"Point"}
}