{
  "type": "Feature",
  "properties": {
    "gn:admin1_code":"7",
    "gn:asciiname":"Franey Corner",
    "gn:country_code":"CA",
    "gn:dem":193,
    "gn:feature_class":"P",
    "gn:feature_code":"PPLL",
    "gn:name":"Franey Corner",
    "gn:population":0,
    "gn:timezone":"America/Halifax",
    "iso:country":"CA",
    "wof:name":"Franey Corner",
    "wof:placetype":"locality"
},
  "geometry": {"coordinates":[-64.66547,44.73345],"type":"Point"}
}