{
  "type": "Feature",
  "properties": {
    "iso:country":"CA",
    "name:eng_x_preferred":[
        "Boylston"
    ],
    "name:nld_x_preferred":[
        "Boylston"
    ],
    "qs:name":"Boylston",
    "qs:name_adm0":"Canada",
    "qs:name_adm1":"Nova Scotia",
    "qs:photos":8,
    "qs:photos_1k":2,
    "qs:photos_9k":1,
    "qs:photos_9r":1,
    "qs:photos_all":8,
    "qs:photos_sr":1,
    "qs:placetype":"Town",
    "qs:pop_sr":"0",
    "wd:wordcount":56,
    "wof:name":"Boylston",
    "wof:placetype":"locality"
},
  "geometry": {"coordinates":[-61.5058955,45.435803],"type":"Point"}
}