{
  "type": "Feature",
  "properties": {
    "gn:country":"CA",
    "gn:fcode":"PPL",
    "gn:pop":0,
    "iso:country":"CA",
    "name:cat_x_preferred":[
        "Shubenacadie"
    ],
    "name:dut_x_preferred":[
        "Shubenacadie"
    ],
    "name:eng_x_preferred":[
        "Shubenacadie"
    ],
    "name:fre_x_preferred":[
        "Shub\u00e9nacadie"
    ],
    "name:jpn_x_preferred":[
        "\u30ce\u30d0\u30b9\u30b3\u30b7\u30a2\u5dde"
    ],
    "qs:name":"Shubenacadie",
    "qs:name_adm0":"Canada",
    "qs:name_adm1":"Nova Scotia",
    "qs:photos":291,
    "qs:photos_1k":59,
    "qs:photos_9k":1,
    "qs:photos_9r":4,
    "qs:photos_all":291,
    "qs:photos_sr":5,
    "qs:placetype":"Town",
    "qs:pop_sr":"0",
    "wd:wordcount":22,
    "wof:name":"Shubenacadie",
    "wof:placetype":"locality",
    "wof:population":0
},
  "geometry": {"coordinates":[-63.39869,45.08345],"type":"Point"}
}