{
  "type": "Feature",
  "properties": {
    "gn:admin1_code":"11",
    "gn:asciiname":"Lone Rock",
    "gn:country_code":"CA",
    "gn:dem":632,
    "gn:feature_class":"P",
    "gn:feature_code":"PPLL",
    "gn:name":"Lone Rock",
    "gn:population":0,
    "gn:timezone":"America/Edmonton",
    "iso:country":"CA",
    "wof:name":"Lone Rock",
    "wof:placetype":"locality"
},
  "geometry": {"coordinates":[-109.88484,53.05016],"type":"Point"}
}