{
  "type": "Feature",
  "properties": {
    "gn:admin1_code":"8",
    "gn:asciiname":"Trapper's Landing",
    "gn:country_code":"CA",
    "gn:dem":410,
    "gn:feature_class":"P",
    "gn:feature_code":"PPLL",
    "gn:name":"Trapper's Landing",
    "gn:population":0,
    "gn:timezone":"America/Winnipeg",
    "iso:country":"CA",
    "wof:name":"Trapper's Landing",
    "wof:placetype":"locality"
},
  "geometry": {"coordinates":[-90.71659,50.2004],"type":"Point"}
}