{
  "type": "Feature",
  "properties": {
    "iso:country":"CA",
    "name:eng_x_preferred":[
        "Grimsby Beach"
    ],
    "qs:gn_adm0_cc":"CA",
    "qs:gn_local":5967149,
    "qs:gn_nam_loc":"grimsby",
    "qs:gn_namadm1":"08",
    "qs:local_max":468,
    "qs:local_sum":468,
    "qs:localhoods":1,
    "qs:name":"Grimsby Beach",
    "qs:name_adm0":"Canada",
    "qs:name_adm1":"Ontario",
    "qs:name_adm2":"Niagara",
    "qs:name_local":"Grimsby",
    "qs:photo_max":196,
    "qs:photo_sum":468,
    "qs:placetype":"Suburb",
    "qs:quad_count":37,
    "qs:woe_adm0":23424775,
    "qs:woe_adm1":2344922,
    "qs:woe_adm2":29375033,
    "qs:woe_funk":"Parented by a neighborhood",
    "qs:woe_lau":0,
    "qs:woe_local":4371,
    "qs:woe_ver":"7.10.0",
    "wof:lang":[
        "eng"
    ],
    "wof:name":"Grimsby Beach",
    "wof:placetype":"neighbourhood"
},
  "geometry": {"coordinates":[-79.577929,43.201545],"type":"Point"}
}