{
  "type": "Feature",
  "properties": {
    "gn:admin1_code":"7",
    "gn:asciiname":"Hardwood Hill",
    "gn:country_code":"CA",
    "gn:dem":34,
    "gn:feature_class":"P",
    "gn:feature_code":"PPL",
    "gn:name":"Hardwood Hill",
    "gn:population":0,
    "gn:timezone":"America/Halifax",
    "iso:country":"CA",
    "wof:name":"Hardwood Hill",
    "wof:placetype":"locality"
},
  "geometry": {"coordinates":[-62.81453000000001,45.65589],"type":"Point"}
}