{
  "type": "Feature",
  "properties": {
    "gn:admin1_code":"1",
    "gn:asciiname":"Highway",
    "gn:country_code":"CA",
    "gn:dem":785,
    "gn:feature_class":"P",
    "gn:feature_code":"PPL",
    "gn:name":"Highway",
    "gn:population":0,
    "gn:timezone":"America/Edmonton",
    "iso:country":"CA",
    "name:ang_x_preferred":[
        "H\u0113ahstr\u01e3t"
    ],
    "name:ara_x_preferred":[
        "\u0637\u0631\u064a\u0642 \u0633\u0631\u064a\u0639"
    ],
    "name:bel_x_preferred":[
        "\u0410\u045e\u0442\u0430\u043c\u0430\u0431\u0456\u043b\u044c\u043d\u0430\u044f \u0434\u0430\u0440\u043e\u0433\u0430"
    ],
    "name:ben_x_preferred":[
        "\u09b9\u09be\u0987\u0993\u09af\u09bc\u09c7"
    ],
    "name:bpy_x_preferred":[
        "\u09b9\u09be\u0987\u09f1\u09c7\u0987\u099c"
    ],
    "name:ckb_x_preferred":[
        "\u0634\u0627\u0695\u06ce\u06af\u06d5"
    ],
    "name:deu_x_preferred":[
        "Highway"
    ],
    "name:est_x_preferred":[
        "Maantee"
    ],
    "name:fas_x_preferred":[
        "\u0628\u0632\u0631\u06af\u200c\u0631\u0627\u0647"
    ],
    "name:fin_x_preferred":[
        "Maantie"
    ],
    "name:fra_x_preferred":[
        "Highway"
    ],
    "name:hin_x_preferred":[
        "\u0930\u093e\u091c\u092e\u093e\u0930\u094d\u0917"
    ],
    "name:kan_x_preferred":[
        "\u0cb9\u0cc6\u0ca6\u0ccd\u0ca6\u0cbe\u0cb0\u0cbf"
    ],
    "name:kaz_x_preferred":[
        "\u0410\u0432\u0442\u043e\u043c\u043e\u0431\u0438\u043b\u044c \u0436\u043e\u043b\u044b"
    ],
    "name:kir_x_preferred":[
        "\u0410\u0432\u0442\u043e\u043c\u043e\u0431\u0438\u043b\u044c \u0436\u043e\u043b\u0443"
    ],
    "name:kor_x_preferred":[
        "\uac04\uc120\ub3c4\ub85c"
    ],
    "name:mar_x_preferred":[
        "\u0928\u093f\u092f\u0902\u0924\u094d\u0930\u093f\u0924-\u092a\u094d\u0930\u0935\u0947\u0936 \u092e\u0939\u093e\u092e\u093e\u0930\u094d\u0917"
    ],
    "name:msa_x_preferred":[
        "Lebuh raya"
    ],
    "name:nep_x_preferred":[
        "\u0930\u093e\u091c\u092e\u093e\u0930\u094d\u0917"
    ],
    "name:new_x_preferred":[
        "\u0939\u093e\u0907\u0935\u0947\u091c"
    ],
    "name:nrm_x_preferred":[
        "C\u00e2ochie"
    ],
    "name:pan_x_preferred":[
        "\u0a38\u0a3c\u0a3e\u0a39\u0a30\u0a3e\u0a39"
    ],
    "name:por_x_preferred":[
        "Rodovia"
    ],
    "name:rus_x_preferred":[
        "\u0410\u0432\u0442\u043e\u043c\u043e\u0431\u0438\u043b\u044c\u043d\u0430\u044f \u0434\u043e\u0440\u043e\u0433\u0430"
    ],
    "name:som_x_preferred":[
        "Wadoweyn"
    ],
    "name:tam_x_preferred":[
        "\u0ba8\u0bc6\u0b9f\u0bc1\u0b9e\u0bcd\u0b9a\u0bbe\u0bb2\u0bc8"
    ],
    "name:tha_x_preferred":[
        "\u0e17\u0e32\u0e07\u0e2b\u0e25\u0e27\u0e07"
    ],
    "name:ukr_x_preferred":[
        "\u0410\u0432\u0442\u043e\u043c\u043e\u0431\u0456\u043b\u044c\u043d\u0430 \u0434\u043e\u0440\u043e\u0433\u0430"
    ],
    "name:urd_x_preferred":[
        "\u0634\u0627\u06c1\u0631\u0627\u06c1"
    ],
    "name:vie_x_preferred":[
        "Xa l\u1ed9"
    ],
    "name:yid_x_preferred":[
        "\u05e9\u05d8\u05e8\u05d0\u05d6"
    ],
    "wof:name":"Highway",
    "wof:placetype":"locality"
},
  "geometry": {"coordinates":[-115.47972,53.88944],"type":"Point"}
}