{
  "type": "Feature",
  "properties": {
    "gn:admin1_code":"1",
    "gn:asciiname":"Highway",
    "gn:country_code":"CA",
    "gn:dem":785,
    "gn:feature_class":"P",
    "gn:feature_code":"PPL",
    "gn:name":"Highway",
    "gn:population":0,
    "gn:timezone":"America/Edmonton",
    "iso:country":"CA",
    "wof:name":"Highway",
    "wof:placetype":"locality"
},
  "geometry": {"coordinates":[-115.47972,53.88944],"type":"Point"}
}