{
  "type": "Feature",
  "properties": {
    "gn:admin1_code":"8",
    "gn:asciiname":"Osnaburgh House",
    "gn:country_code":"CA",
    "gn:dem":371,
    "gn:feature_class":"P",
    "gn:feature_code":"PPLL",
    "gn:name":"Osnaburgh House",
    "gn:population":0,
    "gn:timezone":"America/Toronto",
    "iso:country":"CA",
    "wof:name":"Osnaburgh House",
    "wof:placetype":"locality"
},
  "geometry": {"coordinates":[-90.26685999999999,51.13341],"type":"Point"}
}