{
  "type": "Feature",
  "properties": {
    "gn:admin1_code":"8",
    "gn:asciiname":"Plainfield",
    "gn:country_code":"CA",
    "gn:dem":109,
    "gn:feature_class":"P",
    "gn:feature_code":"PPL",
    "gn:name":"Plainfield",
    "gn:population":0,
    "gn:timezone":"America/Toronto",
    "iso:country":"CA",
    "wof:name":"Plainfield",
    "wof:placetype":"locality"
},
  "geometry": {"coordinates":[-77.34833,44.29083],"type":"Point"}
}