{
  "type": "Feature",
  "properties": {
    "gn:admin1_code":"8",
    "gn:asciiname":"Hurdville",
    "gn:country_code":"CA",
    "gn:dem":240,
    "gn:feature_class":"P",
    "gn:feature_code":"PPL",
    "gn:name":"Hurdville",
    "gn:population":0,
    "gn:timezone":"America/Toronto",
    "iso:country":"CA",
    "wof:name":"Hurdville",
    "wof:placetype":"locality"
},
  "geometry": {"coordinates":[-79.92166999999998,45.44083],"type":"Point"}
}