{
  "type": "Feature",
  "properties": {
    "gn:admin1_code":"4",
    "gn:asciiname":"Teahans Corner",
    "gn:country_code":"CA",
    "gn:dem":332,
    "gn:feature_class":"P",
    "gn:feature_code":"PPLL",
    "gn:name":"Teahans Corner",
    "gn:population":0,
    "gn:timezone":"America/Moncton",
    "iso:country":"CA",
    "wof:name":"Teahans Corner",
    "wof:placetype":"locality"
},
  "geometry": {"coordinates":[-64.96548,45.70016],"type":"Point"}
}