{
  "type": "Feature",
  "properties": {
    "gn:admin1_code":"11.0",
    "gn:asciiname":"Chortitz",
    "gn:country_code":"CA",
    "gn:dem":522,
    "gn:feature_class":"P",
    "gn:feature_code":"PPLL",
    "gn:name":"Chortitz",
    "gn:population":0,
    "gn:timezone":"America/Regina",
    "iso:country":"CA",
    "wof:name":"Chortitz",
    "wof:placetype":"locality"
},
  "geometry": {"coordinates":[-106.55118,52.50009],"type":"Point"}
}