{
  "type": "Feature",
  "properties": {
    "iso:country":"CA",
    "name:eng_x_preferred":[
        "Beaumaris"
    ],
    "name:nld_x_preferred":[
        "Beaumaris"
    ],
    "qs_pg:aaroncc":"CA",
    "qs_pg:name":"Beaumaris",
    "qs_pg:name_adm0":"Canada",
    "qs_pg:name_adm1":"Ontario",
    "qs_pg:photos":837,
    "qs_pg:photos_1k":170,
    "qs_pg:photos_9k":4,
    "qs_pg:photos_9r":6,
    "qs_pg:photos_all":837,
    "qs_pg:photos_sr":9,
    "qs_pg:pop_sr":0,
    "qs_pg:qs_pg_placetype":"locality",
    "qs_pg:qs_pg_placetype_gp":"Town",
    "qs_pg:woe_adm0":23424775,
    "woe:adm0_id":23424775,
    "woe:name_adm0":"Canada",
    "woe:name_adm1":"Ontario",
    "woe:placetype":"Town",
    "wof:name":"Beaumaris",
    "wof:placetype":"locality"
},
  "geometry": {"coordinates":[-79.511661,45.094489],"type":"Point"}
}