{
  "type": "Feature",
  "properties": {
    "gn:country":"CA",
    "gn:fcode":"PPL",
    "gn:population":968,
    "iso:country":"CA",
    "name:ceb_x_preferred":[
        "Hare Bay"
    ],
    "name:eng_x_preferred":[
        "Hare Bay"
    ],
    "name:nld_x_preferred":[
        "Hare Bay"
    ],
    "name:swe_x_preferred":[
        "Hare Bay"
    ],
    "qs:name":"Hare Bay",
    "qs:name_adm0":"Canada",
    "qs:name_adm1":"Newfoundland and Labrador",
    "qs:photos_9k":1,
    "qs:photos_9r":1,
    "qs:photos_all":2,
    "qs:photos_sr":0,
    "qs:placetype":"Town",
    "qs:pop_sr":"2",
    "wd:wordcount":30,
    "wof:name":"Hare Bay",
    "wof:placetype":"locality",
    "wof:population":968
},
  "geometry": {"coordinates":[-54.01481,48.8499],"type":"Point"}
}