{
  "type": "Feature",
  "properties": {
    "gn:admin1_code":"12",
    "gn:asciiname":"Lansing",
    "gn:country_code":"CA",
    "gn:dem":607,
    "gn:feature_class":"P",
    "gn:feature_code":"PPLL",
    "gn:name":"Lansing",
    "gn:population":0,
    "gn:timezone":"America/Whitehorse",
    "iso:country":"CA",
    "wof:name":"Lansing",
    "wof:placetype":"locality"
},
  "geometry": {"coordinates":[-133.47621999999998,63.7441],"type":"Point"}
}