{
  "type": "Feature",
  "properties": {
    "gn:admin1_code":"1",
    "gn:asciiname":"Welling",
    "gn:country_code":"CA",
    "gn:dem":958,
    "gn:feature_class":"P",
    "gn:feature_code":"PPLL",
    "gn:name":"Welling",
    "gn:population":0,
    "gn:timezone":"America/Edmonton",
    "iso:country":"CA",
    "name:fra_x_preferred":[
        "Welling"
    ],
    "wof:name":"Welling",
    "wof:placetype":"locality"
},
  "geometry": {"coordinates":[-112.78516,49.46668],"type":"Point"}
}