{
  "type": "Feature",
  "properties": {
    "iso:country":"CA",
    "name:deu_x_preferred":[
        "Anahim Lake"
    ],
    "name:eng_x_preferred":[
        "Anahim Lake"
    ],
    "name:fin_x_preferred":[
        "Anahim Lake"
    ],
    "name:fra_x_preferred":[
        "Anahim Lake"
    ],
    "name:nld_x_preferred":[
        "Anahim Lake"
    ],
    "qs_pg:aaroncc":"CA",
    "qs_pg:name":"Anahim Lake",
    "qs_pg:name_adm0":"Canada",
    "qs_pg:name_adm1":"British Columbia",
    "qs_pg:photos":214,
    "qs_pg:photos_1k":43,
    "qs_pg:photos_9k":1,
    "qs_pg:photos_9r":4,
    "qs_pg:photos_all":214,
    "qs_pg:photos_sr":4,
    "qs_pg:pop_sr":0,
    "qs_pg:qs_pg_placetype":"locality",
    "qs_pg:qs_pg_placetype_gp":"Town",
    "qs_pg:woe_adm0":23424775,
    "woe:adm0_id":23424775,
    "woe:name_adm0":"Canada",
    "woe:name_adm1":"British Columbia",
    "woe:placetype":"Town",
    "wof:name":"Anahim Lake",
    "wof:placetype":"locality"
},
  "geometry": {"coordinates":[-125.281305,52.466364],"type":"Point"}
}