{
  "type": "Feature",
  "properties": {
    "gn:admin1_code":"8",
    "gn:asciiname":"Ennotville",
    "gn:country_code":"CA",
    "gn:dem":390,
    "gn:feature_class":"P",
    "gn:feature_code":"PPL",
    "gn:name":"Ennotville",
    "gn:population":0,
    "gn:timezone":"America/Toronto",
    "iso:country":"CA",
    "wof:name":"Ennotville",
    "wof:placetype":"locality"
},
  "geometry": {"coordinates":[-80.32935000000001,43.65682],"type":"Point"}
}