{
  "type": "Feature",
  "properties": {
    "gn:admin1_code":"2",
    "gn:asciiname":"Port Douglas",
    "gn:country_code":"CA",
    "gn:dem":194,
    "gn:feature_class":"P",
    "gn:feature_code":"PPLL",
    "gn:name":"Port Douglas",
    "gn:population":0,
    "gn:timezone":"America/Vancouver",
    "iso:country":"CA",
    "name:deu_x_preferred":[
        "Port Douglas"
    ],
    "name:fas_x_preferred":[
        "\u067e\u0648\u0631\u062a \u062f\u0627\u06af\u0644\u0633"
    ],
    "wof:name":"Port Douglas",
    "wof:placetype":"locality"
},
  "geometry": {"coordinates":[-122.16931,49.76639],"type":"Point"}
}