{
  "type": "Feature",
  "properties": {
    "gn:admin1_code":"2",
    "gn:asciiname":"Port Douglas",
    "gn:country_code":"CA",
    "gn:dem":194,
    "gn:feature_class":"P",
    "gn:feature_code":"PPLL",
    "gn:name":"Port Douglas",
    "gn:population":0,
    "gn:timezone":"America/Vancouver",
    "iso:country":"CA",
    "name:ben_x_preferred":[
        "\u09aa\u09cb\u09b0\u09cd\u099f \u09a1\u0997\u09b2\u09be\u09b8"
    ],
    "name:deu_x_preferred":[
        "Port Douglas"
    ],
    "name:ell_x_preferred":[
        "\u03a0\u03bf\u03c1\u03c4 \u039d\u03c4\u03ac\u03b3\u03ba\u03bb\u03b1\u03c2"
    ],
    "name:fas_x_preferred":[
        "\u067e\u0648\u0631\u062a \u062f\u0627\u06af\u0644\u0633"
    ],
    "name:heb_x_preferred":[
        "\u05e4\u05d5\u05e8\u05d8 \u05d3\u05d2\u05dc\u05e1"
    ],
    "name:hin_x_preferred":[
        "\u092a\u094b\u0930\u094d\u091f \u0921\u0917\u094d\u0932\u0938"
    ],
    "name:hun_x_preferred":[
        "Port Douglas"
    ],
    "name:ind_x_preferred":[
        "Port Douglas"
    ],
    "name:ita_x_preferred":[
        "Port Douglas"
    ],
    "name:rus_x_preferred":[
        "\u041f\u043e\u0440\u0442-\u0414\u0443\u0433\u043b\u0430\u0441"
    ],
    "name:spa_x_preferred":[
        "Port Douglas"
    ],
    "name:tur_x_preferred":[
        "Port Douglas"
    ],
    "name:ukr_x_preferred":[
        "\u041f\u043e\u0440\u0442-\u0414\u0443\u0433\u043b\u0430\u0441"
    ],
    "name:urd_x_preferred":[
        "\u067e\u0648\u0631\u0679 \u0688\u06af\u0644\u0633"
    ],
    "name:vie_x_preferred":[
        "Port Douglas"
    ],
    "wof:name":"Port Douglas",
    "wof:placetype":"locality"
},
  "geometry": {"coordinates":[-122.16931,49.76639],"type":"Point"}
}