{
  "type": "Feature",
  "properties": {
    "gn:admin1_code":"10.0",
    "gn:admin2_code":"16.0",
    "gn:asciiname":"Dunboro",
    "gn:country_code":"CA",
    "gn:dem":229,
    "gn:feature_class":"P",
    "gn:feature_code":"PPL",
    "gn:name":"Dunboro",
    "gn:population":0,
    "gn:timezone":"America/Toronto",
    "iso:country":"CA",
    "wof:name":"Dunboro",
    "wof:placetype":"locality"
},
  "geometry": {"coordinates":[-72.72651,45.14837],"type":"Point"}
}