{
  "type": "Feature",
  "properties": {
    "gn:admin1_code":"8",
    "gn:asciiname":"Fox's Corners",
    "gn:country_code":"CA",
    "gn:dem":266,
    "gn:feature_class":"P",
    "gn:feature_code":"PPLL",
    "gn:name":"Fox's Corners",
    "gn:population":0,
    "gn:timezone":"America/Toronto",
    "iso:country":"CA",
    "wof:name":"Fox's Corners",
    "wof:placetype":"locality"
},
  "geometry": {"coordinates":[-78.59875,44.38432],"type":"Point"}
}