{
  "type": "Feature",
  "properties": {
    "iso:country":"CA",
    "name:eng_x_preferred":[
        "Cape North"
    ],
    "name:gla_x_preferred":[
        "Ceap N\u00f2r"
    ],
    "name:nld_x_preferred":[
        "Cape North"
    ],
    "qs:name":"Cape North",
    "qs:name_adm0":"Canada",
    "qs:name_adm1":"Nova Scotia",
    "qs:photos":82,
    "qs:photos_1k":17,
    "qs:photos_9k":1,
    "qs:photos_9r":3,
    "qs:photos_all":82,
    "qs:photos_sr":3,
    "qs:placetype":"Town",
    "qs:pop_sr":"0",
    "wd:wordcount":32,
    "wof:name":"Cape North",
    "wof:placetype":"locality"
},
  "geometry": {"coordinates":[-60.51675,46.880141],"type":"Point"}
}