{
  "type": "Feature",
  "properties": {
    "gn:admin1_code":"3",
    "gn:asciiname":"Rocky Lake East",
    "gn:country_code":"CA",
    "gn:dem":265,
    "gn:feature_class":"P",
    "gn:feature_code":"PPLL",
    "gn:name":"Rocky Lake East",
    "gn:population":0,
    "gn:timezone":"America/Winnipeg",
    "iso:country":"CA",
    "wof:name":"Rocky Lake East",
    "wof:placetype":"locality"
},
  "geometry": {"coordinates":[-101.43801000000001,54.1251],"type":"Point"}
}