{
  "type": "Feature",
  "properties": {
    "gn:admin1_code":"8.0",
    "gn:asciiname":"Blacks Corners",
    "gn:country_code":"CA",
    "gn:dem":139,
    "gn:feature_class":"P",
    "gn:feature_code":"PPL",
    "gn:name":"Blacks Corners",
    "gn:population":0,
    "gn:timezone":"America/Toronto",
    "iso:country":"CA",
    "wof:name":"Blacks Corners",
    "wof:placetype":"locality"
},
  "geometry": {"coordinates":[-76.10459,45.10755],"type":"Point"}
}