{
  "type": "Feature",
  "properties": {
    "iso:country":"CA",
    "name:bul_x_preferred":[
        "\u0423\u043b\u0443\u043a\u0445\u0430\u043a\u0442\u043e\u043a"
    ],
    "name:ces_x_preferred":[
        "Ulukhaktok"
    ],
    "name:deu_x_preferred":[
        "Ulukhaktok"
    ],
    "name:eng_x_preferred":[
        "Ulukhaktok"
    ],
    "name:fra_x_preferred":[
        "Ulukhaktok"
    ],
    "name:nld_x_preferred":[
        "Ulukhaktok"
    ],
    "name:por_x_preferred":[
        "Ulukhaktok"
    ],
    "name:rus_x_preferred":[
        "\u0423\u043b\u0443\u043a\u0445\u0430\u043a\u0442\u043e\u043a"
    ],
    "name:swe_x_preferred":[
        "Ulukhaktok"
    ],
    "name:tur_x_preferred":[
        "Ulukhaktok"
    ],
    "qs_pg:aaroncc":"CA",
    "qs_pg:name":"Ulukhaktok",
    "qs_pg:name_adm0":"Canada",
    "qs_pg:name_adm1":"Nunavut",
    "qs_pg:photos":87,
    "qs_pg:photos_1k":18,
    "qs_pg:photos_9k":1,
    "qs_pg:photos_9r":3,
    "qs_pg:photos_all":87,
    "qs_pg:photos_sr":3,
    "qs_pg:pop_sr":0,
    "qs_pg:qs_pg_placetype":"locality",
    "qs_pg:qs_pg_placetype_gp":"Town",
    "qs_pg:woe_adm0":23424775,
    "woe:adm0_id":23424775,
    "woe:name_adm0":"Canada",
    "woe:name_adm1":"Nunavut",
    "woe:placetype":"Town",
    "wof:name":"Ulukhaktok",
    "wof:placetype":"locality"
},
  "geometry": {"coordinates":[-117.782535,70.736576],"type":"Point"}
}