{
  "type": "Feature",
  "properties": {
    "gn:admin1_code":"1.0",
    "gn:asciiname":"West Baptiste",
    "gn:country_code":"CA",
    "gn:dem":588,
    "gn:feature_class":"P",
    "gn:feature_code":"PPL",
    "gn:name":"West Baptiste",
    "gn:population":0,
    "gn:timezone":"America/Edmonton",
    "iso:country":"CA",
    "wof:name":"West Baptiste",
    "wof:placetype":"locality"
},
  "geometry": {"coordinates":[-113.5688,54.75016],"type":"Point"}
}