{
  "type": "Feature",
  "properties": {
    "gn:admin1_code":"4",
    "gn:asciiname":"Nashwaak Village",
    "gn:country_code":"CA",
    "gn:dem":19,
    "gn:feature_class":"P",
    "gn:feature_code":"PPL",
    "gn:name":"Nashwaak Village",
    "gn:population":0,
    "gn:timezone":"America/Moncton",
    "iso:country":"CA",
    "name:fra_x_preferred":[
        "Nashwaak Village"
    ],
    "wof:name":"Nashwaak Village",
    "wof:placetype":"locality"
},
  "geometry": {"coordinates":[-66.61158,46.09568],"type":"Point"}
}