{
  "type": "Feature",
  "properties": {
    "gn:admin1_code":"7",
    "gn:asciiname":"Kaneville",
    "gn:country_code":"CA",
    "gn:dem":35,
    "gn:feature_class":"P",
    "gn:feature_code":"PPL",
    "gn:name":"Kaneville",
    "gn:population":0,
    "gn:timezone":"America/Glace_Bay",
    "iso:country":"CA",
    "wof:name":"Kaneville",
    "wof:placetype":"locality"
},
  "geometry": {"coordinates":[-60.10852,46.25026],"type":"Point"}
}