{
  "type": "Feature",
  "properties": {
    "iso:country":"CA",
    "name:eng_x_preferred":[
        "Hammond Bay"
    ],
    "qs:gn_adm0_cc":"CA",
    "qs:gn_local":6085772,
    "qs:gn_nam_loc":"nanaimo",
    "qs:gn_namadm1":"02",
    "qs:local_max":2323,
    "qs:local_sum":7639,
    "qs:localhoods":17,
    "qs:name":"Hammond Bay",
    "qs:name_adm0":"Canada",
    "qs:name_adm1":"British Columbia",
    "qs:name_adm2":"Nanaimo",
    "qs:name_local":"Nanaimo",
    "qs:photo_max":60,
    "qs:photo_sum":633,
    "qs:placetype":"Suburb",
    "qs:quad_count":52,
    "qs:woe_adm0":23424775,
    "qs:woe_adm1":2344916,
    "qs:woe_adm2":29375073,
    "qs:woe_funk":"Grouping neighborhood",
    "qs:woe_lau":0,
    "qs:woe_local":9814,
    "qs:woe_ver":"7.10.0",
    "wof:lang":[
        "eng"
    ],
    "wof:name":"Hammond Bay",
    "wof:placetype":"neighbourhood"
},
  "geometry": {"coordinates":[-123.955934,49.228381],"type":"Point"}
}