{
  "type": "Feature",
  "properties": {
    "gn:admin1_code":"8",
    "gn:asciiname":"Haldane Hill",
    "gn:country_code":"CA",
    "gn:dem":339,
    "gn:feature_class":"P",
    "gn:feature_code":"PPL",
    "gn:name":"Haldane Hill",
    "gn:population":0,
    "gn:timezone":"America/Toronto",
    "iso:country":"CA",
    "wof:name":"Haldane Hill",
    "wof:placetype":"locality"
},
  "geometry": {"coordinates":[-79.42444,45.42139],"type":"Point"}
}