{
  "type": "Feature",
  "properties": {
    "gn:admin1_code":"7",
    "gn:asciiname":"Grande Greve",
    "gn:country_code":"CA",
    "gn:dem":29,
    "gn:feature_class":"P",
    "gn:feature_code":"PPL",
    "gn:name":"Grande Greve",
    "gn:population":0,
    "gn:timezone":"America/Halifax",
    "iso:country":"CA",
    "name:fra_x_preferred":[
        "Grande-Gr\u00e8ve"
    ],
    "wof:name":"Grande Greve",
    "wof:placetype":"locality"
},
  "geometry": {"coordinates":[-60.84444000000001,45.63093],"type":"Point"}
}