{
  "type": "Feature",
  "properties": {
    "gn:admin1_code":"11.0",
    "gn:asciiname":"Arbuthnot",
    "gn:country_code":"CA",
    "gn:dem":779,
    "gn:feature_class":"P",
    "gn:feature_code":"PPL",
    "gn:name":"Arbuthnot",
    "gn:population":0,
    "gn:timezone":"America/Regina",
    "iso:country":"CA",
    "wof:name":"Arbuthnot",
    "wof:placetype":"locality"
},
  "geometry": {"coordinates":[-106.90063000000001,49.8167],"type":"Point"}
}