{
  "type": "Feature",
  "properties": {
    "gn:admin1_code":"1",
    "gn:asciiname":"Warrensville Centre",
    "gn:country_code":"CA",
    "gn:dem":650,
    "gn:feature_class":"P",
    "gn:feature_code":"PPLL",
    "gn:name":"Warrensville Centre",
    "gn:population":0,
    "gn:timezone":"America/Edmonton",
    "iso:country":"CA",
    "wof:name":"Warrensville Centre",
    "wof:placetype":"locality"
},
  "geometry": {"coordinates":[-117.61941000000002,56.30009],"type":"Point"}
}