{
  "type": "Feature",
  "properties": {
    "gn:admin1_code":"11.0",
    "gn:asciiname":"Cleeves",
    "gn:country_code":"CA",
    "gn:dem":592,
    "gn:feature_class":"P",
    "gn:feature_code":"PPLL",
    "gn:name":"Cleeves",
    "gn:population":0,
    "gn:timezone":"America/Regina",
    "iso:country":"CA",
    "wof:name":"Cleeves",
    "wof:placetype":"locality"
},
  "geometry": {"coordinates":[-109.05145,53.46688],"type":"Point"}
}