{
  "type": "Feature",
  "properties": {
    "gn:admin1_code":"7",
    "gn:asciiname":"North River Centre",
    "gn:country_code":"CA",
    "gn:dem":29,
    "gn:feature_class":"P",
    "gn:feature_code":"PPL",
    "gn:name":"North River Centre",
    "gn:population":0,
    "gn:timezone":"America/Halifax",
    "iso:country":"CA",
    "wof:name":"North River Centre",
    "wof:placetype":"locality"
},
  "geometry": {"coordinates":[-60.61645,46.29423],"type":"Point"}
}