{
  "type": "Feature",
  "properties": {
    "gn:admin1_code":"1",
    "gn:asciiname":"Pingle",
    "gn:country_code":"CA",
    "gn:dem":547,
    "gn:feature_class":"P",
    "gn:feature_code":"PPLL",
    "gn:name":"Pingle",
    "gn:population":0,
    "gn:timezone":"America/Edmonton",
    "iso:country":"CA",
    "name:ceb_x_preferred":[
        "Pingle"
    ],
    "name:deu_x_preferred":[
        "Pingle"
    ],
    "wof:name":"Pingle",
    "wof:placetype":"locality"
},
  "geometry": {"coordinates":[-110.91849999999999,55.91691],"type":"Point"}
}