{
  "type": "Feature",
  "properties": {
    "gn:admin1_code":"9.0",
    "gn:asciiname":"Central Kildare",
    "gn:country_code":"CA",
    "gn:dem":5,
    "gn:feature_class":"P",
    "gn:feature_code":"PPLL",
    "gn:name":"Central Kildare",
    "gn:population":0,
    "gn:timezone":"America/Halifax",
    "iso:country":"CA",
    "name:fra_x_preferred":[
        "Central Kildare"
    ],
    "wof:name":"Central Kildare",
    "wof:placetype":"locality"
},
  "geometry": {"coordinates":[-63.99872,46.86684],"type":"Point"}
}