{
  "type": "Feature",
  "properties": {
    "gn:admin1_code":"11",
    "gn:asciiname":"Portreeve",
    "gn:country_code":"CA",
    "gn:dem":672,
    "gn:feature_class":"P",
    "gn:feature_code":"PPL",
    "gn:name":"Portreeve",
    "gn:population":0,
    "gn:timezone":"America/Regina",
    "iso:country":"CA",
    "wof:name":"Portreeve",
    "wof:placetype":"locality"
},
  "geometry": {"coordinates":[-109.01739000000001,50.83338],"type":"Point"}
}