{
  "type": "Feature",
  "properties": {
    "gn:admin1_code":"10",
    "gn:admin2_code":"15.0",
    "gn:admin3_code":"78100.0",
    "gn:asciiname":"Lac-de-l'Orignal",
    "gn:country_code":"CA",
    "gn:dem":492,
    "gn:feature_class":"P",
    "gn:feature_code":"PPL",
    "gn:name":"Lac-de-l'Orignal",
    "gn:population":0,
    "gn:timezone":"America/Toronto",
    "iso:country":"CA",
    "wof:name":"Lac-de-l'Orignal",
    "wof:placetype":"locality"
},
  "geometry": {"coordinates":[-74.32683,46.21615],"type":"Point"}
}