{
  "type": "Feature",
  "properties": {
    "gn:admin1_code":"7.0",
    "gn:asciiname":"Brownsville",
    "gn:country_code":"CA",
    "gn:dem":10,
    "gn:feature_class":"P",
    "gn:feature_code":"PPL",
    "gn:name":"Brownsville",
    "gn:population":0,
    "gn:timezone":"America/Halifax",
    "iso:country":"CA",
    "wof:name":"Brownsville",
    "wof:placetype":"locality"
},
  "geometry": {"coordinates":[-62.39182,45.6454],"type":"Point"}
}