{
  "type": "Feature",
  "properties": {
    "gn:admin1_code":"8",
    "gn:asciiname":"Kaministiquia",
    "gn:country_code":"CA",
    "gn:dem":350,
    "gn:feature_class":"P",
    "gn:feature_code":"PPL",
    "gn:name":"Kaministiquia",
    "gn:population":0,
    "gn:timezone":"America/Toronto",
    "iso:country":"CA",
    "name:deu_x_preferred":[
        "Kaministiquia"
    ],
    "name:fra_x_preferred":[
        "Kaministiquia"
    ],
    "wof:name":"Kaministiquia",
    "wof:placetype":"locality"
},
  "geometry": {"coordinates":[-89.56684,48.5334],"type":"Point"}
}