{
  "type": "Feature",
  "properties": {
    "gn:admin1_code":"8.0",
    "gn:asciiname":"Burnaby",
    "gn:country_code":"CA",
    "gn:dem":187,
    "gn:feature_class":"P",
    "gn:feature_code":"PPL",
    "gn:name":"Burnaby",
    "gn:population":0,
    "gn:timezone":"America/Toronto",
    "iso:country":"CA",
    "wof:name":"Burnaby",
    "wof:placetype":"locality"
},
  "geometry": {"coordinates":[-79.35361,42.86917],"type":"Point"}
}