{
  "type": "Feature",
  "properties": {
    "gn:admin1_code":"8.0",
    "gn:asciiname":"Burnaby",
    "gn:country_code":"CA",
    "gn:dem":187,
    "gn:feature_class":"P",
    "gn:feature_code":"PPL",
    "gn:name":"Burnaby",
    "gn:population":0,
    "gn:timezone":"America/Toronto",
    "iso:country":"CA",
    "name:ara_x_preferred":[
        "\u0628\u0631\u0646\u0627\u0628\u064a"
    ],
    "name:arz_x_preferred":[
        "\u0628\u0631\u0646\u0627\u0628\u0649"
    ],
    "name:ast_x_preferred":[
        "Burnaby"
    ],
    "name:azb_x_preferred":[
        "\u0628\u0648\u0631\u0646\u0627\u0628\u06cc"
    ],
    "name:bul_x_preferred":[
        "\u0411\u044a\u0440\u043d\u0430\u0431\u0438"
    ],
    "name:ceb_x_preferred":[
        "Burnaby"
    ],
    "name:deu_x_preferred":[
        "Burnaby"
    ],
    "name:epo_x_preferred":[
        "Burnaby"
    ],
    "name:fas_x_preferred":[
        "\u0628\u0631\u0646\u0627\u0628\u06cc"
    ],
    "name:fin_x_preferred":[
        "Burnaby"
    ],
    "name:fra_x_preferred":[
        "Burnaby"
    ],
    "name:gle_x_preferred":[
        "Burnaby"
    ],
    "name:ind_x_preferred":[
        "Burnaby"
    ],
    "name:ita_x_preferred":[
        "Burnaby"
    ],
    "name:jpn_x_preferred":[
        "\u30d0\u30fc\u30ca\u30d3\u30fc"
    ],
    "name:kor_x_preferred":[
        "\ubc84\ub108\ube44"
    ],
    "name:lav_x_preferred":[
        "B\u0113rnabija"
    ],
    "name:lit_x_preferred":[
        "Barnabis"
    ],
    "name:nld_x_preferred":[
        "Burnaby"
    ],
    "name:nor_x_preferred":[
        "Burnaby"
    ],
    "name:oss_x_preferred":[
        "\u0411\u0451\u0440\u043d\u0430\u0431\u0438"
    ],
    "name:pnb_x_preferred":[
        "\u0628\u0631\u0646\u06cc\u0628\u06cc"
    ],
    "name:pol_x_preferred":[
        "Burnaby"
    ],
    "name:por_x_preferred":[
        "Burnaby"
    ],
    "name:ron_x_preferred":[
        "Burnaby"
    ],
    "name:rus_x_preferred":[
        "\u0411\u0435\u0440\u043d\u0430\u0431\u0438"
    ],
    "name:sah_x_preferred":[
        "\u0411\u04e9\u0440\u043d\u0430\u0431\u0438"
    ],
    "name:sco_x_preferred":[
        "Burnaby"
    ],
    "name:slk_x_preferred":[
        "Burnaby"
    ],
    "name:spa_x_preferred":[
        "Burnaby"
    ],
    "name:sqi_x_preferred":[
        "Burnaby"
    ],
    "name:srd_x_preferred":[
        "Burnaby"
    ],
    "name:srp_x_preferred":[
        "\u0411\u0435\u0440\u043d\u0430\u0431\u0438"
    ],
    "name:swa_x_preferred":[
        "Burnaby"
    ],
    "name:swe_x_preferred":[
        "Burnaby"
    ],
    "name:tat_x_preferred":[
        "\u0411\u04e9\u0440\u043d\u0430\u0431\u0438"
    ],
    "name:tgl_x_preferred":[
        "Burnaby"
    ],
    "name:tur_x_preferred":[
        "Burnaby"
    ],
    "name:ukr_x_preferred":[
        "\u0411\u0435\u0440\u043d\u0430\u0431\u0456"
    ],
    "name:urd_x_preferred":[
        "\u0628\u0631\u0646\u0627\u0628\u06d2"
    ],
    "name:vie_x_preferred":[
        "Burnaby"
    ],
    "name:vol_x_preferred":[
        "Burnaby"
    ],
    "name:war_x_preferred":[
        "Burnaby"
    ],
    "name:xmf_x_preferred":[
        "\u10d1\u10d4\u10e0\u10dc\u10d0\u10d1\u10d8"
    ],
    "name:zho_x_preferred":[
        "\u672c\u62ff\u6bd4"
    ],
    "wof:name":"Burnaby",
    "wof:placetype":"locality"
},
  "geometry": {"coordinates":[-79.35361,42.86917],"type":"Point"}
}