{
  "type": "Feature",
  "properties": {
    "gn:admin1_code":"8.0",
    "gn:asciiname":"Woermke",
    "gn:country_code":"CA",
    "gn:dem":450,
    "gn:feature_class":"P",
    "gn:feature_code":"PPL",
    "gn:name":"Woermke",
    "gn:population":0,
    "gn:timezone":"America/Toronto",
    "iso:country":"CA",
    "wof:name":"Woermke",
    "wof:placetype":"locality"
},
  "geometry": {"coordinates":[-77.24122,45.39769],"type":"Point"}
}