{
  "type": "Feature",
  "properties": {
    "gn:admin1_code":"8",
    "gn:asciiname":"Senecal",
    "gn:country_code":"CA",
    "gn:dem":82,
    "gn:feature_class":"P",
    "gn:feature_code":"PPL",
    "gn:name":"Senecal",
    "gn:population":0,
    "gn:timezone":"America/Toronto",
    "iso:country":"CA",
    "wof:name":"Senecal",
    "wof:placetype":"locality"
},
  "geometry": {"coordinates":[-74.99611,45.55972],"type":"Point"}
}