{
  "type": "Feature",
  "properties": {
    "gn:admin1_code":"7",
    "gn:asciiname":"Greens Point",
    "gn:country_code":"CA",
    "gn:dem":13,
    "gn:feature_class":"P",
    "gn:feature_code":"PPL",
    "gn:name":"Greens Point",
    "gn:population":0,
    "gn:timezone":"America/Halifax",
    "iso:country":"CA",
    "wof:name":"Greens Point",
    "wof:placetype":"locality"
},
  "geometry": {"coordinates":[-62.65102,45.62715],"type":"Point"}
}