{
  "type": "Feature",
  "properties": {
    "iso:country":"CA",
    "name:eng_x_preferred":[
        "Maple Ridge Town Centre"
    ],
    "qs:gn_adm0_cc":"CA",
    "qs:gn_local":6065686,
    "qs:gn_nam_loc":"maple ridge",
    "qs:gn_namadm1":"02",
    "qs:local_max":639,
    "qs:local_sum":1720,
    "qs:localhoods":8,
    "qs:name":"Maple Ridge Town Centre",
    "qs:name_adm0":"Canada",
    "qs:name_adm1":"British Columbia",
    "qs:name_adm2":"Greater Vancouver",
    "qs:name_local":"Maple Ridge",
    "qs:photo_max":150,
    "qs:photo_sum":233,
    "qs:placetype":"Suburb",
    "qs:quad_count":10,
    "qs:woe_adm0":23424775,
    "qs:woe_adm1":2344916,
    "qs:woe_adm2":29375222,
    "qs:woe_funk":"Parented by a neighborhood",
    "qs:woe_lau":0,
    "qs:woe_local":9813,
    "qs:woe_ver":"7.10.0",
    "wof:lang":[
        "eng"
    ],
    "wof:name":"Maple Ridge Town Centre",
    "wof:placetype":"neighbourhood"
},
  "geometry": {"coordinates":[-122.59865499999999,49.218232],"type":"Point"}
}