{
  "type": "Feature",
  "properties": {
    "gn:admin1_code":"7.0",
    "gn:asciiname":"Clifton",
    "gn:country_code":"CA",
    "gn:dem":48,
    "gn:feature_class":"P",
    "gn:feature_code":"PPL",
    "gn:name":"Clifton",
    "gn:population":0,
    "gn:timezone":"America/Halifax",
    "iso:country":"CA",
    "wof:name":"Clifton",
    "wof:placetype":"locality"
},
  "geometry": {"coordinates":[-63.44846,45.33289],"type":"Point"}
}