{
  "type": "Feature",
  "properties": {
    "iso:country":"CA",
    "name:afr_x_preferred":[
        "Chicoutimi"
    ],
    "name:ara_x_preferred":[
        "\u0634\u064a\u0643\u0648\u062a\u064a\u0645\u064a"
    ],
    "name:ces_x_preferred":[
        "Chicoutimi"
    ],
    "name:deu_x_preferred":[
        "Chicoutimi"
    ],
    "name:eng_x_preferred":[
        "Chicoutimi"
    ],
    "name:fra_x_preferred":[
        "Chicoutimi"
    ],
    "name:heb_x_preferred":[
        "\u05e9\u05d9\u05e7\u05d5\u05d8\u05d9\u05de\u05d9"
    ],
    "name:ita_x_preferred":[
        "Chicoutimi"
    ],
    "name:jpn_x_preferred":[
        "\u30c1\u30af\u30fc\u30c1\u30df"
    ],
    "name:lit_x_preferred":[
        "\u0160ikutimis"
    ],
    "name:nld_x_preferred":[
        "Chicoutimi"
    ],
    "name:pol_x_preferred":[
        "Chicoutimi"
    ],
    "name:por_x_preferred":[
        "Chicoutimi"
    ],
    "name:rus_x_preferred":[
        "\u0428\u0438\u043a\u0443\u0442\u0438\u043c\u0438"
    ],
    "name:slv_x_preferred":[
        "Chicoutimi"
    ],
    "name:spa_x_preferred":[
        "Chicoutimi"
    ],
    "name:sqi_x_preferred":[
        "Chicoutimi"
    ],
    "name:swe_x_preferred":[
        "Chicoutimi"
    ],
    "name:zho_x_preferred":[
        "\u5e0c\u5eab\u8482\u7c73"
    ],
    "qs:gn_adm0_cc":"CA",
    "qs:gn_fcode":"PPL",
    "qs:gn_local":6137270,
    "qs:gn_nam_loc":"Saguenay, Qu\u00e9bec, CA",
    "qs:gn_namadm1":"10",
    "qs:gn_name":"Chicoutimi",
    "qs:local_max":1369,
    "qs:local_sum":2360,
    "qs:localhoods":4,
    "qs:name":"Chicoutimi",
    "qs:name_adm0":"Canada",
    "qs:name_adm1":"Qu\u00e9bec",
    "qs:name_adm2":"Saguenay",
    "qs:name_local":"Saguenay",
    "qs:photo_max":176,
    "qs:photo_sum":1369,
    "qs:placetype":"Suburb",
    "qs:quad_count":116,
    "qs:woe_adm0":23424775,
    "qs:woe_adm1":2344924,
    "qs:woe_adm2":29375050,
    "qs:woe_funk":"Grouping neighborhood",
    "qs:woe_lau":0,
    "qs:woe_local":29374154,
    "qs:woe_ver":"7.10.0",
    "wd:wordcount":1008,
    "wof:lang":[
        "fre"
    ],
    "wof:name":"Chicoutimi",
    "wof:placetype":"neighbourhood"
},
  "geometry": {"coordinates":[-71.069264,48.418884],"type":"Point"}
}