{
  "type": "Feature",
  "properties": {
    "gn:admin1_code":"8",
    "gn:asciiname":"Strabane",
    "gn:country_code":"CA",
    "gn:dem":267,
    "gn:feature_class":"P",
    "gn:feature_code":"PPL",
    "gn:name":"Strabane",
    "gn:population":0,
    "gn:timezone":"America/Toronto",
    "iso:country":"CA",
    "name:bul_x_preferred":[
        "\u0421\u0442\u0440\u0430\u0431\u0430\u043d"
    ],
    "name:cat_x_preferred":[
        "Strabane"
    ],
    "name:ceb_x_preferred":[
        "Strabane"
    ],
    "name:ces_x_preferred":[
        "Strabane"
    ],
    "name:deu_x_preferred":[
        "Strabane"
    ],
    "name:eus_x_preferred":[
        "Strabane"
    ],
    "name:fas_x_preferred":[
        "\u0627\u0633\u062a\u0631\u0627\u0628\u0646"
    ],
    "name:fra_x_preferred":[
        "Strabane"
    ],
    "name:ita_x_preferred":[
        "Strabane"
    ],
    "name:kor_x_preferred":[
        "\uc2a4\ud2b8\ub7ec\ubc34"
    ],
    "name:msa_x_preferred":[
        "Strabane"
    ],
    "name:nld_x_preferred":[
        "Strabane"
    ],
    "name:pol_x_preferred":[
        "Strabane"
    ],
    "name:rus_x_preferred":[
        "\u0421\u0442\u0440\u0430\u0431\u0430\u043d"
    ],
    "name:sco_x_preferred":[
        "Strabane"
    ],
    "name:slk_x_preferred":[
        "Strabane"
    ],
    "name:spa_x_preferred":[
        "Strabane"
    ],
    "name:swe_x_preferred":[
        "Strabane"
    ],
    "name:urd_x_preferred":[
        "\u0627\u0633\u0679\u0631\u0627\u0628\u06cc\u0646"
    ],
    "name:urd_x_variant":[
        "\u0633\u0679\u0631\u0628\u06cc\u0646"
    ],
    "name:vie_x_preferred":[
        "Strabane"
    ],
    "name:zho_x_preferred":[
        "\u65af\u7279\u62c9\u73ed"
    ],
    "wof:name":"Strabane",
    "wof:placetype":"locality"
},
  "geometry": {"coordinates":[-80.03222,43.37917],"type":"Point"}
}