{
  "type": "Feature",
  "properties": {
    "gn:country":"CA",
    "gn:fcode":"PPL",
    "gn:population":0,
    "iso:country":"CA",
    "name:eng_x_preferred":[
        "Warren Landing"
    ],
    "name:fin_x_preferred":[
        "Warren Landing"
    ],
    "name:nld_x_preferred":[
        "Warren Landing"
    ],
    "qs_pg:aaroncc":"CA",
    "qs_pg:gn_country":"CA",
    "qs_pg:gn_fcode":"PPL",
    "qs_pg:gn_pop":0,
    "qs_pg:name":"Warren Landing",
    "qs_pg:name_adm0":"Canada",
    "qs_pg:name_adm1":"Manitoba",
    "qs_pg:photos_9r":0,
    "qs_pg:photos_sr":0,
    "qs_pg:pop_sr":0,
    "qs_pg:qs_pg_placetype":"locality",
    "qs_pg:qs_pg_placetype_gp":"Town",
    "qs_pg:woe_adm0":23424775,
    "woe:adm0_id":23424775,
    "woe:name_adm0":"Canada",
    "woe:name_adm1":"Manitoba",
    "woe:placetype":"Town",
    "wof:name":"Warren Landing",
    "wof:placetype":"locality"
},
  "geometry": {"coordinates":[-97.87090999999999,53.69693],"type":"Point"}
}