{
  "type": "Feature",
  "properties": {
    "gn:admin1_code":"10.0",
    "gn:admin2_code":"8.0",
    "gn:admin3_code":"89008.0",
    "gn:asciiname":"Crique-La Corne",
    "gn:country_code":"CA",
    "gn:dem":300,
    "gn:feature_class":"P",
    "gn:feature_code":"PPL",
    "gn:name":"Crique-La Corne",
    "gn:population":0,
    "gn:timezone":"America/Toronto",
    "iso:country":"CA",
    "wof:name":"Crique-La Corne",
    "wof:placetype":"locality"
},
  "geometry": {"coordinates":[-77.96365,48.25704],"type":"Point"}
}