{
  "type": "Feature",
  "properties": {
    "gn:admin1_code":"10.0",
    "gn:admin2_code":"16",
    "gn:admin3_code":"55015.0",
    "gn:asciiname":"Saint Paul",
    "gn:country_code":"CA",
    "gn:dem":71,
    "gn:feature_class":"P",
    "gn:feature_code":"PPL",
    "gn:name":"Saint Paul",
    "gn:population":0,
    "gn:timezone":"America/Toronto",
    "iso:country":"CA",
    "name:ben_x_preferred":[
        "\u09b8\u09c7\u09a8\u09cd\u099f \u09aa\u09b2"
    ],
    "name:ell_x_preferred":[
        "\u03a3\u03ad\u03b9\u03bd\u03c4 \u03a0\u03bf\u03bb"
    ],
    "name:fas_x_preferred":[
        "\u0633\u0646\u062a \u067e\u0627\u0648\u0644"
    ],
    "name:heb_x_preferred":[
        "\u05e1\u05e0\u05d8 \u05e4\u05d5\u05dc"
    ],
    "name:hin_x_preferred":[
        "\u0938\u0947\u0902\u091f \u092a\u0949\u0932"
    ],
    "name:hun_x_preferred":[
        "Saint Paul"
    ],
    "name:ind_x_preferred":[
        "Saint Paul"
    ],
    "name:kor_x_preferred":[
        "\uc138\uc778\ud2b8 \ud3f4"
    ],
    "name:por_x_preferred":[
        "Saint Paul"
    ],
    "name:spa_x_preferred":[
        "Saint Paul"
    ],
    "name:swe_x_preferred":[
        "Saint Paul River"
    ],
    "name:tur_x_preferred":[
        "Saint Paul"
    ],
    "name:ukr_x_preferred":[
        "\u0421\u0435\u043d\u0442-\u041f\u043e\u043b"
    ],
    "name:urd_x_preferred":[
        "\u0633\u06cc\u0646\u0679 \u067e\u0627\u0644"
    ],
    "name:vie_x_preferred":[
        "S\u00f4ng Saint Paul"
    ],
    "wof:name":"Saint Paul",
    "wof:placetype":"locality"
},
  "geometry": {"coordinates":[-72.8827,45.43541],"type":"Point"}
}