{
  "type": "Feature",
  "properties": {
    "gn:admin1_code":"10.0",
    "gn:admin2_code":"16",
    "gn:admin3_code":"55015.0",
    "gn:asciiname":"Saint Paul",
    "gn:country_code":"CA",
    "gn:dem":71,
    "gn:feature_class":"P",
    "gn:feature_code":"PPL",
    "gn:name":"Saint Paul",
    "gn:population":0,
    "gn:timezone":"America/Toronto",
    "iso:country":"CA",
    "wof:name":"Saint Paul",
    "wof:placetype":"locality"
},
  "geometry": {"coordinates":[-72.8827,45.43541],"type":"Point"}
}