{
  "type": "Feature",
  "properties": {
    "gn:admin1_code":"11",
    "gn:asciiname":"Garden Head",
    "gn:country_code":"CA",
    "gn:dem":957,
    "gn:feature_class":"P",
    "gn:feature_code":"PPLL",
    "gn:name":"Garden Head",
    "gn:population":0,
    "gn:timezone":"America/Regina",
    "iso:country":"CA",
    "wof:name":"Garden Head",
    "wof:placetype":"locality"
},
  "geometry": {"coordinates":[-108.63472,49.80006],"type":"Point"}
}