{
  "type": "Feature",
  "properties": {
    "gn:admin1_code":"10",
    "gn:admin2_code":"4.0",
    "gn:admin3_code":"90012.0",
    "gn:asciiname":"Lac-aux-Brochets",
    "gn:country_code":"CA",
    "gn:dem":219,
    "gn:feature_class":"P",
    "gn:feature_code":"PPL",
    "gn:name":"Lac-aux-Brochets",
    "gn:population":0,
    "gn:timezone":"America/Toronto",
    "iso:country":"CA",
    "wof:name":"Lac-aux-Brochets",
    "wof:placetype":"locality"
},
  "geometry": {"coordinates":[-72.67556,47.21333],"type":"Point"}
}