{
  "type": "Feature",
  "properties": {
    "gn:admin1_code":"12",
    "gn:asciiname":"Moosehide",
    "gn:country_code":"CA",
    "gn:dem":372,
    "gn:feature_class":"P",
    "gn:feature_code":"PPLL",
    "gn:name":"Moosehide",
    "gn:population":0,
    "gn:timezone":"America/Whitehorse",
    "iso:country":"CA",
    "name:deu_x_preferred":[
        "Moosehide"
    ],
    "wof:name":"Moosehide",
    "wof:placetype":"locality"
},
  "geometry": {"coordinates":[-139.43916999999999,64.09526],"type":"Point"}
}