{
  "type": "Feature",
  "properties": {
    "iso:country":"CA",
    "name:ceb_x_preferred":[
        "Greenfield Park"
    ],
    "name:eng_x_preferred":[
        "Greenfield Park"
    ],
    "name:fra_x_preferred":[
        "Greenfield Park"
    ],
    "name:fra_x_variant":[
        "Old Greenfield Park"
    ],
    "name:pol_x_preferred":[
        "Greenfield Park"
    ],
    "name:por_x_preferred":[
        "Greenfield Park"
    ],
    "name:swe_x_preferred":[
        "Greenfield Park"
    ],
    "wd:wordcount":1487,
    "wof:lang":[
        "fre"
    ],
    "wof:name":"Old Greenfield Park",
    "wof:placetype":"neighbourhood",
    "wof:placetype_alt":[
        "borough"
    ]
},
  "geometry": {"coordinates":[-73.480819,45.488214],"type":"Point"}
}