{
  "type": "Feature",
  "properties": {
    "iso:country":"CA",
    "name:ceb_x_preferred":[
        "Greenfield Park"
    ],
    "name:deu_x_preferred":[
        "Greenfield Park"
    ],
    "name:eng_x_preferred":[
        "Greenfield Park"
    ],
    "name:fra_x_preferred":[
        "Greenfield Park"
    ],
    "name:fra_x_variant":[
        "Old Greenfield Park"
    ],
    "name:gle_x_preferred":[
        "Greenfield Park"
    ],
    "name:jpn_x_preferred":[
        "\u30b0\u30ea\u30fc\u30f3\u30d5\u30a3\u30fc\u30eb\u30c9\u30fb\u30d1\u30fc\u30af"
    ],
    "name:nld_x_preferred":[
        "Greenfield Park"
    ],
    "name:pol_x_preferred":[
        "Greenfield Park"
    ],
    "name:por_x_preferred":[
        "Greenfield Park"
    ],
    "name:rus_x_preferred":[
        "\u0413\u0440\u0438\u043d\u0444\u0438\u043b\u0434-\u041f\u0430\u0440\u043a"
    ],
    "name:spa_x_preferred":[
        "Greenfield Park"
    ],
    "name:swe_x_preferred":[
        "Greenfield Park"
    ],
    "name:zho_x_preferred":[
        "\u683c\u6797\u83f2\u723e\u5fb7\u516c\u5712"
    ],
    "wd:wordcount":1487,
    "wof:lang":[
        "fre"
    ],
    "wof:name":"Old Greenfield Park",
    "wof:placetype":"neighbourhood",
    "wof:placetype_alt":[
        "borough"
    ]
},
  "geometry": {"coordinates":[-73.480819,45.488214],"type":"Point"}
}