{
  "type": "Feature",
  "properties": {
    "gn:admin1_code":"8",
    "gn:asciiname":"Keldon",
    "gn:country_code":"CA",
    "gn:dem":485,
    "gn:feature_class":"P",
    "gn:feature_code":"PPL",
    "gn:name":"Keldon",
    "gn:population":0,
    "gn:timezone":"America/Toronto",
    "iso:country":"CA",
    "wof:name":"Keldon",
    "wof:placetype":"locality"
},
  "geometry": {"coordinates":[-80.38528000000002,44.03694],"type":"Point"}
}