{
  "type": "Feature",
  "properties": {
    "gn:admin1_code":"1",
    "gn:asciiname":"Lawton",
    "gn:country_code":"CA",
    "gn:dem":658,
    "gn:feature_class":"P",
    "gn:feature_code":"PPLL",
    "gn:name":"Lawton",
    "gn:population":0,
    "gn:timezone":"America/Edmonton",
    "iso:country":"CA",
    "name:ceb_x_preferred":[
        "Lawton"
    ],
    "name:deu_x_preferred":[
        "Lawton"
    ],
    "name:fra_x_preferred":[
        "Lawton"
    ],
    "name:ita_x_preferred":[
        "Lawton"
    ],
    "name:nld_x_preferred":[
        "Lawton"
    ],
    "name:pol_x_preferred":[
        "Lawton"
    ],
    "name:por_x_preferred":[
        "Lawton"
    ],
    "name:rus_x_preferred":[
        "\u041b\u043e\u0443\u0442\u043e\u043d"
    ],
    "name:spa_x_preferred":[
        "Lawton"
    ],
    "name:srp_x_preferred":[
        "\u041b\u043e\u0442\u043e\u043d"
    ],
    "name:swe_x_preferred":[
        "Lawton"
    ],
    "name:ukr_x_preferred":[
        "\u041b\u043e\u0442\u043e\u043d"
    ],
    "name:vol_x_preferred":[
        "Lawton"
    ],
    "wof:name":"Lawton",
    "wof:placetype":"locality"
},
  "geometry": {"coordinates":[-114.48542,54.05015],"type":"Point"}
}