{
  "type": "Feature",
  "properties": {
    "gn:gn_country":"CA",
    "gn:gn_fcode":"PPLX",
    "gn:gn_pop":25683,
    "gn:population":25683,
    "iso:country":"CA",
    "name:cat_x_preferred":[
        "Walnut Grove"
    ],
    "name:ceb_x_preferred":[
        "Walnut Grove"
    ],
    "name:deu_x_preferred":[
        "Walnut Grove"
    ],
    "name:fin_x_preferred":[
        "Walnut Grove"
    ],
    "name:fra_x_preferred":[
        "Walnut Grove"
    ],
    "name:ido_x_preferred":[
        "Walnut Grove"
    ],
    "name:ind_x_preferred":[
        "Walnut Grove"
    ],
    "name:ita_x_preferred":[
        "Walnut Grove"
    ],
    "name:nld_x_preferred":[
        "Walnut Grove"
    ],
    "name:pol_x_preferred":[
        "Walnut Grove"
    ],
    "name:por_x_preferred":[
        "Walnut Grove"
    ],
    "name:spa_x_preferred":[
        "Walnut Grove"
    ],
    "name:srp_x_preferred":[
        "\u0412\u043e\u043b\u043d\u0430\u0442 \u0413\u0440\u043e\u0443\u0432"
    ],
    "name:swe_x_preferred":[
        "Walnut Grove"
    ],
    "name:vol_x_preferred":[
        "Walnut Grove"
    ],
    "qs_pg:aaroncc":"CA",
    "qs_pg:gn_country":"CA",
    "qs_pg:gn_fcode":"PPLX",
    "qs_pg:gn_pop":25683,
    "qs_pg:name":"Walnut Grove",
    "qs_pg:photos_9r":0,
    "qs_pg:photos_sr":0,
    "qs_pg:pop_sr":7,
    "qs_pg:qs_pg_placetype":"neighbourhood",
    "wof:name":"Walnut Grove",
    "wof:placetype":"neighbourhood",
    "wof:population":25683
},
  "geometry": {"coordinates":[-122.64042000000001,49.16473],"type":"Point"}
}