{
  "type": "Feature",
  "properties": {
    "gn:admin1_code":"8",
    "gn:asciiname":"Elmstead",
    "gn:country_code":"CA",
    "gn:dem":180,
    "gn:feature_class":"P",
    "gn:feature_code":"PPL",
    "gn:name":"Elmstead",
    "gn:population":0,
    "gn:timezone":"America/Toronto",
    "iso:country":"CA",
    "name:nld_x_preferred":[
        "Elmstead"
    ],
    "wof:name":"Elmstead",
    "wof:placetype":"locality"
},
  "geometry": {"coordinates":[-82.846,42.28894],"type":"Point"}
}