{
  "type": "Feature",
  "properties": {
    "iso:country":"CA",
    "name:eng_x_preferred":[
        "Bayview North"
    ],
    "qs:gn_adm0_cc":"CA",
    "qs:gn_local":6122091,
    "qs:gn_nam_loc":"richmond hill",
    "qs:gn_namadm1":"08",
    "qs:local_max":345,
    "qs:local_sum":986,
    "qs:localhoods":5,
    "qs:name":"Bayview North",
    "qs:name_adm0":"Canada",
    "qs:name_adm1":"Ontario",
    "qs:name_adm2":"York",
    "qs:name_local":"Richmond Hill",
    "qs:photo_max":63,
    "qs:photo_sum":345,
    "qs:placetype":"Suburb",
    "qs:quad_count":30,
    "qs:woe_adm0":23424775,
    "qs:woe_adm1":2344922,
    "qs:woe_adm2":29375112,
    "qs:woe_funk":"Parented by a neighborhood",
    "qs:woe_lau":0,
    "qs:woe_local":1333,
    "qs:woe_ver":"7.10.0",
    "wof:lang":[
        "eng"
    ],
    "wof:name":"Bayview North",
    "wof:placetype":"neighbourhood"
},
  "geometry": {"coordinates":[-79.405609,43.89501],"type":"Point"}
}