{
  "type": "Feature",
  "properties": {
    "gn:admin1_code":"8",
    "gn:asciiname":"Morven",
    "gn:country_code":"CA",
    "gn:dem":97,
    "gn:feature_class":"P",
    "gn:feature_code":"PPL",
    "gn:name":"Morven",
    "gn:population":0,
    "gn:timezone":"America/Toronto",
    "iso:country":"CA",
    "wof:name":"Morven",
    "wof:placetype":"locality"
},
  "geometry": {"coordinates":[-76.84343,44.23959],"type":"Point"}
}