{
  "type": "Feature",
  "properties": {
    "gn:admin1_code":"8",
    "gn:asciiname":"Morven",
    "gn:country_code":"CA",
    "gn:dem":97,
    "gn:feature_class":"P",
    "gn:feature_code":"PPL",
    "gn:name":"Morven",
    "gn:population":0,
    "gn:timezone":"America/Toronto",
    "iso:country":"CA",
    "name:ceb_x_preferred":[
        "Morven"
    ],
    "name:deu_x_preferred":[
        "Morven"
    ],
    "name:epo_x_preferred":[
        "Morven"
    ],
    "name:fra_x_preferred":[
        "Morven"
    ],
    "name:ita_x_preferred":[
        "Morven"
    ],
    "name:nld_x_preferred":[
        "Morven"
    ],
    "name:pol_x_preferred":[
        "Morven"
    ],
    "name:por_x_preferred":[
        "Morven"
    ],
    "name:srp_x_preferred":[
        "\u041c\u043e\u0440\u0432\u0435\u043d"
    ],
    "name:swe_x_preferred":[
        "Morven"
    ],
    "name:ukr_x_preferred":[
        "\u041c\u043e\u0440\u0432\u0435\u043d"
    ],
    "name:vol_x_preferred":[
        "Morven"
    ],
    "wof:name":"Morven",
    "wof:placetype":"locality"
},
  "geometry": {"coordinates":[-76.84343,44.23959],"type":"Point"}
}