{
  "type": "Feature",
  "properties": {
    "gn:admin1_code":"8.0",
    "gn:asciiname":"Chisholm's Mills",
    "gn:country_code":"CA",
    "gn:dem":129,
    "gn:feature_class":"P",
    "gn:feature_code":"PPLL",
    "gn:name":"Chisholm's Mills",
    "gn:population":0,
    "gn:timezone":"America/Toronto",
    "iso:country":"CA",
    "wof:name":"Chisholm's Mills",
    "wof:placetype":"locality"
},
  "geometry": {"coordinates":[-77.30946,44.35372],"type":"Point"}
}