{
  "type": "Feature",
  "properties": {
    "gn:admin1_code":"8",
    "gn:asciiname":"Tyranite",
    "gn:country_code":"CA",
    "gn:dem":365,
    "gn:feature_class":"P",
    "gn:feature_code":"PPLL",
    "gn:name":"Tyranite",
    "gn:population":0,
    "gn:timezone":"America/Toronto",
    "iso:country":"CA",
    "wof:name":"Tyranite",
    "wof:placetype":"locality"
},
  "geometry": {"coordinates":[-81.02198,47.65015],"type":"Point"}
}