{
  "type": "Feature",
  "properties": {
    "gn:admin1_code":"8",
    "gn:asciiname":"Kentvale",
    "gn:country_code":"CA",
    "gn:dem":199,
    "gn:feature_class":"P",
    "gn:feature_code":"PPL",
    "gn:name":"Kentvale",
    "gn:population":0,
    "gn:timezone":"America/Toronto",
    "iso:country":"CA",
    "wof:name":"Kentvale",
    "wof:placetype":"locality"
},
  "geometry": {"coordinates":[-84.03471999999999,46.20833],"type":"Point"}
}