{
  "type": "Feature",
  "properties": {
    "gn:admin1_code":"8",
    "gn:asciiname":"Leonards Beach",
    "gn:country_code":"CA",
    "gn:dem":222,
    "gn:feature_class":"P",
    "gn:feature_code":"PPL",
    "gn:name":"Leonards Beach",
    "gn:population":0,
    "gn:timezone":"America/Toronto",
    "iso:country":"CA",
    "wof:name":"Leonards Beach",
    "wof:placetype":"locality"
},
  "geometry": {"coordinates":[-79.53471999999999,44.33972],"type":"Point"}
}