{
  "type": "Feature",
  "properties": {
    "iso:country":"CA",
    "name:eng_x_preferred":[
        "Onward Willow"
    ],
    "name:unk_x_variant":[
        "Onward Willow"
    ],
    "qs:gn_adm0_cc":"CA",
    "qs:gn_local":5967629,
    "qs:gn_nam_loc":"guelph",
    "qs:gn_namadm1":"08",
    "qs:local_max":4293,
    "qs:local_sum":8450,
    "qs:localhoods":11,
    "qs:name":"Onward Willow",
    "qs:name_adm0":"Canada",
    "qs:name_adm1":"Ontario",
    "qs:name_adm2":"Wellington",
    "qs:name_local":"Guelph",
    "qs:photo_max":57,
    "qs:photo_sum":227,
    "qs:placetype":"Suburb",
    "qs:quad_count":24,
    "qs:woe_adm0":23424775,
    "qs:woe_adm1":2344922,
    "qs:woe_adm2":29375207,
    "qs:woe_funk":"Parented by a neighborhood",
    "qs:woe_lau":0,
    "qs:woe_local":4048,
    "qs:woe_ver":"7.10.0",
    "wof:lang":[
        "eng"
    ],
    "wof:name":"Onward Willow",
    "wof:placetype":"neighbourhood"
},
  "geometry": {"coordinates":[-80.264635,43.537531],"type":"Point"}
}