{
  "type": "Feature",
  "properties": {
    "gn:admin1_code":"8",
    "gn:asciiname":"Val Albert",
    "gn:country_code":"CA",
    "gn:dem":222,
    "gn:feature_class":"P",
    "gn:feature_code":"PPL",
    "gn:name":"Val Albert",
    "gn:population":0,
    "gn:timezone":"America/Toronto",
    "iso:country":"CA",
    "wof:name":"Val Albert",
    "wof:placetype":"locality"
},
  "geometry": {"coordinates":[-82.4029,49.40925],"type":"Point"}
}