{
  "type": "Feature",
  "properties": {
    "gn:admin1_code":"8",
    "gn:asciiname":"Two O'Clock",
    "gn:country_code":"CA",
    "gn:dem":195,
    "gn:feature_class":"P",
    "gn:feature_code":"PPL",
    "gn:name":"Two O'Clock",
    "gn:population":0,
    "gn:timezone":"America/Toronto",
    "iso:country":"CA",
    "wof:name":"Two O'Clock",
    "wof:placetype":"locality"
},
  "geometry": {"coordinates":[-81.77460000000001,45.73955],"type":"Point"}
}