{
  "type": "Feature",
  "properties": {
    "gn:admin1_code":"8",
    "gn:asciiname":"University Heights",
    "gn:country_code":"CA",
    "gn:dem":250,
    "gn:feature_class":"P",
    "gn:feature_code":"PPL",
    "gn:name":"University Heights",
    "gn:population":0,
    "gn:timezone":"America/Toronto",
    "iso:country":"CA",
    "wof:name":"University Heights",
    "wof:placetype":"locality"
},
  "geometry": {"coordinates":[-81.28028,42.99722],"type":"Point"}
}