{
  "type": "Feature",
  "properties": {
    "gn:admin1_code":"8",
    "gn:asciiname":"University Heights",
    "gn:country_code":"CA",
    "gn:dem":250,
    "gn:feature_class":"P",
    "gn:feature_code":"PPL",
    "gn:name":"University Heights",
    "gn:population":0,
    "gn:timezone":"America/Toronto",
    "iso:country":"CA",
    "name:ceb_x_preferred":[
        "University Heights"
    ],
    "name:deu_x_preferred":[
        "University Heights"
    ],
    "name:fra_x_preferred":[
        "University Heights"
    ],
    "name:ita_x_preferred":[
        "University Heights"
    ],
    "name:nld_x_preferred":[
        "University Heights"
    ],
    "name:pol_x_preferred":[
        "University Heights"
    ],
    "name:srp_x_preferred":[
        "\u0408\u0443\u043d\u0438\u0432\u0435\u0440\u0441\u0438\u0442\u0438 \u0425\u0430\u0458\u0442\u0441"
    ],
    "name:vol_x_preferred":[
        "University Heights"
    ],
    "wof:name":"University Heights",
    "wof:placetype":"locality"
},
  "geometry": {"coordinates":[-81.28028,42.99722],"type":"Point"}
}