{
  "type": "Feature",
  "properties": {
    "gn:admin1_code":"10.0",
    "gn:admin2_code":"04",
    "gn:admin3_code":"35035.0",
    "gn:asciiname":"Herouxville",
    "gn:country_code":"CA",
    "gn:dem":143,
    "gn:feature_class":"P",
    "gn:feature_code":"PPL",
    "gn:name":"H\u00e9rouxville",
    "gn:population":1340,
    "gn:timezone":"America/Toronto",
    "iso:country":"CA",
    "name:fra_x_preferred":[
        "H\u00e9rouxville"
    ],
    "wof:name":"Herouxville",
    "wof:placetype":"locality",
    "wof:population":1340
},
  "geometry": {"coordinates":[-72.62512,46.66617],"type":"Point"}
}