{
  "type": "Feature",
  "properties": {
    "gn:admin1_code":"3",
    "gn:asciiname":"Kosapechekanesik",
    "gn:country_code":"CA",
    "gn:dem":354,
    "gn:feature_class":"P",
    "gn:feature_code":"PPLL",
    "gn:name":"Kosapechekanesik",
    "gn:population":0,
    "gn:timezone":"America/Winnipeg",
    "iso:country":"CA",
    "wof:name":"Kosapechekanesik",
    "wof:placetype":"locality"
},
  "geometry": {"coordinates":[-101.73506999999999,56.40082],"type":"Point"}
}