{
  "type": "Feature",
  "properties": {
    "gn:admin1_code":"1.0",
    "gn:asciiname":"Caruso",
    "gn:country_code":"CA",
    "gn:dem":976,
    "gn:feature_class":"P",
    "gn:feature_code":"PPLL",
    "gn:name":"Caruso",
    "gn:population":0,
    "gn:timezone":"America/Edmonton",
    "iso:country":"CA",
    "wof:name":"Caruso",
    "wof:placetype":"locality"
},
  "geometry": {"coordinates":[-113.46863999999999,51.05011],"type":"Point"}
}