{
  "type": "Feature",
  "properties": {
    "gn:admin1_code":"8",
    "gn:asciiname":"Sunshine",
    "gn:country_code":"CA",
    "gn:dem":341,
    "gn:feature_class":"P",
    "gn:feature_code":"PPL",
    "gn:name":"Sunshine",
    "gn:population":0,
    "gn:timezone":"America/Toronto",
    "iso:country":"CA",
    "wof:name":"Sunshine",
    "wof:placetype":"locality"
},
  "geometry": {"coordinates":[-89.68583000000002,48.54417],"type":"Point"}
}