{
  "type": "Feature",
  "properties": {
    "gn:admin1_code":"10",
    "gn:admin2_code":"15.0",
    "gn:admin3_code":"75045.0",
    "gn:asciiname":"Lac-en-Coeur",
    "gn:country_code":"CA",
    "gn:dem":352,
    "gn:feature_class":"P",
    "gn:feature_code":"PPL",
    "gn:name":"Lac-en-Coeur",
    "gn:population":0,
    "gn:timezone":"America/Toronto",
    "iso:country":"CA",
    "wof:name":"Lac-en-Coeur",
    "wof:placetype":"locality"
},
  "geometry": {"coordinates":[-74.01765999999998,45.96948],"type":"Point"}
}