{
  "type": "Feature",
  "properties": {
    "gn:country":"CA",
    "gn:fcode":"PPL",
    "gn:pop":0,
    "iso:country":"CA",
    "name:eng_x_preferred":[
        "New Dayton"
    ],
    "name:fra_x_preferred":[
        "New Dayton"
    ],
    "qs:name":"New Dayton",
    "qs:name_adm0":"Canada",
    "qs:name_adm1":"Alberta",
    "qs:photos":15,
    "qs:photos_1k":3,
    "qs:photos_9k":1,
    "qs:photos_9r":1,
    "qs:photos_all":15,
    "qs:photos_sr":1,
    "qs:placetype":"Town",
    "qs:pop_sr":"4",
    "wd:wordcount":564,
    "wof:name":"New Dayton",
    "wof:placetype":"locality",
    "wof:population":0
},
  "geometry": {"coordinates":[-112.37915,49.42326],"type":"Point"}
}