{
  "type": "Feature",
  "properties": {
    "iso:country":"CA",
    "name:dut_x_preferred":[
        "Capucins"
    ],
    "name:eng_x_preferred":[
        "Capucins"
    ],
    "name:fre_x_preferred":[
        "Capucins"
    ],
    "name:por_x_preferred":[
        "Capucins"
    ],
    "name:spa_x_preferred":[
        "Capucins"
    ],
    "qs_pg:aaroncc":"CA",
    "qs_pg:name":"Capucins",
    "qs_pg:name_adm0":"Canada",
    "qs_pg:name_adm1":"Qu\u00e9bec",
    "qs_pg:photos":9,
    "qs_pg:photos_1k":2,
    "qs_pg:photos_9k":1,
    "qs_pg:photos_9r":1,
    "qs_pg:photos_all":9,
    "qs_pg:photos_sr":1,
    "qs_pg:pop_sr":0,
    "qs_pg:qs_pg_placetype":"locality",
    "qs_pg:qs_pg_placetype_gp":"Town",
    "qs_pg:woe_adm0":23424775,
    "woe:adm0_id":23424775,
    "woe:name_adm0":"Canada",
    "woe:name_adm1":"Qu\u00e9bec",
    "woe:placetype":"Town",
    "wof:name":"Capucins",
    "wof:placetype":"locality"
},
  "geometry": {"coordinates":[-66.834068,49.050388],"type":"Point"}
}