{
  "type": "Feature",
  "properties": {
    "gn:gn_country":"CA",
    "gn:gn_fcode":"PPL",
    "gn:gn_pop":0,
    "iso:country":"CA",
    "name:ceb_x_preferred":[
        "Saint-Michel"
    ],
    "name:deu_x_preferred":[
        "Saint-Michel"
    ],
    "name:ell_x_preferred":[
        "\u03a3\u03b1\u03b9\u03bd-\u039c\u03b9\u03c3\u03ad\u03bb"
    ],
    "name:eng_x_preferred":[
        "Saint-Michel"
    ],
    "name:eus_x_preferred":[
        "Saint-Michel"
    ],
    "name:fas_x_preferred":[
        "\u0633\u0646-\u0645\u06cc\u0634\u0644\u060c \u06a9\u0628\u06a9"
    ],
    "name:fas_x_variant":[
        "\u0633\u0646-\u0645\u06cc\u0634\u0644"
    ],
    "name:fra_x_preferred":[
        "Saint-Michel"
    ],
    "name:ita_x_preferred":[
        "Saint-Michel"
    ],
    "name:nld_x_preferred":[
        "Saint-Michel"
    ],
    "name:por_x_preferred":[
        "Saint-Michel"
    ],
    "name:spa_x_preferred":[
        "Saint-Michel"
    ],
    "name:swe_x_preferred":[
        "Saint-Michel"
    ],
    "name:urd_x_preferred":[
        "\u0633\u06cc\u0646\u0679-\u0645\u0686\u0644\u060c \u06a9\u06cc\u0648\u0628\u06a9"
    ],
    "name:urd_x_variant":[
        "\u0633\u06cc\u0646\u0679-\u0645\u0686\u0644"
    ],
    "qs_pg:aaroncc":"CA",
    "qs_pg:gn_country":"CA",
    "qs_pg:gn_fcode":"PPL",
    "qs_pg:gn_pop":0,
    "qs_pg:name":"St.-Michel",
    "qs_pg:name_adm0":"Canada",
    "qs_pg:name_adm1":"Qu\u00e9bec",
    "qs_pg:photos":87,
    "qs_pg:photos_1k":18,
    "qs_pg:photos_9k":1,
    "qs_pg:photos_9r":3,
    "qs_pg:photos_all":87,
    "qs_pg:photos_sr":3,
    "qs_pg:pop_sr":0,
    "qs_pg:qs_pg_placetype":"locality",
    "qs_pg:qs_pg_placetype_gp":"Town",
    "qs_pg:woe_adm0":23424775,
    "woe:adm0_id":23424775,
    "woe:name_adm0":"Canada",
    "woe:name_adm1":"Qu\u00e9bec",
    "woe:placetype":"Town",
    "wof:name":"St.-Michel",
    "wof:placetype":"locality"
},
  "geometry": {"coordinates":[-73.56588000000001,45.23338],"type":"Point"}
}