{
  "type": "Feature",
  "properties": {
    "gn:admin1_code":"10",
    "gn:admin2_code":"17.0",
    "gn:admin3_code":"49058.0",
    "gn:asciiname":"Place-Bellerive",
    "gn:country_code":"CA",
    "gn:dem":79,
    "gn:feature_class":"P",
    "gn:feature_code":"PPL",
    "gn:name":"Place-Bellerive",
    "gn:population":0,
    "gn:timezone":"America/Toronto",
    "iso:country":"CA",
    "wof:name":"Place-Bellerive",
    "wof:placetype":"locality"
},
  "geometry": {"coordinates":[-72.51510999999998,45.9467],"type":"Point"}
}