{
  "type": "Feature",
  "properties": {
    "gn:admin1_code":"2",
    "gn:asciiname":"Loon Lake",
    "gn:country_code":"CA",
    "gn:dem":886,
    "gn:feature_class":"P",
    "gn:feature_code":"PPLL",
    "gn:name":"Loon Lake",
    "gn:population":0,
    "gn:timezone":"America/Vancouver",
    "iso:country":"CA",
    "name:ceb_x_preferred":[
        "Loon Lake"
    ],
    "name:deu_x_preferred":[
        "Loon Lake"
    ],
    "name:swe_x_preferred":[
        "Loon Lake"
    ],
    "wof:name":"Loon Lake",
    "wof:placetype":"locality"
},
  "geometry": {"coordinates":[-121.30262,51.08309000000001],"type":"Point"}
}