{
  "type": "Feature",
  "properties": {
    "gn:admin1_code":"1",
    "gn:asciiname":"Huggett",
    "gn:country_code":"CA",
    "gn:dem":728,
    "gn:feature_class":"P",
    "gn:feature_code":"PPLL",
    "gn:name":"Huggett",
    "gn:population":0,
    "gn:timezone":"America/Edmonton",
    "iso:country":"CA",
    "wof:name":"Huggett",
    "wof:placetype":"locality"
},
  "geometry": {"coordinates":[-114.13536000000001,53.31683],"type":"Point"}
}