{
  "type": "Feature",
  "properties": {
    "gn:admin1_code":"5",
    "gn:asciiname":"Morrisville",
    "gn:country_code":"CA",
    "gn:dem":8,
    "gn:feature_class":"P",
    "gn:feature_code":"PPL",
    "gn:name":"Morrisville",
    "gn:population":0,
    "gn:timezone":"America/St_Johns",
    "iso:country":"CA",
    "name:ceb_x_preferred":[
        "Morrisville"
    ],
    "wof:name":"Morrisville",
    "wof:placetype":"locality"
},
  "geometry": {"coordinates":[-55.76501999999999,47.86665],"type":"Point"}
}