{
  "type": "Feature",
  "properties": {
    "gn:admin1_code":"8.0",
    "gn:asciiname":"Donegal",
    "gn:country_code":"CA",
    "gn:dem":213,
    "gn:feature_class":"P",
    "gn:feature_code":"PPL",
    "gn:name":"Donegal",
    "gn:population":0,
    "gn:timezone":"America/Toronto",
    "iso:country":"CA",
    "name:bre_x_preferred":[
        "Donegal"
    ],
    "name:bul_x_preferred":[
        "\u0414\u043e\u043d\u0438\u0433\u0430\u043b"
    ],
    "name:ceb_x_preferred":[
        "Donegal"
    ],
    "name:deu_x_preferred":[
        "Donegal"
    ],
    "name:ita_x_preferred":[
        "Donegal"
    ],
    "name:nld_x_preferred":[
        "Donegal"
    ],
    "name:nor_x_preferred":[
        "Donegal"
    ],
    "name:pol_x_preferred":[
        "Donegal"
    ],
    "name:rus_x_preferred":[
        "\u0414\u043e\u043d\u0435\u0433\u043e\u043b"
    ],
    "name:slk_x_preferred":[
        "Donegal"
    ],
    "name:slv_x_preferred":[
        "Donegal"
    ],
    "name:swe_x_preferred":[
        "Donegal"
    ],
    "name:ukr_x_preferred":[
        "\u0414\u043e\u043d\u0435\u0433\u0430\u043b"
    ],
    "wof:name":"Donegal",
    "wof:placetype":"locality"
},
  "geometry": {"coordinates":[-77.13689000000002,45.50236],"type":"Point"}
}