{
  "type": "Feature",
  "properties": {
    "gn:admin1_code":"8.0",
    "gn:asciiname":"Dillon",
    "gn:country_code":"CA",
    "gn:dem":181,
    "gn:feature_class":"P",
    "gn:feature_code":"PPL",
    "gn:name":"Dillon",
    "gn:population":0,
    "gn:timezone":"America/Toronto",
    "iso:country":"CA",
    "wof:name":"Dillon",
    "wof:placetype":"locality"
},
  "geometry": {"coordinates":[-80.32194,45.425],"type":"Point"}
}