{
  "type": "Feature",
  "properties": {
    "gn:admin1_code":"8.0",
    "gn:asciiname":"Dillon",
    "gn:country_code":"CA",
    "gn:dem":181,
    "gn:feature_class":"P",
    "gn:feature_code":"PPL",
    "gn:name":"Dillon",
    "gn:population":0,
    "gn:timezone":"America/Toronto",
    "iso:country":"CA",
    "name:cat_x_preferred":[
        "Dillon"
    ],
    "name:ceb_x_preferred":[
        "Dillon"
    ],
    "name:ces_x_preferred":[
        "Dillon"
    ],
    "name:deu_x_preferred":[
        "Dillon"
    ],
    "name:fas_x_preferred":[
        "\u062f\u06cc\u0644\u0648\u0646"
    ],
    "name:fin_x_preferred":[
        "Dillon"
    ],
    "name:fra_x_preferred":[
        "Dillon"
    ],
    "name:heb_x_preferred":[
        "\u05d3\u05d9\u05dc\u05d5\u05df"
    ],
    "name:hun_x_preferred":[
        "Dillon"
    ],
    "name:ita_x_preferred":[
        "Dillon"
    ],
    "name:jpn_x_preferred":[
        "\u30c7\u30a3\u30ed\u30f3"
    ],
    "name:nds_x_preferred":[
        "Dillon"
    ],
    "name:nld_x_preferred":[
        "Dillon"
    ],
    "name:pol_x_preferred":[
        "Dillon"
    ],
    "name:rus_x_preferred":[
        "\u0414\u0438\u043b\u043b\u043e\u043d"
    ],
    "name:srp_x_preferred":[
        "\u0414\u0438\u043b\u043e\u043d"
    ],
    "name:swe_x_preferred":[
        "Dillon"
    ],
    "name:ukr_x_preferred":[
        "\u0414\u0456\u043b\u043b\u043e\u043d"
    ],
    "name:vol_x_preferred":[
        "Dillon"
    ],
    "wof:name":"Dillon",
    "wof:placetype":"locality"
},
  "geometry": {"coordinates":[-80.32194,45.425],"type":"Point"}
}