{
  "type": "Feature",
  "properties": {
    "gn:admin1_code":"1",
    "gn:asciiname":"Galloway",
    "gn:country_code":"CA",
    "gn:dem":984,
    "gn:feature_class":"P",
    "gn:feature_code":"PPLL",
    "gn:name":"Galloway",
    "gn:population":0,
    "gn:timezone":"America/Edmonton",
    "iso:country":"CA",
    "wof:name":"Galloway",
    "wof:placetype":"locality"
},
  "geometry": {"coordinates":[-116.8856,53.53341],"type":"Point"}
}