{
  "type": "Feature",
  "properties": {
    "gn:admin1_code":"1",
    "gn:asciiname":"Galloway",
    "gn:country_code":"CA",
    "gn:dem":984,
    "gn:feature_class":"P",
    "gn:feature_code":"PPLL",
    "gn:name":"Galloway",
    "gn:population":0,
    "gn:timezone":"America/Edmonton",
    "iso:country":"CA",
    "name:bre_x_preferred":[
        "Gall-Ghaidhealaibh"
    ],
    "name:cat_x_preferred":[
        "Galloway"
    ],
    "name:cym_x_preferred":[
        "Galloway"
    ],
    "name:dan_x_preferred":[
        "Galloway"
    ],
    "name:fas_x_preferred":[
        "\u06af\u0627\u0644\u0648\u0648\u06cc"
    ],
    "name:fra_x_preferred":[
        "Galloway"
    ],
    "name:gla_x_preferred":[
        "Gall-Gh\u00e0idhealaibh"
    ],
    "name:gle_x_preferred":[
        "Gall-Ghaidhealaibh"
    ],
    "name:ita_x_preferred":[
        "Galloway"
    ],
    "name:nor_x_preferred":[
        "Galloway"
    ],
    "name:pol_x_preferred":[
        "Galloway"
    ],
    "name:rus_x_preferred":[
        "\u0413\u0430\u043b\u043b\u043e\u0443\u044d\u0439"
    ],
    "name:sco_x_preferred":[
        "Gallowa"
    ],
    "name:spa_x_preferred":[
        "Galloway"
    ],
    "name:swe_x_preferred":[
        "Galloway"
    ],
    "wof:name":"Galloway",
    "wof:placetype":"locality"
},
  "geometry": {"coordinates":[-116.8856,53.53341],"type":"Point"}
}