{
  "type": "Feature",
  "properties": {
    "gn:admin1_code":"10",
    "gn:admin2_code":"11.0",
    "gn:admin3_code":"3010.0",
    "gn:asciiname":"Petite-Anse",
    "gn:country_code":"CA",
    "gn:dem":49,
    "gn:feature_class":"P",
    "gn:feature_code":"PPL",
    "gn:name":"Petite-Anse",
    "gn:population":0,
    "gn:timezone":"America/Toronto",
    "iso:country":"CA",
    "wof:name":"Petite-Anse",
    "wof:placetype":"locality"
},
  "geometry": {"coordinates":[-64.86539,49.1834],"type":"Point"}
}