{
  "type": "Feature",
  "properties": {
    "gn:admin1_code":"8",
    "gn:asciiname":"Ruskview",
    "gn:country_code":"CA",
    "gn:dem":443,
    "gn:feature_class":"P",
    "gn:feature_code":"PPL",
    "gn:name":"Ruskview",
    "gn:population":0,
    "gn:timezone":"America/Toronto",
    "iso:country":"CA",
    "wof:name":"Ruskview",
    "wof:placetype":"locality"
},
  "geometry": {"coordinates":[-80.12166999999999,44.23556],"type":"Point"}
}