{
  "type": "Feature",
  "properties": {
    "gn:admin1_code":"3",
    "gn:asciiname":"Powerview",
    "gn:country_code":"CA",
    "gn:dem":228,
    "gn:feature_class":"P",
    "gn:feature_code":"PPL",
    "gn:name":"Powerview",
    "gn:population":0,
    "gn:timezone":"America/Winnipeg",
    "iso:country":"CA",
    "wof:name":"Powerview",
    "wof:placetype":"locality"
},
  "geometry": {"coordinates":[-96.19868,50.56611],"type":"Point"}
}