{
  "type": "Feature",
  "properties": {
    "gn:admin1_code":"2",
    "gn:asciiname":"Parkland",
    "gn:country_code":"CA",
    "gn:dem":705,
    "gn:feature_class":"P",
    "gn:feature_code":"PPLL",
    "gn:name":"Parkland",
    "gn:population":0,
    "gn:timezone":"America/Dawson_Creek",
    "iso:country":"CA",
    "name:ceb_x_preferred":[
        "Parkland"
    ],
    "name:deu_x_preferred":[
        "Parkland"
    ],
    "name:fra_x_preferred":[
        "Parkland"
    ],
    "name:ita_x_preferred":[
        "Parkland"
    ],
    "name:kor_x_preferred":[
        "\ud30c\ud074\ub79c\ub4dc"
    ],
    "name:nld_x_preferred":[
        "Parkland"
    ],
    "name:pol_x_preferred":[
        "Parkland"
    ],
    "name:por_x_preferred":[
        "Parkland"
    ],
    "name:spa_x_preferred":[
        "Parkland"
    ],
    "name:srp_x_preferred":[
        "\u041f\u0430\u0440\u043a\u043b\u0430\u043d\u0434"
    ],
    "name:urd_x_preferred":[
        "\u067e\u0627\u0631\u06a9\u0644\u06cc\u0646\u0688"
    ],
    "name:vol_x_preferred":[
        "Parkland"
    ],
    "wof:name":"Parkland",
    "wof:placetype":"locality"
},
  "geometry": {"coordinates":[-120.56959000000001,55.9166],"type":"Point"}
}