{
  "type": "Feature",
  "properties": {
    "gn:gn_country":"CA",
    "iso:country":"CA",
    "qs_pg:aaroncc":"CA",
    "qs_pg:gn_country":"CA",
    "qs_pg:name":"Entry Island",
    "qs_pg:name_adm0":"Canada",
    "qs_pg:name_adm1":"Qu\u00e9bec",
    "qs_pg:photos":238,
    "qs_pg:photos_1k":48,
    "qs_pg:photos_9k":1,
    "qs_pg:photos_9r":4,
    "qs_pg:photos_all":238,
    "qs_pg:photos_sr":4,
    "qs_pg:pop_sr":0,
    "qs_pg:qs_pg_placetype":"locality",
    "qs_pg:qs_pg_placetype_gp":"Town",
    "qs_pg:woe_adm0":23424775,
    "woe:adm0_id":23424775,
    "woe:name_adm0":"Canada",
    "woe:name_adm1":"Qu\u00e9bec",
    "woe:placetype":"Town",
    "wof:name":"Entry Island",
    "wof:placetype":"locality"
},
  "geometry": {"coordinates":[-61.699562,47.276521],"type":"Point"}
}