{
  "type": "Feature",
  "properties": {
    "gn:admin1_code":"11",
    "gn:asciiname":"Riceton",
    "gn:country_code":"CA",
    "gn:dem":575,
    "gn:feature_class":"P",
    "gn:feature_code":"PPLL",
    "gn:name":"Riceton",
    "gn:population":0,
    "gn:timezone":"America/Regina",
    "iso:country":"CA",
    "wof:name":"Riceton",
    "wof:placetype":"locality"
},
  "geometry": {"coordinates":[-104.31780000000001,50.11677],"type":"Point"}
}