{
  "type": "Feature",
  "properties": {
    "gn:admin1_code":"14.0",
    "gn:asciiname":"Craig Harbour",
    "gn:country_code":"CA",
    "gn:dem":270,
    "gn:feature_class":"P",
    "gn:feature_code":"PPLL",
    "gn:name":"Craig Harbour",
    "gn:population":0,
    "gn:timezone":"America/Iqaluit",
    "iso:country":"CA",
    "wof:name":"Craig Harbour",
    "wof:placetype":"locality"
},
  "geometry": {"coordinates":[-80.99835,76.20862],"type":"Point"}
}