{
  "type": "Feature",
  "properties": {
    "gn:admin1_code":"11.0",
    "gn:asciiname":"East Poplar",
    "gn:country_code":"CA",
    "gn:dem":778,
    "gn:feature_class":"P",
    "gn:feature_code":"PPLL",
    "gn:name":"East Poplar",
    "gn:population":0,
    "gn:timezone":"America/Regina",
    "iso:country":"CA",
    "wof:name":"East Poplar",
    "wof:placetype":"locality"
},
  "geometry": {"coordinates":[-105.38439,49.06675],"type":"Point"}
}