{
  "type": "Feature",
  "properties": {
    "gn:admin1_code":"7",
    "gn:asciiname":"Malagash Mine",
    "gn:country_code":"CA",
    "gn:dem":19,
    "gn:feature_class":"P",
    "gn:feature_code":"PPL",
    "gn:name":"Malagash Mine",
    "gn:population":0,
    "gn:timezone":"America/Halifax",
    "iso:country":"CA",
    "wof:name":"Malagash Mine",
    "wof:placetype":"locality"
},
  "geometry": {"coordinates":[-63.32465,45.79246],"type":"Point"}
}