{
  "type": "Feature",
  "properties": {
    "iso:country":"CA",
    "name:eng_x_preferred":[
        "College Park East"
    ],
    "wd:wordcount":656,
    "wof:lang":[
        "eng"
    ],
    "wof:name":"College Park East",
    "wof:placetype":"neighbourhood"
},
  "geometry": {"coordinates":[-106.581902,52.121974],"type":"Point"}
}