{
  "type": "Feature",
  "properties": {
    "gn:admin1_code":"8",
    "gn:asciiname":"Laggan",
    "gn:country_code":"CA",
    "gn:dem":85,
    "gn:feature_class":"P",
    "gn:feature_code":"PPL",
    "gn:name":"Laggan",
    "gn:population":0,
    "gn:timezone":"America/Toronto",
    "iso:country":"CA",
    "name:ceb_x_preferred":[
        "Laggan"
    ],
    "name:deu_x_preferred":[
        "Laggan"
    ],
    "name:swe_x_preferred":[
        "Laggan"
    ],
    "wof:name":"Laggan",
    "wof:placetype":"locality"
},
  "geometry": {"coordinates":[-74.70515,45.38951],"type":"Point"}
}