{
  "type": "Feature",
  "properties": {
    "gn:admin1_code":"7",
    "gn:asciiname":"Hoppenderry",
    "gn:country_code":"CA",
    "gn:dem":195,
    "gn:feature_class":"P",
    "gn:feature_code":"PPLL",
    "gn:name":"Hoppenderry",
    "gn:population":0,
    "gn:timezone":"America/Halifax",
    "iso:country":"CA",
    "wof:name":"Hoppenderry",
    "wof:placetype":"locality"
},
  "geometry": {"coordinates":[-61.88186999999999,45.41685],"type":"Point"}
}