{
  "type": "Feature",
  "properties": {
    "gn:admin1_code":"1",
    "gn:asciiname":"Owl River",
    "gn:country_code":"CA",
    "gn:dem":578,
    "gn:feature_class":"P",
    "gn:feature_code":"PPLL",
    "gn:name":"Owl River",
    "gn:population":0,
    "gn:timezone":"America/Edmonton",
    "iso:country":"CA",
    "wof:name":"Owl River",
    "wof:placetype":"locality"
},
  "geometry": {"coordinates":[-111.88518999999999,54.9002],"type":"Point"}
}