{
  "type": "Feature",
  "properties": {
    "gn:admin1_code":"5",
    "gn:asciiname":"Rambler",
    "gn:country_code":"CA",
    "gn:dem":162,
    "gn:feature_class":"P",
    "gn:feature_code":"PPLL",
    "gn:name":"Rambler",
    "gn:population":0,
    "gn:timezone":"America/St_Johns",
    "iso:country":"CA",
    "name:deu_x_preferred":[
        "Rambler"
    ],
    "name:fra_x_preferred":[
        "Rambler"
    ],
    "name:ita_x_preferred":[
        "Rambler"
    ],
    "name:jpn_x_preferred":[
        "\u30e9\u30f3\u30d6\u30e9\u30fc"
    ],
    "name:nld_x_preferred":[
        "Rambler"
    ],
    "name:pol_x_preferred":[
        "Rambler"
    ],
    "name:rus_x_preferred":[
        "Rambler"
    ],
    "wof:name":"Rambler",
    "wof:placetype":"locality"
},
  "geometry": {"coordinates":[-56.0815,49.88326],"type":"Point"}
}