{
  "type": "Feature",
  "properties": {
    "gn:admin1_code":"8",
    "gn:asciiname":"River Canard",
    "gn:country_code":"CA",
    "gn:dem":175,
    "gn:feature_class":"P",
    "gn:feature_code":"PPLL",
    "gn:name":"River Canard",
    "gn:population":0,
    "gn:timezone":"America/Toronto",
    "iso:country":"CA",
    "wof:name":"River Canard",
    "wof:placetype":"locality"
},
  "geometry": {"coordinates":[-83.08315,42.18338],"type":"Point"}
}