{
  "type": "Feature",
  "properties": {
    "gn:admin1_code":"5",
    "gn:asciiname":"Emeril",
    "gn:country_code":"CA",
    "gn:dem":523,
    "gn:feature_class":"P",
    "gn:feature_code":"PPLL",
    "gn:name":"Emeril",
    "gn:population":0,
    "gn:timezone":"America/Goose_Bay",
    "iso:country":"CA",
    "name:fra_x_preferred":[
        "Emeril"
    ],
    "wof:name":"Emeril",
    "wof:placetype":"locality"
},
  "geometry": {"coordinates":[-66.21534,53.08344],"type":"Point"}
}