{
  "type": "Feature",
  "properties": {
    "gn:admin1_code":"1.0",
    "gn:asciiname":"Willesden Green",
    "gn:country_code":"CA",
    "gn:dem":951,
    "gn:feature_class":"P",
    "gn:feature_code":"PPLL",
    "gn:name":"Willesden Green",
    "gn:population":0,
    "gn:timezone":"America/Edmonton",
    "iso:country":"CA",
    "wof:name":"Willesden Green",
    "wof:placetype":"locality"
},
  "geometry": {"coordinates":[-114.58534,52.6834],"type":"Point"}
}