{
  "type": "Feature",
  "properties": {
    "gn:admin1_code":"11",
    "gn:asciiname":"Vawn",
    "gn:country_code":"CA",
    "gn:dem":541,
    "gn:feature_class":"P",
    "gn:feature_code":"PPL",
    "gn:name":"Vawn",
    "gn:population":0,
    "gn:timezone":"America/Regina",
    "iso:country":"CA",
    "wof:name":"Vawn",
    "wof:placetype":"locality"
},
  "geometry": {"coordinates":[-108.68470000000001,53.11686],"type":"Point"}
}