{
  "type": "Feature",
  "properties": {
    "gn:admin1_code":"8",
    "gn:asciiname":"Lake Bernard",
    "gn:country_code":"CA",
    "gn:dem":330,
    "gn:feature_class":"P",
    "gn:feature_code":"PPL",
    "gn:name":"Lake Bernard",
    "gn:population":0,
    "gn:timezone":"America/Toronto",
    "iso:country":"CA",
    "wof:name":"Lake Bernard",
    "wof:placetype":"locality"
},
  "geometry": {"coordinates":[-79.39667,45.70194],"type":"Point"}
}