{
  "type": "Feature",
  "properties": {
    "gn:admin1_code":"7",
    "gn:asciiname":"Lower Mount Thom",
    "gn:country_code":"CA",
    "gn:dem":176,
    "gn:feature_class":"P",
    "gn:feature_code":"PPL",
    "gn:name":"Lower Mount Thom",
    "gn:population":0,
    "gn:timezone":"America/Halifax",
    "iso:country":"CA",
    "wof:name":"Lower Mount Thom",
    "wof:placetype":"locality"
},
  "geometry": {"coordinates":[-62.94724,45.52402],"type":"Point"}
}