{
  "type": "Feature",
  "properties": {
    "gn:admin1_code":"7.0",
    "gn:asciiname":"Acaciaville",
    "gn:country_code":"CA",
    "gn:dem":79,
    "gn:feature_class":"P",
    "gn:feature_code":"PPL",
    "gn:name":"Acaciaville",
    "gn:population":0,
    "gn:timezone":"America/Halifax",
    "iso:country":"CA",
    "wof:name":"Acaciaville",
    "wof:placetype":"locality"
},
  "geometry": {"coordinates":[-65.76246,44.58232],"type":"Point"}
}