{
  "type": "Feature",
  "properties": {
    "gn:admin1_code":"4.0",
    "gn:asciiname":"Cape Breton",
    "gn:country_code":"CA",
    "gn:dem":44,
    "gn:feature_class":"P",
    "gn:feature_code":"PPL",
    "gn:name":"Cape Breton",
    "gn:population":0,
    "gn:timezone":"America/Moncton",
    "iso:country":"CA",
    "wof:name":"Cape Breton",
    "wof:placetype":"locality"
},
  "geometry": {"coordinates":[-64.74921999999999,46.20833],"type":"Point"}
}