{
  "type": "Feature",
  "properties": {
    "gn:admin1_code":"8.0",
    "gn:asciiname":"Bronson",
    "gn:country_code":"CA",
    "gn:dem":319,
    "gn:feature_class":"P",
    "gn:feature_code":"PPL",
    "gn:name":"Bronson",
    "gn:population":0,
    "gn:timezone":"America/Toronto",
    "iso:country":"CA",
    "wof:name":"Bronson",
    "wof:placetype":"locality"
},
  "geometry": {"coordinates":[-77.78889000000002,45.06417],"type":"Point"}
}