{
  "type": "Feature",
  "properties": {
    "gn:admin1_code":"8.0",
    "gn:asciiname":"Bronson",
    "gn:country_code":"CA",
    "gn:dem":319,
    "gn:feature_class":"P",
    "gn:feature_code":"PPL",
    "gn:name":"Bronson",
    "gn:population":0,
    "gn:timezone":"America/Toronto",
    "iso:country":"CA",
    "name:bul_x_preferred":[
        "\u0411\u0440\u043e\u043d\u0441\u044a\u043d"
    ],
    "name:cat_x_preferred":[
        "Bronson"
    ],
    "name:ceb_x_preferred":[
        "Bronson"
    ],
    "name:deu_x_preferred":[
        "Bronson"
    ],
    "name:est_x_preferred":[
        "Bronson"
    ],
    "name:fra_x_preferred":[
        "Bronson"
    ],
    "name:heb_x_preferred":[
        "\u05d1\u05e8\u05d5\u05e0\u05e1\u05d5\u05df"
    ],
    "name:hun_x_preferred":[
        "Bronson"
    ],
    "name:ita_x_preferred":[
        "Bronson"
    ],
    "name:kor_x_preferred":[
        "\ube0c\ub860\uc2a8"
    ],
    "name:nld_x_preferred":[
        "Bronson"
    ],
    "name:pol_x_preferred":[
        "Bronson"
    ],
    "name:por_x_preferred":[
        "Bronson"
    ],
    "name:rus_x_preferred":[
        "\u0411\u0440\u043e\u043d\u0441\u043e\u043d"
    ],
    "name:spa_x_preferred":[
        "Bronson"
    ],
    "name:srp_x_preferred":[
        "\u0411\u0440\u043e\u043d\u0441\u043e\u043d"
    ],
    "name:ukr_x_preferred":[
        "\u0411\u0440\u043e\u043d\u0441\u043e\u043d"
    ],
    "name:urd_x_preferred":[
        "\u0628\u0631\u0648\u0646\u0633\u0646"
    ],
    "name:vol_x_preferred":[
        "Bronson"
    ],
    "wof:name":"Bronson",
    "wof:placetype":"locality"
},
  "geometry": {"coordinates":[-77.78889000000002,45.06417],"type":"Point"}
}