{
  "type": "Feature",
  "properties": {
    "gn:country":"CA",
    "gn:fcode":"PPL",
    "gn:population":0,
    "iso:country":"CA",
    "name:eng_x_preferred":[
        "Morrisburg"
    ],
    "name:fin_x_preferred":[
        "Morrisburg"
    ],
    "name:fra_x_preferred":[
        "Morrisburg"
    ],
    "name:ita_x_preferred":[
        "Morrisburg"
    ],
    "name:rus_x_preferred":[
        "\u041c\u043e\u0440\u0440\u0438\u0441\u0431\u0435\u0440\u0433"
    ],
    "qs_pg:aaroncc":"CA",
    "qs_pg:gn_country":"CA",
    "qs_pg:gn_fcode":"PPL",
    "qs_pg:gn_pop":0,
    "qs_pg:name":"Morrisburg",
    "qs_pg:name_adm0":"Canada",
    "qs_pg:name_adm1":"Ontario",
    "qs_pg:photos":598,
    "qs_pg:photos_1k":121,
    "qs_pg:photos_9k":3,
    "qs_pg:photos_9r":5,
    "qs_pg:photos_all":598,
    "qs_pg:photos_sr":8,
    "qs_pg:pop_sr":0,
    "qs_pg:qs_pg_placetype":"locality",
    "qs_pg:qs_pg_placetype_gp":"Town",
    "qs_pg:woe_adm0":23424775,
    "woe:adm0_id":23424775,
    "woe:name_adm0":"Canada",
    "woe:name_adm1":"Ontario",
    "woe:placetype":"Town",
    "wof:name":"Morrisburg",
    "wof:placetype":"locality",
    "wof:population":3014
},
  "geometry": {"coordinates":[-75.18261,44.9001],"type":"Point"}
}