{
  "type": "Feature",
  "properties": {
    "gn:admin1_code":"8",
    "gn:asciiname":"Milford Haven",
    "gn:country_code":"CA",
    "gn:dem":182,
    "gn:feature_class":"P",
    "gn:feature_code":"PPL",
    "gn:name":"Milford Haven",
    "gn:population":0,
    "gn:timezone":"America/Toronto",
    "iso:country":"CA",
    "wof:name":"Milford Haven",
    "wof:placetype":"locality"
},
  "geometry": {"coordinates":[-83.82850999999999,46.15595],"type":"Point"}
}