{
  "type": "Feature",
  "properties": {
    "gn:admin1_code":"8",
    "gn:asciiname":"Milford Haven",
    "gn:country_code":"CA",
    "gn:dem":182,
    "gn:feature_class":"P",
    "gn:feature_code":"PPL",
    "gn:name":"Milford Haven",
    "gn:population":0,
    "gn:timezone":"America/Toronto",
    "iso:country":"CA",
    "name:ara_x_preferred":[
        "\u0645\u064a\u0644\u0641\u0648\u0631\u062f \u0647\u0627\u0641\u0646"
    ],
    "name:ast_x_preferred":[
        "Aberdaugleddau"
    ],
    "name:bre_x_preferred":[
        "Aberdaugleddau"
    ],
    "name:bul_x_preferred":[
        "\u041c\u0438\u043b\u0444\u043e\u0440\u0434 \u0425\u0435\u0439\u0432\u044a\u043d"
    ],
    "name:cat_x_preferred":[
        "Aberdaugleddau"
    ],
    "name:ceb_x_preferred":[
        "Milford Haven"
    ],
    "name:ces_x_preferred":[
        "Milford Haven"
    ],
    "name:cor_x_preferred":[
        "Aberdaugleddau"
    ],
    "name:cym_x_preferred":[
        "Aberdaugleddau"
    ],
    "name:dan_x_preferred":[
        "Milford Haven"
    ],
    "name:deu_x_preferred":[
        "Milford Haven"
    ],
    "name:est_x_preferred":[
        "Milford Haven"
    ],
    "name:eus_x_preferred":[
        "Milford Haven"
    ],
    "name:fas_x_preferred":[
        "\u0645\u06cc\u0644\u0641\u0648\u062f \u0647\u06cc\u0648\u0646"
    ],
    "name:fin_x_preferred":[
        "Milford Haven"
    ],
    "name:fra_x_preferred":[
        "Milford Haven"
    ],
    "name:gla_x_preferred":[
        "Aberdaugleddau"
    ],
    "name:gle_x_preferred":[
        "Aberdaugleddau"
    ],
    "name:ita_x_preferred":[
        "Milford Haven"
    ],
    "name:lit_x_preferred":[
        "Milford Heivenas"
    ],
    "name:nor_x_preferred":[
        "Milford Haven"
    ],
    "name:pol_x_preferred":[
        "Milford Haven"
    ],
    "name:sme_x_preferred":[
        "Aberdaugleddau"
    ],
    "name:spa_x_preferred":[
        "Milford Haven"
    ],
    "name:swe_x_preferred":[
        "Milford Haven"
    ],
    "name:urd_x_preferred":[
        "\u0645\u06cc\u0644\u0641\u0648\u0631\u0688 \u06c1\u06cc\u0648\u0646"
    ],
    "name:zho_x_preferred":[
        "\u7c73\u723e\u798f\u5fb7\u6e2f"
    ],
    "wof:name":"Milford Haven",
    "wof:placetype":"locality"
},
  "geometry": {"coordinates":[-83.82850999999999,46.15595],"type":"Point"}
}