{
  "type": "Feature",
  "properties": {
    "gn:admin1_code":"3",
    "gn:asciiname":"Metikewap",
    "gn:country_code":"CA",
    "gn:dem":259,
    "gn:feature_class":"P",
    "gn:feature_code":"PPLL",
    "gn:name":"Metikewap",
    "gn:population":0,
    "gn:timezone":"America/Winnipeg",
    "iso:country":"CA",
    "wof:name":"Metikewap",
    "wof:placetype":"locality"
},
  "geometry": {"coordinates":[-101.00051999999999,53.74039000000001],"type":"Point"}
}