{
  "type": "Feature",
  "properties": {
    "gn:admin1_code":"8",
    "gn:asciiname":"Langman",
    "gn:country_code":"CA",
    "gn:dem":208,
    "gn:feature_class":"P",
    "gn:feature_code":"PPL",
    "gn:name":"Langman",
    "gn:population":0,
    "gn:timezone":"America/Toronto",
    "iso:country":"CA",
    "name:deu_x_preferred":[
        "Langman"
    ],
    "wof:name":"Langman",
    "wof:placetype":"locality"
},
  "geometry": {"coordinates":[-79.96688,44.53905],"type":"Point"}
}