{
  "type": "Feature",
  "properties": {
    "iso:country":"CA",
    "name:eng_x_preferred":[
        "Garibaldi"
    ],
    "name:ita_x_preferred":[
        "Garibaldi"
    ],
    "name:jpn_x_preferred":[
        "\u30ac\u30ea\u30d0\u30eb\u30c7\u30a3"
    ],
    "name:nld_x_preferred":[
        "Garibaldi"
    ],
    "name:swe_x_preferred":[
        "Garibaldi"
    ],
    "qs_pg:aaroncc":"CA",
    "qs_pg:name":"Garibaldi",
    "qs_pg:name_adm0":"Canada",
    "qs_pg:name_adm1":"British Columbia",
    "qs_pg:photos":1116,
    "qs_pg:photos_1k":226,
    "qs_pg:photos_9k":5,
    "qs_pg:photos_9r":7,
    "qs_pg:photos_all":1116,
    "qs_pg:photos_sr":11,
    "qs_pg:pop_sr":0,
    "qs_pg:qs_pg_placetype":"locality",
    "qs_pg:qs_pg_placetype_gp":"Town",
    "qs_pg:woe_adm0":23424775,
    "woe:adm0_id":23424775,
    "woe:name_adm0":"Canada",
    "woe:name_adm1":"British Columbia",
    "woe:placetype":"Town",
    "wof:name":"Garibaldi",
    "wof:placetype":"locality"
},
  "geometry": {"coordinates":[-123.136653,49.957722],"type":"Point"}
}