{
  "type": "Feature",
  "properties": {
    "iso:country":"CA",
    "name:eng_x_preferred":[
        "Lakeview"
    ],
    "wof:lang":[
        "eng"
    ],
    "wof:name":"Lakeview",
    "wof:placetype":"neighbourhood"
},
  "geometry": {"coordinates":[-106.595947,52.091996],"type":"Point"}
}