{
  "type": "Feature",
  "properties": {
    "gn:admin1_code":"8",
    "gn:asciiname":"Preneveau",
    "gn:country_code":"CA",
    "gn:dem":198,
    "gn:feature_class":"P",
    "gn:feature_code":"PPL",
    "gn:name":"Preneveau",
    "gn:population":0,
    "gn:timezone":"America/Toronto",
    "iso:country":"CA",
    "wof:name":"Preneveau",
    "wof:placetype":"locality"
},
  "geometry": {"coordinates":[-77.81359,44.43766],"type":"Point"}
}