{
  "type": "Feature",
  "properties": {
    "gn:admin1_code":"10",
    "gn:admin2_code":"7.0",
    "gn:admin3_code":"84065.0",
    "gn:asciiname":"Leclair",
    "gn:country_code":"CA",
    "gn:dem":180,
    "gn:feature_class":"P",
    "gn:feature_code":"PPL",
    "gn:name":"Leclair",
    "gn:population":0,
    "gn:timezone":"America/Toronto",
    "iso:country":"CA",
    "wof:name":"Leclair",
    "wof:placetype":"locality"
},
  "geometry": {"coordinates":[-76.65916999999997,45.89556],"type":"Point"}
}