{
  "type": "Feature",
  "properties": {
    "gn:admin1_code":"8",
    "gn:asciiname":"Manders",
    "gn:country_code":"CA",
    "gn:dem":349,
    "gn:feature_class":"P",
    "gn:feature_code":"PPLL",
    "gn:name":"Manders",
    "gn:population":0,
    "gn:timezone":"America/Winnipeg",
    "iso:country":"CA",
    "wof:name":"Manders",
    "wof:placetype":"locality"
},
  "geometry": {"coordinates":[-94.06706,48.66667],"type":"Point"}
}