{
  "type": "Feature",
  "properties": {
    "gn:admin1_code":"2.0",
    "gn:admin2_code":"5929",
    "gn:asciiname":"Williamsons Landing",
    "gn:country_code":"CA",
    "gn:dem":47,
    "gn:feature_class":"P",
    "gn:feature_code":"PPLL",
    "gn:name":"Williamsons Landing",
    "gn:population":0,
    "gn:timezone":"America/Vancouver",
    "iso:country":"CA",
    "wof:name":"Williamsons Landing",
    "wof:placetype":"locality"
},
  "geometry": {"coordinates":[-123.47512999999999,49.45574000000001],"type":"Point"}
}