{
  "type": "Feature",
  "properties": {
    "gn:admin1_code":"7",
    "gn:asciiname":"Rear Black River",
    "gn:country_code":"CA",
    "gn:dem":50,
    "gn:feature_class":"P",
    "gn:feature_code":"PPLL",
    "gn:name":"Rear Black River",
    "gn:population":0,
    "gn:timezone":"America/Halifax",
    "iso:country":"CA",
    "wof:name":"Rear Black River",
    "wof:placetype":"locality"
},
  "geometry": {"coordinates":[-61.13182,45.68344],"type":"Point"}
}