{
  "type": "Feature",
  "properties": {
    "gn:admin1_code":"5.0",
    "gn:asciiname":"Beaumont",
    "gn:country_code":"CA",
    "gn:dem":35,
    "gn:feature_class":"P",
    "gn:feature_code":"PPL",
    "gn:name":"Beaumont",
    "gn:population":0,
    "gn:timezone":"America/St_Johns",
    "iso:country":"CA",
    "wof:name":"Beaumont",
    "wof:placetype":"locality"
},
  "geometry": {"coordinates":[-55.68147,49.61664],"type":"Point"}
}