{
  "type": "Feature",
  "properties": {
    "gn:gn_country":"CA",
    "gn:gn_fcode":"PPL",
    "gn:gn_pop":11584,
    "gn:population":11584,
    "iso:country":"CA",
    "name:ara_x_preferred":[
        "\u0633\u0627\u0646\u062a \u0645\u0627\u0631\u064a\u060c \u0643\u064a\u0628\u0643"
    ],
    "name:deu_x_preferred":[
        "Sainte-Marie"
    ],
    "name:eng_x_preferred":[
        "Sainte-Marie"
    ],
    "name:eus_x_preferred":[
        "Sainte-Marie"
    ],
    "name:fas_x_preferred":[
        "\u0633\u0646\u062a-\u0645\u0627\u0631\u06cc\u060c \u06a9\u0628\u06a9"
    ],
    "name:fra_x_preferred":[
        "Sainte-Marie"
    ],
    "name:ita_x_preferred":[
        "Sainte-Marie"
    ],
    "name:jpn_x_preferred":[
        "\u30b5\u30f3\u30c8\uff1d\u30de\u30ea\u30fc"
    ],
    "name:nld_x_preferred":[
        "Sainte-Marie"
    ],
    "name:nno_x_preferred":[
        "Sainte-Marie"
    ],
    "name:nob_x_preferred":[
        "Sainte-Marie"
    ],
    "name:por_x_preferred":[
        "Sainte-Marie"
    ],
    "name:ron_x_preferred":[
        "Sainte-Marie"
    ],
    "name:slv_x_preferred":[
        "Sainte-Marie"
    ],
    "name:spa_x_preferred":[
        "Sainte-Marie"
    ],
    "name:srp_x_preferred":[
        "\u0421\u0435\u043d\u0442 \u041c\u0430\u0440\u0438"
    ],
    "name:swe_x_preferred":[
        "Sainte-Marie"
    ],
    "name:tur_x_preferred":[
        "Sainte-Marie"
    ],
    "name:urd_x_preferred":[
        "\u0633\u06cc\u0646-\u0645\u0631\u06d2\u060c \u06a9\u06cc\u0648\u0628\u06a9"
    ],
    "name:zho_x_preferred":[
        "\u8056\u746a\u9e97"
    ],
    "qs_pg:aaroncc":"CA",
    "qs_pg:gn_country":"CA",
    "qs_pg:gn_fcode":"PPL",
    "qs_pg:gn_pop":11584,
    "qs_pg:name":"Ste.-Marie",
    "qs_pg:name_adm0":"Canada",
    "qs_pg:name_adm1":"Qu\u00e9bec",
    "qs_pg:photos":493,
    "qs_pg:photos_1k":100,
    "qs_pg:photos_9k":2,
    "qs_pg:photos_9r":5,
    "qs_pg:photos_all":493,
    "qs_pg:photos_sr":7,
    "qs_pg:pop_sr":6,
    "qs_pg:qs_pg_placetype":"locality",
    "qs_pg:qs_pg_placetype_gp":"Town",
    "qs_pg:woe_adm0":23424775,
    "woe:adm0_id":23424775,
    "woe:name_adm0":"Canada",
    "woe:name_adm1":"Qu\u00e9bec",
    "woe:placetype":"Town",
    "wof:name":"Ste.-Marie",
    "wof:placetype":"locality",
    "wof:population":11584
},
  "geometry": {"coordinates":[-71.01168,46.43401],"type":"Point"}
}