{
  "type": "Feature",
  "properties": {
    "gn:country":"CA",
    "gn:fcode":"PPL",
    "gn:population":0,
    "iso:country":"CA",
    "name:ara_x_preferred":[
        "\u0643\u0648\u0628\u0644\u064a \u0647\u064a\u0644"
    ],
    "name:cat_x_preferred":[
        "Cobble Hill"
    ],
    "name:ceb_x_preferred":[
        "Cobble Hill"
    ],
    "name:ell_x_preferred":[
        "\u039a\u03cc\u03bc\u03c0\u03bb \u03a7\u03af\u03bb"
    ],
    "name:eng_x_preferred":[
        "Cobble Hill"
    ],
    "name:fra_x_preferred":[
        "Cobble Hill"
    ],
    "name:nld_x_preferred":[
        "Cobble Hill"
    ],
    "name:spa_x_preferred":[
        "Cobble Hill"
    ],
    "name:swe_x_preferred":[
        "Cobble Hill"
    ],
    "qs_pg:aaroncc":"CA",
    "qs_pg:gn_country":"CA",
    "qs_pg:gn_fcode":"PPL",
    "qs_pg:gn_pop":0,
    "qs_pg:name":"Cobble Hill",
    "qs_pg:name_adm0":"Canada",
    "qs_pg:name_adm1":"British Columbia",
    "qs_pg:photos":338,
    "qs_pg:photos_1k":68,
    "qs_pg:photos_9k":1,
    "qs_pg:photos_9r":5,
    "qs_pg:photos_all":338,
    "qs_pg:photos_sr":5,
    "qs_pg:pop_sr":0,
    "qs_pg:qs_pg_placetype":"locality",
    "qs_pg:qs_pg_placetype_gp":"Town",
    "qs_pg:woe_adm0":23424775,
    "woe:adm0_id":23424775,
    "woe:name_adm0":"Canada",
    "woe:name_adm1":"British Columbia",
    "woe:placetype":"Town",
    "wof:name":"Cobble Hill",
    "wof:placetype":"locality"
},
  "geometry": {"coordinates":[-123.60263999999999,48.68293],"type":"Point"}
}