{
  "type": "Feature",
  "properties": {
    "gn:admin1_code":"8",
    "gn:asciiname":"Waneeta Beach",
    "gn:country_code":"CA",
    "gn:dem":196,
    "gn:feature_class":"P",
    "gn:feature_code":"PPL",
    "gn:name":"Waneeta Beach",
    "gn:population":0,
    "gn:timezone":"America/Toronto",
    "iso:country":"CA",
    "wof:name":"Waneeta Beach",
    "wof:placetype":"locality"
},
  "geometry": {"coordinates":[-81.01789000000002,42.6584],"type":"Point"}
}