{
  "type": "Feature",
  "properties": {
    "gn:admin1_code":"1.0",
    "gn:asciiname":"Carbon",
    "gn:country_code":"CA",
    "gn:dem":772,
    "gn:feature_class":"P",
    "gn:feature_code":"PPL",
    "gn:name":"Carbon",
    "gn:population":0,
    "gn:timezone":"America/Edmonton",
    "iso:country":"CA",
    "wof:name":"Carbon",
    "wof:placetype":"locality"
},
  "geometry": {"coordinates":[-113.15191000000002,51.48343],"type":"Point"}
}