{
  "type": "Feature",
  "properties": {
    "iso:country":"CA",
    "name:deu_x_preferred":[
        "Thorburn"
    ],
    "name:eng_x_preferred":[
        "Thorburn"
    ],
    "name:rus_x_preferred":[
        "\u0422\u043e\u0440\u0431\u0451\u0440\u043d"
    ],
    "name:swe_x_preferred":[
        "Thorburn"
    ],
    "name:unk_x_variant":[
        "Thorburn"
    ],
    "qs:gn_adm0_cc":"CA",
    "qs:gn_local":6324733,
    "qs:gn_nam_loc":"St. John's, Newfoundland and Labrador, Newfoundland and Labrador, CA",
    "qs:gn_namadm1":"05",
    "qs:local_max":5403,
    "qs:local_sum":16210,
    "qs:localhoods":11,
    "qs:name":"Thorburn",
    "qs:name_adm0":"Canada",
    "qs:name_adm1":"Newfoundland and Labrador",
    "qs:name_adm2":"Newfoundland and Labrador",
    "qs:name_local":"St. John's",
    "qs:photo_max":15,
    "qs:photo_sum":109,
    "qs:placetype":"Suburb",
    "qs:quad_count":33,
    "qs:woe_adm0":23424775,
    "qs:woe_adm1":2344919,
    "qs:woe_adm2":29375216,
    "qs:woe_lau":0,
    "qs:woe_local":3996,
    "qs:woe_ver":"7.10.0",
    "wd:wordcount":203,
    "wof:lang":[
        "eng"
    ],
    "wof:name":"Thorburn",
    "wof:placetype":"neighbourhood"
},
  "geometry": {"coordinates":[-52.834033,47.562085],"type":"Point"}
}