{
  "type": "Feature",
  "properties": {
    "gn:admin1_code":"8",
    "gn:asciiname":"Kinhuron",
    "gn:country_code":"CA",
    "gn:dem":190,
    "gn:feature_class":"P",
    "gn:feature_code":"PPLL",
    "gn:name":"Kinhuron",
    "gn:population":0,
    "gn:timezone":"America/Toronto",
    "iso:country":"CA",
    "wof:name":"Kinhuron",
    "wof:placetype":"locality"
},
  "geometry": {"coordinates":[-81.60587,44.23789],"type":"Point"}
}