{
  "type": "Feature",
  "properties": {
    "gn:admin1_code":"7",
    "gn:asciiname":"Wallace Highlands",
    "gn:country_code":"CA",
    "gn:dem":68,
    "gn:feature_class":"P",
    "gn:feature_code":"PPL",
    "gn:name":"Wallace Highlands",
    "gn:population":0,
    "gn:timezone":"America/Halifax",
    "iso:country":"CA",
    "wof:name":"Wallace Highlands",
    "wof:placetype":"locality"
},
  "geometry": {"coordinates":[-63.45823000000001,45.72648],"type":"Point"}
}