{
  "type": "Feature",
  "properties": {
    "gn:admin1_code":"5",
    "gn:asciiname":"Pynns",
    "gn:country_code":"CA",
    "gn:dem":5,
    "gn:feature_class":"P",
    "gn:feature_code":"PPLL",
    "gn:name":"Pynns",
    "gn:population":0,
    "gn:timezone":"America/St_Johns",
    "iso:country":"CA",
    "wof:name":"Pynns",
    "wof:placetype":"locality"
},
  "geometry": {"coordinates":[-57.54835,49.10001],"type":"Point"}
}