{
  "type": "Feature",
  "properties": {
    "gn:admin1_code":"9",
    "gn:asciiname":"Lower Newtown",
    "gn:country_code":"CA",
    "gn:dem":31,
    "gn:feature_class":"P",
    "gn:feature_code":"PPLL",
    "gn:name":"Lower Newtown",
    "gn:population":0,
    "gn:timezone":"America/Halifax",
    "iso:country":"CA",
    "wof:name":"Lower Newtown",
    "wof:placetype":"locality"
},
  "geometry": {"coordinates":[-62.86537,46.11681],"type":"Point"}
}