{
  "type": "Feature",
  "properties": {
    "gn:admin1_code":"7",
    "gn:asciiname":"Sandford",
    "gn:country_code":"CA",
    "gn:dem":35,
    "gn:feature_class":"P",
    "gn:feature_code":"PPL",
    "gn:name":"Sandford",
    "gn:population":0,
    "gn:timezone":"America/Halifax",
    "iso:country":"CA",
    "wof:name":"Sandford",
    "wof:placetype":"locality"
},
  "geometry": {"coordinates":[-66.14775,43.92079],"type":"Point"}
}