{
  "type": "Feature",
  "properties": {
    "gn:admin1_code":"8",
    "gn:asciiname":"Lasswade",
    "gn:country_code":"CA",
    "gn:dem":319,
    "gn:feature_class":"P",
    "gn:feature_code":"PPL",
    "gn:name":"Lasswade",
    "gn:population":0,
    "gn:timezone":"America/Toronto",
    "iso:country":"CA",
    "wof:name":"Lasswade",
    "wof:placetype":"locality"
},
  "geometry": {"coordinates":[-77.94707,44.75864],"type":"Point"}
}