{
  "type": "Feature",
  "properties": {
    "gn:admin1_code":"7",
    "gn:asciiname":"North Wallace Bay",
    "gn:country_code":"CA",
    "gn:dem":5,
    "gn:feature_class":"P",
    "gn:feature_code":"PPL",
    "gn:name":"North Wallace Bay",
    "gn:population":0,
    "gn:timezone":"America/Halifax",
    "iso:country":"CA",
    "wof:name":"North Wallace Bay",
    "wof:placetype":"locality"
},
  "geometry": {"coordinates":[-63.5551,45.84004],"type":"Point"}
}