{
  "type": "Feature",
  "properties": {
    "iso:country":"CA",
    "name:eng_x_preferred":[
        "South Telford"
    ],
    "qs:gn_adm0_cc":"CA",
    "qs:gn_local":6051562,
    "qs:gn_nam_loc":"leduc",
    "qs:gn_namadm1":"01",
    "qs:local_max":78,
    "qs:local_sum":143,
    "qs:localhoods":2,
    "qs:name":"South Telford",
    "qs:name_adm0":"Canada",
    "qs:name_adm1":"Alberta",
    "qs:name_adm2":"Alberta",
    "qs:name_local":"Leduc",
    "qs:photo_max":12,
    "qs:photo_sum":65,
    "qs:placetype":"Suburb",
    "qs:quad_count":16,
    "qs:woe_adm0":23424775,
    "qs:woe_adm1":2344915,
    "qs:woe_adm2":29375228,
    "qs:woe_funk":"Parented by a neighborhood",
    "qs:woe_lau":0,
    "qs:woe_local":8691,
    "qs:woe_ver":"7.10.0",
    "wof:lang":[
        "eng"
    ],
    "wof:name":"South Telford",
    "wof:placetype":"neighbourhood"
},
  "geometry": {"coordinates":[-113.526875,53.260238],"type":"Point"}
}