{
  "type": "Feature",
  "properties": {
    "iso:country":"CA",
    "name:eng_x_preferred":[
        "Downtown Newmarket"
    ],
    "qs:gn_local":0,
    "qs:local_max":273,
    "qs:local_sum":273,
    "qs:localhoods":1,
    "qs:name":"Downtown Newmarket",
    "qs:name_adm0":"Canada",
    "qs:name_adm1":"Ontario",
    "qs:name_adm2":"York",
    "qs:name_local":"Bogarttown",
    "qs:photo_max":72,
    "qs:photo_sum":273,
    "qs:placetype":"Suburb",
    "qs:quad_count":21,
    "qs:woe_adm0":23424775,
    "qs:woe_adm1":2344922,
    "qs:woe_adm2":29375112,
    "qs:woe_funk":"Grouping neighborhood",
    "qs:woe_lau":0,
    "qs:woe_local":55999132,
    "qs:woe_ver":"7.10.0",
    "wof:lang":[
        "eng"
    ],
    "wof:name":"Downtown Newmarket",
    "wof:placetype":"neighbourhood"
},
  "geometry": {"coordinates":[-79.45824500000001,44.052556],"type":"Point"}
}