{
  "type": "Feature",
  "properties": {
    "gn:admin1_code":"8",
    "gn:asciiname":"Minniehill",
    "gn:country_code":"CA",
    "gn:dem":335,
    "gn:feature_class":"P",
    "gn:feature_code":"PPL",
    "gn:name":"Minniehill",
    "gn:population":0,
    "gn:timezone":"America/Toronto",
    "iso:country":"CA",
    "wof:name":"Minniehill",
    "wof:placetype":"locality"
},
  "geometry": {"coordinates":[-80.60583000000003,44.53917],"type":"Point"}
}