{
  "type": "Feature",
  "properties": {
    "gn:admin1_code":"5",
    "gn:asciiname":"Rouge Harbour",
    "gn:country_code":"CA",
    "gn:dem":143,
    "gn:feature_class":"P",
    "gn:feature_code":"PPLL",
    "gn:name":"Rouge Harbour",
    "gn:population":0,
    "gn:timezone":"America/St_Johns",
    "iso:country":"CA",
    "wof:name":"Rouge Harbour",
    "wof:placetype":"locality"
},
  "geometry": {"coordinates":[-55.91486,49.76666],"type":"Point"}
}