{
  "type": "Feature",
  "properties": {
    "gn:admin1_code":"8",
    "gn:asciiname":"Three Bridges",
    "gn:country_code":"CA",
    "gn:dem":277,
    "gn:feature_class":"P",
    "gn:feature_code":"PPLL",
    "gn:name":"Three Bridges",
    "gn:population":0,
    "gn:timezone":"America/Toronto",
    "iso:country":"CA",
    "name:deu_x_preferred":[
        "Three Bridges"
    ],
    "name:nld_x_preferred":[
        "Three Bridges"
    ],
    "name:pol_x_preferred":[
        "Three Bridges"
    ],
    "wof:name":"Three Bridges",
    "wof:placetype":"locality"
},
  "geometry": {"coordinates":[-81.05473000000001,43.04179],"type":"Point"}
}