{
  "type": "Feature",
  "properties": {
    "gn:admin1_code":"7.0",
    "gn:asciiname":"Caledonia Mills",
    "gn:country_code":"CA",
    "gn:dem":132,
    "gn:feature_class":"P",
    "gn:feature_code":"PPL",
    "gn:name":"Caledonia Mills",
    "gn:population":0,
    "gn:timezone":"America/Halifax",
    "iso:country":"CA",
    "name:gla_x_preferred":[
        "An Daigear"
    ],
    "wof:name":"Caledonia Mills",
    "wof:placetype":"locality"
},
  "geometry": {"coordinates":[-61.7984,45.48744],"type":"Point"}
}