{
  "type": "Feature",
  "properties": {
    "gn:gn_country":"CA",
    "iso:country":"CA",
    "name:ceb_x_preferred":[
        "Bayfield"
    ],
    "name:deu_x_preferred":[
        "Bayfield"
    ],
    "name:fra_x_preferred":[
        "Bayfield"
    ],
    "name:ita_x_preferred":[
        "Bayfield"
    ],
    "name:nld_x_preferred":[
        "Bayfield"
    ],
    "name:pol_x_preferred":[
        "Bayfield"
    ],
    "name:por_x_preferred":[
        "Bayfield"
    ],
    "name:srp_x_preferred":[
        "\u0411\u0430\u0458\u0444\u0438\u043b\u0434"
    ],
    "name:ukr_x_preferred":[
        "\u0411\u0435\u0439\u0444\u0456\u043b\u0434"
    ],
    "name:vol_x_preferred":[
        "Bayfield"
    ],
    "qs_pg:aaroncc":"CA",
    "qs_pg:gn_country":"CA",
    "qs_pg:name":"Bayfield",
    "qs_pg:name_adm0":"Canada",
    "qs_pg:name_adm1":"New Brunswick",
    "qs_pg:photos":448,
    "qs_pg:photos_1k":91,
    "qs_pg:photos_9k":2,
    "qs_pg:photos_9r":5,
    "qs_pg:photos_all":448,
    "qs_pg:photos_sr":6,
    "qs_pg:pop_sr":0,
    "qs_pg:qs_pg_placetype":"locality",
    "qs_pg:qs_pg_placetype_gp":"Town",
    "qs_pg:woe_adm0":23424775,
    "woe:adm0_id":23424775,
    "woe:name_adm0":"Canada",
    "woe:name_adm1":"New Brunswick",
    "woe:placetype":"Town",
    "wof:name":"Bayfield",
    "wof:placetype":"locality"
},
  "geometry": {"coordinates":[-63.8150695,46.162771],"type":"Point"}
}