{
  "type": "Feature",
  "properties": {
    "gn:admin1_code":"1",
    "gn:asciiname":"Moose Wallow",
    "gn:country_code":"CA",
    "gn:dem":728,
    "gn:feature_class":"P",
    "gn:feature_code":"PPLL",
    "gn:name":"Moose Wallow",
    "gn:population":0,
    "gn:timezone":"America/Edmonton",
    "iso:country":"CA",
    "wof:name":"Moose Wallow",
    "wof:placetype":"locality"
},
  "geometry": {"coordinates":[-114.95219,54.20014000000001],"type":"Point"}
}