{
  "type": "Feature",
  "properties": {
    "gn:admin1_code":"1",
    "gn:asciiname":"Hawk Hills",
    "gn:country_code":"CA",
    "gn:dem":516,
    "gn:feature_class":"P",
    "gn:feature_code":"PPLL",
    "gn:name":"Hawk Hills",
    "gn:population":0,
    "gn:timezone":"America/Edmonton",
    "iso:country":"CA",
    "wof:name":"Hawk Hills",
    "wof:placetype":"locality"
},
  "geometry": {"coordinates":[-117.46944999999999,57.23342],"type":"Point"}
}