{
  "type": "Feature",
  "properties": {
    "gn:admin1_code":"5",
    "gn:asciiname":"Stanley Cove",
    "gn:country_code":"CA",
    "gn:dem":166,
    "gn:feature_class":"P",
    "gn:feature_code":"PPLL",
    "gn:name":"Stanley Cove",
    "gn:population":0,
    "gn:timezone":"America/St_Johns",
    "iso:country":"CA",
    "wof:name":"Stanley Cove",
    "wof:placetype":"locality"
},
  "geometry": {"coordinates":[-56.16505,47.69995],"type":"Point"}
}