{
  "type": "Feature",
  "properties": {
    "gn:admin1_code":"12",
    "gn:asciiname":"Hillcrest",
    "gn:country_code":"CA",
    "gn:dem":651,
    "gn:feature_class":"P",
    "gn:feature_code":"PPL",
    "gn:name":"Hillcrest",
    "gn:population":0,
    "gn:timezone":"America/Whitehorse",
    "iso:country":"CA",
    "wof:name":"Hillcrest",
    "wof:placetype":"locality"
},
  "geometry": {"coordinates":[-135.09028000000001,60.7125],"type":"Point"}
}