{
  "type": "Feature",
  "properties": {
    "gn:admin1_code":"12",
    "gn:asciiname":"Hillcrest",
    "gn:country_code":"CA",
    "gn:dem":651,
    "gn:feature_class":"P",
    "gn:feature_code":"PPL",
    "gn:name":"Hillcrest",
    "gn:population":0,
    "gn:timezone":"America/Whitehorse",
    "iso:country":"CA",
    "name:bar_x_preferred":[
        "Hillcrest"
    ],
    "name:cat_x_preferred":[
        "Hillcrest"
    ],
    "name:ceb_x_preferred":[
        "Hillcrest"
    ],
    "name:deu_x_preferred":[
        "Hillcrest"
    ],
    "name:ita_x_preferred":[
        "Hillcrest"
    ],
    "name:nld_x_preferred":[
        "Hillcrest"
    ],
    "name:pol_x_preferred":[
        "Hillcrest"
    ],
    "name:por_x_preferred":[
        "Hillcrest"
    ],
    "name:srp_x_preferred":[
        "\u0425\u0438\u043b\u043a\u0440\u0435\u0441\u0442"
    ],
    "name:ukr_x_preferred":[
        "\u0413\u0456\u043b\u043b\u043a\u0440\u0435\u0441\u0442"
    ],
    "name:vol_x_preferred":[
        "Hillcrest"
    ],
    "wof:name":"Hillcrest",
    "wof:placetype":"locality"
},
  "geometry": {"coordinates":[-135.09028000000001,60.7125],"type":"Point"}
}