{
  "type": "Feature",
  "properties": {
    "gn:admin1_code":"7",
    "gn:asciiname":"North West Harbour",
    "gn:country_code":"CA",
    "gn:dem":9,
    "gn:feature_class":"P",
    "gn:feature_code":"PPL",
    "gn:name":"North West Harbour",
    "gn:population":0,
    "gn:timezone":"America/Halifax",
    "iso:country":"CA",
    "wof:name":"North West Harbour",
    "wof:placetype":"locality"
},
  "geometry": {"coordinates":[-65.41419999999999,43.56319000000001],"type":"Point"}
}