{
  "type": "Feature",
  "properties": {
    "gn:admin1_code":"7",
    "gn:asciiname":"Eden Lake",
    "gn:country_code":"CA",
    "gn:dem":124,
    "gn:feature_class":"P",
    "gn:feature_code":"PPL",
    "gn:name":"Eden Lake",
    "gn:population":0,
    "gn:timezone":"America/Halifax",
    "iso:country":"CA",
    "name:ara_x_preferred":[
        "\u0628\u062d\u064a\u0631\u0629 \u0639\u062f\u0646"
    ],
    "name:bre_x_preferred":[
        "Eden Lake"
    ],
    "name:ces_x_preferred":[
        "Jezero smrti"
    ],
    "name:deu_x_preferred":[
        "Eden Lake"
    ],
    "name:eml_x_preferred":[
        "Eden Lake"
    ],
    "name:eus_x_preferred":[
        "Eden Lake"
    ],
    "name:fas_x_preferred":[
        "\u062f\u0631\u06cc\u0627\u0686\u0647 \u0628\u0647\u0634\u062a"
    ],
    "name:fin_x_preferred":[
        "Eden Lake"
    ],
    "name:fra_x_preferred":[
        "Eden Lake"
    ],
    "name:hun_x_preferred":[
        "Gyilkos kil\u00e1t\u00e1sok"
    ],
    "name:ita_x_preferred":[
        "Eden Lake"
    ],
    "name:jpn_x_preferred":[
        "\u30d0\u30a4\u30aa\u30ec\u30f3\u30b9\u30fb\u30ec\u30a4\u30af"
    ],
    "name:nld_x_preferred":[
        "Eden Lake"
    ],
    "name:pol_x_preferred":[
        "Eden Lake"
    ],
    "name:por_x_preferred":[
        "Eden Lake"
    ],
    "name:rus_x_preferred":[
        "\u0420\u0430\u0439\u0441\u043a\u043e\u0435 \u043e\u0437\u0435\u0440\u043e"
    ],
    "name:spa_x_preferred":[
        "Eden Lake"
    ],
    "name:swe_x_preferred":[
        "Eden Lake"
    ],
    "name:ukr_x_preferred":[
        "\u0420\u0430\u0439\u0441\u044c\u043a\u0435 \u043e\u0437\u0435\u0440\u043e"
    ],
    "name:zho_x_preferred":[
        "\u4f0a\u7538\u6e56"
    ],
    "wof:name":"Eden Lake",
    "wof:placetype":"locality"
},
  "geometry": {"coordinates":[-62.29437,45.40465],"type":"Point"}
}