{
  "type": "Feature",
  "properties": {
    "gn:admin1_code":"9",
    "gn:asciiname":"Richmond",
    "gn:country_code":"CA",
    "gn:dem":38,
    "gn:feature_class":"P",
    "gn:feature_code":"PPL",
    "gn:name":"Richmond",
    "gn:population":0,
    "gn:timezone":"America/Halifax",
    "iso:country":"CA",
    "name:ben_x_preferred":[
        "\u09b0\u09bf\u099a\u09ae\u09a8\u09cd\u09a1"
    ],
    "name:ell_x_preferred":[
        "\u03a1\u03af\u03c4\u03c3\u03bc\u03bf\u03bd\u03c4"
    ],
    "name:fra_x_preferred":[
        "Richmond"
    ],
    "name:heb_x_preferred":[
        "\u05e8\u05d9\u05e6'\u05de\u05d5\u05e0\u05d3"
    ],
    "name:hin_x_preferred":[
        "\u0930\u093f\u091a\u092e\u0902\u0921"
    ],
    "name:hun_x_preferred":[
        "Richmond"
    ],
    "name:ind_x_preferred":[
        "Richmond"
    ],
    "name:ita_x_preferred":[
        "Richmond"
    ],
    "name:kor_x_preferred":[
        "\ub9ac\uce58\uba3c\ub4dc"
    ],
    "name:pol_x_preferred":[
        "Richmond"
    ],
    "name:rus_x_preferred":[
        "\u0420\u0438\u0447\u043c\u043e\u043d\u0434"
    ],
    "name:spa_x_preferred":[
        "Richmond"
    ],
    "name:tur_x_preferred":[
        "Richmond"
    ],
    "name:ukr_x_preferred":[
        "\u0420\u0456\u0447\u043c\u043e\u043d\u0434"
    ],
    "name:urd_x_preferred":[
        "\u0631\u0686\u0645\u0646\u0688"
    ],
    "name:vie_x_preferred":[
        "Richmond"
    ],
    "wof:name":"Richmond",
    "wof:placetype":"locality"
},
  "geometry": {"coordinates":[-63.98203,46.51684],"type":"Point"}
}