{
  "type": "Feature",
  "properties": {
    "gn:admin1_code":"9",
    "gn:asciiname":"Richmond",
    "gn:country_code":"CA",
    "gn:dem":38,
    "gn:feature_class":"P",
    "gn:feature_code":"PPL",
    "gn:name":"Richmond",
    "gn:population":0,
    "gn:timezone":"America/Halifax",
    "iso:country":"CA",
    "name:fra_x_preferred":[
        "Richmond"
    ],
    "wof:name":"Richmond",
    "wof:placetype":"locality"
},
  "geometry": {"coordinates":[-63.98203,46.51684],"type":"Point"}
}