{
  "type": "Feature",
  "properties": {
    "gn:admin1_code":"8",
    "gn:asciiname":"Pine Orchard",
    "gn:country_code":"CA",
    "gn:dem":279,
    "gn:feature_class":"P",
    "gn:feature_code":"PPL",
    "gn:name":"Pine Orchard",
    "gn:population":0,
    "gn:timezone":"America/Toronto",
    "iso:country":"CA",
    "wof:name":"Pine Orchard",
    "wof:placetype":"locality"
},
  "geometry": {"coordinates":[-79.37945000000001,44.0582],"type":"Point"}
}