{
  "type": "Feature",
  "properties": {
    "gn:admin1_code":"7.0",
    "gn:asciiname":"Clayton Park",
    "gn:country_code":"CA",
    "gn:dem":88,
    "gn:feature_class":"P",
    "gn:feature_code":"PPL",
    "gn:name":"Clayton Park",
    "gn:population":0,
    "gn:timezone":"America/Halifax",
    "iso:country":"CA",
    "wof:name":"Clayton Park",
    "wof:placetype":"locality"
},
  "geometry": {"coordinates":[-63.64731,44.66029],"type":"Point"}
}