{
  "type": "Feature",
  "properties": {
    "gn:admin1_code":"10",
    "gn:admin2_code":"08",
    "gn:admin3_code":"88070.0",
    "gn:asciiname":"Saint-Nazaire-de-Berry",
    "gn:country_code":"CA",
    "gn:dem":302,
    "gn:feature_class":"P",
    "gn:feature_code":"PPL",
    "gn:name":"Saint-Nazaire-de-Berry",
    "gn:population":0,
    "gn:timezone":"America/Toronto",
    "iso:country":"CA",
    "wof:name":"Saint-Nazaire-de-Berry",
    "wof:placetype":"locality"
},
  "geometry": {"coordinates":[-78.25894,48.71954],"type":"Point"}
}