{
  "type": "Feature",
  "properties": {
    "gn:admin1_code":"8.0",
    "gn:asciiname":"Berryton",
    "gn:country_code":"CA",
    "gn:dem":109,
    "gn:feature_class":"P",
    "gn:feature_code":"PPL",
    "gn:name":"Berryton",
    "gn:population":0,
    "gn:timezone":"America/Toronto",
    "iso:country":"CA",
    "name:deu_x_preferred":[
        "Berryton"
    ],
    "wof:name":"Berryton",
    "wof:placetype":"locality"
},
  "geometry": {"coordinates":[-76.19704,44.46149000000001],"type":"Point"}
}