{
  "type": "Feature",
  "properties": {
    "gn:admin1_code":"10",
    "gn:admin2_code":"5.0",
    "gn:admin3_code":"44045.0",
    "gn:asciiname":"South Barnston",
    "gn:country_code":"CA",
    "gn:dem":401,
    "gn:feature_class":"P",
    "gn:feature_code":"PPL",
    "gn:name":"South Barnston",
    "gn:population":0,
    "gn:timezone":"America/Toronto",
    "iso:country":"CA",
    "wof:name":"South Barnston",
    "wof:placetype":"locality"
},
  "geometry": {"coordinates":[-71.97954,45.05782],"type":"Point"}
}