{
  "type": "Feature",
  "properties": {
    "gn:admin1_code":"3",
    "gn:asciiname":"Sclater",
    "gn:country_code":"CA",
    "gn:dem":353,
    "gn:feature_class":"P",
    "gn:feature_code":"PPLL",
    "gn:name":"Sclater",
    "gn:population":0,
    "gn:timezone":"America/Winnipeg",
    "iso:country":"CA",
    "wof:name":"Sclater",
    "wof:placetype":"locality"
},
  "geometry": {"coordinates":[-100.61058,51.92971],"type":"Point"}
}