{
  "type": "Feature",
  "properties": {
    "gn:country":"CA",
    "gn:fcode":"PPL",
    "gn:population":0,
    "iso:country":"CA",
    "name:eng_x_preferred":[
        "Woodside"
    ],
    "name:nld_x_preferred":[
        "Woodside"
    ],
    "qs:name":"Woodside",
    "qs:name_adm0":"Canada",
    "qs:name_adm1":"Nova Scotia",
    "qs:photos_9r":0,
    "qs:photos_sr":0,
    "qs:placetype":"Town",
    "qs:pop_sr":"0",
    "wd:wordcount":455,
    "wof:name":"Woodside",
    "wof:placetype":"locality",
    "wof:population":0
},
  "geometry": {"coordinates":[-63.54869,44.65015],"type":"Point"}
}