{
  "type": "Feature",
  "properties": {
    "gn:admin1_code":"8",
    "gn:asciiname":"Trinity",
    "gn:country_code":"CA",
    "gn:dem":223,
    "gn:feature_class":"P",
    "gn:feature_code":"PPL",
    "gn:name":"Trinity",
    "gn:population":0,
    "gn:timezone":"America/Toronto",
    "iso:country":"CA",
    "wof:name":"Trinity",
    "wof:placetype":"locality"
},
  "geometry": {"coordinates":[-80.03639,43.17389],"type":"Point"}
}