{
  "type": "Feature",
  "properties": {
    "gn:admin1_code":"10",
    "gn:admin2_code":"16",
    "gn:admin3_code":"71083.0",
    "gn:asciiname":"Radisson",
    "gn:country_code":"CA",
    "gn:dem":76,
    "gn:feature_class":"P",
    "gn:feature_code":"PPL",
    "gn:name":"Radisson",
    "gn:population":0,
    "gn:timezone":"America/Toronto",
    "iso:country":"CA",
    "name:ceb_x_preferred":[
        "Radisson"
    ],
    "name:deu_x_preferred":[
        "Radisson"
    ],
    "name:fin_x_preferred":[
        "Radisson"
    ],
    "name:fra_x_preferred":[
        "Radisson"
    ],
    "name:ita_x_preferred":[
        "Radisson"
    ],
    "name:nld_x_preferred":[
        "Radisson"
    ],
    "name:pol_x_preferred":[
        "Radisson"
    ],
    "name:rus_x_preferred":[
        "\u0420\u0430\u0434\u0438\u0441\u0441\u043e\u043d"
    ],
    "name:swe_x_preferred":[
        "Radisson"
    ],
    "wof:name":"Radisson",
    "wof:placetype":"locality"
},
  "geometry": {"coordinates":[-74.20461,45.45227],"type":"Point"}
}