{
  "type": "Feature",
  "properties": {
    "gn:admin1_code":"10",
    "gn:admin2_code":"16",
    "gn:admin3_code":"71083.0",
    "gn:asciiname":"Radisson",
    "gn:country_code":"CA",
    "gn:dem":76,
    "gn:feature_class":"P",
    "gn:feature_code":"PPL",
    "gn:name":"Radisson",
    "gn:population":0,
    "gn:timezone":"America/Toronto",
    "iso:country":"CA",
    "wof:name":"Radisson",
    "wof:placetype":"locality"
},
  "geometry": {"coordinates":[-74.20461,45.45227],"type":"Point"}
}