{
  "type": "Feature",
  "properties": {
    "gn:admin1_code":"10",
    "gn:admin2_code":"16",
    "gn:admin3_code":"71083.0",
    "gn:asciiname":"Radisson",
    "gn:country_code":"CA",
    "gn:dem":76,
    "gn:feature_class":"P",
    "gn:feature_code":"PPL",
    "gn:name":"Radisson",
    "gn:population":0,
    "gn:timezone":"America/Toronto",
    "iso:country":"CA",
    "name:ben_x_preferred":[
        "\u09b0"
    ],
    "name:ceb_x_preferred":[
        "Radisson"
    ],
    "name:deu_x_preferred":[
        "Radisson"
    ],
    "name:ell_x_preferred":[
        "\u03a1\u03ac\u03bd\u03c4\u03b9\u03c3\u03bf\u03bd"
    ],
    "name:fin_x_preferred":[
        "Radisson"
    ],
    "name:fra_x_preferred":[
        "Radisson"
    ],
    "name:heb_x_preferred":[
        "\u05e8\u05d3\u05d9\u05e1\u05d5\u05df"
    ],
    "name:hin_x_preferred":[
        "\u0930\u0948\u0921\u0940\u0938\u0928"
    ],
    "name:hun_x_preferred":[
        "Radisson"
    ],
    "name:ind_x_preferred":[
        "Radisson"
    ],
    "name:ita_x_preferred":[
        "Radisson"
    ],
    "name:kor_x_preferred":[
        "\ub798\ub514\uc2a8"
    ],
    "name:nld_x_preferred":[
        "Radisson"
    ],
    "name:pol_x_preferred":[
        "Radisson"
    ],
    "name:rus_x_preferred":[
        "\u0420\u0430\u0434\u0438\u0441\u0441\u043e\u043d"
    ],
    "name:spa_x_preferred":[
        "Radisson"
    ],
    "name:swe_x_preferred":[
        "Radisson"
    ],
    "name:tur_x_preferred":[
        "Radisson"
    ],
    "name:ukr_x_preferred":[
        "\u0420\u0435\u0434\u0456\u0441\u0441\u043e\u043d"
    ],
    "name:urd_x_preferred":[
        "\u0631\u06cc\u0688\u06cc\u0633\u0646"
    ],
    "name:vie_x_preferred":[
        "Radisson"
    ],
    "name:zho_cn_x_preferred":[
        "\u62c9\u8fea\u68ee"
    ],
    "name:zho_tw_x_preferred":[
        "\u96f7\u8fea\u68ee"
    ],
    "wof:name":"Radisson",
    "wof:placetype":"locality"
},
  "geometry": {"coordinates":[-74.20461,45.45227],"type":"Point"}
}