{
  "type": "Feature",
  "properties": {
    "gn:admin1_code":"8",
    "gn:asciiname":"Glendale Beach",
    "gn:country_code":"CA",
    "gn:dem":200,
    "gn:feature_class":"P",
    "gn:feature_code":"PPL",
    "gn:name":"Glendale Beach",
    "gn:population":0,
    "gn:timezone":"America/Toronto",
    "iso:country":"CA",
    "wof:name":"Glendale Beach",
    "wof:placetype":"locality"
},
  "geometry": {"coordinates":[-82.0688,43.12961],"type":"Point"}
}