{
  "type": "Feature",
  "properties": {
    "iso:country":"CA",
    "name:ceb_x_preferred":[
        "Hatchet Lake"
    ],
    "name:eng_x_preferred":[
        "Hatchet Lake"
    ],
    "name:swe_x_preferred":[
        "Hatchet Lake"
    ],
    "qs:name":"Hatchet Lake",
    "qs:name_adm0":"Canada",
    "qs:name_adm1":"Nova Scotia",
    "qs:photos":35,
    "qs:photos_1k":7,
    "qs:photos_9k":1,
    "qs:photos_9r":2,
    "qs:photos_all":35,
    "qs:photos_sr":2,
    "qs:placetype":"Town",
    "qs:pop_sr":"0",
    "wd:wordcount":85,
    "wof:name":"Hatchet Lake",
    "wof:placetype":"locality"
},
  "geometry": {"coordinates":[-63.717913,44.568019],"type":"Point"}
}