{
  "type": "Feature",
  "properties": {
    "gn:admin1_code":"7",
    "gn:asciiname":"Hartville",
    "gn:country_code":"CA",
    "gn:dem":58,
    "gn:feature_class":"P",
    "gn:feature_code":"PPL",
    "gn:name":"Hartville",
    "gn:population":0,
    "gn:timezone":"America/Halifax",
    "iso:country":"CA",
    "name:cat_x_preferred":[
        "Hartville"
    ],
    "name:ceb_x_preferred":[
        "Hartville"
    ],
    "name:deu_x_preferred":[
        "Hartville"
    ],
    "name:fra_x_preferred":[
        "Hartville"
    ],
    "name:ita_x_preferred":[
        "Hartville"
    ],
    "name:nld_x_preferred":[
        "Hartville"
    ],
    "name:pol_x_preferred":[
        "Hartville"
    ],
    "name:por_x_preferred":[
        "Hartville"
    ],
    "name:rus_x_preferred":[
        "\u0425\u0430\u0440\u0442\u0432\u0438\u043b\u043b"
    ],
    "name:srp_x_preferred":[
        "\u0425\u0430\u0440\u0442\u0432\u0438\u043b"
    ],
    "name:swe_x_preferred":[
        "Hartville"
    ],
    "name:vol_x_preferred":[
        "Hartville"
    ],
    "wof:name":"Hartville",
    "wof:placetype":"locality"
},
  "geometry": {"coordinates":[-64.02321999999999,44.94711],"type":"Point"}
}