{
  "type": "Feature",
  "properties": {
    "gn:admin1_code":"8",
    "gn:asciiname":"Sulphide",
    "gn:country_code":"CA",
    "gn:dem":155,
    "gn:feature_class":"P",
    "gn:feature_code":"PPL",
    "gn:name":"Sulphide",
    "gn:population":0,
    "gn:timezone":"America/Toronto",
    "iso:country":"CA",
    "wof:name":"Sulphide",
    "wof:placetype":"locality"
},
  "geometry": {"coordinates":[-77.23276,44.51682],"type":"Point"}
}