{
  "type": "Feature",
  "properties": {
    "gn:admin1_code":"8.0",
    "gn:asciiname":"Cowan's Bay",
    "gn:country_code":"CA",
    "gn:dem":256,
    "gn:feature_class":"P",
    "gn:feature_code":"PPL",
    "gn:name":"Cowan's Bay",
    "gn:population":0,
    "gn:timezone":"America/Toronto",
    "iso:country":"CA",
    "wof:name":"Cowan's Bay",
    "wof:placetype":"locality"
},
  "geometry": {"coordinates":[-78.54333000000003,44.33583],"type":"Point"}
}