{
  "type": "Feature",
  "properties": {
    "gn:admin1_code":"3",
    "gn:asciiname":"Sidney",
    "gn:country_code":"CA",
    "gn:dem":377,
    "gn:feature_class":"P",
    "gn:feature_code":"PPL",
    "gn:name":"Sidney",
    "gn:population":0,
    "gn:timezone":"America/Winnipeg",
    "iso:country":"CA",
    "name:ben_x_preferred":[
        "\u09b8\u09bf\u09a1\u09a8\u09bf"
    ],
    "name:ell_x_preferred":[
        "\u03a3\u03af\u03bd\u03c4\u03bd\u03b5\u03ca"
    ],
    "name:heb_x_preferred":[
        "\u05e1\u05d9\u05d3\u05e0\u05d9"
    ],
    "name:hin_x_preferred":[
        "\u0938\u093f\u0921\u0928\u0940"
    ],
    "name:ind_x_preferred":[
        "Sidney"
    ],
    "name:ita_x_preferred":[
        "Sidney"
    ],
    "name:kor_x_preferred":[
        "\uc2dc\ub4dc\ub2c8"
    ],
    "name:rus_x_preferred":[
        "\u0421\u0438\u0434\u043d\u0435\u0439"
    ],
    "name:tur_x_preferred":[
        "Sidney"
    ],
    "name:urd_x_preferred":[
        "\u0633\u0688\u0646\u06cc"
    ],
    "name:vie_x_preferred":[
        "Sidney"
    ],
    "name:zho_cn_x_preferred":[
        "\u6089\u5c3c"
    ],
    "name:zho_tw_x_preferred":[
        "\u6089\u5c3c"
    ],
    "wof:name":"Sidney",
    "wof:placetype":"locality"
},
  "geometry": {"coordinates":[-99.07969,49.90003],"type":"Point"}
}