{
  "type": "Feature",
  "properties": {
    "gn:admin1_code":"7.0",
    "gn:asciiname":"Cornwallis Square",
    "gn:country_code":"CA",
    "gn:dem":27,
    "gn:feature_class":"P",
    "gn:feature_code":"PPL",
    "gn:name":"Cornwallis Square",
    "gn:population":0,
    "gn:timezone":"America/Halifax",
    "iso:country":"CA",
    "wof:name":"Cornwallis Square",
    "wof:placetype":"locality"
},
  "geometry": {"coordinates":[-64.66547,45.08345],"type":"Point"}
}