{
  "type": "Feature",
  "properties": {
    "gn:admin1_code":"7.0",
    "gn:asciiname":"Black Rock",
    "gn:country_code":"CA",
    "gn:dem":11,
    "gn:feature_class":"P",
    "gn:feature_code":"PPL",
    "gn:name":"Black Rock",
    "gn:population":0,
    "gn:timezone":"America/Halifax",
    "iso:country":"CA",
    "wof:name":"Black Rock",
    "wof:placetype":"locality"
},
  "geometry": {"coordinates":[-64.76089,45.17001],"type":"Point"}
}