{
  "type": "Feature",
  "properties": {
    "gn:admin1_code":"7.0",
    "gn:asciiname":"Black Rock",
    "gn:country_code":"CA",
    "gn:dem":11,
    "gn:feature_class":"P",
    "gn:feature_code":"PPL",
    "gn:name":"Black Rock",
    "gn:population":0,
    "gn:timezone":"America/Halifax",
    "iso:country":"CA",
    "name:ceb_x_preferred":[
        "Black Rock"
    ],
    "name:deu_x_preferred":[
        "Black Rock"
    ],
    "name:fas_x_preferred":[
        "\u0628\u0644\u06a9 \u0631\u0627\u06a9"
    ],
    "name:fra_x_preferred":[
        "Black Rock"
    ],
    "name:ita_x_preferred":[
        "Black Rock"
    ],
    "name:kor_x_preferred":[
        "\ube14\ub799\ub85d"
    ],
    "name:nld_x_preferred":[
        "Black Rock"
    ],
    "name:pol_x_preferred":[
        "Black Rock"
    ],
    "name:por_x_preferred":[
        "Black Rock"
    ],
    "name:rus_x_preferred":[
        "\u0411\u043b\u044d\u043a-\u0420\u043e\u043a"
    ],
    "name:spa_x_preferred":[
        "Black Rock"
    ],
    "name:srp_x_preferred":[
        "\u0411\u043b\u0435\u043a \u0420\u043e\u043a"
    ],
    "name:swe_x_preferred":[
        "Black Rock"
    ],
    "name:ukr_x_preferred":[
        "\u0411\u043b\u0435\u043a-\u0420\u043e\u043a"
    ],
    "name:vol_x_preferred":[
        "Black Rock"
    ],
    "wof:name":"Black Rock",
    "wof:placetype":"locality"
},
  "geometry": {"coordinates":[-64.76089,45.17001],"type":"Point"}
}