{
  "type": "Feature",
  "properties": {
    "iso:country":"CA",
    "name:deu_x_preferred":[
        "Les Boules"
    ],
    "name:eng_x_preferred":[
        "Les Boules"
    ],
    "name:fra_x_preferred":[
        "Les Boules"
    ],
    "name:ita_x_preferred":[
        "Les Boules"
    ],
    "qs_pg:aaroncc":"CA",
    "qs_pg:name":"Les Boules",
    "qs_pg:name_adm0":"Canada",
    "qs_pg:name_adm1":"Qu\u00e9bec",
    "qs_pg:photos":14,
    "qs_pg:photos_1k":3,
    "qs_pg:photos_9k":1,
    "qs_pg:photos_9r":1,
    "qs_pg:photos_all":14,
    "qs_pg:photos_sr":1,
    "qs_pg:pop_sr":0,
    "qs_pg:qs_pg_placetype":"locality",
    "qs_pg:qs_pg_placetype_gp":"Town",
    "qs_pg:woe_adm0":23424775,
    "woe:adm0_id":23424775,
    "woe:name_adm0":"Canada",
    "woe:name_adm1":"Qu\u00e9bec",
    "woe:placetype":"Town",
    "wof:name":"Les Boules",
    "wof:placetype":"locality"
},
  "geometry": {"coordinates":[-67.920742,48.677077],"type":"Point"}
}