{
  "type": "Feature",
  "properties": {
    "iso:country":"CA",
    "name:ceb_x_preferred":[
        "Eagle Hills"
    ],
    "name:eng_x_preferred":[
        "Eagle Hills"
    ],
    "qs:gn_adm0_cc":"CA",
    "qs:gn_local":6173577,
    "qs:gn_nam_loc":"vaughan",
    "qs:gn_namadm1":"08",
    "qs:local_max":1426,
    "qs:local_sum":6970,
    "qs:localhoods":22,
    "qs:name":"Eagle Hills",
    "qs:name_adm0":"Canada",
    "qs:name_adm1":"Ontario",
    "qs:name_adm2":"York",
    "qs:name_local":"Vaughan",
    "qs:photo_max":45,
    "qs:photo_sum":105,
    "qs:placetype":"Suburb",
    "qs:quad_count":20,
    "qs:woe_adm0":23424775,
    "qs:woe_adm1":2344922,
    "qs:woe_adm2":29375112,
    "qs:woe_funk":"Parented by a neighborhood",
    "qs:woe_lau":0,
    "qs:woe_local":23396899,
    "qs:woe_ver":"7.10.0",
    "wd:wordcount":44,
    "wof:lang":[
        "eng"
    ],
    "wof:name":"Eagle Hills",
    "wof:placetype":"neighbourhood"
},
  "geometry": {"coordinates":[-79.508634,43.851365],"type":"Point"}
}