{
  "type": "Feature",
  "properties": {
    "gn:admin1_code":"4",
    "gn:asciiname":"Thomaston Corner",
    "gn:country_code":"CA",
    "gn:dem":123,
    "gn:feature_class":"P",
    "gn:feature_code":"PPL",
    "gn:name":"Thomaston Corner",
    "gn:population":0,
    "gn:timezone":"America/Moncton",
    "iso:country":"CA",
    "wof:name":"Thomaston Corner",
    "wof:placetype":"locality"
},
  "geometry": {"coordinates":[-67.13198,45.65522],"type":"Point"}
}