{
  "type": "Feature",
  "properties": {
    "gn:admin1_code":"4",
    "gn:asciiname":"Five Fathom Hole",
    "gn:country_code":"CA",
    "gn:dem":32,
    "gn:feature_class":"P",
    "gn:feature_code":"PPL",
    "gn:name":"Five Fathom Hole",
    "gn:population":0,
    "gn:timezone":"America/Moncton",
    "iso:country":"CA",
    "wof:name":"Five Fathom Hole",
    "wof:placetype":"locality"
},
  "geometry": {"coordinates":[-66.25539000000001,45.18984],"type":"Point"}
}