{
  "type": "Feature",
  "properties": {
    "gn:admin1_code":"9",
    "gn:asciiname":"Glenfinnan",
    "gn:country_code":"CA",
    "gn:dem":6,
    "gn:feature_class":"P",
    "gn:feature_code":"PPLL",
    "gn:name":"Glenfinnan",
    "gn:population":0,
    "gn:timezone":"America/Halifax",
    "iso:country":"CA",
    "name:azb_x_preferred":[
        "\u0642\u0644\u0646\u0641\u06cc\u0646\u0627\u0646"
    ],
    "name:deu_x_preferred":[
        "Glenfinnan"
    ],
    "name:eus_x_preferred":[
        "Glenfinnan"
    ],
    "name:fas_x_preferred":[
        "\u06af\u0644\u0646\u0641\u06cc\u0646\u0627\u0646"
    ],
    "name:fra_x_preferred":[
        "Glenfinnan"
    ],
    "name:gla_x_preferred":[
        "Gleann Fhionnainn"
    ],
    "name:gle_x_preferred":[
        "Gleann Fhionnainn"
    ],
    "name:ita_x_preferred":[
        "Glenfinnan"
    ],
    "name:kaz_x_preferred":[
        "\u0413\u043b\u0435\u043d\u0444\u0438\u043d\u043d\u0430\u043d"
    ],
    "name:nld_x_preferred":[
        "Glenfinnan"
    ],
    "name:pol_x_preferred":[
        "Glenfinnan"
    ],
    "name:rus_x_preferred":[
        "\u0413\u043b\u0435\u043d\u0444\u0438\u043d\u043d\u0430\u043d"
    ],
    "name:swe_x_preferred":[
        "Glenfinnan"
    ],
    "wof:name":"Glenfinnan",
    "wof:placetype":"locality"
},
  "geometry": {"coordinates":[-62.98198000000001,46.28341],"type":"Point"}
}