{
  "type": "Feature",
  "properties": {
    "gn:admin1_code":"9",
    "gn:asciiname":"Glenfinnan",
    "gn:country_code":"CA",
    "gn:dem":6,
    "gn:feature_class":"P",
    "gn:feature_code":"PPLL",
    "gn:name":"Glenfinnan",
    "gn:population":0,
    "gn:timezone":"America/Halifax",
    "iso:country":"CA",
    "wof:name":"Glenfinnan",
    "wof:placetype":"locality"
},
  "geometry": {"coordinates":[-62.98198000000001,46.28341],"type":"Point"}
}