{
  "type": "Feature",
  "properties": {
    "gn:admin1_code":"5",
    "gn:asciiname":"Tompkins",
    "gn:country_code":"CA",
    "gn:dem":16,
    "gn:feature_class":"P",
    "gn:feature_code":"PPL",
    "gn:name":"Tompkins",
    "gn:population":0,
    "gn:timezone":"America/St_Johns",
    "iso:country":"CA",
    "name:fra_x_preferred":[
        "Tompkins"
    ],
    "wof:name":"Tompkins",
    "wof:placetype":"locality"
},
  "geometry": {"coordinates":[-59.21528000000001,47.80001],"type":"Point"}
}