{
  "type": "Feature",
  "properties": {
    "gn:admin1_code":"8",
    "gn:asciiname":"Glenvale",
    "gn:country_code":"CA",
    "gn:dem":287,
    "gn:feature_class":"P",
    "gn:feature_code":"PPL",
    "gn:name":"Glenvale",
    "gn:population":0,
    "gn:timezone":"America/Toronto",
    "iso:country":"CA",
    "wof:name":"Glenvale",
    "wof:placetype":"locality"
},
  "geometry": {"coordinates":[-80.16056,47.87111],"type":"Point"}
}