{
  "type": "Feature",
  "properties": {
    "gn:country":"CA",
    "iso:country":"CA",
    "name:bre_x_preferred":[
        "Leading Tickles"
    ],
    "name:ceb_x_preferred":[
        "Leading Tickles"
    ],
    "name:cos_x_preferred":[
        "Leading Tickles"
    ],
    "name:dan_x_preferred":[
        "Leading Tickles"
    ],
    "name:deu_x_preferred":[
        "Leading Tickles"
    ],
    "name:eng_x_preferred":[
        "Leading Tickles"
    ],
    "name:fra_x_preferred":[
        "Leading Tickles"
    ],
    "name:ind_x_preferred":[
        "Leading Tickles"
    ],
    "name:ita_x_preferred":[
        "Leading Tickles"
    ],
    "name:nds_x_preferred":[
        "Leading Tickles"
    ],
    "name:nld_x_preferred":[
        "Leading Tickles"
    ],
    "name:por_x_preferred":[
        "Leading Tickles"
    ],
    "name:ron_x_preferred":[
        "Leading Tickles"
    ],
    "name:spa_x_preferred":[
        "Leading Tickles"
    ],
    "name:swe_x_preferred":[
        "Leading Tickles"
    ],
    "name:tah_x_preferred":[
        "Leading Tickles"
    ],
    "qs:name":"Leading Tickles",
    "qs:name_adm0":"Canada",
    "qs:name_adm1":"Newfoundland and Labrador",
    "qs:photos":75,
    "qs:photos_1k":15,
    "qs:photos_9k":1,
    "qs:photos_9r":2,
    "qs:photos_all":75,
    "qs:photos_sr":2,
    "qs:placetype":"Town",
    "qs:pop_sr":"0",
    "wd:wordcount":89,
    "wof:name":"Leading Tickles",
    "wof:placetype":"locality"
},
  "geometry": {"coordinates":[-55.448856,49.510609],"type":"Point"}
}