{
  "type": "Feature",
  "properties": {
    "gn:admin1_code":"3",
    "gn:asciiname":"Less Crossing",
    "gn:country_code":"CA",
    "gn:dem":233,
    "gn:feature_class":"P",
    "gn:feature_code":"PPLL",
    "gn:name":"Less Crossing",
    "gn:population":0,
    "gn:timezone":"America/Winnipeg",
    "iso:country":"CA",
    "wof:name":"Less Crossing",
    "wof:placetype":"locality"
},
  "geometry": {"coordinates":[-96.99593,50.0614],"type":"Point"}
}