{
  "type": "Feature",
  "properties": {
    "gn:country":"CA",
    "gn:fcode":"PPL",
    "gn:pop":0,
    "iso:country":"CA",
    "name:eng_x_preferred":[
        "Carseland"
    ],
    "name:fre_x_preferred":[
        "Carseland"
    ],
    "qs:name":"Carseland",
    "qs:name_adm0":"Canada",
    "qs:name_adm1":"Alberta",
    "qs:photos":58,
    "qs:photos_1k":12,
    "qs:photos_9k":1,
    "qs:photos_9r":2,
    "qs:photos_all":58,
    "qs:photos_sr":2,
    "qs:placetype":"Town",
    "qs:pop_sr":"5",
    "wd:wordcount":480,
    "wof:name":"Carseland",
    "wof:placetype":"locality",
    "wof:population":0
},
  "geometry": {"coordinates":[-113.46474000000001,50.84801],"type":"Point"}
}