{
  "type": "Feature",
  "properties": {
    "gn:admin1_code":"7",
    "gn:asciiname":"Harrington",
    "gn:country_code":"CA",
    "gn:dem":29,
    "gn:feature_class":"P",
    "gn:feature_code":"PPL",
    "gn:name":"Harrington",
    "gn:population":0,
    "gn:timezone":"America/Halifax",
    "iso:country":"CA",
    "name:amh_x_preferred":[
        "\u1200\u122a\u1295\u130d\u1270\u1295"
    ],
    "name:bul_x_preferred":[
        "\u0425\u0430\u0440\u0438\u043d\u0433\u0442\u044a\u043d"
    ],
    "name:cat_x_preferred":[
        "Harrington"
    ],
    "name:ceb_x_preferred":[
        "Harrington"
    ],
    "name:ces_x_preferred":[
        "Harrington"
    ],
    "name:deu_x_preferred":[
        "Harrington"
    ],
    "name:fra_x_preferred":[
        "Harrington"
    ],
    "name:heb_x_preferred":[
        "\u05d4\u05e8\u05d9\u05e0\u05d2\u05d8\u05d5\u05df"
    ],
    "name:ita_x_preferred":[
        "Harrington"
    ],
    "name:jpn_x_preferred":[
        "\u30cf\u30ea\u30f3\u30c8\u30f3"
    ],
    "name:kor_x_preferred":[
        "\ud574\ub9c1\ud134"
    ],
    "name:lav_x_preferred":[
        "Heringtons"
    ],
    "name:nld_x_preferred":[
        "Harrington"
    ],
    "name:pol_x_preferred":[
        "Harrington"
    ],
    "name:por_x_preferred":[
        "Harrington"
    ],
    "name:rus_x_preferred":[
        "\u0425\u0430\u0440\u0440\u0438\u043d\u0433\u0442\u043e\u043d"
    ],
    "name:slk_x_preferred":[
        "Harrington"
    ],
    "name:spa_x_preferred":[
        "Harrington"
    ],
    "name:srp_x_preferred":[
        "\u0425\u0435\u0440\u0438\u043d\u0433\u0442\u043e\u043d"
    ],
    "name:swe_x_preferred":[
        "Harrington"
    ],
    "name:ukr_x_preferred":[
        "\u0413\u0430\u0440\u0440\u0456\u043d\u0433\u0442\u043e\u043d"
    ],
    "name:vol_x_preferred":[
        "Harrington"
    ],
    "wof:name":"Harrington",
    "wof:placetype":"locality"
},
  "geometry": {"coordinates":[-66.07304999999999,44.09407],"type":"Point"}
}