{
  "type": "Feature",
  "properties": {
    "gn:admin1_code":"7",
    "gn:asciiname":"Harrington",
    "gn:country_code":"CA",
    "gn:dem":29,
    "gn:feature_class":"P",
    "gn:feature_code":"PPL",
    "gn:name":"Harrington",
    "gn:population":0,
    "gn:timezone":"America/Halifax",
    "iso:country":"CA",
    "wof:name":"Harrington",
    "wof:placetype":"locality"
},
  "geometry": {"coordinates":[-66.07304999999999,44.09407],"type":"Point"}
}