{
  "type": "Feature",
  "properties": {
    "gn:admin1_code":"2",
    "gn:admin2_code":"5924.0",
    "gn:asciiname":"Shelter Point",
    "gn:country_code":"CA",
    "gn:dem":9,
    "gn:feature_class":"P",
    "gn:feature_code":"PPL",
    "gn:name":"Shelter Point",
    "gn:population":0,
    "gn:timezone":"America/Vancouver",
    "iso:country":"CA",
    "wof:name":"Shelter Point",
    "wof:placetype":"locality"
},
  "geometry": {"coordinates":[-125.18545,49.93063],"type":"Point"}
}