{
  "type": "Feature",
  "properties": {
    "gn:admin1_code":"1",
    "gn:asciiname":"Lone Pine",
    "gn:country_code":"CA",
    "gn:dem":732,
    "gn:feature_class":"P",
    "gn:feature_code":"PPLL",
    "gn:name":"Lone Pine",
    "gn:population":0,
    "gn:timezone":"America/Edmonton",
    "iso:country":"CA",
    "name:deu_x_preferred":[
        "Lone Pine"
    ],
    "name:pol_x_preferred":[
        "Lone Pine"
    ],
    "wof:name":"Lone Pine",
    "wof:placetype":"locality"
},
  "geometry": {"coordinates":[-115.11891,54.30014],"type":"Point"}
}