{
  "type": "Feature",
  "properties": {
    "iso:country":"CA",
    "name:ara_x_preferred":[
        "\u0633\u062a\u0627\u0631\u0628\u0648\u0643"
    ],
    "name:ben_x_preferred":[
        "\u09b8\u09cd\u099f\u09be\u09b0\u09ac\u09be\u0995"
    ],
    "name:deu_x_preferred":[
        "Starbuck"
    ],
    "name:ell_x_preferred":[
        "\u03a3\u03c4\u03ac\u03bc\u03c0\u03b1\u03ba"
    ],
    "name:eng_x_preferred":[
        "Starbuck Island"
    ],
    "name:eng_x_variant":[
        "Starbuck"
    ],
    "name:fas_x_preferred":[
        "\u0627\u0633\u062a\u0627\u0631\u0628\u0627\u06a9"
    ],
    "name:fra_x_preferred":[
        "Starbuck"
    ],
    "name:heb_x_preferred":[
        "\u05d4\u05d0\u05d9 \u05e1\u05d8\u05d0\u05e8\u05d1\u05d0\u05e7"
    ],
    "name:hin_x_preferred":[
        "\u0938\u094d\u091f\u093e\u0930\u092c\u0915 "
    ],
    "name:hun_x_preferred":[
        "Starbuck"
    ],
    "name:ind_x_preferred":[
        "Starbuck"
    ],
    "name:ita_x_preferred":[
        "Starbuck"
    ],
    "name:jpn_x_preferred":[
        "\u30b9\u30bf\u30fc\u30d0\u30c3\u30af\u5cf6"
    ],
    "name:jpn_x_variant":[
        "\u30b9\u30bf\u30fc\u30d0\u30c3\u30af"
    ],
    "name:kor_x_preferred":[
        "\uc2a4\ud0c0\ubc85"
    ],
    "name:nld_x_preferred":[
        "Starbuck"
    ],
    "name:pol_x_preferred":[
        "Starbuck"
    ],
    "name:por_x_preferred":[
        "Starbuck"
    ],
    "name:rus_x_preferred":[
        "\u041e\u0441\u0442\u0440\u043e\u0432 \u0421\u0442\u0430\u0440\u0431\u0430\u043a"
    ],
    "name:spa_x_preferred":[
        "Isla Starbuck"
    ],
    "name:swe_x_preferred":[
        "Starbuck Island"
    ],
    "name:tur_x_preferred":[
        "Starbuck"
    ],
    "name:ukr_x_preferred":[
        "\u0421\u0442\u0430\u0440\u0431\u0430\u043a"
    ],
    "name:urd_x_preferred":[
        "\u0627\u0633\u0679\u0627\u0631\u0628\u06a9"
    ],
    "name:vie_x_preferred":[
        "\u0110\u1ea3o Starbuck"
    ],
    "name:zho_cn_x_preferred":[
        "\u65af\u5854\u5df4\u514b\u5c9b"
    ],
    "name:zho_tw_x_preferred":[
        "\u65af\u5854\u5df4\u514b\u5cf6"
    ],
    "qs_pg:aaroncc":"CA",
    "qs_pg:name":"Starbuck",
    "qs_pg:name_adm0":"Canada",
    "qs_pg:name_adm1":"Manitoba",
    "qs_pg:photos":37,
    "qs_pg:photos_1k":7,
    "qs_pg:photos_9k":1,
    "qs_pg:photos_9r":2,
    "qs_pg:photos_all":37,
    "qs_pg:photos_sr":2,
    "qs_pg:pop_sr":0,
    "qs_pg:qs_pg_placetype":"locality",
    "qs_pg:qs_pg_placetype_gp":"Town",
    "qs_pg:woe_adm0":23424775,
    "woe:adm0_id":23424775,
    "woe:name_adm0":"Canada",
    "woe:name_adm1":"Manitoba",
    "woe:placetype":"Town",
    "wof:name":"Starbuck",
    "wof:placetype":"locality"
},
  "geometry": {"coordinates":[-97.61901,49.768871],"type":"Point"}
}