{
  "type": "Feature",
  "properties": {
    "gn:admin1_code":"8.0",
    "gn:asciiname":"Cedar Valley",
    "gn:country_code":"CA",
    "gn:dem":276,
    "gn:feature_class":"P",
    "gn:feature_code":"PPL",
    "gn:name":"Cedar Valley",
    "gn:population":0,
    "gn:timezone":"America/Toronto",
    "iso:country":"CA",
    "name:ceb_x_preferred":[
        "Cedar Valley"
    ],
    "name:deu_x_preferred":[
        "Cedar Valley"
    ],
    "name:pol_x_preferred":[
        "Cedar Valley"
    ],
    "wof:name":"Cedar Valley",
    "wof:placetype":"locality"
},
  "geometry": {"coordinates":[-79.34304,44.08595],"type":"Point"}
}