{
  "type": "Feature",
  "properties": {
    "gn:admin1_code":"8",
    "gn:asciiname":"Picnic Grove",
    "gn:country_code":"CA",
    "gn:dem":56,
    "gn:feature_class":"P",
    "gn:feature_code":"PPL",
    "gn:name":"Picnic Grove",
    "gn:population":0,
    "gn:timezone":"America/Toronto",
    "iso:country":"CA",
    "wof:name":"Picnic Grove",
    "wof:placetype":"locality"
},
  "geometry": {"coordinates":[-74.46935999999999,45.19128],"type":"Point"}
}