{
  "type": "Feature",
  "properties": {
    "gn:admin1_code":"11",
    "gn:asciiname":"Mantario",
    "gn:country_code":"CA",
    "gn:dem":685,
    "gn:feature_class":"P",
    "gn:feature_code":"PPL",
    "gn:name":"Mantario",
    "gn:population":0,
    "gn:timezone":"America/Regina",
    "iso:country":"CA",
    "wof:name":"Mantario",
    "wof:placetype":"locality"
},
  "geometry": {"coordinates":[-109.70155,51.26681],"type":"Point"}
}