{
  "type": "Feature",
  "properties": {
    "iso:country":"CA",
    "name:eng_x_preferred":[
        "The Bowl"
    ],
    "qs:gn_adm0_cc":"CA",
    "qs:gn_local":6113365,
    "qs:gn_nam_loc":"prince george",
    "qs:gn_namadm1":"02",
    "qs:local_max":391,
    "qs:local_sum":2115,
    "qs:localhoods":13,
    "qs:name":"The Bowl",
    "qs:name_adm0":"Canada",
    "qs:name_adm1":"British Columbia",
    "qs:name_adm2":"Fraser-Fort George",
    "qs:name_local":"Prince George",
    "qs:photo_max":55,
    "qs:photo_sum":149,
    "qs:placetype":"Suburb",
    "qs:quad_count":19,
    "qs:woe_adm0":23424775,
    "qs:woe_adm1":2344916,
    "qs:woe_adm2":29375235,
    "qs:woe_funk":"Grouping neighborhood",
    "qs:woe_lau":0,
    "qs:woe_local":9537,
    "qs:woe_ver":"7.10.0",
    "wof:lang":[
        "eng"
    ],
    "wof:name":"The Bowl",
    "wof:placetype":"neighbourhood"
},
  "geometry": {"coordinates":[-122.77449799999999,53.906486],"type":"Point"}
}