{
  "type": "Feature",
  "properties": {
    "gn:admin1_code":"8.0",
    "gn:asciiname":"Cashions Glen",
    "gn:country_code":"CA",
    "gn:dem":68,
    "gn:feature_class":"P",
    "gn:feature_code":"PPL",
    "gn:name":"Cashions Glen",
    "gn:population":0,
    "gn:timezone":"America/Toronto",
    "iso:country":"CA",
    "wof:name":"Cashions Glen",
    "wof:placetype":"locality"
},
  "geometry": {"coordinates":[-74.68541999999999,45.10317],"type":"Point"}
}