{
  "type": "Feature",
  "properties": {
    "gn:admin1_code":"8",
    "gn:asciiname":"Gores Landing",
    "gn:country_code":"CA",
    "gn:dem":205,
    "gn:feature_class":"P",
    "gn:feature_code":"PPL",
    "gn:name":"Gores Landing",
    "gn:population":0,
    "gn:timezone":"America/Toronto",
    "iso:country":"CA",
    "wof:name":"Gores Landing",
    "wof:placetype":"locality"
},
  "geometry": {"coordinates":[-78.23278000000001,44.11861],"type":"Point"}
}