{
  "type": "Feature",
  "properties": {
    "gn:gn_country":"CA",
    "gn:gn_fcode":"PPL",
    "gn:gn_pop":0,
    "iso:country":"CA",
    "name:dut_x_preferred":[
        "Yarrow"
    ],
    "name:eng_x_preferred":[
        "Yarrow"
    ],
    "name:fre_x_preferred":[
        "Yarrow"
    ],
    "name:urd_x_preferred":[
        "\u06cc\u0627\u0631\u0631\u0648\u0648\u060c \u0628\u0631\u0679\u0634 \u06a9\u0648\u0644\u0645\u0628\u06cc\u0627"
    ],
    "qs_pg:aaroncc":"CA",
    "qs_pg:gn_country":"CA",
    "qs_pg:gn_fcode":"PPL",
    "qs_pg:gn_pop":0,
    "qs_pg:name":"Yarrow",
    "qs_pg:name_adm0":"Canada",
    "qs_pg:name_adm1":"British Columbia",
    "qs_pg:photos_9r":0,
    "qs_pg:photos_sr":0,
    "qs_pg:pop_sr":0,
    "qs_pg:qs_pg_placetype":"locality",
    "qs_pg:qs_pg_placetype_gp":"Town",
    "qs_pg:woe_adm0":23424775,
    "woe:adm0_id":23424775,
    "woe:name_adm0":"Canada",
    "woe:name_adm1":"British Columbia",
    "woe:placetype":"Town",
    "wof:name":"Yarrow",
    "wof:placetype":"locality"
},
  "geometry": {"coordinates":[-122.05034000000001,49.08207],"type":"Point"}
}