{
  "type": "Feature",
  "properties": {
    "gn:admin1_code":"4.0",
    "gn:asciiname":"Bright",
    "gn:country_code":"CA",
    "gn:dem":145,
    "gn:feature_class":"P",
    "gn:feature_code":"PPLL",
    "gn:name":"Bright",
    "gn:population":0,
    "gn:timezone":"America/Moncton",
    "iso:country":"CA",
    "wof:name":"Bright",
    "wof:placetype":"locality"
},
  "geometry": {"coordinates":[-67.09694,46.17888],"type":"Point"}
}