{
  "type": "Feature",
  "properties": {
    "gn:admin1_code":"4",
    "gn:asciiname":"Hamtown Corner",
    "gn:country_code":"CA",
    "gn:dem":252,
    "gn:feature_class":"P",
    "gn:feature_code":"PPL",
    "gn:name":"Hamtown Corner",
    "gn:population":0,
    "gn:timezone":"America/Moncton",
    "iso:country":"CA",
    "wof:name":"Hamtown Corner",
    "wof:placetype":"locality"
},
  "geometry": {"coordinates":[-66.77473000000001,46.12032],"type":"Point"}
}