{
  "type": "Feature",
  "properties": {
    "gn:admin1_code":"11.0",
    "gn:asciiname":"Adanac",
    "gn:country_code":"CA",
    "gn:dem":647,
    "gn:feature_class":"P",
    "gn:feature_code":"PPL",
    "gn:name":"Adanac",
    "gn:population":0,
    "gn:timezone":"America/Regina",
    "iso:country":"CA",
    "name:fas_x_preferred":[
        "\u0627\u062f\u0627\u0646\u0627\u06a9"
    ],
    "wof:name":"Adanac",
    "wof:placetype":"locality"
},
  "geometry": {"coordinates":[-109.05628,52.45285],"type":"Point"}
}