{
  "type": "Feature",
  "properties": {
    "gn:admin1_code":"11.0",
    "gn:asciiname":"Windsor Park",
    "gn:country_code":"CA",
    "gn:dem":546,
    "gn:feature_class":"P",
    "gn:feature_code":"PPL",
    "gn:name":"Windsor Park",
    "gn:population":0,
    "gn:timezone":"America/Regina",
    "iso:country":"CA",
    "name:ara_x_preferred":[
        "\u0648\u064a\u0646\u062f\u0633\u0648\u0631 \u0628\u0627\u0631\u0643"
    ],
    "name:bar_x_preferred":[
        "Windsor Park"
    ],
    "name:bul_x_preferred":[
        "\u0423\u0438\u043d\u0434\u0437\u044a\u0440 \u041f\u0430\u0440\u043a"
    ],
    "name:deu_x_preferred":[
        "Windsor Park"
    ],
    "name:est_x_preferred":[
        "Windsor Park"
    ],
    "name:eus_x_preferred":[
        "Windsor Park"
    ],
    "name:fin_x_preferred":[
        "Windsor Park"
    ],
    "name:fra_x_preferred":[
        "Windsor Park"
    ],
    "name:heb_x_preferred":[
        "\u05d5\u05d9\u05e0\u05d3\u05d6\u05d5\u05e8 \u05e4\u05d0\u05e8\u05e7"
    ],
    "name:hun_x_preferred":[
        "Windsor Park"
    ],
    "name:ind_x_preferred":[
        "Windsor Park"
    ],
    "name:ita_x_preferred":[
        "Windsor Park"
    ],
    "name:jpn_x_preferred":[
        "\u30a6\u30a3\u30f3\u30b6\u30fc\u30fb\u30d1\u30fc\u30af"
    ],
    "name:kor_x_preferred":[
        "\uc708\uc800 \ud30c\ud06c"
    ],
    "name:nld_x_preferred":[
        "Windsor Park"
    ],
    "name:nor_x_preferred":[
        "Windsor Park"
    ],
    "name:pol_x_preferred":[
        "Windsor Park"
    ],
    "name:por_x_preferred":[
        "Windsor Park"
    ],
    "name:ron_x_preferred":[
        "Windsor Park"
    ],
    "name:rus_x_preferred":[
        "\u0423\u0438\u043d\u0434\u0437\u043e\u0440 \u041f\u0430\u0440\u043a"
    ],
    "name:spa_x_preferred":[
        "Windsor Park"
    ],
    "name:swe_x_preferred":[
        "Windsor Park"
    ],
    "name:tur_x_preferred":[
        "Windsor Park"
    ],
    "name:ukr_x_preferred":[
        "\u0412\u0456\u043d\u0434\u0437\u043e\u0440 \u041f\u0430\u0440\u043a"
    ],
    "name:zho_x_preferred":[
        "\u6e29\u838e\u516c\u56ed"
    ],
    "wof:name":"Windsor Park",
    "wof:placetype":"locality"
},
  "geometry": {"coordinates":[-105.50057,50.40003],"type":"Point"}
}