{
  "type": "Feature",
  "properties": {
    "gn:admin1_code":"3",
    "gn:asciiname":"Kapuskaypachik",
    "gn:country_code":"CA",
    "gn:dem":353,
    "gn:feature_class":"P",
    "gn:feature_code":"PPLL",
    "gn:name":"Kapuskaypachik",
    "gn:population":0,
    "gn:timezone":"America/Winnipeg",
    "iso:country":"CA",
    "wof:name":"Kapuskaypachik",
    "wof:placetype":"locality"
},
  "geometry": {"coordinates":[-101.3224,58.1545],"type":"Point"}
}