{
  "type": "Feature",
  "properties": {
    "gn:admin1_code":"1",
    "gn:asciiname":"Owlseye",
    "gn:country_code":"CA",
    "gn:dem":657,
    "gn:feature_class":"P",
    "gn:feature_code":"PPLL",
    "gn:name":"Owlseye",
    "gn:population":0,
    "gn:timezone":"America/Edmonton",
    "iso:country":"CA",
    "wof:name":"Owlseye",
    "wof:placetype":"locality"
},
  "geometry": {"coordinates":[-111.43510000000001,54.06687],"type":"Point"}
}