{
  "type": "Feature",
  "properties": {
    "iso:country":"CA",
    "name:eng_x_preferred":[
        "New Waterford"
    ],
    "name:gla_x_preferred":[
        "Port Lairge \u00d9r"
    ],
    "name:unk_x_variant":[
        "New Waterford"
    ],
    "qs:gn_adm0_cc":"CA",
    "qs:gn_fcode":"PPL",
    "qs:gn_local":6354908,
    "qs:gn_nam_loc":"sydney",
    "qs:gn_namadm1":"07",
    "qs:gn_name":"New Waterford",
    "qs:local_max":789,
    "qs:local_sum":2869,
    "qs:localhoods":18,
    "qs:name":"New Waterford",
    "qs:name_adm0":"Canada",
    "qs:name_adm1":"Nova Scotia",
    "qs:name_adm2":"Cape Breton",
    "qs:name_local":"Sydney",
    "qs:photo_max":13,
    "qs:photo_sum":22,
    "qs:placetype":"Suburb",
    "qs:quad_count":9,
    "qs:woe_adm0":23424775,
    "qs:woe_adm1":2344921,
    "qs:woe_adm2":29375130,
    "qs:woe_lau":0,
    "qs:woe_local":3755,
    "qs:woe_ver":"7.10.0",
    "wd:wordcount":665,
    "wof:lang":[
        "eng"
    ],
    "wof:name":"New Waterford",
    "wof:placetype":"neighbourhood"
},
  "geometry": {"coordinates":[-60.089971,46.253948],"type":"Point"}
}