{
  "type": "Feature",
  "properties": {
    "gn:admin1_code":"11",
    "gn:asciiname":"Ratner",
    "gn:country_code":"CA",
    "gn:dem":411,
    "gn:feature_class":"P",
    "gn:feature_code":"PPLL",
    "gn:name":"Ratner",
    "gn:population":0,
    "gn:timezone":"America/Regina",
    "iso:country":"CA",
    "name:deu_x_preferred":[
        "Ratner"
    ],
    "name:fra_x_preferred":[
        "Ratner"
    ],
    "name:heb_x_preferred":[
        "\u05e8\u05d8\u05e0\u05e8"
    ],
    "name:rus_x_preferred":[
        "\u0420\u0430\u0442\u043d\u0435\u0440"
    ],
    "name:ukr_x_preferred":[
        "\u0420\u0430\u0442\u043d\u0435\u0440"
    ],
    "wof:name":"Ratner",
    "wof:placetype":"locality"
},
  "geometry": {"coordinates":[-104.30095,53.16676],"type":"Point"}
}