{
  "type": "Feature",
  "properties": {
    "gn:admin1_code":"7",
    "gn:asciiname":"Middle River",
    "gn:country_code":"CA",
    "gn:dem":35,
    "gn:feature_class":"P",
    "gn:feature_code":"PPL",
    "gn:name":"Middle River",
    "gn:population":0,
    "gn:timezone":"America/Halifax",
    "iso:country":"CA",
    "wof:name":"Middle River",
    "wof:placetype":"locality"
},
  "geometry": {"coordinates":[-60.92404000000001,46.15713],"type":"Point"}
}