{
  "type": "Feature",
  "properties": {
    "gn:admin1_code":"7.0",
    "gn:asciiname":"West Omg;esvo;;e",
    "gn:country_code":"CA",
    "gn:dem":168,
    "gn:feature_class":"P",
    "gn:feature_code":"PPL",
    "gn:name":"West Omg;esvo;;e",
    "gn:population":0,
    "gn:timezone":"America/Halifax",
    "iso:country":"CA",
    "wof:name":"West Omg;esvo;;e",
    "wof:placetype":"locality"
},
  "geometry": {"coordinates":[-65.16734,44.85039],"type":"Point"}
}