{
  "type": "Feature",
  "properties": {
    "gn:admin1_code":"7.0",
    "gn:asciiname":"Dunmore",
    "gn:country_code":"CA",
    "gn:dem":34,
    "gn:feature_class":"P",
    "gn:feature_code":"PPL",
    "gn:name":"Dunmore",
    "gn:population":0,
    "gn:timezone":"America/Halifax",
    "iso:country":"CA",
    "name:ceb_x_preferred":[
        "Dunmore"
    ],
    "name:deu_x_preferred":[
        "Dunmore"
    ],
    "name:epo_x_preferred":[
        "Dunmore"
    ],
    "name:ita_x_preferred":[
        "Dunmore"
    ],
    "name:kat_x_preferred":[
        "\u10d3\u10d0\u10dc\u10db\u10dd\u10e0\u10d8"
    ],
    "name:nld_x_preferred":[
        "Dunmore"
    ],
    "name:por_x_preferred":[
        "Dunmore"
    ],
    "name:rus_x_preferred":[
        "\u0414\u0430\u043d\u043c\u043e\u0440"
    ],
    "name:srp_x_preferred":[
        "\u0414\u0430\u043d\u043c\u043e\u0440"
    ],
    "name:swe_x_preferred":[
        "Dunmore"
    ],
    "wof:name":"Dunmore",
    "wof:placetype":"locality"
},
  "geometry": {"coordinates":[-61.91815,45.5256],"type":"Point"}
}