{
  "type": "Feature",
  "properties": {
    "gn:admin1_code":"7.0",
    "gn:asciiname":"Dunmore",
    "gn:country_code":"CA",
    "gn:dem":34,
    "gn:feature_class":"P",
    "gn:feature_code":"PPL",
    "gn:name":"Dunmore",
    "gn:population":0,
    "gn:timezone":"America/Halifax",
    "iso:country":"CA",
    "wof:name":"Dunmore",
    "wof:placetype":"locality"
},
  "geometry": {"coordinates":[-61.91815,45.5256],"type":"Point"}
}