{
  "type": "Feature",
  "properties": {
    "gn:admin1_code":"10",
    "gn:admin2_code":"7.0",
    "gn:admin3_code":"83020.0",
    "gn:asciiname":"Lac-du-Brochet",
    "gn:country_code":"CA",
    "gn:dem":238,
    "gn:feature_class":"P",
    "gn:feature_code":"PPL",
    "gn:name":"Lac-du-Brochet",
    "gn:population":0,
    "gn:timezone":"America/Toronto",
    "iso:country":"CA",
    "wof:name":"Lac-du-Brochet",
    "wof:placetype":"locality"
},
  "geometry": {"coordinates":[-75.82356,45.92255],"type":"Point"}
}