{
  "type": "Feature",
  "properties": {
    "gn:admin1_code":"8",
    "gn:asciiname":"Moons Beach",
    "gn:country_code":"CA",
    "gn:dem":224,
    "gn:feature_class":"P",
    "gn:feature_code":"PPL",
    "gn:name":"Moons Beach",
    "gn:population":0,
    "gn:timezone":"America/Toronto",
    "iso:country":"CA",
    "wof:name":"Moons Beach",
    "wof:placetype":"locality"
},
  "geometry": {"coordinates":[-79.41221999999998,44.55095],"type":"Point"}
}