{
  "type": "Feature",
  "properties": {
    "gn:admin1_code":"2.0",
    "gn:asciiname":"70 Mile House",
    "gn:country_code":"CA",
    "gn:dem":1084,
    "gn:feature_class":"P",
    "gn:feature_code":"PPL",
    "gn:name":"70 Mile House",
    "gn:population":0,
    "gn:timezone":"America/Vancouver",
    "iso:country":"CA",
    "wof:name":"70 Mile House",
    "wof:placetype":"locality"
},
  "geometry": {"coordinates":[-121.39652,51.30341],"type":"Point"}
}