{
  "type": "Feature",
  "properties": {
    "iso:country":"CA",
    "name:eng_x_preferred":[
        "College Heights"
    ],
    "qs:name":"College Heights",
    "qs:name_adm0":"Canada",
    "qs:name_adm1":"Alberta",
    "qs:photos":18,
    "qs:photos_1k":4,
    "qs:photos_9k":1,
    "qs:photos_9r":1,
    "qs:photos_all":18,
    "qs:photos_sr":1,
    "qs:placetype":"Town",
    "qs:pop_sr":"0",
    "wd:wordcount":186,
    "wof:name":"College Heights",
    "wof:placetype":"locality"
},
  "geometry": {"coordinates":[-113.7342405,52.489411],"type":"Point"}
}