{
  "type": "Feature",
  "properties": {
    "gn:admin1_code":"3",
    "gn:asciiname":"Griswold",
    "gn:country_code":"CA",
    "gn:dem":436,
    "gn:feature_class":"P",
    "gn:feature_code":"PPL",
    "gn:name":"Griswold",
    "gn:population":0,
    "gn:timezone":"America/Winnipeg",
    "iso:country":"CA",
    "name:deu_x_preferred":[
        "Griswold"
    ],
    "name:fra_x_preferred":[
        "Griswold"
    ],
    "name:ita_x_preferred":[
        "Griswold"
    ],
    "name:pol_x_preferred":[
        "Griswold"
    ],
    "name:ukr_x_preferred":[
        "\u0413\u0440\u0438\u0441\u0432\u0443\u0434"
    ],
    "name:vol_x_preferred":[
        "Griswold"
    ],
    "wof:name":"Griswold",
    "wof:placetype":"locality"
},
  "geometry": {"coordinates":[-100.47169,49.775],"type":"Point"}
}