{
  "type": "Feature",
  "properties": {
    "gn:admin1_code":"3",
    "gn:asciiname":"Griswold",
    "gn:country_code":"CA",
    "gn:dem":436,
    "gn:feature_class":"P",
    "gn:feature_code":"PPL",
    "gn:name":"Griswold",
    "gn:population":0,
    "gn:timezone":"America/Winnipeg",
    "iso:country":"CA",
    "wof:name":"Griswold",
    "wof:placetype":"locality"
},
  "geometry": {"coordinates":[-100.47169,49.775],"type":"Point"}
}