{
  "type": "Feature",
  "properties": {
    "gn:admin1_code":"7",
    "gn:asciiname":"Laggan",
    "gn:country_code":"CA",
    "gn:dem":204,
    "gn:feature_class":"P",
    "gn:feature_code":"PPL",
    "gn:name":"Laggan",
    "gn:population":0,
    "gn:timezone":"America/Halifax",
    "iso:country":"CA",
    "wof:name":"Laggan",
    "wof:placetype":"locality"
},
  "geometry": {"coordinates":[-62.32926,45.54127],"type":"Point"}
}