{
  "type": "Feature",
  "properties": {
    "gn:admin1_code":"7.0",
    "gn:asciiname":"East Side Port L'Hebert",
    "gn:country_code":"CA",
    "gn:dem":22,
    "gn:feature_class":"P",
    "gn:feature_code":"PPL",
    "gn:name":"East Side Port L'Hebert",
    "gn:population":0,
    "gn:timezone":"America/Halifax",
    "iso:country":"CA",
    "wof:name":"East Side Port L'Hebert",
    "wof:placetype":"locality"
},
  "geometry": {"coordinates":[-64.92511999999999,43.82187],"type":"Point"}
}