{
  "type": "Feature",
  "properties": {
    "iso:country":"CA",
    "name:eng_x_preferred":[
        "Richvale"
    ],
    "qs:gn_adm0_cc":"CA",
    "qs:gn_local":6122091,
    "qs:gn_nam_loc":"hespeler",
    "qs:gn_namadm1":"08",
    "qs:local_max":232,
    "qs:local_sum":232,
    "qs:localhoods":1,
    "qs:name":"Richvale",
    "qs:name_adm0":"Canada",
    "qs:name_adm1":"Ontario",
    "qs:name_adm2":"York",
    "qs:name_local":"Richmond Hill South",
    "qs:photo_max":50,
    "qs:photo_sum":232,
    "qs:placetype":"Suburb",
    "qs:quad_count":18,
    "qs:woe_adm0":23424775,
    "qs:woe_adm1":2344922,
    "qs:woe_adm2":29375112,
    "qs:woe_funk":"Grouping neighborhood",
    "qs:woe_lau":0,
    "qs:woe_local":55999659,
    "qs:woe_ver":"7.10.0",
    "wof:lang":[
        "eng"
    ],
    "wof:name":"Richvale",
    "wof:placetype":"neighbourhood"
},
  "geometry": {"coordinates":[-79.43807,43.855832],"type":"Point"}
}