{
  "type": "Feature",
  "properties": {
    "gn:admin1_code":"8",
    "gn:asciiname":"Madsen",
    "gn:country_code":"CA",
    "gn:dem":401,
    "gn:feature_class":"P",
    "gn:feature_code":"PPL",
    "gn:name":"Madsen",
    "gn:population":0,
    "gn:timezone":"America/Winnipeg",
    "iso:country":"CA",
    "wof:name":"Madsen",
    "wof:placetype":"locality"
},
  "geometry": {"coordinates":[-93.91714,50.96676],"type":"Point"}
}