{
  "type": "Feature",
  "properties": {
    "gn:admin1_code":"11.0",
    "gn:asciiname":"Borderland",
    "gn:country_code":"CA",
    "gn:dem":933,
    "gn:feature_class":"P",
    "gn:feature_code":"PPLL",
    "gn:name":"Borderland",
    "gn:population":0,
    "gn:timezone":"America/Regina",
    "iso:country":"CA",
    "wof:name":"Borderland",
    "wof:placetype":"locality"
},
  "geometry": {"coordinates":[-106.10115999999999,49.01676],"type":"Point"}
}