{
  "type": "Feature",
  "properties": {
    "gn:admin1_code":"3",
    "gn:asciiname":"Hybord",
    "gn:country_code":"CA",
    "gn:dem":236,
    "gn:feature_class":"P",
    "gn:feature_code":"PPLL",
    "gn:name":"Hybord",
    "gn:population":0,
    "gn:timezone":"America/Winnipeg",
    "iso:country":"CA",
    "wof:name":"Hybord",
    "wof:placetype":"locality"
},
  "geometry": {"coordinates":[-99.29015,53.16972],"type":"Point"}
}