{
  "type": "Feature",
  "properties": {
    "gn:admin1_code":"10",
    "gn:admin2_code":"15.0",
    "gn:admin3_code":"79065.0",
    "gn:asciiname":"Lac-David",
    "gn:country_code":"CA",
    "gn:dem":297,
    "gn:feature_class":"P",
    "gn:feature_code":"PPL",
    "gn:name":"Lac-David",
    "gn:population":0,
    "gn:timezone":"America/Toronto",
    "iso:country":"CA",
    "wof:name":"Lac-David",
    "wof:placetype":"locality"
},
  "geometry": {"coordinates":[-75.21444,46.59056],"type":"Point"}
}