{
  "type": "Feature",
  "properties": {
    "gn:admin1_code":"9.0",
    "gn:asciiname":"Clermont",
    "gn:country_code":"CA",
    "gn:dem":14,
    "gn:feature_class":"P",
    "gn:feature_code":"PPLL",
    "gn:name":"Clermont",
    "gn:population":0,
    "gn:timezone":"America/Halifax",
    "iso:country":"CA",
    "name:bre_x_preferred":[
        "Clermont"
    ],
    "name:cat_x_preferred":[
        "Clermont"
    ],
    "name:ceb_x_preferred":[
        "Clermont"
    ],
    "name:ces_x_preferred":[
        "Clermont"
    ],
    "name:cym_x_preferred":[
        "Clermont"
    ],
    "name:deu_x_preferred":[
        "Clermont"
    ],
    "name:epo_x_preferred":[
        "Clermont"
    ],
    "name:est_x_preferred":[
        "Clermont"
    ],
    "name:fas_x_preferred":[
        "\u06a9\u0644\u0631\u0645\u0648\u0646"
    ],
    "name:fin_x_preferred":[
        "Clermont"
    ],
    "name:fra_x_preferred":[
        "Clermont"
    ],
    "name:glg_x_preferred":[
        "Clermont"
    ],
    "name:ita_x_preferred":[
        "Clermont"
    ],
    "name:jpn_x_preferred":[
        "\u30af\u30ec\u30eb\u30e2\u30f3"
    ],
    "name:kor_x_preferred":[
        "\ud074\ub808\ub974\ubabd"
    ],
    "name:nds_x_preferred":[
        "Clermont"
    ],
    "name:nld_x_preferred":[
        "Clermont"
    ],
    "name:oci_x_preferred":[
        "Clermont"
    ],
    "name:pms_x_preferred":[
        "Clermont"
    ],
    "name:pol_x_preferred":[
        "Clermont"
    ],
    "name:por_x_preferred":[
        "Clermont"
    ],
    "name:ron_x_preferred":[
        "Clermont"
    ],
    "name:rus_x_preferred":[
        "\u041a\u043b\u0435\u0440\u043c\u043e\u043d"
    ],
    "name:slk_x_preferred":[
        "Clermont"
    ],
    "name:spa_x_preferred":[
        "Clermont"
    ],
    "name:srp_x_preferred":[
        "\u041a\u043b\u0435\u0440\u043c\u043e\u043d"
    ],
    "name:swe_x_preferred":[
        "Clermont"
    ],
    "name:tur_x_preferred":[
        "Clermont"
    ],
    "name:ukr_x_preferred":[
        "\u041a\u043b\u0435\u0440\u043c\u043e\u043d"
    ],
    "name:vol_x_preferred":[
        "Clermont"
    ],
    "wof:name":"Clermont",
    "wof:placetype":"locality"
},
  "geometry": {"coordinates":[-63.68202,46.45013],"type":"Point"}
}