{
  "type": "Feature",
  "properties": {
    "gn:admin1_code":"8.0",
    "gn:asciiname":"Bismarck",
    "gn:country_code":"CA",
    "gn:dem":185,
    "gn:feature_class":"P",
    "gn:feature_code":"PPL",
    "gn:name":"Bismarck",
    "gn:population":0,
    "gn:timezone":"America/Toronto",
    "iso:country":"CA",
    "name:ara_x_preferred":[
        "\u0628\u064a\u0633\u0645\u0627\u0631\u0643"
    ],
    "name:bre_x_preferred":[
        "Bismarck"
    ],
    "name:bul_x_preferred":[
        "\u0411\u0438\u0441\u043c\u0430\u0440\u043a"
    ],
    "name:cat_x_preferred":[
        "Bismarck"
    ],
    "name:ceb_x_preferred":[
        "Bismarck"
    ],
    "name:ces_x_preferred":[
        "Bismarck"
    ],
    "name:cym_x_preferred":[
        "Bismarck"
    ],
    "name:dan_x_preferred":[
        "Bismarck"
    ],
    "name:deu_x_preferred":[
        "Bismarck"
    ],
    "name:ell_x_preferred":[
        "\u0392\u03af\u03c3\u03bc\u03b1\u03c1\u03ba"
    ],
    "name:epo_x_preferred":[
        "Bismarck"
    ],
    "name:est_x_preferred":[
        "Bismarck"
    ],
    "name:fas_x_preferred":[
        "\u0628\u06cc\u0633\u0645\u0627\u0631\u06a9"
    ],
    "name:fin_x_preferred":[
        "Bismarck"
    ],
    "name:fra_x_preferred":[
        "Bismarck"
    ],
    "name:heb_x_preferred":[
        "\u05d1\u05d9\u05e1\u05de\u05e8\u05e7"
    ],
    "name:hrv_x_preferred":[
        "Bismarck"
    ],
    "name:hun_x_preferred":[
        "Bismarck"
    ],
    "name:ido_x_preferred":[
        "Bismarck"
    ],
    "name:ind_x_preferred":[
        "Bismarck"
    ],
    "name:ita_x_preferred":[
        "Bismarck"
    ],
    "name:jpn_x_preferred":[
        "\u30d3\u30b9\u30de\u30eb\u30af"
    ],
    "name:kor_x_preferred":[
        "\ube44\uc2a4\ub9c8\ub974\ud06c"
    ],
    "name:lav_x_preferred":[
        "Bismarck"
    ],
    "name:lit_x_preferred":[
        "Bismarkas"
    ],
    "name:mkd_x_preferred":[
        "\u0411\u0438\u0437\u043c\u0430\u0440\u043a"
    ],
    "name:nld_x_preferred":[
        "Bismarck"
    ],
    "name:nor_x_preferred":[
        "Bismarck"
    ],
    "name:oci_x_preferred":[
        "Bismarck"
    ],
    "name:pol_x_preferred":[
        "Bismarck"
    ],
    "name:por_x_preferred":[
        "Bismarck"
    ],
    "name:ron_x_preferred":[
        "Bismarck"
    ],
    "name:rus_x_preferred":[
        "\u0411\u0438\u0441\u043c\u0430\u0440\u043a"
    ],
    "name:san_x_preferred":[
        "\u092c\u093f\u0938\u094d\u092e\u093e\u0930\u094d\u0915\u094d"
    ],
    "name:sco_x_preferred":[
        "Bismarck"
    ],
    "name:slk_x_preferred":[
        "Bismarck"
    ],
    "name:spa_x_preferred":[
        "Bismarck"
    ],
    "name:srp_x_preferred":[
        "\u0411\u0438\u0437\u043c\u0430\u0440\u043a"
    ],
    "name:swe_x_preferred":[
        "Bismarck"
    ],
    "name:tha_x_preferred":[
        "\u0e1a\u0e34\u0e2a\u0e21\u0e32\u0e23\u0e4c\u0e01"
    ],
    "name:tur_x_preferred":[
        "Bismarck"
    ],
    "name:ukr_x_preferred":[
        "\u0411\u0456\u0441\u043c\u0430\u0440\u043a"
    ],
    "name:urd_x_preferred":[
        "\u0628\u0633\u0645\u0627\u0631\u06a9"
    ],
    "name:vol_x_preferred":[
        "Bismarck"
    ],
    "name:zho_x_preferred":[
        "\u4ffe\u65af\u9ea6"
    ],
    "wof:name":"Bismarck",
    "wof:placetype":"locality"
},
  "geometry": {"coordinates":[-79.50345,43.04193],"type":"Point"}
}