{
  "type": "Feature",
  "properties": {
    "gn:admin1_code":"8.0",
    "gn:asciiname":"Bismarck",
    "gn:country_code":"CA",
    "gn:dem":185,
    "gn:feature_class":"P",
    "gn:feature_code":"PPL",
    "gn:name":"Bismarck",
    "gn:population":0,
    "gn:timezone":"America/Toronto",
    "iso:country":"CA",
    "wof:name":"Bismarck",
    "wof:placetype":"locality"
},
  "geometry": {"coordinates":[-79.50345,43.04193],"type":"Point"}
}