{
  "type": "Feature",
  "properties": {
    "gn:admin1_code":"8",
    "gn:asciiname":"Goshen",
    "gn:country_code":"CA",
    "gn:dem":274,
    "gn:feature_class":"P",
    "gn:feature_code":"PPL",
    "gn:name":"Goshen",
    "gn:population":0,
    "gn:timezone":"America/Toronto",
    "iso:country":"CA",
    "name:cat_x_preferred":[
        "Goshen"
    ],
    "name:ceb_x_preferred":[
        "Goshen"
    ],
    "name:deu_x_preferred":[
        "Goshen"
    ],
    "name:fra_x_preferred":[
        "Goshen"
    ],
    "name:heb_x_preferred":[
        "\u05d2\u05d5\u05e9\u05df"
    ],
    "name:hun_x_preferred":[
        "Goshen"
    ],
    "name:ido_x_preferred":[
        "Goshen"
    ],
    "name:ita_x_preferred":[
        "Goshen"
    ],
    "name:nld_x_preferred":[
        "Goshen"
    ],
    "name:pol_x_preferred":[
        "Goshen"
    ],
    "name:por_x_preferred":[
        "Goshen"
    ],
    "name:rus_x_preferred":[
        "\u0413\u043e\u0448\u0435\u043d"
    ],
    "name:spa_x_preferred":[
        "Goshen"
    ],
    "name:srp_x_preferred":[
        "\u0413\u043e\u0448\u0435\u043d"
    ],
    "name:swe_x_preferred":[
        "Goshen"
    ],
    "name:ukr_x_preferred":[
        "\u0413\u043e\u0448\u0435\u043d"
    ],
    "name:vol_x_preferred":[
        "Goshen"
    ],
    "wof:name":"Goshen",
    "wof:placetype":"locality"
},
  "geometry": {"coordinates":[-81.63778000000001,43.4925],"type":"Point"}
}