{
  "type": "Feature",
  "properties": {
    "gn:admin1_code":"8",
    "gn:asciiname":"Goshen",
    "gn:country_code":"CA",
    "gn:dem":274,
    "gn:feature_class":"P",
    "gn:feature_code":"PPL",
    "gn:name":"Goshen",
    "gn:population":0,
    "gn:timezone":"America/Toronto",
    "iso:country":"CA",
    "wof:name":"Goshen",
    "wof:placetype":"locality"
},
  "geometry": {"coordinates":[-81.63778000000001,43.4925],"type":"Point"}
}