{
  "type": "Feature",
  "properties": {
    "gn:country":"CA",
    "gn:fcode":"PPL",
    "gn:pop":0,
    "iso:country":"CA",
    "name:ara_x_preferred":[
        "\u0643\u0627\u0646\u064a\u0646\u063a"
    ],
    "name:dut_x_preferred":[
        "Canning"
    ],
    "name:eng_x_preferred":[
        "Canning"
    ],
    "name:fre_x_preferred":[
        "Canning"
    ],
    "name:gla_x_preferred":[
        "Canning"
    ],
    "name:swe_x_preferred":[
        "Canning"
    ],
    "qs:name":"Canning",
    "qs:name_adm0":"Canada",
    "qs:name_adm1":"Nova Scotia",
    "qs:photos":623,
    "qs:photos_1k":126,
    "qs:photos_9k":3,
    "qs:photos_9r":5,
    "qs:photos_all":623,
    "qs:photos_sr":8,
    "qs:placetype":"Town",
    "qs:pop_sr":"3",
    "wd:wordcount":3585,
    "wof:name":"Canning",
    "wof:placetype":"locality",
    "wof:population":0
},
  "geometry": {"coordinates":[-64.41546,45.15015],"type":"Point"}
}