{
  "type": "Feature",
  "properties": {
    "gn:admin1_code":"2.0",
    "gn:admin2_code":"5924",
    "gn:asciiname":"Blind Channel",
    "gn:country_code":"CA",
    "gn:dem":6,
    "gn:feature_class":"P",
    "gn:feature_code":"PPL",
    "gn:name":"Blind Channel",
    "gn:population":0,
    "gn:timezone":"America/Vancouver",
    "iso:country":"CA",
    "wof:name":"Blind Channel",
    "wof:placetype":"locality"
},
  "geometry": {"coordinates":[-125.50270999999999,50.41322],"type":"Point"}
}