{
  "type": "Feature",
  "properties": {
    "gn:admin1_code":"11",
    "gn:asciiname":"Lake Park",
    "gn:country_code":"CA",
    "gn:dem":451,
    "gn:feature_class":"P",
    "gn:feature_code":"PPLL",
    "gn:name":"Lake Park",
    "gn:population":0,
    "gn:timezone":"America/Regina",
    "iso:country":"CA",
    "name:ceb_x_preferred":[
        "Lake Park"
    ],
    "name:deu_x_preferred":[
        "Lake Park"
    ],
    "name:fra_x_preferred":[
        "Lake Park"
    ],
    "name:ita_x_preferred":[
        "Lake Park"
    ],
    "name:kor_x_preferred":[
        "\ub808\uc774\ud06c\ud30c\ud06c"
    ],
    "name:nld_x_preferred":[
        "Lake Park"
    ],
    "name:pol_x_preferred":[
        "Lake Park"
    ],
    "name:por_x_preferred":[
        "Lake Park"
    ],
    "name:rus_x_preferred":[
        "\u041b\u0435\u0439\u043a-\u041f\u0430\u0440\u043a"
    ],
    "name:spa_x_preferred":[
        "Lake Park"
    ],
    "name:srp_x_preferred":[
        "\u041b\u0435\u0458\u043a \u041f\u0430\u0440\u043a"
    ],
    "name:swe_x_preferred":[
        "Lake Park"
    ],
    "name:ukr_x_preferred":[
        "\u041b\u0435\u0439\u043a-\u041f\u0430\u0440\u043a"
    ],
    "name:vol_x_preferred":[
        "Lake Park"
    ],
    "wof:name":"Lake Park",
    "wof:placetype":"locality"
},
  "geometry": {"coordinates":[-105.30101000000001,53.05006],"type":"Point"}
}