{
  "type": "Feature",
  "properties": {
    "gn:admin1_code":"11",
    "gn:asciiname":"Lake Park",
    "gn:country_code":"CA",
    "gn:dem":451,
    "gn:feature_class":"P",
    "gn:feature_code":"PPLL",
    "gn:name":"Lake Park",
    "gn:population":0,
    "gn:timezone":"America/Regina",
    "iso:country":"CA",
    "wof:name":"Lake Park",
    "wof:placetype":"locality"
},
  "geometry": {"coordinates":[-105.30101000000001,53.05006],"type":"Point"}
}