{
  "type": "Feature",
  "properties": {
    "gn:admin1_code":"8",
    "gn:asciiname":"Kinghurst",
    "gn:country_code":"CA",
    "gn:dem":319,
    "gn:feature_class":"P",
    "gn:feature_code":"PPL",
    "gn:name":"Kinghurst",
    "gn:population":0,
    "gn:timezone":"America/Toronto",
    "iso:country":"CA",
    "wof:name":"Kinghurst",
    "wof:placetype":"locality"
},
  "geometry": {"coordinates":[-80.93902,44.3201],"type":"Point"}
}