{
  "type": "Feature",
  "properties": {
    "gn:admin1_code":"4.0",
    "gn:asciiname":"Belleisle Creek",
    "gn:country_code":"CA",
    "gn:dem":57,
    "gn:feature_class":"P",
    "gn:feature_code":"PPL",
    "gn:name":"Belleisle Creek",
    "gn:population":0,
    "gn:timezone":"America/Moncton",
    "iso:country":"CA",
    "wof:name":"Belleisle Creek",
    "wof:placetype":"locality"
},
  "geometry": {"coordinates":[-65.75060000000001,45.71903],"type":"Point"}
}