{
  "type": "Feature",
  "properties": {
    "gn:admin1_code":"10",
    "gn:admin2_code":"15.0",
    "gn:admin3_code":"78120.0",
    "gn:asciiname":"Lac-Caribou",
    "gn:country_code":"CA",
    "gn:dem":291,
    "gn:feature_class":"P",
    "gn:feature_code":"PPL",
    "gn:name":"Lac-Caribou",
    "gn:population":0,
    "gn:timezone":"America/Toronto",
    "iso:country":"CA",
    "wof:name":"Lac-Caribou",
    "wof:placetype":"locality"
},
  "geometry": {"coordinates":[-74.70768000000002,46.28671],"type":"Point"}
}