{
  "type": "Feature",
  "properties": {
    "gn:admin1_code":"8",
    "gn:asciiname":"Walden",
    "gn:country_code":"CA",
    "gn:dem":246,
    "gn:feature_class":"P",
    "gn:feature_code":"PPL",
    "gn:name":"Walden",
    "gn:population":0,
    "gn:timezone":"America/Toronto",
    "iso:country":"CA",
    "name:ceb_x_preferred":[
        "Walden"
    ],
    "name:fas_x_preferred":[
        "\u0648\u0627\u0644\u062f\u0646"
    ],
    "name:fra_x_preferred":[
        "Walden"
    ],
    "name:swe_x_preferred":[
        "Walden"
    ],
    "wof:name":"Walden",
    "wof:placetype":"locality"
},
  "geometry": {"coordinates":[-81.39539000000001,46.38354],"type":"Point"}
}