{
  "type": "Feature",
  "properties": {
    "gn:admin1_code":"8.0",
    "gn:asciiname":"Binkham",
    "gn:country_code":"CA",
    "gn:dem":434,
    "gn:feature_class":"P",
    "gn:feature_code":"PPL",
    "gn:name":"Binkham",
    "gn:population":0,
    "gn:timezone":"America/Toronto",
    "iso:country":"CA",
    "wof:name":"Binkham",
    "wof:placetype":"locality"
},
  "geometry": {"coordinates":[-80.10171,43.81126],"type":"Point"}
}