{
  "type": "Feature",
  "properties": {
    "gn:admin1_code":"11",
    "gn:asciiname":"Gunnar",
    "gn:country_code":"CA",
    "gn:dem":207,
    "gn:feature_class":"P",
    "gn:feature_code":"PPLL",
    "gn:name":"Gunnar",
    "gn:population":0,
    "gn:timezone":"America/Regina",
    "iso:country":"CA",
    "name:dan_x_preferred":[
        "Gunnar"
    ],
    "name:deu_x_preferred":[
        "Gunnar"
    ],
    "name:fin_x_preferred":[
        "Gunnar"
    ],
    "name:fra_x_preferred":[
        "Gunnar"
    ],
    "name:isl_x_preferred":[
        "Gunnar"
    ],
    "name:nno_x_preferred":[
        "Gunnar"
    ],
    "name:nor_x_preferred":[
        "Gunnar"
    ],
    "name:rus_x_preferred":[
        "\u0413\u0443\u043d\u043d\u0430\u0440"
    ],
    "name:swe_x_preferred":[
        "Gunnar"
    ],
    "wof:name":"Gunnar",
    "wof:placetype":"locality"
},
  "geometry": {"coordinates":[-108.88481000000002,59.38371],"type":"Point"}
}