{
  "type": "Feature",
  "properties": {
    "gn:admin1_code":"11",
    "gn:asciiname":"Gunnar",
    "gn:country_code":"CA",
    "gn:dem":207,
    "gn:feature_class":"P",
    "gn:feature_code":"PPLL",
    "gn:name":"Gunnar",
    "gn:population":0,
    "gn:timezone":"America/Regina",
    "iso:country":"CA",
    "wof:name":"Gunnar",
    "wof:placetype":"locality"
},
  "geometry": {"coordinates":[-108.88481000000002,59.38371],"type":"Point"}
}