{
  "type": "Feature",
  "properties": {
    "gn:admin1_code":"7",
    "gn:asciiname":"Milford Station",
    "gn:country_code":"CA",
    "gn:dem":20,
    "gn:feature_class":"P",
    "gn:feature_code":"PPL",
    "gn:name":"Milford Station",
    "gn:population":0,
    "gn:timezone":"America/Halifax",
    "iso:country":"CA",
    "wof:name":"Milford Station",
    "wof:placetype":"locality"
},
  "geometry": {"coordinates":[-63.43636,45.0408],"type":"Point"}
}