{
  "type": "Feature",
  "properties": {
    "gn:admin1_code":"5.0",
    "gn:asciiname":"Birchy Cove",
    "gn:country_code":"CA",
    "gn:dem":69,
    "gn:feature_class":"P",
    "gn:feature_code":"PPLL",
    "gn:name":"Birchy Cove",
    "gn:population":0,
    "gn:timezone":"America/St_Johns",
    "iso:country":"CA",
    "name:fra_x_preferred":[
        "Birchy Cove"
    ],
    "wof:name":"Birchy Cove",
    "wof:placetype":"locality"
},
  "geometry": {"coordinates":[-56.01488000000001,49.68326],"type":"Point"}
}