{
  "type": "Feature",
  "properties": {
    "gn:admin1_code":"11",
    "gn:asciiname":"Gilroy",
    "gn:country_code":"CA",
    "gn:dem":642,
    "gn:feature_class":"P",
    "gn:feature_code":"PPLL",
    "gn:name":"Gilroy",
    "gn:population":0,
    "gn:timezone":"America/Regina",
    "iso:country":"CA",
    "name:deu_x_preferred":[
        "Gilroy"
    ],
    "name:fra_x_preferred":[
        "Gilroy"
    ],
    "name:jpn_x_preferred":[
        "\u30ae\u30eb\u30ed\u30a4"
    ],
    "name:nld_x_preferred":[
        "Gilroy"
    ],
    "name:por_x_preferred":[
        "Gilroy"
    ],
    "name:rus_x_preferred":[
        "\u0413\u0438\u043b\u0440\u043e\u0439"
    ],
    "name:sco_x_preferred":[
        "Gilroy"
    ],
    "wof:name":"Gilroy",
    "wof:placetype":"locality"
},
  "geometry": {"coordinates":[-106.73456000000002,50.90006],"type":"Point"}
}