{
  "type": "Feature",
  "properties": {
    "gn:admin1_code":"8.0",
    "gn:asciiname":"Bothwell's Corner",
    "gn:country_code":"CA",
    "gn:dem":260,
    "gn:feature_class":"P",
    "gn:feature_code":"PPL",
    "gn:name":"Bothwell's Corner",
    "gn:population":0,
    "gn:timezone":"America/Toronto",
    "iso:country":"CA",
    "wof:name":"Bothwell's Corner",
    "wof:placetype":"locality"
},
  "geometry": {"coordinates":[-80.87694,44.57861],"type":"Point"}
}