{
  "type": "Feature",
  "properties": {
    "gn:admin1_code":"7",
    "gn:asciiname":"Georges River",
    "gn:country_code":"CA",
    "gn:dem":8,
    "gn:feature_class":"P",
    "gn:feature_code":"PPL",
    "gn:name":"Georges River",
    "gn:population":0,
    "gn:timezone":"America/Glace_Bay",
    "iso:country":"CA",
    "name:afr_x_preferred":[
        "Georges-rivier"
    ],
    "name:ara_x_preferred":[
        "\u0646\u0647\u0631 \u062c\u0648\u0631\u062c"
    ],
    "name:deu_x_preferred":[
        "Georges River"
    ],
    "name:epo_x_preferred":[
        "Rivero Georges"
    ],
    "name:fra_x_preferred":[
        "Georges River"
    ],
    "name:jpn_x_preferred":[
        "\u30b8\u30e7\u30fc\u30b8\u30ba\u30fb\u30ea\u30d0\u30fc"
    ],
    "name:rus_x_preferred":[
        "\u0414\u0436\u043e\u0440\u0434\u0436\u0435\u0441"
    ],
    "name:zho_x_preferred":[
        "\u4e54\u6cbb\u65af\u6cb3"
    ],
    "wof:name":"Georges River",
    "wof:placetype":"locality"
},
  "geometry": {"coordinates":[-60.3152,46.21309],"type":"Point"}
}