{
  "type": "Feature",
  "properties": {
    "iso:country":"CA",
    "name:eng_x_preferred":[
        "Bayview Glen"
    ],
    "name:eng_x_variant":[
        "Bayview Glen School"
    ],
    "name:kor_x_preferred":[
        "\ubca0\uc774\ubdf0 \uae00\ub80c \uc2a4\ucfe8"
    ],
    "wd:wordcount":699,
    "wof:lang":[
        "eng"
    ],
    "wof:name":"Bayview Glen",
    "wof:placetype":"neighbourhood"
},
  "geometry": {"coordinates":[-79.39661099999999,43.808949],"type":"Point"}
}