{
  "type": "Feature",
  "properties": {
    "gn:admin1_code":"7.0",
    "gn:asciiname":"Belgiumtown",
    "gn:country_code":"CA",
    "gn:dem":51,
    "gn:feature_class":"P",
    "gn:feature_code":"PPL",
    "gn:name":"Belgiumtown",
    "gn:population":0,
    "gn:timezone":"America/Glace_Bay",
    "iso:country":"CA",
    "wof:name":"Belgiumtown",
    "wof:placetype":"locality"
},
  "geometry": {"coordinates":[-60.01139000000001,46.19095],"type":"Point"}
}