{
  "type": "Feature",
  "properties": {
    "gn:admin1_code":"1.0",
    "gn:asciiname":"Dapp",
    "gn:country_code":"CA",
    "gn:dem":611,
    "gn:feature_class":"P",
    "gn:feature_code":"PPLL",
    "gn:name":"Dapp",
    "gn:population":0,
    "gn:timezone":"America/Edmonton",
    "iso:country":"CA",
    "name:fra_x_preferred":[
        "Dapp"
    ],
    "wof:name":"Dapp",
    "wof:placetype":"locality"
},
  "geometry": {"coordinates":[-113.91879,54.35015],"type":"Point"}
}