{
  "type": "Feature",
  "properties": {
    "gn:admin1_code":"8",
    "gn:asciiname":"Watabeag",
    "gn:country_code":"CA",
    "gn:dem":276,
    "gn:feature_class":"P",
    "gn:feature_code":"PPL",
    "gn:name":"Watabeag",
    "gn:population":0,
    "gn:timezone":"America/Toronto",
    "iso:country":"CA",
    "wof:name":"Watabeag",
    "wof:placetype":"locality"
},
  "geometry": {"coordinates":[-80.55110999999999,48.56611],"type":"Point"}
}