{
  "type": "Feature",
  "properties": {
    "gn:admin1_code":"1",
    "gn:asciiname":"Grouard",
    "gn:country_code":"CA",
    "gn:dem":584,
    "gn:feature_class":"P",
    "gn:feature_code":"PPL",
    "gn:name":"Grouard",
    "gn:population":0,
    "gn:timezone":"America/Edmonton",
    "iso:country":"CA",
    "name:fra_x_preferred":[
        "Grouard"
    ],
    "wof:name":"Grouard",
    "wof:placetype":"locality"
},
  "geometry": {"coordinates":[-116.16110999999999,55.52028000000001],"type":"Point"}
}