{
  "type": "Feature",
  "properties": {
    "gn:admin1_code":"1",
    "gn:asciiname":"Pirmez Creek",
    "gn:country_code":"CA",
    "gn:dem":1178,
    "gn:feature_class":"P",
    "gn:feature_code":"PPLL",
    "gn:name":"Pirmez Creek",
    "gn:population":0,
    "gn:timezone":"America/Edmonton",
    "iso:country":"CA",
    "wof:name":"Pirmez Creek",
    "wof:placetype":"locality"
},
  "geometry": {"coordinates":[-114.402,51.03341],"type":"Point"}
}