{
  "type": "Feature",
  "properties": {
    "gn:admin1_code":"8.0",
    "gn:asciiname":"Crown Hill",
    "gn:country_code":"CA",
    "gn:dem":248,
    "gn:feature_class":"P",
    "gn:feature_code":"PPL",
    "gn:name":"Crown Hill",
    "gn:population":0,
    "gn:timezone":"America/Toronto",
    "iso:country":"CA",
    "name:ceb_x_preferred":[
        "Crown Hill"
    ],
    "wof:name":"Crown Hill",
    "wof:placetype":"locality"
},
  "geometry": {"coordinates":[-79.64194000000001,44.43389000000001],"type":"Point"}
}