{
  "type": "Feature",
  "properties": {
    "gn:admin1_code":"2.0",
    "gn:asciiname":"Corbin",
    "gn:country_code":"CA",
    "gn:dem":1648,
    "gn:feature_class":"P",
    "gn:feature_code":"PPLL",
    "gn:name":"Corbin",
    "gn:population":0,
    "gn:timezone":"America/Edmonton",
    "iso:country":"CA",
    "wof:name":"Corbin",
    "wof:placetype":"locality"
},
  "geometry": {"coordinates":[-114.652,49.51671],"type":"Point"}
}