{
  "type": "Feature",
  "properties": {
    "gn:admin1_code":"11",
    "gn:asciiname":"Rosenort",
    "gn:country_code":"CA",
    "gn:dem":880,
    "gn:feature_class":"P",
    "gn:feature_code":"PPLL",
    "gn:name":"Rosenort",
    "gn:population":0,
    "gn:timezone":"America/Regina",
    "iso:country":"CA",
    "wof:name":"Rosenort",
    "wof:placetype":"locality"
},
  "geometry": {"coordinates":[-107.58463,50.13336],"type":"Point"}
}