{
  "type": "Feature",
  "properties": {
    "gn:admin1_code":"4",
    "gn:asciiname":"Sainte-Anne-de-Kent",
    "gn:country_code":"CA",
    "gn:dem":19,
    "gn:feature_class":"P",
    "gn:feature_code":"PPL",
    "gn:name":"Sainte-Anne-de-Kent",
    "gn:population":0,
    "gn:timezone":"America/Moncton",
    "iso:country":"CA",
    "name:fra_x_preferred":[
        "Sainte-Anne-de-Kent"
    ],
    "wof:name":"Sainte-Anne-de-Kent",
    "wof:placetype":"locality"
},
  "geometry": {"coordinates":[-64.77401999999999,46.55191],"type":"Point"}
}