{
  "type": "Feature",
  "properties": {
    "gn:admin1_code":"8",
    "gn:asciiname":"Foxmead",
    "gn:country_code":"CA",
    "gn:dem":205,
    "gn:feature_class":"P",
    "gn:feature_code":"PPL",
    "gn:name":"Foxmead",
    "gn:population":0,
    "gn:timezone":"America/Toronto",
    "iso:country":"CA",
    "wof:name":"Foxmead",
    "wof:placetype":"locality"
},
  "geometry": {"coordinates":[-79.57222,44.69167],"type":"Point"}
}