{
  "type": "Feature",
  "properties": {
    "gn:admin1_code":"8",
    "gn:asciiname":"Poland",
    "gn:country_code":"CA",
    "gn:dem":473,
    "gn:feature_class":"P",
    "gn:feature_code":"PPLL",
    "gn:name":"Poland",
    "gn:population":0,
    "gn:timezone":"America/Toronto",
    "iso:country":"CA",
    "wof:name":"Poland",
    "wof:placetype":"locality"
},
  "geometry": {"coordinates":[-90.11685,48.93342],"type":"Point"}
}