{
  "type": "Feature",
  "properties": {
    "gn:admin1_code":"7",
    "gn:asciiname":"Judique South",
    "gn:country_code":"CA",
    "gn:dem":14,
    "gn:feature_class":"P",
    "gn:feature_code":"PPLL",
    "gn:name":"Judique South",
    "gn:population":0,
    "gn:timezone":"America/Halifax",
    "iso:country":"CA",
    "wof:name":"Judique South",
    "wof:placetype":"locality"
},
  "geometry": {"coordinates":[-61.49014,45.852],"type":"Point"}
}