{
  "type": "Feature",
  "properties": {
    "gn:admin1_code":"3",
    "gn:asciiname":"Seech",
    "gn:country_code":"CA",
    "gn:dem":633,
    "gn:feature_class":"P",
    "gn:feature_code":"PPLL",
    "gn:name":"Seech",
    "gn:population":0,
    "gn:timezone":"America/Winnipeg",
    "iso:country":"CA",
    "wof:name":"Seech",
    "wof:placetype":"locality"
},
  "geometry": {"coordinates":[-100.43774999999999,50.68251],"type":"Point"}
}