{
  "type": "Feature",
  "properties": {
    "gn:admin1_code":"7",
    "gn:asciiname":"Lingan",
    "gn:country_code":"CA",
    "gn:dem":22,
    "gn:feature_class":"P",
    "gn:feature_code":"PPL",
    "gn:name":"Lingan",
    "gn:population":0,
    "gn:timezone":"America/Glace_Bay",
    "iso:country":"CA",
    "name:gla_x_preferred":[
        "Liongan"
    ],
    "wof:name":"Lingan",
    "wof:placetype":"locality"
},
  "geometry": {"coordinates":[-60.06137,46.23041],"type":"Point"}
}