{
  "type": "Feature",
  "properties": {
    "iso:country":"CA",
    "name:eng_x_preferred":[
        "Lucasville"
    ],
    "qs:name":"Lucasville",
    "qs:name_adm0":"Canada",
    "qs:name_adm1":"Nova Scotia",
    "qs:photos":304,
    "qs:photos_1k":62,
    "qs:photos_9k":1,
    "qs:photos_9r":5,
    "qs:photos_all":304,
    "qs:photos_sr":5,
    "qs:placetype":"Town",
    "qs:pop_sr":"0",
    "wd:wordcount":11,
    "wof:name":"Lucasville",
    "wof:placetype":"locality"
},
  "geometry": {"coordinates":[-63.771091,44.733791],"type":"Point"}
}