{
  "type": "Feature",
  "properties": {
    "gn:admin1_code":"7",
    "gn:asciiname":"Truemanville",
    "gn:country_code":"CA",
    "gn:dem":62,
    "gn:feature_class":"P",
    "gn:feature_code":"PPL",
    "gn:name":"Truemanville",
    "gn:population":0,
    "gn:timezone":"America/Halifax",
    "iso:country":"CA",
    "name:gla_x_preferred":[
        "Truemanville"
    ],
    "wof:name":"Truemanville",
    "wof:placetype":"locality"
},
  "geometry": {"coordinates":[-64.07519000000001,45.85572],"type":"Point"}
}