{
  "type": "Feature",
  "properties": {
    "iso:country":"CA",
    "name:ind_x_preferred":[
        "Bandar Udara Eureka"
    ],
    "oa:elevation_ft":"256",
    "oa:type":"small_airport",
    "wd:wordcount":78,
    "woe:hierarchy":{
        "country_id":23424775,
        "county_id":29375230,
        "planet_id":1,
        "state_id":20069920
    },
    "wof:name":"Eureka Airport",
    "wof:placetype":"campus"
},
  "geometry": {"coordinates":[-85.81194444444399,79.994444444444],"type":"Point"}
}