{
  "type": "Feature",
  "properties": {
    "iso:country":"CA",
    "name:ceb_x_preferred":[
        "Eureka Man"
    ],
    "name:eng_x_preferred":[
        "Eureka Aerodrome"
    ],
    "name:fas_x_preferred":[
        "\u0641\u0631\u0648\u062f\u06af\u0627\u0647 \u0627\u0648\u0631\u06cc\u06a9\u0627"
    ],
    "name:fin_x_preferred":[
        "Eurekan lentoasema"
    ],
    "name:fra_x_preferred":[
        "a\u00e9roport d\u2019Eureka"
    ],
    "name:ind_x_preferred":[
        "Bandar Udara Eureka"
    ],
    "name:jpn_x_preferred":[
        "\u30e6\u30fc\u30ea\u30ab\u98db\u884c\u5834"
    ],
    "name:msa_x_preferred":[
        "Lapangan Terbang Eureka"
    ],
    "name:pms_x_preferred":[
        "Eureka Airport"
    ],
    "name:swe_x_preferred":[
        "Eureka Man"
    ],
    "name:tgk_x_preferred":[
        "\u0424\u0443\u0440\u0443\u0434\u0433\u043e\u04b3\u0438 \u043e\u0432\u0440\u0438\u043a\u043e"
    ],
    "oa:elevation_ft":"256",
    "oa:type":"small_airport",
    "wd:wordcount":78,
    "woe:hierarchy":{
        "country_id":23424775,
        "county_id":29375230,
        "planet_id":1,
        "state_id":20069920
    },
    "wof:name":"Eureka Airport",
    "wof:placetype":"campus"
},
  "geometry": {"coordinates":[-85.81194444444399,79.994444444444],"type":"Point"}
}