{
  "type": "Feature",
  "properties": {
    "gn:admin1_code":"11",
    "gn:asciiname":"Larkhaven",
    "gn:country_code":"CA",
    "gn:dem":498,
    "gn:feature_class":"P",
    "gn:feature_code":"PPL",
    "gn:name":"Larkhaven",
    "gn:population":0,
    "gn:timezone":"America/Regina",
    "iso:country":"CA",
    "wof:name":"Larkhaven",
    "wof:placetype":"locality"
},
  "geometry": {"coordinates":[-106.68478,52.16143],"type":"Point"}
}