{
  "type": "Feature",
  "properties": {
    "gn:admin1_code":"3",
    "gn:asciiname":"Lakeland",
    "gn:country_code":"CA",
    "gn:dem":257,
    "gn:feature_class":"P",
    "gn:feature_code":"PPLL",
    "gn:name":"Lakeland",
    "gn:population":0,
    "gn:timezone":"America/Winnipeg",
    "iso:country":"CA",
    "wof:name":"Lakeland",
    "wof:placetype":"locality"
},
  "geometry": {"coordinates":[-98.66746000000001,50.26942],"type":"Point"}
}