{
  "type": "Feature",
  "properties": {
    "gn:admin1_code":"3",
    "gn:asciiname":"Lakeland",
    "gn:country_code":"CA",
    "gn:dem":257,
    "gn:feature_class":"P",
    "gn:feature_code":"PPLL",
    "gn:name":"Lakeland",
    "gn:population":0,
    "gn:timezone":"America/Winnipeg",
    "iso:country":"CA",
    "name:ceb_x_preferred":[
        "Lakeland"
    ],
    "name:deu_x_preferred":[
        "Lakeland"
    ],
    "name:fra_x_preferred":[
        "Lakeland"
    ],
    "name:ita_x_preferred":[
        "Lakeland"
    ],
    "name:kor_x_preferred":[
        "\ub808\uc774\ud074\ub79c\ub4dc"
    ],
    "name:nld_x_preferred":[
        "Lakeland"
    ],
    "name:pol_x_preferred":[
        "Lakeland"
    ],
    "name:por_x_preferred":[
        "Lakeland"
    ],
    "name:rus_x_preferred":[
        "\u041b\u0435\u0439\u043a\u043b\u0435\u043d\u0434"
    ],
    "name:spa_x_preferred":[
        "Lakeland"
    ],
    "name:srp_x_preferred":[
        "\u041b\u0435\u0458\u043a\u043b\u0430\u043d\u0434"
    ],
    "name:ukr_x_preferred":[
        "\u041b\u0435\u0439\u043a\u043b\u0435\u043d\u0434"
    ],
    "name:urd_x_preferred":[
        "\u0644\u06cc\u06a9\u0644\u06cc\u0646\u0688"
    ],
    "name:vol_x_preferred":[
        "Lakeland"
    ],
    "wof:name":"Lakeland",
    "wof:placetype":"locality"
},
  "geometry": {"coordinates":[-98.66746000000001,50.26942],"type":"Point"}
}