{
  "type": "Feature",
  "properties": {
    "gn:admin1_code":"11",
    "gn:asciiname":"Rowatt",
    "gn:country_code":"CA",
    "gn:dem":572,
    "gn:feature_class":"P",
    "gn:feature_code":"PPL",
    "gn:name":"Rowatt",
    "gn:population":0,
    "gn:timezone":"America/Regina",
    "iso:country":"CA",
    "wof:name":"Rowatt",
    "wof:placetype":"locality"
},
  "geometry": {"coordinates":[-104.61722,50.33337],"type":"Point"}
}