{
  "type": "Feature",
  "properties": {
    "iso:country":"CA",
    "oa:elevation_ft":"121",
    "oa:type":"medium_airport",
    "woe:hierarchy":{
        "country_id":23424775,
        "county_id":29375258,
        "planet_id":1,
        "state_id":2344924
    },
    "wof:name":"Aeroport d\u00e9 Lourdes-d\u00e9-Blanc-Sablon",
    "wof:placetype":"campus"
},
  "geometry": {"coordinates":[-57.186111111111,51.441944444444],"type":"Point"}
}