{
  "type": "Feature",
  "properties": {
    "iso:country":"CA",
    "name:ceb_x_preferred":[
        "Lourdes-de-Blanc-Sablon Airport"
    ],
    "name:eng_x_preferred":[
        "Lourdes-de-Blanc-Sablon Airport"
    ],
    "name:fas_x_preferred":[
        "\u0641\u0631\u0648\u062f\u06af\u0627\u0647 \u0644\u0648\u0631\u062f\u0632 \u062f \u0628\u0644\u0627\u0646\u06a9 \u0633\u0627\u0628\u0644\u0648\u0646"
    ],
    "name:fra_x_preferred":[
        "a\u00e9roport Lourdes-de-Blanc-Sablon"
    ],
    "name:ita_x_preferred":[
        "aeroporto Lourdes-de-Blanc-Sablon"
    ],
    "name:msa_x_preferred":[
        "Lapangan Terbang Lourdes-De-Blanc-Sablon"
    ],
    "name:pms_x_preferred":[
        "Lourdes-de-Blanc-Sablon Airport"
    ],
    "name:ron_x_preferred":[
        "Aeroportul Lourdes-de-Blanc-Sablon"
    ],
    "name:swe_x_preferred":[
        "Lourdes-de-Blanc-Sablon Airport"
    ],
    "name:tgk_x_preferred":[
        "\u0424\u0443\u0440\u0443\u0434\u0433\u043e\u04b3\u0438 \u043b\u0443\u0440\u0434\u0437 \u0434 \u0431\u043b\u043e\u043d\u043a \u0441\u043e\u0431\u043b\u0443\u043d"
    ],
    "oa:elevation_ft":"121",
    "oa:type":"medium_airport",
    "woe:hierarchy":{
        "country_id":23424775,
        "county_id":29375258,
        "planet_id":1,
        "state_id":2344924
    },
    "wof:name":"Aeroport d\u00e9 Lourdes-d\u00e9-Blanc-Sablon",
    "wof:placetype":"campus"
},
  "geometry": {"coordinates":[-57.186111111111,51.441944444444],"type":"Point"}
}