{
  "type": "Feature",
  "properties": {
    "gn:admin1_code":"7",
    "gn:asciiname":"Folly Mountain",
    "gn:country_code":"CA",
    "gn:dem":134,
    "gn:feature_class":"P",
    "gn:feature_code":"PPL",
    "gn:name":"Folly Mountain",
    "gn:population":0,
    "gn:timezone":"America/Halifax",
    "iso:country":"CA",
    "name:ceb_x_preferred":[
        "Folly Mountain"
    ],
    "name:swe_x_preferred":[
        "Folly Mountain"
    ],
    "wof:name":"Folly Mountain",
    "wof:placetype":"locality"
},
  "geometry": {"coordinates":[-63.53043,45.48382],"type":"Point"}
}