{
  "type": "Feature",
  "properties": {
    "gn:admin1_code":"3",
    "gn:asciiname":"Fisherton",
    "gn:country_code":"CA",
    "gn:dem":259,
    "gn:feature_class":"P",
    "gn:feature_code":"PPLL",
    "gn:name":"Fisherton",
    "gn:population":0,
    "gn:timezone":"America/Winnipeg",
    "iso:country":"CA",
    "wof:name":"Fisherton",
    "wof:placetype":"locality"
},
  "geometry": {"coordinates":[-97.76739999999999,51.15671],"type":"Point"}
}