{
  "type": "Feature",
  "properties": {
    "iso:country":"CA",
    "name:ara_x_preferred":[
        "\u0648\u0633\u0637 \u0627\u0644\u0628\u0644\u062f"
    ],
    "name:arz_x_preferred":[
        "\u0648\u0633\u0637 \u0627\u0644\u0628\u0644\u062f"
    ],
    "name:ast_x_preferred":[
        "Distritu financieru"
    ],
    "name:ben_x_preferred":[
        "\u09b6\u09b9\u09b0\u09c7\u09b0 \u0995\u09c7\u09a8\u09cd\u09a6\u09cd\u09b0\u09b8\u09cd\u09a5\u09b2"
    ],
    "name:bul_x_preferred":[
        "\u0426\u0435\u043d\u0442\u044a\u0440"
    ],
    "name:ces_x_preferred":[
        "Downtown"
    ],
    "name:deu_x_preferred":[
        "Downtown"
    ],
    "name:eng_x_preferred":[
        "Downtown"
    ],
    "name:eng_x_variant":[
        "downtown"
    ],
    "name:epo_x_preferred":[
        "urbocentro"
    ],
    "name:fas_x_preferred":[
        "\u0647\u0633\u062a\u0647 \u0634\u0647\u0631"
    ],
    "name:fra_x_preferred":[
        "centre-ville"
    ],
    "name:hun_x_preferred":[
        "belv\u00e1ros"
    ],
    "name:jpn_x_preferred":[
        "\u30c0\u30a6\u30f3\u30bf\u30a6\u30f3"
    ],
    "name:kor_x_preferred":[
        "\ub3c4\uc2ec"
    ],
    "name:nld_x_preferred":[
        "downtown"
    ],
    "name:pol_x_preferred":[
        "centrum miasta"
    ],
    "name:por_x_preferred":[
        "centro"
    ],
    "name:ron_x_preferred":[
        "Centru civic"
    ],
    "name:rus_x_preferred":[
        "\u0434\u0430\u0443\u043d\u0442\u0430\u0443\u043d"
    ],
    "name:sco_x_preferred":[
        "Downtown"
    ],
    "name:spa_x_preferred":[
        "downtown"
    ],
    "name:swe_x_preferred":[
        "Downtown"
    ],
    "name:ukr_x_preferred":[
        "\u0434\u0430\u0443\u043d\u0442\u0430\u0443\u043d"
    ],
    "name:wuu_x_preferred":[
        "\u4e0b\u57ce"
    ],
    "name:yue_x_preferred":[
        "\u4e0b\u57ce"
    ],
    "name:zho_x_preferred":[
        "\u4e0b\u57ce"
    ],
    "qs:gn_adm0_cc":"CA",
    "qs:gn_local":6324729,
    "qs:gn_nam_loc":"Halifax, Halifax, Nova Scotia, CA",
    "qs:gn_namadm1":"07",
    "qs:local_max":32392,
    "qs:local_sum":46326,
    "qs:localhoods":10,
    "qs:name":"Downtown",
    "qs:name_adm0":"Canada",
    "qs:name_adm1":"Nova Scotia",
    "qs:name_adm2":"Halifax",
    "qs:name_local":"Halifax",
    "qs:photo_max":4730,
    "qs:photo_sum":32392,
    "qs:placetype":"Suburb",
    "qs:quad_count":124,
    "qs:woe_adm0":23424775,
    "qs:woe_adm1":2344921,
    "qs:woe_adm2":29375176,
    "qs:woe_lau":0,
    "qs:woe_local":4177,
    "qs:woe_ver":"7.10.0",
    "wd:wordcount":1123,
    "wof:lang":[
        "eng"
    ],
    "wof:name":"Downtown",
    "wof:placetype":"neighbourhood"
},
  "geometry": {"coordinates":[-63.574695,44.646683],"type":"Point"}
}