{
  "type": "Feature",
  "properties": {
    "gn:admin1_code":"1",
    "gn:asciiname":"Kingman",
    "gn:country_code":"CA",
    "gn:dem":746,
    "gn:feature_class":"P",
    "gn:feature_code":"PPL",
    "gn:name":"Kingman",
    "gn:population":0,
    "gn:timezone":"America/Edmonton",
    "iso:country":"CA",
    "name:ben_x_preferred":[
        "\u0995\u09bf\u0982\u09ae\u09cd\u09af\u09be\u09a8"
    ],
    "name:ell_x_preferred":[
        "\u039a\u03af\u03bd\u03b3\u03ba\u03bc\u03b1\u03bd"
    ],
    "name:fra_x_preferred":[
        "Kingman"
    ],
    "name:hin_x_preferred":[
        "\u0915\u093f\u0902\u0917\u092e\u0948\u0928"
    ],
    "name:ind_x_preferred":[
        "Kingman"
    ],
    "wof:name":"Kingman",
    "wof:placetype":"locality"
},
  "geometry": {"coordinates":[-112.75194,53.21684],"type":"Point"}
}