{
  "type": "Feature",
  "properties": {
    "gn:admin1_code":"1",
    "gn:asciiname":"Kingman",
    "gn:country_code":"CA",
    "gn:dem":746,
    "gn:feature_class":"P",
    "gn:feature_code":"PPL",
    "gn:name":"Kingman",
    "gn:population":0,
    "gn:timezone":"America/Edmonton",
    "iso:country":"CA",
    "name:fra_x_preferred":[
        "Kingman"
    ],
    "wof:name":"Kingman",
    "wof:placetype":"locality"
},
  "geometry": {"coordinates":[-112.75194,53.21684000000001],"type":"Point"}
}