{
  "type": "Feature",
  "properties": {
    "gn:admin1_code":"8",
    "gn:asciiname":"Sine",
    "gn:country_code":"CA",
    "gn:dem":157,
    "gn:feature_class":"P",
    "gn:feature_code":"PPL",
    "gn:name":"Sine",
    "gn:population":0,
    "gn:timezone":"America/Toronto",
    "iso:country":"CA",
    "wof:name":"Sine",
    "wof:placetype":"locality"
},
  "geometry": {"coordinates":[-77.58194,44.34306],"type":"Point"}
}