{
  "type": "Feature",
  "properties": {
    "gn:admin1_code":"3",
    "gn:asciiname":"Greenfarm",
    "gn:country_code":"CA",
    "gn:dem":261,
    "gn:feature_class":"P",
    "gn:feature_code":"PPLL",
    "gn:name":"Greenfarm",
    "gn:population":0,
    "gn:timezone":"America/Winnipeg",
    "iso:country":"CA",
    "wof:name":"Greenfarm",
    "wof:placetype":"locality"
},
  "geometry": {"coordinates":[-97.85742999999999,49.2072],"type":"Point"}
}