{
  "type": "Feature",
  "properties": {
    "gn:admin1_code":"10",
    "gn:admin2_code":"8.0",
    "gn:asciiname":"Lac-Caugnawana",
    "gn:country_code":"CA",
    "gn:dem":334,
    "gn:feature_class":"P",
    "gn:feature_code":"PPL",
    "gn:name":"Lac-Caugnawana",
    "gn:population":0,
    "gn:timezone":"America/Toronto",
    "iso:country":"CA",
    "wof:name":"Lac-Caugnawana",
    "wof:placetype":"locality"
},
  "geometry": {"coordinates":[-78.30639000000002,46.535],"type":"Point"}
}