{
  "type": "Feature",
  "properties": {
    "gn:admin1_code":"8.0",
    "gn:asciiname":"Dunns Valley",
    "gn:country_code":"CA",
    "gn:dem":232,
    "gn:feature_class":"P",
    "gn:feature_code":"PPL",
    "gn:name":"Dunns Valley",
    "gn:population":0,
    "gn:timezone":"America/Toronto",
    "iso:country":"CA",
    "wof:name":"Dunns Valley",
    "wof:placetype":"locality"
},
  "geometry": {"coordinates":[-83.62470999999999,46.46656],"type":"Point"}
}