{
  "type": "Feature",
  "properties": {
    "gn:admin1_code":"7",
    "gn:asciiname":"South Manchester",
    "gn:country_code":"CA",
    "gn:dem":45,
    "gn:feature_class":"P",
    "gn:feature_code":"PPL",
    "gn:name":"South Manchester",
    "gn:population":0,
    "gn:timezone":"America/Halifax",
    "iso:country":"CA",
    "wof:name":"South Manchester",
    "wof:placetype":"locality"
},
  "geometry": {"coordinates":[-61.44492,45.40576],"type":"Point"}
}