{
  "type": "Feature",
  "properties": {
    "gn:admin1_code":"11.0",
    "gn:asciiname":"Dernic",
    "gn:country_code":"CA",
    "gn:dem":513,
    "gn:feature_class":"P",
    "gn:feature_code":"PPLL",
    "gn:name":"Dernic",
    "gn:population":0,
    "gn:timezone":"America/Regina",
    "iso:country":"CA",
    "wof:name":"Dernic",
    "wof:placetype":"locality"
},
  "geometry": {"coordinates":[-102.86766,51.73328],"type":"Point"}
}