{
  "type": "Feature",
  "properties": {
    "gn:admin1_code":"8",
    "gn:asciiname":"Marshall Park",
    "gn:country_code":"CA",
    "gn:dem":197,
    "gn:feature_class":"P",
    "gn:feature_code":"PPL",
    "gn:name":"Marshall Park",
    "gn:population":0,
    "gn:timezone":"America/Toronto",
    "iso:country":"CA",
    "name:ceb_x_preferred":[
        "Marshall Park"
    ],
    "wof:name":"Marshall Park",
    "wof:placetype":"locality"
},
  "geometry": {"coordinates":[-79.44083000000001,46.27639],"type":"Point"}
}