{
  "type": "Feature",
  "properties": {
    "gn:admin1_code":"8.0",
    "gn:asciiname":"Ardtrea",
    "gn:country_code":"CA",
    "gn:dem":227,
    "gn:feature_class":"P",
    "gn:feature_code":"PPL",
    "gn:name":"Ardtrea",
    "gn:population":0,
    "gn:timezone":"America/Toronto",
    "iso:country":"CA",
    "wof:name":"Ardtrea",
    "wof:placetype":"locality"
},
  "geometry": {"coordinates":[-79.4025,44.68667],"type":"Point"}
}