{
  "type": "Feature",
  "properties": {
    "gn:admin1_code":"11",
    "gn:asciiname":"Lens",
    "gn:country_code":"CA",
    "gn:dem":445,
    "gn:feature_class":"P",
    "gn:feature_code":"PPLL",
    "gn:name":"Lens",
    "gn:population":0,
    "gn:timezone":"America/Regina",
    "iso:country":"CA",
    "name:afr_x_preferred":[
        "Lens"
    ],
    "name:ara_x_preferred":[
        "\u0639\u062f\u0633\u0629"
    ],
    "name:arg_x_preferred":[
        "Lens"
    ],
    "name:azb_x_preferred":[
        "\u0644\u0646\u0632"
    ],
    "name:cat_x_preferred":[
        "Lens"
    ],
    "name:ceb_x_preferred":[
        "Lens"
    ],
    "name:ces_x_preferred":[
        "Lens"
    ],
    "name:deu_x_preferred":[
        "Lens"
    ],
    "name:ell_x_preferred":[
        "\u039b\u03b1\u03bd\u03c2"
    ],
    "name:epo_x_preferred":[
        "Lens"
    ],
    "name:eus_x_preferred":[
        "Lens"
    ],
    "name:fas_x_preferred":[
        "\u0644\u0646\u0632"
    ],
    "name:fin_x_preferred":[
        "Lens"
    ],
    "name:fra_x_preferred":[
        "Lens"
    ],
    "name:glg_x_preferred":[
        "Lens"
    ],
    "name:heb_x_preferred":[
        "\u05e2\u05d3\u05e9\u05d4"
    ],
    "name:hun_x_preferred":[
        "Lens"
    ],
    "name:ita_x_preferred":[
        "Lens"
    ],
    "name:jpn_x_preferred":[
        "\u30ec\u30f3\u30ba"
    ],
    "name:kan_x_preferred":[
        "\u0cae\u0cb8\u0cc2\u0cb0"
    ],
    "name:kor_x_preferred":[
        "\ub80c\uc988"
    ],
    "name:lit_x_preferred":[
        "Lens"
    ],
    "name:lmo_x_preferred":[
        "Lens"
    ],
    "name:ltz_x_preferred":[
        "Lens"
    ],
    "name:nld_x_preferred":[
        "Lens"
    ],
    "name:oci_x_preferred":[
        "Lens"
    ],
    "name:pms_x_preferred":[
        "Lens"
    ],
    "name:por_x_preferred":[
        "Lens"
    ],
    "name:rus_x_preferred":[
        "\u041b\u0435\u043d\u0441"
    ],
    "name:sco_x_preferred":[
        "Lens"
    ],
    "name:slk_x_preferred":[
        "Lens"
    ],
    "name:slv_x_preferred":[
        "Lens"
    ],
    "name:spa_x_preferred":[
        "Lens"
    ],
    "name:swe_x_preferred":[
        "Lens"
    ],
    "name:tha_x_preferred":[
        "\u0e40\u0e25\u0e19\u0e2a\u0e4c"
    ],
    "name:tur_x_preferred":[
        "Lens"
    ],
    "name:ukr_x_preferred":[
        "\u041b\u0435\u043d\u0441"
    ],
    "name:urd_x_preferred":[
        "\u0639\u062f\u0633\u06c1"
    ],
    "name:vol_x_preferred":[
        "Lens"
    ],
    "wof:name":"Lens",
    "wof:placetype":"locality"
},
  "geometry": {"coordinates":[-103.06765,52.6167],"type":"Point"}
}