{
  "type": "Feature",
  "properties": {
    "gn:admin1_code":"4.0",
    "gn:asciiname":"Drisdelle",
    "gn:country_code":"CA",
    "gn:dem":28,
    "gn:feature_class":"P",
    "gn:feature_code":"PPL",
    "gn:name":"Drisdelle",
    "gn:population":0,
    "gn:timezone":"America/Moncton",
    "iso:country":"CA",
    "wof:name":"Drisdelle",
    "wof:placetype":"locality"
},
  "geometry": {"coordinates":[-64.39075,46.13528],"type":"Point"}
}