{
  "type": "Feature",
  "properties": {
    "gn:admin1_code":"8",
    "gn:asciiname":"Moxam's Landing",
    "gn:country_code":"CA",
    "gn:dem":239,
    "gn:feature_class":"P",
    "gn:feature_code":"PPLL",
    "gn:name":"Moxam's Landing",
    "gn:population":0,
    "gn:timezone":"America/Toronto",
    "iso:country":"CA",
    "wof:name":"Moxam's Landing",
    "wof:placetype":"locality"
},
  "geometry": {"coordinates":[-81.08584,46.37368],"type":"Point"}
}