{
  "type": "Feature",
  "properties": {
    "gn:country":"CA",
    "gn:fcode":"PPL",
    "gn:population":0,
    "iso:country":"CA",
    "name:bre_x_preferred":[
        "Sainte-Christine-d'Auvergne"
    ],
    "name:ceb_x_preferred":[
        "Sainte-Christine-d'Auvergne"
    ],
    "name:cos_x_preferred":[
        "Sainte-Christine-d'Auvergne"
    ],
    "name:dan_x_preferred":[
        "Sainte-Christine-d'Auvergne"
    ],
    "name:deu_x_preferred":[
        "Sainte-Christine-d'Auvergne"
    ],
    "name:eng_x_preferred":[
        "Sainte-Christine-d'Auvergne"
    ],
    "name:eus_x_preferred":[
        "Sainte-Christine-d'Auvergne"
    ],
    "name:fas_x_preferred":[
        "\u0633\u0646\u062a-\u06a9\u0631\u06cc\u0633\u062a\u06cc\u0646-\u062f\u0648\u0648\u0631\u06cc\u0646\u060c \u06a9\u0628\u06a9"
    ],
    "name:fas_x_variant":[
        "\u0633\u0646\u062a-\u06a9\u0631\u06cc\u0633\u062a\u06cc\u0646-\u062f\u0648\u0648\u0631\u06cc\u0646"
    ],
    "name:fra_x_preferred":[
        "Sainte-Christine-d'Auvergne"
    ],
    "name:gle_x_preferred":[
        "Sainte-Christine-d'Auvergne"
    ],
    "name:ind_x_preferred":[
        "Sainte-Christine-d'Auvergne"
    ],
    "name:ita_x_preferred":[
        "Sainte-Christine-d'Auvergne"
    ],
    "name:jpn_x_preferred":[
        "\u30b5\u30f3\u30c8\uff1d\u30af\u30ea\u30b9\u30c6\u30a3\u30fc\u30cc\uff1d\u30c9\u30f4\u30a7\u30eb\u30cb\u30e5"
    ],
    "name:ltz_x_preferred":[
        "Sainte-Christine-d'Auvergne"
    ],
    "name:nds_x_preferred":[
        "Sainte-Christine-d'Auvergne"
    ],
    "name:nld_x_preferred":[
        "Sainte-Christine-d'Auvergne"
    ],
    "name:nob_x_preferred":[
        "Sainte-Christine-d'Auvergne"
    ],
    "name:por_x_preferred":[
        "Sainte-Christine-d'Auvergne"
    ],
    "name:ron_x_preferred":[
        "Sainte-Christine-d'Auvergne"
    ],
    "name:spa_x_preferred":[
        "Sainte-Christine-d'Auvergne"
    ],
    "name:swe_x_preferred":[
        "Sainte-Christine-d'Auvergne"
    ],
    "name:tah_x_preferred":[
        "Sainte-Christine-d'Auvergne"
    ],
    "name:urd_x_preferred":[
        "\u0633\u06cc\u0646-\u06a9\u0631\u0633\u0679\u06cc\u0646-\u062f\u0648\u0648\u0631\u06af\u0646\u06d2\u060c \u06a9\u06cc\u0648\u0628\u06a9"
    ],
    "name:urd_x_variant":[
        "\u0633\u06cc\u0646-\u06a9\u0631\u0633\u0679\u06cc\u0646-\u062f\u0648\u0648\u0631\u06af\u0646\u06d2"
    ],
    "qs_pg:aaroncc":"CA",
    "qs_pg:gn_country":"CA",
    "qs_pg:gn_fcode":"PPL",
    "qs_pg:gn_pop":0,
    "qs_pg:name":"Ste.-christine-d'auvergne",
    "qs_pg:name_adm0":"Canada",
    "qs_pg:name_adm1":"Qu\u00e9bec",
    "qs_pg:photos":100,
    "qs_pg:photos_1k":20,
    "qs_pg:photos_9k":1,
    "qs_pg:photos_9r":3,
    "qs_pg:photos_all":100,
    "qs_pg:photos_sr":3,
    "qs_pg:pop_sr":0,
    "qs_pg:qs_pg_placetype":"locality",
    "qs_pg:qs_pg_placetype_gp":"Town",
    "qs_pg:woe_adm0":23424775,
    "woe:adm0_id":23424775,
    "woe:name_adm0":"Canada",
    "woe:name_adm1":"Qu\u00e9bec",
    "woe:placetype":"Town",
    "wof:name":"Ste.-christine-d'auvergne",
    "wof:placetype":"locality"
},
  "geometry": {"coordinates":[-71.96579,46.81675],"type":"Point"}
}