{
  "type": "Feature",
  "properties": {
    "gn:admin1_code":"10",
    "gn:admin2_code":"7.0",
    "gn:admin3_code":"84055.0",
    "gn:asciiname":"Klukeville",
    "gn:country_code":"CA",
    "gn:dem":277,
    "gn:feature_class":"P",
    "gn:feature_code":"PPL",
    "gn:name":"Klukeville",
    "gn:population":0,
    "gn:timezone":"America/Toronto",
    "iso:country":"CA",
    "wof:name":"Klukeville",
    "wof:placetype":"locality"
},
  "geometry": {"coordinates":[-76.45389,45.94694000000001],"type":"Point"}
}