{
  "type": "Feature",
  "properties": {
    "gn:admin1_code":"1",
    "gn:asciiname":"Highridge",
    "gn:country_code":"CA",
    "gn:dem":705,
    "gn:feature_class":"P",
    "gn:feature_code":"PPLL",
    "gn:name":"Highridge",
    "gn:population":0,
    "gn:timezone":"America/Edmonton",
    "iso:country":"CA",
    "wof:name":"Highridge",
    "wof:placetype":"locality"
},
  "geometry": {"coordinates":[-114.13538,54.05015],"type":"Point"}
}