{
  "type": "Feature",
  "properties": {
    "gn:admin1_code":"7",
    "gn:asciiname":"Pettigrew Settlement",
    "gn:country_code":"CA",
    "gn:dem":21,
    "gn:feature_class":"P",
    "gn:feature_code":"PPL",
    "gn:name":"Pettigrew Settlement",
    "gn:population":0,
    "gn:timezone":"America/Halifax",
    "iso:country":"CA",
    "wof:name":"Pettigrew Settlement",
    "wof:placetype":"locality"
},
  "geometry": {"coordinates":[-64.35648,45.54228],"type":"Point"}
}