{
  "type": "Feature",
  "properties": {
    "gn:country":"CA",
    "gn:fcode":"PPL",
    "gn:population":0,
    "iso:country":"CA",
    "name:ceb_x_preferred":[
        "Petty Harbour-Maddox Cove"
    ],
    "name:dan_x_preferred":[
        "Petty Harbour-Maddox Cove"
    ],
    "name:deu_x_preferred":[
        "Petty Harbour-Maddox Cove"
    ],
    "name:eng_x_preferred":[
        "Petty Harbour-Maddox Cove"
    ],
    "name:eng_x_variant":[
        "Petty Harbour\u2013Maddox Cove"
    ],
    "name:fra_x_preferred":[
        "Petty Harbour-Maddox Cove"
    ],
    "name:nld_x_preferred":[
        "Petty Harbour-Maddox Cove"
    ],
    "name:spa_x_preferred":[
        "Petty Harbour-Maddox Cove"
    ],
    "name:swe_x_preferred":[
        "Petty Harbour-Maddox Cove"
    ],
    "name:zho_x_preferred":[
        "\u4f69\u63d0\u6e2f-\u99ac\u591a\u514b\u65af\u7063"
    ],
    "qs:name":"Petty Harbour-Maddox Cove",
    "qs:name_adm0":"Canada",
    "qs:name_adm1":"Newfoundland and Labrador",
    "qs:photos":136,
    "qs:photos_1k":28,
    "qs:photos_9k":1,
    "qs:photos_9r":3,
    "qs:photos_all":136,
    "qs:photos_sr":3,
    "qs:placetype":"Town",
    "qs:pop_sr":"0",
    "wd:wordcount":362,
    "wof:name":"Petty Harbour-Maddox Cove",
    "wof:placetype":"locality",
    "wof:population":0
},
  "geometry": {"coordinates":[-52.71475,47.46659],"type":"Point"}
}