{
  "type": "Feature",
  "properties": {
    "gn:country":"CA",
    "gn:fcode":"PPL",
    "gn:pop":0,
    "iso:country":"CA",
    "name:eng_x_preferred":[
        "Petty Harbour-Maddox Cove"
    ],
    "qs:name":"Petty Harbour-Maddox Cove",
    "qs:name_adm0":"Canada",
    "qs:name_adm1":"Newfoundland and Labrador",
    "qs:photos":136,
    "qs:photos_1k":28,
    "qs:photos_9k":1,
    "qs:photos_9r":3,
    "qs:photos_all":136,
    "qs:photos_sr":3,
    "qs:placetype":"Town",
    "qs:pop_sr":"0",
    "wd:wordcount":362,
    "wof:name":"Petty Harbour-Maddox Cove",
    "wof:placetype":"locality",
    "wof:population":0
},
  "geometry": {"coordinates":[-52.71475,47.46659],"type":"Point"}
}