{
  "type": "Feature",
  "properties": {
    "iso:country":"CA",
    "name:dut_x_preferred":[
        "Bramalea"
    ],
    "name:eng_x_preferred":[
        "Bramalea"
    ],
    "qs_pg:aaroncc":"CA",
    "qs_pg:name":"Bramalea",
    "qs_pg:name_adm0":"Canada",
    "qs_pg:name_adm1":"Ontario",
    "qs_pg:photos":655,
    "qs_pg:photos_1k":133,
    "qs_pg:photos_9k":3,
    "qs_pg:photos_9r":5,
    "qs_pg:photos_all":655,
    "qs_pg:photos_sr":8,
    "qs_pg:pop_sr":0,
    "qs_pg:qs_pg_placetype":"locality",
    "qs_pg:qs_pg_placetype_gp":"Town",
    "qs_pg:woe_adm0":23424775,
    "woe:adm0_id":23424775,
    "woe:name_adm0":"Canada",
    "woe:name_adm1":"Ontario",
    "woe:placetype":"Town",
    "wof:name":"Bramalea",
    "wof:placetype":"locality"
},
  "geometry": {"coordinates":[-79.72417799999999,43.725836],"type":"Point"}
}