{
  "type": "Feature",
  "properties": {
    "gn:admin1_code":"7.0",
    "gn:asciiname":"Yarmouth Bar",
    "gn:country_code":"CA",
    "gn:dem":5,
    "gn:feature_class":"P",
    "gn:feature_code":"PPL",
    "gn:name":"Yarmouth Bar",
    "gn:population":0,
    "gn:timezone":"America/Halifax",
    "iso:country":"CA",
    "wof:name":"Yarmouth Bar",
    "wof:placetype":"locality"
},
  "geometry": {"coordinates":[-66.14768000000001,43.81848],"type":"Point"}
}