{
  "type": "Feature",
  "properties": {
    "gn:admin1_code":"2",
    "gn:asciiname":"Takla Landing",
    "gn:country_code":"CA",
    "gn:dem":728,
    "gn:feature_class":"P",
    "gn:feature_code":"PPLL",
    "gn:name":"Takla Landing",
    "gn:population":0,
    "gn:timezone":"America/Vancouver",
    "iso:country":"CA",
    "wof:name":"Takla Landing",
    "wof:placetype":"locality"
},
  "geometry": {"coordinates":[-125.97017,55.48313],"type":"Point"}
}