{
  "type": "Feature",
  "properties": {
    "iso:country":"CA",
    "name:cat_x_preferred":[
        "Petersburg"
    ],
    "name:ceb_x_preferred":[
        "Petersburg"
    ],
    "name:deu_x_preferred":[
        "Petersburg"
    ],
    "name:est_x_preferred":[
        "Petersburg"
    ],
    "name:fin_x_preferred":[
        "Petersburg"
    ],
    "name:fra_x_preferred":[
        "Petersburg"
    ],
    "name:ita_x_preferred":[
        "Petersburg"
    ],
    "name:jpn_x_preferred":[
        "\u30d4\u30fc\u30bf\u30fc\u30ba\u30d0\u30fc\u30b0"
    ],
    "name:kor_x_preferred":[
        "\ud53c\ud130\uc988\ubc84\uadf8"
    ],
    "name:nld_x_preferred":[
        "Petersburg"
    ],
    "name:nor_x_preferred":[
        "Petersburg"
    ],
    "name:pol_x_preferred":[
        "Petersburg"
    ],
    "name:ron_x_preferred":[
        "Petersburg"
    ],
    "name:rus_x_preferred":[
        "\u041f\u0435\u0442\u0435\u0440\u0441\u0431\u0443\u0440\u0433"
    ],
    "name:sco_x_preferred":[
        "Petersburg"
    ],
    "name:slk_x_preferred":[
        "Petersburg"
    ],
    "name:spa_x_preferred":[
        "Petersburg"
    ],
    "name:srp_x_preferred":[
        "\u041f\u0438\u0442\u0435\u0440\u0441\u0431\u0443\u0440\u0433"
    ],
    "name:swe_x_preferred":[
        "Petersburg"
    ],
    "name:tur_x_preferred":[
        "Petersburg"
    ],
    "name:ukr_x_preferred":[
        "\u041f\u0456\u0442\u0435\u0440\u0441\u0431\u0435\u0440\u0433"
    ],
    "name:urd_x_preferred":[
        "\u067e\u06cc\u0679\u0631\u0632\u0628\u0631\u06af"
    ],
    "name:vol_x_preferred":[
        "Petersburg"
    ],
    "name:zho_x_preferred":[
        "\u5f7c\u5fb7\u5821"
    ],
    "qs_pg:aaroncc":"CA",
    "qs_pg:name":"Petersburg",
    "qs_pg:name_adm0":"Canada",
    "qs_pg:name_adm1":"Ontario",
    "qs_pg:photos":198,
    "qs_pg:photos_1k":40,
    "qs_pg:photos_9k":1,
    "qs_pg:photos_9r":4,
    "qs_pg:photos_all":198,
    "qs_pg:photos_sr":4,
    "qs_pg:pop_sr":0,
    "qs_pg:qs_pg_placetype":"locality",
    "qs_pg:qs_pg_placetype_gp":"Town",
    "qs_pg:woe_adm0":23424775,
    "woe:adm0_id":23424775,
    "woe:name_adm0":"Canada",
    "woe:name_adm1":"Ontario",
    "woe:placetype":"Town",
    "wof:name":"Petersburg",
    "wof:placetype":"locality"
},
  "geometry": {"coordinates":[-80.611925,43.413433],"type":"Point"}
}