{
  "type": "Feature",
  "properties": {
    "gn:admin1_code":"4",
    "gn:asciiname":"Saint-Fabien",
    "gn:country_code":"CA",
    "gn:dem":58,
    "gn:feature_class":"P",
    "gn:feature_code":"PPL",
    "gn:name":"Saint-Fabien",
    "gn:population":0,
    "gn:timezone":"America/Moncton",
    "iso:country":"CA",
    "wof:name":"Saint-Fabien",
    "wof:placetype":"locality"
},
  "geometry": {"coordinates":[-64.87720999999999,46.43163],"type":"Point"}
}