{
  "type": "Feature",
  "properties": {
    "gn:admin1_code":"7.0",
    "gn:asciiname":"Claremont",
    "gn:country_code":"CA",
    "gn:dem":112,
    "gn:feature_class":"P",
    "gn:feature_code":"PPLL",
    "gn:name":"Claremont",
    "gn:population":0,
    "gn:timezone":"America/Halifax",
    "iso:country":"CA",
    "name:bar_x_preferred":[
        "Claremont"
    ],
    "name:cat_x_preferred":[
        "Claremont"
    ],
    "name:ceb_x_preferred":[
        "Claremont"
    ],
    "name:deu_x_preferred":[
        "Claremont"
    ],
    "name:fra_x_preferred":[
        "Claremont"
    ],
    "name:ido_x_preferred":[
        "Claremont"
    ],
    "name:ita_x_preferred":[
        "Claremont"
    ],
    "name:jpn_x_preferred":[
        "\u30af\u30ec\u30a2\u30e2\u30f3\u30c8"
    ],
    "name:kor_x_preferred":[
        "\ud074\ub808\uc5b4\ubaac\ud2b8"
    ],
    "name:mlg_x_preferred":[
        "Claremont"
    ],
    "name:nld_x_preferred":[
        "Claremont"
    ],
    "name:pol_x_preferred":[
        "Claremont"
    ],
    "name:por_x_preferred":[
        "Claremont"
    ],
    "name:rus_x_preferred":[
        "\u041a\u043b\u044d\u0440\u043c\u043e\u043d\u0442"
    ],
    "name:spa_x_preferred":[
        "Claremont"
    ],
    "name:swe_x_preferred":[
        "Claremont"
    ],
    "name:ukr_x_preferred":[
        "\u041a\u043b\u0435\u0440\u043c\u043e\u043d\u0442"
    ],
    "name:vol_x_preferred":[
        "Claremont"
    ],
    "wof:name":"Claremont",
    "wof:placetype":"locality"
},
  "geometry": {"coordinates":[-63.96543000000001,45.68345],"type":"Point"}
}