{
  "type": "Feature",
  "properties": {
    "gn:admin1_code":"7.0",
    "gn:asciiname":"Claremont",
    "gn:country_code":"CA",
    "gn:dem":112,
    "gn:feature_class":"P",
    "gn:feature_code":"PPLL",
    "gn:name":"Claremont",
    "gn:population":0,
    "gn:timezone":"America/Halifax",
    "iso:country":"CA",
    "wof:name":"Claremont",
    "wof:placetype":"locality"
},
  "geometry": {"coordinates":[-63.96543000000001,45.68345],"type":"Point"}
}