{
  "type": "Feature",
  "properties": {
    "iso:country":"CA",
    "name:chi_x_preferred":[
        "\u8def\u6613\u65af\u6e56"
    ],
    "name:dut_x_preferred":[
        "Lake Louise"
    ],
    "name:eng_x_preferred":[
        "Lake Louise"
    ],
    "name:fre_x_preferred":[
        "Lake Louise"
    ],
    "name:ger_x_preferred":[
        "Lake Louise"
    ],
    "name:ita_x_preferred":[
        "Lake Louise"
    ],
    "name:nno_x_preferred":[
        "Lake Louise i Alberta"
    ],
    "name:nob_x_preferred":[
        "Lake Louise"
    ],
    "name:srp_x_preferred":[
        "\u041b\u0435\u0458\u043a \u041b\u0443\u0438\u0437"
    ],
    "name:swe_x_preferred":[
        "Lake Louise"
    ],
    "name:urd_x_preferred":[
        "\u0644\u06cc\u06a9 \u0644\u0648\u0626\u0633\u060c \u0627\u0644\u0628\u0631\u0679\u0627"
    ],
    "ne:ADM0CAP":0.0,
    "ne:ADM0NAME":"Canada",
    "ne:ADM0_A3":"CAN",
    "ne:ADM1NAME":"Alberta",
    "ne:ADMIN1_COD":0,
    "ne:CAPALT":0,
    "ne:CHANGED":0,
    "ne:CHECKME":0,
    "ne:COMPARE":0,
    "ne:DIFFASCII":0,
    "ne:ELEVATION":0.0,
    "ne:FEATURECLA":"Populated place",
    "ne:GEONAMEID":-1,
    "ne:GEONAMESNO":"No GeoNames match due to small population, not in GeoNames, or poor NEV placement.",
    "ne:GN_POP":0,
    "ne:GTOPO30":0.0,
    "ne:ISO_A2":"CA",
    "ne:LABELRANK":2,
    "ne:LATITUDE":51.433694,
    "ne:LONGITUDE":-116.183281,
    "ne:LS_MATCH":1,
    "ne:LS_NAME":"Lake Louise",
    "ne:MAX_AREAKM":3.0,
    "ne:MAX_AREAMI":1.0,
    "ne:MAX_BBXMAX":-116.166667,
    "ne:MAX_BBXMIN":-116.191667,
    "ne:MAX_BBYMAX":51.433333,
    "ne:MAX_BBYMIN":51.408333,
    "ne:MAX_NATSCA":20.0,
    "ne:MAX_PERKM":9.0,
    "ne:MAX_PERMI":6.0,
    "ne:MAX_POP10":1248,
    "ne:MAX_POP20":1248,
    "ne:MAX_POP300":0,
    "ne:MAX_POP310":0,
    "ne:MAX_POP50":0,
    "ne:MEAN_BBXC":-116.176389,
    "ne:MEAN_BBYC":51.423611,
    "ne:MEGACITY":0,
    "ne:MIN_AREAKM":3.0,
    "ne:MIN_AREAMI":1.0,
    "ne:MIN_BBXMAX":-116.166667,
    "ne:MIN_BBXMIN":-116.191667,
    "ne:MIN_BBYMAX":51.433333,
    "ne:MIN_BBYMIN":51.408333,
    "ne:MIN_PERKM":9.0,
    "ne:MIN_PERMI":6.0,
    "ne:NAME":"Lake Louise",
    "ne:NAMEASCII":"Lake Louise",
    "ne:NAMEDIFF":0,
    "ne:NATSCALE":20,
    "ne:POP1950":0,
    "ne:POP1955":0,
    "ne:POP1960":0,
    "ne:POP1965":0,
    "ne:POP1970":0,
    "ne:POP1975":0,
    "ne:POP1980":0,
    "ne:POP1985":0,
    "ne:POP1990":0,
    "ne:POP1995":0,
    "ne:POP2000":0,
    "ne:POP2005":0,
    "ne:POP2010":0,
    "ne:POP2015":0,
    "ne:POP2020":0,
    "ne:POP2025":0,
    "ne:POP2050":0,
    "ne:POP_MAX":1248,
    "ne:POP_MIN":1248,
    "ne:POP_OTHER":974,
    "ne:RANK_MAX":3,
    "ne:RANK_MIN":3,
    "ne:SCALERANK":7,
    "ne:SOV0NAME":"Canada",
    "ne:SOV_A3":"CAN",
    "ne:UN_FID":0,
    "ne:UN_LAT":0.0,
    "ne:UN_LONG":0.0,
    "ne:WORLDCITY":0,
    "ne:min_zoom":6.7,
    "wof:name":"Lake Louise",
    "wof:placetype":"locality"
},
  "geometry": {"coordinates":[-116.18328068221791,51.43369386708417],"type":"Point"}
}