{
  "type": "Feature",
  "properties": {
    "iso:country":"CA",
    "name:eng_x_preferred":[
        "Bounty"
    ],
    "name:fas_x_preferred":[
        "\u0628\u0627\u0648\u0646\u062a\u06cc"
    ],
    "name:nld_x_preferred":[
        "Bounty"
    ],
    "qs_pg:aaroncc":"CA",
    "qs_pg:name":"Bounty",
    "qs_pg:name_adm0":"Canada",
    "qs_pg:name_adm1":"Saskatchewan",
    "qs_pg:photos":5,
    "qs_pg:photos_1k":1,
    "qs_pg:photos_9k":1,
    "qs_pg:photos_9r":1,
    "qs_pg:photos_all":5,
    "qs_pg:photos_sr":1,
    "qs_pg:pop_sr":0,
    "qs_pg:qs_pg_placetype":"locality",
    "qs_pg:qs_pg_placetype_gp":"Town",
    "qs_pg:woe_adm0":23424775,
    "woe:adm0_id":23424775,
    "woe:name_adm0":"Canada",
    "woe:name_adm1":"Saskatchewan",
    "woe:placetype":"Town",
    "wof:name":"Bounty",
    "wof:placetype":"locality"
},
  "geometry": {"coordinates":[-107.363056,51.523043],"type":"Point"}
}