{
  "type": "Feature",
  "properties": {
    "gn:admin1_code":"8.0",
    "gn:asciiname":"Bentpath",
    "gn:country_code":"CA",
    "gn:dem":195,
    "gn:feature_class":"P",
    "gn:feature_code":"PPL",
    "gn:name":"Bentpath",
    "gn:population":0,
    "gn:timezone":"America/Toronto",
    "iso:country":"CA",
    "name:cat_x_preferred":[
        "Bentpath"
    ],
    "name:deu_x_preferred":[
        "Bentpath"
    ],
    "name:gla_x_preferred":[
        "Bentpath"
    ],
    "name:gle_x_preferred":[
        "Bentpath"
    ],
    "name:sco_x_preferred":[
        "Bentpath"
    ],
    "wof:name":"Bentpath",
    "wof:placetype":"locality"
},
  "geometry": {"coordinates":[-82.17491,42.71235],"type":"Point"}
}