{
  "type": "Feature",
  "properties": {
    "gn:admin1_code":"11",
    "gn:asciiname":"Strong Pine",
    "gn:country_code":"CA",
    "gn:dem":466,
    "gn:feature_class":"P",
    "gn:feature_code":"PPLL",
    "gn:name":"Strong Pine",
    "gn:population":0,
    "gn:timezone":"America/Regina",
    "iso:country":"CA",
    "wof:name":"Strong Pine",
    "wof:placetype":"locality"
},
  "geometry": {"coordinates":[-105.25098,53.31678],"type":"Point"}
}