{
  "type": "Feature",
  "properties": {
    "gn:admin1_code":"10",
    "gn:admin2_code":"14.0",
    "gn:admin3_code":"62080.0",
    "gn:asciiname":"Lac-Saint-Louis",
    "gn:country_code":"CA",
    "gn:dem":469,
    "gn:feature_class":"P",
    "gn:feature_code":"PPL",
    "gn:name":"Lac-Saint-Louis",
    "gn:population":0,
    "gn:timezone":"America/Toronto",
    "iso:country":"CA",
    "wof:name":"Lac-Saint-Louis",
    "wof:placetype":"locality"
},
  "geometry": {"coordinates":[-73.80514000000002,46.56115],"type":"Point"}
}