{
  "type": "Feature",
  "properties": {
    "gn:admin1_code":"1",
    "gn:asciiname":"Ridgeclough",
    "gn:country_code":"CA",
    "gn:dem":613,
    "gn:feature_class":"P",
    "gn:feature_code":"PPLL",
    "gn:name":"Ridgeclough",
    "gn:population":0,
    "gn:timezone":"America/Edmonton",
    "iso:country":"CA",
    "wof:name":"Ridgeclough",
    "wof:placetype":"locality"
},
  "geometry": {"coordinates":[-110.03485000000001,52.93346],"type":"Point"}
}