{
  "type": "Feature",
  "properties": {
    "gn:admin1_code":"7",
    "gn:asciiname":"Martins Brook",
    "gn:country_code":"CA",
    "gn:dem":30,
    "gn:feature_class":"P",
    "gn:feature_code":"PPL",
    "gn:name":"Martins Brook",
    "gn:population":0,
    "gn:timezone":"America/Halifax",
    "iso:country":"CA",
    "wof:name":"Martins Brook",
    "wof:placetype":"locality"
},
  "geometry": {"coordinates":[-64.3395,44.40878],"type":"Point"}
}