{
  "type": "Feature",
  "properties": {
    "gn:admin1_code":"8",
    "gn:asciiname":"Lower Holleford",
    "gn:country_code":"CA",
    "gn:dem":156,
    "gn:feature_class":"P",
    "gn:feature_code":"PPL",
    "gn:name":"Lower Holleford",
    "gn:population":0,
    "gn:timezone":"America/Toronto",
    "iso:country":"CA",
    "wof:name":"Lower Holleford",
    "wof:placetype":"locality"
},
  "geometry": {"coordinates":[-76.62567,44.46923],"type":"Point"}
}