{
  "type": "Feature",
  "properties": {
    "gn:admin1_code":"7",
    "gn:asciiname":"Hilltown",
    "gn:country_code":"CA",
    "gn:dem":81,
    "gn:feature_class":"P",
    "gn:feature_code":"PPL",
    "gn:name":"Hilltown",
    "gn:population":0,
    "gn:timezone":"America/Halifax",
    "iso:country":"CA",
    "wof:name":"Hilltown",
    "wof:placetype":"locality"
},
  "geometry": {"coordinates":[-65.90355,44.31593],"type":"Point"}
}