{
  "type": "Feature",
  "properties": {
    "gn:admin1_code":"7.0",
    "gn:asciiname":"Woodfield",
    "gn:country_code":"CA",
    "gn:dem":208,
    "gn:feature_class":"P",
    "gn:feature_code":"PPLL",
    "gn:name":"Woodfield",
    "gn:population":0,
    "gn:timezone":"America/Halifax",
    "iso:country":"CA",
    "wof:name":"Woodfield",
    "wof:placetype":"locality"
},
  "geometry": {"coordinates":[-62.38191,45.51685],"type":"Point"}
}