{
  "type": "Feature",
  "properties": {
    "gn:admin1_code":"1.0",
    "gn:asciiname":"Allingham",
    "gn:country_code":"CA",
    "gn:dem":895,
    "gn:feature_class":"P",
    "gn:feature_code":"PPLL",
    "gn:name":"Allingham",
    "gn:population":0,
    "gn:timezone":"America/Edmonton",
    "iso:country":"CA",
    "name:fra_x_preferred":[
        "Allingham"
    ],
    "name:jpn_x_preferred":[
        "\u30a2\u30ea\u30f3\u30ac\u30e0"
    ],
    "name:rus_x_preferred":[
        "\u0410\u043b\u043b\u0438\u043d\u0433\u0435\u043c"
    ],
    "name:swe_x_preferred":[
        "Allingham"
    ],
    "wof:name":"Allingham",
    "wof:placetype":"locality"
},
  "geometry": {"coordinates":[-113.60196000000001,51.70011],"type":"Point"}
}