{
  "type": "Feature",
  "properties": {
    "iso:country":"CA",
    "name:ara_x_preferred":[
        "\u0625\u064a\u0646\u0648\u062e"
    ],
    "name:ceb_x_preferred":[
        "Enoch"
    ],
    "name:ces_x_preferred":[
        "Enoch"
    ],
    "name:deu_x_preferred":[
        "Enoch"
    ],
    "name:eng_x_preferred":[
        "Enoch"
    ],
    "name:fas_x_preferred":[
        "\u062e\u0646\u0648\u062e"
    ],
    "name:fra_x_preferred":[
        "Enoch"
    ],
    "name:ita_x_preferred":[
        "Enoch"
    ],
    "name:kor_x_preferred":[
        "\uc5d0\ub179"
    ],
    "name:nor_x_preferred":[
        "Henok"
    ],
    "name:pol_x_preferred":[
        "Enoch"
    ],
    "name:rus_x_preferred":[
        "\u042d\u043d\u043e\u0445"
    ],
    "name:slk_x_preferred":[
        "Henoch"
    ],
    "name:swe_x_preferred":[
        "Enoch"
    ],
    "name:yid_x_preferred":[
        "\u05d7\u05e0\u05d5\u05da"
    ],
    "qs:name":"Enoch",
    "qs:name_adm0":"Canada",
    "qs:name_adm1":"Alberta",
    "qs:photos":536,
    "qs:photos_1k":109,
    "qs:photos_9k":2,
    "qs:photos_9r":5,
    "qs:photos_all":536,
    "qs:photos_sr":7,
    "qs:placetype":"Town",
    "qs:pop_sr":"0",
    "wd:wordcount":310,
    "wof:name":"Enoch",
    "wof:placetype":"locality"
},
  "geometry": {"coordinates":[-113.695621,53.509897],"type":"Point"}
}