{
  "type": "Feature",
  "properties": {
    "iso:country":"CA",
    "name:eng_x_preferred":[
        "Enoch"
    ],
    "qs:name":"Enoch",
    "qs:name_adm0":"Canada",
    "qs:name_adm1":"Alberta",
    "qs:photos":536,
    "qs:photos_1k":109,
    "qs:photos_9k":2,
    "qs:photos_9r":5,
    "qs:photos_all":536,
    "qs:photos_sr":7,
    "qs:placetype":"Town",
    "qs:pop_sr":"0",
    "wd:wordcount":310,
    "wof:name":"Enoch",
    "wof:placetype":"locality"
},
  "geometry": {"coordinates":[-113.695621,53.509897],"type":"Point"}
}