{
  "type": "Feature",
  "properties": {
    "gn:admin1_code":"7",
    "gn:asciiname":"Rhodes Corner",
    "gn:country_code":"CA",
    "gn:dem":60,
    "gn:feature_class":"P",
    "gn:feature_code":"PPL",
    "gn:name":"Rhodes Corner",
    "gn:population":0,
    "gn:timezone":"America/Halifax",
    "iso:country":"CA",
    "wof:name":"Rhodes Corner",
    "wof:placetype":"locality"
},
  "geometry": {"coordinates":[-64.41784,44.37839],"type":"Point"}
}