{
  "type": "Feature",
  "properties": {
    "gn:country":"CA",
    "gn:fcode":"PPL",
    "gn:population":0,
    "iso:country":"CA",
    "name:eng_x_preferred":[
        "St. Lawrence"
    ],
    "qs:name":"St. Lawrence",
    "qs:name_adm0":"Canada",
    "qs:name_adm1":"Newfoundland and Labrador",
    "qs:photos":95,
    "qs:photos_1k":19,
    "qs:photos_9k":1,
    "qs:photos_9r":3,
    "qs:photos_all":95,
    "qs:photos_sr":3,
    "qs:placetype":"Town",
    "qs:pop_sr":"0",
    "wof:name":"St. Lawrence",
    "wof:placetype":"locality",
    "wof:population":0
},
  "geometry": {"coordinates":[-55.39832,46.91664],"type":"Point"}
}