{
  "type": "Feature",
  "properties": {
    "gn:admin1_code":"2",
    "gn:asciiname":"Gilpin",
    "gn:country_code":"CA",
    "gn:dem":510,
    "gn:feature_class":"P",
    "gn:feature_code":"PPL",
    "gn:name":"Gilpin",
    "gn:population":0,
    "gn:timezone":"America/Vancouver",
    "iso:country":"CA",
    "wof:name":"Gilpin",
    "wof:placetype":"locality"
},
  "geometry": {"coordinates":[-118.31667,49.00972],"type":"Point"}
}