{
  "type": "Feature",
  "properties": {
    "gn:admin1_code":"5",
    "gn:asciiname":"Southern Harbour Station",
    "gn:country_code":"CA",
    "gn:dem":112,
    "gn:feature_class":"P",
    "gn:feature_code":"PPLL",
    "gn:name":"Southern Harbour Station",
    "gn:population":0,
    "gn:timezone":"America/St_Johns",
    "iso:country":"CA",
    "wof:name":"Southern Harbour Station",
    "wof:placetype":"locality"
},
  "geometry": {"coordinates":[-53.91483,47.74989],"type":"Point"}
}