{
  "type": "Feature",
  "properties": {
    "gn:admin1_code":"3",
    "gn:asciiname":"Newdale",
    "gn:country_code":"CA",
    "gn:dem":603,
    "gn:feature_class":"P",
    "gn:feature_code":"PPL",
    "gn:name":"Newdale",
    "gn:population":0,
    "gn:timezone":"America/Winnipeg",
    "iso:country":"CA",
    "wof:name":"Newdale",
    "wof:placetype":"locality"
},
  "geometry": {"coordinates":[-100.20415,50.35171],"type":"Point"}
}