{
  "type": "Feature",
  "properties": {
    "gn:admin1_code":"9.0",
    "gn:asciiname":"Churchill",
    "gn:country_code":"CA",
    "gn:dem":56,
    "gn:feature_class":"P",
    "gn:feature_code":"PPLL",
    "gn:name":"Churchill",
    "gn:population":0,
    "gn:timezone":"America/Halifax",
    "iso:country":"CA",
    "name:ara_x_preferred":[
        "\u062a\u0634\u0631\u0634\u0644"
    ],
    "name:ben_x_preferred":[
        "\u099a\u09be\u09b0\u09cd\u099a\u09bf\u09b2"
    ],
    "name:ell_x_preferred":[
        "\u03a4\u03c3\u03cc\u03c1\u03c4\u03c3\u03b9\u03bb"
    ],
    "name:fas_x_preferred":[
        "\u0686\u0631\u0686\u06cc\u0644"
    ],
    "name:fra_x_preferred":[
        "Churchill"
    ],
    "name:heb_x_preferred":[
        "\u05e6'\u05e8\u05e6'\u05d9\u05dc"
    ],
    "name:hin_x_preferred":[
        "\u091a\u0930\u094d\u091a\u093f\u0932"
    ],
    "name:hun_x_preferred":[
        "Churchill"
    ],
    "name:ind_x_preferred":[
        "Churchill"
    ],
    "name:kor_x_preferred":[
        "\ucc98\uce60"
    ],
    "name:por_x_preferred":[
        "Churchill"
    ],
    "name:urd_x_preferred":[
        "\u0686\u0631\u0686\u0644"
    ],
    "name:vie_x_preferred":[
        "S\u00f4ng Churchill"
    ],
    "wof:name":"Churchill",
    "wof:placetype":"locality"
},
  "geometry": {"coordinates":[-63.332,46.21682],"type":"Point"}
}