{
  "type": "Feature",
  "properties": {
    "gn:admin1_code":"4.0",
    "gn:asciiname":"Berryton",
    "gn:country_code":"CA",
    "gn:dem":107,
    "gn:feature_class":"P",
    "gn:feature_code":"PPL",
    "gn:name":"Berryton",
    "gn:population":0,
    "gn:timezone":"America/Moncton",
    "iso:country":"CA",
    "name:deu_x_preferred":[
        "Berryton"
    ],
    "wof:name":"Berryton",
    "wof:placetype":"locality"
},
  "geometry": {"coordinates":[-64.87513,45.88966],"type":"Point"}
}