{
  "type": "Feature",
  "properties": {
    "gn:admin1_code":"11",
    "gn:asciiname":"High Tor",
    "gn:country_code":"CA",
    "gn:dem":574,
    "gn:feature_class":"P",
    "gn:feature_code":"PPLL",
    "gn:name":"High Tor",
    "gn:population":0,
    "gn:timezone":"America/Regina",
    "iso:country":"CA",
    "name:ceb_x_preferred":[
        "High Tor"
    ],
    "name:swe_x_preferred":[
        "High Tor"
    ],
    "wof:name":"High Tor",
    "wof:placetype":"locality"
},
  "geometry": {"coordinates":[-103.30095,52.4667],"type":"Point"}
}