{
  "type": "Feature",
  "properties": {
    "gn:admin1_code":"7",
    "gn:asciiname":"Vaughan",
    "gn:country_code":"CA",
    "gn:dem":108,
    "gn:feature_class":"P",
    "gn:feature_code":"PPL",
    "gn:name":"Vaughan",
    "gn:population":0,
    "gn:timezone":"America/Halifax",
    "iso:country":"CA",
    "wof:name":"Vaughan",
    "wof:placetype":"locality"
},
  "geometry": {"coordinates":[-64.23118000000001,44.84067],"type":"Point"}
}