{
  "type": "Feature",
  "properties": {
    "gn:country":"CA",
    "gn:fcode":"ADMD",
    "gn:pop":0,
    "iso:country":"CA",
    "name:eng_x_preferred":[
        "Lake of Bays"
    ],
    "qs:name":"Lake of Bays",
    "qs:photos_9r":0,
    "qs:photos_sr":0,
    "qs:pop_sr":"0",
    "wd:population":3506,
    "wd:wordcount":690,
    "wof:name":"Lake of Bays",
    "wof:placetype":"localadmin",
    "wof:population":3506
},
  "geometry": {"coordinates":[-78.99961,45.25011],"type":"Point"}
}