{
  "type": "Feature",
  "properties": {
    "gn:admin1_code":"8.0",
    "gn:asciiname":"Brinkman's Corners",
    "gn:country_code":"CA",
    "gn:dem":218,
    "gn:feature_class":"P",
    "gn:feature_code":"PPL",
    "gn:name":"Brinkman's Corners",
    "gn:population":0,
    "gn:timezone":"America/Toronto",
    "iso:country":"CA",
    "wof:name":"Brinkman's Corners",
    "wof:placetype":"locality"
},
  "geometry": {"coordinates":[-81.39428000000002,45.14532],"type":"Point"}
}