{
  "type": "Feature",
  "properties": {
    "iso:country":"CA",
    "name:eng_x_preferred":[
        "Franklin Beach"
    ],
    "qs:gn_local":0,
    "qs:local_max":20,
    "qs:local_sum":20,
    "qs:localhoods":1,
    "qs:name":"Franklin Beach",
    "qs:name_adm0":"Canada",
    "qs:name_adm1":"Ontario",
    "qs:name_adm2":"York",
    "qs:name_local":"Willow Beach",
    "qs:photo_max":7,
    "qs:photo_sum":20,
    "qs:placetype":"Suburb",
    "qs:quad_count":5,
    "qs:woe_adm0":23424775,
    "qs:woe_adm1":2344922,
    "qs:woe_adm2":29375112,
    "qs:woe_funk":"Grouping neighborhood",
    "qs:woe_lau":0,
    "qs:woe_local":55999461,
    "qs:woe_ver":"7.10.0",
    "wof:lang":[
        "eng"
    ],
    "wof:name":"Franklin Beach",
    "wof:placetype":"neighbourhood"
},
  "geometry": {"coordinates":[-79.383545,44.3209],"type":"Point"}
}