{
  "type": "Feature",
  "properties": {
    "iso:country":"CA",
    "name:eng_x_preferred":[
        "Marion Bridge"
    ],
    "name:gla_x_preferred":[
        "Drochaid Mhira"
    ],
    "name:gle_x_preferred":[
        "Drochaid Mhira"
    ],
    "qs:name":"Marion Bridge",
    "qs:name_adm0":"Canada",
    "qs:name_adm1":"Nova Scotia",
    "qs:photos":66,
    "qs:photos_1k":13,
    "qs:photos_9k":1,
    "qs:photos_9r":2,
    "qs:photos_all":66,
    "qs:photos_sr":2,
    "qs:placetype":"Town",
    "qs:pop_sr":"0",
    "wd:wordcount":28,
    "wof:name":"Marion Bridge",
    "wof:placetype":"locality"
},
  "geometry": {"coordinates":[-60.213031,45.984796],"type":"Point"}
}