{
  "type": "Feature",
  "properties": {
    "gn:admin1_code":"5",
    "gn:asciiname":"Ming's Bight",
    "gn:country_code":"CA",
    "gn:dem":106,
    "gn:feature_class":"P",
    "gn:feature_code":"PPL",
    "gn:name":"Ming's Bight",
    "gn:population":0,
    "gn:timezone":"America/St_Johns",
    "iso:country":"CA",
    "wof:name":"Ming's Bight",
    "wof:placetype":"locality"
},
  "geometry": {"coordinates":[-56.04816,49.98327000000001],"type":"Point"}
}