{
  "type": "Feature",
  "properties": {
    "iso:country":"CA",
    "name:eng_x_preferred":[
        "Armdale"
    ],
    "name:jpn_x_preferred":[
        "\u30a2\u30fc\u30e0\u30c7\u30fc\u30eb"
    ],
    "name:nld_x_preferred":[
        "Armdale"
    ],
    "qs:gn_adm0_cc":"CA",
    "qs:gn_local":6324729,
    "qs:gn_nam_loc":"Halifax, Halifax, Nova Scotia, CA",
    "qs:gn_namadm1":"07",
    "qs:local_max":32392,
    "qs:local_sum":46326,
    "qs:localhoods":10,
    "qs:name":"Armdale",
    "qs:name_adm0":"Canada",
    "qs:name_adm1":"Nova Scotia",
    "qs:name_adm2":"Halifax",
    "qs:name_local":"Halifax",
    "qs:photo_max":541,
    "qs:photo_sum":1559,
    "qs:placetype":"Suburb",
    "qs:quad_count":55,
    "qs:woe_adm0":23424775,
    "qs:woe_adm1":2344921,
    "qs:woe_adm2":29375176,
    "qs:woe_lau":0,
    "qs:woe_local":4177,
    "qs:woe_ver":"7.10.0",
    "wd:wordcount":506,
    "wof:lang":[
        "eng"
    ],
    "wof:name":"Armdale",
    "wof:placetype":"neighbourhood"
},
  "geometry": {"coordinates":[-63.619805,44.640959],"type":"Point"}
}