{
  "type": "Feature",
  "properties": {
    "gn:admin1_code":"4",
    "gn:asciiname":"Ratter Corner",
    "gn:country_code":"CA",
    "gn:dem":142,
    "gn:feature_class":"P",
    "gn:feature_code":"PPL",
    "gn:name":"Ratter Corner",
    "gn:population":0,
    "gn:timezone":"America/Moncton",
    "iso:country":"CA",
    "wof:name":"Ratter Corner",
    "wof:placetype":"locality"
},
  "geometry": {"coordinates":[-65.58821999999999,45.64061],"type":"Point"}
}