{
  "type": "Feature",
  "properties": {
    "gn:country":"CA",
    "gn:fcode":"PPL",
    "gn:pop":0,
    "iso:country":"CA",
    "name:eng_x_preferred":[
        "Trinity"
    ],
    "qs:name":"Trinity",
    "qs:name_adm0":"Canada",
    "qs:name_adm1":"Newfoundland and Labrador",
    "qs:photos":1174,
    "qs:photos_1k":238,
    "qs:photos_9k":5,
    "qs:photos_9r":7,
    "qs:photos_all":1174,
    "qs:photos_sr":11,
    "qs:placetype":"Town",
    "qs:pop_sr":"0",
    "wd:wordcount":9391,
    "wof:name":"Trinity",
    "wof:placetype":"locality",
    "wof:population":0
},
  "geometry": {"coordinates":[-53.36477,48.36659],"type":"Point"}
}