{
  "type": "Feature",
  "properties": {
    "gn:admin1_code":"8",
    "gn:asciiname":"Springvale",
    "gn:country_code":"CA",
    "gn:dem":204,
    "gn:feature_class":"P",
    "gn:feature_code":"PPL",
    "gn:name":"Springvale",
    "gn:population":0,
    "gn:timezone":"America/Toronto",
    "iso:country":"CA",
    "name:ceb_x_preferred":[
        "Springvale"
    ],
    "name:deu_x_preferred":[
        "Springvale"
    ],
    "name:jpn_x_preferred":[
        "\u30b9\u30d7\u30ea\u30f3\u30b0\u30f4\u30a7\u30a4\u30eb"
    ],
    "name:pol_x_preferred":[
        "Springvale"
    ],
    "name:spa_x_preferred":[
        "Springvale"
    ],
    "name:swe_x_preferred":[
        "Springvale"
    ],
    "wof:name":"Springvale",
    "wof:placetype":"locality"
},
  "geometry": {"coordinates":[-81.90361,43.17056],"type":"Point"}
}