{
  "type": "Feature",
  "properties": {
    "gn:admin1_code":"8",
    "gn:asciiname":"Springvale",
    "gn:country_code":"CA",
    "gn:dem":204,
    "gn:feature_class":"P",
    "gn:feature_code":"PPL",
    "gn:name":"Springvale",
    "gn:population":0,
    "gn:timezone":"America/Toronto",
    "iso:country":"CA",
    "wof:name":"Springvale",
    "wof:placetype":"locality"
},
  "geometry": {"coordinates":[-81.90361,43.17056],"type":"Point"}
}