{
  "type": "Feature",
  "properties": {
    "gn:admin1_code":"4",
    "gn:asciiname":"Richibucto-Village",
    "gn:country_code":"CA",
    "gn:dem":6,
    "gn:feature_class":"P",
    "gn:feature_code":"PPL",
    "gn:name":"Richibucto-Village",
    "gn:population":0,
    "gn:timezone":"America/Moncton",
    "iso:country":"CA",
    "wof:name":"Richibucto-Village",
    "wof:placetype":"locality"
},
  "geometry": {"coordinates":[-64.75457,46.65504],"type":"Point"}
}