{
  "type": "Feature",
  "properties": {
    "gn:admin1_code":"8.0",
    "gn:asciiname":"Clardon Beach",
    "gn:country_code":"CA",
    "gn:dem":223,
    "gn:feature_class":"P",
    "gn:feature_code":"PPL",
    "gn:name":"Clardon Beach",
    "gn:population":0,
    "gn:timezone":"America/Toronto",
    "iso:country":"CA",
    "wof:name":"Clardon Beach",
    "wof:placetype":"locality"
},
  "geometry": {"coordinates":[-79.46805999999999,44.23361],"type":"Point"}
}