{
  "type": "Feature",
  "properties": {
    "gn:admin1_code":"5.0",
    "gn:asciiname":"Salt Harbour",
    "gn:country_code":"CA",
    "gn:dem":7,
    "gn:feature_class":"P",
    "gn:feature_code":"PPL",
    "gn:name":"Salt Harbour",
    "gn:population":0,
    "gn:timezone":"America/St_Johns",
    "iso:country":"CA",
    "wof:name":"Salt Harbour",
    "wof:placetype":"locality"
},
  "geometry": {"coordinates":[-54.61462,49.64796],"type":"Point"}
}