{
  "type": "Feature",
  "properties": {
    "gn:admin1_code":"2",
    "gn:asciiname":"McConnel",
    "gn:country_code":"CA",
    "gn:dem":747,
    "gn:feature_class":"P",
    "gn:feature_code":"PPL",
    "gn:name":"McConnel",
    "gn:population":0,
    "gn:timezone":"America/Creston",
    "iso:country":"CA",
    "name:deu_x_preferred":[
        "McConnel"
    ],
    "wof:name":"McConnel",
    "wof:placetype":"locality"
},
  "geometry": {"coordinates":[-116.33963,49.15549],"type":"Point"}
}