{
  "type": "Feature",
  "properties": {
    "gn:admin1_code":"8",
    "gn:asciiname":"Rosegrove Beach",
    "gn:country_code":"CA",
    "gn:dem":276,
    "gn:feature_class":"P",
    "gn:feature_code":"PPL",
    "gn:name":"Rosegrove Beach",
    "gn:population":0,
    "gn:timezone":"America/Toronto",
    "iso:country":"CA",
    "wof:name":"Rosegrove Beach",
    "wof:placetype":"locality"
},
  "geometry": {"coordinates":[-80.02806,48.02972000000001],"type":"Point"}
}