{
  "type": "Feature",
  "properties": {
    "gn:admin1_code":"7",
    "gn:asciiname":"Eight Island Lake",
    "gn:country_code":"CA",
    "gn:dem":78,
    "gn:feature_class":"P",
    "gn:feature_code":"PPL",
    "gn:name":"Eight Island Lake",
    "gn:population":0,
    "gn:timezone":"America/Halifax",
    "iso:country":"CA",
    "wof:name":"Eight Island Lake",
    "wof:placetype":"locality"
},
  "geometry": {"coordinates":[-61.94641,45.35662],"type":"Point"}
}