{
  "type": "Feature",
  "properties": {
    "gn:admin1_code":"8",
    "gn:asciiname":"Six Mile Corner",
    "gn:country_code":"CA",
    "gn:dem":385,
    "gn:feature_class":"P",
    "gn:feature_code":"PPLL",
    "gn:name":"Six Mile Corner",
    "gn:population":0,
    "gn:timezone":"America/Winnipeg",
    "iso:country":"CA",
    "wof:name":"Six Mile Corner",
    "wof:placetype":"locality"
},
  "geometry": {"coordinates":[-92.70452,49.78474],"type":"Point"}
}