{
  "type": "Feature",
  "properties": {
    "gn:admin1_code":"8",
    "gn:asciiname":"Laurel",
    "gn:country_code":"CA",
    "gn:dem":492,
    "gn:feature_class":"P",
    "gn:feature_code":"PPL",
    "gn:name":"Laurel",
    "gn:population":0,
    "gn:timezone":"America/Toronto",
    "iso:country":"CA",
    "name:bul_x_preferred":[
        "\u041b\u043e\u0440\u044a\u043b"
    ],
    "name:cat_x_preferred":[
        "Laurel"
    ],
    "name:ceb_x_preferred":[
        "Laurel"
    ],
    "name:ces_x_preferred":[
        "Laurel"
    ],
    "name:deu_x_preferred":[
        "Laurel"
    ],
    "name:fra_x_preferred":[
        "Laurel"
    ],
    "name:ita_x_preferred":[
        "Laurel"
    ],
    "name:jpn_x_preferred":[
        "\u30ed\u30fc\u30ec\u30eb"
    ],
    "name:nld_x_preferred":[
        "Laurel"
    ],
    "name:pol_x_preferred":[
        "Laurel"
    ],
    "name:por_x_preferred":[
        "Laurel"
    ],
    "name:rus_x_preferred":[
        "\u041b\u0430\u0432\u0440"
    ],
    "name:slk_x_preferred":[
        "Laurel"
    ],
    "name:spa_x_preferred":[
        "Laurel"
    ],
    "name:srp_x_preferred":[
        "\u041b\u043e\u0440\u0435\u043b"
    ],
    "name:swe_x_preferred":[
        "Laurel"
    ],
    "name:tgl_x_preferred":[
        "Laurel"
    ],
    "name:ukr_x_preferred":[
        "\u041b\u043e\u0440\u0435\u043b"
    ],
    "name:vol_x_preferred":[
        "Laurel"
    ],
    "wof:name":"Laurel",
    "wof:placetype":"locality"
},
  "geometry": {"coordinates":[-80.20971999999998,43.9525],"type":"Point"}
}