{
  "type": "Feature",
  "properties": {
    "gn:admin1_code":"8",
    "gn:asciiname":"Laurel",
    "gn:country_code":"CA",
    "gn:dem":492,
    "gn:feature_class":"P",
    "gn:feature_code":"PPL",
    "gn:name":"Laurel",
    "gn:population":0,
    "gn:timezone":"America/Toronto",
    "iso:country":"CA",
    "wof:name":"Laurel",
    "wof:placetype":"locality"
},
  "geometry": {"coordinates":[-80.20971999999998,43.9525],"type":"Point"}
}