{
  "type": "Feature",
  "properties": {
    "gn:admin1_code":"11",
    "gn:asciiname":"Langbank",
    "gn:country_code":"CA",
    "gn:dem":661,
    "gn:feature_class":"P",
    "gn:feature_code":"PPLL",
    "gn:name":"Langbank",
    "gn:population":0,
    "gn:timezone":"America/Regina",
    "iso:country":"CA",
    "wof:name":"Langbank",
    "wof:placetype":"locality"
},
  "geometry": {"coordinates":[-102.30099,50.05003],"type":"Point"}
}