{
  "type": "Feature",
  "properties": {
    "gn:admin1_code":"8",
    "gn:asciiname":"Keewaydin",
    "gn:country_code":"CA",
    "gn:dem":301,
    "gn:feature_class":"P",
    "gn:feature_code":"PPLL",
    "gn:name":"Keewaydin",
    "gn:population":0,
    "gn:timezone":"America/Toronto",
    "iso:country":"CA",
    "name:fra_x_preferred":[
        "Keewaydin"
    ],
    "wof:name":"Keewaydin",
    "wof:placetype":"locality"
},
  "geometry": {"coordinates":[-80.09389,47.08193],"type":"Point"}
}