{
  "type": "Feature",
  "properties": {
    "gn:admin1_code":"8",
    "gn:asciiname":"Living Springs",
    "gn:country_code":"CA",
    "gn:dem":421,
    "gn:feature_class":"P",
    "gn:feature_code":"PPL",
    "gn:name":"Living Springs",
    "gn:population":0,
    "gn:timezone":"America/Toronto",
    "iso:country":"CA",
    "wof:name":"Living Springs",
    "wof:placetype":"locality"
},
  "geometry": {"coordinates":[-80.40233000000001,43.75791],"type":"Point"}
}