{
  "type": "Feature",
  "properties": {
    "iso:country":"CA",
    "name:cat_x_preferred":[
        "Grandview"
    ],
    "name:ceb_x_preferred":[
        "Grandview"
    ],
    "name:deu_x_preferred":[
        "Grandview"
    ],
    "name:eng_x_preferred":[
        "Grandview"
    ],
    "name:fin_x_preferred":[
        "Grandview"
    ],
    "name:fra_x_preferred":[
        "Grandview"
    ],
    "name:ita_x_preferred":[
        "Grandview"
    ],
    "name:kor_x_preferred":[
        "\uadf8\ub79c\ub4dc\ubdf0"
    ],
    "name:nld_x_preferred":[
        "Grandview"
    ],
    "name:pol_x_preferred":[
        "Grandview"
    ],
    "name:srp_x_preferred":[
        "\u0413\u0440\u0430\u043d\u0434\u0432\u0458\u0443"
    ],
    "name:swe_x_preferred":[
        "Grandview"
    ],
    "name:ukr_x_preferred":[
        "\u0413\u0440\u0430\u043d\u0434\u0432'\u044e"
    ],
    "name:vol_x_preferred":[
        "Grandview"
    ],
    "name:zho_x_preferred":[
        "\u683c\u5170\u5fb7\u7ef4\u5c24"
    ],
    "wof:lang":[
        "eng"
    ],
    "wof:name":"Grandview",
    "wof:placetype":"neighbourhood"
},
  "geometry": {"coordinates":[-79.415488,43.80613],"type":"Point"}
}