{
  "type": "Feature",
  "properties": {
    "iso:country":"CA",
    "name:eng_x_preferred":[
        "Grandview"
    ],
    "wof:lang":[
        "eng"
    ],
    "wof:name":"Grandview",
    "wof:placetype":"neighbourhood"
},
  "geometry": {"coordinates":[-79.415488,43.80613],"type":"Point"}
}