{
  "type": "Feature",
  "properties": {
    "gn:admin1_code":"10.0",
    "gn:admin2_code":"5.0",
    "gn:admin3_code":"45055.0",
    "gn:asciiname":"Capelton",
    "gn:country_code":"CA",
    "gn:dem":168,
    "gn:feature_class":"P",
    "gn:feature_code":"PPL",
    "gn:name":"Capelton",
    "gn:population":0,
    "gn:timezone":"America/Toronto",
    "iso:country":"CA",
    "wof:name":"Capelton",
    "wof:placetype":"locality"
},
  "geometry": {"coordinates":[-71.90000000000001,45.31667],"type":"Point"}
}