{
  "type": "Feature",
  "properties": {
    "gn:admin1_code":"4",
    "gn:asciiname":"Simpson Corner",
    "gn:country_code":"CA",
    "gn:dem":41,
    "gn:feature_class":"P",
    "gn:feature_code":"PPL",
    "gn:name":"Simpson Corner",
    "gn:population":0,
    "gn:timezone":"America/Moncton",
    "iso:country":"CA",
    "wof:name":"Simpson Corner",
    "wof:placetype":"locality"
},
  "geometry": {"coordinates":[-67.17492,45.22895],"type":"Point"}
}