{
  "type": "Feature",
  "properties": {
    "gn:admin1_code":"1",
    "gn:asciiname":"Meyonhk",
    "gn:country_code":"CA",
    "gn:dem":686,
    "gn:feature_class":"P",
    "gn:feature_code":"PPL",
    "gn:name":"Meyonhk",
    "gn:population":0,
    "gn:timezone":"America/Edmonton",
    "iso:country":"CA",
    "wof:name":"Meyonhk",
    "wof:placetype":"locality"
},
  "geometry": {"coordinates":[-113.44167,53.45556],"type":"Point"}
}