{
  "type": "Feature",
  "properties": {
    "gn:admin1_code":"8.0",
    "gn:asciiname":"Ardmore Beach",
    "gn:country_code":"CA",
    "gn:dem":175,
    "gn:feature_class":"P",
    "gn:feature_code":"PPLL",
    "gn:name":"Ardmore Beach",
    "gn:population":0,
    "gn:timezone":"America/Toronto",
    "iso:country":"CA",
    "wof:name":"Ardmore Beach",
    "wof:placetype":"locality"
},
  "geometry": {"coordinates":[-80.00577,44.7012],"type":"Point"}
}