{
  "type": "Feature",
  "properties": {
    "gn:admin1_code":"7",
    "gn:asciiname":"Mackdale",
    "gn:country_code":"CA",
    "gn:dem":86,
    "gn:feature_class":"P",
    "gn:feature_code":"PPL",
    "gn:name":"Mackdale",
    "gn:population":0,
    "gn:timezone":"America/Halifax",
    "iso:country":"CA",
    "wof:name":"Mackdale",
    "wof:placetype":"locality"
},
  "geometry": {"coordinates":[-61.35037,45.67735],"type":"Point"}
}