{
  "type": "Feature",
  "properties": {
    "gn:admin1_code":"7.0",
    "gn:asciiname":"Caribou",
    "gn:country_code":"CA",
    "gn:dem":16,
    "gn:feature_class":"P",
    "gn:feature_code":"PPL",
    "gn:name":"Caribou",
    "gn:population":0,
    "gn:timezone":"America/Halifax",
    "iso:country":"CA",
    "name:fra_x_preferred":[
        "Caribou"
    ],
    "name:por_x_preferred":[
        "Caribou"
    ],
    "wof:name":"Caribou",
    "wof:placetype":"locality"
},
  "geometry": {"coordinates":[-62.6964,45.73275],"type":"Point"}
}