{
  "type": "Feature",
  "properties": {
    "gn:admin1_code":"4",
    "gn:asciiname":"Pineau",
    "gn:country_code":"CA",
    "gn:dem":74,
    "gn:feature_class":"P",
    "gn:feature_code":"PPL",
    "gn:name":"Pineau",
    "gn:population":0,
    "gn:timezone":"America/Moncton",
    "iso:country":"CA",
    "wof:name":"Pineau",
    "wof:placetype":"locality"
},
  "geometry": {"coordinates":[-65.33523000000001,46.70524],"type":"Point"}
}