{
  "type": "Feature",
  "properties": {
    "gn:admin1_code":"8",
    "gn:asciiname":"Lyons",
    "gn:country_code":"CA",
    "gn:dem":265,
    "gn:feature_class":"P",
    "gn:feature_code":"PPL",
    "gn:name":"Lyons",
    "gn:population":0,
    "gn:timezone":"America/Toronto",
    "iso:country":"CA",
    "wof:name":"Lyons",
    "wof:placetype":"locality"
},
  "geometry": {"coordinates":[-80.98694,42.8475],"type":"Point"}
}