{
  "type": "Feature",
  "properties": {
    "gn:admin1_code":"2",
    "gn:asciiname":"Rykerts",
    "gn:country_code":"CA",
    "gn:dem":531,
    "gn:feature_class":"P",
    "gn:feature_code":"PPLL",
    "gn:name":"Rykerts",
    "gn:population":0,
    "gn:timezone":"America/Creston",
    "iso:country":"CA",
    "wof:name":"Rykerts",
    "wof:placetype":"locality"
},
  "geometry": {"coordinates":[-116.50211000000002,48.99988],"type":"Point"}
}