{
  "type": "Feature",
  "properties": {
    "iso:country":"CA",
    "name:ara_x_preferred":[
        "\u0633\u064a\u0644\u0641\u0631\u0633\u062a\u0648\u0646"
    ],
    "name:ast_x_preferred":[
        "Silverstone"
    ],
    "name:ceb_x_preferred":[
        "Silverstone"
    ],
    "name:cym_x_preferred":[
        "Silverstone"
    ],
    "name:dan_x_preferred":[
        "Silverstone"
    ],
    "name:deu_x_preferred":[
        "Silverstone"
    ],
    "name:eng_x_preferred":[
        "Silverstone"
    ],
    "name:fas_x_preferred":[
        "\u0633\u06cc\u0644\u0648\u0631\u0633\u062a\u0648\u0646"
    ],
    "name:fin_x_preferred":[
        "Silverstone"
    ],
    "name:fra_x_preferred":[
        "Silverstone"
    ],
    "name:glg_x_preferred":[
        "Silverstone"
    ],
    "name:hun_x_preferred":[
        "Silverstone"
    ],
    "name:ita_x_preferred":[
        "Silverstone"
    ],
    "name:jpn_x_preferred":[
        "\u30b7\u30eb\u30d0\u30fc\u30b9\u30c8\u30fc\u30f3"
    ],
    "name:lav_x_preferred":[
        "Silverstona"
    ],
    "name:lit_x_preferred":[
        "Silverstonas"
    ],
    "name:nld_x_preferred":[
        "Silverstone"
    ],
    "name:pol_x_preferred":[
        "Silverstone"
    ],
    "name:por_x_preferred":[
        "Silverstone"
    ],
    "name:rus_x_preferred":[
        "\u0421\u0438\u043b\u0432\u0435\u0440\u0441\u0442\u043e\u043d"
    ],
    "name:scn_x_preferred":[
        "Silverstone"
    ],
    "name:spa_x_preferred":[
        "Silverstone"
    ],
    "name:swe_x_preferred":[
        "Silverstone"
    ],
    "name:ukr_x_preferred":[
        "\u0421\u0456\u043b\u044c\u0432\u0435\u0440\u0441\u0442\u043e\u0443\u043d"
    ],
    "name:vol_x_preferred":[
        "Silverstone"
    ],
    "name:zho_x_preferred":[
        "\u9521\u5c14\u5f17\u65af\u901a"
    ],
    "torsdfa:AREA_NAME":"Mount Olive-Silverstone-Jamestown (2)",
    "torsdfa:AREA_S_CD":"002",
    "wof:lang":[
        "eng"
    ],
    "wof:name":"Silverstone",
    "wof:placetype":"neighbourhood"
},
  "geometry": {"coordinates":[-79.588973,43.74844],"type":"Point"}
}