{
  "type": "Feature",
  "properties": {
    "iso:country":"CA",
    "name:eng_x_preferred":[
        "Silverstone"
    ],
    "torsdfa:AREA_NAME":"Mount Olive-Silverstone-Jamestown (2)",
    "torsdfa:AREA_S_CD":"002",
    "wof:lang":[
        "eng"
    ],
    "wof:name":"Silverstone",
    "wof:placetype":"neighbourhood"
},
  "geometry": {"coordinates":[-79.588973,43.74844],"type":"Point"}
}