{
  "type": "Feature",
  "properties": {
    "gn:country":"CA",
    "iso:country":"CA",
    "name:eng_x_preferred":[
        "Stoney Island"
    ],
    "name:nld_x_preferred":[
        "Stoney Island"
    ],
    "qs:name":"Stoney Island",
    "qs:name_adm0":"Canada",
    "qs:name_adm1":"Nova Scotia",
    "qs:photos":35,
    "qs:photos_1k":7,
    "qs:photos_9k":1,
    "qs:photos_9r":2,
    "qs:photos_all":35,
    "qs:photos_sr":2,
    "qs:placetype":"Town",
    "qs:pop_sr":"0",
    "wd:wordcount":67,
    "wof:name":"Stoney Island",
    "wof:placetype":"locality"
},
  "geometry": {"coordinates":[-65.58837800000001,43.450426],"type":"Point"}
}