{
  "type": "Feature",
  "properties": {
    "gn:admin1_code":"8.0",
    "gn:asciiname":"Belcreft Beach",
    "gn:country_code":"CA",
    "gn:dem":179,
    "gn:feature_class":"P",
    "gn:feature_code":"PPL",
    "gn:name":"Belcreft Beach",
    "gn:population":0,
    "gn:timezone":"America/Toronto",
    "iso:country":"CA",
    "wof:name":"Belcreft Beach",
    "wof:placetype":"locality"
},
  "geometry": {"coordinates":[-82.98917,42.01528],"type":"Point"}
}