{
  "type": "Feature",
  "properties": {
    "gn:admin1_code":"4",
    "gn:asciiname":"Tweedside",
    "gn:country_code":"CA",
    "gn:dem":151,
    "gn:feature_class":"P",
    "gn:feature_code":"PPL",
    "gn:name":"Tweedside",
    "gn:population":0,
    "gn:timezone":"America/Moncton",
    "iso:country":"CA",
    "wof:name":"Tweedside",
    "wof:placetype":"locality"
},
  "geometry": {"coordinates":[-67.01375,45.64467],"type":"Point"}
}