{
  "type": "Feature",
  "properties": {
    "gn:admin1_code":"12",
    "gn:asciiname":"Forty Mile",
    "gn:country_code":"CA",
    "gn:dem":287,
    "gn:feature_class":"P",
    "gn:feature_code":"PPLL",
    "gn:name":"Forty Mile",
    "gn:population":0,
    "gn:timezone":"America/Whitehorse",
    "iso:country":"CA",
    "wof:name":"Forty Mile",
    "wof:placetype":"locality"
},
  "geometry": {"coordinates":[-140.53643,64.42305],"type":"Point"}
}