{
  "type": "Feature",
  "properties": {
    "gn:admin1_code":"12",
    "gn:asciiname":"Forty Mile",
    "gn:country_code":"CA",
    "gn:dem":287,
    "gn:feature_class":"P",
    "gn:feature_code":"PPLL",
    "gn:name":"Forty Mile",
    "gn:population":0,
    "gn:timezone":"America/Whitehorse",
    "iso:country":"CA",
    "name:deu_x_preferred":[
        "Forty Mile"
    ],
    "name:fra_x_preferred":[
        "Forty Mile"
    ],
    "name:por_x_preferred":[
        "Forty Mile"
    ],
    "name:rus_x_preferred":[
        "\u0424\u043e\u0440\u0442\u0438-\u041c\u0430\u0439\u043b"
    ],
    "name:ukr_x_preferred":[
        "\u0424\u043e\u0440\u0442\u0456-\u041c\u0430\u0439\u043b"
    ],
    "wof:name":"Forty Mile",
    "wof:placetype":"locality"
},
  "geometry": {"coordinates":[-140.53643,64.42305],"type":"Point"}
}