{
  "type": "Feature",
  "properties": {
    "gn:admin1_code":"1",
    "gn:asciiname":"Shonts",
    "gn:country_code":"CA",
    "gn:dem":681,
    "gn:feature_class":"P",
    "gn:feature_code":"PPLL",
    "gn:name":"Shonts",
    "gn:population":0,
    "gn:timezone":"America/Edmonton",
    "iso:country":"CA",
    "wof:name":"Shonts",
    "wof:placetype":"locality"
},
  "geometry": {"coordinates":[-112.5852,53.33344],"type":"Point"}
}