{
  "type": "Feature",
  "properties": {
    "gn:admin1_code":"4",
    "gn:asciiname":"Nelson-Miramichi",
    "gn:country_code":"CA",
    "gn:dem":24,
    "gn:feature_class":"P",
    "gn:feature_code":"PPL",
    "gn:name":"Nelson-Miramichi",
    "gn:population":0,
    "gn:timezone":"America/Moncton",
    "iso:country":"CA",
    "wof:name":"Nelson-Miramichi",
    "wof:placetype":"locality"
},
  "geometry": {"coordinates":[-65.54061,46.9786],"type":"Point"}
}