{
  "type": "Feature",
  "properties": {
    "iso:country":"CA",
    "name:eng_x_preferred":[
        "Turcot Interchange"
    ],
    "name:fra_x_preferred":[
        "Turcot Interchange"
    ],
    "name:fra_x_variant":[
        "\u00c9changeur Turcot"
    ],
    "wof:name":"Turcot Interchange",
    "wof:placetype":"microhood"
},
  "geometry": {"coordinates":[-73.59985260691732,45.4679772743718],"type":"Point"}
}