{
  "type": "Feature",
  "properties": {
    "gn:admin1_code":"8",
    "gn:asciiname":"Sharps Corners",
    "gn:country_code":"CA",
    "gn:dem":146,
    "gn:feature_class":"P",
    "gn:feature_code":"PPL",
    "gn:name":"Sharps Corners",
    "gn:population":0,
    "gn:timezone":"America/Toronto",
    "iso:country":"CA",
    "wof:name":"Sharps Corners",
    "wof:placetype":"locality"
},
  "geometry": {"coordinates":[-77.00166999999998,44.335],"type":"Point"}
}