{
  "type": "Feature",
  "properties": {
    "gn:admin1_code":"8",
    "gn:asciiname":"Long Bay",
    "gn:country_code":"CA",
    "gn:dem":219,
    "gn:feature_class":"P",
    "gn:feature_code":"PPL",
    "gn:name":"Long Bay",
    "gn:population":0,
    "gn:timezone":"America/Toronto",
    "iso:country":"CA",
    "name:ceb_x_preferred":[
        "Long Bay"
    ],
    "name:deu_x_preferred":[
        "Long Bay"
    ],
    "name:swe_x_preferred":[
        "Long Bay"
    ],
    "wof:name":"Long Bay",
    "wof:placetype":"locality"
},
  "geometry": {"coordinates":[-82.40288000000002,45.80544],"type":"Point"}
}