{
  "type": "Feature",
  "properties": {
    "gn:admin1_code":"8",
    "gn:asciiname":"Quarries",
    "gn:country_code":"CA",
    "gn:dem":99,
    "gn:feature_class":"P",
    "gn:feature_code":"PPL",
    "gn:name":"Quarries",
    "gn:population":0,
    "gn:timezone":"America/Toronto",
    "iso:country":"CA",
    "wof:name":"Quarries",
    "wof:placetype":"locality"
},
  "geometry": {"coordinates":[-75.62805999999998,45.44472],"type":"Point"}
}