{
  "type": "Feature",
  "properties": {
    "gn:admin1_code":"7.0",
    "gn:asciiname":"East River St. Marys",
    "gn:country_code":"CA",
    "gn:dem":59,
    "gn:feature_class":"P",
    "gn:feature_code":"PPL",
    "gn:name":"East River St. Marys",
    "gn:population":0,
    "gn:timezone":"America/Halifax",
    "iso:country":"CA",
    "wof:name":"East River St. Marys",
    "wof:placetype":"locality"
},
  "geometry": {"coordinates":[-62.16581,45.39094],"type":"Point"}
}