{
  "type": "Feature",
  "properties": {
    "gn:admin1_code":"3",
    "gn:asciiname":"Skylake",
    "gn:country_code":"CA",
    "gn:dem":253,
    "gn:feature_class":"P",
    "gn:feature_code":"PPLL",
    "gn:name":"Skylake",
    "gn:population":0,
    "gn:timezone":"America/Winnipeg",
    "iso:country":"CA",
    "wof:name":"Skylake",
    "wof:placetype":"locality"
},
  "geometry": {"coordinates":[-97.36677,50.84691],"type":"Point"}
}