{
  "type": "Feature",
  "properties": {
    "iso:country":"CA",
    "name:eng_x_preferred":[
        "Moreton's Harbour"
    ],
    "name:nld_x_preferred":[
        "Moreton's Harbour"
    ],
    "name:nob_x_preferred":[
        "Moreton's Harbour"
    ],
    "qs:name":"Moreton's Harbour",
    "qs:name_adm0":"Canada",
    "qs:name_adm1":"Newfoundland and Labrador",
    "qs:photos":14,
    "qs:photos_1k":3,
    "qs:photos_9k":1,
    "qs:photos_9r":1,
    "qs:photos_all":14,
    "qs:photos_sr":1,
    "qs:placetype":"Town",
    "qs:pop_sr":"0",
    "wd:wordcount":86,
    "wof:name":"Moreton's Harbour",
    "wof:placetype":"locality"
},
  "geometry": {"coordinates":[-54.864065,49.570641],"type":"Point"}
}