{
  "type": "Feature",
  "properties": {
    "gn:country":"CA",
    "gn:fcode":"PPL",
    "gn:population":0,
    "iso:country":"CA",
    "name:eng_x_preferred":[
        "Middle Musquodoboit"
    ],
    "name:fra_x_preferred":[
        "Middle Musquodoboit"
    ],
    "qs:name":"Middle Musquodoboit",
    "qs:name_adm0":"Canada",
    "qs:name_adm1":"Nova Scotia",
    "qs:photos_9k":1,
    "qs:photos_9r":1,
    "qs:photos_all":3,
    "qs:photos_sr":0,
    "qs:placetype":"Town",
    "qs:pop_sr":"0",
    "wd:wordcount":498,
    "wof:name":"Middle Musquodoboit",
    "wof:placetype":"locality",
    "wof:population":0
},
  "geometry": {"coordinates":[-63.14867,45.05015],"type":"Point"}
}