{
  "type": "Feature",
  "properties": {
    "gn:admin1_code":"8",
    "gn:asciiname":"Fairview",
    "gn:country_code":"CA",
    "gn:dem":145,
    "gn:feature_class":"P",
    "gn:feature_code":"PPL",
    "gn:name":"Fairview",
    "gn:population":0,
    "gn:timezone":"America/Toronto",
    "iso:country":"CA",
    "wof:name":"Fairview",
    "wof:placetype":"locality"
},
  "geometry": {"coordinates":[-79.63145,43.58623],"type":"Point"}
}