{
  "type": "Feature",
  "properties": {
    "gn:admin1_code":"8.0",
    "gn:asciiname":"Anderson Lake",
    "gn:country_code":"CA",
    "gn:dem":229,
    "gn:feature_class":"P",
    "gn:feature_code":"PPL",
    "gn:name":"Anderson Lake",
    "gn:population":0,
    "gn:timezone":"America/Toronto",
    "iso:country":"CA",
    "name:ceb_x_preferred":[
        "Anderson Lake"
    ],
    "name:deu_x_preferred":[
        "Anderson Lake"
    ],
    "name:swe_x_preferred":[
        "Anderson Lake"
    ],
    "wof:name":"Anderson Lake",
    "wof:placetype":"locality"
},
  "geometry": {"coordinates":[-81.73317,46.23062],"type":"Point"}
}