{
  "type": "Feature",
  "properties": {
    "gn:admin1_code":"8",
    "gn:admin2_code":"3557",
    "gn:asciiname":"Sault Ship Canal",
    "gn:country_code":"CA",
    "gn:dem":174,
    "gn:feature_class":"P",
    "gn:feature_code":"PPLL",
    "gn:name":"Sault Ship Canal",
    "gn:population":0,
    "gn:timezone":"America/Toronto",
    "iso:country":"CA",
    "wof:name":"Sault Ship Canal",
    "wof:placetype":"locality"
},
  "geometry": {"coordinates":[-84.34822,46.51213],"type":"Point"}
}