{
  "type": "Feature",
  "properties": {
    "gn:admin1_code":"8.0",
    "gn:asciiname":"Wrigley Corners",
    "gn:country_code":"CA",
    "gn:dem":310,
    "gn:feature_class":"P",
    "gn:feature_code":"PPL",
    "gn:name":"Wrigley Corners",
    "gn:population":0,
    "gn:timezone":"America/Toronto",
    "iso:country":"CA",
    "wof:name":"Wrigley Corners",
    "wof:placetype":"locality"
},
  "geometry": {"coordinates":[-80.38484,43.29096],"type":"Point"}
}