{
  "type": "Feature",
  "properties": {
    "gn:admin1_code":"7",
    "gn:asciiname":"Summerville",
    "gn:country_code":"CA",
    "gn:dem":55,
    "gn:feature_class":"P",
    "gn:feature_code":"PPL",
    "gn:name":"Summerville",
    "gn:population":0,
    "gn:timezone":"America/Halifax",
    "iso:country":"CA",
    "wof:name":"Summerville",
    "wof:placetype":"locality"
},
  "geometry": {"coordinates":[-64.16409,45.09842],"type":"Point"}
}