{
  "type": "Feature",
  "properties": {
    "iso:country":"CA",
    "name:eng_x_preferred":[
        "Jollimore"
    ],
    "qs:gn_adm0_cc":"CA",
    "qs:gn_local":6324729,
    "qs:gn_nam_loc":"Halifax, Halifax, Nova Scotia, CA",
    "qs:gn_namadm1":"07",
    "qs:local_max":32392,
    "qs:local_sum":46326,
    "qs:localhoods":10,
    "qs:name":"Jollimore",
    "qs:name_adm0":"Canada",
    "qs:name_adm1":"Nova Scotia",
    "qs:name_adm2":"Halifax",
    "qs:name_local":"Halifax",
    "qs:photo_max":311,
    "qs:photo_sum":1087,
    "qs:placetype":"Suburb",
    "qs:quad_count":34,
    "qs:woe_adm0":23424775,
    "qs:woe_adm1":2344921,
    "qs:woe_adm2":29375176,
    "qs:woe_lau":0,
    "qs:woe_local":4177,
    "qs:woe_ver":"7.10.0",
    "wof:lang":[
        "eng"
    ],
    "wof:name":"Jollimore",
    "wof:placetype":"neighbourhood"
},
  "geometry": {"coordinates":[-63.60059,44.629825],"type":"Point"}
}