{
  "type": "Feature",
  "properties": {
    "iso:country":"CA",
    "name:eng_x_preferred":[
        "Fort Chambly National Historic Site"
    ],
    "name:eng_x_variant":[
        "Fort Chambly National Historic Site"
    ],
    "qs:gn_local":0,
    "qs:local_max":0,
    "qs:local_sum":0,
    "qs:localhoods":0,
    "qs:name":"Fort Chambly National Historic Site",
    "qs:name_adm0":"Canada",
    "qs:name_adm1":"Qu\u00e9bec",
    "qs:name_adm2":"Longueuil",
    "qs:name_en":"Fort Chambly National Historic Site",
    "qs:photo_max":309,
    "qs:photo_sum":462,
    "qs:placetype":"Suburb",
    "qs:quad_count":6,
    "qs:woe_adm0":23424775,
    "qs:woe_adm1":2344924,
    "qs:woe_adm2":29375100,
    "qs:woe_funk":"Parented by a neighborhood",
    "qs:woe_lau":0,
    "qs:woe_local":0,
    "qs:woe_ver":"7.3.1",
    "wof:name":"Fort Chambly National Historic Site",
    "wof:placetype":"neighbourhood"
},
  "geometry": {"coordinates":[-73.276915,45.449225],"type":"Point"}
}