{
  "type": "Feature",
  "properties": {
    "gn:admin1_code":"5.0",
    "gn:asciiname":"Black River",
    "gn:country_code":"CA",
    "gn:dem":13,
    "gn:feature_class":"P",
    "gn:feature_code":"PPLL",
    "gn:name":"Black River",
    "gn:population":0,
    "gn:timezone":"America/St_Johns",
    "iso:country":"CA",
    "name:fra_x_preferred":[
        "Black River"
    ],
    "wof:name":"Black River",
    "wof:placetype":"locality"
},
  "geometry": {"coordinates":[-54.16486,47.8832],"type":"Point"}
}