{
  "type": "Feature",
  "properties": {
    "gn:admin1_code":"5.0",
    "gn:asciiname":"East Landing",
    "gn:country_code":"CA",
    "gn:dem":-9999,
    "gn:feature_class":"P",
    "gn:feature_code":"PPLL",
    "gn:name":"East Landing",
    "gn:population":0,
    "gn:timezone":"America/St_Johns",
    "iso:country":"CA",
    "wof:name":"East Landing",
    "wof:placetype":"locality"
},
  "geometry": {"coordinates":[-53.06481,46.66658],"type":"Point"}
}