{
  "type": "Feature",
  "properties": {
    "iso:country":"CA",
    "name:eng_x_preferred":[
        "Gillis Lake"
    ],
    "name:gla_x_preferred":[
        "Loch a' Ghilliosaich"
    ],
    "qs:name":"Gillis Lake",
    "qs:name_adm0":"Canada",
    "qs:name_adm1":"Nova Scotia",
    "qs:photos":6,
    "qs:photos_1k":1,
    "qs:photos_9k":1,
    "qs:photos_9r":1,
    "qs:photos_all":6,
    "qs:photos_sr":1,
    "qs:placetype":"Town",
    "qs:pop_sr":"0",
    "wd:wordcount":54,
    "wof:name":"Gillis Lake",
    "wof:placetype":"locality"
},
  "geometry": {"coordinates":[-60.392435,46.05163],"type":"Point"}
}