{
  "type": "Feature",
  "properties": {
    "gn:admin1_code":"7",
    "gn:asciiname":"New Prospect",
    "gn:country_code":"CA",
    "gn:dem":28,
    "gn:feature_class":"P",
    "gn:feature_code":"PPL",
    "gn:name":"New Prospect",
    "gn:population":0,
    "gn:timezone":"America/Halifax",
    "iso:country":"CA",
    "name:deu_x_preferred":[
        "New Prospect"
    ],
    "wof:name":"New Prospect",
    "wof:placetype":"locality"
},
  "geometry": {"coordinates":[-64.27266,45.42632],"type":"Point"}
}