{
  "type": "Feature",
  "properties": {
    "iso:country":"CA",
    "name:cat_x_preferred":[
        "Irondale"
    ],
    "name:ceb_x_preferred":[
        "Irondale"
    ],
    "name:deu_x_preferred":[
        "Irondale"
    ],
    "name:fra_x_preferred":[
        "Irondale"
    ],
    "name:ido_x_preferred":[
        "Irondale"
    ],
    "name:ita_x_preferred":[
        "Irondale"
    ],
    "name:nld_x_preferred":[
        "Irondale"
    ],
    "name:pol_x_preferred":[
        "Irondale"
    ],
    "name:por_x_preferred":[
        "Irondale"
    ],
    "name:spa_x_preferred":[
        "Irondale"
    ],
    "name:srp_x_preferred":[
        "\u0410\u0458\u0440\u043e\u043d\u0434\u0435\u0458\u043b"
    ],
    "name:ukr_x_preferred":[
        "\u0410\u0439\u0440\u043e\u043d\u0434\u0435\u0439\u043b"
    ],
    "name:vol_x_preferred":[
        "Irondale"
    ],
    "qs_pg:aaroncc":"CA",
    "qs_pg:name":"Irondale",
    "qs_pg:name_adm0":"Canada",
    "qs_pg:name_adm1":"Ontario",
    "qs_pg:photos":47,
    "qs_pg:photos_1k":10,
    "qs_pg:photos_9k":1,
    "qs_pg:photos_9r":2,
    "qs_pg:photos_all":47,
    "qs_pg:photos_sr":2,
    "qs_pg:pop_sr":0,
    "qs_pg:qs_pg_placetype":"locality",
    "qs_pg:qs_pg_placetype_gp":"Town",
    "qs_pg:woe_adm0":23424775,
    "woe:adm0_id":23424775,
    "woe:name_adm0":"Canada",
    "woe:name_adm1":"Ontario",
    "woe:placetype":"Town",
    "wof:name":"Irondale",
    "wof:placetype":"locality"
},
  "geometry": {"coordinates":[-78.50099899999999,44.853069],"type":"Point"}
}