{
  "type": "Feature",
  "properties": {
    "gn:admin1_code":"10",
    "gn:admin2_code":"5.0",
    "gn:admin3_code":"44045.0",
    "gn:asciiname":"Way's Mills",
    "gn:country_code":"CA",
    "gn:dem":268,
    "gn:feature_class":"P",
    "gn:feature_code":"PPL",
    "gn:name":"Way's Mills",
    "gn:population":0,
    "gn:timezone":"America/Toronto",
    "iso:country":"CA",
    "wof:name":"Way's Mills",
    "wof:placetype":"locality"
},
  "geometry": {"coordinates":[-71.97676,45.10227],"type":"Point"}
}