{
  "type": "Feature",
  "properties": {
    "iso:country":"CA",
    "name:eng_x_preferred":[
        "Chedoke Park B"
    ],
    "qs:gn_adm0_cc":"CA",
    "qs:gn_local":5969782,
    "qs:gn_nam_loc":"hamilton",
    "qs:gn_namadm1":"08",
    "qs:local_max":3547,
    "qs:local_sum":20353,
    "qs:localhoods":46,
    "qs:name":"Chedoke Park B",
    "qs:name_adm0":"Canada",
    "qs:name_adm1":"Ontario",
    "qs:name_adm2":"Hamilton",
    "qs:name_local":"Hamilton",
    "qs:photo_max":28,
    "qs:photo_sum":69,
    "qs:placetype":"Suburb",
    "qs:quad_count":8,
    "qs:woe_adm0":23424775,
    "qs:woe_adm1":2344922,
    "qs:woe_adm2":29375120,
    "qs:woe_lau":0,
    "qs:woe_local":4125,
    "qs:woe_ver":"7.10.0",
    "wof:lang":[
        "eng"
    ],
    "wof:name":"Chedoke Park B",
    "wof:placetype":"neighbourhood"
},
  "geometry": {"coordinates":[-79.90722100000001,43.246419],"type":"Point"}
}