{
  "type": "Feature",
  "properties": {
    "gn:admin1_code":"8",
    "gn:asciiname":"Walls",
    "gn:country_code":"CA",
    "gn:dem":350,
    "gn:feature_class":"P",
    "gn:feature_code":"PPL",
    "gn:name":"Walls",
    "gn:population":0,
    "gn:timezone":"America/Toronto",
    "iso:country":"CA",
    "name:deu_x_preferred":[
        "Walls"
    ],
    "name:fra_x_preferred":[
        "Walls"
    ],
    "name:ita_x_preferred":[
        "Walls"
    ],
    "name:pol_x_preferred":[
        "Walls"
    ],
    "wof:name":"Walls",
    "wof:placetype":"locality"
},
  "geometry": {"coordinates":[-79.34611,45.48111],"type":"Point"}
}