{
  "type": "Feature",
  "properties": {
    "gn:country":"CA",
    "iso:country":"CA",
    "name:eng_x_preferred":[
        "Boutiliers Point"
    ],
    "qs:name":"Boutiliers Point",
    "qs:name_adm0":"Canada",
    "qs:name_adm1":"Nova Scotia",
    "qs:photos":69,
    "qs:photos_1k":14,
    "qs:photos_9k":1,
    "qs:photos_9r":2,
    "qs:photos_all":69,
    "qs:photos_sr":2,
    "qs:placetype":"Town",
    "qs:pop_sr":"0",
    "wd:wordcount":243,
    "wof:name":"Boutiliers Point",
    "wof:placetype":"locality"
},
  "geometry": {"coordinates":[-63.9506,44.66557],"type":"Point"}
}