{
  "type": "Feature",
  "properties": {
    "gn:admin1_code":"8",
    "gn:asciiname":"Martels Corners",
    "gn:country_code":"CA",
    "gn:dem":68,
    "gn:feature_class":"P",
    "gn:feature_code":"PPL",
    "gn:name":"Martels Corners",
    "gn:population":0,
    "gn:timezone":"America/Toronto",
    "iso:country":"CA",
    "wof:name":"Martels Corners",
    "wof:placetype":"locality"
},
  "geometry": {"coordinates":[-75.10833000000002,45.36833],"type":"Point"}
}