{
  "type": "Feature",
  "properties": {
    "gn:admin1_code":"1",
    "gn:asciiname":"Standard",
    "gn:country_code":"CA",
    "gn:dem":900,
    "gn:feature_class":"P",
    "gn:feature_code":"PPL",
    "gn:name":"Standard",
    "gn:population":0,
    "gn:timezone":"America/Edmonton",
    "iso:country":"CA",
    "wof:name":"Standard",
    "wof:placetype":"locality"
},
  "geometry": {"coordinates":[-112.98520000000001,51.11682],"type":"Point"}
}