{
  "type": "Feature",
  "properties": {
    "gn:admin1_code":"8",
    "gn:asciiname":"Golden Hill",
    "gn:country_code":"CA",
    "gn:dem":80,
    "gn:feature_class":"P",
    "gn:feature_code":"PPL",
    "gn:name":"Golden Hill",
    "gn:population":0,
    "gn:timezone":"America/Toronto",
    "iso:country":"CA",
    "wof:name":"Golden Hill",
    "wof:placetype":"locality"
},
  "geometry": {"coordinates":[-74.60583000000003,45.50778],"type":"Point"}
}