{
  "type": "Feature",
  "properties": {
    "gn:admin1_code":"10.0",
    "gn:admin2_code":"16.0",
    "gn:admin3_code":"46058.0",
    "gn:asciiname":"Domaine-Mont-Louis",
    "gn:country_code":"CA",
    "gn:dem":245,
    "gn:feature_class":"P",
    "gn:feature_code":"PPL",
    "gn:name":"Domaine-Mont-Louis",
    "gn:population":0,
    "gn:timezone":"America/Toronto",
    "iso:country":"CA",
    "wof:name":"Domaine-Mont-Louis",
    "wof:placetype":"locality"
},
  "geometry": {"coordinates":[-72.60595000000001,45.10032],"type":"Point"}
}