{
  "type": "Feature",
  "properties": {
    "gn:admin1_code":"7",
    "gn:asciiname":"Elderbank",
    "gn:country_code":"CA",
    "gn:dem":25,
    "gn:feature_class":"P",
    "gn:feature_code":"PPL",
    "gn:name":"Elderbank",
    "gn:population":0,
    "gn:timezone":"America/Halifax",
    "iso:country":"CA",
    "wof:name":"Elderbank",
    "wof:placetype":"locality"
},
  "geometry": {"coordinates":[-63.21633000000001,44.9803],"type":"Point"}
}