{
  "type": "Feature",
  "properties": {
    "gn:admin1_code":"11",
    "gn:asciiname":"Mount Royal",
    "gn:country_code":"CA",
    "gn:dem":575,
    "gn:feature_class":"P",
    "gn:feature_code":"PPL",
    "gn:name":"Mount Royal",
    "gn:population":0,
    "gn:timezone":"America/Regina",
    "iso:country":"CA",
    "wof:name":"Mount Royal",
    "wof:placetype":"locality"
},
  "geometry": {"coordinates":[-104.67138,50.46448],"type":"Point"}
}