{
  "type": "Feature",
  "properties": {
    "gn:admin1_code":"11",
    "gn:asciiname":"Mount Royal",
    "gn:country_code":"CA",
    "gn:dem":575,
    "gn:feature_class":"P",
    "gn:feature_code":"PPL",
    "gn:name":"Mount Royal",
    "gn:population":0,
    "gn:timezone":"America/Regina",
    "iso:country":"CA",
    "name:afr_x_preferred":[
        "Mont Royal"
    ],
    "name:ara_x_preferred":[
        "\u0645\u0648\u0646\u062a \u0631\u0648\u064a\u0627\u0644"
    ],
    "name:deu_x_preferred":[
        "Mont Royal"
    ],
    "name:fra_x_preferred":[
        "Mont Royal"
    ],
    "name:hye_x_preferred":[
        "\u0544\u0578\u0576 \u054c\u0578\u0582\u0561\u0575\u0561\u056c"
    ],
    "name:nld_x_preferred":[
        "Mont Royal"
    ],
    "name:pol_x_preferred":[
        "Mont Royal"
    ],
    "name:por_x_preferred":[
        "Monte Royal"
    ],
    "name:rus_x_preferred":[
        "\u041c\u043e\u043d-\u0420\u0443\u0430\u044f\u043b\u044c"
    ],
    "name:spa_x_preferred":[
        "Monte Royal"
    ],
    "name:swe_x_preferred":[
        "Mont Royal"
    ],
    "name:zho_x_preferred":[
        "\u7687\u5bb6\u5c71"
    ],
    "wof:name":"Mount Royal",
    "wof:placetype":"locality"
},
  "geometry": {"coordinates":[-104.67138,50.46448],"type":"Point"}
}