{
  "type": "Feature",
  "properties": {
    "gn:admin1_code":"3",
    "gn:asciiname":"Indian Bay",
    "gn:country_code":"CA",
    "gn:dem":324,
    "gn:feature_class":"P",
    "gn:feature_code":"PPLL",
    "gn:name":"Indian Bay",
    "gn:population":0,
    "gn:timezone":"America/Winnipeg",
    "iso:country":"CA",
    "name:ceb_x_preferred":[
        "Indian Bay"
    ],
    "name:fra_x_preferred":[
        "Indian Bay"
    ],
    "name:swe_x_preferred":[
        "Indian Bay"
    ],
    "wof:name":"Indian Bay",
    "wof:placetype":"locality"
},
  "geometry": {"coordinates":[-95.19719000000001,49.6253],"type":"Point"}
}