{
  "type": "Feature",
  "properties": {
    "iso:country":"CA",
    "qs_pg:aaroncc":"CA",
    "qs_pg:name":"Woodview",
    "qs_pg:name_adm0":"Canada",
    "qs_pg:name_adm1":"Ontario",
    "qs_pg:photos":93,
    "qs_pg:photos_1k":19,
    "qs_pg:photos_9k":1,
    "qs_pg:photos_9r":3,
    "qs_pg:photos_all":93,
    "qs_pg:photos_sr":3,
    "qs_pg:pop_sr":0,
    "qs_pg:qs_pg_placetype":"locality",
    "qs_pg:qs_pg_placetype_gp":"Town",
    "qs_pg:woe_adm0":23424775,
    "woe:adm0_id":23424775,
    "woe:name_adm0":"Canada",
    "woe:name_adm1":"Ontario",
    "woe:placetype":"Town",
    "wof:name":"Woodview",
    "wof:placetype":"locality"
},
  "geometry": {"coordinates":[-78.23149600000001,44.339166],"type":"Point"}
}