{
  "type": "Feature",
  "properties": {
    "gn:admin1_code":"7.0",
    "gn:asciiname":"Aulds Cove",
    "gn:country_code":"CA",
    "gn:dem":8,
    "gn:feature_class":"P",
    "gn:feature_code":"PPL",
    "gn:name":"Aulds Cove",
    "gn:population":0,
    "gn:timezone":"America/Halifax",
    "iso:country":"CA",
    "name:gla_x_preferred":[
        "Camus an Tuirc-nimhe"
    ],
    "wof:name":"Aulds Cove",
    "wof:placetype":"locality"
},
  "geometry": {"coordinates":[-61.43859000000001,45.64847],"type":"Point"}
}