{
  "type": "Feature",
  "properties": {
    "gn:admin1_code":"5.0",
    "gn:asciiname":"Bide Arm",
    "gn:country_code":"CA",
    "gn:dem":-1,
    "gn:feature_class":"P",
    "gn:feature_code":"PPL",
    "gn:name":"Bide Arm",
    "gn:population":0,
    "gn:timezone":"America/St_Johns",
    "iso:country":"CA",
    "name:ceb_x_preferred":[
        "Bide Arm"
    ],
    "name:fra_x_preferred":[
        "Bide Arm"
    ],
    "name:por_x_preferred":[
        "Bide Arm"
    ],
    "name:swe_x_preferred":[
        "Bide Arm"
    ],
    "wof:name":"Bide Arm",
    "wof:placetype":"locality"
},
  "geometry": {"coordinates":[-56.09809,50.81679000000001],"type":"Point"}
}