{
  "type": "Feature",
  "properties": {
    "gn:admin1_code":"9",
    "gn:asciiname":"Stanchel",
    "gn:country_code":"CA",
    "gn:dem":88,
    "gn:feature_class":"P",
    "gn:feature_code":"PPLL",
    "gn:name":"Stanchel",
    "gn:population":0,
    "gn:timezone":"America/Halifax",
    "iso:country":"CA",
    "wof:name":"Stanchel",
    "wof:placetype":"locality"
},
  "geometry": {"coordinates":[-63.44871,46.31683],"type":"Point"}
}