{
  "type": "Feature",
  "properties": {
    "gn:admin1_code":"8",
    "gn:asciiname":"Petaguishene Beach",
    "gn:country_code":"CA",
    "gn:dem":186,
    "gn:feature_class":"P",
    "gn:feature_code":"PPL",
    "gn:name":"Petaguishene Beach",
    "gn:population":0,
    "gn:timezone":"America/Toronto",
    "iso:country":"CA",
    "wof:name":"Petaguishene Beach",
    "wof:placetype":"locality"
},
  "geometry": {"coordinates":[-79.94891,44.80457],"type":"Point"}
}