{
  "type": "Feature",
  "properties": {
    "gn:admin1_code":"1",
    "gn:asciiname":"Waterhole",
    "gn:country_code":"CA",
    "gn:dem":615,
    "gn:feature_class":"P",
    "gn:feature_code":"PPLL",
    "gn:name":"Waterhole",
    "gn:population":0,
    "gn:timezone":"America/Edmonton",
    "iso:country":"CA",
    "wof:name":"Waterhole",
    "wof:placetype":"locality"
},
  "geometry": {"coordinates":[-118.40276,56.01675],"type":"Point"}
}