{
  "type": "Feature",
  "properties": {
    "gn:admin1_code":"7",
    "gn:asciiname":"Greenwood",
    "gn:country_code":"CA",
    "gn:dem":10,
    "gn:feature_class":"P",
    "gn:feature_code":"PPLL",
    "gn:name":"Greenwood",
    "gn:population":0,
    "gn:timezone":"America/Halifax",
    "iso:country":"CA",
    "wof:name":"Greenwood",
    "wof:placetype":"locality"
},
  "geometry": {"coordinates":[-65.38632,43.57376],"type":"Point"}
}