{
  "type": "Feature",
  "properties": {
    "gn:admin1_code":"7",
    "gn:asciiname":"Greenwood",
    "gn:country_code":"CA",
    "gn:dem":10,
    "gn:feature_class":"P",
    "gn:feature_code":"PPLL",
    "gn:name":"Greenwood",
    "gn:population":0,
    "gn:timezone":"America/Halifax",
    "iso:country":"CA",
    "name:bul_x_preferred":[
        "\u0413\u0440\u0438\u0439\u043d\u0443\u0434"
    ],
    "name:cat_x_preferred":[
        "Greenwood"
    ],
    "name:ceb_x_preferred":[
        "Greenwood"
    ],
    "name:ces_x_preferred":[
        "Greenwood"
    ],
    "name:deu_x_preferred":[
        "Greenwood"
    ],
    "name:fin_x_preferred":[
        "Greenwood"
    ],
    "name:fra_x_preferred":[
        "Greenwood"
    ],
    "name:heb_x_preferred":[
        "\u05d2\u05e8\u05d9\u05e0\u05d5\u05d5\u05d3"
    ],
    "name:hun_x_preferred":[
        "Greenwood"
    ],
    "name:ita_x_preferred":[
        "Greenwood"
    ],
    "name:jpn_x_preferred":[
        "\u30b0\u30ea\u30fc\u30f3\u30a6\u30c3\u30c9"
    ],
    "name:kor_x_preferred":[
        "\uadf8\ub9b0\uc6b0\ub4dc"
    ],
    "name:nld_x_preferred":[
        "Greenwood"
    ],
    "name:pol_x_preferred":[
        "Greenwood"
    ],
    "name:por_x_preferred":[
        "Greenwood"
    ],
    "name:rus_x_preferred":[
        "\u0413\u0440\u0438\u043d\u0432\u0443\u0434"
    ],
    "name:spa_x_preferred":[
        "Greenwood"
    ],
    "name:srp_x_preferred":[
        "\u0413\u0440\u0438\u043d\u0432\u0443\u0434"
    ],
    "name:swe_x_preferred":[
        "Greenwood"
    ],
    "name:ukr_x_preferred":[
        "\u0490\u0440\u0456\u043d\u0432\u0443\u0434"
    ],
    "name:vol_x_preferred":[
        "Greenwood"
    ],
    "wof:name":"Greenwood",
    "wof:placetype":"locality"
},
  "geometry": {"coordinates":[-65.38632,43.57376],"type":"Point"}
}