{
  "type": "Feature",
  "properties": {
    "gn:admin1_code":"10",
    "gn:admin2_code":"11.0",
    "gn:admin3_code":"1023.0",
    "gn:asciiname":"La Baie",
    "gn:country_code":"CA",
    "gn:dem":13,
    "gn:feature_class":"P",
    "gn:feature_code":"PPL",
    "gn:name":"La Baie",
    "gn:population":0,
    "gn:timezone":"America/Halifax",
    "iso:country":"CA",
    "name:ceb_x_preferred":[
        "La Baie"
    ],
    "name:fra_x_preferred":[
        "La Baie"
    ],
    "wof:name":"La Baie",
    "wof:placetype":"locality"
},
  "geometry": {"coordinates":[-61.8715,47.23562],"type":"Point"}
}