{
  "type": "Feature",
  "properties": {
    "gn:admin1_code":"8.0",
    "gn:asciiname":"Byersville",
    "gn:country_code":"CA",
    "gn:dem":208,
    "gn:feature_class":"P",
    "gn:feature_code":"PPL",
    "gn:name":"Byersville",
    "gn:population":0,
    "gn:timezone":"America/Toronto",
    "iso:country":"CA",
    "wof:name":"Byersville",
    "wof:placetype":"locality"
},
  "geometry": {"coordinates":[-78.35054000000002,44.28656],"type":"Point"}
}