{
  "type": "Feature",
  "properties": {
    "gn:admin1_code":"11.0",
    "gn:asciiname":"Avebury",
    "gn:country_code":"CA",
    "gn:dem":571,
    "gn:feature_class":"P",
    "gn:feature_code":"PPLL",
    "gn:name":"Avebury",
    "gn:population":0,
    "gn:timezone":"America/Regina",
    "iso:country":"CA",
    "name:ara_x_preferred":[
        "\u0623\u0641\u064a\u0628\u0631\u064a"
    ],
    "name:bel_x_preferred":[
        "\u042d\u045e\u0431\u044e\u0440\u044b"
    ],
    "name:bre_x_preferred":[
        "Avebury"
    ],
    "name:cat_x_preferred":[
        "Avebury"
    ],
    "name:ceb_x_preferred":[
        "Avebury Stones"
    ],
    "name:ces_x_preferred":[
        "Avebury"
    ],
    "name:cym_x_preferred":[
        "Avebury"
    ],
    "name:dan_x_preferred":[
        "Avebury"
    ],
    "name:deu_x_preferred":[
        "Avebury"
    ],
    "name:fas_x_preferred":[
        "\u0627\u06cc\u0648\u0628\u0631\u06cc"
    ],
    "name:fin_x_preferred":[
        "Avebury"
    ],
    "name:fra_x_preferred":[
        "Avebury"
    ],
    "name:gle_x_preferred":[
        "Avebury"
    ],
    "name:glg_x_preferred":[
        "Avebury"
    ],
    "name:heb_x_preferred":[
        "\u05d0\u05d9\u05d9\u05d5\u05d5\u05d1\u05e8\u05d9"
    ],
    "name:hrv_x_preferred":[
        "Avebury"
    ],
    "name:hun_x_preferred":[
        "Avebury"
    ],
    "name:hye_x_preferred":[
        "\u0537\u0575\u057e\u0562\u0565\u0580\u056b"
    ],
    "name:isl_x_preferred":[
        "Avebury"
    ],
    "name:ita_x_preferred":[
        "Avebury"
    ],
    "name:jpn_x_preferred":[
        "\u30a8\u30fc\u30f4\u30d9\u30ea\u30fc"
    ],
    "name:kan_x_preferred":[
        "\u0c86\u0cb5\u0ccd\u0cac\u0cb0\u0cbf"
    ],
    "name:kat_x_preferred":[
        "\u10d4\u10d8\u10d5\u10d1\u10d4\u10e0\u10d8"
    ],
    "name:lit_x_preferred":[
        "Eivberis"
    ],
    "name:nor_x_preferred":[
        "Avebury"
    ],
    "name:pol_x_preferred":[
        "Avebury"
    ],
    "name:por_x_preferred":[
        "Avebury"
    ],
    "name:ron_x_preferred":[
        "Avebury"
    ],
    "name:rus_x_preferred":[
        "\u042d\u0439\u0432\u0431\u0435\u0440\u0438"
    ],
    "name:slv_x_preferred":[
        "Avebury"
    ],
    "name:spa_x_preferred":[
        "Avebury"
    ],
    "name:swe_x_preferred":[
        "Avebury"
    ],
    "name:ukr_x_preferred":[
        "\u0415\u0439\u0432\u0431\u0435\u0440\u0456"
    ],
    "name:vie_x_preferred":[
        "Avebury"
    ],
    "name:zho_x_preferred":[
        "\u57c3\u592b\u4f2f\u91cc"
    ],
    "wof:name":"Avebury",
    "wof:placetype":"locality"
},
  "geometry": {"coordinates":[-106.98446,53.1501],"type":"Point"}
}