{
  "type": "Feature",
  "properties": {
    "gn:admin1_code":"11.0",
    "gn:asciiname":"Avebury",
    "gn:country_code":"CA",
    "gn:dem":571,
    "gn:feature_class":"P",
    "gn:feature_code":"PPLL",
    "gn:name":"Avebury",
    "gn:population":0,
    "gn:timezone":"America/Regina",
    "iso:country":"CA",
    "wof:name":"Avebury",
    "wof:placetype":"locality"
},
  "geometry": {"coordinates":[-106.98446,53.1501],"type":"Point"}
}