{
  "type": "Feature",
  "properties": {
    "gn:admin1_code":"3",
    "gn:asciiname":"Lobbville",
    "gn:country_code":"CA",
    "gn:dem":325,
    "gn:feature_class":"P",
    "gn:feature_code":"PPLL",
    "gn:name":"Lobbville",
    "gn:population":0,
    "gn:timezone":"America/Winnipeg",
    "iso:country":"CA",
    "wof:name":"Lobbville",
    "wof:placetype":"locality"
},
  "geometry": {"coordinates":[-99.1925,50.12503],"type":"Point"}
}