{
  "type": "Feature",
  "properties": {
    "gn:admin1_code":"1",
    "gn:asciiname":"Sunwapta",
    "gn:country_code":"CA",
    "gn:dem":682,
    "gn:feature_class":"P",
    "gn:feature_code":"PPL",
    "gn:name":"Sunwapta",
    "gn:population":0,
    "gn:timezone":"America/Edmonton",
    "iso:country":"CA",
    "name:heb_x_preferred":[
        "\u05e1\u05d0\u05e0\u05d5\u05d0\u05e4\u05d8\u05d4"
    ],
    "wof:name":"Sunwapta",
    "wof:placetype":"locality"
},
  "geometry": {"coordinates":[-113.65000000000001,53.55],"type":"Point"}
}