{
  "type": "Feature",
  "properties": {
    "gn:admin1_code":"7",
    "gn:asciiname":"Princedale",
    "gn:country_code":"CA",
    "gn:dem":163,
    "gn:feature_class":"P",
    "gn:feature_code":"PPL",
    "gn:name":"Princedale",
    "gn:population":0,
    "gn:timezone":"America/Halifax",
    "iso:country":"CA",
    "wof:name":"Princedale",
    "wof:placetype":"locality"
},
  "geometry": {"coordinates":[-65.51124,44.64842],"type":"Point"}
}