{
  "type": "Feature",
  "properties": {
    "gn:admin1_code":"10",
    "gn:admin2_code":"7.0",
    "gn:admin3_code":"80115.0",
    "gn:asciiname":"Vernet",
    "gn:country_code":"CA",
    "gn:dem":174,
    "gn:feature_class":"P",
    "gn:feature_code":"PPL",
    "gn:name":"Vernet",
    "gn:population":0,
    "gn:timezone":"America/Toronto",
    "iso:country":"CA",
    "wof:name":"Vernet",
    "wof:placetype":"locality"
},
  "geometry": {"coordinates":[-74.76685000000001,45.86338],"type":"Point"}
}