{
  "type": "Feature",
  "properties": {
    "gn:admin1_code":"2",
    "gn:admin2_code":"5927.0",
    "gn:asciiname":"Homfray Creek",
    "gn:country_code":"CA",
    "gn:dem":128,
    "gn:feature_class":"P",
    "gn:feature_code":"PPLL",
    "gn:name":"Homfray Creek",
    "gn:population":0,
    "gn:timezone":"America/Vancouver",
    "iso:country":"CA",
    "wof:name":"Homfray Creek",
    "wof:placetype":"locality"
},
  "geometry": {"coordinates":[-124.63028,50.29597],"type":"Point"}
}