{
  "type": "Feature",
  "properties": {
    "gn:admin1_code":"5",
    "gn:asciiname":"Irishtown-Summerside",
    "gn:country_code":"CA",
    "gn:dem":96,
    "gn:feature_class":"P",
    "gn:feature_code":"PPL",
    "gn:name":"Irishtown-Summerside",
    "gn:population":0,
    "gn:timezone":"America/St_Johns",
    "iso:country":"CA",
    "name:ceb_x_preferred":[
        "Irishtown-Summerside"
    ],
    "name:fra_x_preferred":[
        "Irishtown-Summerside"
    ],
    "name:swe_x_preferred":[
        "Irishtown-Summerside"
    ],
    "wof:name":"Irishtown-Summerside",
    "wof:placetype":"locality"
},
  "geometry": {"coordinates":[-57.9817,48.98331],"type":"Point"}
}