{
  "type": "Feature",
  "properties": {
    "gn:admin1_code":"2",
    "gn:admin2_code":"5955.0",
    "gn:asciiname":"Two Rivers",
    "gn:country_code":"CA",
    "gn:dem":661,
    "gn:feature_class":"P",
    "gn:feature_code":"PPL",
    "gn:name":"Two Rivers",
    "gn:population":0,
    "gn:timezone":"America/Dawson_Creek",
    "iso:country":"CA",
    "wof:name":"Two Rivers",
    "wof:placetype":"locality"
},
  "geometry": {"coordinates":[-120.53400999999999,56.18299],"type":"Point"}
}