{
  "type": "Feature",
  "properties": {
    "gn:admin1_code":"7.0",
    "gn:asciiname":"East Gore",
    "gn:country_code":"CA",
    "gn:dem":122,
    "gn:feature_class":"P",
    "gn:feature_code":"PPL",
    "gn:name":"East Gore",
    "gn:population":0,
    "gn:timezone":"America/Halifax",
    "iso:country":"CA",
    "wof:name":"East Gore",
    "wof:placetype":"locality"
},
  "geometry": {"coordinates":[-63.68324000000001,45.11631],"type":"Point"}
}