{
  "type": "Feature",
  "properties": {
    "gn:admin1_code":"4.0",
    "gn:asciiname":"Centreton",
    "gn:country_code":"CA",
    "gn:dem":107,
    "gn:feature_class":"P",
    "gn:feature_code":"PPL",
    "gn:name":"Centreton",
    "gn:population":0,
    "gn:timezone":"America/Moncton",
    "iso:country":"CA",
    "wof:name":"Centreton",
    "wof:placetype":"locality"
},
  "geometry": {"coordinates":[-66.08436999999999,45.43568],"type":"Point"}
}