{
  "type": "Feature",
  "properties": {
    "gn:country":"CA",
    "gn:fcode":"PPL",
    "gn:pop":0,
    "iso:country":"CA",
    "name:eng_x_preferred":[
        "Fortune"
    ],
    "qs:name":"Fortune",
    "qs:name_adm0":"Canada",
    "qs:name_adm1":"Newfoundland and Labrador",
    "qs:photos":92,
    "qs:photos_1k":19,
    "qs:photos_9k":1,
    "qs:photos_9r":3,
    "qs:photos_all":92,
    "qs:photos_sr":3,
    "qs:placetype":"Town",
    "qs:pop_sr":"4",
    "wd:wordcount":298,
    "wof:name":"Fortune",
    "wof:placetype":"locality",
    "wof:population":0
},
  "geometry": {"coordinates":[-55.83164,47.06665],"type":"Point"}
}