{
  "type": "Feature",
  "properties": {
    "gn:country":"CA",
    "gn:fcode":"PPL",
    "gn:population":0,
    "iso:country":"CA",
    "name:cat_x_preferred":[
        "Fortune"
    ],
    "name:deu_x_preferred":[
        "Fortune"
    ],
    "name:eng_x_preferred":[
        "Fortune"
    ],
    "name:fin_x_preferred":[
        "Fortune"
    ],
    "name:fra_x_preferred":[
        "Fortune"
    ],
    "name:hun_x_preferred":[
        "Fortune"
    ],
    "name:hye_x_preferred":[
        "Fortune"
    ],
    "name:ita_x_preferred":[
        "Fortune"
    ],
    "name:jpn_x_preferred":[
        "\u30d5\u30a9\u30fc\u30c1\u30e5\u30f3"
    ],
    "name:nds_x_preferred":[
        "Fortune"
    ],
    "name:nld_x_preferred":[
        "Fortune"
    ],
    "name:por_x_preferred":[
        "Fortune"
    ],
    "name:rus_x_preferred":[
        "Fortune"
    ],
    "name:spa_x_preferred":[
        "Fortune"
    ],
    "name:swe_x_preferred":[
        "Fortune"
    ],
    "name:tur_x_preferred":[
        "Fortune"
    ],
    "name:urd_x_preferred":[
        "\u0641\u0627\u0631\u0686\u0648\u0646"
    ],
    "name:zho_x_preferred":[
        "Fortune"
    ],
    "qs:name":"Fortune",
    "qs:name_adm0":"Canada",
    "qs:name_adm1":"Newfoundland and Labrador",
    "qs:photos":92,
    "qs:photos_1k":19,
    "qs:photos_9k":1,
    "qs:photos_9r":3,
    "qs:photos_all":92,
    "qs:photos_sr":3,
    "qs:placetype":"Town",
    "qs:pop_sr":"4",
    "wd:wordcount":298,
    "wof:name":"Fortune",
    "wof:placetype":"locality",
    "wof:population":0
},
  "geometry": {"coordinates":[-55.83164,47.06665],"type":"Point"}
}