{
  "type": "Feature",
  "properties": {
    "gn:admin1_code":"3.0",
    "gn:asciiname":"Caye",
    "gn:country_code":"CA",
    "gn:dem":284,
    "gn:feature_class":"P",
    "gn:feature_code":"PPLL",
    "gn:name":"Caye",
    "gn:population":0,
    "gn:timezone":"America/Winnipeg",
    "iso:country":"CA",
    "wof:name":"Caye",
    "wof:placetype":"locality"
},
  "geometry": {"coordinates":[-98.66546,49.98112],"type":"Point"}
}