{
  "type": "Feature",
  "properties": {
    "gn:admin1_code":"9",
    "gn:asciiname":"Maple Plains",
    "gn:country_code":"CA",
    "gn:dem":47,
    "gn:feature_class":"P",
    "gn:feature_code":"PPLL",
    "gn:name":"Maple Plains",
    "gn:population":0,
    "gn:timezone":"America/Halifax",
    "iso:country":"CA",
    "wof:name":"Maple Plains",
    "wof:placetype":"locality"
},
  "geometry": {"coordinates":[-63.56541,46.28343],"type":"Point"}
}