{
  "type": "Feature",
  "properties": {
    "gn:admin1_code":"8",
    "gn:admin2_code":"3518.0",
    "gn:admin3_code":"5923134.0",
    "gn:asciiname":"Newcastle Village",
    "gn:country_code":"CA",
    "gn:dem":99,
    "gn:feature_class":"P",
    "gn:feature_code":"PPL",
    "gn:name":"Newcastle Village",
    "gn:population":0,
    "gn:timezone":"America/Toronto",
    "iso:country":"CA",
    "name:eng_x_preferred":[
        "Newcastle"
    ],
    "name:fra_x_preferred":[
        "Newcastle"
    ],
    "wof:name":"Newcastle Village",
    "wof:placetype":"locality"
},
  "geometry": {"coordinates":[-78.58972,43.91722],"type":"Point"}
}