{
  "type": "Feature",
  "properties": {
    "gn:admin1_code":"8.0",
    "gn:asciiname":"Bellamys Mill",
    "gn:country_code":"CA",
    "gn:dem":114,
    "gn:feature_class":"P",
    "gn:feature_code":"PPL",
    "gn:name":"Bellamys Mill",
    "gn:population":0,
    "gn:timezone":"America/Toronto",
    "iso:country":"CA",
    "wof:name":"Bellamys Mill",
    "wof:placetype":"locality"
},
  "geometry": {"coordinates":[-76.02110999999999,44.72306],"type":"Point"}
}