{
  "type": "Feature",
  "properties": {
    "gn:country":"CA",
    "gn:fcode":"PPL",
    "gn:pop":0,
    "iso:country":"CA",
    "name:ceb_x_preferred":[
        "Baine Harbour"
    ],
    "name:eng_x_preferred":[
        "Baine Harbour"
    ],
    "name:fra_x_preferred":[
        "Baine Harbour"
    ],
    "name:nld_x_preferred":[
        "Baine Harbour"
    ],
    "name:por_x_preferred":[
        "Baine Harbour"
    ],
    "name:swe_x_preferred":[
        "Baine Harbour"
    ],
    "qs:name":"Baine Harbour",
    "qs:name_adm0":"Canada",
    "qs:name_adm1":"Newfoundland and Labrador",
    "qs:photos":13,
    "qs:photos_1k":3,
    "qs:photos_9k":1,
    "qs:photos_9r":1,
    "qs:photos_all":13,
    "qs:photos_sr":1,
    "qs:placetype":"Town",
    "qs:pop_sr":"0",
    "wd:wordcount":99,
    "wof:name":"Baine Harbour",
    "wof:placetype":"locality",
    "wof:population":0
},
  "geometry": {"coordinates":[-54.89826,47.36663],"type":"Point"}
}