{
  "type": "Feature",
  "properties": {
    "gn:admin1_code":"8",
    "gn:asciiname":"Mennonite Corner",
    "gn:country_code":"CA",
    "gn:dem":361,
    "gn:feature_class":"P",
    "gn:feature_code":"PPL",
    "gn:name":"Mennonite Corner",
    "gn:population":0,
    "gn:timezone":"America/Toronto",
    "iso:country":"CA",
    "wof:name":"Mennonite Corner",
    "wof:placetype":"locality"
},
  "geometry": {"coordinates":[-80.81276,43.42457],"type":"Point"}
}