{
  "type": "Feature",
  "properties": {
    "gn:admin1_code":"8.0",
    "gn:asciiname":"Bieman's Corners",
    "gn:country_code":"CA",
    "gn:dem":357,
    "gn:feature_class":"P",
    "gn:feature_code":"PPL",
    "gn:name":"Bieman's Corners",
    "gn:population":0,
    "gn:timezone":"America/Toronto",
    "iso:country":"CA",
    "wof:name":"Bieman's Corners",
    "wof:placetype":"locality"
},
  "geometry": {"coordinates":[-80.9935,44.00461],"type":"Point"}
}