{
  "type": "Feature",
  "properties": {
    "gn:admin1_code":"11.0",
    "gn:asciiname":"Wynot",
    "gn:country_code":"CA",
    "gn:dem":654,
    "gn:feature_class":"P",
    "gn:feature_code":"PPLL",
    "gn:name":"Wynot",
    "gn:population":0,
    "gn:timezone":"America/Regina",
    "iso:country":"CA",
    "wof:name":"Wynot",
    "wof:placetype":"locality"
},
  "geometry": {"coordinates":[-103.98436,51.45006],"type":"Point"}
}