{
  "type": "Feature",
  "properties": {
    "gn:admin1_code":"7",
    "gn:asciiname":"Frasers Mountain",
    "gn:country_code":"CA",
    "gn:dem":119,
    "gn:feature_class":"P",
    "gn:feature_code":"PPL",
    "gn:name":"Frasers Mountain",
    "gn:population":0,
    "gn:timezone":"America/Halifax",
    "iso:country":"CA",
    "wof:name":"Frasers Mountain",
    "wof:placetype":"locality"
},
  "geometry": {"coordinates":[-62.5886,45.60176],"type":"Point"}
}