{
  "type": "Feature",
  "properties": {
    "gn:admin1_code":"3.0",
    "gn:asciiname":"Brereton Lake",
    "gn:country_code":"CA",
    "gn:dem":314,
    "gn:feature_class":"P",
    "gn:feature_code":"PPLL",
    "gn:name":"Brereton Lake",
    "gn:population":0,
    "gn:timezone":"America/Winnipeg",
    "iso:country":"CA",
    "wof:name":"Brereton Lake",
    "wof:placetype":"locality"
},
  "geometry": {"coordinates":[-95.52912000000001,49.9136],"type":"Point"}
}