{
  "type": "Feature",
  "properties": {
    "iso:country":"CA",
    "qs_pg:aaroncc":"CA",
    "qs_pg:name":"Chum Creek Indian Reserve 2",
    "qs_pg:name_adm0":"Canada",
    "qs_pg:name_adm1":"British Columbia",
    "qs_pg:photos":144,
    "qs_pg:photos_1k":29,
    "qs_pg:photos_9k":1,
    "qs_pg:photos_9r":3,
    "qs_pg:photos_all":144,
    "qs_pg:photos_sr":3,
    "qs_pg:pop_sr":0,
    "qs_pg:qs_pg_placetype":"locality",
    "qs_pg:qs_pg_placetype_gp":"Town",
    "qs_pg:woe_adm0":23424775,
    "woe:adm0_id":23424775,
    "woe:name_adm0":"Canada",
    "woe:name_adm1":"British Columbia",
    "woe:placetype":"Town",
    "wof:name":"Chum Creek Indian Reserve 2",
    "wof:placetype":"locality"
},
  "geometry": {"coordinates":[-119.596953,50.872874],"type":"Point"}
}