{
  "type": "Feature",
  "properties": {
    "iso:country":"CA",
    "name:azb_x_preferred":[
        "\u0648\u0648\u0644\u0631"
    ],
    "name:ceb_x_preferred":[
        "Wooler"
    ],
    "name:cym_x_preferred":[
        "Wooler"
    ],
    "name:fas_x_preferred":[
        "\u0648\u0648\u0644\u0631"
    ],
    "name:fra_x_preferred":[
        "Wooler"
    ],
    "name:gle_x_preferred":[
        "Wooler"
    ],
    "name:ita_x_preferred":[
        "Wooler"
    ],
    "name:nld_x_preferred":[
        "Wooler"
    ],
    "name:nno_x_preferred":[
        "Wooler"
    ],
    "name:pol_x_preferred":[
        "Wooler"
    ],
    "name:ron_x_preferred":[
        "Wooler"
    ],
    "name:swe_x_preferred":[
        "Wooler"
    ],
    "name:vol_x_preferred":[
        "Wooler"
    ],
    "qs_pg:aaroncc":"CA",
    "qs_pg:name":"Wooler",
    "qs_pg:name_adm0":"Canada",
    "qs_pg:name_adm1":"Ontario",
    "qs_pg:photos":16,
    "qs_pg:photos_1k":3,
    "qs_pg:photos_9k":1,
    "qs_pg:photos_9r":1,
    "qs_pg:photos_all":16,
    "qs_pg:photos_sr":1,
    "qs_pg:pop_sr":0,
    "qs_pg:qs_pg_placetype":"locality",
    "qs_pg:qs_pg_placetype_gp":"Town",
    "qs_pg:woe_adm0":23424775,
    "woe:adm0_id":23424775,
    "woe:name_adm0":"Canada",
    "woe:name_adm1":"Ontario",
    "woe:placetype":"Town",
    "wof:name":"Wooler",
    "wof:placetype":"locality"
},
  "geometry": {"coordinates":[-77.6594135,44.1409145],"type":"Point"}
}