{
  "type": "Feature",
  "properties": {
    "gn:admin1_code":"8",
    "gn:asciiname":"New California",
    "gn:country_code":"CA",
    "gn:dem":183,
    "gn:feature_class":"P",
    "gn:feature_code":"PPL",
    "gn:name":"New California",
    "gn:population":0,
    "gn:timezone":"America/Toronto",
    "iso:country":"CA",
    "name:spa_x_preferred":[
        "Nueva California"
    ],
    "wof:name":"New California",
    "wof:placetype":"locality"
},
  "geometry": {"coordinates":[-82.78711,42.03054],"type":"Point"}
}