{
  "type": "Feature",
  "properties": {
    "gn:admin1_code":"7.0",
    "gn:asciiname":"Baleine",
    "gn:country_code":"CA",
    "gn:dem":6,
    "gn:feature_class":"P",
    "gn:feature_code":"PPLL",
    "gn:name":"Baleine",
    "gn:population":0,
    "gn:timezone":"America/Glace_Bay",
    "iso:country":"CA",
    "wof:name":"Baleine",
    "wof:placetype":"locality"
},
  "geometry": {"coordinates":[-59.81513,45.95014000000001],"type":"Point"}
}