{
  "type": "Feature",
  "properties": {
    "gn:admin1_code":"1.0",
    "gn:asciiname":"Altario",
    "gn:country_code":"CA",
    "gn:dem":726,
    "gn:feature_class":"P",
    "gn:feature_code":"PPL",
    "gn:name":"Altario",
    "gn:population":0,
    "gn:timezone":"America/Edmonton",
    "iso:country":"CA",
    "name:fra_x_preferred":[
        "Altario"
    ],
    "wof:name":"Altario",
    "wof:placetype":"locality"
},
  "geometry": {"coordinates":[-110.16222,51.91861],"type":"Point"}
}