{
  "type": "Feature",
  "properties": {
    "iso:country":"CA",
    "name:eng_x_preferred":[
        "Parc r\u00e9gional du canal de Beauharnois"
    ],
    "name:fra_x_colloquial":[
        "Parc regional du canal de Beauharnois"
    ],
    "name:fra_x_preferred":[
        "Parc r\u00e9gional du canal de Beauharnois"
    ],
    "qs:gn_local":0,
    "qs:local_max":286,
    "qs:local_sum":385,
    "qs:localhoods":4,
    "qs:name":"Parc r\u00e9gional du canal de Beauharnois",
    "qs:name_adm0":"Canada",
    "qs:name_adm1":"Qu\u00e9bec",
    "qs:name_adm2":"Beauharnois-Salaberry",
    "qs:name_local":"Beauharnois-Salaberry",
    "qs:photo_max":78,
    "qs:photo_sum":286,
    "qs:placetype":"Suburb",
    "qs:quad_count":56,
    "qs:woe_adm0":23424775,
    "qs:woe_adm1":2344924,
    "qs:woe_adm2":29375171,
    "qs:woe_funk":"Grouping neighborhood",
    "qs:woe_lau":0,
    "qs:woe_local":29375171,
    "qs:woe_ver":"7.10.0",
    "wof:lang":[
        "fre"
    ],
    "wof:name":"Parc r\u00e9gional du canal de Beauharnois",
    "wof:placetype":"neighbourhood"
},
  "geometry": {"coordinates":[-73.998796,45.271705],"type":"Point"}
}