{
  "type": "Feature",
  "properties": {
    "gn:admin1_code":"7",
    "gn:asciiname":"Tarbot",
    "gn:country_code":"CA",
    "gn:dem":65,
    "gn:feature_class":"P",
    "gn:feature_code":"PPL",
    "gn:name":"Tarbot",
    "gn:population":0,
    "gn:timezone":"America/Halifax",
    "iso:country":"CA",
    "wof:name":"Tarbot",
    "wof:placetype":"locality"
},
  "geometry": {"coordinates":[-60.59546,46.33446],"type":"Point"}
}