{
  "type": "Feature",
  "properties": {
    "gn:admin1_code":"7.0",
    "gn:asciiname":"Arisaig",
    "gn:country_code":"CA",
    "gn:dem":26,
    "gn:feature_class":"P",
    "gn:feature_code":"PPL",
    "gn:name":"Arisaig",
    "gn:population":0,
    "gn:timezone":"America/Halifax",
    "iso:country":"CA",
    "name:gla_x_preferred":[
        "\u00c0rasaig"
    ],
    "name:gle_x_preferred":[
        "\u00c1rasaig"
    ],
    "wof:name":"Arisaig",
    "wof:placetype":"locality"
},
  "geometry": {"coordinates":[-62.16237,45.7602],"type":"Point"}
}