{
  "type": "Feature",
  "properties": {
    "gn:admin1_code":"3",
    "gn:asciiname":"Laurentia Beach",
    "gn:country_code":"CA",
    "gn:dem":247,
    "gn:feature_class":"P",
    "gn:feature_code":"PPLL",
    "gn:name":"Laurentia Beach",
    "gn:population":0,
    "gn:timezone":"America/Winnipeg",
    "iso:country":"CA",
    "wof:name":"Laurentia Beach",
    "wof:placetype":"locality"
},
  "geometry": {"coordinates":[-97.95931,50.41922],"type":"Point"}
}