{
  "type": "Feature",
  "properties": {
    "gn:admin1_code":"11",
    "gn:asciiname":"Midnight Lake",
    "gn:country_code":"CA",
    "gn:dem":687,
    "gn:feature_class":"P",
    "gn:feature_code":"PPLL",
    "gn:name":"Midnight Lake",
    "gn:population":0,
    "gn:timezone":"America/Regina",
    "iso:country":"CA",
    "wof:name":"Midnight Lake",
    "wof:placetype":"locality"
},
  "geometry": {"coordinates":[-108.38466,53.45016999999999],"type":"Point"}
}