{
  "type": "Feature",
  "properties": {
    "gn:admin1_code":"7",
    "gn:asciiname":"Meadowville",
    "gn:country_code":"CA",
    "gn:dem":85,
    "gn:feature_class":"P",
    "gn:feature_code":"PPL",
    "gn:name":"Meadowville",
    "gn:population":0,
    "gn:timezone":"America/Halifax",
    "iso:country":"CA",
    "name:fra_x_preferred":[
        "Meadowville"
    ],
    "wof:name":"Meadowville",
    "wof:placetype":"locality"
},
  "geometry": {"coordinates":[-62.9176,45.68778],"type":"Point"}
}