{
  "type": "Feature",
  "properties": {
    "gn:admin1_code":"8",
    "gn:asciiname":"Mannheim",
    "gn:country_code":"CA",
    "gn:dem":347,
    "gn:feature_class":"P",
    "gn:feature_code":"PPL",
    "gn:name":"Mannheim",
    "gn:population":0,
    "gn:timezone":"America/Toronto",
    "iso:country":"CA",
    "wof:name":"Mannheim",
    "wof:placetype":"locality"
},
  "geometry": {"coordinates":[-80.54538000000002,43.39812],"type":"Point"}
}