{
  "type": "Feature",
  "properties": {
    "iso:country":"CA",
    "name:eng_x_preferred":[
        "Skiff"
    ],
    "name:fra_x_preferred":[
        "Skiff"
    ],
    "qs:name":"Skiff",
    "qs:name_adm0":"Canada",
    "qs:name_adm1":"Alberta",
    "qs:photos":7,
    "qs:photos_1k":1,
    "qs:photos_9k":1,
    "qs:photos_9r":1,
    "qs:photos_all":7,
    "qs:photos_sr":1,
    "qs:placetype":"Town",
    "qs:pop_sr":"0",
    "wd:wordcount":1125,
    "wof:name":"Skiff",
    "wof:placetype":"locality"
},
  "geometry": {"coordinates":[-111.790437,49.504408],"type":"Point"}
}