{
  "type": "Feature",
  "properties": {
    "gn:admin1_code":"4",
    "gn:asciiname":"Ingalls Head",
    "gn:country_code":"CA",
    "gn:dem":11,
    "gn:feature_class":"P",
    "gn:feature_code":"PPL",
    "gn:name":"Ingalls Head",
    "gn:population":0,
    "gn:timezone":"America/Moncton",
    "iso:country":"CA",
    "wof:name":"Ingalls Head",
    "wof:placetype":"locality"
},
  "geometry": {"coordinates":[-66.76178,44.66342],"type":"Point"}
}