{
  "type": "Feature",
  "properties": {
    "gn:admin1_code":"7",
    "gn:asciiname":"Lochview Road",
    "gn:country_code":"CA",
    "gn:dem":28,
    "gn:feature_class":"P",
    "gn:feature_code":"PPL",
    "gn:name":"Lochview Road",
    "gn:population":0,
    "gn:timezone":"America/Halifax",
    "iso:country":"CA",
    "wof:name":"Lochview Road",
    "wof:placetype":"locality"
},
  "geometry": {"coordinates":[-63.61523,44.82506],"type":"Point"}
}