{
  "type": "Feature",
  "properties": {
    "gn:admin1_code":"7.0",
    "gn:asciiname":"Country Harbour Mines",
    "gn:country_code":"CA",
    "gn:dem":6,
    "gn:feature_class":"P",
    "gn:feature_code":"PPL",
    "gn:name":"Country Harbour Mines",
    "gn:population":0,
    "gn:timezone":"America/Halifax",
    "iso:country":"CA",
    "wof:name":"Country Harbour Mines",
    "wof:placetype":"locality"
},
  "geometry": {"coordinates":[-61.82168000000001,45.2541],"type":"Point"}
}