{
  "type": "Feature",
  "properties": {
    "gn:admin1_code":"8.0",
    "gn:asciiname":"Corwin Crescent",
    "gn:country_code":"CA",
    "gn:dem":197,
    "gn:feature_class":"P",
    "gn:feature_code":"PPL",
    "gn:name":"Corwin Crescent",
    "gn:population":0,
    "gn:timezone":"America/Toronto",
    "iso:country":"CA",
    "wof:name":"Corwin Crescent",
    "wof:placetype":"locality"
},
  "geometry": {"coordinates":[-79.10361,43.08417],"type":"Point"}
}