{
  "type": "Feature",
  "properties": {
    "gn:admin1_code":"2",
    "gn:admin2_code":"5943",
    "gn:asciiname":"Quatsino",
    "gn:country_code":"CA",
    "gn:dem":21,
    "gn:feature_class":"P",
    "gn:feature_code":"PPL",
    "gn:name":"Quatsino",
    "gn:population":0,
    "gn:timezone":"America/Vancouver",
    "iso:country":"CA",
    "wof:name":"Quatsino",
    "wof:placetype":"locality"
},
  "geometry": {"coordinates":[-127.65749,50.53313],"type":"Point"}
}