{
  "type": "Feature",
  "properties": {
    "gn:admin1_code":"10.0",
    "gn:admin2_code":"4.0",
    "gn:admin3_code":"90012.0",
    "gn:asciiname":"Clova",
    "gn:country_code":"CA",
    "gn:dem":420,
    "gn:feature_class":"P",
    "gn:feature_code":"PPL",
    "gn:name":"Clova",
    "gn:population":0,
    "gn:timezone":"America/Toronto",
    "iso:country":"CA",
    "name:fra_x_preferred":[
        "Clova"
    ],
    "wof:name":"Clova",
    "wof:placetype":"locality"
},
  "geometry": {"coordinates":[-75.36139,48.10889],"type":"Point"}
}