{
  "type": "Feature",
  "properties": {
    "gn:admin1_code":"11",
    "gn:asciiname":"Gardiner Park",
    "gn:country_code":"CA",
    "gn:dem":576,
    "gn:feature_class":"P",
    "gn:feature_code":"PPL",
    "gn:name":"Gardiner Park",
    "gn:population":0,
    "gn:timezone":"America/Regina",
    "iso:country":"CA",
    "wof:name":"Gardiner Park",
    "wof:placetype":"locality"
},
  "geometry": {"coordinates":[-104.55332,50.44171],"type":"Point"}
}