{
  "type": "Feature",
  "properties": {
    "gn:admin1_code":"8.0",
    "gn:asciiname":"Westmount",
    "gn:country_code":"CA",
    "gn:dem":242,
    "gn:feature_class":"P",
    "gn:feature_code":"PPL",
    "gn:name":"Westmount",
    "gn:population":0,
    "gn:timezone":"America/Toronto",
    "iso:country":"CA",
    "wof:name":"Westmount",
    "wof:placetype":"locality"
},
  "geometry": {"coordinates":[-80.74844,42.86396],"type":"Point"}
}