{
  "type": "Feature",
  "properties": {
    "gn:admin1_code":"8",
    "gn:asciiname":"Tashota",
    "gn:country_code":"CA",
    "gn:dem":325,
    "gn:feature_class":"P",
    "gn:feature_code":"PPL",
    "gn:name":"Tashota",
    "gn:population":0,
    "gn:timezone":"America/Toronto",
    "iso:country":"CA",
    "wof:name":"Tashota",
    "wof:placetype":"locality"
},
  "geometry": {"coordinates":[-87.66670000000001,50.23343],"type":"Point"}
}