{
  "type": "Feature",
  "properties": {
    "gn:admin1_code":"2.0",
    "gn:admin2_code":"5926",
    "gn:asciiname":"Bevan",
    "gn:country_code":"CA",
    "gn:dem":148,
    "gn:feature_class":"P",
    "gn:feature_code":"PPL",
    "gn:name":"Bevan",
    "gn:population":0,
    "gn:timezone":"America/Vancouver",
    "iso:country":"CA",
    "name:ita_x_preferred":[
        "Bevan"
    ],
    "wof:name":"Bevan",
    "wof:placetype":"locality"
},
  "geometry": {"coordinates":[-125.08965000000001,49.65857000000001],"type":"Point"}
}