{
  "type": "Feature",
  "properties": {
    "gn:admin1_code":"7.0",
    "gn:asciiname":"Crows Nest",
    "gn:country_code":"CA",
    "gn:dem":24,
    "gn:feature_class":"P",
    "gn:feature_code":"PPL",
    "gn:name":"Crows Nest",
    "gn:population":0,
    "gn:timezone":"America/Halifax",
    "iso:country":"CA",
    "name:ceb_x_preferred":[
        "Crows Nest"
    ],
    "name:deu_x_preferred":[
        "Crows Nest"
    ],
    "name:ita_x_preferred":[
        "Crows Nest"
    ],
    "name:mlg_x_preferred":[
        "Crows Nest"
    ],
    "name:swe_x_preferred":[
        "Crows Nest"
    ],
    "wof:name":"Crows Nest",
    "wof:placetype":"locality"
},
  "geometry": {"coordinates":[-62.06693000000001,45.24793],"type":"Point"}
}