{
  "type": "Feature",
  "properties": {
    "gn:admin1_code":"8.0",
    "gn:asciiname":"Williscroft",
    "gn:country_code":"CA",
    "gn:dem":246,
    "gn:feature_class":"P",
    "gn:feature_code":"PPL",
    "gn:name":"Williscroft",
    "gn:population":0,
    "gn:timezone":"America/Toronto",
    "iso:country":"CA",
    "wof:name":"Williscroft",
    "wof:placetype":"locality"
},
  "geometry": {"coordinates":[-81.23194000000002,44.37667],"type":"Point"}
}