{
  "type": "Feature",
  "properties": {
    "gn:country":"CA",
    "gn:fcode":"PPL",
    "gn:population":550,
    "iso:country":"CA",
    "name:ceb_x_preferred":[
        "Bragg Creek"
    ],
    "name:deu_x_preferred":[
        "Bragg Creek"
    ],
    "name:eng_x_preferred":[
        "Bragg Creek"
    ],
    "name:fas_x_preferred":[
        "\u0628\u0631\u06af \u06a9\u0631\u06cc\u06a9"
    ],
    "name:fra_x_preferred":[
        "Bragg Creek"
    ],
    "name:nld_x_preferred":[
        "Bragg Creek"
    ],
    "name:swe_x_preferred":[
        "Bragg Creek"
    ],
    "qs_pg:aaroncc":"CA",
    "qs_pg:gn_country":"CA",
    "qs_pg:gn_fcode":"PPL",
    "qs_pg:gn_pop":550,
    "qs_pg:name":"Bragg Creek",
    "qs_pg:photos_9r":0,
    "qs_pg:photos_sr":0,
    "qs_pg:pop_sr":2,
    "qs_pg:qs_pg_placetype":"locality",
    "wof:name":"Bragg Creek",
    "wof:placetype":"locality",
    "wof:population":550
},
  "geometry": {"coordinates":[-114.56028000000001,50.95129],"type":"Point"}
}