{
  "type": "Feature",
  "properties": {
    "gn:admin1_code":"7",
    "gn:asciiname":"Lake Charlotte",
    "gn:country_code":"CA",
    "gn:dem":15,
    "gn:feature_class":"P",
    "gn:feature_code":"PPL",
    "gn:name":"Lake Charlotte",
    "gn:population":0,
    "gn:timezone":"America/Halifax",
    "iso:country":"CA",
    "wof:name":"Lake Charlotte",
    "wof:placetype":"locality"
},
  "geometry": {"coordinates":[-62.95011,44.76776],"type":"Point"}
}