{
  "type": "Feature",
  "properties": {
    "gn:admin1_code":"8",
    "gn:asciiname":"McIntosh Springs",
    "gn:country_code":"CA",
    "gn:dem":270,
    "gn:feature_class":"P",
    "gn:feature_code":"PPL",
    "gn:name":"McIntosh Springs",
    "gn:population":0,
    "gn:timezone":"America/Toronto",
    "iso:country":"CA",
    "wof:name":"McIntosh Springs",
    "wof:placetype":"locality"
},
  "geometry": {"coordinates":[-80.86648000000002,48.63347],"type":"Point"}
}