{
  "type": "Feature",
  "properties": {
    "gn:admin1_code":"7.0",
    "gn:asciiname":"Casey Corner",
    "gn:country_code":"CA",
    "gn:dem":212,
    "gn:feature_class":"P",
    "gn:feature_code":"PPLL",
    "gn:name":"Casey Corner",
    "gn:population":0,
    "gn:timezone":"America/Halifax",
    "iso:country":"CA",
    "wof:name":"Casey Corner",
    "wof:placetype":"locality"
},
  "geometry": {"coordinates":[-64.54876999999999,45.01685],"type":"Point"}
}