{
  "type": "Feature",
  "properties": {
    "gn:admin1_code":"7",
    "gn:asciiname":"Little River",
    "gn:country_code":"CA",
    "gn:dem":42,
    "gn:feature_class":"P",
    "gn:feature_code":"PPL",
    "gn:name":"Little River",
    "gn:population":0,
    "gn:timezone":"America/Halifax",
    "iso:country":"CA",
    "name:ceb_x_preferred":[
        "Little River"
    ],
    "name:deu_x_preferred":[
        "Little River"
    ],
    "name:ita_x_preferred":[
        "Little River"
    ],
    "name:nld_x_preferred":[
        "Little River"
    ],
    "name:pol_x_preferred":[
        "Little River"
    ],
    "name:por_x_preferred":[
        "Little River"
    ],
    "name:spa_x_preferred":[
        "Little River"
    ],
    "name:srp_x_preferred":[
        "\u041b\u0438\u0442\u043b \u0420\u0438\u0432\u0435\u0440"
    ],
    "name:swe_x_preferred":[
        "Little River"
    ],
    "name:vol_x_preferred":[
        "Little River"
    ],
    "wof:name":"Little River",
    "wof:placetype":"locality"
},
  "geometry": {"coordinates":[-63.90696,45.77102],"type":"Point"}
}