{
  "type": "Feature",
  "properties": {
    "gn:admin1_code":"7",
    "gn:asciiname":"Little River",
    "gn:country_code":"CA",
    "gn:dem":42,
    "gn:feature_class":"P",
    "gn:feature_code":"PPL",
    "gn:name":"Little River",
    "gn:population":0,
    "gn:timezone":"America/Halifax",
    "iso:country":"CA",
    "wof:name":"Little River",
    "wof:placetype":"locality"
},
  "geometry": {"coordinates":[-63.90696,45.77102],"type":"Point"}
}