{
  "type": "Feature",
  "properties": {
    "iso:country":"CA",
    "name:ceb_x_preferred":[
        "Forest Hills"
    ],
    "name:ces_x_preferred":[
        "Forest Hills"
    ],
    "name:deu_x_preferred":[
        "Forest Hills"
    ],
    "name:eng_x_preferred":[
        "Forest Hills"
    ],
    "name:fra_x_preferred":[
        "Forest Hills"
    ],
    "name:ita_x_preferred":[
        "Forest Hills"
    ],
    "name:kor_x_preferred":[
        "\ud3ec\ub9ac\uc2a4\ud2b8\ud790\uc2a4"
    ],
    "name:nld_x_preferred":[
        "Forest Hills"
    ],
    "name:pol_x_preferred":[
        "Forest Hills"
    ],
    "name:por_x_preferred":[
        "Forest Hills"
    ],
    "name:spa_x_preferred":[
        "Forest Hills"
    ],
    "name:srp_x_preferred":[
        "\u0424\u043e\u0440\u0438\u0441\u0442 \u0425\u0438\u043b\u0441"
    ],
    "name:swe_x_preferred":[
        "Forest Hills"
    ],
    "name:ukr_x_preferred":[
        "\u0424\u043e\u0440\u0435\u0441\u0442-\u0413\u0456\u043b\u043b\u0441"
    ],
    "name:urd_x_preferred":[
        "\u0641\u0627\u0631\u0633\u0679 \u06c1\u0644\u0632"
    ],
    "name:vol_x_preferred":[
        "Forest Hills"
    ],
    "qs:gn_adm0_cc":"CA",
    "qs:gn_local":6138517,
    "qs:gn_nam_loc":"Saint John, Saint John, New Brunswick, CA",
    "qs:gn_namadm1":"04",
    "qs:local_max":7851,
    "qs:local_sum":18216,
    "qs:localhoods":28,
    "qs:name":"Forest Hills",
    "qs:name_adm0":"Canada",
    "qs:name_adm1":"New Brunswick",
    "qs:name_adm2":"Saint John",
    "qs:name_local":"Saint John",
    "qs:photo_max":35,
    "qs:photo_sum":42,
    "qs:placetype":"Suburb",
    "qs:quad_count":5,
    "qs:woe_adm0":23424775,
    "qs:woe_adm1":2344918,
    "qs:woe_adm2":29375162,
    "qs:woe_lau":0,
    "qs:woe_local":1533,
    "qs:woe_ver":"7.10.0",
    "wd:wordcount":235,
    "wof:lang":[
        "eng"
    ],
    "wof:name":"Forest Hills",
    "wof:placetype":"neighbourhood"
},
  "geometry": {"coordinates":[-66.004678,45.312924],"type":"Point"}
}