{
  "type": "Feature",
  "properties": {
    "gn:admin1_code":"8",
    "gn:asciiname":"Old Cut",
    "gn:country_code":"CA",
    "gn:dem":176,
    "gn:feature_class":"P",
    "gn:feature_code":"PPL",
    "gn:name":"Old Cut",
    "gn:population":0,
    "gn:timezone":"America/Toronto",
    "iso:country":"CA",
    "wof:name":"Old Cut",
    "wof:placetype":"locality"
},
  "geometry": {"coordinates":[-80.40000000000001,42.58639],"type":"Point"}
}