{
  "type": "Feature",
  "properties": {
    "gn:admin1_code":"1",
    "gn:asciiname":"Poplar Hill",
    "gn:country_code":"CA",
    "gn:dem":749,
    "gn:feature_class":"P",
    "gn:feature_code":"PPLL",
    "gn:name":"Poplar Hill",
    "gn:population":0,
    "gn:timezone":"America/Edmonton",
    "iso:country":"CA",
    "name:ceb_x_preferred":[
        "Poplar Hill"
    ],
    "name:deu_x_preferred":[
        "Poplar Hill"
    ],
    "name:swe_x_preferred":[
        "Poplar Hill"
    ],
    "wof:name":"Poplar Hill",
    "wof:placetype":"locality"
},
  "geometry": {"coordinates":[-119.30276000000001,55.34995],"type":"Point"}
}