{
  "type": "Feature",
  "properties": {
    "iso:country":"CA",
    "name:eng_x_preferred":[
        "Arcs Lac des"
    ],
    "qs:name":"Arcs Lac des",
    "qs:name_adm0":"Canada",
    "qs:name_adm1":"Alberta",
    "qs:photos":703,
    "qs:photos_1k":142,
    "qs:photos_9k":3,
    "qs:photos_9r":5,
    "qs:photos_all":703,
    "qs:photos_sr":8,
    "qs:placetype":"Town",
    "qs:pop_sr":"0",
    "wof:name":"Arcs Lac des",
    "wof:placetype":"locality"
},
  "geometry": {"coordinates":[-115.162982,51.044739],"type":"Point"}
}