{
  "type": "Feature",
  "properties": {
    "gn:admin1_code":"2",
    "gn:asciiname":"Sahara Heights",
    "gn:country_code":"CA",
    "gn:dem":85,
    "gn:feature_class":"P",
    "gn:feature_code":"PPL",
    "gn:name":"Sahara Heights",
    "gn:population":0,
    "gn:timezone":"America/Vancouver",
    "iso:country":"CA",
    "wof:name":"Sahara Heights",
    "wof:placetype":"locality"
},
  "geometry": {"coordinates":[-124.78333000000001,49.25],"type":"Point"}
}