{
  "type": "Feature",
  "properties": {
    "gn:admin1_code":"8",
    "gn:asciiname":"Forest",
    "gn:country_code":"CA",
    "gn:dem":154,
    "gn:feature_class":"P",
    "gn:feature_code":"PPL",
    "gn:name":"Forest",
    "gn:population":0,
    "gn:timezone":"America/Toronto",
    "iso:country":"CA",
    "wof:name":"Forest",
    "wof:placetype":"locality"
},
  "geometry": {"coordinates":[-76.61750000000001,44.3675],"type":"Point"}
}