{
  "type": "Feature",
  "properties": {
    "iso:country":"CA",
    "name:deu_x_preferred":[
        "Allandale"
    ],
    "name:eng_x_preferred":[
        "Allandale"
    ],
    "name:unk_x_variant":[
        "Allandale"
    ],
    "qs:gn_adm0_cc":"CA",
    "qs:gn_local":5894171,
    "qs:gn_nam_loc":"barrie",
    "qs:gn_namadm1":"08",
    "qs:local_max":3173,
    "qs:local_sum":6611,
    "qs:localhoods":14,
    "qs:name":"Allandale",
    "qs:name_adm0":"Canada",
    "qs:name_adm1":"Ontario",
    "qs:name_adm2":"Simcoe",
    "qs:name_local":"Barrie",
    "qs:photo_max":210,
    "qs:photo_sum":822,
    "qs:placetype":"Suburb",
    "qs:quad_count":46,
    "qs:woe_adm0":23424775,
    "qs:woe_adm1":2344922,
    "qs:woe_adm2":29375066,
    "qs:woe_lau":0,
    "qs:woe_local":4097,
    "qs:woe_ver":"7.10.0",
    "wof:lang":[
        "eng"
    ],
    "wof:name":"Allandale",
    "wof:placetype":"neighbourhood"
},
  "geometry": {"coordinates":[-79.684417,44.374322],"type":"Point"}
}