{
  "type": "Feature",
  "properties": {
    "iso:country":"CA",
    "name:eng_x_preferred":[
        "Caswell Hill"
    ],
    "wd:wordcount":592,
    "wof:lang":[
        "eng"
    ],
    "wof:name":"Caswell Hill",
    "wof:placetype":"neighbourhood"
},
  "geometry": {"coordinates":[-106.663572,52.132066],"type":"Point"}
}