{
  "type": "Feature",
  "properties": {
    "gn:admin1_code":"10",
    "gn:admin2_code":"7.0",
    "gn:admin3_code":"80085.0",
    "gn:asciiname":"Jarnac",
    "gn:country_code":"CA",
    "gn:dem":221,
    "gn:feature_class":"P",
    "gn:feature_code":"PPL",
    "gn:name":"Jarnac",
    "gn:population":0,
    "gn:timezone":"America/Toronto",
    "iso:country":"CA",
    "wof:name":"Jarnac",
    "wof:placetype":"locality"
},
  "geometry": {"coordinates":[-75.23354,45.78366],"type":"Point"}
}