{
  "type": "Feature",
  "properties": {
    "gn:admin1_code":"10",
    "gn:admin2_code":"7.0",
    "gn:admin3_code":"80085.0",
    "gn:asciiname":"Jarnac",
    "gn:country_code":"CA",
    "gn:dem":221,
    "gn:feature_class":"P",
    "gn:feature_code":"PPL",
    "gn:name":"Jarnac",
    "gn:population":0,
    "gn:timezone":"America/Toronto",
    "iso:country":"CA",
    "name:bel_x_preferred":[
        "\u0416\u0430\u0440\u043d\u0430\u043a"
    ],
    "name:bos_x_preferred":[
        "Jarnac"
    ],
    "name:cat_x_preferred":[
        "Jarnac"
    ],
    "name:ceb_x_preferred":[
        "Jarnac"
    ],
    "name:deu_x_preferred":[
        "Jarnac"
    ],
    "name:epo_x_preferred":[
        "Jarnac"
    ],
    "name:eus_x_preferred":[
        "Jarnac"
    ],
    "name:fin_x_preferred":[
        "Jarnac"
    ],
    "name:fra_x_preferred":[
        "Jarnac"
    ],
    "name:hun_x_preferred":[
        "Jarnac"
    ],
    "name:hye_x_preferred":[
        "\u053a\u0561\u0580\u0576\u0561\u056f"
    ],
    "name:ita_x_preferred":[
        "Jarnac"
    ],
    "name:lat_x_preferred":[
        "Iarnacum"
    ],
    "name:msa_x_preferred":[
        "Jarnac"
    ],
    "name:nld_x_preferred":[
        "Jarnac"
    ],
    "name:nno_x_preferred":[
        "Jarnac"
    ],
    "name:oci_x_preferred":[
        "Jarnac"
    ],
    "name:pol_x_preferred":[
        "Jarnac"
    ],
    "name:por_x_preferred":[
        "Jarnac"
    ],
    "name:ron_x_preferred":[
        "Jarnac"
    ],
    "name:rus_x_preferred":[
        "\u0416\u0430\u0440\u043d\u0430\u043a"
    ],
    "name:slk_x_preferred":[
        "Jarnac"
    ],
    "name:slv_x_preferred":[
        "Jarnac"
    ],
    "name:spa_x_preferred":[
        "Jarnac"
    ],
    "name:swe_x_preferred":[
        "Jarnac"
    ],
    "name:ukr_x_preferred":[
        "\u0416\u0430\u0440\u043d\u0430\u043a"
    ],
    "name:urd_x_preferred":[
        "\u062c\u0631\u0646\u0627\u06a9"
    ],
    "name:vie_x_preferred":[
        "Jarnac"
    ],
    "name:vol_x_preferred":[
        "Jarnac"
    ],
    "name:war_x_preferred":[
        "Jarnac"
    ],
    "name:zho_x_preferred":[
        "\u96c5\u5c14\u7eb3\u514b"
    ],
    "wof:name":"Jarnac",
    "wof:placetype":"locality"
},
  "geometry": {"coordinates":[-75.23354,45.78366],"type":"Point"}
}