{
  "type": "Feature",
  "properties": {
    "iso:country":"CA",
    "name:eng_x_preferred":[
        "Breton Cove"
    ],
    "name:nld_x_preferred":[
        "Breton Cove"
    ],
    "qs:name":"Breton Cove",
    "qs:name_adm0":"Canada",
    "qs:name_adm1":"Nova Scotia",
    "qs:photos":26,
    "qs:photos_1k":5,
    "qs:photos_9k":1,
    "qs:photos_9r":2,
    "qs:photos_all":26,
    "qs:photos_sr":2,
    "qs:placetype":"Town",
    "qs:pop_sr":"0",
    "wd:wordcount":52,
    "wof:name":"Breton Cove",
    "wof:placetype":"locality"
},
  "geometry": {"coordinates":[-60.477657,46.41424],"type":"Point"}
}