{
  "type": "Feature",
  "properties": {
    "gn:admin1_code":"2",
    "gn:asciiname":"Kobes",
    "gn:country_code":"CA",
    "gn:dem":893,
    "gn:feature_class":"P",
    "gn:feature_code":"PPLL",
    "gn:name":"Kobes",
    "gn:population":0,
    "gn:timezone":"America/Dawson_Creek",
    "iso:country":"CA",
    "wof:name":"Kobes",
    "wof:placetype":"locality"
},
  "geometry": {"coordinates":[-121.65293,56.63874000000001],"type":"Point"}
}