{
  "type": "Feature",
  "properties": {
    "iso:country":"CA",
    "name:eng_x_preferred":[
        "Dundurn A"
    ],
    "name:eng_x_variant":[
        "Dundurn Press"
    ],
    "name:fra_x_preferred":[
        "Dundurn Press"
    ],
    "qs:gn_local":0,
    "qs:local_max":2020,
    "qs:local_sum":3503,
    "qs:localhoods":5,
    "qs:name":"Dundurn A",
    "qs:name_adm0":"Canada",
    "qs:name_adm1":"Ontario",
    "qs:name_adm2":"Hamilton",
    "qs:name_local":"Hamilton",
    "qs:photo_max":256,
    "qs:photo_sum":2020,
    "qs:placetype":"Suburb",
    "qs:quad_count":51,
    "qs:woe_adm0":23424775,
    "qs:woe_adm1":2344922,
    "qs:woe_adm2":29375120,
    "qs:woe_lau":0,
    "qs:woe_local":29375120,
    "qs:woe_ver":"7.10.0",
    "wd:wordcount":330,
    "wof:lang":[
        "eng"
    ],
    "wof:name":"Dundurn A",
    "wof:placetype":"neighbourhood"
},
  "geometry": {"coordinates":[-79.883411,43.290697],"type":"Point"}
}