{
  "type": "Feature",
  "properties": {
    "gn:admin1_code":"8.0",
    "gn:admin2_code":"3558",
    "gn:asciiname":"Armstrong",
    "gn:country_code":"CA",
    "gn:dem":357,
    "gn:feature_class":"P",
    "gn:feature_code":"PPL",
    "gn:name":"Armstrong",
    "gn:population":0,
    "gn:timezone":"America/Toronto",
    "iso:country":"CA",
    "name:eng_x_preferred":[
        "Armstrong"
    ],
    "name:urd_x_preferred":[
        "\u0622\u0631\u0645\u0633\u0679\u0631\u0627\u0646\u06af"
    ],
    "wof:name":"Armstrong",
    "wof:placetype":"locality"
},
  "geometry": {"coordinates":[-89.05518000000002,50.29449],"type":"Point"}
}