{
  "type": "Feature",
  "properties": {
    "gn:admin1_code":"3",
    "gn:asciiname":"Wallace Lake",
    "gn:country_code":"CA",
    "gn:dem":311,
    "gn:feature_class":"P",
    "gn:feature_code":"PPLL",
    "gn:name":"Wallace Lake",
    "gn:population":0,
    "gn:timezone":"America/Winnipeg",
    "iso:country":"CA",
    "wof:name":"Wallace Lake",
    "wof:placetype":"locality"
},
  "geometry": {"coordinates":[-95.35442,51.00173],"type":"Point"}
}