{
  "type": "Feature",
  "properties": {
    "gn:admin1_code":"2",
    "gn:asciiname":"Shere",
    "gn:country_code":"CA",
    "gn:dem":754,
    "gn:feature_class":"P",
    "gn:feature_code":"PPLL",
    "gn:name":"Shere",
    "gn:population":0,
    "gn:timezone":"America/Vancouver",
    "iso:country":"CA",
    "name:ceb_x_preferred":[
        "Shere"
    ],
    "name:nld_x_preferred":[
        "Shere"
    ],
    "name:pol_x_preferred":[
        "Shere"
    ],
    "name:spa_x_preferred":[
        "Shere"
    ],
    "name:swe_x_preferred":[
        "Shere"
    ],
    "wof:name":"Shere",
    "wof:placetype":"locality"
},
  "geometry": {"coordinates":[-119.58588,53.03329],"type":"Point"}
}