{
  "type": "Feature",
  "properties": {
    "gn:admin1_code":"7",
    "gn:asciiname":"Lornevale",
    "gn:country_code":"CA",
    "gn:dem":127,
    "gn:feature_class":"P",
    "gn:feature_code":"PPL",
    "gn:name":"Lornevale",
    "gn:population":0,
    "gn:timezone":"America/Halifax",
    "iso:country":"CA",
    "wof:name":"Lornevale",
    "wof:placetype":"locality"
},
  "geometry": {"coordinates":[-63.6588,45.47062],"type":"Point"}
}