{
  "type": "Feature",
  "properties": {
    "gn:admin1_code":"4.0",
    "gn:asciiname":"West Branch",
    "gn:country_code":"CA",
    "gn:dem":5,
    "gn:feature_class":"P",
    "gn:feature_code":"PPL",
    "gn:name":"West Branch",
    "gn:population":0,
    "gn:timezone":"America/Moncton",
    "iso:country":"CA",
    "name:ceb_x_preferred":[
        "West Branch"
    ],
    "name:deu_x_preferred":[
        "West Branch"
    ],
    "name:fra_x_preferred":[
        "West Branch"
    ],
    "name:ita_x_preferred":[
        "West Branch"
    ],
    "name:nld_x_preferred":[
        "West Branch"
    ],
    "name:pol_x_preferred":[
        "West Branch"
    ],
    "name:por_x_preferred":[
        "West Branch"
    ],
    "name:srp_x_preferred":[
        "\u0412\u0435\u0441\u0442 \u0411\u0440\u0430\u043d\u0447"
    ],
    "name:swe_x_preferred":[
        "West Branch"
    ],
    "name:vol_x_preferred":[
        "West Branch"
    ],
    "wof:name":"West Branch",
    "wof:placetype":"locality"
},
  "geometry": {"coordinates":[-64.95026999999999,46.54413],"type":"Point"}
}