{
  "type": "Feature",
  "properties": {
    "gn:admin1_code":"10",
    "gn:admin2_code":"05",
    "gn:admin3_code":"45030.0",
    "gn:asciiname":"Potton Springs",
    "gn:country_code":"CA",
    "gn:dem":204,
    "gn:feature_class":"P",
    "gn:feature_code":"PPL",
    "gn:name":"Potton Springs",
    "gn:population":0,
    "gn:timezone":"America/Toronto",
    "iso:country":"CA",
    "wof:name":"Potton Springs",
    "wof:placetype":"locality"
},
  "geometry": {"coordinates":[-72.36261,45.14393],"type":"Point"}
}