{
  "type": "Feature",
  "properties": {
    "gn:admin1_code":"2",
    "gn:asciiname":"McLeod Lake",
    "gn:country_code":"CA",
    "gn:dem":675,
    "gn:feature_class":"P",
    "gn:feature_code":"PPLL",
    "gn:name":"McLeod Lake",
    "gn:population":0,
    "gn:timezone":"America/Vancouver",
    "iso:country":"CA",
    "wof:name":"McLeod Lake",
    "wof:placetype":"locality"
},
  "geometry": {"coordinates":[-123.03637000000001,54.98318],"type":"Point"}
}