{
  "type": "Feature",
  "properties": {
    "gn:admin1_code":"4.0",
    "gn:asciiname":"Belyeas Cove",
    "gn:country_code":"CA",
    "gn:dem":24,
    "gn:feature_class":"P",
    "gn:feature_code":"PPL",
    "gn:name":"Belyeas Cove",
    "gn:population":0,
    "gn:timezone":"America/Moncton",
    "iso:country":"CA",
    "wof:name":"Belyeas Cove",
    "wof:placetype":"locality"
},
  "geometry": {"coordinates":[-66.00232,45.71481],"type":"Point"}
}