{
  "type": "Feature",
  "properties": {
    "iso:country":"CA",
    "name:deu_x_preferred":[
        "Frankville"
    ],
    "qs_pg:aaroncc":"CA",
    "qs_pg:name":"Frankville",
    "qs_pg:name_adm0":"Canada",
    "qs_pg:name_adm1":"Ontario",
    "qs_pg:photos":3,
    "qs_pg:photos_1k":1,
    "qs_pg:photos_9k":1,
    "qs_pg:photos_9r":1,
    "qs_pg:photos_all":3,
    "qs_pg:photos_sr":1,
    "qs_pg:pop_sr":0,
    "qs_pg:qs_pg_placetype":"locality",
    "qs_pg:qs_pg_placetype_gp":"Town",
    "qs_pg:woe_adm0":23424775,
    "woe:adm0_id":23424775,
    "woe:name_adm0":"Canada",
    "woe:name_adm1":"Ontario",
    "woe:placetype":"Town",
    "wof:name":"Frankville",
    "wof:placetype":"locality"
},
  "geometry": {"coordinates":[-75.93557699999999,44.704733],"type":"Point"}
}