{
  "type": "Feature",
  "properties": {
    "gn:admin1_code":"8",
    "gn:asciiname":"Linden Beach",
    "gn:country_code":"CA",
    "gn:dem":184,
    "gn:feature_class":"P",
    "gn:feature_code":"PPL",
    "gn:name":"Linden Beach",
    "gn:population":0,
    "gn:timezone":"America/Toronto",
    "iso:country":"CA",
    "wof:name":"Linden Beach",
    "wof:placetype":"locality"
},
  "geometry": {"coordinates":[-82.7582,42.02351],"type":"Point"}
}