{
  "type": "Feature",
  "properties": {
    "gn:admin1_code":"11",
    "gn:asciiname":"Smoky Burn",
    "gn:country_code":"CA",
    "gn:dem":318,
    "gn:feature_class":"P",
    "gn:feature_code":"PPLL",
    "gn:name":"Smoky Burn",
    "gn:population":0,
    "gn:timezone":"America/Regina",
    "iso:country":"CA",
    "wof:name":"Smoky Burn",
    "wof:placetype":"locality"
},
  "geometry": {"coordinates":[-103.13423,53.36677],"type":"Point"}
}