{
  "type": "Feature",
  "properties": {
    "gn:country":"CA",
    "gn:fcode":"PPL",
    "gn:population":0,
    "iso:country":"CA",
    "name:ceb_x_preferred":[
        "Saint-Bonaventure"
    ],
    "name:deu_x_preferred":[
        "Saint-Bonaventure"
    ],
    "name:eng_x_preferred":[
        "Saint-Bonaventure"
    ],
    "name:eus_x_preferred":[
        "Saint-Bonaventure"
    ],
    "name:fas_x_preferred":[
        "\u0633\u0646-\u0628\u0648\u0646\u0627\u0648\u0627\u0646\u062a\u0648\u0631\u060c \u06a9\u0628\u06a9"
    ],
    "name:fas_x_variant":[
        "\u0633\u0646-\u0628\u0648\u0646\u0627\u0648\u0627\u0646\u062a\u0648\u0631"
    ],
    "name:fra_x_preferred":[
        "Saint-Bonaventure"
    ],
    "name:ita_x_preferred":[
        "Saint-Bonaventure"
    ],
    "name:nld_x_preferred":[
        "Saint-Bonaventure"
    ],
    "name:por_x_preferred":[
        "Saint-Bonaventure"
    ],
    "name:spa_x_preferred":[
        "Saint-Bonaventure"
    ],
    "name:swe_x_preferred":[
        "Saint-Bonaventure"
    ],
    "name:urd_x_preferred":[
        "\u0633\u06cc\u0646\u0679-\u0628\u0648\u0646\u0648\u0646\u062a\u0631\u06d2\u060c \u06a9\u06cc\u0648\u0628\u06a9"
    ],
    "name:urd_x_variant":[
        "\u0633\u06cc\u0646\u0679-\u0628\u0648\u0646\u0648\u0646\u062a\u0631\u06d2"
    ],
    "qs_pg:aaroncc":"CA",
    "qs_pg:gn_country":"CA",
    "qs_pg:gn_fcode":"PPL",
    "qs_pg:gn_pop":0,
    "qs_pg:name":"St.-Bonaventure",
    "qs_pg:name_adm0":"Canada",
    "qs_pg:name_adm1":"Qu\u00e9bec",
    "qs_pg:photos":13,
    "qs_pg:photos_1k":3,
    "qs_pg:photos_9k":1,
    "qs_pg:photos_9r":1,
    "qs_pg:photos_all":13,
    "qs_pg:photos_sr":1,
    "qs_pg:pop_sr":0,
    "qs_pg:qs_pg_placetype":"locality",
    "qs_pg:qs_pg_placetype_gp":"Town",
    "qs_pg:woe_adm0":23424775,
    "woe:adm0_id":23424775,
    "woe:name_adm0":"Canada",
    "woe:name_adm1":"Qu\u00e9bec",
    "woe:placetype":"Town",
    "wof:name":"St.-Bonaventure",
    "wof:placetype":"locality"
},
  "geometry": {"coordinates":[-72.68241999999999,45.96676],"type":"Point"}
}