{
  "type": "Feature",
  "properties": {
    "iso:country":"CA",
    "qs_pg:aaroncc":"CA",
    "qs_pg:name":"Jakes Corner",
    "qs_pg:name_adm0":"Canada",
    "qs_pg:name_adm1":"Yukon Territory",
    "qs_pg:photos":22,
    "qs_pg:photos_1k":4,
    "qs_pg:photos_9k":1,
    "qs_pg:photos_9r":1,
    "qs_pg:photos_all":22,
    "qs_pg:photos_sr":1,
    "qs_pg:pop_sr":0,
    "qs_pg:qs_pg_placetype":"locality",
    "qs_pg:qs_pg_placetype_gp":"Town",
    "qs_pg:woe_adm0":23424775,
    "woe:adm0_id":23424775,
    "woe:name_adm0":"Canada",
    "woe:name_adm1":"Yukon Territory",
    "woe:placetype":"Town",
    "wof:name":"Jakes Corner",
    "wof:placetype":"locality"
},
  "geometry": {"coordinates":[-133.99162899999999,60.3338165],"type":"Point"}
}