{
  "type": "Feature",
  "properties": {
    "gn:admin1_code":"8.0",
    "gn:asciiname":"Brooks Mill",
    "gn:country_code":"CA",
    "gn:dem":362,
    "gn:feature_class":"P",
    "gn:feature_code":"PPL",
    "gn:name":"Brooks Mill",
    "gn:population":0,
    "gn:timezone":"America/Toronto",
    "iso:country":"CA",
    "wof:name":"Brooks Mill",
    "wof:placetype":"locality"
},
  "geometry": {"coordinates":[-79.01721999999999,45.42222],"type":"Point"}
}