{
  "type": "Feature",
  "properties": {
    "gn:admin1_code":"10",
    "gn:admin2_code":"7.0",
    "gn:admin3_code":"84065.0",
    "gn:asciiname":"Jim Lake",
    "gn:country_code":"CA",
    "gn:dem":223,
    "gn:feature_class":"P",
    "gn:feature_code":"PPL",
    "gn:name":"Jim Lake",
    "gn:population":0,
    "gn:timezone":"America/Toronto",
    "iso:country":"CA",
    "wof:name":"Jim Lake",
    "wof:placetype":"locality"
},
  "geometry": {"coordinates":[-76.77249,46.10561],"type":"Point"}
}