{
  "type": "Feature",
  "properties": {
    "gn:admin1_code":"11",
    "gn:asciiname":"Enid",
    "gn:country_code":"CA",
    "gn:dem":645,
    "gn:feature_class":"P",
    "gn:feature_code":"PPLL",
    "gn:name":"Enid",
    "gn:population":0,
    "gn:timezone":"America/Regina",
    "iso:country":"CA",
    "wof:name":"Enid",
    "wof:placetype":"locality"
},
  "geometry": {"coordinates":[-103.95107,51.13338],"type":"Point"}
}