{
  "type": "Feature",
  "properties": {
    "gn:admin1_code":"11",
    "gn:asciiname":"Enid",
    "gn:country_code":"CA",
    "gn:dem":645,
    "gn:feature_class":"P",
    "gn:feature_code":"PPLL",
    "gn:name":"Enid",
    "gn:population":0,
    "gn:timezone":"America/Regina",
    "iso:country":"CA",
    "name:ceb_x_preferred":[
        "Enid"
    ],
    "name:ces_x_preferred":[
        "Enid"
    ],
    "name:deu_x_preferred":[
        "Enid"
    ],
    "name:est_x_preferred":[
        "Enid"
    ],
    "name:ita_x_preferred":[
        "Enid"
    ],
    "name:nld_x_preferred":[
        "Enid"
    ],
    "name:pol_x_preferred":[
        "Enid"
    ],
    "name:por_x_preferred":[
        "Enid"
    ],
    "name:spa_x_preferred":[
        "Enid"
    ],
    "name:swe_x_preferred":[
        "Enid"
    ],
    "wof:name":"Enid",
    "wof:placetype":"locality"
},
  "geometry": {"coordinates":[-103.95107,51.13338],"type":"Point"}
}