{
  "type": "Feature",
  "properties": {
    "gn:admin1_code":"7",
    "gn:asciiname":"Pockwock",
    "gn:country_code":"CA",
    "gn:dem":108,
    "gn:feature_class":"P",
    "gn:feature_code":"PPL",
    "gn:name":"Pockwock",
    "gn:population":0,
    "gn:timezone":"America/Halifax",
    "iso:country":"CA",
    "wof:name":"Pockwock",
    "wof:placetype":"locality"
},
  "geometry": {"coordinates":[-63.85493,44.77616],"type":"Point"}
}