{
  "type": "Feature",
  "properties": {
    "gn:admin1_code":"8",
    "gn:asciiname":"Manitou Park",
    "gn:country_code":"CA",
    "gn:dem":195,
    "gn:feature_class":"P",
    "gn:feature_code":"PPL",
    "gn:name":"Manitou Park",
    "gn:population":0,
    "gn:timezone":"America/Toronto",
    "iso:country":"CA",
    "wof:name":"Manitou Park",
    "wof:placetype":"locality"
},
  "geometry": {"coordinates":[-84.27339000000001,46.52928],"type":"Point"}
}