{
  "type": "Feature",
  "properties": {
    "gn:admin1_code":"3",
    "gn:asciiname":"Riverland",
    "gn:country_code":"CA",
    "gn:dem":261,
    "gn:feature_class":"P",
    "gn:feature_code":"PPLL",
    "gn:name":"Riverland",
    "gn:population":0,
    "gn:timezone":"America/Winnipeg",
    "iso:country":"CA",
    "name:ces_x_preferred":[
        "Riverland"
    ],
    "name:deu_x_preferred":[
        "Riverland"
    ],
    "name:fas_x_preferred":[
        "\u0631\u06cc\u0648\u0631\u0644\u0646\u062f"
    ],
    "name:fra_x_preferred":[
        "Riverland"
    ],
    "wof:name":"Riverland",
    "wof:placetype":"locality"
},
  "geometry": {"coordinates":[-95.99335000000001,50.2525],"type":"Point"}
}