{
  "type": "Feature",
  "properties": {
    "gn:admin1_code":"1.0",
    "gn:asciiname":"Cardiff",
    "gn:country_code":"CA",
    "gn:dem":707,
    "gn:feature_class":"P",
    "gn:feature_code":"PPL",
    "gn:name":"Cardiff",
    "gn:population":0,
    "gn:timezone":"America/Edmonton",
    "iso:country":"CA",
    "name:fra_x_preferred":[
        "Cardiff"
    ],
    "wof:name":"Cardiff",
    "wof:placetype":"locality"
},
  "geometry": {"coordinates":[-113.59999999999999,53.77278],"type":"Point"}
}