{
  "type": "Feature",
  "properties": {
    "gn:admin1_code":"8",
    "gn:asciiname":"Hazeldean",
    "gn:country_code":"CA",
    "gn:dem":121,
    "gn:feature_class":"P",
    "gn:feature_code":"PPL",
    "gn:name":"Hazeldean",
    "gn:population":0,
    "gn:timezone":"America/Toronto",
    "iso:country":"CA",
    "wof:name":"Hazeldean",
    "wof:placetype":"locality"
},
  "geometry": {"coordinates":[-75.88266,45.3001],"type":"Point"}
}