{
  "type": "Feature",
  "properties": {
    "gn:admin1_code":"7",
    "gn:asciiname":"Forks Baddeck",
    "gn:country_code":"CA",
    "gn:dem":42,
    "gn:feature_class":"P",
    "gn:feature_code":"PPL",
    "gn:name":"Forks Baddeck",
    "gn:population":0,
    "gn:timezone":"America/Halifax",
    "iso:country":"CA",
    "wof:name":"Forks Baddeck",
    "wof:placetype":"locality"
},
  "geometry": {"coordinates":[-60.76899,46.18116],"type":"Point"}
}