{
  "type": "Feature",
  "properties": {
    "gn:country":"CA",
    "gn:fcode":"PPLL",
    "gn:pop":0,
    "iso:country":"CA",
    "name:dut_x_preferred":[
        "New Annan"
    ],
    "name:eng_x_preferred":[
        "New Annan"
    ],
    "name:fre_x_preferred":[
        "New Annan"
    ],
    "qs:name":"New Annan",
    "qs:name_adm0":"Canada",
    "qs:name_adm1":"Prince Edward Island",
    "qs:photos_9r":0,
    "qs:photos_sr":0,
    "qs:placetype":"Town",
    "qs:pop_sr":"0",
    "wd:wordcount":225,
    "wof:name":"New Annan",
    "wof:placetype":"locality",
    "wof:population":0
},
  "geometry": {"coordinates":[-63.71542,46.41683],"type":"Point"}
}