{
  "type": "Feature",
  "properties": {
    "gn:admin1_code":"11.0",
    "gn:asciiname":"Cree Lake",
    "gn:country_code":"CA",
    "gn:dem":485,
    "gn:feature_class":"P",
    "gn:feature_code":"PPLL",
    "gn:name":"Cree Lake",
    "gn:population":0,
    "gn:timezone":"America/Regina",
    "iso:country":"CA",
    "name:bul_x_preferred":[
        "\u041a\u0440\u0438"
    ],
    "name:ceb_x_preferred":[
        "Cree Lake"
    ],
    "name:ces_x_preferred":[
        "Cree Lake"
    ],
    "name:chv_x_preferred":[
        "\u041a\u0440\u0438"
    ],
    "name:deu_x_preferred":[
        "Cree Lake"
    ],
    "name:fra_x_preferred":[
        "Lac Cree"
    ],
    "name:lav_x_preferred":[
        "Kr\u012b ezers"
    ],
    "name:por_x_preferred":[
        "Lago Cree"
    ],
    "name:rus_x_preferred":[
        "\u041a\u0440\u0438"
    ],
    "name:spa_x_preferred":[
        "Lago Cree"
    ],
    "name:zho_x_preferred":[
        "\u514b\u91cc\u6e56"
    ],
    "wof:name":"Cree Lake",
    "wof:placetype":"locality"
},
  "geometry": {"coordinates":[-106.83456,57.36691],"type":"Point"}
}