{
  "type": "Feature",
  "properties": {
    "gn:admin1_code":"11.0",
    "gn:asciiname":"Cree Lake",
    "gn:country_code":"CA",
    "gn:dem":485,
    "gn:feature_class":"P",
    "gn:feature_code":"PPLL",
    "gn:name":"Cree Lake",
    "gn:population":0,
    "gn:timezone":"America/Regina",
    "iso:country":"CA",
    "name:ara_x_preferred":[
        "\u0628\u062d\u064a\u0631\u0629 \u0643\u0631\u064a"
    ],
    "name:ben_x_preferred":[
        "\u0995\u09cd\u09b0\u09c0 \u09b2\u09c7\u0995"
    ],
    "name:bul_x_preferred":[
        "\u041a\u0440\u0438"
    ],
    "name:ceb_x_preferred":[
        "Cree Lake"
    ],
    "name:ces_x_preferred":[
        "Cree Lake"
    ],
    "name:chv_x_preferred":[
        "\u041a\u0440\u0438"
    ],
    "name:deu_x_preferred":[
        "Cree Lake"
    ],
    "name:ell_x_preferred":[
        "\u039b\u03af\u03bc\u03bd\u03b7 \u039a\u03c1\u03b9"
    ],
    "name:fas_x_preferred":[
        "\u062f\u0631\u06cc\u0627\u0686\u0647 \u06a9\u0650\u0631\u06cc"
    ],
    "name:fra_x_preferred":[
        "Lac Cree"
    ],
    "name:heb_x_preferred":[
        "\u05d0\u05d2\u05dd \u05e7\u05b0\u05e8\u05b4\u05d9"
    ],
    "name:hin_x_preferred":[
        "\u0915\u094d\u0930\u0940 \u091d\u0940\u0932"
    ],
    "name:hun_x_preferred":[
        "Cree-t\u00f3"
    ],
    "name:ind_x_preferred":[
        "Danau Cree"
    ],
    "name:ita_x_preferred":[
        "Cree Lake"
    ],
    "name:kor_x_preferred":[
        "\ud06c\ub9ac \ub808\uc774\ud06c"
    ],
    "name:lav_x_preferred":[
        "Kr\u012b ezers"
    ],
    "name:por_x_preferred":[
        "Lago Cree"
    ],
    "name:rus_x_preferred":[
        "\u041a\u0440\u0438"
    ],
    "name:spa_x_preferred":[
        "Lago Cree"
    ],
    "name:tur_x_preferred":[
        "Cree G\u00f6l\u00fc"
    ],
    "name:ukr_x_preferred":[
        "\u043e\u0437\u0435\u0440\u043e \u041a\u0440\u0456"
    ],
    "name:urd_x_preferred":[
        "\u06a9\u0631\u06cc \u062c\u06be\u06cc\u0644"
    ],
    "name:vie_x_preferred":[
        "H\u1ed3 Cree"
    ],
    "name:zho_x_preferred":[
        "\u514b\u91cc\u6e56"
    ],
    "wof:name":"Cree Lake",
    "wof:placetype":"locality"
},
  "geometry": {"coordinates":[-106.83456,57.36691],"type":"Point"}
}