{
  "type": "Feature",
  "properties": {
    "gn:admin1_code":"11.0",
    "gn:asciiname":"Cree Lake",
    "gn:country_code":"CA",
    "gn:dem":485,
    "gn:feature_class":"P",
    "gn:feature_code":"PPLL",
    "gn:name":"Cree Lake",
    "gn:population":0,
    "gn:timezone":"America/Regina",
    "iso:country":"CA",
    "wof:name":"Cree Lake",
    "wof:placetype":"locality"
},
  "geometry": {"coordinates":[-106.83456,57.36691],"type":"Point"}
}