{
  "type": "Feature",
  "properties": {
    "gn:admin1_code":"8",
    "gn:asciiname":"Moore Centre",
    "gn:country_code":"CA",
    "gn:dem":193,
    "gn:feature_class":"P",
    "gn:feature_code":"PPL",
    "gn:name":"Moore Centre",
    "gn:population":0,
    "gn:timezone":"America/Toronto",
    "iso:country":"CA",
    "wof:name":"Moore Centre",
    "wof:placetype":"locality"
},
  "geometry": {"coordinates":[-82.34931999999998,42.83757],"type":"Point"}
}