{
  "type": "Feature",
  "properties": {
    "gn:admin1_code":"8.0",
    "gn:asciiname":"Donwood",
    "gn:country_code":"CA",
    "gn:dem":221,
    "gn:feature_class":"P",
    "gn:feature_code":"PPL",
    "gn:name":"Donwood",
    "gn:population":0,
    "gn:timezone":"America/Toronto",
    "iso:country":"CA",
    "wof:name":"Donwood",
    "wof:placetype":"locality"
},
  "geometry": {"coordinates":[-78.28305999999998,44.32806],"type":"Point"}
}