{
  "type": "Feature",
  "properties": {
    "gn:admin1_code":"10",
    "gn:admin2_code":"9.0",
    "gn:admin3_code":"97007.0",
    "gn:asciiname":"Plage-Ferguson",
    "gn:country_code":"CA",
    "gn:dem":9,
    "gn:feature_class":"P",
    "gn:feature_code":"PPL",
    "gn:name":"Plage-Ferguson",
    "gn:population":0,
    "gn:timezone":"America/Toronto",
    "iso:country":"CA",
    "wof:name":"Plage-Ferguson",
    "wof:placetype":"locality"
},
  "geometry": {"coordinates":[-66.27995,50.20922],"type":"Point"}
}