{
  "type": "Feature",
  "properties": {
    "gn:admin1_code":"8.0",
    "gn:asciiname":"The Blue Mountains",
    "gn:country_code":"CA",
    "gn:dem":199,
    "gn:feature_class":"P",
    "gn:feature_code":"PPL",
    "gn:name":"The Blue Mountains",
    "gn:population":0,
    "gn:timezone":"America/Toronto",
    "iso:country":"CA",
    "wof:name":"The Blue Mountains",
    "wof:placetype":"locality"
},
  "geometry": {"coordinates":[-80.458,44.5584],"type":"Point"}
}