{
  "type": "Feature",
  "properties": {
    "gn:admin1_code":"7.0",
    "gn:asciiname":"Birch Plain",
    "gn:country_code":"CA",
    "gn:dem":21,
    "gn:feature_class":"P",
    "gn:feature_code":"PPL",
    "gn:name":"Birch Plain",
    "gn:population":0,
    "gn:timezone":"America/Halifax",
    "iso:country":"CA",
    "wof:name":"Birch Plain",
    "wof:placetype":"locality"
},
  "geometry": {"coordinates":[-60.43431,46.50535],"type":"Point"}
}