{
  "type": "Feature",
  "properties": {
    "gn:admin1_code":"10",
    "gn:admin2_code":"14.0",
    "gn:admin3_code":"62025.0",
    "gn:asciiname":"Lac-Rouge-Nord",
    "gn:country_code":"CA",
    "gn:dem":272,
    "gn:feature_class":"P",
    "gn:feature_code":"PPL",
    "gn:name":"Lac-Rouge-Nord",
    "gn:population":0,
    "gn:timezone":"America/Toronto",
    "iso:country":"CA",
    "wof:name":"Lac-Rouge-Nord",
    "wof:placetype":"locality"
},
  "geometry": {"coordinates":[-73.70709000000002,46.19337],"type":"Point"}
}