{
  "type": "Feature",
  "properties": {
    "gn:admin1_code":"7.0",
    "gn:asciiname":"Wharton",
    "gn:country_code":"CA",
    "gn:dem":37,
    "gn:feature_class":"P",
    "gn:feature_code":"PPL",
    "gn:name":"Wharton",
    "gn:population":0,
    "gn:timezone":"America/Halifax",
    "iso:country":"CA",
    "name:gla_x_preferred":[
        "Wharton"
    ],
    "wof:name":"Wharton",
    "wof:placetype":"locality"
},
  "geometry": {"coordinates":[-64.39738,45.42155],"type":"Point"}
}