{
  "type": "Feature",
  "properties": {
    "gn:admin1_code":"7",
    "gn:asciiname":"Strathlorne",
    "gn:country_code":"CA",
    "gn:dem":71,
    "gn:feature_class":"P",
    "gn:feature_code":"PPL",
    "gn:name":"Strathlorne",
    "gn:population":0,
    "gn:timezone":"America/Halifax",
    "iso:country":"CA",
    "wof:name":"Strathlorne",
    "wof:placetype":"locality"
},
  "geometry": {"coordinates":[-61.28182,46.18344],"type":"Point"}
}