{
  "type": "Feature",
  "properties": {
    "gn:admin1_code":"10",
    "gn:admin2_code":"10.0",
    "gn:asciiname":"Tasiujaq",
    "gn:country_code":"CA",
    "gn:dem":6,
    "gn:feature_class":"P",
    "gn:feature_code":"PPL",
    "gn:name":"Tasiujaq",
    "gn:population":0,
    "gn:timezone":"America/Toronto",
    "iso:country":"CA",
    "name:ceb_x_preferred":[
        "Tasiujaq"
    ],
    "name:cre_x_preferred":[
        "\u1455\u14ef\u1405\u152d\u1483"
    ],
    "name:eng_x_preferred":[
        "Tasiujaq"
    ],
    "name:fra_x_preferred":[
        "Tasiujaq"
    ],
    "name:ita_x_preferred":[
        "Tasiujaq"
    ],
    "name:pol_x_preferred":[
        "Tasiujaq"
    ],
    "name:swe_x_preferred":[
        "Tasiujaq"
    ],
    "name:ukr_x_preferred":[
        "\u0422\u0430\u0441\u0456\u0443\u0434\u0436\u0430\u043a"
    ],
    "wof:name":"Tasiujaq",
    "wof:placetype":"locality"
},
  "geometry": {"coordinates":[-69.92764,58.69594],"type":"Point"}
}