{
  "type": "Feature",
  "properties": {
    "gn:admin1_code":"3",
    "gn:asciiname":"Vimy Ridge",
    "gn:country_code":"CA",
    "gn:dem":409,
    "gn:feature_class":"P",
    "gn:feature_code":"PPLL",
    "gn:name":"Vimy Ridge",
    "gn:population":0,
    "gn:timezone":"America/Winnipeg",
    "iso:country":"CA",
    "wof:name":"Vimy Ridge",
    "wof:placetype":"locality"
},
  "geometry": {"coordinates":[-100.60398000000001,51.75751],"type":"Point"}
}