{
  "type": "Feature",
  "properties": {
    "gn:country":"CA",
    "gn:fcode":"ADMD",
    "gn:population":0,
    "iso:country":"CA",
    "name:eng_x_preferred":[
        "Lunenburg"
    ],
    "name:fra_x_preferred":[
        "Comt\u00e9 de Lunenburg"
    ],
    "name:gla_x_preferred":[
        "Siorrachd Lunenburg"
    ],
    "name:ita_x_preferred":[
        "Contea di Lunenburg"
    ],
    "name:pdc_x_preferred":[
        "Lunenburg Kaundi"
    ],
    "name:pol_x_preferred":[
        "Hrabstwo Lunenburg"
    ],
    "name:rus_x_preferred":[
        "\u041b\u0443\u043d\u0435\u043d\u0431\u0435\u0440\u0433"
    ],
    "name:spa_x_preferred":[
        "Condado de Lunenburg"
    ],
    "name:sqi_x_preferred":[
        "Kontea Lunenburg"
    ],
    "name:ukr_x_preferred":[
        "\u041b\u0443\u043d\u0435\u043d\u0431\u0435\u0440\u0433"
    ],
    "qs:name":"Lunenburg",
    "qs:photos_9r":0,
    "qs:photos_sr":0,
    "qs:pop_sr":"0",
    "wd:wordcount":73,
    "wof:name":"Lunenburg",
    "wof:placetype":"localadmin",
    "wof:population":0
},
  "geometry": {"coordinates":[-64.59877,44.43345],"type":"Point"}
}