{
  "type": "Feature",
  "properties": {
    "iso:country":"CA",
    "name:ara_x_preferred":[
        "\u0645\u0631\u062a\u0641\u0639\u0627\u062a"
    ],
    "name:bar_x_preferred":[
        "Highlands"
    ],
    "name:bel_x_preferred":[
        "\u0423\u0437\u0432\u044b\u0448\u0448\u0430"
    ],
    "name:bul_x_preferred":[
        "\u041f\u043b\u0430\u043d\u0438\u043d\u0441\u043a\u0430 \u0437\u0435\u043c\u044f"
    ],
    "name:ces_x_preferred":[
        "Vyso\u010dina"
    ],
    "name:dan_x_preferred":[
        "H\u00f8jland"
    ],
    "name:deu_x_preferred":[
        "Hochland"
    ],
    "name:ell_x_preferred":[
        "\u03a5\u03c8\u03af\u03c0\u03b5\u03b4\u03bf"
    ],
    "name:eng_x_preferred":[
        "Highland"
    ],
    "name:est_x_preferred":[
        "M\u00e4gismaa"
    ],
    "name:fas_x_preferred":[
        "\u06a9\u0648\u0647\u0633\u0627\u0631"
    ],
    "name:fry_x_preferred":[
        "Heechflakte"
    ],
    "name:hye_x_preferred":[
        "\u0532\u0561\u0580\u0571\u0580\u0561\u057e\u0561\u0576\u0564\u0561\u056f"
    ],
    "name:ilo_x_preferred":[
        "Tangkig"
    ],
    "name:isl_x_preferred":[
        "H\u00e1lendi"
    ],
    "name:kat_x_preferred":[
        "\u10db\u10d0\u10e6\u10da\u10dd\u10d1\u10d8"
    ],
    "name:mal_x_preferred":[
        "\u0d09\u0d28\u0d4d\u0d28\u0d24\u0d2e\u0d47\u0d16\u0d32"
    ],
    "name:nld_x_preferred":[
        "Hoogvlakte"
    ],
    "name:nno_x_preferred":[
        "H\u00f8gland"
    ],
    "name:nor_x_preferred":[
        "H\u00f8yland"
    ],
    "name:pol_x_preferred":[
        "Wy\u017cyna"
    ],
    "name:por_x_preferred":[
        "Terras altas"
    ],
    "name:rus_x_preferred":[
        "\u041d\u0430\u0433\u043e\u0440\u044c\u0435"
    ],
    "name:sco_x_preferred":[
        "Hieland"
    ],
    "name:slk_x_preferred":[
        "Vyso\u010dina"
    ],
    "name:srp_x_preferred":[
        "\u0412\u0438\u0441\u0438\u0458\u0430"
    ],
    "name:swe_x_preferred":[
        "H\u00f6gland"
    ],
    "name:tgl_x_preferred":[
        "Paltok"
    ],
    "name:tur_x_preferred":[
        "Da\u011fl\u0131k"
    ],
    "name:ukr_x_preferred":[
        "\u041d\u0430\u0433\u0456\u0440'\u044f"
    ],
    "name:vie_x_preferred":[
        "Highland"
    ],
    "name:vie_x_variant":[
        "S\u01a1n nguy\u00ean"
    ],
    "name:xmf_x_preferred":[
        "\u10d6\u10e3\u10d9\u10d8"
    ],
    "qs:gn_local":0,
    "qs:local_max":9600,
    "qs:local_sum":25118,
    "qs:localhoods":26,
    "qs:name":"Highland",
    "qs:name_adm0":"Canada",
    "qs:name_adm1":"Ontario",
    "qs:name_adm2":"Middlesex",
    "qs:name_local":"London",
    "qs:photo_max":236,
    "qs:photo_sum":488,
    "qs:placetype":"Suburb",
    "qs:quad_count":26,
    "qs:woe_adm0":23424775,
    "qs:woe_adm1":2344922,
    "qs:woe_adm2":29375211,
    "qs:woe_lau":0,
    "qs:woe_local":4063,
    "qs:woe_ver":"7.10.0",
    "wof:lang":[
        "eng"
    ],
    "wof:name":"Highland",
    "wof:placetype":"neighbourhood"
},
  "geometry": {"coordinates":[-81.258258,42.949433],"type":"Point"}
}