{
  "type": "Feature",
  "properties": {
    "gn:admin1_code":"8.0",
    "gn:asciiname":"Abingdon",
    "gn:country_code":"CA",
    "gn:dem":201,
    "gn:feature_class":"P",
    "gn:feature_code":"PPL",
    "gn:name":"Abingdon",
    "gn:population":0,
    "gn:timezone":"America/Toronto",
    "iso:country":"CA",
    "name:cat_x_preferred":[
        "Abingdon"
    ],
    "name:ceb_x_preferred":[
        "Abingdon"
    ],
    "name:dan_x_preferred":[
        "Abingdon"
    ],
    "name:deu_x_preferred":[
        "Abingdon"
    ],
    "name:fin_x_preferred":[
        "Abingdon"
    ],
    "name:fra_x_preferred":[
        "Abingdon"
    ],
    "name:glg_x_preferred":[
        "Abingdon"
    ],
    "name:ido_x_preferred":[
        "Abingdon"
    ],
    "name:ita_x_preferred":[
        "Abingdon"
    ],
    "name:jpn_x_preferred":[
        "\u30a2\u30d3\u30f3\u30c9\u30f3"
    ],
    "name:kor_x_preferred":[
        "\uc560\ube59\ub358"
    ],
    "name:nld_x_preferred":[
        "Abingdon"
    ],
    "name:nor_x_preferred":[
        "Abingdon"
    ],
    "name:pol_x_preferred":[
        "Abingdon"
    ],
    "name:por_x_preferred":[
        "Abingdon"
    ],
    "name:rus_x_preferred":[
        "\u0410\u0431\u0438\u043d\u0433\u0434\u043e\u043d"
    ],
    "name:spa_x_preferred":[
        "Abingdon"
    ],
    "name:srp_x_preferred":[
        "\u0410\u0431\u0438\u043d\u0433\u0434\u043e\u043d"
    ],
    "name:swe_x_preferred":[
        "Abingdon"
    ],
    "name:ukr_x_preferred":[
        "\u0410\u0431\u0456\u043d\u0433\u0434\u043e\u043d"
    ],
    "name:vol_x_preferred":[
        "Abingdon"
    ],
    "wof:name":"Abingdon",
    "wof:placetype":"locality"
},
  "geometry": {"coordinates":[-79.685,43.08361],"type":"Point"}
}