{
  "type": "Feature",
  "properties": {
    "iso:country":"CA",
    "name:ceb_x_preferred":[
        "Hearst"
    ],
    "name:eng_x_preferred":[
        "Hearst"
    ],
    "name:fas_x_preferred":[
        "\u0641\u0631\u0648\u062f\u06af\u0627\u0647 \u0647\u0631\u0633\u062a"
    ],
    "name:msa_x_preferred":[
        "Lapangan Terbang Hearst Mun"
    ],
    "name:pms_x_preferred":[
        "Hearst"
    ],
    "name:ron_x_preferred":[
        "Aeroportul Municipal Hearst"
    ],
    "name:swe_x_preferred":[
        "Hearst"
    ],
    "name:tgk_x_preferred":[
        "\u0424\u0443\u0440\u0443\u0434\u0433\u043e\u04b3\u0438 \u04b3\u0440\u0441\u0442"
    ],
    "oa:elevation_ft":"827",
    "oa:type":"medium_airport",
    "woe:hierarchy":{
        "country_id":23424775,
        "county_id":29375242,
        "planet_id":1,
        "state_id":2344922
    },
    "wof:name":"Hearst Municipal Airport",
    "wof:placetype":"campus"
},
  "geometry": {"coordinates":[-83.68689999999999,49.7139],"type":"Point"}
}