{
  "type": "Feature",
  "properties": {
    "gn:admin1_code":"7.0",
    "gn:asciiname":"Clydesdale",
    "gn:country_code":"CA",
    "gn:dem":137,
    "gn:feature_class":"P",
    "gn:feature_code":"PPLL",
    "gn:name":"Clydesdale",
    "gn:population":0,
    "gn:timezone":"America/Halifax",
    "iso:country":"CA",
    "name:ara_x_preferred":[
        "\u0643\u0644\u0627\u064a\u062f\u064a\u0632\u062f\u0627\u0644"
    ],
    "name:ceb_x_preferred":[
        "Clydesdale"
    ],
    "name:epo_x_preferred":[
        "Clydesdale"
    ],
    "name:fra_x_preferred":[
        "Clydesdale"
    ],
    "name:gle_x_preferred":[
        "Dail Chluaidh"
    ],
    "name:sco_x_preferred":[
        "Clydesdale"
    ],
    "name:swe_x_preferred":[
        "Clydesdale"
    ],
    "wof:name":"Clydesdale",
    "wof:placetype":"locality"
},
  "geometry": {"coordinates":[-63.18196999999999,45.61685],"type":"Point"}
}