{
  "type": "Feature",
  "properties": {
    "gn:admin1_code":"8.0",
    "gn:asciiname":"Allsaw",
    "gn:country_code":"CA",
    "gn:dem":335,
    "gn:feature_class":"P",
    "gn:feature_code":"PPL",
    "gn:name":"Allsaw",
    "gn:population":0,
    "gn:timezone":"America/Toronto",
    "iso:country":"CA",
    "wof:name":"Allsaw",
    "wof:placetype":"locality"
},
  "geometry": {"coordinates":[-78.61111,44.98889000000001],"type":"Point"}
}