{
  "type": "Feature",
  "properties": {
    "gn:admin1_code":"2.0",
    "gn:asciiname":"Baynes Lake",
    "gn:country_code":"CA",
    "gn:dem":798,
    "gn:feature_class":"P",
    "gn:feature_code":"PPL",
    "gn:name":"Baynes Lake",
    "gn:population":0,
    "gn:timezone":"America/Edmonton",
    "iso:country":"CA",
    "wof:name":"Baynes Lake",
    "wof:placetype":"locality"
},
  "geometry": {"coordinates":[-115.21666999999999,49.23333],"type":"Point"}
}