{
  "type": "Feature",
  "properties": {
    "gn:admin1_code":"11",
    "gn:asciiname":"Swarthmore",
    "gn:country_code":"CA",
    "gn:dem":683,
    "gn:feature_class":"P",
    "gn:feature_code":"PPLL",
    "gn:name":"Swarthmore",
    "gn:population":0,
    "gn:timezone":"America/Regina",
    "iso:country":"CA",
    "name:ita_x_preferred":[
        "Swarthmore"
    ],
    "wof:name":"Swarthmore",
    "wof:placetype":"locality"
},
  "geometry": {"coordinates":[-108.98474,52.58344],"type":"Point"}
}