{
  "type": "Feature",
  "properties": {
    "gn:admin1_code":"5",
    "gn:asciiname":"Stuckless Cove",
    "gn:country_code":"CA",
    "gn:dem":38,
    "gn:feature_class":"P",
    "gn:feature_code":"PPLL",
    "gn:name":"Stuckless Cove",
    "gn:population":0,
    "gn:timezone":"America/St_Johns",
    "iso:country":"CA",
    "wof:name":"Stuckless Cove",
    "wof:placetype":"locality"
},
  "geometry": {"coordinates":[-56.54821,49.84999000000001],"type":"Point"}
}