{
  "type": "Feature",
  "properties": {
    "gn:admin1_code":"1",
    "gn:asciiname":"Tower Estates",
    "gn:country_code":"CA",
    "gn:dem":734,
    "gn:feature_class":"P",
    "gn:feature_code":"PPL",
    "gn:name":"Tower Estates",
    "gn:population":0,
    "gn:timezone":"America/Edmonton",
    "iso:country":"CA",
    "wof:name":"Tower Estates",
    "wof:placetype":"locality"
},
  "geometry": {"coordinates":[-110.72778,50.02778],"type":"Point"}
}