{
  "type": "Feature",
  "properties": {
    "gn:admin1_code":"4",
    "gn:asciiname":"Elmwood Estates",
    "gn:country_code":"CA",
    "gn:dem":26,
    "gn:feature_class":"P",
    "gn:feature_code":"PPL",
    "gn:name":"Elmwood Estates",
    "gn:population":0,
    "gn:timezone":"America/Moncton",
    "iso:country":"CA",
    "wof:name":"Elmwood Estates",
    "wof:placetype":"locality"
},
  "geometry": {"coordinates":[-64.76666999999999,46.11667],"type":"Point"}
}