{
  "type": "Feature",
  "properties": {
    "gn:admin1_code":"7",
    "gn:asciiname":"MacNeils Vale",
    "gn:country_code":"CA",
    "gn:dem":139,
    "gn:feature_class":"P",
    "gn:feature_code":"PPLL",
    "gn:name":"MacNeils Vale",
    "gn:population":0,
    "gn:timezone":"America/Halifax",
    "iso:country":"CA",
    "wof:name":"MacNeils Vale",
    "wof:placetype":"locality"
},
  "geometry": {"coordinates":[-60.81519,46.01684],"type":"Point"}
}