{
  "type": "Feature",
  "properties": {
    "gn:admin1_code":"2.0",
    "gn:asciiname":"Woodsdale",
    "gn:country_code":"CA",
    "gn:dem":536,
    "gn:feature_class":"P",
    "gn:feature_code":"PPL",
    "gn:name":"Woodsdale",
    "gn:population":0,
    "gn:timezone":"America/Vancouver",
    "iso:country":"CA",
    "wof:name":"Woodsdale",
    "wof:placetype":"locality"
},
  "geometry": {"coordinates":[-119.38333,50.05],"type":"Point"}
}