{
  "type": "Feature",
  "properties": {
    "gn:admin1_code":"7.0",
    "gn:asciiname":"West Bay",
    "gn:country_code":"CA",
    "gn:dem":33,
    "gn:feature_class":"P",
    "gn:feature_code":"PPLL",
    "gn:name":"West Bay",
    "gn:population":0,
    "gn:timezone":"America/Halifax",
    "iso:country":"CA",
    "name:ceb_x_preferred":[
        "West Bay"
    ],
    "name:deu_x_preferred":[
        "West Bay"
    ],
    "name:swe_x_preferred":[
        "West Bay"
    ],
    "wof:name":"West Bay",
    "wof:placetype":"locality"
},
  "geometry": {"coordinates":[-64.39447,45.37208],"type":"Point"}
}