{
  "type": "Feature",
  "properties": {
    "gn:admin1_code":"8",
    "gn:asciiname":"German Settlement",
    "gn:country_code":"CA",
    "gn:dem":204,
    "gn:feature_class":"P",
    "gn:feature_code":"PPL",
    "gn:name":"German Settlement",
    "gn:population":0,
    "gn:timezone":"America/Toronto",
    "iso:country":"CA",
    "wof:name":"German Settlement",
    "wof:placetype":"locality"
},
  "geometry": {"coordinates":[-77.45251999999998,45.5221],"type":"Point"}
}