{
  "type": "Feature",
  "properties": {
    "gn:admin1_code":"2.0",
    "gn:asciiname":"Boothroyd",
    "gn:country_code":"CA",
    "gn:dem":306,
    "gn:feature_class":"P",
    "gn:feature_code":"PPL",
    "gn:name":"Boothroyd",
    "gn:population":0,
    "gn:timezone":"America/Vancouver",
    "iso:country":"CA",
    "name:deu_x_preferred":[
        "Boothroyd"
    ],
    "wof:name":"Boothroyd",
    "wof:placetype":"locality"
},
  "geometry": {"coordinates":[-121.48333,49.96528],"type":"Point"}
}