{
  "type": "Feature",
  "properties": {
    "gn:admin1_code":"1",
    "gn:asciiname":"Roma",
    "gn:country_code":"CA",
    "gn:dem":551,
    "gn:feature_class":"P",
    "gn:feature_code":"PPLL",
    "gn:name":"Roma",
    "gn:population":0,
    "gn:timezone":"America/Edmonton",
    "iso:country":"CA",
    "wof:name":"Roma",
    "wof:placetype":"locality"
},
  "geometry": {"coordinates":[-117.41939000000001,56.21679],"type":"Point"}
}