{
  "type": "Feature",
  "properties": {
    "gn:admin1_code":"7",
    "gn:asciiname":"Middle LaHave",
    "gn:country_code":"CA",
    "gn:dem":5,
    "gn:feature_class":"P",
    "gn:feature_code":"PPL",
    "gn:name":"Middle LaHave",
    "gn:population":0,
    "gn:timezone":"America/Halifax",
    "iso:country":"CA",
    "wof:name":"Middle LaHave",
    "wof:placetype":"locality"
},
  "geometry": {"coordinates":[-64.39960000000001,44.32066],"type":"Point"}
}