{
  "type": "Feature",
  "properties": {
    "gn:admin1_code":"11",
    "gn:asciiname":"Golburn",
    "gn:country_code":"CA",
    "gn:dem":478,
    "gn:feature_class":"P",
    "gn:feature_code":"PPLL",
    "gn:name":"Golburn",
    "gn:population":0,
    "gn:timezone":"America/Regina",
    "iso:country":"CA",
    "wof:name":"Golburn",
    "wof:placetype":"locality"
},
  "geometry": {"coordinates":[-104.01766000000001,52.76671],"type":"Point"}
}