{
  "type": "Feature",
  "properties": {
    "gn:admin1_code":"7",
    "gn:asciiname":"Little Pond",
    "gn:country_code":"CA",
    "gn:dem":24,
    "gn:feature_class":"P",
    "gn:feature_code":"PPL",
    "gn:name":"Little Pond",
    "gn:population":0,
    "gn:timezone":"America/Glace_Bay",
    "iso:country":"CA",
    "wof:name":"Little Pond",
    "wof:placetype":"locality"
},
  "geometry": {"coordinates":[-60.27285,46.2791],"type":"Point"}
}