{
  "type": "Feature",
  "properties": {
    "gn:admin1_code":"8",
    "gn:asciiname":"Glen Cross",
    "gn:country_code":"CA",
    "gn:dem":324,
    "gn:feature_class":"P",
    "gn:feature_code":"PPL",
    "gn:name":"Glen Cross",
    "gn:population":0,
    "gn:timezone":"America/Toronto",
    "iso:country":"CA",
    "wof:name":"Glen Cross",
    "wof:placetype":"locality"
},
  "geometry": {"coordinates":[-80.04544,43.9846],"type":"Point"}
}