{
  "type": "Feature",
  "properties": {
    "gn:admin1_code":"7",
    "gn:asciiname":"Glenville",
    "gn:country_code":"CA",
    "gn:dem":74,
    "gn:feature_class":"P",
    "gn:feature_code":"PPL",
    "gn:name":"Glenville",
    "gn:population":0,
    "gn:timezone":"America/Halifax",
    "iso:country":"CA",
    "wof:name":"Glenville",
    "wof:placetype":"locality"
},
  "geometry": {"coordinates":[-61.31675,46.15371],"type":"Point"}
}