{
  "type": "Feature",
  "properties": {
    "gn:admin1_code":"7",
    "gn:asciiname":"Glenville",
    "gn:country_code":"CA",
    "gn:dem":74,
    "gn:feature_class":"P",
    "gn:feature_code":"PPL",
    "gn:name":"Glenville",
    "gn:population":0,
    "gn:timezone":"America/Halifax",
    "iso:country":"CA",
    "name:bar_x_preferred":[
        "Glenville"
    ],
    "name:cat_x_preferred":[
        "Glenville"
    ],
    "name:ceb_x_preferred":[
        "Glenville"
    ],
    "name:deu_x_preferred":[
        "Glenville"
    ],
    "name:hun_x_preferred":[
        "Glenville"
    ],
    "name:ita_x_preferred":[
        "Glenville"
    ],
    "name:nld_x_preferred":[
        "Glenville"
    ],
    "name:pol_x_preferred":[
        "Glenville"
    ],
    "name:por_x_preferred":[
        "Glenville"
    ],
    "name:rus_x_preferred":[
        "\u0413\u043b\u0435\u043d\u0432\u0438\u043b\u043b"
    ],
    "name:srp_x_preferred":[
        "\u0413\u043b\u0435\u043d\u0432\u0438\u043b"
    ],
    "name:swe_x_preferred":[
        "Glenville"
    ],
    "name:vol_x_preferred":[
        "Glenville"
    ],
    "wof:name":"Glenville",
    "wof:placetype":"locality"
},
  "geometry": {"coordinates":[-61.31675,46.15371],"type":"Point"}
}