{
  "type": "Feature",
  "properties": {
    "gn:admin1_code":"8.0",
    "gn:asciiname":"Chambers Corners",
    "gn:country_code":"CA",
    "gn:dem":176,
    "gn:feature_class":"P",
    "gn:feature_code":"PPL",
    "gn:name":"Chambers Corners",
    "gn:population":0,
    "gn:timezone":"America/Toronto",
    "iso:country":"CA",
    "wof:name":"Chambers Corners",
    "wof:placetype":"locality"
},
  "geometry": {"coordinates":[-79.37888000000002,42.94462],"type":"Point"}
}