{
  "type": "Feature",
  "properties": {
    "gn:admin1_code":"10",
    "gn:admin2_code":"14.0",
    "gn:admin3_code":"62007.0",
    "gn:asciiname":"Place-Jardin-des-Beaux-Arts",
    "gn:country_code":"CA",
    "gn:dem":137,
    "gn:feature_class":"P",
    "gn:feature_code":"PPL",
    "gn:name":"Place-Jardin-des-Beaux-Arts",
    "gn:population":0,
    "gn:timezone":"America/Toronto",
    "iso:country":"CA",
    "wof:name":"Place-Jardin-des-Beaux-Arts",
    "wof:placetype":"locality"
},
  "geometry": {"coordinates":[-73.43347,46.15504],"type":"Point"}
}