{
  "type": "Feature",
  "properties": {
    "gn:country":"CA",
    "gn:fcode":"PPL",
    "gn:population":0,
    "iso:country":"CA",
    "name:ara_x_preferred":[
        "\u062c\u0632\u064a\u0631\u0629 \u0643\u0627\u0645\u0628\u0644"
    ],
    "name:ben_x_preferred":[
        "\u0995\u09cd\u09af\u09be\u09ae\u09ae\u09cd\u09aa\u09ac\u09c7\u09b2 \u0986\u0987\u09b2\u09cd\u09af\u09be\u09a8\u09cd\u09a1"
    ],
    "name:ceb_x_preferred":[
        "Campbell Island"
    ],
    "name:deu_x_preferred":[
        "Campbell Island"
    ],
    "name:ell_x_preferred":[
        "\u039d\u03ae\u03c3\u03bf\u03c2 \u039a\u03ac\u03bc\u03c0\u03b5\u03bb"
    ],
    "name:fas_x_preferred":[
        "\u062c\u0632\u06cc\u0631\u0647 \u06a9\u0627\u0645\u067e\u0628\u0644"
    ],
    "name:fra_x_preferred":[
        "\u00cele Campbell"
    ],
    "name:heb_x_preferred":[
        "\u05d4\u05d0\u05d9 \u05e7\u05de\u05e4\u05d1\u05dc"
    ],
    "name:hin_x_preferred":[
        "\u0915\u0948\u092e\u094d\u092a\u092c\u0947\u0932 \u0926\u094d\u0935\u0940\u092a"
    ],
    "name:hun_x_preferred":[
        "Campbell-sziget"
    ],
    "name:ita_x_preferred":[
        "Isola Campbell"
    ],
    "name:kor_x_preferred":[
        "\ucea0\ubca8 \uc544\uc77c\ub79c\ub4dc"
    ],
    "name:por_x_preferred":[
        "Campbell Island"
    ],
    "name:spa_x_preferred":[
        "Isla Campbell"
    ],
    "name:swe_x_preferred":[
        "Campbell Island"
    ],
    "name:tur_x_preferred":[
        "Campbell Adas\u0131"
    ],
    "name:urd_x_preferred":[
        "\u06a9\u06cc\u0645\u067e\u0628\u0644 \u062c\u0632\u06cc\u0631\u06c1"
    ],
    "name:vie_x_preferred":[
        "\u0110\u1ea3o Campbell"
    ],
    "qs_pg:aaroncc":"CA",
    "qs_pg:gn_country":"CA",
    "qs_pg:gn_fcode":"PPL",
    "qs_pg:gn_pop":0,
    "qs_pg:name":"Campbell Island",
    "qs_pg:name_adm0":"Canada",
    "qs_pg:name_adm1":"British Columbia",
    "qs_pg:photos":67,
    "qs_pg:photos_1k":14,
    "qs_pg:photos_9k":1,
    "qs_pg:photos_9r":2,
    "qs_pg:photos_all":67,
    "qs_pg:photos_sr":2,
    "qs_pg:pop_sr":0,
    "qs_pg:qs_pg_placetype":"locality",
    "qs_pg:qs_pg_placetype_gp":"Town",
    "qs_pg:woe_adm0":23424775,
    "woe:adm0_id":23424775,
    "woe:name_adm0":"Canada",
    "woe:name_adm1":"British Columbia",
    "woe:placetype":"Town",
    "wof:name":"Campbell Island",
    "wof:placetype":"locality"
},
  "geometry": {"coordinates":[-128.14501000000001,52.16903],"type":"Point"}
}