{
  "type": "Feature",
  "properties": {
    "gn:country":"CA",
    "gn:fcode":"PPL",
    "gn:population":0,
    "iso:country":"CA",
    "name:ceb_x_preferred":[
        "Campbell Island"
    ],
    "name:deu_x_preferred":[
        "Campbell Island"
    ],
    "name:fra_x_preferred":[
        "\u00cele Campbell"
    ],
    "name:por_x_preferred":[
        "Campbell Island"
    ],
    "name:spa_x_preferred":[
        "Isla Campbell"
    ],
    "name:swe_x_preferred":[
        "Campbell Island"
    ],
    "name:vie_x_preferred":[
        "\u0110\u1ea3o Campbell"
    ],
    "qs_pg:aaroncc":"CA",
    "qs_pg:gn_country":"CA",
    "qs_pg:gn_fcode":"PPL",
    "qs_pg:gn_pop":0,
    "qs_pg:name":"Campbell Island",
    "qs_pg:name_adm0":"Canada",
    "qs_pg:name_adm1":"British Columbia",
    "qs_pg:photos":67,
    "qs_pg:photos_1k":14,
    "qs_pg:photos_9k":1,
    "qs_pg:photos_9r":2,
    "qs_pg:photos_all":67,
    "qs_pg:photos_sr":2,
    "qs_pg:pop_sr":0,
    "qs_pg:qs_pg_placetype":"locality",
    "qs_pg:qs_pg_placetype_gp":"Town",
    "qs_pg:woe_adm0":23424775,
    "woe:adm0_id":23424775,
    "woe:name_adm0":"Canada",
    "woe:name_adm1":"British Columbia",
    "woe:placetype":"Town",
    "wof:name":"Campbell Island",
    "wof:placetype":"locality"
},
  "geometry": {"coordinates":[-128.14501000000001,52.16903],"type":"Point"}
}