{
  "type": "Feature",
  "properties": {
    "iso:country":"CA",
    "name:bre_x_preferred":[
        "Gleichen"
    ],
    "name:ceb_x_preferred":[
        "Gleichen"
    ],
    "name:cos_x_preferred":[
        "Gleichen"
    ],
    "name:dan_x_preferred":[
        "Gleichen"
    ],
    "name:deu_x_preferred":[
        "Gleichen"
    ],
    "name:eng_x_preferred":[
        "Gleichen"
    ],
    "name:fas_x_preferred":[
        "\u06af\u0644\u06cc\u0686\u0646"
    ],
    "name:fra_x_preferred":[
        "Gleichen"
    ],
    "name:ind_x_preferred":[
        "Gleichen"
    ],
    "name:ita_x_preferred":[
        "Gleichen"
    ],
    "name:nds_x_preferred":[
        "Gleichen"
    ],
    "name:nld_x_preferred":[
        "Gleichen"
    ],
    "name:por_x_preferred":[
        "Gleichen"
    ],
    "name:ron_x_preferred":[
        "Gleichen"
    ],
    "name:spa_x_preferred":[
        "Gleichen"
    ],
    "name:swe_x_preferred":[
        "Gleichen"
    ],
    "name:tah_x_preferred":[
        "Gleichen"
    ],
    "qs:name":"Gleichen",
    "qs:name_adm0":"Canada",
    "qs:name_adm1":"Alberta",
    "qs:photos":43,
    "qs:photos_1k":9,
    "qs:photos_9k":1,
    "qs:photos_9r":2,
    "qs:photos_all":43,
    "qs:photos_sr":2,
    "qs:placetype":"Town",
    "qs:pop_sr":"0",
    "wd:wordcount":416,
    "wof:name":"Gleichen",
    "wof:placetype":"locality"
},
  "geometry": {"coordinates":[-113.054294,50.865805],"type":"Point"}
}