{
  "type": "Feature",
  "properties": {
    "gn:country":"CA",
    "gn:fcode":"PPL",
    "gn:population":0,
    "iso:country":"CA",
    "name:deu_x_preferred":[
        "Harbour Main"
    ],
    "name:eng_x_preferred":[
        "Harbour Main"
    ],
    "qs:name":"Harbour Main",
    "qs:name_adm0":"Canada",
    "qs:name_adm1":"Newfoundland and Labrador",
    "qs:photos":10,
    "qs:photos_1k":2,
    "qs:photos_9k":1,
    "qs:photos_9r":1,
    "qs:photos_all":10,
    "qs:photos_sr":1,
    "qs:placetype":"Town",
    "qs:pop_sr":"0",
    "wd:wordcount":145,
    "wof:name":"Harbour Main",
    "wof:placetype":"locality",
    "wof:population":0
},
  "geometry": {"coordinates":[-53.16478,47.43319],"type":"Point"}
}