{
  "type": "Feature",
  "properties": {
    "gn:admin1_code":"7.0",
    "gn:asciiname":"Brickyard Road",
    "gn:country_code":"CA",
    "gn:dem":10,
    "gn:feature_class":"P",
    "gn:feature_code":"PPL",
    "gn:name":"Brickyard Road",
    "gn:population":0,
    "gn:timezone":"America/Glace_Bay",
    "iso:country":"CA",
    "wof:name":"Brickyard Road",
    "wof:placetype":"locality"
},
  "geometry": {"coordinates":[-60.02891999999999,46.02696],"type":"Point"}
}