{
  "type": "Feature",
  "properties": {
    "gn:admin1_code":"11",
    "gn:asciiname":"Tate",
    "gn:country_code":"CA",
    "gn:dem":527,
    "gn:feature_class":"P",
    "gn:feature_code":"PPL",
    "gn:name":"Tate",
    "gn:population":0,
    "gn:timezone":"America/Regina",
    "iso:country":"CA",
    "name:bel_x_preferred":[
        "\u0413\u0430\u043b\u0435\u0440\u044d\u044f \u0422\u044d\u0439\u0442"
    ],
    "name:cat_x_preferred":[
        "Tate"
    ],
    "name:ces_x_preferred":[
        "Tate Gallery"
    ],
    "name:dan_x_preferred":[
        "Tate Gallery"
    ],
    "name:deu_x_preferred":[
        "Tate Gallery"
    ],
    "name:epo_x_preferred":[
        "Tate"
    ],
    "name:fas_x_preferred":[
        "\u062a\u06cc\u062a"
    ],
    "name:fra_x_preferred":[
        "Tate"
    ],
    "name:glg_x_preferred":[
        "Tate"
    ],
    "name:heb_x_preferred":[
        "\u05d2\u05dc\u05e8\u05d9\u05d9\u05ea \u05d8\u05d9\u05d9\u05d8"
    ],
    "name:hun_x_preferred":[
        "Tate"
    ],
    "name:ind_x_preferred":[
        "Tate"
    ],
    "name:ita_x_preferred":[
        "Tate"
    ],
    "name:jpn_x_preferred":[
        "\u30c6\u30fc\u30c8\u30fb\u30ae\u30e3\u30e9\u30ea\u30fc"
    ],
    "name:kat_x_preferred":[
        "\u10e2\u10d4\u10d8\u10e2\u10d8"
    ],
    "name:kor_x_preferred":[
        "\ud14c\uc774\ud2b8"
    ],
    "name:lat_x_preferred":[
        "Pinacotheca Tate"
    ],
    "name:lit_x_preferred":[
        "Tate muziejus"
    ],
    "name:mkd_x_preferred":[
        "\u0422\u0435\u0458\u0442"
    ],
    "name:nld_x_preferred":[
        "Tate Gallery"
    ],
    "name:nor_x_preferred":[
        "Tate Gallery"
    ],
    "name:pol_x_preferred":[
        "Tate"
    ],
    "name:por_x_preferred":[
        "Tate"
    ],
    "name:rus_x_preferred":[
        "\u0413\u0430\u043b\u0435\u0440\u0435\u044f \u0422\u0435\u0439\u0442"
    ],
    "name:spa_x_preferred":[
        "Tate"
    ],
    "name:srp_x_preferred":[
        "\u0422\u0435\u0458\u0442 \u0433\u0430\u043b\u0435\u0440\u0438\u0458\u0435"
    ],
    "name:swe_x_preferred":[
        "Tate"
    ],
    "name:tha_x_preferred":[
        "\u0e2b\u0e2d\u0e28\u0e34\u0e25\u0e1b\u0e4c\u0e40\u0e17\u0e15"
    ],
    "name:tur_x_preferred":[
        "Tate"
    ],
    "name:ukr_x_preferred":[
        "\u0422\u0435\u0439\u0442"
    ],
    "name:zho_x_preferred":[
        "\u6cf0\u7279\u7f8e\u8853\u9928"
    ],
    "wof:name":"Tate",
    "wof:placetype":"locality"
},
  "geometry": {"coordinates":[-104.8339,51.45003],"type":"Point"}
}