{
  "type": "Feature",
  "properties": {
    "gn:admin1_code":"11",
    "gn:asciiname":"Tate",
    "gn:country_code":"CA",
    "gn:dem":527,
    "gn:feature_class":"P",
    "gn:feature_code":"PPL",
    "gn:name":"Tate",
    "gn:population":0,
    "gn:timezone":"America/Regina",
    "iso:country":"CA",
    "wof:name":"Tate",
    "wof:placetype":"locality"
},
  "geometry": {"coordinates":[-104.8339,51.45003],"type":"Point"}
}