{
  "type": "Feature",
  "properties": {
    "gn:admin1_code":"1",
    "gn:asciiname":"Hamlin",
    "gn:country_code":"CA",
    "gn:dem":646,
    "gn:feature_class":"P",
    "gn:feature_code":"PPLL",
    "gn:name":"Hamlin",
    "gn:population":0,
    "gn:timezone":"America/Edmonton",
    "iso:country":"CA",
    "wof:name":"Hamlin",
    "wof:placetype":"locality"
},
  "geometry": {"coordinates":[-111.90184000000001,53.96686],"type":"Point"}
}