{
  "type": "Feature",
  "properties": {
    "gn:admin1_code":"7.0",
    "gn:asciiname":"Briar Lake",
    "gn:country_code":"CA",
    "gn:dem":60,
    "gn:feature_class":"P",
    "gn:feature_code":"PPL",
    "gn:name":"Briar Lake",
    "gn:population":0,
    "gn:timezone":"America/Halifax",
    "iso:country":"CA",
    "wof:name":"Briar Lake",
    "wof:placetype":"locality"
},
  "geometry": {"coordinates":[-65.96987,44.14406],"type":"Point"}
}