{
  "type": "Feature",
  "properties": {
    "gn:admin1_code":"5",
    "gn:asciiname":"Point au Mal",
    "gn:country_code":"CA",
    "gn:dem":13,
    "gn:feature_class":"P",
    "gn:feature_code":"PPL",
    "gn:name":"Point au Mal",
    "gn:population":0,
    "gn:timezone":"America/St_Johns",
    "iso:country":"CA",
    "wof:name":"Point au Mal",
    "wof:placetype":"locality"
},
  "geometry": {"coordinates":[-58.65583,48.65931],"type":"Point"}
}