{
  "type": "Feature",
  "properties": {
    "gn:admin1_code":"8.0",
    "gn:asciiname":"Burnside",
    "gn:country_code":"CA",
    "gn:dem":198,
    "gn:feature_class":"P",
    "gn:feature_code":"PPL",
    "gn:name":"Burnside",
    "gn:population":0,
    "gn:timezone":"America/Toronto",
    "iso:country":"CA",
    "name:bar_x_preferred":[
        "Burnside"
    ],
    "name:cat_x_preferred":[
        "Burnside"
    ],
    "name:ceb_x_preferred":[
        "Burnside"
    ],
    "name:deu_x_preferred":[
        "Burnside"
    ],
    "name:fra_x_preferred":[
        "Burnside"
    ],
    "name:ita_x_preferred":[
        "Burnside"
    ],
    "name:jpn_x_preferred":[
        "\u30d0\u30fc\u30f3\u30b5\u30a4\u30c9"
    ],
    "name:nld_x_preferred":[
        "Burnside"
    ],
    "name:pol_x_preferred":[
        "Burnside"
    ],
    "name:por_x_preferred":[
        "Burnside"
    ],
    "name:rus_x_preferred":[
        "\u0411\u0451\u0440\u043d\u0441\u0430\u0439\u0434"
    ],
    "name:spa_x_preferred":[
        "Burnside"
    ],
    "name:srp_x_preferred":[
        "\u0411\u0435\u0440\u043d\u0441\u0430\u0458\u0434"
    ],
    "name:swe_x_preferred":[
        "Burnside"
    ],
    "name:ukr_x_preferred":[
        "\u0411\u0435\u0440\u043d\u0441\u0430\u0439\u0434"
    ],
    "name:vol_x_preferred":[
        "Burnside"
    ],
    "wof:name":"Burnside",
    "wof:placetype":"locality"
},
  "geometry": {"coordinates":[-79.51871,44.75261],"type":"Point"}
}