{
  "type": "Feature",
  "properties": {
    "gn:admin1_code":"8.0",
    "gn:asciiname":"Burnside",
    "gn:country_code":"CA",
    "gn:dem":198,
    "gn:feature_class":"P",
    "gn:feature_code":"PPL",
    "gn:name":"Burnside",
    "gn:population":0,
    "gn:timezone":"America/Toronto",
    "iso:country":"CA",
    "wof:name":"Burnside",
    "wof:placetype":"locality"
},
  "geometry": {"coordinates":[-79.51871,44.75261],"type":"Point"}
}