{
  "type": "Feature",
  "properties": {
    "gn:admin1_code":"5",
    "gn:asciiname":"Lobster Cove",
    "gn:country_code":"CA",
    "gn:dem":45,
    "gn:feature_class":"P",
    "gn:feature_code":"PPL",
    "gn:name":"Lobster Cove",
    "gn:population":0,
    "gn:timezone":"America/St_Johns",
    "iso:country":"CA",
    "name:fra_x_preferred":[
        "Lobster Cove"
    ],
    "wof:name":"Lobster Cove",
    "wof:placetype":"locality"
},
  "geometry": {"coordinates":[-57.94832,49.61671],"type":"Point"}
}