{
  "type": "Feature",
  "properties": {
    "gn:admin1_code":"1",
    "gn:asciiname":"Kerensky",
    "gn:country_code":"CA",
    "gn:dem":632,
    "gn:feature_class":"P",
    "gn:feature_code":"PPLL",
    "gn:name":"Kerensky",
    "gn:population":0,
    "gn:timezone":"America/Edmonton",
    "iso:country":"CA",
    "wof:name":"Kerensky",
    "wof:placetype":"locality"
},
  "geometry": {"coordinates":[-113.1353,54.01685],"type":"Point"}
}