{
  "type": "Feature",
  "properties": {
    "gn:admin1_code":"12",
    "gn:asciiname":"Gold Bottom",
    "gn:country_code":"CA",
    "gn:dem":609,
    "gn:feature_class":"P",
    "gn:feature_code":"PPLL",
    "gn:name":"Gold Bottom",
    "gn:population":0,
    "gn:timezone":"America/Whitehorse",
    "iso:country":"CA",
    "wof:name":"Gold Bottom",
    "wof:placetype":"locality"
},
  "geometry": {"coordinates":[-138.96271000000002,63.96337],"type":"Point"}
}