{
  "type": "Feature",
  "properties": {
    "gn:admin1_code":"4",
    "gn:asciiname":"Smiths Crossing",
    "gn:country_code":"CA",
    "gn:dem":54,
    "gn:feature_class":"P",
    "gn:feature_code":"PPL",
    "gn:name":"Smiths Crossing",
    "gn:population":0,
    "gn:timezone":"America/Moncton",
    "iso:country":"CA",
    "wof:name":"Smiths Crossing",
    "wof:placetype":"locality"
},
  "geometry": {"coordinates":[-65.80718,46.7758],"type":"Point"}
}