{
  "type": "Feature",
  "properties": {
    "gn:admin1_code":"8",
    "gn:asciiname":"Glen Rae",
    "gn:country_code":"CA",
    "gn:dem":207,
    "gn:feature_class":"P",
    "gn:feature_code":"PPLL",
    "gn:name":"Glen Rae",
    "gn:population":0,
    "gn:timezone":"America/Toronto",
    "iso:country":"CA",
    "wof:name":"Glen Rae",
    "wof:placetype":"locality"
},
  "geometry": {"coordinates":[-82.0359,42.81728],"type":"Point"}
}