{
  "type": "Feature",
  "properties": {
    "gn:admin1_code":"7.0",
    "gn:asciiname":"Commodore Park",
    "gn:country_code":"CA",
    "gn:dem":55,
    "gn:feature_class":"P",
    "gn:feature_code":"PPL",
    "gn:name":"Commodore Park",
    "gn:population":0,
    "gn:timezone":"America/Halifax",
    "iso:country":"CA",
    "wof:name":"Commodore Park",
    "wof:placetype":"locality"
},
  "geometry": {"coordinates":[-63.53094,44.68037],"type":"Point"}
}