{
  "type": "Feature",
  "properties": {
    "gn:admin1_code":"8",
    "gn:asciiname":"Warren",
    "gn:country_code":"CA",
    "gn:dem":240,
    "gn:feature_class":"P",
    "gn:feature_code":"PPL",
    "gn:name":"Warren",
    "gn:population":0,
    "gn:timezone":"America/Toronto",
    "iso:country":"CA",
    "wof:name":"Warren",
    "wof:placetype":"locality"
},
  "geometry": {"coordinates":[-80.29969,46.45009],"type":"Point"}
}