{
  "type": "Feature",
  "properties": {
    "gn:country":"CA",
    "iso:country":"CA",
    "name:ceb_x_preferred":[
        "Sturdies Bay"
    ],
    "name:eng_x_preferred":[
        "Sturdies Bay"
    ],
    "name:nld_x_preferred":[
        "Sturdies Bay"
    ],
    "name:swe_x_preferred":[
        "Sturdies Bay"
    ],
    "qs_pg:aaroncc":"CA",
    "qs_pg:gn_country":"CA",
    "qs_pg:name":"Sturdies Bay",
    "qs_pg:name_adm0":"Canada",
    "qs_pg:name_adm1":"British Columbia",
    "qs_pg:photos":1621,
    "qs_pg:photos_1k":328,
    "qs_pg:photos_9k":7,
    "qs_pg:photos_9r":8,
    "qs_pg:photos_all":1621,
    "qs_pg:photos_sr":13,
    "qs_pg:pop_sr":0,
    "qs_pg:qs_pg_placetype":"locality",
    "qs_pg:qs_pg_placetype_gp":"Town",
    "qs_pg:woe_adm0":23424775,
    "woe:adm0_id":23424775,
    "woe:name_adm0":"Canada",
    "woe:name_adm1":"British Columbia",
    "woe:placetype":"Town",
    "wof:name":"Sturdies Bay",
    "wof:placetype":"locality"
},
  "geometry": {"coordinates":[-123.306083,48.87772],"type":"Point"}
}