{
  "type": "Feature",
  "properties": {
    "gn:admin1_code":"13.0",
    "gn:asciiname":"Brownings Landing",
    "gn:country_code":"CA",
    "gn:dem":132,
    "gn:feature_class":"P",
    "gn:feature_code":"PPLL",
    "gn:name":"Brownings Landing",
    "gn:population":0,
    "gn:timezone":"America/Yellowknife",
    "iso:country":"CA",
    "wof:name":"Brownings Landing",
    "wof:placetype":"locality"
},
  "geometry": {"coordinates":[-119.80289999999999,61.3002],"type":"Point"}
}