{
  "type": "Feature",
  "properties": {
    "iso:country":"CA",
    "name:dan_x_preferred":[
        "Neustadt"
    ],
    "name:dut_x_preferred":[
        "Neustadt"
    ],
    "name:eng_x_preferred":[
        "Neustadt"
    ],
    "name:ger_x_preferred":[
        "Neustadt"
    ],
    "name:heb_x_preferred":[
        "\u05e0\u05d5\u05d9\u05e9\u05d8\u05d0\u05d3"
    ],
    "name:pdc_x_preferred":[
        "Nei-Schtadt"
    ],
    "qs_pg:aaroncc":"CA",
    "qs_pg:name":"Neustadt",
    "qs_pg:name_adm0":"Canada",
    "qs_pg:name_adm1":"Ontario",
    "qs_pg:photos":26,
    "qs_pg:photos_1k":5,
    "qs_pg:photos_9k":1,
    "qs_pg:photos_9r":2,
    "qs_pg:photos_all":26,
    "qs_pg:photos_sr":2,
    "qs_pg:pop_sr":0,
    "qs_pg:qs_pg_placetype":"locality",
    "qs_pg:qs_pg_placetype_gp":"Town",
    "qs_pg:woe_adm0":23424775,
    "woe:adm0_id":23424775,
    "woe:name_adm0":"Canada",
    "woe:name_adm1":"Ontario",
    "woe:placetype":"Town",
    "wof:name":"Neustadt",
    "wof:placetype":"locality"
},
  "geometry": {"coordinates":[-81.00481499999999,44.115675],"type":"Point"}
}