{
  "type": "Feature",
  "properties": {
    "gn:admin1_code":"8",
    "gn:asciiname":"Elmgrove",
    "gn:country_code":"CA",
    "gn:dem":218,
    "gn:feature_class":"P",
    "gn:feature_code":"PPL",
    "gn:name":"Elmgrove",
    "gn:population":0,
    "gn:timezone":"America/Toronto",
    "iso:country":"CA",
    "wof:name":"Elmgrove",
    "wof:placetype":"locality"
},
  "geometry": {"coordinates":[-79.82056,44.19278],"type":"Point"}
}