{
  "type": "Feature",
  "properties": {
    "gn:admin1_code":"1",
    "gn:asciiname":"Silver Sands",
    "gn:country_code":"CA",
    "gn:dem":755,
    "gn:feature_class":"P",
    "gn:feature_code":"PPL",
    "gn:name":"Silver Sands",
    "gn:population":0,
    "gn:timezone":"America/Edmonton",
    "iso:country":"CA",
    "wof:name":"Silver Sands",
    "wof:placetype":"locality"
},
  "geometry": {"coordinates":[-114.6521,53.63343],"type":"Point"}
}