{
  "type": "Feature",
  "properties": {
    "gn:admin1_code":"5.0",
    "gn:asciiname":"Benton",
    "gn:country_code":"CA",
    "gn:dem":54,
    "gn:feature_class":"P",
    "gn:feature_code":"PPL",
    "gn:name":"Benton",
    "gn:population":0,
    "gn:timezone":"America/St_Johns",
    "iso:country":"CA",
    "name:fra_x_preferred":[
        "Benton"
    ],
    "wof:name":"Benton",
    "wof:placetype":"locality"
},
  "geometry": {"coordinates":[-54.41483,48.89991],"type":"Point"}
}