{
  "type": "Feature",
  "properties": {
    "gn:admin1_code":"1.0",
    "gn:asciiname":"Cygnet",
    "gn:country_code":"CA",
    "gn:dem":929,
    "gn:feature_class":"P",
    "gn:feature_code":"PPLL",
    "gn:name":"Cygnet",
    "gn:population":0,
    "gn:timezone":"America/Edmonton",
    "iso:country":"CA",
    "wof:name":"Cygnet",
    "wof:placetype":"locality"
},
  "geometry": {"coordinates":[-113.952,52.26681],"type":"Point"}
}