{
  "type": "Feature",
  "properties": {
    "gn:admin1_code":"7",
    "gn:asciiname":"L'Archeveque",
    "gn:country_code":"CA",
    "gn:dem":0,
    "gn:feature_class":"P",
    "gn:feature_code":"PPL",
    "gn:name":"L'Archeveque",
    "gn:population":0,
    "gn:timezone":"America/Halifax",
    "iso:country":"CA",
    "wof:name":"L'Archeveque",
    "wof:placetype":"locality"
},
  "geometry": {"coordinates":[-60.57743000000001,45.62613],"type":"Point"}
}