{
  "type": "Feature",
  "properties": {
    "gn:admin1_code":"8",
    "gn:asciiname":"Shisler Point",
    "gn:country_code":"CA",
    "gn:dem":185,
    "gn:feature_class":"P",
    "gn:feature_code":"PPL",
    "gn:name":"Shisler Point",
    "gn:population":0,
    "gn:timezone":"America/Toronto",
    "iso:country":"CA",
    "wof:name":"Shisler Point",
    "wof:placetype":"locality"
},
  "geometry": {"coordinates":[-79.13484,42.87324],"type":"Point"}
}