{
  "type": "Feature",
  "properties": {
    "iso:country":"CA",
    "name:dut_x_preferred":[
        "Hoyt"
    ],
    "name:eng_x_preferred":[
        "Hoyt"
    ],
    "name:fre_x_preferred":[
        "Hoyt"
    ],
    "qs_pg:aaroncc":"CA",
    "qs_pg:name":"Hoyt",
    "qs_pg:name_adm0":"Canada",
    "qs_pg:name_adm1":"New Brunswick",
    "qs_pg:photos":96,
    "qs_pg:photos_1k":19,
    "qs_pg:photos_9k":1,
    "qs_pg:photos_9r":3,
    "qs_pg:photos_all":96,
    "qs_pg:photos_sr":3,
    "qs_pg:pop_sr":0,
    "qs_pg:qs_pg_placetype":"locality",
    "qs_pg:qs_pg_placetype_gp":"Town",
    "qs_pg:woe_adm0":23424775,
    "woe:adm0_id":23424775,
    "woe:name_adm0":"Canada",
    "woe:name_adm1":"New Brunswick",
    "woe:placetype":"Town",
    "wof:name":"Hoyt",
    "wof:placetype":"locality"
},
  "geometry": {"coordinates":[-66.549041,45.578258],"type":"Point"}
}