{
  "type": "Feature",
  "properties": {
    "iso:country":"CA",
    "name:dan_x_preferred":[
        "Rama"
    ],
    "name:eng_x_preferred":[
        "Rama"
    ],
    "name:fry_x_preferred":[
        "Rama"
    ],
    "name:nld_x_preferred":[
        "Rama"
    ],
    "qs_pg:aaroncc":"CA",
    "qs_pg:name":"Rama",
    "qs_pg:name_adm0":"Canada",
    "qs_pg:name_adm1":"Ontario",
    "qs_pg:photos":397,
    "qs_pg:photos_1k":80,
    "qs_pg:photos_9k":2,
    "qs_pg:photos_9r":5,
    "qs_pg:photos_all":397,
    "qs_pg:photos_sr":6,
    "qs_pg:pop_sr":0,
    "qs_pg:qs_pg_placetype":"locality",
    "qs_pg:qs_pg_placetype_gp":"Town",
    "qs_pg:woe_adm0":23424775,
    "woe:adm0_id":23424775,
    "woe:name_adm0":"Canada",
    "woe:name_adm1":"Ontario",
    "woe:placetype":"Town",
    "wof:name":"Rama",
    "wof:placetype":"locality"
},
  "geometry": {"coordinates":[-79.285473,44.717397],"type":"Point"}
}