{
  "type": "Feature",
  "properties": {
    "iso:country":"CA",
    "name:kor_x_preferred":[
        "\uadf8\ub9b0\ubc45\ud06c"
    ],
    "qs_pg:aaroncc":"CA",
    "qs_pg:name":"Greenbank",
    "qs_pg:name_adm0":"Canada",
    "qs_pg:name_adm1":"Ontario",
    "qs_pg:photos":14,
    "qs_pg:photos_1k":3,
    "qs_pg:photos_9r":0,
    "qs_pg:photos_sr":1,
    "qs_pg:pop_sr":0,
    "qs_pg:qs_pg_placetype":"locality",
    "qs_pg:qs_pg_placetype_gp":"Town",
    "qs_pg:woe_adm0":23424775,
    "woe:adm0_id":23424775,
    "woe:name_adm0":"Canada",
    "woe:name_adm1":"Ontario",
    "woe:placetype":"Town",
    "wof:name":"Greenbank",
    "wof:placetype":"locality"
},
  "geometry": {"coordinates":[-79.0252155,44.163858],"type":"Point"}
}