{
  "type": "Feature",
  "properties": {
    "gn:admin1_code":"7",
    "gn:asciiname":"Garlands Crossing",
    "gn:country_code":"CA",
    "gn:dem":22,
    "gn:feature_class":"P",
    "gn:feature_code":"PPL",
    "gn:name":"Garlands Crossing",
    "gn:population":0,
    "gn:timezone":"America/Halifax",
    "iso:country":"CA",
    "wof:name":"Garlands Crossing",
    "wof:placetype":"locality"
},
  "geometry": {"coordinates":[-64.10965,44.97443],"type":"Point"}
}