{
  "type": "Feature",
  "properties": {
    "gn:admin1_code":"8.0",
    "gn:asciiname":"Ambassador Beach",
    "gn:country_code":"CA",
    "gn:dem":179,
    "gn:feature_class":"P",
    "gn:feature_code":"PPLL",
    "gn:name":"Ambassador Beach",
    "gn:population":0,
    "gn:timezone":"America/Toronto",
    "iso:country":"CA",
    "wof:name":"Ambassador Beach",
    "wof:placetype":"locality"
},
  "geometry": {"coordinates":[-82.98544,42.01319],"type":"Point"}
}