{
  "type": "Feature",
  "properties": {
    "iso:country":"CA",
    "name:eng_x_preferred":[
        "Steeles"
    ],
    "torsdfa:AREA_NAME":"Steeles (116)",
    "torsdfa:AREA_S_CD":"116",
    "wof:lang":[
        "eng"
    ],
    "wof:name":"Steeles",
    "wof:placetype":"neighbourhood"
},
  "geometry": {"coordinates":[-79.321212,43.812981],"type":"Point"}
}