{
  "type": "Feature",
  "properties": {
    "gn:admin1_code":"11.0",
    "gn:asciiname":"Witchekan",
    "gn:country_code":"CA",
    "gn:dem":584,
    "gn:feature_class":"P",
    "gn:feature_code":"PPLL",
    "gn:name":"Witchekan",
    "gn:population":0,
    "gn:timezone":"America/Regina",
    "iso:country":"CA",
    "wof:name":"Witchekan",
    "wof:placetype":"locality"
},
  "geometry": {"coordinates":[-107.56793999999999,53.50013000000001],"type":"Point"}
}