{
  "type": "Feature",
  "properties": {
    "gn:admin1_code":"7",
    "gn:asciiname":"Polsons Brook",
    "gn:country_code":"CA",
    "gn:dem":99,
    "gn:feature_class":"P",
    "gn:feature_code":"PPL",
    "gn:name":"Polsons Brook",
    "gn:population":0,
    "gn:timezone":"America/Halifax",
    "iso:country":"CA",
    "wof:name":"Polsons Brook",
    "wof:placetype":"locality"
},
  "geometry": {"coordinates":[-61.88876,45.45218],"type":"Point"}
}