{
  "type": "Feature",
  "properties": {
    "gn:admin1_code":"8.0",
    "gn:asciiname":"Bruces",
    "gn:country_code":"CA",
    "gn:dem":248,
    "gn:feature_class":"P",
    "gn:feature_code":"PPL",
    "gn:name":"Bruces",
    "gn:population":0,
    "gn:timezone":"America/Toronto",
    "iso:country":"CA",
    "wof:name":"Bruces",
    "wof:placetype":"locality"
},
  "geometry": {"coordinates":[-80.25198,43.2743],"type":"Point"}
}