{
  "type": "Feature",
  "properties": {
    "gn:admin1_code":"10",
    "gn:admin2_code":"15.0",
    "gn:admin3_code":"75017.0",
    "gn:asciiname":"Place-Citation",
    "gn:country_code":"CA",
    "gn:dem":134,
    "gn:feature_class":"P",
    "gn:feature_code":"PPL",
    "gn:name":"Place-Citation",
    "gn:population":0,
    "gn:timezone":"America/Toronto",
    "iso:country":"CA",
    "wof:name":"Place-Citation",
    "wof:placetype":"locality"
},
  "geometry": {"coordinates":[-74.03376999999998,45.79782],"type":"Point"}
}