{
  "type": "Feature",
  "properties": {
    "gn:admin1_code":"9",
    "gn:asciiname":"Midgell",
    "gn:country_code":"CA",
    "gn:dem":7,
    "gn:feature_class":"P",
    "gn:feature_code":"PPLL",
    "gn:name":"Midgell",
    "gn:population":0,
    "gn:timezone":"America/Halifax",
    "iso:country":"CA",
    "wof:name":"Midgell",
    "wof:placetype":"locality"
},
  "geometry": {"coordinates":[-62.64865,46.41681],"type":"Point"}
}