{
  "type": "Feature",
  "properties": {
    "iso:country":"CA",
    "name:eng_x_preferred":[
        "Blockhouse"
    ],
    "name:gla_x_preferred":[
        "Blockhouse"
    ],
    "name:nld_x_preferred":[
        "Blockhouse"
    ],
    "qs:name":"Blockhouse",
    "qs:name_adm0":"Canada",
    "qs:name_adm1":"Nova Scotia",
    "qs:photos":15,
    "qs:photos_1k":3,
    "qs:photos_9k":1,
    "qs:photos_9r":1,
    "qs:photos_all":15,
    "qs:photos_sr":1,
    "qs:placetype":"Town",
    "qs:pop_sr":"0",
    "wd:wordcount":1725,
    "wof:name":"Blockhouse",
    "wof:placetype":"locality"
},
  "geometry": {"coordinates":[-64.42100000000001,44.448977],"type":"Point"}
}