{
  "type": "Feature",
  "properties": {
    "gn:admin1_code":"3",
    "gn:asciiname":"Rosenfeld",
    "gn:country_code":"CA",
    "gn:dem":241,
    "gn:feature_class":"P",
    "gn:feature_code":"PPL",
    "gn:name":"Rosenfeld",
    "gn:population":0,
    "gn:timezone":"America/Winnipeg",
    "iso:country":"CA",
    "wof:name":"Rosenfeld",
    "wof:placetype":"locality"
},
  "geometry": {"coordinates":[-97.5496,49.19919],"type":"Point"}
}