{
  "type": "Feature",
  "properties": {
    "gn:admin1_code":"3",
    "gn:asciiname":"Rosenfeld",
    "gn:country_code":"CA",
    "gn:dem":241,
    "gn:feature_class":"P",
    "gn:feature_code":"PPL",
    "gn:name":"Rosenfeld",
    "gn:population":0,
    "gn:timezone":"America/Winnipeg",
    "iso:country":"CA",
    "name:bel_x_preferred":[
        "\u0420\u043e\u0437\u0435\u043d\u0444\u0435\u043b\u044c\u0434"
    ],
    "name:cat_x_preferred":[
        "Rosenfeld"
    ],
    "name:ceb_x_preferred":[
        "Rosenfeld"
    ],
    "name:ces_x_preferred":[
        "Rosenfeld"
    ],
    "name:deu_x_preferred":[
        "Rosenfeld"
    ],
    "name:fin_x_preferred":[
        "Rosenfeld"
    ],
    "name:fra_x_preferred":[
        "Rosenfeld"
    ],
    "name:heb_x_preferred":[
        "\u05e8\u05d5\u05d6\u05e0\u05e4\u05dc\u05d3"
    ],
    "name:hun_x_preferred":[
        "Rosenfeld"
    ],
    "name:ita_x_preferred":[
        "Rosenfeld"
    ],
    "name:jpn_x_preferred":[
        "\u30ed\u30fc\u30bc\u30f3\u30d5\u30a7\u30eb\u30c8"
    ],
    "name:nds_x_preferred":[
        "Rosenfeld"
    ],
    "name:nld_x_preferred":[
        "Rosenfeld"
    ],
    "name:pol_x_preferred":[
        "Rosenfeld"
    ],
    "name:por_x_preferred":[
        "Rosenfeld"
    ],
    "name:ron_x_preferred":[
        "Rosenfeld"
    ],
    "name:rus_x_preferred":[
        "\u0420\u043e\u0437\u0435\u043d\u0444\u0435\u043b\u044c\u0434"
    ],
    "name:spa_x_preferred":[
        "Rosenfeld"
    ],
    "name:swe_x_preferred":[
        "Rosenfeld"
    ],
    "name:ukr_x_preferred":[
        "\u0420\u043e\u0437\u0435\u043d\u0444\u0435\u043b\u044c\u0434"
    ],
    "wof:name":"Rosenfeld",
    "wof:placetype":"locality"
},
  "geometry": {"coordinates":[-97.5496,49.19919],"type":"Point"}
}