{
  "type": "Feature",
  "properties": {
    "gn:gn_country":"CA",
    "gn:gn_fcode":"PPL",
    "gn:gn_pop":0,
    "iso:country":"CA",
    "name:ceb_x_preferred":[
        "Crofton"
    ],
    "name:eng_x_preferred":[
        "Crofton"
    ],
    "name:fra_x_preferred":[
        "Crofton"
    ],
    "name:ita_x_preferred":[
        "Crofton"
    ],
    "name:nld_x_preferred":[
        "Crofton"
    ],
    "name:swe_x_preferred":[
        "Crofton"
    ],
    "qs_pg:aaroncc":"CA",
    "qs_pg:gn_country":"CA",
    "qs_pg:gn_fcode":"PPL",
    "qs_pg:gn_pop":0,
    "qs_pg:name":"Crofton",
    "qs_pg:name_adm0":"Canada",
    "qs_pg:name_adm1":"British Columbia",
    "qs_pg:photos":2152,
    "qs_pg:photos_1k":436,
    "qs_pg:photos_9k":10,
    "qs_pg:photos_9r":9,
    "qs_pg:photos_all":2152,
    "qs_pg:photos_sr":16,
    "qs_pg:pop_sr":0,
    "qs_pg:qs_pg_placetype":"locality",
    "qs_pg:qs_pg_placetype_gp":"Town",
    "qs_pg:woe_adm0":23424775,
    "woe:adm0_id":23424775,
    "woe:name_adm0":"Canada",
    "woe:name_adm1":"British Columbia",
    "woe:placetype":"Town",
    "wof:name":"Crofton",
    "wof:placetype":"locality"
},
  "geometry": {"coordinates":[-123.65266,48.86633],"type":"Point"}
}