{
  "type": "Feature",
  "properties": {
    "gn:admin1_code":"8.0",
    "gn:asciiname":"Dewars",
    "gn:country_code":"CA",
    "gn:dem":124,
    "gn:feature_class":"P",
    "gn:feature_code":"PPL",
    "gn:name":"Dewars",
    "gn:population":0,
    "gn:timezone":"America/Toronto",
    "iso:country":"CA",
    "wof:name":"Dewars",
    "wof:placetype":"locality"
},
  "geometry": {"coordinates":[-76.47778000000002,45.47667],"type":"Point"}
}