{
  "type": "Feature",
  "properties": {
    "iso:country":"CA",
    "name:cat_x_preferred":[
        "Maillard"
    ],
    "name:deu_x_preferred":[
        "Maillard"
    ],
    "name:fra_x_preferred":[
        "Maillard"
    ],
    "name:ita_x_preferred":[
        "Maillard"
    ],
    "name:nds_x_preferred":[
        "Maillard"
    ],
    "name:nld_x_preferred":[
        "Maillard"
    ],
    "name:por_x_preferred":[
        "Maillard"
    ],
    "name:rus_x_preferred":[
        "\u041c\u0430\u0439\u044f\u0440"
    ],
    "qs_pg:aaroncc":"CA",
    "qs_pg:name":"Maillard",
    "qs_pg:name_adm0":"Canada",
    "qs_pg:name_adm1":"Qu\u00e9bec",
    "qs_pg:photos":33,
    "qs_pg:photos_1k":7,
    "qs_pg:photos_9k":1,
    "qs_pg:photos_9r":2,
    "qs_pg:photos_all":33,
    "qs_pg:photos_sr":2,
    "qs_pg:pop_sr":0,
    "qs_pg:qs_pg_placetype":"locality",
    "qs_pg:qs_pg_placetype_gp":"Town",
    "qs_pg:woe_adm0":23424775,
    "woe:adm0_id":23424775,
    "woe:name_adm0":"Canada",
    "woe:name_adm1":"Qu\u00e9bec",
    "woe:placetype":"Town",
    "wof:name":"Maillard",
    "wof:placetype":"locality"
},
  "geometry": {"coordinates":[-70.550765,47.346965],"type":"Point"}
}