{
  "type": "Feature",
  "properties": {
    "iso:country":"CA",
    "name:eng_x_preferred":[
        "Buck Lake"
    ],
    "name:fre_x_preferred":[
        "Buck Lake"
    ],
    "qs:name":"Buck Lake",
    "qs:name_adm0":"Canada",
    "qs:name_adm1":"Alberta",
    "qs:photos":38,
    "qs:photos_1k":8,
    "qs:photos_9k":1,
    "qs:photos_9r":2,
    "qs:photos_all":38,
    "qs:photos_sr":2,
    "qs:placetype":"Town",
    "qs:pop_sr":"0",
    "wd:wordcount":1381,
    "wof:name":"Buck Lake",
    "wof:placetype":"locality"
},
  "geometry": {"coordinates":[-114.782838,52.9422495],"type":"Point"}
}