{
  "type": "Feature",
  "properties": {
    "gn:admin1_code":"4",
    "gn:asciiname":"Knightville",
    "gn:country_code":"CA",
    "gn:dem":77,
    "gn:feature_class":"P",
    "gn:feature_code":"PPL",
    "gn:name":"Knightville",
    "gn:population":0,
    "gn:timezone":"America/Moncton",
    "iso:country":"CA",
    "wof:name":"Knightville",
    "wof:placetype":"locality"
},
  "geometry": {"coordinates":[-65.36783,45.86129],"type":"Point"}
}