{
  "type": "Feature",
  "properties": {
    "gn:admin1_code":"8",
    "gn:asciiname":"Fairview Island",
    "gn:country_code":"CA",
    "gn:dem":331,
    "gn:feature_class":"P",
    "gn:feature_code":"PPL",
    "gn:name":"Fairview Island",
    "gn:population":0,
    "gn:timezone":"America/Toronto",
    "iso:country":"CA",
    "wof:name":"Fairview Island",
    "wof:placetype":"locality"
},
  "geometry": {"coordinates":[-79.06873,45.22481],"type":"Point"}
}