{
  "type": "Feature",
  "properties": {
    "gn:admin1_code":"7.0",
    "gn:asciiname":"Berwick West",
    "gn:country_code":"CA",
    "gn:dem":65,
    "gn:feature_class":"P",
    "gn:feature_code":"PPL",
    "gn:name":"Berwick West",
    "gn:population":0,
    "gn:timezone":"America/Halifax",
    "iso:country":"CA",
    "wof:name":"Berwick West",
    "wof:placetype":"locality"
},
  "geometry": {"coordinates":[-64.76048,45.02913],"type":"Point"}
}