{
  "type": "Feature",
  "properties": {
    "gn:admin1_code":"3",
    "gn:asciiname":"Tummel",
    "gn:country_code":"CA",
    "gn:dem":530,
    "gn:feature_class":"P",
    "gn:feature_code":"PPLL",
    "gn:name":"Tummel",
    "gn:population":0,
    "gn:timezone":"America/Winnipeg",
    "iso:country":"CA",
    "name:nor_x_preferred":[
        "Tummel"
    ],
    "name:swe_x_preferred":[
        "Tummel"
    ],
    "wof:name":"Tummel",
    "wof:placetype":"locality"
},
  "geometry": {"coordinates":[-101.38670999999999,51.13939],"type":"Point"}
}