{
  "type": "Feature",
  "properties": {
    "gn:admin1_code":"10",
    "gn:admin2_code":"7.0",
    "gn:admin3_code":"84082.0",
    "gn:asciiname":"Wabash",
    "gn:country_code":"CA",
    "gn:dem":140,
    "gn:feature_class":"P",
    "gn:feature_code":"PPL",
    "gn:name":"Wabash",
    "gn:population":0,
    "gn:timezone":"America/Toronto",
    "iso:country":"CA",
    "name:ara_x_preferred":[
        "\u0648\u0627\u0628\u0627\u0634"
    ],
    "name:ben_x_preferred":[
        "\u0993\u09af\u09bc\u09be\u09ac\u09be\u09b6"
    ],
    "name:ceb_x_preferred":[
        "Wabash"
    ],
    "name:ces_x_preferred":[
        "Wabash"
    ],
    "name:deu_x_preferred":[
        "Wabash"
    ],
    "name:ell_x_preferred":[
        "\u039f\u03c5\u03ac\u03bc\u03c0\u03b1\u03c2"
    ],
    "name:fra_x_preferred":[
        "Wabash"
    ],
    "name:hin_x_preferred":[
        "\u0935\u093e\u092c\u093e\u0936 "
    ],
    "name:ind_x_preferred":[
        "Wabash"
    ],
    "name:kor_x_preferred":[
        "\uc640\ubc14\uc2dc"
    ],
    "name:nld_x_preferred":[
        "Wabash"
    ],
    "name:pol_x_preferred":[
        "Wabash"
    ],
    "name:por_x_preferred":[
        "Wabash"
    ],
    "name:rus_x_preferred":[
        "\u0423\u043e\u0431\u0430\u0448"
    ],
    "name:srp_x_preferred":[
        "\u0412\u043e\u0431\u0430\u0448"
    ],
    "name:swe_x_preferred":[
        "Wabash"
    ],
    "name:tur_x_preferred":[
        "Wabash"
    ],
    "name:urd_x_preferred":[
        "\u0648\u0627\u0628\u0627\u0634"
    ],
    "wof:name":"Wabash",
    "wof:placetype":"locality"
},
  "geometry": {"coordinates":[-77.10917000000001,45.86639],"type":"Point"}
}