{
  "type": "Feature",
  "properties": {
    "gn:admin1_code":"10",
    "gn:admin2_code":"7.0",
    "gn:admin3_code":"84082.0",
    "gn:asciiname":"Wabash",
    "gn:country_code":"CA",
    "gn:dem":140,
    "gn:feature_class":"P",
    "gn:feature_code":"PPL",
    "gn:name":"Wabash",
    "gn:population":0,
    "gn:timezone":"America/Toronto",
    "iso:country":"CA",
    "name:ceb_x_preferred":[
        "Wabash"
    ],
    "name:ces_x_preferred":[
        "Wabash"
    ],
    "name:deu_x_preferred":[
        "Wabash"
    ],
    "name:fra_x_preferred":[
        "Wabash"
    ],
    "name:nld_x_preferred":[
        "Wabash"
    ],
    "name:pol_x_preferred":[
        "Wabash"
    ],
    "name:por_x_preferred":[
        "Wabash"
    ],
    "name:rus_x_preferred":[
        "\u0423\u043e\u0431\u0430\u0448"
    ],
    "name:srp_x_preferred":[
        "\u0412\u043e\u0431\u0430\u0448"
    ],
    "wof:name":"Wabash",
    "wof:placetype":"locality"
},
  "geometry": {"coordinates":[-77.10916999999998,45.86639],"type":"Point"}
}