{
  "type": "Feature",
  "properties": {
    "gn:admin1_code":"8",
    "gn:asciiname":"Huron Ridge",
    "gn:country_code":"CA",
    "gn:dem":194,
    "gn:feature_class":"P",
    "gn:feature_code":"PPL",
    "gn:name":"Huron Ridge",
    "gn:population":0,
    "gn:timezone":"America/Toronto",
    "iso:country":"CA",
    "wof:name":"Huron Ridge",
    "wof:placetype":"locality"
},
  "geometry": {"coordinates":[-81.62931999999998,44.1936],"type":"Point"}
}