{
  "type": "Feature",
  "properties": {
    "gn:asciiname":"Marysville",
    "gn:country_code":"CA",
    "gn:dem":80,
    "gn:feature_class":"P",
    "gn:feature_code":"PPL",
    "gn:name":"Marysville",
    "gn:population":0,
    "gn:timezone":"America/Toronto",
    "iso:country":"CA",
    "name:bul_x_preferred":[
        "\u041c\u0435\u0440\u0438\u0441\u0432\u0438\u043b"
    ],
    "name:cat_x_preferred":[
        "Marysville"
    ],
    "name:ceb_x_preferred":[
        "Marysville"
    ],
    "name:ces_x_preferred":[
        "Marysville"
    ],
    "name:deu_x_preferred":[
        "Marysville"
    ],
    "name:fas_x_preferred":[
        "\u0645\u0627\u0631\u06cc\u0633 \u0648\u06cc\u0644"
    ],
    "name:fra_x_preferred":[
        "Marysville"
    ],
    "name:hun_x_preferred":[
        "Marysville"
    ],
    "name:ita_x_preferred":[
        "Marysville"
    ],
    "name:kor_x_preferred":[
        "\uba54\ub9ac\uc988\ube4c"
    ],
    "name:nld_x_preferred":[
        "Marysville"
    ],
    "name:pol_x_preferred":[
        "Marysville"
    ],
    "name:por_x_preferred":[
        "Marysville"
    ],
    "name:rus_x_preferred":[
        "\u041c\u044d\u0440\u0438\u0441\u0432\u0438\u043b\u043b"
    ],
    "name:spa_x_preferred":[
        "Marysville"
    ],
    "name:srp_x_preferred":[
        "\u041c\u0435\u0440\u0438\u0441\u0432\u0438\u043b"
    ],
    "name:swe_x_preferred":[
        "Marysville"
    ],
    "name:urd_x_preferred":[
        "\u0645\u06cc\u0631\u06cc\u0632\u0648\u06cc\u0644"
    ],
    "name:vol_x_preferred":[
        "Marysville"
    ],
    "wof:name":"Marysville",
    "wof:placetype":"locality"
},
  "geometry": {"coordinates":[-76.43814999999999,44.19384],"type":"Point"}
}