{
  "type": "Feature",
  "properties": {
    "gn:admin1_code":"3",
    "gn:asciiname":"Golden Bay",
    "gn:country_code":"CA",
    "gn:dem":241,
    "gn:feature_class":"P",
    "gn:feature_code":"PPLL",
    "gn:name":"Golden Bay",
    "gn:population":0,
    "gn:timezone":"America/Winnipeg",
    "iso:country":"CA",
    "wof:name":"Golden Bay",
    "wof:placetype":"locality"
},
  "geometry": {"coordinates":[-96.38338,50.06219],"type":"Point"}
}