{
  "type": "Feature",
  "properties": {
    "gn:admin1_code":"3",
    "gn:asciiname":"Golden Bay",
    "gn:country_code":"CA",
    "gn:dem":241,
    "gn:feature_class":"P",
    "gn:feature_code":"PPLL",
    "gn:name":"Golden Bay",
    "gn:population":0,
    "gn:timezone":"America/Winnipeg",
    "iso:country":"CA",
    "name:deu_x_preferred":[
        "Golden Bay"
    ],
    "name:fra_x_preferred":[
        "Golden Bay"
    ],
    "name:jpn_x_preferred":[
        "\u30b4\u30fc\u30eb\u30c7\u30f3\u6e7e"
    ],
    "name:kat_x_preferred":[
        "\u10d2\u10dd\u10da\u10d3\u10d4\u10dc-\u10d1\u10d4\u10d8"
    ],
    "name:nld_x_preferred":[
        "Golden Bay"
    ],
    "name:nno_x_preferred":[
        "Golden Bay"
    ],
    "name:nor_x_preferred":[
        "Golden Bay"
    ],
    "name:rus_x_preferred":[
        "\u0413\u043e\u043b\u0434\u0435\u043d-\u0411\u0435\u0439"
    ],
    "name:urd_x_preferred":[
        "\u06af\u0648\u0644\u0688\u0646 \u0628\u06d2"
    ],
    "name:zho_x_preferred":[
        "\u91d1\u7063"
    ],
    "wof:name":"Golden Bay",
    "wof:placetype":"locality"
},
  "geometry": {"coordinates":[-96.38338,50.06219],"type":"Point"}
}