{
  "type": "Feature",
  "properties": {
    "gn:admin1_code":"10",
    "gn:admin2_code":"5.0",
    "gn:admin3_code":"42088.0",
    "gn:asciiname":"Greenlay",
    "gn:country_code":"CA",
    "gn:dem":149,
    "gn:feature_class":"P",
    "gn:feature_code":"PPL",
    "gn:name":"Greenlay",
    "gn:population":0,
    "gn:timezone":"America/Toronto",
    "iso:country":"CA",
    "wof:name":"Greenlay",
    "wof:placetype":"locality"
},
  "geometry": {"coordinates":[-72.01093,45.55976],"type":"Point"}
}