{
  "type": "Feature",
  "properties": {
    "gn:admin1_code":"10",
    "gn:admin2_code":"8.0",
    "gn:admin3_code":"88085.0",
    "gn:asciiname":"Manneville",
    "gn:country_code":"CA",
    "gn:dem":305,
    "gn:feature_class":"P",
    "gn:feature_code":"PPL",
    "gn:name":"Manneville",
    "gn:population":0,
    "gn:timezone":"America/Toronto",
    "iso:country":"CA",
    "wof:name":"Manneville",
    "wof:placetype":"locality"
},
  "geometry": {"coordinates":[-78.43006,48.54704],"type":"Point"}
}