{
  "type": "Feature",
  "properties": {
    "iso:country":"CA",
    "name:eng_x_preferred":[
        "Jordan Falls"
    ],
    "name:nld_x_preferred":[
        "Jordan Falls"
    ],
    "qs:name":"Jordan Falls",
    "qs:name_adm0":"Canada",
    "qs:name_adm1":"Nova Scotia",
    "qs:photos":28,
    "qs:photos_1k":6,
    "qs:photos_9k":1,
    "qs:photos_9r":2,
    "qs:photos_all":28,
    "qs:photos_sr":2,
    "qs:placetype":"Town",
    "qs:pop_sr":"0",
    "wd:wordcount":83,
    "wof:name":"Jordan Falls",
    "wof:placetype":"locality"
},
  "geometry": {"coordinates":[-65.2360645,43.816081],"type":"Point"}
}