{
  "type": "Feature",
  "properties": {
    "gn:admin1_code":"8",
    "gn:asciiname":"Jellicoe",
    "gn:country_code":"CA",
    "gn:dem":339,
    "gn:feature_class":"P",
    "gn:feature_code":"PPL",
    "gn:name":"Jellicoe",
    "gn:population":0,
    "gn:timezone":"America/Toronto",
    "iso:country":"CA",
    "name:deu_x_preferred":[
        "Jellicoe"
    ],
    "name:fra_x_preferred":[
        "Jellicoe"
    ],
    "name:nds_x_preferred":[
        "Jellicoe"
    ],
    "wof:name":"Jellicoe",
    "wof:placetype":"locality"
},
  "geometry": {"coordinates":[-87.51669,49.68342],"type":"Point"}
}