{
  "type": "Feature",
  "properties": {
    "gn:admin1_code":"8.0",
    "gn:asciiname":"Dundurn",
    "gn:country_code":"CA",
    "gn:dem":245,
    "gn:feature_class":"P",
    "gn:feature_code":"PPLL",
    "gn:name":"Dundurn",
    "gn:population":0,
    "gn:timezone":"America/Toronto",
    "iso:country":"CA",
    "wof:name":"Dundurn",
    "wof:placetype":"locality"
},
  "geometry": {"coordinates":[-80.30185999999998,42.9612],"type":"Point"}
}