{
  "type": "Feature",
  "properties": {
    "gn:admin1_code":"1.0",
    "gn:asciiname":"Bluesky",
    "gn:country_code":"CA",
    "gn:dem":640,
    "gn:feature_class":"P",
    "gn:feature_code":"PPL",
    "gn:name":"Bluesky",
    "gn:population":0,
    "gn:timezone":"America/Edmonton",
    "iso:country":"CA",
    "name:fra_x_preferred":[
        "Bluesky"
    ],
    "wof:name":"Bluesky",
    "wof:placetype":"locality"
},
  "geometry": {"coordinates":[-118.23605000000001,56.06676],"type":"Point"}
}