{
  "type": "Feature",
  "properties": {
    "gn:admin1_code":"8",
    "gn:asciiname":"Hopeville",
    "gn:country_code":"CA",
    "gn:dem":493,
    "gn:feature_class":"P",
    "gn:feature_code":"PPL",
    "gn:name":"Hopeville",
    "gn:population":0,
    "gn:timezone":"America/Toronto",
    "iso:country":"CA",
    "name:deu_x_preferred":[
        "Hopeville"
    ],
    "name:nds_x_preferred":[
        "Hopeville"
    ],
    "wof:name":"Hopeville",
    "wof:placetype":"locality"
},
  "geometry": {"coordinates":[-80.54729,44.11682],"type":"Point"}
}