{
  "type": "Feature",
  "properties": {
    "gn:admin1_code":"8.0",
    "gn:asciiname":"Dixon",
    "gn:country_code":"CA",
    "gn:dem":91,
    "gn:feature_class":"P",
    "gn:feature_code":"PPL",
    "gn:name":"Dixon",
    "gn:population":0,
    "gn:timezone":"America/Toronto",
    "iso:country":"CA",
    "wof:name":"Dixon",
    "wof:placetype":"locality"
},
  "geometry": {"coordinates":[-74.97639000000002,45.0875],"type":"Point"}
}