{
  "type": "Feature",
  "properties": {
    "gn:admin1_code":"8.0",
    "gn:asciiname":"Dixon",
    "gn:country_code":"CA",
    "gn:dem":91,
    "gn:feature_class":"P",
    "gn:feature_code":"PPL",
    "gn:name":"Dixon",
    "gn:population":0,
    "gn:timezone":"America/Toronto",
    "iso:country":"CA",
    "name:ara_x_preferred":[
        "\u062f\u064a\u0643\u0633\u0648\u0646"
    ],
    "name:bel_x_preferred":[
        "\u0414\u044b\u043a\u0441\u0430\u043d"
    ],
    "name:cat_x_preferred":[
        "Dixon"
    ],
    "name:ceb_x_preferred":[
        "Dixon"
    ],
    "name:ces_x_preferred":[
        "Dixon"
    ],
    "name:deu_x_preferred":[
        "Dixon"
    ],
    "name:fin_x_preferred":[
        "Dixon"
    ],
    "name:fra_x_preferred":[
        "Dixon"
    ],
    "name:glg_x_preferred":[
        "Dixon"
    ],
    "name:heb_x_preferred":[
        "\u05d3\u05d9\u05e7\u05e1\u05d5\u05df"
    ],
    "name:ita_x_preferred":[
        "Dixon"
    ],
    "name:jpn_x_preferred":[
        "\u30c7\u30a3\u30af\u30bd\u30f3"
    ],
    "name:nld_x_preferred":[
        "Dixon"
    ],
    "name:pol_x_preferred":[
        "Dixon"
    ],
    "name:por_x_preferred":[
        "Dixon"
    ],
    "name:rus_x_preferred":[
        "\u0414\u0438\u043a\u0441\u043e\u043d"
    ],
    "name:spa_x_preferred":[
        "Dixon"
    ],
    "name:srp_x_preferred":[
        "\u0414\u0438\u043a\u0441\u043e\u043d"
    ],
    "name:swe_x_preferred":[
        "Dixon"
    ],
    "name:ukr_x_preferred":[
        "\u0414\u0456\u043a\u0441\u043e\u043d"
    ],
    "name:urd_x_preferred":[
        "\u0688\u06a9\u0633\u0646"
    ],
    "name:vol_x_preferred":[
        "Dixon"
    ],
    "name:zho_x_preferred":[
        "\u8fea\u514b\u68ee"
    ],
    "wof:name":"Dixon",
    "wof:placetype":"locality"
},
  "geometry": {"coordinates":[-74.97639000000002,45.0875],"type":"Point"}
}