{
  "type": "Feature",
  "properties": {
    "iso:country":"CA",
    "name:cat_x_preferred":[
        "Hillsdale"
    ],
    "name:ceb_x_preferred":[
        "Hillsdale"
    ],
    "name:deu_x_preferred":[
        "Hillsdale"
    ],
    "name:fas_x_preferred":[
        "\u0647\u06cc\u0644\u0632\u062f\u06cc\u0644"
    ],
    "name:ita_x_preferred":[
        "Hillsdale"
    ],
    "name:nld_x_preferred":[
        "Hillsdale"
    ],
    "name:pol_x_preferred":[
        "Hillsdale"
    ],
    "name:por_x_preferred":[
        "Hillsdale"
    ],
    "name:rus_x_preferred":[
        "\u0425\u0438\u043b\u0441\u0434\u0435\u0439\u043b"
    ],
    "name:spa_x_preferred":[
        "Hillsdale"
    ],
    "name:srp_x_preferred":[
        "\u0425\u0438\u043b\u0441\u0434\u0435\u0458\u043b"
    ],
    "name:swe_x_preferred":[
        "Hillsdale"
    ],
    "name:ukr_x_preferred":[
        "\u0413\u0456\u043b\u043b\u0441\u0434\u0435\u0439\u043b"
    ],
    "name:urd_x_preferred":[
        "\u06c1\u0644\u0632\u0688\u06cc\u0644"
    ],
    "name:vol_x_preferred":[
        "Hillsdale"
    ],
    "qs_pg:aaroncc":"CA",
    "qs_pg:name":"Hillsdale",
    "qs_pg:name_adm0":"Canada",
    "qs_pg:name_adm1":"Ontario",
    "qs_pg:photos":147,
    "qs_pg:photos_1k":30,
    "qs_pg:photos_9k":1,
    "qs_pg:photos_9r":3,
    "qs_pg:photos_all":147,
    "qs_pg:photos_sr":3,
    "qs_pg:pop_sr":0,
    "qs_pg:qs_pg_placetype":"locality",
    "qs_pg:qs_pg_placetype_gp":"Town",
    "qs_pg:woe_adm0":23424775,
    "woe:adm0_id":23424775,
    "woe:name_adm0":"Canada",
    "woe:name_adm1":"Ontario",
    "woe:placetype":"Town",
    "wof:name":"Hillsdale",
    "wof:placetype":"locality"
},
  "geometry": {"coordinates":[-79.74323200000001,44.584079],"type":"Point"}
}