{
  "type": "Feature",
  "properties": {
    "gn:admin1_code":"8",
    "gn:asciiname":"Glenwater",
    "gn:country_code":"CA",
    "gn:dem":367,
    "gn:feature_class":"P",
    "gn:feature_code":"PPL",
    "gn:name":"Glenwater",
    "gn:population":0,
    "gn:timezone":"America/Toronto",
    "iso:country":"CA",
    "wof:name":"Glenwater",
    "wof:placetype":"locality"
},
  "geometry": {"coordinates":[-89.78389,48.54667],"type":"Point"}
}