{
  "type": "Feature",
  "properties": {
    "gn:admin1_code":"1",
    "gn:asciiname":"Finnegan",
    "gn:country_code":"CA",
    "gn:dem":654,
    "gn:feature_class":"P",
    "gn:feature_code":"PPLL",
    "gn:name":"Finnegan",
    "gn:population":0,
    "gn:timezone":"America/Edmonton",
    "iso:country":"CA",
    "wof:name":"Finnegan",
    "wof:placetype":"locality"
},
  "geometry": {"coordinates":[-112.06852000000001,51.1168],"type":"Point"}
}