{
  "type": "Feature",
  "properties": {
    "gn:admin1_code":"10.0",
    "gn:admin2_code":"16.0",
    "gn:admin3_code":"69075.0",
    "gn:asciiname":"Dundee Centre",
    "gn:country_code":"CA",
    "gn:dem":57,
    "gn:feature_class":"P",
    "gn:feature_code":"PPL",
    "gn:name":"Dundee Centre",
    "gn:population":0,
    "gn:timezone":"America/Toronto",
    "iso:country":"CA",
    "wof:name":"Dundee Centre",
    "wof:placetype":"locality"
},
  "geometry": {"coordinates":[-74.42796,45.02893],"type":"Point"}
}