{
  "type": "Feature",
  "properties": {
    "iso:country":"CA",
    "name:eng_x_preferred":[
        "Blacklock"
    ],
    "name:unk_x_variant":[
        "Blacklock"
    ],
    "qs:gn_adm0_cc":"CA",
    "qs:gn_local":6049430,
    "qs:gn_nam_loc":"langley",
    "qs:gn_namadm1":"02",
    "qs:local_max":1111,
    "qs:local_sum":2058,
    "qs:localhoods":4,
    "qs:name":"Blacklock",
    "qs:name_adm0":"Canada",
    "qs:name_adm1":"British Columbia",
    "qs:name_adm2":"Greater Vancouver",
    "qs:name_local":"Langley",
    "qs:photo_max":192,
    "qs:photo_sum":241,
    "qs:placetype":"Suburb",
    "qs:quad_count":13,
    "qs:woe_adm0":23424775,
    "qs:woe_adm1":2344916,
    "qs:woe_adm2":29375222,
    "qs:woe_funk":"Parented by a neighborhood",
    "qs:woe_lau":0,
    "qs:woe_local":9823,
    "qs:woe_ver":"7.10.0",
    "wd:wordcount":204,
    "wof:lang":[
        "eng"
    ],
    "wof:name":"Blacklock",
    "wof:placetype":"neighbourhood"
},
  "geometry": {"coordinates":[-122.64193400000001,49.091981],"type":"Point"}
}