{
  "type": "Feature",
  "properties": {
    "gn:admin1_code":"7",
    "gn:asciiname":"Skye Glen",
    "gn:country_code":"CA",
    "gn:dem":52,
    "gn:feature_class":"P",
    "gn:feature_code":"PPL",
    "gn:name":"Skye Glen",
    "gn:population":0,
    "gn:timezone":"America/Halifax",
    "iso:country":"CA",
    "wof:name":"Skye Glen",
    "wof:placetype":"locality"
},
  "geometry": {"coordinates":[-61.20208,46.0389],"type":"Point"}
}