{
  "type": "Feature",
  "properties": {
    "gn:admin1_code":"2.0",
    "gn:asciiname":"Cassin",
    "gn:country_code":"CA",
    "gn:dem":29,
    "gn:feature_class":"P",
    "gn:feature_code":"PPL",
    "gn:name":"Cassin",
    "gn:population":0,
    "gn:timezone":"America/Vancouver",
    "iso:country":"CA",
    "name:deu_x_preferred":[
        "Cassin"
    ],
    "name:epo_x_preferred":[
        "Cassin"
    ],
    "name:fra_x_preferred":[
        "Cassin"
    ],
    "name:ita_x_preferred":[
        "Cassin"
    ],
    "name:nld_x_preferred":[
        "Cassin"
    ],
    "name:rus_x_preferred":[
        "\u041a\u0430\u0441\u0441\u0435\u043d"
    ],
    "name:ukr_x_preferred":[
        "\u041a\u0430\u0441\u0441\u0435\u043d"
    ],
    "wof:name":"Cassin",
    "wof:placetype":"locality"
},
  "geometry": {"coordinates":[-122.81667,49.27639],"type":"Point"}
}