{
  "type": "Feature",
  "properties": {
    "gn:admin1_code":"8.0",
    "gn:asciiname":"Wexford Heights",
    "gn:country_code":"CA",
    "gn:dem":167,
    "gn:feature_class":"P",
    "gn:feature_code":"PPL",
    "gn:name":"Wexford Heights",
    "gn:population":0,
    "gn:timezone":"America/Toronto",
    "iso:country":"CA",
    "wof:name":"Wexford Heights",
    "wof:placetype":"locality"
},
  "geometry": {"coordinates":[-79.27776999999998,43.74567],"type":"Point"}
}