{
  "type": "Feature",
  "properties": {
    "gn:admin1_code":"8.0",
    "gn:asciiname":"West Humber Estates",
    "gn:country_code":"CA",
    "gn:dem":150,
    "gn:feature_class":"P",
    "gn:feature_code":"PPL",
    "gn:name":"West Humber Estates",
    "gn:population":0,
    "gn:timezone":"America/Toronto",
    "iso:country":"CA",
    "wof:name":"West Humber Estates",
    "wof:placetype":"locality"
},
  "geometry": {"coordinates":[-79.58745,43.72794],"type":"Point"}
}