{
  "type": "Feature",
  "properties": {
    "gn:admin1_code":"7.0",
    "gn:asciiname":"West Roachvale",
    "gn:country_code":"CA",
    "gn:dem":45,
    "gn:feature_class":"P",
    "gn:feature_code":"PPL",
    "gn:name":"West Roachvale",
    "gn:population":0,
    "gn:timezone":"America/Halifax",
    "iso:country":"CA",
    "wof:name":"West Roachvale",
    "wof:placetype":"locality"
},
  "geometry": {"coordinates":[-61.60637,45.34792],"type":"Point"}
}