{
  "type": "Feature",
  "properties": {
    "gn:admin1_code":"10.0",
    "gn:admin2_code":"16.0",
    "gn:admin3_code":"67035.0",
    "gn:asciiname":"Domaine-des-Copains",
    "gn:country_code":"CA",
    "gn:dem":25,
    "gn:feature_class":"P",
    "gn:feature_code":"PPL",
    "gn:name":"Domaine-des-Copains",
    "gn:population":0,
    "gn:timezone":"America/Toronto",
    "iso:country":"CA",
    "wof:name":"Domaine-des-Copains",
    "wof:placetype":"locality"
},
  "geometry": {"coordinates":[-73.5667,45.3833],"type":"Point"}
}