{
  "type": "Feature",
  "properties": {
    "gn:admin1_code":"10",
    "gn:admin2_code":"9.0",
    "gn:admin3_code":"98012.0",
    "gn:asciiname":"L'Anse-du-Portage",
    "gn:country_code":"CA",
    "gn:dem":3,
    "gn:feature_class":"P",
    "gn:feature_code":"PPL",
    "gn:name":"L'Anse-du-Portage",
    "gn:population":0,
    "gn:timezone":"America/Blanc-Sablon",
    "iso:country":"CA",
    "wof:name":"L'Anse-du-Portage",
    "wof:placetype":"locality"
},
  "geometry": {"coordinates":[-58.29187,51.23367],"type":"Point"}
}