{
  "type": "Feature",
  "properties": {
    "iso:country":"CA",
    "qs_pg:aaroncc":"CA",
    "qs_pg:name":"St. Isidore-de-Bellevue",
    "qs_pg:name_adm0":"Canada",
    "qs_pg:name_adm1":"Saskatchewan",
    "qs_pg:photos":114,
    "qs_pg:photos_1k":23,
    "qs_pg:photos_9k":1,
    "qs_pg:photos_9r":3,
    "qs_pg:photos_all":114,
    "qs_pg:photos_sr":3,
    "qs_pg:pop_sr":0,
    "qs_pg:qs_pg_placetype":"locality",
    "qs_pg:qs_pg_placetype_gp":"Town",
    "qs_pg:woe_adm0":23424775,
    "woe:adm0_id":23424775,
    "woe:name_adm0":"Canada",
    "woe:name_adm1":"Saskatchewan",
    "woe:placetype":"Town",
    "wof:name":"St. Isidore-de-Bellevue",
    "wof:placetype":"locality"
},
  "geometry": {"coordinates":[-105.920391,52.785582],"type":"Point"}
}