{
  "type": "Feature",
  "properties": {
    "gn:admin1_code":"7.0",
    "gn:asciiname":"Bay View",
    "gn:country_code":"CA",
    "gn:dem":45,
    "gn:feature_class":"P",
    "gn:feature_code":"PPL",
    "gn:name":"Bay View",
    "gn:population":0,
    "gn:timezone":"America/Halifax",
    "iso:country":"CA",
    "wof:name":"Bay View",
    "wof:placetype":"locality"
},
  "geometry": {"coordinates":[-62.68057,45.70233],"type":"Point"}
}