{
  "type": "Feature",
  "properties": {
    "gn:admin1_code":"7",
    "gn:asciiname":"Millers Corner",
    "gn:country_code":"CA",
    "gn:dem":50,
    "gn:feature_class":"P",
    "gn:feature_code":"PPLL",
    "gn:name":"Millers Corner",
    "gn:population":0,
    "gn:timezone":"America/Halifax",
    "iso:country":"CA",
    "wof:name":"Millers Corner",
    "wof:placetype":"locality"
},
  "geometry": {"coordinates":[-63.68201,45.18345],"type":"Point"}
}