{
  "type": "Feature",
  "properties": {
    "gn:admin1_code":"8",
    "gn:asciiname":"Tapleytown",
    "gn:country_code":"CA",
    "gn:dem":203,
    "gn:feature_class":"P",
    "gn:feature_code":"PPL",
    "gn:name":"Tapleytown",
    "gn:population":0,
    "gn:timezone":"America/Toronto",
    "iso:country":"CA",
    "wof:name":"Tapleytown",
    "wof:placetype":"locality"
},
  "geometry": {"coordinates":[-79.73033000000002,43.18014],"type":"Point"}
}