{
  "type": "Feature",
  "properties": {
    "gn:admin1_code":"4.0",
    "gn:asciiname":"Cherry Hill",
    "gn:country_code":"CA",
    "gn:dem":123,
    "gn:feature_class":"P",
    "gn:feature_code":"PPL",
    "gn:name":"Cherry Hill",
    "gn:population":0,
    "gn:timezone":"America/Moncton",
    "iso:country":"CA",
    "wof:name":"Cherry Hill",
    "wof:placetype":"locality"
},
  "geometry": {"coordinates":[-66.03381999999999,45.79373],"type":"Point"}
}