{
  "type": "Feature",
  "properties": {
    "gn:admin1_code":"8.0",
    "gn:asciiname":"Bolingbroke",
    "gn:country_code":"CA",
    "gn:dem":162,
    "gn:feature_class":"P",
    "gn:feature_code":"PPL",
    "gn:name":"Bolingbroke",
    "gn:population":0,
    "gn:timezone":"America/Toronto",
    "iso:country":"CA",
    "name:ceb_x_preferred":[
        "Bolingbroke"
    ],
    "name:deu_x_preferred":[
        "Bolingbroke"
    ],
    "name:fra_x_preferred":[
        "Bolingbroke"
    ],
    "name:ind_x_preferred":[
        "Bolingbroke"
    ],
    "name:nds_x_preferred":[
        "Bolingbroke"
    ],
    "name:rus_x_preferred":[
        "\u0411\u043e\u043b\u0438\u043d\u0433\u0431\u0440\u043e\u043a"
    ],
    "name:swe_x_preferred":[
        "Bolingbroke"
    ],
    "wof:name":"Bolingbroke",
    "wof:placetype":"locality"
},
  "geometry": {"coordinates":[-76.51925,44.75959],"type":"Point"}
}