{
  "type": "Feature",
  "properties": {
    "gn:admin1_code":"8.0",
    "gn:asciiname":"Bolingbroke",
    "gn:country_code":"CA",
    "gn:dem":162,
    "gn:feature_class":"P",
    "gn:feature_code":"PPL",
    "gn:name":"Bolingbroke",
    "gn:population":0,
    "gn:timezone":"America/Toronto",
    "iso:country":"CA",
    "wof:name":"Bolingbroke",
    "wof:placetype":"locality"
},
  "geometry": {"coordinates":[-76.51925,44.75959],"type":"Point"}
}