{
  "type": "Feature",
  "properties": {
    "gn:admin1_code":"7",
    "gn:asciiname":"Victoria Vale",
    "gn:country_code":"CA",
    "gn:dem":129,
    "gn:feature_class":"P",
    "gn:feature_code":"PPL",
    "gn:name":"Victoria Vale",
    "gn:population":0,
    "gn:timezone":"America/Halifax",
    "iso:country":"CA",
    "name:gla_x_preferred":[
        "Victoria Vale"
    ],
    "wof:name":"Victoria Vale",
    "wof:placetype":"locality"
},
  "geometry": {"coordinates":[-65.07330999999999,44.99521],"type":"Point"}
}