{
  "type": "Feature",
  "properties": {
    "gn:admin1_code":"1.0",
    "gn:asciiname":"Barlee Junction",
    "gn:country_code":"CA",
    "gn:dem":736,
    "gn:feature_class":"P",
    "gn:feature_code":"PPLL",
    "gn:name":"Barlee Junction",
    "gn:population":0,
    "gn:timezone":"America/Edmonton",
    "iso:country":"CA",
    "wof:name":"Barlee Junction",
    "wof:placetype":"locality"
},
  "geometry": {"coordinates":[-112.81865000000001,53.05014],"type":"Point"}
}