{
  "type": "Feature",
  "properties": {
    "gn:admin1_code":"8",
    "gn:asciiname":"Grantley",
    "gn:country_code":"CA",
    "gn:dem":87,
    "gn:feature_class":"P",
    "gn:feature_code":"PPL",
    "gn:name":"Grantley",
    "gn:population":0,
    "gn:timezone":"America/Toronto",
    "iso:country":"CA",
    "wof:name":"Grantley",
    "wof:placetype":"locality"
},
  "geometry": {"coordinates":[-75.15111,45.07806],"type":"Point"}
}