{
  "type": "Feature",
  "properties": {
    "gn:gn_country":"CA",
    "gn:gn_fcode":"PPL",
    "gn:gn_pop":0,
    "gn:population":3193,
    "iso:country":"CA",
    "name:deu_x_preferred":[
        "Saint-Thomas"
    ],
    "name:eng_x_preferred":[
        "Saint-Thomas"
    ],
    "name:eus_x_preferred":[
        "Saint-Thomas"
    ],
    "name:fas_x_preferred":[
        "\u0633\u0646-\u062a\u0648\u0645\u0627\u060c \u06a9\u0628\u06a9"
    ],
    "name:fas_x_variant":[
        "\u0633\u0646-\u062a\u0648\u0645\u0627"
    ],
    "name:fra_x_preferred":[
        "Saint-Thomas"
    ],
    "name:ita_x_preferred":[
        "Saint-Thomas"
    ],
    "name:nld_x_preferred":[
        "Saint-Thomas"
    ],
    "name:por_x_preferred":[
        "Saint-Thomas"
    ],
    "name:spa_x_preferred":[
        "Saint-Thomas"
    ],
    "name:urd_x_preferred":[
        "\u0633\u06cc\u0646\u0679 \u062a\u06be\u0627\u0645\u0633\u060c \u06a9\u06cc\u0648\u0628\u06cc\u06a9"
    ],
    "name:urd_x_variant":[
        "\u0633\u06cc\u0646\u0679 \u062a\u06be\u0627\u0645\u0633"
    ],
    "qs_pg:aaroncc":"CA",
    "qs_pg:gn_country":"CA",
    "qs_pg:gn_fcode":"PPL",
    "qs_pg:gn_pop":0,
    "qs_pg:name":"St.-Thomas",
    "qs_pg:name_adm0":"Canada",
    "qs_pg:name_adm1":"Qu\u00e9bec",
    "qs_pg:photos":114,
    "qs_pg:photos_1k":23,
    "qs_pg:photos_9k":1,
    "qs_pg:photos_9r":3,
    "qs_pg:photos_all":114,
    "qs_pg:photos_sr":3,
    "qs_pg:pop_sr":0,
    "qs_pg:qs_pg_placetype":"locality",
    "qs_pg:qs_pg_placetype_gp":"Town",
    "qs_pg:woe_adm0":23424775,
    "woe:adm0_id":23424775,
    "woe:name_adm0":"Canada",
    "woe:name_adm1":"Qu\u00e9bec",
    "woe:placetype":"Town",
    "wof:name":"St.-Thomas",
    "wof:placetype":"locality",
    "wof:population":3193
},
  "geometry": {"coordinates":[-73.34914999999999,46.01677],"type":"Point"}
}