{
  "type": "Feature",
  "properties": {
    "gn:admin1_code":"8",
    "gn:asciiname":"Victoria Corners",
    "gn:country_code":"CA",
    "gn:dem":280,
    "gn:feature_class":"P",
    "gn:feature_code":"PPL",
    "gn:name":"Victoria Corners",
    "gn:population":0,
    "gn:timezone":"America/Toronto",
    "iso:country":"CA",
    "wof:name":"Victoria Corners",
    "wof:placetype":"locality"
},
  "geometry": {"coordinates":[-80.42678000000002,44.50195],"type":"Point"}
}