{
  "type": "Feature",
  "properties": {
    "gn:admin1_code":"7",
    "gn:asciiname":"South Ingonish Harbour",
    "gn:country_code":"CA",
    "gn:dem":2,
    "gn:feature_class":"P",
    "gn:feature_code":"PPL",
    "gn:name":"South Ingonish Harbour",
    "gn:population":0,
    "gn:timezone":"America/Halifax",
    "iso:country":"CA",
    "wof:name":"South Ingonish Harbour",
    "wof:placetype":"locality"
},
  "geometry": {"coordinates":[-60.43762,46.62965],"type":"Point"}
}