{
  "type": "Feature",
  "properties": {
    "gn:admin1_code":"2",
    "gn:asciiname":"Leo Creek",
    "gn:country_code":"CA",
    "gn:dem":688,
    "gn:feature_class":"P",
    "gn:feature_code":"PPL",
    "gn:name":"Leo Creek",
    "gn:population":0,
    "gn:timezone":"America/Vancouver",
    "iso:country":"CA",
    "wof:name":"Leo Creek",
    "wof:placetype":"locality"
},
  "geometry": {"coordinates":[-125.56667,55.08333],"type":"Point"}
}