{
  "type": "Feature",
  "properties": {
    "gn:admin1_code":"1.0",
    "gn:asciiname":"Eagle Hill",
    "gn:country_code":"CA",
    "gn:dem":1024,
    "gn:feature_class":"P",
    "gn:feature_code":"PPL",
    "gn:name":"Eagle Hill",
    "gn:population":0,
    "gn:timezone":"America/Edmonton",
    "iso:country":"CA",
    "wof:name":"Eagle Hill",
    "wof:placetype":"locality"
},
  "geometry": {"coordinates":[-114.38,51.82694],"type":"Point"}
}