{
  "type": "Feature",
  "properties": {
    "gn:admin1_code":"2",
    "gn:asciiname":"Garnet Valley",
    "gn:country_code":"CA",
    "gn:dem":623,
    "gn:feature_class":"P",
    "gn:feature_code":"PPL",
    "gn:name":"Garnet Valley",
    "gn:population":0,
    "gn:timezone":"America/Vancouver",
    "iso:country":"CA",
    "wof:name":"Garnet Valley",
    "wof:placetype":"locality"
},
  "geometry": {"coordinates":[-119.70833,49.64167],"type":"Point"}
}