{
  "type": "Feature",
  "properties": {
    "gn:admin1_code":"8",
    "gn:asciiname":"Melrose Gardens",
    "gn:country_code":"CA",
    "gn:dem":274,
    "gn:feature_class":"P",
    "gn:feature_code":"PPL",
    "gn:name":"Melrose Gardens",
    "gn:population":0,
    "gn:timezone":"America/Toronto",
    "iso:country":"CA",
    "wof:name":"Melrose Gardens",
    "wof:placetype":"locality"
},
  "geometry": {"coordinates":[-81.34983000000003,48.49035],"type":"Point"}
}