{
  "type": "Feature",
  "properties": {
    "gn:admin1_code":"8",
    "gn:asciiname":"Magpie Mine",
    "gn:country_code":"CA",
    "gn:dem":396,
    "gn:feature_class":"P",
    "gn:feature_code":"PPL",
    "gn:name":"Magpie Mine",
    "gn:population":0,
    "gn:timezone":"America/Toronto",
    "iso:country":"CA",
    "wof:name":"Magpie Mine",
    "wof:placetype":"locality"
},
  "geometry": {"coordinates":[-84.71556,48.21333],"type":"Point"}
}