{
  "type": "Feature",
  "properties": {
    "gn:admin1_code":"8",
    "gn:asciiname":"Elmwood",
    "gn:country_code":"CA",
    "gn:dem":88,
    "gn:feature_class":"P",
    "gn:feature_code":"PPL",
    "gn:name":"Elmwood",
    "gn:population":0,
    "gn:timezone":"America/Toronto",
    "iso:country":"CA",
    "name:cat_x_preferred":[
        "Elmwood"
    ],
    "name:ceb_x_preferred":[
        "Elmwood"
    ],
    "name:deu_x_preferred":[
        "Elmwood"
    ],
    "name:ita_x_preferred":[
        "Elmwood"
    ],
    "name:nld_x_preferred":[
        "Elmwood"
    ],
    "name:pol_x_preferred":[
        "Elmwood"
    ],
    "name:por_x_preferred":[
        "Elmwood"
    ],
    "name:srp_x_preferred":[
        "\u0415\u043b\u043c\u0432\u0443\u0434"
    ],
    "name:ukr_x_preferred":[
        "\u0415\u043b\u043c\u0432\u0443\u0434"
    ],
    "name:vol_x_preferred":[
        "Elmwood"
    ],
    "wof:name":"Elmwood",
    "wof:placetype":"locality"
},
  "geometry": {"coordinates":[-76.62833000000001,44.22917],"type":"Point"}
}