{
  "type": "Feature",
  "properties": {
    "gn:admin1_code":"8",
    "gn:asciiname":"Elmwood",
    "gn:country_code":"CA",
    "gn:dem":88,
    "gn:feature_class":"P",
    "gn:feature_code":"PPL",
    "gn:name":"Elmwood",
    "gn:population":0,
    "gn:timezone":"America/Toronto",
    "iso:country":"CA",
    "wof:name":"Elmwood",
    "wof:placetype":"locality"
},
  "geometry": {"coordinates":[-76.62833000000001,44.22917],"type":"Point"}
}