{
  "type": "Feature",
  "properties": {
    "gn:admin1_code":"8.0",
    "gn:asciiname":"Willow Beach",
    "gn:country_code":"CA",
    "gn:dem":177,
    "gn:feature_class":"P",
    "gn:feature_code":"PPL",
    "gn:name":"Willow Beach",
    "gn:population":0,
    "gn:timezone":"America/Toronto",
    "iso:country":"CA",
    "wof:name":"Willow Beach",
    "wof:placetype":"locality"
},
  "geometry": {"coordinates":[-83.09278,42.0425],"type":"Point"}
}