{
  "type": "Feature",
  "properties": {
    "gn:admin1_code":"8",
    "gn:asciiname":"Mulloys",
    "gn:country_code":"CA",
    "gn:dem":83,
    "gn:feature_class":"P",
    "gn:feature_code":"PPL",
    "gn:name":"Mulloys",
    "gn:population":0,
    "gn:timezone":"America/Toronto",
    "iso:country":"CA",
    "wof:name":"Mulloys",
    "wof:placetype":"locality"
},
  "geometry": {"coordinates":[-75.40333000000003,45.07583],"type":"Point"}
}