{
  "type": "Feature",
  "properties": {
    "gn:admin1_code":"2",
    "gn:asciiname":"Vermilion Crossing",
    "gn:country_code":"CA",
    "gn:dem":1319,
    "gn:feature_class":"P",
    "gn:feature_code":"PPLL",
    "gn:name":"Vermilion Crossing",
    "gn:population":0,
    "gn:timezone":"America/Edmonton",
    "iso:country":"CA",
    "wof:name":"Vermilion Crossing",
    "wof:placetype":"locality"
},
  "geometry": {"coordinates":[-115.98542999999999,51.0333],"type":"Point"}
}