{
  "type": "Feature",
  "properties": {
    "gn:admin1_code":"8",
    "gn:asciiname":"Pomona",
    "gn:country_code":"CA",
    "gn:dem":467,
    "gn:feature_class":"P",
    "gn:feature_code":"PPL",
    "gn:name":"Pomona",
    "gn:population":0,
    "gn:timezone":"America/Toronto",
    "iso:country":"CA",
    "wof:name":"Pomona",
    "wof:placetype":"locality"
},
  "geometry": {"coordinates":[-80.65045000000001,44.23921],"type":"Point"}
}