{
  "type": "Feature",
  "properties": {
    "gn:admin1_code":"8",
    "gn:asciiname":"Pomona",
    "gn:country_code":"CA",
    "gn:dem":467,
    "gn:feature_class":"P",
    "gn:feature_code":"PPL",
    "gn:name":"Pomona",
    "gn:population":0,
    "gn:timezone":"America/Toronto",
    "iso:country":"CA",
    "name:als_x_preferred":[
        "Pomona"
    ],
    "name:bar_x_preferred":[
        "Pomona"
    ],
    "name:bos_x_preferred":[
        "Pomona"
    ],
    "name:cat_x_preferred":[
        "Pomona"
    ],
    "name:ceb_x_preferred":[
        "Pomona"
    ],
    "name:deu_x_preferred":[
        "Pomona"
    ],
    "name:fas_x_preferred":[
        "\u067e\u0648\u0645\u0648\u0646\u0627"
    ],
    "name:fin_x_preferred":[
        "Pomona"
    ],
    "name:fra_x_preferred":[
        "Pomone"
    ],
    "name:glg_x_preferred":[
        "Pomona"
    ],
    "name:ita_x_preferred":[
        "Pomona"
    ],
    "name:jpn_x_preferred":[
        "\u30dd\u30e2\u30ca"
    ],
    "name:kor_x_preferred":[
        "\ud3ec\ubaa8\ub098"
    ],
    "name:lat_x_preferred":[
        "Pomona"
    ],
    "name:nds_x_preferred":[
        "Pomona"
    ],
    "name:nld_x_preferred":[
        "Pomona"
    ],
    "name:nor_x_preferred":[
        "Pomona"
    ],
    "name:pol_x_preferred":[
        "Pomona"
    ],
    "name:por_x_preferred":[
        "Pomona"
    ],
    "name:rus_x_preferred":[
        "\u041f\u043e\u043c\u043e\u043d\u0430"
    ],
    "name:spa_x_preferred":[
        "Pomona"
    ],
    "name:srp_x_preferred":[
        "\u041f\u043e\u043c\u043e\u043d\u0430"
    ],
    "name:swe_x_preferred":[
        "Pomona"
    ],
    "name:tur_x_preferred":[
        "Pomona"
    ],
    "name:vep_x_preferred":[
        "Pomon"
    ],
    "name:vol_x_preferred":[
        "Pomona"
    ],
    "wof:name":"Pomona",
    "wof:placetype":"locality"
},
  "geometry": {"coordinates":[-80.65045000000001,44.23921],"type":"Point"}
}