{
  "type": "Feature",
  "properties": {
    "gn:admin1_code":"4.0",
    "gn:asciiname":"Coal Branch",
    "gn:country_code":"CA",
    "gn:dem":63,
    "gn:feature_class":"P",
    "gn:feature_code":"PPL",
    "gn:name":"Coal Branch",
    "gn:population":0,
    "gn:timezone":"America/Moncton",
    "iso:country":"CA",
    "wof:name":"Coal Branch",
    "wof:placetype":"locality"
},
  "geometry": {"coordinates":[-65.14953,46.35561],"type":"Point"}
}