{
  "type": "Feature",
  "properties": {
    "gn:admin1_code":"4",
    "gn:asciiname":"Mouth of Keswick",
    "gn:country_code":"CA",
    "gn:dem":4,
    "gn:feature_class":"P",
    "gn:feature_code":"PPL",
    "gn:name":"Mouth of Keswick",
    "gn:population":0,
    "gn:timezone":"America/Moncton",
    "iso:country":"CA",
    "wof:name":"Mouth of Keswick",
    "wof:placetype":"locality"
},
  "geometry": {"coordinates":[-66.83218000000001,46.00011],"type":"Point"}
}