{
  "type": "Feature",
  "properties": {
    "gn:admin1_code":"1",
    "gn:asciiname":"Raley",
    "gn:country_code":"CA",
    "gn:dem":1120,
    "gn:feature_class":"P",
    "gn:feature_code":"PPLL",
    "gn:name":"Raley",
    "gn:population":0,
    "gn:timezone":"America/Edmonton",
    "iso:country":"CA",
    "wof:name":"Raley",
    "wof:placetype":"locality"
},
  "geometry": {"coordinates":[-113.18519000000001,49.28328],"type":"Point"}
}