{
  "type": "Feature",
  "properties": {
    "gn:admin1_code":"7",
    "gn:asciiname":"North Earltown",
    "gn:country_code":"CA",
    "gn:dem":149,
    "gn:feature_class":"P",
    "gn:feature_code":"PPL",
    "gn:name":"North Earltown",
    "gn:population":0,
    "gn:timezone":"America/Halifax",
    "iso:country":"CA",
    "wof:name":"North Earltown",
    "wof:placetype":"locality"
},
  "geometry": {"coordinates":[-63.13748,45.6189],"type":"Point"}
}