{
  "type": "Feature",
  "properties": {
    "gn:admin1_code":"1.0",
    "gn:asciiname":"Wild Horse",
    "gn:country_code":"CA",
    "gn:dem":854,
    "gn:feature_class":"P",
    "gn:feature_code":"PPLL",
    "gn:name":"Wild Horse",
    "gn:population":0,
    "gn:timezone":"America/Edmonton",
    "iso:country":"CA",
    "wof:name":"Wild Horse",
    "wof:placetype":"locality"
},
  "geometry": {"coordinates":[-110.21823999999999,49.00001],"type":"Point"}
}