{
  "type": "Feature",
  "properties": {
    "gn:admin1_code":"11",
    "gn:asciiname":"Serath",
    "gn:country_code":"CA",
    "gn:dem":593,
    "gn:feature_class":"P",
    "gn:feature_code":"PPL",
    "gn:name":"Serath",
    "gn:population":0,
    "gn:timezone":"America/Regina",
    "iso:country":"CA",
    "wof:name":"Serath",
    "wof:placetype":"locality"
},
  "geometry": {"coordinates":[-104.51721999999999,51.18337],"type":"Point"}
}