{
  "type": "Feature",
  "properties": {
    "gn:admin1_code":"10",
    "gn:admin2_code":"15",
    "gn:admin3_code":"74005.0",
    "gn:asciiname":"Sainte-Monique",
    "gn:country_code":"CA",
    "gn:dem":73,
    "gn:feature_class":"P",
    "gn:feature_code":"PPL",
    "gn:name":"Sainte-Monique",
    "gn:population":0,
    "gn:timezone":"America/Toronto",
    "iso:country":"CA",
    "wof:name":"Sainte-Monique",
    "wof:placetype":"locality"
},
  "geometry": {"coordinates":[-74.00126999999998,45.66365],"type":"Point"}
}