{
  "type": "Feature",
  "properties": {
    "gn:country":"CA",
    "gn:fcode":"PPL",
    "gn:population":0,
    "iso:country":"CA",
    "name:ceb_x_preferred":[
        "Saint-Henri-de-Taillon"
    ],
    "name:deu_x_preferred":[
        "Saint-Henri-de-Taillon"
    ],
    "name:ell_x_preferred":[
        "\u03a3\u03b1\u03b9\u03bd\u03c4-\u0391\u03bd\u03c1\u03af-\u03bd\u03c4\u03b5-\u03a4\u03b1\u03b3\u03b9\u03cc\u03bd"
    ],
    "name:eng_x_preferred":[
        "Saint-Henri-de-Taillon"
    ],
    "name:eus_x_preferred":[
        "Saint-Henri-de-Taillon"
    ],
    "name:fas_x_preferred":[
        "\u0633\u0646-\u0622\u0646\u0631\u06cc-\u062f\u0648-\u062a\u0627\u06cc\u06cc\u0648\u0646\u060c \u06a9\u0628\u06a9"
    ],
    "name:fas_x_variant":[
        "\u0633\u0646-\u0622\u0646\u0631\u06cc-\u062f\u0648-\u062a\u0627\u06cc\u06cc\u0648\u0646"
    ],
    "name:fra_x_preferred":[
        "Saint-Henri-de-Taillon"
    ],
    "name:ita_x_preferred":[
        "Saint-Henri-de-Taillon"
    ],
    "name:nld_x_preferred":[
        "Saint-Henri-de-Taillon"
    ],
    "name:por_x_preferred":[
        "Saint-Henri-de-Taillon"
    ],
    "name:spa_x_preferred":[
        "Saint-Henri-de-Taillon"
    ],
    "name:swe_x_preferred":[
        "Saint-Henri-de-Taillon"
    ],
    "name:urd_x_preferred":[
        "\u0633\u06cc\u0646\u0679-\u06c1\u0646\u0631\u06cc-\u062f\u06d2-\u062a\u0644\u0648\u06ba \u060c \u06a9\u06cc\u0648\u0628\u06a9"
    ],
    "name:urd_x_variant":[
        "\u0633\u06cc\u0646\u0679-\u06c1\u0646\u0631\u06cc-\u062f\u06d2-\u062a\u0644\u0648\u06ba",
        "\u0633\u06cc\u0646\u0679-\u06c1\u0646\u0631\u06cc-\u062f\u06d2-\u062a\u0644\u0648\u06ba "
    ],
    "qs_pg:aaroncc":"CA",
    "qs_pg:gn_country":"CA",
    "qs_pg:gn_fcode":"PPL",
    "qs_pg:gn_pop":0,
    "qs_pg:name":"St.-Henri-de-Taillon",
    "qs_pg:name_adm0":"Canada",
    "qs_pg:name_adm1":"Qu\u00e9bec",
    "qs_pg:photos":175,
    "qs_pg:photos_1k":35,
    "qs_pg:photos_9k":1,
    "qs_pg:photos_9r":4,
    "qs_pg:photos_all":175,
    "qs_pg:photos_sr":4,
    "qs_pg:pop_sr":0,
    "qs_pg:qs_pg_placetype":"locality",
    "qs_pg:qs_pg_placetype_gp":"Town",
    "qs_pg:woe_adm0":23424775,
    "woe:adm0_id":23424775,
    "woe:name_adm0":"Canada",
    "woe:name_adm1":"Qu\u00e9bec",
    "woe:placetype":"Town",
    "wof:name":"St.-Henri-de-Taillon",
    "wof:placetype":"locality"
},
  "geometry": {"coordinates":[-71.83241,48.6668],"type":"Point"}
}