{
  "type": "Feature",
  "properties": {
    "gn:admin1_code":"4",
    "gn:asciiname":"Lower Tower Hill",
    "gn:country_code":"CA",
    "gn:dem":146,
    "gn:feature_class":"P",
    "gn:feature_code":"PPL",
    "gn:name":"Lower Tower Hill",
    "gn:population":0,
    "gn:timezone":"America/Moncton",
    "iso:country":"CA",
    "wof:name":"Lower Tower Hill",
    "wof:placetype":"locality"
},
  "geometry": {"coordinates":[-67.18725000000001,45.30039],"type":"Point"}
}