{
  "type": "Feature",
  "properties": {
    "gn:admin1_code":"2",
    "gn:asciiname":"Rumble Beach",
    "gn:country_code":"CA",
    "gn:dem":39,
    "gn:feature_class":"P",
    "gn:feature_code":"PPL",
    "gn:name":"Rumble Beach",
    "gn:population":0,
    "gn:timezone":"America/Vancouver",
    "iso:country":"CA",
    "wof:name":"Rumble Beach",
    "wof:placetype":"locality"
},
  "geometry": {"coordinates":[-127.48472,50.42778],"type":"Point"}
}