{
  "type": "Feature",
  "properties": {
    "gn:country":"CA",
    "gn:fcode":"ADMD",
    "gn:population":0,
    "iso:country":"CA",
    "name:eng_x_preferred":[
        "Cornwallis"
    ],
    "qs:name":"Cornwallis",
    "qs:photos_9r":0,
    "qs:photos_sr":0,
    "qs:pop_sr":"0",
    "wof:name":"Cornwallis",
    "wof:placetype":"localadmin",
    "wof:population":0
},
  "geometry": {"coordinates":[-99.84805,49.79722],"type":"Point"}
}