{
  "type": "Feature",
  "properties": {
    "gn:admin1_code":"3.0",
    "gn:asciiname":"Clematis",
    "gn:country_code":"CA",
    "gn:dem":274,
    "gn:feature_class":"P",
    "gn:feature_code":"PPLL",
    "gn:name":"Clematis",
    "gn:population":0,
    "gn:timezone":"America/Winnipeg",
    "iso:country":"CA",
    "wof:name":"Clematis",
    "wof:placetype":"locality"
},
  "geometry": {"coordinates":[-97.58508999999999,50.61062],"type":"Point"}
}