{
  "type": "Feature",
  "properties": {
    "gn:admin1_code":"5",
    "gn:asciiname":"Round Cove",
    "gn:country_code":"CA",
    "gn:dem":82,
    "gn:feature_class":"P",
    "gn:feature_code":"PPLL",
    "gn:name":"Round Cove",
    "gn:population":0,
    "gn:timezone":"America/St_Johns",
    "iso:country":"CA",
    "wof:name":"Round Cove",
    "wof:placetype":"locality"
},
  "geometry": {"coordinates":[-55.71502,47.64994],"type":"Point"}
}