{
  "type": "Feature",
  "properties": {
    "iso:country":"CA",
    "name:eng_x_preferred":[
        "La Berge"
    ],
    "name:fra_x_preferred":[
        "La Berge"
    ],
    "name:unk_x_variant":[
        "La Berge"
    ],
    "qs:gn_local":0,
    "qs:local_max":73,
    "qs:local_sum":179,
    "qs:localhoods":3,
    "qs:name":"La Berge",
    "qs:name_adm0":"Canada",
    "qs:name_adm1":"Qu\u00e9bec",
    "qs:name_adm2":"Roussillon",
    "qs:name_local":"Roussillon",
    "qs:photo_max":12,
    "qs:photo_sum":73,
    "qs:placetype":"Suburb",
    "qs:quad_count":17,
    "qs:woe_adm0":23424775,
    "qs:woe_adm1":2344924,
    "qs:woe_adm2":29375054,
    "qs:woe_lau":0,
    "qs:woe_local":29375054,
    "qs:woe_ver":"7.10.0",
    "wof:lang":[
        "fre"
    ],
    "wof:name":"La Berge",
    "wof:placetype":"neighbourhood"
},
  "geometry": {"coordinates":[-73.487061,45.436083],"type":"Point"}
}