{
  "type": "Feature",
  "properties": {
    "gn:admin1_code":"10",
    "gn:admin2_code":"09",
    "gn:admin3_code":"98010.0",
    "gn:asciiname":"Port-Saint-Servan",
    "gn:country_code":"CA",
    "gn:dem":14,
    "gn:feature_class":"P",
    "gn:feature_code":"PPL",
    "gn:name":"Port-Saint-Servan",
    "gn:population":0,
    "gn:timezone":"America/Blanc-Sablon",
    "iso:country":"CA",
    "wof:name":"Port-Saint-Servan",
    "wof:placetype":"locality"
},
  "geometry": {"coordinates":[-58.03008000000001,51.31681],"type":"Point"}
}