{
  "type": "Feature",
  "properties": {
    "gn:admin1_code":"10",
    "gn:admin2_code":"15.0",
    "gn:admin3_code":"77012.0",
    "gn:asciiname":"Le Coin-des-Anglais",
    "gn:country_code":"CA",
    "gn:dem":373,
    "gn:feature_class":"P",
    "gn:feature_code":"PPL",
    "gn:name":"Le Coin-des-Anglais",
    "gn:population":0,
    "gn:timezone":"America/Toronto",
    "iso:country":"CA",
    "wof:name":"Le Coin-des-Anglais",
    "wof:placetype":"locality"
},
  "geometry": {"coordinates":[-74.01682,46.08532],"type":"Point"}
}