{
  "type": "Feature",
  "properties": {
    "gn:admin1_code":"7",
    "gn:asciiname":"Fort Lawrence",
    "gn:country_code":"CA",
    "gn:dem":8,
    "gn:feature_class":"P",
    "gn:feature_code":"PPL",
    "gn:name":"Fort Lawrence",
    "gn:population":0,
    "gn:timezone":"America/Halifax",
    "iso:country":"CA",
    "wof:name":"Fort Lawrence",
    "wof:placetype":"locality"
},
  "geometry": {"coordinates":[-64.24874,45.85015],"type":"Point"}
}