{
  "type": "Feature",
  "properties": {
    "gn:admin1_code":"8",
    "gn:asciiname":"Links Mills",
    "gn:country_code":"CA",
    "gn:dem":98,
    "gn:feature_class":"P",
    "gn:feature_code":"PPL",
    "gn:name":"Links Mills",
    "gn:population":0,
    "gn:timezone":"America/Toronto",
    "iso:country":"CA",
    "wof:name":"Links Mills",
    "wof:placetype":"locality"
},
  "geometry": {"coordinates":[-76.76513,44.22322],"type":"Point"}
}