{
  "type": "Feature",
  "properties": {
    "gn:admin1_code":"9",
    "gn:asciiname":"Hamilton",
    "gn:country_code":"CA",
    "gn:dem":9,
    "gn:feature_class":"P",
    "gn:feature_code":"PPLL",
    "gn:name":"Hamilton",
    "gn:population":0,
    "gn:timezone":"America/Halifax",
    "iso:country":"CA",
    "wof:name":"Hamilton",
    "wof:placetype":"locality"
},
  "geometry": {"coordinates":[-63.69872,46.50013],"type":"Point"}
}