{
  "type": "Feature",
  "properties": {
    "gn:admin1_code":"5",
    "gn:asciiname":"Point Enragee",
    "gn:country_code":"CA",
    "gn:dem":36,
    "gn:feature_class":"P",
    "gn:feature_code":"PPLL",
    "gn:name":"Point Enrag\u00e9e",
    "gn:population":0,
    "gn:timezone":"America/St_Johns",
    "iso:country":"CA",
    "wof:name":"Point Enragee",
    "wof:placetype":"locality"
},
  "geometry": {"coordinates":[-55.28159,47.38323],"type":"Point"}
}