{
  "type": "Feature",
  "properties": {
    "gn:admin1_code":"1.0",
    "gn:asciiname":"Cooking Lake",
    "gn:country_code":"CA",
    "gn:dem":740,
    "gn:feature_class":"P",
    "gn:feature_code":"PPL",
    "gn:name":"Cooking Lake",
    "gn:population":0,
    "gn:timezone":"America/Edmonton",
    "iso:country":"CA",
    "wof:name":"Cooking Lake",
    "wof:placetype":"locality"
},
  "geometry": {"coordinates":[-113.12166999999999,53.41139],"type":"Point"}
}