{
  "type": "Feature",
  "properties": {
    "iso:country":"CA",
    "name:eng_x_preferred":[
        "Waverley"
    ],
    "qs:name":"Waverley",
    "qs:name_adm0":"Canada",
    "qs:name_adm1":"Nova Scotia",
    "qs:photos":120,
    "qs:photos_1k":24,
    "qs:photos_9k":1,
    "qs:photos_9r":3,
    "qs:photos_all":120,
    "qs:photos_sr":3,
    "qs:placetype":"Town",
    "qs:pop_sr":"0",
    "wd:wordcount":392,
    "wof:name":"Waverley",
    "wof:placetype":"locality"
},
  "geometry": {"coordinates":[-63.582397,44.772345],"type":"Point"}
}