{
  "type": "Feature",
  "properties": {
    "gn:admin1_code":"4.0",
    "gn:asciiname":"Baillie",
    "gn:country_code":"CA",
    "gn:dem":146,
    "gn:feature_class":"P",
    "gn:feature_code":"PPL",
    "gn:name":"Baillie",
    "gn:population":0,
    "gn:timezone":"America/Moncton",
    "iso:country":"CA",
    "wof:name":"Baillie",
    "wof:placetype":"locality"
},
  "geometry": {"coordinates":[-67.26293000000001,45.38732],"type":"Point"}
}