{
  "type": "Feature",
  "properties": {
    "gn:admin1_code":"8",
    "gn:asciiname":"Green Acres",
    "gn:country_code":"CA",
    "gn:dem":116,
    "gn:feature_class":"P",
    "gn:feature_code":"PPL",
    "gn:name":"Green Acres",
    "gn:population":0,
    "gn:timezone":"America/Toronto",
    "iso:country":"CA",
    "name:ara_x_preferred":[
        "\u063a\u0631\u064a\u0646 \u0623\u064a\u0643\u0631\u0632"
    ],
    "name:fra_x_preferred":[
        "Les Arpents verts"
    ],
    "name:glg_x_preferred":[
        "Granxeiro \u00faltimo modelo"
    ],
    "name:nld_x_preferred":[
        "Green Acres"
    ],
    "name:rus_x_preferred":[
        "\u0417\u0435\u043b\u0451\u043d\u044b\u0435 \u043f\u0440\u043e\u0441\u0442\u043e\u0440\u044b"
    ],
    "wof:name":"Green Acres",
    "wof:placetype":"locality"
},
  "geometry": {"coordinates":[-77.68722,44.27361],"type":"Point"}
}