{
  "type": "Feature",
  "properties": {
    "gn:admin1_code":"8",
    "gn:asciiname":"Green Acres",
    "gn:country_code":"CA",
    "gn:dem":116,
    "gn:feature_class":"P",
    "gn:feature_code":"PPL",
    "gn:name":"Green Acres",
    "gn:population":0,
    "gn:timezone":"America/Toronto",
    "iso:country":"CA",
    "wof:name":"Green Acres",
    "wof:placetype":"locality"
},
  "geometry": {"coordinates":[-77.68722,44.27361],"type":"Point"}
}