{
  "type": "Feature",
  "properties": {
    "gn:admin1_code":"8",
    "gn:asciiname":"Maplewood",
    "gn:country_code":"CA",
    "gn:dem":357,
    "gn:feature_class":"P",
    "gn:feature_code":"PPL",
    "gn:name":"Maplewood",
    "gn:population":0,
    "gn:timezone":"America/Toronto",
    "iso:country":"CA",
    "wof:name":"Maplewood",
    "wof:placetype":"locality"
},
  "geometry": {"coordinates":[-80.90222,43.26806],"type":"Point"}
}