{
  "type": "Feature",
  "properties": {
    "gn:admin1_code":"8",
    "gn:asciiname":"Maplewood",
    "gn:country_code":"CA",
    "gn:dem":357,
    "gn:feature_class":"P",
    "gn:feature_code":"PPL",
    "gn:name":"Maplewood",
    "gn:population":0,
    "gn:timezone":"America/Toronto",
    "iso:country":"CA",
    "name:ceb_x_preferred":[
        "Maplewood"
    ],
    "name:deu_x_preferred":[
        "Maplewood"
    ],
    "name:fra_x_preferred":[
        "Maplewood"
    ],
    "name:ita_x_preferred":[
        "Maplewood"
    ],
    "name:kor_x_preferred":[
        "\uba54\uc774\ud50c\uc6b0\ub4dc"
    ],
    "name:nld_x_preferred":[
        "Maplewood"
    ],
    "name:pol_x_preferred":[
        "Maplewood"
    ],
    "name:por_x_preferred":[
        "Maplewood"
    ],
    "name:srp_x_preferred":[
        "\u041c\u0435\u0458\u043f\u043b\u0432\u0443\u0434"
    ],
    "name:ukr_x_preferred":[
        "\u041c\u0435\u0439\u043f\u043b\u0432\u0443\u0434"
    ],
    "name:vol_x_preferred":[
        "Maplewood"
    ],
    "wof:name":"Maplewood",
    "wof:placetype":"locality"
},
  "geometry": {"coordinates":[-80.90222,43.26806],"type":"Point"}
}