{
  "type": "Feature",
  "properties": {
    "gn:admin1_code":"5",
    "gn:asciiname":"The Beaches",
    "gn:country_code":"CA",
    "gn:dem":-9999,
    "gn:feature_class":"P",
    "gn:feature_code":"PPL",
    "gn:name":"The Beaches",
    "gn:population":0,
    "gn:timezone":"America/St_Johns",
    "iso:country":"CA",
    "name:fra_x_preferred":[
        "The Beaches"
    ],
    "wof:name":"The Beaches",
    "wof:placetype":"locality"
},
  "geometry": {"coordinates":[-56.83156,49.5833],"type":"Point"}
}