{
  "type": "Feature",
  "properties": {
    "iso:country":"CA",
    "name:eng_x_preferred":[
        "Laidlaw"
    ],
    "name:nld_x_preferred":[
        "Laidlaw"
    ],
    "qs_pg:aaroncc":"CA",
    "qs_pg:name":"Laidlaw",
    "qs_pg:name_adm0":"Canada",
    "qs_pg:name_adm1":"British Columbia",
    "qs_pg:photos":27,
    "qs_pg:photos_1k":5,
    "qs_pg:photos_9k":1,
    "qs_pg:photos_9r":2,
    "qs_pg:photos_all":27,
    "qs_pg:photos_sr":2,
    "qs_pg:pop_sr":0,
    "qs_pg:qs_pg_placetype":"locality",
    "qs_pg:qs_pg_placetype_gp":"Town",
    "qs_pg:woe_adm0":23424775,
    "woe:adm0_id":23424775,
    "woe:name_adm0":"Canada",
    "woe:name_adm1":"British Columbia",
    "woe:placetype":"Town",
    "wof:name":"Laidlaw",
    "wof:placetype":"locality"
},
  "geometry": {"coordinates":[-121.621681,49.309931],"type":"Point"}
}