{
  "type": "Feature",
  "properties": {
    "iso:country":"CA",
    "name:eng_x_preferred":[
        "South Cameron"
    ],
    "qs:gn_adm0_cc":"CA",
    "qs:gn_local":6182962,
    "qs:gn_nam_loc":"windsor",
    "qs:gn_namadm1":"08",
    "qs:local_max":3456,
    "qs:local_sum":19250,
    "qs:localhoods":22,
    "qs:name":"South Cameron",
    "qs:name_adm0":"Canada",
    "qs:name_adm1":"Ontario",
    "qs:name_adm2":"Essex",
    "qs:name_local":"Windsor",
    "qs:photo_max":12,
    "qs:photo_sum":36,
    "qs:placetype":"Suburb",
    "qs:quad_count":8,
    "qs:woe_adm0":23424775,
    "qs:woe_adm1":2344922,
    "qs:woe_adm2":29375056,
    "qs:woe_lau":0,
    "qs:woe_local":4079,
    "qs:woe_ver":"7.10.0",
    "wof:lang":[
        "eng"
    ],
    "wof:name":"South Cameron",
    "wof:placetype":"neighbourhood"
},
  "geometry": {"coordinates":[-83.045391,42.284172],"type":"Point"}
}