{
  "type": "Feature",
  "properties": {
    "gn:admin1_code":"9",
    "gn:asciiname":"Orwell Cove",
    "gn:country_code":"CA",
    "gn:dem":33,
    "gn:feature_class":"P",
    "gn:feature_code":"PPLL",
    "gn:name":"Orwell Cove",
    "gn:population":0,
    "gn:timezone":"America/Halifax",
    "iso:country":"CA",
    "wof:name":"Orwell Cove",
    "wof:placetype":"locality"
},
  "geometry": {"coordinates":[-62.86537,46.13341],"type":"Point"}
}