{
  "type": "Feature",
  "properties": {
    "gn:admin1_code":"9.0",
    "gn:asciiname":"Wilmot Valley",
    "gn:country_code":"CA",
    "gn:dem":14,
    "gn:feature_class":"P",
    "gn:feature_code":"PPLL",
    "gn:name":"Wilmot Valley",
    "gn:population":0,
    "gn:timezone":"America/Halifax",
    "iso:country":"CA",
    "wof:name":"Wilmot Valley",
    "wof:placetype":"locality"
},
  "geometry": {"coordinates":[-63.69872,46.40013],"type":"Point"}
}