{
  "type": "Feature",
  "properties": {
    "gn:admin1_code":"4",
    "gn:asciiname":"Strathadam",
    "gn:country_code":"CA",
    "gn:dem":33,
    "gn:feature_class":"P",
    "gn:feature_code":"PPL",
    "gn:name":"Strathadam",
    "gn:population":0,
    "gn:timezone":"America/Moncton",
    "iso:country":"CA",
    "wof:name":"Strathadam",
    "wof:placetype":"locality"
},
  "geometry": {"coordinates":[-65.6678,46.96718],"type":"Point"}
}