{
  "type": "Feature",
  "properties": {
    "gn:admin1_code":"2.0",
    "gn:admin2_code":"5931.0",
    "gn:asciiname":"Dentville",
    "gn:country_code":"CA",
    "gn:dem":6,
    "gn:feature_class":"P",
    "gn:feature_code":"PPL",
    "gn:name":"Dentville",
    "gn:population":0,
    "gn:timezone":"America/Vancouver",
    "iso:country":"CA",
    "wof:name":"Dentville",
    "wof:placetype":"locality"
},
  "geometry": {"coordinates":[-123.15494,49.7121],"type":"Point"}
}