{
  "type": "Feature",
  "properties": {
    "gn:country":"CA",
    "iso:country":"CA",
    "name:deu_x_preferred":[
        "Kildonan"
    ],
    "qs_pg:aaroncc":"CA",
    "qs_pg:gn_country":"CA",
    "qs_pg:name":"Kildonan",
    "qs_pg:name_adm0":"Canada",
    "qs_pg:name_adm1":"British Columbia",
    "qs_pg:photos":42,
    "qs_pg:photos_1k":9,
    "qs_pg:photos_9k":1,
    "qs_pg:photos_9r":2,
    "qs_pg:photos_all":42,
    "qs_pg:photos_sr":2,
    "qs_pg:pop_sr":0,
    "qs_pg:qs_pg_placetype":"locality",
    "qs_pg:qs_pg_placetype_gp":"Town",
    "qs_pg:woe_adm0":23424775,
    "woe:adm0_id":23424775,
    "woe:name_adm0":"Canada",
    "woe:name_adm1":"British Columbia",
    "woe:placetype":"Town",
    "wof:name":"Kildonan",
    "wof:placetype":"locality"
},
  "geometry": {"coordinates":[-125.026302,48.971653],"type":"Point"}
}