{
  "type": "Feature",
  "properties": {
    "gn:admin1_code":"7",
    "gn:asciiname":"Pleasant Valley",
    "gn:country_code":"CA",
    "gn:dem":201,
    "gn:feature_class":"P",
    "gn:feature_code":"PPL",
    "gn:name":"Pleasant Valley",
    "gn:population":0,
    "gn:timezone":"America/Halifax",
    "iso:country":"CA",
    "name:ara_x_preferred":[
        "\u0628\u0644\u064a\u0632\u0627\u0646\u062a \u0641\u0627\u0644\u064a"
    ],
    "name:cat_x_preferred":[
        "Pleasant Valley"
    ],
    "name:ceb_x_preferred":[
        "Pleasant Valley"
    ],
    "name:deu_x_preferred":[
        "Pleasant Valley"
    ],
    "name:fra_x_preferred":[
        "Pleasant Valley"
    ],
    "name:ita_x_preferred":[
        "Pleasant Valley"
    ],
    "name:nld_x_preferred":[
        "Pleasant Valley"
    ],
    "name:pol_x_preferred":[
        "Pleasant Valley"
    ],
    "name:por_x_preferred":[
        "Pleasant Valley"
    ],
    "name:spa_x_preferred":[
        "Pleasant Valley"
    ],
    "name:srp_x_preferred":[
        "\u041f\u043b\u0435\u0437\u0430\u043d\u0442 \u0412\u0430\u043b\u0438"
    ],
    "name:swe_x_preferred":[
        "Pleasant Valley"
    ],
    "name:vol_x_preferred":[
        "Pleasant Valley"
    ],
    "wof:name":"Pleasant Valley",
    "wof:placetype":"locality"
},
  "geometry": {"coordinates":[-62.87438,45.09895],"type":"Point"}
}