{
  "type": "Feature",
  "properties": {
    "gn:country":"CA",
    "gn:fcode":"ADMD",
    "gn:pop":0,
    "iso:country":"CA",
    "name:eng_x_preferred":[
        "St. Clements"
    ],
    "qs:name":"St. Clements",
    "qs:photos_9r":0,
    "qs:photos_sr":0,
    "qs:pop_sr":"0",
    "wd:wordcount":134,
    "wof:name":"St. Clements",
    "wof:placetype":"localadmin",
    "wof:population":0
},
  "geometry": {"coordinates":[-96.75121,50.1642],"type":"Point"}
}