{
  "type": "Feature",
  "properties": {
    "gn:admin1_code":"8",
    "gn:asciiname":"Geneva Park",
    "gn:country_code":"CA",
    "gn:dem":230,
    "gn:feature_class":"P",
    "gn:feature_code":"PPL",
    "gn:name":"Geneva Park",
    "gn:population":0,
    "gn:timezone":"America/Toronto",
    "iso:country":"CA",
    "wof:name":"Geneva Park",
    "wof:placetype":"locality"
},
  "geometry": {"coordinates":[-79.36389,44.67389],"type":"Point"}
}