{
  "type": "Feature",
  "properties": {
    "gn:admin1_code":"8",
    "gn:asciiname":"Silverdale",
    "gn:country_code":"CA",
    "gn:dem":184,
    "gn:feature_class":"P",
    "gn:feature_code":"PPL",
    "gn:name":"Silverdale",
    "gn:population":0,
    "gn:timezone":"America/Toronto",
    "iso:country":"CA",
    "name:ceb_x_preferred":[
        "Silverdale"
    ],
    "name:deu_x_preferred":[
        "Silverdale"
    ],
    "name:fra_x_preferred":[
        "Silverdale"
    ],
    "name:ita_x_preferred":[
        "Silverdale"
    ],
    "name:nld_x_preferred":[
        "Silverdale"
    ],
    "name:pol_x_preferred":[
        "Silverdale"
    ],
    "name:spa_x_preferred":[
        "Silverdale"
    ],
    "name:srp_x_preferred":[
        "\u0421\u0438\u043b\u0432\u0435\u0440\u0434\u0435\u0458\u043b"
    ],
    "name:swe_x_preferred":[
        "Silverdale"
    ],
    "name:vol_x_preferred":[
        "Silverdale"
    ],
    "wof:name":"Silverdale",
    "wof:placetype":"locality"
},
  "geometry": {"coordinates":[-79.45444000000001,43.07583],"type":"Point"}
}