{
  "type": "Feature",
  "properties": {
    "gn:admin1_code":"7",
    "gn:asciiname":"Upper Nine Mile River",
    "gn:country_code":"CA",
    "gn:dem":49,
    "gn:feature_class":"P",
    "gn:feature_code":"PPL",
    "gn:name":"Upper Nine Mile River",
    "gn:population":0,
    "gn:timezone":"America/Halifax",
    "iso:country":"CA",
    "wof:name":"Upper Nine Mile River",
    "wof:placetype":"locality"
},
  "geometry": {"coordinates":[-63.62643000000001,45.07921],"type":"Point"}
}