{
  "type": "Feature",
  "properties": {
    "gn:admin1_code":"8",
    "gn:asciiname":"Landerkin",
    "gn:country_code":"CA",
    "gn:dem":461,
    "gn:feature_class":"P",
    "gn:feature_code":"PPL",
    "gn:name":"Landerkin",
    "gn:population":0,
    "gn:timezone":"America/Toronto",
    "iso:country":"CA",
    "wof:name":"Landerkin",
    "wof:placetype":"locality"
},
  "geometry": {"coordinates":[-80.62056,44.01111],"type":"Point"}
}