{
  "type": "Feature",
  "properties": {
    "gn:admin1_code":"2.0",
    "gn:asciiname":"East Kelowna",
    "gn:country_code":"CA",
    "gn:dem":425,
    "gn:feature_class":"P",
    "gn:feature_code":"PPL",
    "gn:name":"East Kelowna",
    "gn:population":0,
    "gn:timezone":"America/Vancouver",
    "iso:country":"CA",
    "wof:name":"East Kelowna",
    "wof:placetype":"locality"
},
  "geometry": {"coordinates":[-119.425,49.8625],"type":"Point"}
}