{
  "type": "Feature",
  "properties": {
    "iso:country":"CA",
    "name:eng_x_preferred":[
        "108 Mile Ranch"
    ],
    "name:fra_x_preferred":[
        "108 Mile Ranch"
    ],
    "name:nld_x_preferred":[
        "108 Mile Ranch"
    ],
    "name:urd_x_preferred":[
        "108 \u0645\u0627\u0626\u0644  \u0631\u06cc\u0646\u0686\u060c \u0628\u0631\u0679\u0634 \u06a9\u0648\u0644\u0645\u0628\u06cc\u0627"
    ],
    "qs_pg:aaroncc":"CA",
    "qs_pg:name":"108 Mile Ranch",
    "qs_pg:name_adm0":"Canada",
    "qs_pg:name_adm1":"British Columbia",
    "qs_pg:photos":212,
    "qs_pg:photos_1k":43,
    "qs_pg:photos_9k":1,
    "qs_pg:photos_9r":4,
    "qs_pg:photos_all":212,
    "qs_pg:photos_sr":4,
    "qs_pg:pop_sr":0,
    "qs_pg:qs_pg_placetype":"locality",
    "qs_pg:qs_pg_placetype_gp":"Town",
    "qs_pg:woe_adm0":23424775,
    "woe:adm0_id":23424775,
    "woe:name_adm0":"Canada",
    "woe:name_adm1":"British Columbia",
    "woe:placetype":"Town",
    "wof:name":"108 Mile Ranch",
    "wof:placetype":"locality"
},
  "geometry": {"coordinates":[-121.35289849999999,51.746588],"type":"Point"}
}