{
  "type": "Feature",
  "properties": {
    "gn:admin1_code":"11.0",
    "gn:asciiname":"Coriander",
    "gn:country_code":"CA",
    "gn:dem":843,
    "gn:feature_class":"P",
    "gn:feature_code":"PPLL",
    "gn:name":"Coriander",
    "gn:population":0,
    "gn:timezone":"America/Regina",
    "iso:country":"CA",
    "wof:name":"Coriander",
    "wof:placetype":"locality"
},
  "geometry": {"coordinates":[-107.56798999999999,49.30005],"type":"Point"}
}