{
  "type": "Feature",
  "properties": {
    "iso:country":"CA",
    "name:cat_x_preferred":[
        "Bright"
    ],
    "name:ceb_x_preferred":[
        "Bright"
    ],
    "name:deu_x_preferred":[
        "Bright"
    ],
    "name:fra_x_preferred":[
        "Bright"
    ],
    "name:ita_x_preferred":[
        "Bright"
    ],
    "name:jpn_x_preferred":[
        "\u30d6\u30e9\u30a4\u30c8"
    ],
    "name:kor_x_preferred":[
        "\ube0c\ub77c\uc774\ud2b8"
    ],
    "name:nld_x_preferred":[
        "Bright"
    ],
    "name:pol_x_preferred":[
        "Bright"
    ],
    "name:rus_x_preferred":[
        "\u0411\u0440\u0430\u0439\u0442"
    ],
    "name:swe_x_preferred":[
        "Bright"
    ],
    "name:ukr_x_preferred":[
        "\u0411\u0440\u0430\u0439\u0442"
    ],
    "qs_pg:aaroncc":"CA",
    "qs_pg:name":"Bright",
    "qs_pg:name_adm0":"Canada",
    "qs_pg:name_adm1":"Ontario",
    "qs_pg:photos":4,
    "qs_pg:photos_1k":1,
    "qs_pg:photos_9k":1,
    "qs_pg:photos_9r":1,
    "qs_pg:photos_all":4,
    "qs_pg:photos_sr":1,
    "qs_pg:pop_sr":0,
    "qs_pg:qs_pg_placetype":"locality",
    "qs_pg:qs_pg_placetype_gp":"Town",
    "qs_pg:woe_adm0":23424775,
    "woe:adm0_id":23424775,
    "woe:name_adm0":"Canada",
    "woe:name_adm1":"Ontario",
    "woe:placetype":"Town",
    "wof:name":"Bright",
    "wof:placetype":"locality"
},
  "geometry": {"coordinates":[-80.650892,43.257404],"type":"Point"}
}