{
  "type": "Feature",
  "properties": {
    "gn:admin1_code":"8.0",
    "gn:asciiname":"Canton",
    "gn:country_code":"CA",
    "gn:dem":115,
    "gn:feature_class":"P",
    "gn:feature_code":"PPL",
    "gn:name":"Canton",
    "gn:population":0,
    "gn:timezone":"America/Toronto",
    "iso:country":"CA",
    "name:bre_x_preferred":[
        "Canton"
    ],
    "name:bul_x_preferred":[
        "\u041a\u0430\u043d\u0442\u044a\u043d"
    ],
    "name:cat_x_preferred":[
        "Canton"
    ],
    "name:ceb_x_preferred":[
        "Canton"
    ],
    "name:ces_x_preferred":[
        "Canton"
    ],
    "name:cym_x_preferred":[
        "Canton"
    ],
    "name:deu_x_preferred":[
        "Canton"
    ],
    "name:eus_x_preferred":[
        "Canton"
    ],
    "name:fin_x_preferred":[
        "Canton"
    ],
    "name:fra_x_preferred":[
        "Canton"
    ],
    "name:hin_x_preferred":[
        "\u0915\u0948\u0923\u094d\u091f\u0928"
    ],
    "name:ita_x_preferred":[
        "Canton"
    ],
    "name:pol_x_preferred":[
        "Canton"
    ],
    "name:por_x_preferred":[
        "Canton"
    ],
    "name:roh_x_preferred":[
        "Chantun"
    ],
    "name:ron_x_preferred":[
        "Canton"
    ],
    "name:rus_x_preferred":[
        "\u041a\u044d\u043d\u0442\u043e\u043d"
    ],
    "name:scn_x_preferred":[
        "Cantuni"
    ],
    "name:slk_x_preferred":[
        "Canton"
    ],
    "name:spa_x_preferred":[
        "Canton"
    ],
    "name:swa_x_preferred":[
        "Canton"
    ],
    "name:swe_x_preferred":[
        "Canton"
    ],
    "name:urd_x_preferred":[
        "\u06a9\u06cc\u0646\u0679\u0646"
    ],
    "name:vol_x_preferred":[
        "Canton"
    ],
    "wof:name":"Canton",
    "wof:placetype":"locality"
},
  "geometry": {"coordinates":[-78.35096999999998,43.9976],"type":"Point"}
}