{
  "type": "Feature",
  "properties": {
    "gn:admin1_code":"8.0",
    "gn:asciiname":"Canton",
    "gn:country_code":"CA",
    "gn:dem":115,
    "gn:feature_class":"P",
    "gn:feature_code":"PPL",
    "gn:name":"Canton",
    "gn:population":0,
    "gn:timezone":"America/Toronto",
    "iso:country":"CA",
    "wof:name":"Canton",
    "wof:placetype":"locality"
},
  "geometry": {"coordinates":[-78.35096999999998,43.9976],"type":"Point"}
}