{
  "type": "Feature",
  "properties": {
    "iso:country":"CA",
    "name:ceb_x_preferred":[
        "Forest Hill"
    ],
    "name:deu_x_preferred":[
        "Forest Hill"
    ],
    "name:eng_x_preferred":[
        "Forest Hill"
    ],
    "name:hbs_x_preferred":[
        "Forist Hil"
    ],
    "name:ita_x_preferred":[
        "Forest Hill"
    ],
    "name:mlg_x_preferred":[
        "Forest Hill"
    ],
    "name:nld_x_preferred":[
        "Forest Hill"
    ],
    "name:pol_x_preferred":[
        "Forest Hill"
    ],
    "name:por_x_preferred":[
        "Forest Hill"
    ],
    "name:spa_x_preferred":[
        "Forest Hill"
    ],
    "name:srp_x_preferred":[
        "\u0424\u043e\u0440\u0438\u0441\u0442 \u0425\u0438\u043b"
    ],
    "name:swe_x_preferred":[
        "Forest Hill"
    ],
    "qs:gn_adm0_cc":"CA",
    "qs:gn_local":5992996,
    "qs:gn_nam_loc":"kitchener",
    "qs:gn_namadm1":"08",
    "qs:local_max":6042,
    "qs:local_sum":26102,
    "qs:localhoods":44,
    "qs:name":"Forest Hill",
    "qs:name_adm0":"Canada",
    "qs:name_adm1":"Ontario",
    "qs:name_adm2":"Waterloo",
    "qs:name_local":"Kitchener",
    "qs:photo_max":1,
    "qs:photo_sum":1,
    "qs:placetype":"Suburb",
    "qs:quad_count":1,
    "qs:woe_adm0":23424775,
    "qs:woe_adm1":2344922,
    "qs:woe_adm2":29375060,
    "qs:woe_lau":0,
    "qs:woe_local":4051,
    "qs:woe_ver":"7.10.0",
    "wd:wordcount":207,
    "wof:lang":[
        "eng"
    ],
    "wof:name":"Forest Hill",
    "wof:placetype":"neighbourhood"
},
  "geometry": {"coordinates":[-80.517426,43.42799],"type":"Point"}
}