{
  "type": "Feature",
  "properties": {
    "gn:admin1_code":"7",
    "gn:asciiname":"South Canaan",
    "gn:country_code":"CA",
    "gn:dem":29,
    "gn:feature_class":"P",
    "gn:feature_code":"PPL",
    "gn:name":"South Canaan",
    "gn:population":0,
    "gn:timezone":"America/Halifax",
    "iso:country":"CA",
    "wof:name":"South Canaan",
    "wof:placetype":"locality"
},
  "geometry": {"coordinates":[-65.8793,43.94121],"type":"Point"}
}