{
  "type": "Feature",
  "properties": {
    "gn:admin1_code":"7",
    "gn:asciiname":"South Cape Highlands",
    "gn:country_code":"CA",
    "gn:dem":333,
    "gn:feature_class":"P",
    "gn:feature_code":"PPLL",
    "gn:name":"South Cape Highlands",
    "gn:population":0,
    "gn:timezone":"America/Halifax",
    "iso:country":"CA",
    "wof:name":"South Cape Highlands",
    "wof:placetype":"locality"
},
  "geometry": {"coordinates":[-61.38183000000001,46.15014],"type":"Point"}
}