{
  "type": "Feature",
  "properties": {
    "gn:admin1_code":"8.0",
    "gn:asciiname":"Bolger",
    "gn:country_code":"CA",
    "gn:dem":246,
    "gn:feature_class":"P",
    "gn:feature_code":"PPL",
    "gn:name":"Bolger",
    "gn:population":0,
    "gn:timezone":"America/Toronto",
    "iso:country":"CA",
    "name:deu_x_preferred":[
        "Bolger"
    ],
    "name:jpn_x_preferred":[
        "\u30dc\u30eb\u30b8\u30e3\u30fc"
    ],
    "name:nds_x_preferred":[
        "Bolger"
    ],
    "name:rus_x_preferred":[
        "\u0411\u043e\u043b\u0434\u0436\u0435\u0440"
    ],
    "name:slv_x_preferred":[
        "Bolger"
    ],
    "wof:name":"Bolger",
    "wof:placetype":"locality"
},
  "geometry": {"coordinates":[-80.13297,45.68339],"type":"Point"}
}