{
  "type": "Feature",
  "properties": {
    "gn:admin1_code":"8",
    "gn:asciiname":"Orchardville",
    "gn:country_code":"CA",
    "gn:dem":387,
    "gn:feature_class":"P",
    "gn:feature_code":"PPL",
    "gn:name":"Orchardville",
    "gn:population":0,
    "gn:timezone":"America/Toronto",
    "iso:country":"CA",
    "wof:name":"Orchardville",
    "wof:placetype":"locality"
},
  "geometry": {"coordinates":[-80.79848,44.08052],"type":"Point"}
}