{
  "type": "Feature",
  "properties": {
    "gn:admin1_code":"7",
    "gn:asciiname":"Red River",
    "gn:country_code":"CA",
    "gn:dem":17,
    "gn:feature_class":"P",
    "gn:feature_code":"PPL",
    "gn:name":"Red River",
    "gn:population":0,
    "gn:timezone":"America/Halifax",
    "iso:country":"CA",
    "wof:name":"Red River",
    "wof:placetype":"locality"
},
  "geometry": {"coordinates":[-60.79316,46.83256],"type":"Point"}
}