{
  "type": "Feature",
  "properties": {
    "gn:admin1_code":"7",
    "gn:asciiname":"Red River",
    "gn:country_code":"CA",
    "gn:dem":17,
    "gn:feature_class":"P",
    "gn:feature_code":"PPL",
    "gn:name":"Red River",
    "gn:population":0,
    "gn:timezone":"America/Halifax",
    "iso:country":"CA",
    "name:ara_x_preferred":[
        "\u0627\u0644\u0646\u0647\u0631 \u0627\u0644\u0623\u062d\u0645\u0631"
    ],
    "name:bul_x_preferred":[
        "\u0420\u0435\u0434 \u0420\u0438\u0432\u044a\u0440"
    ],
    "name:ceb_x_preferred":[
        "Red River"
    ],
    "name:ces_x_preferred":[
        "Red River"
    ],
    "name:deu_x_preferred":[
        "Red River"
    ],
    "name:est_x_preferred":[
        "Red River"
    ],
    "name:fas_x_preferred":[
        "\u0631\u0648\u062f \u0633\u0631\u062e"
    ],
    "name:fin_x_preferred":[
        "Red River"
    ],
    "name:fry_x_preferred":[
        "Reade Rivier"
    ],
    "name:heb_x_preferred":[
        "\u05d4\u05e0\u05d4\u05e8 \u05d4\u05d0\u05d3\u05d5\u05dd"
    ],
    "name:ita_x_preferred":[
        "Red River"
    ],
    "name:jpn_x_preferred":[
        "\u30ec\u30c3\u30c9\u5ddd"
    ],
    "name:kor_x_preferred":[
        "\ub808\ub4dc \uac15"
    ],
    "name:nds_x_preferred":[
        "Red River"
    ],
    "name:nld_x_preferred":[
        "Red River"
    ],
    "name:nor_x_preferred":[
        "Red River"
    ],
    "name:pol_x_preferred":[
        "Red River"
    ],
    "name:rus_x_preferred":[
        "\u0420\u0435\u0434-\u0420\u0438\u0432\u0435\u0440"
    ],
    "name:spa_x_preferred":[
        "Red River"
    ],
    "name:srp_x_preferred":[
        "\u0420\u0435\u0434 \u0420\u0438\u0432\u0435\u0440"
    ],
    "name:swe_x_preferred":[
        "Red River"
    ],
    "name:ukr_x_preferred":[
        "\u0420\u0435\u0434-\u0420\u0456\u0432\u0435\u0440"
    ],
    "name:vie_x_preferred":[
        "S\u00f4ng Red"
    ],
    "name:zho_x_preferred":[
        "\u7ea2\u6cb3"
    ],
    "wof:name":"Red River",
    "wof:placetype":"locality"
},
  "geometry": {"coordinates":[-60.79316,46.83256],"type":"Point"}
}