{
  "type": "Feature",
  "properties": {
    "gn:admin1_code":"8",
    "gn:asciiname":"Taylor",
    "gn:country_code":"CA",
    "gn:dem":115,
    "gn:feature_class":"P",
    "gn:feature_code":"PPL",
    "gn:name":"Taylor",
    "gn:population":0,
    "gn:timezone":"America/Toronto",
    "iso:country":"CA",
    "wof:name":"Taylor",
    "wof:placetype":"locality"
},
  "geometry": {"coordinates":[-76.21222,44.41472],"type":"Point"}
}