{
  "type": "Feature",
  "properties": {
    "gn:admin1_code":"8",
    "gn:asciiname":"Taylor",
    "gn:country_code":"CA",
    "gn:dem":115,
    "gn:feature_class":"P",
    "gn:feature_code":"PPL",
    "gn:name":"Taylor",
    "gn:population":0,
    "gn:timezone":"America/Toronto",
    "iso:country":"CA",
    "name:ara_x_preferred":[
        "\u062a\u0627\u064a\u0644\u0648\u0631"
    ],
    "name:bel_x_preferred":[
        "\u0422\u044d\u0439\u043b\u0430\u0440"
    ],
    "name:bul_x_preferred":[
        "\u0422\u0435\u0439\u043b\u044a\u0440"
    ],
    "name:cat_x_preferred":[
        "Taylor"
    ],
    "name:ceb_x_preferred":[
        "Taylor"
    ],
    "name:ces_x_preferred":[
        "Taylor"
    ],
    "name:deu_x_preferred":[
        "Taylor"
    ],
    "name:fas_x_preferred":[
        "\u062a\u06cc\u0644\u0648\u0631"
    ],
    "name:fin_x_preferred":[
        "Taylor"
    ],
    "name:fra_x_preferred":[
        "Taylor"
    ],
    "name:heb_x_preferred":[
        "\u05d8\u05d9\u05d9\u05dc\u05d5\u05e8"
    ],
    "name:ita_x_preferred":[
        "Taylor"
    ],
    "name:jpn_x_preferred":[
        "\u30c6\u30a4\u30e9\u30fc"
    ],
    "name:kor_x_preferred":[
        "\ud14c\uc77c\ub7ec"
    ],
    "name:lav_x_preferred":[
        "Teilors"
    ],
    "name:lit_x_preferred":[
        "Taylor"
    ],
    "name:nld_x_preferred":[
        "Taylor"
    ],
    "name:nor_x_preferred":[
        "Taylor"
    ],
    "name:pol_x_preferred":[
        "Taylor"
    ],
    "name:por_x_preferred":[
        "Taylor"
    ],
    "name:ron_x_preferred":[
        "Taylor"
    ],
    "name:rus_x_preferred":[
        "\u0422\u0435\u0439\u043b\u043e\u0440"
    ],
    "name:slv_x_preferred":[
        "Taylor"
    ],
    "name:spa_x_preferred":[
        "Taylor"
    ],
    "name:srp_x_preferred":[
        "\u0422\u0435\u0458\u043b\u043e\u0440"
    ],
    "name:swa_x_preferred":[
        "Taylor"
    ],
    "name:swe_x_preferred":[
        "Taylor"
    ],
    "name:ukr_x_preferred":[
        "\u0422\u0435\u0439\u043b\u043e\u0440"
    ],
    "name:urd_x_preferred":[
        "\u0679\u06cc\u0644\u0631"
    ],
    "name:vie_x_preferred":[
        "Taylor"
    ],
    "name:vol_x_preferred":[
        "Taylor"
    ],
    "wof:name":"Taylor",
    "wof:placetype":"locality"
},
  "geometry": {"coordinates":[-76.21222,44.41472],"type":"Point"}
}