{
  "type": "Feature",
  "properties": {
    "gn:admin1_code":"8",
    "gn:asciiname":"Riverside",
    "gn:country_code":"CA",
    "gn:dem":211,
    "gn:feature_class":"P",
    "gn:feature_code":"PPLL",
    "gn:name":"Riverside",
    "gn:population":0,
    "gn:timezone":"America/Toronto",
    "iso:country":"CA",
    "wof:name":"Riverside",
    "wof:placetype":"locality"
},
  "geometry": {"coordinates":[-79.79134999999999,44.68791],"type":"Point"}
}