{
  "type": "Feature",
  "properties": {
    "iso:country":"CA",
    "name:eng_x_preferred":[
        "East Beaver Creek"
    ],
    "name:unk_x_variant":[
        "East Beaver Creek"
    ],
    "qs:gn_adm0_cc":"CA",
    "qs:gn_local":6066513,
    "qs:gn_nam_loc":"markham",
    "qs:gn_namadm1":"08",
    "qs:local_max":458,
    "qs:local_sum":2399,
    "qs:localhoods":12,
    "qs:name":"East Beaver Creek",
    "qs:name_adm0":"Canada",
    "qs:name_adm1":"Ontario",
    "qs:name_adm2":"York",
    "qs:name_local":"Markham",
    "qs:photo_max":83,
    "qs:photo_sum":400,
    "qs:placetype":"Suburb",
    "qs:quad_count":25,
    "qs:woe_adm0":23424775,
    "qs:woe_adm1":2344922,
    "qs:woe_adm2":29375112,
    "qs:woe_funk":"Parented by a neighborhood",
    "qs:woe_lau":0,
    "qs:woe_local":935,
    "qs:woe_ver":"7.10.0",
    "wof:lang":[
        "eng"
    ],
    "wof:name":"East Beaver Creek",
    "wof:placetype":"neighbourhood"
},
  "geometry": {"coordinates":[-79.378596,43.855977],"type":"Point"}
}