{
  "type": "Feature",
  "properties": {
    "gn:admin1_code":"3.0",
    "gn:asciiname":"Denbeigh Point",
    "gn:country_code":"CA",
    "gn:dem":256,
    "gn:feature_class":"P",
    "gn:feature_code":"PPLL",
    "gn:name":"Denbeigh Point",
    "gn:population":0,
    "gn:timezone":"America/Winnipeg",
    "iso:country":"CA",
    "wof:name":"Denbeigh Point",
    "wof:placetype":"locality"
},
  "geometry": {"coordinates":[-99.78269,52.89312],"type":"Point"}
}