{
  "type": "Feature",
  "properties": {
    "gn:admin1_code":"10.0",
    "gn:admin2_code":"11",
    "gn:asciiname":"Gagne",
    "gn:country_code":"CA",
    "gn:dem":11,
    "gn:feature_class":"P",
    "gn:feature_code":"PPL",
    "gn:name":"Gagn\u00e9",
    "gn:population":0,
    "gn:timezone":"America/Toronto",
    "iso:country":"CA",
    "wof:name":"Gagne",
    "wof:placetype":"locality"
},
  "geometry": {"coordinates":[-65.94711,48.19796],"type":"Point"}
}