{
  "type": "Feature",
  "properties": {
    "gn:admin1_code":"10.0",
    "gn:admin2_code":"4.0",
    "gn:admin3_code":"51075.0",
    "gn:asciiname":"Domaine-Ouellet",
    "gn:country_code":"CA",
    "gn:dem":175,
    "gn:feature_class":"P",
    "gn:feature_code":"PPL",
    "gn:name":"Domaine-Ouellet",
    "gn:population":0,
    "gn:timezone":"America/Toronto",
    "iso:country":"CA",
    "wof:name":"Domaine-Ouellet",
    "wof:placetype":"locality"
},
  "geometry": {"coordinates":[-72.91485,46.49864],"type":"Point"}
}