{
  "type": "Feature",
  "properties": {
    "gn:admin1_code":"8",
    "gn:asciiname":"Stoco",
    "gn:country_code":"CA",
    "gn:dem":144,
    "gn:feature_class":"P",
    "gn:feature_code":"PPL",
    "gn:name":"Stoco",
    "gn:population":0,
    "gn:timezone":"America/Toronto",
    "iso:country":"CA",
    "wof:name":"Stoco",
    "wof:placetype":"locality"
},
  "geometry": {"coordinates":[-77.27500000000001,44.46083],"type":"Point"}
}