{
  "type": "Feature",
  "properties": {
    "gn:admin1_code":"8",
    "gn:asciiname":"Tolmie",
    "gn:country_code":"CA",
    "gn:dem":196,
    "gn:feature_class":"P",
    "gn:feature_code":"PPL",
    "gn:name":"Tolmie",
    "gn:population":0,
    "gn:timezone":"America/Toronto",
    "iso:country":"CA",
    "name:deu_x_preferred":[
        "Tolmie"
    ],
    "wof:name":"Tolmie",
    "wof:placetype":"locality"
},
  "geometry": {"coordinates":[-81.21458,44.63098],"type":"Point"}
}