{
  "type": "Feature",
  "properties": {
    "gn:admin1_code":"11",
    "gn:asciiname":"Neely",
    "gn:country_code":"CA",
    "gn:dem":536,
    "gn:feature_class":"P",
    "gn:feature_code":"PPL",
    "gn:name":"Neely",
    "gn:population":0,
    "gn:timezone":"America/Regina",
    "iso:country":"CA",
    "wof:name":"Neely",
    "wof:placetype":"locality"
},
  "geometry": {"coordinates":[-105.78393,51.93337],"type":"Point"}
}