{
  "type": "Feature",
  "properties": {
    "gn:admin1_code":"12",
    "gn:asciiname":"Fort Selkirk",
    "gn:country_code":"CA",
    "gn:dem":547,
    "gn:feature_class":"P",
    "gn:feature_code":"PPLL",
    "gn:name":"Fort Selkirk",
    "gn:population":0,
    "gn:timezone":"America/Whitehorse",
    "iso:country":"CA",
    "wof:name":"Fort Selkirk",
    "wof:placetype":"locality"
},
  "geometry": {"coordinates":[-137.38990999999999,62.77499],"type":"Point"}
}