{
  "type": "Feature",
  "properties": {
    "gn:admin1_code":"12",
    "gn:asciiname":"Fort Selkirk",
    "gn:country_code":"CA",
    "gn:dem":547,
    "gn:feature_class":"P",
    "gn:feature_code":"PPLL",
    "gn:name":"Fort Selkirk",
    "gn:population":0,
    "gn:timezone":"America/Whitehorse",
    "iso:country":"CA",
    "name:deu_x_preferred":[
        "Fort Selkirk"
    ],
    "name:epo_x_preferred":[
        "Fort Selkirk"
    ],
    "name:fra_x_preferred":[
        "Fort Selkirk"
    ],
    "name:rus_x_preferred":[
        "\u0424\u043e\u0440\u0442-\u0421\u0435\u043b\u043a\u0435\u0440\u043a"
    ],
    "wof:name":"Fort Selkirk",
    "wof:placetype":"locality"
},
  "geometry": {"coordinates":[-137.38990999999999,62.77499],"type":"Point"}
}