{
  "type": "Feature",
  "properties": {
    "gn:admin1_code":"4",
    "gn:asciiname":"Spence Settlement",
    "gn:country_code":"CA",
    "gn:dem":3,
    "gn:feature_class":"P",
    "gn:feature_code":"PPL",
    "gn:name":"Spence Settlement",
    "gn:population":0,
    "gn:timezone":"America/Moncton",
    "iso:country":"CA",
    "wof:name":"Spence Settlement",
    "wof:placetype":"locality"
},
  "geometry": {"coordinates":[-63.88531,46.1425],"type":"Point"}
}