{
  "type": "Feature",
  "properties": {
    "gn:admin1_code":"3",
    "gn:asciiname":"Spruce Siding",
    "gn:country_code":"CA",
    "gn:dem":292,
    "gn:feature_class":"P",
    "gn:feature_code":"PPLL",
    "gn:name":"Spruce Siding",
    "gn:population":0,
    "gn:timezone":"America/Winnipeg",
    "iso:country":"CA",
    "wof:name":"Spruce Siding",
    "wof:placetype":"locality"
},
  "geometry": {"coordinates":[-96.04335,49.72389],"type":"Point"}
}