{
  "type": "Feature",
  "properties": {
    "iso:country":"CA",
    "name:eng_x_variant":[
        "Town of York"
    ],
    "wof:name":"Old Town",
    "wof:placetype":"microhood"
},
  "geometry": {"coordinates":[-79.36887197910872,43.65275035140584],"type":"Point"}
}