{
  "type": "Feature",
  "properties": {
    "gn:admin1_code":"1",
    "gn:admin2_code":"4808027.0",
    "gn:asciiname":"Sunbreaker Cove",
    "gn:country_code":"CA",
    "gn:dem":960,
    "gn:feature_class":"P",
    "gn:feature_code":"PPL",
    "gn:name":"Sunbreaker Cove",
    "gn:population":0,
    "gn:timezone":"America/Edmonton",
    "iso:country":"CA",
    "name:fra_x_preferred":[
        "Sunbreaker Cove"
    ],
    "wof:name":"Sunbreaker Cove",
    "wof:placetype":"locality"
},
  "geometry": {"coordinates":[-114.19421,52.38864],"type":"Point"}
}