{
  "type": "Feature",
  "properties": {
    "gn:admin1_code":"8",
    "gn:asciiname":"Salem Corners",
    "gn:country_code":"CA",
    "gn:dem":294,
    "gn:feature_class":"P",
    "gn:feature_code":"PPL",
    "gn:name":"Salem Corners",
    "gn:population":0,
    "gn:timezone":"America/Toronto",
    "iso:country":"CA",
    "wof:name":"Salem Corners",
    "wof:placetype":"locality"
},
  "geometry": {"coordinates":[-78.93639,44.28139],"type":"Point"}
}