{
  "type": "Feature",
  "properties": {
    "gn:admin1_code":"8",
    "gn:asciiname":"Happy Hollow",
    "gn:country_code":"CA",
    "gn:dem":79,
    "gn:feature_class":"P",
    "gn:feature_code":"PPL",
    "gn:name":"Happy Hollow",
    "gn:population":0,
    "gn:timezone":"America/Toronto",
    "iso:country":"CA",
    "name:ceb_x_preferred":[
        "Happy Hollow"
    ],
    "name:deu_x_preferred":[
        "Happy Hollow"
    ],
    "wof:name":"Happy Hollow",
    "wof:placetype":"locality"
},
  "geometry": {"coordinates":[-74.62822,45.53252],"type":"Point"}
}