{
  "type": "Feature",
  "properties": {
    "gn:admin1_code":"7",
    "gn:asciiname":"Rear Dunvegan",
    "gn:country_code":"CA",
    "gn:dem":49,
    "gn:feature_class":"P",
    "gn:feature_code":"PPLL",
    "gn:name":"Rear Dunvegan",
    "gn:population":0,
    "gn:timezone":"America/Halifax",
    "iso:country":"CA",
    "wof:name":"Rear Dunvegan",
    "wof:placetype":"locality"
},
  "geometry": {"coordinates":[-61.19851,46.33344],"type":"Point"}
}