{
  "type": "Feature",
  "properties": {
    "gn:admin1_code":"8",
    "gn:asciiname":"Mayerville",
    "gn:country_code":"CA",
    "gn:dem":69,
    "gn:feature_class":"P",
    "gn:feature_code":"PPL",
    "gn:name":"Mayerville",
    "gn:population":0,
    "gn:timezone":"America/Toronto",
    "iso:country":"CA",
    "wof:name":"Mayerville",
    "wof:placetype":"locality"
},
  "geometry": {"coordinates":[-75.06389,45.27306],"type":"Point"}
}