{
  "type": "Feature",
  "properties": {
    "gn:admin1_code":"11",
    "gn:asciiname":"Valeport",
    "gn:country_code":"CA",
    "gn:dem":517,
    "gn:feature_class":"P",
    "gn:feature_code":"PPLL",
    "gn:name":"Valeport",
    "gn:population":0,
    "gn:timezone":"America/Regina",
    "iso:country":"CA",
    "wof:name":"Valeport",
    "wof:placetype":"locality"
},
  "geometry": {"coordinates":[-104.86781999999999,50.75008],"type":"Point"}
}