{
  "type": "Feature",
  "properties": {
    "gn:admin1_code":"7.0",
    "gn:asciiname":"Castle Bay",
    "gn:country_code":"CA",
    "gn:dem":-9999,
    "gn:feature_class":"P",
    "gn:feature_code":"PPL",
    "gn:name":"Castle Bay",
    "gn:population":0,
    "gn:timezone":"America/Glace_Bay",
    "iso:country":"CA",
    "name:gla_x_preferred":[
        "B\u00e0gh a' Chaisteil"
    ],
    "wof:name":"Castle Bay",
    "wof:placetype":"locality"
},
  "geometry": {"coordinates":[-60.64848000000001,45.91684],"type":"Point"}
}