{
  "type": "Feature",
  "properties": {
    "gn:admin1_code":"2",
    "gn:asciiname":"Trout Creek",
    "gn:country_code":"CA",
    "gn:dem":342,
    "gn:feature_class":"P",
    "gn:feature_code":"PPL",
    "gn:name":"Trout Creek",
    "gn:population":0,
    "gn:timezone":"America/Vancouver",
    "iso:country":"CA",
    "name:ceb_x_preferred":[
        "Trout Creek"
    ],
    "name:swe_x_preferred":[
        "Trout Creek"
    ],
    "wof:name":"Trout Creek",
    "wof:placetype":"locality"
},
  "geometry": {"coordinates":[-119.61667,49.56667],"type":"Point"}
}