{
  "type": "Feature",
  "properties": {
    "gn:admin1_code":"1.0",
    "gn:asciiname":"Crowchild",
    "gn:country_code":"CA",
    "gn:dem":1146,
    "gn:feature_class":"P",
    "gn:feature_code":"PPLL",
    "gn:name":"Crowchild",
    "gn:population":0,
    "gn:timezone":"America/Edmonton",
    "iso:country":"CA",
    "wof:name":"Crowchild",
    "wof:placetype":"locality"
},
  "geometry": {"coordinates":[-114.2353,50.95011],"type":"Point"}
}