{
  "type": "Feature",
  "properties": {
    "gn:admin1_code":"10",
    "gn:admin2_code":"5.0",
    "gn:admin3_code":"45030.0",
    "gn:asciiname":"Highwater",
    "gn:country_code":"CA",
    "gn:dem":170,
    "gn:feature_class":"P",
    "gn:feature_code":"PPL",
    "gn:name":"Highwater",
    "gn:population":0,
    "gn:timezone":"America/Toronto",
    "iso:country":"CA",
    "wof:name":"Highwater",
    "wof:placetype":"locality"
},
  "geometry": {"coordinates":[-72.43011,45.02532],"type":"Point"}
}