{
  "type": "Feature",
  "properties": {
    "gn:admin1_code":"10.0",
    "gn:admin2_code":"11",
    "gn:admin3_code":"3005.0",
    "gn:asciiname":"Cap-des-Rosiers",
    "gn:country_code":"CA",
    "gn:dem":14,
    "gn:feature_class":"P",
    "gn:feature_code":"PPL",
    "gn:name":"Cap-des-Rosiers",
    "gn:population":0,
    "gn:timezone":"America/Toronto",
    "iso:country":"CA",
    "wof:name":"Cap-des-Rosiers",
    "wof:placetype":"locality"
},
  "geometry": {"coordinates":[-64.21061999999999,48.86178],"type":"Point"}
}