{
  "type": "Feature",
  "properties": {
    "iso:country":"CA",
    "name:ceb_x_preferred":[
        "Red Hill"
    ],
    "name:deu_x_preferred":[
        "Red Hill"
    ],
    "name:eng_x_preferred":[
        "Red Hill"
    ],
    "name:fra_x_preferred":[
        "Red Hill"
    ],
    "name:hbs_x_preferred":[
        "Red Hil"
    ],
    "name:ita_x_preferred":[
        "Red Hill"
    ],
    "name:mlg_x_preferred":[
        "Red Hill"
    ],
    "name:nld_x_preferred":[
        "Red Hill"
    ],
    "name:pol_x_preferred":[
        "Red Hill"
    ],
    "name:srp_x_preferred":[
        "\u0420\u0435\u0434 \u0425\u0438\u043b"
    ],
    "name:swe_x_preferred":[
        "Red Hill"
    ],
    "name:ukr_x_preferred":[
        "\u0420\u0435\u0434-\u0413\u0456\u043b\u043b"
    ],
    "name:vol_x_preferred":[
        "Red Hill"
    ],
    "qs:gn_local":0,
    "qs:local_max":716,
    "qs:local_sum":1071,
    "qs:localhoods":5,
    "qs:name":"Red Hill",
    "qs:name_adm0":"Canada",
    "qs:name_adm1":"Ontario",
    "qs:name_adm2":"Hamilton",
    "qs:name_local":"Mount Albion",
    "qs:photo_max":80,
    "qs:photo_sum":256,
    "qs:placetype":"Suburb",
    "qs:quad_count":25,
    "qs:woe_adm0":23424775,
    "qs:woe_adm1":2344922,
    "qs:woe_adm2":29375120,
    "qs:woe_funk":"Parented by a neighborhood",
    "qs:woe_lau":0,
    "qs:woe_local":55999225,
    "qs:woe_ver":"7.10.0",
    "wof:lang":[
        "eng"
    ],
    "wof:name":"Red Hill",
    "wof:placetype":"neighbourhood"
},
  "geometry": {"coordinates":[-79.789861,43.212299],"type":"Point"}
}