{
  "type": "Feature",
  "properties": {
    "gn:admin1_code":"9",
    "gn:asciiname":"Hillsborough Park",
    "gn:country_code":"CA",
    "gn:dem":12,
    "gn:feature_class":"P",
    "gn:feature_code":"PPLL",
    "gn:name":"Hillsborough Park",
    "gn:population":0,
    "gn:timezone":"America/Halifax",
    "iso:country":"CA",
    "name:ita_x_preferred":[
        "Hillsborough Park"
    ],
    "name:nld_x_preferred":[
        "Hillsborough Park"
    ],
    "wof:name":"Hillsborough Park",
    "wof:placetype":"locality"
},
  "geometry": {"coordinates":[-63.09728000000001,46.26322],"type":"Point"}
}