{
  "type": "Feature",
  "properties": {
    "gn:admin1_code":"8",
    "gn:asciiname":"Rossclair",
    "gn:country_code":"CA",
    "gn:dem":226,
    "gn:feature_class":"P",
    "gn:feature_code":"PPL",
    "gn:name":"Rossclair",
    "gn:population":0,
    "gn:timezone":"America/Toronto",
    "iso:country":"CA",
    "wof:name":"Rossclair",
    "wof:placetype":"locality"
},
  "geometry": {"coordinates":[-79.54833000000001,45.06306],"type":"Point"}
}