{
  "type": "Feature",
  "properties": {
    "gn:admin1_code":"10",
    "gn:admin2_code":"17",
    "gn:admin3_code":"38010.0",
    "gn:asciiname":"Saint-Gregoire-le-Grand",
    "gn:country_code":"CA",
    "gn:dem":30,
    "gn:feature_class":"P",
    "gn:feature_code":"PPL",
    "gn:name":"Saint-Gr\u00e9goire-le-Grand",
    "gn:population":0,
    "gn:timezone":"America/Toronto",
    "iso:country":"CA",
    "wof:name":"Saint-Gregoire-le-Grand",
    "wof:placetype":"locality"
},
  "geometry": {"coordinates":[-72.51222,46.27226],"type":"Point"}
}