{
  "type": "Feature",
  "properties": {
    "iso:country":"CA",
    "name:eng_x_preferred":[
        "Glenn Falls"
    ],
    "qs:gn_adm0_cc":"CA",
    "qs:gn_local":6138517,
    "qs:gn_nam_loc":"Saint John, Saint John, New Brunswick, CA",
    "qs:gn_namadm1":"04",
    "qs:local_max":7851,
    "qs:local_sum":18216,
    "qs:localhoods":28,
    "qs:name":"Glenn Falls",
    "qs:name_adm0":"Canada",
    "qs:name_adm1":"New Brunswick",
    "qs:name_adm2":"Saint John",
    "qs:name_local":"Saint John",
    "qs:photo_max":107,
    "qs:photo_sum":122,
    "qs:placetype":"Suburb",
    "qs:quad_count":9,
    "qs:woe_adm0":23424775,
    "qs:woe_adm1":2344918,
    "qs:woe_adm2":29375162,
    "qs:woe_lau":0,
    "qs:woe_local":1533,
    "qs:woe_ver":"7.10.0",
    "wof:lang":[
        "eng"
    ],
    "wof:name":"Glenn Falls",
    "wof:placetype":"neighbourhood"
},
  "geometry": {"coordinates":[-66.006952,45.317571],"type":"Point"}
}