{
  "type": "Feature",
  "properties": {
    "gn:admin1_code":"1",
    "gn:asciiname":"Mountain House",
    "gn:country_code":"CA",
    "gn:dem":979,
    "gn:feature_class":"P",
    "gn:feature_code":"PPLL",
    "gn:name":"Mountain House",
    "gn:population":0,
    "gn:timezone":"America/Edmonton",
    "iso:country":"CA",
    "name:ceb_x_preferred":[
        "Mountain House"
    ],
    "name:deu_x_preferred":[
        "Mountain House"
    ],
    "wof:name":"Mountain House",
    "wof:placetype":"locality"
},
  "geometry": {"coordinates":[-114.33531000000001,51.96681],"type":"Point"}
}