{
  "type": "Feature",
  "properties": {
    "gn:admin1_code":"8",
    "gn:asciiname":"Squirrel Town",
    "gn:country_code":"CA",
    "gn:dem":185,
    "gn:feature_class":"P",
    "gn:feature_code":"PPLL",
    "gn:name":"Squirrel Town",
    "gn:population":0,
    "gn:timezone":"America/Toronto",
    "iso:country":"CA",
    "wof:name":"Squirrel Town",
    "wof:placetype":"locality"
},
  "geometry": {"coordinates":[-81.8831,45.66677],"type":"Point"}
}