{
  "type": "Feature",
  "properties": {
    "gn:admin1_code":"2",
    "gn:asciiname":"Kitchener",
    "gn:country_code":"CA",
    "gn:dem":732,
    "gn:feature_class":"P",
    "gn:feature_code":"PPL",
    "gn:name":"Kitchener",
    "gn:population":0,
    "gn:timezone":"America/Creston",
    "iso:country":"CA",
    "name:azb_x_preferred":[
        "\u06a9\u06cc\u0686\u0646\u0631"
    ],
    "name:ceb_x_preferred":[
        "Kitchener"
    ],
    "name:deu_x_preferred":[
        "Kitchener"
    ],
    "name:fra_x_preferred":[
        "Kitchener"
    ],
    "name:fry_x_preferred":[
        "Kitchener"
    ],
    "name:jpn_x_preferred":[
        "\u30ad\u30c3\u30c1\u30ca\u30fc"
    ],
    "name:kor_x_preferred":[
        "\ud0a4\uce58\ub108"
    ],
    "name:nld_x_preferred":[
        "Kitchener"
    ],
    "name:pol_x_preferred":[
        "Kitchener"
    ],
    "name:por_x_preferred":[
        "Kitchener"
    ],
    "name:rus_x_preferred":[
        "\u041a\u0438\u0442\u0447\u0435\u043d\u0435\u0440"
    ],
    "name:spa_x_preferred":[
        "Kitchener"
    ],
    "name:swe_x_preferred":[
        "Kitchener"
    ],
    "name:tur_x_preferred":[
        "Kitchener"
    ],
    "wof:name":"Kitchener",
    "wof:placetype":"locality"
},
  "geometry": {"coordinates":[-116.33823,49.15819000000001],"type":"Point"}
}