{
  "type": "Feature",
  "properties": {
    "gn:admin1_code":"1",
    "gn:asciiname":"Summerview",
    "gn:country_code":"CA",
    "gn:dem":1119,
    "gn:feature_class":"P",
    "gn:feature_code":"PPLL",
    "gn:name":"Summerview",
    "gn:population":0,
    "gn:timezone":"America/Edmonton",
    "iso:country":"CA",
    "wof:name":"Summerview",
    "wof:placetype":"locality"
},
  "geometry": {"coordinates":[-113.88523000000001,49.58328],"type":"Point"}
}