{
  "type": "Feature",
  "properties": {
    "gn:admin1_code":"7",
    "gn:asciiname":"Pleasant Point",
    "gn:country_code":"CA",
    "gn:dem":20,
    "gn:feature_class":"P",
    "gn:feature_code":"PPL",
    "gn:name":"Pleasant Point",
    "gn:population":0,
    "gn:timezone":"America/Halifax",
    "iso:country":"CA",
    "name:ceb_x_preferred":[
        "Pleasant Point"
    ],
    "name:deu_x_preferred":[
        "Pleasant Point"
    ],
    "name:fra_x_preferred":[
        "Pleasant Point"
    ],
    "name:swe_x_preferred":[
        "Pleasant Point"
    ],
    "wof:name":"Pleasant Point",
    "wof:placetype":"locality"
},
  "geometry": {"coordinates":[-65.09801999999999,43.72137],"type":"Point"}
}