{
  "type": "Feature",
  "properties": {
    "gn:admin1_code":"5.0",
    "gn:asciiname":"Buchans Junction",
    "gn:country_code":"CA",
    "gn:dem":175,
    "gn:feature_class":"P",
    "gn:feature_code":"PPL",
    "gn:name":"Buchans Junction",
    "gn:population":0,
    "gn:timezone":"America/St_Johns",
    "iso:country":"CA",
    "wof:name":"Buchans Junction",
    "wof:placetype":"locality"
},
  "geometry": {"coordinates":[-56.4649,48.85],"type":"Point"}
}