{
  "type": "Feature",
  "properties": {
    "gn:admin1_code":"2.0",
    "gn:asciiname":"Eagle Ridge",
    "gn:country_code":"CA",
    "gn:dem":74,
    "gn:feature_class":"P",
    "gn:feature_code":"PPL",
    "gn:name":"Eagle Ridge",
    "gn:population":0,
    "gn:timezone":"America/Vancouver",
    "iso:country":"CA",
    "name:ceb_x_preferred":[
        "Eagle Ridge"
    ],
    "name:swe_x_preferred":[
        "Eagle Ridge"
    ],
    "wof:name":"Eagle Ridge",
    "wof:placetype":"locality"
},
  "geometry": {"coordinates":[-122.82167,49.28778],"type":"Point"}
}