{
  "type": "Feature",
  "properties": {
    "gn:country":"CA",
    "gn:fcode":"ADMD",
    "gn:population":0,
    "iso:country":"CA",
    "name:eng_x_preferred":[
        "North Dundas"
    ],
    "qs:name":"North Dundas",
    "qs:photos_9r":0,
    "qs:photos_sr":0,
    "qs:pop_sr":"0",
    "wd:wordcount":22,
    "wof:name":"North Dundas",
    "wof:placetype":"localadmin",
    "wof:population":0
},
  "geometry": {"coordinates":[-75.44933,45.0668],"type":"Point"}
}