{
  "type": "Feature",
  "properties": {
    "gn:admin1_code":"4",
    "gn:asciiname":"Reeds Point",
    "gn:country_code":"CA",
    "gn:dem":11,
    "gn:feature_class":"P",
    "gn:feature_code":"PPL",
    "gn:name":"Reeds Point",
    "gn:population":0,
    "gn:timezone":"America/Moncton",
    "iso:country":"CA",
    "wof:name":"Reeds Point",
    "wof:placetype":"locality"
},
  "geometry": {"coordinates":[-65.98383000000001,45.45894000000001],"type":"Point"}
}