{
  "type": "Feature",
  "properties": {
    "gn:admin1_code":"2.0",
    "gn:asciiname":"Crescent",
    "gn:country_code":"CA",
    "gn:dem":93,
    "gn:feature_class":"P",
    "gn:feature_code":"PPL",
    "gn:name":"Crescent",
    "gn:population":0,
    "gn:timezone":"America/Vancouver",
    "iso:country":"CA",
    "name:ara_x_preferred":[
        "\u0647\u0644\u0627\u0644"
    ],
    "name:arz_x_preferred":[
        "\u0647\u0644\u0627\u0644"
    ],
    "name:aze_x_preferred":[
        "Aypara"
    ],
    "name:bos_x_preferred":[
        "Polumjesec"
    ],
    "name:bul_x_preferred":[
        "\u041f\u043e\u043b\u0443\u043c\u0435\u0441\u0435\u0446"
    ],
    "name:dan_x_preferred":[
        "Halvm\u00e5ne"
    ],
    "name:deu_x_preferred":[
        "Mondsichel"
    ],
    "name:epo_x_preferred":[
        "Lunarko"
    ],
    "name:fas_x_preferred":[
        "\u0647\u0644\u0627\u0644"
    ],
    "name:fin_x_preferred":[
        "Kuun sirppi"
    ],
    "name:fra_x_preferred":[
        "Croissant"
    ],
    "name:heb_x_preferred":[
        "\u05e1\u05d4\u05e8"
    ],
    "name:hrv_x_preferred":[
        "Polumjesec"
    ],
    "name:ido_x_preferred":[
        "Krecento"
    ],
    "name:ind_x_preferred":[
        "Bulan sabit"
    ],
    "name:jpn_x_preferred":[
        "\u4e09\u65e5\u6708"
    ],
    "name:kat_x_preferred":[
        "\u10dc\u10d0\u10ee\u10d4\u10d5\u10d0\u10e0\u10db\u10d7\u10d5\u10d0\u10e0\u10d4"
    ],
    "name:kor_x_preferred":[
        "\ucd08\uc2b9\ub2ec"
    ],
    "name:nor_x_preferred":[
        "Halvm\u00e5ne"
    ],
    "name:pol_x_preferred":[
        "P\u00f3\u0142ksi\u0119\u017cyc"
    ],
    "name:por_x_preferred":[
        "Crescente"
    ],
    "name:rus_x_preferred":[
        "\u041f\u043e\u043b\u0443\u043c\u0435\u0441\u044f\u0446"
    ],
    "name:spa_x_preferred":[
        "Media luna"
    ],
    "name:swa_x_preferred":[
        "Hilali"
    ],
    "name:swe_x_preferred":[
        "M\u00e5nsk\u00e4ra"
    ],
    "name:tgl_x_preferred":[
        "Gasuklay"
    ],
    "name:tur_x_preferred":[
        "Hilal"
    ],
    "name:ukr_x_preferred":[
        "\u041f\u0456\u0432\u043c\u0456\u0441\u044f\u0446\u044c"
    ],
    "name:urd_x_preferred":[
        "\u06c1\u0644\u0627\u0644"
    ],
    "wof:name":"Crescent",
    "wof:placetype":"locality"
},
  "geometry": {"coordinates":[-122.84999999999999,49.05],"type":"Point"}
}