{
  "type": "Feature",
  "properties": {
    "gn:admin1_code":"2.0",
    "gn:asciiname":"Crescent",
    "gn:country_code":"CA",
    "gn:dem":93,
    "gn:feature_class":"P",
    "gn:feature_code":"PPL",
    "gn:name":"Crescent",
    "gn:population":0,
    "gn:timezone":"America/Vancouver",
    "iso:country":"CA",
    "wof:name":"Crescent",
    "wof:placetype":"locality"
},
  "geometry": {"coordinates":[-122.84999999999999,49.05],"type":"Point"}
}