{
  "type": "Feature",
  "properties": {
    "gn:admin1_code":"9",
    "gn:asciiname":"St. Peters Harbour",
    "gn:country_code":"CA",
    "gn:dem":14,
    "gn:feature_class":"P",
    "gn:feature_code":"PPLL",
    "gn:name":"St. Peters Harbour",
    "gn:population":0,
    "gn:timezone":"America/Halifax",
    "iso:country":"CA",
    "wof:name":"St. Peters Harbour",
    "wof:placetype":"locality"
},
  "geometry": {"coordinates":[-62.74866,46.43341],"type":"Point"}
}