{
  "type": "Feature",
  "properties": {
    "gn:admin1_code":"8.0",
    "gn:asciiname":"Barnesdale",
    "gn:country_code":"CA",
    "gn:dem":92,
    "gn:feature_class":"P",
    "gn:feature_code":"PPL",
    "gn:name":"Barnesdale",
    "gn:population":0,
    "gn:timezone":"America/Toronto",
    "iso:country":"CA",
    "wof:name":"Barnesdale",
    "wof:placetype":"locality"
},
  "geometry": {"coordinates":[-79.27916999999999,43.18306],"type":"Point"}
}