{
  "type": "Feature",
  "properties": {
    "gn:admin1_code":"12",
    "gn:asciiname":"Thistle Creek",
    "gn:country_code":"CA",
    "gn:dem":400,
    "gn:feature_class":"P",
    "gn:feature_code":"PPLL",
    "gn:name":"Thistle Creek",
    "gn:population":0,
    "gn:timezone":"America/Whitehorse",
    "iso:country":"CA",
    "wof:name":"Thistle Creek",
    "wof:placetype":"locality"
},
  "geometry": {"coordinates":[-139.50422,63.05911999999999],"type":"Point"}
}