{
  "type": "Feature",
  "properties": {
    "gn:admin1_code":"11",
    "gn:asciiname":"Eyre",
    "gn:country_code":"CA",
    "gn:dem":667,
    "gn:feature_class":"P",
    "gn:feature_code":"PPLL",
    "gn:name":"Eyre",
    "gn:population":0,
    "gn:timezone":"America/Regina",
    "iso:country":"CA",
    "wof:name":"Eyre",
    "wof:placetype":"locality"
},
  "geometry": {"coordinates":[-109.81827,51.26682],"type":"Point"}
}