{
  "type": "Feature",
  "properties": {
    "gn:admin1_code":"7",
    "gn:asciiname":"Highland Village",
    "gn:country_code":"CA",
    "gn:dem":23,
    "gn:feature_class":"P",
    "gn:feature_code":"PPL",
    "gn:name":"Highland Village",
    "gn:population":0,
    "gn:timezone":"America/Halifax",
    "iso:country":"CA",
    "name:fra_x_preferred":[
        "Highland Village"
    ],
    "name:pol_x_preferred":[
        "Highland Village"
    ],
    "wof:name":"Highland Village",
    "wof:placetype":"locality"
},
  "geometry": {"coordinates":[-63.65573000000001,45.39652],"type":"Point"}
}