{
  "type": "Feature",
  "properties": {
    "gn:admin1_code":"4.0",
    "gn:asciiname":"Bull Moose Hill",
    "gn:country_code":"CA",
    "gn:dem":195,
    "gn:feature_class":"P",
    "gn:feature_code":"PPL",
    "gn:name":"Bull Moose Hill",
    "gn:population":0,
    "gn:timezone":"America/Moncton",
    "iso:country":"CA",
    "wof:name":"Bull Moose Hill",
    "wof:placetype":"locality"
},
  "geometry": {"coordinates":[-65.77982,45.72851],"type":"Point"}
}