{
  "type": "Feature",
  "properties": {
    "gn:admin1_code":"7.0",
    "gn:asciiname":"West Liscomb",
    "gn:country_code":"CA",
    "gn:dem":4,
    "gn:feature_class":"P",
    "gn:feature_code":"PPL",
    "gn:name":"West Liscomb",
    "gn:population":0,
    "gn:timezone":"America/Halifax",
    "iso:country":"CA",
    "wof:name":"West Liscomb",
    "wof:placetype":"locality"
},
  "geometry": {"coordinates":[-62.09965,44.99905],"type":"Point"}
}