{
  "type": "Feature",
  "properties": {
    "iso:country":"CA",
    "name:eng_x_preferred":[
        "La Clairi\u00e8re"
    ],
    "name:fra_x_colloquial":[
        "La Clairiere"
    ],
    "name:fra_x_preferred":[
        "La Clairi\u00e8re"
    ],
    "qs:gn_adm0_cc":"CA",
    "qs:gn_local":6049863,
    "qs:gn_nam_loc":"la prairie",
    "qs:gn_namadm1":"10",
    "qs:local_max":142,
    "qs:local_sum":200,
    "qs:localhoods":3,
    "qs:name":"La Clairi\u00e8re",
    "qs:name_adm0":"Canada",
    "qs:name_adm1":"Qu\u00e9bec",
    "qs:name_adm2":"Roussillon",
    "qs:name_local":"La Prairie",
    "qs:photo_max":3,
    "qs:photo_sum":4,
    "qs:placetype":"Suburb",
    "qs:quad_count":2,
    "qs:woe_adm0":23424775,
    "qs:woe_adm1":2344924,
    "qs:woe_adm2":29375054,
    "qs:woe_lau":0,
    "qs:woe_local":821,
    "qs:woe_ver":"7.10.0",
    "wof:lang":[
        "fre"
    ],
    "wof:name":"La Clairi\u00e8re",
    "wof:placetype":"neighbourhood"
},
  "geometry": {"coordinates":[-73.468323,45.420622],"type":"Point"}
}