{
  "type": "Feature",
  "properties": {
    "gn:admin1_code":"8",
    "gn:asciiname":"Remington Park",
    "gn:country_code":"CA",
    "gn:dem":191,
    "gn:feature_class":"P",
    "gn:feature_code":"PPL",
    "gn:name":"Remington Park",
    "gn:population":0,
    "gn:timezone":"America/Toronto",
    "iso:country":"CA",
    "wof:name":"Remington Park",
    "wof:placetype":"locality"
},
  "geometry": {"coordinates":[-83.00778000000003,42.28583],"type":"Point"}
}