{
  "type": "Feature",
  "properties": {
    "gn:admin1_code":"10",
    "gn:admin2_code":"15.0",
    "gn:admin3_code":"78060.0",
    "gn:asciiname":"Morrison",
    "gn:country_code":"CA",
    "gn:dem":179,
    "gn:feature_class":"P",
    "gn:feature_code":"PPL",
    "gn:name":"Morrison",
    "gn:population":0,
    "gn:timezone":"America/Toronto",
    "iso:country":"CA",
    "name:bel_x_preferred":[
        "\u041c\u043e\u0440\u044b\u0441\u0430\u043d"
    ],
    "name:ceb_x_preferred":[
        "Morrison"
    ],
    "name:ces_x_preferred":[
        "Morrison"
    ],
    "name:deu_x_preferred":[
        "Morrison"
    ],
    "name:fin_x_preferred":[
        "Morrison"
    ],
    "name:fra_x_preferred":[
        "Morrison"
    ],
    "name:hun_x_preferred":[
        "Morrison"
    ],
    "name:ita_x_preferred":[
        "Morrison"
    ],
    "name:jpn_x_preferred":[
        "\u30e2\u30ea\u30bd\u30f3"
    ],
    "name:kor_x_preferred":[
        "\ubaa8\ub9ac\uc2a8"
    ],
    "name:lav_x_preferred":[
        "Morisons"
    ],
    "name:nld_x_preferred":[
        "Morrison"
    ],
    "name:pol_x_preferred":[
        "Morrison"
    ],
    "name:por_x_preferred":[
        "Morrison"
    ],
    "name:ron_x_preferred":[
        "Morrison"
    ],
    "name:rus_x_preferred":[
        "\u041c\u043e\u0440\u0440\u0438\u0441\u043e\u043d"
    ],
    "name:spa_x_preferred":[
        "Morrison"
    ],
    "name:swe_x_preferred":[
        "Morrison"
    ],
    "name:ukr_x_preferred":[
        "\u041c\u043e\u0440\u0440\u0456\u0441\u043e\u043d"
    ],
    "name:vie_x_preferred":[
        "Morrison"
    ],
    "name:vol_x_preferred":[
        "Morrison"
    ],
    "wof:name":"Morrison",
    "wof:placetype":"locality"
},
  "geometry": {"coordinates":[-74.58407,45.96088],"type":"Point"}
}