{
  "type": "Feature",
  "properties": {
    "gn:admin1_code":"10",
    "gn:admin2_code":"15.0",
    "gn:admin3_code":"78060.0",
    "gn:asciiname":"Morrison",
    "gn:country_code":"CA",
    "gn:dem":179,
    "gn:feature_class":"P",
    "gn:feature_code":"PPL",
    "gn:name":"Morrison",
    "gn:population":0,
    "gn:timezone":"America/Toronto",
    "iso:country":"CA",
    "wof:name":"Morrison",
    "wof:placetype":"locality"
},
  "geometry": {"coordinates":[-74.58407,45.96088],"type":"Point"}
}