{
  "type": "Feature",
  "properties": {
    "gn:admin1_code":"8",
    "gn:asciiname":"Southview Beach",
    "gn:country_code":"CA",
    "gn:dem":222,
    "gn:feature_class":"P",
    "gn:feature_code":"PPL",
    "gn:name":"Southview Beach",
    "gn:population":0,
    "gn:timezone":"America/Toronto",
    "iso:country":"CA",
    "wof:name":"Southview Beach",
    "wof:placetype":"locality"
},
  "geometry": {"coordinates":[-79.26178,44.56347],"type":"Point"}
}