{
  "type": "Feature",
  "properties": {
    "gn:admin1_code":"11",
    "gn:asciiname":"Glen Harbour",
    "gn:country_code":"CA",
    "gn:dem":486,
    "gn:feature_class":"P",
    "gn:feature_code":"PPL",
    "gn:name":"Glen Harbour",
    "gn:population":0,
    "gn:timezone":"America/Regina",
    "iso:country":"CA",
    "wof:name":"Glen Harbour",
    "wof:placetype":"locality"
},
  "geometry": {"coordinates":[-105.10113,50.88338],"type":"Point"}
}