{
  "type": "Feature",
  "properties": {
    "gn:admin1_code":"5",
    "gn:asciiname":"Loon Bay",
    "gn:country_code":"CA",
    "gn:dem":30,
    "gn:feature_class":"P",
    "gn:feature_code":"PPL",
    "gn:name":"Loon Bay",
    "gn:population":0,
    "gn:timezone":"America/St_Johns",
    "iso:country":"CA",
    "name:fra_x_preferred":[
        "Loon Bay"
    ],
    "wof:name":"Loon Bay",
    "wof:placetype":"locality"
},
  "geometry": {"coordinates":[-54.83144,49.26663],"type":"Point"}
}