{
  "type": "Feature",
  "properties": {
    "gn:admin1_code":"7.0",
    "gn:asciiname":"Beinn Scalpie",
    "gn:country_code":"CA",
    "gn:dem":238,
    "gn:feature_class":"P",
    "gn:feature_code":"PPLL",
    "gn:name":"Beinn Scalpie",
    "gn:population":0,
    "gn:timezone":"America/Halifax",
    "iso:country":"CA",
    "wof:name":"Beinn Scalpie",
    "wof:placetype":"locality"
},
  "geometry": {"coordinates":[-60.56517,46.20014000000001],"type":"Point"}
}