{
  "type": "Feature",
  "properties": {
    "gn:admin1_code":"2",
    "gn:admin2_code":"5923.0",
    "gn:asciiname":"Stewardson Inlet",
    "gn:country_code":"CA",
    "gn:dem":23,
    "gn:feature_class":"P",
    "gn:feature_code":"PPLL",
    "gn:name":"Stewardson Inlet",
    "gn:population":0,
    "gn:timezone":"America/Vancouver",
    "iso:country":"CA",
    "wof:name":"Stewardson Inlet",
    "wof:placetype":"locality"
},
  "geometry": {"coordinates":[-126.31538999999999,49.42133],"type":"Point"}
}