{
  "type": "Feature",
  "properties": {
    "gn:admin1_code":"3",
    "gn:asciiname":"Victor",
    "gn:country_code":"CA",
    "gn:dem":419,
    "gn:feature_class":"P",
    "gn:feature_code":"PPLL",
    "gn:name":"Victor",
    "gn:population":0,
    "gn:timezone":"America/Winnipeg",
    "iso:country":"CA",
    "wof:name":"Victor",
    "wof:placetype":"locality"
},
  "geometry": {"coordinates":[-101.42622,50.4564],"type":"Point"}
}