{
  "type": "Feature",
  "properties": {
    "gn:admin1_code":"1",
    "gn:asciiname":"Tennion",
    "gn:country_code":"CA",
    "gn:dem":848,
    "gn:feature_class":"P",
    "gn:feature_code":"PPLL",
    "gn:name":"Tennion",
    "gn:population":0,
    "gn:timezone":"America/Edmonton",
    "iso:country":"CA",
    "wof:name":"Tennion",
    "wof:placetype":"locality"
},
  "geometry": {"coordinates":[-112.58513000000001,49.96674],"type":"Point"}
}