{
  "type": "Feature",
  "properties": {
    "gn:admin1_code":"7",
    "gn:asciiname":"Hawker",
    "gn:country_code":"CA",
    "gn:dem":12,
    "gn:feature_class":"P",
    "gn:feature_code":"PPL",
    "gn:name":"Hawker",
    "gn:population":0,
    "gn:timezone":"America/Halifax",
    "iso:country":"CA",
    "name:ceb_x_preferred":[
        "Hawker"
    ],
    "name:deu_x_preferred":[
        "Hawker"
    ],
    "name:ita_x_preferred":[
        "Hawker"
    ],
    "name:pol_x_preferred":[
        "Hawker"
    ],
    "name:swe_x_preferred":[
        "Hawker"
    ],
    "wof:name":"Hawker",
    "wof:placetype":"locality"
},
  "geometry": {"coordinates":[-60.99325,45.63417000000001],"type":"Point"}
}