{
  "type": "Feature",
  "properties": {
    "gn:admin1_code":"8",
    "gn:asciiname":"Ladysmith",
    "gn:country_code":"CA",
    "gn:dem":188,
    "gn:feature_class":"P",
    "gn:feature_code":"PPL",
    "gn:name":"Ladysmith",
    "gn:population":0,
    "gn:timezone":"America/Toronto",
    "iso:country":"CA",
    "name:ceb_x_preferred":[
        "Ladysmith"
    ],
    "name:deu_x_preferred":[
        "Ladysmith"
    ],
    "name:fas_x_preferred":[
        "\u0644\u06cc\u062f\u06cc \u0627\u0633\u0645\u06cc\u062a"
    ],
    "name:fin_x_preferred":[
        "Ladysmith"
    ],
    "name:fra_x_preferred":[
        "Ladysmith"
    ],
    "name:hun_x_preferred":[
        "Ladysmith"
    ],
    "name:ita_x_preferred":[
        "Ladysmith"
    ],
    "name:nld_x_preferred":[
        "Ladysmith"
    ],
    "name:nor_x_preferred":[
        "Ladysmith"
    ],
    "name:swe_x_preferred":[
        "Ladysmith"
    ],
    "wof:name":"Ladysmith",
    "wof:placetype":"locality"
},
  "geometry": {"coordinates":[-82.40806000000001,42.79],"type":"Point"}
}