{
  "type": "Feature",
  "properties": {
    "gn:admin1_code":"7",
    "gn:asciiname":"Limerock",
    "gn:country_code":"CA",
    "gn:dem":66,
    "gn:feature_class":"P",
    "gn:feature_code":"PPLL",
    "gn:name":"Limerock",
    "gn:population":0,
    "gn:timezone":"America/Halifax",
    "iso:country":"CA",
    "wof:name":"Limerock",
    "wof:placetype":"locality"
},
  "geometry": {"coordinates":[-62.84865,45.55015],"type":"Point"}
}