{
  "type": "Feature",
  "properties": {
    "gn:admin1_code":"8",
    "gn:asciiname":"Poplar Lodge",
    "gn:country_code":"CA",
    "gn:dem":265,
    "gn:feature_class":"P",
    "gn:feature_code":"PPL",
    "gn:name":"Poplar Lodge",
    "gn:population":0,
    "gn:timezone":"America/Toronto",
    "iso:country":"CA",
    "wof:name":"Poplar Lodge",
    "wof:placetype":"locality"
},
  "geometry": {"coordinates":[-88.09040999999998,49.63524],"type":"Point"}
}