{
  "type": "Feature",
  "properties": {
    "gn:admin1_code":"2",
    "gn:asciiname":"Gang Ranch",
    "gn:country_code":"CA",
    "gn:dem":644,
    "gn:feature_class":"P",
    "gn:feature_code":"PPL",
    "gn:name":"Gang Ranch",
    "gn:population":0,
    "gn:timezone":"America/Vancouver",
    "iso:country":"CA",
    "wof:name":"Gang Ranch",
    "wof:placetype":"locality"
},
  "geometry": {"coordinates":[-122.33608,51.5498],"type":"Point"}
}