{
  "type": "Feature",
  "properties": {
    "gn:country":"CA",
    "gn:fcode":"PPL",
    "gn:pop":0,
    "iso:country":"CA",
    "name:eng_x_preferred":[
        "Joggins"
    ],
    "qs:name":"Joggins",
    "qs:name_adm0":"Canada",
    "qs:name_adm1":"Nova Scotia",
    "qs:photos":243,
    "qs:photos_1k":49,
    "qs:photos_9k":1,
    "qs:photos_9r":4,
    "qs:photos_all":243,
    "qs:photos_sr":4,
    "qs:placetype":"Town",
    "qs:pop_sr":"0",
    "wd:wordcount":2111,
    "wof:name":"Joggins",
    "wof:placetype":"locality",
    "wof:population":0
},
  "geometry": {"coordinates":[-64.43205,45.68345],"type":"Point"}
}