{
  "type": "Feature",
  "properties": {
    "gn:country":"CA",
    "gn:fcode":"PPL",
    "gn:population":0,
    "iso:country":"CA",
    "name:deu_x_preferred":[
        "Joggins Fossil-Klippen"
    ],
    "name:eng_x_preferred":[
        "Joggins"
    ],
    "name:gla_x_preferred":[
        "Joggins"
    ],
    "name:hrv_x_preferred":[
        "Joggins"
    ],
    "name:hun_x_preferred":[
        "Joggins"
    ],
    "name:jpn_x_preferred":[
        "\u30b8\u30e7\u30ae\u30f3\u30ba"
    ],
    "name:kat_x_preferred":[
        "\u10ef\u10dd\u10d2\u10d8\u10dc\u10e1\u10d8"
    ],
    "name:nld_x_preferred":[
        "Joggins"
    ],
    "name:pol_x_preferred":[
        "Joggins"
    ],
    "name:swe_x_preferred":[
        "Joggins"
    ],
    "name:tur_x_preferred":[
        "Joggins"
    ],
    "name:ukr_x_preferred":[
        "\u0414\u0436\u043e\u0433\u0433\u0456\u043d\u0441"
    ],
    "name:vie_x_preferred":[
        "Joggins"
    ],
    "qs:name":"Joggins",
    "qs:name_adm0":"Canada",
    "qs:name_adm1":"Nova Scotia",
    "qs:photos":243,
    "qs:photos_1k":49,
    "qs:photos_9k":1,
    "qs:photos_9r":4,
    "qs:photos_all":243,
    "qs:photos_sr":4,
    "qs:placetype":"Town",
    "qs:pop_sr":"0",
    "wd:wordcount":2111,
    "wof:name":"Joggins",
    "wof:placetype":"locality",
    "wof:population":0
},
  "geometry": {"coordinates":[-64.43205,45.68345],"type":"Point"}
}