{
  "type": "Feature",
  "properties": {
    "gn:admin1_code":"8",
    "gn:asciiname":"Guiney",
    "gn:country_code":"CA",
    "gn:dem":282,
    "gn:feature_class":"P",
    "gn:feature_code":"PPL",
    "gn:name":"Guiney",
    "gn:population":0,
    "gn:timezone":"America/Toronto",
    "iso:country":"CA",
    "name:deu_x_preferred":[
        "Guiney"
    ],
    "name:fra_x_preferred":[
        "Guiney"
    ],
    "wof:name":"Guiney",
    "wof:placetype":"locality"
},
  "geometry": {"coordinates":[-77.44,45.30639],"type":"Point"}
}