{
  "type": "Feature",
  "properties": {
    "gn:admin1_code":"8",
    "gn:asciiname":"Palmquist",
    "gn:country_code":"CA",
    "gn:dem":239,
    "gn:feature_class":"P",
    "gn:feature_code":"PPLL",
    "gn:name":"Palmquist",
    "gn:population":0,
    "gn:timezone":"America/Toronto",
    "iso:country":"CA",
    "wof:name":"Palmquist",
    "wof:placetype":"locality"
},
  "geometry": {"coordinates":[-84.54458000000002,49.79956],"type":"Point"}
}