{
  "type": "Feature",
  "properties": {
    "gn:admin1_code":"8",
    "gn:asciiname":"Temagami North",
    "gn:country_code":"CA",
    "gn:dem":304,
    "gn:feature_class":"P",
    "gn:feature_code":"PPL",
    "gn:name":"Temagami North",
    "gn:population":0,
    "gn:timezone":"America/Toronto",
    "iso:country":"CA",
    "wof:name":"Temagami North",
    "wof:placetype":"locality"
},
  "geometry": {"coordinates":[-79.79000000000001,47.11194],"type":"Point"}
}