{
  "type": "Feature",
  "properties": {
    "gn:admin1_code":"3",
    "gn:asciiname":"Novra",
    "gn:country_code":"CA",
    "gn:dem":329,
    "gn:feature_class":"P",
    "gn:feature_code":"PPLL",
    "gn:name":"Novra",
    "gn:population":0,
    "gn:timezone":"America/Winnipeg",
    "iso:country":"CA",
    "wof:name":"Novra",
    "wof:placetype":"locality"
},
  "geometry": {"coordinates":[-101.07308,52.52894000000001],"type":"Point"}
}