{
  "type": "Feature",
  "properties": {
    "gn:admin1_code":"8",
    "gn:asciiname":"Sherwood Forrest",
    "gn:country_code":"CA",
    "gn:dem":120,
    "gn:feature_class":"P",
    "gn:feature_code":"PPL",
    "gn:name":"Sherwood Forrest",
    "gn:population":0,
    "gn:timezone":"America/Toronto",
    "iso:country":"CA",
    "wof:name":"Sherwood Forrest",
    "wof:placetype":"locality"
},
  "geometry": {"coordinates":[-79.65912,43.53754],"type":"Point"}
}