{
  "type": "Feature",
  "properties": {
    "iso:country":"CA",
    "name:eng_x_preferred":[
        "Otonabee"
    ],
    "qs:gn_adm0_cc":"CA",
    "qs:gn_local":6101645,
    "qs:gn_nam_loc":"peterborough",
    "qs:gn_namadm1":"08",
    "qs:local_max":3171,
    "qs:local_sum":5857,
    "qs:localhoods":5,
    "qs:name":"Otonabee",
    "qs:name_adm0":"Canada",
    "qs:name_adm1":"Ontario",
    "qs:name_adm2":"Peterborough",
    "qs:name_local":"Peterborough",
    "qs:photo_max":18,
    "qs:photo_sum":138,
    "qs:placetype":"Suburb",
    "qs:quad_count":35,
    "qs:woe_adm0":23424775,
    "qs:woe_adm1":2344922,
    "qs:woe_adm2":29375059,
    "qs:woe_lau":0,
    "qs:woe_local":4100,
    "qs:woe_ver":"7.10.0",
    "wof:lang":[
        "eng"
    ],
    "wof:name":"Otonabee",
    "wof:placetype":"neighbourhood"
},
  "geometry": {"coordinates":[-78.35021500000001,44.272175],"type":"Point"}
}