{
  "type": "Feature",
  "properties": {
    "gn:admin1_code":"9",
    "gn:admin2_code":"1102",
    "gn:asciiname":"Royalty Junction",
    "gn:country_code":"CA",
    "gn:dem":51,
    "gn:feature_class":"P",
    "gn:feature_code":"PPLL",
    "gn:name":"Royalty Junction",
    "gn:population":0,
    "gn:timezone":"America/Halifax",
    "iso:country":"CA",
    "wof:name":"Royalty Junction",
    "wof:placetype":"locality"
},
  "geometry": {"coordinates":[-63.1422,46.29642],"type":"Point"}
}