{
  "type": "Feature",
  "properties": {
    "gn:admin1_code":"2",
    "gn:asciiname":"Ocean Park",
    "gn:country_code":"CA",
    "gn:dem":78,
    "gn:feature_class":"P",
    "gn:feature_code":"PPL",
    "gn:name":"Ocean Park",
    "gn:population":0,
    "gn:timezone":"America/Vancouver",
    "iso:country":"CA",
    "wof:name":"Ocean Park",
    "wof:placetype":"locality"
},
  "geometry": {"coordinates":[-122.86667,49.03333],"type":"Point"}
}