{
  "type": "Feature",
  "properties": {
    "iso:country":"CA",
    "name:ceb_x_preferred":[
        "Thomasburg"
    ],
    "name:dan_x_preferred":[
        "Thomasburg"
    ],
    "name:deu_x_preferred":[
        "Thomasburg"
    ],
    "name:epo_x_preferred":[
        "Thomasburg"
    ],
    "name:est_x_preferred":[
        "Thomasburg"
    ],
    "name:eus_x_preferred":[
        "Thomasburg"
    ],
    "name:fas_x_preferred":[
        "\u062a\u0648\u0645\u0627\u0633\u0628\u0648\u0631\u06af"
    ],
    "name:fra_x_preferred":[
        "Thomasburg"
    ],
    "name:hun_x_preferred":[
        "Thomasburg"
    ],
    "name:ita_x_preferred":[
        "Thomasburg"
    ],
    "name:kaz_x_preferred":[
        "\u0422\u043e\u043c\u0430\u0441\u0431\u0443\u0440\u0433"
    ],
    "name:kir_x_preferred":[
        "\u0422\u043e\u043c\u0430\u0441\u0431\u0443\u0440\u0433"
    ],
    "name:lat_x_preferred":[
        "Thomasburg"
    ],
    "name:msa_x_preferred":[
        "Thomasburg"
    ],
    "name:nld_x_preferred":[
        "Thomasburg"
    ],
    "name:pol_x_preferred":[
        "Thomasburg"
    ],
    "name:por_x_preferred":[
        "Thomasburg"
    ],
    "name:ron_x_preferred":[
        "Thomasburg"
    ],
    "name:rus_x_preferred":[
        "\u0422\u043e\u043c\u0430\u0441\u0431\u0443\u0440\u0433"
    ],
    "name:spa_x_preferred":[
        "Thomasburg"
    ],
    "name:srp_x_preferred":[
        "\u0422\u043e\u043c\u0430\u0441\u0431\u0443\u0440\u0433"
    ],
    "name:ukr_x_preferred":[
        "\u0422\u043e\u043c\u0430\u0441\u0431\u0443\u0440\u0433"
    ],
    "name:uzb_x_preferred":[
        "Thomasburg"
    ],
    "name:vie_x_preferred":[
        "Thomasburg"
    ],
    "name:vol_x_preferred":[
        "Thomasburg"
    ],
    "name:war_x_preferred":[
        "Thomasburg"
    ],
    "name:zho_x_preferred":[
        "\u6258\u9a6c\u65af\u5821"
    ],
    "qs_pg:aaroncc":"CA",
    "qs_pg:name":"Thomasburg",
    "qs_pg:name_adm0":"Canada",
    "qs_pg:name_adm1":"Ontario",
    "qs_pg:photos":139,
    "qs_pg:photos_1k":28,
    "qs_pg:photos_9k":1,
    "qs_pg:photos_9r":3,
    "qs_pg:photos_all":139,
    "qs_pg:photos_sr":3,
    "qs_pg:pop_sr":0,
    "qs_pg:qs_pg_placetype":"locality",
    "qs_pg:qs_pg_placetype_gp":"Town",
    "qs_pg:woe_adm0":23424775,
    "woe:adm0_id":23424775,
    "woe:name_adm0":"Canada",
    "woe:name_adm1":"Ontario",
    "woe:placetype":"Town",
    "wof:name":"Thomasburg",
    "wof:placetype":"locality"
},
  "geometry": {"coordinates":[-77.31306499999999,44.403089],"type":"Point"}
}