{
  "type": "Feature",
  "properties": {
    "gn:admin1_code":"11.0",
    "gn:asciiname":"Bayard",
    "gn:country_code":"CA",
    "gn:dem":662,
    "gn:feature_class":"P",
    "gn:feature_code":"PPLL",
    "gn:name":"Bayard",
    "gn:population":0,
    "gn:timezone":"America/Regina",
    "iso:country":"CA",
    "wof:name":"Bayard",
    "wof:placetype":"locality"
},
  "geometry": {"coordinates":[-105.28442,50.01676],"type":"Point"}
}