{
  "type": "Feature",
  "properties": {
    "iso:country":"CA",
    "name:eng_x_preferred":[
        "Welham"
    ],
    "name:pol_x_preferred":[
        "Welham"
    ],
    "qs:gn_adm0_cc":"CA",
    "qs:gn_local":5894171,
    "qs:gn_nam_loc":"barrie",
    "qs:gn_namadm1":"08",
    "qs:local_max":3173,
    "qs:local_sum":6611,
    "qs:localhoods":14,
    "qs:name":"Welham",
    "qs:name_adm0":"Canada",
    "qs:name_adm1":"Ontario",
    "qs:name_adm2":"Simcoe",
    "qs:name_local":"Barrie",
    "qs:photo_max":124,
    "qs:photo_sum":253,
    "qs:placetype":"Suburb",
    "qs:quad_count":9,
    "qs:woe_adm0":23424775,
    "qs:woe_adm1":2344922,
    "qs:woe_adm2":29375066,
    "qs:woe_funk":"Parented by a neighborhood",
    "qs:woe_lau":0,
    "qs:woe_local":4097,
    "qs:woe_ver":"7.10.0",
    "wd:wordcount":54,
    "wof:lang":[
        "eng"
    ],
    "wof:name":"Welham",
    "wof:placetype":"neighbourhood"
},
  "geometry": {"coordinates":[-79.67723599999999,44.340429],"type":"Point"}
}