{
  "type": "Feature",
  "properties": {
    "gn:admin1_code":"8.0",
    "gn:asciiname":"Windy Point",
    "gn:country_code":"CA",
    "gn:dem":339,
    "gn:feature_class":"P",
    "gn:feature_code":"PPL",
    "gn:name":"Windy Point",
    "gn:population":0,
    "gn:timezone":"America/Winnipeg",
    "iso:country":"CA",
    "wof:name":"Windy Point",
    "wof:placetype":"locality"
},
  "geometry": {"coordinates":[-93.18792000000001,48.68822],"type":"Point"}
}