{
  "type": "Feature",
  "properties": {
    "gn:country":"CA",
    "gn:fcode":"PPL",
    "gn:population":0,
    "iso:country":"CA",
    "name:ara_x_preferred":[
        "\u0633\u0627\u064a\u0646\u062a \u0623\u0646\u062a\u0648\u0646\u064a"
    ],
    "name:arz_x_preferred":[
        "\u0633\u0627\u064a\u0646\u062a \u0627\u0646\u062a\u0648\u0646\u0649"
    ],
    "name:ceb_x_preferred":[
        "Saint-Antoine"
    ],
    "name:eng_x_preferred":[
        "Saint-Antoine"
    ],
    "name:fas_x_preferred":[
        "\u0633\u0646\u062a \u0627\u0646\u062a\u0648\u0627\u0646"
    ],
    "name:fra_x_preferred":[
        "Saint-Antoine"
    ],
    "name:ita_x_preferred":[
        "Saint-Antoine"
    ],
    "name:nld_x_preferred":[
        "Saint-Antoine"
    ],
    "name:rus_x_preferred":[
        "\u0421\u0435\u043d-\u0410\u043d\u0442\u0443\u0430\u043d"
    ],
    "name:swe_x_preferred":[
        "Saint-Antoine"
    ],
    "name:ukr_x_preferred":[
        "\u0421\u0435\u043d-\u0410\u043d\u0442\u0443\u0430\u043d"
    ],
    "name:urd_x_preferred":[
        "\u0633\u06cc\u0646\u0679-\u0627\u0646\u062a\u0648\u06cc\u0646\u06d2\u060c \u0646\u06cc\u0648 \u0628\u0631\u0646\u0633\u0648\u06a9"
    ],
    "name:urd_x_variant":[
        "\u0633\u06cc\u0646\u0679-\u0627\u0646\u062a\u0648\u06cc\u0646\u06d2"
    ],
    "qs_pg:aaroncc":"CA",
    "qs_pg:gn_country":"CA",
    "qs_pg:gn_fcode":"PPL",
    "qs_pg:gn_pop":0,
    "qs_pg:name":"St.-Antoine",
    "qs_pg:name_adm0":"Canada",
    "qs_pg:name_adm1":"New Brunswick",
    "qs_pg:photos_9k":1,
    "qs_pg:photos_9r":1,
    "qs_pg:photos_all":3,
    "qs_pg:photos_sr":0,
    "qs_pg:pop_sr":0,
    "qs_pg:qs_pg_placetype":"locality",
    "qs_pg:qs_pg_placetype_gp":"Town",
    "qs_pg:woe_adm0":23424775,
    "woe:adm0_id":23424775,
    "woe:name_adm0":"Canada",
    "woe:name_adm1":"New Brunswick",
    "woe:placetype":"Town",
    "wof:name":"St.-Antoine",
    "wof:placetype":"locality"
},
  "geometry": {"coordinates":[-64.74985,46.36294],"type":"Point"}
}