{
  "type": "Feature",
  "properties": {
    "gn:admin1_code":"11.0",
    "gn:asciiname":"Zeneta",
    "gn:country_code":"CA",
    "gn:dem":525,
    "gn:feature_class":"P",
    "gn:feature_code":"PPL",
    "gn:name":"Zeneta",
    "gn:population":0,
    "gn:timezone":"America/Regina",
    "iso:country":"CA",
    "wof:name":"Zeneta",
    "wof:placetype":"locality"
},
  "geometry": {"coordinates":[-102.06713999999999,50.73334000000001],"type":"Point"}
}