{
  "type": "Feature",
  "properties": {
    "gn:admin1_code":"10",
    "gn:admin2_code":"15.0",
    "gn:admin3_code":"77065.0",
    "gn:asciiname":"Lac-Vingt-Sous",
    "gn:country_code":"CA",
    "gn:dem":447,
    "gn:feature_class":"P",
    "gn:feature_code":"PPL",
    "gn:name":"Lac-Vingt-Sous",
    "gn:population":0,
    "gn:timezone":"America/Toronto",
    "iso:country":"CA",
    "wof:name":"Lac-Vingt-Sous",
    "wof:placetype":"locality"
},
  "geometry": {"coordinates":[-74.36906,45.94977],"type":"Point"}
}