{
  "type": "Feature",
  "properties": {
    "iso:country":"CA",
    "name:eng_x_preferred":[
        "Downtown Stouffville"
    ],
    "qs:gn_adm0_cc":"CA",
    "qs:gn_local":6157718,
    "qs:gn_nam_loc":"stouffville",
    "qs:gn_namadm1":"08",
    "qs:local_max":593,
    "qs:local_sum":932,
    "qs:localhoods":4,
    "qs:name":"Downtown Stouffville",
    "qs:name_adm0":"Canada",
    "qs:name_adm1":"Ontario",
    "qs:name_adm2":"York",
    "qs:name_local":"Stouffville",
    "qs:photo_max":49,
    "qs:photo_sum":163,
    "qs:placetype":"Suburb",
    "qs:quad_count":19,
    "qs:woe_adm0":23424775,
    "qs:woe_adm1":2344922,
    "qs:woe_adm2":29375112,
    "qs:woe_lau":0,
    "qs:woe_local":1761,
    "qs:woe_ver":"7.10.0",
    "wof:lang":[
        "eng"
    ],
    "wof:name":"Downtown Stouffville",
    "wof:placetype":"neighbourhood"
},
  "geometry": {"coordinates":[-79.250196,43.973967],"type":"Point"}
}