{
  "type": "Feature",
  "properties": {
    "gn:admin1_code":"11",
    "gn:asciiname":"Foeda",
    "gn:country_code":"CA",
    "gn:dem":577,
    "gn:feature_class":"P",
    "gn:feature_code":"PPLL",
    "gn:name":"Foeda",
    "gn:population":0,
    "gn:timezone":"America/Regina",
    "iso:country":"CA",
    "wof:name":"Foeda",
    "wof:placetype":"locality"
},
  "geometry": {"coordinates":[-102.81761,49.15007],"type":"Point"}
}