{
  "type": "Feature",
  "properties": {
    "gn:admin1_code":"8",
    "gn:asciiname":"Minto",
    "gn:country_code":"CA",
    "gn:dem":179,
    "gn:feature_class":"P",
    "gn:feature_code":"PPL",
    "gn:name":"Minto",
    "gn:population":0,
    "gn:timezone":"America/Toronto",
    "iso:country":"CA",
    "name:ceb_x_preferred":[
        "Minto"
    ],
    "name:deu_x_preferred":[
        "Minto"
    ],
    "name:fra_x_preferred":[
        "Minto"
    ],
    "name:ita_x_preferred":[
        "Minto"
    ],
    "name:nld_x_preferred":[
        "Minto"
    ],
    "name:pol_x_preferred":[
        "Minto"
    ],
    "name:por_x_preferred":[
        "Minto"
    ],
    "name:rus_x_preferred":[
        "\u041c\u0438\u043d\u0442\u043e"
    ],
    "name:srp_x_preferred":[
        "\u041c\u0438\u043d\u0442\u043e"
    ],
    "name:swe_x_preferred":[
        "Minto"
    ],
    "name:ukr_x_preferred":[
        "\u041c\u0456\u043d\u0442\u043e"
    ],
    "name:vol_x_preferred":[
        "Minto"
    ],
    "wof:name":"Minto",
    "wof:placetype":"locality"
},
  "geometry": {"coordinates":[-77.5438,44.36377],"type":"Point"}
}