{
  "type": "Feature",
  "properties": {
    "gn:admin1_code":"10",
    "gn:admin2_code":"5.0",
    "gn:admin3_code":"44037.0",
    "gn:asciiname":"Stanhope",
    "gn:country_code":"CA",
    "gn:dem":398,
    "gn:feature_class":"P",
    "gn:feature_code":"PPL",
    "gn:name":"Stanhope",
    "gn:population":0,
    "gn:timezone":"America/Toronto",
    "iso:country":"CA",
    "name:ceb_x_preferred":[
        "Stanhope"
    ],
    "name:deu_x_preferred":[
        "Stanhope"
    ],
    "name:fin_x_preferred":[
        "Stanhope"
    ],
    "name:fra_x_preferred":[
        "Stanhope"
    ],
    "name:ita_x_preferred":[
        "Stanhope"
    ],
    "name:nld_x_preferred":[
        "Stanhope"
    ],
    "name:pol_x_preferred":[
        "Stanhope"
    ],
    "name:por_x_preferred":[
        "Stanhope"
    ],
    "name:rus_x_preferred":[
        "\u0421\u0442\u044d\u043d\u0445\u043e\u0443\u043f"
    ],
    "name:spa_x_preferred":[
        "Stanhope"
    ],
    "name:srp_x_preferred":[
        "\u0421\u0442\u0430\u043d\u0445\u043e\u043f"
    ],
    "name:swe_x_preferred":[
        "Stanhope"
    ],
    "name:vol_x_preferred":[
        "Stanhope"
    ],
    "wof:name":"Stanhope",
    "wof:placetype":"locality"
},
  "geometry": {"coordinates":[-71.79898,45.01254],"type":"Point"}
}