{
  "type": "Feature",
  "properties": {
    "gn:admin1_code":"10",
    "gn:admin2_code":"5.0",
    "gn:admin3_code":"44037.0",
    "gn:asciiname":"Stanhope",
    "gn:country_code":"CA",
    "gn:dem":398,
    "gn:feature_class":"P",
    "gn:feature_code":"PPL",
    "gn:name":"Stanhope",
    "gn:population":0,
    "gn:timezone":"America/Toronto",
    "iso:country":"CA",
    "wof:name":"Stanhope",
    "wof:placetype":"locality"
},
  "geometry": {"coordinates":[-71.79898,45.01254],"type":"Point"}
}