{
  "type": "Feature",
  "properties": {
    "gn:country":"CA",
    "iso:country":"CA",
    "name:ceb_x_preferred":[
        "Pleasant Bay"
    ],
    "name:eng_x_preferred":[
        "Pleasant Bay"
    ],
    "name:fra_x_preferred":[
        "Pleasant Bay"
    ],
    "name:nld_x_preferred":[
        "Pleasant Bay"
    ],
    "name:swe_x_preferred":[
        "Pleasant Bay"
    ],
    "qs:name":"Pleasant Bay",
    "qs:name_adm0":"Canada",
    "qs:name_adm1":"Nova Scotia",
    "qs:photos":673,
    "qs:photos_1k":136,
    "qs:photos_9k":3,
    "qs:photos_9r":5,
    "qs:photos_all":673,
    "qs:photos_sr":8,
    "qs:placetype":"Town",
    "qs:pop_sr":"0",
    "wd:wordcount":23,
    "wof:name":"Pleasant Bay",
    "wof:placetype":"locality"
},
  "geometry": {"coordinates":[-60.829925,46.822557],"type":"Point"}
}