{
  "type": "Feature",
  "properties": {
    "gn:admin1_code":"8",
    "gn:asciiname":"Moraviantown",
    "gn:country_code":"CA",
    "gn:dem":193,
    "gn:feature_class":"P",
    "gn:feature_code":"PPL",
    "gn:name":"Moraviantown",
    "gn:population":0,
    "gn:timezone":"America/Toronto",
    "iso:country":"CA",
    "wof:name":"Moraviantown",
    "wof:placetype":"locality"
},
  "geometry": {"coordinates":[-81.89354,42.58097],"type":"Point"}
}