{
  "type": "Feature",
  "properties": {
    "gn:admin1_code":"8.0",
    "gn:asciiname":"Eastbourne",
    "gn:country_code":"CA",
    "gn:dem":225,
    "gn:feature_class":"P",
    "gn:feature_code":"PPL",
    "gn:name":"Eastbourne",
    "gn:population":0,
    "gn:timezone":"America/Toronto",
    "iso:country":"CA",
    "wof:name":"Eastbourne",
    "wof:placetype":"locality"
},
  "geometry": {"coordinates":[-79.4832,44.29403],"type":"Point"}
}