{
  "type": "Feature",
  "properties": {
    "gn:admin1_code":"8",
    "gn:asciiname":"Rocher Fendu",
    "gn:country_code":"CA",
    "gn:dem":120,
    "gn:feature_class":"P",
    "gn:feature_code":"PPL",
    "gn:name":"Rocher Fendu",
    "gn:population":0,
    "gn:timezone":"America/Toronto",
    "iso:country":"CA",
    "wof:name":"Rocher Fendu",
    "wof:placetype":"locality"
},
  "geometry": {"coordinates":[-76.79599,45.75086],"type":"Point"}
}