{
  "type": "Feature",
  "properties": {
    "gn:admin1_code":"2",
    "gn:asciiname":"McLean Ranch",
    "gn:country_code":"CA",
    "gn:dem":689,
    "gn:feature_class":"P",
    "gn:feature_code":"PPLL",
    "gn:name":"McLean Ranch",
    "gn:population":0,
    "gn:timezone":"America/Dawson_Creek",
    "iso:country":"CA",
    "wof:name":"McLean Ranch",
    "wof:placetype":"locality"
},
  "geometry": {"coordinates":[-122.15300999999999,56.51656],"type":"Point"}
}