{
  "type": "Feature",
  "properties": {
    "gn:admin1_code":"4.0",
    "gn:asciiname":"New Bandon",
    "gn:country_code":"CA",
    "gn:dem":136,
    "gn:feature_class":"P",
    "gn:feature_code":"PPL",
    "gn:name":"New Bandon",
    "gn:population":0,
    "gn:timezone":"America/Moncton",
    "iso:country":"CA",
    "wof:name":"New Bandon",
    "wof:placetype":"locality"
},
  "geometry": {"coordinates":[-66.24919,46.50064],"type":"Point"}
}