{
  "type": "Feature",
  "properties": {
    "gn:admin1_code":"7.0",
    "gn:asciiname":"West Jeddore",
    "gn:country_code":"CA",
    "gn:dem":8,
    "gn:feature_class":"P",
    "gn:feature_code":"PPL",
    "gn:name":"West Jeddore",
    "gn:population":0,
    "gn:timezone":"America/Halifax",
    "iso:country":"CA",
    "wof:name":"West Jeddore",
    "wof:placetype":"locality"
},
  "geometry": {"coordinates":[-63.01504,44.72618],"type":"Point"}
}