{
  "type": "Feature",
  "properties": {
    "gn:admin1_code":"4",
    "gn:asciiname":"Grande-Aldouane",
    "gn:country_code":"CA",
    "gn:dem":4,
    "gn:feature_class":"P",
    "gn:feature_code":"PPL",
    "gn:name":"Grande-Aldouane",
    "gn:population":0,
    "gn:timezone":"America/Moncton",
    "iso:country":"CA",
    "wof:name":"Grande-Aldouane",
    "wof:placetype":"locality"
},
  "geometry": {"coordinates":[-64.92788,46.71167],"type":"Point"}
}