{
  "type": "Feature",
  "properties": {
    "gn:admin1_code":"10.0",
    "gn:admin2_code":"16.0",
    "gn:asciiname":"Domaine-Richard",
    "gn:country_code":"CA",
    "gn:dem":121,
    "gn:feature_class":"P",
    "gn:feature_code":"PPL",
    "gn:name":"Domaine-Richard",
    "gn:population":0,
    "gn:timezone":"America/Toronto",
    "iso:country":"CA",
    "wof:name":"Domaine-Richard",
    "wof:placetype":"locality"
},
  "geometry": {"coordinates":[-72.71873000000002,45.44087],"type":"Point"}
}