{
  "type": "Feature",
  "properties": {
    "gn:admin1_code":"8",
    "gn:asciiname":"Point Abino",
    "gn:country_code":"CA",
    "gn:dem":180,
    "gn:feature_class":"P",
    "gn:feature_code":"PPL",
    "gn:name":"Point Abino",
    "gn:population":0,
    "gn:timezone":"America/Toronto",
    "iso:country":"CA",
    "wof:name":"Point Abino",
    "wof:placetype":"locality"
},
  "geometry": {"coordinates":[-79.10250000000001,42.85556],"type":"Point"}
}