{
  "type": "Feature",
  "properties": {
    "gn:admin1_code":"2",
    "gn:asciiname":"Mud Bay",
    "gn:country_code":"CA",
    "gn:dem":26,
    "gn:feature_class":"P",
    "gn:feature_code":"PPLL",
    "gn:name":"Mud Bay",
    "gn:population":0,
    "gn:timezone":"America/Vancouver",
    "iso:country":"CA",
    "name:ceb_x_preferred":[
        "Mud Bay"
    ],
    "name:swe_x_preferred":[
        "Mud Bay"
    ],
    "wof:name":"Mud Bay",
    "wof:placetype":"locality"
},
  "geometry": {"coordinates":[-122.88591,49.09966],"type":"Point"}
}