{
  "type": "Feature",
  "properties": {
    "gn:admin1_code":"4",
    "gn:asciiname":"Spring Brook",
    "gn:country_code":"CA",
    "gn:dem":21,
    "gn:feature_class":"P",
    "gn:feature_code":"PPL",
    "gn:name":"Spring Brook",
    "gn:population":0,
    "gn:timezone":"America/Moncton",
    "iso:country":"CA",
    "name:ceb_x_preferred":[
        "Spring Brook"
    ],
    "name:deu_x_preferred":[
        "Spring Brook"
    ],
    "name:ita_x_preferred":[
        "Spring Brook"
    ],
    "name:pol_x_preferred":[
        "Spring Brook"
    ],
    "name:swe_x_preferred":[
        "Spring Brook"
    ],
    "wof:name":"Spring Brook",
    "wof:placetype":"locality"
},
  "geometry": {"coordinates":[-64.88242,46.51600000000001],"type":"Point"}
}