{
  "type": "Feature",
  "properties": {
    "gn:admin1_code":"8",
    "gn:asciiname":"Glen Buell",
    "gn:country_code":"CA",
    "gn:dem":126,
    "gn:feature_class":"P",
    "gn:feature_code":"PPL",
    "gn:name":"Glen Buell",
    "gn:population":0,
    "gn:timezone":"America/Toronto",
    "iso:country":"CA",
    "wof:name":"Glen Buell",
    "wof:placetype":"locality"
},
  "geometry": {"coordinates":[-75.84936,44.63341],"type":"Point"}
}