{
  "type": "Feature",
  "properties": {
    "gn:admin1_code":"10",
    "gn:admin2_code":"15.0",
    "gn:admin3_code":"79088.0",
    "gn:asciiname":"Navarre",
    "gn:country_code":"CA",
    "gn:dem":213,
    "gn:feature_class":"P",
    "gn:feature_code":"PPL",
    "gn:name":"Navarre",
    "gn:population":0,
    "gn:timezone":"America/Toronto",
    "iso:country":"CA",
    "wof:name":"Navarre",
    "wof:placetype":"locality"
},
  "geometry": {"coordinates":[-75.56361,46.50667],"type":"Point"}
}