{
  "type": "Feature",
  "properties": {
    "gn:admin1_code":"3.0",
    "gn:asciiname":"Bender",
    "gn:country_code":"CA",
    "gn:dem":278,
    "gn:feature_class":"P",
    "gn:feature_code":"PPLL",
    "gn:name":"Bender",
    "gn:population":0,
    "gn:timezone":"America/Winnipeg",
    "iso:country":"CA",
    "name:aze_x_preferred":[
        "B\u0259nd\u0259r"
    ],
    "name:ceb_x_preferred":[
        "Bender"
    ],
    "name:ces_x_preferred":[
        "Bender"
    ],
    "name:deu_x_preferred":[
        "Bender"
    ],
    "name:eus_x_preferred":[
        "Bender"
    ],
    "name:fin_x_preferred":[
        "Bender"
    ],
    "name:fra_x_preferred":[
        "Bender"
    ],
    "name:heb_x_preferred":[
        "\u05d1\u05e0\u05d3\u05e8"
    ],
    "name:ita_x_preferred":[
        "Bender"
    ],
    "name:nld_x_preferred":[
        "Bender"
    ],
    "name:nor_x_preferred":[
        "Bender"
    ],
    "name:pol_x_preferred":[
        "Bender"
    ],
    "name:por_x_preferred":[
        "Bender"
    ],
    "name:rus_x_preferred":[
        "\u0411\u0435\u043d\u0434\u0435\u0440"
    ],
    "name:spa_x_preferred":[
        "Bender"
    ],
    "name:swe_x_preferred":[
        "Bender"
    ],
    "name:ukr_x_preferred":[
        "\u0411\u0435\u043d\u0434\u0435\u0440"
    ],
    "wof:name":"Bender",
    "wof:placetype":"locality"
},
  "geometry": {"coordinates":[-97.47958,50.68421],"type":"Point"}
}