{
  "type": "Feature",
  "properties": {
    "gn:admin1_code":"3.0",
    "gn:asciiname":"Bender",
    "gn:country_code":"CA",
    "gn:dem":278,
    "gn:feature_class":"P",
    "gn:feature_code":"PPLL",
    "gn:name":"Bender",
    "gn:population":0,
    "gn:timezone":"America/Winnipeg",
    "iso:country":"CA",
    "wof:name":"Bender",
    "wof:placetype":"locality"
},
  "geometry": {"coordinates":[-97.47958,50.68421],"type":"Point"}
}