{
  "type": "Feature",
  "properties": {
    "gn:admin1_code":"4",
    "gn:asciiname":"Salina",
    "gn:country_code":"CA",
    "gn:dem":112,
    "gn:feature_class":"P",
    "gn:feature_code":"PPL",
    "gn:name":"Salina",
    "gn:population":0,
    "gn:timezone":"America/Moncton",
    "iso:country":"CA",
    "name:arg_x_preferred":[
        "Salina"
    ],
    "name:ben_x_preferred":[
        "\u09b8\u09cd\u09af\u09be\u09b2\u09bf\u09a8\u09be"
    ],
    "name:cat_x_preferred":[
        "Salina"
    ],
    "name:ceb_x_preferred":[
        "Salina"
    ],
    "name:ces_x_preferred":[
        "Salina"
    ],
    "name:deu_x_preferred":[
        "Salina"
    ],
    "name:eus_x_preferred":[
        "Salina"
    ],
    "name:fra_x_preferred":[
        "Salina"
    ],
    "name:heb_x_preferred":[
        "\u05e1\u05dc\u05d9\u05e0\u05d4"
    ],
    "name:hin_x_preferred":[
        "\u0938\u0932\u0940\u0928\u093e"
    ],
    "name:ind_x_preferred":[
        "Salina"
    ],
    "name:ita_x_preferred":[
        "Salina"
    ],
    "name:kor_x_preferred":[
        "\uc124\ub77c\uc774\ub098"
    ],
    "name:nld_x_preferred":[
        "Salina"
    ],
    "name:pol_x_preferred":[
        "Salina"
    ],
    "name:por_x_preferred":[
        "Salina"
    ],
    "name:rus_x_preferred":[
        "\u0421\u0430\u043b\u0438\u043d\u0430"
    ],
    "name:spa_x_preferred":[
        "Salina"
    ],
    "name:srp_x_preferred":[
        "\u0421\u0430\u043b\u0430\u0458\u043d\u0430"
    ],
    "name:swe_x_preferred":[
        "Salina"
    ],
    "name:ukr_x_preferred":[
        "\u0421\u0430\u043b\u0456\u043d\u0430"
    ],
    "name:urd_x_preferred":[
        "\u0633\u06cc\u0644\u0627\u0626\u0646\u0627"
    ],
    "name:vol_x_preferred":[
        "Salina"
    ],
    "wof:name":"Salina",
    "wof:placetype":"locality"
},
  "geometry": {"coordinates":[-65.70547999999999,45.52841],"type":"Point"}
}