{
  "type": "Feature",
  "properties": {
    "iso:country":"CA",
    "name:eng_x_preferred":[
        "Darwell"
    ],
    "name:nld_x_preferred":[
        "Darwell"
    ],
    "qs:name":"Darwell",
    "qs:name_adm0":"Canada",
    "qs:name_adm1":"Alberta",
    "qs:photos":40,
    "qs:photos_1k":8,
    "qs:photos_9k":1,
    "qs:photos_9r":2,
    "qs:photos_all":40,
    "qs:photos_sr":2,
    "qs:placetype":"Town",
    "qs:pop_sr":"0",
    "wof:name":"Darwell",
    "wof:placetype":"locality"
},
  "geometry": {"coordinates":[-114.55890599999999,53.681029],"type":"Point"}
}