{
  "type": "Feature",
  "properties": {
    "gn:admin1_code":"10",
    "gn:admin2_code":"7.0",
    "gn:admin3_code":"81017.0",
    "gn:asciiname":"Parc-Champlain",
    "gn:country_code":"CA",
    "gn:dem":93,
    "gn:feature_class":"P",
    "gn:feature_code":"PPL",
    "gn:name":"Parc-Champlain",
    "gn:population":0,
    "gn:timezone":"America/Toronto",
    "iso:country":"CA",
    "wof:name":"Parc-Champlain",
    "wof:placetype":"locality"
},
  "geometry": {"coordinates":[-75.79161999999999,45.42033],"type":"Point"}
}