{
  "type": "Feature",
  "properties": {
    "gn:admin1_code":"1.0",
    "gn:asciiname":"Derwent",
    "gn:country_code":"CA",
    "gn:dem":611,
    "gn:feature_class":"P",
    "gn:feature_code":"PPL",
    "gn:name":"Derwent",
    "gn:population":0,
    "gn:timezone":"America/Edmonton",
    "iso:country":"CA",
    "name:nld_x_preferred":[
        "Derwent"
    ],
    "wof:name":"Derwent",
    "wof:placetype":"locality"
},
  "geometry": {"coordinates":[-110.96841000000001,53.65016],"type":"Point"}
}