{
  "type": "Feature",
  "properties": {
    "gn:admin1_code":"1.0",
    "gn:asciiname":"Derwent",
    "gn:country_code":"CA",
    "gn:dem":611,
    "gn:feature_class":"P",
    "gn:feature_code":"PPL",
    "gn:name":"Derwent",
    "gn:population":0,
    "gn:timezone":"America/Edmonton",
    "iso:country":"CA",
    "name:ara_x_preferred":[
        "\u062f\u0631\u0648\u0646\u062a"
    ],
    "name:ben_x_preferred":[
        "\u09a6\u09c7\u09b0\u09cb\u09df\u09c7\u09a8\u09cd\u099f"
    ],
    "name:ell_x_preferred":[
        "\u039d\u03c4\u03ad\u03c1\u03b3\u03bf\u03c5\u03b5\u03bd\u03c4"
    ],
    "name:fas_x_preferred":[
        "\u062f\u0631\u0648\u0646\u062a"
    ],
    "name:hin_x_preferred":[
        "\u0921\u0947\u0930\u0935\u0947\u0902\u091f"
    ],
    "name:hun_x_preferred":[
        "Derwent"
    ],
    "name:ind_x_preferred":[
        "Derwent"
    ],
    "name:nld_x_preferred":[
        "Derwent"
    ],
    "name:tur_x_preferred":[
        "Derwent"
    ],
    "name:urd_x_preferred":[
        "\u0688\u0631\u0648\u06cc\u0646\u0679"
    ],
    "name:vie_x_preferred":[
        "S\u00f4ng Derwent"
    ],
    "wof:name":"Derwent",
    "wof:placetype":"locality"
},
  "geometry": {"coordinates":[-110.96841000000001,53.65016],"type":"Point"}
}