{
  "type": "Feature",
  "properties": {
    "gn:admin1_code":"7.0",
    "gn:asciiname":"Coffinscroft",
    "gn:country_code":"CA",
    "gn:dem":4,
    "gn:feature_class":"P",
    "gn:feature_code":"PPL",
    "gn:name":"Coffinscroft",
    "gn:population":0,
    "gn:timezone":"America/Halifax",
    "iso:country":"CA",
    "wof:name":"Coffinscroft",
    "wof:placetype":"locality"
},
  "geometry": {"coordinates":[-65.55386,43.54839000000001],"type":"Point"}
}