{
  "type": "Feature",
  "properties": {
    "gn:admin1_code":"8",
    "gn:asciiname":"Lifford",
    "gn:country_code":"CA",
    "gn:dem":327,
    "gn:feature_class":"P",
    "gn:feature_code":"PPL",
    "gn:name":"Lifford",
    "gn:population":0,
    "gn:timezone":"America/Toronto",
    "iso:country":"CA",
    "name:ast_x_preferred":[
        "Lifford"
    ],
    "name:bul_x_preferred":[
        "\u041b\u0438\u0444\u043e\u0440\u0434"
    ],
    "name:cat_x_preferred":[
        "Lifford"
    ],
    "name:ceb_x_preferred":[
        "Leifear"
    ],
    "name:cym_x_preferred":[
        "Lifford"
    ],
    "name:deu_x_preferred":[
        "Lifford"
    ],
    "name:eus_x_preferred":[
        "Lifford"
    ],
    "name:fas_x_preferred":[
        "\u0644\u06cc\u0641\u0648\u0631\u062f"
    ],
    "name:fra_x_preferred":[
        "Lifford"
    ],
    "name:fry_x_preferred":[
        "Lifford"
    ],
    "name:gla_x_preferred":[
        "Leifear"
    ],
    "name:gle_x_preferred":[
        "Leifear"
    ],
    "name:glg_x_preferred":[
        "Lifford"
    ],
    "name:glv_x_preferred":[
        "Leffyr"
    ],
    "name:heb_x_preferred":[
        "\u05dc\u05d9\u05e4\u05d5\u05e8\u05d3"
    ],
    "name:ita_x_preferred":[
        "Lifford"
    ],
    "name:kor_x_preferred":[
        "\ub9ac\ud37c\ub4dc"
    ],
    "name:lit_x_preferred":[
        "Lifordas"
    ],
    "name:nld_x_preferred":[
        "Lifford"
    ],
    "name:nno_x_preferred":[
        "Lifford"
    ],
    "name:oss_x_preferred":[
        "\u041b\u0438\u0444\u0444\u043e\u0440\u0434"
    ],
    "name:pol_x_preferred":[
        "Lifford"
    ],
    "name:rus_x_preferred":[
        "\u041b\u0438\u0444\u0444\u043e\u0440\u0434"
    ],
    "name:slk_x_preferred":[
        "Lifford"
    ],
    "name:spa_x_preferred":[
        "Lifford"
    ],
    "name:srp_x_preferred":[
        "\u041b\u0438\u0444\u043e\u0440\u0434"
    ],
    "name:swa_x_preferred":[
        "Lifford"
    ],
    "name:swe_x_preferred":[
        "Lifford"
    ],
    "name:ukr_x_preferred":[
        "\u041b\u0456\u0444\u0444\u043e\u0440\u0434"
    ],
    "name:urd_x_preferred":[
        "\u0644\u0641\u0631\u0688"
    ],
    "name:zho_x_preferred":[
        "\u5229\u798f\u5fb7"
    ],
    "wof:name":"Lifford",
    "wof:placetype":"locality"
},
  "geometry": {"coordinates":[-78.648,44.19066],"type":"Point"}
}