{
  "type": "Feature",
  "properties": {
    "gn:admin1_code":"8",
    "gn:asciiname":"Lifford",
    "gn:country_code":"CA",
    "gn:dem":327,
    "gn:feature_class":"P",
    "gn:feature_code":"PPL",
    "gn:name":"Lifford",
    "gn:population":0,
    "gn:timezone":"America/Toronto",
    "iso:country":"CA",
    "wof:name":"Lifford",
    "wof:placetype":"locality"
},
  "geometry": {"coordinates":[-78.648,44.19066],"type":"Point"}
}