{
  "type": "Feature",
  "properties": {
    "gn:admin1_code":"8",
    "gn:asciiname":"Port Crewe",
    "gn:country_code":"CA",
    "gn:dem":193,
    "gn:feature_class":"P",
    "gn:feature_code":"PPL",
    "gn:name":"Port Crewe",
    "gn:population":0,
    "gn:timezone":"America/Toronto",
    "iso:country":"CA",
    "wof:name":"Port Crewe",
    "wof:placetype":"locality"
},
  "geometry": {"coordinates":[-82.20718000000002,42.19542],"type":"Point"}
}