{
  "type": "Feature",
  "properties": {
    "gn:admin1_code":"10",
    "gn:admin2_code":"04",
    "gn:admin3_code":"90012.0",
    "gn:asciiname":"Rapide-Blanc",
    "gn:country_code":"CA",
    "gn:dem":269,
    "gn:feature_class":"P",
    "gn:feature_code":"PPL",
    "gn:name":"Rapide-Blanc",
    "gn:population":0,
    "gn:timezone":"America/Toronto",
    "iso:country":"CA",
    "wof:name":"Rapide-Blanc",
    "wof:placetype":"locality"
},
  "geometry": {"coordinates":[-72.96344000000001,47.7931],"type":"Point"}
}