{
  "type": "Feature",
  "properties": {
    "gn:country":"CA",
    "iso:country":"CA",
    "name:eng_x_preferred":[
        "Summerside 38"
    ],
    "name:nld_x_preferred":[
        "Summerside 38"
    ],
    "name:swe_x_preferred":[
        "Summerside 38"
    ],
    "qs:name":"Summerside 38",
    "qs:name_adm0":"Canada",
    "qs:name_adm1":"Nova Scotia",
    "qs:photos":21,
    "qs:photos_1k":4,
    "qs:photos_9k":1,
    "qs:photos_9r":1,
    "qs:photos_all":21,
    "qs:photos_sr":1,
    "qs:placetype":"Town",
    "qs:pop_sr":"0",
    "wof:name":"Summerside 38",
    "wof:placetype":"locality"
},
  "geometry": {"coordinates":[-61.754322,45.649988],"type":"Point"}
}