{
  "type": "Feature",
  "properties": {
    "iso:country":"CA",
    "name:eng_x_preferred":[
        "Mono Road"
    ],
    "qs:gn_fcode":"PPL",
    "qs:gn_local":0,
    "qs:gn_namadm1":"08",
    "qs:gn_name":"Mono Road",
    "qs:local_max":221,
    "qs:local_sum":382,
    "qs:localhoods":2,
    "qs:name":"Mono Road",
    "qs:name_adm0":"Canada",
    "qs:name_adm1":"Ontario",
    "qs:name_adm2":"Peel",
    "qs:name_local":"Caledon East",
    "qs:photo_max":67,
    "qs:photo_sum":221,
    "qs:placetype":"Suburb",
    "qs:quad_count":20,
    "qs:woe_adm0":23424775,
    "qs:woe_adm1":2344922,
    "qs:woe_adm2":29375178,
    "qs:woe_funk":"Grouping neighborhood",
    "qs:woe_lau":0,
    "qs:woe_local":55999177,
    "qs:woe_ver":"7.10.0",
    "wof:lang":[
        "eng"
    ],
    "wof:name":"Mono Road",
    "wof:placetype":"neighbourhood"
},
  "geometry": {"coordinates":[-79.85192499999999,43.870518],"type":"Point"}
}