{
  "type": "Feature",
  "properties": {
    "gn:admin1_code":"1",
    "gn:asciiname":"Majestic",
    "gn:country_code":"CA",
    "gn:dem":706,
    "gn:feature_class":"P",
    "gn:feature_code":"PPLL",
    "gn:name":"Majestic",
    "gn:population":0,
    "gn:timezone":"America/Edmonton",
    "iso:country":"CA",
    "name:deu_x_preferred":[
        "Majestic"
    ],
    "name:fin_x_preferred":[
        "Majestic"
    ],
    "name:fra_x_preferred":[
        "Majestic"
    ],
    "name:ita_x_preferred":[
        "Majestic"
    ],
    "name:jpn_x_preferred":[
        "\u30de\u30b8\u30a7\u30b9\u30c6\u30a3\u30c3\u30af"
    ],
    "name:kor_x_preferred":[
        "\uba38\uc81c\uc2a4\ud2f1"
    ],
    "name:nld_x_preferred":[
        "Majestic"
    ],
    "name:pol_x_preferred":[
        "Majestic"
    ],
    "name:por_x_preferred":[
        "Majestic"
    ],
    "name:rus_x_preferred":[
        "\u041c\u0430\u0434\u0436\u0435\u0441\u0442\u0438\u043a"
    ],
    "name:spa_x_preferred":[
        "Majestic"
    ],
    "wof:name":"Majestic",
    "wof:placetype":"locality"
},
  "geometry": {"coordinates":[-110.83498,50.85011],"type":"Point"}
}