{
  "type": "Feature",
  "properties": {
    "gn:admin1_code":"1",
    "gn:asciiname":"Majestic",
    "gn:country_code":"CA",
    "gn:dem":706,
    "gn:feature_class":"P",
    "gn:feature_code":"PPLL",
    "gn:name":"Majestic",
    "gn:population":0,
    "gn:timezone":"America/Edmonton",
    "iso:country":"CA",
    "wof:name":"Majestic",
    "wof:placetype":"locality"
},
  "geometry": {"coordinates":[-110.83498,50.85011],"type":"Point"}
}