{
  "type": "Feature",
  "properties": {
    "iso:country":"CA",
    "name:eng_x_preferred":[
        "Valmont sur Parcs"
    ],
    "name:fra_x_preferred":[
        "Valmont sur Parcs"
    ],
    "qs:gn_adm0_cc":"CA",
    "qs:gn_local":6119518,
    "qs:gn_nam_loc":"repentigny",
    "qs:gn_namadm1":"10",
    "qs:local_max":64,
    "qs:local_sum":116,
    "qs:localhoods":2,
    "qs:name":"Valmont sur Parcs",
    "qs:name_adm0":"Canada",
    "qs:name_adm1":"Qu\u00e9bec",
    "qs:name_adm2":"l'Assomption",
    "qs:name_local":"Repentigny",
    "qs:photo_max":25,
    "qs:photo_sum":64,
    "qs:placetype":"Suburb",
    "qs:quad_count":7,
    "qs:woe_adm0":23424775,
    "qs:woe_adm1":2344924,
    "qs:woe_adm2":29375179,
    "qs:woe_funk":"Parented by a neighborhood",
    "qs:woe_lau":0,
    "qs:woe_local":1322,
    "qs:woe_ver":"7.10.0",
    "wof:lang":[
        "fre"
    ],
    "wof:name":"Valmont sur Parcs",
    "wof:placetype":"neighbourhood"
},
  "geometry": {"coordinates":[-73.43511100000001,45.779342],"type":"Point"}
}