{
  "type": "Feature",
  "properties": {
    "gn:admin1_code":"4",
    "gn:asciiname":"Hersonville",
    "gn:country_code":"CA",
    "gn:dem":50,
    "gn:feature_class":"P",
    "gn:feature_code":"PPL",
    "gn:name":"Hersonville",
    "gn:population":0,
    "gn:timezone":"America/Moncton",
    "iso:country":"CA",
    "wof:name":"Hersonville",
    "wof:placetype":"locality"
},
  "geometry": {"coordinates":[-66.97103,45.00792],"type":"Point"}
}