{
  "type": "Feature",
  "properties": {
    "gn:admin1_code":"8.0",
    "gn:asciiname":"Wilsonwood",
    "gn:country_code":"CA",
    "gn:dem":183,
    "gn:feature_class":"P",
    "gn:feature_code":"PPL",
    "gn:name":"Wilsonwood",
    "gn:population":0,
    "gn:timezone":"America/Toronto",
    "iso:country":"CA",
    "wof:name":"Wilsonwood",
    "wof:placetype":"locality"
},
  "geometry": {"coordinates":[-82.15987,42.39396],"type":"Point"}
}