{
  "type": "Feature",
  "properties": {
    "gn:gn_country":"CA",
    "gn:gn_fcode":"PPL",
    "gn:gn_pop":0,
    "iso:country":"CA",
    "name:ara_x_preferred":[
        "\u062a\u0634\u064a\u0628\u0627\u0648\u0627\u060c \u0623\u0648\u0646\u062a\u0627\u0631\u064a\u0648"
    ],
    "name:eng_x_preferred":[
        "Chippawa"
    ],
    "name:nld_x_preferred":[
        "Chippawa"
    ],
    "name:pol_x_preferred":[
        "Chippawa"
    ],
    "name:zho_x_preferred":[
        "\u5947\u5e15\u74e6"
    ],
    "qs_pg:aaroncc":"CA",
    "qs_pg:gn_country":"CA",
    "qs_pg:gn_fcode":"PPL",
    "qs_pg:gn_pop":0,
    "qs_pg:name":"Chippawa",
    "qs_pg:name_adm0":"Canada",
    "qs_pg:name_adm1":"Ontario",
    "qs_pg:photos":243,
    "qs_pg:photos_1k":49,
    "qs_pg:photos_9k":1,
    "qs_pg:photos_9r":4,
    "qs_pg:photos_all":243,
    "qs_pg:photos_sr":4,
    "qs_pg:pop_sr":0,
    "qs_pg:qs_pg_placetype":"locality",
    "qs_pg:qs_pg_placetype_gp":"Town",
    "qs_pg:woe_adm0":23424775,
    "woe:adm0_id":23424775,
    "woe:name_adm0":"Canada",
    "woe:name_adm1":"Ontario",
    "woe:placetype":"Town",
    "wof:name":"Chippawa",
    "wof:placetype":"locality"
},
  "geometry": {"coordinates":[-79.04957,43.06682],"type":"Point"}
}