{
  "type": "Feature",
  "properties": {
    "gn:admin1_code":"10.0",
    "gn:admin2_code":"5.0",
    "gn:admin3_code":"40047.0",
    "gn:asciiname":"Domaine-Mar-Lodge",
    "gn:country_code":"CA",
    "gn:dem":185,
    "gn:feature_class":"P",
    "gn:feature_code":"PPL",
    "gn:name":"Domaine-Mar-Lodge",
    "gn:population":0,
    "gn:timezone":"America/Toronto",
    "iso:country":"CA",
    "wof:name":"Domaine-Mar-Lodge",
    "wof:placetype":"locality"
},
  "geometry": {"coordinates":[-72.00066,45.78143],"type":"Point"}
}