{
  "type": "Feature",
  "properties": {
    "iso:country":"CA",
    "name:cat_x_preferred":[
        "Le Bic"
    ],
    "name:deu_x_preferred":[
        "Le Bic"
    ],
    "name:eng_x_preferred":[
        "Le Bic"
    ],
    "name:fra_x_preferred":[
        "Le Bic"
    ],
    "name:ita_x_preferred":[
        "Le Bic"
    ],
    "name:nld_x_preferred":[
        "Le Bic"
    ],
    "name:oci_x_preferred":[
        "Le Bic"
    ],
    "name:spa_x_preferred":[
        "Le Bic"
    ],
    "qs_pg:aaroncc":"CA",
    "qs_pg:name":"Le Bic",
    "qs_pg:name_adm0":"Canada",
    "qs_pg:name_adm1":"Qu\u00e9bec",
    "qs_pg:photos":1087,
    "qs_pg:photos_1k":220,
    "qs_pg:photos_9k":5,
    "qs_pg:photos_9r":7,
    "qs_pg:photos_all":1087,
    "qs_pg:photos_sr":11,
    "qs_pg:pop_sr":0,
    "qs_pg:qs_pg_placetype":"locality",
    "qs_pg:qs_pg_placetype_gp":"Town",
    "qs_pg:woe_adm0":23424775,
    "woe:adm0_id":23424775,
    "woe:name_adm0":"Canada",
    "woe:name_adm1":"Qu\u00e9bec",
    "woe:placetype":"Town",
    "wof:name":"Le Bic",
    "wof:placetype":"locality"
},
  "geometry": {"coordinates":[-68.73235699999999,48.37233],"type":"Point"}
}