{
  "type": "Feature",
  "properties": {
    "gn:admin1_code":"7",
    "gn:asciiname":"Middleton",
    "gn:country_code":"CA",
    "gn:dem":40,
    "gn:feature_class":"P",
    "gn:feature_code":"PPL",
    "gn:name":"Middleton",
    "gn:population":0,
    "gn:timezone":"America/Halifax",
    "iso:country":"CA",
    "name:cat_x_preferred":[
        "Middleton"
    ],
    "name:ceb_x_preferred":[
        "Middleton"
    ],
    "name:dan_x_preferred":[
        "Middleton"
    ],
    "name:deu_x_preferred":[
        "Middleton"
    ],
    "name:est_x_preferred":[
        "Middleton"
    ],
    "name:fas_x_preferred":[
        "\u0645\u06cc\u062f\u0644\u062a\u0648\u0646"
    ],
    "name:fin_x_preferred":[
        "Middleton"
    ],
    "name:fra_x_preferred":[
        "Middleton"
    ],
    "name:heb_x_preferred":[
        "\u05de\u05d9\u05d3\u05dc\u05d8\u05d5\u05df"
    ],
    "name:ita_x_preferred":[
        "Middleton"
    ],
    "name:kat_x_preferred":[
        "\u10db\u10d8\u10d3\u10da\u10e2\u10dd\u10dc\u10d8"
    ],
    "name:kor_x_preferred":[
        "\ubbf8\ub4e4\ud134"
    ],
    "name:nds_x_preferred":[
        "Middleton"
    ],
    "name:nld_x_preferred":[
        "Middleton"
    ],
    "name:nor_x_preferred":[
        "Middleton"
    ],
    "name:pol_x_preferred":[
        "Middleton"
    ],
    "name:por_x_preferred":[
        "Middleton"
    ],
    "name:rus_x_preferred":[
        "\u041c\u0438\u0434\u0434\u043b\u0442\u043e\u043d"
    ],
    "name:slv_x_preferred":[
        "Middleton"
    ],
    "name:spa_x_preferred":[
        "Middleton"
    ],
    "name:srp_x_preferred":[
        "\u041c\u0438\u0434\u043b\u0442\u043e\u043d"
    ],
    "name:swe_x_preferred":[
        "Middleton"
    ],
    "name:ukr_x_preferred":[
        "\u041c\u0456\u0434\u0434\u043b\u0442\u043e\u043d"
    ],
    "name:vol_x_preferred":[
        "Middleton"
    ],
    "wof:name":"Middleton",
    "wof:placetype":"locality"
},
  "geometry": {"coordinates":[-63.17932,45.71659],"type":"Point"}
}