{
  "type": "Feature",
  "properties": {
    "gn:admin1_code":"7",
    "gn:asciiname":"Middleton",
    "gn:country_code":"CA",
    "gn:dem":40,
    "gn:feature_class":"P",
    "gn:feature_code":"PPL",
    "gn:name":"Middleton",
    "gn:population":0,
    "gn:timezone":"America/Halifax",
    "iso:country":"CA",
    "wof:name":"Middleton",
    "wof:placetype":"locality"
},
  "geometry": {"coordinates":[-63.17932,45.71659],"type":"Point"}
}