{
  "type": "Feature",
  "properties": {
    "gn:admin1_code":"9.0",
    "gn:asciiname":"Crapaud",
    "gn:country_code":"CA",
    "gn:dem":11,
    "gn:feature_class":"P",
    "gn:feature_code":"PPL",
    "gn:name":"Crapaud",
    "gn:population":0,
    "gn:timezone":"America/Halifax",
    "iso:country":"CA",
    "wof:name":"Crapaud",
    "wof:placetype":"locality"
},
  "geometry": {"coordinates":[-63.49871,46.23343],"type":"Point"}
}