{
  "type": "Feature",
  "properties": {
    "gn:admin1_code":"8.0",
    "gn:asciiname":"Windfall",
    "gn:country_code":"CA",
    "gn:dem":186,
    "gn:feature_class":"P",
    "gn:feature_code":"PPL",
    "gn:name":"Windfall",
    "gn:population":0,
    "gn:timezone":"America/Toronto",
    "iso:country":"CA",
    "wof:name":"Windfall",
    "wof:placetype":"locality"
},
  "geometry": {"coordinates":[-82.45889,42.15556],"type":"Point"}
}