{
  "type": "Feature",
  "properties": {
    "gn:admin1_code":"5",
    "gn:asciiname":"Grand Le Pierre",
    "gn:country_code":"CA",
    "gn:dem":50,
    "gn:feature_class":"P",
    "gn:feature_code":"PPL",
    "gn:name":"Grand Le Pierre",
    "gn:population":0,
    "gn:timezone":"America/St_Johns",
    "iso:country":"CA",
    "name:ceb_x_preferred":[
        "Grand Le Pierre"
    ],
    "name:fra_x_preferred":[
        "Grand le Pierre"
    ],
    "name:swe_x_preferred":[
        "Grand Le Pierre"
    ],
    "wof:name":"Grand Le Pierre",
    "wof:placetype":"locality"
},
  "geometry": {"coordinates":[-54.78151999999999,47.68321],"type":"Point"}
}