{
  "type": "Feature",
  "properties": {
    "gn:admin1_code":"10",
    "gn:admin2_code":"8.0",
    "gn:admin3_code":"88022.0",
    "gn:asciiname":"Fiedmont",
    "gn:country_code":"CA",
    "gn:dem":299,
    "gn:feature_class":"P",
    "gn:feature_code":"PPL",
    "gn:name":"Fiedmont",
    "gn:population":0,
    "gn:timezone":"America/Toronto",
    "iso:country":"CA",
    "wof:name":"Fiedmont",
    "wof:placetype":"locality"
},
  "geometry": {"coordinates":[-77.66619,48.36688],"type":"Point"}
}