{
  "type": "Feature",
  "properties": {
    "gn:gn_country":"CA",
    "gn:gn_fcode":"PPL",
    "gn:gn_pop":0,
    "iso:country":"CA",
    "name:ara_x_preferred":[
        "\u0633\u0627\u0646 \u0622\u0645\u0627\u0628\u0644\u060c \u0643\u064a\u0628\u0643"
    ],
    "name:baq_x_preferred":[
        "Saint-Amable"
    ],
    "name:dut_x_preferred":[
        "Saint-Amable"
    ],
    "name:eng_x_preferred":[
        "Saint-Amable"
    ],
    "name:fre_x_preferred":[
        "Saint-Amable"
    ],
    "name:ger_x_preferred":[
        "Saint-Amable"
    ],
    "name:per_x_preferred":[
        "\u0633\u0646-\u0622\u0645\u0628\u0644\u060c \u06a9\u0628\u06a9"
    ],
    "name:spa_x_preferred":[
        "Saint-Amable"
    ],
    "name:swe_x_preferred":[
        "Saint-Amable"
    ],
    "name:urd_x_preferred":[
        "\u0633\u06cc\u0646\u0679-\u0627\u0645\u0628\u0644\u06d2\u060c \u06a9\u06cc\u0648\u0628\u06a9"
    ],
    "qs_pg:aaroncc":"CA",
    "qs_pg:gn_country":"CA",
    "qs_pg:gn_fcode":"PPL",
    "qs_pg:gn_pop":0,
    "qs_pg:name":"St.-Amable",
    "qs_pg:name_adm0":"Canada",
    "qs_pg:name_adm1":"Qu\u00e9bec",
    "qs_pg:photos":253,
    "qs_pg:photos_1k":51,
    "qs_pg:photos_9k":1,
    "qs_pg:photos_9r":4,
    "qs_pg:photos_all":253,
    "qs_pg:photos_sr":5,
    "qs_pg:pop_sr":0,
    "qs_pg:qs_pg_placetype":"locality",
    "qs_pg:qs_pg_placetype_gp":"Town",
    "qs_pg:woe_adm0":23424775,
    "woe:adm0_id":23424775,
    "woe:name_adm0":"Canada",
    "woe:name_adm1":"Qu\u00e9bec",
    "woe:placetype":"Town",
    "wof:name":"St.-Amable",
    "wof:placetype":"locality"
},
  "geometry": {"coordinates":[-73.29916,45.65008],"type":"Point"}
}