{
  "type": "Feature",
  "properties": {
    "gn:admin1_code":"8",
    "gn:asciiname":"Folger",
    "gn:country_code":"CA",
    "gn:dem":251,
    "gn:feature_class":"P",
    "gn:feature_code":"PPL",
    "gn:name":"Folger",
    "gn:population":0,
    "gn:timezone":"America/Toronto",
    "iso:country":"CA",
    "name:deu_x_preferred":[
        "Folger"
    ],
    "name:fra_x_preferred":[
        "Folger"
    ],
    "name:rus_x_preferred":[
        "\u0424\u043e\u043b\u0434\u0436\u0435\u0440"
    ],
    "name:swe_x_preferred":[
        "Folger"
    ],
    "wof:name":"Folger",
    "wof:placetype":"locality"
},
  "geometry": {"coordinates":[-76.72194,45.0675],"type":"Point"}
}