{
  "type": "Feature",
  "properties": {
    "gn:admin1_code":"8",
    "gn:asciiname":"Folger",
    "gn:country_code":"CA",
    "gn:dem":251,
    "gn:feature_class":"P",
    "gn:feature_code":"PPL",
    "gn:name":"Folger",
    "gn:population":0,
    "gn:timezone":"America/Toronto",
    "iso:country":"CA",
    "wof:name":"Folger",
    "wof:placetype":"locality"
},
  "geometry": {"coordinates":[-76.72194,45.0675],"type":"Point"}
}