{
  "type": "Feature",
  "properties": {
    "gn:admin1_code":"7",
    "gn:asciiname":"Little Harbour Road",
    "gn:country_code":"CA",
    "gn:dem":69,
    "gn:feature_class":"P",
    "gn:feature_code":"PPL",
    "gn:name":"Little Harbour Road",
    "gn:population":0,
    "gn:timezone":"America/Halifax",
    "iso:country":"CA",
    "wof:name":"Little Harbour Road",
    "wof:placetype":"locality"
},
  "geometry": {"coordinates":[-62.58076,45.62218],"type":"Point"}
}