{
  "type": "Feature",
  "properties": {
    "gn:admin1_code":"10.0",
    "gn:admin2_code":"16.0",
    "gn:admin3_code":"53065.0",
    "gn:asciiname":"Chenail-du-Moine",
    "gn:country_code":"CA",
    "gn:dem":7,
    "gn:feature_class":"P",
    "gn:feature_code":"PPL",
    "gn:name":"Chenail-du-Moine",
    "gn:population":0,
    "gn:timezone":"America/Toronto",
    "iso:country":"CA",
    "wof:name":"Chenail-du-Moine",
    "wof:placetype":"locality"
},
  "geometry": {"coordinates":[-72.9879,46.07003],"type":"Point"}
}