{
  "type": "Feature",
  "properties": {
    "gn:admin1_code":"11",
    "gn:asciiname":"Hillside",
    "gn:country_code":"CA",
    "gn:dem":652,
    "gn:feature_class":"P",
    "gn:feature_code":"PPLL",
    "gn:name":"Hillside",
    "gn:population":0,
    "gn:timezone":"America/Regina",
    "iso:country":"CA",
    "wof:name":"Hillside",
    "wof:placetype":"locality"
},
  "geometry": {"coordinates":[-108.06801000000002,53.06685],"type":"Point"}
}