{
  "type": "Feature",
  "properties": {
    "gn:admin1_code":"11.0",
    "gn:asciiname":"Armley",
    "gn:country_code":"CA",
    "gn:dem":366,
    "gn:feature_class":"P",
    "gn:feature_code":"PPL",
    "gn:name":"Armley",
    "gn:population":0,
    "gn:timezone":"America/Regina",
    "iso:country":"CA",
    "wof:name":"Armley",
    "wof:placetype":"locality"
},
  "geometry": {"coordinates":[-104.03424,53.11676],"type":"Point"}
}