{
  "type": "Feature",
  "properties": {
    "gn:admin1_code":"1",
    "gn:asciiname":"Shining Bank",
    "gn:country_code":"CA",
    "gn:dem":857,
    "gn:feature_class":"P",
    "gn:feature_code":"PPLL",
    "gn:name":"Shining Bank",
    "gn:population":0,
    "gn:timezone":"America/Edmonton",
    "iso:country":"CA",
    "wof:name":"Shining Bank",
    "wof:placetype":"locality"
},
  "geometry": {"coordinates":[-115.98554,53.88344],"type":"Point"}
}