{
  "type": "Feature",
  "properties": {
    "gn:admin1_code":"8",
    "gn:asciiname":"Tollgate",
    "gn:country_code":"CA",
    "gn:dem":312,
    "gn:feature_class":"P",
    "gn:feature_code":"PPLL",
    "gn:name":"Tollgate",
    "gn:population":0,
    "gn:timezone":"America/Toronto",
    "iso:country":"CA",
    "wof:name":"Tollgate",
    "wof:placetype":"locality"
},
  "geometry": {"coordinates":[-80.77500999999999,43.1593],"type":"Point"}
}