{
  "type": "Feature",
  "properties": {
    "gn:admin1_code":"2",
    "gn:admin2_code":"5943",
    "gn:asciiname":"Scott Cove",
    "gn:country_code":"CA",
    "gn:dem":8,
    "gn:feature_class":"P",
    "gn:feature_code":"PPLL",
    "gn:name":"Scott Cove",
    "gn:population":0,
    "gn:timezone":"America/Vancouver",
    "iso:country":"CA",
    "wof:name":"Scott Cove",
    "wof:placetype":"locality"
},
  "geometry": {"coordinates":[-126.46146,50.76562],"type":"Point"}
}