{
  "type": "Feature",
  "properties": {
    "gn:admin1_code":"7",
    "gn:asciiname":"Pleasant Hills",
    "gn:country_code":"CA",
    "gn:dem":88,
    "gn:feature_class":"P",
    "gn:feature_code":"PPLL",
    "gn:name":"Pleasant Hills",
    "gn:population":0,
    "gn:timezone":"America/Halifax",
    "iso:country":"CA",
    "name:cat_x_preferred":[
        "Pleasant Hills"
    ],
    "name:ceb_x_preferred":[
        "Pleasant Hills"
    ],
    "name:deu_x_preferred":[
        "Pleasant Hills"
    ],
    "name:ita_x_preferred":[
        "Pleasant Hills"
    ],
    "name:nld_x_preferred":[
        "Pleasant Hills"
    ],
    "name:pol_x_preferred":[
        "Pleasant Hills"
    ],
    "name:srp_x_preferred":[
        "\u041f\u043b\u0435\u0437\u0435\u043d\u0442 \u0425\u0438\u043b\u0441"
    ],
    "name:swe_x_preferred":[
        "Pleasant Hills"
    ],
    "name:vol_x_preferred":[
        "Pleasant Hills"
    ],
    "wof:name":"Pleasant Hills",
    "wof:placetype":"locality"
},
  "geometry": {"coordinates":[-63.84873,45.43345],"type":"Point"}
}