{
  "type": "Feature",
  "properties": {
    "gn:country":"CA",
    "gn:fcode":"PPL",
    "gn:population":0,
    "iso:country":"CA",
    "name:eng_x_preferred":[
        "Brookfield"
    ],
    "name:fra_x_preferred":[
        "Brookfield"
    ],
    "name:ita_x_preferred":[
        "Brookfield"
    ],
    "name:nld_x_preferred":[
        "Brookfield"
    ],
    "name:spa_x_preferred":[
        "Brookfield"
    ],
    "name:urd_x_preferred":[
        "\u0628\u0631\u0648\u06a9\u0641\u06cc\u0644\u0688\u060c \u0646\u0648\u0648\u0627 \u0633\u06a9\u0648\u0634\u06cc\u0627"
    ],
    "name:urd_x_variant":[
        "\u0628\u0631\u0648\u06a9\u0641\u06cc\u0644\u0688"
    ],
    "qs:name":"Brookfield",
    "qs:name_adm0":"Canada",
    "qs:name_adm1":"Nova Scotia",
    "qs:photos":31,
    "qs:photos_1k":6,
    "qs:photos_9k":1,
    "qs:photos_9r":2,
    "qs:photos_all":31,
    "qs:photos_sr":2,
    "qs:placetype":"Town",
    "qs:pop_sr":"0",
    "wd:wordcount":164,
    "wof:name":"Brookfield",
    "wof:placetype":"locality",
    "wof:population":0
},
  "geometry": {"coordinates":[-63.28198,45.25015],"type":"Point"}
}