{
  "type": "Feature",
  "properties": {
    "gn:admin1_code":"1.0",
    "gn:asciiname":"Decoigne",
    "gn:country_code":"CA",
    "gn:dem":1121,
    "gn:feature_class":"P",
    "gn:feature_code":"PPLL",
    "gn:name":"Decoigne",
    "gn:population":0,
    "gn:timezone":"America/Edmonton",
    "iso:country":"CA",
    "wof:name":"Decoigne",
    "wof:placetype":"locality"
},
  "geometry": {"coordinates":[-118.3691,52.88331],"type":"Point"}
}