{
  "type": "Feature",
  "properties": {
    "gn:admin1_code":"2.0",
    "gn:admin2_code":"5929",
    "gn:asciiname":"Malibu",
    "gn:country_code":"CA",
    "gn:dem":21,
    "gn:feature_class":"P",
    "gn:feature_code":"PPL",
    "gn:name":"Malibu",
    "gn:population":0,
    "gn:timezone":"America/Vancouver",
    "iso:country":"CA",
    "wof:name":"Malibu",
    "wof:placetype":"locality"
},
  "geometry": {"coordinates":[-123.85242,50.16531],"type":"Point"}
}