{
  "type": "Feature",
  "properties": {
    "gn:admin1_code":"5",
    "gn:asciiname":"O'Brien",
    "gn:country_code":"CA",
    "gn:dem":104,
    "gn:feature_class":"P",
    "gn:feature_code":"PPLL",
    "gn:name":"O'Brien",
    "gn:population":0,
    "gn:timezone":"America/St_Johns",
    "iso:country":"CA",
    "name:cat_x_preferred":[
        "O'Brien"
    ],
    "name:ceb_x_preferred":[
        "O'Brien"
    ],
    "name:ces_x_preferred":[
        "O'Brien"
    ],
    "name:deu_x_preferred":[
        "O\u2019Brien"
    ],
    "name:fas_x_preferred":[
        "\u0627\u0648\u0628\u0631\u0627\u06cc\u0627\u0646"
    ],
    "name:fin_x_preferred":[
        "O\u2019Brien"
    ],
    "name:fra_x_preferred":[
        "O'Brien"
    ],
    "name:heb_x_preferred":[
        "\u05d0\u05d5'\u05d1\u05e8\u05d9\u05d0\u05df"
    ],
    "name:ita_x_preferred":[
        "O'Brien"
    ],
    "name:jpn_x_preferred":[
        "\u30aa\u30d6\u30e9\u30a4\u30a8\u30f3"
    ],
    "name:nld_x_preferred":[
        "O'Brien"
    ],
    "name:pol_x_preferred":[
        "O\u2019Brien"
    ],
    "name:rus_x_preferred":[
        "\u041e\u2019\u0411\u0440\u0430\u0439\u0435\u043d"
    ],
    "name:spa_x_preferred":[
        "O'Brien"
    ],
    "name:srp_x_preferred":[
        "\u041e'\u0411\u0440\u0430\u0458\u0435\u043d"
    ],
    "name:swe_x_preferred":[
        "O'Brien"
    ],
    "name:ukr_x_preferred":[
        "\u041e'\u0411\u0440\u0430\u0454\u043d"
    ],
    "wof:name":"O'Brien",
    "wof:placetype":"locality"
},
  "geometry": {"coordinates":[-54.99817,49.04993],"type":"Point"}
}