{
  "type": "Feature",
  "properties": {
    "gn:admin1_code":"4",
    "gn:asciiname":"McKinleyville",
    "gn:country_code":"CA",
    "gn:dem":34,
    "gn:feature_class":"P",
    "gn:feature_code":"PPL",
    "gn:name":"McKinleyville",
    "gn:population":0,
    "gn:timezone":"America/Moncton",
    "iso:country":"CA",
    "wof:name":"McKinleyville",
    "wof:placetype":"locality"
},
  "geometry": {"coordinates":[-65.66530999999999,46.86743],"type":"Point"}
}