{
  "type": "Feature",
  "properties": {
    "iso:country":"CA",
    "name:ceb_x_preferred":[
        "Fall River"
    ],
    "name:deu_x_preferred":[
        "New Harbour"
    ],
    "name:eng_x_preferred":[
        "Fall River"
    ],
    "name:urd_x_preferred":[
        "\u0641\u0627\u0644 \u0631\u06cc\u0648\u0631\u060c \u0646\u0648\u0648\u0627 \u0633\u06a9\u0627\u0679\u06cc\u0627"
    ],
    "name:urd_x_variant":[
        "\u0641\u0627\u0644 \u0631\u06cc\u0648\u0631"
    ],
    "name:zho_x_preferred":[
        "\u79cb\u6cb3\u5e02"
    ],
    "qs:name":"Fall River",
    "qs:name_adm0":"Canada",
    "qs:name_adm1":"Nova Scotia",
    "qs:photos":265,
    "qs:photos_1k":54,
    "qs:photos_9k":1,
    "qs:photos_9r":4,
    "qs:photos_all":265,
    "qs:photos_sr":5,
    "qs:placetype":"Town",
    "qs:pop_sr":"0",
    "wof:name":"Fall River",
    "wof:placetype":"locality"
},
  "geometry": {"coordinates":[-63.606719,44.820515],"type":"Point"}
}