{
  "type": "Feature",
  "properties": {
    "gn:admin1_code":"11.0",
    "gn:asciiname":"Dendron",
    "gn:country_code":"CA",
    "gn:dem":727,
    "gn:feature_class":"P",
    "gn:feature_code":"PPL",
    "gn:name":"Dendron",
    "gn:population":0,
    "gn:timezone":"America/Regina",
    "iso:country":"CA",
    "name:ita_x_preferred":[
        "Dendron"
    ],
    "wof:name":"Dendron",
    "wof:placetype":"locality"
},
  "geometry": {"coordinates":[-107.11799000000001,50.11676],"type":"Point"}
}