{
  "type": "Feature",
  "properties": {
    "gn:admin1_code":"9",
    "gn:asciiname":"Union Road",
    "gn:country_code":"CA",
    "gn:dem":52,
    "gn:feature_class":"P",
    "gn:feature_code":"PPLL",
    "gn:name":"Union Road",
    "gn:population":0,
    "gn:timezone":"America/Halifax",
    "iso:country":"CA",
    "wof:name":"Union Road",
    "wof:placetype":"locality"
},
  "geometry": {"coordinates":[-62.69866,46.18341],"type":"Point"}
}