{
  "type": "Feature",
  "properties": {
    "gn:admin1_code":"7",
    "gn:asciiname":"Lewis Lake",
    "gn:country_code":"CA",
    "gn:dem":83,
    "gn:feature_class":"P",
    "gn:feature_code":"PPL",
    "gn:name":"Lewis Lake",
    "gn:population":0,
    "gn:timezone":"America/Halifax",
    "iso:country":"CA",
    "name:ceb_x_preferred":[
        "Lewis Lake"
    ],
    "name:swe_x_preferred":[
        "Lewis Lake"
    ],
    "wof:name":"Lewis Lake",
    "wof:placetype":"locality"
},
  "geometry": {"coordinates":[-63.83533000000001,44.68209],"type":"Point"}
}