{
  "type": "Feature",
  "properties": {
    "gn:admin1_code":"1",
    "gn:asciiname":"Southlands",
    "gn:country_code":"CA",
    "gn:dem":714,
    "gn:feature_class":"P",
    "gn:feature_code":"PPL",
    "gn:name":"Southlands",
    "gn:population":0,
    "gn:timezone":"America/Edmonton",
    "iso:country":"CA",
    "wof:name":"Southlands",
    "wof:placetype":"locality"
},
  "geometry": {"coordinates":[-110.65000000000001,49.99583],"type":"Point"}
}