{
  "type": "Feature",
  "properties": {
    "iso:country":"CA",
    "name:eng_x_preferred":[
        "Enfield"
    ],
    "name:fin_x_preferred":[
        "Enfield"
    ],
    "name:fra_x_preferred":[
        "Enfield"
    ],
    "name:nld_x_preferred":[
        "Enfield"
    ],
    "name:swe_x_preferred":[
        "Enfield"
    ],
    "qs:name":"Enfield",
    "qs:name_adm0":"Canada",
    "qs:name_adm1":"Nova Scotia",
    "qs:photos":107,
    "qs:photos_1k":22,
    "qs:photos_9k":1,
    "qs:photos_9r":3,
    "qs:photos_all":107,
    "qs:photos_sr":3,
    "qs:placetype":"Town",
    "qs:pop_sr":"0",
    "wd:wordcount":319,
    "wof:name":"Enfield",
    "wof:placetype":"locality"
},
  "geometry": {"coordinates":[-63.535995,44.934182],"type":"Point"}
}