{
  "type": "Feature",
  "properties": {
    "gn:admin1_code":"1",
    "gn:asciiname":"Sabine",
    "gn:country_code":"CA",
    "gn:dem":830,
    "gn:feature_class":"P",
    "gn:feature_code":"PPLL",
    "gn:name":"Sabine",
    "gn:population":0,
    "gn:timezone":"America/Edmonton",
    "iso:country":"CA",
    "name:ara_x_preferred":[
        "\u0633\u0627\u0628\u064a\u0648\u0646"
    ],
    "name:ben_x_preferred":[
        "\u09b8\u09be\u09ac\u09bf\u09a8"
    ],
    "name:ell_x_preferred":[
        "\u03a3\u03b1\u03bc\u03c0\u03af\u03bd\u03b5"
    ],
    "name:fas_x_preferred":[
        "\u0633\u0627\u0628\u06cc\u0646"
    ],
    "name:heb_x_preferred":[
        "\u05e1\u05d0\u05d1\u05d9\u05df"
    ],
    "name:hin_x_preferred":[
        "\u0938\u092c\u0940\u0928"
    ],
    "name:ind_x_preferred":[
        "Sabine"
    ],
    "name:kor_x_preferred":[
        "\uc0ac\ube48"
    ],
    "name:swe_x_preferred":[
        "Sabine River"
    ],
    "name:tur_x_preferred":[
        "Sabine"
    ],
    "name:ukr_x_preferred":[
        "\u0421\u0430\u0431\u0456\u043d\u0435"
    ],
    "name:urd_x_preferred":[
        "\u0633\u0627\u0628\u0627\u0626\u0646"
    ],
    "name:vie_x_preferred":[
        "S\u00f4ng Sabine"
    ],
    "wof:name":"Sabine",
    "wof:placetype":"locality"
},
  "geometry": {"coordinates":[-112.60189,52.20013],"type":"Point"}
}