{
  "type": "Feature",
  "properties": {
    "gn:admin1_code":"1",
    "gn:asciiname":"Sabine",
    "gn:country_code":"CA",
    "gn:dem":830,
    "gn:feature_class":"P",
    "gn:feature_code":"PPLL",
    "gn:name":"Sabine",
    "gn:population":0,
    "gn:timezone":"America/Edmonton",
    "iso:country":"CA",
    "wof:name":"Sabine",
    "wof:placetype":"locality"
},
  "geometry": {"coordinates":[-112.60189,52.20013],"type":"Point"}
}