{
  "type": "Feature",
  "properties": {
    "gn:admin1_code":"8",
    "gn:asciiname":"Londesborough",
    "gn:country_code":"CA",
    "gn:dem":298,
    "gn:feature_class":"P",
    "gn:feature_code":"PPL",
    "gn:name":"Londesborough",
    "gn:population":0,
    "gn:timezone":"America/Toronto",
    "iso:country":"CA",
    "wof:name":"Londesborough",
    "wof:placetype":"locality"
},
  "geometry": {"coordinates":[-81.47750000000001,43.69889000000001],"type":"Point"}
}