{
  "type": "Feature",
  "properties": {
    "gn:admin1_code":"9",
    "gn:asciiname":"North Rustico Harbour",
    "gn:country_code":"CA",
    "gn:dem":0,
    "gn:feature_class":"P",
    "gn:feature_code":"PPLL",
    "gn:name":"North Rustico Harbour",
    "gn:population":0,
    "gn:timezone":"America/Halifax",
    "iso:country":"CA",
    "wof:name":"North Rustico Harbour",
    "wof:placetype":"locality"
},
  "geometry": {"coordinates":[-63.2987,46.46682],"type":"Point"}
}