{
  "type": "Feature",
  "properties": {
    "gn:admin1_code":"8",
    "gn:asciiname":"Elliotts Corners",
    "gn:country_code":"CA",
    "gn:dem":248,
    "gn:feature_class":"P",
    "gn:feature_code":"PPL",
    "gn:name":"Elliotts Corners",
    "gn:population":0,
    "gn:timezone":"America/Toronto",
    "iso:country":"CA",
    "wof:name":"Elliotts Corners",
    "wof:placetype":"locality"
},
  "geometry": {"coordinates":[-79.81194000000001,44.71139],"type":"Point"}
}