{
  "type": "Feature",
  "properties": {
    "gn:admin1_code":"5",
    "gn:asciiname":"Gadds Harbour",
    "gn:country_code":"CA",
    "gn:dem":15,
    "gn:feature_class":"P",
    "gn:feature_code":"PPL",
    "gn:name":"Gadds Harbour",
    "gn:population":0,
    "gn:timezone":"America/St_Johns",
    "iso:country":"CA",
    "wof:name":"Gadds Harbour",
    "wof:placetype":"locality"
},
  "geometry": {"coordinates":[-57.88162,49.51671],"type":"Point"}
}