{
  "type": "Feature",
  "properties": {
    "gn:admin1_code":"8",
    "gn:asciiname":"Hornby Station",
    "gn:country_code":"CA",
    "gn:dem":197,
    "gn:feature_class":"P",
    "gn:feature_code":"PPL",
    "gn:name":"Hornby Station",
    "gn:population":0,
    "gn:timezone":"America/Toronto",
    "iso:country":"CA",
    "wof:name":"Hornby Station",
    "wof:placetype":"locality"
},
  "geometry": {"coordinates":[-79.81610000000001,43.56161],"type":"Point"}
}