{
  "type": "Feature",
  "properties": {
    "gn:admin1_code":"7",
    "gn:asciiname":"New France",
    "gn:country_code":"CA",
    "gn:dem":130,
    "gn:feature_class":"P",
    "gn:feature_code":"PPLL",
    "gn:name":"New France",
    "gn:population":0,
    "gn:timezone":"America/Halifax",
    "iso:country":"CA",
    "wof:name":"New France",
    "wof:placetype":"locality"
},
  "geometry": {"coordinates":[-65.76714,44.31685],"type":"Point"}
}