{
  "type": "Feature",
  "properties": {
    "gn:admin1_code":"11",
    "gn:asciiname":"Hoey",
    "gn:country_code":"CA",
    "gn:dem":462,
    "gn:feature_class":"P",
    "gn:feature_code":"PPLL",
    "gn:name":"Hoey",
    "gn:population":0,
    "gn:timezone":"America/Regina",
    "iso:country":"CA",
    "name:fra_x_preferred":[
        "Hoey"
    ],
    "wof:name":"Hoey",
    "wof:placetype":"locality"
},
  "geometry": {"coordinates":[-105.80107,52.86677],"type":"Point"}
}