{
  "type": "Feature",
  "properties": {
    "gn:admin1_code":"11",
    "gn:asciiname":"Nashlyn",
    "gn:country_code":"CA",
    "gn:dem":907,
    "gn:feature_class":"P",
    "gn:feature_code":"PPLL",
    "gn:name":"Nashlyn",
    "gn:population":0,
    "gn:timezone":"America/Regina",
    "iso:country":"CA",
    "name:fra_x_preferred":[
        "Nashlyn"
    ],
    "wof:name":"Nashlyn",
    "wof:placetype":"locality"
},
  "geometry": {"coordinates":[-109.51817,49.20003],"type":"Point"}
}