{
  "type": "Feature",
  "properties": {
    "gn:admin1_code":"1",
    "gn:asciiname":"Happy Hollow",
    "gn:country_code":"CA",
    "gn:dem":560,
    "gn:feature_class":"P",
    "gn:feature_code":"PPLL",
    "gn:name":"Happy Hollow",
    "gn:population":0,
    "gn:timezone":"America/Edmonton",
    "iso:country":"CA",
    "name:ceb_x_preferred":[
        "Happy Hollow"
    ],
    "name:deu_x_preferred":[
        "Happy Hollow"
    ],
    "wof:name":"Happy Hollow",
    "wof:placetype":"locality"
},
  "geometry": {"coordinates":[-110.55175,54.50018000000001],"type":"Point"}
}