{
  "type": "Feature",
  "properties": {
    "gn:admin1_code":"8.0",
    "gn:asciiname":"Bigelow",
    "gn:country_code":"CA",
    "gn:dem":233,
    "gn:feature_class":"P",
    "gn:feature_code":"PPL",
    "gn:name":"Bigelow",
    "gn:population":0,
    "gn:timezone":"America/Toronto",
    "iso:country":"CA",
    "name:ceb_x_preferred":[
        "Bigelow"
    ],
    "name:deu_x_preferred":[
        "Bigelow"
    ],
    "name:epo_x_preferred":[
        "Bigelow"
    ],
    "name:fra_x_preferred":[
        "Bigelow"
    ],
    "name:ita_x_preferred":[
        "Bigelow"
    ],
    "name:jpn_x_preferred":[
        "\u30d3\u30b2\u30ed\u30fc"
    ],
    "name:nld_x_preferred":[
        "Bigelow"
    ],
    "name:pol_x_preferred":[
        "Bigelow"
    ],
    "name:por_x_preferred":[
        "Bigelow"
    ],
    "name:rus_x_preferred":[
        "\u0411\u0438\u0433\u0435\u043b\u043e\u0443"
    ],
    "name:spa_x_preferred":[
        "Bigelow"
    ],
    "name:srp_x_preferred":[
        "\u0411\u0438\u0433\u0435\u043b\u043e\u0443"
    ],
    "name:swe_x_preferred":[
        "Bigelow"
    ],
    "name:ukr_x_preferred":[
        "\u0411\u0456\u0433\u0435\u043b\u043e\u0432"
    ],
    "name:vol_x_preferred":[
        "Bigelow"
    ],
    "wof:name":"Bigelow",
    "wof:placetype":"locality"
},
  "geometry": {"coordinates":[-79.5175,47.29611],"type":"Point"}
}