{
  "type": "Feature",
  "properties": {
    "gn:admin1_code":"8.0",
    "gn:asciiname":"Del Ray",
    "gn:country_code":"CA",
    "gn:dem":141,
    "gn:feature_class":"P",
    "gn:feature_code":"PPL",
    "gn:name":"Del Ray",
    "gn:population":0,
    "gn:timezone":"America/Toronto",
    "iso:country":"CA",
    "wof:name":"Del Ray",
    "wof:placetype":"locality"
},
  "geometry": {"coordinates":[-79.48317,43.70362],"type":"Point"}
}