{
  "type": "Feature",
  "properties": {
    "iso:country":"CA",
    "name:bel_x_preferred":[
        "\u0406\u0442\u0430\u043d"
    ],
    "name:cat_x_preferred":[
        "Eaton"
    ],
    "name:ceb_x_preferred":[
        "Eaton"
    ],
    "name:deu_x_preferred":[
        "Eaton"
    ],
    "name:fra_x_preferred":[
        "Eaton"
    ],
    "name:heb_x_preferred":[
        "\u05d0\u05d9\u05d8\u05d5\u05df"
    ],
    "name:ita_x_preferred":[
        "Eaton"
    ],
    "name:lav_x_preferred":[
        "\u012atons"
    ],
    "name:mlg_x_preferred":[
        "Eaton"
    ],
    "name:nds_x_preferred":[
        "Eaton"
    ],
    "name:nld_x_preferred":[
        "Eaton"
    ],
    "name:pol_x_preferred":[
        "Eaton"
    ],
    "name:por_x_preferred":[
        "Eaton"
    ],
    "name:ron_x_preferred":[
        "Eaton"
    ],
    "name:rus_x_preferred":[
        "Eaton"
    ],
    "name:spa_x_preferred":[
        "Eaton"
    ],
    "name:srp_x_preferred":[
        "\u0418\u0442\u043e\u043d"
    ],
    "name:swe_x_preferred":[
        "Eaton"
    ],
    "name:ukr_x_preferred":[
        "\u0406\u0442\u043e\u043d"
    ],
    "name:vol_x_preferred":[
        "Eaton"
    ],
    "qs_pg:aaroncc":"CA",
    "qs_pg:name":"Eaton",
    "qs_pg:name_adm0":"Canada",
    "qs_pg:name_adm1":"Qu\u00e9bec",
    "qs_pg:photos":20,
    "qs_pg:photos_1k":4,
    "qs_pg:photos_9k":1,
    "qs_pg:photos_9r":1,
    "qs_pg:photos_all":20,
    "qs_pg:photos_sr":1,
    "qs_pg:pop_sr":0,
    "qs_pg:qs_pg_placetype":"locality",
    "qs_pg:qs_pg_placetype_gp":"Town",
    "qs_pg:woe_adm0":23424775,
    "woe:adm0_id":23424775,
    "woe:name_adm0":"Canada",
    "woe:name_adm1":"Qu\u00e9bec",
    "woe:placetype":"Town",
    "wof:name":"Eaton",
    "wof:placetype":"locality"
},
  "geometry": {"coordinates":[-71.6928985,45.372572],"type":"Point"}
}