{
  "type": "Feature",
  "properties": {
    "gn:admin1_code":"8",
    "gn:asciiname":"Masonville",
    "gn:country_code":"CA",
    "gn:dem":270,
    "gn:feature_class":"P",
    "gn:feature_code":"PPL",
    "gn:name":"Masonville",
    "gn:population":0,
    "gn:timezone":"America/Toronto",
    "iso:country":"CA",
    "name:ceb_x_preferred":[
        "Masonville"
    ],
    "name:deu_x_preferred":[
        "Masonville"
    ],
    "name:fra_x_preferred":[
        "Masonville"
    ],
    "name:ita_x_preferred":[
        "Masonville"
    ],
    "name:nld_x_preferred":[
        "Masonville"
    ],
    "name:pol_x_preferred":[
        "Masonville"
    ],
    "name:por_x_preferred":[
        "Masonville"
    ],
    "name:srp_x_preferred":[
        "\u041c\u0435\u0458\u0441\u043e\u043d\u0432\u0438\u043b"
    ],
    "name:ukr_x_preferred":[
        "\u041c\u0435\u0439\u0441\u043e\u043d\u0432\u0456\u043b\u043b"
    ],
    "name:vol_x_preferred":[
        "Masonville"
    ],
    "wof:name":"Masonville",
    "wof:placetype":"locality"
},
  "geometry": {"coordinates":[-81.28706,43.02256],"type":"Point"}
}