{
  "type": "Feature",
  "properties": {
    "gn:country":"CA",
    "gn:fcode":"PPL",
    "gn:pop":0,
    "iso:country":"CA",
    "name:eng_x_preferred":[
        "Hunter River"
    ],
    "name:fra_x_preferred":[
        "Hunter River"
    ],
    "name:heb_x_preferred":[
        "\u05e0\u05d4\u05e8 \u05d4\u05d0\u05e0\u05d8\u05e8"
    ],
    "name:ita_x_preferred":[
        "Hunter River"
    ],
    "name:nld_x_preferred":[
        "Hunter River"
    ],
    "name:nob_x_preferred":[
        "Hunter River"
    ],
    "name:slv_x_preferred":[
        "Hunter River"
    ],
    "name:swe_x_preferred":[
        "Hunter River"
    ],
    "qs:name":"Hunter River",
    "qs:name_adm0":"Canada",
    "qs:name_adm1":"Prince Edward Island",
    "qs:photos":97,
    "qs:photos_1k":20,
    "qs:photos_9k":1,
    "qs:photos_9r":3,
    "qs:photos_all":97,
    "qs:photos_sr":3,
    "qs:placetype":"Town",
    "qs:pop_sr":"0",
    "wof:name":"Hunter River",
    "wof:placetype":"locality",
    "wof:population":0
},
  "geometry": {"coordinates":[-63.3487,46.35012],"type":"Point"}
}