{
  "type": "Feature",
  "properties": {
    "gn:admin1_code":"2",
    "gn:admin2_code":"5949",
    "gn:asciiname":"Remo",
    "gn:country_code":"CA",
    "gn:dem":47,
    "gn:feature_class":"P",
    "gn:feature_code":"PPL",
    "gn:name":"Remo",
    "gn:population":0,
    "gn:timezone":"America/Vancouver",
    "iso:country":"CA",
    "name:dan_x_preferred":[
        "Remo"
    ],
    "name:deu_x_preferred":[
        "Remo"
    ],
    "name:epo_x_preferred":[
        "Remo"
    ],
    "name:fra_x_preferred":[
        "Remo"
    ],
    "name:ita_x_preferred":[
        "Remo"
    ],
    "name:pol_x_preferred":[
        "Remo"
    ],
    "name:por_x_preferred":[
        "Remo"
    ],
    "name:rus_x_preferred":[
        "Remo"
    ],
    "name:spa_x_preferred":[
        "Remo"
    ],
    "wof:name":"Remo",
    "wof:placetype":"locality"
},
  "geometry": {"coordinates":[-128.71778999999998,54.49564],"type":"Point"}
}