{
  "type": "Feature",
  "properties": {
    "gn:admin1_code":"8",
    "gn:asciiname":"Huntley",
    "gn:country_code":"CA",
    "gn:dem":115,
    "gn:feature_class":"P",
    "gn:feature_code":"PPL",
    "gn:name":"Huntley",
    "gn:population":0,
    "gn:timezone":"America/Toronto",
    "iso:country":"CA",
    "wof:name":"Huntley",
    "wof:placetype":"locality"
},
  "geometry": {"coordinates":[-75.97457,45.29583],"type":"Point"}
}