{
  "type": "Feature",
  "properties": {
    "gn:admin1_code":"8",
    "gn:asciiname":"Huntley",
    "gn:country_code":"CA",
    "gn:dem":115,
    "gn:feature_class":"P",
    "gn:feature_code":"PPL",
    "gn:name":"Huntley",
    "gn:population":0,
    "gn:timezone":"America/Toronto",
    "iso:country":"CA",
    "name:cat_x_preferred":[
        "Huntley"
    ],
    "name:ceb_x_preferred":[
        "Huntley"
    ],
    "name:deu_x_preferred":[
        "Huntley"
    ],
    "name:est_x_preferred":[
        "Huntley"
    ],
    "name:fra_x_preferred":[
        "Huntley"
    ],
    "name:ita_x_preferred":[
        "Huntley"
    ],
    "name:nld_x_preferred":[
        "Huntley"
    ],
    "name:pol_x_preferred":[
        "Huntley"
    ],
    "name:por_x_preferred":[
        "Huntley"
    ],
    "name:rus_x_preferred":[
        "\u0425\u0430\u043d\u0442\u043b\u0438"
    ],
    "name:srp_x_preferred":[
        "\u0425\u0430\u043d\u0442\u043b\u0438"
    ],
    "name:swe_x_preferred":[
        "Huntley"
    ],
    "name:ukr_x_preferred":[
        "\u0413\u0430\u043d\u0442\u043b\u0456"
    ],
    "name:vol_x_preferred":[
        "Huntley"
    ],
    "wof:name":"Huntley",
    "wof:placetype":"locality"
},
  "geometry": {"coordinates":[-75.97457,45.29583],"type":"Point"}
}