{
  "type": "Feature",
  "properties": {
    "gn:admin1_code":"7",
    "gn:asciiname":"Northfield",
    "gn:country_code":"CA",
    "gn:dem":40,
    "gn:feature_class":"P",
    "gn:feature_code":"PPL",
    "gn:name":"Northfield",
    "gn:population":0,
    "gn:timezone":"America/Halifax",
    "iso:country":"CA",
    "wof:name":"Northfield",
    "wof:placetype":"locality"
},
  "geometry": {"coordinates":[-64.61601,44.46655],"type":"Point"}
}