{
  "type": "Feature",
  "properties": {
    "gn:admin1_code":"7",
    "gn:asciiname":"Northfield",
    "gn:country_code":"CA",
    "gn:dem":40,
    "gn:feature_class":"P",
    "gn:feature_code":"PPL",
    "gn:name":"Northfield",
    "gn:population":0,
    "gn:timezone":"America/Halifax",
    "iso:country":"CA",
    "name:cat_x_preferred":[
        "Northfield"
    ],
    "name:ceb_x_preferred":[
        "Northfield"
    ],
    "name:deu_x_preferred":[
        "Northfield"
    ],
    "name:fra_x_preferred":[
        "Northfield"
    ],
    "name:ita_x_preferred":[
        "Northfield"
    ],
    "name:jpn_x_preferred":[
        "\u30ce\u30fc\u30b9\u30d5\u30a3\u30fc\u30eb\u30c9"
    ],
    "name:nld_x_preferred":[
        "Northfield"
    ],
    "name:pol_x_preferred":[
        "Northfield"
    ],
    "name:por_x_preferred":[
        "Northfield"
    ],
    "name:rus_x_preferred":[
        "\u041d\u043e\u0440\u0442\u0444\u0438\u043b\u0434"
    ],
    "name:spa_x_preferred":[
        "Northfield"
    ],
    "name:srp_x_preferred":[
        "\u041d\u043e\u0440\u0442\u0444\u0438\u043b\u0434"
    ],
    "name:swe_x_preferred":[
        "Northfield"
    ],
    "name:urd_x_preferred":[
        "\u0646\u0627\u0631\u062a\u06be\u0641\u06cc\u0644\u0688"
    ],
    "name:vol_x_preferred":[
        "Northfield"
    ],
    "wof:name":"Northfield",
    "wof:placetype":"locality"
},
  "geometry": {"coordinates":[-64.61601,44.46655],"type":"Point"}
}