{
  "type": "Feature",
  "properties": {
    "gn:admin1_code":"8",
    "gn:asciiname":"Heckston",
    "gn:country_code":"CA",
    "gn:dem":94,
    "gn:feature_class":"P",
    "gn:feature_code":"PPL",
    "gn:name":"Heckston",
    "gn:population":0,
    "gn:timezone":"America/Toronto",
    "iso:country":"CA",
    "wof:name":"Heckston",
    "wof:placetype":"locality"
},
  "geometry": {"coordinates":[-75.53081,44.96962],"type":"Point"}
}