{
  "type": "Feature",
  "properties": {
    "gn:admin1_code":"9.0",
    "gn:asciiname":"Brockton",
    "gn:country_code":"CA",
    "gn:dem":44,
    "gn:feature_class":"P",
    "gn:feature_code":"PPLL",
    "gn:name":"Brockton",
    "gn:population":0,
    "gn:timezone":"America/Halifax",
    "iso:country":"CA",
    "wof:name":"Brockton",
    "wof:placetype":"locality"
},
  "geometry": {"coordinates":[-64.24874,46.80015],"type":"Point"}
}