{
  "type": "Feature",
  "properties": {
    "gn:admin1_code":"3",
    "gn:asciiname":"Lyleton",
    "gn:country_code":"CA",
    "gn:dem":464,
    "gn:feature_class":"P",
    "gn:feature_code":"PPL",
    "gn:name":"Lyleton",
    "gn:population":0,
    "gn:timezone":"America/Winnipeg",
    "iso:country":"CA",
    "wof:name":"Lyleton",
    "wof:placetype":"locality"
},
  "geometry": {"coordinates":[-101.17867,49.05784],"type":"Point"}
}