{
  "type": "Feature",
  "properties": {
    "gn:admin1_code":"7",
    "gn:asciiname":"New Chester",
    "gn:country_code":"CA",
    "gn:dem":57,
    "gn:feature_class":"P",
    "gn:feature_code":"PPL",
    "gn:name":"New Chester",
    "gn:population":0,
    "gn:timezone":"America/Halifax",
    "iso:country":"CA",
    "wof:name":"New Chester",
    "wof:placetype":"locality"
},
  "geometry": {"coordinates":[-62.21399,45.03328],"type":"Point"}
}