{
  "type": "Feature",
  "properties": {
    "gn:admin1_code":"8",
    "gn:asciiname":"Peffers",
    "gn:country_code":"CA",
    "gn:dem":387,
    "gn:feature_class":"P",
    "gn:feature_code":"PPL",
    "gn:name":"Peffers",
    "gn:population":0,
    "gn:timezone":"America/Toronto",
    "iso:country":"CA",
    "wof:name":"Peffers",
    "wof:placetype":"locality"
},
  "geometry": {"coordinates":[-80.89972,43.62694000000001],"type":"Point"}
}