{
  "type": "Feature",
  "properties": {
    "gn:admin1_code":"2.0",
    "gn:admin2_code":"5924.0",
    "gn:asciiname":"Church House",
    "gn:country_code":"CA",
    "gn:dem":7,
    "gn:feature_class":"P",
    "gn:feature_code":"PPLL",
    "gn:name":"Church House",
    "gn:population":0,
    "gn:timezone":"America/Vancouver",
    "iso:country":"CA",
    "wof:name":"Church House",
    "wof:placetype":"locality"
},
  "geometry": {"coordinates":[-125.07628,50.33516],"type":"Point"}
}