{
  "type": "Feature",
  "properties": {
    "gn:country":"CA",
    "gn:fcode":"ADMD",
    "gn:population":0,
    "iso:country":"CA",
    "name:bar_x_preferred":[
        "Chatsworth"
    ],
    "name:cat_x_preferred":[
        "Chatsworth"
    ],
    "name:ceb_x_preferred":[
        "Chatsworth"
    ],
    "name:ces_x_preferred":[
        "Chatsworth"
    ],
    "name:deu_x_preferred":[
        "Chatsworth"
    ],
    "name:eng_x_preferred":[
        "Chatsworth"
    ],
    "name:fra_x_preferred":[
        "Chatsworth"
    ],
    "name:ita_x_preferred":[
        "Chatsworth"
    ],
    "name:nld_x_preferred":[
        "Chatsworth"
    ],
    "name:pol_x_preferred":[
        "Chatsworth"
    ],
    "name:srp_x_preferred":[
        "\u0427\u0430\u0442\u0441\u0432\u043e\u0440\u0442"
    ],
    "name:swe_x_preferred":[
        "Chatsworth"
    ],
    "name:ukr_x_preferred":[
        "\u0427\u0430\u0442\u0441\u0432\u043e\u0440\u0442"
    ],
    "name:vol_x_preferred":[
        "Chatsworth"
    ],
    "name:zho_x_preferred":[
        "\u67e5\u8328\u6c83\u601d"
    ],
    "qs:name":"Chatsworth",
    "qs:photos_9r":0,
    "qs:photos_sr":0,
    "qs:pop_sr":"0",
    "wd:wordcount":151,
    "wof:name":"Chatsworth",
    "wof:placetype":"localadmin",
    "wof:population":0
},
  "geometry": {"coordinates":[-80.87472,44.38339],"type":"Point"}
}