{
  "type": "Feature",
  "properties": {
    "gn:country":"CA",
    "gn:fcode":"ADMD",
    "gn:pop":0,
    "iso:country":"CA",
    "name:eng_x_preferred":[
        "Chatsworth"
    ],
    "qs:name":"Chatsworth",
    "qs:photos_9r":0,
    "qs:photos_sr":0,
    "qs:pop_sr":"0",
    "wd:wordcount":151,
    "wof:name":"Chatsworth",
    "wof:placetype":"localadmin",
    "wof:population":0
},
  "geometry": {"coordinates":[-80.87472,44.38339],"type":"Point"}
}