{
  "type": "Feature",
  "properties": {
    "gn:admin1_code":"7",
    "gn:asciiname":"McLellans Brook",
    "gn:country_code":"CA",
    "gn:dem":49,
    "gn:feature_class":"P",
    "gn:feature_code":"PPL",
    "gn:name":"McLellans Brook",
    "gn:population":0,
    "gn:timezone":"America/Halifax",
    "iso:country":"CA",
    "wof:name":"McLellans Brook",
    "wof:placetype":"locality"
},
  "geometry": {"coordinates":[-62.60351,45.54600000000001],"type":"Point"}
}