{
  "type": "Feature",
  "properties": {
    "gn:admin1_code":"10",
    "gn:admin2_code":"14.0",
    "gn:admin3_code":"64015.0",
    "gn:asciiname":"Mascouche-Ouest",
    "gn:country_code":"CA",
    "gn:dem":57,
    "gn:feature_class":"P",
    "gn:feature_code":"PPL",
    "gn:name":"Mascouche-Ouest",
    "gn:population":0,
    "gn:timezone":"America/Toronto",
    "iso:country":"CA",
    "wof:name":"Mascouche-Ouest",
    "wof:placetype":"locality"
},
  "geometry": {"coordinates":[-73.65653,45.75171],"type":"Point"}
}