{
  "type": "Feature",
  "properties": {
    "gn:admin1_code":"7",
    "gn:asciiname":"Glenkeen",
    "gn:country_code":"CA",
    "gn:dem":10,
    "gn:feature_class":"P",
    "gn:feature_code":"PPL",
    "gn:name":"Glenkeen",
    "gn:population":0,
    "gn:timezone":"America/Halifax",
    "iso:country":"CA",
    "name:gle_x_preferred":[
        "Gleann Caoin"
    ],
    "name:spa_x_preferred":[
        "Glenkeen"
    ],
    "wof:name":"Glenkeen",
    "wof:placetype":"locality"
},
  "geometry": {"coordinates":[-61.49831,45.42117],"type":"Point"}
}