{
  "type": "Feature",
  "properties": {
    "gn:admin1_code":"5",
    "gn:asciiname":"Lewin's Cove",
    "gn:country_code":"CA",
    "gn:dem":40,
    "gn:feature_class":"P",
    "gn:feature_code":"PPL",
    "gn:name":"Lewin's Cove",
    "gn:population":0,
    "gn:timezone":"America/St_Johns",
    "iso:country":"CA",
    "name:ceb_x_preferred":[
        "Lewin's Cove"
    ],
    "name:fra_x_preferred":[
        "Lewin's Cove"
    ],
    "name:nld_x_preferred":[
        "Lewin's Cove"
    ],
    "name:swe_x_preferred":[
        "Lewin's Cove"
    ],
    "wof:name":"Lewin's Cove",
    "wof:placetype":"locality"
},
  "geometry": {"coordinates":[-55.215,47.08324],"type":"Point"}
}