{
  "type": "Feature",
  "properties": {
    "gn:admin1_code":"2",
    "gn:asciiname":"Greendale",
    "gn:country_code":"CA",
    "gn:dem":7,
    "gn:feature_class":"P",
    "gn:feature_code":"PPL",
    "gn:name":"Greendale",
    "gn:population":0,
    "gn:timezone":"America/Vancouver",
    "iso:country":"CA",
    "name:bar_x_preferred":[
        "Greendale"
    ],
    "name:ceb_x_preferred":[
        "Greendale"
    ],
    "name:deu_x_preferred":[
        "Greendale"
    ],
    "name:ita_x_preferred":[
        "Greendale"
    ],
    "name:jpn_x_preferred":[
        "\u30b0\u30ea\u30fc\u30f3\u30c7\u30fc\u30eb"
    ],
    "name:nld_x_preferred":[
        "Greendale"
    ],
    "name:pol_x_preferred":[
        "Greendale"
    ],
    "name:por_x_preferred":[
        "Greendale"
    ],
    "name:srp_x_preferred":[
        "\u0413\u0440\u0438\u043d\u0434\u0435\u0458\u043b"
    ],
    "name:ukr_x_preferred":[
        "\u0413\u0440\u0456\u043d\u0434\u0435\u0439\u043b"
    ],
    "name:vol_x_preferred":[
        "Greendale"
    ],
    "wof:name":"Greendale",
    "wof:placetype":"locality"
},
  "geometry": {"coordinates":[-122.05,49.11667],"type":"Point"}
}