{
  "type": "Feature",
  "properties": {
    "gn:admin1_code":"2",
    "gn:asciiname":"Greendale",
    "gn:country_code":"CA",
    "gn:dem":7,
    "gn:feature_class":"P",
    "gn:feature_code":"PPL",
    "gn:name":"Greendale",
    "gn:population":0,
    "gn:timezone":"America/Vancouver",
    "iso:country":"CA",
    "wof:name":"Greendale",
    "wof:placetype":"locality"
},
  "geometry": {"coordinates":[-122.05,49.11667],"type":"Point"}
}