{
  "type": "Feature",
  "properties": {
    "gn:admin1_code":"7.0",
    "gn:asciiname":"Big Pond Centre",
    "gn:country_code":"CA",
    "gn:dem":66,
    "gn:feature_class":"P",
    "gn:feature_code":"PPLL",
    "gn:name":"Big Pond Centre",
    "gn:population":0,
    "gn:timezone":"America/Glace_Bay",
    "iso:country":"CA",
    "wof:name":"Big Pond Centre",
    "wof:placetype":"locality"
},
  "geometry": {"coordinates":[-60.56517,45.88344],"type":"Point"}
}