{
  "type": "Feature",
  "properties": {
    "gn:admin1_code":"8",
    "gn:asciiname":"Smooth Town",
    "gn:country_code":"CA",
    "gn:dem":214,
    "gn:feature_class":"P",
    "gn:feature_code":"PPL",
    "gn:name":"Smooth Town",
    "gn:population":0,
    "gn:timezone":"America/Toronto",
    "iso:country":"CA",
    "wof:name":"Smooth Town",
    "wof:placetype":"locality"
},
  "geometry": {"coordinates":[-80.07417,43.03222],"type":"Point"}
}