{
  "type": "Feature",
  "properties": {
    "iso:country":"CA",
    "qs_pg:aaroncc":"CA",
    "qs_pg:name":"Hilbre",
    "qs_pg:name_adm0":"Canada",
    "qs_pg:name_adm1":"Manitoba",
    "qs_pg:photos":2,
    "qs_pg:photos_1k":1,
    "qs_pg:photos_9k":1,
    "qs_pg:photos_9r":1,
    "qs_pg:photos_all":2,
    "qs_pg:photos_sr":1,
    "qs_pg:pop_sr":0,
    "qs_pg:qs_pg_placetype":"locality",
    "qs_pg:qs_pg_placetype_gp":"Town",
    "qs_pg:woe_adm0":23424775,
    "woe:adm0_id":23424775,
    "woe:name_adm0":"Canada",
    "woe:name_adm1":"Manitoba",
    "woe:placetype":"Town",
    "wof:name":"Hilbre",
    "wof:placetype":"locality"
},
  "geometry": {"coordinates":[-98.55993700000001,51.507727],"type":"Point"}
}