{
  "type": "Feature",
  "properties": {
    "gn:admin1_code":"8",
    "gn:asciiname":"Elmdale",
    "gn:country_code":"CA",
    "gn:dem":180,
    "gn:feature_class":"P",
    "gn:feature_code":"PPL",
    "gn:name":"Elmdale",
    "gn:population":0,
    "gn:timezone":"America/Toronto",
    "iso:country":"CA",
    "name:deu_x_preferred":[
        "Elmdale"
    ],
    "name:fas_x_preferred":[
        "\u0627\u0644\u0645\u062f\u06cc\u0644"
    ],
    "name:fra_x_preferred":[
        "Elmdale"
    ],
    "name:ido_x_preferred":[
        "Elmdale"
    ],
    "name:ita_x_preferred":[
        "Elmdale"
    ],
    "name:nld_x_preferred":[
        "Elmdale"
    ],
    "name:pol_x_preferred":[
        "Elmdale"
    ],
    "name:por_x_preferred":[
        "Elmdale"
    ],
    "name:rus_x_preferred":[
        "\u042d\u043b\u043c\u0434\u0435\u0439\u043b"
    ],
    "name:spa_x_preferred":[
        "Elmdale"
    ],
    "name:srp_x_preferred":[
        "\u0415\u043b\u043c\u0434\u0435\u0458\u043b"
    ],
    "name:vol_x_preferred":[
        "Elmdale"
    ],
    "wof:name":"Elmdale",
    "wof:placetype":"locality"
},
  "geometry": {"coordinates":[-82.48056,42.04278],"type":"Point"}
}