{
  "type": "Feature",
  "properties": {
    "gn:admin1_code":"8",
    "gn:asciiname":"Havilland",
    "gn:country_code":"CA",
    "gn:dem":184,
    "gn:feature_class":"P",
    "gn:feature_code":"PPL",
    "gn:name":"Havilland",
    "gn:population":0,
    "gn:timezone":"America/Toronto",
    "iso:country":"CA",
    "wof:name":"Havilland",
    "wof:placetype":"locality"
},
  "geometry": {"coordinates":[-84.40194,46.81667],"type":"Point"}
}