{
  "type": "Feature",
  "properties": {
    "iso:country":"CA",
    "name:eng_x_preferred":[
        "Inner Harbour"
    ],
    "qs:gn_adm0_cc":"CA",
    "qs:gn_local":5992500,
    "qs:gn_nam_loc":"kingston",
    "qs:gn_namadm1":"08",
    "qs:local_max":7347,
    "qs:local_sum":21295,
    "qs:localhoods":36,
    "qs:name":"Inner Harbour",
    "qs:name_adm0":"Canada",
    "qs:name_adm1":"Ontario",
    "qs:name_adm2":"Frontenac",
    "qs:name_local":"Kingston",
    "qs:photo_max":348,
    "qs:photo_sum":1310,
    "qs:placetype":"Suburb",
    "qs:quad_count":44,
    "qs:woe_adm0":23424775,
    "qs:woe_adm1":2344922,
    "qs:woe_adm2":29375131,
    "qs:woe_lau":0,
    "qs:woe_local":4145,
    "qs:woe_ver":"7.10.0",
    "wd:wordcount":68,
    "wof:lang":[
        "eng"
    ],
    "wof:name":"Inner Harbour",
    "wof:placetype":"neighbourhood"
},
  "geometry": {"coordinates":[-76.476789,44.237551],"type":"Point"}
}