{
  "type": "Feature",
  "properties": {
    "gn:admin1_code":"10",
    "gn:admin2_code":"7.0",
    "gn:admin3_code":"84045.0",
    "gn:asciiname":"Leach Lake",
    "gn:country_code":"CA",
    "gn:dem":204,
    "gn:feature_class":"P",
    "gn:feature_code":"PPL",
    "gn:name":"Leach Lake",
    "gn:population":0,
    "gn:timezone":"America/Toronto",
    "iso:country":"CA",
    "wof:name":"Leach Lake",
    "wof:placetype":"locality"
},
  "geometry": {"coordinates":[-76.48278000000001,45.79472],"type":"Point"}
}