{
  "type": "Feature",
  "properties": {
    "gn:admin1_code":"8",
    "gn:asciiname":"Lawton's Corners",
    "gn:country_code":"CA",
    "gn:dem":227,
    "gn:feature_class":"P",
    "gn:feature_code":"PPLL",
    "gn:name":"Lawton's Corners",
    "gn:population":0,
    "gn:timezone":"America/Toronto",
    "iso:country":"CA",
    "wof:name":"Lawton's Corners",
    "wof:placetype":"locality"
},
  "geometry": {"coordinates":[-81.12223,42.70289],"type":"Point"}
}