{
  "type": "Feature",
  "properties": {
    "gn:admin1_code":"8",
    "gn:asciiname":"McFarlane Lake",
    "gn:country_code":"CA",
    "gn:dem":233,
    "gn:feature_class":"P",
    "gn:feature_code":"PPL",
    "gn:name":"McFarlane Lake",
    "gn:population":0,
    "gn:timezone":"America/Toronto",
    "iso:country":"CA",
    "wof:name":"McFarlane Lake",
    "wof:placetype":"locality"
},
  "geometry": {"coordinates":[-80.94504000000001,46.43512],"type":"Point"}
}