{
  "type": "Feature",
  "properties": {
    "gn:admin1_code":"8",
    "gn:asciiname":"Vandeleur",
    "gn:country_code":"CA",
    "gn:dem":415,
    "gn:feature_class":"P",
    "gn:feature_code":"PPL",
    "gn:name":"Vandeleur",
    "gn:population":0,
    "gn:timezone":"America/Toronto",
    "iso:country":"CA",
    "wof:name":"Vandeleur",
    "wof:placetype":"locality"
},
  "geometry": {"coordinates":[-80.55944000000002,44.3325],"type":"Point"}
}