{
  "type": "Feature",
  "properties": {
    "gn:admin1_code":"10.0",
    "gn:admin2_code":"16",
    "gn:asciiname":"Brooklet",
    "gn:country_code":"CA",
    "gn:dem":148,
    "gn:feature_class":"P",
    "gn:feature_code":"PPL",
    "gn:name":"Brooklet",
    "gn:population":0,
    "gn:timezone":"America/Toronto",
    "iso:country":"CA",
    "name:ceb_x_preferred":[
        "Brooklet"
    ],
    "name:swe_x_preferred":[
        "Brooklet"
    ],
    "wof:name":"Brooklet",
    "wof:placetype":"locality"
},
  "geometry": {"coordinates":[-74.04711,45.00699],"type":"Point"}
}