{
  "type": "Feature",
  "properties": {
    "gn:admin1_code":"7",
    "gn:asciiname":"Prince Albert",
    "gn:country_code":"CA",
    "gn:dem":157,
    "gn:feature_class":"P",
    "gn:feature_code":"PPL",
    "gn:name":"Prince Albert",
    "gn:population":0,
    "gn:timezone":"America/Halifax",
    "iso:country":"CA",
    "wof:name":"Prince Albert",
    "wof:placetype":"locality"
},
  "geometry": {"coordinates":[-65.05211,45.00007],"type":"Point"}
}