{
  "type": "Feature",
  "properties": {
    "gn:admin1_code":"2.0",
    "gn:asciiname":"Cypress Park",
    "gn:country_code":"CA",
    "gn:dem":41,
    "gn:feature_class":"P",
    "gn:feature_code":"PPL",
    "gn:name":"Cypress Park",
    "gn:population":0,
    "gn:timezone":"America/Vancouver",
    "iso:country":"CA",
    "wof:name":"Cypress Park",
    "wof:placetype":"locality"
},
  "geometry": {"coordinates":[-123.23972000000001,49.34278],"type":"Point"}
}