{
  "type": "Feature",
  "properties": {
    "gn:admin1_code":"8",
    "gn:asciiname":"L'Amable",
    "gn:country_code":"CA",
    "gn:dem":360,
    "gn:feature_class":"P",
    "gn:feature_code":"PPL",
    "gn:name":"L'Amable",
    "gn:population":0,
    "gn:timezone":"America/Toronto",
    "iso:country":"CA",
    "wof:name":"L'Amable",
    "wof:placetype":"locality"
},
  "geometry": {"coordinates":[-77.78778,45.01111],"type":"Point"}
}