{
  "type": "Feature",
  "properties": {
    "gn:admin1_code":"1",
    "gn:asciiname":"Fawcett",
    "gn:country_code":"CA",
    "gn:dem":615,
    "gn:feature_class":"P",
    "gn:feature_code":"PPL",
    "gn:name":"Fawcett",
    "gn:population":0,
    "gn:timezone":"America/Edmonton",
    "iso:country":"CA",
    "wof:name":"Fawcett",
    "wof:placetype":"locality"
},
  "geometry": {"coordinates":[-114.08542,54.53345],"type":"Point"}
}