{
  "type": "Feature",
  "properties": {
    "gn:admin1_code":"3",
    "gn:asciiname":"Haywood",
    "gn:country_code":"CA",
    "gn:dem":293,
    "gn:feature_class":"P",
    "gn:feature_code":"PPL",
    "gn:name":"Haywood",
    "gn:population":0,
    "gn:timezone":"America/Winnipeg",
    "iso:country":"CA",
    "wof:name":"Haywood",
    "wof:placetype":"locality"
},
  "geometry": {"coordinates":[-98.19714,49.66671],"type":"Point"}
}