{
  "type": "Feature",
  "properties": {
    "gn:admin1_code":"8",
    "gn:asciiname":"Hopkins Corners",
    "gn:country_code":"CA",
    "gn:dem":138,
    "gn:feature_class":"P",
    "gn:feature_code":"PPL",
    "gn:name":"Hopkins Corners",
    "gn:population":0,
    "gn:timezone":"America/Toronto",
    "iso:country":"CA",
    "wof:name":"Hopkins Corners",
    "wof:placetype":"locality"
},
  "geometry": {"coordinates":[-79.92667,43.29],"type":"Point"}
}