{
  "type": "Feature",
  "properties": {
    "gn:admin1_code":"2",
    "gn:admin2_code":"5945.0",
    "gn:asciiname":"Namu",
    "gn:country_code":"CA",
    "gn:dem":18,
    "gn:feature_class":"P",
    "gn:feature_code":"PPLL",
    "gn:name":"Namu",
    "gn:population":0,
    "gn:timezone":"America/Vancouver",
    "iso:country":"CA",
    "name:eng_x_preferred":[
        "Namu"
    ],
    "wof:name":"Namu",
    "wof:placetype":"locality"
},
  "geometry": {"coordinates":[-127.86575000000001,51.86063],"type":"Point"}
}