{
  "type": "Feature",
  "properties": {
    "gn:admin1_code":"1",
    "gn:asciiname":"Sion",
    "gn:country_code":"CA",
    "gn:dem":693,
    "gn:feature_class":"P",
    "gn:feature_code":"PPLL",
    "gn:name":"Sion",
    "gn:population":0,
    "gn:timezone":"America/Edmonton",
    "iso:country":"CA",
    "name:als_x_preferred":[
        "Sion"
    ],
    "name:bre_x_preferred":[
        "Sion"
    ],
    "name:bul_x_preferred":[
        "\u0421\u0438\u043e\u043d"
    ],
    "name:cat_x_preferred":[
        "Sion"
    ],
    "name:ceb_x_preferred":[
        "Sion"
    ],
    "name:ces_x_preferred":[
        "Sion"
    ],
    "name:cym_x_preferred":[
        "Sion"
    ],
    "name:dan_x_preferred":[
        "Sion"
    ],
    "name:deu_x_preferred":[
        "Sion"
    ],
    "name:eus_x_preferred":[
        "Sion"
    ],
    "name:fin_x_preferred":[
        "Sion"
    ],
    "name:fra_x_preferred":[
        "Sion"
    ],
    "name:hun_x_preferred":[
        "Sion"
    ],
    "name:ind_x_preferred":[
        "Sion"
    ],
    "name:ita_x_preferred":[
        "Sion"
    ],
    "name:jpn_x_preferred":[
        "\u30b7\u30aa\u30f3"
    ],
    "name:kor_x_preferred":[
        "\uc2dc\uc628"
    ],
    "name:lat_x_preferred":[
        "Sion"
    ],
    "name:lit_x_preferred":[
        "Sionas"
    ],
    "name:nld_x_preferred":[
        "Sion"
    ],
    "name:nor_x_preferred":[
        "Sion"
    ],
    "name:pms_x_preferred":[
        "Sion"
    ],
    "name:por_x_preferred":[
        "Sion"
    ],
    "name:ron_x_preferred":[
        "Sion"
    ],
    "name:rus_x_preferred":[
        "\u0421\u0438\u043e\u043d"
    ],
    "name:slk_x_preferred":[
        "Sion"
    ],
    "name:spa_x_preferred":[
        "Sion"
    ],
    "name:swe_x_preferred":[
        "Sion"
    ],
    "wof:name":"Sion",
    "wof:placetype":"locality"
},
  "geometry": {"coordinates":[-114.15208,53.88344],"type":"Point"}
}