{
  "type": "Feature",
  "properties": {
    "iso:country":"CA",
    "name:eng_x_preferred":[
        "Bright's Grove"
    ],
    "name:eng_x_variant":[
        "Brights Grove"
    ],
    "qs:gn_adm0_cc":"CA",
    "qs:gn_local":6141190,
    "qs:gn_nam_loc":"sarnia",
    "qs:gn_namadm1":"08",
    "qs:local_max":1209,
    "qs:local_sum":4368,
    "qs:localhoods":10,
    "qs:name":"Bright's Grove",
    "qs:name_adm0":"Canada",
    "qs:name_adm1":"Ontario",
    "qs:name_adm2":"Lambton",
    "qs:name_local":"Sarnia",
    "qs:photo_max":32,
    "qs:photo_sum":131,
    "qs:placetype":"Suburb",
    "qs:quad_count":18,
    "qs:woe_adm0":23424775,
    "qs:woe_adm1":2344922,
    "qs:woe_adm2":29375144,
    "qs:woe_funk":"Parented by a neighborhood",
    "qs:woe_lau":0,
    "qs:woe_local":1646,
    "qs:woe_ver":"7.10.0",
    "wof:lang":[
        "eng"
    ],
    "wof:name":"Bright's Grove",
    "wof:placetype":"neighbourhood"
},
  "geometry": {"coordinates":[-82.250235,43.031611],"type":"Point"}
}