{
  "type": "Feature",
  "properties": {
    "iso:country":"CA",
    "name:ceb_x_preferred":[
        "Carnarvon"
    ],
    "name:ces_x_preferred":[
        "Carnarvon"
    ],
    "name:cym_x_preferred":[
        "Caernarfon"
    ],
    "name:deu_x_preferred":[
        "Carnarvon"
    ],
    "name:fra_x_preferred":[
        "Carnarvon"
    ],
    "name:ind_x_preferred":[
        "Caernarvon"
    ],
    "name:ita_x_preferred":[
        "Caernarvon"
    ],
    "name:jav_x_preferred":[
        "Caernarvon"
    ],
    "name:mlg_x_preferred":[
        "Carnarvon"
    ],
    "name:nld_x_preferred":[
        "Carnarvon"
    ],
    "name:pol_x_preferred":[
        "Caernarvon"
    ],
    "name:swe_x_preferred":[
        "Carnarvon"
    ],
    "name:ukr_x_preferred":[
        "\u041a\u0435\u0440\u043d\u0430\u0440\u0432\u043e\u043d"
    ],
    "qs_pg:aaroncc":"CA",
    "qs_pg:name":"Carnarvon",
    "qs_pg:name_adm0":"Canada",
    "qs_pg:name_adm1":"Ontario",
    "qs_pg:photos":310,
    "qs_pg:photos_1k":63,
    "qs_pg:photos_9k":1,
    "qs_pg:photos_9r":5,
    "qs_pg:photos_all":310,
    "qs_pg:photos_sr":5,
    "qs_pg:pop_sr":0,
    "qs_pg:qs_pg_placetype":"locality",
    "qs_pg:qs_pg_placetype_gp":"Town",
    "qs_pg:woe_adm0":23424775,
    "woe:adm0_id":23424775,
    "woe:name_adm0":"Canada",
    "woe:name_adm1":"Ontario",
    "woe:placetype":"Town",
    "wof:name":"Carnarvon",
    "wof:placetype":"locality"
},
  "geometry": {"coordinates":[-78.7045305,45.023977],"type":"Point"}
}