{
  "type": "Feature",
  "properties": {
    "gn:admin1_code":"8",
    "gn:asciiname":"Kilcoo Camp",
    "gn:country_code":"CA",
    "gn:dem":285,
    "gn:feature_class":"P",
    "gn:feature_code":"PPL",
    "gn:name":"Kilcoo Camp",
    "gn:population":0,
    "gn:timezone":"America/Toronto",
    "iso:country":"CA",
    "wof:name":"Kilcoo Camp",
    "wof:placetype":"locality"
},
  "geometry": {"coordinates":[-78.76380999999998,44.85651],"type":"Point"}
}