{
  "type": "Feature",
  "properties": {
    "gn:admin1_code":"10",
    "gn:admin2_code":"4.0",
    "gn:admin3_code":"90012.0",
    "gn:asciiname":"Fitzpatrick",
    "gn:country_code":"CA",
    "gn:dem":152,
    "gn:feature_class":"P",
    "gn:feature_code":"PPL",
    "gn:name":"Fitzpatrick",
    "gn:population":0,
    "gn:timezone":"America/Toronto",
    "iso:country":"CA",
    "name:deu_x_preferred":[
        "Fitzpatrick"
    ],
    "name:fra_x_preferred":[
        "Fitzpatrick"
    ],
    "name:jpn_x_preferred":[
        "\u30d5\u30a3\u30c3\u30c4\u30d1\u30c8\u30ea\u30c3\u30af"
    ],
    "name:pol_x_preferred":[
        "Fitzpatrick"
    ],
    "name:rus_x_preferred":[
        "\u0424\u0438\u0446\u043f\u0430\u0442\u0440\u0438\u043a"
    ],
    "name:ukr_x_preferred":[
        "\u0424\u0456\u0446\u043f\u0430\u0442\u0440\u0456\u043a"
    ],
    "name:zho_x_preferred":[
        "\u83f2\u8332\u67cf\u5fb7\u70c8"
    ],
    "wof:name":"Fitzpatrick",
    "wof:placetype":"locality"
},
  "geometry": {"coordinates":[-72.77444,47.48417],"type":"Point"}
}