{
  "type": "Feature",
  "properties": {
    "gn:admin1_code":"8",
    "gn:asciiname":"Kuhryville",
    "gn:country_code":"CA",
    "gn:dem":368,
    "gn:feature_class":"P",
    "gn:feature_code":"PPL",
    "gn:name":"Kuhryville",
    "gn:population":0,
    "gn:timezone":"America/Toronto",
    "iso:country":"CA",
    "wof:name":"Kuhryville",
    "wof:placetype":"locality"
},
  "geometry": {"coordinates":[-81.03471999999999,43.52611],"type":"Point"}
}