{
  "type": "Feature",
  "properties": {
    "iso:country":"CA",
    "qs_pg:aaroncc":"CA",
    "qs_pg:name":"Burrard Inlet Indian Reserve 3",
    "qs_pg:name_adm0":"Canada",
    "qs_pg:name_adm1":"British Columbia",
    "qs_pg:photos":1675,
    "qs_pg:photos_1k":339,
    "qs_pg:photos_9k":7,
    "qs_pg:photos_9r":8,
    "qs_pg:photos_all":1675,
    "qs_pg:photos_sr":14,
    "qs_pg:pop_sr":0,
    "qs_pg:qs_pg_placetype":"locality",
    "qs_pg:qs_pg_placetype_gp":"Town",
    "qs_pg:woe_adm0":23424775,
    "woe:adm0_id":23424775,
    "woe:name_adm0":"Canada",
    "woe:name_adm1":"British Columbia",
    "woe:placetype":"Town",
    "wof:name":"Burrard Inlet Indian Reserve 3",
    "wof:placetype":"locality"
},
  "geometry": {"coordinates":[-122.999871,49.281027],"type":"Point"}
}