{
  "type": "Feature",
  "properties": {
    "gn:admin1_code":"7",
    "gn:asciiname":"Spa Springs",
    "gn:country_code":"CA",
    "gn:dem":56,
    "gn:feature_class":"P",
    "gn:feature_code":"PPL",
    "gn:name":"Spa Springs",
    "gn:population":0,
    "gn:timezone":"America/Halifax",
    "iso:country":"CA",
    "name:gla_x_preferred":[
        "Spa Springs"
    ],
    "wof:name":"Spa Springs",
    "wof:placetype":"locality"
},
  "geometry": {"coordinates":[-65.04949999999999,44.97948],"type":"Point"}
}