{
  "type": "Feature",
  "properties": {
    "iso:country":"CA",
    "name:deu_x_preferred":[
        "Moonstone"
    ],
    "name:heb_x_preferred":[
        "\u05d0\u05d1\u05df \u05d4\u05d9\u05e8\u05d7"
    ],
    "name:ita_x_preferred":[
        "Moonstone"
    ],
    "name:jpn_x_preferred":[
        "\u30e0\u30fc\u30f3\u30b9\u30c8\u30fc\u30f3"
    ],
    "name:nld_x_preferred":[
        "Maansteen"
    ],
    "name:nor_x_preferred":[
        "M\u00e5nestein"
    ],
    "name:rus_x_preferred":[
        "\u041b\u0443\u043d\u043d\u044b\u0439 \u043a\u0430\u043c\u0435\u043d\u044c"
    ],
    "name:ukr_x_preferred":[
        "\u041c\u0456\u0441\u044f\u0447\u043d\u0438\u0439 \u043a\u0430\u043c\u0456\u043d\u044c"
    ],
    "qs_pg:aaroncc":"CA",
    "qs_pg:name":"Moonstone",
    "qs_pg:name_adm0":"Canada",
    "qs_pg:name_adm1":"Ontario",
    "qs_pg:photos":200,
    "qs_pg:photos_1k":41,
    "qs_pg:photos_9k":1,
    "qs_pg:photos_9r":4,
    "qs_pg:photos_all":200,
    "qs_pg:photos_sr":4,
    "qs_pg:pop_sr":0,
    "qs_pg:qs_pg_placetype":"locality",
    "qs_pg:qs_pg_placetype_gp":"Town",
    "qs_pg:woe_adm0":23424775,
    "woe:adm0_id":23424775,
    "woe:name_adm0":"Canada",
    "woe:name_adm1":"Ontario",
    "woe:placetype":"Town",
    "wof:name":"Moonstone",
    "wof:placetype":"locality"
},
  "geometry": {"coordinates":[-79.657573,44.652596],"type":"Point"}
}