{
  "type": "Feature",
  "properties": {
    "gn:admin1_code":"2",
    "gn:asciiname":"Steamboat",
    "gn:country_code":"CA",
    "gn:dem":766,
    "gn:feature_class":"P",
    "gn:feature_code":"PPLL",
    "gn:name":"Steamboat",
    "gn:population":0,
    "gn:timezone":"America/Fort_Nelson",
    "iso:country":"CA",
    "wof:name":"Steamboat",
    "wof:placetype":"locality"
},
  "geometry": {"coordinates":[-123.71973,58.68298000000001],"type":"Point"}
}