{
  "type": "Feature",
  "properties": {
    "gn:admin1_code":"7",
    "gn:asciiname":"Halls Harbour",
    "gn:country_code":"CA",
    "gn:dem":19,
    "gn:feature_class":"P",
    "gn:feature_code":"PPL",
    "gn:name":"Halls Harbour",
    "gn:population":0,
    "gn:timezone":"America/Halifax",
    "iso:country":"CA",
    "name:eng_x_preferred":[
        "Hall's Harbour"
    ],
    "wof:name":"Halls Harbour",
    "wof:placetype":"locality"
},
  "geometry": {"coordinates":[-64.61830999999999,45.20154],"type":"Point"}
}