{
  "type": "Feature",
  "properties": {
    "gn:admin1_code":"8",
    "gn:asciiname":"Queensway Gardens",
    "gn:country_code":"CA",
    "gn:dem":195,
    "gn:feature_class":"P",
    "gn:feature_code":"PPL",
    "gn:name":"Queensway Gardens",
    "gn:population":0,
    "gn:timezone":"America/Toronto",
    "iso:country":"CA",
    "wof:name":"Queensway Gardens",
    "wof:placetype":"locality"
},
  "geometry": {"coordinates":[-79.11306,43.10972],"type":"Point"}
}