{
  "type": "Feature",
  "properties": {
    "gn:admin1_code":"1.0",
    "gn:asciiname":"Chin",
    "gn:country_code":"CA",
    "gn:dem":846,
    "gn:feature_class":"P",
    "gn:feature_code":"PPLL",
    "gn:name":"Chin",
    "gn:population":0,
    "gn:timezone":"America/Edmonton",
    "iso:country":"CA",
    "name:fra_x_preferred":[
        "Chin"
    ],
    "wof:name":"Chin",
    "wof:placetype":"locality"
},
  "geometry": {"coordinates":[-112.45183,49.76672],"type":"Point"}
}