{
  "type": "Feature",
  "properties": {
    "gn:admin1_code":"8",
    "gn:asciiname":"The Slash",
    "gn:country_code":"CA",
    "gn:dem":189,
    "gn:feature_class":"P",
    "gn:feature_code":"PPL",
    "gn:name":"The Slash",
    "gn:population":0,
    "gn:timezone":"America/Toronto",
    "iso:country":"CA",
    "wof:name":"The Slash",
    "wof:placetype":"locality"
},
  "geometry": {"coordinates":[-81.96117,45.62401],"type":"Point"}
}