{
  "type": "Feature",
  "properties": {
    "gn:admin1_code":"1",
    "gn:asciiname":"Grave Flats",
    "gn:country_code":"CA",
    "gn:dem":1551,
    "gn:feature_class":"P",
    "gn:feature_code":"PPLL",
    "gn:name":"Grave Flats",
    "gn:population":0,
    "gn:timezone":"America/Edmonton",
    "iso:country":"CA",
    "wof:name":"Grave Flats",
    "wof:placetype":"locality"
},
  "geometry": {"coordinates":[-116.83557,52.88336],"type":"Point"}
}