{
  "type": "Feature",
  "properties": {
    "gn:admin1_code":"2",
    "gn:asciiname":"Farrell Creek",
    "gn:country_code":"CA",
    "gn:dem":438,
    "gn:feature_class":"P",
    "gn:feature_code":"PPLL",
    "gn:name":"Farrell Creek",
    "gn:population":0,
    "gn:timezone":"America/Dawson_Creek",
    "iso:country":"CA",
    "wof:name":"Farrell Creek",
    "wof:placetype":"locality"
},
  "geometry": {"coordinates":[-121.71972,56.1166],"type":"Point"}
}