{
  "type": "Feature",
  "properties": {
    "gn:admin1_code":"8",
    "gn:asciiname":"Filey Beach",
    "gn:country_code":"CA",
    "gn:dem":227,
    "gn:feature_class":"P",
    "gn:feature_code":"PPL",
    "gn:name":"Filey Beach",
    "gn:population":0,
    "gn:timezone":"America/Toronto",
    "iso:country":"CA",
    "wof:name":"Filey Beach",
    "wof:placetype":"locality"
},
  "geometry": {"coordinates":[-79.40805999999998,44.31722],"type":"Point"}
}