{
  "type": "Feature",
  "properties": {
    "gn:admin1_code":"8.0",
    "gn:asciiname":"Bryanston",
    "gn:country_code":"CA",
    "gn:dem":296,
    "gn:feature_class":"P",
    "gn:feature_code":"PPL",
    "gn:name":"Bryanston",
    "gn:population":0,
    "gn:timezone":"America/Toronto",
    "iso:country":"CA",
    "name:ceb_x_preferred":[
        "Bryanston"
    ],
    "name:cym_x_preferred":[
        "Bryanston"
    ],
    "name:ita_x_preferred":[
        "Bryanston"
    ],
    "name:nld_x_preferred":[
        "Bryanston"
    ],
    "name:pol_x_preferred":[
        "Bryanston"
    ],
    "name:swe_x_preferred":[
        "Bryanston"
    ],
    "wof:name":"Bryanston",
    "wof:placetype":"locality"
},
  "geometry": {"coordinates":[-81.26916999999997,43.12556],"type":"Point"}
}