{
  "type": "Feature",
  "properties": {
    "gn:admin1_code":"8.0",
    "gn:asciiname":"Beech Corners",
    "gn:country_code":"CA",
    "gn:dem":315,
    "gn:feature_class":"P",
    "gn:feature_code":"PPL",
    "gn:name":"Beech Corners",
    "gn:population":0,
    "gn:timezone":"America/Toronto",
    "iso:country":"CA",
    "wof:name":"Beech Corners",
    "wof:placetype":"locality"
},
  "geometry": {"coordinates":[-77.05540000000001,44.94625],"type":"Point"}
}