{
  "type": "Feature",
  "properties": {
    "gn:admin1_code":"8.0",
    "gn:asciiname":"Chenaux",
    "gn:country_code":"CA",
    "gn:dem":158,
    "gn:feature_class":"P",
    "gn:feature_code":"PPL",
    "gn:name":"Chenaux",
    "gn:population":0,
    "gn:timezone":"America/Toronto",
    "iso:country":"CA",
    "wof:name":"Chenaux",
    "wof:placetype":"locality"
},
  "geometry": {"coordinates":[-76.71639,45.57222],"type":"Point"}
}