{
  "type": "Feature",
  "properties": {
    "gn:admin1_code":"10.0",
    "gn:admin2_code":"17.0",
    "gn:admin3_code":"39130.0",
    "gn:asciiname":"Domaine-Thibodeau",
    "gn:country_code":"CA",
    "gn:dem":86,
    "gn:feature_class":"P",
    "gn:feature_code":"PPL",
    "gn:name":"Domaine-Thibodeau",
    "gn:population":0,
    "gn:timezone":"America/Toronto",
    "iso:country":"CA",
    "wof:name":"Domaine-Thibodeau",
    "wof:placetype":"locality"
},
  "geometry": {"coordinates":[-72.19121,46.07781],"type":"Point"}
}