{
  "type": "Feature",
  "properties": {
    "iso:country":"CA",
    "name:eng_x_preferred":[
        "Mira Gut"
    ],
    "name:gla_x_preferred":[
        "Gut Mhira"
    ],
    "qs:name":"Mira Gut",
    "qs:name_adm0":"Canada",
    "qs:name_adm1":"Nova Scotia",
    "qs:photos":143,
    "qs:photos_1k":29,
    "qs:photos_9k":1,
    "qs:photos_9r":3,
    "qs:photos_all":143,
    "qs:photos_sr":3,
    "qs:placetype":"Town",
    "qs:pop_sr":"0",
    "wd:wordcount":79,
    "wof:name":"Mira Gut",
    "wof:placetype":"locality"
},
  "geometry": {"coordinates":[-59.961662,46.03674],"type":"Point"}
}