{
  "type": "Feature",
  "properties": {
    "gn:country":"CA",
    "gn:fcode":"PPL",
    "gn:population":0,
    "iso:country":"CA",
    "name:eng_x_preferred":[
        "Lance Cove"
    ],
    "name:eng_x_variant":[
        "Lower Lance Cove"
    ],
    "qs:name":"Lance Cove",
    "qs:name_adm0":"Canada",
    "qs:name_adm1":"Newfoundland and Labrador",
    "qs:photos":38,
    "qs:photos_1k":8,
    "qs:photos_9k":1,
    "qs:photos_9r":2,
    "qs:photos_all":38,
    "qs:photos_sr":2,
    "qs:placetype":"Town",
    "qs:pop_sr":"4",
    "wd:wordcount":32,
    "wof:name":"Lance Cove",
    "wof:placetype":"locality",
    "wof:population":0
},
  "geometry": {"coordinates":[-53.83142,47.6832],"type":"Point"}
}