{
  "type": "Feature",
  "properties": {
    "gn:admin1_code":"10.0",
    "gn:admin2_code":"7.0",
    "gn:admin3_code":"83050.0",
    "gn:asciiname":"Chalifoux",
    "gn:country_code":"CA",
    "gn:dem":158,
    "gn:feature_class":"P",
    "gn:feature_code":"PPL",
    "gn:name":"Chalifoux",
    "gn:population":0,
    "gn:timezone":"America/Toronto",
    "iso:country":"CA",
    "wof:name":"Chalifoux",
    "wof:placetype":"locality"
},
  "geometry": {"coordinates":[-75.93222,46.22278],"type":"Point"}
}