{
  "type": "Feature",
  "properties": {
    "gn:admin1_code":"8",
    "gn:asciiname":"Lorrain",
    "gn:country_code":"CA",
    "gn:dem":281,
    "gn:feature_class":"P",
    "gn:feature_code":"PPL",
    "gn:name":"Lorrain",
    "gn:population":0,
    "gn:timezone":"America/Toronto",
    "iso:country":"CA",
    "name:deu_x_preferred":[
        "Lorrain"
    ],
    "name:fra_x_preferred":[
        "Lorrain"
    ],
    "name:ukr_x_preferred":[
        "\u041b\u043e\u0440\u0440\u0435\u043d"
    ],
    "wof:name":"Lorrain",
    "wof:placetype":"locality"
},
  "geometry": {"coordinates":[-79.76778,47.36083],"type":"Point"}
}