{
  "type": "Feature",
  "properties": {
    "gn:admin1_code":"8",
    "gn:asciiname":"Lorrain",
    "gn:country_code":"CA",
    "gn:dem":281,
    "gn:feature_class":"P",
    "gn:feature_code":"PPL",
    "gn:name":"Lorrain",
    "gn:population":0,
    "gn:timezone":"America/Toronto",
    "iso:country":"CA",
    "wof:name":"Lorrain",
    "wof:placetype":"locality"
},
  "geometry": {"coordinates":[-79.76778,47.36083],"type":"Point"}
}