{
  "type": "Feature",
  "properties": {
    "gn:admin1_code":"11.0",
    "gn:asciiname":"Clayridge",
    "gn:country_code":"CA",
    "gn:dem":599,
    "gn:feature_class":"P",
    "gn:feature_code":"PPLL",
    "gn:name":"Clayridge",
    "gn:population":0,
    "gn:timezone":"America/Regina",
    "iso:country":"CA",
    "wof:name":"Clayridge",
    "wof:placetype":"locality"
},
  "geometry": {"coordinates":[-102.08427,50.43331],"type":"Point"}
}