{
  "type": "Feature",
  "properties": {
    "gn:admin1_code":"1",
    "gn:asciiname":"Weberville",
    "gn:country_code":"CA",
    "gn:dem":501,
    "gn:feature_class":"P",
    "gn:feature_code":"PPLL",
    "gn:name":"Weberville",
    "gn:population":0,
    "gn:timezone":"America/Edmonton",
    "iso:country":"CA",
    "wof:name":"Weberville",
    "wof:placetype":"locality"
},
  "geometry": {"coordinates":[-117.31938999999998,56.2834],"type":"Point"}
}