{
  "type": "Feature",
  "properties": {
    "gn:admin1_code":"7",
    "gn:asciiname":"Fairmount",
    "gn:country_code":"CA",
    "gn:dem":77,
    "gn:feature_class":"P",
    "gn:feature_code":"PPL",
    "gn:name":"Fairmount",
    "gn:population":0,
    "gn:timezone":"America/Halifax",
    "iso:country":"CA",
    "wof:name":"Fairmount",
    "wof:placetype":"locality"
},
  "geometry": {"coordinates":[-63.63475,44.64428],"type":"Point"}
}