{
  "type": "Feature",
  "properties": {
    "gn:admin1_code":"7",
    "gn:asciiname":"Fairmount",
    "gn:country_code":"CA",
    "gn:dem":77,
    "gn:feature_class":"P",
    "gn:feature_code":"PPL",
    "gn:name":"Fairmount",
    "gn:population":0,
    "gn:timezone":"America/Halifax",
    "iso:country":"CA",
    "name:cat_x_preferred":[
        "Fairmount"
    ],
    "name:ceb_x_preferred":[
        "Fairmount"
    ],
    "name:deu_x_preferred":[
        "Fairmount"
    ],
    "name:est_x_preferred":[
        "Fairmount"
    ],
    "name:ita_x_preferred":[
        "Fairmount"
    ],
    "name:nld_x_preferred":[
        "Fairmount"
    ],
    "name:pol_x_preferred":[
        "Fairmount"
    ],
    "name:por_x_preferred":[
        "Fairmount"
    ],
    "name:spa_x_preferred":[
        "Fairmount"
    ],
    "name:srp_x_preferred":[
        "\u0424\u0435\u0440\u043c\u0430\u0443\u043d\u0442"
    ],
    "name:ukr_x_preferred":[
        "\u0424\u0435\u0439\u0440\u043c\u0430\u0443\u043d\u0442"
    ],
    "name:urd_x_preferred":[
        "\u0641\u06cc\u0626\u0631\u0645\u0627\u0624\u0646\u0679"
    ],
    "name:vol_x_preferred":[
        "Fairmount"
    ],
    "wof:name":"Fairmount",
    "wof:placetype":"locality"
},
  "geometry": {"coordinates":[-63.63475,44.64428],"type":"Point"}
}