{
  "type": "Feature",
  "properties": {
    "gn:admin1_code":"4",
    "gn:admin2_code":"1301.0",
    "gn:asciiname":"Simms Corner",
    "gn:country_code":"CA",
    "gn:dem":34,
    "gn:feature_class":"P",
    "gn:feature_code":"PPLL",
    "gn:name":"Simms Corner",
    "gn:population":0,
    "gn:timezone":"America/Moncton",
    "iso:country":"CA",
    "wof:name":"Simms Corner",
    "wof:placetype":"locality"
},
  "geometry": {"coordinates":[-66.09278,45.2564],"type":"Point"}
}