{
  "type": "Feature",
  "properties": {
    "gn:admin1_code":"1",
    "gn:asciiname":"Helina",
    "gn:country_code":"CA",
    "gn:dem":600,
    "gn:feature_class":"P",
    "gn:feature_code":"PPLL",
    "gn:name":"Helina",
    "gn:population":0,
    "gn:timezone":"America/Edmonton",
    "iso:country":"CA",
    "name:ceb_x_preferred":[
        "Helina"
    ],
    "name:min_x_preferred":[
        "Helina"
    ],
    "name:ron_x_preferred":[
        "Helina"
    ],
    "name:swe_x_preferred":[
        "Helina"
    ],
    "wof:name":"Helina",
    "wof:placetype":"locality"
},
  "geometry": {"coordinates":[-111.48515999999999,54.48349],"type":"Point"}
}