{
  "type": "Feature",
  "properties": {
    "gn:admin1_code":"11",
    "gn:asciiname":"Fertile",
    "gn:country_code":"CA",
    "gn:dem":514,
    "gn:feature_class":"P",
    "gn:feature_code":"PPL",
    "gn:name":"Fertile",
    "gn:population":0,
    "gn:timezone":"America/Regina",
    "iso:country":"CA",
    "wof:name":"Fertile",
    "wof:placetype":"locality"
},
  "geometry": {"coordinates":[-101.45045,49.38334],"type":"Point"}
}