{
  "type": "Feature",
  "properties": {
    "gn:country":"CA",
    "gn:fcode":"PPL",
    "gn:population":0,
    "iso:country":"CA",
    "name:ceb_x_preferred":[
        "Saint-Gabriel-de-Brandon"
    ],
    "name:deu_x_preferred":[
        "Saint-Gabriel-de-Brandon"
    ],
    "name:ell_x_preferred":[
        "\u03a3\u03b1\u03b9\u03bd-\u0393\u03ba\u03b1\u03bc\u03c0\u03c1\u03b9\u03ad\u03bb-\u03bd\u03c4\u03b5-\u039c\u03c0\u03c1\u03b1\u03bd\u03c4\u03cc\u03bd"
    ],
    "name:eng_x_preferred":[
        "Saint-Gabriel-de-Brandon"
    ],
    "name:eus_x_preferred":[
        "Saint-Gabriel-de-Brandon"
    ],
    "name:fas_x_preferred":[
        "\u0633\u0646-\u06af\u0627\u0628\u0631\u06cc\u0644-\u062f\u0648-\u0628\u0631\u0627\u0646\u062f\u0648\u0646\u060c \u06a9\u0628\u06a9"
    ],
    "name:fas_x_variant":[
        "\u0633\u0646-\u06af\u0627\u0628\u0631\u06cc\u0644-\u062f\u0648-\u0628\u0631\u0627\u0646\u062f\u0648\u0646"
    ],
    "name:fra_x_preferred":[
        "Saint-Gabriel-de-Brandon"
    ],
    "name:nld_x_preferred":[
        "Saint-Gabriel-de-Brandon"
    ],
    "name:por_x_preferred":[
        "Saint-Gabriel-de-Brandon"
    ],
    "name:spa_x_preferred":[
        "Saint-Gabriel-de-Brandon"
    ],
    "name:swe_x_preferred":[
        "Saint-Gabriel-de-Brandon"
    ],
    "name:urd_x_preferred":[
        "\u0633\u06cc\u0646\u0679-\u06af\u06cc\u0628\u0631\u06cc\u0644-\u062f\u06d2-\u0628\u0631\u06cc\u0646\u0688\u0646\u060c \u06a9\u06cc\u0648\u0628\u06a9"
    ],
    "name:urd_x_variant":[
        "\u0633\u06cc\u0646\u0679-\u06af\u06cc\u0628\u0631\u06cc\u0644-\u062f\u06d2-\u0628\u0631\u06cc\u0646\u0688\u0646"
    ],
    "qs_pg:aaroncc":"CA",
    "qs_pg:gn_country":"CA",
    "qs_pg:gn_fcode":"PPL",
    "qs_pg:gn_pop":0,
    "qs_pg:name":"St.-Gabriel-de-Brandon",
    "qs_pg:name_adm0":"Canada",
    "qs_pg:name_adm1":"Qu\u00e9bec",
    "qs_pg:photos":82,
    "qs_pg:photos_1k":17,
    "qs_pg:photos_9k":1,
    "qs_pg:photos_9r":3,
    "qs_pg:photos_all":82,
    "qs_pg:photos_sr":3,
    "qs_pg:pop_sr":0,
    "qs_pg:qs_pg_placetype":"locality",
    "qs_pg:qs_pg_placetype_gp":"Town",
    "qs_pg:woe_adm0":23424775,
    "woe:adm0_id":23424775,
    "woe:name_adm0":"Canada",
    "woe:name_adm1":"Qu\u00e9bec",
    "woe:placetype":"Town",
    "wof:name":"St.-Gabriel-de-Brandon",
    "wof:placetype":"locality"
},
  "geometry": {"coordinates":[-73.38284,46.28516],"type":"Point"}
}