{
  "type": "Feature",
  "properties": {
    "gn:admin1_code":"8",
    "gn:asciiname":"Evanturel",
    "gn:country_code":"CA",
    "gn:dem":37,
    "gn:feature_class":"P",
    "gn:feature_code":"PPLL",
    "gn:name":"Evanturel",
    "gn:population":0,
    "gn:timezone":"America/Toronto",
    "iso:country":"CA",
    "name:pol_x_preferred":[
        "Evanturel"
    ],
    "wof:name":"Evanturel",
    "wof:placetype":"locality"
},
  "geometry": {"coordinates":[-74.79066999999998,45.6134],"type":"Point"}
}