{
  "type": "Feature",
  "properties": {
    "gn:admin1_code":"8",
    "gn:asciiname":"Ravenshoe",
    "gn:country_code":"CA",
    "gn:dem":252,
    "gn:feature_class":"P",
    "gn:feature_code":"PPL",
    "gn:name":"Ravenshoe",
    "gn:population":0,
    "gn:timezone":"America/Toronto",
    "iso:country":"CA",
    "wof:name":"Ravenshoe",
    "wof:placetype":"locality"
},
  "geometry": {"coordinates":[-79.4075,44.20556],"type":"Point"}
}