{
  "type": "Feature",
  "properties": {
    "gn:country":"CA",
    "gn:fcode":"PPL",
    "gn:population":0,
    "iso:country":"CA",
    "name:eng_x_preferred":[
        "Pubnico"
    ],
    "name:fra_x_preferred":[
        "Pubnico"
    ],
    "name:nld_x_preferred":[
        "Pubnico"
    ],
    "qs:name":"Pubnico",
    "qs:name_adm0":"Canada",
    "qs:name_adm1":"Nova Scotia",
    "qs:photos":20,
    "qs:photos_1k":4,
    "qs:photos_9k":1,
    "qs:photos_9r":1,
    "qs:photos_all":20,
    "qs:photos_sr":1,
    "qs:placetype":"Town",
    "qs:pop_sr":"0",
    "wd:wordcount":62,
    "wof:name":"Pubnico",
    "wof:placetype":"locality",
    "wof:population":0
},
  "geometry": {"coordinates":[-65.78339,43.70337],"type":"Point"}
}