{
  "type": "Feature",
  "properties": {
    "gn:admin1_code":"1",
    "gn:asciiname":"Little Buffalo",
    "gn:country_code":"CA",
    "gn:dem":555,
    "gn:feature_class":"P",
    "gn:feature_code":"PPL",
    "gn:name":"Little Buffalo",
    "gn:population":0,
    "gn:timezone":"America/Edmonton",
    "iso:country":"CA",
    "wof:name":"Little Buffalo",
    "wof:placetype":"locality"
},
  "geometry": {"coordinates":[-116.1075,56.4375],"type":"Point"}
}