{
  "type": "Feature",
  "properties": {
    "gn:admin1_code":"8",
    "gn:asciiname":"Prices Corner",
    "gn:country_code":"CA",
    "gn:dem":475,
    "gn:feature_class":"P",
    "gn:feature_code":"PPL",
    "gn:name":"Prices Corner",
    "gn:population":0,
    "gn:timezone":"America/Toronto",
    "iso:country":"CA",
    "wof:name":"Prices Corner",
    "wof:placetype":"locality"
},
  "geometry": {"coordinates":[-80.23546999999998,43.81775],"type":"Point"}
}