{
  "type": "Feature",
  "properties": {
    "gn:admin1_code":"2",
    "gn:asciiname":"Matsqui",
    "gn:country_code":"CA",
    "gn:dem":6,
    "gn:feature_class":"P",
    "gn:feature_code":"PPL",
    "gn:name":"Matsqui",
    "gn:population":0,
    "gn:timezone":"America/Vancouver",
    "iso:country":"CA",
    "wof:name":"Matsqui",
    "wof:placetype":"locality"
},
  "geometry": {"coordinates":[-122.29167,49.10833],"type":"Point"}
}