{
  "type": "Feature",
  "properties": {
    "gn:admin1_code":"8",
    "gn:asciiname":"Foot's Bay",
    "gn:country_code":"CA",
    "gn:dem":246,
    "gn:feature_class":"P",
    "gn:feature_code":"PPL",
    "gn:name":"Foot's Bay",
    "gn:population":0,
    "gn:timezone":"America/Toronto",
    "iso:country":"CA",
    "wof:name":"Foot's Bay",
    "wof:placetype":"locality"
},
  "geometry": {"coordinates":[-79.74290999999999,45.13089],"type":"Point"}
}