{
  "type": "Feature",
  "properties": {
    "gn:admin1_code":"10",
    "gn:admin2_code":"15.0",
    "gn:admin3_code":"77022.0",
    "gn:asciiname":"Lac-Pilon",
    "gn:country_code":"CA",
    "gn:dem":376,
    "gn:feature_class":"P",
    "gn:feature_code":"PPL",
    "gn:name":"Lac-Pilon",
    "gn:population":0,
    "gn:timezone":"America/Toronto",
    "iso:country":"CA",
    "wof:name":"Lac-Pilon",
    "wof:placetype":"locality"
},
  "geometry": {"coordinates":[-74.02377,45.99893],"type":"Point"}
}