{
  "type": "Feature",
  "properties": {
    "gn:admin1_code":"7",
    "gn:asciiname":"South Range",
    "gn:country_code":"CA",
    "gn:dem":136,
    "gn:feature_class":"P",
    "gn:feature_code":"PPL",
    "gn:name":"South Range",
    "gn:population":0,
    "gn:timezone":"America/Halifax",
    "iso:country":"CA",
    "wof:name":"South Range",
    "wof:placetype":"locality"
},
  "geometry": {"coordinates":[-65.77768,44.49604],"type":"Point"}
}