{
  "type": "Feature",
  "properties": {
    "gn:admin1_code":"1",
    "gn:asciiname":"Lure",
    "gn:country_code":"CA",
    "gn:dem":761,
    "gn:feature_class":"P",
    "gn:feature_code":"PPLL",
    "gn:name":"Lure",
    "gn:population":0,
    "gn:timezone":"America/Edmonton",
    "iso:country":"CA",
    "name:ceb_x_preferred":[
        "Lure"
    ],
    "name:deu_x_preferred":[
        "Lure"
    ],
    "name:fra_x_preferred":[
        "Lure"
    ],
    "name:ita_x_preferred":[
        "Lure"
    ],
    "name:nld_x_preferred":[
        "Lure"
    ],
    "name:nno_x_preferred":[
        "Lure"
    ],
    "name:nor_x_preferred":[
        "Lure"
    ],
    "name:por_x_preferred":[
        "Lure"
    ],
    "name:scn_x_preferred":[
        "Lure"
    ],
    "name:spa_x_preferred":[
        "Lure"
    ],
    "name:swe_x_preferred":[
        "Lure"
    ],
    "wof:name":"Lure",
    "wof:placetype":"locality"
},
  "geometry": {"coordinates":[-111.50173999999998,52.16683],"type":"Point"}
}