{
  "type": "Feature",
  "properties": {
    "gn:admin1_code":"4",
    "gn:asciiname":"Graham Corner",
    "gn:country_code":"CA",
    "gn:dem":203,
    "gn:feature_class":"P",
    "gn:feature_code":"PPL",
    "gn:name":"Graham Corner",
    "gn:population":0,
    "gn:timezone":"America/Moncton",
    "iso:country":"CA",
    "wof:name":"Graham Corner",
    "wof:placetype":"locality"
},
  "geometry": {"coordinates":[-67.68625,45.84078],"type":"Point"}
}