{
  "type": "Feature",
  "properties": {
    "gn:admin1_code":"7",
    "gn:asciiname":"Glen Morrison",
    "gn:country_code":"CA",
    "gn:dem":83,
    "gn:feature_class":"P",
    "gn:feature_code":"PPLL",
    "gn:name":"Glen Morrison",
    "gn:population":0,
    "gn:timezone":"America/Glace_Bay",
    "iso:country":"CA",
    "wof:name":"Glen Morrison",
    "wof:placetype":"locality"
},
  "geometry": {"coordinates":[-60.31516,46.00014],"type":"Point"}
}