{
  "type": "Feature",
  "properties": {
    "gn:admin1_code":"8",
    "gn:asciiname":"Forest Lea",
    "gn:country_code":"CA",
    "gn:dem":144,
    "gn:feature_class":"P",
    "gn:feature_code":"PPL",
    "gn:name":"Forest Lea",
    "gn:population":0,
    "gn:timezone":"America/Toronto",
    "iso:country":"CA",
    "wof:name":"Forest Lea",
    "wof:placetype":"locality"
},
  "geometry": {"coordinates":[-77.21417,45.82583],"type":"Point"}
}