{
  "type": "Feature",
  "properties": {
    "gn:admin1_code":"8",
    "gn:asciiname":"Grantham",
    "gn:country_code":"CA",
    "gn:dem":90,
    "gn:feature_class":"P",
    "gn:feature_code":"PPL",
    "gn:name":"Grantham",
    "gn:population":0,
    "gn:timezone":"America/Toronto",
    "iso:country":"CA",
    "name:ast_x_preferred":[
        "Grantham"
    ],
    "name:azb_x_preferred":[
        "\u0642\u0631\u0627\u0646\u062a\u0647\u0627\u0645"
    ],
    "name:bul_x_preferred":[
        "\u0413\u0440\u0430\u043d\u0442\u044a\u043c"
    ],
    "name:ceb_x_preferred":[
        "Grantham"
    ],
    "name:cym_x_preferred":[
        "Grantham"
    ],
    "name:dan_x_preferred":[
        "Grantham"
    ],
    "name:deu_x_preferred":[
        "Grantham"
    ],
    "name:epo_x_preferred":[
        "Grantham"
    ],
    "name:fas_x_preferred":[
        "\u06af\u0631\u0627\u0646\u062a\u0647\u0627\u0645"
    ],
    "name:fin_x_preferred":[
        "Grantham"
    ],
    "name:fra_x_preferred":[
        "Grantham"
    ],
    "name:gle_x_preferred":[
        "Grantham"
    ],
    "name:ind_x_preferred":[
        "Grantham"
    ],
    "name:ita_x_preferred":[
        "Grantham"
    ],
    "name:jpn_x_preferred":[
        "\u30b0\u30e9\u30f3\u30b5\u30e0"
    ],
    "name:kor_x_preferred":[
        "\uadf8\ub79c\uc12c"
    ],
    "name:lit_x_preferred":[
        "Grantamas"
    ],
    "name:nld_x_preferred":[
        "Grantham"
    ],
    "name:nno_x_preferred":[
        "Grantham"
    ],
    "name:nor_x_preferred":[
        "Grantham"
    ],
    "name:pol_x_preferred":[
        "Grantham"
    ],
    "name:por_x_preferred":[
        "Grantham"
    ],
    "name:ron_x_preferred":[
        "Grantham"
    ],
    "name:rus_x_preferred":[
        "\u0413\u0440\u0430\u043d\u0442\u0435\u043c"
    ],
    "name:sco_x_preferred":[
        "Grantham"
    ],
    "name:spa_x_preferred":[
        "Grantham"
    ],
    "name:srp_x_preferred":[
        "\u0413\u0440\u0430\u043d\u0442\u0430\u043c"
    ],
    "name:swe_x_preferred":[
        "Grantham"
    ],
    "name:tur_x_preferred":[
        "Grantham"
    ],
    "name:vol_x_preferred":[
        "Grantham"
    ],
    "name:zho_x_preferred":[
        "\u683c\u5170\u745f\u59c6"
    ],
    "wof:name":"Grantham",
    "wof:placetype":"locality"
},
  "geometry": {"coordinates":[-79.22528,43.20639],"type":"Point"}
}