{
  "type": "Feature",
  "properties": {
    "gn:admin1_code":"8",
    "gn:asciiname":"Grantham",
    "gn:country_code":"CA",
    "gn:dem":90,
    "gn:feature_class":"P",
    "gn:feature_code":"PPL",
    "gn:name":"Grantham",
    "gn:population":0,
    "gn:timezone":"America/Toronto",
    "iso:country":"CA",
    "wof:name":"Grantham",
    "wof:placetype":"locality"
},
  "geometry": {"coordinates":[-79.22528,43.20639],"type":"Point"}
}