{
  "type": "Feature",
  "properties": {
    "gn:admin1_code":"4",
    "gn:asciiname":"Lakeside",
    "gn:country_code":"CA",
    "gn:dem":12,
    "gn:feature_class":"P",
    "gn:feature_code":"PPL",
    "gn:name":"Lakeside",
    "gn:population":0,
    "gn:timezone":"America/Moncton",
    "iso:country":"CA",
    "wof:name":"Lakeside",
    "wof:placetype":"locality"
},
  "geometry": {"coordinates":[-65.84014999999999,45.51153],"type":"Point"}
}