{
  "type": "Feature",
  "properties": {
    "gn:admin1_code":"11.0",
    "gn:asciiname":"Clearwater River",
    "gn:country_code":"CA",
    "gn:dem":448,
    "gn:feature_class":"P",
    "gn:feature_code":"PPL",
    "gn:name":"Clearwater River",
    "gn:population":0,
    "gn:timezone":"America/Regina",
    "iso:country":"CA",
    "wof:name":"Clearwater River",
    "wof:placetype":"locality"
},
  "geometry": {"coordinates":[-109.49802,56.52928000000001],"type":"Point"}
}