{
  "type": "Feature",
  "properties": {
    "gn:admin1_code":"8",
    "gn:asciiname":"Fergusons Beach",
    "gn:country_code":"CA",
    "gn:dem":77,
    "gn:feature_class":"P",
    "gn:feature_code":"PPL",
    "gn:name":"Fergusons Beach",
    "gn:population":0,
    "gn:timezone":"America/Toronto",
    "iso:country":"CA",
    "wof:name":"Fergusons Beach",
    "wof:placetype":"locality"
},
  "geometry": {"coordinates":[-76.57126,45.51761],"type":"Point"}
}