{
  "type": "Feature",
  "properties": {
    "gn:admin1_code":"1",
    "gn:asciiname":"Neutral Hills",
    "gn:country_code":"CA",
    "gn:dem":733,
    "gn:feature_class":"P",
    "gn:feature_code":"PPLL",
    "gn:name":"Neutral Hills",
    "gn:population":0,
    "gn:timezone":"America/Edmonton",
    "iso:country":"CA",
    "wof:name":"Neutral Hills",
    "wof:placetype":"locality"
},
  "geometry": {"coordinates":[-110.95166999999999,52.23343],"type":"Point"}
}