{
  "type": "Feature",
  "properties": {
    "iso:country":"CA",
    "name:eng_x_preferred":[
        "Ste. Anne du Ruisseau"
    ],
    "name:nld_x_preferred":[
        "Ste. Anne du Ruisseau"
    ],
    "qs:name":"Ste. Anne du Ruisseau",
    "qs:name_adm0":"Canada",
    "qs:name_adm1":"Nova Scotia",
    "qs:photos":14,
    "qs:photos_1k":3,
    "qs:photos_9k":1,
    "qs:photos_9r":1,
    "qs:photos_all":14,
    "qs:photos_sr":1,
    "qs:placetype":"Town",
    "qs:pop_sr":"0",
    "wd:wordcount":168,
    "wof:name":"Ste. Anne du Ruisseau",
    "wof:placetype":"locality"
},
  "geometry": {"coordinates":[-65.928574,43.833256],"type":"Point"}
}