{
  "type": "Feature",
  "properties": {
    "gn:admin1_code":"10",
    "gn:admin2_code":"9.0",
    "gn:admin3_code":"98015.0",
    "gn:asciiname":"Harrington Harbour",
    "gn:country_code":"CA",
    "gn:dem":2,
    "gn:feature_class":"P",
    "gn:feature_code":"PPL",
    "gn:name":"Harrington Harbour",
    "gn:population":0,
    "gn:timezone":"America/Blanc-Sablon",
    "iso:country":"CA",
    "name:ceb_x_preferred":[
        "Harrington Harbour"
    ],
    "name:fra_x_preferred":[
        "Harrington Harbour"
    ],
    "name:swe_x_preferred":[
        "Harrington Harbour"
    ],
    "wof:name":"Harrington Harbour",
    "wof:placetype":"locality"
},
  "geometry": {"coordinates":[-59.47801,50.50012],"type":"Point"}
}