{
  "type": "Feature",
  "properties": {
    "gn:admin1_code":"7.0",
    "gn:asciiname":"Hachet Lake",
    "gn:country_code":"CA",
    "gn:dem":71,
    "gn:feature_class":"P",
    "gn:feature_code":"PPL",
    "gn:name":"Hachet Lake",
    "gn:population":0,
    "gn:timezone":"America/Halifax",
    "iso:country":"CA",
    "wof:name":"Hachet Lake",
    "wof:placetype":"locality"
},
  "geometry": {"coordinates":[-63.71294,44.56806],"type":"Point"}
}