{
  "type": "Feature",
  "properties": {
    "iso:country":"CA",
    "name:eng_x_preferred":[
        "Kayville"
    ],
    "qs_pg:aaroncc":"CA",
    "qs_pg:name":"Kayville",
    "qs_pg:name_adm0":"Canada",
    "qs_pg:name_adm1":"Saskatchewan",
    "qs_pg:photos":13,
    "qs_pg:photos_1k":3,
    "qs_pg:photos_9k":1,
    "qs_pg:photos_9r":1,
    "qs_pg:photos_all":13,
    "qs_pg:photos_sr":1,
    "qs_pg:pop_sr":0,
    "qs_pg:qs_pg_placetype":"locality",
    "qs_pg:qs_pg_placetype_gp":"Town",
    "qs_pg:woe_adm0":23424775,
    "woe:adm0_id":23424775,
    "woe:name_adm0":"Canada",
    "woe:name_adm1":"Saskatchewan",
    "woe:placetype":"Town",
    "wof:name":"Kayville",
    "wof:placetype":"locality"
},
  "geometry": {"coordinates":[-105.146112,49.725511],"type":"Point"}
}