{
  "type": "Feature",
  "properties": {
    "gn:country":"CA",
    "gn:fcode":"PPL",
    "gn:population":0,
    "iso:country":"CA",
    "name:ceb_x_preferred":[
        "Rocky Harbour"
    ],
    "name:eng_x_preferred":[
        "Rocky Harbour"
    ],
    "name:swe_x_preferred":[
        "Rocky Harbour"
    ],
    "qs:name":"Rocky Harbour",
    "qs:name_adm0":"Canada",
    "qs:name_adm1":"Newfoundland and Labrador",
    "qs:photos":895,
    "qs:photos_1k":181,
    "qs:photos_9k":4,
    "qs:photos_9r":6,
    "qs:photos_all":895,
    "qs:photos_sr":10,
    "qs:placetype":"Town",
    "qs:pop_sr":"9",
    "wd:wordcount":36,
    "wof:name":"Rocky Harbour",
    "wof:placetype":"locality",
    "wof:population":0
},
  "geometry": {"coordinates":[-57.91502,49.60001],"type":"Point"}
}