{
  "type": "Feature",
  "properties": {
    "iso:country":"CA",
    "name:eng_x_preferred":[
        "City Centre"
    ],
    "name:unk_x_variant":[
        "City Centre"
    ],
    "qs:gn_local":0,
    "qs:local_max":1631,
    "qs:local_sum":1631,
    "qs:localhoods":1,
    "qs:name":"City Centre",
    "qs:name_adm0":"Canada",
    "qs:name_adm1":"British Columbia",
    "qs:name_adm2":"Central Okanagan",
    "qs:name_local":"Kelowna North",
    "qs:photo_max":247,
    "qs:photo_sum":1631,
    "qs:placetype":"Suburb",
    "qs:quad_count":33,
    "qs:woe_adm0":23424775,
    "qs:woe_adm1":2344916,
    "qs:woe_adm2":29375224,
    "qs:woe_funk":"Grouping neighborhood",
    "qs:woe_lau":0,
    "qs:woe_local":55856440,
    "qs:woe_ver":"7.10.0",
    "wd:wordcount":610,
    "wof:lang":[
        "eng"
    ],
    "wof:name":"City Centre",
    "wof:placetype":"neighbourhood"
},
  "geometry": {"coordinates":[-119.498034,49.886788],"type":"Point"}
}