{
  "type": "Feature",
  "properties": {
    "gn:admin1_code":"3.0",
    "gn:asciiname":"Bristol",
    "gn:country_code":"CA",
    "gn:dem":269,
    "gn:feature_class":"P",
    "gn:feature_code":"PPLL",
    "gn:name":"Bristol",
    "gn:population":0,
    "gn:timezone":"America/Winnipeg",
    "iso:country":"CA",
    "wof:name":"Bristol",
    "wof:placetype":"locality"
},
  "geometry": {"coordinates":[-96.73891,49.47279],"type":"Point"}
}