{
  "type": "Feature",
  "properties": {
    "gn:admin1_code":"2",
    "gn:asciiname":"Port Washington",
    "gn:country_code":"CA",
    "gn:dem":15,
    "gn:feature_class":"P",
    "gn:feature_code":"PPL",
    "gn:name":"Port Washington",
    "gn:population":0,
    "gn:timezone":"America/Vancouver",
    "iso:country":"CA",
    "name:cat_x_preferred":[
        "Port Washington"
    ],
    "name:ceb_x_preferred":[
        "Port Washington"
    ],
    "name:deu_x_preferred":[
        "Port Washington"
    ],
    "name:fra_x_preferred":[
        "Port Washington"
    ],
    "name:ita_x_preferred":[
        "Port Washington"
    ],
    "name:nld_x_preferred":[
        "Port Washington"
    ],
    "name:pol_x_preferred":[
        "Port Washington"
    ],
    "name:por_x_preferred":[
        "Port Washington"
    ],
    "name:srp_x_preferred":[
        "\u041f\u043e\u0440\u0442 \u0412\u043e\u0448\u0438\u043d\u0433\u0442\u043e\u043d"
    ],
    "name:swe_x_preferred":[
        "Port Washington"
    ],
    "name:vol_x_preferred":[
        "Port Washington"
    ],
    "wof:name":"Port Washington",
    "wof:placetype":"locality"
},
  "geometry": {"coordinates":[-123.31999999999999,48.81306],"type":"Point"}
}