{
  "type": "Feature",
  "properties": {
    "gn:admin1_code":"11",
    "gn:asciiname":"Muscow",
    "gn:country_code":"CA",
    "gn:dem":580,
    "gn:feature_class":"P",
    "gn:feature_code":"PPLL",
    "gn:name":"Muscow",
    "gn:population":0,
    "gn:timezone":"America/Regina",
    "iso:country":"CA",
    "wof:name":"Muscow",
    "wof:placetype":"locality"
},
  "geometry": {"coordinates":[-103.91773999999999,50.75007],"type":"Point"}
}