{
  "type": "Feature",
  "properties": {
    "gn:admin1_code":"8",
    "gn:asciiname":"Onakawana",
    "gn:country_code":"CA",
    "gn:dem":54,
    "gn:feature_class":"P",
    "gn:feature_code":"PPL",
    "gn:name":"Onakawana",
    "gn:population":0,
    "gn:timezone":"America/Toronto",
    "iso:country":"CA",
    "wof:name":"Onakawana",
    "wof:placetype":"locality"
},
  "geometry": {"coordinates":[-81.43626,50.5987],"type":"Point"}
}