{
  "type": "Feature",
  "properties": {
    "gn:admin1_code":"8",
    "gn:asciiname":"Rylstone",
    "gn:country_code":"CA",
    "gn:dem":195,
    "gn:feature_class":"P",
    "gn:feature_code":"PPL",
    "gn:name":"Rylstone",
    "gn:population":0,
    "gn:timezone":"America/Toronto",
    "iso:country":"CA",
    "name:ceb_x_preferred":[
        "Rylstone"
    ],
    "name:nld_x_preferred":[
        "Rylstone"
    ],
    "name:pol_x_preferred":[
        "Rylstone"
    ],
    "name:swe_x_preferred":[
        "Rylstone"
    ],
    "wof:name":"Rylstone",
    "wof:placetype":"locality"
},
  "geometry": {"coordinates":[-77.70389,44.39194000000001],"type":"Point"}
}