{
  "type": "Feature",
  "properties": {
    "gn:admin1_code":"4",
    "gn:asciiname":"Hawkshaw",
    "gn:country_code":"CA",
    "gn:dem":56,
    "gn:feature_class":"P",
    "gn:feature_code":"PPL",
    "gn:name":"Hawkshaw",
    "gn:population":0,
    "gn:timezone":"America/Moncton",
    "iso:country":"CA",
    "wof:name":"Hawkshaw",
    "wof:placetype":"locality"
},
  "geometry": {"coordinates":[-67.23296999999999,45.97371],"type":"Point"}
}