{
  "type": "Feature",
  "properties": {
    "gn:admin1_code":"9",
    "gn:asciiname":"Hebron",
    "gn:country_code":"CA",
    "gn:dem":11,
    "gn:feature_class":"P",
    "gn:feature_code":"PPLL",
    "gn:name":"Hebron",
    "gn:population":0,
    "gn:timezone":"America/Halifax",
    "iso:country":"CA",
    "name:ceb_x_preferred":[
        "Hebron"
    ],
    "name:fra_x_preferred":[
        "Hebron"
    ],
    "name:swe_x_preferred":[
        "Hebron"
    ],
    "wof:name":"Hebron",
    "wof:placetype":"locality"
},
  "geometry": {"coordinates":[-64.26544,46.63345],"type":"Point"}
}