{
  "type": "Feature",
  "properties": {
    "gn:admin1_code":"8.0",
    "gn:asciiname":"Bowermans",
    "gn:country_code":"CA",
    "gn:dem":110,
    "gn:feature_class":"P",
    "gn:feature_code":"PPL",
    "gn:name":"Bowermans",
    "gn:population":0,
    "gn:timezone":"America/Toronto",
    "iso:country":"CA",
    "wof:name":"Bowermans",
    "wof:placetype":"locality"
},
  "geometry": {"coordinates":[-77.36464000000002,44.00847],"type":"Point"}
}