{
  "type": "Feature",
  "properties": {
    "gn:admin1_code":"7.0",
    "gn:asciiname":"Cameron Settlement",
    "gn:country_code":"CA",
    "gn:dem":111,
    "gn:feature_class":"P",
    "gn:feature_code":"PPL",
    "gn:name":"Cameron Settlement",
    "gn:population":0,
    "gn:timezone":"America/Halifax",
    "iso:country":"CA",
    "wof:name":"Cameron Settlement",
    "wof:placetype":"locality"
},
  "geometry": {"coordinates":[-62.49361,45.28411],"type":"Point"}
}