{
  "type": "Feature",
  "properties": {
    "gn:admin1_code":"1.0",
    "gn:asciiname":"Doan",
    "gn:country_code":"CA",
    "gn:dem":977,
    "gn:feature_class":"P",
    "gn:feature_code":"PPLL",
    "gn:name":"Doan",
    "gn:population":0,
    "gn:timezone":"America/Edmonton",
    "iso:country":"CA",
    "name:deu_x_preferred":[
        "Doan"
    ],
    "name:fra_x_preferred":[
        "Doan"
    ],
    "name:swe_x_preferred":[
        "Doan"
    ],
    "name:vie_x_preferred":[
        "\u0110o\u00e0n"
    ],
    "wof:name":"Doan",
    "wof:placetype":"locality"
},
  "geometry": {"coordinates":[-114.05216,51.97055],"type":"Point"}
}