{
  "type": "Feature",
  "properties": {
    "gn:admin1_code":"4.0",
    "gn:asciiname":"Clarendon",
    "gn:country_code":"CA",
    "gn:dem":70,
    "gn:feature_class":"P",
    "gn:feature_code":"PPL",
    "gn:name":"Clarendon",
    "gn:population":0,
    "gn:timezone":"America/Moncton",
    "iso:country":"CA",
    "wof:name":"Clarendon",
    "wof:placetype":"locality"
},
  "geometry": {"coordinates":[-66.41946,45.48042],"type":"Point"}
}