{
  "type": "Feature",
  "properties": {
    "gn:admin1_code":"1",
    "gn:asciiname":"Snaring",
    "gn:country_code":"CA",
    "gn:dem":1051,
    "gn:feature_class":"P",
    "gn:feature_code":"PPLL",
    "gn:name":"Snaring",
    "gn:population":0,
    "gn:timezone":"America/Edmonton",
    "iso:country":"CA",
    "wof:name":"Snaring",
    "wof:placetype":"locality"
},
  "geometry": {"coordinates":[-118.06908,53.08333],"type":"Point"}
}