{
  "type": "Feature",
  "properties": {
    "gn:admin1_code":"8",
    "gn:asciiname":"Mabee's Corners",
    "gn:country_code":"CA",
    "gn:dem":240,
    "gn:feature_class":"P",
    "gn:feature_code":"PPL",
    "gn:name":"Mabee's Corners",
    "gn:population":0,
    "gn:timezone":"America/Toronto",
    "iso:country":"CA",
    "wof:name":"Mabee's Corners",
    "wof:placetype":"locality"
},
  "geometry": {"coordinates":[-80.68038,42.77924],"type":"Point"}
}