{
  "type": "Feature",
  "properties": {
    "gn:admin1_code":"2",
    "gn:admin2_code":"5947.0",
    "gn:asciiname":"Kung",
    "gn:country_code":"CA",
    "gn:dem":39,
    "gn:feature_class":"P",
    "gn:feature_code":"PPLL",
    "gn:name":"Kung",
    "gn:population":0,
    "gn:timezone":"America/Vancouver",
    "iso:country":"CA",
    "name:deu_x_preferred":[
        "Kung"
    ],
    "name:fra_x_preferred":[
        "Kung"
    ],
    "name:swe_x_preferred":[
        "Kung"
    ],
    "wof:name":"Kung",
    "wof:placetype":"locality"
},
  "geometry": {"coordinates":[-132.57058000000001,54.05003000000001],"type":"Point"}
}