{
  "type": "Feature",
  "properties": {
    "gn:admin1_code":"4",
    "gn:asciiname":"Springdale",
    "gn:country_code":"CA",
    "gn:dem":66,
    "gn:feature_class":"P",
    "gn:feature_code":"PPL",
    "gn:name":"Springdale",
    "gn:population":0,
    "gn:timezone":"America/Moncton",
    "iso:country":"CA",
    "wof:name":"Springdale",
    "wof:placetype":"locality"
},
  "geometry": {"coordinates":[-65.3231,45.77519],"type":"Point"}
}