{
  "type": "Feature",
  "properties": {
    "gn:admin1_code":"4",
    "gn:asciiname":"Springdale",
    "gn:country_code":"CA",
    "gn:dem":66,
    "gn:feature_class":"P",
    "gn:feature_code":"PPL",
    "gn:name":"Springdale",
    "gn:population":0,
    "gn:timezone":"America/Moncton",
    "iso:country":"CA",
    "name:bre_x_preferred":[
        "Springdale"
    ],
    "name:cat_x_preferred":[
        "Springdale"
    ],
    "name:ceb_x_preferred":[
        "Springdale"
    ],
    "name:deu_x_preferred":[
        "Springdale"
    ],
    "name:fas_x_preferred":[
        "\u0627\u0633\u067e\u0631\u06cc\u0646\u06af\u062f\u06cc\u0644"
    ],
    "name:fin_x_preferred":[
        "Springdale"
    ],
    "name:fra_x_preferred":[
        "Springdale"
    ],
    "name:ita_x_preferred":[
        "Springdale"
    ],
    "name:kor_x_preferred":[
        "\uc2a4\ud504\ub9c1\ub370\uc77c"
    ],
    "name:nld_x_preferred":[
        "Springdale"
    ],
    "name:pol_x_preferred":[
        "Springdale"
    ],
    "name:por_x_preferred":[
        "Springdale"
    ],
    "name:rus_x_preferred":[
        "\u0421\u043f\u0440\u0438\u043d\u0433\u0434\u0435\u0439\u043b"
    ],
    "name:spa_x_preferred":[
        "Springdale"
    ],
    "name:srp_x_preferred":[
        "\u0421\u043f\u0440\u0438\u043d\u0433\u0434\u0435\u0458\u043b"
    ],
    "name:swe_x_preferred":[
        "Springdale"
    ],
    "name:vol_x_preferred":[
        "Springdale"
    ],
    "wof:name":"Springdale",
    "wof:placetype":"locality"
},
  "geometry": {"coordinates":[-65.3231,45.77519],"type":"Point"}
}