{
  "type": "Feature",
  "properties": {
    "gn:admin1_code":"5",
    "gn:asciiname":"Thorburn Lake",
    "gn:country_code":"CA",
    "gn:dem":131,
    "gn:feature_class":"P",
    "gn:feature_code":"PPLL",
    "gn:name":"Thorburn Lake",
    "gn:population":0,
    "gn:timezone":"America/St_Johns",
    "iso:country":"CA",
    "wof:name":"Thorburn Lake",
    "wof:placetype":"locality"
},
  "geometry": {"coordinates":[-54.16483,48.26661],"type":"Point"}
}