{
  "type": "Feature",
  "properties": {
    "gn:admin1_code":"1",
    "gn:asciiname":"Kleskun Hill",
    "gn:country_code":"CA",
    "gn:dem":672,
    "gn:feature_class":"P",
    "gn:feature_code":"PPLL",
    "gn:name":"Kleskun Hill",
    "gn:population":0,
    "gn:timezone":"America/Edmonton",
    "iso:country":"CA",
    "wof:name":"Kleskun Hill",
    "wof:placetype":"locality"
},
  "geometry": {"coordinates":[-118.48599,55.24999],"type":"Point"}
}