{
  "type": "Feature",
  "properties": {
    "gn:admin1_code":"8.0",
    "gn:asciiname":"Delamere",
    "gn:country_code":"CA",
    "gn:dem":205,
    "gn:feature_class":"P",
    "gn:feature_code":"PPL",
    "gn:name":"Delamere",
    "gn:population":0,
    "gn:timezone":"America/Toronto",
    "iso:country":"CA",
    "name:ceb_x_preferred":[
        "Delamere"
    ],
    "name:swe_x_preferred":[
        "Delamere"
    ],
    "wof:name":"Delamere",
    "wof:placetype":"locality"
},
  "geometry": {"coordinates":[-80.71641,46.16678],"type":"Point"}
}