{
  "type": "Feature",
  "properties": {
    "gn:admin1_code":"4",
    "gn:asciiname":"Skiff Lake",
    "gn:country_code":"CA",
    "gn:dem":213,
    "gn:feature_class":"P",
    "gn:feature_code":"PPL",
    "gn:name":"Skiff Lake",
    "gn:population":0,
    "gn:timezone":"America/Moncton",
    "iso:country":"CA",
    "wof:name":"Skiff Lake",
    "wof:placetype":"locality"
},
  "geometry": {"coordinates":[-67.54878000000001,45.82772],"type":"Point"}
}