{
  "type": "Feature",
  "properties": {
    "gn:admin1_code":"7",
    "gn:asciiname":"Framboise",
    "gn:country_code":"CA",
    "gn:dem":14,
    "gn:feature_class":"P",
    "gn:feature_code":"PPL",
    "gn:name":"Framboise",
    "gn:population":0,
    "gn:timezone":"America/Halifax",
    "iso:country":"CA",
    "name:fra_x_preferred":[
        "Framboise"
    ],
    "wof:name":"Framboise",
    "wof:placetype":"locality"
},
  "geometry": {"coordinates":[-60.36267,45.71974],"type":"Point"}
}