{
  "type": "Feature",
  "properties": {
    "gn:admin1_code":"7",
    "gn:asciiname":"Queensland",
    "gn:country_code":"CA",
    "gn:dem":10,
    "gn:feature_class":"P",
    "gn:feature_code":"PPL",
    "gn:name":"Queensland",
    "gn:population":0,
    "gn:timezone":"America/Halifax",
    "iso:country":"CA",
    "wof:name":"Queensland",
    "wof:placetype":"locality"
},
  "geometry": {"coordinates":[-64.02584,44.63548],"type":"Point"}
}