{
  "type": "Feature",
  "properties": {
    "gn:admin1_code":"8",
    "gn:asciiname":"Oakdale",
    "gn:country_code":"CA",
    "gn:dem":201,
    "gn:feature_class":"P",
    "gn:feature_code":"PPL",
    "gn:name":"Oakdale",
    "gn:population":0,
    "gn:timezone":"America/Toronto",
    "iso:country":"CA",
    "wof:name":"Oakdale",
    "wof:placetype":"locality"
},
  "geometry": {"coordinates":[-82.03971,42.70875],"type":"Point"}
}