{
  "type": "Feature",
  "properties": {
    "gn:admin1_code":"8",
    "gn:asciiname":"Oakdale",
    "gn:country_code":"CA",
    "gn:dem":201,
    "gn:feature_class":"P",
    "gn:feature_code":"PPL",
    "gn:name":"Oakdale",
    "gn:population":0,
    "gn:timezone":"America/Toronto",
    "iso:country":"CA",
    "name:cat_x_preferred":[
        "Oakdale"
    ],
    "name:ceb_x_preferred":[
        "Oakdale"
    ],
    "name:cym_x_preferred":[
        "Oakdale"
    ],
    "name:deu_x_preferred":[
        "Oakdale"
    ],
    "name:fra_x_preferred":[
        "Oakdale"
    ],
    "name:ita_x_preferred":[
        "Oakdale"
    ],
    "name:nld_x_preferred":[
        "Oakdale"
    ],
    "name:pol_x_preferred":[
        "Oakdale"
    ],
    "name:por_x_preferred":[
        "Oakdale"
    ],
    "name:spa_x_preferred":[
        "Oakdale"
    ],
    "name:srp_x_preferred":[
        "\u041e\u0443\u043a\u0434\u0435\u0458\u043b"
    ],
    "name:swe_x_preferred":[
        "Oakdale"
    ],
    "name:vol_x_preferred":[
        "Oakdale"
    ],
    "wof:name":"Oakdale",
    "wof:placetype":"locality"
},
  "geometry": {"coordinates":[-82.03971,42.70875],"type":"Point"}
}