{
  "type": "Feature",
  "properties": {
    "gn:admin1_code":"8.0",
    "gn:asciiname":"Moffat Pond",
    "gn:country_code":"CA",
    "gn:dem":387,
    "gn:feature_class":"P",
    "gn:feature_code":"PPL",
    "gn:name":"Moffat Pond",
    "gn:population":0,
    "gn:timezone":"America/Toronto",
    "iso:country":"CA",
    "wof:name":"Moffat Pond",
    "wof:placetype":"locality"
},
  "geometry": {"coordinates":[-78.11884000000001,45.21618],"type":"Point"}
}