{
  "type": "Feature",
  "properties": {
    "gn:admin1_code":"8.0",
    "gn:asciiname":"Craig Shore",
    "gn:country_code":"CA",
    "gn:dem":138,
    "gn:feature_class":"P",
    "gn:feature_code":"PPL",
    "gn:name":"Craig Shore",
    "gn:population":0,
    "gn:timezone":"America/Toronto",
    "iso:country":"CA",
    "wof:name":"Craig Shore",
    "wof:placetype":"locality"
},
  "geometry": {"coordinates":[-76.16778000000002,45.04167],"type":"Point"}
}