{
  "type": "Feature",
  "properties": {
    "gn:admin1_code":"8.0",
    "gn:asciiname":"Brooks Landing",
    "gn:country_code":"CA",
    "gn:dem":175,
    "gn:feature_class":"P",
    "gn:feature_code":"PPL",
    "gn:name":"Brooks Landing",
    "gn:population":0,
    "gn:timezone":"America/Toronto",
    "iso:country":"CA",
    "wof:name":"Brooks Landing",
    "wof:placetype":"locality"
},
  "geometry": {"coordinates":[-80.33651,45.43266],"type":"Point"}
}