{
  "type": "Feature",
  "properties": {
    "gn:admin1_code":"10",
    "gn:admin2_code":"7.0",
    "gn:admin3_code":"81017.0",
    "gn:asciiname":"Pointe-Gatineau",
    "gn:country_code":"CA",
    "gn:dem":49,
    "gn:feature_class":"P",
    "gn:feature_code":"PPL",
    "gn:name":"Pointe-Gatineau",
    "gn:population":0,
    "gn:timezone":"America/Toronto",
    "iso:country":"CA",
    "wof:name":"Pointe-Gatineau",
    "wof:placetype":"locality"
},
  "geometry": {"coordinates":[-75.69794,45.4654],"type":"Point"}
}