{
  "type": "Feature",
  "properties": {
    "gn:admin1_code":"8",
    "gn:asciiname":"Gull Rock",
    "gn:country_code":"CA",
    "gn:dem":235,
    "gn:feature_class":"P",
    "gn:feature_code":"PPL",
    "gn:name":"Gull Rock",
    "gn:population":0,
    "gn:timezone":"America/Toronto",
    "iso:country":"CA",
    "wof:name":"Gull Rock",
    "wof:placetype":"locality"
},
  "geometry": {"coordinates":[-79.59278,45.21556],"type":"Point"}
}