{
  "type": "Feature",
  "properties": {
    "gn:admin1_code":"12",
    "gn:asciiname":"Little Salmon",
    "gn:country_code":"CA",
    "gn:dem":533,
    "gn:feature_class":"P",
    "gn:feature_code":"PPLL",
    "gn:name":"Little Salmon",
    "gn:population":0,
    "gn:timezone":"America/Whitehorse",
    "iso:country":"CA",
    "wof:name":"Little Salmon",
    "wof:placetype":"locality"
},
  "geometry": {"coordinates":[-135.68736000000001,62.04948],"type":"Point"}
}