{
  "type": "Feature",
  "properties": {
    "gn:admin1_code":"10",
    "gn:admin2_code":"04",
    "gn:admin3_code":"35020.0",
    "gn:asciiname":"Proulxville",
    "gn:country_code":"CA",
    "gn:dem":132,
    "gn:feature_class":"P",
    "gn:feature_code":"PPL",
    "gn:name":"Proulxville",
    "gn:population":0,
    "gn:timezone":"America/Toronto",
    "iso:country":"CA",
    "wof:name":"Proulxville",
    "wof:placetype":"locality"
},
  "geometry": {"coordinates":[-72.50454999999999,46.66892],"type":"Point"}
}