{
  "type": "Feature",
  "properties": {
    "gn:admin1_code":"10",
    "gn:admin2_code":"16.0",
    "gn:admin3_code":"70035.0",
    "gn:asciiname":"Landreville",
    "gn:country_code":"CA",
    "gn:dem":46,
    "gn:feature_class":"P",
    "gn:feature_code":"PPL",
    "gn:name":"Landreville",
    "gn:population":0,
    "gn:timezone":"America/Toronto",
    "iso:country":"CA",
    "name:cat_x_preferred":[
        "Landreville"
    ],
    "name:ceb_x_preferred":[
        "Landreville"
    ],
    "name:eus_x_preferred":[
        "Landreville"
    ],
    "name:fra_x_preferred":[
        "Landreville"
    ],
    "name:hun_x_preferred":[
        "Landreville"
    ],
    "name:hye_x_preferred":[
        "\u053c\u0561\u0576\u0564\u0580\u0587\u056b\u056c"
    ],
    "name:ita_x_preferred":[
        "Landreville"
    ],
    "name:lat_x_preferred":[
        "Landreville"
    ],
    "name:msa_x_preferred":[
        "Landreville"
    ],
    "name:nld_x_preferred":[
        "Landreville"
    ],
    "name:oci_x_preferred":[
        "Landreville"
    ],
    "name:pms_x_preferred":[
        "Landreville"
    ],
    "name:pol_x_preferred":[
        "Landreville"
    ],
    "name:por_x_preferred":[
        "Landreville"
    ],
    "name:ron_x_preferred":[
        "Landreville"
    ],
    "name:rus_x_preferred":[
        "\u041b\u0430\u043d\u0434\u0440\u0435\u0432\u0438\u043b\u044c"
    ],
    "name:slk_x_preferred":[
        "Landreville"
    ],
    "name:spa_x_preferred":[
        "Landreville"
    ],
    "name:swe_x_preferred":[
        "Landreville"
    ],
    "name:ukr_x_preferred":[
        "\u041b\u0430\u043d\u0434\u0440\u0435\u0432\u0456\u043b\u044c"
    ],
    "name:urd_x_preferred":[
        "\u0644\u0627\u0646\u0688\u0631\u06cc\u0648\u06cc\u0644"
    ],
    "name:vie_x_preferred":[
        "Landreville"
    ],
    "name:vol_x_preferred":[
        "Landreville"
    ],
    "name:war_x_preferred":[
        "Landreville"
    ],
    "name:zho_x_preferred":[
        "\u6717\u5fb7\u52d2\u7ef4\u5c14"
    ],
    "wof:name":"Landreville",
    "wof:placetype":"locality"
},
  "geometry": {"coordinates":[-74.03822,45.16504000000001],"type":"Point"}
}