{
  "type": "Feature",
  "properties": {
    "gn:admin1_code":"10",
    "gn:admin2_code":"16.0",
    "gn:admin3_code":"70035.0",
    "gn:asciiname":"Landreville",
    "gn:country_code":"CA",
    "gn:dem":46,
    "gn:feature_class":"P",
    "gn:feature_code":"PPL",
    "gn:name":"Landreville",
    "gn:population":0,
    "gn:timezone":"America/Toronto",
    "iso:country":"CA",
    "wof:name":"Landreville",
    "wof:placetype":"locality"
},
  "geometry": {"coordinates":[-74.03822,45.16504000000001],"type":"Point"}
}