{
  "type": "Feature",
  "properties": {
    "gn:admin1_code":"7.0",
    "gn:asciiname":"Woodlawn Heights",
    "gn:country_code":"CA",
    "gn:dem":84,
    "gn:feature_class":"P",
    "gn:feature_code":"PPL",
    "gn:name":"Woodlawn Heights",
    "gn:population":0,
    "gn:timezone":"America/Halifax",
    "iso:country":"CA",
    "wof:name":"Woodlawn Heights",
    "wof:placetype":"locality"
},
  "geometry": {"coordinates":[-63.51837,44.68323],"type":"Point"}
}