{
  "type": "Feature",
  "properties": {
    "gn:gn_country":"CA",
    "gn:gn_fcode":"PPL",
    "gn:gn_pop":0,
    "iso:country":"CA",
    "name:bre_x_preferred":[
        "Saint-Blaise-sur-Richelieu"
    ],
    "name:ceb_x_preferred":[
        "Saint-Blaise-sur-Richelieu"
    ],
    "name:cos_x_preferred":[
        "Saint-Blaise-sur-Richelieu"
    ],
    "name:dan_x_preferred":[
        "Saint-Blaise-sur-Richelieu"
    ],
    "name:deu_x_preferred":[
        "Saint-Blaise-sur-Richelieu"
    ],
    "name:eng_x_preferred":[
        "Saint-Blaise-sur-Richelieu"
    ],
    "name:eus_x_preferred":[
        "Saint-Blaise-sur-Richelieu"
    ],
    "name:fas_x_preferred":[
        "\u0633\u0646-\u0628\u0644\u0632-\u0633\u0648\u0631-\u0631\u06cc\u0634\u0648\u0644\u06cc\u0648\u060c \u06a9\u0628\u06a9"
    ],
    "name:fas_x_variant":[
        "\u0633\u0646-\u0628\u0644\u0632-\u0633\u0648\u0631-\u0631\u06cc\u0634\u0648\u0644\u06cc\u0648"
    ],
    "name:fra_x_preferred":[
        "Saint-Blaise-sur-Richelieu"
    ],
    "name:ind_x_preferred":[
        "Saint-Blaise-sur-Richelieu"
    ],
    "name:ita_x_preferred":[
        "Saint-Blaise-sur-Richelieu"
    ],
    "name:nds_x_preferred":[
        "Saint-Blaise-sur-Richelieu"
    ],
    "name:nld_x_preferred":[
        "Saint-Blaise-sur-Richelieu"
    ],
    "name:por_x_preferred":[
        "Saint-Blaise-sur-Richelieu"
    ],
    "name:ron_x_preferred":[
        "Saint-Blaise-sur-Richelieu"
    ],
    "name:spa_x_preferred":[
        "Saint-Blaise-sur-Richelieu"
    ],
    "name:swe_x_preferred":[
        "Saint-Blaise-sur-Richelieu"
    ],
    "name:tah_x_preferred":[
        "Saint-Blaise-sur-Richelieu"
    ],
    "name:urd_x_preferred":[
        "\u0633\u06cc\u0646\u0679-\u0628\u0644\u0627\u0633\u06d2-\u0633\u0631-\u0631\u06cc\u0686\u0644\u06cc\u0648\u060c \u06a9\u06cc\u0648\u0628\u06a9"
    ],
    "name:urd_x_variant":[
        "\u0633\u06cc\u0646\u0679-\u0628\u0644\u0627\u0633\u06d2-\u0633\u0631-\u0631\u06cc\u0686\u0644\u06cc\u0648"
    ],
    "qs_pg:aaroncc":"CA",
    "qs_pg:gn_country":"CA",
    "qs_pg:gn_fcode":"PPL",
    "qs_pg:gn_pop":0,
    "qs_pg:name":"St.-Blaise-sur-Richelieu",
    "qs_pg:name_adm0":"Canada",
    "qs_pg:name_adm1":"Qu\u00e9bec",
    "qs_pg:photos":107,
    "qs_pg:photos_1k":22,
    "qs_pg:photos_9k":1,
    "qs_pg:photos_9r":3,
    "qs_pg:photos_all":107,
    "qs_pg:photos_sr":3,
    "qs_pg:pop_sr":0,
    "qs_pg:qs_pg_placetype":"locality",
    "qs_pg:qs_pg_placetype_gp":"Town",
    "qs_pg:woe_adm0":23424775,
    "woe:adm0_id":23424775,
    "woe:name_adm0":"Canada",
    "woe:name_adm1":"Qu\u00e9bec",
    "woe:placetype":"Town",
    "wof:name":"St.-Blaise-sur-Richelieu",
    "wof:placetype":"locality"
},
  "geometry": {"coordinates":[-73.28246,45.21678],"type":"Point"}
}