{
  "type": "Feature",
  "properties": {
    "gn:admin1_code":"7.0",
    "gn:asciiname":"Bridgeville",
    "gn:country_code":"CA",
    "gn:dem":70,
    "gn:feature_class":"P",
    "gn:feature_code":"PPL",
    "gn:name":"Bridgeville",
    "gn:population":0,
    "gn:timezone":"America/Halifax",
    "iso:country":"CA",
    "wof:name":"Bridgeville",
    "wof:placetype":"locality"
},
  "geometry": {"coordinates":[-62.60825,45.43408],"type":"Point"}
}