{
  "type": "Feature",
  "properties": {
    "gn:admin1_code":"10.0",
    "gn:admin2_code":"8.0",
    "gn:admin3_code":"86042.0",
    "gn:asciiname":"Duprat",
    "gn:country_code":"CA",
    "gn:dem":309,
    "gn:feature_class":"P",
    "gn:feature_code":"PPL",
    "gn:name":"Duprat",
    "gn:population":0,
    "gn:timezone":"America/Toronto",
    "iso:country":"CA",
    "wof:name":"Duprat",
    "wof:placetype":"locality"
},
  "geometry": {"coordinates":[-79.04342,48.32175],"type":"Point"}
}