{
  "type": "Feature",
  "properties": {
    "gn:admin1_code":"8",
    "gn:asciiname":"Meyersburg",
    "gn:country_code":"CA",
    "gn:dem":117,
    "gn:feature_class":"P",
    "gn:feature_code":"PPL",
    "gn:name":"Meyersburg",
    "gn:population":0,
    "gn:timezone":"America/Toronto",
    "iso:country":"CA",
    "wof:name":"Meyersburg",
    "wof:placetype":"locality"
},
  "geometry": {"coordinates":[-77.81619999999999,44.25012],"type":"Point"}
}