{
  "type": "Feature",
  "properties": {
    "gn:admin1_code":"8",
    "gn:asciiname":"Fallbrook",
    "gn:country_code":"CA",
    "gn:dem":148,
    "gn:feature_class":"P",
    "gn:feature_code":"PPL",
    "gn:name":"Fallbrook",
    "gn:population":0,
    "gn:timezone":"America/Toronto",
    "iso:country":"CA",
    "wof:name":"Fallbrook",
    "wof:placetype":"locality"
},
  "geometry": {"coordinates":[-76.39139,44.95778],"type":"Point"}
}