{
  "type": "Feature",
  "properties": {
    "iso:country":"CA",
    "name:cat_x_preferred":[
        "Old Crow"
    ],
    "name:dan_x_preferred":[
        "Old Crow"
    ],
    "name:deu_x_preferred":[
        "Old Crow"
    ],
    "name:eng_x_preferred":[
        "Old Crow"
    ],
    "name:fra_x_preferred":[
        "Old Crow"
    ],
    "name:jpn_x_preferred":[
        "\u30aa\u30fc\u30eb\u30c9\u30af\u30ed\u30a6"
    ],
    "name:mrj_x_preferred":[
        "\u041e\u043b\u0434-\u041a\u0440\u043e\u0443"
    ],
    "name:nld_x_preferred":[
        "Old Crow"
    ],
    "name:rus_x_preferred":[
        "\u041e\u043b\u0434-\u041a\u0440\u043e\u0443"
    ],
    "name:spa_x_preferred":[
        "Old Crow"
    ],
    "name:swe_x_preferred":[
        "Old Crow"
    ],
    "name:zho_x_preferred":[
        "\u65e7\u514b\u7f57"
    ],
    "qs_pg:aaroncc":"CA",
    "qs_pg:name":"Old Crow",
    "qs_pg:name_adm0":"Canada",
    "qs_pg:name_adm1":"Yukon Territory",
    "qs_pg:photos":74,
    "qs_pg:photos_1k":15,
    "qs_pg:photos_9k":1,
    "qs_pg:photos_9r":2,
    "qs_pg:photos_all":74,
    "qs_pg:photos_sr":2,
    "qs_pg:pop_sr":0,
    "qs_pg:qs_pg_placetype":"locality",
    "qs_pg:qs_pg_placetype_gp":"Town",
    "qs_pg:woe_adm0":23424775,
    "woe:adm0_id":23424775,
    "woe:name_adm0":"Canada",
    "woe:name_adm1":"Yukon Territory",
    "woe:placetype":"Town",
    "wof:name":"Old Crow",
    "wof:placetype":"locality"
},
  "geometry": {"coordinates":[-139.845528,67.567156],"type":"Point"}
}