{
  "type": "Feature",
  "properties": {
    "gn:admin1_code":"1",
    "gn:asciiname":"Ksituan",
    "gn:country_code":"CA",
    "gn:dem":621,
    "gn:feature_class":"P",
    "gn:feature_code":"PPLL",
    "gn:name":"Ksituan",
    "gn:population":0,
    "gn:timezone":"America/Edmonton",
    "iso:country":"CA",
    "wof:name":"Ksituan",
    "wof:placetype":"locality"
},
  "geometry": {"coordinates":[-119.01949,55.89997],"type":"Point"}
}