{
  "type": "Feature",
  "properties": {
    "gn:admin1_code":"8",
    "gn:asciiname":"McGinnis Creek",
    "gn:country_code":"CA",
    "gn:dem":324,
    "gn:feature_class":"P",
    "gn:feature_code":"PPL",
    "gn:name":"McGinnis Creek",
    "gn:population":0,
    "gn:timezone":"America/Winnipeg",
    "iso:country":"CA",
    "wof:name":"McGinnis Creek",
    "wof:placetype":"locality"
},
  "geometry": {"coordinates":[-94.65528,48.85544],"type":"Point"}
}