{
  "type": "Feature",
  "properties": {
    "gn:admin1_code":"8",
    "gn:asciiname":"Metz",
    "gn:country_code":"CA",
    "gn:dem":469,
    "gn:feature_class":"P",
    "gn:feature_code":"PPL",
    "gn:name":"Metz",
    "gn:population":0,
    "gn:timezone":"America/Toronto",
    "iso:country":"CA",
    "wof:name":"Metz",
    "wof:placetype":"locality"
},
  "geometry": {"coordinates":[-80.44333,43.80917],"type":"Point"}
}