{
  "type": "Feature",
  "properties": {
    "gn:admin1_code":"10",
    "gn:admin2_code":"15.0",
    "gn:admin3_code":"79025.0",
    "gn:asciiname":"Kiamika",
    "gn:country_code":"CA",
    "gn:dem":221,
    "gn:feature_class":"P",
    "gn:feature_code":"PPL",
    "gn:name":"Kiamika",
    "gn:population":0,
    "gn:timezone":"America/Toronto",
    "iso:country":"CA",
    "wof:name":"Kiamika",
    "wof:placetype":"locality"
},
  "geometry": {"coordinates":[-75.3771,46.41871],"type":"Point"}
}