{
  "type": "Feature",
  "properties": {
    "gn:admin1_code":"8.0",
    "gn:asciiname":"Calabogie",
    "gn:country_code":"CA",
    "gn:dem":159,
    "gn:feature_class":"P",
    "gn:feature_code":"PPL",
    "gn:name":"Calabogie",
    "gn:population":0,
    "gn:timezone":"America/Toronto",
    "iso:country":"CA",
    "wof:name":"Calabogie",
    "wof:placetype":"locality"
},
  "geometry": {"coordinates":[-76.72165,45.30152],"type":"Point"}
}