{
  "type": "Feature",
  "properties": {
    "gn:admin1_code":"8.0",
    "gn:asciiname":"Amherstburg",
    "gn:country_code":"CA",
    "gn:dem":181,
    "gn:feature_class":"P",
    "gn:feature_code":"PPL",
    "gn:name":"Amherstburg",
    "gn:population":0,
    "gn:timezone":"America/Toronto",
    "iso:country":"CA",
    "wof:name":"Amherstburg",
    "wof:placetype":"locality"
},
  "geometry": {"coordinates":[-83.09985,42.10009],"type":"Point"}
}