{
  "type": "Feature",
  "properties": {
    "gn:admin1_code":"8.0",
    "gn:asciiname":"Amherstburg",
    "gn:country_code":"CA",
    "gn:dem":181,
    "gn:feature_class":"P",
    "gn:feature_code":"PPL",
    "gn:name":"Amherstburg",
    "gn:population":0,
    "gn:timezone":"America/Toronto",
    "iso:country":"CA",
    "name:ara_x_preferred":[
        "\u0623\u0645\u0647\u064a\u0631\u0633\u062a\u0628\u0627\u0631\u062c"
    ],
    "name:cat_x_preferred":[
        "Amherstburg"
    ],
    "name:deu_x_preferred":[
        "Amherstburg"
    ],
    "name:fas_x_preferred":[
        "\u0627\u0645\u0647\u0631\u0633\u062a\u200c\u0628\u0631\u06af"
    ],
    "name:fra_x_preferred":[
        "Amherstburg"
    ],
    "name:ita_x_preferred":[
        "Amherstburg"
    ],
    "name:pol_x_preferred":[
        "Amherstburg"
    ],
    "name:srp_x_preferred":[
        "\u0410\u043c\u0435\u0440\u0441\u0442\u0431\u0443\u0440\u0433"
    ],
    "name:swe_x_preferred":[
        "Amherstburg"
    ],
    "wof:name":"Amherstburg",
    "wof:placetype":"locality"
},
  "geometry": {"coordinates":[-83.09985,42.10009],"type":"Point"}
}