{
  "type": "Feature",
  "properties": {
    "gn:admin1_code":"8",
    "gn:asciiname":"Hoath Head",
    "gn:country_code":"CA",
    "gn:dem":316,
    "gn:feature_class":"P",
    "gn:feature_code":"PPL",
    "gn:name":"Hoath Head",
    "gn:population":0,
    "gn:timezone":"America/Toronto",
    "iso:country":"CA",
    "wof:name":"Hoath Head",
    "wof:placetype":"locality"
},
  "geometry": {"coordinates":[-80.84737,44.5256],"type":"Point"}
}