{
  "type": "Feature",
  "properties": {
    "gn:admin1_code":"11",
    "gn:asciiname":"Kilronan",
    "gn:country_code":"CA",
    "gn:dem":631,
    "gn:feature_class":"P",
    "gn:feature_code":"PPLL",
    "gn:name":"Kilronan",
    "gn:population":0,
    "gn:timezone":"America/Regina",
    "iso:country":"CA",
    "name:bre_x_preferred":[
        "Cill R\u00f3n\u00e1in"
    ],
    "name:cat_x_preferred":[
        "Cill R\u00f3n\u00e1in"
    ],
    "name:ceb_x_preferred":[
        "Kilronan"
    ],
    "name:deu_x_preferred":[
        "Cill R\u00f3n\u00e1in"
    ],
    "name:eus_x_preferred":[
        "Cill R\u00f3n\u00e1in"
    ],
    "name:fas_x_preferred":[
        "\u06a9\u06cc\u0644\u0631\u0648\u0646\u0627\u0646"
    ],
    "name:fin_x_preferred":[
        "Cill R\u00f3n\u00e1in"
    ],
    "name:fra_x_preferred":[
        "Cill R\u00f3n\u00e1in"
    ],
    "name:gle_x_preferred":[
        "Cill R\u00f3n\u00e1in"
    ],
    "name:ita_x_preferred":[
        "Cill R\u00f3n\u00e1in"
    ],
    "name:kat_x_preferred":[
        "\u10d9\u10d8\u10da\u10e0\u10dd\u10dc\u10d0\u10dc\u10d8"
    ],
    "name:nld_x_preferred":[
        "Cill R\u00f3n\u00e1in"
    ],
    "name:rus_x_preferred":[
        "\u041a\u0438\u043b\u0440\u043e\u043d\u0430\u043d"
    ],
    "name:spa_x_preferred":[
        "Cill R\u00f3n\u00e1in"
    ],
    "name:swe_x_preferred":[
        "Kilronan"
    ],
    "wof:name":"Kilronan",
    "wof:placetype":"locality"
},
  "geometry": {"coordinates":[-109.4015,53.65019],"type":"Point"}
}