{
  "type": "Feature",
  "properties": {
    "gn:admin1_code":"11",
    "gn:asciiname":"Kilronan",
    "gn:country_code":"CA",
    "gn:dem":631,
    "gn:feature_class":"P",
    "gn:feature_code":"PPLL",
    "gn:name":"Kilronan",
    "gn:population":0,
    "gn:timezone":"America/Regina",
    "iso:country":"CA",
    "wof:name":"Kilronan",
    "wof:placetype":"locality"
},
  "geometry": {"coordinates":[-109.4015,53.65019],"type":"Point"}
}