{
  "type": "Feature",
  "properties": {
    "gn:admin1_code":"11.0",
    "gn:asciiname":"Barrier Ford",
    "gn:country_code":"CA",
    "gn:dem":537,
    "gn:feature_class":"P",
    "gn:feature_code":"PPLL",
    "gn:name":"Barrier Ford",
    "gn:population":0,
    "gn:timezone":"America/Regina",
    "iso:country":"CA",
    "wof:name":"Barrier Ford",
    "wof:placetype":"locality"
},
  "geometry": {"coordinates":[-103.70098,52.5333],"type":"Point"}
}