{
  "type": "Feature",
  "properties": {
    "iso:country":"CA",
    "name:ceb_x_preferred":[
        "Central"
    ],
    "name:deu_x_preferred":[
        "Central"
    ],
    "name:eng_x_preferred":[
        "Central"
    ],
    "name:est_x_preferred":[
        "Central"
    ],
    "name:fas_x_preferred":[
        "\u0645\u0631\u06a9\u0632\u06cc"
    ],
    "name:fra_x_preferred":[
        "Central"
    ],
    "name:ita_x_preferred":[
        "Central"
    ],
    "name:jpn_x_preferred":[
        "\u30bb\u30f3\u30c8\u30e9\u30eb"
    ],
    "name:kor_x_preferred":[
        "\uc13c\ud2b8\ub7f4"
    ],
    "name:nld_x_preferred":[
        "Central"
    ],
    "name:pol_x_preferred":[
        "Central"
    ],
    "name:por_x_preferred":[
        "Central"
    ],
    "name:rus_x_preferred":[
        "\u0426\u0435\u043d\u0442\u0440\u0430\u043b\u044c"
    ],
    "name:slk_x_preferred":[
        "Centr\u00e1l"
    ],
    "name:spa_x_preferred":[
        "Central"
    ],
    "name:swe_x_preferred":[
        "Central"
    ],
    "name:tam_x_preferred":[
        "\u0b9a\u0bc6\u0ba9\u0bcd\u0b9f\u0bcd\u0bb0\u0bb2\u0bcd"
    ],
    "name:tha_x_preferred":[
        "\u0e01\u0e25\u0e32\u0e07"
    ],
    "name:ukr_x_preferred":[
        "\u0421\u0435\u043d\u0442\u0440\u0430\u043b"
    ],
    "name:vol_x_preferred":[
        "Central"
    ],
    "name:zho_x_preferred":[
        "\u4e2d"
    ],
    "qs:gn_adm0_cc":"CA",
    "qs:gn_local":5969782,
    "qs:gn_nam_loc":"hamilton",
    "qs:gn_namadm1":"08",
    "qs:local_max":3547,
    "qs:local_sum":20353,
    "qs:localhoods":46,
    "qs:name":"Central",
    "qs:name_adm0":"Canada",
    "qs:name_adm1":"Ontario",
    "qs:name_adm2":"Hamilton",
    "qs:name_local":"Hamilton",
    "qs:photo_max":294,
    "qs:photo_sum":1645,
    "qs:placetype":"Suburb",
    "qs:quad_count":39,
    "qs:woe_adm0":23424775,
    "qs:woe_adm1":2344922,
    "qs:woe_adm2":29375120,
    "qs:woe_funk":"Grouping neighborhood",
    "qs:woe_lau":0,
    "qs:woe_local":4125,
    "qs:woe_ver":"7.10.0",
    "wof:lang":[
        "eng"
    ],
    "wof:name":"Central",
    "wof:placetype":"neighbourhood"
},
  "geometry": {"coordinates":[-79.872218,43.261108],"type":"Point"}
}