{
  "type": "Feature",
  "properties": {
    "gn:admin1_code":"12",
    "gn:asciiname":"Kynocks",
    "gn:country_code":"CA",
    "gn:dem":893,
    "gn:feature_class":"P",
    "gn:feature_code":"PPLL",
    "gn:name":"Kynocks",
    "gn:population":0,
    "gn:timezone":"America/Whitehorse",
    "iso:country":"CA",
    "wof:name":"Kynocks",
    "wof:placetype":"locality"
},
  "geometry": {"coordinates":[-135.97748000000001,61.2619],"type":"Point"}
}