{
  "type": "Feature",
  "properties": {
    "gn:admin1_code":"8",
    "gn:asciiname":"Reid's Mill",
    "gn:country_code":"CA",
    "gn:dem":315,
    "gn:feature_class":"P",
    "gn:feature_code":"PPLL",
    "gn:name":"Reid's Mill",
    "gn:population":0,
    "gn:timezone":"America/Toronto",
    "iso:country":"CA",
    "wof:name":"Reid's Mill",
    "wof:placetype":"locality"
},
  "geometry": {"coordinates":[-80.44968,43.3168],"type":"Point"}
}