{
  "type": "Feature",
  "properties": {
    "iso:country":"CA",
    "name:eng_x_preferred":[
        "Irishtown"
    ],
    "name:fra_x_preferred":[
        "Irishtown"
    ],
    "name:nld_x_preferred":[
        "Irishtown"
    ],
    "qs_pg:aaroncc":"CA",
    "qs_pg:name":"Irishtown",
    "qs_pg:name_adm0":"Canada",
    "qs_pg:name_adm1":"New Brunswick",
    "qs_pg:photos":46,
    "qs_pg:photos_1k":9,
    "qs_pg:photos_9k":1,
    "qs_pg:photos_9r":2,
    "qs_pg:photos_all":46,
    "qs_pg:photos_sr":2,
    "qs_pg:pop_sr":0,
    "qs_pg:qs_pg_placetype":"locality",
    "qs_pg:qs_pg_placetype_gp":"Town",
    "qs_pg:woe_adm0":23424775,
    "woe:adm0_id":23424775,
    "woe:name_adm0":"Canada",
    "woe:name_adm1":"New Brunswick",
    "woe:placetype":"Town",
    "wof:name":"Irishtown",
    "wof:placetype":"locality"
},
  "geometry": {"coordinates":[-64.798393,46.206032],"type":"Point"}
}