{
  "type": "Feature",
  "properties": {
    "gn:admin1_code":"5",
    "gn:asciiname":"Upper Ferry",
    "gn:country_code":"CA",
    "gn:dem":5,
    "gn:feature_class":"P",
    "gn:feature_code":"PPL",
    "gn:name":"Upper Ferry",
    "gn:population":0,
    "gn:timezone":"America/St_Johns",
    "iso:country":"CA",
    "name:fra_x_preferred":[
        "Upper Ferry"
    ],
    "wof:name":"Upper Ferry",
    "wof:placetype":"locality"
},
  "geometry": {"coordinates":[-59.24858,47.85001],"type":"Point"}
}