{
  "type": "Feature",
  "properties": {
    "gn:admin1_code":"1",
    "gn:asciiname":"Stewart",
    "gn:country_code":"CA",
    "gn:dem":916,
    "gn:feature_class":"P",
    "gn:feature_code":"PPLL",
    "gn:name":"Stewart",
    "gn:population":0,
    "gn:timezone":"America/Edmonton",
    "iso:country":"CA",
    "name:bre_x_preferred":[
        "Stewart"
    ],
    "name:ceb_x_preferred":[
        "Stewart"
    ],
    "name:deu_x_preferred":[
        "Stewart"
    ],
    "name:fin_x_preferred":[
        "Stewart"
    ],
    "name:fra_x_preferred":[
        "Stewart"
    ],
    "name:ita_x_preferred":[
        "Stewart"
    ],
    "name:lav_x_preferred":[
        "Stjuarts"
    ],
    "name:nld_x_preferred":[
        "Stewart"
    ],
    "name:pol_x_preferred":[
        "Stewart"
    ],
    "name:por_x_preferred":[
        "Stewart"
    ],
    "name:rus_x_preferred":[
        "Stewart"
    ],
    "name:slv_x_preferred":[
        "Stewart"
    ],
    "name:spa_x_preferred":[
        "Stewart"
    ],
    "name:swe_x_preferred":[
        "Stewart"
    ],
    "name:vie_x_preferred":[
        "Stewart"
    ],
    "name:vol_x_preferred":[
        "Stewart"
    ],
    "name:zho_x_preferred":[
        "\u65af\u5716\u723e\u7279"
    ],
    "wof:name":"Stewart",
    "wof:placetype":"locality"
},
  "geometry": {"coordinates":[-112.73515,49.64999],"type":"Point"}
}