{
  "type": "Feature",
  "properties": {
    "gn:admin1_code":"1",
    "gn:asciiname":"Stewart",
    "gn:country_code":"CA",
    "gn:dem":916,
    "gn:feature_class":"P",
    "gn:feature_code":"PPLL",
    "gn:name":"Stewart",
    "gn:population":0,
    "gn:timezone":"America/Edmonton",
    "iso:country":"CA",
    "name:ara_x_preferred":[
        "\u0633\u062a\u064a\u0648\u0627\u0631\u062a"
    ],
    "name:ben_x_preferred":[
        "\u09b8\u09cd\u099f\u09c1\u09af\u09bc\u09be\u09b0\u09cd\u099f"
    ],
    "name:bre_x_preferred":[
        "Stewart"
    ],
    "name:ceb_x_preferred":[
        "Stewart"
    ],
    "name:deu_x_preferred":[
        "Stewart"
    ],
    "name:ell_x_preferred":[
        "\u03a3\u03c4\u03b9\u03bf\u03cd\u03b1\u03c1\u03c4"
    ],
    "name:fin_x_preferred":[
        "Stewart"
    ],
    "name:fra_x_preferred":[
        "Stewart"
    ],
    "name:heb_x_preferred":[
        "\u05e1\u05d8\u05d9\u05d5\u05d0\u05e8\u05d8"
    ],
    "name:hin_x_preferred":[
        "\u0938\u094d\u091f\u0940\u0935\u0930\u094d\u091f"
    ],
    "name:hun_x_preferred":[
        "Stewart"
    ],
    "name:ind_x_preferred":[
        "Stewart"
    ],
    "name:ita_x_preferred":[
        "Stewart"
    ],
    "name:jpn_x_preferred":[
        "\u30b9\u30c1\u30e5\u30a2\u30fc\u30c8\u5ddd"
    ],
    "name:kor_x_preferred":[
        "\uc2a4\ud29c\uc5b4\ud2b8"
    ],
    "name:lav_x_preferred":[
        "Stjuarts"
    ],
    "name:nld_x_preferred":[
        "Stewart"
    ],
    "name:pol_x_preferred":[
        "Stewart"
    ],
    "name:por_x_preferred":[
        "Stewart"
    ],
    "name:rus_x_preferred":[
        "Stewart"
    ],
    "name:slv_x_preferred":[
        "Stewart"
    ],
    "name:spa_x_preferred":[
        "Stewart"
    ],
    "name:swe_x_preferred":[
        "Stewart"
    ],
    "name:tur_x_preferred":[
        "Stewart"
    ],
    "name:ukr_x_preferred":[
        "\u0421\u0442\u044e\u0430\u0440\u0442"
    ],
    "name:urd_x_preferred":[
        "\u0627\u0633\u0679\u06cc\u0648\u0631\u0679"
    ],
    "name:vie_x_preferred":[
        "S\u00f4ng Stewart"
    ],
    "name:vie_x_variant":[
        "Stewart"
    ],
    "name:vol_x_preferred":[
        "Stewart"
    ],
    "name:zho_cn_x_preferred":[
        "\u65af\u56fe\u5c14\u7279\u6cb3"
    ],
    "name:zho_tw_x_preferred":[
        "\u53f8\u5f92\u83ef\u6cb3"
    ],
    "name:zho_x_preferred":[
        "\u65af\u5716\u723e\u7279"
    ],
    "wof:name":"Stewart",
    "wof:placetype":"locality"
},
  "geometry": {"coordinates":[-112.73515,49.64999],"type":"Point"}
}