{
  "type": "Feature",
  "properties": {
    "iso:country":"CA",
    "name:eng_x_preferred":[
        "Quidi Vidi"
    ],
    "name:zho_x_preferred":[
        "\u5947\u5730\u7dad\u5730"
    ],
    "qs:gn_adm0_cc":"CA",
    "qs:gn_local":6324733,
    "qs:gn_nam_loc":"St. John's, Newfoundland and Labrador, Newfoundland and Labrador, CA",
    "qs:gn_namadm1":"05",
    "qs:local_max":5403,
    "qs:local_sum":16210,
    "qs:localhoods":11,
    "qs:name":"Quidi Vidi",
    "qs:name_adm0":"Canada",
    "qs:name_adm1":"Newfoundland and Labrador",
    "qs:name_adm2":"Newfoundland and Labrador",
    "qs:name_local":"St. John's",
    "qs:photo_max":799,
    "qs:photo_sum":5403,
    "qs:placetype":"Suburb",
    "qs:quad_count":107,
    "qs:woe_adm0":23424775,
    "qs:woe_adm1":2344919,
    "qs:woe_adm2":29375216,
    "qs:woe_lau":0,
    "qs:woe_local":3996,
    "qs:woe_ver":"7.10.0",
    "wd:wordcount":403,
    "wof:lang":[
        "eng"
    ],
    "wof:name":"Quidi Vidi",
    "wof:placetype":"neighbourhood"
},
  "geometry": {"coordinates":[-52.685807,47.572692],"type":"Point"}
}