{
  "type": "Feature",
  "properties": {
    "gn:admin1_code":"11",
    "gn:asciiname":"Expanse",
    "gn:country_code":"CA",
    "gn:dem":683,
    "gn:feature_class":"P",
    "gn:feature_code":"PPL",
    "gn:name":"Expanse",
    "gn:population":0,
    "gn:timezone":"America/Regina",
    "iso:country":"CA",
    "wof:name":"Expanse",
    "wof:placetype":"locality"
},
  "geometry": {"coordinates":[-105.85057999999999,49.98336],"type":"Point"}
}