{
  "type": "Feature",
  "properties": {
    "gn:admin1_code":"2",
    "gn:asciiname":"Scotia Bay",
    "gn:country_code":"CA",
    "gn:dem":689,
    "gn:feature_class":"P",
    "gn:feature_code":"PPLL",
    "gn:name":"Scotia Bay",
    "gn:population":0,
    "gn:timezone":"America/Vancouver",
    "iso:country":"CA",
    "name:deu_x_preferred":[
        "Scotia Bay"
    ],
    "name:nno_x_preferred":[
        "Scotia Bay"
    ],
    "name:spa_x_preferred":[
        "Bah\u00eda Scotia"
    ],
    "name:swe_x_preferred":[
        "Scotia"
    ],
    "name:zho_x_preferred":[
        "\u65af\u79d1\u820d\u7063"
    ],
    "wof:name":"Scotia Bay",
    "wof:placetype":"locality"
},
  "geometry": {"coordinates":[-133.82026999999999,59.59942],"type":"Point"}
}