{
  "type": "Feature",
  "properties": {
    "gn:admin1_code":"8",
    "gn:asciiname":"Reeve Craig",
    "gn:country_code":"CA",
    "gn:dem":90,
    "gn:feature_class":"P",
    "gn:feature_code":"PPL",
    "gn:name":"Reeve Craig",
    "gn:population":0,
    "gn:timezone":"America/Toronto",
    "iso:country":"CA",
    "wof:name":"Reeve Craig",
    "wof:placetype":"locality"
},
  "geometry": {"coordinates":[-75.64237,45.09894],"type":"Point"}
}