{
  "type": "Feature",
  "properties": {
    "gn:country":"CA",
    "gn:fcode":"PPL",
    "gn:population":0,
    "iso:country":"CA",
    "name:eng_x_preferred":[
        "Dingwall"
    ],
    "name:gla_x_preferred":[
        "Inbhir Pheofharain"
    ],
    "name:nld_x_preferred":[
        "Dingwall"
    ],
    "qs:name":"Dingwall",
    "qs:name_adm0":"Canada",
    "qs:name_adm1":"Nova Scotia",
    "qs:photos":218,
    "qs:photos_1k":44,
    "qs:photos_9k":1,
    "qs:photos_9r":4,
    "qs:photos_all":218,
    "qs:photos_sr":4,
    "qs:placetype":"Town",
    "qs:pop_sr":"0",
    "wd:wordcount":946,
    "wof:name":"Dingwall",
    "wof:placetype":"locality",
    "wof:population":0
},
  "geometry": {"coordinates":[-60.46516,46.90014],"type":"Point"}
}