{
  "type": "Feature",
  "properties": {
    "gn:admin1_code":"8",
    "gn:asciiname":"Highland",
    "gn:country_code":"CA",
    "gn:dem":229,
    "gn:feature_class":"P",
    "gn:feature_code":"PPL",
    "gn:name":"Highland",
    "gn:population":0,
    "gn:timezone":"America/Toronto",
    "iso:country":"CA",
    "wof:name":"Highland",
    "wof:placetype":"locality"
},
  "geometry": {"coordinates":[-79.81395999999999,47.59575],"type":"Point"}
}