{
  "type": "Feature",
  "properties": {
    "gn:admin1_code":"8",
    "gn:asciiname":"Gillies Hill",
    "gn:country_code":"CA",
    "gn:dem":257,
    "gn:feature_class":"P",
    "gn:feature_code":"PPL",
    "gn:name":"Gillies Hill",
    "gn:population":0,
    "gn:timezone":"America/Toronto",
    "iso:country":"CA",
    "wof:name":"Gillies Hill",
    "wof:placetype":"locality"
},
  "geometry": {"coordinates":[-81.18167,44.32833],"type":"Point"}
}