{
  "type": "Feature",
  "properties": {
    "gn:admin1_code":"8.0",
    "gn:asciiname":"Clarence",
    "gn:country_code":"CA",
    "gn:dem":77,
    "gn:feature_class":"P",
    "gn:feature_code":"PPL",
    "gn:name":"Clarence",
    "gn:population":0,
    "gn:timezone":"America/Toronto",
    "iso:country":"CA",
    "name:ara_x_preferred":[
        "\u0643\u0644\u0627\u0631\u0646\u0633"
    ],
    "name:ceb_x_preferred":[
        "Clarence"
    ],
    "name:deu_x_preferred":[
        "Clarence"
    ],
    "name:fra_x_preferred":[
        "Clarence"
    ],
    "name:heb_x_preferred":[
        "\u05e7\u05dc\u05e8\u05e0\u05e1"
    ],
    "name:ita_x_preferred":[
        "Clarence"
    ],
    "name:jpn_x_preferred":[
        "\u30af\u30e9\u30ec\u30f3\u30b9"
    ],
    "name:kor_x_preferred":[
        "\ud074\ub798\ub7f0\uc2a4"
    ],
    "name:nld_x_preferred":[
        "Clarence"
    ],
    "name:pol_x_preferred":[
        "Clarence"
    ],
    "name:por_x_preferred":[
        "Clarence"
    ],
    "name:ron_x_preferred":[
        "Clarence"
    ],
    "name:rus_x_preferred":[
        "\u041a\u043b\u0430\u0440\u0435\u043d\u0441"
    ],
    "name:spa_x_preferred":[
        "Clarence"
    ],
    "name:srp_x_preferred":[
        "\u041a\u043b\u0435\u0440\u0435\u043d\u0441"
    ],
    "name:swe_x_preferred":[
        "Clarence"
    ],
    "name:ukr_x_preferred":[
        "\u041a\u043b\u0430\u0440\u0435\u043d\u0441"
    ],
    "name:urd_x_preferred":[
        "\u06a9\u0644\u06cc\u0631\u0646\u0633"
    ],
    "name:vie_x_preferred":[
        "Clarence"
    ],
    "name:vol_x_preferred":[
        "Clarence"
    ],
    "wof:name":"Clarence",
    "wof:placetype":"locality"
},
  "geometry": {"coordinates":[-75.24821,45.56399999999999],"type":"Point"}
}