{
  "type": "Feature",
  "properties": {
    "iso:country":"CA",
    "wof:name":"Upper Lonsdale",
    "wof:placetype":"neighbourhood"
},
  "geometry": {"coordinates":[-123.0720946969895,49.34011279447071],"type":"Point"}
}