{
  "type": "Feature",
  "properties": {
    "iso:country":"CA",
    "name:eng_x_preferred":[
        "Woodbridge Farms"
    ],
    "wof:lang":[
        "eng"
    ],
    "wof:name":"Woodbridge Farms",
    "wof:placetype":"neighbourhood"
},
  "geometry": {"coordinates":[-113.326328,53.526732],"type":"Point"}
}