{
  "type": "Feature",
  "properties": {
    "gn:admin1_code":"8",
    "gn:asciiname":"Moore Park",
    "gn:country_code":"CA",
    "gn:dem":156,
    "gn:feature_class":"P",
    "gn:feature_code":"PPL",
    "gn:name":"Moore Park",
    "gn:population":0,
    "gn:timezone":"America/Toronto",
    "iso:country":"CA",
    "name:ceb_x_preferred":[
        "Moore Park"
    ],
    "name:swe_x_preferred":[
        "Moore Park"
    ],
    "wof:name":"Moore Park",
    "wof:placetype":"locality"
},
  "geometry": {"coordinates":[-79.37860999999999,43.69056],"type":"Point"}
}