{
  "type": "Feature",
  "properties": {
    "gn:admin1_code":"4",
    "gn:asciiname":"Honeydale",
    "gn:country_code":"CA",
    "gn:dem":108,
    "gn:feature_class":"P",
    "gn:feature_code":"PPL",
    "gn:name":"Honeydale",
    "gn:population":0,
    "gn:timezone":"America/Moncton",
    "iso:country":"CA",
    "wof:name":"Honeydale",
    "wof:placetype":"locality"
},
  "geometry": {"coordinates":[-67.20636,45.3615],"type":"Point"}
}