{
  "type": "Feature",
  "properties": {
    "gn:admin1_code":"8",
    "gn:asciiname":"Miners Bay",
    "gn:country_code":"CA",
    "gn:dem":283,
    "gn:feature_class":"P",
    "gn:feature_code":"PPL",
    "gn:name":"Miners Bay",
    "gn:population":0,
    "gn:timezone":"America/Toronto",
    "iso:country":"CA",
    "wof:name":"Miners Bay",
    "wof:placetype":"locality"
},
  "geometry": {"coordinates":[-78.76861,44.8225],"type":"Point"}
}