{
  "type": "Feature",
  "properties": {
    "gn:admin1_code":"3",
    "gn:asciiname":"Wanasing Beach",
    "gn:country_code":"CA",
    "gn:dem":223,
    "gn:feature_class":"P",
    "gn:feature_code":"PPLL",
    "gn:name":"Wanasing Beach",
    "gn:population":0,
    "gn:timezone":"America/Winnipeg",
    "iso:country":"CA",
    "wof:name":"Wanasing Beach",
    "wof:placetype":"locality"
},
  "geometry": {"coordinates":[-96.52751000000001,50.70001],"type":"Point"}
}