{
  "type": "Feature",
  "properties": {
    "iso:country":"CA",
    "name:eng_x_preferred":[
        "Secord Woods"
    ],
    "qs:gn_adm0_cc":"CA",
    "qs:gn_local":6155721,
    "qs:gn_nam_loc":"st. catharines",
    "qs:gn_namadm1":"08",
    "qs:local_max":2526,
    "qs:local_sum":12246,
    "qs:localhoods":16,
    "qs:name":"Secord Woods",
    "qs:name_adm0":"Canada",
    "qs:name_adm1":"Ontario",
    "qs:name_adm2":"Niagara",
    "qs:name_local":"St. Catharines",
    "qs:photo_max":154,
    "qs:photo_sum":438,
    "qs:placetype":"Suburb",
    "qs:quad_count":30,
    "qs:woe_adm0":23424775,
    "qs:woe_adm1":2344922,
    "qs:woe_adm2":29375033,
    "qs:woe_lau":0,
    "qs:woe_local":4126,
    "qs:woe_ver":"7.10.0",
    "wof:lang":[
        "eng"
    ],
    "wof:name":"Secord Woods",
    "wof:placetype":"neighbourhood"
},
  "geometry": {"coordinates":[-79.196589,43.154277],"type":"Point"}
}