{
  "type": "Feature",
  "properties": {
    "gn:admin1_code":"1",
    "gn:asciiname":"Furman",
    "gn:country_code":"CA",
    "gn:dem":1266,
    "gn:feature_class":"P",
    "gn:feature_code":"PPLL",
    "gn:name":"Furman",
    "gn:population":0,
    "gn:timezone":"America/Edmonton",
    "iso:country":"CA",
    "wof:name":"Furman",
    "wof:placetype":"locality"
},
  "geometry": {"coordinates":[-113.98522,49.96676],"type":"Point"}
}