{
  "type": "Feature",
  "properties": {
    "gn:admin1_code":"1",
    "gn:asciiname":"Furman",
    "gn:country_code":"CA",
    "gn:dem":1266,
    "gn:feature_class":"P",
    "gn:feature_code":"PPLL",
    "gn:name":"Furman",
    "gn:population":0,
    "gn:timezone":"America/Edmonton",
    "iso:country":"CA",
    "name:bel_x_preferred":[
        "\u0424\u0443\u0440\u043c\u0430\u043d"
    ],
    "name:deu_x_preferred":[
        "Furman"
    ],
    "name:fin_x_preferred":[
        "Furman"
    ],
    "name:fra_x_preferred":[
        "Furman"
    ],
    "name:ita_x_preferred":[
        "Furman"
    ],
    "name:pol_x_preferred":[
        "Furman"
    ],
    "name:por_x_preferred":[
        "Furman"
    ],
    "name:rus_x_preferred":[
        "\u0424\u0443\u0440\u043c\u0430\u043d"
    ],
    "name:ukr_x_preferred":[
        "\u0424\u0443\u0440\u043c\u0430\u043d"
    ],
    "wof:name":"Furman",
    "wof:placetype":"locality"
},
  "geometry": {"coordinates":[-113.98522,49.96676],"type":"Point"}
}