{
  "type": "Feature",
  "properties": {
    "iso:country":"CA",
    "name:ceb_x_preferred":[
        "Rimouski Airport"
    ],
    "name:eng_x_preferred":[
        "Rimouski Airport"
    ],
    "name:fas_x_preferred":[
        "\u0641\u0631\u0648\u062f\u06af\u0627\u0647 \u0631\u06cc\u0645\u0648\u0633\u06a9\u06cc"
    ],
    "name:fra_x_preferred":[
        "A\u00e9roport international Jean-Lesage de Qu\u00e9bec"
    ],
    "name:msa_x_preferred":[
        "Lapangan Terbang Rimouski"
    ],
    "name:pms_x_preferred":[
        "Rimouski Airport"
    ],
    "name:ron_x_preferred":[
        "Aeroportul Rimouski"
    ],
    "name:rus_x_preferred":[
        "\u0430\u044d\u0440\u043e\u043f\u043e\u0440\u0442 \u0420\u0438\u043c\u0443\u0441\u043a\u0438"
    ],
    "name:swe_x_preferred":[
        "Rimouski Airport"
    ],
    "name:tgk_x_preferred":[
        "\u0424\u0443\u0440\u0443\u0434\u0433\u043e\u04b3\u0438 \u0440\u0438\u043c\u0443\u0441\u043a\u0438"
    ],
    "name:zho_x_preferred":[
        "\u91cc\u7a46\u65af\u57fa\u673a\u573a"
    ],
    "oa:elevation_ft":"82",
    "oa:type":"medium_airport",
    "woe:hierarchy":{
        "country_id":23424775,
        "county_id":29375135,
        "planet_id":1,
        "state_id":2344924
    },
    "wof:name":"A\u00e9roport de Rimouski",
    "wof:placetype":"campus"
},
  "geometry": {"coordinates":[-68.49639999999999,48.4778],"type":"Point"}
}