{
  "type": "Feature",
  "properties": {
    "iso:country":"CA",
    "name:fra_x_preferred":[
        "A\u00e9roport international Jean-Lesage de Qu\u00e9bec"
    ],
    "oa:elevation_ft":"82",
    "oa:type":"medium_airport",
    "woe:hierarchy":{
        "country_id":23424775,
        "county_id":29375135,
        "planet_id":1,
        "state_id":2344924
    },
    "wof:name":"A\u00e9roport de Rimouski",
    "wof:placetype":"campus"
},
  "geometry": {"coordinates":[-68.49639999999999,48.4778],"type":"Point"}
}