{
  "type": "Feature",
  "properties": {
    "gn:gn_country":"CA",
    "gn:gn_fcode":"PPL",
    "gn:gn_pop":0,
    "iso:country":"CA",
    "name:ceb_x_preferred":[
        "Saint-Majorique-de-Grantham"
    ],
    "name:deu_x_preferred":[
        "Saint-Majorique-de-Grantham"
    ],
    "name:eng_x_preferred":[
        "Saint-Majorique-de-Grantham"
    ],
    "name:eus_x_preferred":[
        "Saint-Majorique-de-Grantham"
    ],
    "name:fas_x_preferred":[
        "\u0633\u0646-\u0645\u0627\u0698\u0648\u0631\u06cc\u06a9-\u062f\u0648-\u06af\u0631\u0627\u0646\u062a\u0647\u0627\u0645\u060c \u06a9\u0628\u06a9"
    ],
    "name:fas_x_variant":[
        "\u0633\u0646-\u0645\u0627\u0698\u0648\u0631\u06cc\u06a9-\u062f\u0648-\u06af\u0631\u0627\u0646\u062a\u0647\u0627\u0645"
    ],
    "name:fra_x_preferred":[
        "Saint-Majorique-de-Grantham"
    ],
    "name:nld_x_preferred":[
        "Saint-Majorique-de-Grantham"
    ],
    "name:por_x_preferred":[
        "Saint-Majorique-de-Grantham"
    ],
    "name:spa_x_preferred":[
        "Saint-Majorique-de-Grantham"
    ],
    "name:swe_x_preferred":[
        "Saint-Majorique-de-Grantham"
    ],
    "name:urd_x_preferred":[
        "\u0633\u06cc\u0646\u0679-\u0645\u062c\u0648\u0631\u0642\u0639\u06d2-\u062f\u06d2-\u06af\u0631\u0627\u0646\u062a\u06c1\u0645"
    ],
    "qs_pg:aaroncc":"CA",
    "qs_pg:gn_country":"CA",
    "qs_pg:gn_fcode":"PPL",
    "qs_pg:gn_pop":0,
    "qs_pg:name":"St.-Majorique-de-Grantham",
    "qs_pg:name_adm0":"Canada",
    "qs_pg:name_adm1":"Qu\u00e9bec",
    "qs_pg:photos":87,
    "qs_pg:photos_1k":18,
    "qs_pg:photos_9k":1,
    "qs_pg:photos_9r":3,
    "qs_pg:photos_all":87,
    "qs_pg:photos_sr":3,
    "qs_pg:pop_sr":0,
    "qs_pg:qs_pg_placetype":"locality",
    "qs_pg:qs_pg_placetype_gp":"Town",
    "qs_pg:woe_adm0":23424775,
    "woe:adm0_id":23424775,
    "woe:name_adm0":"Canada",
    "woe:name_adm1":"Qu\u00e9bec",
    "woe:placetype":"Town",
    "wof:name":"St.-Majorique-de-Grantham",
    "wof:placetype":"locality"
},
  "geometry": {"coordinates":[-72.58242,45.93336],"type":"Point"}
}