{
  "type": "Feature",
  "properties": {
    "gn:admin1_code":"8",
    "gn:asciiname":"Pinedale",
    "gn:country_code":"CA",
    "gn:dem":312,
    "gn:feature_class":"P",
    "gn:feature_code":"PPL",
    "gn:name":"Pinedale",
    "gn:population":0,
    "gn:timezone":"America/Toronto",
    "iso:country":"CA",
    "wof:name":"Pinedale",
    "wof:placetype":"locality"
},
  "geometry": {"coordinates":[-79.00979,44.24901],"type":"Point"}
}