{
  "type": "Feature",
  "properties": {
    "gn:admin1_code":"1",
    "gn:asciiname":"Taylorville",
    "gn:country_code":"CA",
    "gn:dem":1252,
    "gn:feature_class":"P",
    "gn:feature_code":"PPLL",
    "gn:name":"Taylorville",
    "gn:population":0,
    "gn:timezone":"America/Edmonton",
    "iso:country":"CA",
    "wof:name":"Taylorville",
    "wof:placetype":"locality"
},
  "geometry": {"coordinates":[-113.11857000000001,49.03327],"type":"Point"}
}