{
  "type": "Feature",
  "properties": {
    "gn:admin1_code":"2",
    "gn:admin2_code":"5935.0",
    "gn:asciiname":"Traders Cove",
    "gn:country_code":"CA",
    "gn:dem":507,
    "gn:feature_class":"P",
    "gn:feature_code":"PPL",
    "gn:name":"Traders Cove",
    "gn:population":0,
    "gn:timezone":"America/Vancouver",
    "iso:country":"CA",
    "wof:name":"Traders Cove",
    "wof:placetype":"locality"
},
  "geometry": {"coordinates":[-119.50696000000001,49.94139000000001],"type":"Point"}
}