{
  "type": "Feature",
  "properties": {
    "gn:admin1_code":"2",
    "gn:admin2_code":"5945.0",
    "gn:asciiname":"Oweekeno",
    "gn:country_code":"CA",
    "gn:dem":10,
    "gn:feature_class":"P",
    "gn:feature_code":"PPL",
    "gn:name":"Oweekeno",
    "gn:population":0,
    "gn:timezone":"America/Vancouver",
    "iso:country":"CA",
    "wof:name":"Oweekeno",
    "wof:placetype":"locality"
},
  "geometry": {"coordinates":[-127.23052,51.67999],"type":"Point"}
}