{
  "type": "Feature",
  "properties": {
    "gn:admin1_code":"4.0",
    "gn:asciiname":"Days Corner",
    "gn:country_code":"CA",
    "gn:dem":87,
    "gn:feature_class":"P",
    "gn:feature_code":"PPLL",
    "gn:name":"Days Corner",
    "gn:population":0,
    "gn:timezone":"America/Moncton",
    "iso:country":"CA",
    "wof:name":"Days Corner",
    "wof:placetype":"locality"
},
  "geometry": {"coordinates":[-66.18214999999999,45.46685],"type":"Point"}
}