{
  "type": "Feature",
  "properties": {
    "gn:admin1_code":"10",
    "gn:admin2_code":"11.0",
    "gn:admin3_code":"1023.0",
    "gn:asciiname":"La Montagne",
    "gn:country_code":"CA",
    "gn:dem":26,
    "gn:feature_class":"P",
    "gn:feature_code":"PPL",
    "gn:name":"La Montagne",
    "gn:population":0,
    "gn:timezone":"America/Halifax",
    "iso:country":"CA",
    "name:ceb_x_preferred":[
        "La Montagne"
    ],
    "name:fra_x_preferred":[
        "La Montagne"
    ],
    "name:ita_x_preferred":[
        "La Montagne"
    ],
    "name:nld_x_preferred":[
        "La Montagne"
    ],
    "name:oci_x_preferred":[
        "La Montagne"
    ],
    "name:rus_x_preferred":[
        "\u041b\u0430-\u041c\u043e\u043d\u0442\u0430\u043d\u044c"
    ],
    "name:slk_x_preferred":[
        "La Montagne"
    ],
    "name:spa_x_preferred":[
        "La Montagne"
    ],
    "name:swe_x_preferred":[
        "La Montagne"
    ],
    "name:ukr_x_preferred":[
        "\u041b\u0430-\u041c\u043e\u043d\u0442\u0430\u043d\u044c"
    ],
    "wof:name":"La Montagne",
    "wof:placetype":"locality"
},
  "geometry": {"coordinates":[-61.96595,47.24618],"type":"Point"}
}