{
  "type": "Feature",
  "properties": {
    "gn:admin1_code":"11.0",
    "gn:asciiname":"Descharme Lake",
    "gn:country_code":"CA",
    "gn:dem":450,
    "gn:feature_class":"P",
    "gn:feature_code":"PPLL",
    "gn:name":"Descharme Lake",
    "gn:population":0,
    "gn:timezone":"America/Regina",
    "iso:country":"CA",
    "wof:name":"Descharme Lake",
    "wof:placetype":"locality"
},
  "geometry": {"coordinates":[-109.20156,57.10021999999999],"type":"Point"}
}