{
  "type": "Feature",
  "properties": {
    "gn:admin1_code":"8",
    "gn:asciiname":"Jobrin",
    "gn:country_code":"CA",
    "gn:dem":296,
    "gn:feature_class":"P",
    "gn:feature_code":"PPL",
    "gn:name":"Jobrin",
    "gn:population":0,
    "gn:timezone":"America/Toronto",
    "iso:country":"CA",
    "wof:name":"Jobrin",
    "wof:placetype":"locality"
},
  "geometry": {"coordinates":[-86.10625,50.11716],"type":"Point"}
}