{
  "type": "Feature",
  "properties": {
    "gn:admin1_code":"7.0",
    "gn:asciiname":"Albany",
    "gn:country_code":"CA",
    "gn:dem":178,
    "gn:feature_class":"P",
    "gn:feature_code":"PPL",
    "gn:name":"Albany",
    "gn:population":0,
    "gn:timezone":"America/Halifax",
    "iso:country":"CA",
    "wof:name":"Albany",
    "wof:placetype":"locality"
},
  "geometry": {"coordinates":[-65.0488,44.80015],"type":"Point"}
}