{
  "type": "Feature",
  "properties": {
    "gn:admin1_code":"7.0",
    "gn:asciiname":"Albany",
    "gn:country_code":"CA",
    "gn:dem":178,
    "gn:feature_class":"P",
    "gn:feature_code":"PPL",
    "gn:name":"Albany",
    "gn:population":0,
    "gn:timezone":"America/Halifax",
    "iso:country":"CA",
    "name:ara_x_preferred":[
        "\u0623\u0644\u0628\u0627\u0646\u064a\u0627"
    ],
    "name:ben_x_preferred":[
        "\u0986\u09b2\u09ac\u09c7\u09a8\u09bf"
    ],
    "name:ell_x_preferred":[
        "\u038f\u03bb\u03bc\u03c0\u03b1\u03bd\u03b9"
    ],
    "name:heb_x_preferred":[
        "\u05d0\u05dc\u05d1\u05e0\u05d9"
    ],
    "name:hin_x_preferred":[
        "\u0905\u0932\u094d\u092c\u0947\u0928\u0940"
    ],
    "name:hun_x_preferred":[
        "Albany"
    ],
    "name:ind_x_preferred":[
        "Albany"
    ],
    "name:kor_x_preferred":[
        "\uc54c\ubc14\ub2c8"
    ],
    "name:tur_x_preferred":[
        "Albany"
    ],
    "name:vie_x_preferred":[
        "S\u00f4ng Albany"
    ],
    "name:zho_cn_x_preferred":[
        "\u5965\u5c14\u5df4\u5c3c\u6cb3"
    ],
    "name:zho_tw_x_preferred":[
        "\u5967\u5df4\u5c3c"
    ],
    "wof:name":"Albany",
    "wof:placetype":"locality"
},
  "geometry": {"coordinates":[-65.0488,44.80015],"type":"Point"}
}