{
  "type": "Feature",
  "properties": {
    "iso:country":"CA",
    "name:ceb_x_preferred":[
        "Crestwood"
    ],
    "name:deu_x_preferred":[
        "Crestwood"
    ],
    "name:eng_x_preferred":[
        "Crestwood"
    ],
    "name:fra_x_preferred":[
        "Crestwood"
    ],
    "name:ita_x_preferred":[
        "Crestwood"
    ],
    "name:nld_x_preferred":[
        "Crestwood"
    ],
    "name:pol_x_preferred":[
        "Crestwood"
    ],
    "name:por_x_preferred":[
        "Crestwood"
    ],
    "name:srp_x_preferred":[
        "\u041a\u0440\u0435\u0441\u0442\u0432\u0443\u0434"
    ],
    "name:swe_x_preferred":[
        "Crestwood"
    ],
    "name:ukr_x_preferred":[
        "\u041a\u0440\u0435\u0441\u0442\u0432\u0443\u0434"
    ],
    "name:urd_x_preferred":[
        "\u06a9\u0631\u06cc\u0633\u0679\u0648\u0648\u0688"
    ],
    "name:vol_x_preferred":[
        "Crestwood"
    ],
    "qs:gn_adm0_cc":"CA",
    "qs:gn_local":6173577,
    "qs:gn_nam_loc":"vaughan",
    "qs:gn_namadm1":"08",
    "qs:local_max":1426,
    "qs:local_sum":6970,
    "qs:localhoods":22,
    "qs:name":"Crestwood",
    "qs:name_adm0":"Canada",
    "qs:name_adm1":"Ontario",
    "qs:name_adm2":"York",
    "qs:name_local":"Vaughan",
    "qs:photo_max":29,
    "qs:photo_sum":41,
    "qs:placetype":"Suburb",
    "qs:quad_count":3,
    "qs:woe_adm0":23424775,
    "qs:woe_adm1":2344922,
    "qs:woe_adm2":29375112,
    "qs:woe_funk":"Parented by a neighborhood",
    "qs:woe_lau":0,
    "qs:woe_local":23396899,
    "qs:woe_ver":"7.10.0",
    "wof:lang":[
        "eng"
    ],
    "wof:name":"Crestwood",
    "wof:placetype":"neighbourhood"
},
  "geometry": {"coordinates":[-79.437805,43.80101],"type":"Point"}
}