{
  "type": "Feature",
  "properties": {
    "gn:admin1_code":"1",
    "gn:asciiname":"Henday",
    "gn:country_code":"CA",
    "gn:dem":973,
    "gn:feature_class":"P",
    "gn:feature_code":"PPLL",
    "gn:name":"Henday",
    "gn:population":0,
    "gn:timezone":"America/Edmonton",
    "iso:country":"CA",
    "wof:name":"Henday",
    "wof:placetype":"locality"
},
  "geometry": {"coordinates":[-114.01869000000001,51.95011],"type":"Point"}
}