{
  "type": "Feature",
  "properties": {
    "gn:admin1_code":"11",
    "gn:asciiname":"Neuanlage",
    "gn:country_code":"CA",
    "gn:dem":517,
    "gn:feature_class":"P",
    "gn:feature_code":"PPLL",
    "gn:name":"Neuanlage",
    "gn:population":0,
    "gn:timezone":"America/Regina",
    "iso:country":"CA",
    "wof:name":"Neuanlage",
    "wof:placetype":"locality"
},
  "geometry": {"coordinates":[-106.46787999999999,52.45009],"type":"Point"}
}