{
  "type": "Feature",
  "properties": {
    "gn:admin1_code":"1",
    "gn:asciiname":"Inland",
    "gn:country_code":"CA",
    "gn:dem":672,
    "gn:feature_class":"P",
    "gn:feature_code":"PPLL",
    "gn:name":"Inland",
    "gn:population":0,
    "gn:timezone":"America/Edmonton",
    "iso:country":"CA",
    "name:deu_x_preferred":[
        "Inland"
    ],
    "name:ita_x_preferred":[
        "Inland"
    ],
    "name:pol_x_preferred":[
        "Inland"
    ],
    "name:swe_x_preferred":[
        "Inland"
    ],
    "wof:name":"Inland",
    "wof:placetype":"locality"
},
  "geometry": {"coordinates":[-112.18513,53.41684],"type":"Point"}
}